{
  "type": "Feature",
  "properties": {
    "addr:full":"541 E Fir St Union OR 97883",
    "addr:housenumber":"541",
    "addr:postcode":"97883",
    "addr:street":"E Fir St",
    "iso:country":"US",
    "sg:address":"541 E Fir St",
    "sg:city":"Union",
    "sg:classifiers":[
        {
            "category":"Professional",
            "type":"Services"
        }
    ],
    "sg:phone":"+1 541 562 9380",
    "sg:postcode":"97883",
    "sg:province":"OR",
    "sg:tags":[
        "establishment"
    ],
    "wof:name":"A M Todd Co",
    "wof:placetype":"venue"
},
  "geometry": {"coordinates":[-117.861108,45.214843],"type":"Point"}
}