{
  "type": "Feature",
  "properties": {
    "addr:full":"135 E 19th Ave Eugene OR 97401",
    "addr:housenumber":"135",
    "addr:postcode":"97401",
    "addr:street":"E 19Th Ave",
    "iso:country":"US",
    "sg:address":"135 E 19th Ave",
    "sg:city":"Eugene",
    "sg:classifiers":[
        {
            "category":"Real Estate",
            "subcategory":"Real Estate Operator",
            "type":"Services"
        }
    ],
    "sg:phone":"+1 541 343 0131",
    "sg:postcode":"97401",
    "sg:province":"OR",
    "sg:tags":[
        "building",
        "apartment"
    ],
    "wof:name":"Pearl Gardens Apartments",
    "wof:placetype":"venue"
},
  "geometry": {"coordinates":[-123.091129,44.039095],"type":"Point"}
}