{
  "type": "Feature",
  "properties": {
    "iso:country":"US",
    "sg:address":"4200 NW Columbia Ave",
    "sg:city":"Portland",
    "sg:classifiers":[
        {
            "category":"Professional",
            "subcategory":"Computer Services",
            "type":"Services"
        },
        {
            "category":"Shopping",
            "subcategory":"Computers & Home Electronics",
            "type":"Retail Goods"
        }
    ],
    "sg:phone":"+1 503 531 0252",
    "sg:postcode":"97229",
    "sg:province":"OR",
    "sg:tags":[
        "software",
        "programing",
        "custom"
    ],
    "sg:website":"www.seaquest.com",
    "wof:name":"Seaquest Software Incorporated",
    "wof:placetype":"venue"
},
  "geometry": {"coordinates":[-122.87282500000001,45.548931],"type":"Point"}
}