{
  "type": "Feature",
  "properties": {
    "iso:country":"US",
    "sg:address":"15637 S Lammer Rd",
    "sg:city":"Oregon City",
    "sg:classifiers":[
        {
            "category":"Recreation",
            "type":"Entertainment"
        }
    ],
    "sg:phone":"+1 503 632 3747",
    "sg:postcode":"97045",
    "sg:province":"OR",
    "sg:tags":[
        "stable"
    ],
    "wof:name":"Marriott Performance Horses",
    "wof:placetype":"venue"
},
  "geometry": {"coordinates":[-122.545204,45.300047],"type":"Point"}
}