{
  "type": "Feature",
  "properties": {
    "addr:full":"18480 SW Pacific Dr Tualatin OR 97062",
    "addr:housenumber":"18480",
    "addr:postcode":"97062",
    "addr:street":"Sw Pacific Dr",
    "iso:country":"US",
    "sg:address":"18480 SW Pacific Dr",
    "sg:city":"Tualatin",
    "sg:classifiers":[
        {
            "category":"Building & Trades",
            "subcategory":"Landscaping Services",
            "type":"Services"
        }
    ],
    "sg:phone":"+1 503 625 9600",
    "sg:postcode":"97062",
    "sg:province":"OR",
    "sg:tags":[
        "landscape",
        "contractor"
    ],
    "wof:name":"Willamette Landscape Services",
    "wof:placetype":"venue"
},
  "geometry": {"coordinates":[-122.81302100000001,45.386547],"type":"Point"}
}