{
  "type": "Feature",
  "properties": {
    "iso:country":"US",
    "sg:address":"114 N 2nd St",
    "sg:city":"Jefferson",
    "sg:classifiers":[
        {
            "category":"Food & Beverages",
            "subcategory":"Groceries & Convenience Stores",
            "type":"Retail Goods"
        }
    ],
    "sg:phone":"+1 541 327 2002",
    "sg:postcode":"97352",
    "sg:province":"OR",
    "sg:tags":[
        "market"
    ],
    "wof:name":"Santiam Market",
    "wof:placetype":"venue"
},
  "geometry": {"coordinates":[-123.0102,44.71854],"type":"Point"}
}