{
  "type": "Feature",
  "properties": {
    "addr:full":"166 Gateway Blvd Cottage Grove OR 97424",
    "addr:housenumber":"166",
    "addr:postcode":"97424",
    "addr:street":"Gateway Blvd",
    "iso:country":"US",
    "sg:address":"166 Gateway Blvd",
    "sg:city":"Cottage Grove",
    "sg:classifiers":[
        {
            "category":"Restaurant",
            "type":"Food & Drink"
        }
    ],
    "sg:phone":"+1 541 942 7156",
    "sg:postcode":"97424",
    "sg:province":"OR",
    "sg:tags":[
        "eating"
    ],
    "wof:name":"Jasper's Deli",
    "wof:placetype":"venue"
},
  "geometry": {"coordinates":[-123.048591,43.79573],"type":"Point"}
}