{
  "type": "Feature",
  "properties": {
    "iso:country":"US",
    "sg:address":"1826 NW Rimrock Rd",
    "sg:city":"Bend",
    "sg:classifiers":[
        {
            "category":"Building & Trades",
            "subcategory":"Construction",
            "type":"Services"
        }
    ],
    "sg:phone":"+1 541 382 6442",
    "sg:postcode":"97701",
    "sg:province":"OR",
    "sg:tags":[
        "maintenance",
        "contractor"
    ],
    "wof:name":"Alphaclean Commercial Mntnc",
    "wof:placetype":"venue"
},
  "geometry": {"coordinates":[-121.33690900000001,44.069085],"type":"Point"}
}