{
  "type": "Feature",
  "properties": {
    "addr:full":"2455 NW Marshall Street Portland OR 97210",
    "addr:housenumber":"2455",
    "addr:postcode":"97210",
    "addr:street":"Nw Marshall Street",
    "iso:country":"US",
    "sg:address":"2455 NW Marshall Street",
    "sg:city":"Portland",
    "sg:classifiers":[
        {
            "category":"Professional",
            "subcategory":"Lawyer & Legal Services",
            "type":"Services"
        }
    ],
    "sg:phone":"+1 503 224 0336",
    "sg:postcode":"97210",
    "sg:province":"OR",
    "wof:name":"Elliott Amy Atty",
    "wof:placetype":"venue"
},
  "geometry": {"coordinates":[-122.70191699999999,45.530476],"type":"Point"}
}