{
  "type": "Feature",
  "properties": {
    "iso:country":"US",
    "sg:address":"1115 Pacific Ave",
    "sg:city":"Tillamook",
    "sg:classifiers":[
        {
            "category":"Utilities",
            "subcategory":"Electric",
            "type":"Services"
        }
    ],
    "sg:phone":"+1 503 842 2535",
    "sg:postcode":"97141",
    "sg:province":"OR",
    "sg:tags":[
        "company"
    ],
    "sg:website":"www.tpud.org",
    "wof:name":"Tillamook People's Utility",
    "wof:placetype":"venue"
},
  "geometry": {"coordinates":[-123.843065,45.450228],"type":"Point"}
}