{
  "type": "Feature",
  "properties": {
    "addr:full":"1101 NE Alpine Ave Mcminnville OR 97128",
    "addr:housenumber":"1101",
    "addr:postcode":"97128",
    "addr:street":"Ne Alpine Ave",
    "iso:country":"US",
    "sg:address":"1101 NE Alpine Ave",
    "sg:city":"Mcminnville",
    "sg:classifiers":[
        {
            "category":"Building & Trades",
            "subcategory":"Electrical",
            "type":"Services"
        }
    ],
    "sg:phone":"+1 503 472 4003",
    "sg:postcode":"97128",
    "sg:province":"OR",
    "sg:tags":[
        "electric",
        "contractor"
    ],
    "wof:name":"D-N-D Electrical Contractors",
    "wof:placetype":"venue"
},
  "geometry": {"coordinates":[-123.186131,45.215516],"type":"Point"}
}