{
  "type": "Feature",
  "properties": {
    "iso:country":"US",
    "sg:address":"527 SW 12th Avenue",
    "sg:city":"Portland",
    "sg:classifiers":[
        {
            "category":"Restaurant",
            "type":"Food & Drink"
        }
    ],
    "sg:phone":"+1 503 241 7163",
    "sg:postcode":"97205",
    "sg:province":"OR",
    "sg:tags":[
        "german",
        "italian"
    ],
    "sg:website":"www.grunerpdx.com",
    "wof:name":"Gr?ner",
    "wof:placetype":"venue"
},
  "geometry": {"coordinates":[-122.683654,45.521517],"type":"Point"}
}