{
  "type": "Feature",
  "properties": {
    "iso:country":"US",
    "sg:address":"70360 Columbia River Hwy",
    "sg:city":"Rainier",
    "sg:classifiers":[
        {
            "category":"Building & Trades",
            "subcategory":"Construction",
            "type":"Services"
        }
    ],
    "sg:phone":"+1 503 556 2359",
    "sg:postcode":"97048",
    "sg:province":"OR",
    "sg:tags":[
        "nonresidential"
    ],
    "wof:name":"Estimate Services",
    "wof:placetype":"venue"
},
  "geometry": {"coordinates":[-122.874968,46.008756],"type":"Point"}
}