{
  "type": "Feature",
  "properties": {
    "iso:country":"US",
    "sg:address":"1187 56th St",
    "sg:city":"Springfield",
    "sg:classifiers":[
        {
            "category":"Shopping",
            "subcategory":"Hobbies, Toys, & Games",
            "type":"Retail Goods"
        }
    ],
    "sg:phone":"+1 541 746 6045",
    "sg:postcode":"97478",
    "sg:province":"OR",
    "sg:tags":[
        "craft"
    ],
    "wof:name":"Hand Crafted Treasures",
    "wof:placetype":"venue"
},
  "geometry": {"coordinates":[-122.929678,44.055633],"type":"Point"}
}