{
  "type": "Feature",
  "properties": {
    "addr:full":"11102 SW Capitol Hwy Portland OR 97219",
    "addr:housenumber":"11102",
    "addr:postcode":"97219",
    "addr:street":"Sw Capitol Hwy",
    "iso:country":"US",
    "sg:address":"11102 SW Capitol Hwy",
    "sg:city":"Portland",
    "sg:classifiers":[
        {
            "category":"Deli",
            "type":"Food & Drink"
        },
        {
            "category":"Food & Beverages",
            "subcategory":"Groceries & Convenience Stores",
            "type":"Retail Goods"
        }
    ],
    "sg:phone":"+1 503 245 1676",
    "sg:postcode":"97219",
    "sg:province":"OR",
    "wof:name":"Capitol Highway Deli Foodmart",
    "wof:placetype":"venue"
},
  "geometry": {"coordinates":[-122.726997,45.445301],"type":"Point"}
}