{
  "type": "Feature",
  "properties": {
    "addr:full":"30252 Bellfountain Rd Corvallis OR 97333",
    "addr:housenumber":"30252",
    "addr:postcode":"97333",
    "addr:street":"Bellfountain Rd",
    "iso:country":"US",
    "sg:address":"30252 Bellfountain Rd",
    "sg:city":"Corvallis",
    "sg:classifiers":[
        {
            "category":"Education",
            "subcategory":"School",
            "type":"Public Place"
        }
    ],
    "sg:phone":"+1 541 757 5981",
    "sg:postcode":"97333",
    "sg:province":"OR",
    "wof:name":"Inavale Elementary School",
    "wof:placetype":"venue"
},
  "geometry": {"coordinates":[-123.337177,44.463094],"type":"Point"}
}