{
  "type": "Feature",
  "properties": {
    "iso:country":"US",
    "sg:address":"809 N Rosa Parks Way",
    "sg:city":"Portland",
    "sg:classifiers":[
        {
            "category":"Autos & Motor Vehicles",
            "subcategory":"Auto Supplies",
            "type":"Retail Goods"
        },
        {
            "category":"Manufacturing",
            "subcategory":"Motor Vehicles & Parts",
            "type":"Manufacturing & Wholesale Goods"
        }
    ],
    "sg:phone":"+1 503 206 8530",
    "sg:postcode":"97217",
    "sg:province":"OR",
    "sg:tags":[
        "automobile",
        "electric",
        "motors-used"
    ],
    "wof:name":"R And M Motors Portland",
    "wof:placetype":"venue"
},
  "geometry": {"coordinates":[-122.674954,45.56992],"type":"Point"}
}