{
  "type": "Feature",
  "properties": {
    "iso:country":"US",
    "sg:address":"13665 SW Larch Pl Apt 36",
    "sg:city":"Beaverton",
    "sg:classifiers":[
        {
            "category":"Real Estate",
            "subcategory":"Real Estate Operator",
            "type":"Services"
        }
    ],
    "sg:phone":"+1 503 644 4496",
    "sg:postcode":"97005",
    "sg:province":"OR",
    "sg:tags":[
        "apartment"
    ],
    "wof:name":"Spencer House Apartments",
    "wof:placetype":"venue"
},
  "geometry": {"coordinates":[-122.818001,45.484901],"type":"Point"}
}