{
  "type": "Feature",
  "properties": {
    "addr:full":"350 Horseshoe Dr Grants Pass OR 97526",
    "addr:housenumber":"350",
    "addr:postcode":"97526",
    "addr:street":"Horseshoe Dr",
    "iso:country":"US",
    "sg:address":"350 Horseshoe Dr",
    "sg:city":"Grants Pass",
    "sg:classifiers":[
        {
            "category":"Freight",
            "type":"Transportation"
        }
    ],
    "sg:phone":"+1 541 476 1708",
    "sg:postcode":"97526",
    "sg:province":"OR",
    "sg:tags":[
        "operator",
        "local",
        "trucking"
    ],
    "wof:name":"Prl Company",
    "wof:placetype":"venue"
},
  "geometry": {"coordinates":[-123.33615500000001,42.507537],"type":"Point"}
}