{
  "type": "Feature",
  "properties": {
    "iso:country":"US",
    "sg:address":"2107 NE 82nd Ave",
    "sg:city":"Portland",
    "sg:classifiers":[
        {
            "category":"Shopping",
            "subcategory":"Department Store",
            "type":"Retail Goods"
        }
    ],
    "sg:phone":"+1 503 253 5028",
    "sg:postcode":"97220",
    "sg:province":"OR",
    "sg:tags":[
        "wholesale",
        "discount"
    ],
    "sg:website":"portlandmiicloseout.fatcow.com/p...",
    "wof:name":"Portland Closeout",
    "wof:placetype":"venue"
},
  "geometry": {"coordinates":[-122.579262,45.537817],"type":"Point"}
}