{
  "type": "Feature",
  "properties": {
    "iso:country":"US",
    "sg:address":"1142 Willagillespie Rd",
    "sg:city":"Eugene",
    "sg:classifiers":[
        {
            "category":"Health Services",
            "subcategory":"Chiropractor",
            "type":"Services"
        }
    ],
    "sg:phone":"+1 541 343 4913",
    "sg:postcode":"97401",
    "sg:province":"OR",
    "wof:name":"Accident & Injured Workers",
    "wof:placetype":"venue"
},
  "geometry": {"coordinates":[-123.100402,44.0728],"type":"Point"}
}