{
  "type": "Feature",
  "properties": {
    "addr:full":"119 Arbor Dr Eugene OR 97404",
    "addr:housenumber":"119",
    "addr:postcode":"97404",
    "addr:street":"Arbor Dr",
    "iso:country":"US",
    "sg:address":"119 Arbor Dr",
    "sg:city":"Eugene",
    "sg:classifiers":[
        {
            "category":"Professional",
            "type":"Services"
        }
    ],
    "sg:phone":"+1 541 688 4264",
    "sg:postcode":"97404",
    "sg:province":"OR",
    "wof:name":"Ava Eugene",
    "wof:placetype":"venue"
},
  "geometry": {"coordinates":[-123.118906,44.081765],"type":"Point"}
}