{
  "type": "Feature",
  "properties": {
    "addr:full":"205 Daisy Ln Roseburg OR 97470",
    "addr:housenumber":"205",
    "addr:postcode":"97470",
    "addr:street":"Daisy Ln",
    "iso:country":"US",
    "sg:address":"205 Daisy Ln",
    "sg:city":"Roseburg",
    "sg:classifiers":[
        {
            "category":"Recreation",
            "type":"Entertainment"
        }
    ],
    "sg:phone":"+1 541 679 8191",
    "sg:postcode":"97470",
    "sg:province":"OR",
    "wof:name":"Lyle Andrews Guide Service",
    "wof:placetype":"venue"
},
  "geometry": {"coordinates":[-123.487829,43.181051],"type":"Point"}
}