{
  "type": "Feature",
  "properties": {
    "iso:country":"US",
    "sg:address":"671 W Main St",
    "sg:city":"John Day",
    "sg:classifiers":[
        {
            "category":"Professional",
            "subcategory":"Accounting & Tax Preparation",
            "type":"Services"
        }
    ],
    "sg:phone":"+1 541 575 2704",
    "sg:postcode":"97845",
    "sg:province":"OR",
    "sg:tags":[
        "return",
        "filing"
    ],
    "wof:name":"K T Income Tax Svc",
    "wof:placetype":"venue"
},
  "geometry": {"coordinates":[-118.960319,44.419893],"type":"Point"}
}