{
  "type": "Feature",
  "properties": {
    "iso:country":"US",
    "sg:address":"3905 SW 141st Ave",
    "sg:city":"Beaverton",
    "sg:classifiers":[
        {
            "category":"Wholesale",
            "subcategory":"Computers",
            "type":"Manufacturing & Wholesale Goods"
        }
    ],
    "sg:phone":"+1 503 746 6910",
    "sg:postcode":"97005",
    "sg:province":"OR",
    "sg:website":"www.autosked.com",
    "wof:name":"Autosked",
    "wof:placetype":"venue"
},
  "geometry": {"coordinates":[-122.821883,45.491472],"type":"Point"}
}