{
  "type": "Feature",
  "properties": {
    "iso:country":"US",
    "sg:address":"1148 NE Revere Ave",
    "sg:city":"Bend",
    "sg:classifiers":[
        {
            "category":"Shopping",
            "subcategory":"Music",
            "type":"Retail Goods"
        }
    ],
    "sg:phone":"+1 541 383 5078",
    "sg:postcode":"97701",
    "sg:province":"OR",
    "wof:name":"Evaristo Records",
    "wof:placetype":"venue"
},
  "geometry": {"coordinates":[-121.289439,44.067728],"type":"Point"}
}