{
  "type": "Feature",
  "properties": {
    "iso:country":"US",
    "sg:address":"340 A St",
    "sg:city":"Ashland",
    "sg:classifiers":[
        {
            "category":"Real Estate",
            "subcategory":"Real Estate Agent",
            "type":"Services"
        }
    ],
    "sg:phone":"+1 541 482 2537",
    "sg:postcode":"97520",
    "sg:province":"OR",
    "sg:website":"www.nwbrealestate.com",
    "wof:name":"Northwest Brokers Real Estate",
    "wof:placetype":"venue"
},
  "geometry": {"coordinates":[-122.709433,42.198584],"type":"Point"}
}