{
  "type": "Feature",
  "properties": {
    "iso:country":"US",
    "sg:address":"61395 K Bar Rd",
    "sg:city":"Bend",
    "sg:classifiers":[
        {
            "category":"Retail",
            "subcategory":"Animal Services",
            "type":"Services"
        }
    ],
    "sg:phone":"+1 541 383 3030",
    "sg:postcode":"97701",
    "sg:province":"OR",
    "wof:name":"Aloha Llamas",
    "wof:placetype":"venue"
},
  "geometry": {"coordinates":[-121.16234799999999,44.033255],"type":"Point"}
}