{
  "type": "Feature",
  "properties": {
    "iso:country":"US",
    "sg:address":"3041 SE Alder Ct",
    "sg:city":"Portland",
    "sg:classifiers":[
        {
            "category":"Professional",
            "subcategory":"Art Services",
            "type":"Services"
        }
    ],
    "sg:phone":"+1 503 235 9028",
    "sg:postcode":"97214",
    "sg:province":"OR",
    "sg:tags":[
        "photographer"
    ],
    "wof:name":"Chris Johnsen Photography",
    "wof:placetype":"venue"
},
  "geometry": {"coordinates":[-122.633754,45.517615],"type":"Point"}
}