{
  "type": "Feature",
  "properties": {
    "iso:country":"US",
    "sg:address":"1735 Cascade Ave",
    "sg:city":"Hood River",
    "sg:classifiers":[
        {
            "category":"Real Estate",
            "subcategory":"Surveying",
            "type":"Services"
        }
    ],
    "sg:phone":"+1 541 386 4531",
    "sg:postcode":"97031",
    "sg:province":"OR",
    "sg:tags":[
        "surveyor"
    ],
    "wof:name":"Terra Surveying",
    "wof:placetype":"venue"
},
  "geometry": {"coordinates":[-121.529287,45.709223],"type":"Point"}
}