{
  "type": "Feature",
  "properties": {
    "iso:country":"US",
    "sg:address":"1011 Ne Alberta St",
    "sg:city":"Portland",
    "sg:classifiers":[
        {
            "category":"Shopping",
            "subcategory":"Clothing, Apparel, & Fashions",
            "type":"Retail Goods"
        },
        {
            "category":"Shopping",
            "subcategory":"Bicycles & Sporting Goods",
            "type":"Retail Goods"
        },
        {
            "category":"Shopping",
            "subcategory":"Luggage & Leather Goods",
            "type":"Retail Goods"
        }
    ],
    "sg:phone":"+1 503 442 1456",
    "sg:postcode":"97211",
    "sg:province":"OR",
    "sg:tags":[
        "outdoor",
        "gear",
        "accessory"
    ],
    "sg:website":"www.blackstarbags.com",
    "wof:name":"Black Star Bags",
    "wof:placetype":"venue"
},
  "geometry": {"coordinates":[-122.65542499999999,45.559232],"type":"Point"}
}