{
  "type": "Feature",
  "properties": {
    "addr:full":"6024 SE Taylor Ct. Portland OR 97215",
    "addr:housenumber":"6024",
    "addr:postcode":"97215",
    "addr:street":"Se Taylor Ct.",
    "iso:country":"US",
    "sg:address":"6024 SE Taylor Ct.",
    "sg:city":"Portland",
    "sg:classifiers":[
        {
            "category":"Communications",
            "type":"Services"
        }
    ],
    "sg:phone":"+1 503 780 1054",
    "sg:postcode":"97215",
    "sg:province":"OR",
    "sg:tags":[
        "web",
        "design"
    ],
    "sg:website":"www.sirius-media.com",
    "wof:name":"Sirius Media",
    "wof:placetype":"venue"
},
  "geometry": {"coordinates":[-122.60144200000001,45.515231],"type":"Point"}
}