{
  "type": "Feature",
  "properties": {
    "addr:full":"29791 SW Kinsman Rd Wilsonville OR 97070",
    "addr:housenumber":"29791",
    "addr:postcode":"97070",
    "addr:street":"Sw Kinsman Rd",
    "iso:country":"US",
    "sg:address":"29791 SW Kinsman Rd",
    "sg:city":"Wilsonville",
    "sg:classifiers":[
        {
            "category":"Building & Trades",
            "subcategory":"Construction",
            "type":"Services"
        }
    ],
    "sg:phone":"+1 503 685 9505",
    "sg:postcode":"97070",
    "sg:province":"OR",
    "sg:tags":[
        "asbestos",
        "removal"
    ],
    "wof:name":"Rose City Contracting",
    "wof:placetype":"venue"
},
  "geometry": {"coordinates":[-122.778075,45.304951],"type":"Point"}
}