{
  "type": "Feature",
  "properties": {
    "iso:country":"US",
    "sg:address":"3535 SW California St",
    "sg:city":"Portland",
    "sg:classifiers":[
        {
            "category":"Building & Trades",
            "subcategory":"Construction",
            "type":"Services"
        }
    ],
    "sg:phone":"+1 503 245 3558",
    "sg:postcode":"97219",
    "sg:province":"OR",
    "sg:tags":[
        "consultant",
        "management"
    ],
    "wof:name":"Os Chase Archtechture",
    "wof:placetype":"venue"
},
  "geometry": {"coordinates":[-122.713111,45.474789],"type":"Point"}
}