{
  "type": "Feature",
  "properties": {
    "iso:country":"US",
    "sg:address":"710 SE Englewood Dr",
    "sg:city":"Hillsboro",
    "sg:classifiers":[
        {
            "category":"Personal",
            "subcategory":"Beauty Salon",
            "type":"Services"
        }
    ],
    "sg:phone":"+1 503 292 3059",
    "sg:postcode":"97123",
    "sg:province":"OR",
    "sg:tags":[
        "shop"
    ],
    "wof:name":"Moz Curlup and Dye",
    "wof:placetype":"venue"
},
  "geometry": {"coordinates":[-122.97752800000001,45.512811],"type":"Point"}
}