{
  "type": "Feature",
  "properties": {
    "iso:country":"US",
    "sg:address":"20595 SW Tualatin Valley Hwy",
    "sg:city":"Beaverton",
    "sg:classifiers":[
        {
            "category":"Travel",
            "subcategory":"Travel Agent",
            "type":"Entertainment"
        }
    ],
    "sg:phone":"+1 503 356 9160",
    "sg:postcode":"97006",
    "sg:province":"OR",
    "sg:tags":[
        "agency",
        "bureau"
    ],
    "wof:name":"Tropical Escapes LLP",
    "wof:placetype":"venue"
},
  "geometry": {"coordinates":[-122.890842,45.49638],"type":"Point"}
}