{
  "type": "Feature",
  "properties": {
    "iso:country":"US",
    "sg:address":"2732 Sunnyview Ln",
    "sg:city":"Eugene",
    "sg:classifiers":[
        {
            "category":"Professional",
            "subcategory":"Computer Services",
            "type":"Services"
        }
    ],
    "sg:phone":"+1 541 684 4462",
    "sg:postcode":"97405",
    "sg:province":"OR",
    "sg:tags":[
        "design",
        "system"
    ],
    "wof:name":"Omegawave LLC",
    "wof:placetype":"venue"
},
  "geometry": {"coordinates":[-123.150435,44.030294],"type":"Point"}
}