{
  "type": "Feature",
  "properties": {
    "addr:full":"16582 Alsea Hwy Alsea OR 97324",
    "addr:housenumber":"16582",
    "addr:postcode":"97324",
    "addr:street":"Alsea Hwy",
    "iso:country":"US",
    "sg:address":"16582 Alsea Hwy",
    "sg:city":"Alsea",
    "sg:classifiers":[
        {
            "category":"Building & Trades",
            "subcategory":"Construction",
            "type":"Services"
        }
    ],
    "sg:phone":"+1 541 487 7253",
    "sg:postcode":"97324",
    "sg:province":"OR",
    "sg:tags":[
        "excavation",
        "contractor"
    ],
    "wof:name":"D Miller Excavating",
    "wof:placetype":"venue"
},
  "geometry": {"coordinates":[-123.694862,44.346741],"type":"Point"}
}