{
  "type": "Feature",
  "properties": {
    "addr:full":"3050 N Delta Hwy Eugene OR 97408",
    "addr:housenumber":"3050",
    "addr:postcode":"97408",
    "addr:street":"N Delta Hwy",
    "iso:country":"US",
    "sg:address":"3050 N Delta Hwy",
    "sg:city":"Eugene",
    "sg:classifiers":[
        {
            "category":"Communications",
            "type":"Services"
        }
    ],
    "sg:phone":"+1 541 344 5991",
    "sg:postcode":"97408",
    "sg:province":"OR",
    "wof:name":"FSH Communications",
    "wof:placetype":"venue"
},
  "geometry": {"coordinates":[-123.094257,44.097893],"type":"Point"}
}