{
  "type": "Feature",
  "properties": {
    "addr:full":"11754 Dixie Rd Central Point OR 97502",
    "addr:housenumber":"11754",
    "addr:postcode":"97502",
    "addr:street":"Dixie Rd",
    "iso:country":"US",
    "sg:address":"11754 Dixie Rd",
    "sg:city":"Central Point",
    "sg:classifiers":[
        {
            "category":"Building & Trades",
            "subcategory":"Construction",
            "type":"Services"
        }
    ],
    "sg:phone":"+1 541 773 5459",
    "sg:postcode":"97502",
    "sg:province":"OR",
    "sg:tags":[
        "residential",
        "contractor"
    ],
    "wof:name":"Steve St Martin Construction",
    "wof:placetype":"venue"
},
  "geometry": {"coordinates":[-122.94759500000001,42.487341],"type":"Point"}
}