{
  "type": "Feature",
  "properties": {
    "addr:full":"5005 SW Murray Blvd # 706 Beaverton OR 97005",
    "addr:housenumber":"5005",
    "addr:postcode":"97005",
    "addr:street":"Sw Murray Blvd # 706",
    "iso:country":"US",
    "sg:address":"5005 SW Murray Blvd # 706",
    "sg:city":"Beaverton",
    "sg:classifiers":[
        {
            "category":"Professional",
            "subcategory":"Advertising",
            "type":"Services"
        }
    ],
    "sg:phone":"+1 503 319 7372",
    "sg:postcode":"97005",
    "sg:province":"OR",
    "sg:tags":[
        "promotion",
        "sale"
    ],
    "sg:website":"http://www.nosquirrels.com",
    "wof:name":"Sciurus Enterprises, Inc.",
    "wof:placetype":"venue"
},
  "geometry": {"coordinates":[-122.82611199999999,45.483377],"type":"Point"}
}