{
  "type": "Feature",
  "properties": {
    "addr:full":"3935 NW Aloclek Pl A100 Hillsboro OR 97124",
    "addr:housenumber":"3935;a100",
    "addr:postcode":"97124",
    "addr:street":"Nw Aloclek Pl",
    "iso:country":"US",
    "sg:address":"3935 NW Aloclek Pl A100",
    "sg:city":"Hillsboro",
    "sg:classifiers":[
        {
            "category":"Professional",
            "type":"Services"
        }
    ],
    "sg:phone":"+1 503 466 6800",
    "sg:postcode":"97124",
    "sg:province":"OR",
    "sg:tags":[
        "processing",
        "data"
    ],
    "wof:name":"Lockheed Martin",
    "wof:placetype":"venue"
},
  "geometry": {"coordinates":[-122.8904,45.548165],"type":"Point"}
}