{
  "type": "Feature",
  "properties": {
    "iso:country":"US",
    "sg:address":"10630 NE Marx St",
    "sg:city":"Portland",
    "sg:classifiers":[
        {
            "category":"Building & Trades",
            "subcategory":"Plumbing",
            "type":"Services"
        }
    ],
    "sg:phone":"+1 503 253 4828",
    "sg:postcode":"97220",
    "sg:province":"OR",
    "sg:website":"www.metro-rooter.com",
    "wof:name":"Metro Rooter & Plumbing",
    "wof:placetype":"venue"
},
  "geometry": {"coordinates":[-122.552942,45.560696],"type":"Point"}
}