{
  "type": "Feature",
  "properties": {
    "iso:country":"US",
    "sg:address":"1210 Dry Hollow Rd",
    "sg:city":"The Dalles",
    "sg:classifiers":[
        {
            "category":"Health Services",
            "subcategory":"Doctor",
            "type":"Services"
        }
    ],
    "sg:phone":"+1 541 298 4976",
    "sg:postcode":"97058",
    "sg:province":"OR",
    "wof:name":"R B Koch DMD",
    "wof:placetype":"venue"
},
  "geometry": {"coordinates":[-121.166737,45.593753],"type":"Point"}
}