{
  "type": "Feature",
  "properties": {
    "addr:full":"3131 NE Glisan St Portland OR 97232",
    "addr:housenumber":"3131",
    "addr:postcode":"97232",
    "addr:street":"Ne Glisan St",
    "iso:country":"US",
    "sg:address":"3131 NE Glisan St",
    "sg:city":"Portland",
    "sg:classifiers":[
        {
            "category":"Education",
            "subcategory":"School",
            "type":"Public Place"
        },
        {
            "category":"Organizations",
            "subcategory":"Religious Organization",
            "type":"Services"
        }
    ],
    "sg:phone":"+1 503 234 7031",
    "sg:postcode":"97232",
    "sg:province":"OR",
    "sg:tags":[
        "high",
        "middle",
        "elementary"
    ],
    "wof:name":"Agia Sophia Academy",
    "wof:placetype":"venue"
},
  "geometry": {"coordinates":[-122.632631,45.526597],"type":"Point"}
}