{
  "type": "Feature",
  "properties": {
    "addr:full":"20675 SW 65th Ave Tualatin OR 97062",
    "addr:housenumber":"20675",
    "addr:postcode":"97062",
    "addr:street":"Sw 65Th Ave",
    "iso:country":"US",
    "sg:address":"20675 SW 65th Ave",
    "sg:city":"Tualatin",
    "sg:classifiers":[
        {
            "category":"Building & Trades",
            "subcategory":"Plumbing",
            "type":"Services"
        },
        {
            "category":"Building & Trades",
            "subcategory":"Construction",
            "type":"Services"
        }
    ],
    "sg:phone":"+1 503 692 1234",
    "sg:postcode":"97062",
    "sg:province":"OR",
    "sg:tags":[
        "repair",
        "system",
        "specialty",
        "heating",
        "clean",
        "contractor",
        "air conditioning",
        "boilers-repair"
    ],
    "wof:name":"Fresh Air Co Inc",
    "wof:placetype":"venue"
},
  "geometry": {"coordinates":[-122.74391799999999,45.369629],"type":"Point"}
}