{
  "type": "Feature",
  "properties": {
    "addr:full":"7317 SE 65th Ave Portland OR 97206",
    "addr:housenumber":"7317",
    "addr:postcode":"97206",
    "addr:street":"Se 65Th Ave",
    "iso:country":"US",
    "sg:address":"7317 SE 65th Ave",
    "sg:city":"Portland",
    "sg:classifiers":[
        {
            "category":"Professional",
            "type":"Services"
        }
    ],
    "sg:phone":"+1 503 775 9064",
    "sg:postcode":"97206",
    "sg:province":"OR",
    "wof:name":"Lenora J Sturgis",
    "wof:placetype":"venue"
},
  "geometry": {"coordinates":[-122.59624599999999,45.469583],"type":"Point"}
}