{
  "type": "Feature",
  "properties": {
    "iso:country":"US",
    "sg:address":"1161 SW 14th Ave",
    "sg:city":"Ontario",
    "sg:classifiers":[
        {
            "category":"Retail",
            "subcategory":"Repair Shop",
            "type":"Services"
        }
    ],
    "sg:phone":"+1 541 823 8049",
    "sg:postcode":"97914",
    "sg:province":"OR",
    "sg:tags":[
        "appliance"
    ],
    "wof:name":"Marks Appliance Service",
    "wof:placetype":"venue"
},
  "geometry": {"coordinates":[-116.97959,44.014021],"type":"Point"}
}