{
  "type": "Feature",
  "properties": {
    "addr:full":"3280 W 1st Ave Eugene OR 97402",
    "addr:housenumber":"3280",
    "addr:postcode":"97402",
    "addr:street":"W 1St Ave",
    "iso:country":"US",
    "sg:address":"3280 W 1st Ave",
    "sg:city":"Eugene",
    "sg:classifiers":[
        {
            "category":"Wholesale",
            "subcategory":"Hardware",
            "type":"Manufacturing & Wholesale Goods"
        }
    ],
    "sg:phone":"+1 541 485 8611",
    "sg:postcode":"97402",
    "sg:province":"OR",
    "sg:tags":[
        "plumbing",
        "fixture",
        "supply"
    ],
    "wof:name":"FNW/Familian Northwest",
    "wof:placetype":"venue"
},
  "geometry": {"coordinates":[-123.145819,44.058784],"type":"Point"}
}