{
  "type": "Feature",
  "properties": {
    "addr:full":"1515 NW Fir Ave Redmond OR 97756",
    "addr:housenumber":"1515",
    "addr:postcode":"97756",
    "addr:street":"Nw Fir Ave",
    "iso:country":"US",
    "sg:address":"1515 NW Fir Ave",
    "sg:city":"Redmond",
    "sg:classifiers":[
        {
            "category":"Real Estate",
            "subcategory":"Developer",
            "type":"Services"
        }
    ],
    "sg:phone":"+1 541 548 3601",
    "sg:postcode":"97756",
    "sg:province":"OR",
    "sg:tags":[
        "mobile",
        "home"
    ],
    "wof:name":"Remington Arms Mobile Home Pk",
    "wof:placetype":"venue"
},
  "geometry": {"coordinates":[-121.18419,44.281396],"type":"Point"}
}