{
  "type": "Feature",
  "properties": {
    "iso:country":"US",
    "sg:address":"1325 I St",
    "sg:city":"Coos Bay",
    "sg:classifiers":[
        {
            "category":"Building & Trades",
            "subcategory":"Construction",
            "type":"Services"
        }
    ],
    "sg:phone":"+1 541 269 9708",
    "sg:postcode":"97420",
    "sg:province":"OR",
    "wof:name":"Zosel Pat Contracting",
    "wof:placetype":"venue"
},
  "geometry": {"coordinates":[-124.189812,43.358656],"type":"Point"}
}