{
  "type": "Feature",
  "properties": {
    "addr:full":"1901 NW 26th At Upshur Portland OR 97210",
    "addr:housenumber":"1901",
    "addr:postcode":"97210",
    "addr:street":"Nw 26Th At",
    "iso:country":"US",
    "sg:address":"1901 NW 26th At Upshur",
    "sg:city":"Portland",
    "sg:classifiers":[
        {
            "category":"Sports & Exercise",
            "subcategory":"Gym",
            "type":"Entertainment"
        }
    ],
    "sg:phone":"+1 541 490 3607",
    "sg:postcode":"97210",
    "sg:province":"OR",
    "sg:tags":[
        "yoga"
    ],
    "sg:website":"yoganwpdx.com/",
    "wof:name":"Yoga NW",
    "wof:placetype":"venue"
},
  "geometry": {"coordinates":[-122.704882,45.536113],"type":"Point"}
}