{
  "type": "Feature",
  "properties": {
    "iso:country":"US",
    "sg:address":"12625 SW Grant Ave",
    "sg:city":"Portland",
    "sg:classifiers":[
        {
            "category":"Health Services",
            "subcategory":"Clinic",
            "type":"Services"
        }
    ],
    "sg:phone":"+1 503 620 8425",
    "sg:postcode":"97223",
    "sg:province":"OR",
    "sg:tags":[
        "home",
        "care"
    ],
    "wof:name":"Grant Home Care",
    "wof:placetype":"venue"
},
  "geometry": {"coordinates":[-122.778353,45.429825],"type":"Point"}
}