{
  "type": "Feature",
  "properties": {
    "iso:country":"US",
    "sg:address":"2328 NW Mill Pond Rd",
    "sg:city":"Portland",
    "sg:classifiers":[
        {
            "category":"Real Estate",
            "subcategory":"Real Estate Agent",
            "type":"Services"
        }
    ],
    "sg:phone":"+1 503 297 5921",
    "sg:postcode":"97229",
    "sg:province":"OR",
    "wof:name":"Steven E Marcy",
    "wof:placetype":"venue"
},
  "geometry": {"coordinates":[-122.78394900000001,45.538689],"type":"Point"}
}