{
  "type": "Feature",
  "properties": {
    "iso:country":"US",
    "sg:address":"1706 Campbell St",
    "sg:city":"Baker City",
    "sg:classifiers":[
        {
            "category":"Food & Beverages",
            "subcategory":"Specialty",
            "type":"Retail Goods"
        }
    ],
    "sg:phone":"+1 541 524 9290",
    "sg:postcode":"97814",
    "sg:province":"OR",
    "sg:tags":[
        "tea",
        "coffee"
    ],
    "wof:name":"Coffee Corral",
    "wof:placetype":"venue"
},
  "geometry": {"coordinates":[-117.826033,44.781772],"type":"Point"}
}