{
  "type": "Feature",
  "properties": {
    "iso:country":"US",
    "sg:address":"12070 SW Fischer Rd",
    "sg:city":"Portland",
    "sg:classifiers":[
        {
            "category":"Building & Trades",
            "subcategory":"Construction",
            "type":"Services"
        }
    ],
    "sg:phone":"+1 503 620 5796",
    "sg:postcode":"97224",
    "sg:province":"OR",
    "sg:tags":[
        "house"
    ],
    "wof:name":"Double V General Construction",
    "wof:placetype":"venue"
},
  "geometry": {"coordinates":[-122.802042,45.397898],"type":"Point"}
}