{
  "type": "Feature",
  "properties": {
    "iso:country":"US",
    "sg:address":"3160 N Main St",
    "sg:city":"Prineville",
    "sg:classifiers":[
        {
            "category":"Building & Trades",
            "subcategory":"Construction",
            "type":"Services"
        }
    ],
    "sg:phone":"+1 541 447 5956",
    "sg:postcode":"97754",
    "sg:province":"OR",
    "sg:tags":[
        "general",
        "contractor"
    ],
    "wof:name":"Garside Construction",
    "wof:placetype":"venue"
},
  "geometry": {"coordinates":[-120.846839,44.329633],"type":"Point"}
}