{
  "type": "Feature",
  "properties": {
    "iso:country":"US",
    "sg:address":"428 N State St",
    "sg:city":"Lake Oswego",
    "sg:classifiers":[
        {
            "category":"Shopping",
            "subcategory":"Bicycles & Sporting Goods",
            "type":"Retail Goods"
        }
    ],
    "sg:phone":"+1 503 699 8665",
    "sg:postcode":"97034",
    "sg:province":"OR",
    "sg:tags":[
        "bike"
    ],
    "sg:website":"www.Lakeside-bikes.com",
    "wof:name":"Lakeside Bicycles",
    "wof:placetype":"venue"
},
  "geometry": {"coordinates":[-122.66300200000001,45.419899],"type":"Point"}
}