{
  "type": "Feature",
  "properties": {
    "iso:country":"US",
    "sg:address":"3700 NE 185th Dr",
    "sg:city":"Portland",
    "sg:classifiers":[
        {
            "category":"Real Estate",
            "subcategory":"Real Estate Services",
            "type":"Services"
        },
        {
            "category":"Real Estate",
            "subcategory":"Real Estate Agent",
            "type":"Services"
        }
    ],
    "sg:phone":"+1 503 533 9233",
    "sg:postcode":"97230",
    "sg:province":"OR",
    "sg:tags":[
        "buyer",
        "broker"
    ],
    "wof:name":"Harley Grahn",
    "wof:placetype":"venue"
},
  "geometry": {"coordinates":[-122.472932,45.550299],"type":"Point"}
}