{
  "type": "Feature",
  "properties": {
    "iso:country":"US",
    "sg:address":"4655 NW 235th Ave",
    "sg:city":"Hillsboro",
    "sg:classifiers":[
        {
            "category":"Wholesale",
            "subcategory":"Machinery & Supplies",
            "type":"Manufacturing & Wholesale Goods"
        }
    ],
    "sg:phone":"+1 503 693 6152",
    "sg:postcode":"97124",
    "sg:province":"OR",
    "sg:tags":[
        "medical-cylinder",
        "bulk",
        "gas-industrial"
    ],
    "sg:website":"http://www.cryostar.com",
    "wof:name":"Boc Gases Special Gases",
    "wof:placetype":"venue"
},
  "geometry": {"coordinates":[-122.918301,45.553653],"type":"Point"}
}