{
  "type": "Feature",
  "properties": {
    "iso:country":"US",
    "sg:address":"820 7th St",
    "sg:city":"Oregon City",
    "sg:classifiers":[
        {
            "category":"Utilities",
            "subcategory":"Refuse",
            "type":"Services"
        }
    ],
    "sg:phone":"+1 503 829 6183",
    "sg:postcode":"97045",
    "sg:province":"OR",
    "sg:tags":[
        "garbage",
        "collection"
    ],
    "wof:name":"Molalla Sanitary Svc",
    "wof:placetype":"venue"
},
  "geometry": {"coordinates":[-122.60264599999999,45.355097],"type":"Point"}
}