{
  "type": "Feature",
  "properties": {
    "iso:country":"US",
    "sg:address":"3009 Maplewood Ct",
    "sg:city":"Philomath",
    "sg:classifiers":[
        {
            "category":"Professional",
            "type":"Services"
        }
    ],
    "sg:phone":"+1 541 929 5620",
    "sg:postcode":"97370",
    "sg:province":"OR",
    "wof:name":"Planting Seeds Inc",
    "wof:placetype":"venue"
},
  "geometry": {"coordinates":[-123.339923,44.539845],"type":"Point"}
}