{
  "type": "Feature",
  "properties": {
    "iso:country":"US",
    "sg:address":"4901 Scotts Valley Rd",
    "sg:city":"Yoncalla",
    "sg:classifiers":[
        {
            "category":"Restaurant",
            "type":"Food & Drink"
        }
    ],
    "sg:phone":"+1 541 849 2518",
    "sg:postcode":"97499",
    "sg:province":"OR",
    "sg:tags":[
        "eating"
    ],
    "wof:name":"Just Ducky Diner",
    "wof:placetype":"venue"
},
  "geometry": {"coordinates":[-123.15293800000001,43.60518],"type":"Point"}
}