{
  "type": "Feature",
  "properties": {
    "addr:full":"4831 SW Richardson Dr Portland OR 97239",
    "addr:housenumber":"4831",
    "addr:postcode":"97239",
    "addr:street":"Sw Richardson Dr",
    "iso:country":"US",
    "sg:address":"4831 SW Richardson Dr",
    "sg:city":"Portland",
    "sg:classifiers":[
        {
            "category":"Professional",
            "subcategory":"Advertising",
            "type":"Services"
        }
    ],
    "sg:phone":"+1 503 244 8024",
    "sg:postcode":"97239",
    "sg:province":"OR",
    "sg:tags":[
        "agency"
    ],
    "wof:name":"Eps Inc",
    "wof:placetype":"venue"
},
  "geometry": {"coordinates":[-122.703459,45.487291],"type":"Point"}
}