{
  "type": "Feature",
  "properties": {
    "iso:country":"US",
    "sg:address":"2929 NE Jackson School Rd",
    "sg:city":"Hillsboro",
    "sg:classifiers":[
        {
            "category":"Cinema",
            "subcategory":"Movie Rental",
            "type":"Entertainment"
        }
    ],
    "sg:phone":"+1 503 443 3961",
    "sg:postcode":"97124",
    "sg:province":"OR",
    "sg:tags":[
        "video",
        "tape"
    ],
    "wof:name":"Cleanflicks Northwest LLC",
    "wof:placetype":"venue"
},
  "geometry": {"coordinates":[-122.97978999999999,45.545646],"type":"Point"}
}