{
  "type": "Feature",
  "properties": {
    "addr:full":"7932 NE Halsey St Portland OR 97213",
    "addr:housenumber":"7932",
    "addr:postcode":"97213",
    "addr:street":"Ne Halsey St",
    "iso:country":"US",
    "sg:address":"7932 NE Halsey St",
    "sg:city":"Portland",
    "sg:classifiers":[
        {
            "category":"Insurance",
            "subcategory":"Insurance Agent",
            "type":"Services"
        }
    ],
    "sg:phone":"+1 503 252 6609",
    "sg:postcode":"97213",
    "sg:province":"OR",
    "wof:name":"Terry Helland Insurance Agency",
    "wof:placetype":"venue"
},
  "geometry": {"coordinates":[-122.581203,45.533534],"type":"Point"}
}