{
  "type": "Feature",
  "properties": {
    "iso:country":"US",
    "sg:address":"12766 NW Hartford St",
    "sg:city":"Portland",
    "sg:classifiers":[
        {
            "category":"Health Services",
            "subcategory":"Health Practitioner",
            "type":"Services"
        }
    ],
    "sg:phone":"+1 503 747 3307",
    "sg:postcode":"97229",
    "sg:province":"OR",
    "sg:tags":[
        "nutritionist"
    ],
    "sg:website":"rosemaryssolutions.com",
    "wof:name":"Rosemary's Solutions for Sustainable Wellness",
    "wof:placetype":"venue"
},
  "geometry": {"coordinates":[-122.80829799999999,45.544355],"type":"Point"}
}