{
  "type": "Feature",
  "properties": {
    "iso:country":"US",
    "sg:address":"201 Bateman Dr Ste 17",
    "sg:city":"Central Point",
    "sg:classifiers":[
        {
            "category":"Food & Beverages",
            "subcategory":"Candy",
            "type":"Retail Goods"
        }
    ],
    "sg:phone":"+1 541 664 0369",
    "sg:postcode":"97502",
    "sg:province":"OR",
    "sg:tags":[
        "store"
    ],
    "sg:website":"www.petesgourmetconfections.com",
    "wof:name":"Pete's Gourmet Confections",
    "wof:placetype":"venue"
},
  "geometry": {"coordinates":[-122.882972,42.394997],"type":"Point"}
}