{
  "type": "Feature",
  "properties": {
    "addr:full":"461 S Valley View Rd Ashland OR 97520",
    "addr:housenumber":"461",
    "addr:postcode":"97520",
    "addr:street":"S Valley View Rd",
    "iso:country":"US",
    "sg:address":"461 S Valley View Rd",
    "sg:city":"Ashland",
    "sg:classifiers":[
        {
            "category":"Retail",
            "subcategory":"Auto Repair",
            "type":"Services"
        }
    ],
    "sg:phone":"+1 541 482 3995",
    "sg:postcode":"97520",
    "sg:province":"OR",
    "sg:tags":[
        "general"
    ],
    "wof:name":"Siskiyou Auto Care",
    "wof:placetype":"venue"
},
  "geometry": {"coordinates":[-122.740533,42.224179],"type":"Point"}
}