{
  "type": "Feature",
  "properties": {
    "addr:full":"1810 E Powell Blvd Gresham OR 97080",
    "addr:housenumber":"1810",
    "addr:postcode":"97080",
    "addr:street":"E Powell Blvd",
    "iso:country":"US",
    "sg:address":"1810 E Powell Blvd",
    "sg:city":"Gresham",
    "sg:classifiers":[
        {
            "category":"Building & Trades",
            "subcategory":"Plumbing",
            "type":"Services"
        }
    ],
    "sg:phone":"+1 503 661 3877",
    "sg:postcode":"97080",
    "sg:province":"OR",
    "sg:tags":[
        "balancing",
        "air"
    ],
    "wof:name":"System Commissioning",
    "wof:placetype":"venue"
},
  "geometry": {"coordinates":[-122.41191000000001,45.495924],"type":"Point"}
}