{
  "type": "Feature",
  "properties": {
    "iso:country":"US",
    "sg:address":"809 W Sheridan St",
    "sg:city":"Newberg",
    "sg:classifiers":[
        {
            "category":"Shopping",
            "type":"Retail Goods"
        }
    ],
    "sg:phone":"+1 503 538 9509",
    "sg:postcode":"97132",
    "sg:province":"OR",
    "sg:tags":[
        "cards",
        "sport",
        "baseball",
        "memorabilia"
    ],
    "wof:name":"Newberg Sports Cards Co",
    "wof:placetype":"venue"
},
  "geometry": {"coordinates":[-122.99021999999999,45.302176],"type":"Point"}
}