{
  "type": "Feature",
  "properties": {
    "iso:country":"US",
    "sg:address":"614 Moonshine Park Rd",
    "sg:city":"Logsden",
    "sg:classifiers":[
        {
            "category":"Farming",
            "subcategory":"Nursery",
            "type":"Manufacturing & Wholesale Goods"
        }
    ],
    "sg:phone":"+1 541 444 9324",
    "sg:postcode":"97357",
    "sg:province":"OR",
    "sg:tags":[
        "ornamental"
    ],
    "wof:name":"Fruits of Labor",
    "wof:placetype":"venue"
},
  "geometry": {"coordinates":[-123.789959,44.744143],"type":"Point"}
}