{
  "type": "Feature",
  "properties": {
    "iso:country":"US",
    "sg:address":"5415 SW Westgate Dr Ste 100",
    "sg:city":"Portland",
    "sg:classifiers":[
        {
            "category":"Real Estate",
            "subcategory":"Surveying",
            "type":"Services"
        },
        {
            "category":"Professional",
            "subcategory":"Business Services",
            "type":"Services"
        },
        {
            "category":"Professional",
            "subcategory":"Engineering",
            "type":"Services"
        }
    ],
    "sg:phone":"+1 503 419 2500",
    "sg:postcode":"97221",
    "sg:province":"OR",
    "sg:tags":[
        "land",
        "civil",
        "consultant",
        "surveyor",
        "planning",
        "coach",
        "engineer"
    ],
    "sg:website":"http://www.cardnowrg.com",
    "wof:name":"Cardno WRG",
    "wof:placetype":"venue"
},
  "geometry": {"coordinates":[-122.731959,45.510455],"type":"Point"}
}