{
  "type": "Feature",
  "properties": {
    "iso:country":"US",
    "sg:address":"1020 Ivy St",
    "sg:city":"Junction City",
    "sg:classifiers":[
        {
            "category":"Retail",
            "subcategory":"Auto Repair",
            "type":"Services"
        }
    ],
    "sg:phone":"+1 541 998 6541",
    "sg:postcode":"97448",
    "sg:province":"OR",
    "sg:tags":[
        "body"
    ],
    "wof:name":"Countryside Interiors",
    "wof:placetype":"venue"
},
  "geometry": {"coordinates":[-123.204808,44.223258],"type":"Point"}
}