{
  "type": "Feature",
  "properties": {
    "iso:country":"US",
    "sg:address":"SE 2nd St and SE Clay",
    "sg:city":"Portland",
    "sg:classifiers":[
        {
            "category":"Landmark",
            "subcategory":"Historic",
            "type":"Public Place"
        }
    ],
    "sg:postcode":"97214",
    "sg:province":"OR",
    "sg:tags":[
        "building",
        "historical"
    ],
    "wof:name":"Old Taylor Electric Supply Co Building",
    "wof:placetype":"venue"
},
  "geometry": {"coordinates":[-122.663826,45.511535],"type":"Point"}
}