{
  "type": "Feature",
  "properties": {
    "addr:full":"3030 NE Hogan Dr Ste F Gresham OR 97030",
    "addr:housenumber":"3030",
    "addr:postcode":"97030",
    "addr:street":"Ne Hogan Dr Ste F",
    "iso:country":"US",
    "sg:address":"3030 NE Hogan Dr Ste F",
    "sg:city":"Gresham",
    "sg:classifiers":[
        {
            "category":"Retail",
            "subcategory":"Veterinary Services",
            "type":"Services"
        }
    ],
    "sg:phone":"+1 503 667 2763",
    "sg:postcode":"97030",
    "sg:province":"OR",
    "sg:tags":[
        "veterinarian"
    ],
    "wof:name":"A Animal Health Services Spay & Neuter Clinics",
    "wof:placetype":"venue"
},
  "geometry": {"coordinates":[-122.412003,45.5172],"type":"Point"}
}