{
  "type": "Feature",
  "properties": {
    "iso:country":"US",
    "sg:address":"704 SW Hurbert St",
    "sg:city":"Newport",
    "sg:classifiers":[
        {
            "category":"Restaurant",
            "type":"Food & Drink"
        }
    ],
    "sg:phone":"+1 541 574 0011",
    "sg:postcode":"97365",
    "sg:province":"OR",
    "sg:tags":[
        "shop",
        "coffee"
    ],
    "wof:name":"Solid Ground Coffee House",
    "wof:placetype":"venue"
},
  "geometry": {"coordinates":[-124.057304,44.633673],"type":"Point"}
}