{
  "type": "Feature",
  "properties": {
    "addr:full":"856 Water St Springfield OR 97477",
    "addr:housenumber":"856",
    "addr:postcode":"97477",
    "addr:street":"Water St",
    "iso:country":"US",
    "sg:address":"856 Water St",
    "sg:city":"Springfield",
    "sg:classifiers":[
        {
            "category":"Building & Trades",
            "subcategory":"Landscaping Services",
            "type":"Services"
        }
    ],
    "sg:phone":"+1 541 988 9273",
    "sg:postcode":"97477",
    "sg:province":"OR",
    "wof:name":"Scotts Landscape Maintenance",
    "wof:placetype":"venue"
},
  "geometry": {"coordinates":[-123.02779,44.052769],"type":"Point"}
}