{
  "type": "Feature",
  "properties": {
    "iso:country":"US",
    "sg:address":"704 SW 6th St",
    "sg:city":"Redmond",
    "sg:classifiers":[
        {
            "category":"Restaurant",
            "type":"Food & Drink"
        },
        {
            "category":"Ice Cream",
            "type":"Food & Drink"
        }
    ],
    "sg:menulink":"http://www.allmenus.com/or/redmond/175853-dairy-queen/menu/",
    "sg:phone":"+1 541 548 2616",
    "sg:postcode":"97756",
    "sg:province":"OR",
    "sg:tags":[
        "burger",
        "american",
        "ice",
        "cream"
    ],
    "wof:name":"Dairy Queen",
    "wof:placetype":"venue"
},
  "geometry": {"coordinates":[-121.174161,44.270436],"type":"Point"}
}