{
  "type": "Feature",
  "properties": {
    "iso:country":"US",
    "sg:address":"1427 Erika Ave NE",
    "sg:city":"Keizer",
    "sg:classifiers":[
        {
            "category":"Communications",
            "type":"Services"
        }
    ],
    "sg:phone":"+1 503 391 4989",
    "sg:postcode":"97303",
    "sg:province":"OR",
    "wof:name":"Media Guard",
    "wof:placetype":"venue"
},
  "geometry": {"coordinates":[-123.013374,45.032827],"type":"Point"}
}