{
  "type": "Feature",
  "properties": {
    "iso:country":"US",
    "sg:address":"1101 16th St",
    "sg:city":"Springfield",
    "sg:classifiers":[
        {
            "category":"Insurance",
            "subcategory":"Insurance Agent",
            "type":"Services"
        }
    ],
    "sg:phone":"+1 541 485 6026",
    "sg:postcode":"97477",
    "sg:province":"OR",
    "sg:tags":[
        "life"
    ],
    "wof:name":"Advanced Insurance Planning",
    "wof:placetype":"venue"
},
  "geometry": {"coordinates":[-123.00175,44.056205],"type":"Point"}
}