{
  "type": "Feature",
  "properties": {
    "iso:country":"US",
    "sg:address":"957 NE Stephens St",
    "sg:city":"Roseburg",
    "sg:classifiers":[
        {
            "category":"Shopping",
            "subcategory":"Computers & Home Electronics",
            "type":"Retail Goods"
        }
    ],
    "sg:phone":"+1 541 957 9036",
    "sg:postcode":"97470",
    "sg:province":"OR",
    "sg:tags":[
        "sound",
        "automobile",
        "equipment"
    ],
    "sg:website":"www.goodvibrationsaudio.com",
    "wof:name":"Good Vibrations",
    "wof:placetype":"venue"
},
  "geometry": {"coordinates":[-123.345309,43.220867],"type":"Point"}
}