{
  "type": "Feature",
  "properties": {
    "addr:full":"16338 SE Stark Street Portland OR 97233",
    "addr:postcode":"16338;97233",
    "addr:street":"Se Stark Street",
    "iso:country":"US",
    "sg:address":"16338 SE Stark Street",
    "sg:city":"Portland",
    "sg:classifiers":[
        {
            "category":"Health Services",
            "subcategory":"Dentist",
            "type":"Services"
        }
    ],
    "sg:phone":"+1 503 761 2243",
    "sg:postcode":"97233",
    "sg:province":"OR",
    "sg:tags":[
        "pediatric"
    ],
    "sg:website":"www.pediatricdentistrypc.com",
    "wof:name":"Larsen Noel DMD",
    "wof:placetype":"venue"
},
  "geometry": {"coordinates":[-122.494484,45.519039],"type":"Point"}
}