{
  "type": "Feature",
  "properties": {
    "iso:country":"US",
    "sg:address":"111 SW 5th Ave Suite 1720",
    "sg:city":"Portland",
    "sg:classifiers":[
        {
            "category":"Professional",
            "subcategory":"Employment Agencies",
            "type":"Services"
        }
    ],
    "sg:phone":"+1 877 233 1510",
    "sg:postcode":"97204",
    "sg:province":"OR",
    "sg:tags":[
        "opportunity",
        "temporary",
        "contractor"
    ],
    "sg:website":"http://www.appleone.com/?sc=26",
    "wof:name":"AppleOne",
    "wof:placetype":"venue"
},
  "geometry": {"coordinates":[-122.675507,45.522598],"type":"Point"}
}