{
  "type": "Feature",
  "properties": {
    "addr:full":"16495 Watergap Rd Williams OR 97544",
    "addr:housenumber":"16495",
    "addr:postcode":"97544",
    "addr:street":"Watergap Rd",
    "iso:country":"US",
    "sg:address":"16495 Watergap Rd",
    "sg:city":"Williams",
    "sg:classifiers":[
        {
            "category":"Retail",
            "subcategory":"Auto Repair",
            "type":"Services"
        }
    ],
    "sg:phone":"+1 541 846 6146",
    "sg:postcode":"97544",
    "sg:province":"OR",
    "sg:tags":[
        "general"
    ],
    "wof:name":"Oregon Diesel",
    "wof:placetype":"venue"
},
  "geometry": {"coordinates":[-123.27517899999999,42.249108],"type":"Point"}
}