{
  "type": "Feature",
  "properties": {
    "addr:full":"3200 Delap Rd Klamath Falls OR 97601",
    "addr:housenumber":"3200",
    "addr:postcode":"97601",
    "addr:street":"Delap Rd",
    "iso:country":"US",
    "sg:address":"3200 Delap Rd",
    "sg:city":"Klamath Falls",
    "sg:classifiers":[
        {
            "category":"Government",
            "subcategory":"Office",
            "type":"Public Place"
        }
    ],
    "sg:phone":"+1 541 883 5681",
    "sg:postcode":"97601",
    "sg:province":"OR",
    "sg:tags":[
        "state",
        "manages",
        "protects",
        "forest",
        "land"
    ],
    "wof:name":"Klamath-Lake District Office",
    "wof:placetype":"venue"
},
  "geometry": {"coordinates":[-121.80088600000001,42.192208],"type":"Point"}
}