{
  "type": "Feature",
  "properties": {
    "iso:country":"US",
    "sg:address":"13135 SE Foster Rd",
    "sg:city":"Portland",
    "sg:classifiers":[
        {
            "category":"Professional",
            "subcategory":"Business Services",
            "type":"Services"
        },
        {
            "category":"Manufacturing",
            "subcategory":"Apparel",
            "type":"Manufacturing & Wholesale Goods"
        }
    ],
    "sg:phone":"+1 503 762 1733",
    "sg:postcode":"97236",
    "sg:province":"OR",
    "sg:tags":[
        "embroidery"
    ],
    "wof:name":"Grammi Z's Embroidery",
    "wof:placetype":"venue"
},
  "geometry": {"coordinates":[-122.528921,45.476839],"type":"Point"}
}