{
  "type": "Feature",
  "properties": {
    "iso:country":"US",
    "sg:address":"4491 SE Tillamook Loop",
    "sg:city":"Prineville",
    "sg:classifiers":[
        {
            "category":"Building & Trades",
            "subcategory":"Construction",
            "type":"Services"
        }
    ],
    "sg:phone":"+1 541 447 7881",
    "sg:postcode":"97754",
    "sg:province":"OR",
    "sg:tags":[
        "systems-repairing",
        "system",
        "specialty",
        "heating",
        "equipment",
        "contractor",
        "air conditioning"
    ],
    "wof:name":"Mobile Cool",
    "wof:placetype":"venue"
},
  "geometry": {"coordinates":[-120.80591200000001,44.171809],"type":"Point"}
}