{
  "type": "Feature",
  "properties": {
    "iso:country":"US",
    "sg:address":"10514 Leverman Rd SE",
    "sg:city":"Aumsville",
    "sg:classifiers":[
        {
            "category":"Building & Trades",
            "subcategory":"Plumbing",
            "type":"Services"
        }
    ],
    "sg:phone":"+1 503 749 2021",
    "sg:postcode":"97325",
    "sg:province":"OR",
    "sg:tags":[
        "contractor"
    ],
    "wof:name":"Hopkins Plumbing",
    "wof:placetype":"venue"
},
  "geometry": {"coordinates":[-122.844475,44.837563],"type":"Point"}
}