{
  "type": "Feature",
  "properties": {
    "addr:full":"4110 Pacific Ave Forest Grove OR 97116",
    "addr:housenumber":"4110",
    "addr:postcode":"97116",
    "addr:street":"Pacific Ave",
    "iso:country":"US",
    "sg:address":"4110 Pacific Ave",
    "sg:city":"Forest Grove",
    "sg:classifiers":[
        {
            "category":"Banks & Credit Unions",
            "subcategory":"Bank",
            "type":"Services"
        }
    ],
    "sg:phone":"+1 503 359 4495",
    "sg:postcode":"97116",
    "sg:province":"OR",
    "sg:tags":[
        "state",
        "executive",
        "commercial"
    ],
    "wof:name":"Forest Grove",
    "wof:placetype":"venue"
},
  "geometry": {"coordinates":[-123.076412,45.520119],"type":"Point"}
}