{
  "type": "Feature",
  "properties": {
    "addr:full":"6235 SW Burlingame Avenue Portland OR 97239",
    "addr:housenumber":"6235",
    "addr:postcode":"97239",
    "addr:street":"Sw Burlingame Avenue",
    "iso:country":"US",
    "sg:address":"6235 SW Burlingame Avenue",
    "sg:city":"Portland",
    "sg:classifiers":[
        {
            "category":"Real Estate",
            "subcategory":"Real Estate Operator",
            "type":"Services"
        }
    ],
    "sg:phone":"+1 503 246 6645",
    "sg:postcode":"97239",
    "sg:province":"OR",
    "sg:tags":[
        "apartment"
    ],
    "wof:name":"West Hills Terrace",
    "wof:placetype":"venue"
},
  "geometry": {"coordinates":[-122.691345,45.478895],"type":"Point"}
}