{
  "type": "Feature",
  "properties": {
    "iso:country":"US",
    "sg:address":"300 SW Wilson Ln",
    "sg:city":"Boardman",
    "sg:classifiers":[
        {
            "category":"Government",
            "subcategory":"Fire Station",
            "type":"Public Place"
        }
    ],
    "sg:phone":"+1 541 481 3473",
    "sg:postcode":"97818",
    "sg:province":"OR",
    "sg:tags":[
        "department"
    ],
    "wof:name":"Boardman Rur Fire Prtction Dst",
    "wof:placetype":"venue"
},
  "geometry": {"coordinates":[-119.703896,45.827976],"type":"Point"}
}