{
  "type": "Feature",
  "properties": {
    "iso:country":"US",
    "sg:address":"1024 W C St",
    "sg:city":"Rainier",
    "sg:classifiers":[
        {
            "category":"Farming",
            "subcategory":"Farm",
            "type":"Manufacturing & Wholesale Goods"
        }
    ],
    "sg:phone":"+1 503 556 0113",
    "sg:postcode":"97048",
    "sg:province":"OR",
    "sg:tags":[
        "food",
        "covered",
        "crop"
    ],
    "wof:name":"Columbia Hydroseeding Inc",
    "wof:placetype":"venue"
},
  "geometry": {"coordinates":[-122.949929,46.091785],"type":"Point"}
}