{
  "type": "Feature",
  "properties": {
    "iso:country":"US",
    "sg:address":"4370 Silverton Rd NE",
    "sg:city":"Salem",
    "sg:classifiers":[
        {
            "category":"Freight",
            "type":"Transportation"
        }
    ],
    "sg:phone":"+1 503 363 7411",
    "sg:postcode":"97305",
    "sg:province":"OR",
    "sg:tags":[
        "recreational",
        "vehicle"
    ],
    "wof:name":"Bridges Rv Storage",
    "wof:placetype":"venue"
},
  "geometry": {"coordinates":[-122.976297,44.969799],"type":"Point"}
}