{
  "type": "Feature",
  "properties": {
    "addr:full":"3140 Juanipero Way Medford OR 97504",
    "addr:housenumber":"3140",
    "addr:postcode":"97504",
    "addr:street":"Juanipero Way",
    "iso:country":"US",
    "sg:address":"3140 Juanipero Way",
    "sg:city":"Medford",
    "sg:classifiers":[
        {
            "category":"Insurance",
            "subcategory":"Hazard Insurance",
            "type":"Services"
        },
        {
            "category":"Insurance",
            "subcategory":"Life Insurance",
            "type":"Services"
        }
    ],
    "sg:phone":"+1 541 773 2246",
    "sg:postcode":"97504",
    "sg:province":"OR",
    "wof:name":"Nwn Mutl Life Ins Co Of Milwaukee Wisconsin",
    "wof:placetype":"venue"
},
  "geometry": {"coordinates":[-122.82489,42.310139],"type":"Point"}
}