{
  "type": "Feature",
  "properties": {
    "iso:country":"US",
    "sg:address":"1155 Fir Acres Dr",
    "sg:city":"Eugene",
    "sg:classifiers":[
        {
            "category":"Wholesale",
            "subcategory":"Groceries",
            "type":"Manufacturing & Wholesale Goods"
        }
    ],
    "sg:phone":"+1 541 953 9690",
    "sg:postcode":"97401",
    "sg:province":"OR",
    "wof:name":"Reiki Room",
    "wof:placetype":"venue"
},
  "geometry": {"coordinates":[-123.096908,44.080816],"type":"Point"}
}