{
  "type": "Feature",
  "properties": {
    "iso:country":"US",
    "sg:address":"1619 Olmar Dr NW",
    "sg:city":"Grants Pass",
    "sg:classifiers":[
        {
            "category":"Retail",
            "subcategory":"Repair Shop",
            "type":"Services"
        }
    ],
    "sg:phone":"+1 541 474 0866",
    "sg:postcode":"97526",
    "sg:province":"OR",
    "sg:tags":[
        "electrical"
    ],
    "wof:name":"Action Appliance Service",
    "wof:placetype":"venue"
},
  "geometry": {"coordinates":[-123.341379,42.448514],"type":"Point"}
}