{
  "type": "Feature",
  "properties": {
    "iso:country":"US",
    "sg:address":"700 SE Emigrant Ave",
    "sg:city":"Pendleton",
    "sg:classifiers":[
        {
            "category":"Government",
            "subcategory":"Office",
            "type":"Public Place"
        }
    ],
    "sg:phone":"+1 541 276 9220",
    "sg:postcode":"97801",
    "sg:province":"OR",
    "sg:tags":[
        "division"
    ],
    "wof:name":"Human Services Oregon Dept",
    "wof:placetype":"venue"
},
  "geometry": {"coordinates":[-118.778728,45.672909],"type":"Point"}
}