{
  "type": "Feature",
  "properties": {
    "iso:country":"US",
    "sg:address":"1387 Pressler Ct S",
    "sg:city":"Salem",
    "sg:classifiers":[
        {
            "category":"Banks & Credit Unions",
            "subcategory":"Bank",
            "type":"Services"
        }
    ],
    "sg:phone":"+1 503 364 1567",
    "sg:postcode":"97306",
    "sg:province":"OR",
    "sg:tags":[
        "loan",
        "real estate"
    ],
    "wof:name":"M M Mortgage",
    "wof:placetype":"venue"
},
  "geometry": {"coordinates":[-123.063581,44.879868],"type":"Point"}
}