{
  "type": "Feature",
  "properties": {
    "iso:country":"US",
    "sg:address":"7134 SE 34th Avenue",
    "sg:city":"Portland",
    "sg:classifiers":[
        {
            "category":"Real Estate",
            "subcategory":"Architect",
            "type":"Services"
        }
    ],
    "sg:phone":"+1 503 774 5005",
    "sg:postcode":"97202",
    "sg:province":"OR",
    "wof:name":"Sternberg Bruce Architect",
    "wof:placetype":"venue"
},
  "geometry": {"coordinates":[-122.62839700000001,45.471993],"type":"Point"}
}