{
  "type": "Feature",
  "properties": {
    "iso:country":"US",
    "sg:address":"8749 NW Marshall St",
    "sg:city":"Portland",
    "sg:classifiers":[
        {
            "category":"Farming",
            "subcategory":"Farm & Veterinary Services",
            "type":"Manufacturing & Wholesale Goods"
        }
    ],
    "sg:phone":"+1 503 296 7859",
    "sg:postcode":"97229",
    "sg:province":"OR",
    "sg:tags":[
        "harvesting-contract",
        "crop",
        "harvesting"
    ],
    "wof:name":"Three Angels Vineyard",
    "wof:placetype":"venue"
},
  "geometry": {"coordinates":[-122.76779399999999,45.530992],"type":"Point"}
}