{
  "type": "Feature",
  "properties": {
    "iso:country":"US",
    "sg:address":"17419 SE Division St",
    "sg:city":"Portland",
    "sg:classifiers":[
        {
            "category":"Personal",
            "subcategory":"Beauty Salon",
            "type":"Services"
        }
    ],
    "sg:phone":"+1 503 258 1350",
    "sg:postcode":"97236",
    "sg:province":"OR",
    "sg:tags":[
        "shop"
    ],
    "wof:name":"Hair For Everyone",
    "wof:placetype":"venue"
},
  "geometry": {"coordinates":[-122.483865,45.504658],"type":"Point"}
}