{
  "type": "Feature",
  "properties": {
    "addr:full":"1121 Bothwick St Myrtle Point OR 97458",
    "addr:housenumber":"1121",
    "addr:postcode":"97458",
    "addr:street":"Bothwick St",
    "iso:country":"US",
    "sg:address":"1121 Bothwick St",
    "sg:city":"Myrtle Point",
    "sg:classifiers":[
        {
            "category":"Organizations",
            "subcategory":"Religious Organization",
            "type":"Services"
        },
        {
            "category":"Education",
            "subcategory":"School",
            "type":"Public Place"
        }
    ],
    "sg:phone":"+1 541 572 5012",
    "sg:postcode":"97458",
    "sg:province":"OR",
    "sg:tags":[
        "church"
    ],
    "wof:name":"Myrtle Point Christn Assembly",
    "wof:placetype":"venue"
},
  "geometry": {"coordinates":[-124.136448,43.060881],"type":"Point"}
}