{
  "type": "Feature",
  "properties": {
    "iso:country":"US",
    "sg:address":"3740 Market St NE",
    "sg:city":"Salem",
    "sg:classifiers":[
        {
            "category":"Shopping",
            "subcategory":"Department Store",
            "type":"Retail Goods"
        }
    ],
    "sg:phone":"+1 503 581 6324",
    "sg:postcode":"97301",
    "sg:province":"OR",
    "wof:name":"Fred Meyer",
    "wof:placetype":"venue"
},
  "geometry": {"coordinates":[-122.985465,44.950225],"type":"Point"}
}