{
  "type": "Feature",
  "properties": {
    "iso:country":"US",
    "sg:address":"35175 Riverside Dr SW",
    "sg:city":"Albany",
    "sg:classifiers":[
        {
            "category":"Building & Trades",
            "subcategory":"Construction",
            "type":"Services"
        }
    ],
    "sg:phone":"+1 541 928 7074",
    "sg:postcode":"97321",
    "sg:province":"OR",
    "sg:tags":[
        "contractor",
        "nonresidential"
    ],
    "wof:name":"Charles Womack Masonry",
    "wof:placetype":"venue"
},
  "geometry": {"coordinates":[-123.169929,44.598999],"type":"Point"}
}