{
  "type": "Feature",
  "properties": {
    "addr:full":"5755 SE Lincoln St Portland OR 97215",
    "addr:housenumber":"5755",
    "addr:postcode":"97215",
    "addr:street":"Se Lincoln St",
    "iso:country":"US",
    "sg:address":"5755 SE Lincoln St",
    "sg:city":"Portland",
    "sg:classifiers":[
        {
            "category":"Sports & Exercise",
            "subcategory":"Gym",
            "type":"Entertainment"
        }
    ],
    "sg:phone":"+1 503 233 3686",
    "sg:postcode":"97215",
    "sg:province":"OR",
    "sg:tags":[
        "fitness",
        "physical",
        "facility"
    ],
    "wof:name":"Jungle Gym Fitness Center",
    "wof:placetype":"venue"
},
  "geometry": {"coordinates":[-122.60351,45.508142],"type":"Point"}
}