{
  "type": "Feature",
  "properties": {
    "addr:full":"4435 N Channel Ave Portland OR 97217",
    "addr:housenumber":"4435",
    "addr:postcode":"97217",
    "addr:street":"N Channel Ave",
    "iso:country":"US",
    "sg:address":"4435 N Channel Ave",
    "sg:city":"Portland",
    "sg:classifiers":[
        {
            "category":"Education",
            "subcategory":"School",
            "type":"Public Place"
        }
    ],
    "sg:phone":"+1 503 745 3532",
    "sg:postcode":"97217",
    "sg:province":"OR",
    "sg:tags":[
        "k-",
        "private"
    ],
    "wof:name":"First Gear Academy",
    "wof:placetype":"venue"
},
  "geometry": {"coordinates":[-122.704329,45.556581],"type":"Point"}
}