{
  "type": "Feature",
  "properties": {
    "addr:full":"1607 Robin Way Medford OR 97504",
    "addr:housenumber":"1607",
    "addr:postcode":"97504",
    "addr:street":"Robin Way",
    "iso:country":"US",
    "sg:address":"1607 Robin Way",
    "sg:city":"Medford",
    "sg:classifiers":[
        {
            "category":"Shopping",
            "subcategory":"Bicycles & Sporting Goods",
            "type":"Retail Goods"
        }
    ],
    "sg:phone":"+1 541 779 3052",
    "sg:postcode":"97504",
    "sg:province":"OR",
    "wof:name":"2fish Products Inc",
    "wof:placetype":"venue"
},
  "geometry": {"coordinates":[-122.850521,42.373398],"type":"Point"}
}