{
  "type": "Feature",
  "properties": {
    "iso:country":"US",
    "sg:address":"241 SW G St",
    "sg:city":"Grants Pass",
    "sg:classifiers":[
        {
            "category":"Restaurant",
            "type":"Food & Drink"
        }
    ],
    "sg:phone":"+1 541 955 6540",
    "sg:postcode":"97526",
    "sg:province":"OR",
    "sg:tags":[
        "eating"
    ],
    "wof:name":"Gst Deli",
    "wof:placetype":"venue"
},
  "geometry": {"coordinates":[-123.32888,42.439413],"type":"Point"}
}