{
  "type": "Feature",
  "properties": {
    "addr:full":"6464 SW Borland Rd Tualatin OR 97062",
    "addr:housenumber":"6464",
    "addr:postcode":"97062",
    "addr:street":"Sw Borland Rd",
    "iso:country":"US",
    "sg:address":"6464 SW Borland Rd",
    "sg:city":"Tualatin",
    "sg:classifiers":[
        {
            "category":"Health Services",
            "subcategory":"Doctor",
            "type":"Services"
        }
    ],
    "sg:phone":"+1 503 692 4880",
    "sg:postcode":"97062",
    "sg:province":"OR",
    "sg:tags":[
        "medical"
    ],
    "wof:name":"Burgess Elisa A MD",
    "wof:placetype":"venue"
},
  "geometry": {"coordinates":[-122.74237599999999,45.376648],"type":"Point"}
}