{
  "type": "Feature",
  "properties": {
    "iso:country":"US",
    "sg:address":"507 NE Obrien Pl",
    "sg:city":"Pendleton",
    "sg:classifiers":[
        {
            "category":"Building & Trades",
            "subcategory":"Construction",
            "type":"Services"
        }
    ],
    "sg:phone":"+1 541 276 7949",
    "sg:postcode":"97801",
    "sg:province":"OR",
    "sg:tags":[
        "house"
    ],
    "wof:name":"Duane Wood",
    "wof:placetype":"venue"
},
  "geometry": {"coordinates":[-118.752244,45.676784],"type":"Point"}
}