{
  "type": "Feature",
  "properties": {
    "iso:country":"US",
    "sg:address":"5055 Hwy 201",
    "sg:city":"Ontario",
    "sg:classifiers":[
        {
            "category":"Autos & Motor Vehicles",
            "subcategory":"Automobile Sales",
            "type":"Retail Goods"
        }
    ],
    "sg:phone":"+1 541 262 3956",
    "sg:postcode":"97914",
    "sg:province":"OR",
    "sg:tags":[
        "used"
    ],
    "wof:name":"H B H Sales L L C",
    "wof:placetype":"venue"
},
  "geometry": {"coordinates":[-116.944644,44.168482],"type":"Point"}
}