{
  "type": "Feature",
  "properties": {
    "addr:full":"450 E Main St John Day OR 97845",
    "addr:housenumber":"450",
    "addr:postcode":"97845",
    "addr:street":"E Main St",
    "iso:country":"US",
    "sg:address":"450 E Main St",
    "sg:city":"John Day",
    "sg:classifiers":[
        {
            "category":"Government",
            "subcategory":"Police Station",
            "type":"Public Place"
        }
    ],
    "sg:phone":"+1 541 575 0030",
    "sg:postcode":"97845",
    "sg:province":"OR",
    "sg:tags":[
        "department"
    ],
    "wof:name":"John Day Police Dept",
    "wof:placetype":"venue"
},
  "geometry": {"coordinates":[-118.94690199999999,44.416012],"type":"Point"}
}