{
  "type": "Feature",
  "properties": {
    "iso:country":"US",
    "sg:address":"1501 NE Davis St",
    "sg:city":"Portland",
    "sg:classifiers":[
        {
            "category":"Wholesale",
            "subcategory":"Motor Vehicles",
            "type":"Manufacturing & Wholesale Goods"
        }
    ],
    "sg:phone":"+1 503 258 0500",
    "sg:postcode":"97232",
    "sg:province":"OR",
    "sg:tags":[
        "automobile",
        "truck",
        "broker"
    ],
    "sg:website":"www.autoland.com",
    "wof:name":"Autoland",
    "wof:placetype":"venue"
},
  "geometry": {"coordinates":[-122.650728,45.5244],"type":"Point"}
}