{
  "type": "Feature",
  "properties": {
    "iso:country":"US",
    "sg:address":"3425 10th St",
    "sg:city":"Baker City",
    "sg:classifiers":[
        {
            "category":"Retail",
            "subcategory":"Veterinary Services",
            "type":"Services"
        }
    ],
    "sg:phone":"+1 541 523 7772",
    "sg:postcode":"97814",
    "sg:province":"OR",
    "wof:name":"Baker Veterinary Hospital",
    "wof:placetype":"venue"
},
  "geometry": {"coordinates":[-117.841595,44.791411],"type":"Point"}
}