{
  "type": "Feature",
  "properties": {
    "addr:full":"2228 SE 96th Ave Portland OR 97216",
    "addr:housenumber":"2228",
    "addr:postcode":"97216",
    "addr:street":"Se 96Th Ave",
    "iso:country":"US",
    "sg:address":"2228 SE 96th Ave",
    "sg:city":"Portland",
    "sg:classifiers":[
        {
            "category":"Building & Trades",
            "subcategory":"Cleaning & Sanitation",
            "type":"Services"
        }
    ],
    "sg:phone":"+1 503 762 6001",
    "sg:postcode":"97216",
    "sg:province":"OR",
    "sg:tags":[
        "maintenance"
    ],
    "wof:name":"Strugar Cleaning Services",
    "wof:placetype":"venue"
},
  "geometry": {"coordinates":[-122.563227,45.505838],"type":"Point"}
}