{
  "type": "Feature",
  "properties": {
    "addr:full":"1750 43rd St Florence OR 97439",
    "addr:housenumber":"1750",
    "addr:postcode":"97439",
    "addr:street":"43Rd St",
    "iso:country":"US",
    "sg:address":"1750 43rd St",
    "sg:city":"Florence",
    "sg:classifiers":[
        {
            "category":"Building & Trades",
            "subcategory":"Construction",
            "type":"Services"
        }
    ],
    "sg:phone":"+1 541 902 8788",
    "sg:postcode":"97439",
    "sg:province":"OR",
    "sg:tags":[
        "concrete",
        "contractor"
    ],
    "wof:name":"Monte Harris Construction",
    "wof:placetype":"venue"
},
  "geometry": {"coordinates":[-124.102847,44.00378],"type":"Point"}
}