{
  "type": "Feature",
  "properties": {
    "addr:full":"1386 SW Taylors Ferry Ct Portland OR 97219",
    "addr:housenumber":"1386",
    "addr:postcode":"97219",
    "addr:street":"Sw Taylors Ferry Ct",
    "iso:country":"US",
    "sg:address":"1386 SW Taylors Ferry Ct",
    "sg:city":"Portland",
    "sg:classifiers":[
        {
            "category":"Manufacturing",
            "subcategory":"Chemicals & Compounds",
            "type":"Manufacturing & Wholesale Goods"
        }
    ],
    "sg:phone":"+1 503 246 8700",
    "sg:postcode":"97219",
    "sg:province":"OR",
    "wof:name":"Remet Corp",
    "wof:placetype":"venue"
},
  "geometry": {"coordinates":[-122.691689,45.459309],"type":"Point"}
}