{
  "type": "Feature",
  "properties": {
    "iso:country":"US",
    "sg:address":"1200 Executive Pkwy # 360",
    "sg:city":"Eugene",
    "sg:classifiers":[
        {
            "category":"Health Services",
            "subcategory":"Clinic",
            "type":"Services"
        },
        {
            "category":"Community Center",
            "type":"Public Place"
        }
    ],
    "sg:phone":"+1 541 762 1155",
    "sg:postcode":"97401",
    "sg:province":"OR",
    "sg:tags":[
        "medical",
        "welfare"
    ],
    "wof:name":"Optimal Health",
    "wof:placetype":"venue"
},
  "geometry": {"coordinates":[-123.108131,44.070148],"type":"Point"}
}