{
  "type": "Feature",
  "properties": {
    "addr:full":"1551 Johnson St Medford OR 97504",
    "addr:housenumber":"1551",
    "addr:postcode":"97504",
    "addr:street":"Johnson St",
    "iso:country":"US",
    "sg:address":"1551 Johnson St",
    "sg:city":"Medford",
    "sg:classifiers":[
        {
            "category":"Building & Trades",
            "subcategory":"Construction",
            "type":"Services"
        }
    ],
    "sg:phone":"+1 541 770 5785",
    "sg:postcode":"97504",
    "sg:province":"OR",
    "sg:tags":[
        "downspouts",
        "gutter"
    ],
    "wof:name":"Southern Oregon Continous Gtrs",
    "wof:placetype":"venue"
},
  "geometry": {"coordinates":[-122.864341,42.345449],"type":"Point"}
}