{
  "type": "Feature",
  "properties": {
    "addr:full":"477 Sherwood Loop Florence OR 97439",
    "addr:housenumber":"477",
    "addr:postcode":"97439",
    "addr:street":"Sherwood Loop",
    "iso:country":"US",
    "sg:address":"477 Sherwood Loop",
    "sg:city":"Florence",
    "sg:classifiers":[
        {
            "category":"Farming",
            "subcategory":"Livestock Farm",
            "type":"Manufacturing & Wholesale Goods"
        }
    ],
    "sg:phone":"+1 541 997 6563",
    "sg:postcode":"97439",
    "sg:province":"OR",
    "sg:tags":[
        "animal",
        "general"
    ],
    "wof:name":"Roger Fegles",
    "wof:placetype":"venue"
},
  "geometry": {"coordinates":[-124.09792400000001,44.006676],"type":"Point"}
}