{
  "type": "Feature",
  "properties": {
    "iso:country":"US",
    "sg:address":"14301 SE Eola Village Rd",
    "sg:city":"Mcminnville",
    "sg:classifiers":[
        {
            "category":"Farming",
            "subcategory":"Dairy Farm",
            "type":"Manufacturing & Wholesale Goods"
        }
    ],
    "sg:phone":"+1 503 835 5555",
    "sg:postcode":"97128",
    "sg:province":"OR",
    "wof:name":"Joseph Rosenast",
    "wof:placetype":"venue"
},
  "geometry": {"coordinates":[-123.152045,45.15653],"type":"Point"}
}