{
  "type": "Feature",
  "properties": {
    "addr:full":"4800 SW Macadam Ave Portland OR 97239",
    "addr:housenumber":"4800",
    "addr:postcode":"97239",
    "addr:street":"Sw Macadam Ave",
    "iso:country":"US",
    "sg:address":"4800 SW Macadam Ave",
    "sg:city":"Portland",
    "sg:classifiers":[
        {
            "category":"Professional",
            "subcategory":"Business Services",
            "type":"Services"
        }
    ],
    "sg:phone":"+1 503 550 2459",
    "sg:postcode":"97239",
    "sg:province":"OR",
    "sg:tags":[
        "organizing",
        "services-household"
    ],
    "sg:website":"http://www.tpmoregon.com",
    "wof:name":"Turner Properties & Management",
    "wof:placetype":"venue"
},
  "geometry": {"coordinates":[-122.674683,45.48872],"type":"Point"}
}