{
  "type": "Feature",
  "properties": {
    "iso:country":"US",
    "sg:address":"2921 Micah Cir",
    "sg:city":"Medford",
    "sg:classifiers":[
        {
            "category":"Building & Trades",
            "subcategory":"Construction",
            "type":"Services"
        }
    ],
    "sg:phone":"+1 541 774 9650",
    "sg:postcode":"97504",
    "sg:province":"OR",
    "sg:tags":[
        "indoor",
        "paint",
        "outdoor",
        "home"
    ],
    "wof:name":"House Painter",
    "wof:placetype":"venue"
},
  "geometry": {"coordinates":[-122.838477,42.358898],"type":"Point"}
}