{
  "type": "Feature",
  "properties": {
    "addr:full":"12660 SW 121st Ave Portland OR 97223",
    "addr:housenumber":"12660",
    "addr:postcode":"97223",
    "addr:street":"Sw 121St Ave",
    "iso:country":"US",
    "sg:address":"12660 SW 121st Ave",
    "sg:city":"Portland",
    "sg:classifiers":[
        {
            "category":"Wholesale",
            "subcategory":"Metals & Minerals",
            "type":"Manufacturing & Wholesale Goods"
        }
    ],
    "sg:phone":"+1 503 590 3001",
    "sg:postcode":"97223",
    "sg:province":"OR",
    "sg:tags":[
        "center"
    ],
    "wof:name":"R K Bergquist",
    "wof:placetype":"venue"
},
  "geometry": {"coordinates":[-122.79982099999999,45.42791],"type":"Point"}
}