{
  "type": "Feature",
  "properties": {
    "addr:full":"3181 SW Sam Jackson Park Rd Portland OR 97239",
    "addr:housenumber":"3181",
    "addr:postcode":"97239",
    "addr:street":"Sw;Jackson Park Rd",
    "iso:country":"US",
    "sg:address":"3181 SW Sam Jackson Park Rd",
    "sg:city":"Portland",
    "sg:classifiers":[
        {
            "category":"Health Services",
            "subcategory":"Health Practitioner",
            "type":"Services"
        }
    ],
    "sg:phone":"+1 800 516 3535",
    "sg:postcode":"97239",
    "sg:province":"OR",
    "sg:tags":[
        "control",
        "weight"
    ],
    "sg:website":"http://www.weightwatchers.com/Index.aspx?cid=YP",
    "wof:name":"Weight Watchers - Portland",
    "wof:placetype":"venue"
},
  "geometry": {"coordinates":[-122.68517300000001,45.49965],"type":"Point"}
}