{
  "type": "Feature",
  "properties": {
    "iso:country":"US",
    "sg:address":"1145 Maple St SW",
    "sg:city":"Albany",
    "sg:classifiers":[
        {
            "category":"Real Estate",
            "subcategory":"Real Estate Operator",
            "type":"Services"
        }
    ],
    "sg:phone":"+1 541 926 2830",
    "sg:postcode":"97321",
    "sg:province":"OR",
    "sg:tags":[
        "building",
        "nonresidential"
    ],
    "wof:name":"Mbe Properties LLC",
    "wof:placetype":"venue"
},
  "geometry": {"coordinates":[-123.11167500000001,44.62831],"type":"Point"}
}