{
  "type": "Feature",
  "properties": {
    "iso:country":"US",
    "sg:address":"2828 Zee Ln NE",
    "sg:city":"Keizer",
    "sg:classifiers":[
        {
            "category":"Recreation",
            "type":"Entertainment"
        },
        {
            "category":"Retail",
            "subcategory":"Animal Services",
            "type":"Services"
        }
    ],
    "sg:phone":"+1 503 463 5197",
    "sg:postcode":"97303",
    "sg:province":"OR",
    "sg:tags":[
        "stable"
    ],
    "wof:name":"Keizer Equestrian Ctr",
    "wof:placetype":"venue"
},
  "geometry": {"coordinates":[-122.995523,45.020564],"type":"Point"}
}