{
  "type": "Feature",
  "properties": {
    "addr:full":"4377 SW Canal Dr Redmond OR 97756",
    "addr:housenumber":"4377",
    "addr:postcode":"97756",
    "addr:street":"Sw Canal Dr",
    "iso:country":"US",
    "sg:address":"4377 SW Canal Dr",
    "sg:city":"Redmond",
    "sg:classifiers":[
        {
            "category":"Real Estate",
            "subcategory":"Real Estate Operator",
            "type":"Services"
        }
    ],
    "sg:phone":"+1 541 548 3403",
    "sg:postcode":"97756",
    "sg:province":"OR",
    "sg:tags":[
        "mobile",
        "home",
        "community"
    ],
    "wof:name":"Diamond H Trailer Park",
    "wof:placetype":"venue"
},
  "geometry": {"coordinates":[-121.215215,44.235049],"type":"Point"}
}