{
  "type": "Feature",
  "properties": {
    "addr:full":"349 Chetco Ave Brookings OR 97415",
    "addr:housenumber":"349",
    "addr:postcode":"97415",
    "addr:street":"Chetco Ave",
    "iso:country":"US",
    "sg:address":"349 Chetco Ave",
    "sg:city":"Brookings",
    "sg:classifiers":[
        {
            "category":"Restaurant",
            "type":"Food & Drink"
        }
    ],
    "sg:phone":"+1 541 469 2535",
    "sg:postcode":"97415",
    "sg:province":"OR",
    "sg:website":"http://www.dairyqueen.com",
    "wof:name":"Dairy Queen",
    "wof:placetype":"venue"
},
  "geometry": {"coordinates":[-124.27549,42.054395],"type":"Point"}
}