{
  "type": "Feature",
  "properties": {
    "addr:full":"27240 SW 207th Ave Sherwood OR 97140",
    "addr:housenumber":"27240",
    "addr:postcode":"97140",
    "addr:street":"Sw 207Th Ave",
    "iso:country":"US",
    "sg:address":"27240 SW 207th Ave",
    "sg:city":"Sherwood",
    "sg:classifiers":[
        {
            "category":"Wholesale",
            "subcategory":"Machinery & Supplies",
            "type":"Manufacturing & Wholesale Goods"
        }
    ],
    "sg:phone":"+1 503 538 1762",
    "sg:postcode":"97140",
    "sg:province":"OR",
    "sg:tags":[
        "equipment",
        "industrial"
    ],
    "wof:name":"Oregon Industrial Resources",
    "wof:placetype":"venue"
},
  "geometry": {"coordinates":[-122.89084,45.323532],"type":"Point"}
}