{
  "type": "Feature",
  "properties": {
    "iso:country":"US",
    "sg:address":"455 Old Garden Valley Rd",
    "sg:city":"Roseburg",
    "sg:classifiers":[
        {
            "category":"Building & Trades",
            "subcategory":"Construction",
            "type":"Services"
        }
    ],
    "sg:phone":"+1 541 957 5090",
    "sg:postcode":"97470",
    "sg:province":"OR",
    "sg:tags":[
        "house"
    ],
    "wof:name":"Ark Construction",
    "wof:placetype":"venue"
},
  "geometry": {"coordinates":[-123.419444,43.2744],"type":"Point"}
}