{
  "type": "Feature",
  "properties": {
    "addr:full":"401 Aav Lake Oswego OR 97034",
    "addr:housenumber":"401",
    "addr:postcode":"97034",
    "addr:street":"Aav",
    "iso:country":"US",
    "sg:address":"401 Aav",
    "sg:city":"Lake Oswego",
    "sg:classifiers":[
        {
            "category":"Food & Beverages",
            "subcategory":"Groceries & Convenience Stores",
            "type":"Retail Goods"
        }
    ],
    "sg:phone":"+1 503 675 4480",
    "sg:postcode":"97034",
    "sg:province":"OR",
    "sg:website":"shop.safeway.com",
    "wof:name":"Safeway Food & Drug",
    "wof:placetype":"venue"
},
  "geometry": {"coordinates":[-122.668536,45.417197],"type":"Point"}
}