{
  "type": "Feature",
  "properties": {
    "iso:country":"US",
    "sg:address":"2608 Cherry Ave NE",
    "sg:city":"Salem",
    "sg:classifiers":[
        {
            "category":"Transit Center",
            "subcategory":"Freight",
            "type":"Transportation"
        },
        {
            "category":"Freight",
            "type":"Transportation"
        }
    ],
    "sg:phone":"+1 503 362 5779",
    "sg:postcode":"97301",
    "sg:province":"OR",
    "sg:tags":[
        "local",
        "trucking-motor",
        "trucking"
    ],
    "wof:name":"Farwest Auto And Truck Specialties",
    "wof:placetype":"venue"
},
  "geometry": {"coordinates":[-123.0194,44.963313],"type":"Point"}
}