{
  "type": "Feature",
  "properties": {
    "iso:country":"US",
    "sg:address":"3863 Iberis St NE",
    "sg:city":"Salem",
    "sg:classifiers":[
        {
            "category":"Real Estate",
            "subcategory":"Real Estate Operator",
            "type":"Services"
        }
    ],
    "sg:phone":"+1 503 390 4184",
    "sg:postcode":"97305",
    "sg:province":"OR",
    "sg:tags":[
        "apartment"
    ],
    "wof:name":"Whispering Pines",
    "wof:placetype":"venue"
},
  "geometry": {"coordinates":[-122.98375299999999,44.981843],"type":"Point"}
}