{
  "type": "Feature",
  "properties": {
    "addr:full":"1581 S Main St Lebanon OR 97355",
    "addr:housenumber":"1581",
    "addr:postcode":"97355",
    "addr:street":"S Main St",
    "iso:country":"US",
    "sg:address":"1581 S Main St",
    "sg:city":"Lebanon",
    "sg:classifiers":[
        {
            "category":"Restaurant",
            "type":"Food & Drink"
        }
    ],
    "sg:phone":"+1 541 259 2026",
    "sg:postcode":"97355",
    "sg:province":"OR",
    "wof:name":"Red Beards Steak & Seafood",
    "wof:placetype":"venue"
},
  "geometry": {"coordinates":[-122.906976,44.531125],"type":"Point"}
}