{
  "type": "Feature",
  "properties": {
    "iso:country":"US",
    "sg:address":"1001 Molalla Ave",
    "sg:city":"Oregon City",
    "sg:classifiers":[
        {
            "category":"Health Services",
            "subcategory":"Health Practitioner",
            "type":"Services"
        }
    ],
    "sg:phone":"+1 503 607 0047",
    "sg:postcode":"97045",
    "sg:province":"OR",
    "sg:tags":[
        "therapist",
        "physical"
    ],
    "wof:name":"Pro Active Ortho & Sports",
    "wof:placetype":"venue"
},
  "geometry": {"coordinates":[-122.593597,45.340467],"type":"Point"}
}