{
  "type": "Feature",
  "properties": {
    "iso:country":"US",
    "sg:address":"5968 SE Alexander St",
    "sg:city":"Hillsboro",
    "sg:classifiers":[
        {
            "category":"Organizations",
            "subcategory":"Religious Organization",
            "type":"Services"
        }
    ],
    "sg:phone":"+1 503 259 8889",
    "sg:postcode":"97123",
    "sg:province":"OR",
    "sg:tags":[
        "church"
    ],
    "wof:name":"Aloha Bible Church Inc",
    "wof:placetype":"venue"
},
  "geometry": {"coordinates":[-122.921588,45.497556],"type":"Point"}
}