{
  "type": "Feature",
  "properties": {
    "iso:country":"US",
    "sg:address":"1009 NE Failing St",
    "sg:city":"Portland",
    "sg:classifiers":[
        {
            "category":"Professional",
            "type":"Services"
        }
    ],
    "sg:phone":"+1 503 282 7482",
    "sg:postcode":"97212",
    "sg:province":"OR",
    "sg:tags":[
        "engineer"
    ],
    "wof:name":"Alder Geotechnical Services",
    "wof:placetype":"venue"
},
  "geometry": {"coordinates":[-122.655592,45.550799],"type":"Point"}
}