{
  "type": "Feature",
  "properties": {
    "addr:full":"1216 C St Hood River OR 97031",
    "addr:housenumber":"1216",
    "addr:postcode":"97031",
    "addr:street":"C St",
    "iso:country":"US",
    "sg:address":"1216 C St",
    "sg:city":"Hood River",
    "sg:classifiers":[
        {
            "category":"Food & Beverages",
            "subcategory":"Specialty",
            "type":"Retail Goods"
        }
    ],
    "sg:phone":"+1 541 386 3828",
    "sg:postcode":"97031",
    "sg:province":"OR",
    "wof:name":"Espresso Etc",
    "wof:placetype":"venue"
},
  "geometry": {"coordinates":[-121.52457699999999,45.701693],"type":"Point"}
}