{
  "type": "Feature",
  "properties": {
    "addr:full":"635 Capitol St NE Salem OR 97301",
    "addr:housenumber":"635",
    "addr:postcode":"97301",
    "addr:street":"Capitol St Ne",
    "iso:country":"US",
    "sg:address":"635 Capitol St NE",
    "sg:city":"Salem",
    "sg:classifiers":[
        {
            "category":"Government",
            "subcategory":"Office",
            "type":"Public Place"
        }
    ],
    "sg:phone":"+1 503 986 4551",
    "sg:postcode":"97301",
    "sg:province":"OR",
    "sg:tags":[
        "sector",
        "regulation",
        "commercial"
    ],
    "wof:name":"Western Weights & Measurers",
    "wof:placetype":"venue"
},
  "geometry": {"coordinates":[-123.02605699999999,44.943572],"type":"Point"}
}