{
  "type": "Feature",
  "properties": {
    "iso:country":"US",
    "sg:address":"27 W 5th Ave",
    "sg:city":"Eugene",
    "sg:classifiers":[
        {
            "category":"Food & Beverages",
            "subcategory":"Specialty",
            "type":"Retail Goods"
        }
    ],
    "sg:phone":"+1 541 686 6136",
    "sg:postcode":"97401",
    "sg:province":"OR",
    "wof:name":"Mrs Thmpsons Hrbs Gfts Flklore",
    "wof:placetype":"venue"
},
  "geometry": {"coordinates":[-123.093881,44.054409],"type":"Point"}
}