{
  "type": "Feature",
  "properties": {
    "iso:country":"US",
    "sg:address":"78120 Pitcher Ln",
    "sg:city":"Cottage Grove",
    "sg:classifiers":[
        {
            "category":"Education",
            "subcategory":"School",
            "type":"Public Place"
        }
    ],
    "sg:phone":"+1 541 767 0946",
    "sg:postcode":"97424",
    "sg:province":"OR",
    "wof:name":"Commandos",
    "wof:placetype":"venue"
},
  "geometry": {"coordinates":[-123.028268,43.781934],"type":"Point"}
}