{
  "type": "Feature",
  "properties": {
    "addr:full":"7170 E Burnside St Portland OR 97215",
    "addr:housenumber":"7170",
    "addr:postcode":"97215",
    "addr:street":"E Burnside St",
    "iso:country":"US",
    "sg:address":"7170 E Burnside St",
    "sg:city":"Portland",
    "sg:classifiers":[
        {
            "category":"Wholesale",
            "subcategory":"Hardware",
            "type":"Manufacturing & Wholesale Goods"
        }
    ],
    "sg:phone":"+1 503 703 7821",
    "sg:postcode":"97215",
    "sg:province":"OR",
    "sg:tags":[
        "prevention",
        "flow",
        "back",
        "devices"
    ],
    "wof:name":"Clearwater Backflow",
    "wof:placetype":"venue"
},
  "geometry": {"coordinates":[-122.589399,45.52303],"type":"Point"}
}