{
  "type": "Feature",
  "properties": {
    "addr:full":"5000 Cirrus Dr Medford OR 97504",
    "addr:housenumber":"5000",
    "addr:postcode":"97504",
    "addr:street":"Cirrus Dr",
    "iso:country":"US",
    "sg:address":"5000 Cirrus Dr",
    "sg:city":"Medford",
    "sg:classifiers":[
        {
            "category":"Airport",
            "type":"Transportation"
        }
    ],
    "sg:phone":"+1 541 779 5445",
    "sg:postcode":"97504",
    "sg:province":"OR",
    "sg:tags":[
        "aircraft",
        "maintenance"
    ],
    "sg:website":"www.jetcentermfr.com",
    "wof:name":"Jet Center",
    "wof:placetype":"venue"
},
  "geometry": {"coordinates":[-122.881523,42.376782],"type":"Point"}
}