{
  "type": "Feature",
  "properties": {
    "addr:full":"2841 Highland Ave Grants Pass OR 97526",
    "addr:housenumber":"2841",
    "addr:postcode":"97526",
    "addr:street":"Highland Ave",
    "iso:country":"US",
    "sg:address":"2841 Highland Ave",
    "sg:city":"Grants Pass",
    "sg:classifiers":[
        {
            "category":"Wholesale",
            "subcategory":"Auto Parts",
            "type":"Manufacturing & Wholesale Goods"
        }
    ],
    "sg:phone":"+1 541 956 9151",
    "sg:postcode":"97526",
    "sg:province":"OR",
    "sg:tags":[
        "automobile",
        "rebuilt"
    ],
    "wof:name":"Auto Recycling Co Inc",
    "wof:placetype":"venue"
},
  "geometry": {"coordinates":[-123.347538,42.475225],"type":"Point"}
}