{
  "type": "Feature",
  "properties": {
    "addr:full":"Sw 10th Ave And Alder Downtown Portland OR 97205",
    "addr:postcode":"97205",
    "addr:street":"Sw 10Th Ave And Alder",
    "iso:country":"US",
    "sg:address":"Sw 10th Ave And Alder Downtown",
    "sg:city":"Portland",
    "sg:classifiers":[
        {
            "category":"Food Court",
            "type":"Food & Drink"
        },
        {
            "category":"Restaurant",
            "type":"Food & Drink"
        }
    ],
    "sg:phone":"+1 971 344 3704",
    "sg:postcode":"97205",
    "sg:province":"OR",
    "sg:tags":[
        "polish",
        "stand"
    ],
    "wof:name":"Eurodish",
    "wof:placetype":"venue"
},
  "geometry": {"coordinates":[-122.681741,45.520681],"type":"Point"}
}