{
  "type": "Feature",
  "properties": {
    "addr:full":"325 NE 84th Ave Portland OR 97220",
    "addr:housenumber":"325",
    "addr:postcode":"97220",
    "addr:street":"Ne 84Th Ave",
    "iso:country":"US",
    "sg:address":"325 NE 84th Ave",
    "sg:city":"Portland",
    "sg:classifiers":[
        {
            "category":"Organizations",
            "subcategory":"Religious Organization",
            "type":"Services"
        }
    ],
    "sg:phone":"+1 503 253 2263",
    "sg:postcode":"97220",
    "sg:province":"OR",
    "wof:name":"Ancient Free & Accepted Masons",
    "wof:placetype":"venue"
},
  "geometry": {"coordinates":[-122.577072,45.525647],"type":"Point"}
}