{
  "type": "Feature",
  "properties": {
    "iso:country":"US",
    "sg:address":"875 Fairway View Dr",
    "sg:city":"Eugene",
    "sg:classifiers":[
        {
            "category":"Home & Garden",
            "subcategory":"Home Furnishings",
            "type":"Retail Goods"
        }
    ],
    "sg:phone":"+1 541 342 1400",
    "sg:postcode":"97401",
    "sg:province":"OR",
    "wof:name":"Curtains LLC",
    "wof:placetype":"venue"
},
  "geometry": {"coordinates":[-123.08480299999999,44.073],"type":"Point"}
}