{
  "type": "Feature",
  "properties": {
    "iso:country":"US",
    "sg:address":"8324 SW Nimbus Ave",
    "sg:city":"Beaverton",
    "sg:classifiers":[
        {
            "category":"Building & Trades",
            "subcategory":"Construction",
            "type":"Services"
        }
    ],
    "sg:phone":"+1 503 646 0521",
    "sg:postcode":"97008",
    "sg:province":"OR",
    "sg:tags":[
        "contractor"
    ],
    "wof:name":"Lmc Inc",
    "wof:placetype":"venue"
},
  "geometry": {"coordinates":[-122.789134,45.459646],"type":"Point"}
}