{
  "type": "Feature",
  "properties": {
    "iso:country":"US",
    "sg:address":"1933 NE 49th Ave",
    "sg:city":"Portland",
    "sg:classifiers":[
        {
            "category":"Professional",
            "subcategory":"Art Services",
            "type":"Services"
        }
    ],
    "sg:phone":"+1 503 284 0716",
    "sg:postcode":"97213",
    "sg:province":"OR",
    "sg:tags":[
        "commercial",
        "design"
    ],
    "wof:name":"Jigsaw Graphics",
    "wof:placetype":"venue"
},
  "geometry": {"coordinates":[-122.613022,45.537567],"type":"Point"}
}