{
  "type": "Feature",
  "properties": {
    "iso:country":"US",
    "sg:address":"1368 SW 11th Ave",
    "sg:city":"Ontario",
    "sg:classifiers":[
        {
            "category":"Retail",
            "subcategory":"Auto Repair",
            "type":"Services"
        }
    ],
    "sg:phone":"+1 208 230 3368",
    "sg:postcode":"97914",
    "sg:province":"OR",
    "sg:tags":[
        "body"
    ],
    "wof:name":"Dent-B-Gone",
    "wof:placetype":"venue"
},
  "geometry": {"coordinates":[-116.983598,44.019728],"type":"Point"}
}