{
  "type": "Feature",
  "properties": {
    "iso:country":"US",
    "sg:address":"11120 SW Capitol Hwy",
    "sg:city":"Portland",
    "sg:classifiers":[
        {
            "category":"Restaurant",
            "type":"Food & Drink"
        }
    ],
    "sg:phone":"+1 503 245 2143",
    "sg:postcode":"97219",
    "sg:province":"OR",
    "wof:name":"Subway Capitol 2542",
    "wof:placetype":"venue"
},
  "geometry": {"coordinates":[-122.72709399999999,45.444892],"type":"Point"}
}