{
  "type": "Feature",
  "properties": {
    "iso:country":"US",
    "sg:address":"2525 NW Saint Helens Rd",
    "sg:city":"Portland",
    "sg:classifiers":[
        {
            "category":"Retail",
            "subcategory":"Auto Repair",
            "type":"Services"
        }
    ],
    "sg:phone":"+1 503 228 5558",
    "sg:postcode":"97210",
    "sg:province":"OR",
    "sg:tags":[
        "truck"
    ],
    "wof:name":"Rowe Bros Rebuilders & Equip",
    "wof:placetype":"venue"
},
  "geometry": {"coordinates":[-122.71844,45.540005],"type":"Point"}
}