{
  "type": "Feature",
  "properties": {
    "iso:country":"US",
    "sg:address":"358 N Broadway St",
    "sg:city":"Estacada",
    "sg:classifiers":[
        {
            "category":"Personal",
            "subcategory":"Barber",
            "type":"Services"
        }
    ],
    "sg:phone":"+1 503 630 4161",
    "sg:postcode":"97023",
    "sg:province":"OR",
    "sg:tags":[
        "shop"
    ],
    "wof:name":"Duane's Barber Shop",
    "wof:placetype":"venue"
},
  "geometry": {"coordinates":[-122.33499,45.292245],"type":"Point"}
}