{
  "type": "Feature",
  "properties": {
    "iso:country":"US",
    "sg:address":"13330 SW Aquaduct Ct",
    "sg:city":"Beaverton",
    "sg:classifiers":[
        {
            "category":"Shopping",
            "subcategory":"Gifts & Souvenirs",
            "type":"Retail Goods"
        }
    ],
    "sg:phone":"+1 503 524 4876",
    "sg:postcode":"97008",
    "sg:province":"OR",
    "wof:name":"Broadway Gifts",
    "wof:placetype":"venue"
},
  "geometry": {"coordinates":[-122.814386,45.448703],"type":"Point"}
}