{
  "type": "Feature",
  "properties": {
    "addr:full":"1926 Pacific Ave Forest Grove OR 97116",
    "addr:housenumber":"1926",
    "addr:postcode":"97116",
    "addr:street":"Pacific Ave",
    "iso:country":"US",
    "sg:address":"1926 Pacific Ave",
    "sg:city":"Forest Grove",
    "sg:classifiers":[
        {
            "category":"Banks & Credit Unions",
            "subcategory":"Bank",
            "type":"Services"
        }
    ],
    "sg:phone":"+1 503 357 6165",
    "sg:postcode":"97116",
    "sg:province":"OR",
    "sg:website":"www.bankofthewest.com",
    "wof:name":"Bank Of The West",
    "wof:placetype":"venue"
},
  "geometry": {"coordinates":[-123.112511,45.519584],"type":"Point"}
}