{
  "type": "Feature",
  "properties": {
    "addr:full":"861 NE 122nd Ave Portland OR 97230",
    "addr:housenumber":"861",
    "addr:postcode":"97230",
    "addr:street":"Ne 122Nd Ave",
    "iso:country":"US",
    "sg:address":"861 NE 122nd Ave",
    "sg:city":"Portland",
    "sg:classifiers":[
        {
            "category":"Travel",
            "subcategory":"Hotels & Motels",
            "type":"Entertainment"
        }
    ],
    "sg:phone":"+1 503 236 4175",
    "sg:postcode":"97230",
    "sg:province":"OR",
    "wof:name":"Rose Manor Inn",
    "wof:placetype":"venue"
},
  "geometry": {"coordinates":[-122.53780500000001,45.527397],"type":"Point"}
}