{
  "type": "Feature",
  "properties": {
    "addr:full":"1300 NW Hwy 99W Mcminnville OR 97128",
    "addr:housenumber":"1300",
    "addr:postcode":"97128",
    "addr:street":"Nw Hwy 99W",
    "iso:country":"US",
    "sg:address":"1300 NW Hwy 99W",
    "sg:city":"Mcminnville",
    "sg:classifiers":[
        {
            "category":"Real Estate",
            "subcategory":"Real Estate Agent",
            "type":"Services"
        }
    ],
    "sg:phone":"+1 503 472 9521",
    "sg:postcode":"97128",
    "sg:province":"OR",
    "wof:name":"Century 21",
    "wof:placetype":"venue"
},
  "geometry": {"coordinates":[-123.198899,45.217698],"type":"Point"}
}