{
  "type": "Feature",
  "properties": {
    "iso:country":"US",
    "sg:address":"1301 S G St",
    "sg:city":"Lakeview",
    "sg:classifiers":[
        {
            "category":"Building & Trades",
            "subcategory":"Landscaping Services",
            "type":"Services"
        }
    ],
    "sg:phone":"+1 541 947 2151",
    "sg:postcode":"97630",
    "sg:province":"OR",
    "sg:tags":[
        "forester"
    ],
    "sg:website":"http://www.fs.fed.us/",
    "wof:name":"Fremont Winema National Forest",
    "wof:placetype":"venue"
},
  "geometry": {"coordinates":[-120.347443,42.172711],"type":"Point"}
}