{
  "type": "Feature",
  "properties": {
    "iso:country":"US",
    "sg:address":"110 NE 1st St",
    "sg:city":"Newport",
    "sg:classifiers":[
        {
            "category":"Professional",
            "subcategory":"Business Services",
            "type":"Services"
        }
    ],
    "sg:phone":"+1 541 265 2366",
    "sg:postcode":"97365",
    "sg:province":"OR",
    "sg:tags":[
        "bus"
    ],
    "wof:name":"Riddell Sheet Metal",
    "wof:placetype":"venue"
},
  "geometry": {"coordinates":[-124.050906,44.636919],"type":"Point"}
}