{
  "type": "Feature",
  "properties": {
    "iso:country":"US",
    "sg:address":"17570 Ocean Blvd",
    "sg:city":"Rockaway Beach",
    "sg:classifiers":[
        {
            "category":"Real Estate",
            "subcategory":"Real Estate Agent",
            "type":"Services"
        }
    ],
    "sg:phone":"+1 503 355 8080",
    "sg:postcode":"97136",
    "sg:province":"OR",
    "sg:tags":[
        "inspection"
    ],
    "wof:name":"Day Star Home Inspections",
    "wof:placetype":"venue"
},
  "geometry": {"coordinates":[-123.949818,45.584911],"type":"Point"}
}