{
  "type": "Feature",
  "properties": {
    "iso:country":"US",
    "sg:address":"627 SE Hillcrest Rd",
    "sg:city":"John Day",
    "sg:classifiers":[
        {
            "category":"Organizations",
            "subcategory":"Religious Organization",
            "type":"Services"
        }
    ],
    "sg:phone":"+1 541 575 2348",
    "sg:postcode":"97845",
    "sg:province":"OR",
    "wof:name":"Redeemer Lutheran Church",
    "wof:placetype":"venue"
},
  "geometry": {"coordinates":[-118.940184,44.415094],"type":"Point"}
}