{
  "type": "Feature",
  "properties": {
    "addr:full":"1930 Turner Rd SE Salem OR 97302",
    "addr:housenumber":"1930",
    "addr:postcode":"97302",
    "addr:street":"Turner Rd Se",
    "iso:country":"US",
    "sg:address":"1930 Turner Rd SE",
    "sg:city":"Salem",
    "sg:classifiers":[
        {
            "category":"Home & Garden",
            "subcategory":"Building Materials",
            "type":"Retail Goods"
        }
    ],
    "sg:phone":"+1 503 589 4333",
    "sg:postcode":"97302",
    "sg:province":"OR",
    "wof:name":"Lowes",
    "wof:placetype":"venue"
},
  "geometry": {"coordinates":[-123.00199499999999,44.917572],"type":"Point"}
}