{
  "type": "Feature",
  "properties": {
    "iso:country":"US",
    "sg:address":"1336 E Burnside Street",
    "sg:city":"Portland",
    "sg:classifiers":[
        {
            "category":"Professional",
            "subcategory":"Lawyer & Legal Services",
            "type":"Services"
        }
    ],
    "sg:phone":"+1 503 241 1320",
    "sg:postcode":"97214",
    "sg:province":"OR",
    "wof:name":"Bush L Leslie",
    "wof:placetype":"venue"
},
  "geometry": {"coordinates":[-122.65221699999999,45.522836],"type":"Point"}
}