{
  "type": "Feature",
  "properties": {
    "iso:country":"US",
    "sg:address":"21785 SW Tualatin Valley Hwy",
    "sg:city":"Beaverton",
    "sg:classifiers":[
        {
            "category":"Autos & Motor Vehicles",
            "subcategory":"Auto Supplies",
            "type":"Retail Goods"
        },
        {
            "category":"Retail",
            "subcategory":"Auto Repair",
            "type":"Services"
        }
    ],
    "sg:phone":"+1 503 649 4080",
    "sg:postcode":"97006",
    "sg:province":"OR",
    "sg:tags":[
        "automobile",
        "equipment",
        "car",
        "performance",
        "sport",
        "racing"
    ],
    "sg:website":"http://www.fordsandmore.com",
    "wof:name":"Fords And More",
    "wof:placetype":"venue"
},
  "geometry": {"coordinates":[-122.900993,45.497364],"type":"Point"}
}