{
  "type": "Feature",
  "properties": {
    "iso:country":"US",
    "sg:address":"300 Hillhouse Ave",
    "sg:city":"Medford",
    "sg:classifiers":[
        {
            "category":"Professional",
            "subcategory":"Detective & Security Services",
            "type":"Services"
        }
    ],
    "sg:phone":"+1 541 779 6596",
    "sg:postcode":"97504",
    "sg:province":"OR",
    "sg:tags":[
        "guard",
        "patrol"
    ],
    "wof:name":"Action Security Inc",
    "wof:placetype":"venue"
},
  "geometry": {"coordinates":[-122.851354,42.332716],"type":"Point"}
}