{
  "type": "Feature",
  "properties": {
    "iso:country":"US",
    "sg:address":"4742 Liberty Rd S",
    "sg:city":"Salem",
    "sg:classifiers":[
        {
            "category":"Home & Garden",
            "subcategory":"Garden Supply",
            "type":"Retail Goods"
        }
    ],
    "sg:phone":"+1 503 371 3615",
    "sg:postcode":"97302",
    "sg:province":"OR",
    "wof:name":"Garden Gate Interiors",
    "wof:placetype":"venue"
},
  "geometry": {"coordinates":[-123.06015,44.890446],"type":"Point"}
}