{
  "type": "Feature",
  "properties": {
    "iso:country":"US",
    "sg:address":"1604 Orchard St",
    "sg:city":"Cove",
    "sg:classifiers":[
        {
            "category":"Shopping",
            "type":"Retail Goods"
        }
    ],
    "sg:phone":"+1 541 963 2231",
    "sg:postcode":"97824",
    "sg:province":"OR",
    "sg:tags":[
        "monument"
    ],
    "wof:name":"Marowe Monument",
    "wof:placetype":"venue"
},
  "geometry": {"coordinates":[-117.81225,45.303383],"type":"Point"}
}