{
  "type": "Feature",
  "properties": {
    "iso:country":"US",
    "sg:address":"295 W B St",
    "sg:city":"Lebanon",
    "sg:classifiers":[
        {
            "category":"Professional",
            "type":"Services"
        }
    ],
    "sg:phone":"+1 541 258 2732",
    "sg:postcode":"97355",
    "sg:province":"OR",
    "wof:name":"Richard Shindler",
    "wof:placetype":"venue"
},
  "geometry": {"coordinates":[-122.910133,44.534745],"type":"Point"}
}