{
  "type": "Feature",
  "properties": {
    "addr:full":"1011 McKinley St Eugene OR 97402",
    "addr:housenumber":"1011",
    "addr:postcode":"97402",
    "addr:street":"Mckinley St",
    "iso:country":"US",
    "sg:address":"1011 McKinley St",
    "sg:city":"Eugene",
    "sg:classifiers":[
        {
            "category":"Manufacturing",
            "subcategory":"Chemicals & Compounds",
            "type":"Manufacturing & Wholesale Goods"
        }
    ],
    "sg:phone":"+1 541 342 1821",
    "sg:postcode":"97402",
    "sg:province":"OR",
    "sg:tags":[
        "paint"
    ],
    "sg:website":"www.forrestpaint.com",
    "wof:name":"Forrest Paint Co",
    "wof:placetype":"venue"
},
  "geometry": {"coordinates":[-123.129835,44.048268],"type":"Point"}
}