{
  "type": "Feature",
  "properties": {
    "iso:country":"US",
    "sg:address":"875 N Hwy 99W",
    "sg:city":"Dundee",
    "sg:classifiers":[
        {
            "category":"Insurance",
            "subcategory":"Insurance Agent",
            "type":"Services"
        }
    ],
    "sg:phone":"+1 503 538 4600",
    "sg:postcode":"97115",
    "sg:province":"OR",
    "wof:name":"Larissa De Hart Insurance",
    "wof:placetype":"venue"
},
  "geometry": {"coordinates":[-123.01208800000001,45.276369],"type":"Point"}
}