{
  "type": "Feature",
  "properties": {
    "iso:country":"US",
    "sg:address":"14913 SE 82nd Dr",
    "sg:city":"Clackamas",
    "sg:classifiers":[
        {
            "category":"Wholesale",
            "subcategory":"Fruits & Vegetables",
            "type":"Manufacturing & Wholesale Goods"
        }
    ],
    "sg:phone":"+1 503 655 3803",
    "sg:postcode":"97015",
    "sg:province":"OR",
    "sg:tags":[
        "citrus",
        "fresh"
    ],
    "wof:name":"Sunkist Growers Inc",
    "wof:placetype":"venue"
},
  "geometry": {"coordinates":[-122.569935,45.416418],"type":"Point"}
}