{
  "type": "Feature",
  "properties": {
    "addr:full":"1405 NE Killingsworth St Portland OR 97211",
    "addr:housenumber":"1405",
    "addr:postcode":"97211",
    "addr:street":"Ne Killingsworth St",
    "iso:country":"US",
    "sg:address":"1405 NE Killingsworth St",
    "sg:city":"Portland",
    "sg:classifiers":[
        {
            "category":"Retail",
            "subcategory":"Auto Repair",
            "type":"Services"
        }
    ],
    "sg:phone":"+1 503 288 3927",
    "sg:postcode":"97211",
    "sg:province":"OR",
    "wof:name":"Tuan Auto Service",
    "wof:placetype":"venue"
},
  "geometry": {"coordinates":[-122.650002,45.562801],"type":"Point"}
}