{
  "type": "Feature",
  "properties": {
    "addr:full":"617 SE 146th Ave Portland OR 97233",
    "addr:housenumber":"617",
    "addr:postcode":"97233",
    "addr:street":"Se 146Th Ave",
    "iso:country":"US",
    "sg:address":"617 SE 146th Ave",
    "sg:city":"Portland",
    "sg:classifiers":[
        {
            "category":"Building & Trades",
            "subcategory":"Cleaning & Sanitation",
            "type":"Services"
        }
    ],
    "sg:phone":"+1 503 577 7779",
    "sg:postcode":"97233",
    "sg:province":"OR",
    "sg:tags":[
        "maintenance"
    ],
    "wof:name":"Zacarias Cleaning & Maint",
    "wof:placetype":"venue"
},
  "geometry": {"coordinates":[-122.51334900000001,45.518897],"type":"Point"}
}