{
  "type": "Feature",
  "properties": {
    "iso:country":"US",
    "sg:address":"1526 NE Alberta St",
    "sg:city":"Portland",
    "sg:classifiers":[
        {
            "category":"Cinema",
            "subcategory":"Movie Rental",
            "type":"Entertainment"
        }
    ],
    "sg:phone":"+1 503 267 1126",
    "sg:postcode":"97211",
    "sg:province":"OR",
    "sg:tags":[
        "picture",
        "exchange",
        "motion",
        "distributor",
        "film"
    ],
    "wof:name":"Sour Apple Productions",
    "wof:placetype":"venue"
},
  "geometry": {"coordinates":[-122.649455,45.55909],"type":"Point"}
}