{
  "type": "Feature",
  "properties": {
    "addr:full":"28555 Brownsville Rd Brownsville OR 97327",
    "addr:housenumber":"28555",
    "addr:postcode":"97327",
    "addr:street":"Brownsville Rd",
    "iso:country":"US",
    "sg:address":"28555 Brownsville Rd",
    "sg:city":"Brownsville",
    "sg:classifiers":[
        {
            "category":"Farming",
            "subcategory":"Livestock Farm",
            "type":"Manufacturing & Wholesale Goods"
        }
    ],
    "sg:phone":"+1 541 466 3324",
    "sg:postcode":"97327",
    "sg:province":"OR",
    "sg:tags":[
        "feedlot",
        "field",
        "crop",
        "beef",
        "cattle"
    ],
    "wof:name":"Steve Cowdrey",
    "wof:placetype":"venue"
},
  "geometry": {"coordinates":[-122.98593700000001,44.418594],"type":"Point"}
}