{
  "type": "Feature",
  "properties": {
    "addr:full":"8515 SE 92nd Ave Portland OR 97266",
    "addr:housenumber":"8515",
    "addr:postcode":"97266",
    "addr:street":"Se 92Nd Ave",
    "iso:country":"US",
    "sg:address":"8515 SE 92nd Ave",
    "sg:city":"Portland",
    "sg:classifiers":[
        {
            "category":"Place Of Worship",
            "subcategory":"Church",
            "type":"Public Place"
        },
        {
            "category":"Place Of Worship",
            "type":"Public Place"
        }
    ],
    "sg:phone":"+1 503 771 4353",
    "sg:postcode":"97266",
    "sg:province":"OR",
    "sg:tags":[
        "christ",
        "churches-community"
    ],
    "wof:name":"Russellville Community Church",
    "wof:placetype":"venue"
},
  "geometry": {"coordinates":[-122.56863800000001,45.461695],"type":"Point"}
}