{
  "type": "Feature",
  "properties": {
    "iso:country":"US",
    "sg:address":"82438 Kingsley Rd",
    "sg:city":"Dufur",
    "sg:classifiers":[
        {
            "category":"Building & Trades",
            "subcategory":"Plumbing",
            "type":"Services"
        }
    ],
    "sg:phone":"+1 541 467 2200",
    "sg:postcode":"97021",
    "sg:province":"OR",
    "sg:tags":[
        "conditioning",
        "air",
        "system",
        "contractor"
    ],
    "wof:name":"Cascade Geothermal",
    "wof:placetype":"venue"
},
  "geometry": {"coordinates":[-121.199229,45.341532],"type":"Point"}
}