{
  "type": "Feature",
  "properties": {
    "iso:country":"US",
    "sg:address":"7736 SW Nimbus Ave",
    "sg:city":"Beaverton",
    "sg:classifiers":[
        {
            "category":"Building & Trades",
            "subcategory":"Plumbing",
            "type":"Services"
        }
    ],
    "sg:phone":"+1 503 644 8698",
    "sg:postcode":"97008",
    "sg:province":"OR",
    "sg:tags":[
        "contractor"
    ],
    "wof:name":"Craftwork Plumbing Inc",
    "wof:placetype":"venue"
},
  "geometry": {"coordinates":[-122.789001,45.4627],"type":"Point"}
}