{
  "type": "Feature",
  "properties": {
    "iso:country":"US",
    "sg:address":"4548 N Michigan Ave",
    "sg:city":"Portland",
    "sg:classifiers":[
        {
            "category":"Shopping",
            "subcategory":"Department Store",
            "type":"Retail Goods"
        }
    ],
    "sg:phone":"+1 503 705 5300",
    "sg:postcode":"97217",
    "sg:province":"OR",
    "sg:tags":[
        "variety"
    ],
    "wof:name":"Vip Industrial Supply",
    "wof:placetype":"venue"
},
  "geometry": {"coordinates":[-122.677014,45.555655],"type":"Point"}
}