{
  "type": "Feature",
  "properties": {
    "iso:country":"US",
    "sg:address":"34365 Hwy 101 S",
    "sg:city":"Cloverdale",
    "sg:classifiers":[
        {
            "category":"Food & Beverages",
            "subcategory":"Groceries & Convenience Stores",
            "type":"Retail Goods"
        }
    ],
    "sg:phone":"+1 503 392 3174",
    "sg:postcode":"97112",
    "sg:province":"OR",
    "sg:tags":[
        "grocer"
    ],
    "wof:name":"Liberty Market",
    "wof:placetype":"venue"
},
  "geometry": {"coordinates":[-123.889189,45.206667],"type":"Point"}
}