{
  "type": "Feature",
  "properties": {
    "iso:country":"US",
    "sg:address":"16285 SW 85th Ave",
    "sg:city":"Portland",
    "sg:classifiers":[
        {
            "category":"Wholesale",
            "subcategory":"Machinery & Supplies",
            "type":"Manufacturing & Wholesale Goods"
        }
    ],
    "sg:phone":"+1 503 620 0213",
    "sg:postcode":"97224",
    "sg:province":"OR",
    "sg:tags":[
        "janitorial"
    ],
    "wof:name":"Janitorial Supplies & Ppr Pdts",
    "wof:placetype":"venue"
},
  "geometry": {"coordinates":[-122.764577,45.401135],"type":"Point"}
}