{
  "type": "Feature",
  "properties": {
    "addr:full":"2791 19th St SE Salem OR 97302",
    "addr:housenumber":"2791",
    "addr:postcode":"97302",
    "addr:street":"19Th St Se",
    "iso:country":"US",
    "sg:address":"2791 19th St SE",
    "sg:city":"Salem",
    "sg:classifiers":[
        {
            "category":"Restaurant",
            "type":"Food & Drink"
        }
    ],
    "sg:phone":"+1 503 378 1072",
    "sg:postcode":"97302",
    "sg:province":"OR",
    "wof:name":"McDonalds",
    "wof:placetype":"venue"
},
  "geometry": {"coordinates":[-123.021152,44.913122],"type":"Point"}
}