{
  "type": "Feature",
  "properties": {
    "iso:country":"US",
    "sg:address":"38753 Proctor Blvd",
    "sg:city":"Sandy",
    "sg:classifiers":[
        {
            "category":"Restaurant",
            "type":"Food & Drink"
        }
    ],
    "sg:phone":"+1 503 668 5696",
    "sg:postcode":"97055",
    "sg:province":"OR",
    "sg:tags":[
        "eating"
    ],
    "wof:name":"My Deli & Catering",
    "wof:placetype":"venue"
},
  "geometry": {"coordinates":[-122.264947,45.397392],"type":"Point"}
}