{
  "type": "Feature",
  "properties": {
    "addr:full":"1001 SW Emkay Dr Bend OR 97702",
    "addr:housenumber":"1001",
    "addr:postcode":"97702",
    "addr:street":"Sw Emkay Dr",
    "iso:country":"US",
    "sg:address":"1001 SW Emkay Dr",
    "sg:city":"Bend",
    "sg:classifiers":[
        {
            "category":"Social Services",
            "subcategory":"Adult Care",
            "type":"Services"
        }
    ],
    "sg:phone":"+1 541 388 6161",
    "sg:postcode":"97702",
    "sg:province":"OR",
    "sg:tags":[
        "foster"
    ],
    "sg:website":"www.oregon.gov/dhs",
    "wof:name":"Foster Care Certification",
    "wof:placetype":"venue"
},
  "geometry": {"coordinates":[-121.325928,44.045082],"type":"Point"}
}