{
  "type": "Feature",
  "properties": {
    "addr:full":"945 12th St SE Salem OR 97302",
    "addr:housenumber":"945",
    "addr:postcode":"97302",
    "addr:street":"12Th St Se",
    "iso:country":"US",
    "sg:address":"945 12th St SE",
    "sg:city":"Salem",
    "sg:classifiers":[
        {
            "category":"Autos & Motor Vehicles",
            "subcategory":"Automobile Sales",
            "type":"Retail Goods"
        }
    ],
    "sg:phone":"+1 503 399 1664",
    "sg:postcode":"97302",
    "sg:province":"OR",
    "sg:tags":[
        "car",
        "dealer"
    ],
    "wof:name":"Lassen Auto & Truck Ctr",
    "wof:placetype":"venue"
},
  "geometry": {"coordinates":[-123.03071300000001,44.928708],"type":"Point"}
}