{
  "type": "Feature",
  "properties": {
    "iso:country":"US",
    "sg:address":"503 Aldin Cir",
    "sg:city":"Talent",
    "sg:classifiers":[
        {
            "category":"Building & Trades",
            "subcategory":"Plumbing",
            "type":"Services"
        }
    ],
    "sg:phone":"+1 541 858 4044",
    "sg:postcode":"97540",
    "sg:province":"OR",
    "sg:tags":[
        "heating",
        "contractor"
    ],
    "wof:name":"Nw Heating & Air Conditioning",
    "wof:placetype":"venue"
},
  "geometry": {"coordinates":[-122.79057,42.237965],"type":"Point"}
}