{
  "type": "Feature",
  "properties": {
    "addr:full":"399 E 10th Ave Eugene OR 97401",
    "addr:housenumber":"399",
    "addr:postcode":"97401",
    "addr:street":"E 10Th Ave",
    "iso:country":"US",
    "sg:address":"399 E 10th Ave",
    "sg:city":"Eugene",
    "sg:classifiers":[
        {
            "category":"Professional",
            "subcategory":"Lawyer & Legal Services",
            "type":"Services"
        }
    ],
    "sg:phone":"+1 541 484 1200",
    "sg:postcode":"97401",
    "sg:province":"OR",
    "sg:tags":[
        "attorney",
        "practice",
        "family",
        "law"
    ],
    "sg:website":"http://Mediationnorthwest.com",
    "wof:name":"Gentili Armbrust Julie",
    "wof:placetype":"venue"
},
  "geometry": {"coordinates":[-123.087186,44.048809],"type":"Point"}
}