{
  "type": "Feature",
  "properties": {
    "iso:country":"US",
    "sg:address":"3085 River Rd N",
    "sg:city":"Keizer",
    "sg:classifiers":[
        {
            "category":"Professional",
            "subcategory":"Accounting & Tax Preparation",
            "type":"Services"
        }
    ],
    "sg:phone":"+1 503 390 7880",
    "sg:postcode":"97303",
    "sg:province":"OR",
    "sg:tags":[
        "accountant"
    ],
    "sg:website":"www.johnsonglaze.com",
    "wof:name":"Johnson Glaze & Co",
    "wof:placetype":"venue"
},
  "geometry": {"coordinates":[-123.03135,44.969893],"type":"Point"}
}