{
  "type": "Feature",
  "properties": {
    "iso:country":"US",
    "sg:address":"4183 SW Greenleaf Dr",
    "sg:city":"Portland",
    "sg:classifiers":[
        {
            "category":"Building & Trades",
            "subcategory":"Landscaping Services",
            "type":"Services"
        }
    ],
    "sg:phone":"+1 503 227 7208",
    "sg:postcode":"97221",
    "sg:province":"OR",
    "sg:tags":[
        "landscape"
    ],
    "wof:name":"Clive Den Gardens",
    "wof:placetype":"venue"
},
  "geometry": {"coordinates":[-122.719354,45.501817],"type":"Point"}
}