{
  "type": "Feature",
  "properties": {
    "iso:country":"US",
    "sg:address":"325 US Hwy 30",
    "sg:city":"St Helens",
    "sg:classifiers":[
        {
            "category":"Professional",
            "subcategory":"Management & Consulting",
            "type":"Services"
        }
    ],
    "sg:phone":"+1 503 397 4989",
    "sg:postcode":"97051",
    "sg:province":"OR",
    "sg:tags":[
        "selling",
        "establishment",
        "direct"
    ],
    "wof:name":"Shaklee Distributor",
    "wof:placetype":"venue"
},
  "geometry": {"coordinates":[-122.819367,45.861428],"type":"Point"}
}