{
  "type": "Feature",
  "properties": {
    "iso:country":"US",
    "sg:address":"1520 NE Providence Dr",
    "sg:city":"Bend",
    "sg:classifiers":[
        {
            "category":"Retail",
            "subcategory":"Portrait Studio",
            "type":"Services"
        }
    ],
    "sg:phone":"+1 541 389 0403",
    "sg:postcode":"97701",
    "sg:province":"OR",
    "sg:tags":[
        "photo"
    ],
    "wof:name":"Central Oregon Images",
    "wof:placetype":"venue"
},
  "geometry": {"coordinates":[-121.256552,44.065416],"type":"Point"}
}