{
  "type": "Feature",
  "properties": {
    "iso:country":"US",
    "sg:address":"4745 Brooklake Rd NE",
    "sg:city":"Salem",
    "sg:classifiers":[
        {
            "category":"Freight",
            "type":"Transportation"
        }
    ],
    "sg:phone":"+1 503 390 2999",
    "sg:postcode":"97305",
    "sg:province":"OR",
    "sg:tags":[
        "warehouse",
        "storage"
    ],
    "wof:name":"Ameri Cold Logistics",
    "wof:placetype":"venue"
},
  "geometry": {"coordinates":[-122.960487,45.048916],"type":"Point"}
}