{
  "type": "Feature",
  "properties": {
    "iso:country":"US",
    "sg:address":"1060 S Pacific Hwy",
    "sg:city":"Woodburn",
    "sg:classifiers":[
        {
            "category":"Retail",
            "subcategory":"Animal Services",
            "type":"Services"
        }
    ],
    "sg:phone":"+1 503 981 9442",
    "sg:postcode":"97071",
    "sg:province":"OR",
    "sg:tags":[
        "pet",
        "grooming",
        "washing"
    ],
    "wof:name":"A Golden Touch Pet Grooming",
    "wof:placetype":"venue"
},
  "geometry": {"coordinates":[-122.852737,45.127055],"type":"Point"}
}