{
  "type": "Feature",
  "properties": {
    "iso:country":"US",
    "sg:address":"555 River Rd",
    "sg:city":"Eugene",
    "sg:classifiers":[
        {
            "category":"Autos & Motor Vehicles",
            "subcategory":"Motorcycle Sales",
            "type":"Retail Goods"
        }
    ],
    "sg:phone":"+1 541 607 9000",
    "sg:postcode":"97404",
    "sg:province":"OR",
    "sg:tags":[
        "scooter"
    ],
    "wof:name":"Cycle Sports Of Eugene",
    "wof:placetype":"venue"
},
  "geometry": {"coordinates":[-123.11821500000001,44.069787],"type":"Point"}
}