{
  "type": "Feature",
  "properties": {
    "iso:country":"US",
    "sg:address":"1178 SW 4th St",
    "sg:city":"Ontario",
    "sg:classifiers":[
        {
            "category":"Government",
            "subcategory":"Court House",
            "type":"Public Place"
        }
    ],
    "sg:phone":"+1 541 889 5712",
    "sg:postcode":"97914",
    "sg:province":"OR",
    "sg:tags":[
        "county"
    ],
    "wof:name":"Malheur County Municipal Court",
    "wof:placetype":"venue"
},
  "geometry": {"coordinates":[-116.970507,44.017136],"type":"Point"}
}