{
  "type": "Feature",
  "properties": {
    "iso:country":"US",
    "sg:address":"1600 SE 4th Ave Ste A",
    "sg:city":"Canby",
    "sg:classifiers":[
        {
            "category":"Utilities",
            "subcategory":"Refuse",
            "type":"Services"
        },
        {
            "category":"Utilities",
            "subcategory":"Recycling",
            "type":"Services"
        }
    ],
    "sg:phone":"+1 503 266 7903",
    "sg:postcode":"97013",
    "sg:province":"OR",
    "sg:tags":[
        "rubbish",
        "container",
        "collection",
        "garbage",
        "removal"
    ],
    "sg:website":"http://www.kbrecycling.com",
    "wof:name":"K B Recycling Inc",
    "wof:placetype":"venue"
},
  "geometry": {"coordinates":[-122.676117,45.261421],"type":"Point"}
}