{
  "type": "Feature",
  "properties": {
    "addr:full":"7206 NE Sandy Blvd Portland OR 97213",
    "addr:housenumber":"7206",
    "addr:postcode":"97213",
    "addr:street":"Ne Sandy Blvd",
    "iso:country":"US",
    "sg:address":"7206 NE Sandy Blvd",
    "sg:city":"Portland",
    "sg:classifiers":[
        {
            "category":"Shopping",
            "subcategory":"Pharmacy",
            "type":"Retail Goods"
        }
    ],
    "sg:phone":"+1 503 284 1159",
    "sg:postcode":"97213",
    "sg:province":"OR",
    "sg:tags":[
        "drugstore"
    ],
    "sg:website":"www.fairleyspharmacy.com",
    "wof:name":"Fairley's Pharmacy",
    "wof:placetype":"venue"
},
  "geometry": {"coordinates":[-122.588435,45.548351],"type":"Point"}
}