{
  "type": "Feature",
  "properties": {
    "iso:country":"US",
    "sg:address":"4169 NE Pin Oak St",
    "sg:city":"Corvallis",
    "sg:classifiers":[
        {
            "category":"Building & Trades",
            "subcategory":"Electrical",
            "type":"Services"
        },
        {
            "category":"Wholesale",
            "subcategory":"Electrical",
            "type":"Manufacturing & Wholesale Goods"
        }
    ],
    "sg:phone":"+1 541 758 5277",
    "sg:postcode":"97330",
    "sg:province":"OR",
    "sg:tags":[
        "control",
        "instrumentation",
        "electronic"
    ],
    "wof:name":"Central Point Control Systems",
    "wof:placetype":"venue"
},
  "geometry": {"coordinates":[-123.216523,44.599863],"type":"Point"}
}