{
  "type": "Feature",
  "properties": {
    "addr:full":"1018 Elm St Forest Grove OR 97116",
    "addr:housenumber":"1018",
    "addr:postcode":"97116",
    "addr:street":"Elm St",
    "iso:country":"US",
    "sg:address":"1018 Elm St",
    "sg:city":"Forest Grove",
    "sg:classifiers":[
        {
            "category":"Building & Trades",
            "subcategory":"Construction",
            "type":"Services"
        }
    ],
    "sg:phone":"+1 503 359 1303",
    "sg:postcode":"97116",
    "sg:province":"OR",
    "sg:tags":[
        "general",
        "contractor"
    ],
    "wof:name":"5 J's Construction Svc",
    "wof:placetype":"venue"
},
  "geometry": {"coordinates":[-123.103172,45.509146],"type":"Point"}
}