{
  "type": "Feature",
  "properties": {
    "iso:country":"US",
    "sg:address":"1563 Sleepy Hollow Loop",
    "sg:city":"Grants Pass",
    "sg:classifiers":[
        {
            "category":"Retail",
            "subcategory":"Portrait Studio",
            "type":"Services"
        }
    ],
    "sg:phone":"+1 541 479 0269",
    "sg:postcode":"97527",
    "sg:province":"OR",
    "sg:tags":[
        "photo"
    ],
    "wof:name":"Distinctive Moments Photograph",
    "wof:placetype":"venue"
},
  "geometry": {"coordinates":[-123.43526300000001,42.381549],"type":"Point"}
}