{
  "type": "Feature",
  "properties": {
    "addr:full":"2230 Pacific Ave Forest Grove OR 97116",
    "addr:housenumber":"2230",
    "addr:postcode":"97116",
    "addr:street":"Pacific Ave",
    "iso:country":"US",
    "sg:address":"2230 Pacific Ave",
    "sg:city":"Forest Grove",
    "sg:classifiers":[
        {
            "category":"Manufacturing",
            "subcategory":"Chemicals & Compounds",
            "type":"Manufacturing & Wholesale Goods"
        }
    ],
    "sg:phone":"+1 503 359 7993",
    "sg:postcode":"97116",
    "sg:province":"OR",
    "sg:tags":[
        "mfg",
        "biological",
        "product",
        "substance",
        "diagnostic"
    ],
    "wof:name":"Triple Point Biologics Inc",
    "wof:placetype":"venue"
},
  "geometry": {"coordinates":[-123.10708700000001,45.519561],"type":"Point"}
}