{
  "type": "Feature",
  "properties": {
    "addr:full":"505 NW 14th Ave Portland OR 97209",
    "addr:housenumber":"505",
    "addr:postcode":"97209",
    "addr:street":"Nw 14Th Ave",
    "iso:country":"US",
    "sg:address":"505 NW 14th Ave",
    "sg:city":"Portland",
    "sg:classifiers":[
        {
            "category":"Manufacturing",
            "subcategory":"Glass & Minerals",
            "type":"Manufacturing & Wholesale Goods"
        },
        {
            "category":"Retail",
            "subcategory":"Auto Repair",
            "type":"Services"
        },
        {
            "category":"Building & Trades",
            "subcategory":"Construction",
            "type":"Services"
        }
    ],
    "sg:phone":"+1 888 769 0384",
    "sg:postcode":"97209",
    "sg:province":"OR",
    "sg:tags":[
        "plate",
        "installation",
        "windows-repair",
        "glass-auto",
        "glass-wholesale",
        "window",
        "windshield",
        "manufacturer",
        "replacement"
    ],
    "sg:website":"http://www.msglassoutlet.com",
    "wof:name":"MS Glass Outlet",
    "wof:placetype":"venue"
},
  "geometry": {"coordinates":[-122.685348,45.526499],"type":"Point"}
}