{
  "type": "Feature",
  "properties": {
    "iso:country":"US",
    "sg:address":"225 NE Hillcrest Dr",
    "sg:city":"Grants Pass",
    "sg:classifiers":[
        {
            "category":"Communications",
            "subcategory":"Radio Station",
            "type":"Services"
        }
    ],
    "sg:phone":"+1 541 474 2324",
    "sg:postcode":"97526",
    "sg:province":"OR",
    "sg:tags":[
        "talk",
        "show"
    ],
    "sg:website":"www.talkradionetwork.com",
    "wof:name":"Talk Radio Network",
    "wof:placetype":"venue"
},
  "geometry": {"coordinates":[-123.319266,42.457947],"type":"Point"}
}