{
  "type": "Feature",
  "properties": {
    "iso:country":"US",
    "sg:address":"465 SW Rimrock Way",
    "sg:city":"Redmond",
    "sg:classifiers":[
        {
            "category":"Park",
            "type":"Public Place"
        }
    ],
    "sg:phone":"+1 541 548 7275",
    "sg:postcode":"97756",
    "sg:province":"OR",
    "wof:name":"Central Oregon Park & Rec",
    "wof:placetype":"venue"
},
  "geometry": {"coordinates":[-121.189262,44.273103],"type":"Point"}
}