{
  "type": "Feature",
  "properties": {
    "addr:full":"825 NE 20th Ave Portland OR 97232",
    "addr:housenumber":"825",
    "addr:postcode":"97232",
    "addr:street":"Ne 20Th Ave",
    "iso:country":"US",
    "sg:address":"825 NE 20th Ave",
    "sg:city":"Portland",
    "sg:classifiers":[
        {
            "category":"Health Services",
            "subcategory":"Doctor",
            "type":"Services"
        }
    ],
    "sg:phone":"+1 503 261 6759",
    "sg:postcode":"97232",
    "sg:province":"OR",
    "sg:tags":[
        "physician",
        "surgeon"
    ],
    "wof:name":"Adventist Health/Physical",
    "wof:placetype":"venue"
},
  "geometry": {"coordinates":[-122.64552500000001,45.529108],"type":"Point"}
}