{
  "type": "Feature",
  "properties": {
    "addr:full":"1825 N 4th St Lakeview OR 97630",
    "addr:housenumber":"1825",
    "addr:postcode":"97630",
    "addr:street":"N 4Th St",
    "iso:country":"US",
    "sg:address":"1825 N 4th St",
    "sg:city":"Lakeview",
    "sg:classifiers":[
        {
            "category":"Autos & Motor Vehicles",
            "subcategory":"Automobile Sales",
            "type":"Retail Goods"
        }
    ],
    "sg:phone":"+1 541 947 2113",
    "sg:postcode":"97630",
    "sg:province":"OR",
    "sg:tags":[
        "car",
        "dealer"
    ],
    "wof:name":"Auto Haven Used & Classic Cars",
    "wof:placetype":"venue"
},
  "geometry": {"coordinates":[-120.35896200000001,42.193361],"type":"Point"}
}