{
  "type": "Feature",
  "properties": {
    "iso:country":"US",
    "sg:address":"3824 River Rd N",
    "sg:city":"Keizer",
    "sg:classifiers":[
        {
            "category":"Professional",
            "subcategory":"Business Services",
            "type":"Services"
        }
    ],
    "sg:phone":"+1 503 304 3929",
    "sg:postcode":"97303",
    "sg:province":"OR",
    "sg:tags":[
        "box",
        "mail"
    ],
    "wof:name":"Mailbox Service Center",
    "wof:placetype":"venue"
},
  "geometry": {"coordinates":[-123.026515,44.981798],"type":"Point"}
}