{
  "type": "Feature",
  "properties": {
    "iso:country":"US",
    "sg:address":"17675 SE Pine St",
    "sg:city":"Portland",
    "sg:classifiers":[
        {
            "category":"Building & Trades",
            "subcategory":"Construction",
            "type":"Services"
        }
    ],
    "sg:phone":"+1 503 252 8303",
    "sg:postcode":"97233",
    "sg:province":"OR",
    "sg:tags":[
        "house"
    ],
    "wof:name":"C Clonts Construction",
    "wof:placetype":"venue"
},
  "geometry": {"coordinates":[-122.47964,45.520689],"type":"Point"}
}