{
  "type": "Feature",
  "properties": {
    "iso:country":"US",
    "sg:address":"900 State St",
    "sg:city":"Salem",
    "sg:classifiers":[
        {
            "category":"Education",
            "subcategory":"School",
            "type":"Public Place"
        }
    ],
    "sg:phone":"+1 503 373 3335",
    "sg:postcode":"97301",
    "sg:province":"OR",
    "wof:name":"Greater Oregon Acad For Ldrshp",
    "wof:placetype":"venue"
},
  "geometry": {"coordinates":[-123.032023,44.938198],"type":"Point"}
}