{
  "type": "Feature",
  "properties": {
    "iso:country":"US",
    "sg:address":"1732 Viewpoint Ter",
    "sg:city":"Cannon Beach",
    "sg:classifiers":[
        {
            "category":"Professional",
            "type":"Services"
        }
    ],
    "sg:phone":"+1 503 440 1854",
    "sg:postcode":"97110",
    "sg:province":"OR",
    "sg:tags":[
        "establishment"
    ],
    "wof:name":"Klopf & Klopf",
    "wof:placetype":"venue"
},
  "geometry": {"coordinates":[-123.963207,45.884611],"type":"Point"}
}