{
  "type": "Feature",
  "properties": {
    "addr:full":"611 Sitka Ave Newberg OR 97132",
    "addr:housenumber":"611",
    "addr:postcode":"97132",
    "addr:street":"Sitka Ave",
    "iso:country":"US",
    "sg:address":"611 Sitka Ave",
    "sg:city":"Newberg",
    "sg:classifiers":[
        {
            "category":"Real Estate",
            "subcategory":"Real Estate Agent",
            "type":"Services"
        }
    ],
    "sg:phone":"+1 503 246 2819",
    "sg:postcode":"97132",
    "sg:province":"OR",
    "wof:name":"Marcena Inc",
    "wof:placetype":"venue"
},
  "geometry": {"coordinates":[-122.959076,45.304103],"type":"Point"}
}