{
  "type": "Feature",
  "properties": {
    "addr:full":"2700 Gilham Rd Eugene OR 97408",
    "addr:postcode":"2700;97408",
    "addr:street":"Gilham Rd",
    "iso:country":"US",
    "sg:address":"2700 Gilham Rd",
    "sg:city":"Eugene",
    "sg:classifiers":[
        {
            "category":"Organizations",
            "subcategory":"Religious Organization",
            "type":"Services"
        }
    ],
    "sg:phone":"+1 541 343 1840",
    "sg:postcode":"97408",
    "sg:province":"OR",
    "sg:tags":[
        "church"
    ],
    "sg:website":"www.harvestcommchurch.org",
    "wof:name":"Harvest Community Church Inc",
    "wof:placetype":"venue"
},
  "geometry": {"coordinates":[-123.080957,44.092928],"type":"Point"}
}