{
  "type": "Feature",
  "properties": {
    "addr:full":"27725 Jahn Rd Grand Ronde OR 97347",
    "addr:postcode":"27725;97347",
    "addr:street":"Jahn Rd",
    "iso:country":"US",
    "sg:address":"27725 Jahn Rd",
    "sg:city":"Grand Ronde",
    "sg:classifiers":[
        {
            "category":"Freight",
            "type":"Transportation"
        }
    ],
    "sg:phone":"+1 503 879 5131",
    "sg:postcode":"97347",
    "sg:province":"OR",
    "wof:name":"Sidehill Trucking Inc",
    "wof:placetype":"venue"
},
  "geometry": {"coordinates":[-123.60117,45.058458],"type":"Point"}
}