{
  "type": "Feature",
  "properties": {
    "iso:country":"US",
    "sg:address":"2345 NW 31st Ave",
    "sg:city":"Portland",
    "sg:classifiers":[
        {
            "category":"Wholesale",
            "subcategory":"Electrical",
            "type":"Manufacturing & Wholesale Goods"
        }
    ],
    "sg:phone":"+1 503 221 4400",
    "sg:postcode":"97210",
    "sg:province":"OR",
    "sg:tags":[
        "equipment",
        "electric",
        "equipment-testing",
        "supply"
    ],
    "sg:website":"http://www.wescodist.com",
    "wof:name":"Wesco Distribution, Inc.",
    "wof:placetype":"venue"
},
  "geometry": {"coordinates":[-122.713847,45.539154],"type":"Point"}
}