{
  "type": "Feature",
  "properties": {
    "iso:country":"US",
    "sg:address":"10777 SW Cascade Ave",
    "sg:city":"Tigard",
    "sg:classifiers":[
        {
            "category":"Real Estate",
            "subcategory":"Real Estate Agent",
            "type":"Services"
        }
    ],
    "sg:phone":"+1 503 670 9442",
    "sg:postcode":"97223",
    "sg:province":"OR",
    "sg:tags":[
        "support"
    ],
    "wof:name":"Trammell Crow Co",
    "wof:placetype":"venue"
},
  "geometry": {"coordinates":[-122.782049,45.444353],"type":"Point"}
}