{
  "type": "Feature",
  "properties": {
    "iso:country":"US",
    "sg:address":"1570 Woodland Dr",
    "sg:city":"Coos Bay",
    "sg:classifiers":[
        {
            "category":"Recreation",
            "type":"Entertainment"
        }
    ],
    "sg:phone":"+1 541 267 3796",
    "sg:postcode":"97420",
    "sg:province":"OR",
    "wof:name":"Fishing Vessel Apache",
    "wof:placetype":"venue"
},
  "geometry": {"coordinates":[-124.2379,43.379202],"type":"Point"}
}