{
  "type": "Feature",
  "properties": {
    "addr:full":"1429 SE 37th Ave Portland OR 97214",
    "addr:housenumber":"1429",
    "addr:postcode":"97214",
    "addr:street":"Se 37Th Ave",
    "iso:country":"US",
    "sg:address":"1429 SE 37th Ave",
    "sg:city":"Portland",
    "sg:classifiers":[
        {
            "category":"Restaurant",
            "type":"Food & Drink"
        }
    ],
    "sg:phone":"+1 503 236 6886",
    "sg:postcode":"97214",
    "sg:province":"OR",
    "sg:tags":[
        "italian"
    ],
    "sg:website":"www.3doorsdowncafe.com",
    "wof:name":"3 Doors Down Cafe",
    "wof:placetype":"venue"
},
  "geometry": {"coordinates":[-122.62587000000001,45.512608],"type":"Point"}
}