{
  "type": "Feature",
  "properties": {
    "iso:country":"US",
    "sg:address":"1150 NW 36th St",
    "sg:city":"Ontario",
    "sg:classifiers":[
        {
            "category":"Organizations",
            "subcategory":"Religious Organization",
            "type":"Services"
        }
    ],
    "sg:phone":"+1 541 889 5826",
    "sg:postcode":"97914",
    "sg:province":"OR",
    "wof:name":"Jesus Arija",
    "wof:placetype":"venue"
},
  "geometry": {"coordinates":[-117.02034500000001,44.038545],"type":"Point"}
}