{
  "type": "Feature",
  "properties": {
    "iso:country":"US",
    "sg:address":"509 SW 3rd Ave",
    "sg:city":"Portland",
    "sg:classifiers":[
        {
            "category":"Wholesale",
            "subcategory":"Jewelry",
            "type":"Manufacturing & Wholesale Goods"
        },
        {
            "category":"Shopping",
            "subcategory":"Jewelry",
            "type":"Retail Goods"
        },
        {
            "category":"Manufacturing",
            "subcategory":"Jewelry",
            "type":"Manufacturing & Wholesale Goods"
        }
    ],
    "sg:phone":"+1 503 224 6640",
    "sg:postcode":"97204",
    "sg:province":"OR",
    "sg:tags":[
        "designer",
        "jewelers-wholesale",
        "supply",
        "jeweler",
        "finding",
        "manufacturer"
    ],
    "wof:name":"Rose Jewelry",
    "wof:placetype":"venue"
},
  "geometry": {"coordinates":[-122.674842,45.519527],"type":"Point"}
}