{
  "type": "Feature",
  "properties": {
    "addr:full":"630 Center St NE Salem OR 97301",
    "addr:housenumber":"630",
    "addr:postcode":"97301",
    "addr:street":"Center St Ne",
    "iso:country":"US",
    "sg:address":"630 Center St NE",
    "sg:city":"Salem",
    "sg:classifiers":[
        {
            "category":"Banks & Credit Unions",
            "subcategory":"Bank",
            "type":"Services"
        },
        {
            "category":"Banks & Credit Unions",
            "subcategory":"Financial Services",
            "type":"Services"
        }
    ],
    "sg:phone":"+1 503 588 6700",
    "sg:postcode":"97301",
    "sg:province":"OR",
    "sg:tags":[
        "saving",
        "loan",
        "commercial"
    ],
    "sg:website":"https://www.chase.com/",
    "wof:name":"CHASE Bank",
    "wof:placetype":"venue"
},
  "geometry": {"coordinates":[-123.033405,44.942348],"type":"Point"}
}