{
  "type": "Feature",
  "properties": {
    "iso:country":"US",
    "sg:address":"125 E 8th Ave",
    "sg:city":"Eugene",
    "sg:classifiers":[
        {
            "category":"Government",
            "subcategory":"Office",
            "type":"Public Place"
        }
    ],
    "sg:phone":"+1 541 682 3665",
    "sg:postcode":"97401",
    "sg:province":"OR",
    "wof:name":"Lane County Human Resources",
    "wof:placetype":"venue"
},
  "geometry": {"coordinates":[-123.09072,44.051091],"type":"Point"}
}