{
  "type": "Feature",
  "properties": {
    "addr:full":"1469 Siskiyou Blvd Ashland OR 97520",
    "addr:housenumber":"1469",
    "addr:postcode":"97520",
    "addr:street":"Siskiyou Blvd",
    "iso:country":"US",
    "sg:address":"1469 Siskiyou Blvd",
    "sg:city":"Ashland",
    "sg:classifiers":[
        {
            "category":"Restaurant",
            "type":"Food & Drink"
        }
    ],
    "sg:phone":"+1 541 482 5559",
    "sg:postcode":"97520",
    "sg:province":"OR",
    "sg:tags":[
        "eating",
        "pizza"
    ],
    "wof:name":"Giseppis Pizzeria & Sports Den",
    "wof:placetype":"venue"
},
  "geometry": {"coordinates":[-122.690344,42.184539],"type":"Point"}
}