{
  "type": "Feature",
  "properties": {
    "iso:country":"US",
    "sg:address":"1510 Adams Ave",
    "sg:city":"La Grande",
    "sg:classifiers":[
        {
            "category":"Travel",
            "subcategory":"Hotels & Motels",
            "type":"Entertainment"
        }
    ],
    "sg:phone":"+1 541 963 4154",
    "sg:postcode":"97850",
    "sg:province":"OR",
    "wof:name":"Royal Motor Inn",
    "wof:placetype":"venue"
},
  "geometry": {"coordinates":[-118.090588,45.326086],"type":"Point"}
}