{
  "type": "Feature",
  "properties": {
    "iso:country":"US",
    "sg:address":"3540 SE Division St",
    "sg:city":"Portland",
    "sg:classifiers":[
        {
            "category":"Shopping",
            "subcategory":"Used Merchandise",
            "type":"Retail Goods"
        }
    ],
    "sg:phone":"+1 503 922 9745",
    "sg:postcode":"97202",
    "sg:province":"OR",
    "sg:tags":[
        "vintage",
        "consignment"
    ],
    "sg:website":"www.myspace.com/westcoastvintage...",
    "wof:name":"Time Bomb Vintage",
    "wof:placetype":"venue"
},
  "geometry": {"coordinates":[-122.627583,45.504762],"type":"Point"}
}