{
  "type": "Feature",
  "properties": {
    "iso:country":"US",
    "sg:address":"1260 Lancaster Dr NE",
    "sg:city":"Salem",
    "sg:classifiers":[
        {
            "category":"Shopping",
            "subcategory":"Clothing, Apparel, & Fashions",
            "type":"Retail Goods"
        }
    ],
    "sg:phone":"+1 503 589 0800",
    "sg:postcode":"97301",
    "sg:province":"OR",
    "sg:tags":[
        "sport",
        "sp"
    ],
    "wof:name":"Portsman Warehouse",
    "wof:placetype":"venue"
},
  "geometry": {"coordinates":[-122.98353899999999,44.945746],"type":"Point"}
}