{
  "type": "Feature",
  "properties": {
    "addr:full":"304 NE San Bayo Cir Newport OR 97365",
    "addr:housenumber":"304",
    "addr:postcode":"97365",
    "addr:street":"Ne San Bayo Cir",
    "iso:country":"US",
    "sg:address":"304 NE San Bayo Cir",
    "sg:city":"Newport",
    "sg:classifiers":[
        {
            "category":"Professional",
            "subcategory":"Lawyer & Legal Services",
            "type":"Services"
        }
    ],
    "sg:phone":"+1 541 574 9539",
    "sg:postcode":"97365",
    "sg:province":"OR",
    "sg:tags":[
        "attorney"
    ],
    "wof:name":"Nyla Jebousek",
    "wof:placetype":"venue"
},
  "geometry": {"coordinates":[-124.049992,44.649519],"type":"Point"}
}