{
  "type": "Feature",
  "properties": {
    "addr:full":"225 SW Columbia Street Portland OR 97201",
    "addr:housenumber":"225",
    "addr:postcode":"97201",
    "addr:street":"Sw Columbia Street",
    "iso:country":"US",
    "sg:address":"225 SW Columbia Street",
    "sg:city":"Portland",
    "sg:classifiers":[
        {
            "category":"Retail",
            "subcategory":"Laundry & Dry Cleaning",
            "type":"Services"
        }
    ],
    "sg:phone":"+1 503 227 4444",
    "sg:postcode":"97201",
    "sg:province":"OR",
    "wof:name":"Levine's Drycleaning",
    "wof:placetype":"venue"
},
  "geometry": {"coordinates":[-122.677792,45.513403],"type":"Point"}
}