{
  "type": "Feature",
  "properties": {
    "iso:country":"US",
    "sg:address":"5729 Main St",
    "sg:city":"Springfield",
    "sg:classifiers":[
        {
            "category":"Real Estate",
            "subcategory":"Real Estate Agent",
            "type":"Services"
        }
    ],
    "sg:phone":"+1 541 747 0224",
    "sg:postcode":"97478",
    "sg:province":"OR",
    "sg:tags":[
        "management"
    ],
    "wof:name":"APS Property Management",
    "wof:placetype":"venue"
},
  "geometry": {"coordinates":[-122.926984,44.045612],"type":"Point"}
}