{
  "type": "Feature",
  "properties": {
    "addr:full":"3835 NE Hancock St Portland OR 97212",
    "addr:housenumber":"3835",
    "addr:postcode":"97212",
    "addr:street":"Ne Hancock St",
    "iso:country":"US",
    "sg:address":"3835 NE Hancock St",
    "sg:city":"Portland",
    "sg:classifiers":[
        {
            "category":"Freight",
            "type":"Transportation"
        }
    ],
    "sg:phone":"+1 503 281 4645",
    "sg:postcode":"97212",
    "sg:province":"OR",
    "sg:tags":[
        "arrangement"
    ],
    "wof:name":"Beaver Freight Services LLC",
    "wof:placetype":"venue"
},
  "geometry": {"coordinates":[-122.623216,45.53659],"type":"Point"}
}