{
  "type": "Feature",
  "properties": {
    "iso:country":"US",
    "sg:address":"2261 Demaray Dr",
    "sg:city":"Grants Pass",
    "sg:classifiers":[
        {
            "category":"Professional",
            "type":"Services"
        }
    ],
    "sg:phone":"+1 541 956 8760",
    "sg:postcode":"97527",
    "sg:province":"OR",
    "sg:tags":[
        "establishment"
    ],
    "wof:name":"Ohana LLC",
    "wof:placetype":"venue"
},
  "geometry": {"coordinates":[-123.381981,42.413049],"type":"Point"}
}