{
  "type": "Feature",
  "properties": {
    "iso:country":"US",
    "sg:address":"1701 NE 152nd Pl",
    "sg:city":"Portland",
    "sg:classifiers":[
        {
            "category":"Manufacturing",
            "subcategory":"Tools & Machinery",
            "type":"Manufacturing & Wholesale Goods"
        }
    ],
    "sg:phone":"+1 503 254 7741",
    "sg:postcode":"97230",
    "sg:province":"OR",
    "sg:tags":[
        "food",
        "product",
        "mfg"
    ],
    "wof:name":"Melvin Leroy Bruhn",
    "wof:placetype":"venue"
},
  "geometry": {"coordinates":[-122.50606399999999,45.534305],"type":"Point"}
}