{
  "type": "Feature",
  "properties": {
    "iso:country":"US",
    "sg:address":"9800 SE Sunnyside Rd",
    "sg:city":"Clackamas",
    "sg:classifiers":[
        {
            "category":"Coffee & Tea",
            "type":"Food & Drink"
        },
        {
            "category":"Restaurant",
            "type":"Food & Drink"
        }
    ],
    "sg:phone":"+1 503 571 6322",
    "sg:postcode":"97015",
    "sg:province":"OR",
    "sg:tags":[
        "shop",
        "espresso"
    ],
    "wof:name":"Espresso International",
    "wof:placetype":"venue"
},
  "geometry": {"coordinates":[-122.563312,45.433308],"type":"Point"}
}