{
  "type": "Feature",
  "properties": {
    "addr:full":"225 NE Middlefield Rd Portland OR 97211",
    "addr:housenumber":"225",
    "addr:postcode":"97211",
    "addr:street":"Ne Middlefield Rd",
    "iso:country":"US",
    "sg:address":"225 NE Middlefield Rd",
    "sg:city":"Portland",
    "sg:classifiers":[
        {
            "category":"Manufacturing",
            "subcategory":"Building Materials",
            "type":"Manufacturing & Wholesale Goods"
        }
    ],
    "sg:phone":"+1 503 283 1326",
    "sg:postcode":"97211",
    "sg:province":"OR",
    "wof:name":"C E Snodgrass Inc",
    "wof:placetype":"venue"
},
  "geometry": {"coordinates":[-122.666905,45.596353],"type":"Point"}
}