{
  "type": "Feature",
  "properties": {
    "addr:full":"2075 Broadview St Eugene OR 97405",
    "addr:housenumber":"2075",
    "addr:postcode":"97405",
    "addr:street":"Broadview St",
    "iso:country":"US",
    "sg:address":"2075 Broadview St",
    "sg:city":"Eugene",
    "sg:classifiers":[
        {
            "category":"Personal",
            "subcategory":"Barber",
            "type":"Services"
        }
    ],
    "sg:phone":"+1 541 338 4995",
    "sg:postcode":"97405",
    "sg:province":"OR",
    "sg:tags":[
        "shop"
    ],
    "wof:name":"South Eugene Barbers",
    "wof:placetype":"venue"
},
  "geometry": {"coordinates":[-123.136628,44.037773],"type":"Point"}
}