{
  "type": "Feature",
  "properties": {
    "iso:country":"US",
    "sg:address":"1017 E Pine St",
    "sg:city":"Central Point",
    "sg:classifiers":[
        {
            "category":"Banks & Credit Unions",
            "subcategory":"Bank",
            "type":"Services"
        }
    ],
    "sg:phone":"+1 541 665 5262",
    "sg:postcode":"97502",
    "sg:province":"OR",
    "sg:website":"www.peoplesbankofcommerce.com",
    "wof:name":"People's Bank of Commerce",
    "wof:placetype":"venue"
},
  "geometry": {"coordinates":[-122.909299,42.378367],"type":"Point"}
}