{
  "type": "Feature",
  "properties": {
    "addr:full":"10812 SE Oak St Milwaukie OR 97222",
    "addr:housenumber":"10812",
    "addr:postcode":"97222",
    "addr:street":"Se Oak St",
    "iso:country":"US",
    "sg:address":"10812 SE Oak St",
    "sg:city":"Milwaukie",
    "sg:classifiers":[
        {
            "category":"Shopping",
            "subcategory":"Mobile Phones",
            "type":"Retail Goods"
        }
    ],
    "sg:phone":"+1 503 513 4848",
    "sg:postcode":"97222",
    "sg:province":"OR",
    "wof:name":"Cellular Plus",
    "wof:placetype":"venue"
},
  "geometry": {"coordinates":[-122.628257,45.444664],"type":"Point"}
}