{
  "type": "Feature",
  "properties": {
    "iso:country":"US",
    "sg:address":"157 Main St W",
    "sg:city":"Monmouth",
    "sg:classifiers":[
        {
            "category":"Personal",
            "subcategory":"Barber",
            "type":"Services"
        }
    ],
    "sg:phone":"+1 503 606 3024",
    "sg:postcode":"97361",
    "sg:province":"OR",
    "wof:name":"Barbers On Main",
    "wof:placetype":"venue"
},
  "geometry": {"coordinates":[-123.23732800000001,44.848486],"type":"Point"}
}