{
  "type": "Feature",
  "properties": {
    "iso:country":"US",
    "sg:address":"5095 SW Fern Hill Rd",
    "sg:city":"Forest Grove",
    "sg:classifiers":[
        {
            "category":"Farming",
            "subcategory":"Livestock Farm",
            "type":"Manufacturing & Wholesale Goods"
        }
    ],
    "sg:phone":"+1 503 357 6526",
    "sg:postcode":"97116",
    "sg:province":"OR",
    "sg:tags":[
        "wheat",
        "beef",
        "cash",
        "grain",
        "cattle",
        "feedlot"
    ],
    "wof:name":"Knox John H",
    "wof:placetype":"venue"
},
  "geometry": {"coordinates":[-123.099692,45.483227],"type":"Point"}
}