{
  "type": "Feature",
  "properties": {
    "addr:full":"8205 SW 24th Ave Portland OR 97219",
    "addr:housenumber":"8205",
    "addr:postcode":"97219",
    "addr:street":"Sw 24Th Ave",
    "iso:country":"US",
    "sg:address":"8205 SW 24th Ave",
    "sg:city":"Portland",
    "sg:classifiers":[
        {
            "category":"Professional",
            "subcategory":"Business Services",
            "type":"Services"
        }
    ],
    "sg:phone":"+1 503 245 3111",
    "sg:postcode":"97219",
    "sg:province":"OR",
    "sg:tags":[
        "information",
        "referral"
    ],
    "wof:name":"Found Object",
    "wof:placetype":"venue"
},
  "geometry": {"coordinates":[-122.702214,45.465054],"type":"Point"}
}