{
  "type": "Feature",
  "properties": {
    "iso:country":"US",
    "sg:address":"391 Saint Helens St",
    "sg:city":"St Helens",
    "sg:classifiers":[
        {
            "category":"Building & Trades",
            "subcategory":"Electrical",
            "type":"Services"
        }
    ],
    "sg:phone":"+1 503 397 1022",
    "sg:postcode":"97051",
    "sg:province":"OR",
    "sg:tags":[
        "electrical",
        "electric",
        "contractor"
    ],
    "wof:name":"St Helen's Electric",
    "wof:placetype":"venue"
},
  "geometry": {"coordinates":[-122.801457,45.863196],"type":"Point"}
}