{
  "type": "Feature",
  "properties": {
    "iso:country":"US",
    "sg:address":"405 NE 3rd St",
    "sg:city":"Prineville",
    "sg:classifiers":[
        {
            "category":"Food & Beverages",
            "subcategory":"Groceries & Convenience Stores",
            "type":"Retail Goods"
        }
    ],
    "sg:phone":"+1 541 447 7287",
    "sg:postcode":"97754",
    "sg:province":"OR",
    "wof:name":"7-Eleven",
    "wof:placetype":"venue"
},
  "geometry": {"coordinates":[-120.843422,44.303022],"type":"Point"}
}