{
  "type": "Feature",
  "properties": {
    "iso:country":"US",
    "sg:address":"61106 Finchwood Dr",
    "sg:city":"Bend",
    "sg:classifiers":[
        {
            "category":"Health Services",
            "subcategory":"Health Practitioner",
            "type":"Services"
        }
    ],
    "sg:phone":"+1 541 385 8958",
    "sg:postcode":"97702",
    "sg:province":"OR",
    "sg:tags":[
        "nutritionist"
    ],
    "wof:name":"Transformation Enzymes NW",
    "wof:placetype":"venue"
},
  "geometry": {"coordinates":[-121.33000800000001,44.020141],"type":"Point"}
}