{
  "type": "Feature",
  "properties": {
    "iso:country":"US",
    "sg:address":"13486 NW Cornell Rd",
    "sg:city":"Portland",
    "sg:classifiers":[
        {
            "category":"Education",
            "subcategory":"Music School",
            "type":"Public Place"
        }
    ],
    "sg:phone":"+1 503 626 7181",
    "sg:postcode":"97229",
    "sg:province":"OR",
    "sg:tags":[
        "instruction-instrumental"
    ],
    "wof:name":"Westside Music School",
    "wof:placetype":"venue"
},
  "geometry": {"coordinates":[-122.81509200000001,45.526993],"type":"Point"}
}