{
  "type": "Feature",
  "properties": {
    "iso:country":"US",
    "sg:address":"717 N Killingsworth Ct",
    "sg:city":"Portland",
    "sg:classifiers":[
        {
            "category":"Education",
            "subcategory":"School",
            "type":"Public Place"
        }
    ],
    "sg:phone":"+1 503 735 1825",
    "sg:postcode":"97217",
    "sg:province":"OR",
    "sg:tags":[
        "high",
        "middle",
        "elementary"
    ],
    "wof:name":"Opportunities Industrialization Center",
    "wof:placetype":"venue"
},
  "geometry": {"coordinates":[-122.674004,45.561798],"type":"Point"}
}