{
  "type": "Feature",
  "properties": {
    "iso:country":"US",
    "sg:address":"11705 SW Pacific Hwy",
    "sg:city":"Portland",
    "sg:classifiers":[
        {
            "category":"Restaurant",
            "type":"Food & Drink"
        },
        {
            "category":"Ice Cream",
            "type":"Food & Drink"
        }
    ],
    "sg:menulink":"http://www.allmenus.com/or/beaverton-hillsboro/243637-baskin-robbins/menu/",
    "sg:phone":"+1 503 620 0794",
    "sg:postcode":"97223",
    "sg:province":"OR",
    "sg:tags":[
        "american",
        "ice",
        "cream"
    ],
    "wof:name":"Baskin-Robbins",
    "wof:placetype":"venue"
},
  "geometry": {"coordinates":[-122.757966,45.437283],"type":"Point"}
}