{
  "type": "Feature",
  "properties": {
    "addr:full":"4648 SE 48th Ave Portland OR 97206",
    "addr:housenumber":"4648",
    "addr:postcode":"97206",
    "addr:street":"Se 48Th Ave",
    "iso:country":"US",
    "sg:address":"4648 SE 48th Ave",
    "sg:city":"Portland",
    "sg:classifiers":[
        {
            "category":"Shopping",
            "type":"Retail Goods"
        }
    ],
    "sg:phone":"+1 503 777 0155",
    "sg:postcode":"97206",
    "sg:province":"OR",
    "sg:tags":[
        "merchandise"
    ],
    "wof:name":"Knit Castle",
    "wof:placetype":"venue"
},
  "geometry": {"coordinates":[-122.61284000000001,45.489839],"type":"Point"}
}