{
  "type": "Feature",
  "properties": {
    "iso:country":"US",
    "sg:address":"620 Applegate St",
    "sg:city":"Jacksonville",
    "sg:classifiers":[
        {
            "category":"Professional",
            "subcategory":"Research",
            "type":"Services"
        }
    ],
    "sg:phone":"+1 541 929 2495",
    "sg:postcode":"97530",
    "sg:province":"OR",
    "sg:tags":[
        "development",
        "laboratory"
    ],
    "wof:name":"Wetsat Inc",
    "wof:placetype":"venue"
},
  "geometry": {"coordinates":[-122.971671,42.310777],"type":"Point"}
}