{
  "type": "Feature",
  "properties": {
    "addr:full":"1600 SW 4th Ave # 770 Portland OR 97201",
    "addr:housenumber":"1600",
    "addr:postcode":"97201",
    "addr:street":"Sw 4Th Ave # 770",
    "iso:country":"US",
    "sg:address":"1600 SW 4th Ave # 770",
    "sg:city":"Portland",
    "sg:classifiers":[
        {
            "category":"Professional",
            "subcategory":"Engineering",
            "type":"Services"
        }
    ],
    "sg:phone":"+1 503 227 7611",
    "sg:postcode":"97201",
    "sg:province":"OR",
    "sg:tags":[
        "consulting",
        "engineer"
    ],
    "wof:name":"Pacific Energy Systems Inc",
    "wof:placetype":"venue"
},
  "geometry": {"coordinates":[-122.67981,45.512531],"type":"Point"}
}