{
  "type": "Feature",
  "properties": {
    "iso:country":"US",
    "sg:address":"862 Creek Rd",
    "sg:city":"Oakland",
    "sg:classifiers":[
        {
            "category":"Building & Trades",
            "subcategory":"Plumbing",
            "type":"Services"
        }
    ],
    "sg:phone":"+1 541 459 2824",
    "sg:postcode":"97410",
    "sg:province":"OR",
    "sg:tags":[
        "septic"
    ],
    "wof:name":"SOUTHERN Septic Svc",
    "wof:placetype":"venue"
},
  "geometry": {"coordinates":[-123.253671,42.798345],"type":"Point"}
}