{
  "type": "Feature",
  "properties": {
    "iso:country":"US",
    "sg:address":"1314 12th St",
    "sg:city":"Hood River",
    "sg:classifiers":[
        {
            "category":"Personal",
            "type":"Services"
        }
    ],
    "sg:phone":"+1 541 386 3480",
    "sg:postcode":"97031",
    "sg:province":"OR",
    "sg:tags":[
        "costume"
    ],
    "wof:name":"Just Imagine Costumes & More",
    "wof:placetype":"venue"
},
  "geometry": {"coordinates":[-121.523704,45.70083],"type":"Point"}
}