{
  "type": "Feature",
  "properties": {
    "addr:full":"2665 Alvarado Ter S Salem OR 97302",
    "addr:housenumber":"2665",
    "addr:postcode":"97302",
    "addr:street":"Alvarado Ter S",
    "iso:country":"US",
    "sg:address":"2665 Alvarado Ter S",
    "sg:city":"Salem",
    "sg:classifiers":[
        {
            "category":"Organizations",
            "subcategory":"Community Association",
            "type":"Services"
        }
    ],
    "sg:phone":"+1 503 364 8144",
    "sg:postcode":"97302",
    "sg:province":"OR",
    "wof:name":"Hudson Cncl 1 Cryptic Masons",
    "wof:placetype":"venue"
},
  "geometry": {"coordinates":[-123.054607,44.916014],"type":"Point"}
}