{
  "type": "Feature",
  "properties": {
    "addr:full":"61235 Parrell Rd Bend OR 97702",
    "addr:postcode":"61235;97702",
    "addr:street":"Parrell Rd",
    "iso:country":"US",
    "sg:address":"61235 Parrell Rd",
    "sg:city":"Bend",
    "sg:classifiers":[
        {
            "category":"Retail",
            "subcategory":"Car Wash",
            "type":"Services"
        }
    ],
    "sg:phone":"+1 541 390 6202",
    "sg:postcode":"97702",
    "sg:province":"OR",
    "sg:tags":[
        "carwash"
    ],
    "wof:name":"B&T Auto Spa",
    "wof:placetype":"venue"
},
  "geometry": {"coordinates":[-121.312427,44.023818],"type":"Point"}
}