{
  "type": "Feature",
  "properties": {
    "iso:country":"US",
    "sg:address":"51600 Huntington Rd",
    "sg:city":"La Pine",
    "sg:classifiers":[
        {
            "category":"Health Services",
            "subcategory":"Doctor",
            "type":"Services"
        }
    ],
    "sg:phone":"+1 541 382 3344",
    "sg:postcode":"97739",
    "sg:province":"OR",
    "sg:tags":[
        "physician",
        "surgeon"
    ],
    "wof:name":"Orthopaedic & Neurosurgical",
    "wof:placetype":"venue"
},
  "geometry": {"coordinates":[-121.503962,43.678155],"type":"Point"}
}