{
  "type": "Feature",
  "properties": {
    "addr:full":"4861 Upton Rd Central Point OR 97502",
    "addr:housenumber":"4861",
    "addr:postcode":"97502",
    "addr:street":"Upton Rd",
    "iso:country":"US",
    "sg:address":"4861 Upton Rd",
    "sg:city":"Central Point",
    "sg:classifiers":[
        {
            "category":"Retail",
            "subcategory":"Repair Shop",
            "type":"Services"
        }
    ],
    "sg:phone":"+1 541 665 2676",
    "sg:postcode":"97502",
    "sg:province":"OR",
    "wof:name":"ARC System Services",
    "wof:placetype":"venue"
},
  "geometry": {"coordinates":[-122.920034,42.392324],"type":"Point"}
}