{
  "type": "Feature",
  "properties": {
    "addr:full":"7160 SW Fir Loop Portland OR 97223",
    "addr:housenumber":"7160",
    "addr:postcode":"97223",
    "addr:street":"Sw Fir Loop",
    "iso:country":"US",
    "sg:address":"7160 SW Fir Loop",
    "sg:city":"Portland",
    "sg:classifiers":[
        {
            "category":"Building & Trades",
            "subcategory":"Plumbing",
            "type":"Services"
        }
    ],
    "sg:phone":"+1 503 624 9476",
    "sg:postcode":"97223",
    "sg:province":"OR",
    "sg:tags":[
        "contractor"
    ],
    "wof:name":"Prs AC",
    "wof:placetype":"venue"
},
  "geometry": {"coordinates":[-122.751007,45.423217],"type":"Point"}
}