{
  "type": "Feature",
  "properties": {
    "iso:country":"US",
    "sg:address":"1556 E 1st St",
    "sg:city":"Newberg",
    "sg:classifiers":[
        {
            "category":"Personal",
            "type":"Services"
        }
    ],
    "sg:phone":"+1 503 554 8267",
    "sg:postcode":"97132",
    "sg:province":"OR",
    "wof:name":"Mary Nathalie Lmt",
    "wof:placetype":"venue"
},
  "geometry": {"coordinates":[-122.960882,45.300295],"type":"Point"}
}