{
  "type": "Feature",
  "properties": {
    "iso:country":"US",
    "sg:address":"7233 SW Canyon Dr",
    "sg:city":"Portland",
    "sg:classifiers":[
        {
            "category":"Manufacturing",
            "subcategory":"Printing",
            "type":"Manufacturing & Wholesale Goods"
        },
        {
            "category":"Wholesale",
            "subcategory":"Books, Periodicals, & Newspapers",
            "type":"Manufacturing & Wholesale Goods"
        }
    ],
    "sg:phone":"+1 503 297 5157",
    "sg:postcode":"97225",
    "sg:province":"OR",
    "sg:tags":[
        "publisher",
        "guide",
        "publishers-directory"
    ],
    "wof:name":"Bonafide Country Newspaper",
    "wof:placetype":"venue"
},
  "geometry": {"coordinates":[-122.75066,45.498332],"type":"Point"}
}