{
  "type": "Feature",
  "properties": {
    "iso:country":"US",
    "sg:address":"5530 SW Kelly Ave",
    "sg:city":"Portland",
    "sg:classifiers":[
        {
            "category":"Professional",
            "subcategory":"Lawyer & Legal Services",
            "type":"Services"
        }
    ],
    "sg:phone":"+1 503 226 3906",
    "sg:postcode":"97239",
    "sg:province":"OR",
    "sg:tags":[
        "attorney",
        "law",
        "specialized"
    ],
    "wof:name":"Garrettson Goldberg Fenrich MA",
    "wof:placetype":"venue"
},
  "geometry": {"coordinates":[-122.67573400000001,45.482684],"type":"Point"}
}