{
  "type": "Feature",
  "properties": {
    "addr:full":"483 19th St SE Salem OR 97301",
    "addr:housenumber":"483",
    "addr:postcode":"97301",
    "addr:street":"19Th St Se",
    "iso:country":"US",
    "sg:address":"483 19th St SE",
    "sg:city":"Salem",
    "sg:classifiers":[
        {
            "category":"Professional",
            "subcategory":"Business Services",
            "type":"Services"
        }
    ],
    "sg:phone":"+1 503 371 1947",
    "sg:postcode":"97301",
    "sg:province":"OR",
    "sg:tags":[
        "architectural"
    ],
    "wof:name":"Pacific Northwest Design",
    "wof:placetype":"venue"
},
  "geometry": {"coordinates":[-123.01985999999999,44.931563],"type":"Point"}
}