{
  "type": "Feature",
  "properties": {
    "addr:full":"9000 S.W. Beaverton Hillsdale Hwy Portland OR 97225",
    "addr:housenumber":"9000",
    "addr:postcode":"97225",
    "addr:street":"S.W.;Hillsdale Hwy",
    "iso:country":"US",
    "sg:address":"9000 S.W. Beaverton Hillsdale Hwy",
    "sg:city":"Portland",
    "sg:classifiers":[
        {
            "category":"Education",
            "subcategory":"School",
            "type":"Public Place"
        }
    ],
    "sg:phone":"+1 503 292 2663",
    "sg:postcode":"97225",
    "sg:province":"OR",
    "sg:tags":[
        "high",
        "middle"
    ],
    "sg:website":"www.jesuitportland.org/s/173/spl...",
    "wof:name":"Jesuit High School",
    "wof:placetype":"venue"
},
  "geometry": {"coordinates":[-122.769644,45.48638],"type":"Point"}
}