{
  "type": "Feature",
  "properties": {
    "addr:full":"10125 SE Bob Schumacher Rd Happy Valley OR 97086",
    "addr:postcode":"10125;97086",
    "addr:street":"Se;Schumacher Rd",
    "iso:country":"US",
    "sg:address":"10125 SE Bob Schumacher Rd",
    "sg:city":"Happy Valley",
    "sg:classifiers":[
        {
            "category":"Real Estate",
            "subcategory":"Real Estate Operator",
            "type":"Services"
        }
    ],
    "sg:phone":"+1 503 777 5788",
    "sg:postcode":"97086",
    "sg:province":"OR",
    "sg:tags":[
        "apartment"
    ],
    "wof:name":"Mount Scott Associates Ltd Partnership",
    "wof:placetype":"venue"
},
  "geometry": {"coordinates":[-122.56892499999999,45.449963],"type":"Point"}
}