{
  "type": "Feature",
  "properties": {
    "iso:country":"US",
    "sg:address":"1808 Belmont Ave",
    "sg:city":"Hood River",
    "sg:classifiers":[
        {
            "category":"Health Services",
            "subcategory":"Health Practitioner",
            "type":"Services"
        }
    ],
    "sg:phone":"+1 541 386 9735",
    "sg:postcode":"97031",
    "sg:province":"OR",
    "wof:name":"Tim Foley Physical Therapy",
    "wof:placetype":"venue"
},
  "geometry": {"coordinates":[-121.53103400000001,45.699751],"type":"Point"}
}