{
  "type": "Feature",
  "properties": {
    "iso:country":"US",
    "sg:address":"4135 Filbert Ave NE",
    "sg:city":"Salem",
    "sg:classifiers":[
        {
            "category":"Building & Trades",
            "subcategory":"Construction",
            "type":"Services"
        }
    ],
    "sg:phone":"+1 503 463 8557",
    "sg:postcode":"97303",
    "sg:province":"OR",
    "sg:tags":[
        "contractor"
    ],
    "wof:name":"Retro 3 Contractors LLC",
    "wof:placetype":"venue"
},
  "geometry": {"coordinates":[-123.021832,44.985266],"type":"Point"}
}