{
  "type": "Feature",
  "properties": {
    "iso:country":"US",
    "sg:address":"3680 Balm St S",
    "sg:city":"Salem",
    "sg:classifiers":[
        {
            "category":"Building & Trades",
            "subcategory":"Construction",
            "type":"Services"
        }
    ],
    "sg:phone":"+1 503 589 5567",
    "sg:postcode":"97302",
    "sg:province":"OR",
    "sg:tags":[
        "house"
    ],
    "wof:name":"William Zoerner Building Cnstr",
    "wof:placetype":"venue"
},
  "geometry": {"coordinates":[-123.07044999999999,44.902668],"type":"Point"}
}