{
  "type": "Feature",
  "properties": {
    "addr:full":"1075 SW Bertha Blvd Portland OR 97219",
    "addr:housenumber":"1075",
    "addr:postcode":"97219",
    "addr:street":"Sw Bertha Blvd",
    "iso:country":"US",
    "sg:address":"1075 SW Bertha Blvd",
    "sg:city":"Portland",
    "sg:classifiers":[
        {
            "category":"Organizations",
            "subcategory":"Membership Organization",
            "type":"Services"
        }
    ],
    "sg:phone":"+1 503 244 7724",
    "sg:postcode":"97219",
    "sg:province":"OR",
    "wof:name":"Education Advocates",
    "wof:placetype":"venue"
},
  "geometry": {"coordinates":[-122.688688,45.471122],"type":"Point"}
}