{
  "type": "Feature",
  "properties": {
    "iso:country":"US",
    "sg:address":"12390 NE Marx St",
    "sg:city":"Portland",
    "sg:classifiers":[
        {
            "category":"Manufacturing",
            "subcategory":"Glass & Minerals",
            "type":"Manufacturing & Wholesale Goods"
        }
    ],
    "sg:phone":"+1 503 258 0858",
    "sg:postcode":"97230",
    "sg:province":"OR",
    "sg:tags":[
        "glassware",
        "glassware-wholesale",
        "manufacturer"
    ],
    "wof:name":"Smith & Greene Company",
    "wof:placetype":"venue"
},
  "geometry": {"coordinates":[-122.53587400000001,45.559183],"type":"Point"}
}