{
  "type": "Feature",
  "properties": {
    "iso:country":"US",
    "sg:address":"12744 SE Stark St",
    "sg:city":"Portland",
    "sg:classifiers":[
        {
            "category":"Social Services",
            "type":"Services"
        }
    ],
    "sg:phone":"+1 503 261 0600",
    "sg:postcode":"97233",
    "sg:province":"OR",
    "sg:tags":[
        "counselor",
        "marriage",
        "family"
    ],
    "wof:name":"Cindy Brodner MA",
    "wof:placetype":"venue"
},
  "geometry": {"coordinates":[-122.532005,45.518981],"type":"Point"}
}