{
  "type": "Feature",
  "properties": {
    "addr:full":"2305 Pacific Ave Forest Grove OR 97116",
    "addr:housenumber":"2305",
    "addr:postcode":"97116",
    "addr:street":"Pacific Ave",
    "iso:country":"US",
    "sg:address":"2305 Pacific Ave",
    "sg:city":"Forest Grove",
    "sg:classifiers":[
        {
            "category":"Health Services",
            "subcategory":"Doctor",
            "type":"Services"
        }
    ],
    "sg:phone":"+1 503 693 1954",
    "sg:postcode":"97116",
    "sg:province":"OR",
    "sg:tags":[
        "medical"
    ],
    "wof:name":"Hopson Jane ND",
    "wof:placetype":"venue"
},
  "geometry": {"coordinates":[-123.104787,45.519714],"type":"Point"}
}