{
  "type": "Feature",
  "properties": {
    "iso:country":"US",
    "sg:address":"1712 W Main St",
    "sg:city":"Medford",
    "sg:classifiers":[
        {
            "category":"Retail",
            "subcategory":"Laundry & Dry Cleaning",
            "type":"Services"
        }
    ],
    "sg:phone":"+1 541 773 4803",
    "sg:postcode":"97501",
    "sg:province":"OR",
    "sg:tags":[
        "garment",
        "agent"
    ],
    "wof:name":"West Main Laundromat",
    "wof:placetype":"venue"
},
  "geometry": {"coordinates":[-122.89248499999999,42.323742],"type":"Point"}
}