{
  "type": "Feature",
  "properties": {
    "addr:full":"1310 12th St SE Salem OR 97302",
    "addr:housenumber":"1310",
    "addr:postcode":"97302",
    "addr:street":"12Th St Se",
    "iso:country":"US",
    "sg:address":"1310 12th St SE",
    "sg:city":"Salem",
    "sg:classifiers":[
        {
            "category":"Manufacturing",
            "subcategory":"Printing",
            "type":"Manufacturing & Wholesale Goods"
        }
    ],
    "sg:phone":"+1 503 581 1181",
    "sg:postcode":"97302",
    "sg:province":"OR",
    "sg:tags":[
        "commercial",
        "lithographic"
    ],
    "wof:name":"ABC Printers Inc",
    "wof:placetype":"venue"
},
  "geometry": {"coordinates":[-123.03059399999999,44.923928],"type":"Point"}
}