{
  "type": "Feature",
  "properties": {
    "iso:country":"US",
    "sg:address":"3255 NE 82nd Ave",
    "sg:city":"Portland",
    "sg:classifiers":[
        {
            "category":"Restaurant",
            "type":"Food & Drink"
        }
    ],
    "sg:phone":"+1 503 255 8226",
    "sg:postcode":"97220",
    "sg:province":"OR",
    "sg:tags":[
        "mexican"
    ],
    "wof:name":"Taco House Original",
    "wof:placetype":"venue"
},
  "geometry": {"coordinates":[-122.579002,45.546001],"type":"Point"}
}