{
  "type": "Feature",
  "properties": {
    "addr:full":"79370 State Hwy 99 Cottage Grove OR 97424",
    "addr:housenumber":"79370",
    "addr:postcode":"97424",
    "addr:street":"State Hwy 99",
    "iso:country":"US",
    "sg:address":"79370 State Hwy 99",
    "sg:city":"Cottage Grove",
    "sg:classifiers":[
        {
            "category":"Manufacturing",
            "subcategory":"Building Materials",
            "type":"Manufacturing & Wholesale Goods"
        }
    ],
    "sg:phone":"+1 541 942 4777",
    "sg:postcode":"97424",
    "sg:province":"OR",
    "sg:tags":[
        "cabinet"
    ],
    "wof:name":"Maddux Fine Cabinetry",
    "wof:placetype":"venue"
},
  "geometry": {"coordinates":[-123.04989,43.808809],"type":"Point"}
}