{
  "type": "Feature",
  "properties": {
    "iso:country":"US",
    "sg:address":"8333 NE Russell Street",
    "sg:city":"Portland",
    "sg:classifiers":[
        {
            "category":"Sports & Exercise",
            "subcategory":"Gym",
            "type":"Entertainment"
        }
    ],
    "sg:phone":"+1 503 235 9559",
    "sg:postcode":"97220",
    "sg:province":"OR",
    "wof:name":"Grand Avenue Boxing Club",
    "wof:placetype":"venue"
},
  "geometry": {"coordinates":[-122.577192,45.540839],"type":"Point"}
}