{
  "type": "Feature",
  "properties": {
    "addr:full":"6540 NW 60th St Redmond OR 97756",
    "addr:housenumber":"6540",
    "addr:postcode":"97756",
    "addr:street":"Nw 60Th St",
    "iso:country":"US",
    "sg:address":"6540 NW 60th St",
    "sg:city":"Redmond",
    "sg:classifiers":[
        {
            "category":"Shopping",
            "type":"Retail Goods"
        }
    ],
    "sg:phone":"+1 541 923 5092",
    "sg:postcode":"97756",
    "sg:province":"OR",
    "sg:tags":[
        "merchandise"
    ],
    "wof:name":"Carole J Lind",
    "wof:placetype":"venue"
},
  "geometry": {"coordinates":[-121.242651,44.336992],"type":"Point"}
}