{
  "type": "Feature",
  "properties": {
    "addr:full":"545 NE 47th Ave Portland OR 97213",
    "addr:housenumber":"545",
    "addr:postcode":"97213",
    "addr:street":"Ne 47Th Ave",
    "iso:country":"US",
    "sg:address":"545 NE 47th Ave",
    "sg:city":"Portland",
    "sg:classifiers":[
        {
            "category":"Health Services",
            "subcategory":"Doctor",
            "type":"Services"
        }
    ],
    "sg:phone":"+1 503 215 9700",
    "sg:postcode":"97213",
    "sg:province":"OR",
    "sg:tags":[
        "physician",
        "surgeon"
    ],
    "sg:website":"www.providence.org",
    "wof:name":"Providence Medical Group",
    "wof:placetype":"venue"
},
  "geometry": {"coordinates":[-122.615077,45.526945],"type":"Point"}
}