{
  "type": "Feature",
  "properties": {
    "addr:full":"1740 SW Court Pl Pendleton OR 97801",
    "addr:housenumber":"1740",
    "addr:postcode":"97801",
    "addr:street":"Sw Court Pl",
    "iso:country":"US",
    "sg:address":"1740 SW Court Pl",
    "sg:city":"Pendleton",
    "sg:phone":"+1 541 276 6422",
    "sg:postcode":"97801",
    "sg:province":"OR",
    "sg:tags":[
        "depository",
        "communications",
        "telegraph",
        "banking"
    ],
    "wof:name":"Cashco",
    "wof:placetype":"venue"
},
  "geometry": {"coordinates":[-118.803713,45.667784],"type":"Point"}
}