{
  "type": "Feature",
  "properties": {
    "iso:country":"US",
    "sg:address":"566 Beall Ln",
    "sg:city":"Central Point",
    "sg:classifiers":[
        {
            "category":"Real Estate",
            "subcategory":"Developer",
            "type":"Services"
        }
    ],
    "sg:phone":"+1 541 664 3617",
    "sg:postcode":"97502",
    "sg:province":"OR",
    "sg:tags":[
        "cemetery"
    ],
    "wof:name":"Ohana LLC",
    "wof:placetype":"venue"
},
  "geometry": {"coordinates":[-122.896695,42.362703],"type":"Point"}
}