{
  "type": "Feature",
  "properties": {
    "iso:country":"US",
    "sg:address":"738 NE 151st Ave",
    "sg:city":"Portland",
    "sg:classifiers":[
        {
            "category":"Professional",
            "subcategory":"Accounting & Tax Preparation",
            "type":"Services"
        }
    ],
    "sg:phone":"+1 503 282 8222",
    "sg:postcode":"97230",
    "sg:province":"OR",
    "sg:tags":[
        "return"
    ],
    "wof:name":"TST Tax Service LLC",
    "wof:placetype":"venue"
},
  "geometry": {"coordinates":[-122.50712799999999,45.528637],"type":"Point"}
}