{
  "type": "Feature",
  "properties": {
    "iso:country":"US",
    "sg:address":"18080 SW Lower Boones Ferry Rd",
    "sg:city":"Tigard",
    "sg:classifiers":[
        {
            "category":"Organizations",
            "subcategory":"Religious Organization",
            "type":"Services"
        }
    ],
    "sg:phone":"+1 503 603 0303",
    "sg:postcode":"97224",
    "sg:province":"OR",
    "sg:tags":[
        "church"
    ],
    "sg:website":"www.tualatinfoursquare.org",
    "wof:name":"Tualatin Foursquare Church",
    "wof:placetype":"venue"
},
  "geometry": {"coordinates":[-122.754341,45.389525],"type":"Point"}
}