{
  "type": "Feature",
  "properties": {
    "iso:country":"US",
    "sg:address":"184 King St",
    "sg:city":"Oregon City",
    "sg:classifiers":[
        {
            "category":"Professional",
            "type":"Services"
        }
    ],
    "sg:phone":"+1 503 656 9225",
    "sg:postcode":"97045",
    "sg:province":"OR",
    "wof:name":"Wendy M Quist",
    "wof:placetype":"venue"
},
  "geometry": {"coordinates":[-122.619242,45.338951],"type":"Point"}
}