{
  "type": "Feature",
  "properties": {
    "iso:country":"US",
    "sg:address":"17360 Smith Ave",
    "sg:city":"Sandy",
    "sg:classifiers":[
        {
            "category":"Professional",
            "subcategory":"Computer Services",
            "type":"Services"
        }
    ],
    "sg:phone":"+1 503 668 3540",
    "sg:postcode":"97055",
    "sg:province":"OR",
    "wof:name":"Computer Shop Inc",
    "wof:placetype":"venue"
},
  "geometry": {"coordinates":[-122.260672,45.397554],"type":"Point"}
}