{
  "type": "Feature",
  "properties": {
    "iso:country":"US",
    "sg:address":"1616 SW Sunset Blvd",
    "sg:city":"Portland",
    "sg:classifiers":[
        {
            "category":"Health Services",
            "subcategory":"Dentist",
            "type":"Services"
        }
    ],
    "sg:phone":"+1 503 246 6785",
    "sg:postcode":"97239",
    "sg:province":"OR",
    "sg:tags":[
        "orthodontist"
    ],
    "wof:name":"Jevning Leslie R Orthodontist",
    "wof:placetype":"venue"
},
  "geometry": {"coordinates":[-122.69499999999999,45.480099],"type":"Point"}
}