{
  "type": "Feature",
  "properties": {
    "addr:full":"5002 SE Woodward Street Portland OR 97206",
    "addr:housenumber":"5002",
    "addr:postcode":"97206",
    "addr:street":"Se Woodward Street",
    "iso:country":"US",
    "sg:address":"5002 SE Woodward Street",
    "sg:city":"Portland",
    "sg:classifiers":[
        {
            "category":"Food & Beverages",
            "subcategory":"Groceries & Convenience Stores",
            "type":"Retail Goods"
        }
    ],
    "sg:phone":"+1 503 236 8453",
    "sg:postcode":"97206",
    "sg:province":"OR",
    "wof:name":"Franklin Market",
    "wof:placetype":"venue"
},
  "geometry": {"coordinates":[-122.61102200000001,45.501479],"type":"Point"}
}