{
  "type": "Feature",
  "properties": {
    "iso:country":"US",
    "sg:address":"10791 Oak St",
    "sg:city":"Donald",
    "sg:classifiers":[
        {
            "category":"Shopping",
            "subcategory":"Bicycles & Sporting Goods",
            "type":"Retail Goods"
        }
    ],
    "sg:phone":"+1 503 678 2424",
    "sg:postcode":"97020",
    "sg:province":"OR",
    "sg:tags":[
        "repair",
        "gun",
        "gunsmith"
    ],
    "wof:name":"Rich's Gun Shop",
    "wof:placetype":"venue"
},
  "geometry": {"coordinates":[-122.839329,45.223172],"type":"Point"}
}