{
  "type": "Feature",
  "properties": {
    "iso:country":"US",
    "sg:address":"100 SW Baseline St",
    "sg:city":"Hillsboro",
    "sg:classifiers":[
        {
            "category":"Professional",
            "subcategory":"Lawyer & Legal Services",
            "type":"Services"
        }
    ],
    "sg:phone":"+1 503 640 4243",
    "sg:postcode":"97123",
    "sg:province":"OR",
    "sg:tags":[
        "plan"
    ],
    "wof:name":"Marsha Cordon",
    "wof:placetype":"venue"
},
  "geometry": {"coordinates":[-122.98983,45.520142],"type":"Point"}
}