{
  "type": "Feature",
  "properties": {
    "iso:country":"US",
    "sg:address":"225 Pioneer Pkwy E",
    "sg:city":"Springfield",
    "sg:classifiers":[
        {
            "category":"Manufacturing",
            "subcategory":"Printing",
            "type":"Manufacturing & Wholesale Goods"
        }
    ],
    "sg:phone":"+1 541 726 9020",
    "sg:postcode":"97477",
    "sg:province":"OR",
    "sg:tags":[
        "lithographic",
        "commercial",
        "photocopying"
    ],
    "wof:name":"Best Little Printhouse In Town",
    "wof:placetype":"venue"
},
  "geometry": {"coordinates":[-123.021961,44.046291],"type":"Point"}
}