{
  "type": "Feature",
  "properties": {
    "iso:country":"US",
    "sg:address":"29955 SW Boones Ferry Rd",
    "sg:city":"Wilsonville",
    "sg:classifiers":[
        {
            "category":"Personal",
            "subcategory":"Beauty Salon",
            "type":"Services"
        }
    ],
    "sg:phone":"+1 503 582 0103",
    "sg:postcode":"97070",
    "sg:province":"OR",
    "wof:name":"D-J Nails",
    "wof:placetype":"venue"
},
  "geometry": {"coordinates":[-122.771904,45.303617],"type":"Point"}
}