{
  "type": "Feature",
  "properties": {
    "addr:full":"8624 Wagner Creek Rd Talent OR 97540",
    "addr:housenumber":"8624",
    "addr:postcode":"97540",
    "addr:street":"Wagner Creek Rd",
    "iso:country":"US",
    "sg:address":"8624 Wagner Creek Rd",
    "sg:city":"Talent",
    "sg:classifiers":[
        {
            "category":"Wholesale",
            "subcategory":"Books, Periodicals, & Newspapers",
            "type":"Manufacturing & Wholesale Goods"
        }
    ],
    "sg:phone":"+1 541 535 7659",
    "sg:postcode":"97540",
    "sg:province":"OR",
    "sg:tags":[
        "publisher",
        "book"
    ],
    "wof:name":"Last Minute Publications",
    "wof:placetype":"venue"
},
  "geometry": {"coordinates":[-122.791275,42.214238],"type":"Point"}
}