{
  "type": "Feature",
  "properties": {
    "iso:country":"US",
    "sg:address":"488 Brookside Dr",
    "sg:city":"Eugene",
    "sg:classifiers":[
        {
            "category":"Wholesale",
            "subcategory":"Machinery & Supplies",
            "type":"Manufacturing & Wholesale Goods"
        }
    ],
    "sg:phone":"+1 541 465 1304",
    "sg:postcode":"97405",
    "sg:province":"OR",
    "sg:tags":[
        "equipment",
        "pneumatic",
        "component"
    ],
    "wof:name":"Buchanan Automation",
    "wof:placetype":"venue"
},
  "geometry": {"coordinates":[-123.098078,44.006238],"type":"Point"}
}