{
  "type": "Feature",
  "properties": {
    "iso:country":"US",
    "sg:address":"8811 Huff Ave NE",
    "sg:city":"Salem",
    "sg:classifiers":[
        {
            "category":"Manufacturing",
            "subcategory":"Toys & Sporting Goods",
            "type":"Manufacturing & Wholesale Goods"
        }
    ],
    "sg:phone":"+1 503 390 5714",
    "sg:postcode":"97303",
    "sg:province":"OR",
    "sg:tags":[
        "equipment",
        "batting",
        "mfg"
    ],
    "wof:name":"ABC",
    "wof:placetype":"venue"
},
  "geometry": {"coordinates":[-122.978326,45.04739],"type":"Point"}
}