{
  "type": "Feature",
  "properties": {
    "iso:country":"US",
    "sg:address":"92 W 17th Ave",
    "sg:city":"Eugene",
    "sg:classifiers":[
        {
            "category":"Shopping",
            "subcategory":"Jewelry",
            "type":"Retail Goods"
        }
    ],
    "sg:phone":"+1 541 687 1244",
    "sg:postcode":"97401",
    "sg:province":"OR",
    "wof:name":"Optical Mystic Jewelry",
    "wof:placetype":"venue"
},
  "geometry": {"coordinates":[-123.0936,44.041065],"type":"Point"}
}