{
  "type": "Feature",
  "properties": {
    "addr:full":"3333 NW 35th Ave Portland OR 97210",
    "addr:housenumber":"3333",
    "addr:postcode":"97210",
    "addr:street":"Nw 35Th Ave",
    "iso:country":"US",
    "sg:address":"3333 NW 35th Ave",
    "sg:city":"Portland",
    "sg:classifiers":[
        {
            "category":"Building & Trades",
            "subcategory":"Plumbing",
            "type":"Services"
        }
    ],
    "sg:phone":"+1 503 253 1393",
    "sg:postcode":"97210",
    "sg:province":"OR",
    "sg:tags":[
        "sewer",
        "cleaning",
        "drain"
    ],
    "wof:name":"Metro Rooter",
    "wof:placetype":"venue"
},
  "geometry": {"coordinates":[-122.718986,45.548745],"type":"Point"}
}