{
  "type": "Feature",
  "properties": {
    "iso:country":"US",
    "sg:address":"3333 NW 35th Ave",
    "sg:city":"Portland",
    "sg:classifiers":[
        {
            "category":"Building & Trades",
            "subcategory":"Plumbing",
            "type":"Services"
        }
    ],
    "sg:phone":"+1 503 253 1393",
    "sg:postcode":"97210",
    "sg:province":"OR",
    "sg:tags":[
        "sewer",
        "cleaning",
        "drain"
    ],
    "wof:name":"Metro Rooter",
    "wof:placetype":"venue"
},
  "geometry": {"coordinates":[-122.718986,45.548745],"type":"Point"}
}