{
  "type": "Feature",
  "properties": {
    "iso:country":"US",
    "sg:address":"625 SE Corliss Ave",
    "sg:city":"Corvallis",
    "sg:classifiers":[
        {
            "category":"Health Services",
            "subcategory":"Medical Lab",
            "type":"Services"
        }
    ],
    "sg:phone":"+1 541 758 0600",
    "sg:postcode":"97333",
    "sg:province":"OR",
    "sg:tags":[
        "laboratory"
    ],
    "wof:name":"E-B Dental Lab",
    "wof:placetype":"venue"
},
  "geometry": {"coordinates":[-123.263198,44.51486],"type":"Point"}
}