{
  "type": "Feature",
  "properties": {
    "addr:full":"2801 SE 14th Avenue Portland OR 97202",
    "addr:housenumber":"2801",
    "addr:postcode":"97202",
    "addr:street":"Se 14Th Avenue",
    "iso:country":"US",
    "sg:address":"2801 SE 14th Avenue",
    "sg:city":"Portland",
    "sg:classifiers":[
        {
            "category":"Coffee & Tea",
            "type":"Food & Drink"
        }
    ],
    "sg:phone":"+1 503 234 7788",
    "sg:postcode":"97202",
    "sg:province":"OR",
    "wof:name":"K & F Select Fine Coffees",
    "wof:placetype":"venue"
},
  "geometry": {"coordinates":[-122.651563,45.502585],"type":"Point"}
}