{
  "type": "Feature",
  "properties": {
    "iso:country":"US",
    "sg:address":"39713 Mertz Dr SE",
    "sg:city":"Stayton",
    "sg:classifiers":[
        {
            "category":"Retail",
            "subcategory":"Animal Services",
            "type":"Services"
        }
    ],
    "sg:phone":"+1 503 769 4453",
    "sg:postcode":"97383",
    "sg:province":"OR",
    "wof:name":"Oregon Appaloosa Breeders",
    "wof:placetype":"venue"
},
  "geometry": {"coordinates":[-122.820804,44.762545],"type":"Point"}
}