{
  "type": "Feature",
  "properties": {
    "addr:full":"Corner of SW 6th Ave Portland OR 97205",
    "addr:postcode":"97205",
    "addr:street":"Corner Of Sw 6Th Ave",
    "iso:country":"US",
    "sg:address":"Corner of SW 6th Ave",
    "sg:city":"Portland",
    "sg:classifiers":[
        {
            "category":"Restaurant",
            "type":"Food & Drink"
        }
    ],
    "sg:menulink":"http://www.allmenus.com/or/portland/5122-melting-pot/menu/",
    "sg:phone":"+1 503 517 8960",
    "sg:postcode":"97205",
    "sg:province":"OR",
    "sg:tags":[
        "new",
        "american"
    ],
    "wof:name":"Melting Pot",
    "wof:placetype":"venue"
},
  "geometry": {"coordinates":[-122.68006,45.51642],"type":"Point"}
}