{
  "type": "Feature",
  "properties": {
    "iso:country":"US",
    "sg:address":"1915 NW Kearney St",
    "sg:city":"Portland",
    "sg:classifiers":[
        {
            "category":"Health Services",
            "subcategory":"Health Practitioner",
            "type":"Services"
        },
        {
            "category":"Community Center",
            "type":"Public Place"
        }
    ],
    "sg:phone":"+1 503 222 1668",
    "sg:postcode":"97209",
    "sg:province":"OR",
    "sg:tags":[
        "acupuncture",
        "medical"
    ],
    "sg:website":"www.redpeonyhealth.com",
    "wof:name":"Red Peony Acupuncture",
    "wof:placetype":"venue"
},
  "geometry": {"coordinates":[-122.69079600000001,45.529226],"type":"Point"}
}