{
  "type": "Feature",
  "properties": {
    "iso:country":"US",
    "sg:address":"6424 SE Franklin St",
    "sg:city":"Portland",
    "sg:classifiers":[
        {
            "category":"Building & Trades",
            "subcategory":"Cleaning & Sanitation",
            "type":"Services"
        }
    ],
    "sg:phone":"+1 503 284 3186",
    "sg:postcode":"97206",
    "sg:province":"OR",
    "sg:tags":[
        "maintenance"
    ],
    "wof:name":"Larisas Janitorial Service",
    "wof:placetype":"venue"
},
  "geometry": {"coordinates":[-122.596762,45.498809],"type":"Point"}
}