{
  "type": "Feature",
  "properties": {
    "iso:country":"US",
    "sg:address":"115 N 5th St",
    "sg:city":"Klamath Falls",
    "sg:classifiers":[
        {
            "category":"Building & Trades",
            "subcategory":"Equipment Rental",
            "type":"Services"
        }
    ],
    "sg:phone":"+1 541 884 7728",
    "sg:postcode":"97601",
    "sg:province":"OR",
    "wof:name":"Facilities Leasing Corporation",
    "wof:placetype":"venue"
},
  "geometry": {"coordinates":[-121.784026,42.224561],"type":"Point"}
}