{
  "type": "Feature",
  "properties": {
    "iso:country":"US",
    "sg:address":"8451 S Hwy 97",
    "sg:city":"Redmond",
    "sg:classifiers":[
        {
            "category":"Retail",
            "subcategory":"Animal Services",
            "type":"Services"
        }
    ],
    "sg:phone":"+1 541 504 9595",
    "sg:postcode":"97756",
    "sg:province":"OR",
    "wof:name":"Stargate Doggie Dude Ranch",
    "wof:placetype":"venue"
},
  "geometry": {"coordinates":[-121.228414,44.201211],"type":"Point"}
}