{
  "type": "Feature",
  "properties": {
    "iso:country":"US",
    "sg:address":"20975 State Hwy 62",
    "sg:city":"Shady Cove",
    "sg:classifiers":[
        {
            "category":"Real Estate",
            "subcategory":"Real Estate Agent",
            "type":"Services"
        }
    ],
    "sg:phone":"+1 541 878 7368",
    "sg:postcode":"97539",
    "sg:province":"OR",
    "wof:name":"Northwoods Property Management",
    "wof:placetype":"venue"
},
  "geometry": {"coordinates":[-122.81675,42.604915],"type":"Point"}
}