{
  "type": "Feature",
  "properties": {
    "iso:country":"US",
    "sg:address":"123 SW 2nd Ave",
    "sg:city":"Canby",
    "sg:classifiers":[
        {
            "category":"Insurance",
            "subcategory":"Insurance Agent",
            "type":"Services"
        }
    ],
    "sg:phone":"+1 503 263 6285",
    "sg:postcode":"97013",
    "sg:province":"OR",
    "wof:name":"Grange Insurance",
    "wof:placetype":"venue"
},
  "geometry": {"coordinates":[-122.69158,45.26107],"type":"Point"}
}