{
  "type": "Feature",
  "properties": {
    "addr:full":"1475 Franklin Blvd Eugene OR 97403",
    "addr:housenumber":"1475",
    "addr:postcode":"97403",
    "addr:street":"Franklin Blvd",
    "iso:country":"US",
    "sg:address":"1475 Franklin Blvd",
    "sg:city":"Eugene",
    "sg:classifiers":[
        {
            "category":"Coffee & Tea",
            "type":"Food & Drink"
        },
        {
            "category":"Restaurant",
            "type":"Food & Drink"
        }
    ],
    "sg:phone":"+1 541 342 8212",
    "sg:postcode":"97403",
    "sg:province":"OR",
    "wof:name":"Espresso Milano Coffee Company",
    "wof:placetype":"venue"
},
  "geometry": {"coordinates":[-123.07120500000001,44.046909],"type":"Point"}
}