{
  "type": "Feature",
  "properties": {
    "addr:full":"1001 SW 5th Ave Ste 1100 Portland OR 97204",
    "addr:housenumber":"1001",
    "addr:postcode":"97204",
    "addr:street":"Sw 5Th Ave Ste 1100",
    "iso:country":"US",
    "sg:address":"1001 SW 5th Ave Ste 1100",
    "sg:city":"Portland",
    "sg:classifiers":[
        {
            "category":"Education",
            "subcategory":"School",
            "type":"Public Place"
        }
    ],
    "sg:phone":"+1 503 226 8006",
    "sg:postcode":"97204",
    "sg:province":"OR",
    "sg:tags":[
        "high"
    ],
    "sg:website":"http://www.apollogrp.com",
    "wof:name":"Insight Schools",
    "wof:placetype":"venue"
},
  "geometry": {"coordinates":[-122.67865,45.5168],"type":"Point"}
}