{
  "type": "Feature",
  "properties": {
    "addr:full":"57564 Redding Rd Heppner OR 97836",
    "addr:postcode":"57564;97836",
    "addr:street":"Redding Rd",
    "iso:country":"US",
    "sg:address":"57564 Redding Rd",
    "sg:city":"Heppner",
    "sg:phone":"+1 541 676 9730",
    "sg:postcode":"97836",
    "sg:province":"OR",
    "sg:tags":[
        "farm",
        "wheat"
    ],
    "wof:name":"Roger Palmer",
    "wof:placetype":"venue"
},
  "geometry": {"coordinates":[-119.816101,45.247174],"type":"Point"}
}