{
  "type": "Feature",
  "properties": {
    "iso:country":"US",
    "sg:address":"323 N Washington St",
    "sg:city":"Prairie City",
    "sg:classifiers":[
        {
            "category":"Building & Trades",
            "subcategory":"Construction",
            "type":"Services"
        }
    ],
    "sg:phone":"+1 541 820 3576",
    "sg:postcode":"97869",
    "sg:province":"OR",
    "sg:tags":[
        "general",
        "contractor"
    ],
    "wof:name":"Double C Construction Inc",
    "wof:placetype":"venue"
},
  "geometry": {"coordinates":[-118.711748,44.469407],"type":"Point"}
}