{
  "type": "Feature",
  "properties": {
    "iso:country":"US",
    "sg:address":"22640 SW Miami Dr",
    "sg:city":"Tualatin",
    "sg:classifiers":[
        {
            "category":"Professional",
            "type":"Services"
        }
    ],
    "sg:phone":"+1 503 691 8338",
    "sg:postcode":"97062",
    "sg:province":"OR",
    "sg:tags":[
        "establishment"
    ],
    "wof:name":"Fisher & Fisher",
    "wof:placetype":"venue"
},
  "geometry": {"coordinates":[-122.780614,45.35595],"type":"Point"}
}