{
  "type": "Feature",
  "properties": {
    "addr:full":"1071 Commercial St SE Salem OR 97302",
    "addr:housenumber":"1071",
    "addr:postcode":"97302",
    "addr:street":"Commercial St Se",
    "iso:country":"US",
    "sg:address":"1071 Commercial St SE",
    "sg:city":"Salem",
    "sg:classifiers":[
        {
            "category":"Shopping",
            "subcategory":"Books",
            "type":"Retail Goods"
        }
    ],
    "sg:phone":"+1 503 364 7980",
    "sg:postcode":"97302",
    "sg:province":"OR",
    "wof:name":"Danger Zone",
    "wof:placetype":"venue"
},
  "geometry": {"coordinates":[-123.044144,44.930945],"type":"Point"}
}