{
  "type": "Feature",
  "properties": {
    "addr:full":"838 Northside Rd Sutherlin OR 97479",
    "addr:housenumber":"838",
    "addr:postcode":"97479",
    "addr:street":"Northside Rd",
    "iso:country":"US",
    "sg:address":"838 Northside Rd",
    "sg:city":"Sutherlin",
    "sg:classifiers":[
        {
            "category":"Building & Trades",
            "subcategory":"Construction",
            "type":"Services"
        },
        {
            "category":"Military Area",
            "subcategory":"Armory",
            "type":"Public Place"
        }
    ],
    "sg:phone":"+1 541 784 5487",
    "sg:postcode":"97479",
    "sg:province":"OR",
    "sg:tags":[
        "repair",
        "fence-sales",
        "fence",
        "contractor"
    ],
    "wof:name":"R And M Enterprises",
    "wof:placetype":"venue"
},
  "geometry": {"coordinates":[-123.26658999999999,43.404115],"type":"Point"}
}