{
  "type": "Feature",
  "properties": {
    "iso:country":"US",
    "sg:address":"1511 SE 122nd Ave",
    "sg:city":"Portland",
    "sg:classifiers":[
        {
            "category":"Health Services",
            "subcategory":"Chiropractor",
            "type":"Services"
        }
    ],
    "sg:phone":"+1 503 408 1900",
    "sg:postcode":"97233",
    "sg:province":"OR",
    "wof:name":"Auto Accident Whiplash Ctr",
    "wof:placetype":"venue"
},
  "geometry": {"coordinates":[-122.537724,45.511609],"type":"Point"}
}