{
  "type": "Feature",
  "properties": {
    "iso:country":"US",
    "sg:address":"15323 SE Thornbridge Dr",
    "sg:city":"Clackamas",
    "sg:classifiers":[
        {
            "category":"Professional",
            "subcategory":"Computer Services",
            "type":"Services"
        }
    ],
    "sg:phone":"+1 503 558 0265",
    "sg:postcode":"97015",
    "sg:province":"OR",
    "sg:tags":[
        "repair"
    ],
    "wof:name":"Mt Hood Computer Resources",
    "wof:placetype":"venue"
},
  "geometry": {"coordinates":[-122.50599699999999,45.420799],"type":"Point"}
}