{
  "type": "Feature",
  "properties": {
    "addr:full":"3425 SW Illinois St Portland OR 97239",
    "addr:housenumber":"3425",
    "addr:postcode":"97239",
    "addr:street":"Sw Illinois St",
    "iso:country":"US",
    "sg:address":"3425 SW Illinois St",
    "sg:city":"Portland",
    "sg:classifiers":[
        {
            "category":"Professional",
            "subcategory":"Business Services",
            "type":"Services"
        }
    ],
    "sg:phone":"+1 971 570 8394",
    "sg:postcode":"97239",
    "sg:province":"OR",
    "wof:name":"Miller Information Technology",
    "wof:placetype":"venue"
},
  "geometry": {"coordinates":[-122.712019,45.479421],"type":"Point"}
}