{
  "type": "Feature",
  "properties": {
    "addr:full":"1244 W 6th St The Dalles OR 97058",
    "addr:housenumber":"1244",
    "addr:postcode":"97058",
    "addr:street":"W 6Th St",
    "iso:country":"US",
    "sg:address":"1244 W 6th St",
    "sg:city":"The Dalles",
    "sg:classifiers":[
        {
            "category":"Banks & Credit Unions",
            "subcategory":"Bank",
            "type":"Services"
        }
    ],
    "sg:phone":"+1 541 298 5200",
    "sg:postcode":"97058",
    "sg:province":"OR",
    "sg:tags":[
        "cashing",
        "check"
    ],
    "wof:name":"Check 'n Go",
    "wof:placetype":"venue"
},
  "geometry": {"coordinates":[-121.20204099999999,45.60732],"type":"Point"}
}