{
  "type": "Feature",
  "properties": {
    "iso:country":"US",
    "sg:address":"22165 SE Lafayette Hwy",
    "sg:city":"Dayton",
    "sg:classifiers":[
        {
            "category":"Professional",
            "subcategory":"Business Services",
            "type":"Services"
        }
    ],
    "sg:phone":"+1 503 868 7862",
    "sg:postcode":"97114",
    "sg:province":"OR",
    "wof:name":"Kraben Enterprises",
    "wof:placetype":"venue"
},
  "geometry": {"coordinates":[-123.093329,45.098915],"type":"Point"}
}