{
  "type": "Feature",
  "properties": {
    "iso:country":"US",
    "sg:address":"11083 W Stayton Rd SE",
    "sg:city":"Aumsville",
    "sg:classifiers":[
        {
            "category":"Building & Trades",
            "subcategory":"Landscaping Services",
            "type":"Services"
        }
    ],
    "sg:phone":"+1 503 580 3988",
    "sg:postcode":"97325",
    "sg:province":"OR",
    "sg:tags":[
        "landscape",
        "contractor"
    ],
    "wof:name":"R Franco Restoration, Inc",
    "wof:placetype":"venue"
},
  "geometry": {"coordinates":[-122.874908,44.793281],"type":"Point"}
}