{
  "type": "Feature",
  "properties": {
    "iso:country":"US",
    "sg:address":"3861 SW 117th Ave",
    "sg:city":"Beaverton",
    "sg:classifiers":[
        {
            "category":"Shopping",
            "subcategory":"Clothing, Apparel, & Fashions",
            "type":"Retail Goods"
        }
    ],
    "sg:phone":"+1 503 671 9522",
    "sg:postcode":"97005",
    "sg:province":"OR",
    "wof:name":"Avenue",
    "wof:placetype":"venue"
},
  "geometry": {"coordinates":[-122.797785,45.489695],"type":"Point"}
}