{
  "type": "Feature",
  "properties": {
    "addr:full":"623 SE 12th Ave Portland OR 97214",
    "addr:housenumber":"623",
    "addr:postcode":"97214",
    "addr:street":"Se 12Th Ave",
    "iso:country":"US",
    "sg:address":"623 SE 12th Ave",
    "sg:city":"Portland",
    "sg:classifiers":[
        {
            "category":"Manufacturing",
            "subcategory":"Metals",
            "type":"Manufacturing & Wholesale Goods"
        }
    ],
    "sg:phone":"+1 503 517 0336",
    "sg:postcode":"97214",
    "sg:province":"OR",
    "sg:tags":[
        "ornamental",
        "work",
        "metal-wholesale",
        "manufacturer",
        "fabrication",
        "structural"
    ],
    "sg:website":"http://www.dyadiciron.com",
    "wof:name":"Dyadic Iron Works Inc",
    "wof:placetype":"venue"
},
  "geometry": {"coordinates":[-122.653655,45.518479],"type":"Point"}
}