{
  "type": "Feature",
  "properties": {
    "iso:country":"US",
    "sg:address":"341 SE Mill St",
    "sg:city":"Dallas",
    "sg:classifiers":[
        {
            "category":"Restaurant",
            "type":"Food & Drink"
        }
    ],
    "sg:phone":"+1 503 623 7430",
    "sg:postcode":"97338",
    "sg:province":"OR",
    "sg:tags":[
        "eating"
    ],
    "wof:name":"McDonalds",
    "wof:placetype":"venue"
},
  "geometry": {"coordinates":[-123.313579,44.921444],"type":"Point"}
}