{
  "type": "Feature",
  "properties": {
    "addr:full":"2300 Broadway St Baker City OR 97814",
    "addr:housenumber":"2300",
    "addr:postcode":"97814",
    "addr:street":"Broadway St",
    "iso:country":"US",
    "sg:address":"2300 Broadway St",
    "sg:city":"Baker City",
    "sg:classifiers":[
        {
            "category":"Shopping",
            "subcategory":"Clothing, Apparel, & Fashions",
            "type":"Retail Goods"
        }
    ],
    "sg:phone":"+1 541 523 2236",
    "sg:postcode":"97814",
    "sg:province":"OR",
    "wof:name":"Wolf Star",
    "wof:placetype":"venue"
},
  "geometry": {"coordinates":[-117.835769,44.778106],"type":"Point"}
}