{
  "type": "Feature",
  "properties": {
    "iso:country":"US",
    "sg:address":"9461 SW Washington Dr",
    "sg:city":"Portland",
    "sg:classifiers":[
        {
            "category":"Food & Beverages",
            "subcategory":"Dairy",
            "type":"Retail Goods"
        }
    ],
    "sg:phone":"+1 503 639 1667",
    "sg:postcode":"97223",
    "sg:province":"OR",
    "sg:tags":[
        "product",
        "eating"
    ],
    "wof:name":"Baskin-Robbins",
    "wof:placetype":"venue"
},
  "geometry": {"coordinates":[-122.766047,45.452626],"type":"Point"}
}