{
  "type": "Feature",
  "properties": {
    "addr:full":"7475 SW 136th Ave Beaverton OR 97008",
    "addr:housenumber":"7475",
    "addr:postcode":"97008",
    "addr:street":"Sw 136Th Ave",
    "iso:country":"US",
    "sg:address":"7475 SW 136th Ave",
    "sg:city":"Beaverton",
    "sg:classifiers":[
        {
            "category":"Building & Trades",
            "subcategory":"Construction",
            "type":"Services"
        }
    ],
    "sg:phone":"+1 503 579 4620",
    "sg:postcode":"97008",
    "sg:province":"OR",
    "sg:tags":[
        "carpentry",
        "contractor"
    ],
    "wof:name":"Griffin Terr",
    "wof:placetype":"venue"
},
  "geometry": {"coordinates":[-122.81783799999999,45.466329],"type":"Point"}
}