{
  "type": "Feature",
  "properties": {
    "iso:country":"US",
    "sg:address":"710 S Oregon St",
    "sg:city":"Ontario",
    "sg:classifiers":[
        {
            "category":"Utilities",
            "subcategory":"Natural Gas",
            "type":"Services"
        }
    ],
    "sg:phone":"+1 541 889 3169",
    "sg:postcode":"97914",
    "sg:province":"OR",
    "sg:tags":[
        "transmission",
        "distribution"
    ],
    "wof:name":"Ameri Gas Inc",
    "wof:placetype":"venue"
},
  "geometry": {"coordinates":[-116.964922,44.020347],"type":"Point"}
}