{
  "type": "Feature",
  "properties": {
    "iso:country":"US",
    "sg:address":"11001 Meadows Rd",
    "sg:city":"White City",
    "sg:classifiers":[
        {
            "category":"Building & Trades",
            "subcategory":"Construction",
            "type":"Services"
        }
    ],
    "sg:phone":"+1 541 826 2364",
    "sg:postcode":"97503",
    "sg:province":"OR",
    "sg:tags":[
        "house"
    ],
    "wof:name":"Lavender Woods",
    "wof:placetype":"venue"
},
  "geometry": {"coordinates":[-122.925449,42.509449],"type":"Point"}
}