{
  "type": "Feature",
  "properties": {
    "iso:country":"US",
    "sg:address":"1409 SW Maplecrest Dr",
    "sg:city":"Portland",
    "sg:classifiers":[
        {
            "category":"Wholesale",
            "subcategory":"Computers",
            "type":"Manufacturing & Wholesale Goods"
        },
        {
            "category":"Professional",
            "subcategory":"Computer Services",
            "type":"Services"
        }
    ],
    "sg:phone":"+1 503 244 3285",
    "sg:postcode":"97219",
    "sg:province":"OR",
    "sg:tags":[
        "software",
        "repair",
        "cd-rom",
        "equipment-service",
        "equipment"
    ],
    "wof:name":"Green Wire Computer Services",
    "wof:placetype":"venue"
},
  "geometry": {"coordinates":[-122.693293,45.453084],"type":"Point"}
}