{
  "type": "Feature",
  "properties": {
    "iso:country":"US",
    "sg:address":"510 Nick Young Rd",
    "sg:city":"Eagle Point",
    "sg:classifiers":[
        {
            "category":"Building & Trades",
            "subcategory":"Construction",
            "type":"Services"
        }
    ],
    "sg:phone":"+1 541 826 9016",
    "sg:postcode":"97524",
    "sg:province":"OR",
    "sg:tags":[
        "contractor"
    ],
    "wof:name":"Jensen Fabrication",
    "wof:placetype":"venue"
},
  "geometry": {"coordinates":[-122.830886,42.461959],"type":"Point"}
}