{
  "type": "Feature",
  "properties": {
    "addr:full":"1837 NW 156th Ave Beaverton OR 97006",
    "addr:housenumber":"1837",
    "addr:postcode":"97006",
    "addr:street":"Nw 156Th Ave",
    "iso:country":"US",
    "sg:address":"1837 NW 156th Ave",
    "sg:city":"Beaverton",
    "sg:classifiers":[
        {
            "category":"Professional",
            "subcategory":"Business Services",
            "type":"Services"
        }
    ],
    "sg:phone":"+1 503 533 5311",
    "sg:postcode":"97006",
    "sg:province":"OR",
    "wof:name":"Whitefox Group",
    "wof:placetype":"venue"
},
  "geometry": {"coordinates":[-122.83667199999999,45.532959],"type":"Point"}
}