{
  "type": "Feature",
  "properties": {
    "iso:country":"US",
    "sg:address":"236 Dewey Ln",
    "sg:city":"Roseburg",
    "sg:classifiers":[
        {
            "category":"Building & Trades",
            "subcategory":"Construction",
            "type":"Services"
        }
    ],
    "sg:phone":"+1 541 679 0269",
    "sg:postcode":"97470",
    "sg:province":"OR",
    "sg:tags":[
        "house"
    ],
    "wof:name":"Johnson Jodean Building & Dev",
    "wof:placetype":"venue"
},
  "geometry": {"coordinates":[-123.34746800000001,43.121969],"type":"Point"}
}