{
  "type": "Feature",
  "properties": {
    "iso:country":"US",
    "sg:address":"92433 Leaf Court Dr",
    "sg:city":"Astoria",
    "sg:classifiers":[
        {
            "category":"Manufacturing",
            "subcategory":"Rubber & Plastics",
            "type":"Manufacturing & Wholesale Goods"
        },
        {
            "category":"Shopping",
            "subcategory":"Hobbies, Toys, & Games",
            "type":"Retail Goods"
        }
    ],
    "sg:phone":"+1 503 325 8217",
    "sg:postcode":"97103",
    "sg:province":"OR",
    "sg:tags":[
        "shop",
        "stamp",
        "model",
        "hobby",
        "supply"
    ],
    "wof:name":"Paper Moon, Astoria",
    "wof:placetype":"venue"
},
  "geometry": {"coordinates":[-123.583685,46.161092],"type":"Point"}
}