{
  "type": "Feature",
  "properties": {
    "iso:country":"US",
    "sg:address":"1240 NW Kline Pl",
    "sg:city":"Corvallis",
    "sg:classifiers":[
        {
            "category":"Home & Garden",
            "subcategory":"Building Materials",
            "type":"Retail Goods"
        }
    ],
    "sg:phone":"+1 541 754 2111",
    "sg:postcode":"97330",
    "sg:province":"OR",
    "wof:name":"Creative Glass Works LLC",
    "wof:placetype":"venue"
},
  "geometry": {"coordinates":[-123.29477799999999,44.578677],"type":"Point"}
}