{
  "type": "Feature",
  "properties": {
    "iso:country":"US",
    "sg:address":"322 NW 5th Ave Ste 305",
    "sg:city":"Portland",
    "sg:classifiers":[
        {
            "category":"Personal",
            "type":"Services"
        },
        {
            "category":"Retail",
            "subcategory":"Event Space",
            "type":"Services"
        }
    ],
    "sg:phone":"+1 503 224 6100",
    "sg:postcode":"97209",
    "sg:province":"OR",
    "sg:tags":[
        "party",
        "planning",
        "meeting"
    ],
    "wof:name":"Eventbuilders",
    "wof:placetype":"venue"
},
  "geometry": {"coordinates":[-122.675498,45.525394],"type":"Point"}
}