{
  "type": "Feature",
  "properties": {
    "iso:country":"US",
    "sg:address":"45 Thornton Rd",
    "sg:city":"Cottage Grove",
    "sg:classifiers":[
        {
            "category":"Shopping",
            "subcategory":"Bicycles & Sporting Goods",
            "type":"Retail Goods"
        }
    ],
    "sg:phone":"+1 541 942 0913",
    "sg:postcode":"97424",
    "sg:province":"OR",
    "sg:tags":[
        "sales"
    ],
    "wof:name":"Awesome Alloy",
    "wof:placetype":"venue"
},
  "geometry": {"coordinates":[-123.04057,43.797799],"type":"Point"}
}