{
  "type": "Feature",
  "properties": {
    "addr:full":"394 SW 211th Ave Beaverton OR 97006",
    "addr:housenumber":"394",
    "addr:postcode":"97006",
    "addr:street":"Sw 211Th Ave",
    "iso:country":"US",
    "sg:address":"394 SW 211th Ave",
    "sg:city":"Beaverton",
    "sg:classifiers":[
        {
            "category":"Wholesale",
            "subcategory":"Toys & Hobbies",
            "type":"Manufacturing & Wholesale Goods"
        }
    ],
    "sg:phone":"+1 503 531 8811",
    "sg:postcode":"97006",
    "sg:province":"OR",
    "wof:name":"Nelson Hobby Specialty",
    "wof:placetype":"venue"
},
  "geometry": {"coordinates":[-122.894063,45.516884],"type":"Point"}
}