{
  "type": "Feature",
  "properties": {
    "addr:full":"5300 NW 19th St Terrebonne OR 97760",
    "addr:housenumber":"5300",
    "addr:postcode":"97760",
    "addr:street":"Nw 19Th St",
    "iso:country":"US",
    "sg:address":"5300 NW 19th St",
    "sg:city":"Terrebonne",
    "sg:classifiers":[
        {
            "category":"Building & Trades",
            "subcategory":"Construction",
            "type":"Services"
        }
    ],
    "sg:phone":"+1 541 548 4955",
    "sg:postcode":"97760",
    "sg:province":"OR",
    "sg:tags":[
        "flooring",
        "contractor"
    ],
    "wof:name":"Eric Capucci",
    "wof:placetype":"venue"
},
  "geometry": {"coordinates":[-121.18556599999999,44.328784],"type":"Point"}
}