{
  "type": "Feature",
  "properties": {
    "addr:full":"29756 Hillcrest St Gold Beach OR 97444",
    "addr:housenumber":"29756",
    "addr:postcode":"97444",
    "addr:street":"Hillcrest St",
    "iso:country":"US",
    "sg:address":"29756 Hillcrest St",
    "sg:city":"Gold Beach",
    "sg:classifiers":[
        {
            "category":"Social Services",
            "type":"Services"
        }
    ],
    "sg:phone":"+1 541 247 0282",
    "sg:postcode":"97444",
    "sg:province":"OR",
    "sg:tags":[
        "counselor",
        "marriage",
        "family"
    ],
    "wof:name":"Tom Mc Kenzie",
    "wof:placetype":"venue"
},
  "geometry": {"coordinates":[-124.42178800000001,42.415089],"type":"Point"}
}