{
  "type": "Feature",
  "properties": {
    "iso:country":"US",
    "sg:address":"8835 SW Canyon Ln",
    "sg:city":"Portland",
    "sg:classifiers":[
        {
            "category":"Restaurant",
            "type":"Food & Drink"
        }
    ],
    "sg:phone":"+1 503 297 2665",
    "sg:postcode":"97225",
    "sg:province":"OR",
    "sg:tags":[
        "shop",
        "coffee"
    ],
    "wof:name":"Doctor Java Naturopathic Clnc",
    "wof:placetype":"venue"
},
  "geometry": {"coordinates":[-122.767613,45.498129],"type":"Point"}
}