{
  "type": "Feature",
  "properties": {
    "iso:country":"US",
    "sg:address":"9130 SW Pioneer Ct",
    "sg:city":"Wilsonville",
    "sg:classifiers":[
        {
            "category":"Wholesale",
            "subcategory":"Hardware",
            "type":"Manufacturing & Wholesale Goods"
        }
    ],
    "sg:phone":"+1 503 570 9610",
    "sg:postcode":"97070",
    "sg:province":"OR",
    "sg:tags":[
        "builder",
        "industrial",
        "supply"
    ],
    "wof:name":"Bell Hardware",
    "wof:placetype":"venue"
},
  "geometry": {"coordinates":[-122.771647,45.338901],"type":"Point"}
}