{
  "type": "Feature",
  "properties": {
    "addr:full":"5115 NE Sandy Boulevard Portland OR 97213",
    "addr:housenumber":"5115",
    "addr:postcode":"97213",
    "addr:street":"Ne Sandy Boulevard",
    "iso:country":"US",
    "sg:address":"5115 NE Sandy Boulevard",
    "sg:city":"Portland",
    "sg:classifiers":[
        {
            "category":"Restaurant",
            "type":"Food & Drink"
        }
    ],
    "sg:phone":"+1 503 289 8195",
    "sg:postcode":"97213",
    "sg:province":"OR",
    "wof:name":"Sylvia's Italian Restaurant & Class Act Dinner Theater",
    "wof:placetype":"venue"
},
  "geometry": {"coordinates":[-122.610567,45.539929],"type":"Point"}
}