{
  "type": "Feature",
  "properties": {
    "iso:country":"US",
    "sg:address":"115 Anderson Ave",
    "sg:city":"Coos Bay",
    "sg:classifiers":[
        {
            "category":"Shopping",
            "subcategory":"Gifts & Souvenirs",
            "type":"Retail Goods"
        }
    ],
    "sg:phone":"+1 541 266 0276",
    "sg:postcode":"97420",
    "sg:province":"OR",
    "sg:tags":[
        "shop"
    ],
    "wof:name":"Dunes Coastal Gift Store",
    "wof:placetype":"venue"
},
  "geometry": {"coordinates":[-124.21381700000001,43.367142],"type":"Point"}
}