{
  "type": "Feature",
  "properties": {
    "addr:full":"3262 N Mississippi Ave Portland OR 97227",
    "addr:housenumber":"3262",
    "addr:postcode":"97227",
    "addr:street":"N Mississippi Ave",
    "iso:country":"US",
    "sg:address":"3262 N Mississippi Ave",
    "sg:city":"Portland",
    "sg:classifiers":[
        {
            "category":"Shopping",
            "subcategory":"Clothing, Apparel, & Fashions",
            "type":"Retail Goods"
        }
    ],
    "sg:phone":"+1 503 890 0715",
    "sg:postcode":"97227",
    "sg:province":"OR",
    "sg:tags":[
        "clothing",
        "women's"
    ],
    "sg:website":"www.phloxpdx.com",
    "wof:name":"Phlox Clothing Boutique",
    "wof:placetype":"venue"
},
  "geometry": {"coordinates":[-122.675611,45.546518],"type":"Point"}
}