{
  "type": "Feature",
  "properties": {
    "iso:country":"US",
    "sg:address":"404 E Hwy 82",
    "sg:city":"Wallowa",
    "sg:classifiers":[
        {
            "category":"Retail",
            "subcategory":"Auto Repair",
            "type":"Services"
        }
    ],
    "sg:phone":"+1 541 886 4812",
    "sg:postcode":"97885",
    "sg:province":"OR",
    "sg:tags":[
        "repairing",
        "automobile"
    ],
    "wof:name":"Schaeffer Automotive Svc",
    "wof:placetype":"venue"
},
  "geometry": {"coordinates":[-117.525458,45.570067],"type":"Point"}
}