{
  "type": "Feature",
  "properties": {
    "iso:country":"US",
    "sg:address":"12905 SW Deer Oak Ln",
    "sg:city":"Beaverton",
    "sg:classifiers":[
        {
            "category":"Manufacturing",
            "subcategory":"Buildings",
            "type":"Manufacturing & Wholesale Goods"
        },
        {
            "category":"Building & Trades",
            "subcategory":"Construction",
            "type":"Services"
        }
    ],
    "sg:phone":"+1 503 746 7338",
    "sg:postcode":"97008",
    "sg:province":"OR",
    "sg:tags":[
        "altering",
        "home",
        "builder",
        "remodeling",
        "contractor"
    ],
    "wof:name":"Mountainwood Homes Inc.",
    "wof:placetype":"venue"
},
  "geometry": {"coordinates":[-122.809494,45.465679],"type":"Point"}
}