{
  "type": "Feature",
  "properties": {
    "iso:country":"US",
    "sg:address":"3284 Lancaster Dr NE",
    "sg:city":"Salem",
    "sg:classifiers":[
        {
            "category":"Banks & Credit Unions",
            "subcategory":"Bank",
            "type":"Services"
        }
    ],
    "sg:phone":"+1 503 373 9890",
    "sg:postcode":"97305",
    "sg:province":"OR",
    "sg:tags":[
        "depository",
        "banking",
        "check",
        "cashing"
    ],
    "wof:name":"Check Into Cash",
    "wof:placetype":"venue"
},
  "geometry": {"coordinates":[-122.98339900000001,44.968603],"type":"Point"}
}