{
  "type": "Feature",
  "properties": {
    "iso:country":"US",
    "sg:address":"3004 NE 28th Ave",
    "sg:city":"Portland",
    "sg:classifiers":[
        {
            "category":"Social Services",
            "type":"Services"
        }
    ],
    "sg:phone":"+1 503 475 5021",
    "sg:postcode":"97212",
    "sg:province":"OR",
    "sg:tags":[
        "organization",
        "welfare"
    ],
    "wof:name":"Red Door Events",
    "wof:placetype":"venue"
},
  "geometry": {"coordinates":[-122.63697999999999,45.544353],"type":"Point"}
}