{
  "type": "Feature",
  "properties": {
    "addr:full":"66880 Central St Bend OR 97701",
    "addr:postcode":"66880;97701",
    "addr:street":"Central St",
    "iso:country":"US",
    "sg:address":"66880 Central St",
    "sg:city":"Bend",
    "sg:classifiers":[
        {
            "category":"Building & Trades",
            "subcategory":"Landscaping Services",
            "type":"Services"
        },
        {
            "category":"Professional",
            "type":"Services"
        }
    ],
    "sg:phone":"+1 541 388 1659",
    "sg:postcode":"97701",
    "sg:province":"OR",
    "sg:tags":[
        "forestry",
        "consulting",
        "forester"
    ],
    "wof:name":"Natural Selection Photography",
    "wof:placetype":"venue"
},
  "geometry": {"coordinates":[-121.430054,44.220257],"type":"Point"}
}