{
  "type": "Feature",
  "properties": {
    "iso:country":"US",
    "sg:address":"1142 NE Roselawn St",
    "sg:city":"Portland",
    "sg:classifiers":[
        {
            "category":"Building & Trades",
            "subcategory":"Construction",
            "type":"Services"
        }
    ],
    "sg:phone":"+1 503 531 8315",
    "sg:postcode":"97211",
    "sg:province":"OR",
    "sg:tags":[
        "house"
    ],
    "wof:name":"Will Davenport",
    "wof:placetype":"venue"
},
  "geometry": {"coordinates":[-122.654188,45.561147],"type":"Point"}
}