{
  "type": "Feature",
  "properties": {
    "iso:country":"US",
    "sg:address":"137 SW Court St",
    "sg:city":"Dallas",
    "sg:classifiers":[
        {
            "category":"Professional",
            "subcategory":"Employment Agencies",
            "type":"Services"
        }
    ],
    "sg:phone":"+1 503 623 9026",
    "sg:postcode":"97338",
    "sg:province":"OR",
    "sg:tags":[
        "opportunity"
    ],
    "wof:name":"Employment Resources Northwest",
    "wof:placetype":"venue"
},
  "geometry": {"coordinates":[-123.318044,44.920412],"type":"Point"}
}