{
  "type": "Feature",
  "properties": {
    "iso:country":"US",
    "sg:address":"490 NE Yamhill St",
    "sg:city":"Willamina",
    "sg:classifiers":[
        {
            "category":"Manufacturing",
            "subcategory":"Wood Products",
            "type":"Manufacturing & Wholesale Goods"
        }
    ],
    "sg:phone":"+1 503 876 6282",
    "sg:postcode":"97396",
    "sg:province":"OR",
    "wof:name":"C R Lake Enterprises",
    "wof:placetype":"venue"
},
  "geometry": {"coordinates":[-123.479707,45.079224],"type":"Point"}
}