{
  "type": "Feature",
  "properties": {
    "addr:full":"2235 NE Diamond Lake Blvd Roseburg OR 97470",
    "addr:housenumber":"2235",
    "addr:postcode":"97470",
    "addr:street":"Ne Diamond Lake Blvd",
    "iso:country":"US",
    "sg:address":"2235 NE Diamond Lake Blvd",
    "sg:city":"Roseburg",
    "sg:classifiers":[
        {
            "category":"Shopping",
            "subcategory":"Used Merchandise",
            "type":"Retail Goods"
        }
    ],
    "sg:phone":"+1 541 464 5865",
    "sg:postcode":"97470",
    "sg:province":"OR",
    "sg:tags":[
        "resale",
        "shop"
    ],
    "wof:name":"Kid Mart",
    "wof:placetype":"venue"
},
  "geometry": {"coordinates":[-123.33011,43.213075],"type":"Point"}
}