{
  "type": "Feature",
  "properties": {
    "iso:country":"US",
    "sg:address":"1800 SW 1st Ave",
    "sg:city":"Portland",
    "sg:classifiers":[
        {
            "category":"Insurance",
            "subcategory":"Insurance Agent",
            "type":"Services"
        }
    ],
    "sg:phone":"+1 503 219 3713",
    "sg:postcode":"97201",
    "sg:province":"OR",
    "wof:name":"Prudential",
    "wof:placetype":"venue"
},
  "geometry": {"coordinates":[-122.677819,45.510072],"type":"Point"}
}