{
  "type": "Feature",
  "properties": {
    "iso:country":"US",
    "sg:address":"15910 NE Sandy Blvd",
    "sg:city":"Portland",
    "sg:classifiers":[
        {
            "category":"Real Estate",
            "subcategory":"Real Estate Operator",
            "type":"Services"
        }
    ],
    "sg:phone":"+1 503 255 4187",
    "sg:postcode":"97230",
    "sg:province":"OR",
    "sg:tags":[
        "building",
        "apartment"
    ],
    "wof:name":"Country View",
    "wof:placetype":"venue"
},
  "geometry": {"coordinates":[-122.497162,45.54967],"type":"Point"}
}