{
  "type": "Feature",
  "properties": {
    "addr:full":"14109 NE Airport Way Portland OR 97230",
    "addr:housenumber":"14109",
    "addr:postcode":"97230",
    "addr:street":"Ne Airport Way",
    "iso:country":"US",
    "sg:address":"14109 NE Airport Way",
    "sg:city":"Portland",
    "sg:classifiers":[
        {
            "category":"Retail",
            "subcategory":"Laundry & Dry Cleaning",
            "type":"Services"
        }
    ],
    "sg:phone":"+1 503 247 8228",
    "sg:postcode":"97230",
    "sg:province":"OR",
    "sg:tags":[
        "linen",
        "supply"
    ],
    "wof:name":"G&K Services Inc",
    "wof:placetype":"venue"
},
  "geometry": {"coordinates":[-122.51723800000001,45.561139],"type":"Point"}
}