{
  "type": "Feature",
  "properties": {
    "addr:full":"210 S Elm St Canby OR 97013",
    "addr:housenumber":"210",
    "addr:postcode":"97013",
    "addr:street":"S Elm St",
    "iso:country":"US",
    "sg:address":"210 S Elm St",
    "sg:city":"Canby",
    "sg:classifiers":[
        {
            "category":"Building & Trades",
            "subcategory":"Construction",
            "type":"Services"
        }
    ],
    "sg:phone":"+1 503 266 3910",
    "sg:postcode":"97013",
    "sg:province":"OR",
    "sg:tags":[
        "general",
        "contractor"
    ],
    "wof:name":"Baldwin Construction",
    "wof:placetype":"venue"
},
  "geometry": {"coordinates":[-122.69622699999999,45.258779],"type":"Point"}
}