{
  "type": "Feature",
  "properties": {
    "iso:country":"US",
    "sg:address":"6602 SE Foster Road",
    "sg:city":"Portland",
    "sg:classifiers":[
        {
            "category":"Home & Garden",
            "subcategory":"Furniture",
            "type":"Retail Goods"
        }
    ],
    "sg:phone":"+1 503 771 0551",
    "sg:postcode":"97206",
    "sg:province":"OR",
    "sg:tags":[
        "store"
    ],
    "sg:website":"www.euroclassicfurniture.com",
    "wof:name":"Euroclassic Furniture",
    "wof:placetype":"venue"
},
  "geometry": {"coordinates":[-122.59479399999999,45.488693],"type":"Point"}
}