{
  "type": "Feature",
  "properties": {
    "iso:country":"US",
    "sg:address":"98 NW Wilson Ave",
    "sg:city":"Gresham",
    "sg:classifiers":[
        {
            "category":"Professional",
            "subcategory":"Detective & Security Services",
            "type":"Services"
        }
    ],
    "sg:phone":"+1 503 665 4223",
    "sg:postcode":"97030",
    "sg:province":"OR",
    "sg:tags":[
        "control",
        "monitoring",
        "fire",
        "consultant",
        "alarm",
        "system",
        "equipment"
    ],
    "sg:website":"http://www.engineeredsystemsgroup.com",
    "wof:name":"Esg Oregon",
    "wof:placetype":"venue"
},
  "geometry": {"coordinates":[-122.44135300000001,45.498821],"type":"Point"}
}