{
  "type": "Feature",
  "properties": {
    "iso:country":"US",
    "sg:address":"23561 Vaughn Rd",
    "sg:city":"Veneta",
    "sg:classifiers":[
        {
            "category":"Building & Trades",
            "subcategory":"Construction",
            "type":"Services"
        }
    ],
    "sg:phone":"+1 541 935 0239",
    "sg:postcode":"97487",
    "sg:province":"OR",
    "sg:tags":[
        "resurfacing",
        "laying",
        "refinishing",
        "floor"
    ],
    "wof:name":"Floor Art",
    "wof:placetype":"venue"
},
  "geometry": {"coordinates":[-123.406556,44.019747],"type":"Point"}
}