{
  "type": "Feature",
  "properties": {
    "addr:full":"3081 Brown Rd NE Salem OR 97305",
    "addr:housenumber":"3081",
    "addr:postcode":"97305",
    "addr:street":"Brown Rd Ne",
    "iso:country":"US",
    "sg:address":"3081 Brown Rd NE",
    "sg:city":"Salem",
    "sg:classifiers":[
        {
            "category":"Retail",
            "subcategory":"Repair Shop",
            "type":"Services"
        }
    ],
    "sg:phone":"+1 503 399 7674",
    "sg:postcode":"97305",
    "sg:province":"OR",
    "wof:name":"Action Rv Repair",
    "wof:placetype":"venue"
},
  "geometry": {"coordinates":[-122.970725,44.965871],"type":"Point"}
}