{
  "type": "Feature",
  "properties": {
    "iso:country":"US",
    "sg:address":"175 S Main St",
    "sg:city":"Milton Freewater",
    "sg:classifiers":[
        {
            "category":"Shopping",
            "subcategory":"Discount & Variety Stores",
            "type":"Retail Goods"
        }
    ],
    "sg:phone":"+1 541 938 7863",
    "sg:postcode":"97862",
    "sg:province":"OR",
    "wof:name":"Dollar Store",
    "wof:placetype":"venue"
},
  "geometry": {"coordinates":[-118.389018,45.934072],"type":"Point"}
}