{
  "type": "Feature",
  "properties": {
    "iso:country":"US",
    "sg:address":"12647 SW 62nd Avenue",
    "sg:city":"Portland",
    "sg:classifiers":[
        {
            "category":"Education",
            "subcategory":"Preschool",
            "type":"Public Place"
        }
    ],
    "sg:phone":"+1 503 705 7745",
    "sg:postcode":"97219",
    "sg:province":"OR",
    "sg:website":"noahsplacepreschool.com/",
    "wof:name":"Noah's Place Preschool",
    "wof:placetype":"venue"
},
  "geometry": {"coordinates":[-122.741834,45.433807],"type":"Point"}
}