{
  "type": "Feature",
  "properties": {
    "addr:full":"13945 S Beavercreek Rd Oregon City OR 97045",
    "addr:housenumber":"13945",
    "addr:postcode":"97045",
    "addr:street":"S Beavercreek Rd",
    "iso:country":"US",
    "sg:address":"13945 S Beavercreek Rd",
    "sg:city":"Oregon City",
    "sg:classifiers":[
        {
            "category":"Real Estate",
            "subcategory":"Real Estate Operator",
            "type":"Services"
        }
    ],
    "sg:phone":"+1 503 657 3054",
    "sg:postcode":"97045",
    "sg:province":"OR",
    "sg:tags":[
        "apartment"
    ],
    "wof:name":"Berry Hill Apartments",
    "wof:placetype":"venue"
},
  "geometry": {"coordinates":[-122.581857,45.333027],"type":"Point"}
}