{
  "type": "Feature",
  "properties": {
    "iso:country":"US",
    "sg:address":"4930 SE 26th Ave",
    "sg:city":"Portland",
    "sg:classifiers":[
        {
            "category":"Wholesale",
            "subcategory":"Machinery & Supplies",
            "type":"Manufacturing & Wholesale Goods"
        }
    ],
    "sg:phone":"+1 503 663 4811",
    "sg:postcode":"97202",
    "sg:province":"OR",
    "wof:name":"Precision Parts Connection",
    "wof:placetype":"venue"
},
  "geometry": {"coordinates":[-122.639475,45.487798],"type":"Point"}
}