{
  "type": "Feature",
  "properties": {
    "iso:country":"US",
    "sg:address":"1995 3rd St",
    "sg:city":"Baker City",
    "sg:classifiers":[
        {
            "category":"Recreation",
            "type":"Entertainment"
        }
    ],
    "sg:phone":"+1 541 523 8342",
    "sg:postcode":"97814",
    "sg:province":"OR",
    "sg:tags":[
        "parks"
    ],
    "wof:name":"Baker County Parks",
    "wof:placetype":"venue"
},
  "geometry": {"coordinates":[-117.833322,44.77625],"type":"Point"}
}