{
  "type": "Feature",
  "properties": {
    "iso:country":"US",
    "sg:address":"1820 12th St SE",
    "sg:city":"Salem",
    "sg:classifiers":[
        {
            "category":"Autos & Motor Vehicles",
            "subcategory":"Auto Supplies",
            "type":"Retail Goods"
        }
    ],
    "sg:phone":"+1 503 581 2203",
    "sg:postcode":"97302",
    "sg:province":"OR",
    "sg:tags":[
        "tire"
    ],
    "wof:name":"O K Tire Stores",
    "wof:placetype":"venue"
},
  "geometry": {"coordinates":[-123.03059399999999,44.919099],"type":"Point"}
}