{
  "type": "Feature",
  "properties": {
    "addr:full":"1450 Molalla Ave Oregon City OR 97045",
    "addr:housenumber":"1450",
    "addr:postcode":"97045",
    "addr:street":"Molalla Ave",
    "iso:country":"US",
    "sg:address":"1450 Molalla Ave",
    "sg:city":"Oregon City",
    "sg:classifiers":[
        {
            "category":"Restaurant",
            "type":"Food & Drink"
        }
    ],
    "sg:menulink":"http://www.allmenus.com/or/northwest-clackamas/201138-mcdonalds/menu/",
    "sg:postcode":"97045",
    "sg:province":"OR",
    "sg:tags":[
        "burger",
        "american"
    ],
    "wof:name":"McDonald's",
    "wof:placetype":"venue"
},
  "geometry": {"coordinates":[-122.589765,45.334883],"type":"Point"}
}