{
  "type": "Feature",
  "properties": {
    "iso:country":"US",
    "sg:address":"1081 Broadway St NE",
    "sg:city":"Salem",
    "sg:classifiers":[
        {
            "category":"Retail",
            "subcategory":"Repair Shop",
            "type":"Services"
        }
    ],
    "sg:phone":"+1 503 585 4480",
    "sg:postcode":"97301",
    "sg:province":"OR",
    "sg:tags":[
        "appliance",
        "part",
        "electrical",
        "microwave",
        "oven"
    ],
    "sg:website":"http://www.unitedrepair.com",
    "wof:name":"United Repair Co",
    "wof:placetype":"venue"
},
  "geometry": {"coordinates":[-123.03197400000001,44.95007],"type":"Point"}
}