{
  "type": "Feature",
  "properties": {
    "iso:country":"US",
    "sg:address":"11560 Smithfield Rd",
    "sg:city":"Dallas",
    "sg:classifiers":[
        {
            "category":"Professional",
            "subcategory":"Employment Agencies",
            "type":"Services"
        }
    ],
    "sg:phone":"+1 503 623 5261",
    "sg:postcode":"97338",
    "sg:province":"OR",
    "wof:name":"Miniature Pig Registry SE",
    "wof:placetype":"venue"
},
  "geometry": {"coordinates":[-123.243669,44.98385],"type":"Point"}
}