{
  "type": "Feature",
  "properties": {
    "addr:full":"1455 E Briarcliff Ln Eugene OR 97404",
    "addr:housenumber":"1455",
    "addr:postcode":"97404",
    "addr:street":"E Briarcliff Ln",
    "iso:country":"US",
    "sg:address":"1455 E Briarcliff Ln",
    "sg:city":"Eugene",
    "sg:classifiers":[
        {
            "category":"Organizations",
            "subcategory":"Community Association",
            "type":"Services"
        }
    ],
    "sg:phone":"+1 541 688 2600",
    "sg:postcode":"97404",
    "sg:province":"OR",
    "sg:tags":[
        "environmental",
        "org"
    ],
    "sg:website":"www.honested.org",
    "wof:name":"Native Forest Council",
    "wof:placetype":"venue"
},
  "geometry": {"coordinates":[-123.115329,44.066526],"type":"Point"}
}