{
  "type": "Feature",
  "properties": {
    "iso:country":"US",
    "sg:address":"1935 Valhalla St",
    "sg:city":"Eugene",
    "sg:classifiers":[
        {
            "category":"Social Services",
            "subcategory":"Job Training",
            "type":"Services"
        }
    ],
    "sg:phone":"+1 541 344 2786",
    "sg:postcode":"97401",
    "sg:province":"OR",
    "sg:tags":[
        "nursing",
        "homes-skilled",
        "facility"
    ],
    "wof:name":"Elderhaven Adult Care Home",
    "wof:placetype":"venue"
},
  "geometry": {"coordinates":[-123.069417,44.083319],"type":"Point"}
}