{
  "type": "Feature",
  "properties": {
    "iso:country":"US",
    "sg:address":"15060 NW Central Dr",
    "sg:city":"Portland",
    "sg:classifiers":[
        {
            "category":"Professional",
            "subcategory":"Research",
            "type":"Services"
        }
    ],
    "sg:phone":"+1 503 970 9862",
    "sg:postcode":"97229",
    "sg:province":"OR",
    "sg:tags":[
        "device",
        "information",
        "medical"
    ],
    "wof:name":"Capatheter Systems",
    "wof:placetype":"venue"
},
  "geometry": {"coordinates":[-122.831869,45.55361],"type":"Point"}
}