{
  "type": "Feature",
  "properties": {
    "iso:country":"US",
    "sg:address":"19200 NE Calkins Ln",
    "sg:city":"Newberg",
    "sg:classifiers":[
        {
            "category":"Manufacturing",
            "subcategory":"Food",
            "type":"Manufacturing & Wholesale Goods"
        }
    ],
    "sg:phone":"+1 503 537 0750",
    "sg:postcode":"97132",
    "sg:province":"OR",
    "sg:tags":[
        "winery"
    ],
    "wof:name":"Mia Jove' Cellars LLC",
    "wof:placetype":"venue"
},
  "geometry": {"coordinates":[-123.049282,45.355486],"type":"Point"}
}