{
  "type": "Feature",
  "properties": {
    "addr:full":"15812 NE Stanton St Portland OR 97230",
    "addr:housenumber":"15812",
    "addr:postcode":"97230",
    "addr:street":"Ne Stanton St",
    "iso:country":"US",
    "sg:address":"15812 NE Stanton St",
    "sg:city":"Portland",
    "sg:classifiers":[
        {
            "category":"Building & Trades",
            "subcategory":"Construction",
            "type":"Services"
        }
    ],
    "sg:phone":"+1 503 253 9630",
    "sg:postcode":"97230",
    "sg:province":"OR",
    "sg:tags":[
        "excavation",
        "grading",
        "contractor"
    ],
    "wof:name":"Rick Myron Bulldozing & Bldg",
    "wof:placetype":"venue"
},
  "geometry": {"coordinates":[-122.499137,45.543947],"type":"Point"}
}