{
  "type": "Feature",
  "properties": {
    "iso:country":"US",
    "sg:address":"200 S Detroit Ave",
    "sg:city":"Detroit",
    "sg:classifiers":[
        {
            "category":"Organizations",
            "subcategory":"Religious Organization",
            "type":"Services"
        }
    ],
    "sg:phone":"+1 503 854 3021",
    "sg:postcode":"97342",
    "sg:province":"OR",
    "sg:tags":[
        "church"
    ],
    "wof:name":"Detroit Community Church",
    "wof:placetype":"venue"
},
  "geometry": {"coordinates":[-122.15104,44.734269],"type":"Point"}
}