{
  "type": "Feature",
  "properties": {
    "iso:country":"US",
    "sg:address":"2601 NW Thurman St",
    "sg:city":"Portland",
    "sg:classifiers":[
        {
            "category":"Communications",
            "subcategory":"Newspaper",
            "type":"Services"
        }
    ],
    "sg:phone":"+1 503 219 0622",
    "sg:postcode":"97210",
    "sg:province":"OR",
    "sg:tags":[
        "print",
        "medium"
    ],
    "wof:name":"Tin House Magazine",
    "wof:placetype":"venue"
},
  "geometry": {"coordinates":[-122.70500199999999,45.535301],"type":"Point"}
}