{
  "type": "Feature",
  "properties": {
    "iso:country":"US",
    "sg:address":"205 Fern Valley Rd",
    "sg:city":"Phoenix",
    "sg:classifiers":[
        {
            "category":"Shopping",
            "subcategory":"Discount & Variety Stores",
            "type":"Retail Goods"
        }
    ],
    "sg:phone":"+1 541 535 1194",
    "sg:postcode":"97535",
    "sg:province":"OR",
    "sg:tags":[
        "merchandise",
        "general"
    ],
    "wof:name":"Pacific NW Mrktplace Outl Mlls",
    "wof:placetype":"venue"
},
  "geometry": {"coordinates":[-122.81925699999999,42.280367],"type":"Point"}
}