{
  "type": "Feature",
  "properties": {
    "addr:full":"6687 Tolo Rd Central Point OR 97502",
    "addr:housenumber":"6687",
    "addr:postcode":"97502",
    "addr:street":"Tolo Rd",
    "iso:country":"US",
    "sg:address":"6687 Tolo Rd",
    "sg:city":"Central Point",
    "sg:classifiers":[
        {
            "category":"Building & Trades",
            "subcategory":"Construction",
            "type":"Services"
        }
    ],
    "sg:phone":"+1 541 665 5415",
    "sg:postcode":"97502",
    "sg:province":"OR",
    "sg:tags":[
        "electrician"
    ],
    "sg:website":"www.keylineconstruction.com",
    "wof:name":"Key Line Construction",
    "wof:placetype":"venue"
},
  "geometry": {"coordinates":[-122.962997,42.412201],"type":"Point"}
}