{
  "type": "Feature",
  "properties": {
    "iso:country":"US",
    "sg:address":"2021 Main St",
    "sg:city":"Baker City",
    "sg:classifiers":[
        {
            "category":"Wholesale",
            "subcategory":"Stationery",
            "type":"Manufacturing & Wholesale Goods"
        }
    ],
    "sg:phone":"+1 541 523 8925",
    "sg:postcode":"97814",
    "sg:province":"OR",
    "sg:tags":[
        "mapping"
    ],
    "wof:name":"TCI Software",
    "wof:placetype":"venue"
},
  "geometry": {"coordinates":[-117.829883,44.777925],"type":"Point"}
}