{
  "type": "Feature",
  "properties": {
    "iso:country":"US",
    "sg:address":"4904 SE Hawthorne Blvd",
    "sg:city":"Portland",
    "sg:classifiers":[
        {
            "category":"Organizations",
            "subcategory":"Community Association",
            "type":"Services"
        }
    ],
    "sg:phone":"+1 503 232 7505",
    "sg:postcode":"97215",
    "sg:province":"OR",
    "wof:name":"Foe 3256",
    "wof:placetype":"venue"
},
  "geometry": {"coordinates":[-122.611519,45.511936],"type":"Point"}
}