{
  "type": "Feature",
  "properties": {
    "addr:full":"4298 SE Belmont St Portland OR 97215",
    "addr:housenumber":"4298",
    "addr:postcode":"97215",
    "addr:street":"Se Belmont St",
    "iso:country":"US",
    "sg:address":"4298 SE Belmont St",
    "sg:city":"Portland",
    "sg:classifiers":[
        {
            "category":"Food Court",
            "type":"Food & Drink"
        },
        {
            "category":"Restaurant",
            "type":"Food & Drink"
        }
    ],
    "sg:postcode":"97215",
    "sg:province":"OR",
    "sg:tags":[
        "mediterranean",
        "stand"
    ],
    "sg:website":"www.facebook.com/eurotrashcart",
    "wof:name":"EuroTrash FoodCart",
    "wof:placetype":"venue"
},
  "geometry": {"coordinates":[-122.61779900000001,45.516547],"type":"Point"}
}