{
  "type": "Feature",
  "properties": {
    "addr:full":"973 Mistletoe Loop N Salem OR 97303",
    "addr:housenumber":"973",
    "addr:postcode":"97303",
    "addr:street":"Mistletoe Loop N",
    "iso:country":"US",
    "sg:address":"973 Mistletoe Loop N",
    "sg:city":"Salem",
    "sg:classifiers":[
        {
            "category":"Building & Trades",
            "subcategory":"Construction",
            "type":"Services"
        }
    ],
    "sg:phone":"+1 503 393 8201",
    "sg:postcode":"97303",
    "sg:province":"OR",
    "wof:name":"All Lined Up Striping",
    "wof:placetype":"venue"
},
  "geometry": {"coordinates":[-123.024192,45.013411],"type":"Point"}
}