{
  "type": "Feature",
  "properties": {
    "addr:full":"411 SW 2nd Ave Portland OR 97204",
    "addr:housenumber":"411",
    "addr:postcode":"97204",
    "addr:street":"Sw 2Nd Ave",
    "iso:country":"US",
    "sg:address":"411 SW 2nd Ave",
    "sg:city":"Portland",
    "sg:classifiers":[
        {
            "category":"Professional",
            "subcategory":"Research",
            "type":"Services"
        }
    ],
    "sg:phone":"+1 503 248 4764",
    "sg:postcode":"97204",
    "sg:province":"OR",
    "sg:tags":[
        "development",
        "marketing",
        "product"
    ],
    "sg:website":"www.fioriinc.com",
    "wof:name":"Fiori",
    "wof:placetype":"venue"
},
  "geometry": {"coordinates":[-122.673748,45.519676],"type":"Point"}
}