{
  "type": "Feature",
  "properties": {
    "iso:country":"US",
    "sg:address":"2151 Corona Ave",
    "sg:city":"Medford",
    "sg:classifiers":[
        {
            "category":"Building & Trades",
            "subcategory":"Construction",
            "type":"Services"
        }
    ],
    "sg:phone":"+1 541 734 7018",
    "sg:postcode":"97504",
    "sg:province":"OR",
    "sg:tags":[
        "carpet",
        "installation",
        "vinyl",
        "contractor"
    ],
    "wof:name":"Wesley Converse Floor Covering",
    "wof:placetype":"venue"
},
  "geometry": {"coordinates":[-122.865454,42.348695],"type":"Point"}
}