{
  "type": "Feature",
  "properties": {
    "iso:country":"US",
    "sg:address":"35970 7th St",
    "sg:city":"Nehalem",
    "sg:classifiers":[
        {
            "category":"Personal",
            "type":"Services"
        }
    ],
    "sg:phone":"+1 503 368 4494",
    "sg:postcode":"97131",
    "sg:province":"OR",
    "sg:tags":[
        "therapist",
        "massage"
    ],
    "wof:name":"Golden Wave Massage",
    "wof:placetype":"venue"
},
  "geometry": {"coordinates":[-123.894088,45.716976],"type":"Point"}
}