{
  "type": "Feature",
  "properties": {
    "iso:country":"US",
    "sg:address":"2741 Bunker Hill Rd S",
    "sg:city":"Salem",
    "sg:classifiers":[
        {
            "category":"Professional",
            "subcategory":"Business Services",
            "type":"Services"
        }
    ],
    "sg:phone":"+1 503 391 6516",
    "sg:postcode":"97306",
    "sg:province":"OR",
    "sg:tags":[
        "trade",
        "exposition",
        "fair",
        "show"
    ],
    "wof:name":"Continental Exhibitors",
    "wof:placetype":"venue"
},
  "geometry": {"coordinates":[-123.084791,44.828782],"type":"Point"}
}