{
  "type": "Feature",
  "properties": {
    "iso:country":"US",
    "sg:address":"56768 Nehalem Hwy S",
    "sg:city":"Vernonia",
    "sg:classifiers":[
        {
            "category":"Sports & Exercise",
            "subcategory":"Race Track",
            "type":"Entertainment"
        }
    ],
    "sg:phone":"+1 503 429 0499",
    "sg:postcode":"97064",
    "sg:province":"OR",
    "wof:name":"Potter Racing Chassis",
    "wof:placetype":"venue"
},
  "geometry": {"coordinates":[-123.231443,45.810732],"type":"Point"}
}