{
  "type": "Feature",
  "properties": {
    "addr:full":"32175 Viewcrest Dr Warren OR 97053",
    "addr:postcode":"32175;97053",
    "addr:street":"Viewcrest Dr",
    "iso:country":"US",
    "sg:address":"32175 Viewcrest Dr",
    "sg:city":"Warren",
    "sg:classifiers":[
        {
            "category":"Professional",
            "subcategory":"Business Services",
            "type":"Services"
        }
    ],
    "sg:phone":"+1 503 543 5454",
    "sg:postcode":"97053",
    "sg:province":"OR",
    "wof:name":"Interiors By Design",
    "wof:placetype":"venue"
},
  "geometry": {"coordinates":[-122.895752,45.802314],"type":"Point"}
}