{
  "type": "Feature",
  "properties": {
    "addr:full":"5627 SW Arctic Dr Beaverton OR 97005",
    "addr:housenumber":"5627",
    "addr:postcode":"97005",
    "addr:street":"Sw Arctic Dr",
    "iso:country":"US",
    "sg:address":"5627 SW Arctic Dr",
    "sg:city":"Beaverton",
    "sg:classifiers":[
        {
            "category":"Wholesale",
            "subcategory":"Auto Parts",
            "type":"Manufacturing & Wholesale Goods"
        }
    ],
    "sg:phone":"+1 503 644 3767",
    "sg:postcode":"97005",
    "sg:province":"OR",
    "sg:website":"www.industrialfinishes.com",
    "wof:name":"Industrial Finishes & Systems",
    "wof:placetype":"venue"
},
  "geometry": {"coordinates":[-122.778676,45.478897],"type":"Point"}
}