{
  "type": "Feature",
  "properties": {
    "iso:country":"US",
    "sg:address":"8751 SW Pamlico Ct",
    "sg:city":"Tualatin",
    "sg:classifiers":[
        {
            "category":"Manufacturing",
            "subcategory":"Building Materials",
            "type":"Manufacturing & Wholesale Goods"
        }
    ],
    "sg:phone":"+1 503 692 8105",
    "sg:postcode":"97062",
    "sg:province":"OR",
    "sg:tags":[
        "joinery",
        "parts",
        "stair"
    ],
    "wof:name":"Westfire",
    "wof:placetype":"venue"
},
  "geometry": {"coordinates":[-122.76719,45.36633],"type":"Point"}
}