{
  "type": "Feature",
  "properties": {
    "addr:full":"12141 SE Division Street Portland OR 97266",
    "addr:postcode":"12141;97266",
    "addr:street":"Se Division Street",
    "iso:country":"US",
    "sg:address":"12141 SE Division Street",
    "sg:city":"Portland",
    "sg:classifiers":[
        {
            "category":"Autos & Motor Vehicles",
            "subcategory":"Auto Supplies",
            "type":"Retail Goods"
        },
        {
            "category":"Retail",
            "subcategory":"Auto Repair",
            "type":"Services"
        }
    ],
    "sg:phone":"+1 503 761 7632",
    "sg:postcode":"97266",
    "sg:province":"OR",
    "sg:tags":[
        "tire"
    ],
    "wof:name":"Firestone Tire & Service Centers",
    "wof:placetype":"venue"
},
  "geometry": {"coordinates":[-122.53806899999999,45.504205],"type":"Point"}
}