{
  "type": "Feature",
  "properties": {
    "addr:full":"1800 S 28th Ct Coos Bay OR 97420",
    "addr:housenumber":"1800",
    "addr:postcode":"97420",
    "addr:street":"S 28Th Ct",
    "iso:country":"US",
    "sg:address":"1800 S 28th Ct",
    "sg:city":"Coos Bay",
    "sg:classifiers":[
        {
            "category":"Travel",
            "subcategory":"Campground",
            "type":"Entertainment"
        }
    ],
    "sg:phone":"+1 541 269 0999",
    "sg:postcode":"97420",
    "sg:province":"OR",
    "sg:tags":[
        "recreational",
        "trailer",
        "parks",
        "vehicle"
    ],
    "wof:name":"Alder Acres Rv Park",
    "wof:placetype":"venue"
},
  "geometry": {"coordinates":[-124.246504,43.379939],"type":"Point"}
}