{
  "type": "Feature",
  "properties": {
    "iso:country":"US",
    "sg:address":"1236 Disk Dr",
    "sg:city":"Medford",
    "sg:classifiers":[
        {
            "category":"Communications",
            "subcategory":"Radio Station",
            "type":"Services"
        }
    ],
    "sg:phone":"+1 541 776 5368",
    "sg:postcode":"97501",
    "sg:province":"OR",
    "sg:tags":[
        "company",
        "broadcasting"
    ],
    "wof:name":"KDOV",
    "wof:placetype":"venue"
},
  "geometry": {"coordinates":[-122.894901,42.33757],"type":"Point"}
}