{
  "type": "Feature",
  "properties": {
    "iso:country":"US",
    "sg:address":"3215 SW Grace Ln",
    "sg:city":"Portland",
    "sg:classifiers":[
        {
            "category":"Professional",
            "subcategory":"Management & Consulting",
            "type":"Services"
        }
    ],
    "sg:phone":"+1 503 296 4913",
    "sg:postcode":"97225",
    "sg:province":"OR",
    "sg:tags":[
        "retail",
        "direct",
        "sales"
    ],
    "wof:name":"Richard Kaiser",
    "wof:placetype":"venue"
},
  "geometry": {"coordinates":[-122.753421,45.498032],"type":"Point"}
}