{
  "type": "Feature",
  "properties": {
    "iso:country":"US",
    "sg:address":"21512 SE Stark St",
    "sg:city":"Gresham",
    "sg:classifiers":[
        {
            "category":"Education",
            "subcategory":"Special Training",
            "type":"Public Place"
        }
    ],
    "sg:phone":"+1 503 489 0761",
    "sg:postcode":"97030",
    "sg:province":"OR",
    "sg:tags":[
        "educational"
    ],
    "wof:name":"Northwest Educational Training",
    "wof:placetype":"venue"
},
  "geometry": {"coordinates":[-122.440275,45.519015],"type":"Point"}
}