{
  "type": "Feature",
  "properties": {
    "iso:country":"US",
    "sg:address":"2080 NW Stewart Pkwy",
    "sg:city":"Roseburg",
    "sg:classifiers":[
        {
            "category":"Banks & Credit Unions",
            "subcategory":"Bank",
            "type":"Services"
        }
    ],
    "sg:phone":"+1 541 673 2421",
    "sg:postcode":"97470",
    "sg:province":"OR",
    "sg:website":"www.usbank.com",
    "wof:name":"US Bank",
    "wof:placetype":"venue"
},
  "geometry": {"coordinates":[-123.372395,43.233273],"type":"Point"}
}