{
  "type": "Feature",
  "properties": {
    "addr:full":"5321 SE 64th Ave Portland OR 97206",
    "addr:housenumber":"5321",
    "addr:postcode":"97206",
    "addr:street":"Se 64Th Ave",
    "iso:country":"US",
    "sg:address":"5321 SE 64th Ave",
    "sg:city":"Portland",
    "sg:classifiers":[
        {
            "category":"Professional",
            "subcategory":"Advertising",
            "type":"Services"
        }
    ],
    "sg:phone":"+1 503 788 5293",
    "sg:postcode":"97206",
    "sg:province":"OR",
    "wof:name":"Rainbow Digitizing Embroidery",
    "wof:placetype":"venue"
},
  "geometry": {"coordinates":[-122.597691,45.483692],"type":"Point"}
}