{
  "type": "Feature",
  "properties": {
    "addr:full":"4235 SE Schiller St Portland OR 97206",
    "addr:housenumber":"4235",
    "addr:postcode":"97206",
    "addr:street":"Se Schiller St",
    "iso:country":"US",
    "sg:address":"4235 SE Schiller St",
    "sg:city":"Portland",
    "sg:classifiers":[
        {
            "category":"Building & Trades",
            "subcategory":"Construction",
            "type":"Services"
        }
    ],
    "sg:phone":"+1 503 777 3363",
    "sg:postcode":"97206",
    "sg:province":"OR",
    "sg:tags":[
        "drywall",
        "dry wall",
        "contractor"
    ],
    "wof:name":"Ron Rust Drywall Inc",
    "wof:placetype":"venue"
},
  "geometry": {"coordinates":[-122.620368,45.488096],"type":"Point"}
}