{
  "type": "Feature",
  "properties": {
    "addr:full":"5245 NE Elam Young Pkwy Hillsboro OR 97124",
    "addr:housenumber":"5245",
    "addr:postcode":"97124",
    "addr:street":"Ne Elam Young Pkwy",
    "iso:country":"US",
    "sg:address":"5245 NE Elam Young Pkwy",
    "sg:city":"Hillsboro",
    "sg:classifiers":[
        {
            "category":"Manufacturing",
            "subcategory":"Printing",
            "type":"Manufacturing & Wholesale Goods"
        }
    ],
    "sg:phone":"+1 503 844 4960",
    "sg:postcode":"97124",
    "sg:province":"OR",
    "sg:tags":[
        "publisher"
    ],
    "sg:website":"www.binfordandmort.com",
    "wof:name":"Binford & Mort Publishing",
    "wof:placetype":"venue"
},
  "geometry": {"coordinates":[-122.930679,45.527841],"type":"Point"}
}