{
  "type": "Feature",
  "properties": {
    "addr:full":"1195 SE 36th St Troutdale OR 97060",
    "addr:housenumber":"1195",
    "addr:postcode":"97060",
    "addr:street":"Se 36Th St",
    "iso:country":"US",
    "sg:address":"1195 SE 36th St",
    "sg:city":"Troutdale",
    "sg:classifiers":[
        {
            "category":"Professional",
            "subcategory":"Accounting & Tax Preparation",
            "type":"Services"
        }
    ],
    "sg:phone":"+1 503 665 8286",
    "sg:postcode":"97060",
    "sg:province":"OR",
    "wof:name":"Northwest Resource Management",
    "wof:placetype":"venue"
},
  "geometry": {"coordinates":[-122.37749599999999,45.515228],"type":"Point"}
}