{
  "type": "Feature",
  "properties": {
    "iso:country":"US",
    "sg:address":"700 SW Stark St",
    "sg:city":"Portland",
    "sg:classifiers":[
        {
            "category":"Retail",
            "subcategory":"Laundry & Dry Cleaning",
            "type":"Services"
        }
    ],
    "sg:phone":"+1 503 226 1977",
    "sg:postcode":"97205",
    "sg:province":"OR",
    "sg:tags":[
        "cleaner",
        "rug",
        "carpet"
    ],
    "wof:name":"Chem-Dry",
    "wof:placetype":"venue"
},
  "geometry": {"coordinates":[-122.678551,45.521351],"type":"Point"}
}