{
  "type": "Feature",
  "properties": {
    "iso:country":"US",
    "sg:address":"3930 NW Susbauer Rd",
    "sg:city":"Cornelius",
    "sg:classifiers":[
        {
            "category":"Building & Trades",
            "subcategory":"Construction",
            "type":"Services"
        }
    ],
    "sg:phone":"+1 503 310 6993",
    "sg:postcode":"97113",
    "sg:province":"OR",
    "sg:tags":[
        "wallcoverings-installation",
        "wallpaper",
        "painting",
        "contractor"
    ],
    "sg:website":"http://www.monicaf.com",
    "wof:name":"Positively Paint",
    "wof:placetype":"venue"
},
  "geometry": {"coordinates":[-123.038787,45.546612],"type":"Point"}
}