{
  "type": "Feature",
  "properties": {
    "addr:full":"36996 Hwy 245 Baker City OR 97814",
    "addr:housenumber":"36996",
    "addr:postcode":"97814",
    "addr:street":"Hwy 245",
    "iso:country":"US",
    "sg:address":"36996 Hwy 245",
    "sg:city":"Baker City",
    "sg:classifiers":[
        {
            "category":"Building & Trades",
            "subcategory":"Construction",
            "type":"Services"
        }
    ],
    "sg:phone":"+1 541 523 7326",
    "sg:postcode":"97814",
    "sg:province":"OR",
    "sg:tags":[
        "excavation",
        "contractor",
        "general"
    ],
    "wof:name":"Floyd Morgan Excavating",
    "wof:placetype":"venue"
},
  "geometry": {"coordinates":[-117.868358,44.64057],"type":"Point"}
}