{
  "type": "Feature",
  "properties": {
    "iso:country":"US",
    "sg:address":"439 Pyle Dr",
    "sg:city":"Grants Pass",
    "sg:classifiers":[
        {
            "category":"Building & Trades",
            "subcategory":"Construction",
            "type":"Services"
        }
    ],
    "sg:phone":"+1 541 956 1280",
    "sg:postcode":"97527",
    "sg:province":"OR",
    "sg:tags":[
        "nonresidential"
    ],
    "wof:name":"Jab 3 Co",
    "wof:placetype":"venue"
},
  "geometry": {"coordinates":[-123.38761,42.394707],"type":"Point"}
}