{
  "type": "Feature",
  "properties": {
    "iso:country":"US",
    "sg:address":"994 Antelope Rd",
    "sg:city":"White City",
    "sg:classifiers":[
        {
            "category":"Professional",
            "subcategory":"Management & Consulting",
            "type":"Services"
        }
    ],
    "sg:phone":"+1 541 826 2405",
    "sg:postcode":"97503",
    "sg:province":"OR",
    "sg:tags":[
        "manufacturing",
        "business"
    ],
    "wof:name":"Ascentron Inc",
    "wof:placetype":"venue"
},
  "geometry": {"coordinates":[-122.875831,42.427289],"type":"Point"}
}