{
  "type": "Feature",
  "properties": {
    "addr:full":"11817 NW Blackhawk Dr Portland OR 97229",
    "addr:housenumber":"11817",
    "addr:postcode":"97229",
    "addr:street":"Nw Blackhawk Dr",
    "iso:country":"US",
    "sg:address":"11817 NW Blackhawk Dr",
    "sg:city":"Portland",
    "sg:classifiers":[
        {
            "category":"Wholesale",
            "subcategory":"Electrical",
            "type":"Manufacturing & Wholesale Goods"
        }
    ],
    "sg:phone":"+1 503 531 9361",
    "sg:postcode":"97229",
    "sg:province":"OR",
    "sg:tags":[
        "international",
        "product",
        "trading"
    ],
    "wof:name":"Kte Technologies",
    "wof:placetype":"venue"
},
  "geometry": {"coordinates":[-122.79823500000001,45.542148],"type":"Point"}
}