{
  "type": "Feature",
  "properties": {
    "iso:country":"US",
    "sg:address":"SE 16th Ave & Harrison St",
    "sg:city":"Portland",
    "sg:classifiers":[
        {
            "category":"Park",
            "type":"Public Place"
        }
    ],
    "sg:postcode":"97214",
    "sg:province":"OR",
    "sg:website":"www.portlandonline.com/parks/fin...",
    "wof:name":"Ladd's Circle & Squares",
    "wof:placetype":"venue"
},
  "geometry": {"coordinates":[-122.649002,45.508499],"type":"Point"}
}