{
  "type": "Feature",
  "properties": {
    "addr:full":"29382 SW Glacier Way Wilsonville OR 97070",
    "addr:housenumber":"29382",
    "addr:postcode":"97070",
    "addr:street":"Sw Glacier Way",
    "iso:country":"US",
    "sg:address":"29382 SW Glacier Way",
    "sg:city":"Wilsonville",
    "sg:classifiers":[
        {
            "category":"Professional",
            "subcategory":"Computer Services",
            "type":"Services"
        }
    ],
    "sg:phone":"+1 503 682 8886",
    "sg:postcode":"97070",
    "sg:province":"OR",
    "sg:tags":[
        "datum"
    ],
    "wof:name":"Josh Williams Web Design",
    "wof:placetype":"venue"
},
  "geometry": {"coordinates":[-122.787752,45.306698],"type":"Point"}
}