{
  "type": "Feature",
  "properties": {
    "iso:country":"US",
    "sg:address":"7180 SW Fir Loop",
    "sg:city":"Tigard",
    "sg:classifiers":[
        {
            "category":"Professional",
            "subcategory":"Employment Agencies",
            "type":"Services"
        }
    ],
    "sg:phone":"+1 503 684 1305",
    "sg:postcode":"97223",
    "sg:province":"OR",
    "sg:tags":[
        "help",
        "contractor"
    ],
    "wof:name":"North American Contract",
    "wof:placetype":"venue"
},
  "geometry": {"coordinates":[-122.75095,45.423215],"type":"Point"}
}