{
  "type": "Feature",
  "properties": {
    "iso:country":"US",
    "sg:address":"970 W 12th Ave",
    "sg:city":"Junction City",
    "sg:classifiers":[
        {
            "category":"Professional",
            "type":"Services"
        }
    ],
    "sg:phone":"+1 541 998 5633",
    "sg:postcode":"97448",
    "sg:province":"OR",
    "wof:name":"Faithworks",
    "wof:placetype":"venue"
},
  "geometry": {"coordinates":[-123.210887,44.224173],"type":"Point"}
}