{
  "type": "Feature",
  "properties": {
    "addr:full":"9150 SW Lehman St Portland OR 97223",
    "addr:housenumber":"9150",
    "addr:postcode":"97223",
    "addr:street":"Sw Lehman St",
    "iso:country":"US",
    "sg:address":"9150 SW Lehman St",
    "sg:city":"Portland",
    "sg:classifiers":[
        {
            "category":"Food & Beverages",
            "subcategory":"Specialty",
            "type":"Retail Goods"
        },
        {
            "category":"Food & Beverages",
            "subcategory":"Groceries & Convenience Stores",
            "type":"Retail Goods"
        }
    ],
    "sg:phone":"+1 503 293 0472",
    "sg:postcode":"97223",
    "sg:province":"OR",
    "sg:tags":[
        "grocers-specialty"
    ],
    "wof:name":"Vancouver Oriental Market",
    "wof:placetype":"venue"
},
  "geometry": {"coordinates":[-122.77081699999999,45.44912],"type":"Point"}
}