{
  "type": "Feature",
  "properties": {
    "iso:country":"US",
    "sg:address":"5533 NW Campbell Rd",
    "sg:city":"Madras",
    "sg:classifiers":[
        {
            "category":"Farming",
            "subcategory":"Livestock Farm",
            "type":"Manufacturing & Wholesale Goods"
        }
    ],
    "sg:phone":"+1 541 475 4525",
    "sg:postcode":"97741",
    "sg:province":"OR",
    "sg:tags":[
        "beef",
        "feedlot",
        "cattle"
    ],
    "wof:name":"3 R Ranch",
    "wof:placetype":"venue"
},
  "geometry": {"coordinates":[-121.22589000000001,44.716428],"type":"Point"}
}