{
  "type": "Feature",
  "properties": {
    "iso:country":"US",
    "sg:address":"2870 SW Cedar Hills Blvd",
    "sg:city":"Beaverton",
    "sg:classifiers":[
        {
            "category":"Health Services",
            "subcategory":"Doctor",
            "type":"Services"
        }
    ],
    "sg:phone":"+1 503 646 9222",
    "sg:postcode":"97005",
    "sg:province":"OR",
    "sg:tags":[
        "physician",
        "family",
        "practice",
        "surgeons",
        "medicine",
        "surgeon"
    ],
    "wof:name":"Schwartz Benjamin",
    "wof:placetype":"venue"
},
  "geometry": {"coordinates":[-122.806999,45.4991],"type":"Point"}
}