{
  "type": "Feature",
  "properties": {
    "addr:full":"19575 Decora Ln Hillsboro OR 97124",
    "addr:housenumber":"19575",
    "addr:postcode":"97124",
    "addr:street":"Decora Ln",
    "iso:country":"US",
    "sg:address":"19575 Decora Ln",
    "sg:city":"Hillsboro",
    "sg:classifiers":[
        {
            "category":"Professional",
            "subcategory":"Computer Services",
            "type":"Services"
        }
    ],
    "sg:phone":"+1 503 466 5367",
    "sg:postcode":"97124",
    "sg:province":"OR",
    "sg:tags":[
        "prepackaged",
        "software"
    ],
    "wof:name":"Software Innovation Consulting",
    "wof:placetype":"venue"
},
  "geometry": {"coordinates":[-122.879801,45.540674],"type":"Point"}
}