{
  "type": "Feature",
  "properties": {
    "iso:country":"US",
    "sg:address":"550 S State St",
    "sg:city":"Sutherlin",
    "sg:classifiers":[
        {
            "category":"Food & Beverages",
            "subcategory":"Groceries & Convenience Stores",
            "type":"Retail Goods"
        }
    ],
    "sg:phone":"+1 541 459 4681",
    "sg:postcode":"97479",
    "sg:province":"OR",
    "sg:tags":[
        "meat",
        "market"
    ],
    "wof:name":"Culvers",
    "wof:placetype":"venue"
},
  "geometry": {"coordinates":[-123.311476,43.384296],"type":"Point"}
}