{
  "type": "Feature",
  "properties": {
    "addr:full":"1121 US Hwy 101 Lincoln City OR 97367",
    "addr:housenumber":"1121",
    "addr:postcode":"97367",
    "addr:street":"Us Hwy 101",
    "iso:country":"US",
    "sg:address":"1121 US Hwy 101",
    "sg:city":"Lincoln City",
    "sg:classifiers":[
        {
            "category":"Building & Trades",
            "subcategory":"Construction",
            "type":"Services"
        }
    ],
    "sg:phone":"+1 541 994 2920",
    "sg:postcode":"97367",
    "sg:province":"OR",
    "sg:tags":[
        "excavating",
        "contractor"
    ],
    "wof:name":"Drayton Excavating & Trucking",
    "wof:placetype":"venue"
},
  "geometry": {"coordinates":[-124.013518,44.973762],"type":"Point"}
}