{
  "type": "Feature",
  "properties": {
    "iso:country":"US",
    "sg:address":"2330 Church St SE",
    "sg:city":"Salem",
    "sg:classifiers":[
        {
            "category":"Social Services",
            "type":"Services"
        }
    ],
    "sg:phone":"+1 503 365 0042",
    "sg:postcode":"97302",
    "sg:province":"OR",
    "wof:name":"Andean Ctr For Latin American",
    "wof:placetype":"venue"
},
  "geometry": {"coordinates":[-123.040321,44.918845],"type":"Point"}
}