{
  "type": "Feature",
  "properties": {
    "iso:country":"US",
    "sg:address":"9295 72nd Ave NE",
    "sg:city":"Salem",
    "sg:classifiers":[
        {
            "category":"Wholesale",
            "subcategory":"Plants",
            "type":"Manufacturing & Wholesale Goods"
        }
    ],
    "sg:phone":"+1 503 792 3379",
    "sg:postcode":"97305",
    "sg:province":"OR",
    "sg:tags":[
        "supplies-wholesale",
        "nursery",
        "florists'",
        "tree",
        "manufacturer"
    ],
    "wof:name":"Frank Henny & Sons Nursery",
    "wof:placetype":"venue"
},
  "geometry": {"coordinates":[-122.913394,45.053332],"type":"Point"}
}