{
  "type": "Feature",
  "properties": {
    "iso:country":"US",
    "sg:address":"2902 SW Fairmount Blvd",
    "sg:city":"Portland",
    "sg:classifiers":[
        {
            "category":"Social Services",
            "type":"Services"
        }
    ],
    "sg:phone":"+1 503 227 0653",
    "sg:postcode":"97239",
    "sg:province":"OR",
    "wof:name":"Child Aid Children Literacy",
    "wof:placetype":"venue"
},
  "geometry": {"coordinates":[-122.698003,45.495377],"type":"Point"}
}