{
  "type": "Feature",
  "properties": {
    "iso:country":"US",
    "sg:address":"250 Dustin Way",
    "sg:city":"Grants Pass",
    "sg:classifiers":[
        {
            "category":"Building & Trades",
            "subcategory":"Construction",
            "type":"Services"
        }
    ],
    "sg:phone":"+1 541 956 6977",
    "sg:postcode":"97526",
    "sg:province":"OR",
    "sg:tags":[
        "contractor"
    ],
    "wof:name":"Hobson Construction",
    "wof:placetype":"venue"
},
  "geometry": {"coordinates":[-123.371087,42.452438],"type":"Point"}
}