{
  "type": "Feature",
  "properties": {
    "addr:full":"842 Virgil Ave Eugene OR 97404",
    "addr:housenumber":"842",
    "addr:postcode":"97404",
    "addr:street":"Virgil Ave",
    "iso:country":"US",
    "sg:address":"842 Virgil Ave",
    "sg:city":"Eugene",
    "sg:classifiers":[
        {
            "category":"Freight",
            "type":"Transportation"
        }
    ],
    "sg:phone":"+1 541 607 8220",
    "sg:postcode":"97404",
    "sg:province":"OR",
    "sg:tags":[
        "trucking"
    ],
    "wof:name":"2 B Trucking",
    "wof:placetype":"venue"
},
  "geometry": {"coordinates":[-123.14282,44.082216],"type":"Point"}
}