{
  "type": "Feature",
  "properties": {
    "addr:full":"12844 Old Fort Rd Klamath Falls OR 97601",
    "addr:housenumber":"12844",
    "addr:postcode":"97601",
    "addr:street":"Old Fort Rd",
    "iso:country":"US",
    "sg:address":"12844 Old Fort Rd",
    "sg:city":"Klamath Falls",
    "sg:classifiers":[
        {
            "category":"Farming",
            "subcategory":"Livestock Farm",
            "type":"Manufacturing & Wholesale Goods"
        }
    ],
    "sg:phone":"+1 541 885 6071",
    "sg:postcode":"97601",
    "sg:province":"OR",
    "sg:tags":[
        "ranch"
    ],
    "wof:name":"2 Lazy K Ranch",
    "wof:placetype":"venue"
},
  "geometry": {"coordinates":[-121.788624,42.343961],"type":"Point"}
}