{
  "type": "Feature",
  "properties": {
    "iso:country":"US",
    "sg:address":"39070 Pioneer Blvd",
    "sg:city":"Sandy",
    "sg:classifiers":[
        {
            "category":"Personal",
            "type":"Services"
        }
    ],
    "sg:phone":"+1 503 888 1292",
    "sg:postcode":"97055",
    "sg:province":"OR",
    "wof:name":"Skull Kitchen Tattoo",
    "wof:placetype":"venue"
},
  "geometry": {"coordinates":[-122.260372,45.396166],"type":"Point"}
}