{
  "type": "Feature",
  "properties": {
    "iso:country":"US",
    "sg:address":"735 SE Malden St",
    "sg:city":"Portland",
    "sg:classifiers":[
        {
            "category":"Real Estate",
            "subcategory":"Real Estate Services",
            "type":"Services"
        },
        {
            "category":"Building & Trades",
            "subcategory":"Cleaning & Sanitation",
            "type":"Services"
        }
    ],
    "sg:phone":"+1 503 233 6835",
    "sg:postcode":"97202",
    "sg:province":"OR",
    "sg:tags":[
        "window",
        "maintenance"
    ],
    "wof:name":"Top Squeegee",
    "wof:placetype":"venue"
},
  "geometry": {"coordinates":[-122.65864000000001,45.469328],"type":"Point"}
}