{
  "type": "Feature",
  "properties": {
    "addr:full":"14685 SW Carlsbad Dr Beaverton OR 97007",
    "addr:housenumber":"14685",
    "addr:postcode":"97007",
    "addr:street":"Sw Carlsbad Dr",
    "iso:country":"US",
    "sg:address":"14685 SW Carlsbad Dr",
    "sg:city":"Beaverton",
    "sg:classifiers":[
        {
            "category":"Professional",
            "subcategory":"Business Services",
            "type":"Services"
        }
    ],
    "sg:phone":"+1 503 626 7410",
    "sg:postcode":"97007",
    "sg:province":"OR",
    "wof:name":"Hosford Motor Co",
    "wof:placetype":"venue"
},
  "geometry": {"coordinates":[-122.82800899999999,45.462652],"type":"Point"}
}