{
  "type": "Feature",
  "properties": {
    "iso:country":"US",
    "sg:address":"4719 NW Maple Ave",
    "sg:city":"Redmond",
    "sg:classifiers":[
        {
            "category":"Building & Trades",
            "subcategory":"Construction",
            "type":"Services"
        }
    ],
    "sg:phone":"+1 541 548 8824",
    "sg:postcode":"97756",
    "sg:province":"OR",
    "sg:tags":[
        "house"
    ],
    "wof:name":"Builders Customer Service",
    "wof:placetype":"venue"
},
  "geometry": {"coordinates":[-121.219273,44.29104],"type":"Point"}
}