{
  "type": "Feature",
  "properties": {
    "iso:country":"US",
    "sg:address":"1620 SE Ankeny St",
    "sg:city":"Portland",
    "sg:classifiers":[
        {
            "category":"Health Services",
            "subcategory":"Clinic",
            "type":"Services"
        }
    ],
    "sg:phone":"+1 503 546 0620",
    "sg:postcode":"97214",
    "sg:province":"OR",
    "sg:tags":[
        "specialty",
        "outpatient"
    ],
    "wof:name":"Dynamic Therapies",
    "wof:placetype":"venue"
},
  "geometry": {"coordinates":[-122.648684,45.522103],"type":"Point"}
}