{
  "type": "Feature",
  "properties": {
    "addr:full":"51590 SE Westlake Dr Scappoose OR 97056",
    "addr:postcode":"51590;97056",
    "addr:street":"Se Westlake Dr",
    "iso:country":"US",
    "sg:address":"51590 SE Westlake Dr",
    "sg:city":"Scappoose",
    "sg:classifiers":[
        {
            "category":"Home & Garden",
            "subcategory":"Mobile Homes",
            "type":"Retail Goods"
        }
    ],
    "sg:phone":"+1 503 543 5205",
    "sg:postcode":"97056",
    "sg:province":"OR",
    "sg:tags":[
        "homes-wholesale",
        "manufacturer"
    ],
    "wof:name":"Springlake Community, Inc.",
    "wof:placetype":"venue"
},
  "geometry": {"coordinates":[-122.871427,45.743828],"type":"Point"}
}