{
  "type": "Feature",
  "properties": {
    "iso:country":"US",
    "sg:address":"3926 Grenada Way",
    "sg:city":"Klamath Falls",
    "sg:classifiers":[
        {
            "category":"Home & Garden",
            "subcategory":"Building Materials",
            "type":"Retail Goods"
        }
    ],
    "sg:phone":"+1 541 392 3415",
    "sg:postcode":"97603",
    "sg:province":"OR",
    "wof:name":"Southern Oregon Speech & Lea",
    "wof:placetype":"venue"
},
  "geometry": {"coordinates":[-121.715087,42.190996],"type":"Point"}
}