{
  "type": "Feature",
  "properties": {
    "addr:full":"1607 Williams Hwy Grants Pass OR 97527",
    "addr:housenumber":"1607",
    "addr:postcode":"97527",
    "addr:street":"Williams Hwy",
    "iso:country":"US",
    "sg:address":"1607 Williams Hwy",
    "sg:city":"Grants Pass",
    "sg:classifiers":[
        {
            "category":"Personal",
            "type":"Services"
        },
        {
            "category":"Sports & Exercise",
            "subcategory":"Gym",
            "type":"Entertainment"
        }
    ],
    "sg:phone":"+1 541 955 0728",
    "sg:postcode":"97527",
    "sg:province":"OR",
    "sg:tags":[
        "fitness",
        "program",
        "physical",
        "facility"
    ],
    "wof:name":"Slender Lady",
    "wof:placetype":"venue"
},
  "geometry": {"coordinates":[-123.335649,42.41979],"type":"Point"}
}