{
  "type": "Feature",
  "properties": {
    "iso:country":"US",
    "sg:address":"157 NW 15th St",
    "sg:city":"Newport",
    "sg:classifiers":[
        {
            "category":"Personal",
            "subcategory":"Beauty Salon",
            "type":"Services"
        }
    ],
    "sg:phone":"+1 541 265 9854",
    "sg:postcode":"97365",
    "sg:province":"OR",
    "sg:tags":[
        "shop"
    ],
    "wof:name":"Tips N Toes",
    "wof:placetype":"venue"
},
  "geometry": {"coordinates":[-124.053952,44.648171],"type":"Point"}
}