{
  "type": "Feature",
  "properties": {
    "iso:country":"US",
    "sg:address":"1610 N Adair St",
    "sg:city":"Cornelius",
    "sg:classifiers":[
        {
            "category":"Organizations",
            "subcategory":"Non-profit Organization",
            "type":"Services"
        }
    ],
    "sg:phone":"+1 503 357 7543",
    "sg:postcode":"97113",
    "sg:province":"OR",
    "wof:name":"Straight Ahead Shelter",
    "wof:placetype":"venue"
},
  "geometry": {"coordinates":[-123.053473,45.520983],"type":"Point"}
}