{
  "type": "Feature",
  "properties": {
    "iso:country":"US",
    "sg:address":"2135 SE 58th Ave",
    "sg:city":"Portland",
    "sg:classifiers":[
        {
            "category":"Building & Trades",
            "subcategory":"Landscaping Services",
            "type":"Services"
        }
    ],
    "sg:phone":"+1 503 736 0087",
    "sg:postcode":"97215",
    "sg:province":"OR",
    "sg:tags":[
        "designer",
        "landscape"
    ],
    "wof:name":"Beautiful Bones & Purple Stone",
    "wof:placetype":"venue"
},
  "geometry": {"coordinates":[-122.603838,45.505657],"type":"Point"}
}