{
  "type": "Feature",
  "properties": {
    "addr:full":"13335 SW Ash Ave Portland OR 97223",
    "addr:housenumber":"13335",
    "addr:postcode":"97223",
    "addr:street":"Sw Ash Ave",
    "iso:country":"US",
    "sg:address":"13335 SW Ash Ave",
    "sg:city":"Portland",
    "sg:classifiers":[
        {
            "category":"Home & Garden",
            "subcategory":"Carpets & Floor Coverings",
            "type":"Retail Goods"
        }
    ],
    "sg:phone":"+1 503 620 2858",
    "sg:postcode":"97223",
    "sg:province":"OR",
    "wof:name":"Jvj General Contracting",
    "wof:placetype":"venue"
},
  "geometry": {"coordinates":[-122.776444,45.422854],"type":"Point"}
}