{
  "type": "Feature",
  "properties": {
    "addr:full":"6941 Upper Applegate Rd Jacksonville OR 97530",
    "addr:housenumber":"6941",
    "addr:postcode":"97530",
    "addr:street":"Upper Applegate Rd",
    "iso:country":"US",
    "sg:address":"6941 Upper Applegate Rd",
    "sg:city":"Jacksonville",
    "sg:classifiers":[
        {
            "category":"Manufacturing",
            "subcategory":"Lumber",
            "type":"Manufacturing & Wholesale Goods"
        }
    ],
    "sg:phone":"+1 541 899 1812",
    "sg:postcode":"97530",
    "sg:province":"OR",
    "sg:tags":[
        "government"
    ],
    "wof:name":"US Forestry Dept",
    "wof:placetype":"venue"
},
  "geometry": {"coordinates":[-123.05787100000001,42.151227],"type":"Point"}
}