{
  "type": "Feature",
  "properties": {
    "addr:full":"6844 SE 84th Ave Portland OR 97266",
    "addr:housenumber":"6844",
    "addr:postcode":"97266",
    "addr:street":"Se 84Th Ave",
    "iso:country":"US",
    "sg:address":"6844 SE 84th Ave",
    "sg:city":"Portland",
    "sg:classifiers":[
        {
            "category":"Building & Trades",
            "subcategory":"Construction",
            "type":"Services"
        }
    ],
    "sg:phone":"+1 360 513 8018",
    "sg:postcode":"97266",
    "sg:province":"OR",
    "sg:tags":[
        "contractor"
    ],
    "sg:website":"www.atozhvac.info/",
    "wof:name":"A To Z HVAC AC Repair Heating Service",
    "wof:placetype":"venue"
},
  "geometry": {"coordinates":[-122.57663700000001,45.472802],"type":"Point"}
}