{
  "type": "Feature",
  "properties": {
    "iso:country":"US",
    "sg:address":"450 NE Windy Knolls Dr",
    "sg:city":"Bend",
    "sg:classifiers":[
        {
            "category":"Banks & Credit Unions",
            "subcategory":"Bank",
            "type":"Services"
        }
    ],
    "sg:phone":"+1 541 383 2723",
    "sg:postcode":"97701",
    "sg:province":"OR",
    "sg:tags":[
        "mortgage"
    ],
    "wof:name":"Mortgage Loan Center",
    "wof:placetype":"venue"
},
  "geometry": {"coordinates":[-121.266323,44.053963],"type":"Point"}
}