{
  "type": "Feature",
  "properties": {
    "addr:full":"2305 SE 34th Ave Portland OR 97214",
    "addr:housenumber":"2305",
    "addr:postcode":"97214",
    "addr:street":"Se 34Th Ave",
    "iso:country":"US",
    "sg:address":"2305 SE 34th Ave",
    "sg:city":"Portland",
    "sg:classifiers":[
        {
            "category":"Building & Trades",
            "subcategory":"Construction",
            "type":"Services"
        }
    ],
    "sg:phone":"+1 503 234 1069",
    "sg:postcode":"97214",
    "sg:province":"OR",
    "sg:tags":[
        "carpentry",
        "contractor"
    ],
    "wof:name":"Scott Shuey Design",
    "wof:placetype":"venue"
},
  "geometry": {"coordinates":[-122.629659,45.505486],"type":"Point"}
}