{
  "type": "Feature",
  "properties": {
    "iso:country":"US",
    "sg:address":"15971 Wenbourne Ln",
    "sg:city":"Brookings",
    "sg:classifiers":[
        {
            "category":"Building & Trades",
            "subcategory":"Construction",
            "type":"Services"
        }
    ],
    "sg:phone":"+1 541 412 9337",
    "sg:postcode":"97415",
    "sg:province":"OR",
    "sg:tags":[
        "floor",
        "laying",
        "contractor"
    ],
    "wof:name":"Carpet Deals On Wheels",
    "wof:placetype":"venue"
},
  "geometry": {"coordinates":[-124.25881099999999,42.041637],"type":"Point"}
}