{
  "type": "Feature",
  "properties": {
    "iso:country":"US",
    "sg:address":"555 Valleywood Dr SE",
    "sg:city":"Salem",
    "sg:classifiers":[
        {
            "category":"Professional",
            "subcategory":"Business Services",
            "type":"Services"
        }
    ],
    "sg:phone":"+1 503 363 0881",
    "sg:postcode":"97306",
    "sg:province":"OR",
    "wof:name":"Herb Gedney Enterprises",
    "wof:placetype":"venue"
},
  "geometry": {"coordinates":[-123.047398,44.876259],"type":"Point"}
}