{
  "type": "Feature",
  "properties": {
    "addr:full":"125 E Main St Enterprise OR 97828",
    "addr:housenumber":"125",
    "addr:postcode":"97828",
    "addr:street":"E Main St",
    "iso:country":"US",
    "sg:address":"125 E Main St",
    "sg:city":"Enterprise",
    "sg:classifiers":[
        {
            "category":"Shopping",
            "subcategory":"Computers & Home Electronics",
            "type":"Retail Goods"
        }
    ],
    "sg:phone":"+1 541 426 5971",
    "sg:postcode":"97828",
    "sg:province":"OR",
    "sg:tags":[
        "equipment",
        "dealer"
    ],
    "wof:name":"End Of The Road Computing",
    "wof:placetype":"venue"
},
  "geometry": {"coordinates":[-117.27727400000001,45.42543],"type":"Point"}
}