{
  "type": "Feature",
  "properties": {
    "iso:country":"US",
    "sg:address":"2703 Marine Dr",
    "sg:city":"Astoria",
    "sg:classifiers":[
        {
            "category":"Government",
            "subcategory":"Office",
            "type":"Public Place"
        }
    ],
    "sg:phone":"+1 503 325 7335",
    "sg:postcode":"97103",
    "sg:province":"OR",
    "sg:tags":[
        "disabled",
        "rehabilitation",
        "vocational",
        "for"
    ],
    "wof:name":"Human Services Oregon Dept",
    "wof:placetype":"venue"
},
  "geometry": {"coordinates":[-123.811852,46.189927],"type":"Point"}
}