{
  "type": "Feature",
  "properties": {
    "addr:full":"3004 SE 50th Ave Portland OR 97206",
    "addr:housenumber":"3004",
    "addr:postcode":"97206",
    "addr:street":"Se 50Th Ave",
    "iso:country":"US",
    "sg:address":"3004 SE 50th Ave",
    "sg:city":"Portland",
    "sg:classifiers":[
        {
            "category":"Professional",
            "subcategory":"Engineering",
            "type":"Services"
        }
    ],
    "sg:phone":"+1 503 771 8255",
    "sg:postcode":"97206",
    "sg:province":"OR",
    "sg:tags":[
        "engineer"
    ],
    "wof:name":"Worth Technical Svc",
    "wof:placetype":"venue"
},
  "geometry": {"coordinates":[-122.61127,45.500313],"type":"Point"}
}