{
  "type": "Feature",
  "properties": {
    "addr:full":"N Edison St and Pittsburg Ave Portland OR 97203",
    "addr:postcode":"97203",
    "addr:street":"N Edison St;Pittsburg Ave",
    "iso:country":"US",
    "sg:address":"N Edison St and Pittsburg Ave",
    "sg:city":"Portland",
    "sg:classifiers":[
        {
            "category":"Recreation",
            "subcategory":"Boat Charter",
            "type":"Entertainment"
        },
        {
            "category":"Park",
            "type":"Public Place"
        }
    ],
    "sg:postcode":"97203",
    "sg:province":"OR",
    "sg:tags":[
        "boating"
    ],
    "sg:website":"www.portlandonline.com/parks/fin...",
    "wof:name":"Cathedral Park",
    "wof:placetype":"venue"
},
  "geometry": {"coordinates":[-122.75738,45.587672],"type":"Point"}
}