{
  "type": "Feature",
  "properties": {
    "iso:country":"US",
    "sg:address":"69849 Proudfoot Rd",
    "sg:city":"Ione",
    "sg:classifiers":[
        {
            "category":"Farming",
            "subcategory":"Livestock Farm",
            "type":"Manufacturing & Wholesale Goods"
        },
        {
            "category":"Farming",
            "subcategory":"Farm",
            "type":"Manufacturing & Wholesale Goods"
        }
    ],
    "sg:phone":"+1 541 422 7249",
    "sg:postcode":"97843",
    "sg:province":"OR",
    "sg:tags":[
        "feeding",
        "ranch"
    ],
    "wof:name":"Jason Proudfoot",
    "wof:placetype":"venue"
},
  "geometry": {"coordinates":[-119.726196,45.605301],"type":"Point"}
}