{
  "type": "Feature",
  "properties": {
    "addr:full":"62010 27th St Bend OR 97701",
    "addr:housenumber":"62010",
    "addr:postcode":"97701",
    "addr:street":"27Th St",
    "iso:country":"US",
    "sg:address":"62010 27th St",
    "sg:city":"Bend",
    "sg:classifiers":[
        {
            "category":"Organizations",
            "subcategory":"Religious Organization",
            "type":"Services"
        }
    ],
    "sg:phone":"+1 541 388 4088",
    "sg:postcode":"97701",
    "sg:province":"OR",
    "wof:name":"Desert Streams Church",
    "wof:placetype":"venue"
},
  "geometry": {"coordinates":[-121.26361,44.052297],"type":"Point"}
}