{
  "type": "Feature",
  "properties": {
    "addr:full":"6605 Hays Ln SE Aumsville OR 97325",
    "addr:housenumber":"6605",
    "addr:postcode":"97325",
    "addr:street":"Hays Ln Se",
    "iso:country":"US",
    "sg:address":"6605 Hays Ln SE",
    "sg:city":"Aumsville",
    "sg:classifiers":[
        {
            "category":"Freight",
            "type":"Transportation"
        }
    ],
    "sg:phone":"+1 503 749 2525",
    "sg:postcode":"97325",
    "sg:province":"OR",
    "sg:tags":[
        "operator",
        "local",
        "trucking"
    ],
    "wof:name":"Daryl Fitzpatrick",
    "wof:placetype":"venue"
},
  "geometry": {"coordinates":[-122.859416,44.859191],"type":"Point"}
}