{
  "type": "Feature",
  "properties": {
    "iso:country":"US",
    "sg:address":"161 E Cascade Ave",
    "sg:city":"Sisters",
    "sg:classifiers":[
        {
            "category":"Food & Beverages",
            "subcategory":"Liquor & Beverages",
            "type":"Retail Goods"
        }
    ],
    "sg:phone":"+1 541 549 2675",
    "sg:postcode":"97759",
    "sg:province":"OR",
    "sg:tags":[
        "wine"
    ],
    "wof:name":"Cork Cellars",
    "wof:placetype":"venue"
},
  "geometry": {"coordinates":[-121.549649,44.291252],"type":"Point"}
}