{
  "type": "Feature",
  "properties": {
    "iso:country":"US",
    "sg:address":"472 17th St NE",
    "sg:city":"Salem",
    "sg:classifiers":[
        {
            "category":"Insurance",
            "subcategory":"Insurance Agent",
            "type":"Services"
        }
    ],
    "sg:phone":"+1 503 378 9900",
    "sg:postcode":"97301",
    "sg:province":"OR",
    "wof:name":"Walnut Grove Insurance",
    "wof:placetype":"venue"
},
  "geometry": {"coordinates":[-123.01835699999999,44.938601],"type":"Point"}
}