{
  "type": "Feature",
  "properties": {
    "iso:country":"US",
    "sg:address":"11954 NE Glisan St",
    "sg:city":"Portland",
    "sg:classifiers":[
        {
            "category":"Personal",
            "subcategory":"Beauty Salon",
            "type":"Services"
        }
    ],
    "sg:phone":"+1 503 256 6911",
    "sg:postcode":"97220",
    "sg:province":"OR",
    "wof:name":"Beauty On The Go",
    "wof:placetype":"venue"
},
  "geometry": {"coordinates":[-122.53941500000001,45.526215],"type":"Point"}
}