{
  "type": "Feature",
  "properties": {
    "addr:full":"8230 SE Harrison St Portland OR 97216",
    "addr:housenumber":"8230",
    "addr:postcode":"97216",
    "addr:street":"Se Harrison St",
    "iso:country":"US",
    "sg:address":"8230 SE Harrison St",
    "sg:city":"Portland",
    "sg:classifiers":[
        {
            "category":"Restaurant",
            "type":"Food & Drink"
        }
    ],
    "sg:phone":"+1 503 775 3333",
    "sg:postcode":"97216",
    "sg:province":"OR",
    "wof:name":"Euro Pizza",
    "wof:placetype":"venue"
},
  "geometry": {"coordinates":[-122.57781,45.508286],"type":"Point"}
}