{
  "type": "Feature",
  "properties": {
    "iso:country":"US",
    "sg:address":"23280 Bear Creek Rd",
    "sg:city":"Bend",
    "sg:classifiers":[
        {
            "category":"Professional",
            "subcategory":"Accounting & Tax Preparation",
            "type":"Services"
        }
    ],
    "sg:phone":"+1 541 389 3617",
    "sg:postcode":"97701",
    "sg:province":"OR",
    "sg:tags":[
        "return"
    ],
    "wof:name":"Its Taxing Made Simple",
    "wof:placetype":"venue"
},
  "geometry": {"coordinates":[-121.157387,44.051295],"type":"Point"}
}