{
  "type": "Feature",
  "properties": {
    "addr:full":"1911 Tamarack Pl Ashland OR 97520",
    "addr:housenumber":"1911",
    "addr:postcode":"97520",
    "addr:street":"Tamarack Pl",
    "iso:country":"US",
    "sg:address":"1911 Tamarack Pl",
    "sg:city":"Ashland",
    "sg:classifiers":[
        {
            "category":"Building & Trades",
            "subcategory":"Construction",
            "type":"Services"
        }
    ],
    "sg:phone":"+1 541 488 1473",
    "sg:postcode":"97520",
    "sg:province":"OR",
    "sg:tags":[
        "house"
    ],
    "wof:name":"Dennis Groover Construction",
    "wof:placetype":"venue"
},
  "geometry": {"coordinates":[-122.679778,42.172993],"type":"Point"}
}