{
  "type": "Feature",
  "properties": {
    "addr:full":"16002 SW Tualatin Sherwood Rd Sherwood OR 97140",
    "addr:housenumber":"16002",
    "addr:postcode":"97140",
    "addr:street":"Sw Tualatin Sherwood Rd",
    "iso:country":"US",
    "sg:address":"16002 SW Tualatin Sherwood Rd",
    "sg:city":"Sherwood",
    "sg:classifiers":[
        {
            "category":"Personal",
            "subcategory":"Beauty Salon",
            "type":"Services"
        }
    ],
    "sg:phone":"+1 503 625 6378",
    "sg:postcode":"97140",
    "sg:province":"OR",
    "wof:name":"Trade Secret",
    "wof:placetype":"venue"
},
  "geometry": {"coordinates":[-122.840857,45.368494],"type":"Point"}
}