{
  "type": "Feature",
  "properties": {
    "addr:full":"2022 NE 73rd Ave Portland OR 97213",
    "addr:housenumber":"2022",
    "addr:postcode":"97213",
    "addr:street":"Ne 73Rd Ave",
    "iso:country":"US",
    "sg:address":"2022 NE 73rd Ave",
    "sg:city":"Portland",
    "sg:classifiers":[
        {
            "category":"Shopping",
            "subcategory":"Gifts & Souvenirs",
            "type":"Retail Goods"
        }
    ],
    "sg:phone":"+1 503 261 1463",
    "sg:postcode":"97213",
    "sg:province":"OR",
    "sg:tags":[
        "shop"
    ],
    "wof:name":"Faerie Tales",
    "wof:placetype":"venue"
},
  "geometry": {"coordinates":[-122.587726,45.536843],"type":"Point"}
}