{
  "type": "Feature",
  "properties": {
    "addr:full":"21285 NW Cherry Ln Hillsboro OR 97124",
    "addr:housenumber":"21285",
    "addr:postcode":"97124",
    "addr:street":"Nw Cherry Ln",
    "iso:country":"US",
    "sg:address":"21285 NW Cherry Ln",
    "sg:city":"Hillsboro",
    "sg:classifiers":[
        {
            "category":"Retail",
            "subcategory":"Auto Repair",
            "type":"Services"
        }
    ],
    "sg:phone":"+1 503 643 4674",
    "sg:postcode":"97124",
    "sg:province":"OR",
    "sg:tags":[
        "wrecker"
    ],
    "wof:name":"Professional Towing",
    "wof:placetype":"venue"
},
  "geometry": {"coordinates":[-122.899305,45.530414],"type":"Point"}
}