{
  "type": "Feature",
  "properties": {
    "iso:country":"US",
    "sg:address":"24023 NE Shea Ln",
    "sg:city":"Troutdale",
    "sg:classifiers":[
        {
            "category":"Wholesale",
            "subcategory":"Non-durable Goods",
            "type":"Manufacturing & Wholesale Goods"
        }
    ],
    "sg:phone":"+1 503 492 9554",
    "sg:postcode":"97060",
    "sg:province":"OR",
    "wof:name":"T J Intl",
    "wof:placetype":"venue"
},
  "geometry": {"coordinates":[-122.415806,45.538857],"type":"Point"}
}