{
  "type": "Feature",
  "properties": {
    "iso:country":"US",
    "sg:address":"530 NE Couch Street",
    "sg:city":"Portland",
    "sg:classifiers":[
        {
            "category":"Building & Trades",
            "subcategory":"Locksmith",
            "type":"Services"
        }
    ],
    "sg:phone":"+1 503 281 1177",
    "sg:postcode":"97232",
    "sg:province":"OR",
    "sg:tags":[
        "key"
    ],
    "wof:name":"Allied Fire & Security",
    "wof:placetype":"venue"
},
  "geometry": {"coordinates":[-122.660703,45.52365],"type":"Point"}
}