{
  "type": "Feature",
  "properties": {
    "iso:country":"US",
    "sg:address":"600 NE Norton Ln",
    "sg:city":"Mcminnville",
    "sg:classifiers":[
        {
            "category":"Building & Trades",
            "subcategory":"Construction",
            "type":"Services"
        }
    ],
    "sg:phone":"+1 503 472 8877",
    "sg:postcode":"97128",
    "sg:province":"OR",
    "wof:name":"Arlen Berkey Pole Buildings",
    "wof:placetype":"venue"
},
  "geometry": {"coordinates":[-123.166537,45.203727],"type":"Point"}
}