{
  "type": "Feature",
  "properties": {
    "addr:full":"512 Cole Rd Oakland OR 97462",
    "addr:housenumber":"512",
    "addr:postcode":"97462",
    "addr:street":"Cole Rd",
    "iso:country":"US",
    "sg:address":"512 Cole Rd",
    "sg:city":"Oakland",
    "sg:classifiers":[
        {
            "category":"Organizations",
            "subcategory":"Religious Organization",
            "type":"Services"
        }
    ],
    "sg:phone":"+1 541 459 5078",
    "sg:postcode":"97462",
    "sg:province":"OR",
    "sg:tags":[
        "clergy"
    ],
    "wof:name":"Floyd Hunsaker",
    "wof:placetype":"venue"
},
  "geometry": {"coordinates":[-123.39453899999999,43.389389],"type":"Point"}
}