{
  "type": "Feature",
  "properties": {
    "iso:country":"US",
    "sg:address":"245 SW Morrison St",
    "sg:city":"Portland",
    "sg:classifiers":[
        {
            "category":"Building & Trades",
            "subcategory":"Locksmith",
            "type":"Services"
        }
    ],
    "sg:phone":"+1 503 438 4728",
    "sg:postcode":"97204",
    "sg:province":"OR",
    "sg:tags":[
        "key"
    ],
    "wof:name":"24HRS Locksmith",
    "wof:placetype":"venue"
},
  "geometry": {"coordinates":[-122.67485600000001,45.518458],"type":"Point"}
}