{
  "type": "Feature",
  "properties": {
    "iso:country":"US",
    "sg:address":"909 NW 6th St",
    "sg:city":"Redmond",
    "sg:classifiers":[
        {
            "category":"Shopping",
            "subcategory":"Tobacco",
            "type":"Retail Goods"
        }
    ],
    "sg:phone":"+1 541 923 2896",
    "sg:postcode":"97756",
    "sg:province":"OR",
    "sg:tags":[
        "product"
    ],
    "wof:name":"Tobacco Jo North",
    "wof:placetype":"venue"
},
  "geometry": {"coordinates":[-121.174201,44.284315],"type":"Point"}
}