{
  "type": "Feature",
  "properties": {
    "iso:country":"US",
    "sg:address":"9055 SW Murray Blvd",
    "sg:city":"Beaverton",
    "sg:classifiers":[
        {
            "category":"Shopping",
            "subcategory":"Pharmacy",
            "type":"Retail Goods"
        },
        {
            "category":"Food & Beverages",
            "subcategory":"Groceries & Convenience Stores",
            "type":"Retail Goods"
        }
    ],
    "sg:phone":"+1 503 521 5851",
    "sg:postcode":"97008",
    "sg:province":"OR",
    "sg:tags":[
        "drugstore"
    ],
    "sg:website":"www.haggen.com",
    "wof:name":"Haggen Food and Pharmacy",
    "wof:placetype":"venue"
},
  "geometry": {"coordinates":[-122.826149,45.454316],"type":"Point"}
}