{
  "type": "Feature",
  "properties": {
    "iso:country":"US",
    "sg:address":"616 SW 9th St",
    "sg:city":"Redmond",
    "sg:classifiers":[
        {
            "category":"Organizations",
            "subcategory":"Religious Organization",
            "type":"Services"
        }
    ],
    "sg:phone":"+1 541 923 4979",
    "sg:postcode":"97756",
    "sg:province":"OR",
    "wof:name":"Free Methodist Church",
    "wof:placetype":"venue"
},
  "geometry": {"coordinates":[-121.177402,44.271413],"type":"Point"}
}