{
  "type": "Feature",
  "properties": {
    "iso:country":"US",
    "sg:address":"4103 NE Tillamook Street",
    "sg:city":"Portland",
    "sg:classifiers":[
        {
            "category":"Personal",
            "subcategory":"Nail Salon",
            "type":"Services"
        }
    ],
    "sg:phone":"+1 503 284 2927",
    "sg:postcode":"97212",
    "sg:province":"OR",
    "wof:name":"Lady Fingers",
    "wof:placetype":"venue"
},
  "geometry": {"coordinates":[-122.620603,45.537887],"type":"Point"}
}