{
  "type": "Feature",
  "properties": {
    "iso:country":"US",
    "sg:address":"1900 Marcola Rd",
    "sg:city":"Springfield",
    "sg:classifiers":[
        {
            "category":"Restaurant",
            "type":"Food & Drink"
        }
    ],
    "sg:menulink":"http://www.allmenus.com/or/eugene-springfield/160900-carls-jr/menu/",
    "sg:phone":"+1 541 726 9383",
    "sg:postcode":"97477",
    "sg:province":"OR",
    "sg:tags":[
        "burger",
        "american"
    ],
    "wof:name":"Carl's Jr.",
    "wof:placetype":"venue"
},
  "geometry": {"coordinates":[-122.996576,44.064428],"type":"Point"}
}