{
  "type": "Feature",
  "properties": {
    "addr:full":"803 SE Stephens St Roseburg OR 97470",
    "addr:housenumber":"803",
    "addr:postcode":"97470",
    "addr:street":"Se Stephens St",
    "iso:country":"US",
    "sg:address":"803 SE Stephens St",
    "sg:city":"Roseburg",
    "sg:classifiers":[
        {
            "category":"Personal",
            "subcategory":"Tattoo Parlor",
            "type":"Services"
        }
    ],
    "sg:phone":"+1 541 677 9879",
    "sg:postcode":"97470",
    "sg:province":"OR",
    "sg:tags":[
        "tattooing"
    ],
    "wof:name":"Primal Visions",
    "wof:placetype":"venue"
},
  "geometry": {"coordinates":[-123.34723200000001,43.207652],"type":"Point"}
}