{
  "type": "Feature",
  "properties": {
    "addr:full":"4241 SE Rex St Portland OR 97206",
    "addr:housenumber":"4241",
    "addr:postcode":"97206",
    "addr:street":"Se Rex St",
    "iso:country":"US",
    "sg:address":"4241 SE Rex St",
    "sg:city":"Portland",
    "sg:classifiers":[
        {
            "category":"Shopping",
            "subcategory":"Clothing, Apparel, & Fashions",
            "type":"Retail Goods"
        }
    ],
    "sg:phone":"+1 503 774 4541",
    "sg:postcode":"97206",
    "sg:province":"OR",
    "sg:tags":[
        "dressmaker",
        "custom"
    ],
    "wof:name":"My World",
    "wof:placetype":"venue"
},
  "geometry": {"coordinates":[-122.617254,45.468286],"type":"Point"}
}