{
  "type": "Feature",
  "properties": {
    "iso:country":"US",
    "sg:address":"2150 N Lewis Ave",
    "sg:city":"Portland",
    "sg:classifiers":[
        {
            "category":"Wholesale",
            "subcategory":"Construction Materials",
            "type":"Manufacturing & Wholesale Goods"
        },
        {
            "category":"Home & Garden",
            "subcategory":"Building Materials",
            "type":"Retail Goods"
        },
        {
            "category":"Wholesale",
            "subcategory":"Home Furnishings",
            "type":"Manufacturing & Wholesale Goods"
        }
    ],
    "sg:phone":"+1 503 249 6972",
    "sg:postcode":"97227",
    "sg:province":"OR",
    "sg:tags":[
        "supply",
        "fixture",
        "system",
        "heating",
        "systems-wholesale",
        "equipment",
        "part",
        "plumbing",
        "fixtures",
        "supplies-wholesale",
        "manufacturer"
    ],
    "sg:website":"http://www.braleygray.com",
    "wof:name":"Braley-Gray & Associates, Inc.",
    "wof:placetype":"venue"
},
  "geometry": {"coordinates":[-122.676727,45.53838],"type":"Point"}
}