{
  "type": "Feature",
  "properties": {
    "addr:full":"515 SW Broadway Portland OR 97205",
    "addr:housenumber":"515",
    "addr:postcode":"97205",
    "addr:street":"Sw Broadway",
    "iso:country":"US",
    "sg:address":"515 SW Broadway",
    "sg:city":"Portland",
    "sg:classifiers":[
        {
            "category":"Personal",
            "subcategory":"Shoe Repair & Shine",
            "type":"Services"
        }
    ],
    "sg:phone":"+1 503 226 0765",
    "sg:postcode":"97205",
    "sg:province":"OR",
    "wof:name":"Dereks Fabric Shoe Dyeing",
    "wof:placetype":"venue"
},
  "geometry": {"coordinates":[-122.679293,45.520135],"type":"Point"}
}