{
  "type": "Feature",
  "properties": {
    "addr:full":"450 N Buena Vista Ave Burns OR 97720",
    "addr:housenumber":"450",
    "addr:postcode":"97720",
    "addr:street":"N Buena Vista Ave",
    "iso:country":"US",
    "sg:address":"450 N Buena Vista Ave",
    "sg:city":"Burns",
    "sg:classifiers":[
        {
            "category":"Government",
            "subcategory":"Office",
            "type":"Public Place"
        }
    ],
    "sg:phone":"+1 541 573 2439",
    "sg:postcode":"97720",
    "sg:province":"OR",
    "wof:name":"Harney Juvenile Dept",
    "wof:placetype":"venue"
},
  "geometry": {"coordinates":[-119.05663300000001,43.58945],"type":"Point"}
}