{
  "type": "Feature",
  "properties": {
    "addr:full":"19115 S Beavercreek Rd Oregon City OR 97045",
    "addr:housenumber":"19115",
    "addr:postcode":"97045",
    "addr:street":"S Beavercreek Rd",
    "iso:country":"US",
    "sg:address":"19115 S Beavercreek Rd",
    "sg:city":"Oregon City",
    "sg:classifiers":[
        {
            "category":"Travel",
            "subcategory":"Travel Agent",
            "type":"Entertainment"
        }
    ],
    "sg:phone":"+1 503 656 1623",
    "sg:postcode":"97045",
    "sg:province":"OR",
    "sg:tags":[
        "agency",
        "bureau"
    ],
    "sg:website":"www.canbytravel.com",
    "wof:name":"Oregon City Travel Inc",
    "wof:placetype":"venue"
},
  "geometry": {"coordinates":[-122.569712,45.3297],"type":"Point"}
}