{
  "type": "Feature",
  "properties": {
    "iso:country":"US",
    "sg:address":"210 Sunshine Acres Dr",
    "sg:city":"Eugene",
    "sg:classifiers":[
        {
            "category":"Professional",
            "type":"Services"
        }
    ],
    "sg:phone":"+1 541 338 4008",
    "sg:postcode":"97401",
    "sg:province":"OR",
    "wof:name":"Cedartech Fo Lane Counte",
    "wof:placetype":"venue"
},
  "geometry": {"coordinates":[-123.059485,44.063327],"type":"Point"}
}