{
  "type": "Feature",
  "properties": {
    "iso:country":"US",
    "sg:address":"257 SW Nancy Cir",
    "sg:city":"Gresham",
    "sg:classifiers":[
        {
            "category":"Professional",
            "subcategory":"Management & Consulting",
            "type":"Services"
        }
    ],
    "sg:phone":"+1 503 661 7022",
    "sg:postcode":"97030",
    "sg:province":"OR",
    "wof:name":"Glh Consulting Inc",
    "wof:placetype":"venue"
},
  "geometry": {"coordinates":[-122.47399,45.495223],"type":"Point"}
}