{
  "type": "Feature",
  "properties": {
    "iso:country":"US",
    "sg:address":"1330 12th St SE",
    "sg:city":"Salem",
    "sg:classifiers":[
        {
            "category":"Professional",
            "subcategory":"Management & Consulting",
            "type":"Services"
        }
    ],
    "sg:phone":"+1 503 391 7383",
    "sg:postcode":"97302",
    "sg:province":"OR",
    "wof:name":"12th St Ftnes Sams Per Trining",
    "wof:placetype":"venue"
},
  "geometry": {"coordinates":[-123.03059,44.924128],"type":"Point"}
}