{
  "type": "Feature",
  "properties": {
    "addr:full":"5741 NE Glisan Street Suite 1 Portland OR 97213",
    "addr:housenumber":"5741",
    "addr:postcode":"97213",
    "addr:street":"Ne Glisan Street Suite 1",
    "iso:country":"US",
    "sg:address":"5741 NE Glisan Street Suite 1",
    "sg:city":"Portland",
    "sg:classifiers":[
        {
            "category":"Banks & Credit Unions",
            "subcategory":"Investment Brokerage",
            "type":"Services"
        }
    ],
    "sg:phone":"+1 503 232 4214",
    "sg:postcode":"97213",
    "sg:province":"OR",
    "sg:tags":[
        "investing"
    ],
    "wof:name":"Remington & Woodhouse Financial Products and Services",
    "wof:placetype":"venue"
},
  "geometry": {"coordinates":[-122.60436799999999,45.526478],"type":"Point"}
}