{
  "type": "Feature",
  "properties": {
    "addr:full":"3462 Griffin Creek Rd Medford OR 97501",
    "addr:housenumber":"3462",
    "addr:postcode":"97501",
    "addr:street":"Griffin Creek Rd",
    "iso:country":"US",
    "sg:address":"3462 Griffin Creek Rd",
    "sg:city":"Medford",
    "sg:classifiers":[
        {
            "category":"Freight",
            "type":"Transportation"
        }
    ],
    "sg:phone":"+1 541 770 5369",
    "sg:postcode":"97501",
    "sg:province":"OR",
    "sg:tags":[
        "operator",
        "trucking"
    ],
    "wof:name":"Gary Britt Logging",
    "wof:placetype":"venue"
},
  "geometry": {"coordinates":[-122.90719,42.280002],"type":"Point"}
}