{
  "type": "Feature",
  "properties": {
    "iso:country":"US",
    "sg:address":"8310 N Brandon Ave",
    "sg:city":"Portland",
    "sg:classifiers":[
        {
            "category":"Wholesale",
            "subcategory":"Scrap",
            "type":"Manufacturing & Wholesale Goods"
        }
    ],
    "sg:phone":"+1 503 285 4410",
    "sg:postcode":"97217",
    "sg:province":"OR",
    "sg:tags":[
        "new"
    ],
    "wof:name":"Hartman Steel Inc",
    "wof:placetype":"venue"
},
  "geometry": {"coordinates":[-122.68896100000001,45.583746],"type":"Point"}
}