{
  "type": "Feature",
  "properties": {
    "addr:full":"4281 Jerome Prairie Rd Grants Pass OR 97527",
    "addr:housenumber":"4281",
    "addr:postcode":"97527",
    "addr:street":"Jerome Prairie Rd",
    "iso:country":"US",
    "sg:address":"4281 Jerome Prairie Rd",
    "sg:city":"Grants Pass",
    "sg:classifiers":[
        {
            "category":"Building & Trades",
            "subcategory":"Construction",
            "type":"Services"
        }
    ],
    "sg:phone":"+1 541 476 4249",
    "sg:postcode":"97527",
    "sg:province":"OR",
    "sg:tags":[
        "house"
    ],
    "wof:name":"P D Ristau Construction",
    "wof:placetype":"venue"
},
  "geometry": {"coordinates":[-123.41071100000001,42.389546],"type":"Point"}
}