{
  "type": "Feature",
  "properties": {
    "addr:full":"75724 Rock Crest St Rainier OR 97048",
    "addr:housenumber":"75724",
    "addr:postcode":"97048",
    "addr:street":"Rock Crest St",
    "iso:country":"US",
    "sg:address":"75724 Rock Crest St",
    "sg:city":"Rainier",
    "sg:classifiers":[
        {
            "category":"Food & Beverages",
            "subcategory":"Groceries & Convenience Stores",
            "type":"Retail Goods"
        }
    ],
    "sg:phone":"+1 503 556 8091",
    "sg:postcode":"97048",
    "sg:province":"OR",
    "sg:tags":[
        "grocer",
        "restaurant"
    ],
    "wof:name":"Deli Store",
    "wof:placetype":"venue"
},
  "geometry": {"coordinates":[-122.96351,46.094874],"type":"Point"}
}