{
  "type": "Feature",
  "properties": {
    "addr:full":"16490 SW 72nd Ave Portland OR 97224",
    "addr:housenumber":"16490",
    "addr:postcode":"97224",
    "addr:street":"Sw 72Nd Ave",
    "iso:country":"US",
    "sg:address":"16490 SW 72nd Ave",
    "sg:city":"Portland",
    "sg:classifiers":[
        {
            "category":"Manufacturing",
            "subcategory":"Pet Food",
            "type":"Manufacturing & Wholesale Goods"
        },
        {
            "category":"Shopping",
            "subcategory":"Pets & Pet Supplies",
            "type":"Retail Goods"
        }
    ],
    "sg:phone":"+1 503 624 3967",
    "sg:postcode":"97224",
    "sg:province":"OR",
    "sg:tags":[
        "product",
        "dog",
        "cat",
        "health",
        "furnishing",
        "animal",
        "foods-wholesale",
        "store",
        "manufacturer"
    ],
    "wof:name":"Hill's Pet Nutrition",
    "wof:placetype":"venue"
},
  "geometry": {"coordinates":[-122.74912999999999,45.401957],"type":"Point"}
}