{
  "type": "Feature",
  "properties": {
    "iso:country":"US",
    "sg:address":"906 NW Harriman St",
    "sg:city":"Bend",
    "sg:classifiers":[
        {
            "category":"Insurance",
            "subcategory":"Insurance Agent",
            "type":"Services"
        },
        {
            "category":"Insurance",
            "subcategory":"Hazard Insurance",
            "type":"Services"
        },
        {
            "category":"Insurance",
            "subcategory":"Title Insurance",
            "type":"Services"
        },
        {
            "category":"Insurance",
            "subcategory":"Life Insurance",
            "type":"Services"
        }
    ],
    "sg:phone":"+1 541 318 8835",
    "sg:postcode":"97701",
    "sg:province":"OR",
    "sg:tags":[
        "business",
        "auto",
        "commercial",
        "homeowner",
        "motorcycle",
        "renter"
    ],
    "wof:name":"Allstate Insurance Company - Steve Williams",
    "wof:placetype":"venue"
},
  "geometry": {"coordinates":[-121.31034099999999,44.058995],"type":"Point"}
}