{
  "type": "Feature",
  "properties": {
    "iso:country":"US",
    "sg:address":"1423 Lloyd Ctr",
    "sg:city":"Portland",
    "sg:classifiers":[
        {
            "category":"Home & Garden",
            "subcategory":"Furniture",
            "type":"Retail Goods"
        }
    ],
    "sg:phone":"+1 503 249 5978",
    "sg:postcode":"97232",
    "sg:province":"OR",
    "sg:tags":[
        "store"
    ],
    "sg:website":"www.pier1.com",
    "wof:name":"Pier One Imports",
    "wof:placetype":"venue"
},
  "geometry": {"coordinates":[-122.65398,45.532031],"type":"Point"}
}