{
  "type": "Feature",
  "properties": {
    "addr:full":"21818 SW Columbia Cir Tualatin OR 97062",
    "addr:housenumber":"21818",
    "addr:postcode":"97062",
    "addr:street":"Sw Columbia Cir",
    "iso:country":"US",
    "sg:address":"21818 SW Columbia Cir",
    "sg:city":"Tualatin",
    "sg:classifiers":[
        {
            "category":"Retail",
            "subcategory":"Repair Shop",
            "type":"Services"
        }
    ],
    "sg:phone":"+1 503 692 6074",
    "sg:postcode":"97062",
    "sg:province":"OR",
    "wof:name":"Boyd Broadcast Services",
    "wof:placetype":"venue"
},
  "geometry": {"coordinates":[-122.775025,45.362241],"type":"Point"}
}