{
  "type": "Feature",
  "properties": {
    "addr:full":"1440 NE 223rd Ave Wood Village OR 97060",
    "addr:housenumber":"1440",
    "addr:postcode":"97060",
    "addr:street":"Ne 223Rd Ave",
    "iso:country":"US",
    "sg:address":"1440 NE 223rd Ave",
    "sg:city":"Wood Village",
    "sg:classifiers":[
        {
            "category":"Organizations",
            "subcategory":"Religious Organization",
            "type":"Services"
        }
    ],
    "sg:phone":"+1 503 666 5107",
    "sg:postcode":"97060",
    "sg:province":"OR",
    "sg:tags":[
        "clergy"
    ],
    "wof:name":"F Orlo Hoye",
    "wof:placetype":"venue"
},
  "geometry": {"coordinates":[-122.433576,45.533786],"type":"Point"}
}