{
  "type": "Feature",
  "properties": {
    "iso:country":"US",
    "sg:address":"1211 SW 6th Ave",
    "sg:city":"Portland",
    "sg:classifiers":[
        {
            "category":"Professional",
            "subcategory":"Lawyer & Legal Services",
            "type":"Services"
        }
    ],
    "sg:phone":"+1 503 222 9981",
    "sg:postcode":"97204",
    "sg:province":"OR",
    "sg:tags":[
        "attorney",
        "law",
        "business"
    ],
    "wof:name":"Evans Iii, Walter H. - Schwabe, Williams",
    "wof:placetype":"venue"
},
  "geometry": {"coordinates":[-122.680457,45.515672],"type":"Point"}
}