{
  "type": "Feature",
  "properties": {
    "addr:full":"4437 Andrea Dr NW Salem OR 97304",
    "addr:housenumber":"4437",
    "addr:postcode":"97304",
    "addr:street":"Andrea Dr Nw",
    "iso:country":"US",
    "sg:address":"4437 Andrea Dr NW",
    "sg:city":"Salem",
    "sg:classifiers":[
        {
            "category":"Shopping",
            "subcategory":"Bicycles & Sporting Goods",
            "type":"Retail Goods"
        }
    ],
    "sg:phone":"+1 503 510 4158",
    "sg:postcode":"97304",
    "sg:province":"OR",
    "wof:name":"Gun Locker",
    "wof:placetype":"venue"
},
  "geometry": {"coordinates":[-123.125604,44.938034],"type":"Point"}
}