{
  "type": "Feature",
  "properties": {
    "addr:full":"4624 N Commercial Ave Portland OR 97217",
    "addr:housenumber":"4624",
    "addr:postcode":"97217",
    "addr:street":"N Commercial Ave",
    "iso:country":"US",
    "sg:address":"4624 N Commercial Ave",
    "sg:city":"Portland",
    "sg:classifiers":[
        {
            "category":"Shopping",
            "subcategory":"Hobbies, Toys, & Games",
            "type":"Retail Goods"
        }
    ],
    "sg:phone":"+1 503 232 5377",
    "sg:postcode":"97217",
    "sg:province":"OR",
    "wof:name":"Millennium Toys & Collect",
    "wof:placetype":"venue"
},
  "geometry": {"coordinates":[-122.671115,45.556465],"type":"Point"}
}