{
  "type": "Feature",
  "properties": {
    "iso:country":"US",
    "sg:address":"84058 N Pacific Hwy",
    "sg:city":"Creswell",
    "sg:classifiers":[
        {
            "category":"Retail",
            "subcategory":"Repair Shop",
            "type":"Services"
        },
        {
            "category":"Home & Garden",
            "subcategory":"Furniture",
            "type":"Retail Goods"
        }
    ],
    "sg:phone":"+1 541 895 2086",
    "sg:postcode":"97426",
    "sg:province":"OR",
    "sg:tags":[
        "store",
        "upholsterer"
    ],
    "wof:name":"Duane Marcottes Furniture & Upholstery",
    "wof:placetype":"venue"
},
  "geometry": {"coordinates":[-123.012124,43.949756],"type":"Point"}
}