{
  "type": "Feature",
  "properties": {
    "addr:full":"8431 SE 36th Ave Portland OR 97222",
    "addr:housenumber":"8431",
    "addr:postcode":"97222",
    "addr:street":"Se 36Th Ave",
    "iso:country":"US",
    "sg:address":"8431 SE 36th Ave",
    "sg:city":"Portland",
    "sg:classifiers":[
        {
            "category":"Education",
            "subcategory":"School",
            "type":"Public Place"
        }
    ],
    "sg:phone":"+1 503 654 2300",
    "sg:postcode":"97222",
    "sg:province":"OR",
    "sg:tags":[
        "home",
        "schooling"
    ],
    "wof:name":"Spell To Write & Read",
    "wof:placetype":"venue"
},
  "geometry": {"coordinates":[-122.626352,45.461648],"type":"Point"}
}