{
  "type": "Feature",
  "properties": {
    "addr:full":"309 SW 6th Ave Portland OR 97204",
    "addr:housenumber":"309",
    "addr:postcode":"97204",
    "addr:street":"Sw 6Th Ave",
    "iso:country":"US",
    "sg:address":"309 SW 6th Ave",
    "sg:city":"Portland",
    "sg:classifiers":[
        {
            "category":"Professional",
            "subcategory":"Advertising",
            "type":"Services"
        }
    ],
    "sg:phone":"+1 503 423 2900",
    "sg:postcode":"97204",
    "sg:province":"OR",
    "sg:tags":[
        "counselor"
    ],
    "wof:name":"Avenue A Razorfish Inc",
    "wof:placetype":"venue"
},
  "geometry": {"coordinates":[-122.677566,45.521155],"type":"Point"}
}