{
  "type": "Feature",
  "properties": {
    "iso:country":"US",
    "sg:address":"6700 NE 105th Ave",
    "sg:city":"Portland",
    "sg:classifiers":[
        {
            "category":"Insurance",
            "subcategory":"Insurance Agent",
            "type":"Services"
        },
        {
            "category":"Insurance",
            "subcategory":"Hazard Insurance",
            "type":"Services"
        },
        {
            "category":"Insurance",
            "subcategory":"Title Insurance",
            "type":"Services"
        },
        {
            "category":"Insurance",
            "subcategory":"Life Insurance",
            "type":"Services"
        }
    ],
    "sg:phone":"+1 503 466 0852",
    "sg:postcode":"97220",
    "sg:province":"OR",
    "sg:tags":[
        "business",
        "auto",
        "commercial",
        "homeowner",
        "motorcycle",
        "renter"
    ],
    "wof:name":"Allstate Insurance Company - Shaheen Yazd",
    "wof:placetype":"venue"
},
  "geometry": {"coordinates":[-122.55466,45.566285],"type":"Point"}
}