{
  "type": "Feature",
  "properties": {
    "iso:country":"US",
    "sg:address":"4616 N Albina Ave",
    "sg:city":"Portland",
    "sg:classifiers":[
        {
            "category":"Social Services",
            "type":"Services"
        },
        {
            "category":"Social Services",
            "subcategory":"Adult Care",
            "type":"Services"
        }
    ],
    "sg:phone":"+1 503 595 2346",
    "sg:postcode":"97217",
    "sg:province":"OR",
    "sg:tags":[
        "centers-adult",
        "day"
    ],
    "sg:website":"http://www.voa.org",
    "wof:name":"Volunteer Of America Oregon",
    "wof:placetype":"venue"
},
  "geometry": {"coordinates":[-122.67494600000001,45.556443],"type":"Point"}
}