{
  "type": "Feature",
  "properties": {
    "iso:country":"US",
    "sg:address":"33947 B St",
    "sg:city":"Eugene",
    "sg:classifiers":[
        {
            "category":"Retail",
            "subcategory":"Auto Repair",
            "type":"Services"
        }
    ],
    "sg:phone":"+1 541 741 2308",
    "sg:postcode":"97405",
    "sg:province":"OR",
    "sg:tags":[
        "repairing",
        "automobile"
    ],
    "wof:name":"Brooks Auto Doctor",
    "wof:placetype":"venue"
},
  "geometry": {"coordinates":[-123.011162,43.994835],"type":"Point"}
}