{
  "type": "Feature",
  "properties": {
    "addr:full":"525 S Bay Rd Toledo OR 97391",
    "addr:housenumber":"525",
    "addr:postcode":"97391",
    "addr:street":"S Bay Rd",
    "iso:country":"US",
    "sg:address":"525 S Bay Rd",
    "sg:city":"Toledo",
    "sg:classifiers":[
        {
            "category":"Manufacturing",
            "subcategory":"Lumber",
            "type":"Manufacturing & Wholesale Goods"
        }
    ],
    "sg:phone":"+1 541 336 3652",
    "sg:postcode":"97391",
    "sg:province":"OR",
    "sg:tags":[
        "operator",
        "company",
        "logging",
        "trucking"
    ],
    "wof:name":"Lee Way Logging Inc",
    "wof:placetype":"venue"
},
  "geometry": {"coordinates":[-123.935914,44.595313],"type":"Point"}
}