{
  "type": "Feature",
  "properties": {
    "iso:country":"US",
    "sg:address":"6700 SW Nyberg St",
    "sg:city":"Tualatin",
    "sg:classifiers":[
        {
            "category":"Social Services",
            "subcategory":"Child Care",
            "type":"Services"
        },
        {
            "category":"Education",
            "subcategory":"Preschool",
            "type":"Public Place"
        },
        {
            "category":"Education",
            "subcategory":"School",
            "type":"Public Place"
        }
    ],
    "sg:phone":"+1 503 692 9006",
    "sg:postcode":"97062",
    "sg:province":"OR",
    "sg:tags":[
        "elementary",
        "day"
    ],
    "wof:name":"Montessori Schools-Northwest Inc",
    "wof:placetype":"venue"
},
  "geometry": {"coordinates":[-122.746002,45.3829],"type":"Point"}
}