{
  "type": "Feature",
  "properties": {
    "iso:country":"US",
    "sg:address":"2180 Cross St",
    "sg:city":"Eugene",
    "sg:classifiers":[
        {
            "category":"Home & Garden",
            "subcategory":"Building Materials",
            "type":"Retail Goods"
        }
    ],
    "sg:phone":"+1 541 689 3805",
    "sg:postcode":"97402",
    "sg:province":"OR",
    "sg:tags":[
        "lumber",
        "lumber-used"
    ],
    "wof:name":"Value Lumber Yards",
    "wof:placetype":"venue"
},
  "geometry": {"coordinates":[-123.126874,44.061373],"type":"Point"}
}