{
  "type": "Feature",
  "properties": {
    "addr:full":"3264 Gateway St Springfield OR 97477",
    "addr:housenumber":"3264",
    "addr:postcode":"97477",
    "addr:street":"Gateway St",
    "iso:country":"US",
    "sg:address":"3264 Gateway St",
    "sg:city":"Springfield",
    "sg:classifiers":[
        {
            "category":"Fast Food",
            "type":"Food & Drink"
        },
        {
            "category":"Restaurant",
            "type":"Food & Drink"
        }
    ],
    "sg:phone":"+1 541 746 8043",
    "sg:postcode":"97477",
    "sg:province":"OR",
    "sg:tags":[
        "mexican"
    ],
    "sg:website":"http://www.tacotime.com",
    "wof:name":"TacoTime",
    "wof:placetype":"venue"
},
  "geometry": {"coordinates":[-123.04172800000001,44.080105],"type":"Point"}
}