{
  "type": "Feature",
  "properties": {
    "addr:full":"511 SW 10th Ave Ste 1114 Portland OR 97205",
    "addr:housenumber":"511",
    "addr:postcode":"97205",
    "addr:street":"Sw 10Th Ave Ste 1114",
    "iso:country":"US",
    "sg:address":"511 SW 10th Ave Ste 1114",
    "sg:city":"Portland",
    "sg:phone":"+1 503 766 4989",
    "sg:postcode":"97205",
    "sg:province":"OR",
    "sg:website":"http://portland.citysearch.com/profile/external/8460376/portland_or/downtown_dental_care_lance_bailey_dds.html?publisher=yellowpages&reference_id=1&placement=ypwebsitemip",
    "wof:name":"Downtown Dental Care - Lance Bailey, DDS",
    "wof:placetype":"venue"
},
  "geometry": {"coordinates":[-122.681425,45.521282],"type":"Point"}
}