{
  "type": "Feature",
  "properties": {
    "addr:full":"19155 Willamette Dr West Linn OR 97068",
    "addr:housenumber":"19155",
    "addr:postcode":"97068",
    "addr:street":"Willamette Dr",
    "iso:country":"US",
    "sg:address":"19155 Willamette Dr",
    "sg:city":"West Linn",
    "sg:classifiers":[
        {
            "category":"Building & Trades",
            "subcategory":"Construction",
            "type":"Services"
        }
    ],
    "sg:phone":"+1 503 722 4480",
    "sg:postcode":"97068",
    "sg:province":"OR",
    "sg:tags":[
        "contractor"
    ],
    "wof:name":"Johnson Dicenzo Construction",
    "wof:placetype":"venue"
},
  "geometry": {"coordinates":[-122.639999,45.386398],"type":"Point"}
}