{
  "type": "Feature",
  "properties": {
    "addr:full":"2038 NW Aloclek Dr Hillsboro OR 97124",
    "addr:housenumber":"2038",
    "addr:postcode":"97124",
    "addr:street":"Nw Aloclek Dr",
    "iso:country":"US",
    "sg:address":"2038 NW Aloclek Dr",
    "sg:city":"Hillsboro",
    "sg:classifiers":[
        {
            "category":"Building & Trades",
            "subcategory":"Construction",
            "type":"Services"
        }
    ],
    "sg:phone":"+1 503 439 0811",
    "sg:postcode":"97124",
    "sg:province":"OR",
    "sg:tags":[
        "floor",
        "laying",
        "contractor"
    ],
    "wof:name":"Tualatin Valley Wood Floors",
    "wof:placetype":"venue"
},
  "geometry": {"coordinates":[-122.89502899999999,45.534946],"type":"Point"}
}