{
  "type": "Feature",
  "properties": {
    "iso:country":"US",
    "sg:address":"4141 Hamrick Rd",
    "sg:city":"Central Point",
    "sg:classifiers":[
        {
            "category":"Building & Trades",
            "subcategory":"Construction",
            "type":"Services"
        }
    ],
    "sg:phone":"+1 541 776 6225",
    "sg:postcode":"97502",
    "sg:province":"OR",
    "sg:tags":[
        "highway",
        "maintenance"
    ],
    "wof:name":"Oregon Highway Department",
    "wof:placetype":"venue"
},
  "geometry": {"coordinates":[-122.892935,42.375528],"type":"Point"}
}