{
  "type": "Feature",
  "properties": {
    "addr:full":"10640 NE Halsey St Portland OR 97220",
    "addr:housenumber":"10640",
    "addr:postcode":"97220",
    "addr:street":"Ne Halsey St",
    "iso:country":"US",
    "sg:address":"10640 NE Halsey St",
    "sg:city":"Portland",
    "sg:classifiers":[
        {
            "category":"Banks & Credit Unions",
            "subcategory":"Financial Services",
            "type":"Services"
        }
    ],
    "sg:phone":"+1 503 715 3630",
    "sg:postcode":"97220",
    "sg:province":"OR",
    "sg:tags":[
        "broker",
        "mortgage"
    ],
    "wof:name":"Owner's Choice Mortgage",
    "wof:placetype":"venue"
},
  "geometry": {"coordinates":[-122.55300099999999,45.533401],"type":"Point"}
}