{
  "type": "Feature",
  "properties": {
    "addr:full":"734 NE Baker St Mcminnville OR 97128",
    "addr:housenumber":"734",
    "addr:postcode":"97128",
    "addr:street":"Ne Baker St",
    "iso:country":"US",
    "sg:address":"734 NE Baker St",
    "sg:city":"Mcminnville",
    "sg:classifiers":[
        {
            "category":"Wholesale",
            "subcategory":"Chemicals & Plastics",
            "type":"Manufacturing & Wholesale Goods"
        }
    ],
    "sg:phone":"+1 503 435 1566",
    "sg:postcode":"97128",
    "sg:province":"OR",
    "sg:tags":[
        "oxygen"
    ],
    "wof:name":"Lincare",
    "wof:placetype":"venue"
},
  "geometry": {"coordinates":[-123.19785299999999,45.21334],"type":"Point"}
}