{
  "type": "Feature",
  "properties": {
    "iso:country":"US",
    "sg:address":"92238 Marcola Rd",
    "sg:city":"Marcola",
    "sg:classifiers":[
        {
            "category":"Retail",
            "subcategory":"Car Wash",
            "type":"Services"
        }
    ],
    "sg:phone":"+1 541 933 1550",
    "sg:postcode":"97454",
    "sg:province":"OR",
    "sg:tags":[
        "automobile",
        "detail",
        "clean"
    ],
    "wof:name":"World Product Sales",
    "wof:placetype":"venue"
},
  "geometry": {"coordinates":[-122.849335,44.184791],"type":"Point"}
}