{
  "type": "Feature",
  "properties": {
    "iso:country":"US",
    "sg:address":"377 SE Fowler St",
    "sg:city":"Roseburg",
    "sg:classifiers":[
        {
            "category":"Professional",
            "subcategory":"Lawyer & Legal Services",
            "type":"Services"
        }
    ],
    "sg:phone":"+1 541 672 2149",
    "sg:postcode":"97470",
    "sg:province":"OR",
    "sg:tags":[
        "attorney"
    ],
    "wof:name":"Schmerer Haake",
    "wof:placetype":"venue"
},
  "geometry": {"coordinates":[-123.339778,43.209769],"type":"Point"}
}