{
  "type": "Feature",
  "properties": {
    "iso:country":"US",
    "sg:address":"112 Memorial Un",
    "sg:city":"Corvallis",
    "sg:classifiers":[
        {
            "category":"Restaurant",
            "type":"Food & Drink"
        }
    ],
    "sg:menulink":"http://www.allmenus.com/or/corvallis/240412-panda-express/menu/",
    "sg:phone":"+1 541 737 6888",
    "sg:postcode":"97331",
    "sg:province":"OR",
    "sg:tags":[
        "asian",
        "chinese"
    ],
    "wof:name":"Panda Express",
    "wof:placetype":"venue"
},
  "geometry": {"coordinates":[-123.27785799999999,44.567012],"type":"Point"}
}