{
  "type": "Feature",
  "properties": {
    "iso:country":"US",
    "sg:address":"501 N Fir St",
    "sg:city":"Medford",
    "sg:classifiers":[
        {
            "category":"Retail",
            "subcategory":"Animal Services",
            "type":"Services"
        }
    ],
    "sg:phone":"+1 541 779 7770",
    "sg:postcode":"97501",
    "sg:province":"OR",
    "sg:tags":[
        "pet",
        "grooming",
        "washing"
    ],
    "wof:name":"Your Precious Pets Inc",
    "wof:placetype":"venue"
},
  "geometry": {"coordinates":[-122.87890400000001,42.330366],"type":"Point"}
}