{
  "type": "Feature",
  "properties": {
    "iso:country":"US",
    "sg:address":"13530 SE 177th Ave",
    "sg:city":"Boring",
    "sg:classifiers":[
        {
            "category":"Professional",
            "subcategory":"Business Services",
            "type":"Services"
        }
    ],
    "sg:phone":"+1 503 658 3746",
    "sg:postcode":"97009",
    "sg:province":"OR",
    "wof:name":"Jeb Enterprises Inc",
    "wof:placetype":"venue"
},
  "geometry": {"coordinates":[-122.48061800000001,45.423392],"type":"Point"}
}