{
  "type": "Feature",
  "properties": {
    "iso:country":"US",
    "sg:address":"3236 SE Johnson Creek Blvd",
    "sg:city":"Portland",
    "sg:classifiers":[
        {
            "category":"Building & Trades",
            "subcategory":"Construction",
            "type":"Services"
        }
    ],
    "sg:phone":"+1 503 654 3134",
    "sg:postcode":"97222",
    "sg:province":"OR",
    "sg:tags":[
        "contractor"
    ],
    "wof:name":"Zenith General Contractors LLC",
    "wof:placetype":"venue"
},
  "geometry": {"coordinates":[-122.62913,45.462571],"type":"Point"}
}