{
  "type": "Feature",
  "properties": {
    "iso:country":"US",
    "sg:address":"100 W 4th St",
    "sg:city":"The Dalles",
    "sg:classifiers":[
        {
            "category":"Personal",
            "type":"Services"
        }
    ],
    "sg:phone":"+1 541 298 4424",
    "sg:postcode":"97058",
    "sg:province":"OR",
    "sg:tags":[
        "therapist",
        "massage"
    ],
    "wof:name":"Mid Columbia Massotherapy",
    "wof:placetype":"venue"
},
  "geometry": {"coordinates":[-121.18657899999999,45.60162],"type":"Point"}
}