{
  "type": "Feature",
  "properties": {
    "iso:country":"US",
    "sg:address":"16430 S Springwater Rd",
    "sg:city":"Oregon City",
    "sg:classifiers":[
        {
            "category":"Manufacturing",
            "subcategory":"Lumber",
            "type":"Manufacturing & Wholesale Goods"
        }
    ],
    "sg:phone":"+1 503 631 7029",
    "sg:postcode":"97045",
    "sg:province":"OR",
    "sg:tags":[
        "operation",
        "timber",
        "tract"
    ],
    "wof:name":"Springwater Trees",
    "wof:placetype":"venue"
},
  "geometry": {"coordinates":[-122.46502,45.366945],"type":"Point"}
}