{
  "type": "Feature",
  "properties": {
    "iso:country":"US",
    "sg:address":"2727 NE 54th Avenue",
    "sg:city":"Portland",
    "sg:classifiers":[
        {
            "category":"Education",
            "subcategory":"School",
            "type":"Public Place"
        }
    ],
    "sg:phone":"+1 503 493 8256",
    "sg:postcode":"97213",
    "sg:province":"OR",
    "wof:name":"Archbishop Howard Catholic School-Dev Office",
    "wof:placetype":"venue"
},
  "geometry": {"coordinates":[-122.607803,45.542476],"type":"Point"}
}