{
  "type": "Feature",
  "properties": {
    "addr:full":"101 High St NE Salem OR 97301",
    "addr:housenumber":"101",
    "addr:postcode":"97301",
    "addr:street":"High St Ne",
    "iso:country":"US",
    "sg:address":"101 High St NE",
    "sg:city":"Salem",
    "sg:classifiers":[
        {
            "category":"Banks & Credit Unions",
            "subcategory":"Bank",
            "type":"Services"
        }
    ],
    "sg:phone":"+1 503 485 2222",
    "sg:postcode":"97301",
    "sg:province":"OR",
    "wof:name":"Willamette Valley Bank",
    "wof:placetype":"venue"
},
  "geometry": {"coordinates":[-123.03664999999999,44.94065],"type":"Point"}
}