{
  "type": "Feature",
  "properties": {
    "addr:full":"415 State St Salem OR 97301",
    "addr:housenumber":"415",
    "addr:postcode":"97301",
    "addr:street":"State St",
    "iso:country":"US",
    "sg:address":"415 State St",
    "sg:city":"Salem",
    "sg:classifiers":[
        {
            "category":"Manufacturing",
            "subcategory":"Printing",
            "type":"Manufacturing & Wholesale Goods"
        }
    ],
    "sg:phone":"+1 503 370 8803",
    "sg:postcode":"97301",
    "sg:province":"OR",
    "sg:tags":[
        "printer"
    ],
    "wof:name":"Minuteman Press",
    "wof:placetype":"venue"
},
  "geometry": {"coordinates":[-123.037352,44.939689],"type":"Point"}
}