{
  "type": "Feature",
  "properties": {
    "iso:country":"US",
    "sg:address":"3130 NW Monte Vista Ter",
    "sg:city":"Portland",
    "sg:classifiers":[
        {
            "category":"Professional",
            "type":"Services"
        }
    ],
    "sg:phone":"+1 503 774 5927",
    "sg:postcode":"97210",
    "sg:province":"OR",
    "wof:name":"Hermann & Co A Prof Corp",
    "wof:placetype":"venue"
},
  "geometry": {"coordinates":[-122.713455,45.525984],"type":"Point"}
}