{
  "type": "Feature",
  "properties": {
    "addr:full":"182 SW Academy St Dallas OR 97338",
    "addr:housenumber":"182",
    "addr:postcode":"97338",
    "addr:street":"Sw Academy St",
    "iso:country":"US",
    "sg:address":"182 SW Academy St",
    "sg:city":"Dallas",
    "sg:classifiers":[
        {
            "category":"Education",
            "subcategory":"Junior College",
            "type":"Public Place"
        }
    ],
    "sg:phone":"+1 503 399 5000",
    "sg:postcode":"97338",
    "sg:province":"OR",
    "sg:tags":[
        "technical",
        "institute"
    ],
    "wof:name":"Chemeketa Community College",
    "wof:placetype":"venue"
},
  "geometry": {"coordinates":[-123.318169,44.923986],"type":"Point"}
}