{
  "type": "Feature",
  "properties": {
    "addr:full":"250 SW Bay Blvd Newport OR 97365",
    "addr:housenumber":"250",
    "addr:postcode":"97365",
    "addr:street":"Sw Bay Blvd",
    "iso:country":"US",
    "sg:address":"250 SW Bay Blvd",
    "sg:city":"Newport",
    "sg:classifiers":[
        {
            "category":"Restaurant",
            "type":"Food & Drink"
        }
    ],
    "sg:phone":"+1 541 574 8890",
    "sg:postcode":"97365",
    "sg:province":"OR",
    "sg:tags":[
        "eating"
    ],
    "wof:name":"Sadas Sushi Bar",
    "wof:placetype":"venue"
},
  "geometry": {"coordinates":[-124.051754,44.63083],"type":"Point"}
}