{
  "type": "Feature",
  "properties": {
    "iso:country":"US",
    "sg:address":"400 Villa Rd",
    "sg:city":"Newberg",
    "sg:classifiers":[
        {
            "category":"Social Services",
            "type":"Services"
        }
    ],
    "sg:phone":"+1 503 537 1907",
    "sg:postcode":"97132",
    "sg:province":"OR",
    "sg:tags":[
        "support",
        "group"
    ],
    "sg:website":"www.womenofpurpose.com",
    "wof:name":"Women Of Purpose Intl",
    "wof:placetype":"venue"
},
  "geometry": {"coordinates":[-122.962642,45.302984],"type":"Point"}
}