{
  "type": "Feature",
  "properties": {
    "iso:country":"US",
    "sg:address":"624 A St",
    "sg:city":"Ashland",
    "sg:classifiers":[
        {
            "category":"Recreation",
            "type":"Entertainment"
        }
    ],
    "sg:phone":"+1 541 552 1040",
    "sg:postcode":"97520",
    "sg:province":"OR",
    "sg:tags":[
        "instruction",
        "yoga"
    ],
    "wof:name":"Ashland Dahn Ctr",
    "wof:placetype":"venue"
},
  "geometry": {"coordinates":[-122.705628,42.197781],"type":"Point"}
}