{
  "type": "Feature",
  "properties": {
    "iso:country":"US",
    "sg:address":"5065 S Pacific Hwy",
    "sg:city":"Phoenix",
    "sg:classifiers":[
        {
            "category":"Building & Trades",
            "subcategory":"Landscaping Services",
            "type":"Services"
        }
    ],
    "sg:phone":"+1 541 535 8920",
    "sg:postcode":"97535",
    "sg:province":"OR",
    "sg:tags":[
        "tree"
    ],
    "sg:website":"www.summittforests.com",
    "wof:name":"Summitt Forests Inc",
    "wof:placetype":"venue"
},
  "geometry": {"coordinates":[-122.806671,42.26587],"type":"Point"}
}