{
  "type": "Feature",
  "properties": {
    "iso:country":"US",
    "sg:address":"2726 19th Ave",
    "sg:city":"Forest Grove",
    "sg:classifiers":[
        {
            "category":"Health Services",
            "subcategory":"Health Practitioner",
            "type":"Services"
        }
    ],
    "sg:phone":"+1 503 357 7822",
    "sg:postcode":"97116",
    "sg:province":"OR",
    "sg:tags":[
        "therapist",
        "physical"
    ],
    "wof:name":"Cascadia Physical Therapy Inc",
    "wof:placetype":"venue"
},
  "geometry": {"coordinates":[-123.097696,45.518258],"type":"Point"}
}