{
  "type": "Feature",
  "properties": {
    "iso:country":"US",
    "sg:address":"7449 Gale Rd",
    "sg:city":"Bonanza",
    "sg:phone":"+1 541 545 6779",
    "sg:postcode":"97623",
    "sg:province":"OR",
    "sg:tags":[
        "farm",
        "field",
        "crop"
    ],
    "wof:name":"Robert Parsons",
    "wof:placetype":"venue"
},
  "geometry": {"coordinates":[-121.270697,42.159403],"type":"Point"}
}