{
  "type": "Feature",
  "properties": {
    "iso:country":"US",
    "sg:address":"519 W 3rd St",
    "sg:city":"Newberg",
    "sg:classifiers":[
        {
            "category":"Retail",
            "subcategory":"Repair Shop",
            "type":"Services"
        }
    ],
    "sg:phone":"+1 503 538 5492",
    "sg:postcode":"97132",
    "sg:province":"OR",
    "sg:tags":[
        "hardware",
        "armature",
        "rewinding",
        "supp"
    ],
    "wof:name":"Midget Motors",
    "wof:placetype":"venue"
},
  "geometry": {"coordinates":[-122.9836,45.298773],"type":"Point"}
}