{
  "type": "Feature",
  "properties": {
    "addr:full":"3118 Horseshoe Lake Rd NE St Paul OR 97137",
    "addr:housenumber":"3118",
    "addr:postcode":"97137",
    "addr:street":"Horseshoe Lake Rd Ne",
    "iso:country":"US",
    "sg:address":"3118 Horseshoe Lake Rd NE",
    "sg:city":"St Paul",
    "sg:classifiers":[
        {
            "category":"Farming",
            "subcategory":"Orchard",
            "type":"Manufacturing & Wholesale Goods"
        },
        {
            "category":"Wholesale",
            "subcategory":"Fruits & Vegetables",
            "type":"Manufacturing & Wholesale Goods"
        }
    ],
    "sg:phone":"+1 503 633 4355",
    "sg:postcode":"97137",
    "sg:province":"OR",
    "sg:tags":[
        "shipper",
        "apple",
        "peach",
        "jelly",
        "mfr",
        "jam"
    ],
    "wof:name":"Ernst Family Farms",
    "wof:placetype":"venue"
},
  "geometry": {"coordinates":[-122.999043,45.211557],"type":"Point"}
}