{
  "type": "Feature",
  "properties": {
    "iso:country":"US",
    "sg:address":"23233 S Ridge Rd",
    "sg:city":"Beavercreek",
    "sg:classifiers":[
        {
            "category":"Building & Trades",
            "subcategory":"Construction",
            "type":"Services"
        }
    ],
    "sg:phone":"+1 503 632 8364",
    "sg:postcode":"97004",
    "sg:province":"OR",
    "sg:tags":[
        "steel",
        "erectors"
    ],
    "wof:name":"Skyline Steel Inc",
    "wof:placetype":"venue"
},
  "geometry": {"coordinates":[-122.45469300000001,45.272008],"type":"Point"}
}