{
  "type": "Feature",
  "properties": {
    "iso:country":"US",
    "sg:address":"6576 Salmon River Hwy",
    "sg:city":"Otis",
    "sg:classifiers":[
        {
            "category":"Bars & Pubs",
            "type":"Food & Drink"
        }
    ],
    "sg:phone":"+1 541 994 8819",
    "sg:postcode":"97368",
    "sg:province":"OR",
    "sg:tags":[
        "drinking"
    ],
    "wof:name":"Salmon River Hideaway",
    "wof:placetype":"venue"
},
  "geometry": {"coordinates":[-123.857647,45.021321],"type":"Point"}
}