{
  "type": "Feature",
  "properties": {
    "iso:country":"US",
    "sg:address":"4250 Blanchet Ave NE",
    "sg:city":"St Paul",
    "sg:classifiers":[
        {
            "category":"Home & Garden",
            "subcategory":"Garden Supply",
            "type":"Retail Goods"
        }
    ],
    "sg:phone":"+1 503 633 4281",
    "sg:postcode":"97137",
    "sg:province":"OR",
    "sg:tags":[
        "fertilizer"
    ],
    "sg:website":"www.marionag.com",
    "wof:name":"Marion AG Svc Inc",
    "wof:placetype":"venue"
},
  "geometry": {"coordinates":[-122.974881,45.209594],"type":"Point"}
}