{
  "type": "Feature",
  "properties": {
    "iso:country":"US",
    "sg:address":"212 S Main St",
    "sg:city":"Condon",
    "sg:classifiers":[
        {
            "category":"Cinema",
            "subcategory":"Movie Theater",
            "type":"Entertainment"
        }
    ],
    "sg:phone":"+1 541 384 2120",
    "sg:postcode":"97823",
    "sg:province":"OR",
    "wof:name":"Liberty Theatre",
    "wof:placetype":"venue"
},
  "geometry": {"coordinates":[-120.184877,45.236019],"type":"Point"}
}