{
  "type": "Feature",
  "properties": {
    "addr:full":"403 SE Caruthers St Portland OR 97214",
    "addr:housenumber":"403",
    "addr:postcode":"97214",
    "addr:street":"Se Caruthers St",
    "iso:country":"US",
    "sg:address":"403 SE Caruthers St",
    "sg:city":"Portland",
    "sg:classifiers":[
        {
            "category":"Building & Trades",
            "subcategory":"Electrical",
            "type":"Services"
        }
    ],
    "sg:phone":"+1 503 282 6515",
    "sg:postcode":"97214",
    "sg:province":"OR",
    "sg:tags":[
        "engineering",
        "general"
    ],
    "sg:website":"www.stacywitbeck.com",
    "wof:name":"Stacy & Witbeck Inc",
    "wof:placetype":"venue"
},
  "geometry": {"coordinates":[-122.660965,45.50593],"type":"Point"}
}