{
  "type": "Feature",
  "properties": {
    "iso:country":"US",
    "sg:address":"4000 SE International Way Ste F204",
    "sg:city":"Portland",
    "sg:classifiers":[
        {
            "category":"Banks & Credit Unions",
            "subcategory":"Financial Services",
            "type":"Services"
        }
    ],
    "sg:phone":"+1 503 786 8838",
    "sg:postcode":"97222",
    "sg:province":"OR",
    "sg:tags":[
        "broker",
        "mortgage"
    ],
    "wof:name":"Integrity Mortgage Group",
    "wof:placetype":"venue"
},
  "geometry": {"coordinates":[-122.621403,45.439363],"type":"Point"}
}