{
  "type": "Feature",
  "properties": {
    "iso:country":"US",
    "sg:address":"180 S Pacific Hwy",
    "sg:city":"Woodburn",
    "sg:classifiers":[
        {
            "category":"Building & Trades",
            "subcategory":"Construction",
            "type":"Services"
        }
    ],
    "sg:phone":"+1 503 981 8147",
    "sg:postcode":"97071",
    "sg:province":"OR",
    "sg:tags":[
        "general",
        "contractor"
    ],
    "sg:website":"www.oregonpacificconstruction.com",
    "wof:name":"Oregon Pacific Construction",
    "wof:placetype":"venue"
},
  "geometry": {"coordinates":[-122.845742,45.13483],"type":"Point"}
}