{
  "type": "Feature",
  "properties": {
    "iso:country":"US",
    "sg:address":"424 Wilbur Rd",
    "sg:city":"Roseburg",
    "sg:classifiers":[
        {
            "category":"Building & Trades",
            "subcategory":"Construction",
            "type":"Services"
        }
    ],
    "sg:phone":"+1 541 672 4545",
    "sg:postcode":"97470",
    "sg:province":"OR",
    "sg:tags":[
        "excavating",
        "contractor"
    ],
    "wof:name":"Winchester Rock Products",
    "wof:placetype":"venue"
},
  "geometry": {"coordinates":[-123.349825,43.316644],"type":"Point"}
}