{
  "type": "Feature",
  "properties": {
    "addr:full":"14344 SW 72nd Ave Portland OR 97223",
    "addr:housenumber":"14344",
    "addr:postcode":"97223",
    "addr:street":"Sw 72Nd Ave",
    "iso:country":"US",
    "sg:address":"14344 SW 72nd Ave",
    "sg:city":"Portland",
    "sg:classifiers":[
        {
            "category":"Freight",
            "type":"Transportation"
        }
    ],
    "sg:phone":"+1 503 598 9255",
    "sg:postcode":"97223",
    "sg:province":"OR",
    "sg:tags":[
        "arrangement"
    ],
    "wof:name":"Airborne",
    "wof:placetype":"venue"
},
  "geometry": {"coordinates":[-122.748981,45.417067],"type":"Point"}
}