{
  "type": "Feature",
  "properties": {
    "addr:full":"13015 Hwy 39 Klamath Falls OR 97603",
    "addr:housenumber":"13015",
    "addr:postcode":"97603",
    "addr:street":"Hwy 39",
    "iso:country":"US",
    "sg:address":"13015 Hwy 39",
    "sg:city":"Klamath Falls",
    "sg:classifiers":[
        {
            "category":"Professional",
            "subcategory":"Detective & Security Services",
            "type":"Services"
        }
    ],
    "sg:phone":"+1 541 884 3363",
    "sg:postcode":"97603",
    "sg:province":"OR",
    "sg:tags":[
        "guard",
        "patrol"
    ],
    "wof:name":"Colt Security Agency",
    "wof:placetype":"venue"
},
  "geometry": {"coordinates":[-121.698359,42.112898],"type":"Point"}
}