{
  "type": "Feature",
  "properties": {
    "iso:country":"US",
    "sg:address":"3486 Orchard Heights Rd NW",
    "sg:city":"Salem",
    "sg:classifiers":[
        {
            "category":"Farming",
            "subcategory":"Farm",
            "type":"Manufacturing & Wholesale Goods"
        }
    ],
    "sg:phone":"+1 503 362 2190",
    "sg:postcode":"97304",
    "sg:province":"OR",
    "sg:tags":[
        "crop",
        "general"
    ],
    "wof:name":"Delhd Inc",
    "wof:placetype":"venue"
},
  "geometry": {"coordinates":[-123.099767,44.960877],"type":"Point"}
}