{
  "type": "Feature",
  "properties": {
    "iso:country":"US",
    "sg:address":"3030 NE Weidler St",
    "sg:city":"Portland",
    "sg:classifiers":[
        {
            "category":"Cinema",
            "subcategory":"Movie Rental",
            "type":"Entertainment"
        }
    ],
    "sg:phone":"+1 503 287 7007",
    "sg:postcode":"97232",
    "sg:province":"OR",
    "sg:tags":[
        "game",
        "video"
    ],
    "sg:website":"www.hollywoodvideo.com/storeloca...",
    "wof:name":"Hollywood Video",
    "wof:placetype":"venue"
},
  "geometry": {"coordinates":[-122.635002,45.5345],"type":"Point"}
}