{
  "type": "Feature",
  "properties": {
    "iso:country":"US",
    "sg:address":"4350 Dillard Rd",
    "sg:city":"Eugene",
    "sg:classifiers":[
        {
            "category":"Home & Garden",
            "subcategory":"Garden Supply",
            "type":"Retail Goods"
        },
        {
            "category":"Manufacturing",
            "subcategory":"Paper Products",
            "type":"Manufacturing & Wholesale Goods"
        }
    ],
    "sg:phone":"+1 541 484 1164",
    "sg:postcode":"97405",
    "sg:province":"OR",
    "sg:tags":[
        "plant",
        "bamboo"
    ],
    "wof:name":"Hedge Between",
    "wof:placetype":"venue"
},
  "geometry": {"coordinates":[-123.07377,44.005384],"type":"Point"}
}