{
  "type": "Feature",
  "properties": {
    "iso:country":"US",
    "sg:address":"690 W 1st Ave",
    "sg:city":"Eugene",
    "sg:classifiers":[
        {
            "category":"Professional",
            "subcategory":"Detective & Security Services",
            "type":"Services"
        }
    ],
    "sg:phone":"+1 541 485 8133",
    "sg:postcode":"97402",
    "sg:province":"OR",
    "sg:tags":[
        "car",
        "guard",
        "patrol"
    ],
    "wof:name":"Oregon Armored Service Inc",
    "wof:placetype":"venue"
},
  "geometry": {"coordinates":[-123.1027,44.05866],"type":"Point"}
}