{
  "type": "Feature",
  "properties": {
    "addr:full":"3210 SW Upper Dr Portland OR 97201",
    "addr:housenumber":"3210",
    "addr:postcode":"97201",
    "addr:street":"Sw Upper Dr",
    "iso:country":"US",
    "sg:address":"3210 SW Upper Dr",
    "sg:city":"Portland",
    "sg:phone":"+1 503 209 1017",
    "sg:postcode":"97201",
    "sg:province":"OR",
    "sg:tags":[
        "wholesale",
        "equipment"
    ],
    "wof:name":"ABI Restaurant Supply",
    "wof:placetype":"venue"
},
  "geometry": {"coordinates":[-122.708732,45.505699],"type":"Point"}
}