{
  "type": "Feature",
  "properties": {
    "addr:full":"1111 SW 10th Ave Portland OR 97205",
    "addr:housenumber":"1111",
    "addr:postcode":"97205",
    "addr:street":"Sw 10Th Ave",
    "iso:country":"US",
    "sg:address":"1111 SW 10th Ave",
    "sg:city":"Portland",
    "sg:classifiers":[
        {
            "category":"Sports & Exercise",
            "subcategory":"Gym",
            "type":"Entertainment"
        }
    ],
    "sg:phone":"+1 503 403 9040",
    "sg:postcode":"97205",
    "sg:province":"OR",
    "sg:tags":[
        "trainer"
    ],
    "sg:website":"www.portlandpersonaltraining.com",
    "wof:name":"Portland Personal Training and Weight Loss LLC",
    "wof:placetype":"venue"
},
  "geometry": {"coordinates":[-122.684073,45.517066],"type":"Point"}
}