{
  "type": "Feature",
  "properties": {
    "addr:full":"8700 Trask River Rd Tillamook OR 97141",
    "addr:postcode":"8700;97141",
    "addr:street":"Trask River Rd",
    "iso:country":"US",
    "sg:address":"8700 Trask River Rd",
    "sg:city":"Tillamook",
    "sg:classifiers":[
        {
            "category":"Manufacturing",
            "subcategory":"Lumber",
            "type":"Manufacturing & Wholesale Goods"
        }
    ],
    "sg:phone":"+1 503 842 3109",
    "sg:postcode":"97141",
    "sg:province":"OR",
    "sg:tags":[
        "product",
        "forest",
        "gathering"
    ],
    "wof:name":"Kottre Tree Farms",
    "wof:placetype":"venue"
},
  "geometry": {"coordinates":[-123.777067,45.44226],"type":"Point"}
}