{
  "type": "Feature",
  "properties": {
    "addr:full":"8425 SW Ashford St Portland OR 97224",
    "addr:housenumber":"8425",
    "addr:postcode":"97224",
    "addr:street":"Sw Ashford St",
    "iso:country":"US",
    "sg:address":"8425 SW Ashford St",
    "sg:city":"Portland",
    "sg:classifiers":[
        {
            "category":"Professional",
            "subcategory":"Business Services",
            "type":"Services"
        }
    ],
    "sg:phone":"+1 503 624 2139",
    "sg:postcode":"97224",
    "sg:province":"OR",
    "wof:name":"Primitive Racing",
    "wof:placetype":"venue"
},
  "geometry": {"coordinates":[-122.763605,45.408268],"type":"Point"}
}