{
  "type": "Feature",
  "properties": {
    "iso:country":"US",
    "sg:address":"1661 Edgewater St NW",
    "sg:city":"Salem",
    "sg:classifiers":[
        {
            "category":"Health Services",
            "subcategory":"Health Practitioner",
            "type":"Services"
        }
    ],
    "sg:phone":"+1 503 391 5542",
    "sg:postcode":"97304",
    "sg:province":"OR",
    "wof:name":"West Slem Physcl Therapy Rehab",
    "wof:placetype":"venue"
},
  "geometry": {"coordinates":[-123.069676,44.936204],"type":"Point"}
}