{
  "type": "Feature",
  "properties": {
    "iso:country":"US",
    "sg:address":"8890 SE Mcloughlin Blvd",
    "sg:city":"Portland",
    "sg:classifiers":[
        {
            "category":"Building & Trades",
            "subcategory":"Cleaning & Sanitation",
            "type":"Services"
        },
        {
            "category":"Building & Trades",
            "subcategory":"Construction",
            "type":"Services"
        }
    ],
    "sg:phone":"+1 503 353 1650",
    "sg:postcode":"97222",
    "sg:province":"OR",
    "sg:tags":[
        "pointing",
        "waterproofing",
        "tuck",
        "mason",
        "sandblasting",
        "contractor"
    ],
    "sg:website":"http://www.drmasonry.com",
    "wof:name":"D & R Masonry Restoration",
    "wof:placetype":"venue"
},
  "geometry": {"coordinates":[-122.639641,45.459251],"type":"Point"}
}