{
  "type": "Feature",
  "properties": {
    "iso:country":"US",
    "sg:address":"10965 Barrett Way",
    "sg:city":"Portland",
    "sg:classifiers":[
        {
            "category":"Shopping",
            "subcategory":"Gifts & Souvenirs",
            "type":"Retail Goods"
        }
    ],
    "sg:phone":"+1 503 526 0505",
    "sg:postcode":"97229",
    "sg:province":"OR",
    "wof:name":"Global Gifts & Collectibl",
    "wof:placetype":"venue"
},
  "geometry": {"coordinates":[-122.789428,45.539097],"type":"Point"}
}