{
  "type": "Feature",
  "properties": {
    "addr:full":"13025 SW Barberry Dr Beaverton OR 97008",
    "addr:housenumber":"13025",
    "addr:postcode":"97008",
    "addr:street":"Sw Barberry Dr",
    "iso:country":"US",
    "sg:address":"13025 SW Barberry Dr",
    "sg:city":"Beaverton",
    "sg:classifiers":[
        {
            "category":"Building & Trades",
            "subcategory":"Locksmith",
            "type":"Services"
        }
    ],
    "sg:phone":"+1 503 716 9452",
    "sg:postcode":"97008",
    "sg:province":"OR",
    "sg:tags":[
        "key"
    ],
    "wof:name":"24 All Day Locksmith",
    "wof:placetype":"venue"
},
  "geometry": {"coordinates":[-122.81114700000001,45.462921],"type":"Point"}
}