{
  "type": "Feature",
  "properties": {
    "iso:country":"US",
    "sg:address":"1677 E Harbor St",
    "sg:city":"Warrenton",
    "sg:classifiers":[
        {
            "category":"Food & Beverages",
            "subcategory":"Groceries & Convenience Stores",
            "type":"Retail Goods"
        }
    ],
    "sg:phone":"+1 503 861 2511",
    "sg:postcode":"97146",
    "sg:province":"OR",
    "wof:name":"Harbor St Cigarettes & More",
    "wof:placetype":"venue"
},
  "geometry": {"coordinates":[-123.89955,46.163055],"type":"Point"}
}