{
  "type": "Feature",
  "properties": {
    "addr:full":"1570 W Airway Rd Lebanon OR 97355",
    "addr:housenumber":"1570",
    "addr:postcode":"97355",
    "addr:street":"W Airway Rd",
    "iso:country":"US",
    "sg:address":"1570 W Airway Rd",
    "sg:city":"Lebanon",
    "sg:classifiers":[
        {
            "category":"Freight",
            "type":"Transportation"
        }
    ],
    "sg:phone":"+1 541 258 7867",
    "sg:postcode":"97355",
    "sg:province":"OR",
    "sg:tags":[
        "commercial",
        "storage"
    ],
    "wof:name":"Airway Mini Storage",
    "wof:placetype":"venue"
},
  "geometry": {"coordinates":[-122.92785499999999,44.531334],"type":"Point"}
}