{
  "type": "Feature",
  "properties": {
    "addr:full":"8974 SW Tualatin Sherwood Rd Tualatin OR 97062",
    "addr:housenumber":"8974",
    "addr:postcode":"97062",
    "addr:street":"Sw Tualatin Sherwood Rd",
    "iso:country":"US",
    "sg:address":"8974 SW Tualatin Sherwood Rd",
    "sg:city":"Tualatin",
    "sg:classifiers":[
        {
            "category":"Retail",
            "subcategory":"Funeral Services",
            "type":"Services"
        }
    ],
    "sg:phone":"+1 503 885 7800",
    "sg:postcode":"97062",
    "sg:province":"OR",
    "sg:tags":[
        "crematory"
    ],
    "wof:name":"Crown Memorial Center",
    "wof:placetype":"venue"
},
  "geometry": {"coordinates":[-122.76940999999999,45.380738],"type":"Point"}
}