{
  "type": "Feature",
  "properties": {
    "iso:country":"US",
    "sg:address":"5590 Kilchurn Ave",
    "sg:city":"Lake Oswego",
    "sg:classifiers":[
        {
            "category":"Banks & Credit Unions",
            "subcategory":"Financial Services",
            "type":"Services"
        }
    ],
    "sg:phone":"+1 503 968 9181",
    "sg:postcode":"97035",
    "sg:province":"OR",
    "sg:tags":[
        "annuity",
        "insurance"
    ],
    "wof:name":"Grosvenor Group Investment Svc",
    "wof:placetype":"venue"
},
  "geometry": {"coordinates":[-122.731581,45.43198],"type":"Point"}
}