{
  "type": "Feature",
  "properties": {
    "addr:full":"8044 N Richmond Ave Portland OR 97203",
    "addr:housenumber":"8044",
    "addr:postcode":"97203",
    "addr:street":"N Richmond Ave",
    "iso:country":"US",
    "sg:address":"8044 N Richmond Ave",
    "sg:city":"Portland",
    "sg:classifiers":[
        {
            "category":"Organizations",
            "subcategory":"Religious Organization",
            "type":"Services"
        }
    ],
    "sg:phone":"+1 503 286 0613",
    "sg:postcode":"97203",
    "sg:province":"OR",
    "sg:tags":[
        "church"
    ],
    "sg:website":"www.stjohnschristian.com",
    "wof:name":"St. Johns Christian Church",
    "wof:placetype":"venue"
},
  "geometry": {"coordinates":[-122.749427,45.590672],"type":"Point"}
}