{
  "type": "Feature",
  "properties": {
    "iso:country":"US",
    "sg:address":"29580 SW Farmington Rd",
    "sg:city":"Hillsboro",
    "sg:classifiers":[
        {
            "category":"Building & Trades",
            "subcategory":"Construction",
            "type":"Services"
        }
    ],
    "sg:phone":"+1 503 701 7520",
    "sg:postcode":"97123",
    "sg:province":"OR",
    "sg:tags":[
        "contractor",
        "fence-sales"
    ],
    "sg:website":"http://msdconst.net/default.aspx",
    "wof:name":"MSD Construction",
    "wof:placetype":"venue"
},
  "geometry": {"coordinates":[-122.982518,45.444432],"type":"Point"}
}