{
  "type": "Feature",
  "properties": {
    "addr:full":"2656 SW Willowbrook Ave Gresham OR 97080",
    "addr:housenumber":"2656",
    "addr:postcode":"97080",
    "addr:street":"Sw Willowbrook Ave",
    "iso:country":"US",
    "sg:address":"2656 SW Willowbrook Ave",
    "sg:city":"Gresham",
    "sg:classifiers":[
        {
            "category":"Food & Beverages",
            "subcategory":"Groceries & Convenience Stores",
            "type":"Retail Goods"
        }
    ],
    "sg:phone":"+1 503 255 1074",
    "sg:postcode":"97080",
    "sg:province":"OR",
    "wof:name":"Norwoods Am/PM",
    "wof:placetype":"venue"
},
  "geometry": {"coordinates":[-122.45092099999999,45.480259],"type":"Point"}
}