{
  "type": "Feature",
  "properties": {
    "addr:full":"9226 SE Division St Portland OR 97266",
    "addr:housenumber":"9226",
    "addr:postcode":"97266",
    "addr:street":"Se Division St",
    "iso:country":"US",
    "sg:address":"9226 SE Division St",
    "sg:city":"Portland",
    "sg:classifiers":[
        {
            "category":"Restaurant",
            "type":"Food & Drink"
        }
    ],
    "sg:menulink":"http://www.allmenus.com/or/portland/128653-subway/menu/",
    "sg:phone":"+1 503 771 2325",
    "sg:postcode":"97266",
    "sg:province":"OR",
    "sg:tags":[
        "american",
        "sandwich"
    ],
    "wof:name":"Subway",
    "wof:placetype":"venue"
},
  "geometry": {"coordinates":[-122.567442,45.503521],"type":"Point"}
}