{
  "type": "Feature",
  "properties": {
    "iso:country":"US",
    "sg:address":"2194 SE 182nd Ave",
    "sg:city":"Portland",
    "sg:classifiers":[
        {
            "category":"Shopping",
            "subcategory":"Clothing, Apparel, & Fashions",
            "type":"Retail Goods"
        }
    ],
    "sg:phone":"+1 503 465 6869",
    "sg:postcode":"97233",
    "sg:province":"OR",
    "sg:tags":[
        "wig",
        "toupee",
        "hairpiece"
    ],
    "wof:name":"Wigs Wear House LLC",
    "wof:placetype":"venue"
},
  "geometry": {"coordinates":[-122.475584,45.509107],"type":"Point"}
}