{
  "type": "Feature",
  "properties": {
    "iso:country":"US",
    "sg:address":"5126 NE M L King Boulevard",
    "sg:city":"Portland",
    "sg:classifiers":[
        {
            "category":"Personal",
            "subcategory":"Nail Salon",
            "type":"Services"
        }
    ],
    "sg:phone":"+1 503 287 0583",
    "sg:postcode":"97211",
    "sg:province":"OR",
    "wof:name":"Tiffany Nail Salon",
    "wof:placetype":"venue"
},
  "geometry": {"coordinates":[-122.66125599999999,45.560303],"type":"Point"}
}