{
  "type": "Feature",
  "properties": {
    "iso:country":"US",
    "sg:address":"2484 River Rd",
    "sg:city":"Eugene",
    "sg:classifiers":[
        {
            "category":"Health Services",
            "subcategory":"Doctor",
            "type":"Services"
        }
    ],
    "sg:phone":"+1 541 222 7650",
    "sg:postcode":"97404",
    "sg:province":"OR",
    "sg:tags":[
        "physician",
        "surgeon"
    ],
    "wof:name":"Barrington Shulenberger Rosze Dnp Fnp Anp",
    "wof:placetype":"venue"
},
  "geometry": {"coordinates":[-123.129914,44.100062],"type":"Point"}
}