{
  "type": "Feature",
  "properties": {
    "iso:country":"US",
    "sg:address":"10343 NW Pacific Coast Hwy",
    "sg:city":"Seal Rock",
    "sg:classifiers":[
        {
            "category":"Shopping",
            "type":"Retail Goods"
        }
    ],
    "sg:phone":"+1 541 563 8789",
    "sg:postcode":"97376",
    "sg:province":"OR",
    "sg:tags":[
        "art",
        "gallery",
        "merchandise",
        "dealer"
    ],
    "wof:name":"Heart Song",
    "wof:placetype":"venue"
},
  "geometry": {"coordinates":[-124.082566,44.497434],"type":"Point"}
}