{
  "type": "Feature",
  "properties": {
    "iso:country":"US",
    "sg:address":"1201 Progress Drive #88",
    "sg:city":"Medford",
    "sg:classifiers":[
        {
            "category":"Personal",
            "type":"Services"
        }
    ],
    "sg:phone":"+1 541 261 3335",
    "sg:postcode":"97504",
    "sg:province":"OR",
    "sg:tags":[
        "planning",
        "wedding"
    ],
    "sg:website":"www.magickalmemories.org",
    "wof:name":"Magickal Memories",
    "wof:placetype":"venue"
},
  "geometry": {"coordinates":[-122.871644,42.345058],"type":"Point"}
}