{
  "type": "Feature",
  "properties": {
    "iso:country":"US",
    "sg:address":"1372 Oak St",
    "sg:city":"Eugene",
    "sg:classifiers":[
        {
            "category":"Professional",
            "subcategory":"Accounting & Tax Preparation",
            "type":"Services"
        }
    ],
    "sg:phone":"+1 541 686 1633",
    "sg:postcode":"97401",
    "sg:province":"OR",
    "sg:tags":[
        "consultant",
        "bookkeeper"
    ],
    "wof:name":"Best Tax Service",
    "wof:placetype":"venue"
},
  "geometry": {"coordinates":[-123.09129,44.044673],"type":"Point"}
}