{
  "type": "Feature",
  "properties": {
    "iso:country":"US",
    "sg:address":"1517 NE 8th Ave",
    "sg:city":"Portland",
    "sg:classifiers":[
        {
            "category":"Building & Trades",
            "subcategory":"Cleaning & Sanitation",
            "type":"Services"
        }
    ],
    "sg:phone":"+1 503 254 6242",
    "sg:postcode":"97232",
    "sg:province":"OR",
    "sg:tags":[
        "ventilating",
        "system"
    ],
    "sg:website":"www.indooreco.com",
    "wof:name":"Indoor ECO",
    "wof:placetype":"venue"
},
  "geometry": {"coordinates":[-122.65766600000001,45.534231],"type":"Point"}
}