{
  "type": "Feature",
  "properties": {
    "iso:country":"US",
    "sg:address":"9800 SW Beaverton-Hillsdale Hwy",
    "sg:city":"Beaverton",
    "sg:classifiers":[
        {
            "category":"Professional",
            "subcategory":"Computer Services",
            "type":"Services"
        }
    ],
    "sg:phone":"+1 503 392 3621",
    "sg:postcode":"97005",
    "sg:province":"OR",
    "sg:tags":[
        "information",
        "technology"
    ],
    "wof:name":"Cogent IT",
    "wof:placetype":"venue"
},
  "geometry": {"coordinates":[-122.77839899999999,45.486532],"type":"Point"}
}