{
  "type": "Feature",
  "properties": {
    "addr:full":"17721 NE Riverside Parkway Portland OR 97230",
    "addr:housenumber":"17721",
    "addr:postcode":"97230",
    "addr:street":"Ne Riverside Parkway",
    "iso:country":"US",
    "sg:address":"17721 NE Riverside Parkway",
    "sg:city":"Portland",
    "sg:classifiers":[
        {
            "category":"Building & Trades",
            "subcategory":"Construction",
            "type":"Services"
        }
    ],
    "sg:phone":"+1 503 907 0070",
    "sg:postcode":"97230",
    "sg:province":"OR",
    "sg:tags":[
        "contractor"
    ],
    "wof:name":"Csi Construction",
    "wof:placetype":"venue"
},
  "geometry": {"coordinates":[-122.480661,45.554376],"type":"Point"}
}