{
  "type": "Feature",
  "properties": {
    "addr:full":"2055 SW Leewood Dr Beaverton OR 97006",
    "addr:housenumber":"2055",
    "addr:postcode":"97006",
    "addr:street":"Sw Leewood Dr",
    "iso:country":"US",
    "sg:address":"2055 SW Leewood Dr",
    "sg:city":"Beaverton",
    "sg:classifiers":[
        {
            "category":"Building & Trades",
            "subcategory":"Construction",
            "type":"Services"
        }
    ],
    "sg:phone":"+1 503 642 4602",
    "sg:postcode":"97006",
    "sg:province":"OR",
    "sg:tags":[
        "contractor"
    ],
    "wof:name":"David Kirkman Masonary",
    "wof:placetype":"venue"
},
  "geometry": {"coordinates":[-122.889729,45.505159],"type":"Point"}
}