{
  "type": "Feature",
  "properties": {
    "iso:country":"US",
    "sg:address":"2505 Pacific Blvd SE",
    "sg:city":"Albany",
    "sg:classifiers":[
        {
            "category":"Retail",
            "subcategory":"Auto Rental",
            "type":"Services"
        }
    ],
    "sg:phone":"+1 541 967 4355",
    "sg:postcode":"97321",
    "sg:province":"OR",
    "sg:tags":[
        "passenger",
        "car"
    ],
    "wof:name":"Whitnell Car Rental",
    "wof:placetype":"venue"
},
  "geometry": {"coordinates":[-123.074422,44.637132],"type":"Point"}
}