{
  "type": "Feature",
  "properties": {
    "addr:full":"720 S Mountain Ave Ashland OR 97520",
    "addr:housenumber":"720",
    "addr:postcode":"97520",
    "addr:street":"S Mountain Ave",
    "iso:country":"US",
    "sg:address":"720 S Mountain Ave",
    "sg:city":"Ashland",
    "sg:classifiers":[
        {
            "category":"Building & Trades",
            "subcategory":"Construction",
            "type":"Services"
        }
    ],
    "sg:phone":"+1 541 488 3276",
    "sg:postcode":"97520",
    "sg:province":"OR",
    "sg:tags":[
        "house"
    ],
    "wof:name":"Morris Construction",
    "wof:placetype":"venue"
},
  "geometry": {"coordinates":[-122.69920399999999,42.182408],"type":"Point"}
}