{
  "type": "Feature",
  "properties": {
    "iso:country":"US",
    "sg:address":"710 NE 81st Ave",
    "sg:city":"Portland",
    "sg:classifiers":[
        {
            "category":"Building & Trades",
            "subcategory":"Landscaping Services",
            "type":"Services"
        }
    ],
    "sg:phone":"+1 503 255 5947",
    "sg:postcode":"97213",
    "sg:province":"OR",
    "wof:name":"Donald A Newton",
    "wof:placetype":"venue"
},
  "geometry": {"coordinates":[-122.580164,45.526998],"type":"Point"}
}