{
  "type": "Feature",
  "properties": {
    "addr:full":"30300 SW Parkway Ave Wilsonville OR 97070",
    "addr:housenumber":"30300",
    "addr:postcode":"97070",
    "addr:street":"Sw Parkway Ave",
    "iso:country":"US",
    "sg:address":"30300 SW Parkway Ave",
    "sg:city":"Wilsonville",
    "sg:classifiers":[
        {
            "category":"Bars & Pubs",
            "type":"Food & Drink"
        }
    ],
    "sg:phone":"+1 503 570 8990",
    "sg:postcode":"97070",
    "sg:province":"OR",
    "sg:tags":[
        "drinking"
    ],
    "wof:name":"Five Frogs LLC",
    "wof:placetype":"venue"
},
  "geometry": {"coordinates":[-122.76871800000001,45.298127],"type":"Point"}
}