{
  "type": "Feature",
  "properties": {
    "iso:country":"US",
    "sg:address":"1740 Calistoga Ct",
    "sg:city":"Eugene",
    "sg:classifiers":[
        {
            "category":"Wholesale",
            "subcategory":"Non-durable Goods",
            "type":"Manufacturing & Wholesale Goods"
        }
    ],
    "sg:phone":"+1 541 688 8443",
    "sg:postcode":"97402",
    "sg:province":"OR",
    "wof:name":"Bk Trading",
    "wof:placetype":"venue"
},
  "geometry": {"coordinates":[-123.20399500000001,44.083123],"type":"Point"}
}