{
  "type": "Feature",
  "properties": {
    "iso:country":"US",
    "sg:address":"1012 SW King Ave",
    "sg:city":"Portland",
    "sg:classifiers":[
        {
            "category":"Professional",
            "subcategory":"Management & Consulting",
            "type":"Services"
        }
    ],
    "sg:phone":"+1 503 478 9727",
    "sg:postcode":"97205",
    "sg:province":"OR",
    "sg:tags":[
        "consultant",
        "educational",
        "business"
    ],
    "sg:website":"www.educationalconnections.com",
    "wof:name":"Educational Connections",
    "wof:placetype":"venue"
},
  "geometry": {"coordinates":[-122.695334,45.520692],"type":"Point"}
}