{
  "type": "Feature",
  "properties": {
    "iso:country":"US",
    "sg:address":"601 State St",
    "sg:city":"Hood River",
    "sg:classifiers":[
        {
            "category":"Manufacturing",
            "subcategory":"Glass & Minerals",
            "type":"Manufacturing & Wholesale Goods"
        }
    ],
    "sg:phone":"+1 541 387 4300",
    "sg:postcode":"97031",
    "sg:province":"OR",
    "sg:tags":[
        "product",
        "mfg"
    ],
    "wof:name":"Bottled Glass Solutions",
    "wof:placetype":"venue"
},
  "geometry": {"coordinates":[-121.516366,45.708121],"type":"Point"}
}