{
  "type": "Feature",
  "properties": {
    "iso:country":"US",
    "sg:address":"12106 NE Marx St Suite 122",
    "sg:city":"Portland",
    "sg:classifiers":[
        {
            "category":"Banks & Credit Unions",
            "subcategory":"Bank",
            "type":"Services"
        }
    ],
    "sg:phone":"+1 503 256 5858",
    "sg:postcode":"97220",
    "sg:province":"OR",
    "wof:name":"Pacific NW Federal Credit Union",
    "wof:placetype":"venue"
},
  "geometry": {"coordinates":[-122.538669,45.559306],"type":"Point"}
}