{
  "type": "Feature",
  "properties": {
    "addr:full":"343 Franklin Ave Astoria OR 97103",
    "addr:housenumber":"343",
    "addr:postcode":"97103",
    "addr:street":"Franklin Ave",
    "iso:country":"US",
    "sg:address":"343 Franklin Ave",
    "sg:city":"Astoria",
    "sg:classifiers":[
        {
            "category":"Professional",
            "subcategory":"Business Services",
            "type":"Services"
        }
    ],
    "sg:phone":"+1 503 325 1711",
    "sg:postcode":"97103",
    "sg:province":"OR",
    "wof:name":"DMS Engraving",
    "wof:placetype":"venue"
},
  "geometry": {"coordinates":[-123.839422,46.187018],"type":"Point"}
}