{
  "type": "Feature",
  "properties": {
    "iso:country":"US",
    "sg:address":"16427 NE Airport Way",
    "sg:city":"Portland",
    "sg:classifiers":[
        {
            "category":"Utilities",
            "subcategory":"Telephone",
            "type":"Services"
        }
    ],
    "sg:phone":"+1 503 761 3910",
    "sg:postcode":"97230",
    "sg:province":"OR",
    "sg:tags":[
        "company"
    ],
    "wof:name":"Cms Enterprises Inc",
    "wof:placetype":"venue"
},
  "geometry": {"coordinates":[-122.493723,45.55629],"type":"Point"}
}