{
  "type": "Feature",
  "properties": {
    "iso:country":"US",
    "sg:address":"69324 Craig Loop",
    "sg:city":"Summerville",
    "sg:classifiers":[
        {
            "category":"Building & Trades",
            "subcategory":"Landscaping Services",
            "type":"Services"
        }
    ],
    "sg:phone":"+1 541 534 2425",
    "sg:postcode":"97876",
    "sg:province":"OR",
    "wof:name":"Kens Yard Care",
    "wof:placetype":"venue"
},
  "geometry": {"coordinates":[-118.061551,45.536],"type":"Point"}
}