{
  "type": "Feature",
  "properties": {
    "iso:country":"US",
    "sg:address":"1300 SW 5th Ave",
    "sg:city":"Portland",
    "sg:classifiers":[
        {
            "category":"Building & Trades",
            "subcategory":"Construction",
            "type":"Services"
        }
    ],
    "sg:phone":"+1 503 227 4736",
    "sg:postcode":"97201",
    "sg:province":"OR",
    "sg:tags":[
        "operator",
        "apartment",
        "contractor"
    ],
    "wof:name":"Tokola Development Corporation",
    "wof:placetype":"venue"
},
  "geometry": {"coordinates":[-122.679885,45.514553],"type":"Point"}
}