{
  "type": "Feature",
  "properties": {
    "addr:full":"1125 SW 12th Avenue Ofc Portland OR 97205",
    "addr:housenumber":"1125",
    "addr:postcode":"97205",
    "addr:street":"Sw 12Th Avenue",
    "iso:country":"US",
    "sg:address":"1125 SW 12th Avenue Ofc",
    "sg:city":"Portland",
    "sg:classifiers":[
        {
            "category":"Real Estate",
            "subcategory":"Real Estate Operator",
            "type":"Services"
        }
    ],
    "sg:phone":"+1 503 224 9638",
    "sg:postcode":"97205",
    "sg:province":"OR",
    "sg:tags":[
        "apartment"
    ],
    "wof:name":"Lexington Apt",
    "wof:placetype":"venue"
},
  "geometry": {"coordinates":[-122.692616,45.520333],"type":"Point"}
}