{
  "type": "Feature",
  "properties": {
    "iso:country":"US",
    "sg:address":"1804 SE 1st St",
    "sg:city":"Redmond",
    "sg:classifiers":[
        {
            "category":"Manufacturing",
            "subcategory":"Tools & Machinery",
            "type":"Manufacturing & Wholesale Goods"
        },
        {
            "category":"Manufacturing",
            "subcategory":"Electronics",
            "type":"Manufacturing & Wholesale Goods"
        }
    ],
    "sg:phone":"+1 541 923 5530",
    "sg:postcode":"97756",
    "sg:province":"OR",
    "sg:tags":[
        "equipment",
        "peripheral",
        "computer",
        "electronic",
        "mfg"
    ],
    "sg:website":"www.rastergraf.com",
    "wof:name":"Rastergraf Inc",
    "wof:placetype":"venue"
},
  "geometry": {"coordinates":[-121.168768,44.256583],"type":"Point"}
}