{
  "type": "Feature",
  "properties": {
    "iso:country":"US",
    "sg:address":"2060 NE Darby St",
    "sg:city":"Hillsboro",
    "sg:classifiers":[
        {
            "category":"Manufacturing",
            "subcategory":"Retail Goods",
            "type":"Manufacturing & Wholesale Goods"
        }
    ],
    "sg:phone":"+1 503 844 4924",
    "sg:postcode":"97124",
    "sg:province":"OR",
    "sg:tags":[
        "product",
        "mfg"
    ],
    "wof:name":"Berlands Mfg & Procurement",
    "wof:placetype":"venue"
},
  "geometry": {"coordinates":[-122.960963,45.534499],"type":"Point"}
}