{
  "type": "Feature",
  "properties": {
    "iso:country":"US",
    "sg:address":"11940 SW Pacific Hwy",
    "sg:city":"Tigard",
    "sg:classifiers":[
        {
            "category":"Banks & Credit Unions",
            "subcategory":"Bank",
            "type":"Services"
        }
    ],
    "sg:phone":"+1 503 598 1818",
    "sg:postcode":"97223",
    "sg:province":"OR",
    "sg:tags":[
        "loan"
    ],
    "wof:name":"Paycheck Advance LLC",
    "wof:placetype":"venue"
},
  "geometry": {"coordinates":[-122.765327,45.433857],"type":"Point"}
}