{
  "type": "Feature",
  "properties": {
    "addr:full":"150 Market St Lebanon OR 97355",
    "addr:housenumber":"150",
    "addr:postcode":"97355",
    "addr:street":"Market St",
    "iso:country":"US",
    "sg:address":"150 Market St",
    "sg:city":"Lebanon",
    "sg:classifiers":[
        {
            "category":"Health Services",
            "subcategory":"Doctor",
            "type":"Services"
        }
    ],
    "sg:phone":"+1 541 451 4300",
    "sg:postcode":"97355",
    "sg:province":"OR",
    "sg:tags":[
        "dental",
        "clinic"
    ],
    "wof:name":"Santiam Dental Group",
    "wof:placetype":"venue"
},
  "geometry": {"coordinates":[-122.907106,44.51825],"type":"Point"}
}