{
  "type": "Feature",
  "properties": {
    "iso:country":"US",
    "sg:address":"16040 Reese Rd",
    "sg:city":"Lake Oswego",
    "sg:classifiers":[
        {
            "category":"Professional",
            "subcategory":"Computer Services",
            "type":"Services"
        }
    ],
    "sg:phone":"+1 503 201 6004",
    "sg:postcode":"97035",
    "sg:province":"OR",
    "sg:tags":[
        "information",
        "technology",
        "outsourcing",
        "software"
    ],
    "wof:name":"It Vineyard Inc",
    "wof:placetype":"venue"
},
  "geometry": {"coordinates":[-122.717754,45.409406],"type":"Point"}
}