{
  "type": "Feature",
  "properties": {
    "iso:country":"US",
    "sg:address":"24800 SE Stark St",
    "sg:city":"Gresham",
    "sg:classifiers":[
        {
            "category":"Health Services",
            "subcategory":"Doctor",
            "type":"Services"
        }
    ],
    "sg:phone":"+1 503 674 1580",
    "sg:postcode":"97030",
    "sg:province":"OR",
    "sg:tags":[
        "medicine",
        "internal"
    ],
    "sg:website":"www.legacyhealth.org",
    "wof:name":"Legacy Clinic Mount Hood",
    "wof:placetype":"venue"
},
  "geometry": {"coordinates":[-122.407381,45.517052],"type":"Point"}
}