{
  "type": "Feature",
  "properties": {
    "iso:country":"US",
    "sg:address":"2208 NW Birdsdale Ave # 14",
    "sg:city":"Gresham",
    "sg:classifiers":[
        {
            "category":"Manufacturing",
            "subcategory":"Rubber & Plastics",
            "type":"Manufacturing & Wholesale Goods"
        },
        {
            "category":"Shopping",
            "subcategory":"Party Supplies",
            "type":"Retail Goods"
        }
    ],
    "sg:phone":"+1 503 661 8987",
    "sg:postcode":"97030",
    "sg:province":"OR",
    "sg:tags":[
        "delivery",
        "balloons-retail",
        "balloons-novelty",
        "toy-wholesale",
        "manufacturer"
    ],
    "wof:name":"The Balloon Fair Inc",
    "wof:placetype":"venue"
},
  "geometry": {"coordinates":[-122.45509199999999,45.512331],"type":"Point"}
}