{
  "type": "Feature",
  "properties": {
    "addr:full":"1947 US Hwy 20 Albany OR 97321",
    "addr:housenumber":"1947",
    "addr:postcode":"97321",
    "addr:street":"Us Hwy 20",
    "iso:country":"US",
    "sg:address":"1947 US Hwy 20",
    "sg:city":"Albany",
    "sg:classifiers":[
        {
            "category":"Building & Trades",
            "subcategory":"Landscaping Services",
            "type":"Services"
        }
    ],
    "sg:phone":"+1 541 926 7309",
    "sg:postcode":"97321",
    "sg:province":"OR",
    "sg:tags":[
        "lawn",
        "maintenance",
        "grounds"
    ],
    "wof:name":"Colorwheel Gardens & Landscape",
    "wof:placetype":"venue"
},
  "geometry": {"coordinates":[-123.080146,44.633586],"type":"Point"}
}