{
  "type": "Feature",
  "properties": {
    "addr:full":"2220 NW Stewart Pkwy Roseburg OR 97470",
    "addr:housenumber":"2220",
    "addr:postcode":"97470",
    "addr:street":"Nw Stewart Pkwy",
    "iso:country":"US",
    "sg:address":"2220 NW Stewart Pkwy",
    "sg:city":"Roseburg",
    "sg:classifiers":[
        {
            "category":"Health Services",
            "subcategory":"Doctor",
            "type":"Services"
        }
    ],
    "sg:phone":"+1 541 677 8900",
    "sg:postcode":"97470",
    "sg:province":"OR",
    "sg:tags":[
        "physician",
        "surgeon"
    ],
    "wof:name":"Internal Medicine & Geriatrics",
    "wof:placetype":"venue"
},
  "geometry": {"coordinates":[-123.37238600000001,43.234737],"type":"Point"}
}