{
  "type": "Feature",
  "properties": {
    "addr:full":"710 W Marine Dr Astoria OR 97103",
    "addr:housenumber":"710",
    "addr:postcode":"97103",
    "addr:street":"W Marine Dr",
    "iso:country":"US",
    "sg:address":"710 W Marine Dr",
    "sg:city":"Astoria",
    "sg:classifiers":[
        {
            "category":"Autos & Motor Vehicles",
            "subcategory":"Automobile Sales",
            "type":"Retail Goods"
        },
        {
            "category":"Autos & Motor Vehicles",
            "subcategory":"Auto Supplies",
            "type":"Retail Goods"
        },
        {
            "category":"Retail",
            "subcategory":"Auto Repair",
            "type":"Services"
        }
    ],
    "sg:phone":"+1 503 325 6411",
    "sg:postcode":"97103",
    "sg:province":"OR",
    "sg:tags":[
        "new",
        "part",
        "car",
        "accessory"
    ],
    "sg:website":"http://www.ford.com",
    "wof:name":"Astoria Ford",
    "wof:placetype":"venue"
},
  "geometry": {"coordinates":[-123.855964,46.178961],"type":"Point"}
}