{
  "type": "Feature",
  "properties": {
    "iso:country":"US",
    "sg:address":"7545 NE Glisan St",
    "sg:city":"Portland",
    "sg:classifiers":[
        {
            "category":"Shopping",
            "subcategory":"Books",
            "type":"Retail Goods"
        }
    ],
    "sg:phone":"+1 503 253 9020",
    "sg:postcode":"97213",
    "sg:province":"OR",
    "sg:tags":[
        "dealer"
    ],
    "wof:name":"City Bible Publishing",
    "wof:placetype":"venue"
},
  "geometry": {"coordinates":[-122.585052,45.526517],"type":"Point"}
}