{
  "type": "Feature",
  "properties": {
    "addr:full":"4741 S Rd H Vale OR 97918",
    "addr:housenumber":"4741",
    "addr:postcode":"97918",
    "addr:street":"S Rd H Vale",
    "iso:country":"US",
    "sg:address":"4741 S Rd H",
    "sg:city":"Vale",
    "sg:classifiers":[
        {
            "category":"Professional",
            "type":"Services"
        }
    ],
    "sg:phone":"+1 541 473 2977",
    "sg:postcode":"97918",
    "sg:province":"OR",
    "wof:name":"Richard C Chamberlain Ka",
    "wof:placetype":"venue"
},
  "geometry": {"coordinates":[-117.385479,44.124941],"type":"Point"}
}