{
  "type": "Feature",
  "properties": {
    "addr:full":"7279 SW Bridgeport Rd Portland OR 97224",
    "addr:housenumber":"7279",
    "addr:postcode":"97224",
    "addr:street":"Sw Bridgeport Rd",
    "iso:country":"US",
    "sg:address":"7279 SW Bridgeport Rd",
    "sg:city":"Portland",
    "sg:classifiers":[
        {
            "category":"Shopping",
            "subcategory":"Beauty & Cosmetics",
            "type":"Retail Goods"
        }
    ],
    "sg:phone":"+1 503 620 3627",
    "sg:postcode":"97224",
    "sg:province":"OR",
    "sg:tags":[
        "supply"
    ],
    "sg:website":"www.origins.com",
    "wof:name":"Origins @ Bridgeport Village",
    "wof:placetype":"venue"
},
  "geometry": {"coordinates":[-122.75083600000001,45.395564],"type":"Point"}
}