{
  "type": "Feature",
  "properties": {
    "iso:country":"US",
    "sg:address":"65 SW Yamhill St",
    "sg:city":"Portland",
    "sg:classifiers":[
        {
            "category":"Government",
            "subcategory":"Office",
            "type":"Public Place"
        }
    ],
    "sg:phone":"+1 503 241 5036",
    "sg:postcode":"97204",
    "sg:province":"OR",
    "wof:name":"Yamhill Group",
    "wof:placetype":"venue"
},
  "geometry": {"coordinates":[-122.673637,45.516981],"type":"Point"}
}