{
  "type": "Feature",
  "properties": {
    "iso:country":"US",
    "sg:address":"327 W 10th Ave",
    "sg:city":"Eugene",
    "sg:classifiers":[
        {
            "category":"Social Services",
            "type":"Services"
        }
    ],
    "sg:phone":"+1 541 485 2484",
    "sg:postcode":"97401",
    "sg:province":"OR",
    "wof:name":"Nancy Evergreen MA Couns",
    "wof:placetype":"venue"
},
  "geometry": {"coordinates":[-123.097673,44.048893],"type":"Point"}
}