{
  "type": "Feature",
  "properties": {
    "iso:country":"US",
    "sg:address":"423 King Ave",
    "sg:city":"Ontario",
    "sg:classifiers":[
        {
            "category":"Food & Beverages",
            "subcategory":"Fruits & Vegetables",
            "type":"Retail Goods"
        }
    ],
    "sg:phone":"+1 541 889 2424",
    "sg:postcode":"97914",
    "sg:province":"OR",
    "sg:tags":[
        "produce"
    ],
    "wof:name":"Frahm Fresh Produce",
    "wof:placetype":"venue"
},
  "geometry": {"coordinates":[-116.981345,43.95238],"type":"Point"}
}