{
  "type": "Feature",
  "properties": {
    "iso:country":"US",
    "sg:address":"6567 Boswell Rd",
    "sg:city":"Yoncalla",
    "sg:classifiers":[
        {
            "category":"Home & Garden",
            "subcategory":"Garden Supply",
            "type":"Retail Goods"
        }
    ],
    "sg:phone":"+1 541 849 2790",
    "sg:postcode":"97499",
    "sg:province":"OR",
    "sg:tags":[
        "tree",
        "christmas"
    ],
    "wof:name":"Maurice Hise Tree Grower",
    "wof:placetype":"venue"
},
  "geometry": {"coordinates":[-123.228454,43.636706],"type":"Point"}
}