{
  "type": "Feature",
  "properties": {
    "iso:country":"US",
    "sg:address":"3384 NE Oxford Cir",
    "sg:city":"Corvallis",
    "sg:classifiers":[
        {
            "category":"Real Estate",
            "subcategory":"Real Estate Operator",
            "type":"Services"
        }
    ],
    "sg:phone":"+1 541 757 0842",
    "sg:postcode":"97330",
    "sg:province":"OR",
    "sg:tags":[
        "building",
        "apartment"
    ],
    "wof:name":"Landcaster Bridge Apartments",
    "wof:placetype":"venue"
},
  "geometry": {"coordinates":[-123.24079999999999,44.602228],"type":"Point"}
}