{
  "type": "Feature",
  "properties": {
    "addr:full":"16770 S Leroy Ln Oregon City OR 97045",
    "addr:housenumber":"16770",
    "addr:postcode":"97045",
    "addr:street":"S Leroy Ln",
    "iso:country":"US",
    "sg:address":"16770 S Leroy Ln",
    "sg:city":"Oregon City",
    "sg:classifiers":[
        {
            "category":"Banks & Credit Unions",
            "subcategory":"Bank",
            "type":"Services"
        }
    ],
    "sg:phone":"+1 503 655 5607",
    "sg:postcode":"97045",
    "sg:province":"OR",
    "sg:tags":[
        "broker",
        "mortgage"
    ],
    "wof:name":"Community Mortgage Services",
    "wof:placetype":"venue"
},
  "geometry": {"coordinates":[-122.584626,45.363617],"type":"Point"}
}