{
  "type": "Feature",
  "properties": {
    "addr:full":"15570 SW Village Ct Beaverton OR 97007",
    "addr:housenumber":"15570",
    "addr:postcode":"97007",
    "addr:street":"Sw Village Ct",
    "iso:country":"US",
    "sg:address":"15570 SW Village Ct",
    "sg:city":"Beaverton",
    "sg:classifiers":[
        {
            "category":"Home & Garden",
            "subcategory":"Mobile Homes",
            "type":"Retail Goods"
        }
    ],
    "sg:phone":"+1 503 641 6055",
    "sg:postcode":"97007",
    "sg:province":"OR",
    "wof:name":"Re-Sell Unlimited Inc",
    "wof:placetype":"venue"
},
  "geometry": {"coordinates":[-122.836603,45.478134],"type":"Point"}
}