{
  "type": "Feature",
  "properties": {
    "addr:full":"36885 NW Uebel Rd North Plains OR 97133",
    "addr:housenumber":"36885",
    "addr:postcode":"97133",
    "addr:street":"Nw Uebel Rd",
    "iso:country":"US",
    "sg:address":"36885 NW Uebel Rd",
    "sg:city":"North Plains",
    "sg:classifiers":[
        {
            "category":"Travel",
            "subcategory":"Campground",
            "type":"Entertainment"
        }
    ],
    "sg:phone":"+1 503 647 2853",
    "sg:postcode":"97133",
    "sg:province":"OR",
    "sg:tags":[
        "camp"
    ],
    "wof:name":"Camp Mountaindale",
    "wof:placetype":"venue"
},
  "geometry": {"coordinates":[-123.047127,45.646926],"type":"Point"}
}