{
  "type": "Feature",
  "properties": {
    "iso:country":"US",
    "sg:address":"5806 N Albina Ave",
    "sg:city":"Portland",
    "sg:classifiers":[
        {
            "category":"Education",
            "subcategory":"Special Training",
            "type":"Public Place"
        }
    ],
    "sg:phone":"+1 503 247 9445",
    "sg:postcode":"97217",
    "sg:province":"OR",
    "wof:name":"Peace Pl Afterschool Program",
    "wof:placetype":"venue"
},
  "geometry": {"coordinates":[-122.674864,45.564769],"type":"Point"}
}