{
  "type": "Feature",
  "properties": {
    "iso:country":"US",
    "sg:address":"140 S Detroit Ave",
    "sg:city":"Detroit",
    "sg:classifiers":[
        {
            "category":"Home & Garden",
            "subcategory":"Hardware",
            "type":"Retail Goods"
        }
    ],
    "sg:phone":"+1 503 854 3762",
    "sg:postcode":"97342",
    "sg:province":"OR",
    "wof:name":"Lake Center",
    "wof:placetype":"venue"
},
  "geometry": {"coordinates":[-122.151267,44.734683],"type":"Point"}
}