{
  "type": "Feature",
  "properties": {
    "iso:country":"US",
    "sg:address":"141 E 15th Ave",
    "sg:city":"Eugene",
    "sg:classifiers":[
        {
            "category":"Health Services",
            "subcategory":"Chiropractor",
            "type":"Services"
        }
    ],
    "sg:phone":"+1 541 343 1011",
    "sg:postcode":"97401",
    "sg:province":"OR",
    "sg:tags":[
        "chiropractic"
    ],
    "wof:name":"David Halvor Ott Dc Pc",
    "wof:placetype":"venue"
},
  "geometry": {"coordinates":[-123.09060100000001,44.043331],"type":"Point"}
}