{
  "type": "Feature",
  "properties": {
    "addr:full":"3704 Hwy 30 La Grande OR 97850",
    "addr:housenumber":"3704",
    "addr:postcode":"97850",
    "addr:street":"Hwy 30 La Grande",
    "iso:country":"US",
    "sg:address":"3704 Hwy 30",
    "sg:city":"La Grande",
    "sg:classifiers":[
        {
            "category":"Retail",
            "subcategory":"Repair Shop",
            "type":"Services"
        }
    ],
    "sg:phone":"+1 541 663 9819",
    "sg:postcode":"97850",
    "sg:province":"OR",
    "wof:name":"Steele Septic",
    "wof:placetype":"venue"
},
  "geometry": {"coordinates":[-118.05440400000001,45.304856],"type":"Point"}
}