{
  "type": "Feature",
  "properties": {
    "iso:country":"US",
    "sg:address":"1133 NW Wall St",
    "sg:city":"Bend",
    "sg:classifiers":[
        {
            "category":"Education",
            "subcategory":"Vocational School",
            "type":"Public Place"
        }
    ],
    "sg:phone":"+1 541 389 8010",
    "sg:postcode":"97701",
    "sg:province":"OR",
    "sg:website":"www.careerteched.com",
    "wof:name":"CAREERTECHED.COM",
    "wof:placetype":"venue"
},
  "geometry": {"coordinates":[-121.31185600000001,44.061047],"type":"Point"}
}