{
  "type": "Feature",
  "properties": {
    "iso:country":"US",
    "sg:address":"11940 SW Pacific Hwy Ste C",
    "sg:city":"Tigard",
    "sg:classifiers":[
        {
            "category":"Restaurant",
            "type":"Food & Drink"
        },
        {
            "category":"Food & Beverages",
            "subcategory":"Groceries & Convenience Stores",
            "type":"Retail Goods"
        }
    ],
    "sg:phone":"+1 503 684 5159",
    "sg:postcode":"97223",
    "sg:province":"OR",
    "wof:name":"Las Margaritas",
    "wof:placetype":"venue"
},
  "geometry": {"coordinates":[-122.764999,45.4338],"type":"Point"}
}