{
  "type": "Feature",
  "properties": {
    "iso:country":"US",
    "sg:address":"404 W Monroe St",
    "sg:city":"Burns",
    "sg:classifiers":[
        {
            "category":"Utilities",
            "subcategory":"Mobile Phone",
            "type":"Services"
        }
    ],
    "sg:phone":"+1 541 573 6420",
    "sg:postcode":"97720",
    "sg:province":"OR",
    "sg:tags":[
        "telephone",
        "cellular"
    ],
    "wof:name":"Cellular One",
    "wof:placetype":"venue"
},
  "geometry": {"coordinates":[-119.058727,43.586134],"type":"Point"}
}