{
  "type": "Feature",
  "properties": {
    "iso:country":"US",
    "sg:address":"6645 SW Nyberg St",
    "sg:city":"Tualatin",
    "sg:classifiers":[
        {
            "category":"Travel",
            "subcategory":"Campground",
            "type":"Entertainment"
        }
    ],
    "sg:phone":"+1 503 692 0225",
    "sg:postcode":"97062",
    "sg:province":"OR",
    "sg:tags":[
        "trailer"
    ],
    "wof:name":"Trailer Park of Portland",
    "wof:placetype":"venue"
},
  "geometry": {"coordinates":[-122.748756,45.382757],"type":"Point"}
}