{
  "type": "Feature",
  "properties": {
    "iso:country":"US",
    "sg:address":"2155 NW 2nd St",
    "sg:city":"McMinnville",
    "sg:classifiers":[
        {
            "category":"Organizations",
            "subcategory":"Religious Organization",
            "type":"Services"
        }
    ],
    "sg:phone":"+1 503 472 9021",
    "sg:postcode":"97128",
    "sg:province":"OR",
    "sg:website":"www.maccov.org",
    "wof:name":"McMinnville Covenant Church",
    "wof:placetype":"venue"
},
  "geometry": {"coordinates":[-123.21199799999999,45.225899],"type":"Point"}
}