{
  "type": "Feature",
  "properties": {
    "addr:full":"2125 SW 4th Ave Ste 600 Portland OR 97201",
    "addr:housenumber":"2125",
    "addr:postcode":"97201",
    "addr:street":"Sw 4Th Ave Ste 600",
    "iso:country":"US",
    "sg:address":"2125 SW 4th Ave Ste 600",
    "sg:city":"Portland",
    "sg:classifiers":[
        {
            "category":"Professional",
            "subcategory":"Lawyer & Legal Services",
            "type":"Services"
        }
    ],
    "sg:phone":"+1 503 222 2600",
    "sg:postcode":"97201",
    "sg:province":"OR",
    "wof:name":"Bisaccio Gary A Attorney",
    "wof:placetype":"venue"
},
  "geometry": {"coordinates":[-122.681999,45.507801],"type":"Point"}
}