{
  "type": "Feature",
  "properties": {
    "iso:country":"US",
    "sg:address":"9001 SE 73rd Ave",
    "sg:city":"Portland",
    "sg:classifiers":[
        {
            "category":"Social Services",
            "subcategory":"Adult Care",
            "type":"Services"
        }
    ],
    "sg:phone":"+1 503 777 6317",
    "sg:postcode":"97206",
    "sg:province":"OR",
    "sg:tags":[
        "residential"
    ],
    "sg:website":"www.theinnhome.com",
    "wof:name":"Inn Home For Boys",
    "wof:placetype":"venue"
},
  "geometry": {"coordinates":[-122.587923,45.460475],"type":"Point"}
}