{
  "type": "Feature",
  "properties": {
    "iso:country":"US",
    "sg:address":"415 W Hermiston Ave",
    "sg:city":"Hermiston",
    "sg:classifiers":[
        {
            "category":"Personal",
            "subcategory":"Beauty Salon",
            "type":"Services"
        }
    ],
    "sg:phone":"+1 541 289 7400",
    "sg:postcode":"97838",
    "sg:province":"OR",
    "wof:name":"Maris Beauty Salon",
    "wof:placetype":"venue"
},
  "geometry": {"coordinates":[-119.29567900000001,45.840546],"type":"Point"}
}