{
  "type": "Feature",
  "properties": {
    "iso:country":"US",
    "sg:address":"231 E Main St",
    "sg:city":"Medford",
    "sg:classifiers":[
        {
            "category":"Shopping",
            "subcategory":"Jewelry",
            "type":"Retail Goods"
        }
    ],
    "sg:phone":"+1 541 773 6763",
    "sg:postcode":"97501",
    "sg:province":"OR",
    "wof:name":"Nuich John Jewelers",
    "wof:placetype":"venue"
},
  "geometry": {"coordinates":[-122.87200199999999,42.3269],"type":"Point"}
}