{
  "type": "Feature",
  "properties": {
    "iso:country":"US",
    "sg:address":"697 Country Club Rd",
    "sg:city":"Eugene",
    "sg:classifiers":[
        {
            "category":"Professional",
            "subcategory":"Computer Services",
            "type":"Services"
        }
    ],
    "sg:phone":"+1 541 345 3659",
    "sg:postcode":"97401",
    "sg:province":"OR",
    "wof:name":"Orton Consulting Group",
    "wof:placetype":"venue"
},
  "geometry": {"coordinates":[-123.091938,44.064191],"type":"Point"}
}