{
  "type": "Feature",
  "properties": {
    "iso:country":"US",
    "sg:address":"6950 SW Hampton St",
    "sg:city":"Portland",
    "sg:classifiers":[
        {
            "category":"Health Services",
            "subcategory":"Clinic",
            "type":"Services"
        }
    ],
    "sg:phone":"+1 503 684 5322",
    "sg:postcode":"97223",
    "sg:province":"OR",
    "sg:tags":[
        "counseling",
        "mental"
    ],
    "wof:name":"Schneider John R Psychologist",
    "wof:placetype":"venue"
},
  "geometry": {"coordinates":[-122.748001,45.427502],"type":"Point"}
}