{
  "type": "Feature",
  "properties": {
    "iso:country":"US",
    "sg:address":"3912 SW Dakota St",
    "sg:city":"Portland",
    "sg:classifiers":[
        {
            "category":"Professional",
            "subcategory":"Computer Services",
            "type":"Services"
        }
    ],
    "sg:phone":"+1 503 245 7170",
    "sg:postcode":"97221",
    "sg:province":"OR",
    "sg:tags":[
        "programing",
        "custom"
    ],
    "wof:name":"Charles Turner Consulting",
    "wof:placetype":"venue"
},
  "geometry": {"coordinates":[-122.718568,45.477926],"type":"Point"}
}