{
  "type": "Feature",
  "properties": {
    "iso:country":"US",
    "sg:address":"780 Commercial St SE",
    "sg:city":"Salem",
    "sg:classifiers":[
        {
            "category":"Real Estate",
            "subcategory":"Real Estate Operator",
            "type":"Services"
        }
    ],
    "sg:phone":"+1 503 363 6141",
    "sg:postcode":"97301",
    "sg:province":"OR",
    "sg:tags":[
        "commercial"
    ],
    "wof:name":"Bar Industries Inc",
    "wof:placetype":"venue"
},
  "geometry": {"coordinates":[-123.04374799999999,44.933735],"type":"Point"}
}