{
  "type": "Feature",
  "properties": {
    "addr:full":"15800 SW Hall Blvd Tigard OR 97224",
    "addr:housenumber":"15800",
    "addr:postcode":"97224",
    "addr:street":"Sw Hall Blvd",
    "iso:country":"US",
    "sg:address":"15800 SW Hall Blvd",
    "sg:city":"Tigard",
    "sg:classifiers":[
        {
            "category":"Organizations",
            "subcategory":"Religious Organization",
            "type":"Services"
        }
    ],
    "sg:phone":"+1 503 620 7836",
    "sg:postcode":"97224",
    "sg:province":"OR",
    "sg:tags":[
        "church"
    ],
    "sg:website":"www.tigardfriends.com",
    "wof:name":"Tigard Community Friends Chr",
    "wof:placetype":"venue"
},
  "geometry": {"coordinates":[-122.764443,45.406657],"type":"Point"}
}