{
  "type": "Feature",
  "properties": {
    "iso:country":"US",
    "sg:address":"1285 Liberty St SE",
    "sg:city":"Salem",
    "sg:classifiers":[
        {
            "category":"Health Services",
            "subcategory":"Doctor",
            "type":"Services"
        }
    ],
    "sg:phone":"+1 503 540 7477",
    "sg:postcode":"97302",
    "sg:province":"OR",
    "sg:tags":[
        "medicine",
        "physician",
        "practice",
        "surgeons",
        "family"
    ],
    "sg:website":"http://www.pacificfmc.com",
    "wof:name":"Pacific Family Medical Center",
    "wof:placetype":"venue"
},
  "geometry": {"coordinates":[-123.04262199999999,44.928323],"type":"Point"}
}