{
  "type": "Feature",
  "properties": {
    "iso:country":"US",
    "sg:address":"2825 Pioneer Rd",
    "sg:city":"Medford",
    "sg:classifiers":[
        {
            "category":"Museum",
            "type":"Entertainment"
        }
    ],
    "sg:phone":"+1 541 535 9263",
    "sg:postcode":"97501",
    "sg:province":"OR",
    "sg:tags":[
        "physicist",
        "gallery"
    ],
    "wof:name":"Fermionics",
    "wof:placetype":"venue"
},
  "geometry": {"coordinates":[-122.845252,42.258827],"type":"Point"}
}