{
  "type": "Feature",
  "properties": {
    "addr:full":"845 SW 4th Ave Portland OR 97204",
    "addr:housenumber":"845",
    "addr:postcode":"97204",
    "addr:street":"Sw 4Th Ave",
    "iso:country":"US",
    "sg:address":"845 SW 4th Ave",
    "sg:city":"Portland",
    "sg:classifiers":[
        {
            "category":"Bagels",
            "subcategory":"None",
            "type":"Food & Drink"
        }
    ],
    "sg:phone":"+1 503 445 8188",
    "sg:postcode":"97204",
    "sg:province":"OR",
    "sg:website":"www.kettlemanbagels.com",
    "wof:name":"Kettleman Bagel Company",
    "wof:placetype":"venue"
},
  "geometry": {"coordinates":[-122.67708500000001,45.517559],"type":"Point"}
}