{
  "type": "Feature",
  "properties": {
    "iso:country":"US",
    "sg:address":"2367 SW 218th Dr",
    "sg:city":"Beaverton",
    "sg:classifiers":[
        {
            "category":"Manufacturing",
            "subcategory":"Apparel",
            "type":"Manufacturing & Wholesale Goods"
        }
    ],
    "sg:phone":"+1 503 848 0133",
    "sg:postcode":"97006",
    "sg:province":"OR",
    "sg:tags":[
        "dress",
        "mfg"
    ],
    "wof:name":"Marias",
    "wof:placetype":"venue"
},
  "geometry": {"coordinates":[-122.901536,45.502421],"type":"Point"}
}