{
  "type": "Feature",
  "properties": {
    "addr:full":"2367 SW 218th Dr Beaverton OR 97006",
    "addr:housenumber":"2367",
    "addr:postcode":"97006",
    "addr:street":"Sw 218Th Dr",
    "iso:country":"US",
    "sg:address":"2367 SW 218th Dr",
    "sg:city":"Beaverton",
    "sg:classifiers":[
        {
            "category":"Manufacturing",
            "subcategory":"Apparel",
            "type":"Manufacturing & Wholesale Goods"
        }
    ],
    "sg:phone":"+1 503 848 0133",
    "sg:postcode":"97006",
    "sg:province":"OR",
    "sg:tags":[
        "dress",
        "mfg"
    ],
    "wof:name":"Marias",
    "wof:placetype":"venue"
},
  "geometry": {"coordinates":[-122.90153599999999,45.502421],"type":"Point"}
}