{
  "type": "Feature",
  "properties": {
    "iso:country":"US",
    "sg:address":"727 Center St NE",
    "sg:city":"Salem",
    "sg:classifiers":[
        {
            "category":"Professional",
            "subcategory":"Business Services",
            "type":"Services"
        }
    ],
    "sg:phone":"+1 503 378 1528",
    "sg:postcode":"97301",
    "sg:province":"OR",
    "sg:tags":[
        "reporting"
    ],
    "wof:name":"Denmed Transcription Services",
    "wof:placetype":"venue"
},
  "geometry": {"coordinates":[-123.031064,44.941826],"type":"Point"}
}