{
  "type": "Feature",
  "properties": {
    "addr:full":"10099 N Portland Rd Portland OR 97203",
    "addr:housenumber":"10099",
    "addr:postcode":"97203",
    "addr:street":"N Portland Rd",
    "iso:country":"US",
    "sg:address":"10099 N Portland Rd",
    "sg:city":"Portland",
    "sg:classifiers":[
        {
            "category":"Freight",
            "type":"Transportation"
        }
    ],
    "sg:phone":"+1 503 286 0673",
    "sg:postcode":"97203",
    "sg:province":"OR",
    "sg:tags":[
        "operator",
        "local",
        "trucking"
    ],
    "wof:name":"Green Transfer & Storage Co",
    "wof:placetype":"venue"
},
  "geometry": {"coordinates":[-122.724253,45.596438],"type":"Point"}
}