{
  "type": "Feature",
  "properties": {
    "addr:full":"159 Nob Hill St Ashland OR 97520",
    "addr:housenumber":"159",
    "addr:postcode":"97520",
    "addr:street":"Nob Hill St",
    "iso:country":"US",
    "sg:address":"159 Nob Hill St",
    "sg:city":"Ashland",
    "sg:classifiers":[
        {
            "category":"Professional",
            "type":"Services"
        }
    ],
    "sg:phone":"+1 541 488 2626",
    "sg:postcode":"97520",
    "sg:province":"OR",
    "wof:name":"Cwg Coaching Services LLC",
    "wof:placetype":"venue"
},
  "geometry": {"coordinates":[-122.72005900000001,42.198163],"type":"Point"}
}