{
  "type": "Feature",
  "properties": {
    "iso:country":"US",
    "sg:address":"8383 NE Sandy Blvd",
    "sg:city":"Portland",
    "sg:classifiers":[
        {
            "category":"Professional",
            "subcategory":"Employment Agencies",
            "type":"Services"
        }
    ],
    "sg:phone":"+1 503 255 5110",
    "sg:postcode":"97220",
    "sg:province":"OR",
    "sg:tags":[
        "opportunity"
    ],
    "wof:name":"Auto Careers",
    "wof:placetype":"venue"
},
  "geometry": {"coordinates":[-122.57682,45.553115],"type":"Point"}
}