{
  "type": "Feature",
  "properties": {
    "addr:full":"15749 Lava Dr La Pine OR 97739",
    "addr:housenumber":"15749",
    "addr:postcode":"97739",
    "addr:street":"Lava Dr",
    "iso:country":"US",
    "sg:address":"15749 Lava Dr",
    "sg:city":"La Pine",
    "sg:classifiers":[
        {
            "category":"Building & Trades",
            "subcategory":"Construction",
            "type":"Services"
        }
    ],
    "sg:phone":"+1 541 536 9263",
    "sg:postcode":"97739",
    "sg:province":"OR",
    "sg:tags":[
        "house"
    ],
    "wof:name":"Aarow Custom Homes Corp",
    "wof:placetype":"venue"
},
  "geometry": {"coordinates":[-121.539501,43.758805],"type":"Point"}
}