{
  "type": "Feature",
  "properties": {
    "iso:country":"US",
    "sg:address":"2900 SW Cornelius Pass Rd",
    "sg:city":"Hillsboro",
    "sg:classifiers":[
        {
            "category":"Shopping",
            "subcategory":"Computers & Home Electronics",
            "type":"Retail Goods"
        }
    ],
    "sg:phone":"+1 503 591 7391",
    "sg:postcode":"97123",
    "sg:province":"OR",
    "sg:tags":[
        "equipment",
        "electronic",
        "supply"
    ],
    "wof:name":"Quickar Electronics Inc",
    "wof:placetype":"venue"
},
  "geometry": {"coordinates":[-122.902087,45.498423],"type":"Point"}
}