{
  "type": "Feature",
  "properties": {
    "addr:full":"2530 Orchard Hill Pl Lake Oswego OR 97035",
    "addr:housenumber":"2530",
    "addr:postcode":"97035",
    "addr:street":"Orchard Hill Pl",
    "iso:country":"US",
    "sg:address":"2530 Orchard Hill Pl",
    "sg:city":"Lake Oswego",
    "sg:classifiers":[
        {
            "category":"Shopping",
            "subcategory":"Optical Goods",
            "type":"Retail Goods"
        }
    ],
    "sg:phone":"+1 503 293 3179",
    "sg:postcode":"97035",
    "sg:province":"OR",
    "wof:name":"Golden Eyes LLC",
    "wof:placetype":"venue"
},
  "geometry": {"coordinates":[-122.70317300000001,45.437721],"type":"Point"}
}