{
  "type": "Feature",
  "properties": {
    "addr:full":"4700 Salem Dallas Hwy NW Salem OR 97304",
    "addr:housenumber":"4700",
    "addr:postcode":"97304",
    "addr:street":"Salem Dallas Hwy Nw",
    "iso:country":"US",
    "sg:address":"4700 Salem Dallas Hwy NW",
    "sg:city":"Salem",
    "sg:classifiers":[
        {
            "category":"Travel",
            "subcategory":"Campground",
            "type":"Entertainment"
        }
    ],
    "sg:phone":"+1 503 364 7714",
    "sg:postcode":"97304",
    "sg:province":"OR",
    "sg:tags":[
        "trailer"
    ],
    "wof:name":"Eola Bend Rv Park Inc",
    "wof:placetype":"venue"
},
  "geometry": {"coordinates":[-123.124314,44.931832],"type":"Point"}
}