{
  "type": "Feature",
  "properties": {
    "addr:full":"40675 Baptist Church Dr Lebanon OR 97355",
    "addr:postcode":"97355",
    "addr:street":"Dr",
    "iso:country":"US",
    "sg:address":"40675 Baptist Church Dr",
    "sg:city":"Lebanon",
    "sg:classifiers":[
        {
            "category":"Professional",
            "subcategory":"Business Services",
            "type":"Services"
        }
    ],
    "sg:phone":"+1 541 258 7761",
    "sg:postcode":"97355",
    "sg:province":"OR",
    "wof:name":"DP Industrial Rebuilding",
    "wof:placetype":"venue"
},
  "geometry": {"coordinates":[-122.77789300000001,44.591826],"type":"Point"}
}