{
  "type": "Feature",
  "properties": {
    "iso:country":"US",
    "sg:address":"155 W Coe Ave",
    "sg:city":"Stanfield",
    "sg:classifiers":[
        {
            "category":"Government",
            "subcategory":"Office",
            "type":"Public Place"
        }
    ],
    "sg:phone":"+1 541 449 3831",
    "sg:postcode":"97875",
    "sg:province":"OR",
    "sg:tags":[
        "city"
    ],
    "wof:name":"Stanfield City Hall",
    "wof:placetype":"venue"
},
  "geometry": {"coordinates":[-119.21772799999999,45.780472],"type":"Point"}
}