{
  "type": "Feature",
  "properties": {
    "iso:country":"US",
    "sg:address":"6432 SW Seymour St",
    "sg:city":"Portland",
    "sg:classifiers":[
        {
            "category":"Professional",
            "subcategory":"Computer Services",
            "type":"Services"
        }
    ],
    "sg:phone":"+1 503 291 9853",
    "sg:postcode":"97221",
    "sg:province":"OR",
    "sg:tags":[
        "consultant",
        "designer"
    ],
    "wof:name":"Soho Systems Northwest",
    "wof:placetype":"venue"
},
  "geometry": {"coordinates":[-122.742307,45.489024],"type":"Point"}
}