{
  "type": "Feature",
  "properties": {
    "addr:full":"27905 SE Holst Rd Boring OR 97009",
    "addr:postcode":"27905;97009",
    "addr:street":"Se Holst Rd",
    "iso:country":"US",
    "sg:address":"27905 SE Holst Rd",
    "sg:city":"Boring",
    "sg:classifiers":[
        {
            "category":"Professional",
            "subcategory":"Business Services",
            "type":"Services"
        }
    ],
    "sg:phone":"+1 503 637 3196",
    "sg:postcode":"97009",
    "sg:province":"OR",
    "wof:name":"Coxco Interiors",
    "wof:placetype":"venue"
},
  "geometry": {"coordinates":[-122.37623000000001,45.393386],"type":"Point"}
}