{
  "type": "Feature",
  "properties": {
    "addr:full":"1411 SW Morrison Street Portland OR 97205",
    "addr:housenumber":"1411",
    "addr:postcode":"97205",
    "addr:street":"Sw Morrison Street",
    "iso:country":"US",
    "sg:address":"1411 SW Morrison Street",
    "sg:city":"Portland",
    "sg:classifiers":[
        {
            "category":"Social Services",
            "subcategory":"Child Care",
            "type":"Services"
        },
        {
            "category":"Education",
            "subcategory":"Preschool",
            "type":"Public Place"
        },
        {
            "category":"Education",
            "subcategory":"School",
            "type":"Public Place"
        }
    ],
    "sg:phone":"+1 503 228 2443",
    "sg:postcode":"97205",
    "sg:province":"OR",
    "sg:tags":[
        "elementary",
        "day"
    ],
    "sg:website":"www.thechildrensgarden.com",
    "wof:name":"Children's Garden Learning Centers",
    "wof:placetype":"venue"
},
  "geometry": {"coordinates":[-122.686291,45.521151],"type":"Point"}
}