{
  "type": "Feature",
  "properties": {
    "iso:country":"US",
    "sg:address":"434 Evergreen Rd",
    "sg:city":"Ontario",
    "sg:classifiers":[
        {
            "category":"Farming",
            "subcategory":"Livestock Farm",
            "type":"Manufacturing & Wholesale Goods"
        }
    ],
    "sg:phone":"+1 541 262 3558",
    "sg:postcode":"97914",
    "sg:province":"OR",
    "sg:tags":[
        "feedlot",
        "field",
        "crop",
        "beef",
        "cattle"
    ],
    "wof:name":"William Guthridge",
    "wof:placetype":"venue"
},
  "geometry": {"coordinates":[-116.985636,44.125832],"type":"Point"}
}