{
  "type": "Feature",
  "properties": {
    "iso:country":"US",
    "sg:address":"404 E Main St",
    "sg:city":"Medford",
    "sg:classifiers":[
        {
            "category":"Bars & Pubs",
            "subcategory":"Nightclub",
            "type":"Food & Drink"
        }
    ],
    "sg:phone":"+1 541 773 5535",
    "sg:postcode":"97501",
    "sg:province":"OR",
    "sg:tags":[
        "nightlife"
    ],
    "wof:name":"Shenanigan's On Main",
    "wof:placetype":"venue"
},
  "geometry": {"coordinates":[-122.870434,42.327312],"type":"Point"}
}