{
  "type": "Feature",
  "properties": {
    "addr:full":"1355 River Rd Eugene OR 97404",
    "addr:housenumber":"1355",
    "addr:postcode":"97404",
    "addr:street":"River Rd",
    "iso:country":"US",
    "sg:address":"1355 River Rd",
    "sg:city":"Eugene",
    "sg:classifiers":[
        {
            "category":"Food & Beverages",
            "subcategory":"Groceries & Convenience Stores",
            "type":"Retail Goods"
        }
    ],
    "sg:phone":"+1 541 688 1875",
    "sg:postcode":"97404",
    "sg:province":"OR",
    "wof:name":"River Road Canned Foods Outlet",
    "wof:placetype":"venue"
},
  "geometry": {"coordinates":[-123.123762,44.085195],"type":"Point"}
}