{
  "type": "Feature",
  "properties": {
    "iso:country":"US",
    "sg:address":"7263 Conifer St NE",
    "sg:city":"Salem",
    "sg:classifiers":[
        {
            "category":"Building & Trades",
            "subcategory":"Cleaning & Sanitation",
            "type":"Services"
        }
    ],
    "sg:phone":"+1 503 581 1249",
    "sg:postcode":"97317",
    "sg:province":"OR",
    "sg:tags":[
        "janitor",
        "maintenance"
    ],
    "wof:name":"D J's Cleaning & More",
    "wof:placetype":"venue"
},
  "geometry": {"coordinates":[-122.91146000000001,44.94497],"type":"Point"}
}