{
  "type": "Feature",
  "properties": {
    "iso:country":"US",
    "sg:address":"1704 Adams Ave",
    "sg:city":"La Grande",
    "sg:classifiers":[
        {
            "category":"Health Services",
            "subcategory":"Chiropractor",
            "type":"Services"
        }
    ],
    "sg:phone":"+1 541 963 4068",
    "sg:postcode":"97850",
    "sg:province":"OR",
    "wof:name":"Country Chiropractic Clinic",
    "wof:placetype":"venue"
},
  "geometry": {"coordinates":[-118.088009,45.324499],"type":"Point"}
}