{
  "type": "Feature",
  "properties": {
    "addr:full":"1145 SE Spokane St Portland OR 97202",
    "addr:housenumber":"1145",
    "addr:postcode":"97202",
    "addr:street":"Se Spokane St",
    "iso:country":"US",
    "sg:address":"1145 SE Spokane St",
    "sg:city":"Portland",
    "sg:classifiers":[
        {
            "category":"Building & Trades",
            "subcategory":"Construction",
            "type":"Services"
        }
    ],
    "sg:phone":"+1 503 481 1099",
    "sg:postcode":"97202",
    "sg:province":"OR",
    "sg:tags":[
        "residential"
    ],
    "wof:name":"Victorian Company",
    "wof:placetype":"venue"
},
  "geometry": {"coordinates":[-122.653305,45.465115],"type":"Point"}
}