{
  "type": "Feature",
  "properties": {
    "addr:full":"32505 NE Haugen Rd Newberg OR 97132",
    "addr:housenumber":"32505",
    "addr:postcode":"97132",
    "addr:street":"Ne Haugen Rd",
    "iso:country":"US",
    "sg:address":"32505 NE Haugen Rd",
    "sg:city":"Newberg",
    "sg:classifiers":[
        {
            "category":"Professional",
            "subcategory":"Business Services",
            "type":"Services"
        }
    ],
    "sg:phone":"+1 503 538 3503",
    "sg:postcode":"97132",
    "sg:province":"OR",
    "sg:tags":[
        "drafting"
    ],
    "wof:name":"Cad Consulting",
    "wof:placetype":"venue"
},
  "geometry": {"coordinates":[-122.904472,45.316808],"type":"Point"}
}