{
  "type": "Feature",
  "properties": {
    "iso:country":"US",
    "sg:address":"1415 7th St",
    "sg:city":"Florence",
    "sg:classifiers":[
        {
            "category":"Restaurant",
            "type":"Food & Drink"
        }
    ],
    "sg:phone":"+1 541 902 2525",
    "sg:postcode":"97439",
    "sg:province":"OR",
    "sg:tags":[
        "italian"
    ],
    "wof:name":"Pomodori",
    "wof:placetype":"venue"
},
  "geometry": {"coordinates":[-124.105936,43.972791],"type":"Point"}
}