{
  "type": "Feature",
  "properties": {
    "addr:full":"8220 SE Harrison Street Suite 220 Portland OR 97216",
    "addr:housenumber":"8220",
    "addr:postcode":"97216",
    "addr:street":"Se Harrison Street Suite 220",
    "iso:country":"US",
    "sg:address":"8220 SE Harrison Street Suite 220",
    "sg:city":"Portland",
    "sg:classifiers":[
        {
            "category":"Shopping",
            "subcategory":"Mobile Phones",
            "type":"Retail Goods"
        }
    ],
    "sg:phone":"+1 503 771 1914",
    "sg:postcode":"97216",
    "sg:province":"OR",
    "wof:name":"Intact Wireless",
    "wof:placetype":"venue"
},
  "geometry": {"coordinates":[-122.578419,45.508306],"type":"Point"}
}