{
  "type": "Feature",
  "properties": {
    "iso:country":"US",
    "sg:address":"495 State Hwy 99 N",
    "sg:city":"Eugene",
    "sg:classifiers":[
        {
            "category":"Restaurant",
            "type":"Food & Drink"
        }
    ],
    "sg:phone":"+1 541 689 5711",
    "sg:postcode":"97402",
    "sg:province":"OR",
    "wof:name":"Burrito Boy Inc",
    "wof:placetype":"venue"
},
  "geometry": {"coordinates":[-123.138738,44.065702],"type":"Point"}
}