{
  "type": "Feature",
  "properties": {
    "iso:country":"US",
    "sg:address":"47 Eagle Crest Dr",
    "sg:city":"Lake Oswego",
    "sg:classifiers":[
        {
            "category":"Professional",
            "subcategory":"Engineering",
            "type":"Services"
        }
    ],
    "sg:phone":"+1 503 635 4388",
    "sg:postcode":"97035",
    "sg:province":"OR",
    "sg:tags":[
        "energy",
        "conservation"
    ],
    "wof:name":"Microenergy Technologies Inc",
    "wof:placetype":"venue"
},
  "geometry": {"coordinates":[-122.70850799999999,45.436055],"type":"Point"}
}