{
  "type": "Feature",
  "properties": {
    "iso:country":"US",
    "sg:address":"64711 Otter Run",
    "sg:city":"Bend",
    "sg:classifiers":[
        {
            "category":"Real Estate",
            "subcategory":"Real Estate Agent",
            "type":"Services"
        },
        {
            "category":"Professional",
            "type":"Services"
        }
    ],
    "sg:phone":"+1 541 330 0511",
    "sg:postcode":"97701",
    "sg:province":"OR",
    "sg:tags":[
        "investment"
    ],
    "wof:name":"Sperry Van Ness 5",
    "wof:placetype":"venue"
},
  "geometry": {"coordinates":[-121.32755,44.149169],"type":"Point"}
}