{
  "type": "Feature",
  "properties": {
    "addr:full":"526 NE 52nd Ave Portland OR 97213",
    "addr:housenumber":"526",
    "addr:postcode":"97213",
    "addr:street":"Ne 52Nd Ave",
    "iso:country":"US",
    "sg:address":"526 NE 52nd Ave",
    "sg:city":"Portland",
    "sg:classifiers":[
        {
            "category":"Social Services",
            "type":"Services"
        }
    ],
    "sg:phone":"+1 503 215 6377",
    "sg:postcode":"97213",
    "sg:province":"OR",
    "sg:tags":[
        "information",
        "planning",
        "center",
        "family"
    ],
    "sg:website":"www.nwfs.org",
    "wof:name":"Northwest Family Svc",
    "wof:placetype":"venue"
},
  "geometry": {"coordinates":[-122.610057,45.527027],"type":"Point"}
}