{
  "type": "Feature",
  "properties": {
    "iso:country":"US",
    "sg:address":"260 SW Madison Ave",
    "sg:city":"Corvallis",
    "sg:classifiers":[
        {
            "category":"Professional",
            "subcategory":"Research",
            "type":"Services"
        }
    ],
    "sg:phone":"+1 541 757 8564",
    "sg:postcode":"97333",
    "sg:province":"OR",
    "sg:tags":[
        "environmental",
        "ecological"
    ],
    "wof:name":"Measure Tek",
    "wof:placetype":"venue"
},
  "geometry": {"coordinates":[-123.26089899999999,44.563137],"type":"Point"}
}