{
  "type": "Feature",
  "properties": {
    "iso:country":"US",
    "sg:address":"18970 SW Blamon Ct",
    "sg:city":"Beaverton",
    "sg:classifiers":[
        {
            "category":"Building & Trades",
            "subcategory":"Construction",
            "type":"Services"
        }
    ],
    "sg:phone":"+1 503 332 3585",
    "sg:postcode":"97007",
    "sg:province":"OR",
    "sg:tags":[
        "painting",
        "painter",
        "contractor"
    ],
    "wof:name":"In & Out Painting",
    "wof:placetype":"venue"
},
  "geometry": {"coordinates":[-122.871312,45.49143],"type":"Point"}
}