{
  "type": "Feature",
  "properties": {
    "addr:full":"4000 SW Macadam Ave Portland OR 97219",
    "addr:housenumber":"4000",
    "addr:postcode":"97219",
    "addr:street":"Sw Macadam Ave",
    "iso:country":"US",
    "sg:address":"4000 SW Macadam Ave",
    "sg:city":"Portland",
    "sg:classifiers":[
        {
            "category":"Building & Trades",
            "subcategory":"Cleaning & Sanitation",
            "type":"Services"
        }
    ],
    "sg:phone":"+1 503 246 4130",
    "sg:postcode":"97219",
    "sg:province":"OR",
    "sg:tags":[
        "sanitation",
        "restroom"
    ],
    "wof:name":"Fikes-Williams Inc",
    "wof:placetype":"venue"
},
  "geometry": {"coordinates":[-122.672983,45.493808],"type":"Point"}
}