{
  "type": "Feature",
  "properties": {
    "iso:country":"US",
    "sg:address":"74879 Lost Creek Rd",
    "sg:city":"Clatskanie",
    "sg:classifiers":[
        {
            "category":"Building & Trades",
            "subcategory":"Construction",
            "type":"Services"
        }
    ],
    "sg:phone":"+1 503 728 3107",
    "sg:postcode":"97016",
    "sg:province":"OR",
    "sg:tags":[
        "excavation",
        "contractor"
    ],
    "wof:name":"Tim Fowler Excavating",
    "wof:placetype":"venue"
},
  "geometry": {"coordinates":[-123.075005,46.083919],"type":"Point"}
}