{
  "type": "Feature",
  "properties": {
    "iso:country":"US",
    "sg:address":"4999 State Hwy 234",
    "sg:city":"Central Point",
    "sg:classifiers":[
        {
            "category":"Restaurant",
            "type":"Food & Drink"
        }
    ],
    "sg:phone":"+1 541 830 8992",
    "sg:postcode":"97502",
    "sg:province":"OR",
    "sg:tags":[
        "eating"
    ],
    "wof:name":"Triple Tree Restaurant",
    "wof:placetype":"venue"
},
  "geometry": {"coordinates":[-122.922784,42.367993],"type":"Point"}
}