{
  "type": "Feature",
  "properties": {
    "addr:full":"2705 SE Ankeny St Portland OR 97214",
    "addr:housenumber":"2705",
    "addr:postcode":"97214",
    "addr:street":"Se Ankeny St",
    "iso:country":"US",
    "sg:address":"2705 SE Ankeny St",
    "sg:city":"Portland",
    "sg:classifiers":[
        {
            "category":"Health Services",
            "subcategory":"Clinic",
            "type":"Services"
        }
    ],
    "sg:phone":"+1 503 231 1950",
    "sg:postcode":"97214",
    "sg:province":"OR",
    "wof:name":"Alpha Therap Uetic Corp 411",
    "wof:placetype":"venue"
},
  "geometry": {"coordinates":[-122.637297,45.522207],"type":"Point"}
}