{
  "type": "Feature",
  "properties": {
    "addr:full":"7928 SE Harrison Street Portland OR 97215",
    "addr:housenumber":"7928",
    "addr:postcode":"97215",
    "addr:street":"Se Harrison Street",
    "iso:country":"US",
    "sg:address":"7928 SE Harrison Street",
    "sg:city":"Portland",
    "sg:classifiers":[
        {
            "category":"Health Services",
            "subcategory":"Health Practitioner",
            "type":"Services"
        }
    ],
    "sg:phone":"+1 503 777 1563",
    "sg:postcode":"97215",
    "sg:province":"OR",
    "sg:tags":[
        "acupuncture"
    ],
    "wof:name":"Duarte William Daom Lac",
    "wof:placetype":"venue"
},
  "geometry": {"coordinates":[-122.58144900000001,45.508573],"type":"Point"}
}