{
  "type": "Feature",
  "properties": {
    "iso:country":"US",
    "sg:address":"3038 Lakeview Ct NW",
    "sg:city":"Salem",
    "sg:classifiers":[
        {
            "category":"Real Estate",
            "subcategory":"Surveying",
            "type":"Services"
        }
    ],
    "sg:phone":"+1 503 364 9047",
    "sg:postcode":"97304",
    "sg:province":"OR",
    "wof:name":"Moreland Surveying",
    "wof:placetype":"venue"
},
  "geometry": {"coordinates":[-123.092669,44.950823],"type":"Point"}
}