{
  "type": "Feature",
  "properties": {
    "iso:country":"US",
    "sg:address":"1699 N Terry St",
    "sg:city":"Eugene",
    "sg:classifiers":[
        {
            "category":"Home & Garden",
            "subcategory":"Mobile Homes",
            "type":"Retail Goods"
        }
    ],
    "sg:phone":"+1 541 607 0314",
    "sg:postcode":"97402",
    "sg:province":"OR",
    "wof:name":"Bob's Bargain Homes",
    "wof:placetype":"venue"
},
  "geometry": {"coordinates":[-123.188132,44.081444],"type":"Point"}
}