{
  "type": "Feature",
  "properties": {
    "iso:country":"US",
    "sg:address":"9320 SW Barbur Boulevard",
    "sg:city":"Portland",
    "sg:classifiers":[
        {
            "category":"Professional",
            "subcategory":"Lawyer & Legal Services",
            "type":"Services"
        }
    ],
    "sg:phone":"+1 503 245 4905",
    "sg:postcode":"97219",
    "sg:province":"OR",
    "wof:name":"Nelson Roger A PC Atty",
    "wof:placetype":"venue"
},
  "geometry": {"coordinates":[-122.71051300000001,45.458201],"type":"Point"}
}