{
  "type": "Feature",
  "properties": {
    "addr:full":"22050 E Pinewood Ln Rhododendron OR 97049",
    "addr:housenumber":"22050",
    "addr:postcode":"97049",
    "addr:street":"E Pinewood Ln",
    "iso:country":"US",
    "sg:address":"22050 E Pinewood Ln",
    "sg:city":"Rhododendron",
    "sg:classifiers":[
        {
            "category":"Building & Trades",
            "subcategory":"Construction",
            "type":"Services"
        }
    ],
    "sg:phone":"+1 503 622 5255",
    "sg:postcode":"97049",
    "sg:province":"OR",
    "sg:tags":[
        "carpentry",
        "contractor"
    ],
    "wof:name":"Bryan Gardner",
    "wof:placetype":"venue"
},
  "geometry": {"coordinates":[-121.932754,45.364507],"type":"Point"}
}