{
  "type": "Feature",
  "properties": {
    "iso:country":"US",
    "sg:address":"3206 SE Hawthorne Blvd.",
    "sg:city":"Portland",
    "sg:classifiers":[
        {
            "category":"Professional",
            "subcategory":"Accounting & Tax Preparation",
            "type":"Services"
        }
    ],
    "sg:phone":"+1 503 236 1040",
    "sg:postcode":"97214",
    "sg:province":"OR",
    "sg:tags":[
        "accountant"
    ],
    "sg:website":"www.claritytax.net",
    "wof:name":"Clarity Tax Service, Inc.",
    "wof:placetype":"venue"
},
  "geometry": {"coordinates":[-122.63240500000001,45.511838],"type":"Point"}
}