{
  "type": "Feature",
  "properties": {
    "iso:country":"US",
    "sg:address":"13716 SE Ramona Street",
    "sg:city":"Portland",
    "sg:classifiers":[
        {
            "category":"Communications",
            "type":"Services"
        }
    ],
    "sg:phone":"+1 503 760 7777",
    "sg:postcode":"97236",
    "sg:province":"OR",
    "sg:tags":[
        "recording",
        "rehearsal",
        "studio"
    ],
    "wof:name":"Northstar Recording and Productions",
    "wof:placetype":"venue"
},
  "geometry": {"coordinates":[-122.52202800000001,45.480233],"type":"Point"}
}