{
  "type": "Feature",
  "properties": {
    "addr:full":"1562 NE Vine St Roseburg OR 97470",
    "addr:housenumber":"1562",
    "addr:postcode":"97470",
    "addr:street":"Ne Vine St",
    "iso:country":"US",
    "sg:address":"1562 NE Vine St",
    "sg:city":"Roseburg",
    "sg:classifiers":[
        {
            "category":"Banks & Credit Unions",
            "subcategory":"Bank",
            "type":"Services"
        }
    ],
    "sg:phone":"+1 541 673 5678",
    "sg:postcode":"97470",
    "sg:province":"OR",
    "sg:tags":[
        "broker",
        "mortgage"
    ],
    "wof:name":"Fidelity Mortgage Company",
    "wof:placetype":"venue"
},
  "geometry": {"coordinates":[-123.34707899999999,43.228144],"type":"Point"}
}