{
  "type": "Feature",
  "properties": {
    "addr:full":"38959 Pioneer Blvd Sandy OR 97055",
    "addr:housenumber":"38959",
    "addr:postcode":"97055",
    "addr:street":"Pioneer Blvd",
    "iso:country":"US",
    "sg:address":"38959 Pioneer Blvd",
    "sg:city":"Sandy",
    "sg:classifiers":[
        {
            "category":"Education",
            "subcategory":"Special Training",
            "type":"Public Place"
        },
        {
            "category":"Social Services",
            "subcategory":"Child Care",
            "type":"Services"
        }
    ],
    "sg:phone":"+1 503 668 0200",
    "sg:postcode":"97055",
    "sg:province":"OR",
    "sg:tags":[
        "educational",
        "nursery",
        "tutoring",
        "day"
    ],
    "wof:name":"Impact Learning Center",
    "wof:placetype":"venue"
},
  "geometry": {"coordinates":[-122.26232299999999,45.396286],"type":"Point"}
}