{
  "type": "Feature",
  "properties": {
    "addr:full":"9045 N Ramsey Blvd Portland OR 97203",
    "addr:housenumber":"9045",
    "addr:postcode":"97203",
    "addr:street":"N Ramsey Blvd",
    "iso:country":"US",
    "sg:address":"9045 N Ramsey Blvd",
    "sg:city":"Portland",
    "sg:classifiers":[
        {
            "category":"Retail",
            "subcategory":"Laundry & Dry Cleaning",
            "type":"Services"
        }
    ],
    "sg:phone":"+1 503 283 7733",
    "sg:postcode":"97203",
    "sg:province":"OR",
    "sg:tags":[
        "linen",
        "supply",
        "uniform"
    ],
    "wof:name":"Cintas The Uniform People",
    "wof:placetype":"venue"
},
  "geometry": {"coordinates":[-122.78656100000001,45.624378],"type":"Point"}
}