{
  "type": "Feature",
  "properties": {
    "iso:country":"US",
    "sg:address":"33 N 3rd St",
    "sg:city":"Ashland",
    "sg:classifiers":[
        {
            "category":"Restaurant",
            "type":"Food & Drink"
        }
    ],
    "sg:phone":"+1 541 482 8060",
    "sg:postcode":"97520",
    "sg:province":"OR",
    "sg:tags":[
        "eating"
    ],
    "wof:name":"Los Gordos",
    "wof:placetype":"venue"
},
  "geometry": {"coordinates":[-122.709943,42.194736],"type":"Point"}
}