{
  "type": "Feature",
  "properties": {
    "iso:country":"US",
    "sg:address":"40010 SE Paul Moore Rd",
    "sg:city":"Sandy",
    "sg:classifiers":[
        {
            "category":"Building & Trades",
            "subcategory":"Construction",
            "type":"Services"
        }
    ],
    "sg:phone":"+1 503 668 4881",
    "sg:postcode":"97055",
    "sg:province":"OR",
    "sg:tags":[
        "house"
    ],
    "wof:name":"RG Bothwell Construction",
    "wof:placetype":"venue"
},
  "geometry": {"coordinates":[-122.25620600000001,45.366834],"type":"Point"}
}