{
  "type": "Feature",
  "properties": {
    "iso:country":"US",
    "sg:address":"32691 S Mathias Rd",
    "sg:city":"Molalla",
    "sg:classifiers":[
        {
            "category":"Building & Trades",
            "subcategory":"Construction",
            "type":"Services"
        }
    ],
    "sg:phone":"+1 503 829 2204",
    "sg:postcode":"97038",
    "sg:province":"OR",
    "sg:tags":[
        "paving",
        "contractor"
    ],
    "wof:name":"US Federal Highway Adm",
    "wof:placetype":"venue"
},
  "geometry": {"coordinates":[-122.56940299999999,45.133162],"type":"Point"}
}