{
  "type": "Feature",
  "properties": {
    "addr:full":"1758 SW Marlow Ave Portland OR 97225",
    "addr:housenumber":"1758",
    "addr:postcode":"97225",
    "addr:street":"Sw Marlow Ave",
    "iso:country":"US",
    "sg:address":"1758 SW Marlow Ave",
    "sg:city":"Portland",
    "sg:classifiers":[
        {
            "category":"Building & Trades",
            "subcategory":"Locksmith",
            "type":"Services"
        }
    ],
    "sg:phone":"+1 503 715 2019",
    "sg:postcode":"97225",
    "sg:province":"OR",
    "sg:tags":[
        "key"
    ],
    "wof:name":"23 7 Locksmith",
    "wof:placetype":"venue"
},
  "geometry": {"coordinates":[-122.784395,45.506676],"type":"Point"}
}