{
  "type": "Feature",
  "properties": {
    "addr:full":"1921 SE 3rd Ave Portland OR 97214",
    "addr:housenumber":"1921",
    "addr:postcode":"97214",
    "addr:street":"Se 3Rd Ave",
    "iso:country":"US",
    "sg:address":"1921 SE 3rd Ave",
    "sg:city":"Portland",
    "sg:classifiers":[
        {
            "category":"Professional",
            "subcategory":"Detective & Security Services",
            "type":"Services"
        }
    ],
    "sg:phone":"+1 503 236 2444",
    "sg:postcode":"97214",
    "sg:province":"OR",
    "sg:tags":[
        "information",
        "bureau"
    ],
    "wof:name":"United Service Alliance",
    "wof:placetype":"venue"
},
  "geometry": {"coordinates":[-122.662813,45.509012],"type":"Point"}
}