{
  "type": "Feature",
  "properties": {
    "iso:country":"US",
    "sg:address":"60689 Bozeman Trl",
    "sg:city":"Bend",
    "sg:classifiers":[
        {
            "category":"Social Services",
            "subcategory":"Adult Care",
            "type":"Services"
        }
    ],
    "sg:phone":"+1 541 383 5165",
    "sg:postcode":"97702",
    "sg:province":"OR",
    "sg:tags":[
        "residential"
    ],
    "wof:name":"House of Seven Gables Inc",
    "wof:placetype":"venue"
},
  "geometry": {"coordinates":[-121.163623,44.006334],"type":"Point"}
}