{
  "type": "Feature",
  "properties": {
    "iso:country":"US",
    "sg:address":"4909 N Yale St",
    "sg:city":"Portland",
    "sg:classifiers":[
        {
            "category":"Wholesale",
            "subcategory":"Sporting Goods",
            "type":"Manufacturing & Wholesale Goods"
        }
    ],
    "sg:phone":"+1 503 289 2140",
    "sg:postcode":"97203",
    "sg:province":"OR",
    "wof:name":"Division Pro",
    "wof:placetype":"venue"
},
  "geometry": {"coordinates":[-122.723107,45.575715],"type":"Point"}
}