{
  "type": "Feature",
  "properties": {
    "addr:full":"2890 2nd St Baker City OR 97814",
    "addr:housenumber":"2890",
    "addr:postcode":"97814",
    "addr:street":"2Nd St",
    "iso:country":"US",
    "sg:address":"2890 2nd St",
    "sg:city":"Baker City",
    "sg:classifiers":[
        {
            "category":"Travel",
            "subcategory":"Hotels & Motels",
            "type":"Entertainment"
        }
    ],
    "sg:phone":"+1 541 523 5653",
    "sg:postcode":"97814",
    "sg:province":"OR",
    "sg:tags":[
        "operation"
    ],
    "wof:name":"Harbor View Motel",
    "wof:placetype":"venue"
},
  "geometry": {"coordinates":[-117.831873,44.784412],"type":"Point"}
}