{
  "type": "Feature",
  "properties": {
    "iso:country":"US",
    "sg:address":"455 S Howard St",
    "sg:city":"Stanfield",
    "sg:classifiers":[
        {
            "category":"Retail",
            "subcategory":"Animal Services",
            "type":"Services"
        }
    ],
    "sg:phone":"+1 541 449 3507",
    "sg:postcode":"97875",
    "sg:province":"OR",
    "wof:name":"Marcums Quarter Horses",
    "wof:placetype":"venue"
},
  "geometry": {"coordinates":[-119.20757,45.777004],"type":"Point"}
}