{
  "type": "Feature",
  "properties": {
    "iso:country":"US",
    "sg:address":"3825 River Rd N",
    "sg:city":"Keizer",
    "sg:classifiers":[
        {
            "category":"Retail",
            "subcategory":"Car Wash",
            "type":"Services"
        }
    ],
    "sg:phone":"+1 503 304 1051",
    "sg:postcode":"97303",
    "sg:province":"OR",
    "sg:tags":[
        "polishing",
        "washing"
    ],
    "wof:name":"Splash'n Dash Car Washes",
    "wof:placetype":"venue"
},
  "geometry": {"coordinates":[-123.02666499999999,44.981839],"type":"Point"}
}