{
  "type": "Feature",
  "properties": {
    "addr:full":"18200 NW Johnson Rd Portland OR 97231",
    "addr:housenumber":"18200",
    "addr:postcode":"97231",
    "addr:street":"Nw Johnson Rd",
    "iso:country":"US",
    "sg:address":"18200 NW Johnson Rd",
    "sg:city":"Portland",
    "sg:classifiers":[
        {
            "category":"Retail",
            "subcategory":"Repair Shop",
            "type":"Services"
        }
    ],
    "sg:phone":"+1 503 621 3421",
    "sg:postcode":"97231",
    "sg:province":"OR",
    "sg:tags":[
        "welding"
    ],
    "wof:name":"Skyline Welding",
    "wof:placetype":"venue"
},
  "geometry": {"coordinates":[-122.90879200000001,45.653544],"type":"Point"}
}