{
  "type": "Feature",
  "properties": {
    "iso:country":"US",
    "sg:address":"120 Pleasant Ave",
    "sg:city":"Roseburg",
    "sg:classifiers":[
        {
            "category":"Organizations",
            "subcategory":"Labor Organization",
            "type":"Services"
        }
    ],
    "sg:phone":"+1 541 673 7568",
    "sg:postcode":"97470",
    "sg:province":"OR",
    "wof:name":"Brothrhd of Maintn Way Emply",
    "wof:placetype":"venue"
},
  "geometry": {"coordinates":[-123.35283800000001,43.267057],"type":"Point"}
}