{
  "type": "Feature",
  "properties": {
    "iso:country":"US",
    "sg:address":"2125 SW 4th Ave",
    "sg:city":"Portland",
    "sg:classifiers":[
        {
            "category":"Real Estate",
            "subcategory":"Architect",
            "type":"Services"
        }
    ],
    "sg:phone":"+1 503 827 7979",
    "sg:postcode":"97201",
    "sg:province":"OR",
    "wof:name":"G A Miller Architecture PC",
    "wof:placetype":"venue"
},
  "geometry": {"coordinates":[-122.681911,45.507962],"type":"Point"}
}