{
  "type": "Feature",
  "properties": {
    "iso:country":"US",
    "sg:address":"1923 SE Stark St",
    "sg:city":"Portland",
    "sg:classifiers":[
        {
            "category":"Professional",
            "type":"Services"
        }
    ],
    "sg:phone":"+1 503 231 8309",
    "sg:postcode":"97214",
    "sg:province":"OR",
    "sg:tags":[
        "establishment"
    ],
    "wof:name":"Balsley Mc Nees & Assoc",
    "wof:placetype":"venue"
},
  "geometry": {"coordinates":[-122.645684,45.519395],"type":"Point"}
}