{
  "type": "Feature",
  "properties": {
    "addr:full":"26575 S Nawratil Rd Estacada OR 97023",
    "addr:housenumber":"26575",
    "addr:postcode":"97023",
    "addr:street":"S Nawratil Rd",
    "iso:country":"US",
    "sg:address":"26575 S Nawratil Rd",
    "sg:city":"Estacada",
    "sg:classifiers":[
        {
            "category":"Building & Trades",
            "subcategory":"Construction",
            "type":"Services"
        }
    ],
    "sg:phone":"+1 503 630 6982",
    "sg:postcode":"97023",
    "sg:province":"OR",
    "sg:tags":[
        "floor",
        "laying",
        "contractor"
    ],
    "wof:name":"D&R Flooring & Tile Inc",
    "wof:placetype":"venue"
},
  "geometry": {"coordinates":[-122.31374,45.214901],"type":"Point"}
}