{
  "type": "Feature",
  "properties": {
    "addr:full":"81414 Dufur Valley Rd Dufur OR 97021",
    "addr:postcode":"81414;97021",
    "addr:street":"Dufur Valley Rd",
    "iso:country":"US",
    "sg:address":"81414 Dufur Valley Rd",
    "sg:city":"Dufur",
    "sg:classifiers":[
        {
            "category":"Farming",
            "subcategory":"Farm & Veterinary Services",
            "type":"Manufacturing & Wholesale Goods"
        }
    ],
    "sg:phone":"+1 541 467 2256",
    "sg:postcode":"97021",
    "sg:province":"OR",
    "sg:tags":[
        "crop"
    ],
    "wof:name":"Shough Mountain Sprayers",
    "wof:placetype":"venue"
},
  "geometry": {"coordinates":[-121.228944,45.430213],"type":"Point"}
}