{
  "type": "Feature",
  "properties": {
    "iso:country":"US",
    "sg:address":"16580 Maple Cir",
    "sg:city":"Lake Oswego",
    "sg:classifiers":[
        {
            "category":"Professional",
            "subcategory":"Research",
            "type":"Services"
        }
    ],
    "sg:phone":"+1 503 697 5447",
    "sg:postcode":"97034",
    "sg:province":"OR",
    "sg:tags":[
        "commercial",
        "physical"
    ],
    "wof:name":"Ekatetra",
    "wof:placetype":"venue"
},
  "geometry": {"coordinates":[-122.71368099999999,45.40338],"type":"Point"}
}