{
  "type": "Feature",
  "properties": {
    "addr:full":"1705 N Terry St Portland OR 97217",
    "addr:housenumber":"1705",
    "addr:postcode":"97217",
    "addr:street":"N Terry St",
    "iso:country":"US",
    "sg:address":"1705 N Terry St",
    "sg:city":"Portland",
    "sg:classifiers":[
        {
            "category":"Home & Garden",
            "subcategory":"Garden Supply",
            "type":"Retail Goods"
        },
        {
            "category":"Home & Garden",
            "subcategory":"Furniture",
            "type":"Retail Goods"
        }
    ],
    "sg:phone":"+1 503 289 8077",
    "sg:postcode":"97217",
    "sg:province":"OR",
    "sg:tags":[
        "lawn",
        "product",
        "furnishing",
        "bamboo"
    ],
    "wof:name":"Living By Garden Inc",
    "wof:placetype":"venue"
},
  "geometry": {"coordinates":[-122.68392,45.579532],"type":"Point"}
}