{
  "type": "Feature",
  "properties": {
    "addr:full":"3236 Boardman Ave Klamath Falls OR 97603",
    "addr:housenumber":"3236",
    "addr:postcode":"97603",
    "addr:street":"Boardman Ave",
    "iso:country":"US",
    "sg:address":"3236 Boardman Ave",
    "sg:city":"Klamath Falls",
    "sg:classifiers":[
        {
            "category":"Freight",
            "type":"Transportation"
        }
    ],
    "sg:phone":"+1 541 273 5322",
    "sg:postcode":"97603",
    "sg:province":"OR",
    "sg:tags":[
        "operator",
        "local",
        "trucking"
    ],
    "wof:name":"Chris Hill Trucking",
    "wof:placetype":"venue"
},
  "geometry": {"coordinates":[-121.749906,42.202877],"type":"Point"}
}