{
  "type": "Feature",
  "properties": {
    "iso:country":"US",
    "sg:address":"1805 NW Upshur St",
    "sg:city":"Portland",
    "sg:classifiers":[
        {
            "category":"Home & Garden",
            "subcategory":"Garden Supply",
            "type":"Retail Goods"
        }
    ],
    "sg:phone":"+1 503 224 3623",
    "sg:postcode":"97209",
    "sg:province":"OR",
    "sg:tags":[
        "engine"
    ],
    "wof:name":"E C Distributing Co",
    "wof:placetype":"venue"
},
  "geometry": {"coordinates":[-122.69047,45.536434],"type":"Point"}
}