{
  "type": "Feature",
  "properties": {
    "iso:country":"US",
    "sg:address":"3890 SW 144th Ave",
    "sg:city":"Beaverton",
    "sg:classifiers":[
        {
            "category":"Building & Trades",
            "subcategory":"Locksmith",
            "type":"Services"
        }
    ],
    "sg:phone":"+1 503 715 3886",
    "sg:postcode":"97005",
    "sg:province":"OR",
    "sg:tags":[
        "key"
    ],
    "wof:name":"1 A 1 A Locksmith",
    "wof:placetype":"venue"
},
  "geometry": {"coordinates":[-122.824519,45.491957],"type":"Point"}
}