{
  "type": "Feature",
  "properties": {
    "iso:country":"US",
    "sg:address":"25212 Lawrence Rd",
    "sg:city":"Junction City",
    "sg:classifiers":[
        {
            "category":"Farming",
            "subcategory":"Farm",
            "type":"Manufacturing & Wholesale Goods"
        }
    ],
    "sg:phone":"+1 541 998 3932",
    "sg:postcode":"97448",
    "sg:province":"OR",
    "sg:tags":[
        "crop",
        "general"
    ],
    "wof:name":"Will Williamson",
    "wof:placetype":"venue"
},
  "geometry": {"coordinates":[-123.349143,44.133718],"type":"Point"}
}