{
  "type": "Feature",
  "properties": {
    "addr:full":"704 E 2nd St The Dalles OR 97058",
    "addr:housenumber":"704",
    "addr:postcode":"97058",
    "addr:street":"E 2Nd St",
    "iso:country":"US",
    "sg:address":"704 E 2nd St",
    "sg:city":"The Dalles",
    "sg:classifiers":[
        {
            "category":"Insurance",
            "subcategory":"Insurance Agent",
            "type":"Services"
        }
    ],
    "sg:phone":"+1 541 296 2100",
    "sg:postcode":"97058",
    "sg:province":"OR",
    "wof:name":"Columbia Gorge Insurance",
    "wof:placetype":"venue"
},
  "geometry": {"coordinates":[-121.17706200000001,45.598915],"type":"Point"}
}