{
  "type": "Feature",
  "properties": {
    "addr:full":"12405 SE 97th Ave Clackamas OR 97015",
    "addr:housenumber":"12405",
    "addr:postcode":"97015",
    "addr:street":"Se 97Th Ave",
    "iso:country":"US",
    "sg:address":"12405 SE 97th Ave",
    "sg:city":"Clackamas",
    "sg:classifiers":[
        {
            "category":"Autos & Motor Vehicles",
            "subcategory":"Fuel & Gas Station",
            "type":"Retail Goods"
        }
    ],
    "sg:phone":"+1 503 653 7600",
    "sg:postcode":"97015",
    "sg:province":"OR",
    "wof:name":"Town Center Unocal 76 Service Center",
    "wof:placetype":"venue"
},
  "geometry": {"coordinates":[-122.564003,45.432201],"type":"Point"}
}