{
  "type": "Feature",
  "properties": {
    "addr:full":"606 Village Ter Seaside OR 97138",
    "addr:housenumber":"606",
    "addr:postcode":"97138",
    "addr:street":"Village Ter",
    "iso:country":"US",
    "sg:address":"606 Village Ter",
    "sg:city":"Seaside",
    "sg:classifiers":[
        {
            "category":"Professional",
            "subcategory":"Engineering",
            "type":"Services"
        },
        {
            "category":"Professional",
            "subcategory":"Business Services",
            "type":"Services"
        }
    ],
    "sg:phone":"+1 503 717 0778",
    "sg:postcode":"97138",
    "sg:province":"OR",
    "sg:tags":[
        "consultant",
        "consulting",
        "coach",
        "engineer"
    ],
    "wof:name":"North Coast Consulting",
    "wof:placetype":"venue"
},
  "geometry": {"coordinates":[-123.916584,46.009494],"type":"Point"}
}