{
  "type": "Feature",
  "properties": {
    "iso:country":"US",
    "sg:address":"405 Deschutes Ave",
    "sg:city":"Maupin",
    "sg:classifiers":[
        {
            "category":"Banks & Credit Unions",
            "subcategory":"Bank",
            "type":"Services"
        }
    ],
    "sg:phone":"+1 541 395 2228",
    "sg:postcode":"97037",
    "sg:province":"OR",
    "sg:tags":[
        "saving",
        "commercial"
    ],
    "sg:website":"http://www.crbmortgage.com",
    "wof:name":"River Drifters",
    "wof:placetype":"venue"
},
  "geometry": {"coordinates":[-121.079628,45.17579],"type":"Point"}
}