{
  "type": "Feature",
  "properties": {
    "iso:country":"US",
    "sg:address":"432 Lancaster Dr NE",
    "sg:city":"Salem",
    "sg:classifiers":[
        {
            "category":"Health Services",
            "subcategory":"Dentist",
            "type":"Services"
        }
    ],
    "sg:phone":"+1 503 399 7460",
    "sg:postcode":"97301",
    "sg:province":"OR",
    "sg:tags":[
        "clinic",
        "dental",
        "dentistry",
        "dentists-cosmetic",
        "hygienist"
    ],
    "sg:website":"http://www.salemfamilydentistry.com",
    "wof:name":"Salem Family And Cosmetic Dentistry",
    "wof:placetype":"venue"
},
  "geometry": {"coordinates":[-122.983169,44.934231],"type":"Point"}
}