{
  "type": "Feature",
  "properties": {
    "iso:country":"US",
    "sg:address":"10 Vista St",
    "sg:city":"Depoe Bay",
    "sg:classifiers":[
        {
            "category":"Home & Garden",
            "subcategory":"Garden Supply",
            "type":"Retail Goods"
        }
    ],
    "sg:phone":"+1 541 765 2852",
    "sg:postcode":"97341",
    "sg:province":"OR",
    "sg:tags":[
        "statuary"
    ],
    "wof:name":"Seagull Haven",
    "wof:placetype":"venue"
},
  "geometry": {"coordinates":[-124.063069,44.817447],"type":"Point"}
}