{
  "type": "Feature",
  "properties": {
    "iso:country":"US",
    "sg:address":"6303 Fairway Ave SE",
    "sg:city":"Salem",
    "sg:classifiers":[
        {
            "category":"Government",
            "subcategory":"Office",
            "type":"Public Place"
        }
    ],
    "sg:phone":"+1 503 391 1843",
    "sg:postcode":"97306",
    "sg:province":"OR",
    "sg:tags":[
        "development"
    ],
    "wof:name":"Novare LLC",
    "wof:placetype":"venue"
},
  "geometry": {"coordinates":[-123.019785,44.863148],"type":"Point"}
}