{
  "type": "Feature",
  "properties": {
    "iso:country":"US",
    "sg:address":"1930 NE Cliff Dr",
    "sg:city":"Bend",
    "sg:classifiers":[
        {
            "category":"Restaurant",
            "type":"Food & Drink"
        }
    ],
    "sg:phone":"+1 541 382 7037",
    "sg:postcode":"97701",
    "sg:province":"OR",
    "sg:tags":[
        "eating"
    ],
    "wof:name":"Bk East Inc",
    "wof:placetype":"venue"
},
  "geometry": {"coordinates":[-121.276588,44.067643],"type":"Point"}
}