{
  "type": "Feature",
  "properties": {
    "iso:country":"US",
    "sg:address":"5665 Meadows Rd Ste 250",
    "sg:city":"Lake Oswego",
    "sg:classifiers":[
        {
            "category":"Insurance",
            "subcategory":"Hazard Insurance",
            "type":"Services"
        }
    ],
    "sg:phone":"+1 503 670 7476",
    "sg:postcode":"97035",
    "sg:province":"OR",
    "sg:website":"www.amica.com",
    "wof:name":"Amica",
    "wof:placetype":"venue"
},
  "geometry": {"coordinates":[-122.735793,45.417647],"type":"Point"}
}