{
  "type": "Feature",
  "properties": {
    "addr:full":"140 SW Arthur St Portland OR 97201",
    "addr:housenumber":"140",
    "addr:postcode":"97201",
    "addr:street":"Sw Arthur St",
    "iso:country":"US",
    "sg:address":"140 SW Arthur St",
    "sg:city":"Portland",
    "sg:classifiers":[
        {
            "category":"Professional",
            "subcategory":"Lawyer & Legal Services",
            "type":"Services"
        },
        {
            "category":"Building & Trades",
            "subcategory":"Landscaping Services",
            "type":"Services"
        }
    ],
    "sg:phone":"+1 503 224 7880",
    "sg:postcode":"97201",
    "sg:province":"OR",
    "sg:tags":[
        "attorney",
        "landscape"
    ],
    "wof:name":"Lex F Page",
    "wof:placetype":"venue"
},
  "geometry": {"coordinates":[-122.67867699999999,45.503712],"type":"Point"}
}