{
  "type": "Feature",
  "properties": {
    "addr:full":"91900 Nelson Mountain Rd Deadwood OR 97430",
    "addr:housenumber":"91900",
    "addr:postcode":"97430",
    "addr:street":"Nelson Mountain Rd",
    "iso:country":"US",
    "sg:address":"91900 Nelson Mountain Rd",
    "sg:city":"Deadwood",
    "sg:classifiers":[
        {
            "category":"Professional",
            "subcategory":"Business Services",
            "type":"Services"
        }
    ],
    "sg:phone":"+1 541 964 3280",
    "sg:postcode":"97430",
    "sg:province":"OR",
    "sg:tags":[
        "consultant",
        "coach"
    ],
    "wof:name":"Apple Creek Consulting",
    "wof:placetype":"venue"
},
  "geometry": {"coordinates":[-123.666639,44.094714],"type":"Point"}
}