{
  "type": "Feature",
  "properties": {
    "addr:full":"15 NE 181st Ave Portland OR 97230",
    "addr:housenumber":"15",
    "addr:postcode":"97230",
    "addr:street":"Ne 181St Ave",
    "iso:country":"US",
    "sg:address":"15 NE 181st Ave",
    "sg:city":"Portland",
    "sg:classifiers":[
        {
            "category":"Building & Trades",
            "subcategory":"Locksmith",
            "type":"Services"
        }
    ],
    "sg:phone":"+1 503 405 1083",
    "sg:postcode":"97230",
    "sg:province":"OR",
    "sg:tags":[
        "locksmiths-commercial",
        "industrial",
        "key",
        "lock"
    ],
    "wof:name":"1 Alpha Lock and Key of or",
    "wof:placetype":"venue"
},
  "geometry": {"coordinates":[-122.477296,45.522204],"type":"Point"}
}