{
  "type": "Feature",
  "properties": {
    "iso:country":"US",
    "sg:address":"705 Beatty St Suite B",
    "sg:city":"Medford",
    "sg:classifiers":[
        {
            "category":"Professional",
            "subcategory":"Engineering",
            "type":"Services"
        },
        {
            "category":"Home & Garden",
            "subcategory":"Building Materials",
            "type":"Retail Goods"
        },
        {
            "category":"Building & Trades",
            "subcategory":"Construction",
            "type":"Services"
        }
    ],
    "sg:phone":"+1 541 779 2279",
    "sg:postcode":"97501",
    "sg:province":"OR",
    "sg:tags":[
        "system",
        "specialty",
        "heating",
        "equipment",
        "ventilating",
        "contractor",
        "air conditioning"
    ],
    "wof:name":"Valley Heating & Sheet Metal",
    "wof:placetype":"venue"
},
  "geometry": {"coordinates":[-122.87866200000001,42.338016],"type":"Point"}
}