{
  "type": "Feature",
  "properties": {
    "iso:country":"US",
    "sg:address":"1221 SW 12th Ave",
    "sg:city":"Portland",
    "sg:classifiers":[
        {
            "category":"Education",
            "subcategory":"College",
            "type":"Public Place"
        },
        {
            "category":"Education",
            "subcategory":"Vocational School",
            "type":"Public Place"
        },
        {
            "category":"Personal",
            "subcategory":"Beauty Salon",
            "type":"Services"
        }
    ],
    "sg:phone":"+1 503 226 7355",
    "sg:postcode":"97205",
    "sg:province":"OR",
    "sg:tags":[
        "cosmetology"
    ],
    "sg:website":"www.beaumondecollege.com",
    "wof:name":"Beau Monde College of Hair Design",
    "wof:placetype":"venue"
},
  "geometry": {"coordinates":[-122.686638,45.517033],"type":"Point"}
}