{
  "type": "Feature",
  "properties": {
    "iso:country":"US",
    "sg:address":"1224 Crater Lake Ave",
    "sg:city":"Medford",
    "sg:classifiers":[
        {
            "category":"Professional",
            "type":"Services"
        }
    ],
    "sg:phone":"+1 541 618 1060",
    "sg:postcode":"97504",
    "sg:province":"OR",
    "sg:tags":[
        "establishment"
    ],
    "wof:name":"Tell-A-Nurse",
    "wof:placetype":"venue"
},
  "geometry": {"coordinates":[-122.8602,42.341725],"type":"Point"}
}