{
  "type": "Feature",
  "properties": {
    "addr:full":"12444 NE Airport Way Portland OR 97230",
    "addr:housenumber":"12444",
    "addr:postcode":"97230",
    "addr:street":"Ne Airport Way",
    "iso:country":"US",
    "sg:address":"12444 NE Airport Way",
    "sg:city":"Portland",
    "sg:classifiers":[
        {
            "category":"Restaurant",
            "type":"Food & Drink"
        }
    ],
    "sg:menulink":"http://www.allmenus.com/or/portland/180594-jack-in-the-box/menu/",
    "sg:phone":"+1 503 253 1437",
    "sg:postcode":"97230",
    "sg:province":"OR",
    "sg:tags":[
        "burger",
        "american"
    ],
    "wof:name":"Jack in the Box",
    "wof:placetype":"venue"
},
  "geometry": {"coordinates":[-122.533441,45.564561],"type":"Point"}
}