{
  "type": "Feature",
  "properties": {
    "iso:country":"US",
    "sg:address":"864 NW Garden Valley Blvd",
    "sg:city":"Roseburg",
    "sg:classifiers":[
        {
            "category":"Shopping",
            "subcategory":"Florist",
            "type":"Retail Goods"
        }
    ],
    "sg:phone":"+1 541 673 0929",
    "sg:postcode":"97470",
    "sg:province":"OR",
    "wof:name":"Long's Flowers",
    "wof:placetype":"venue"
},
  "geometry": {"coordinates":[-123.367744,43.228895],"type":"Point"}
}