{
  "type": "Feature",
  "properties": {
    "iso:country":"US",
    "sg:address":"10100 Lakeview Dr",
    "sg:city":"Clatskanie",
    "sg:classifiers":[
        {
            "category":"Wholesale",
            "subcategory":"Electrical",
            "type":"Manufacturing & Wholesale Goods"
        }
    ],
    "sg:phone":"+1 503 755 2626",
    "sg:postcode":"97016",
    "sg:province":"OR",
    "sg:tags":[
        "transmission",
        "equipment",
        "power"
    ],
    "wof:name":"Turn-A-Round Sales",
    "wof:placetype":"venue"
},
  "geometry": {"coordinates":[-123.355512,46.035952],"type":"Point"}
}