{
  "type": "Feature",
  "properties": {
    "iso:country":"US",
    "sg:address":"56835 Venture Ln",
    "sg:city":"Sunriver",
    "sg:classifiers":[
        {
            "category":"Health Services",
            "subcategory":"Doctor",
            "type":"Services"
        }
    ],
    "sg:phone":"+1 541 593 4021",
    "sg:postcode":"97707",
    "sg:province":"OR",
    "sg:tags":[
        "physician",
        "surgeon"
    ],
    "wof:name":"Ben T Chaffey MD",
    "wof:placetype":"venue"
},
  "geometry": {"coordinates":[-121.435031,43.864623],"type":"Point"}
}