{
  "type": "Feature",
  "properties": {
    "addr:full":"3532 SE Powell Portland OR 97202",
    "addr:housenumber":"3532",
    "addr:postcode":"97202",
    "addr:street":"Se Powell",
    "iso:country":"US",
    "sg:address":"3532 SE Powell",
    "sg:city":"Portland",
    "sg:classifiers":[
        {
            "category":"Shopping",
            "subcategory":"Adult",
            "type":"Retail Goods"
        }
    ],
    "sg:phone":"+1 503 234 6033",
    "sg:postcode":"97202",
    "sg:province":"OR",
    "sg:tags":[
        "entertainment"
    ],
    "wof:name":"Glimmers Gentlemens Club",
    "wof:placetype":"venue"
},
  "geometry": {"coordinates":[-122.62797500000001,45.496667],"type":"Point"}
}