{
  "type": "Feature",
  "properties": {
    "addr:full":"407 W 11th Ave Eugene OR 97401",
    "addr:housenumber":"407",
    "addr:postcode":"97401",
    "addr:street":"W 11Th Ave",
    "iso:country":"US",
    "sg:address":"407 W 11th Ave",
    "sg:city":"Eugene",
    "sg:classifiers":[
        {
            "category":"Shopping",
            "subcategory":"Bicycles & Sporting Goods",
            "type":"Retail Goods"
        }
    ],
    "sg:phone":"+1 541 431 7300",
    "sg:postcode":"97401",
    "sg:province":"OR",
    "wof:name":"Wheelworks",
    "wof:placetype":"venue"
},
  "geometry": {"coordinates":[-123.100284,44.047787],"type":"Point"}
}