{
  "type": "Feature",
  "properties": {
    "addr:full":"200 Littlebrook Ln Roseburg OR 97470",
    "addr:housenumber":"200",
    "addr:postcode":"97470",
    "addr:street":"Littlebrook Ln",
    "iso:country":"US",
    "sg:address":"200 Littlebrook Ln",
    "sg:city":"Roseburg",
    "sg:classifiers":[
        {
            "category":"Home & Garden",
            "subcategory":"Mobile Homes",
            "type":"Retail Goods"
        }
    ],
    "sg:phone":"+1 541 679 5500",
    "sg:postcode":"97470",
    "sg:province":"OR",
    "wof:name":"Littlebrook Private Community",
    "wof:placetype":"venue"
},
  "geometry": {"coordinates":[-123.385486,43.166221],"type":"Point"}
}