{
  "type": "Feature",
  "properties": {
    "iso:country":"US",
    "sg:address":"721 SE Cass Ave",
    "sg:city":"Roseburg",
    "sg:classifiers":[
        {
            "category":"Personal",
            "subcategory":"Beauty Salon",
            "type":"Services"
        }
    ],
    "sg:phone":"+1 541 229 3223",
    "sg:postcode":"97470",
    "sg:province":"OR",
    "wof:name":"La Bella Medique",
    "wof:placetype":"venue"
},
  "geometry": {"coordinates":[-123.346456,43.208567],"type":"Point"}
}