{
  "type": "Feature",
  "properties": {
    "iso:country":"US",
    "sg:address":"3275 SW Cedar Hills Blvd",
    "sg:city":"Beaverton",
    "sg:classifiers":[
        {
            "category":"Shopping",
            "subcategory":"Gifts & Souvenirs",
            "type":"Retail Goods"
        }
    ],
    "sg:phone":"+1 503 646 7613",
    "sg:postcode":"97005",
    "sg:province":"OR",
    "wof:name":"Marks Hallmark Shops 27",
    "wof:placetype":"venue"
},
  "geometry": {"coordinates":[-122.809721,45.495132],"type":"Point"}
}