{
  "type": "Feature",
  "properties": {
    "addr:full":"15995 SW Tualatin Sherwood Rd Sherwood OR 97140",
    "addr:housenumber":"15995",
    "addr:postcode":"97140",
    "addr:street":"Sw Tualatin Sherwood Rd",
    "iso:country":"US",
    "sg:address":"15995 SW Tualatin Sherwood Rd",
    "sg:city":"Sherwood",
    "sg:classifiers":[
        {
            "category":"Cinema",
            "subcategory":"Movie Theater",
            "type":"Entertainment"
        }
    ],
    "sg:phone":"+1 503 925 1474",
    "sg:postcode":"97140",
    "sg:province":"OR",
    "sg:website":"http://www.regmovies.com/",
    "wof:name":"Regal Cinema",
    "wof:placetype":"venue"
},
  "geometry": {"coordinates":[-122.841211,45.368647],"type":"Point"}
}