{
  "type": "Feature",
  "properties": {
    "addr:full":"1300 SW 6th Ave Ste 310 Portland OR 97201",
    "addr:housenumber":"1300",
    "addr:postcode":"97201",
    "addr:street":"Sw 6Th Ave Ste 310",
    "iso:country":"US",
    "sg:address":"1300 SW 6th Ave Ste 310",
    "sg:city":"Portland",
    "sg:classifiers":[
        {
            "category":"Recreation",
            "subcategory":"Playground",
            "type":"Entertainment"
        }
    ],
    "sg:phone":"+1 503 223 1157",
    "sg:postcode":"97201",
    "sg:province":"OR",
    "sg:tags":[
        "equipment"
    ],
    "sg:website":"http://www.timberform.com",
    "wof:name":"Cascade Pacific Lumber Co",
    "wof:placetype":"venue"
},
  "geometry": {"coordinates":[-122.680779,45.515079],"type":"Point"}
}