{
  "type": "Feature",
  "properties": {
    "iso:country":"US",
    "sg:address":"111 SW 5th Avenue Suite 1650",
    "sg:city":"Portland",
    "sg:classifiers":[
        {
            "category":"Professional",
            "subcategory":"Lawyer & Legal Services",
            "type":"Services"
        }
    ],
    "sg:phone":"+1 503 227 4600",
    "sg:postcode":"97204",
    "sg:province":"OR",
    "wof:name":"Bennett Hartman Morris & Kaplan Llp",
    "wof:placetype":"venue"
},
  "geometry": {"coordinates":[-122.67555,45.522554],"type":"Point"}
}