{
  "type": "Feature",
  "properties": {
    "iso:country":"US",
    "sg:address":"802 Boone Rd SE",
    "sg:city":"Salem",
    "sg:classifiers":[
        {
            "category":"Real Estate",
            "subcategory":"Real Estate Agent",
            "type":"Services"
        }
    ],
    "sg:phone":"+1 503 743 4630",
    "sg:postcode":"97306",
    "sg:province":"OR",
    "wof:name":"Cascade Rental Management Co",
    "wof:placetype":"venue"
},
  "geometry": {"coordinates":[-123.039812,44.882924],"type":"Point"}
}