{
  "type": "Feature",
  "properties": {
    "iso:country":"US",
    "sg:address":"2370 Meadow Ln",
    "sg:city":"Woodburn",
    "sg:classifiers":[
        {
            "category":"Building & Trades",
            "subcategory":"Construction",
            "type":"Services"
        }
    ],
    "sg:phone":"+1 503 981 5728",
    "sg:postcode":"97071",
    "sg:province":"OR",
    "sg:tags":[
        "contractor"
    ],
    "wof:name":"Lemco",
    "wof:placetype":"venue"
},
  "geometry": {"coordinates":[-122.820963,45.148112],"type":"Point"}
}