{
  "type": "Feature",
  "properties": {
    "addr:full":"6181 Lower River Rd Grants Pass OR 97526",
    "addr:housenumber":"6181",
    "addr:postcode":"97526",
    "addr:street":"Lower River Rd",
    "iso:country":"US",
    "sg:address":"6181 Lower River Rd",
    "sg:city":"Grants Pass",
    "sg:classifiers":[
        {
            "category":"Farming",
            "subcategory":"Dairy Farm",
            "type":"Manufacturing & Wholesale Goods"
        }
    ],
    "sg:phone":"+1 541 479 9380",
    "sg:postcode":"97526",
    "sg:province":"OR",
    "wof:name":"Rogue View Dairy",
    "wof:placetype":"venue"
},
  "geometry": {"coordinates":[-123.43106,42.437965],"type":"Point"}
}