{
  "type": "Feature",
  "properties": {
    "iso:country":"US",
    "sg:address":"51456 Hwy 97",
    "sg:city":"La Pine",
    "sg:classifiers":[
        {
            "category":"Retail",
            "subcategory":"Laundry & Dry Cleaning",
            "type":"Services"
        }
    ],
    "sg:phone":"+1 541 536 3384",
    "sg:postcode":"97739",
    "sg:province":"OR",
    "sg:tags":[
        "cleaners"
    ],
    "wof:name":"LA Pine Dry Cleaning",
    "wof:placetype":"venue"
},
  "geometry": {"coordinates":[-121.504426,43.669196],"type":"Point"}
}