{
  "type": "Feature",
  "properties": {
    "addr:full":"2754 Pacific Hwy Hubbard OR 97032",
    "addr:housenumber":"2754",
    "addr:postcode":"97032",
    "addr:street":"Pacific Hwy",
    "iso:country":"US",
    "sg:address":"2754 Pacific Hwy",
    "sg:city":"Hubbard",
    "sg:classifiers":[
        {
            "category":"Home & Garden",
            "subcategory":"Furniture",
            "type":"Retail Goods"
        }
    ],
    "sg:phone":"+1 503 982 3543",
    "sg:postcode":"97032",
    "sg:province":"OR",
    "wof:name":"Furniture Express",
    "wof:placetype":"venue"
},
  "geometry": {"coordinates":[-122.80801,45.177558],"type":"Point"}
}