{
  "type": "Feature",
  "properties": {
    "iso:country":"US",
    "sg:address":"2073 Olympic St",
    "sg:city":"Springfield",
    "sg:classifiers":[
        {
            "category":"Health Services",
            "subcategory":"Doctor",
            "type":"Services"
        }
    ],
    "sg:phone":"+1 541 747 8328",
    "sg:postcode":"97477",
    "sg:province":"OR",
    "sg:tags":[
        "physician",
        "medical",
        "surgeon"
    ],
    "wof:name":"Allergy & Asthma Center",
    "wof:placetype":"venue"
},
  "geometry": {"coordinates":[-122.997694,44.059506],"type":"Point"}
}