{
  "type": "Feature",
  "properties": {
    "iso:country":"US",
    "sg:address":"23030 NW Chestnut St",
    "sg:city":"Hillsboro",
    "sg:classifiers":[
        {
            "category":"Building & Trades",
            "subcategory":"Landscaping Services",
            "type":"Services"
        }
    ],
    "sg:phone":"+1 503 640 1277",
    "sg:postcode":"97124",
    "sg:province":"OR",
    "sg:tags":[
        "landscape"
    ],
    "wof:name":"Hi-Tech",
    "wof:placetype":"venue"
},
  "geometry": {"coordinates":[-122.913349,45.527816],"type":"Point"}
}