{
  "type": "Feature",
  "properties": {
    "iso:country":"US",
    "sg:address":"529 SW Deschutes Ave",
    "sg:city":"Redmond",
    "sg:classifiers":[
        {
            "category":"Building & Trades",
            "subcategory":"Locksmith",
            "type":"Services"
        },
        {
            "category":"Shopping",
            "type":"Retail Goods"
        }
    ],
    "sg:phone":"+1 541 548 2536",
    "sg:postcode":"97756",
    "sg:province":"OR",
    "sg:tags":[
        "supply",
        "lock",
        "safe",
        "equipment",
        "key",
        "vault"
    ],
    "sg:website":"http://www.a-1lockandsafe-priority1.com",
    "wof:name":"A-1 Lock & Safe Co",
    "wof:placetype":"venue"
},
  "geometry": {"coordinates":[-121.17352,44.273571],"type":"Point"}
}