{
  "type": "Feature",
  "properties": {
    "addr:full":"228 S Oak Rd Tygh Valley OR 97063",
    "addr:housenumber":"228",
    "addr:postcode":"97063",
    "addr:street":"S Oak Rd",
    "iso:country":"US",
    "sg:address":"228 S Oak Rd",
    "sg:city":"Tygh Valley",
    "sg:classifiers":[
        {
            "category":"Freight",
            "type":"Transportation"
        }
    ],
    "sg:phone":"+1 541 544 3330",
    "sg:postcode":"97063",
    "sg:province":"OR",
    "sg:tags":[
        "operator",
        "local",
        "hauling",
        "trucking"
    ],
    "wof:name":"Interstate Trucking Consultant",
    "wof:placetype":"venue"
},
  "geometry": {"coordinates":[-121.30149400000001,45.247066],"type":"Point"}
}