{
  "type": "Feature",
  "properties": {
    "iso:country":"US",
    "sg:address":"9848 N Whitaker Rd",
    "sg:city":"Portland",
    "sg:classifiers":[
        {
            "category":"Restaurant",
            "type":"Food & Drink"
        }
    ],
    "sg:phone":"+1 503 289 9848",
    "sg:postcode":"97217",
    "sg:province":"OR",
    "sg:website":"www.elmers-restaurants.com/",
    "wof:name":"Elmer's",
    "wof:placetype":"venue"
},
  "geometry": {"coordinates":[-122.68168900000001,45.594301],"type":"Point"}
}