{
  "type": "Feature",
  "properties": {
    "iso:country":"US",
    "sg:address":"9347 SW Link St",
    "sg:city":"Cornelius",
    "sg:classifiers":[
        {
            "category":"Restaurant",
            "type":"Food & Drink"
        }
    ],
    "sg:phone":"+1 503 628 8336",
    "sg:postcode":"97113",
    "sg:province":"OR",
    "sg:tags":[
        "eating"
    ],
    "wof:name":"Jinx Cafe II",
    "wof:placetype":"venue"
},
  "geometry": {"coordinates":[-123.004362,45.45267],"type":"Point"}
}