{
  "type": "Feature",
  "properties": {
    "iso:country":"US",
    "sg:address":"888 SW 5th Ave",
    "sg:city":"Portland",
    "sg:classifiers":[
        {
            "category":"Professional",
            "subcategory":"Lawyer & Legal Services",
            "type":"Services"
        }
    ],
    "sg:phone":"+1 503 802 2035",
    "sg:postcode":"97204",
    "sg:province":"OR",
    "wof:name":"Beth Zilbert Jansen",
    "wof:placetype":"venue"
},
  "geometry": {"coordinates":[-122.678015,45.518021],"type":"Point"}
}