{
  "type": "Feature",
  "properties": {
    "addr:full":"1419 SE Hawthorne Blvd Portland OR 97214",
    "addr:housenumber":"1419",
    "addr:postcode":"97214",
    "addr:street":"Se Hawthorne Blvd",
    "iso:country":"US",
    "sg:address":"1419 SE Hawthorne Blvd",
    "sg:city":"Portland",
    "sg:classifiers":[
        {
            "category":"Coffee & Tea",
            "type":"Food & Drink"
        }
    ],
    "sg:phone":"+1 503 239 7150",
    "sg:postcode":"97214",
    "sg:province":"OR",
    "sg:website":"www.yarngarden.net",
    "wof:name":"Yarn Garden Sipperie",
    "wof:placetype":"venue"
},
  "geometry": {"coordinates":[-122.651449,45.512203],"type":"Point"}
}