{
  "type": "Feature",
  "properties": {
    "iso:country":"US",
    "sg:address":"109 9th St",
    "sg:city":"Astoria",
    "sg:classifiers":[
        {
            "category":"Professional",
            "subcategory":"Accounting & Tax Preparation",
            "type":"Services"
        }
    ],
    "sg:phone":"+1 503 325 1166",
    "sg:postcode":"97103",
    "sg:province":"OR",
    "sg:tags":[
        "communication",
        "return",
        "telegraph"
    ],
    "wof:name":"H & R Block",
    "wof:placetype":"venue"
},
  "geometry": {"coordinates":[-123.833748,46.190384],"type":"Point"}
}