{
  "type": "Feature",
  "properties": {
    "addr:full":"602 NW Skyline Crest Rd Portland OR 97229",
    "addr:housenumber":"602",
    "addr:postcode":"97229",
    "addr:street":"Nw Skyline Crest Rd",
    "iso:country":"US",
    "sg:address":"602 NW Skyline Crest Rd",
    "sg:city":"Portland",
    "sg:classifiers":[
        {
            "category":"Manufacturing",
            "subcategory":"Printing",
            "type":"Manufacturing & Wholesale Goods"
        }
    ],
    "sg:phone":"+1 503 297 1887",
    "sg:postcode":"97229",
    "sg:province":"OR",
    "sg:tags":[
        "book",
        "publishing"
    ],
    "wof:name":"Raven Editions",
    "wof:placetype":"venue"
},
  "geometry": {"coordinates":[-122.75468100000001,45.527776],"type":"Point"}
}