{
  "type": "Feature",
  "properties": {
    "iso:country":"US",
    "sg:address":"40873 24th St",
    "sg:city":"Lyons",
    "sg:classifiers":[
        {
            "category":"Professional",
            "subcategory":"Advertising",
            "type":"Services"
        }
    ],
    "sg:phone":"+1 503 859 3761",
    "sg:postcode":"97358",
    "sg:province":"OR",
    "sg:tags":[
        "product",
        "advertising-promotional",
        "specialty"
    ],
    "wof:name":"Decorative Bark Products Inc",
    "wof:placetype":"venue"
},
  "geometry": {"coordinates":[-122.59091100000001,44.770087],"type":"Point"}
}