{
  "type": "Feature",
  "properties": {
    "addr:full":"29818 Brownsville Rd Brownsville OR 97327",
    "addr:housenumber":"29818",
    "addr:postcode":"97327",
    "addr:street":"Brownsville Rd",
    "iso:country":"US",
    "sg:address":"29818 Brownsville Rd",
    "sg:city":"Brownsville",
    "sg:phone":"+1 541 466 3410",
    "sg:postcode":"97327",
    "sg:province":"OR",
    "sg:tags":[
        "farm",
        "wheat"
    ],
    "wof:name":"Webber Farms Inc",
    "wof:placetype":"venue"
},
  "geometry": {"coordinates":[-122.989228,44.447636],"type":"Point"}
}