{
  "type": "Feature",
  "properties": {
    "iso:country":"US",
    "sg:address":"9011 SW Beaverton-Hillsdale Hwy",
    "sg:city":"Portland",
    "sg:classifiers":[
        {
            "category":"Wholesale",
            "subcategory":"Electrical",
            "type":"Manufacturing & Wholesale Goods"
        }
    ],
    "sg:phone":"+1 503 292 8855",
    "sg:postcode":"97225",
    "sg:province":"OR",
    "sg:tags":[
        "equipment",
        "electronic",
        "supply"
    ],
    "sg:website":"www.force-elec.com",
    "wof:name":"Force Electronics",
    "wof:placetype":"venue"
},
  "geometry": {"coordinates":[-122.77050699999999,45.486342],"type":"Point"}
}