{
  "type": "Feature",
  "properties": {
    "iso:country":"US",
    "sg:address":"14251 SE Rust Way",
    "sg:city":"Boring",
    "sg:classifiers":[
        {
            "category":"Organizations",
            "subcategory":"Religious Organization",
            "type":"Services"
        }
    ],
    "sg:phone":"+1 503 658 3179",
    "sg:postcode":"97089",
    "sg:province":"OR",
    "sg:tags":[
        "church"
    ],
    "wof:name":"Damascus Community",
    "wof:placetype":"venue"
},
  "geometry": {"coordinates":[-122.44921100000001,45.419438],"type":"Point"}
}