{
  "type": "Feature",
  "properties": {
    "iso:country":"US",
    "sg:address":"1144 SW Greenwood Ave",
    "sg:city":"Grants Pass",
    "sg:classifiers":[
        {
            "category":"Retail",
            "subcategory":"Portrait Studio",
            "type":"Services"
        }
    ],
    "sg:phone":"+1 541 660 9159",
    "sg:postcode":"97526",
    "sg:province":"OR",
    "sg:tags":[
        "photographer"
    ],
    "wof:name":"J H Photography",
    "wof:placetype":"venue"
},
  "geometry": {"coordinates":[-123.342053,42.432447],"type":"Point"}
}