{
  "type": "Feature",
  "properties": {
    "iso:country":"US",
    "sg:address":"34144 SE Jarl Rd",
    "sg:city":"Boring",
    "sg:classifiers":[
        {
            "category":"Real Estate",
            "subcategory":"Architect",
            "type":"Services"
        }
    ],
    "sg:phone":"+1 503 668 0892",
    "sg:postcode":"97009",
    "sg:province":"OR",
    "sg:tags":[
        "architectural"
    ],
    "wof:name":"Robert W Reed Architect",
    "wof:placetype":"venue"
},
  "geometry": {"coordinates":[-122.306668,45.409196],"type":"Point"}
}