{
  "type": "Feature",
  "properties": {
    "addr:full":"2658 SW Chelmsford Ave Portland OR 97201",
    "addr:housenumber":"2658",
    "addr:postcode":"97201",
    "addr:street":"Sw Chelmsford Ave",
    "iso:country":"US",
    "sg:address":"2658 SW Chelmsford Ave",
    "sg:city":"Portland",
    "sg:classifiers":[
        {
            "category":"Professional",
            "type":"Services"
        }
    ],
    "sg:phone":"+1 503 243 2283",
    "sg:postcode":"97201",
    "sg:province":"OR",
    "sg:website":"www.careersinbalance.com",
    "wof:name":"Careers In Balance",
    "wof:placetype":"venue"
},
  "geometry": {"coordinates":[-122.687325,45.505646],"type":"Point"}
}