{
  "type": "Feature",
  "properties": {
    "addr:full":"21028 State Hwy 99E NE Aurora OR 97002",
    "addr:housenumber":"21028",
    "addr:postcode":"97002",
    "addr:street":"State Hwy 99E Ne",
    "iso:country":"US",
    "sg:address":"21028 State Hwy 99E NE",
    "sg:city":"Aurora",
    "sg:classifiers":[
        {
            "category":"Professional",
            "subcategory":"Lawyer & Legal Services",
            "type":"Services"
        }
    ],
    "sg:phone":"+1 503 678 5275",
    "sg:postcode":"97002",
    "sg:province":"OR",
    "sg:tags":[
        "attorney"
    ],
    "wof:name":"Aurora Law Office",
    "wof:placetype":"venue"
},
  "geometry": {"coordinates":[-122.758393,45.223752],"type":"Point"}
}