{
  "type": "Feature",
  "properties": {
    "addr:full":"30292 SE Lawrence Rd Estacada OR 97023",
    "addr:postcode":"30292;97023",
    "addr:street":"Se Lawrence Rd",
    "iso:country":"US",
    "sg:address":"30292 SE Lawrence Rd",
    "sg:city":"Estacada",
    "sg:classifiers":[
        {
            "category":"Farming",
            "subcategory":"Livestock Farm",
            "type":"Manufacturing & Wholesale Goods"
        },
        {
            "category":"Farming",
            "subcategory":"Farm",
            "type":"Manufacturing & Wholesale Goods"
        }
    ],
    "sg:phone":"+1 503 630 4611",
    "sg:postcode":"97023",
    "sg:province":"OR",
    "sg:website":"http://www.twistedcreekranch.com",
    "wof:name":"Twisted Creek Ranch",
    "wof:placetype":"venue"
},
  "geometry": {"coordinates":[-122.312046,45.303873],"type":"Point"}
}