{
  "type": "Feature",
  "properties": {
    "iso:country":"US",
    "sg:address":"11852 SW Pacific Hwy",
    "sg:city":"Portland",
    "sg:classifiers":[
        {
            "category":"Home & Garden",
            "subcategory":"Furniture",
            "type":"Retail Goods"
        }
    ],
    "sg:phone":"+1 503 620 7500",
    "sg:postcode":"97223",
    "sg:province":"OR",
    "wof:name":"Madison House Furniture",
    "wof:placetype":"venue"
},
  "geometry": {"coordinates":[-122.764742,45.434022],"type":"Point"}
}