{
  "type": "Feature",
  "properties": {
    "addr:full":"121 N Lombard St Portland OR 97217",
    "addr:housenumber":"121",
    "addr:postcode":"97217",
    "addr:street":"N Lombard St",
    "iso:country":"US",
    "sg:address":"121 N Lombard St",
    "sg:city":"Portland",
    "sg:classifiers":[
        {
            "category":"Building & Trades",
            "subcategory":"Locksmith",
            "type":"Services"
        }
    ],
    "sg:phone":"+1 503 714 0064",
    "sg:postcode":"97217",
    "sg:province":"OR",
    "sg:tags":[
        "key"
    ],
    "wof:name":"1 Emergency Portland Locksmith",
    "wof:placetype":"venue"
},
  "geometry": {"coordinates":[-122.66776,45.577357],"type":"Point"}
}