{
  "type": "Feature",
  "properties": {
    "iso:country":"US",
    "sg:address":"1370 Rogue River Hwy",
    "sg:city":"Grants Pass",
    "sg:classifiers":[
        {
            "category":"Professional",
            "subcategory":"Accounting & Tax Preparation",
            "type":"Services"
        }
    ],
    "sg:phone":"+1 541 476 6691",
    "sg:postcode":"97527",
    "sg:province":"OR",
    "sg:tags":[
        "return",
        "filing"
    ],
    "sg:website":"www.a1pro.net",
    "wof:name":"A-1 Professional Svc",
    "wof:placetype":"venue"
},
  "geometry": {"coordinates":[-123.312094,42.4224],"type":"Point"}
}