{
  "type": "Feature",
  "properties": {
    "iso:country":"US",
    "sg:address":"37457 Gore Dr",
    "sg:city":"Lebanon",
    "sg:classifiers":[
        {
            "category":"Health Services",
            "subcategory":"Medical Lab",
            "type":"Services"
        }
    ],
    "sg:phone":"+1 541 258 7885",
    "sg:postcode":"97355",
    "sg:province":"OR",
    "sg:tags":[
        "laboratory"
    ],
    "wof:name":"Jones B Dental Lab",
    "wof:placetype":"venue"
},
  "geometry": {"coordinates":[-122.89752799999999,44.561156],"type":"Point"}
}