{
  "type": "Feature",
  "properties": {
    "addr:full":"14875 SW Peachtree Dr Portland OR 97224",
    "addr:housenumber":"14875",
    "addr:postcode":"97224",
    "addr:street":"Sw Peachtree Dr",
    "iso:country":"US",
    "sg:address":"14875 SW Peachtree Dr",
    "sg:city":"Portland",
    "sg:classifiers":[
        {
            "category":"Professional",
            "subcategory":"Engineering",
            "type":"Services"
        }
    ],
    "sg:phone":"+1 503 590 1533",
    "sg:postcode":"97224",
    "sg:province":"OR",
    "wof:name":"Bolton Engineering",
    "wof:placetype":"venue"
},
  "geometry": {"coordinates":[-122.81719200000001,45.4115],"type":"Point"}
}