{
  "type": "Feature",
  "properties": {
    "iso:country":"US",
    "sg:address":"3544 SE Milwaukie Ave",
    "sg:city":"Portland",
    "sg:classifiers":[
        {
            "category":"Building & Trades",
            "subcategory":"Construction",
            "type":"Services"
        }
    ],
    "sg:phone":"+1 503 232 4321",
    "sg:postcode":"97202",
    "sg:province":"OR",
    "sg:tags":[
        "contractor",
        "painting",
        "hanging"
    ],
    "wof:name":"Spraykote Shop Finishing",
    "wof:placetype":"venue"
},
  "geometry": {"coordinates":[-122.653758,45.497187],"type":"Point"}
}