{
  "type": "Feature",
  "properties": {
    "addr:full":"15725 SE Hanwood Ln Milwaukie OR 97267",
    "addr:postcode":"15725;97267",
    "addr:street":"Se Hanwood Ln",
    "iso:country":"US",
    "sg:address":"15725 SE Hanwood Ln",
    "sg:city":"Milwaukie",
    "sg:classifiers":[
        {
            "category":"Building & Trades",
            "subcategory":"Construction",
            "type":"Services"
        },
        {
            "category":"Utilities",
            "type":"Services"
        }
    ],
    "sg:phone":"+1 503 654 2637",
    "sg:postcode":"97267",
    "sg:province":"OR",
    "sg:tags":[
        "locating"
    ],
    "wof:name":"Locates Down Under Inc",
    "wof:placetype":"venue"
},
  "geometry": {"coordinates":[-122.647724,45.409996],"type":"Point"}
}