{
  "type": "Feature",
  "properties": {
    "addr:full":"2001 Biddle Rd Medford OR 97504",
    "addr:housenumber":"2001",
    "addr:postcode":"97504",
    "addr:street":"Biddle Rd",
    "iso:country":"US",
    "sg:address":"2001 Biddle Rd",
    "sg:city":"Medford",
    "sg:classifiers":[
        {
            "category":"Coffee & Tea",
            "type":"Food & Drink"
        }
    ],
    "sg:postcode":"97504",
    "sg:province":"OR",
    "sg:website":"www.blackrockcoffeebar.com",
    "wof:name":"Black Rock Coffee Bar",
    "wof:placetype":"venue"
},
  "geometry": {"coordinates":[-122.87460400000001,42.347948],"type":"Point"}
}