{
  "type": "Feature",
  "properties": {
    "iso:country":"US",
    "sg:address":"1340 Biddle Rd",
    "sg:city":"Medford",
    "sg:classifiers":[
        {
            "category":"Shopping",
            "subcategory":"Bicycles & Sporting Goods",
            "type":"Retail Goods"
        }
    ],
    "sg:phone":"+1 541 773 5145",
    "sg:postcode":"97504",
    "sg:province":"OR",
    "sg:tags":[
        "equipment",
        "outdoor",
        "gear",
        "camping"
    ],
    "sg:website":"www.mckenzieoutfitters.com",
    "wof:name":"McKenzie Outfitters Inc",
    "wof:placetype":"venue"
},
  "geometry": {"coordinates":[-122.87200199999999,42.3409],"type":"Point"}
}