{
  "type": "Feature",
  "properties": {
    "iso:country":"US",
    "sg:address":"3314 SW 1st Ave",
    "sg:city":"Portland",
    "sg:classifiers":[
        {
            "category":"Recreation",
            "type":"Entertainment"
        }
    ],
    "sg:phone":"+1 503 228 0740",
    "sg:postcode":"97239",
    "sg:province":"OR",
    "sg:tags":[
        "psychic",
        "medium"
    ],
    "wof:name":"CDM Psychic Inst-Portland",
    "wof:placetype":"venue"
},
  "geometry": {"coordinates":[-122.678836,45.498801],"type":"Point"}
}