{
  "type": "Feature",
  "properties": {
    "iso:country":"US",
    "sg:address":"24720 SW Pheasant Ln",
    "sg:city":"Hillsboro",
    "sg:classifiers":[
        {
            "category":"Building & Trades",
            "subcategory":"Construction",
            "type":"Services"
        }
    ],
    "sg:phone":"+1 503 848 9492",
    "sg:postcode":"97123",
    "sg:province":"OR",
    "sg:tags":[
        "concrete",
        "contractor"
    ],
    "wof:name":"Reese General Contracting",
    "wof:placetype":"venue"
},
  "geometry": {"coordinates":[-122.932841,45.48882],"type":"Point"}
}