{
  "type": "Feature",
  "properties": {
    "iso:country":"US",
    "sg:address":"705 Storey Dr",
    "sg:city":"Molalla",
    "sg:classifiers":[
        {
            "category":"Building & Trades",
            "subcategory":"Construction",
            "type":"Services"
        }
    ],
    "sg:phone":"+1 503 829 5125",
    "sg:postcode":"97038",
    "sg:province":"OR",
    "sg:tags":[
        "carpentry",
        "contractor"
    ],
    "wof:name":"Troy A Pruitt",
    "wof:placetype":"venue"
},
  "geometry": {"coordinates":[-122.59783299999999,45.156074],"type":"Point"}
}