{
  "type": "Feature",
  "properties": {
    "iso:country":"US",
    "sg:address":"2020 NW Aloclek Dr",
    "sg:city":"Hillsboro",
    "sg:classifiers":[
        {
            "category":"Personal",
            "subcategory":"Beauty Salon",
            "type":"Services"
        },
        {
            "category":"Personal",
            "subcategory":"Barber",
            "type":"Services"
        }
    ],
    "sg:phone":"+1 503 533 9785",
    "sg:postcode":"97124",
    "sg:province":"OR",
    "sg:tags":[
        "shop"
    ],
    "wof:name":"Ritual Hair Design",
    "wof:placetype":"venue"
},
  "geometry": {"coordinates":[-122.89456,45.53522],"type":"Point"}
}