{
  "type": "Feature",
  "properties": {
    "addr:full":"4730 Village Plaza Loop Eugene OR 97401",
    "addr:housenumber":"4730",
    "addr:postcode":"97401",
    "addr:street":"Village Plaza Loop",
    "iso:country":"US",
    "sg:address":"4730 Village Plaza Loop",
    "sg:city":"Eugene",
    "sg:classifiers":[
        {
            "category":"Restaurant",
            "type":"Food & Drink"
        }
    ],
    "sg:menulink":"http://www.allmenus.com/or/eugene-springfield/44842-los-dos-amigos/menu/",
    "sg:phone":"+1 541 686 8455",
    "sg:postcode":"97401",
    "sg:province":"OR",
    "sg:tags":[
        "mexican"
    ],
    "wof:name":"Los Dos Amigos",
    "wof:placetype":"venue"
},
  "geometry": {"coordinates":[-123.10487000000001,44.088503],"type":"Point"}
}