{
  "type": "Feature",
  "properties": {
    "addr:full":"520 Lindy Ln Coos Bay OR 97420",
    "addr:housenumber":"520",
    "addr:postcode":"97420",
    "addr:street":"Lindy Ln",
    "iso:country":"US",
    "sg:address":"520 Lindy Ln",
    "sg:city":"Coos Bay",
    "sg:classifiers":[
        {
            "category":"Freight",
            "type":"Transportation"
        }
    ],
    "sg:phone":"+1 541 888 3220",
    "sg:postcode":"97420",
    "sg:province":"OR",
    "sg:tags":[
        "trucking"
    ],
    "wof:name":"USF Reddaway Inc",
    "wof:placetype":"venue"
},
  "geometry": {"coordinates":[-124.254487,43.385834],"type":"Point"}
}