{
  "type": "Feature",
  "properties": {
    "addr:full":"2001 SE 11th Ave Portland OR 97214",
    "addr:housenumber":"2001",
    "addr:postcode":"97214",
    "addr:street":"Se 11Th Ave",
    "iso:country":"US",
    "sg:address":"2001 SE 11th Ave",
    "sg:city":"Portland",
    "sg:classifiers":[
        {
            "category":"Building & Trades",
            "subcategory":"Locksmith",
            "type":"Services"
        }
    ],
    "sg:phone":"+1 503 345 1139",
    "sg:postcode":"97214",
    "sg:province":"OR",
    "sg:tags":[
        "lock",
        "industrial",
        "locksmiths-commercial"
    ],
    "wof:name":"000 A Locksmith Service",
    "wof:placetype":"venue"
},
  "geometry": {"coordinates":[-122.65471599999999,45.508659],"type":"Point"}
}