{
  "type": "Feature",
  "properties": {
    "iso:country":"US",
    "sg:address":"1171 Vintage Dr",
    "sg:city":"Elkton",
    "sg:classifiers":[
        {
            "category":"Farming",
            "subcategory":"Vineyard",
            "type":"Manufacturing & Wholesale Goods"
        }
    ],
    "sg:phone":"+1 541 584 2826",
    "sg:postcode":"97436",
    "sg:province":"OR",
    "wof:name":"North Block",
    "wof:placetype":"venue"
},
  "geometry": {"coordinates":[-123.555003,43.610669],"type":"Point"}
}