{
  "type": "Feature",
  "properties": {
    "iso:country":"US",
    "sg:address":"5930 NE 42nd Ave",
    "sg:city":"Portland",
    "sg:classifiers":[
        {
            "category":"Building & Trades",
            "subcategory":"Cleaning & Sanitation",
            "type":"Services"
        }
    ],
    "sg:phone":"+1 503 284 4151",
    "sg:postcode":"97218",
    "sg:province":"OR",
    "sg:tags":[
        "janitor"
    ],
    "wof:name":"Oscran Janitorial Inc",
    "wof:placetype":"venue"
},
  "geometry": {"coordinates":[-122.620361,45.566028],"type":"Point"}
}