{
  "type": "Feature",
  "properties": {
    "iso:country":"US",
    "sg:address":"736 NW I St",
    "sg:city":"Toledo",
    "sg:classifiers":[
        {
            "category":"Retail",
            "subcategory":"Repair Shop",
            "type":"Services"
        },
        {
            "category":"Retail",
            "subcategory":"Auto Repair",
            "type":"Services"
        }
    ],
    "sg:phone":"+1 541 336 2990",
    "sg:postcode":"97391",
    "sg:province":"OR",
    "sg:tags":[
        "repairing",
        "automobile"
    ],
    "wof:name":"M & R Auto Repair",
    "wof:placetype":"venue"
},
  "geometry": {"coordinates":[-123.947031,44.624839],"type":"Point"}
}