{
  "type": "Feature",
  "properties": {
    "addr:full":"1805 Adams Ave La Grande OR 97850",
    "addr:housenumber":"1805",
    "addr:postcode":"97850",
    "addr:street":"Adams Ave",
    "iso:country":"US",
    "sg:address":"1805 Adams Ave",
    "sg:city":"La Grande",
    "sg:classifiers":[
        {
            "category":"Wholesale",
            "subcategory":"Machinery & Supplies",
            "type":"Manufacturing & Wholesale Goods"
        }
    ],
    "sg:phone":"+1 541 963 3101",
    "sg:postcode":"97850",
    "sg:province":"OR",
    "sg:tags":[
        "contractor"
    ],
    "wof:name":"Western States Equipment Co",
    "wof:placetype":"venue"
},
  "geometry": {"coordinates":[-118.086518,45.323738],"type":"Point"}
}