{
  "type": "Feature",
  "properties": {
    "iso:country":"US",
    "sg:address":"107 SE Washington St",
    "sg:city":"Portland",
    "sg:classifiers":[
        {
            "category":"Utilities",
            "subcategory":"Telephone",
            "type":"Services"
        }
    ],
    "sg:phone":"+1 503 232 8219",
    "sg:postcode":"97214",
    "sg:province":"OR",
    "sg:tags":[
        "telecommunication"
    ],
    "wof:name":"Pacific Telecom Svc LLC",
    "wof:placetype":"venue"
},
  "geometry": {"coordinates":[-122.663813,45.518738],"type":"Point"}
}