{
  "type": "Feature",
  "properties": {
    "iso:country":"US",
    "sg:address":"550 S State St",
    "sg:city":"Sutherlin",
    "sg:classifiers":[
        {
            "category":"Building & Trades",
            "subcategory":"Construction",
            "type":"Services"
        }
    ],
    "sg:phone":"+1 541 459 9521",
    "sg:postcode":"97479",
    "sg:province":"OR",
    "sg:tags":[
        "home",
        "general",
        "family",
        "contractor"
    ],
    "wof:name":"Andy Holm Construction",
    "wof:placetype":"venue"
},
  "geometry": {"coordinates":[-123.311476,43.384296],"type":"Point"}
}