{
  "type": "Feature",
  "properties": {
    "addr:full":"2533 NE Hwy 99W Mcminnville OR 97128",
    "addr:housenumber":"2533",
    "addr:postcode":"97128",
    "addr:street":"Ne Hwy 99W",
    "iso:country":"US",
    "sg:address":"2533 NE Hwy 99W",
    "sg:city":"Mcminnville",
    "sg:classifiers":[
        {
            "category":"Personal",
            "subcategory":"Beauty Salon",
            "type":"Services"
        }
    ],
    "sg:phone":"+1 503 474 1568",
    "sg:postcode":"97128",
    "sg:province":"OR",
    "sg:tags":[
        "shop"
    ],
    "sg:website":"www.greatclips.com",
    "wof:name":"Great Clips",
    "wof:placetype":"venue"
},
  "geometry": {"coordinates":[-123.171999,45.228999],"type":"Point"}
}