{
  "type": "Feature",
  "properties": {
    "addr:full":"9104 SE Woodstock Portland OR 97266",
    "addr:housenumber":"9104",
    "addr:postcode":"97266",
    "addr:street":"Se",
    "iso:country":"US",
    "sg:address":"9104 SE Woodstock",
    "sg:city":"Portland",
    "sg:classifiers":[
        {
            "category":"Autos & Motor Vehicles",
            "subcategory":"Motorcycle Sales",
            "type":"Retail Goods"
        }
    ],
    "sg:phone":"+1 503 239 5150",
    "sg:postcode":"97266",
    "sg:province":"OR",
    "sg:website":"www.allamericancycle.com",
    "wof:name":"All American Cycle",
    "wof:placetype":"venue"
},
  "geometry": {"coordinates":[-122.56943200000001,45.479031],"type":"Point"}
}