{
  "type": "Feature",
  "properties": {
    "iso:country":"US",
    "sg:address":"1370 Franklin Blvd",
    "sg:city":"Eugene",
    "sg:classifiers":[
        {
            "category":"Professional",
            "subcategory":"Research",
            "type":"Services"
        }
    ],
    "sg:phone":"+1 541 346 5151",
    "sg:postcode":"97403",
    "sg:province":"OR",
    "sg:tags":[
        "organization",
        "noncommercial"
    ],
    "wof:name":"Institute of Molecular Biology",
    "wof:placetype":"venue"
},
  "geometry": {"coordinates":[-123.077209,44.048124],"type":"Point"}
}