{
  "type": "Feature",
  "properties": {
    "addr:full":"17750 SW Upper Boones Ferry Rd Upr Boones Ferry#150 Portland OR 97224",
    "addr:housenumber":"17750",
    "addr:postcode":"97224",
    "addr:street":"Sw Upper Boones Ferry Rd;Boones Ferry # 150",
    "iso:country":"US",
    "sg:address":"17750 SW Upper Boones Ferry Rd Upr Boones Ferry#150",
    "sg:city":"Portland",
    "sg:classifiers":[
        {
            "category":"Autos & Motor Vehicles",
            "subcategory":"Auto Supplies",
            "type":"Retail Goods"
        },
        {
            "category":"Manufacturing",
            "subcategory":"Electronics",
            "type":"Manufacturing & Wholesale Goods"
        }
    ],
    "sg:phone":"+1 503 598 9393",
    "sg:postcode":"97224",
    "sg:province":"OR",
    "sg:tags":[
        "consultant",
        "robotics",
        "automation"
    ],
    "wof:name":"D W Fritz Automation",
    "wof:placetype":"venue"
},
  "geometry": {"coordinates":[-122.755866,45.391842],"type":"Point"}
}