{
  "type": "Feature",
  "properties": {
    "iso:country":"US",
    "sg:address":"104 5th St",
    "sg:city":"Hood River",
    "sg:classifiers":[
        {
            "category":"Social Services",
            "type":"Services"
        }
    ],
    "sg:phone":"+1 541 386 1650",
    "sg:postcode":"97031",
    "sg:province":"OR",
    "sg:tags":[
        "counselor",
        "marriage",
        "family"
    ],
    "wof:name":"Bodymind Therapy",
    "wof:placetype":"venue"
},
  "geometry": {"coordinates":[-121.515409,45.709551],"type":"Point"}
}