{
  "type": "Feature",
  "properties": {
    "addr:full":"2755 NW 31st Ave Portland OR 97210",
    "addr:housenumber":"2755",
    "addr:postcode":"97210",
    "addr:street":"Nw 31St Ave",
    "iso:country":"US",
    "sg:address":"2755 NW 31st Ave",
    "sg:city":"Portland",
    "sg:classifiers":[
        {
            "category":"Wholesale",
            "subcategory":"Wine & Distilled Alcoholic Beverages",
            "type":"Manufacturing & Wholesale Goods"
        }
    ],
    "sg:phone":"+1 503 224 3150",
    "sg:postcode":"97210",
    "sg:province":"OR",
    "sg:website":"www.mcclaskeyswine.com",
    "wof:name":"Mcclaskey's Wine & Spirits",
    "wof:placetype":"venue"
},
  "geometry": {"coordinates":[-122.71391300000001,45.538907],"type":"Point"}
}