{
  "type": "Feature",
  "properties": {
    "addr:full":"21141 SW Alexander St Beaverton OR 97006",
    "addr:housenumber":"21141",
    "addr:postcode":"97006",
    "addr:street":"Sw Alexander St",
    "iso:country":"US",
    "sg:address":"21141 SW Alexander St",
    "sg:city":"Beaverton",
    "sg:classifiers":[
        {
            "category":"Real Estate",
            "subcategory":"Real Estate Services",
            "type":"Services"
        },
        {
            "category":"Real Estate",
            "subcategory":"Real Estate Operator",
            "type":"Services"
        }
    ],
    "sg:phone":"+1 503 356 0318",
    "sg:postcode":"97006",
    "sg:province":"OR",
    "sg:tags":[
        "vacancy",
        "apartment",
        "rental",
        "finder",
        "listing"
    ],
    "wof:name":"Reedville Apts",
    "wof:placetype":"venue"
},
  "geometry": {"coordinates":[-122.89402800000001,45.498328],"type":"Point"}
}