{
  "type": "Feature",
  "properties": {
    "iso:country":"US",
    "sg:address":"11777 SW Boones Bend Dr",
    "sg:city":"Beaverton",
    "sg:classifiers":[
        {
            "category":"Structure",
            "subcategory":"Office Building",
            "type":"Public Place"
        }
    ],
    "sg:phone":"+1 503 524 6633",
    "sg:postcode":"97008",
    "sg:province":"OR",
    "sg:tags":[
        "park"
    ],
    "wof:name":"Prosperous Properties",
    "wof:placetype":"venue"
},
  "geometry": {"coordinates":[-122.796876,45.445857],"type":"Point"}
}