{
  "type": "Feature",
  "properties": {
    "iso:country":"US",
    "sg:address":"1609 N Bayshore Dr",
    "sg:city":"Coos Bay",
    "sg:classifiers":[
        {
            "category":"Insurance",
            "subcategory":"Insurance Agent",
            "type":"Services"
        }
    ],
    "sg:phone":"+1 541 267 4110",
    "sg:postcode":"97420",
    "sg:province":"OR",
    "sg:tags":[
        "life",
        "carrier"
    ],
    "wof:name":"Allstate",
    "wof:placetype":"venue"
},
  "geometry": {"coordinates":[-124.21923700000001,43.381059],"type":"Point"}
}