{
  "type": "Feature",
  "properties": {
    "iso:country":"US",
    "sg:address":"2860 SW 178th Ave",
    "sg:city":"Beaverton",
    "sg:classifiers":[
        {
            "category":"Retail",
            "subcategory":"Laundry & Dry Cleaning",
            "type":"Services"
        }
    ],
    "sg:phone":"+1 503 848 9066",
    "sg:postcode":"97006",
    "sg:province":"OR",
    "wof:name":"Flores Carpet Cleaning",
    "wof:placetype":"venue"
},
  "geometry": {"coordinates":[-122.86049199999999,45.49936],"type":"Point"}
}