{
  "type": "Feature",
  "properties": {
    "addr:full":"2755 SW 153rd Dr Beaverton OR 97006",
    "addr:housenumber":"2755",
    "addr:postcode":"97006",
    "addr:street":"Sw 153Rd Dr",
    "iso:country":"US",
    "sg:address":"2755 SW 153rd Dr",
    "sg:city":"Beaverton",
    "sg:classifiers":[
        {
            "category":"Manufacturing",
            "subcategory":"Printing",
            "type":"Manufacturing & Wholesale Goods"
        }
    ],
    "sg:phone":"+1 503 469 9141",
    "sg:postcode":"97006",
    "sg:province":"OR",
    "sg:tags":[
        "lithographic",
        "commercial"
    ],
    "wof:name":"IKON Office Solutions",
    "wof:placetype":"venue"
},
  "geometry": {"coordinates":[-122.83478700000001,45.499642],"type":"Point"}
}