{
  "type": "Feature",
  "properties": {
    "iso:country":"US",
    "sg:address":"2244 Riverbanks Rd",
    "sg:city":"Grants Pass",
    "sg:classifiers":[
        {
            "category":"Building & Trades",
            "subcategory":"Construction",
            "type":"Services"
        }
    ],
    "sg:phone":"+1 541 474 0441",
    "sg:postcode":"97527",
    "sg:province":"OR",
    "sg:tags":[
        "contractor"
    ],
    "wof:name":"Paul Bostic Design & Gen Contr",
    "wof:placetype":"venue"
},
  "geometry": {"coordinates":[-123.471218,42.422899],"type":"Point"}
}