{
  "type": "Feature",
  "properties": {
    "iso:country":"US",
    "sg:address":"916 SE Court Ave",
    "sg:city":"Pendleton",
    "sg:classifiers":[
        {
            "category":"Food & Beverages",
            "subcategory":"Groceries & Convenience Stores",
            "type":"Retail Goods"
        }
    ],
    "sg:phone":"+1 541 276 4634",
    "sg:postcode":"97801",
    "sg:province":"OR",
    "wof:name":"Moshers New & Used Furniture",
    "wof:placetype":"venue"
},
  "geometry": {"coordinates":[-118.778257,45.673959],"type":"Point"}
}