{
  "type": "Feature",
  "properties": {
    "addr:full":"5073 Peace Ln Central Point OR 97502",
    "addr:housenumber":"5073",
    "addr:postcode":"97502",
    "addr:street":"Peace Ln",
    "iso:country":"US",
    "sg:address":"5073 Peace Ln",
    "sg:city":"Central Point",
    "sg:classifiers":[
        {
            "category":"Building & Trades",
            "subcategory":"Construction",
            "type":"Services"
        }
    ],
    "sg:phone":"+1 541 772 8320",
    "sg:postcode":"97502",
    "sg:province":"OR",
    "sg:tags":[
        "contractor"
    ],
    "wof:name":"Buck Tiffee",
    "wof:placetype":"venue"
},
  "geometry": {"coordinates":[-122.87053400000001,42.389782],"type":"Point"}
}