{
  "type": "Feature",
  "properties": {
    "iso:country":"US",
    "sg:address":"6385 SW 155th Ave",
    "sg:city":"Beaverton",
    "sg:classifiers":[
        {
            "category":"Building & Trades",
            "subcategory":"Locksmith",
            "type":"Services"
        }
    ],
    "sg:phone":"+1 503 616 9215",
    "sg:postcode":"97007",
    "sg:province":"OR",
    "sg:tags":[
        "key"
    ],
    "wof:name":"Any Place 24 Locksmith",
    "wof:placetype":"venue"
},
  "geometry": {"coordinates":[-122.837586,45.47361],"type":"Point"}
}