{
  "type": "Feature",
  "properties": {
    "addr:full":"3995 Commercial St SE Salem OR 97302",
    "addr:housenumber":"3995",
    "addr:postcode":"97302",
    "addr:street":"Commercial St Se",
    "iso:country":"US",
    "sg:address":"3995 Commercial St SE",
    "sg:city":"Salem",
    "sg:classifiers":[
        {
            "category":"Personal",
            "subcategory":"Beauty Salon",
            "type":"Services"
        }
    ],
    "sg:phone":"+1 503 585 5500",
    "sg:postcode":"97302",
    "sg:province":"OR",
    "wof:name":"Gloria Hair Styling & Facials",
    "wof:placetype":"venue"
},
  "geometry": {"coordinates":[-123.039079,44.899984],"type":"Point"}
}