{
  "type": "Feature",
  "properties": {
    "iso:country":"US",
    "sg:address":"3446 NE Cadet Ave",
    "sg:city":"Portland",
    "sg:classifiers":[
        {
            "category":"Arts & Performance",
            "subcategory":"Theater",
            "type":"Entertainment"
        }
    ],
    "sg:phone":"+1 503 252 2726",
    "sg:postcode":"97220",
    "sg:province":"OR",
    "sg:tags":[
        "musician"
    ],
    "wof:name":"Frank Elliott Pianist",
    "wof:placetype":"venue"
},
  "geometry": {"coordinates":[-122.569174,45.545812],"type":"Point"}
}