{
  "type": "Feature",
  "properties": {
    "addr:full":"11927 NE Sumner St Portland OR 97220",
    "addr:housenumber":"11927",
    "addr:postcode":"97220",
    "addr:street":"Ne Sumner St",
    "iso:country":"US",
    "sg:address":"11927 NE Sumner St",
    "sg:city":"Portland",
    "sg:classifiers":[
        {
            "category":"Freight",
            "type":"Transportation"
        }
    ],
    "sg:phone":"+1 503 258 0801",
    "sg:postcode":"97220",
    "sg:province":"OR",
    "sg:tags":[
        "delivery"
    ],
    "wof:name":"FSA Network Inc",
    "wof:placetype":"venue"
},
  "geometry": {"coordinates":[-122.5427,45.561297],"type":"Point"}
}