{
  "type": "Feature",
  "properties": {
    "addr:full":"22300 NW Pihl Rd Banks OR 97106",
    "addr:housenumber":"22300",
    "addr:postcode":"97106",
    "addr:street":"Nw Pihl Rd",
    "iso:country":"US",
    "sg:address":"22300 NW Pihl Rd",
    "sg:city":"Banks",
    "sg:classifiers":[
        {
            "category":"Building & Trades",
            "subcategory":"Construction",
            "type":"Services"
        }
    ],
    "sg:phone":"+1 503 324 8324",
    "sg:postcode":"97106",
    "sg:province":"OR",
    "sg:tags":[
        "wallcoverings-installation",
        "wallpaper",
        "painting",
        "contractor"
    ],
    "wof:name":"Color Techniques Painting Contractors Inc",
    "wof:placetype":"venue"
},
  "geometry": {"coordinates":[-123.152929,45.682243],"type":"Point"}
}