{
  "type": "Feature",
  "properties": {
    "iso:country":"US",
    "sg:address":"8456 May Rd NE",
    "sg:city":"Mount Angel",
    "sg:classifiers":[
        {
            "category":"Farming",
            "subcategory":"Farm",
            "type":"Manufacturing & Wholesale Goods"
        }
    ],
    "sg:phone":"+1 503 845 6955",
    "sg:postcode":"97362",
    "sg:province":"OR",
    "sg:tags":[
        "crop",
        "general"
    ],
    "wof:name":"Butsch Brothers Farm LLC",
    "wof:placetype":"venue"
},
  "geometry": {"coordinates":[-122.76178,45.04709],"type":"Point"}
}