{
  "type": "Feature",
  "properties": {
    "addr:full":"438 NE 3rd St Mcminnville OR 97128",
    "addr:housenumber":"438",
    "addr:postcode":"97128",
    "addr:street":"Ne 3Rd St",
    "iso:country":"US",
    "sg:address":"438 NE 3rd St",
    "sg:city":"Mcminnville",
    "sg:classifiers":[
        {
            "category":"Shopping",
            "subcategory":"Bicycles & Sporting Goods",
            "type":"Retail Goods"
        }
    ],
    "sg:phone":"+1 503 472 4453",
    "sg:postcode":"97128",
    "sg:province":"OR",
    "sg:tags":[
        "apparel",
        "sport"
    ],
    "wof:name":"Mac Sports",
    "wof:placetype":"venue"
},
  "geometry": {"coordinates":[-123.195249,45.209944],"type":"Point"}
}