{
  "type": "Feature",
  "properties": {
    "iso:country":"US",
    "sg:address":"1708 SW Royal Ave",
    "sg:city":"Gresham",
    "sg:classifiers":[
        {
            "category":"Social Services",
            "type":"Services"
        }
    ],
    "sg:phone":"+1 503 661 5050",
    "sg:postcode":"97080",
    "sg:province":"OR",
    "wof:name":"Western Youth Ranch",
    "wof:placetype":"venue"
},
  "geometry": {"coordinates":[-122.470704,45.483061],"type":"Point"}
}