{
  "type": "Feature",
  "properties": {
    "addr:full":"311 W 13th Ave Eugene OR 97401",
    "addr:housenumber":"311",
    "addr:postcode":"97401",
    "addr:street":"W 13Th Ave",
    "iso:country":"US",
    "sg:address":"311 W 13th Ave",
    "sg:city":"Eugene",
    "sg:classifiers":[
        {
            "category":"Professional",
            "subcategory":"Accounting & Tax Preparation",
            "type":"Services"
        }
    ],
    "sg:phone":"+1 541 302 9445",
    "sg:postcode":"97401",
    "sg:province":"OR",
    "sg:tags":[
        "return",
        "filing"
    ],
    "sg:website":"www.castax.com",
    "wof:name":"Cascade Tax Professionals",
    "wof:placetype":"venue"
},
  "geometry": {"coordinates":[-123.098446,44.045517],"type":"Point"}
}