{
  "type": "Feature",
  "properties": {
    "iso:country":"US",
    "sg:address":"694 Glendale Ave",
    "sg:city":"Ashland",
    "sg:classifiers":[
        {
            "category":"Shopping",
            "subcategory":"Books",
            "type":"Retail Goods"
        }
    ],
    "sg:phone":"+1 541 488 6443",
    "sg:postcode":"97520",
    "sg:province":"OR",
    "wof:name":"Rogue Books",
    "wof:placetype":"venue"
},
  "geometry": {"coordinates":[-122.678382,42.182795],"type":"Point"}
}