{
  "type": "Feature",
  "properties": {
    "iso:country":"US",
    "sg:address":"12229 SE Stark St",
    "sg:city":"Portland",
    "sg:classifiers":[
        {
            "category":"Shopping",
            "subcategory":"Books",
            "type":"Retail Goods"
        }
    ],
    "sg:phone":"+1 503 251 1520",
    "sg:postcode":"97233",
    "sg:province":"OR",
    "sg:tags":[
        "dealer"
    ],
    "wof:name":"LA Roca Christian Books",
    "wof:placetype":"venue"
},
  "geometry": {"coordinates":[-122.53484,45.519116],"type":"Point"}
}