{
  "type": "Feature",
  "properties": {
    "iso:country":"US",
    "sg:address":"13620 SW Beef Bend Rd",
    "sg:city":"Tigard",
    "sg:classifiers":[
        {
            "category":"Retail",
            "subcategory":"Portrait Studio",
            "type":"Services"
        }
    ],
    "sg:phone":"+1 503 590 7733",
    "sg:postcode":"97224",
    "sg:province":"OR",
    "sg:tags":[
        "photographer"
    ],
    "wof:name":"Reflective Images",
    "wof:placetype":"venue"
},
  "geometry": {"coordinates":[-122.816824,45.40333],"type":"Point"}
}