{
  "type": "Feature",
  "properties": {
    "addr:full":"50 Fraser Rd W Tillamook OR 97141",
    "addr:housenumber":"50",
    "addr:postcode":"97141",
    "addr:street":"Fraser Rd W",
    "iso:country":"US",
    "sg:address":"50 Fraser Rd W",
    "sg:city":"Tillamook",
    "sg:classifiers":[
        {
            "category":"Manufacturing",
            "subcategory":"Lumber",
            "type":"Manufacturing & Wholesale Goods"
        }
    ],
    "sg:phone":"+1 503 842 1124",
    "sg:postcode":"97141",
    "sg:province":"OR",
    "sg:tags":[
        "logging"
    ],
    "wof:name":"Ken Oleman",
    "wof:placetype":"venue"
},
  "geometry": {"coordinates":[-123.877392,45.440874],"type":"Point"}
}