{
  "type": "Feature",
  "properties": {
    "addr:full":"327 E Main St Hillsboro OR 97123",
    "addr:housenumber":"327",
    "addr:postcode":"97123",
    "addr:street":"E Main St",
    "iso:country":"US",
    "sg:address":"327 E Main St",
    "sg:city":"Hillsboro",
    "sg:classifiers":[
        {
            "category":"Banks & Credit Unions",
            "subcategory":"Investment Brokerage",
            "type":"Services"
        }
    ],
    "sg:phone":"+1 503 693 7333",
    "sg:postcode":"97123",
    "sg:province":"OR",
    "sg:tags":[
        "security"
    ],
    "wof:name":"SunAmerica",
    "wof:placetype":"venue"
},
  "geometry": {"coordinates":[-122.98478900000001,45.522674],"type":"Point"}
}