{
  "type": "Feature",
  "properties": {
    "addr:full":"4074 NW Saltzman Rd Portland OR 97229",
    "addr:housenumber":"4074",
    "addr:postcode":"97229",
    "addr:street":"Nw Saltzman Rd",
    "iso:country":"US",
    "sg:address":"4074 NW Saltzman Rd",
    "sg:city":"Portland",
    "sg:classifiers":[
        {
            "category":"Personal",
            "subcategory":"Beauty Salon",
            "type":"Services"
        },
        {
            "category":"Personal",
            "subcategory":"Barber",
            "type":"Services"
        },
        {
            "category":"Personal",
            "subcategory":"Day Spa",
            "type":"Services"
        },
        {
            "category":"Personal",
            "subcategory":"Nail Salon",
            "type":"Services"
        }
    ],
    "sg:phone":"+1 503 617 0399",
    "sg:postcode":"97229",
    "sg:province":"OR",
    "wof:name":"Enchante Salon Et Day Spa",
    "wof:placetype":"venue"
},
  "geometry": {"coordinates":[-122.810619,45.548094],"type":"Point"}
}