{
  "type": "Feature",
  "properties": {
    "addr:full":"39261 Proctor Blvd Sandy OR 97055",
    "addr:housenumber":"39261",
    "addr:postcode":"97055",
    "addr:street":"Proctor Blvd",
    "iso:country":"US",
    "sg:address":"39261 Proctor Blvd",
    "sg:city":"Sandy",
    "sg:classifiers":[
        {
            "category":"Shopping",
            "type":"Retail Goods"
        }
    ],
    "sg:phone":"+1 503 668 9823",
    "sg:postcode":"97055",
    "sg:province":"OR",
    "sg:tags":[
        "picture",
        "frame"
    ],
    "wof:name":"Overland Gallery",
    "wof:placetype":"venue"
},
  "geometry": {"coordinates":[-122.25931300000001,45.397363],"type":"Point"}
}