{
  "type": "Feature",
  "properties": {
    "addr:full":"Lloyd Center Portland OR 97201",
    "addr:postcode":"97201",
    "iso:country":"US",
    "sg:address":"Lloyd Center",
    "sg:city":"Portland",
    "sg:classifiers":[
        {
            "category":"Health Services",
            "subcategory":"Chiropractor",
            "type":"Services"
        }
    ],
    "sg:phone":"+1 503 280 9759",
    "sg:postcode":"97201",
    "sg:province":"OR",
    "wof:name":"Blue Heron Chiropractic & Healing Arts Center",
    "wof:placetype":"venue"
},
  "geometry": {"coordinates":[-122.689333,45.511105],"type":"Point"}
}