{
  "type": "Feature",
  "properties": {
    "addr:full":"707 High St Klamath Falls OR 97601",
    "addr:housenumber":"707",
    "addr:postcode":"97601",
    "addr:street":"High St",
    "iso:country":"US",
    "sg:address":"707 High St",
    "sg:city":"Klamath Falls",
    "sg:classifiers":[
        {
            "category":"Organizations",
            "subcategory":"Religious Organization",
            "type":"Services"
        }
    ],
    "sg:phone":"+1 541 884 6272",
    "sg:postcode":"97601",
    "sg:province":"OR",
    "sg:tags":[
        "baptist",
        "church"
    ],
    "wof:name":"First Baptist Church Inc",
    "wof:placetype":"venue"
},
  "geometry": {"coordinates":[-121.782903,42.227159],"type":"Point"}
}