{
  "type": "Feature",
  "properties": {
    "iso:country":"US",
    "sg:address":"4931 Jones Rd SE",
    "sg:city":"Salem",
    "sg:classifiers":[
        {
            "category":"Building & Trades",
            "subcategory":"Construction",
            "type":"Services"
        }
    ],
    "sg:phone":"+1 503 399 7030",
    "sg:postcode":"97302",
    "sg:province":"OR",
    "sg:tags":[
        "house"
    ],
    "wof:name":"Pacific Cascade Enterpris",
    "wof:placetype":"venue"
},
  "geometry": {"coordinates":[-123.047687,44.884142],"type":"Point"}
}