{
  "type": "Feature",
  "properties": {
    "iso:country":"US",
    "sg:address":"32431 NW Ej Smith Rd",
    "sg:city":"Scappoose",
    "sg:classifiers":[
        {
            "category":"Professional",
            "subcategory":"Business Services",
            "type":"Services"
        }
    ],
    "sg:phone":"+1 503 543 6768",
    "sg:postcode":"97056",
    "sg:province":"OR",
    "wof:name":"Graham Pump Sales & Service",
    "wof:placetype":"venue"
},
  "geometry": {"coordinates":[-122.89869400000001,45.770964],"type":"Point"}
}