{
  "type": "Feature",
  "properties": {
    "iso:country":"US",
    "sg:address":"1601 Williams Hwy",
    "sg:city":"Grants Pass",
    "sg:classifiers":[
        {
            "category":"Autos & Motor Vehicles",
            "subcategory":"Auto Supplies",
            "type":"Retail Goods"
        }
    ],
    "sg:phone":"+1 541 472 9700",
    "sg:postcode":"97527",
    "sg:province":"OR",
    "wof:name":"Autozone",
    "wof:placetype":"venue"
},
  "geometry": {"coordinates":[-123.335685,42.41986],"type":"Point"}
}