{
  "type": "Feature",
  "properties": {
    "iso:country":"US",
    "sg:address":"2614 SE 115th Ave Apt Ap",
    "sg:city":"Portland",
    "sg:classifiers":[
        {
            "category":"Place Of Worship",
            "subcategory":"Church",
            "type":"Public Place"
        },
        {
            "category":"Place Of Worship",
            "type":"Public Place"
        }
    ],
    "sg:phone":"+1 503 761 5169",
    "sg:postcode":"97266",
    "sg:province":"OR",
    "sg:tags":[
        "lutheran",
        "america",
        "churches-lutheran",
        "churches-lutheran-evangelical"
    ],
    "wof:name":"Good Shepherd Lutheran Ho",
    "wof:placetype":"venue"
},
  "geometry": {"coordinates":[-122.545435,45.502953],"type":"Point"}
}