{
  "type": "Feature",
  "properties": {
    "addr:full":"5331 SW MacAdam Ave Ste 283 Portland OR 97239",
    "addr:housenumber":"5331",
    "addr:postcode":"97239",
    "addr:street":"Sw Macadam Ave Ste 283",
    "iso:country":"US",
    "sg:address":"5331 SW MacAdam Ave Ste 283",
    "sg:city":"Portland",
    "sg:classifiers":[
        {
            "category":"Building & Trades",
            "subcategory":"Locksmith",
            "type":"Services"
        }
    ],
    "sg:phone":"+1 503 594 7688",
    "sg:postcode":"97239",
    "sg:province":"OR",
    "sg:tags":[
        "key"
    ],
    "wof:name":"Locksmith",
    "wof:placetype":"venue"
},
  "geometry": {"coordinates":[-122.67503000000001,45.484633],"type":"Point"}
}