{
  "type": "Feature",
  "properties": {
    "iso:country":"US",
    "sg:address":"23618 Hall Rd",
    "sg:city":"Cheshire",
    "sg:classifiers":[
        {
            "category":"Farming",
            "subcategory":"Farm",
            "type":"Manufacturing & Wholesale Goods"
        }
    ],
    "sg:phone":"+1 541 998 3933",
    "sg:postcode":"97419",
    "sg:province":"OR",
    "wof:name":"Burp Hollow Farm",
    "wof:placetype":"venue"
},
  "geometry": {"coordinates":[-123.412938,44.163349],"type":"Point"}
}