{
  "type": "Feature",
  "properties": {
    "addr:full":"201 Fern Valley Rd Phoenix OR 97535",
    "addr:housenumber":"201",
    "addr:postcode":"97535",
    "addr:street":"Fern Valley Rd",
    "iso:country":"US",
    "sg:address":"201 Fern Valley Rd",
    "sg:city":"Phoenix",
    "sg:classifiers":[
        {
            "category":"Travel",
            "subcategory":"Campground",
            "type":"Entertainment"
        }
    ],
    "sg:phone":"+1 541 535 2183",
    "sg:postcode":"97535",
    "sg:province":"OR",
    "wof:name":"Holiday Rv Park",
    "wof:placetype":"venue"
},
  "geometry": {"coordinates":[-122.81925699999999,42.280367],"type":"Point"}
}