{
  "type": "Feature",
  "properties": {
    "addr:full":"25081 Schaupp Rd Klamath Falls OR 97603",
    "addr:postcode":"25081;97603",
    "addr:street":"Schaupp Rd",
    "iso:country":"US",
    "sg:address":"25081 Schaupp Rd",
    "sg:city":"Klamath Falls",
    "sg:phone":"+1 541 723 4592",
    "sg:postcode":"97603",
    "sg:province":"OR",
    "sg:tags":[
        "farm",
        "wheat"
    ],
    "wof:name":"Rajnus Grain & Seed",
    "wof:placetype":"venue"
},
  "geometry": {"coordinates":[-121.488241,42.103769],"type":"Point"}
}