{
  "type": "Feature",
  "properties": {
    "addr:full":"30746 S Oswalt Rd Colton OR 97017",
    "addr:housenumber":"30746",
    "addr:postcode":"97017",
    "addr:street":"S Oswalt Rd",
    "iso:country":"US",
    "sg:address":"30746 S Oswalt Rd",
    "sg:city":"Colton",
    "sg:classifiers":[
        {
            "category":"Professional",
            "subcategory":"Engineering",
            "type":"Services"
        },
        {
            "category":"Building & Trades",
            "subcategory":"Construction",
            "type":"Services"
        }
    ],
    "sg:phone":"+1 503 824 4500",
    "sg:postcode":"97017",
    "sg:province":"OR",
    "sg:tags":[
        "system",
        "specialty",
        "heating",
        "equipment",
        "contractor",
        "air conditioning"
    ],
    "wof:name":"Jw Geothermal",
    "wof:placetype":"venue"
},
  "geometry": {"coordinates":[-122.45545300000001,45.15783],"type":"Point"}
}