{
  "type": "Feature",
  "properties": {
    "iso:country":"US",
    "sg:address":"10585 SW 161st Ct",
    "sg:city":"Beaverton",
    "sg:classifiers":[
        {
            "category":"Real Estate",
            "subcategory":"Real Estate Agent",
            "type":"Services"
        }
    ],
    "sg:phone":"+1 503 579 3619",
    "sg:postcode":"97007",
    "sg:province":"OR",
    "wof:name":"Davis Enterprises",
    "wof:placetype":"venue"
},
  "geometry": {"coordinates":[-122.84209,45.444162],"type":"Point"}
}