{
  "type": "Feature",
  "properties": {
    "addr:full":"7175 Valley View Dr Gladstone OR 97027",
    "addr:housenumber":"7175",
    "addr:postcode":"97027",
    "addr:street":"Valley View Dr",
    "iso:country":"US",
    "sg:address":"7175 Valley View Dr",
    "sg:city":"Gladstone",
    "sg:classifiers":[
        {
            "category":"Professional",
            "subcategory":"Business Services",
            "type":"Services"
        }
    ],
    "sg:phone":"+1 503 657 0232",
    "sg:postcode":"97027",
    "sg:province":"OR",
    "wof:name":"Millers Builder Services",
    "wof:placetype":"venue"
},
  "geometry": {"coordinates":[-122.589895,45.398009],"type":"Point"}
}