{
  "type": "Feature",
  "properties": {
    "addr:full":"1214 Kincaid St Eugene OR 97401",
    "addr:housenumber":"1214",
    "addr:postcode":"97401",
    "addr:street":"Kincaid St",
    "iso:country":"US",
    "sg:address":"1214 Kincaid St",
    "sg:city":"Eugene",
    "sg:classifiers":[
        {
            "category":"Restaurant",
            "type":"Food & Drink"
        }
    ],
    "sg:menulink":"http://www.allmenus.com/or/eugene-springfield/48862-rennies-landing/menu/",
    "sg:phone":"+1 541 687 0600",
    "sg:postcode":"97401",
    "sg:province":"OR",
    "sg:tags":[
        "food",
        "american",
        "pub"
    ],
    "wof:name":"Rennie's Landing",
    "wof:placetype":"venue"
},
  "geometry": {"coordinates":[-123.07867400000001,44.046435],"type":"Point"}
}