{
  "type": "Feature",
  "properties": {
    "addr:full":"1314 E Sherman St Newberg OR 97132",
    "addr:housenumber":"1314",
    "addr:postcode":"97132",
    "addr:street":"E Sherman St",
    "iso:country":"US",
    "sg:address":"1314 E Sherman St",
    "sg:city":"Newberg",
    "sg:classifiers":[
        {
            "category":"Health Services",
            "subcategory":"Doctor",
            "type":"Services"
        }
    ],
    "sg:phone":"+1 503 538 2698",
    "sg:postcode":"97132",
    "sg:province":"OR",
    "sg:tags":[
        "physician",
        "surgeon"
    ],
    "wof:name":"Ben Johnson MD",
    "wof:placetype":"venue"
},
  "geometry": {"coordinates":[-122.964472,45.302895],"type":"Point"}
}