{
  "type": "Feature",
  "properties": {
    "iso:country":"US",
    "sg:address":"2121 NW York Street",
    "sg:city":"Portland",
    "sg:classifiers":[
        {
            "category":"Real Estate",
            "subcategory":"Architect",
            "type":"Services"
        }
    ],
    "sg:phone":"+1 503 227 2121",
    "sg:postcode":"97210",
    "sg:province":"OR",
    "wof:name":"Architectural Signing Northwest",
    "wof:placetype":"venue"
},
  "geometry": {"coordinates":[-122.69523100000001,45.53902],"type":"Point"}
}