{
  "type": "Feature",
  "properties": {
    "addr:full":"348 SW Bay Blvd Newport OR 97365",
    "addr:housenumber":"348",
    "addr:postcode":"97365",
    "addr:street":"Sw Bay Blvd",
    "iso:country":"US",
    "sg:address":"348 SW Bay Blvd",
    "sg:city":"Newport",
    "sg:classifiers":[
        {
            "category":"Restaurant",
            "type":"Food & Drink"
        }
    ],
    "sg:phone":"+1 541 265 5569",
    "sg:postcode":"97365",
    "sg:province":"OR",
    "sg:tags":[
        "eating"
    ],
    "wof:name":"Trolly Car The",
    "wof:placetype":"venue"
},
  "geometry": {"coordinates":[-124.05186500000001,44.630812],"type":"Point"}
}