{
  "type": "Feature",
  "properties": {
    "addr:full":"1163 Knutson Ave Medford OR 97504",
    "addr:housenumber":"1163",
    "addr:postcode":"97504",
    "addr:street":"Knutson Ave",
    "iso:country":"US",
    "sg:address":"1163 Knutson Ave",
    "sg:city":"Medford",
    "sg:classifiers":[
        {
            "category":"Freight",
            "type":"Transportation"
        }
    ],
    "sg:phone":"+1 541 770 6824",
    "sg:postcode":"97504",
    "sg:province":"OR",
    "sg:tags":[
        "trucking"
    ],
    "wof:name":"Priority Freight Lines",
    "wof:placetype":"venue"
},
  "geometry": {"coordinates":[-122.87455,42.357849],"type":"Point"}
}