{
  "type": "Feature",
  "properties": {
    "addr:full":"446 Lancaster Dr NE Salem OR 97301",
    "addr:housenumber":"446",
    "addr:postcode":"97301",
    "addr:street":"Lancaster Dr Ne",
    "iso:country":"US",
    "sg:address":"446 Lancaster Dr NE",
    "sg:city":"Salem",
    "sg:classifiers":[
        {
            "category":"Professional",
            "subcategory":"Accounting & Tax Preparation",
            "type":"Services"
        }
    ],
    "sg:phone":"+1 503 391 8005",
    "sg:postcode":"97301",
    "sg:province":"OR",
    "sg:tags":[
        "return",
        "filing"
    ],
    "wof:name":"Jackson Hewitt Tax Svc",
    "wof:placetype":"venue"
},
  "geometry": {"coordinates":[-122.98307800000001,44.934002],"type":"Point"}
}