{
  "type": "Feature",
  "properties": {
    "addr:full":"1755 N Highland St Portland OR 97217",
    "addr:housenumber":"1755",
    "addr:postcode":"97217",
    "addr:street":"N Highland St",
    "iso:country":"US",
    "sg:address":"1755 N Highland St",
    "sg:city":"Portland",
    "sg:classifiers":[
        {
            "category":"Professional",
            "type":"Services"
        }
    ],
    "sg:phone":"+1 503 236 8686",
    "sg:postcode":"97217",
    "sg:province":"OR",
    "wof:name":"Biostudios",
    "wof:placetype":"venue"
},
  "geometry": {"coordinates":[-122.685941,45.569217],"type":"Point"}
}