{
  "type": "Feature",
  "properties": {
    "iso:country":"US",
    "sg:address":"200 N Monroe St",
    "sg:city":"Eugene",
    "sg:classifiers":[
        {
            "category":"Education",
            "subcategory":"School",
            "type":"Public Place"
        }
    ],
    "sg:phone":"+1 541 687 3291",
    "sg:postcode":"97402",
    "sg:province":"OR",
    "wof:name":"Instructional Material Ctr",
    "wof:placetype":"venue"
},
  "geometry": {"coordinates":[-123.104884,44.060876],"type":"Point"}
}