{
  "type": "Feature",
  "properties": {
    "addr:full":"1036 NE A St Grants Pass OR 97526",
    "addr:housenumber":"1036",
    "addr:postcode":"97526",
    "addr:street":"Ne A St",
    "iso:country":"US",
    "sg:address":"1036 NE A St",
    "sg:city":"Grants Pass",
    "sg:classifiers":[
        {
            "category":"Organizations",
            "subcategory":"Religious Organization",
            "type":"Services"
        }
    ],
    "sg:phone":"+1 541 476 4547",
    "sg:postcode":"97526",
    "sg:province":"OR",
    "sg:tags":[
        "church"
    ],
    "wof:name":"Dayspring Baptist Church",
    "wof:placetype":"venue"
},
  "geometry": {"coordinates":[-123.310378,42.442667],"type":"Point"}
}