{
  "type": "Feature",
  "properties": {
    "iso:country":"US",
    "sg:address":"2225 NE 131st Ave",
    "sg:city":"Portland",
    "sg:classifiers":[
        {
            "category":"Wholesale",
            "subcategory":"Durable Goods & Equipment",
            "type":"Manufacturing & Wholesale Goods"
        }
    ],
    "sg:phone":"+1 503 252 6592",
    "sg:postcode":"97230",
    "sg:province":"OR",
    "sg:tags":[
        "representative",
        "manufacturer"
    ],
    "wof:name":"Maxi Marketing",
    "wof:placetype":"venue"
},
  "geometry": {"coordinates":[-122.528225,45.539937],"type":"Point"}
}