{
  "type": "Feature",
  "properties": {
    "iso:country":"US",
    "sg:address":"4505 SW Hall Blvd",
    "sg:city":"Beaverton",
    "sg:classifiers":[
        {
            "category":"Banks & Credit Unions",
            "subcategory":"Bank",
            "type":"Services"
        }
    ],
    "sg:phone":"+1 503 643 0704",
    "sg:postcode":"97005",
    "sg:province":"OR",
    "wof:name":"Travelex Currency Svc",
    "wof:placetype":"venue"
},
  "geometry": {"coordinates":[-122.804043,45.487187],"type":"Point"}
}