{
  "type": "Feature",
  "properties": {
    "addr:full":"13220 Ramsey Rd Gold Hill OR 97525",
    "addr:housenumber":"13220",
    "addr:postcode":"97525",
    "addr:street":"Ramsey Rd",
    "iso:country":"US",
    "sg:address":"13220 Ramsey Rd",
    "sg:city":"Gold Hill",
    "sg:classifiers":[
        {
            "category":"Retail",
            "subcategory":"Repair Shop",
            "type":"Services"
        }
    ],
    "sg:phone":"+1 541 826 1537",
    "sg:postcode":"97525",
    "sg:province":"OR",
    "wof:name":"Canyon Fabrication & Repair",
    "wof:placetype":"venue"
},
  "geometry": {"coordinates":[-122.98802499999999,42.554686],"type":"Point"}
}