{
  "type": "Feature",
  "properties": {
    "addr:full":"2122 NE Lake Dr Lincoln City OR 97367",
    "addr:housenumber":"2122",
    "addr:postcode":"97367",
    "addr:street":"Ne Lake Dr",
    "iso:country":"US",
    "sg:address":"2122 NE Lake Dr",
    "sg:city":"Lincoln City",
    "sg:classifiers":[
        {
            "category":"Professional",
            "subcategory":"Management & Consulting",
            "type":"Services"
        }
    ],
    "sg:phone":"+1 541 994 4800",
    "sg:postcode":"97367",
    "sg:province":"OR",
    "sg:tags":[
        "consultant"
    ],
    "wof:name":"Marie Dickerson Consultant",
    "wof:placetype":"venue"
},
  "geometry": {"coordinates":[-123.99583199999999,44.981171],"type":"Point"}
}