{
  "type": "Feature",
  "properties": {
    "iso:country":"US",
    "sg:address":"576 N Tomahawk Island Dr",
    "sg:city":"Portland",
    "sg:classifiers":[
        {
            "category":"Manufacturing",
            "subcategory":"Tools & Machinery",
            "type":"Manufacturing & Wholesale Goods"
        }
    ],
    "sg:phone":"+1 503 283 1245",
    "sg:postcode":"97217",
    "sg:province":"OR",
    "sg:tags":[
        "machine",
        "mfg",
        "accessory"
    ],
    "wof:name":"Top Snapper Snap Tool Co",
    "wof:placetype":"venue"
},
  "geometry": {"coordinates":[-122.671712,45.606729],"type":"Point"}
}