{
  "type": "Feature",
  "properties": {
    "iso:country":"US",
    "sg:address":"3305 19th Ave",
    "sg:city":"Forest Grove",
    "sg:classifiers":[
        {
            "category":"Health Services",
            "subcategory":"Doctor",
            "type":"Services"
        }
    ],
    "sg:phone":"+1 503 357 7194",
    "sg:postcode":"97116",
    "sg:province":"OR",
    "sg:tags":[
        "medical"
    ],
    "wof:name":"Marilyn J Booth MD",
    "wof:placetype":"venue"
},
  "geometry": {"coordinates":[-123.089234,45.518359],"type":"Point"}
}