{
  "type": "Feature",
  "properties": {
    "iso:country":"US",
    "sg:address":"2723 NW 9th St",
    "sg:city":"Corvallis",
    "sg:classifiers":[
        {
            "category":"Organizations",
            "subcategory":"Non-profit Organization",
            "type":"Services"
        }
    ],
    "sg:phone":"+1 541 753 5520",
    "sg:postcode":"97330",
    "sg:province":"OR",
    "sg:tags":[
        "disability"
    ],
    "wof:name":"Work Unlimited Accounting",
    "wof:placetype":"venue"
},
  "geometry": {"coordinates":[-123.25126,44.595236],"type":"Point"}
}