{
  "type": "Feature",
  "properties": {
    "iso:country":"US",
    "sg:address":"101 N Molalla Ave",
    "sg:city":"Molalla",
    "sg:classifiers":[
        {
            "category":"Professional",
            "subcategory":"Management & Consulting",
            "type":"Services"
        }
    ],
    "sg:phone":"+1 503 829 5003",
    "sg:postcode":"97038",
    "sg:province":"OR",
    "sg:tags":[
        "development",
        "economic",
        "agency"
    ],
    "wof:name":"Teamolalla",
    "wof:placetype":"venue"
},
  "geometry": {"coordinates":[-122.57702,45.147966],"type":"Point"}
}