{
  "type": "Feature",
  "properties": {
    "iso:country":"US",
    "sg:address":"10477 SW Beaverton Hillsdale Hwy Ste H",
    "sg:city":"Beaverton",
    "sg:classifiers":[
        {
            "category":"Professional",
            "subcategory":"Accounting & Tax Preparation",
            "type":"Services"
        },
        {
            "category":"Wholesale",
            "subcategory":"Office Equipment",
            "type":"Manufacturing & Wholesale Goods"
        },
        {
            "category":"Banks & Credit Unions",
            "subcategory":"Financial Services",
            "type":"Services"
        }
    ],
    "sg:phone":"+1 877 546 9703",
    "sg:postcode":"97005",
    "sg:province":"OR",
    "sg:tags":[
        "return",
        "preparation-business",
        "taxes-consultants",
        "loan",
        "supply",
        "machine",
        "representative",
        "alternative",
        "bookkeeping"
    ],
    "sg:website":"http://portland.citysearch.com/profile/external/8415528/beaverton_or/h_r_block.html?publisher=yellowpages&reference_id=1&placement=ypwebsitemip",
    "wof:name":"H&R BLOCK",
    "wof:placetype":"venue"
},
  "geometry": {"coordinates":[-122.78478,45.486526],"type":"Point"}
}