{
  "type": "Feature",
  "properties": {
    "iso:country":"US",
    "sg:address":"1728 NE 40th Ave",
    "sg:city":"Portland",
    "sg:classifiers":[
        {
            "category":"Bars & Pubs",
            "type":"Food & Drink"
        },
        {
            "category":"Bars & Pubs",
            "subcategory":"Lounge",
            "type":"Food & Drink"
        },
        {
            "category":"Brewery",
            "type":"Food & Drink"
        }
    ],
    "sg:phone":"+1 503 943 6157",
    "sg:postcode":"97212",
    "sg:province":"OR",
    "sg:tags":[
        "cocktail"
    ],
    "sg:website":"www.columbiariverbrewpub.com/",
    "wof:name":"Columbia River Brewing",
    "wof:placetype":"venue"
},
  "geometry": {"coordinates":[-122.621791,45.53574],"type":"Point"}
}