{
  "type": "Feature",
  "properties": {
    "addr:full":"970 SE Oak St Hillsboro OR 97123",
    "addr:housenumber":"970",
    "addr:postcode":"97123",
    "addr:street":"Se Oak St",
    "iso:country":"US",
    "sg:address":"970 SE Oak St",
    "sg:city":"Hillsboro",
    "sg:classifiers":[
        {
            "category":"Restaurant",
            "type":"Food & Drink"
        }
    ],
    "sg:phone":"+1 503 681 0707",
    "sg:postcode":"97123",
    "sg:province":"OR",
    "wof:name":"Mayas Restaurants",
    "wof:placetype":"venue"
},
  "geometry": {"coordinates":[-122.97418399999999,45.518631],"type":"Point"}
}