{
  "type": "Feature",
  "properties": {
    "iso:country":"US",
    "sg:address":"102 N Main St",
    "sg:city":"Phoenix",
    "sg:classifiers":[
        {
            "category":"Restaurant",
            "type":"Food & Drink"
        }
    ],
    "sg:phone":"+1 541 535 8446",
    "sg:postcode":"97535",
    "sg:province":"OR",
    "wof:name":"Soco's LA Burrita Restaurant",
    "wof:placetype":"venue"
},
  "geometry": {"coordinates":[-122.81679200000001,42.275359],"type":"Point"}
}