{
  "type": "Feature",
  "properties": {
    "addr:full":"8221 N Denver Ave Portland OR 97217",
    "addr:housenumber":"8221",
    "addr:postcode":"97217",
    "addr:street":"N Denver Ave",
    "iso:country":"US",
    "sg:address":"8221 N Denver Ave",
    "sg:city":"Portland",
    "sg:classifiers":[
        {
            "category":"Shopping",
            "subcategory":"Discount & Variety Stores",
            "type":"Retail Goods"
        }
    ],
    "sg:phone":"+1 503 285 0832",
    "sg:postcode":"97217",
    "sg:province":"OR",
    "sg:tags":[
        "merchandise",
        "general"
    ],
    "wof:name":"Cascade Surplus Electronics",
    "wof:placetype":"venue"
},
  "geometry": {"coordinates":[-122.68696300000001,45.58296],"type":"Point"}
}