{
  "type": "Feature",
  "properties": {
    "iso:country":"US",
    "sg:address":"14780 S Jordan Rd",
    "sg:city":"Mulino",
    "sg:classifiers":[
        {
            "category":"Retail",
            "subcategory":"Auto Repair",
            "type":"Services"
        }
    ],
    "sg:phone":"+1 503 829 5277",
    "sg:postcode":"97042",
    "sg:province":"OR",
    "sg:tags":[
        "body"
    ],
    "wof:name":"Flashback Auto Restoration",
    "wof:placetype":"venue"
},
  "geometry": {"coordinates":[-122.561633,45.19424],"type":"Point"}
}