{
  "type": "Feature",
  "properties": {
    "iso:country":"US",
    "sg:address":"16215 W Hoffeldt Ln",
    "sg:city":"Brookings",
    "sg:classifiers":[
        {
            "category":"Shopping",
            "subcategory":"Crafts & Fabrics",
            "type":"Retail Goods"
        }
    ],
    "sg:phone":"+1 541 469 4684",
    "sg:postcode":"97415",
    "sg:province":"OR",
    "sg:tags":[
        "sewing",
        "hob"
    ],
    "wof:name":"Calico Corner",
    "wof:placetype":"venue"
},
  "geometry": {"coordinates":[-124.258788,42.048356],"type":"Point"}
}