{
  "type": "Feature",
  "properties": {
    "iso:country":"US",
    "sg:address":"1074 S 11th St",
    "sg:city":"Harrisburg",
    "sg:classifiers":[
        {
            "category":"Building & Trades",
            "subcategory":"Construction",
            "type":"Services"
        }
    ],
    "sg:phone":"+1 541 995 1011",
    "sg:postcode":"97420",
    "sg:province":"OR",
    "sg:tags":[
        "builder",
        "operative",
        "real estate"
    ],
    "wof:name":"Wood Homes Inc",
    "wof:placetype":"venue"
},
  "geometry": {"coordinates":[-124.2232,43.358592],"type":"Point"}
}