{
  "type": "Feature",
  "properties": {
    "addr:full":"6511 SW Santa Monica Ct Portland OR 97225",
    "addr:housenumber":"6511",
    "addr:postcode":"97225",
    "addr:street":"Sw Santa Monica Ct",
    "iso:country":"US",
    "sg:address":"6511 SW Santa Monica Ct",
    "sg:city":"Portland",
    "sg:classifiers":[
        {
            "category":"Manufacturing",
            "subcategory":"Printing",
            "type":"Manufacturing & Wholesale Goods"
        }
    ],
    "sg:phone":"+1 503 246 1122",
    "sg:postcode":"97225",
    "sg:province":"OR",
    "sg:tags":[
        "publishing"
    ],
    "wof:name":"Publications Plus",
    "wof:placetype":"venue"
},
  "geometry": {"coordinates":[-122.74262400000001,45.491444],"type":"Point"}
}