{
  "type": "Feature",
  "properties": {
    "addr:full":"1001 NW 14th Ave Portland OR 97209",
    "addr:housenumber":"1001",
    "addr:postcode":"97209",
    "addr:street":"Nw 14Th Ave",
    "iso:country":"US",
    "sg:address":"1001 NW 14th Ave",
    "sg:city":"Portland",
    "sg:classifiers":[
        {
            "category":"Real Estate",
            "subcategory":"Real Estate Agent",
            "type":"Services"
        }
    ],
    "sg:phone":"+1 503 248 2255",
    "sg:postcode":"97209",
    "sg:province":"OR",
    "wof:name":"Ball Parc Properties LLC",
    "wof:placetype":"venue"
},
  "geometry": {"coordinates":[-122.68543099999999,45.530744],"type":"Point"}
}