{
  "type": "Feature",
  "properties": {
    "iso:country":"US",
    "sg:address":"1931 NE Sandy Blvd",
    "sg:city":"Portland",
    "sg:classifiers":[
        {
            "category":"Cinema",
            "subcategory":"Movie Rental",
            "type":"Entertainment"
        },
        {
            "category":"Shopping",
            "subcategory":"Music",
            "type":"Retail Goods"
        }
    ],
    "sg:phone":"+1 503 234 7373",
    "sg:postcode":"97232",
    "sg:province":"OR",
    "sg:tags":[
        "game",
        "video",
        "dvd's"
    ],
    "sg:website":"www.everydaymusic.com",
    "wof:name":"Everday Music",
    "wof:placetype":"venue"
},
  "geometry": {"coordinates":[-122.646004,45.5257],"type":"Point"}
}