{
  "type": "Feature",
  "properties": {
    "addr:full":"968 SW 30th St Ontario OR 97914",
    "addr:housenumber":"968",
    "addr:postcode":"97914",
    "addr:street":"Sw 30Th St",
    "iso:country":"US",
    "sg:address":"968 SW 30th St",
    "sg:city":"Ontario",
    "sg:classifiers":[
        {
            "category":"Place Of Worship",
            "subcategory":"Church",
            "type":"Public Place"
        },
        {
            "category":"Place Of Worship",
            "type":"Public Place"
        }
    ],
    "sg:phone":"+1 541 889 4623",
    "sg:postcode":"97914",
    "sg:province":"OR",
    "sg:tags":[
        "testament",
        "churches-church",
        "christ-new",
        "christ"
    ],
    "wof:name":"Sunrise Christian Church",
    "wof:placetype":"venue"
},
  "geometry": {"coordinates":[-117.005376,44.019171],"type":"Point"}
}