{
  "type": "Feature",
  "properties": {
    "iso:country":"US",
    "sg:address":"2327 NW 161st Ave",
    "sg:city":"Beaverton",
    "sg:classifiers":[
        {
            "category":"Travel",
            "subcategory":"Hotels & Motels",
            "type":"Entertainment"
        }
    ],
    "sg:phone":"+1 503 645 9890",
    "sg:postcode":"97006",
    "sg:province":"OR",
    "sg:tags":[
        "operation"
    ],
    "wof:name":"Kilsea Beach House",
    "wof:placetype":"venue"
},
  "geometry": {"coordinates":[-122.844334,45.536677],"type":"Point"}
}