{
  "type": "Feature",
  "properties": {
    "iso:country":"US",
    "sg:address":"7400 SW MacAdam Ave",
    "sg:city":"Portland",
    "sg:classifiers":[
        {
            "category":"Shopping",
            "subcategory":"Hobbies, Toys, & Games",
            "type":"Retail Goods"
        }
    ],
    "sg:phone":"+1 503 246 0056",
    "sg:postcode":"97219",
    "sg:province":"OR",
    "sg:tags":[
        "toy",
        "store"
    ],
    "sg:website":"www.thekidsbackyardstore.com",
    "wof:name":"Kids' Backyard Store the",
    "wof:placetype":"venue"
},
  "geometry": {"coordinates":[-122.67127499999999,45.471281],"type":"Point"}
}