{
  "type": "Feature",
  "properties": {
    "iso:country":"US",
    "sg:address":"142 High St SE",
    "sg:city":"Salem",
    "sg:classifiers":[
        {
            "category":"Banks & Credit Unions",
            "subcategory":"Bank",
            "type":"Services"
        }
    ],
    "sg:phone":"+1 503 581 8007",
    "sg:postcode":"97301",
    "sg:province":"OR",
    "sg:tags":[
        "loan",
        "real estate"
    ],
    "wof:name":"Willamette Valley Mortgage",
    "wof:placetype":"venue"
},
  "geometry": {"coordinates":[-123.037464,44.938973],"type":"Point"}
}