{
  "type": "Feature",
  "properties": {
    "iso:country":"US",
    "sg:address":"40141 Angberg Ln",
    "sg:city":"Astoria",
    "sg:classifiers":[
        {
            "category":"Real Estate",
            "subcategory":"Architect",
            "type":"Services"
        }
    ],
    "sg:phone":"+1 503 458 6336",
    "sg:postcode":"97103",
    "sg:province":"OR",
    "sg:tags":[
        "architectural"
    ],
    "wof:name":"Tom Potter Architect",
    "wof:placetype":"venue"
},
  "geometry": {"coordinates":[-123.660073,46.160216],"type":"Point"}
}