{
  "type": "Feature",
  "properties": {
    "iso:country":"US",
    "sg:address":"8380 SE Short Rd",
    "sg:city":"Gresham",
    "sg:classifiers":[
        {
            "category":"Building & Trades",
            "subcategory":"Construction",
            "type":"Services"
        }
    ],
    "sg:phone":"+1 503 663 3495",
    "sg:postcode":"97080",
    "sg:province":"OR",
    "sg:tags":[
        "builder",
        "operative"
    ],
    "wof:name":"Nyhof Homes Inc",
    "wof:placetype":"venue"
},
  "geometry": {"coordinates":[-122.35753099999999,45.463128],"type":"Point"}
}