{
  "type": "Feature",
  "properties": {
    "iso:country":"US",
    "sg:address":"13568 SE 97th Ave",
    "sg:city":"Clackamas",
    "sg:classifiers":[
        {
            "category":"Health Services",
            "subcategory":"Doctor",
            "type":"Services"
        }
    ],
    "sg:phone":"+1 503 652 0303",
    "sg:postcode":"97015",
    "sg:province":"OR",
    "sg:tags":[
        "physician",
        "management",
        "surgeons",
        "weight",
        "loss"
    ],
    "wof:name":"The Wickenburg Company",
    "wof:placetype":"venue"
},
  "geometry": {"coordinates":[-122.561842,45.42499],"type":"Point"}
}