{
  "type": "Feature",
  "properties": {
    "iso:country":"US",
    "sg:address":"1715 NW Marshall Street",
    "sg:city":"Portland",
    "sg:classifiers":[
        {
            "category":"Real Estate",
            "subcategory":"Real Estate Operator",
            "type":"Services"
        }
    ],
    "sg:phone":"+1 503 223 7803",
    "sg:postcode":"97209",
    "sg:province":"OR",
    "sg:tags":[
        "apartment"
    ],
    "wof:name":"Marshall Arms",
    "wof:placetype":"venue"
},
  "geometry": {"coordinates":[-122.688638,45.530711],"type":"Point"}
}