{
  "type": "Feature",
  "properties": {
    "iso:country":"US",
    "sg:address":"204 N 1st St",
    "sg:city":"Silverton",
    "sg:classifiers":[
        {
            "category":"Professional",
            "subcategory":"Research",
            "type":"Services"
        }
    ],
    "sg:phone":"+1 503 873 1201",
    "sg:postcode":"97381",
    "sg:province":"OR",
    "sg:tags":[
        "researcher"
    ],
    "wof:name":"Oregon Center For Public Plcy",
    "wof:placetype":"venue"
},
  "geometry": {"coordinates":[-122.782752,45.006663],"type":"Point"}
}