{
  "type": "Feature",
  "properties": {
    "iso:country":"US",
    "sg:address":"4603 3rd St",
    "sg:city":"Tillamook",
    "sg:classifiers":[
        {
            "category":"Communications",
            "subcategory":"Radio Station",
            "type":"Services"
        }
    ],
    "sg:phone":"+1 503 842 2845",
    "sg:postcode":"97141",
    "sg:province":"OR",
    "sg:tags":[
        "company",
        "broadcasting"
    ],
    "wof:name":"Infinite Broadcasting",
    "wof:placetype":"venue"
},
  "geometry": {"coordinates":[-123.804445,45.457408],"type":"Point"}
}