{
  "type": "Feature",
  "properties": {
    "iso:country":"US",
    "sg:address":"20125 NE Interlachen Ln",
    "sg:city":"Fairview",
    "sg:classifiers":[
        {
            "category":"Farming",
            "subcategory":"Fish & Marine Products",
            "type":"Manufacturing & Wholesale Goods"
        }
    ],
    "sg:phone":"+1 503 666 8236",
    "sg:postcode":"97024",
    "sg:province":"OR",
    "sg:tags":[
        "management"
    ],
    "wof:name":"Goose Hollow",
    "wof:placetype":"venue"
},
  "geometry": {"coordinates":[-122.441402,45.552802],"type":"Point"}
}