{
  "type": "Feature",
  "properties": {
    "iso:country":"US",
    "sg:address":"1450 SE 30th Ave",
    "sg:city":"Hillsboro",
    "sg:classifiers":[
        {
            "category":"Wholesale",
            "subcategory":"Machinery & Supplies",
            "type":"Manufacturing & Wholesale Goods"
        }
    ],
    "sg:phone":"+1 503 640 4300",
    "sg:postcode":"97123",
    "sg:province":"OR",
    "sg:tags":[
        "equipment",
        "industrial"
    ],
    "wof:name":"Enerquin Air Corp",
    "wof:placetype":"venue"
},
  "geometry": {"coordinates":[-122.95159700000001,45.508465],"type":"Point"}
}