{
  "type": "Feature",
  "properties": {
    "addr:full":"405 SE 80th Ave Portland OR 97215",
    "addr:housenumber":"405",
    "addr:postcode":"97215",
    "addr:street":"Se 80Th Ave",
    "iso:country":"US",
    "sg:address":"405 SE 80th Ave",
    "sg:city":"Portland",
    "sg:classifiers":[
        {
            "category":"Retail",
            "subcategory":"Repair Shop",
            "type":"Services"
        }
    ],
    "sg:phone":"+1 503 255 4113",
    "sg:postcode":"97215",
    "sg:province":"OR",
    "wof:name":"Economy Prepress Imagesetting",
    "wof:placetype":"venue"
},
  "geometry": {"coordinates":[-122.58154399999999,45.519741],"type":"Point"}
}