{
  "type": "Feature",
  "properties": {
    "iso:country":"US",
    "sg:address":"6404 SW 30th Ave",
    "sg:city":"Portland",
    "sg:classifiers":[
        {
            "category":"Real Estate",
            "subcategory":"Real Estate Operator",
            "type":"Services"
        }
    ],
    "sg:phone":"+1 503 244 2616",
    "sg:postcode":"97239",
    "sg:province":"OR",
    "sg:tags":[
        "apartment"
    ],
    "wof:name":"Hilldale Garden Apartments",
    "wof:placetype":"venue"
},
  "geometry": {"coordinates":[-122.707651,45.477578],"type":"Point"}
}