{
  "type": "Feature",
  "properties": {
    "addr:full":"10721 NE Simpson St Portland OR 97220",
    "addr:housenumber":"10721",
    "addr:postcode":"97220",
    "addr:street":"Ne Simpson St",
    "iso:country":"US",
    "sg:address":"10721 NE Simpson St",
    "sg:city":"Portland",
    "sg:classifiers":[
        {
            "category":"Retail",
            "subcategory":"Auto Repair",
            "type":"Services"
        }
    ],
    "sg:phone":"+1 503 253 7865",
    "sg:postcode":"97220",
    "sg:province":"OR",
    "sg:tags":[
        "automotive"
    ],
    "wof:name":"Northwestern Towing",
    "wof:placetype":"venue"
},
  "geometry": {"coordinates":[-122.552487,45.565371],"type":"Point"}
}