{
  "type": "Feature",
  "properties": {
    "addr:full":"9850 SE Main St Portland OR 97222",
    "addr:housenumber":"9850",
    "addr:postcode":"97222",
    "addr:street":"Se Main St",
    "iso:country":"US",
    "sg:address":"9850 SE Main St",
    "sg:city":"Portland",
    "sg:classifiers":[
        {
            "category":"Home & Garden",
            "subcategory":"Carpets & Floor Coverings",
            "type":"Retail Goods"
        }
    ],
    "sg:phone":"+1 503 287 6989",
    "sg:postcode":"97222",
    "sg:province":"OR",
    "sg:tags":[
        "carpeting"
    ],
    "wof:name":"Corinthian Rug Co",
    "wof:placetype":"venue"
},
  "geometry": {"coordinates":[-122.61599699999999,45.441898],"type":"Point"}
}