{
  "type": "Feature",
  "properties": {
    "iso:country":"US",
    "sg:address":"30834 SW Decker Ridge Rd",
    "sg:city":"Corvallis",
    "sg:classifiers":[
        {
            "category":"Manufacturing",
            "subcategory":"Rubber & Plastics",
            "type":"Manufacturing & Wholesale Goods"
        }
    ],
    "sg:phone":"+1 541 929 5716",
    "sg:postcode":"97333",
    "sg:province":"OR",
    "sg:tags":[
        "product",
        "mfg"
    ],
    "wof:name":"Custom Tool",
    "wof:placetype":"venue"
},
  "geometry": {"coordinates":[-123.41788699999999,44.47459],"type":"Point"}
}