{
  "type": "Feature",
  "properties": {
    "addr:full":"1600 Executive Pkwy Eugene OR 97401",
    "addr:housenumber":"1600",
    "addr:postcode":"97401",
    "addr:street":"Executive Pkwy",
    "iso:country":"US",
    "sg:address":"1600 Executive Pkwy",
    "sg:city":"Eugene",
    "sg:classifiers":[
        {
            "category":"Banks & Credit Unions",
            "subcategory":"Bank",
            "type":"Services"
        }
    ],
    "sg:phone":"+1 541 967 3717",
    "sg:postcode":"97401",
    "sg:province":"OR",
    "sg:tags":[
        "loan",
        "mortgage",
        "real estate"
    ],
    "sg:website":"www.chase.com",
    "wof:name":"Chase Manhattan Mortgage Corp",
    "wof:placetype":"venue"
},
  "geometry": {"coordinates":[-123.108136,44.06995],"type":"Point"}
}