{
  "type": "Feature",
  "properties": {
    "addr:full":"14324 SE Stark St Portland OR 97233",
    "addr:postcode":"14324;97233",
    "addr:street":"Se Stark St",
    "iso:country":"US",
    "sg:address":"14324 SE Stark St",
    "sg:city":"Portland",
    "sg:classifiers":[
        {
            "category":"Government",
            "subcategory":"Fire Station",
            "type":"Public Place"
        },
        {
            "category":"Professional",
            "subcategory":"Detective & Security Services",
            "type":"Services"
        },
        {
            "category":"Home & Garden",
            "subcategory":"Hardware",
            "type":"Retail Goods"
        }
    ],
    "sg:phone":"+1 503 231 2999",
    "sg:postcode":"97233",
    "sg:province":"OR",
    "sg:tags":[
        "extinguisher",
        "industrial",
        "monitoring",
        "supply",
        "commercial",
        "alarm",
        "sprinklers-residential",
        "system",
        "equipment",
        "control",
        "protection",
        "automatic"
    ],
    "sg:website":"http://www.metrosafetyandfire.com",
    "wof:name":"Metro Safety & Fire Inc",
    "wof:placetype":"venue"
},
  "geometry": {"coordinates":[-122.51563,45.519131],"type":"Point"}
}