{
  "type": "Feature",
  "properties": {
    "iso:country":"US",
    "sg:address":"4155 NW Yeon Ave",
    "sg:city":"Portland",
    "sg:classifiers":[
        {
            "category":"Manufacturing",
            "subcategory":"Chemicals & Compounds",
            "type":"Manufacturing & Wholesale Goods"
        }
    ],
    "sg:phone":"+1 503 226 3751",
    "sg:postcode":"97210",
    "sg:province":"OR",
    "sg:tags":[
        "synthetic",
        "resin",
        "mfg"
    ],
    "wof:name":"Eastman Chemical Company",
    "wof:placetype":"venue"
},
  "geometry": {"coordinates":[-122.730107,45.553351],"type":"Point"}
}