{
  "type": "Feature",
  "properties": {
    "addr:full":"1999 E Powell Blvd Gresham OR 97080",
    "addr:housenumber":"1999",
    "addr:postcode":"97080",
    "addr:street":"E Powell Blvd",
    "iso:country":"US",
    "sg:address":"1999 E Powell Blvd",
    "sg:city":"Gresham",
    "sg:classifiers":[
        {
            "category":"Autos & Motor Vehicles",
            "subcategory":"Automobile Sales",
            "type":"Retail Goods"
        }
    ],
    "sg:phone":"+1 503 661 2222",
    "sg:postcode":"97080",
    "sg:province":"OR",
    "sg:tags":[
        "car",
        "dealer"
    ],
    "sg:website":"www.murraychevrolet.com",
    "wof:name":"Murray Mazda",
    "wof:placetype":"venue"
},
  "geometry": {"coordinates":[-122.41337799999999,45.497716],"type":"Point"}
}