{
  "type": "Feature",
  "properties": {
    "addr:full":"5655 SW Philomath Blvd Corvallis OR 97333",
    "addr:housenumber":"5655",
    "addr:postcode":"97333",
    "addr:street":"Sw Philomath Blvd",
    "iso:country":"US",
    "sg:address":"5655 SW Philomath Blvd",
    "sg:city":"Corvallis",
    "sg:classifiers":[
        {
            "category":"Manufacturing",
            "subcategory":"Printing",
            "type":"Manufacturing & Wholesale Goods"
        }
    ],
    "sg:phone":"+1 541 753 0303",
    "sg:postcode":"97333",
    "sg:province":"OR",
    "sg:tags":[
        "lithographic",
        "commercial"
    ],
    "wof:name":"Franklin Press The",
    "wof:placetype":"venue"
},
  "geometry": {"coordinates":[-123.318445,44.548937],"type":"Point"}
}