{
  "type": "Feature",
  "properties": {
    "addr:full":"7374 Mt Jeff Ln SE Salem OR 97317",
    "addr:housenumber":"7374",
    "addr:postcode":"97317",
    "addr:street":"Mt Jeff Ln Se",
    "iso:country":"US",
    "sg:address":"7374 Mt Jeff Ln SE",
    "sg:city":"Salem",
    "sg:classifiers":[
        {
            "category":"Building & Trades",
            "subcategory":"Plumbing",
            "type":"Services"
        }
    ],
    "sg:phone":"+1 503 581 0069",
    "sg:postcode":"97317",
    "sg:province":"OR",
    "sg:tags":[
        "contractor"
    ],
    "wof:name":"Valley Plumbing",
    "wof:placetype":"venue"
},
  "geometry": {"coordinates":[-122.90857099999999,44.875262],"type":"Point"}
}