{
  "type": "Feature",
  "properties": {
    "iso:country":"US",
    "sg:address":"20 W 17th Ave",
    "sg:city":"Eugene",
    "sg:classifiers":[
        {
            "category":"Personal",
            "subcategory":"Beauty Salon",
            "type":"Services"
        }
    ],
    "sg:phone":"+1 541 221 2046",
    "sg:postcode":"97401",
    "sg:province":"OR",
    "wof:name":"Ashcraft Hair Design",
    "wof:placetype":"venue"
},
  "geometry": {"coordinates":[-123.09323,44.041065],"type":"Point"}
}