{
  "type": "Feature",
  "properties": {
    "iso:country":"US",
    "sg:address":"2665 Crater Lake Hwy",
    "sg:city":"Medford",
    "sg:classifiers":[
        {
            "category":"Autos & Motor Vehicles",
            "subcategory":"Motorcycle Sales",
            "type":"Retail Goods"
        }
    ],
    "sg:phone":"+1 541 770 6777",
    "sg:postcode":"97504",
    "sg:province":"OR",
    "sg:tags":[
        "scooter"
    ],
    "wof:name":"Fast Boyz N Girlz Toyz",
    "wof:placetype":"venue"
},
  "geometry": {"coordinates":[-122.866997,42.356098],"type":"Point"}
}