{
  "type": "Feature",
  "properties": {
    "addr:full":"365 NW Harrison Blvd Corvallis OR 97330",
    "addr:housenumber":"365",
    "addr:postcode":"97330",
    "addr:street":"Nw Harrison Blvd",
    "iso:country":"US",
    "sg:address":"365 NW Harrison Blvd",
    "sg:city":"Corvallis",
    "sg:classifiers":[
        {
            "category":"Real Estate",
            "subcategory":"Real Estate Agent",
            "type":"Services"
        }
    ],
    "sg:phone":"+1 541 758 2155",
    "sg:postcode":"97330",
    "sg:province":"OR",
    "sg:website":"www.fredladams.com",
    "wof:name":"Raising The Bar Real Estate",
    "wof:placetype":"venue"
},
  "geometry": {"coordinates":[-123.259863,44.567468],"type":"Point"}
}