{
  "type": "Feature",
  "properties": {
    "addr:full":"3632 River Rd N Keizer OR 97303",
    "addr:housenumber":"3632",
    "addr:postcode":"97303",
    "addr:street":"River Rd N",
    "iso:country":"US",
    "sg:address":"3632 River Rd N",
    "sg:city":"Keizer",
    "sg:classifiers":[
        {
            "category":"Personal",
            "subcategory":"Beauty Salon",
            "type":"Services"
        }
    ],
    "sg:phone":"+1 503 393 6800",
    "sg:postcode":"97303",
    "sg:province":"OR",
    "sg:tags":[
        "shop"
    ],
    "sg:website":"www.radiancesalonspa.com",
    "wof:name":"Radiance Salon & Spa",
    "wof:placetype":"venue"
},
  "geometry": {"coordinates":[-123.02649,44.97864],"type":"Point"}
}