{
  "type": "Feature",
  "properties": {
    "iso:country":"US",
    "sg:address":"3600 Washburn Way",
    "sg:city":"Klamath Falls",
    "sg:classifiers":[
        {
            "category":"Shopping",
            "subcategory":"Optical Goods",
            "type":"Retail Goods"
        }
    ],
    "sg:phone":"+1 541 883 1157",
    "sg:postcode":"97603",
    "sg:province":"OR",
    "wof:name":"National Vision",
    "wof:placetype":"venue"
},
  "geometry": {"coordinates":[-121.75721299999999,42.193232],"type":"Point"}
}