{
  "type": "Feature",
  "properties": {
    "addr:full":"30681 S Needy Rd Canby OR 97013",
    "addr:housenumber":"30681",
    "addr:postcode":"97013",
    "addr:street":"S Needy Rd",
    "iso:country":"US",
    "sg:address":"30681 S Needy Rd",
    "sg:city":"Canby",
    "sg:classifiers":[
        {
            "category":"Professional",
            "subcategory":"Accounting & Tax Preparation",
            "type":"Services"
        }
    ],
    "sg:phone":"+1 503 651 2700",
    "sg:postcode":"97013",
    "sg:province":"OR",
    "sg:tags":[
        "return"
    ],
    "wof:name":"Helen Rieker Ltc",
    "wof:placetype":"venue"
},
  "geometry": {"coordinates":[-122.702063,45.161435],"type":"Point"}
}