{
  "type": "Feature",
  "properties": {
    "iso:country":"US",
    "sg:address":"231 N Main St",
    "sg:city":"Prineville",
    "sg:classifiers":[
        {
            "category":"Shopping",
            "type":"Retail Goods"
        }
    ],
    "sg:phone":"+1 541 416 9183",
    "sg:postcode":"97754",
    "sg:province":"OR",
    "sg:tags":[
        "merchandise"
    ],
    "wof:name":"Trophy Developments LLC",
    "wof:placetype":"venue"
},
  "geometry": {"coordinates":[-120.847132,44.302679],"type":"Point"}
}