{
  "type": "Feature",
  "properties": {
    "iso:country":"US",
    "sg:address":"938 N Cook St",
    "sg:city":"Portland",
    "sg:classifiers":[
        {
            "category":"Restaurant",
            "type":"Food & Drink"
        }
    ],
    "sg:phone":"+1 503 445 9910",
    "sg:postcode":"97227",
    "sg:province":"OR",
    "wof:name":"Lovely Hula Hands",
    "wof:placetype":"venue"
},
  "geometry": {"coordinates":[-122.676475,45.546129],"type":"Point"}
}