{
  "type": "Feature",
  "properties": {
    "iso:country":"US",
    "sg:address":"23180 NW Bennett St",
    "sg:city":"Hillsboro",
    "sg:classifiers":[
        {
            "category":"Manufacturing",
            "subcategory":"Electronics",
            "type":"Manufacturing & Wholesale Goods"
        }
    ],
    "sg:phone":"+1 503 693 0963",
    "sg:postcode":"97124",
    "sg:province":"OR",
    "sg:tags":[
        "semiconductor",
        "devices"
    ],
    "wof:name":"Nikon Precision Inc",
    "wof:placetype":"venue"
},
  "geometry": {"coordinates":[-122.917706,45.55469],"type":"Point"}
}