{
  "type": "Feature",
  "properties": {
    "iso:country":"US",
    "sg:address":"4804 N Albina Ave",
    "sg:city":"Portland",
    "sg:classifiers":[
        {
            "category":"Building & Trades",
            "subcategory":"Cleaning & Sanitation",
            "type":"Services"
        }
    ],
    "sg:phone":"+1 503 284 8041",
    "sg:postcode":"97217",
    "sg:province":"OR",
    "sg:tags":[
        "maintenance"
    ],
    "wof:name":"O&T Cleaning Services LLC",
    "wof:placetype":"venue"
},
  "geometry": {"coordinates":[-122.674859,45.557556],"type":"Point"}
}