{
  "type": "Feature",
  "properties": {
    "addr:full":"2705 NE 52nd Ave Portland OR 97213",
    "addr:housenumber":"2705",
    "addr:postcode":"97213",
    "addr:street":"Ne 52Nd Ave",
    "iso:country":"US",
    "sg:address":"2705 NE 52nd Ave",
    "sg:city":"Portland",
    "sg:classifiers":[
        {
            "category":"Manufacturing",
            "subcategory":"Retail Goods",
            "type":"Manufacturing & Wholesale Goods"
        }
    ],
    "sg:phone":"+1 503 287 7122",
    "sg:postcode":"97213",
    "sg:province":"OR",
    "sg:tags":[
        "product",
        "mfg"
    ],
    "wof:name":"Datatec Industries Inc",
    "wof:placetype":"venue"
},
  "geometry": {"coordinates":[-122.609737,45.543689],"type":"Point"}
}