{
  "type": "Feature",
  "properties": {
    "addr:full":"45 SW D St Madras OR 97741",
    "addr:housenumber":"45",
    "addr:postcode":"97741",
    "addr:street":"Sw D St",
    "iso:country":"US",
    "sg:address":"45 SW D St",
    "sg:city":"Madras",
    "sg:classifiers":[
        {
            "category":"Shopping",
            "subcategory":"Bicycles & Sporting Goods",
            "type":"Retail Goods"
        }
    ],
    "sg:phone":"+1 541 475 6294",
    "sg:postcode":"97741",
    "sg:province":"OR",
    "wof:name":"Sportsworld",
    "wof:placetype":"venue"
},
  "geometry": {"coordinates":[-121.12968600000001,44.633442],"type":"Point"}
}