{
  "type": "Feature",
  "properties": {
    "addr:full":"14330 SW Fanno Creek Loop Portland OR 97224",
    "addr:housenumber":"14330",
    "addr:postcode":"97224",
    "addr:street":"Sw Fanno Creek Loop",
    "iso:country":"US",
    "sg:address":"14330 SW Fanno Creek Loop",
    "sg:city":"Portland",
    "sg:classifiers":[
        {
            "category":"Mining & Drilling",
            "type":"Manufacturing & Wholesale Goods"
        }
    ],
    "sg:phone":"+1 503 670 7278",
    "sg:postcode":"97224",
    "sg:province":"OR",
    "sg:tags":[
        "field"
    ],
    "wof:name":"Concept To Completion",
    "wof:placetype":"venue"
},
  "geometry": {"coordinates":[-122.76363600000001,45.416761],"type":"Point"}
}