{
  "type": "Feature",
  "properties": {
    "addr:full":"2260 SE Court Ave Pendleton OR 97801",
    "addr:housenumber":"2260",
    "addr:postcode":"97801",
    "addr:street":"Se Court Ave",
    "iso:country":"US",
    "sg:address":"2260 SE Court Ave",
    "sg:city":"Pendleton",
    "sg:classifiers":[
        {
            "category":"Autos & Motor Vehicles",
            "subcategory":"Motorcycle Sales",
            "type":"Retail Goods"
        }
    ],
    "sg:phone":"+1 541 278 5123",
    "sg:postcode":"97801",
    "sg:province":"OR",
    "wof:name":"Oregon Power Sports",
    "wof:placetype":"venue"
},
  "geometry": {"coordinates":[-118.76190200000001,45.672984],"type":"Point"}
}