{
  "type": "Feature",
  "properties": {
    "iso:country":"US",
    "sg:address":"585 N Main St",
    "sg:city":"Canyonville",
    "sg:classifiers":[
        {
            "category":"Shopping",
            "subcategory":"Pets & Pet Supplies",
            "type":"Retail Goods"
        }
    ],
    "sg:phone":"+1 541 839 4841",
    "sg:postcode":"97417",
    "sg:province":"OR",
    "sg:tags":[
        "feed",
        "concentrate",
        "supplement"
    ],
    "wof:name":"Rogers Feed Store",
    "wof:placetype":"venue"
},
  "geometry": {"coordinates":[-123.281837,42.934368],"type":"Point"}
}