{
  "type": "Feature",
  "properties": {
    "addr:full":"9745 SE Division St Portland OR 97266",
    "addr:housenumber":"9745",
    "addr:postcode":"97266",
    "addr:street":"Se Division St",
    "iso:country":"US",
    "sg:address":"9745 SE Division St",
    "sg:city":"Portland",
    "sg:classifiers":[
        {
            "category":"Manufacturing",
            "subcategory":"Chemicals & Compounds",
            "type":"Manufacturing & Wholesale Goods"
        },
        {
            "category":"Manufacturing",
            "subcategory":"Tools & Machinery",
            "type":"Manufacturing & Wholesale Goods"
        },
        {
            "category":"Building & Trades",
            "subcategory":"Construction",
            "type":"Services"
        },
        {
            "category":"Home & Garden",
            "subcategory":"Building Materials",
            "type":"Retail Goods"
        },
        {
            "category":"Wholesale",
            "subcategory":"Painting Supplies",
            "type":"Manufacturing & Wholesale Goods"
        },
        {
            "category":"Autos & Motor Vehicles",
            "subcategory":"Auto Supplies",
            "type":"Retail Goods"
        },
        {
            "category":"Building & Trades",
            "subcategory":"Equipment Rental",
            "type":"Services"
        },
        {
            "category":"Manufacturing",
            "subcategory":"Building Materials",
            "type":"Manufacturing & Wholesale Goods"
        }
    ],
    "sg:phone":"+1 503 760 8233",
    "sg:postcode":"97266",
    "sg:province":"OR",
    "sg:tags":[
        "shop",
        "paint",
        "wall",
        "automobile",
        "wallpaper",
        "coating",
        "contractor",
        "paint-wholesale",
        "spraying",
        "body",
        "wallcoverings-installation",
        "wallcoverings",
        "improvement",
        "equipment-renting",
        "painter",
        "manufacturer"
    ],
    "sg:website":"http://portland.citysearch.com/profile/external/8490668/portland_or/sherwin_williams.html?publisher=yellowpages&reference_id=1&placement=ypwebsitemip",
    "wof:name":"Sherwin-Williams",
    "wof:placetype":"venue"
},
  "geometry": {"coordinates":[-122.562782,45.504379],"type":"Point"}
}