{
  "type": "Feature",
  "properties": {
    "iso:country":"US",
    "sg:address":"65867 Hartford Ln",
    "sg:city":"Elgin",
    "sg:classifiers":[
        {
            "category":"Building & Trades",
            "subcategory":"Construction",
            "type":"Services"
        }
    ],
    "sg:phone":"+1 541 437 0305",
    "sg:postcode":"97827",
    "sg:province":"OR",
    "sg:tags":[
        "excavation",
        "contractor"
    ],
    "wof:name":"CRC Excavating",
    "wof:placetype":"venue"
},
  "geometry": {"coordinates":[-117.924108,45.572529],"type":"Point"}
}