{
  "type": "Feature",
  "properties": {
    "addr:full":"1123 Reuben Rd Glendale OR 97442",
    "addr:housenumber":"1123",
    "addr:postcode":"97442",
    "addr:street":"Reuben Rd",
    "iso:country":"US",
    "sg:address":"1123 Reuben Rd",
    "sg:city":"Glendale",
    "sg:classifiers":[
        {
            "category":"Manufacturing",
            "subcategory":"Signs",
            "type":"Manufacturing & Wholesale Goods"
        }
    ],
    "sg:phone":"+1 541 832 2949",
    "sg:postcode":"97442",
    "sg:province":"OR",
    "wof:name":"Safari Signs",
    "wof:placetype":"venue"
},
  "geometry": {"coordinates":[-123.432547,42.74519],"type":"Point"}
}