{
  "type": "Feature",
  "properties": {
    "addr:full":"1710 NE Fairview Ave Grants Pass OR 97526",
    "addr:housenumber":"1710",
    "addr:postcode":"97526",
    "addr:street":"Ne Fairview Ave",
    "iso:country":"US",
    "sg:address":"1710 NE Fairview Ave",
    "sg:city":"Grants Pass",
    "sg:classifiers":[
        {
            "category":"Health Services",
            "subcategory":"Nursing And Care Facility",
            "type":"Services"
        }
    ],
    "sg:phone":"+1 541 479 2606",
    "sg:postcode":"97526",
    "sg:province":"OR",
    "sg:tags":[
        "home"
    ],
    "wof:name":"Regency Care Ctr Grants Pass",
    "wof:placetype":"venue"
},
  "geometry": {"coordinates":[-123.304582,42.438173],"type":"Point"}
}