{
  "type": "Feature",
  "properties": {
    "iso:country":"US",
    "sg:address":"444 Wynooski St",
    "sg:city":"Newberg",
    "sg:classifiers":[
        {
            "category":"Building & Trades",
            "subcategory":"Construction",
            "type":"Services"
        }
    ],
    "sg:phone":"+1 503 554 0677",
    "sg:postcode":"97132",
    "sg:province":"OR",
    "sg:tags":[
        "altering",
        "house",
        "remodeling",
        "contractor"
    ],
    "wof:name":"Ed Buck Construction",
    "wof:placetype":"venue"
},
  "geometry": {"coordinates":[-122.965326,45.297295],"type":"Point"}
}