{
  "type": "Feature",
  "properties": {
    "iso:country":"US",
    "sg:address":"1310 Lloyd Ctr Ste 2",
    "sg:city":"Portland",
    "sg:phone":"+1 503 288 9888",
    "sg:postcode":"97232",
    "sg:province":"OR",
    "wof:name":"La Belle Vie Lloyd's",
    "wof:placetype":"venue"
},
  "geometry": {"coordinates":[-122.65163200000001,45.529691],"type":"Point"}
}