{
  "type": "Feature",
  "properties": {
    "iso:country":"US",
    "sg:address":"260 SW Towle Ave",
    "sg:city":"Gresham",
    "sg:classifiers":[
        {
            "category":"Social Services",
            "subcategory":"Child Care",
            "type":"Services"
        }
    ],
    "sg:phone":"+1 503 665 1213",
    "sg:postcode":"97080",
    "sg:province":"OR",
    "sg:tags":[
        "day"
    ],
    "wof:name":"Stepping Stones Day School Ctr",
    "wof:placetype":"venue"
},
  "geometry": {"coordinates":[-122.446949,45.495315],"type":"Point"}
}