{
  "type": "Feature",
  "properties": {
    "iso:country":"US",
    "sg:address":"9770 SE 82nd Ave",
    "sg:city":"Portland",
    "sg:classifiers":[
        {
            "category":"Shopping",
            "subcategory":"Pawn Shop",
            "type":"Retail Goods"
        }
    ],
    "sg:phone":"+1 503 772 2916",
    "sg:postcode":"97266",
    "sg:province":"OR",
    "sg:website":"www.ilikestuff.com/",
    "wof:name":"Stuff",
    "wof:placetype":"venue"
},
  "geometry": {"coordinates":[-122.579002,45.452],"type":"Point"}
}