{
  "type": "Feature",
  "properties": {
    "iso:country":"US",
    "sg:address":"241 E Main St",
    "sg:city":"Hillsboro",
    "sg:classifiers":[
        {
            "category":"Retail",
            "subcategory":"Funeral Services",
            "type":"Services"
        }
    ],
    "sg:phone":"+1 503 693 7965",
    "sg:postcode":"97123",
    "sg:province":"OR",
    "sg:tags":[
        "director"
    ],
    "wof:name":"Tualatin Valley Funeral",
    "wof:placetype":"venue"
},
  "geometry": {"coordinates":[-122.98679300000001,45.5227],"type":"Point"}
}