{
  "type": "Feature",
  "properties": {
    "iso:country":"US",
    "sg:address":"20704 SE Main Dr",
    "sg:city":"Gresham",
    "sg:classifiers":[
        {
            "category":"Professional",
            "subcategory":"Management & Consulting",
            "type":"Services"
        }
    ],
    "sg:phone":"+1 503 661 7255",
    "sg:postcode":"97030",
    "sg:province":"OR",
    "sg:tags":[
        "retail",
        "direct",
        "sales"
    ],
    "wof:name":"Donna Burgwin Avon Sales",
    "wof:placetype":"venue"
},
  "geometry": {"coordinates":[-122.450748,45.51453],"type":"Point"}
}