{
  "type": "Feature",
  "properties": {
    "iso:country":"US",
    "sg:address":"369 Caves Hwy",
    "sg:city":"Cave Junction",
    "sg:classifiers":[
        {
            "category":"Retail",
            "subcategory":"Veterinary Services",
            "type":"Services"
        }
    ],
    "sg:phone":"+1 541 592 4589",
    "sg:postcode":"97523",
    "sg:province":"OR",
    "sg:tags":[
        "veterinarian"
    ],
    "wof:name":"Dr Joe's Pet Hospital",
    "wof:placetype":"venue"
},
  "geometry": {"coordinates":[-123.642804,42.161619],"type":"Point"}
}