{
  "type": "Feature",
  "properties": {
    "addr:full":"9135 Hwy 97 S Klamath Falls OR 97603",
    "addr:housenumber":"9135",
    "addr:postcode":"97603",
    "addr:street":"Hwy 97 S Klamath",
    "iso:country":"US",
    "sg:address":"9135 Hwy 97 S",
    "sg:city":"Klamath Falls",
    "sg:classifiers":[
        {
            "category":"Wholesale",
            "subcategory":"Machinery & Supplies",
            "type":"Manufacturing & Wholesale Goods"
        }
    ],
    "sg:phone":"+1 541 884 5683",
    "sg:postcode":"97603",
    "sg:province":"OR",
    "sg:tags":[
        "equipment",
        "construction"
    ],
    "wof:name":"Pape Machinery Inc",
    "wof:placetype":"venue"
},
  "geometry": {"coordinates":[-121.810463,42.142931],"type":"Point"}
}