{
  "type": "Feature",
  "properties": {
    "addr:full":"11146 NE Halsey St Portland OR 97220",
    "addr:housenumber":"11146",
    "addr:postcode":"97220",
    "addr:street":"Ne Halsey St",
    "iso:country":"US",
    "sg:address":"11146 NE Halsey St",
    "sg:city":"Portland",
    "sg:classifiers":[
        {
            "category":"Insurance",
            "subcategory":"Insurance Agent",
            "type":"Services"
        }
    ],
    "sg:phone":"+1 503 252 7121",
    "sg:postcode":"97220",
    "sg:province":"OR",
    "wof:name":"State Farm Insurance",
    "wof:placetype":"venue"
},
  "geometry": {"coordinates":[-122.54759900000001,45.533391],"type":"Point"}
}