{
  "type": "Feature",
  "properties": {
    "iso:country":"US",
    "sg:address":"64496 E Brightwood Loop Rd",
    "sg:city":"Brightwood",
    "sg:classifiers":[
        {
            "category":"Building & Trades",
            "subcategory":"Construction",
            "type":"Services"
        }
    ],
    "sg:phone":"+1 503 622 3340",
    "sg:postcode":"97011",
    "sg:province":"OR",
    "wof:name":"New Horizon Communications",
    "wof:placetype":"venue"
},
  "geometry": {"coordinates":[-122.00083600000001,45.365208],"type":"Point"}
}