{
  "type": "Feature",
  "properties": {
    "iso:country":"US",
    "sg:address":"14780 SW Osprey Dr",
    "sg:city":"Beaverton",
    "sg:classifiers":[
        {
            "category":"Shopping",
            "subcategory":"Jewelry",
            "type":"Retail Goods"
        }
    ],
    "sg:phone":"+1 503 579 9365",
    "sg:postcode":"97007",
    "sg:province":"OR",
    "sg:tags":[
        "jeweler"
    ],
    "wof:name":"A B Gem Lab Inc",
    "wof:placetype":"venue"
},
  "geometry": {"coordinates":[-122.826435,45.442745],"type":"Point"}
}