{
  "type": "Feature",
  "properties": {
    "addr:full":"269 NE Polk Station Rd Dallas OR 97338",
    "addr:housenumber":"269",
    "addr:postcode":"97338",
    "addr:street":"Ne Polk Station Rd",
    "iso:country":"US",
    "sg:address":"269 NE Polk Station Rd",
    "sg:city":"Dallas",
    "sg:classifiers":[
        {
            "category":"Retail",
            "subcategory":"Auto Rental",
            "type":"Services"
        }
    ],
    "sg:phone":"+1 503 831 3833",
    "sg:postcode":"97338",
    "sg:province":"OR",
    "sg:tags":[
        "renting",
        "automobile"
    ],
    "wof:name":"Your Choice Auto Rental",
    "wof:placetype":"venue"
},
  "geometry": {"coordinates":[-123.304596,44.930569],"type":"Point"}
}