{
  "type": "Feature",
  "properties": {
    "addr:full":"5920 State Hwy 238 Jacksonville OR 97530",
    "addr:housenumber":"5920",
    "addr:postcode":"97530",
    "addr:street":"State Hwy 238",
    "iso:country":"US",
    "sg:address":"5920 State Hwy 238",
    "sg:city":"Jacksonville",
    "sg:classifiers":[
        {
            "category":"Professional",
            "type":"Services"
        }
    ],
    "sg:phone":"+1 541 899 7437",
    "sg:postcode":"97530",
    "sg:province":"OR",
    "wof:name":"Positive Approach Training",
    "wof:placetype":"venue"
},
  "geometry": {"coordinates":[-123.02762300000001,42.258372],"type":"Point"}
}