{
  "type": "Feature",
  "properties": {
    "addr:full":"3425 NE 47th Ave Portland OR 97213",
    "addr:housenumber":"3425",
    "addr:postcode":"97213",
    "addr:street":"Ne 47Th Ave",
    "iso:country":"US",
    "sg:address":"3425 NE 47th Ave",
    "sg:city":"Portland",
    "sg:classifiers":[
        {
            "category":"Professional",
            "subcategory":"Advertising",
            "type":"Services"
        }
    ],
    "sg:phone":"+1 503 288 7771",
    "sg:postcode":"97213",
    "sg:province":"OR",
    "sg:tags":[
        "representative"
    ],
    "wof:name":"Nervy Girl Zine",
    "wof:placetype":"venue"
},
  "geometry": {"coordinates":[-122.614778,45.547451],"type":"Point"}
}