{
  "type": "Feature",
  "properties": {
    "iso:country":"US",
    "sg:address":"2303 SE 28th Place",
    "sg:city":"Portland",
    "sg:classifiers":[
        {
            "category":"Park",
            "type":"Public Place"
        }
    ],
    "sg:phone":"+1 503 916 5640",
    "sg:postcode":"97214",
    "sg:province":"OR",
    "sg:website":"www.hosford.pps.k12.or.us/",
    "wof:name":"Hosford Middle School Guerrilla Dog Park",
    "wof:placetype":"venue"
},
  "geometry": {"coordinates":[-122.637444,45.506061],"type":"Point"}
}