{
  "type": "Feature",
  "properties": {
    "iso:country":"US",
    "sg:address":"108 SE Court Ave",
    "sg:city":"Pendleton",
    "sg:classifiers":[
        {
            "category":"Shopping",
            "subcategory":"Clothing, Apparel, & Fashions",
            "type":"Retail Goods"
        }
    ],
    "sg:phone":"+1 541 278 2309",
    "sg:postcode":"97801",
    "sg:province":"OR",
    "sg:tags":[
        "tuxedo",
        "rental",
        "wear",
        "formal"
    ],
    "wof:name":"Formal Affairs",
    "wof:placetype":"venue"
},
  "geometry": {"coordinates":[-118.786469,45.67299],"type":"Point"}
}