{
  "type": "Feature",
  "properties": {
    "iso:country":"US",
    "sg:address":"4221 SW Research Way",
    "sg:city":"Corvallis",
    "sg:classifiers":[
        {
            "category":"Food & Beverages",
            "subcategory":"Groceries & Convenience Stores",
            "type":"Retail Goods"
        }
    ],
    "sg:phone":"+1 541 758 1500",
    "sg:postcode":"97333",
    "sg:province":"OR",
    "sg:website":"www.truaxcorp.com",
    "wof:name":"Truax Corp",
    "wof:placetype":"venue"
},
  "geometry": {"coordinates":[-123.296448,44.551639],"type":"Point"}
}