{
  "type": "Feature",
  "properties": {
    "iso:country":"US",
    "sg:address":"10295 SW Ridder Rd",
    "sg:city":"Wilsonville",
    "sg:classifiers":[
        {
            "category":"Utilities",
            "subcategory":"Refuse",
            "type":"Services"
        }
    ],
    "sg:phone":"+1 503 682 3900",
    "sg:postcode":"97070",
    "sg:province":"OR",
    "sg:tags":[
        "garbage",
        "collection"
    ],
    "wof:name":"Keller Drop Box",
    "wof:placetype":"venue"
},
  "geometry": {"coordinates":[-122.781035,45.331757],"type":"Point"}
}