{
  "type": "Feature",
  "properties": {
    "iso:country":"US",
    "sg:address":"2435 NW Front Ave",
    "sg:city":"Portland",
    "sg:classifiers":[
        {
            "category":"Banks & Credit Unions",
            "subcategory":"Financial Services",
            "type":"Services"
        }
    ],
    "sg:phone":"+1 503 226 0012",
    "sg:postcode":"97209",
    "sg:province":"OR",
    "sg:tags":[
        "sharing",
        "profit",
        "annuity",
        "retirement",
        "planning",
        "plan",
        "insurance",
        "pension"
    ],
    "wof:name":"Ilwu-Pma Benefit Plans",
    "wof:placetype":"venue"
},
  "geometry": {"coordinates":[-122.69299100000001,45.540658],"type":"Point"}
}