{
  "type": "Feature",
  "properties": {
    "addr:full":"12555 SW Tualatin Sherwood Rd Tualatin OR 97062",
    "addr:housenumber":"12555",
    "addr:postcode":"97062",
    "addr:street":"Sw Tualatin Sherwood Rd",
    "iso:country":"US",
    "sg:address":"12555 SW Tualatin Sherwood Rd",
    "sg:city":"Tualatin",
    "sg:classifiers":[
        {
            "category":"Wholesale",
            "subcategory":"Stationery",
            "type":"Manufacturing & Wholesale Goods"
        },
        {
            "category":"Manufacturing",
            "subcategory":"Rubber & Plastics",
            "type":"Manufacturing & Wholesale Goods"
        }
    ],
    "sg:phone":"+1 503 691 1161",
    "sg:postcode":"97062",
    "sg:province":"OR",
    "sg:tags":[
        "packaging",
        "material",
        "cor",
        "foam",
        "mfg"
    ],
    "sg:website":"www.p-r-c.com",
    "wof:name":"Packaging Resources Co",
    "wof:placetype":"venue"
},
  "geometry": {"coordinates":[-122.806286,45.369355],"type":"Point"}
}