{
  "type": "Feature",
  "properties": {
    "addr:full":"505 NE 87th Ave Portland OR 97220",
    "addr:housenumber":"505",
    "addr:postcode":"97220",
    "addr:street":"Ne 87Th Ave",
    "iso:country":"US",
    "sg:address":"505 NE 87th Ave",
    "sg:city":"Portland",
    "sg:classifiers":[
        {
            "category":"Health Services",
            "subcategory":"Health Practitioner",
            "type":"Services"
        }
    ],
    "sg:phone":"+1 503 972 3000",
    "sg:postcode":"97220",
    "sg:province":"OR",
    "wof:name":"Southwest Washington Med Ctr",
    "wof:placetype":"venue"
},
  "geometry": {"coordinates":[-122.57360199999999,45.52814],"type":"Point"}
}