{
  "type": "Feature",
  "properties": {
    "iso:country":"US",
    "sg:address":"19634 Clear Night Dr",
    "sg:city":"Bend",
    "sg:classifiers":[
        {
            "category":"Building & Trades",
            "subcategory":"Construction",
            "type":"Services"
        }
    ],
    "sg:phone":"+1 541 382 1633",
    "sg:postcode":"97702",
    "sg:province":"OR",
    "sg:tags":[
        "house",
        "nonresidential"
    ],
    "wof:name":"Jay Bird Construction Inc",
    "wof:placetype":"venue"
},
  "geometry": {"coordinates":[-121.341965,44.027033],"type":"Point"}
}