{
  "type": "Feature",
  "properties": {
    "iso:country":"US",
    "sg:address":"2234 NW 5th St",
    "sg:city":"Bend",
    "sg:classifiers":[
        {
            "category":"Banks & Credit Unions",
            "subcategory":"Financial Services",
            "type":"Services"
        },
        {
            "category":"Organizations",
            "subcategory":"Professional Association",
            "type":"Services"
        }
    ],
    "sg:phone":"+1 541 410 1093",
    "sg:postcode":"97701",
    "sg:province":"OR",
    "sg:tags":[
        "marketing",
        "sale",
        "direct"
    ],
    "wof:name":"Garage Sales Galore",
    "wof:placetype":"venue"
},
  "geometry": {"coordinates":[-121.31883999999999,44.069117],"type":"Point"}
}