{
  "type": "Feature",
  "properties": {
    "iso:country":"US",
    "sg:address":"436 1st St",
    "sg:city":"Lake Oswego",
    "sg:classifiers":[
        {
            "category":"Health Services",
            "subcategory":"Chiropractor",
            "type":"Services"
        }
    ],
    "sg:phone":"+1 971 204 0034",
    "sg:postcode":"97034",
    "sg:province":"OR",
    "wof:name":"Marshall Family Chiropractic",
    "wof:placetype":"venue"
},
  "geometry": {"coordinates":[-122.664098,45.420195],"type":"Point"}
}