{
  "type": "Feature",
  "properties": {
    "addr:full":"315 Brookside Dr Eugene OR 97405",
    "addr:housenumber":"315",
    "addr:postcode":"97405",
    "addr:street":"Brookside Dr",
    "iso:country":"US",
    "sg:address":"315 Brookside Dr",
    "sg:city":"Eugene",
    "sg:classifiers":[
        {
            "category":"Professional",
            "subcategory":"Computer Services",
            "type":"Services"
        }
    ],
    "sg:phone":"+1 541 686 9084",
    "sg:postcode":"97405",
    "sg:province":"OR",
    "sg:tags":[
        "design",
        "system"
    ],
    "wof:name":"Eideashop",
    "wof:placetype":"venue"
},
  "geometry": {"coordinates":[-123.102214,44.004437],"type":"Point"}
}