{
  "type": "Feature",
  "properties": {
    "iso:country":"US",
    "sg:address":"483 S Immonen Rd",
    "sg:city":"Lincoln City",
    "sg:classifiers":[
        {
            "category":"Home & Garden",
            "subcategory":"Home Furnishings",
            "type":"Retail Goods"
        }
    ],
    "sg:phone":"+1 541 996 2415",
    "sg:postcode":"97367",
    "sg:province":"OR",
    "sg:tags":[
        "pottery"
    ],
    "wof:name":"Mossy Creek Pottery & Gallery",
    "wof:placetype":"venue"
},
  "geometry": {"coordinates":[-124.011769,44.887822],"type":"Point"}
}