{
  "type": "Feature",
  "properties": {
    "iso:country":"US",
    "sg:address":"8028 SW 166th Pl",
    "sg:city":"Beaverton",
    "sg:classifiers":[
        {
            "category":"Building & Trades",
            "subcategory":"Construction",
            "type":"Services"
        }
    ],
    "sg:phone":"+1 503 642 3717",
    "sg:postcode":"97007",
    "sg:province":"OR",
    "sg:tags":[
        "contractor"
    ],
    "wof:name":"Beaverton Fence & Deck",
    "wof:placetype":"venue"
},
  "geometry": {"coordinates":[-122.846006,45.462321],"type":"Point"}
}