{
  "type": "Feature",
  "properties": {
    "iso:country":"US",
    "sg:address":"240 NE Ogden Rd",
    "sg:city":"Troutdale",
    "sg:classifiers":[
        {
            "category":"Building & Trades",
            "subcategory":"Plumbing",
            "type":"Services"
        }
    ],
    "sg:phone":"+1 503 351 1904",
    "sg:postcode":"97060",
    "sg:province":"OR",
    "sg:tags":[
        "plumbing",
        "contractor"
    ],
    "wof:name":"Always Ready Plumbing",
    "wof:placetype":"venue"
},
  "geometry": {"coordinates":[-122.352104,45.525215],"type":"Point"}
}