{
  "type": "Feature",
  "properties": {
    "iso:country":"US",
    "sg:address":"10100 SW Youngberg Hill Rd",
    "sg:city":"Mcminnville",
    "sg:phone":"+1 503 472 6051",
    "sg:postcode":"97128",
    "sg:province":"OR",
    "sg:tags":[
        "farm",
        "field",
        "crop"
    ],
    "wof:name":"Dennis Hicks",
    "wof:placetype":"venue"
},
  "geometry": {"coordinates":[-123.272323,45.184797],"type":"Point"}
}