{
  "type": "Feature",
  "properties": {
    "addr:full":"130 NE Exchange Ave Roseburg OR 97470",
    "addr:housenumber":"130",
    "addr:postcode":"97470",
    "addr:street":"Ne Exchange Ave",
    "iso:country":"US",
    "sg:address":"130 NE Exchange Ave",
    "sg:city":"Roseburg",
    "sg:classifiers":[
        {
            "category":"Shopping",
            "type":"Retail Goods"
        },
        {
            "category":"Museum",
            "type":"Entertainment"
        }
    ],
    "sg:phone":"+1 541 672 2180",
    "sg:postcode":"97470",
    "sg:province":"OR",
    "sg:tags":[
        "art",
        "gallery",
        "dealer"
    ],
    "wof:name":"Lizard Prints Fine Art Gallery",
    "wof:placetype":"venue"
},
  "geometry": {"coordinates":[-123.353899,43.236739],"type":"Point"}
}