{
  "type": "Feature",
  "properties": {
    "iso:country":"US",
    "sg:address":"67924 Nehalem Hwy N",
    "sg:city":"Vernonia",
    "sg:classifiers":[
        {
            "category":"Farming",
            "subcategory":"Farm",
            "type":"Manufacturing & Wholesale Goods"
        }
    ],
    "sg:phone":"+1 503 429 5085",
    "sg:postcode":"97064",
    "sg:province":"OR",
    "sg:tags":[
        "crop",
        "general"
    ],
    "wof:name":"Heaven On Earth Farms",
    "wof:placetype":"venue"
},
  "geometry": {"coordinates":[-123.230664,45.980899],"type":"Point"}
}