{
  "type": "Feature",
  "properties": {
    "iso:country":"US",
    "sg:address":"1001 NE 18th St",
    "sg:city":"Mcminnville",
    "sg:phone":"+1 503 472 7822",
    "sg:postcode":"97128",
    "sg:province":"OR",
    "sg:tags":[
        "farm",
        "wheat"
    ],
    "wof:name":"Clarke & Diane Ellingson Farm",
    "wof:placetype":"venue"
},
  "geometry": {"coordinates":[-123.18780099999999,45.221057],"type":"Point"}
}