{
  "type": "Feature",
  "properties": {
    "addr:full":"1037 SW 5th Ave Ontario OR 97914",
    "addr:housenumber":"1037",
    "addr:postcode":"97914",
    "addr:street":"Sw 5Th Ave",
    "iso:country":"US",
    "sg:address":"1037 SW 5th Ave",
    "sg:city":"Ontario",
    "sg:classifiers":[
        {
            "category":"Health Services",
            "subcategory":"Doctor",
            "type":"Services"
        }
    ],
    "sg:phone":"+1 541 889 7277",
    "sg:postcode":"97914",
    "sg:province":"OR",
    "sg:tags":[
        "medical"
    ],
    "wof:name":"John H Phillips MD",
    "wof:placetype":"venue"
},
  "geometry": {"coordinates":[-116.97745399999999,44.024139],"type":"Point"}
}