{
  "type": "Feature",
  "properties": {
    "iso:country":"US",
    "sg:address":"626 US Hwy 26",
    "sg:city":"Ontario",
    "sg:classifiers":[
        {
            "category":"Professional",
            "subcategory":"Business Services",
            "type":"Services"
        }
    ],
    "sg:phone":"+1 541 889 5808",
    "sg:postcode":"97918",
    "sg:province":"OR",
    "sg:tags":[
        "auctioneer"
    ],
    "wof:name":"Baker Auction Co",
    "wof:placetype":"venue"
},
  "geometry": {"coordinates":[-117.235184,43.982744],"type":"Point"}
}