{
  "type": "Feature",
  "properties": {
    "addr:full":"13455 SW 2nd St Beaverton OR 97005",
    "addr:housenumber":"13455",
    "addr:postcode":"97005",
    "addr:street":"Sw 2Nd St",
    "iso:country":"US",
    "sg:address":"13455 SW 2nd St",
    "sg:city":"Beaverton",
    "sg:classifiers":[
        {
            "category":"Building & Trades",
            "subcategory":"Construction",
            "type":"Services"
        }
    ],
    "sg:phone":"+1 503 372 5122",
    "sg:postcode":"97005",
    "sg:province":"OR",
    "sg:tags":[
        "home",
        "builder"
    ],
    "wof:name":"Recovery Homes 1 Ts",
    "wof:placetype":"venue"
},
  "geometry": {"coordinates":[-122.81252499999999,45.486455],"type":"Point"}
}