{
  "type": "Feature",
  "properties": {
    "addr:full":"16306 SE Oatfield Rd Milwaukie OR 97267",
    "addr:postcode":"16306;97267",
    "addr:street":"Se Oatfield Rd",
    "iso:country":"US",
    "sg:address":"16306 SE Oatfield Rd",
    "sg:city":"Milwaukie",
    "sg:classifiers":[
        {
            "category":"Home & Garden",
            "subcategory":"Home Furnishings",
            "type":"Retail Goods"
        }
    ],
    "sg:phone":"+1 503 653 5044",
    "sg:postcode":"97267",
    "sg:province":"OR",
    "sg:tags":[
        "curtain",
        "made",
        "drapery"
    ],
    "wof:name":"Custom Drapery Creations",
    "wof:placetype":"venue"
},
  "geometry": {"coordinates":[-122.612495,45.404775],"type":"Point"}
}