{
  "type": "Feature",
  "properties": {
    "addr:full":"4315 Mill St Eugene OR 97405",
    "addr:housenumber":"4315",
    "addr:postcode":"97405",
    "addr:street":"Mill St",
    "iso:country":"US",
    "sg:address":"4315 Mill St",
    "sg:city":"Eugene",
    "sg:classifiers":[
        {
            "category":"Social Services",
            "subcategory":"Child Care",
            "type":"Services"
        }
    ],
    "sg:phone":"+1 541 485 2970",
    "sg:postcode":"97405",
    "sg:province":"OR",
    "sg:tags":[
        "day"
    ],
    "wof:name":"Jans Pre School",
    "wof:placetype":"venue"
},
  "geometry": {"coordinates":[-123.08966599999999,44.006319],"type":"Point"}
}