{
  "type": "Feature",
  "properties": {
    "iso:country":"US",
    "sg:address":"405 NE 3rd St Ste 7",
    "sg:city":"Mcminnville",
    "sg:classifiers":[
        {
            "category":"Insurance",
            "subcategory":"Hazard Insurance",
            "type":"Services"
        }
    ],
    "sg:phone":"+1 503 472 8071",
    "sg:postcode":"97128",
    "sg:province":"OR",
    "sg:tags":[
        "commercial",
        "business"
    ],
    "wof:name":"Davidson Insurance",
    "wof:placetype":"venue"
},
  "geometry": {"coordinates":[-123.195562,45.210011],"type":"Point"}
}