{
  "type": "Feature",
  "properties": {
    "addr:full":"13531 Clairmont Way Oregon City OR 97045",
    "addr:housenumber":"13531",
    "addr:postcode":"97045",
    "addr:street":"Clairmont Way",
    "iso:country":"US",
    "sg:address":"13531 Clairmont Way",
    "sg:city":"Oregon City",
    "sg:classifiers":[
        {
            "category":"Building & Trades",
            "subcategory":"Plumbing",
            "type":"Services"
        }
    ],
    "sg:phone":"+1 503 283 8998",
    "sg:postcode":"97045",
    "sg:province":"OR",
    "sg:tags":[
        "septic"
    ],
    "wof:name":"Rooter Chief",
    "wof:placetype":"venue"
},
  "geometry": {"coordinates":[-122.58806199999999,45.329968],"type":"Point"}
}