{
  "type": "Feature",
  "properties": {
    "addr:full":"16285 SW 85th Ave Portland OR 97224",
    "addr:housenumber":"16285",
    "addr:postcode":"97224",
    "addr:street":"Sw 85Th Ave",
    "iso:country":"US",
    "sg:address":"16285 SW 85th Ave",
    "sg:city":"Portland",
    "sg:classifiers":[
        {
            "category":"Shopping",
            "subcategory":"Books",
            "type":"Retail Goods"
        }
    ],
    "sg:phone":"+1 503 620 2138",
    "sg:postcode":"97224",
    "sg:province":"OR",
    "sg:tags":[
        "bookstore"
    ],
    "sg:website":"www.monergismbooks.com",
    "wof:name":"Monergism Books",
    "wof:placetype":"venue"
},
  "geometry": {"coordinates":[-122.764741,45.402695],"type":"Point"}
}