{
  "type": "Feature",
  "properties": {
    "iso:country":"US",
    "sg:address":"68170 Nehalem Hwy N",
    "sg:city":"Vernonia",
    "sg:classifiers":[
        {
            "category":"Freight",
            "type":"Transportation"
        }
    ],
    "sg:phone":"+1 503 755 2473",
    "sg:postcode":"97064",
    "sg:province":"OR",
    "sg:tags":[
        "operator",
        "trucking"
    ],
    "wof:name":"L J Christophersen",
    "wof:placetype":"venue"
},
  "geometry": {"coordinates":[-123.240061,45.983565],"type":"Point"}
}