{
  "type": "Feature",
  "properties": {
    "iso:country":"US",
    "sg:address":"1969 NW Admiralty Cir",
    "sg:city":"Waldport",
    "sg:classifiers":[
        {
            "category":"Building & Trades",
            "subcategory":"Construction",
            "type":"Services"
        }
    ],
    "sg:phone":"+1 541 961 5285",
    "sg:postcode":"97394",
    "sg:province":"OR",
    "sg:tags":[
        "wallcoverings-installation",
        "wallpaper",
        "painting",
        "contractor"
    ],
    "wof:name":"Justin Walters Painting",
    "wof:placetype":"venue"
},
  "geometry": {"coordinates":[-124.080524,44.433072],"type":"Point"}
}