{
  "type": "Feature",
  "properties": {
    "addr:full":"27006 SE Stark St Troutdale OR 97060",
    "addr:postcode":"27006;97060",
    "addr:street":"Se Stark St",
    "iso:country":"US",
    "sg:address":"27006 SE Stark St",
    "sg:city":"Troutdale",
    "sg:classifiers":[
        {
            "category":"Retail",
            "subcategory":"Laundry & Dry Cleaning",
            "type":"Services"
        }
    ],
    "sg:phone":"+1 503 669 4911",
    "sg:postcode":"97060",
    "sg:province":"OR",
    "sg:tags":[
        "drycleaning",
        "plant"
    ],
    "wof:name":"Symphony Dry Cleaners",
    "wof:placetype":"venue"
},
  "geometry": {"coordinates":[-122.383641,45.518959],"type":"Point"}
}