{
  "type": "Feature",
  "properties": {
    "iso:country":"US",
    "sg:address":"540 SW 11th St",
    "sg:city":"Hermiston",
    "sg:classifiers":[
        {
            "category":"Health Services",
            "subcategory":"Doctor",
            "type":"Services"
        }
    ],
    "sg:phone":"+1 541 567 2662",
    "sg:postcode":"97838",
    "sg:province":"OR",
    "sg:tags":[
        "dentist"
    ],
    "wof:name":"Durk V Irwin DDS",
    "wof:placetype":"venue"
},
  "geometry": {"coordinates":[-119.31107,45.836795],"type":"Point"}
}