{
  "type": "Feature",
  "properties": {
    "iso:country":"US",
    "sg:address":"354 NE Greenwood Ave",
    "sg:city":"Bend",
    "sg:classifiers":[
        {
            "category":"Wholesale",
            "subcategory":"Construction Materials",
            "type":"Manufacturing & Wholesale Goods"
        }
    ],
    "sg:phone":"+1 541 382 2400",
    "sg:postcode":"97701",
    "sg:province":"OR",
    "wof:name":"Spectrum Hardwoods",
    "wof:placetype":"venue"
},
  "geometry": {"coordinates":[-121.301689,44.060016],"type":"Point"}
}