{
  "type": "Feature",
  "properties": {
    "addr:full":"535 NW 11th Ave Portland OR 97209",
    "addr:housenumber":"535",
    "addr:postcode":"97209",
    "addr:street":"Nw 11Th Ave",
    "iso:country":"US",
    "sg:address":"535 NW 11th Ave",
    "sg:city":"Portland",
    "sg:classifiers":[
        {
            "category":"Retail",
            "subcategory":"Auto Repair",
            "type":"Services"
        }
    ],
    "sg:phone":"+1 503 224 6106",
    "sg:postcode":"97209",
    "sg:province":"OR",
    "sg:tags":[
        "body",
        "automobile",
        "painting"
    ],
    "sg:website":"www.jimstevensautobody.com",
    "wof:name":"Jim Stevens Auto Body",
    "wof:placetype":"venue"
},
  "geometry": {"coordinates":[-122.68226199999999,45.526777],"type":"Point"}
}