{
  "type": "Feature",
  "properties": {
    "iso:country":"US",
    "sg:address":"833 SW 30th St",
    "sg:city":"Ontario",
    "sg:classifiers":[
        {
            "category":"Manufacturing",
            "subcategory":"Tools & Machinery",
            "type":"Manufacturing & Wholesale Goods"
        }
    ],
    "sg:phone":"+1 541 889 8630",
    "sg:postcode":"97914",
    "sg:province":"OR",
    "sg:tags":[
        "fire",
        "equipment",
        "protection"
    ],
    "sg:website":"www.terra-torch.com",
    "wof:name":"Firecon",
    "wof:placetype":"venue"
},
  "geometry": {"coordinates":[-117.005454,44.020697],"type":"Point"}
}