{
  "type": "Feature",
  "properties": {
    "iso:country":"US",
    "sg:address":"4803 SE Woodstock Blvd",
    "sg:city":"Portland",
    "sg:classifiers":[
        {
            "category":"Freight",
            "type":"Transportation"
        }
    ],
    "sg:phone":"+1 503 542 4494",
    "sg:postcode":"97206",
    "sg:province":"OR",
    "sg:tags":[
        "shipping"
    ],
    "wof:name":"The UPS Store",
    "wof:placetype":"venue"
},
  "geometry": {"coordinates":[-122.613321,45.479335],"type":"Point"}
}