{
  "type": "Feature",
  "properties": {
    "iso:country":"US",
    "sg:address":"7720 SW Macadam Ave Apt 32A",
    "sg:city":"Portland",
    "sg:classifiers":[
        {
            "category":"Professional",
            "type":"Services"
        }
    ],
    "sg:phone":"+1 503 245 4181",
    "sg:postcode":"97219",
    "sg:province":"OR",
    "sg:tags":[
        "marine",
        "contractor"
    ],
    "wof:name":"Brouwer Enterprises",
    "wof:placetype":"venue"
},
  "geometry": {"coordinates":[-122.67076900000001,45.468121],"type":"Point"}
}