{
  "type": "Feature",
  "properties": {
    "addr:full":"401 4th St Phoenix OR 97535",
    "addr:housenumber":"401",
    "addr:postcode":"97535",
    "addr:street":"4Th St",
    "iso:country":"US",
    "sg:address":"401 4th St",
    "sg:city":"Phoenix",
    "sg:classifiers":[
        {
            "category":"Education",
            "subcategory":"School",
            "type":"Public Place"
        }
    ],
    "sg:phone":"+1 541 535 1511",
    "sg:postcode":"97535",
    "sg:province":"OR",
    "sg:tags":[
        "district"
    ],
    "sg:website":"http://policy.osba.org/phoenix/",
    "wof:name":"Phoenix-Talent School District",
    "wof:placetype":"venue"
},
  "geometry": {"coordinates":[-122.820503,42.27425],"type":"Point"}
}