{
  "type": "Feature",
  "properties": {
    "addr:full":"525 SW Broadway Portland OR 97205",
    "addr:housenumber":"525",
    "addr:postcode":"97205",
    "addr:street":"Sw Broadway",
    "iso:country":"US",
    "sg:address":"525 SW Broadway",
    "sg:city":"Portland",
    "sg:classifiers":[
        {
            "category":"Shopping",
            "subcategory":"Florist",
            "type":"Retail Goods"
        }
    ],
    "sg:phone":"+1 503 227 6454",
    "sg:postcode":"97205",
    "sg:province":"OR",
    "wof:name":"Dorcas Flowers",
    "wof:placetype":"venue"
},
  "geometry": {"coordinates":[-122.679018,45.520516],"type":"Point"}
}