{
  "type": "Feature",
  "properties": {
    "addr:full":"536 Bond St Astoria OR 97103",
    "addr:housenumber":"536",
    "addr:postcode":"97103",
    "addr:street":"Bond St",
    "iso:country":"US",
    "sg:address":"536 Bond St",
    "sg:city":"Astoria",
    "sg:classifiers":[
        {
            "category":"Professional",
            "subcategory":"Lawyer & Legal Services",
            "type":"Services"
        }
    ],
    "sg:phone":"+1 503 325 5137",
    "sg:postcode":"97103",
    "sg:province":"OR",
    "wof:name":"Elizbeth A Baldwin",
    "wof:placetype":"venue"
},
  "geometry": {"coordinates":[-123.837388,46.189891],"type":"Point"}
}