{
  "type": "Feature",
  "properties": {
    "iso:country":"US",
    "sg:address":"530 Kourt Dr",
    "sg:city":"Eugene",
    "sg:classifiers":[
        {
            "category":"Manufacturing",
            "subcategory":"Toys & Sporting Goods",
            "type":"Manufacturing & Wholesale Goods"
        }
    ],
    "sg:phone":"+1 541 689 1609",
    "sg:postcode":"97404",
    "sg:province":"OR",
    "sg:tags":[
        "juggling",
        "mfg"
    ],
    "wof:name":"Further Realms of Fun",
    "wof:placetype":"venue"
},
  "geometry": {"coordinates":[-123.135751,44.092626],"type":"Point"}
}