{
  "type": "Feature",
  "properties": {
    "addr:full":"18191 Fobert Rd NE Hubbard OR 97032",
    "addr:postcode":"18191;97032",
    "addr:street":"Fobert Rd Ne",
    "iso:country":"US",
    "sg:address":"18191 Fobert Rd NE",
    "sg:city":"Hubbard",
    "sg:classifiers":[
        {
            "category":"Home & Garden",
            "subcategory":"Building Materials",
            "type":"Retail Goods"
        },
        {
            "category":"Retail",
            "subcategory":"Auto Repair",
            "type":"Services"
        }
    ],
    "sg:phone":"+1 503 209 0680",
    "sg:postcode":"97032",
    "sg:province":"OR",
    "sg:tags":[
        "electric",
        "supply",
        "contractor",
        "equipment",
        "electrical",
        "automation"
    ],
    "wof:name":"Creation Electric Inc",
    "wof:placetype":"venue"
},
  "geometry": {"coordinates":[-122.76514299999999,45.185828],"type":"Point"}
}