{
  "type": "Feature",
  "properties": {
    "iso:country":"US",
    "sg:address":"1007 S Pacific Hwy",
    "sg:city":"Talent",
    "sg:classifiers":[
        {
            "category":"Shopping",
            "subcategory":"Florist",
            "type":"Retail Goods"
        }
    ],
    "sg:phone":"+1 541 535 6582",
    "sg:postcode":"97540",
    "sg:province":"OR",
    "wof:name":"Kathys Flowers & Songs",
    "wof:placetype":"venue"
},
  "geometry": {"coordinates":[-122.770808,42.238005],"type":"Point"}
}