{
  "type": "Feature",
  "properties": {
    "addr:full":"10428 SE Stark St Portland OR 97216",
    "addr:housenumber":"10428",
    "addr:postcode":"97216",
    "addr:street":"Se Stark St",
    "iso:country":"US",
    "sg:address":"10428 SE Stark St",
    "sg:city":"Portland",
    "sg:classifiers":[
        {
            "category":"Restaurant",
            "type":"Food & Drink"
        }
    ],
    "sg:menulink":"http://www.allmenus.com/or/portland/6858-dennys/menu/",
    "sg:phone":"+1 503 254 8460",
    "sg:postcode":"97216",
    "sg:province":"OR",
    "sg:tags":[
        "american",
        "diner"
    ],
    "wof:name":"Denny's",
    "wof:placetype":"venue"
},
  "geometry": {"coordinates":[-122.556139,45.519029],"type":"Point"}
}