{
  "type": "Feature",
  "properties": {
    "iso:country":"US",
    "sg:address":"15830 SE 114th Ave",
    "sg:city":"Clackamas",
    "sg:classifiers":[
        {
            "category":"Wholesale",
            "subcategory":"Machinery & Supplies",
            "type":"Manufacturing & Wholesale Goods"
        }
    ],
    "sg:phone":"+1 503 655 4453",
    "sg:postcode":"97015",
    "sg:province":"OR",
    "sg:tags":[
        "equipment",
        "industrial",
        "valve"
    ],
    "sg:website":"http://www.tempressinc.com",
    "wof:name":"Tempress Associates, Inc.",
    "wof:placetype":"venue"
},
  "geometry": {"coordinates":[-122.546313,45.408067],"type":"Point"}
}