{
  "type": "Feature",
  "properties": {
    "iso:country":"US",
    "sg:address":"8111 NE Holman St",
    "sg:city":"Portland",
    "sg:classifiers":[
        {
            "category":"Education",
            "subcategory":"University",
            "type":"Public Place"
        }
    ],
    "sg:phone":"+1 503 256 7300",
    "sg:postcode":"97218",
    "sg:province":"OR",
    "sg:tags":[
        "college"
    ],
    "sg:website":"www.depthofdesign.com/nwcoc.com",
    "wof:name":"Northwest College of Construction",
    "wof:placetype":"venue"
},
  "geometry": {"coordinates":[-122.579088,45.568417],"type":"Point"}
}