{
  "type": "Feature",
  "properties": {
    "iso:country":"US",
    "sg:address":"754 Olive St",
    "sg:city":"Eugene",
    "sg:classifiers":[
        {
            "category":"Professional",
            "subcategory":"Business Services",
            "type":"Services"
        }
    ],
    "sg:phone":"+1 541 484 5307",
    "sg:postcode":"97401",
    "sg:province":"OR",
    "sg:tags":[
        "convention",
        "meeting",
        "facility"
    ],
    "sg:website":"www.visitlanecounty.org",
    "wof:name":"Convention & Visitors Assn",
    "wof:placetype":"venue"
},
  "geometry": {"coordinates":[-123.094342,44.051068],"type":"Point"}
}