{
  "type": "Feature",
  "properties": {
    "addr:full":"3168 NW 185th Ave Portland OR 97229",
    "addr:housenumber":"3168",
    "addr:postcode":"97229",
    "addr:street":"Nw 185Th Ave",
    "iso:country":"US",
    "sg:address":"3168 NW 185th Ave",
    "sg:city":"Portland",
    "sg:classifiers":[
        {
            "category":"Ice Cream",
            "type":"Food & Drink"
        }
    ],
    "sg:phone":"+1 503 690 8439",
    "sg:postcode":"97229",
    "sg:province":"OR",
    "sg:tags":[
        "frozen",
        "yogurt"
    ],
    "wof:name":"Teriyaki Bowl",
    "wof:placetype":"venue"
},
  "geometry": {"coordinates":[-122.866997,45.545601],"type":"Point"}
}