{
  "type": "Feature",
  "properties": {
    "addr:full":"2326 NW Everett St Portland OR 97210",
    "addr:housenumber":"2326",
    "addr:postcode":"97210",
    "addr:street":"Nw Everett St",
    "iso:country":"US",
    "sg:address":"2326 NW Everett St",
    "sg:city":"Portland",
    "sg:classifiers":[
        {
            "category":"Wholesale",
            "subcategory":"Medical Equipment & Supplies",
            "type":"Manufacturing & Wholesale Goods"
        }
    ],
    "sg:phone":"+1 503 223 2333",
    "sg:postcode":"97210",
    "sg:province":"OR",
    "sg:tags":[
        "podiatrist",
        "instrument"
    ],
    "sg:website":"http://www.semlertechnologies.com",
    "wof:name":"Advanced Vascular Dynamics",
    "wof:placetype":"venue"
},
  "geometry": {"coordinates":[-122.698773,45.524804],"type":"Point"}
}