{
  "type": "Feature",
  "properties": {
    "iso:country":"US",
    "sg:address":"6947 Stayton Rd SE",
    "sg:city":"Turner",
    "sg:classifiers":[
        {
            "category":"Building & Trades",
            "subcategory":"Construction",
            "type":"Services"
        }
    ],
    "sg:phone":"+1 503 769 7695",
    "sg:postcode":"97392",
    "sg:province":"OR",
    "sg:tags":[
        "contractor"
    ],
    "wof:name":"B & K Construction",
    "wof:placetype":"venue"
},
  "geometry": {"coordinates":[-122.918663,44.749983],"type":"Point"}
}