{
  "type": "Feature",
  "properties": {
    "iso:country":"US",
    "sg:address":"555 NE Revere Ave",
    "sg:city":"Bend",
    "sg:classifiers":[
        {
            "category":"Shopping",
            "subcategory":"Computers & Home Electronics",
            "type":"Retail Goods"
        }
    ],
    "sg:phone":"+1 541 382 7178",
    "sg:postcode":"97701",
    "sg:province":"OR",
    "sg:tags":[
        "equipment",
        "audio-visual"
    ],
    "wof:name":"Northwest Audio Competitions",
    "wof:placetype":"venue"
},
  "geometry": {"coordinates":[-121.297999,44.06765],"type":"Point"}
}