{
  "type": "Feature",
  "properties": {
    "iso:country":"US",
    "sg:address":"2654 US Hwy 101",
    "sg:city":"Lincoln City",
    "sg:classifiers":[
        {
            "category":"Home & Garden",
            "subcategory":"Building Materials",
            "type":"Retail Goods"
        },
        {
            "category":"Building & Trades",
            "subcategory":"Construction",
            "type":"Services"
        }
    ],
    "sg:phone":"+1 541 994 4442",
    "sg:postcode":"97367",
    "sg:province":"OR",
    "sg:tags":[
        "windows",
        "glass",
        "glazing",
        "contractor"
    ],
    "wof:name":"All Ways Glass Inc",
    "wof:placetype":"venue"
},
  "geometry": {"coordinates":[-124.00712900000001,44.984419],"type":"Point"}
}