{
  "type": "Feature",
  "properties": {
    "iso:country":"US",
    "sg:address":"212 Front St",
    "sg:city":"Gaston",
    "sg:classifiers":[
        {
            "category":"Place Of Worship",
            "type":"Public Place"
        },
        {
            "category":"Organizations",
            "subcategory":"Religious Organization",
            "type":"Services"
        }
    ],
    "sg:phone":"+1 503 985 3351",
    "sg:postcode":"97119",
    "sg:province":"OR",
    "sg:tags":[
        "church"
    ],
    "wof:name":"Wapato Valley Church",
    "wof:placetype":"venue"
},
  "geometry": {"coordinates":[-123.139816,45.437088],"type":"Point"}
}