{
  "type": "Feature",
  "properties": {
    "addr:full":"1108 NW Van Buren Ave Corvallis OR 97330",
    "addr:housenumber":"1108",
    "addr:postcode":"97330",
    "addr:street":"Nw Van Buren Ave",
    "iso:country":"US",
    "sg:address":"1108 NW Van Buren Ave",
    "sg:city":"Corvallis",
    "sg:classifiers":[
        {
            "category":"Personal",
            "type":"Services"
        }
    ],
    "sg:phone":"+1 541 738 0830",
    "sg:postcode":"97330",
    "sg:province":"OR",
    "sg:tags":[
        "tattoo",
        "parlor"
    ],
    "wof:name":"Permagrfix Tttoos Bdy Piercing",
    "wof:placetype":"venue"
},
  "geometry": {"coordinates":[-123.26934,44.568638],"type":"Point"}
}