{
  "type": "Feature",
  "properties": {
    "addr:full":"160 NW 25th St Newport OR 97365",
    "addr:housenumber":"160",
    "addr:postcode":"97365",
    "addr:street":"Nw 25Th St",
    "iso:country":"US",
    "sg:address":"160 NW 25th St",
    "sg:city":"Newport",
    "sg:classifiers":[
        {
            "category":"Shopping",
            "subcategory":"Department Store",
            "type":"Retail Goods"
        }
    ],
    "sg:phone":"+1 541 265 6560",
    "sg:postcode":"97365",
    "sg:province":"OR",
    "sg:tags":[
        "discount"
    ],
    "sg:website":"www.walmart.com",
    "wof:name":"Wal-Mart",
    "wof:placetype":"venue"
},
  "geometry": {"coordinates":[-124.054954,44.654627],"type":"Point"}
}