{
  "type": "Feature",
  "properties": {
    "addr:full":"1220 SW 5th Ave Portland OR 97204",
    "addr:housenumber":"1220",
    "addr:postcode":"97204",
    "addr:street":"Sw 5Th Ave",
    "iso:country":"US",
    "sg:address":"1220 SW 5th Ave",
    "sg:city":"Portland",
    "sg:classifiers":[
        {
            "category":"Government",
            "subcategory":"Office",
            "type":"Public Place"
        }
    ],
    "sg:phone":"+1 503 823 4572",
    "sg:postcode":"97204",
    "sg:province":"OR",
    "sg:tags":[
        "village"
    ],
    "wof:name":"Portland International Rltns",
    "wof:placetype":"venue"
},
  "geometry": {"coordinates":[-122.67962799999999,45.514913],"type":"Point"}
}