{
  "type": "Feature",
  "properties": {
    "iso:country":"US",
    "sg:address":"1951 Redwood Ave",
    "sg:city":"Grants Pass",
    "sg:classifiers":[
        {
            "category":"Social Services",
            "subcategory":"Child Care",
            "type":"Services"
        }
    ],
    "sg:phone":"+1 541 472 1388",
    "sg:postcode":"97527",
    "sg:province":"OR",
    "sg:tags":[
        "day"
    ],
    "wof:name":"Grace Pre School",
    "wof:placetype":"venue"
},
  "geometry": {"coordinates":[-123.365272,42.422344],"type":"Point"}
}