{
  "type": "Feature",
  "properties": {
    "iso:country":"US",
    "sg:address":"590 NE Cherry Hill Rd",
    "sg:city":"Sheridan",
    "sg:classifiers":[
        {
            "category":"Manufacturing",
            "subcategory":"Lumber",
            "type":"Manufacturing & Wholesale Goods"
        }
    ],
    "sg:phone":"+1 503 843 2714",
    "sg:postcode":"97378",
    "sg:province":"OR",
    "sg:tags":[
        "fire",
        "forest"
    ],
    "wof:name":"Brenda Bttrfield Lookout Contr",
    "wof:placetype":"venue"
},
  "geometry": {"coordinates":[-123.38421700000001,45.103159],"type":"Point"}
}