{
  "type": "Feature",
  "properties": {
    "iso:country":"US",
    "sg:address":"19181 N Umpqua Hwy",
    "sg:city":"Glide",
    "sg:classifiers":[
        {
            "category":"Utilities",
            "subcategory":"Cable",
            "type":"Services"
        }
    ],
    "sg:phone":"+1 541 496 0515",
    "sg:postcode":"97443",
    "sg:province":"OR",
    "sg:tags":[
        "television"
    ],
    "wof:name":"Glide Cablevision",
    "wof:placetype":"venue"
},
  "geometry": {"coordinates":[-123.09336500000001,43.300198],"type":"Point"}
}