{
  "type": "Feature",
  "properties": {
    "addr:full":"1717 View Pl Medford OR 97504",
    "addr:housenumber":"1717",
    "addr:postcode":"97504",
    "addr:street":"View Pl",
    "iso:country":"US",
    "sg:address":"1717 View Pl",
    "sg:city":"Medford",
    "sg:classifiers":[
        {
            "category":"Personal",
            "type":"Services"
        }
    ],
    "sg:phone":"+1 541 779 6749",
    "sg:postcode":"97504",
    "sg:province":"OR",
    "wof:name":"Maryanne Harbison",
    "wof:placetype":"venue"
},
  "geometry": {"coordinates":[-122.860433,42.346807],"type":"Point"}
}