{
  "type": "Feature",
  "properties": {
    "addr:full":"754 Hopkins Rd Central Point OR 97502",
    "addr:housenumber":"754",
    "addr:postcode":"97502",
    "addr:street":"Hopkins Rd",
    "iso:country":"US",
    "sg:address":"754 Hopkins Rd",
    "sg:city":"Central Point",
    "sg:classifiers":[
        {
            "category":"Education",
            "subcategory":"Special Training",
            "type":"Public Place"
        }
    ],
    "sg:phone":"+1 541 664 3210",
    "sg:postcode":"97502",
    "sg:province":"OR",
    "sg:tags":[
        "tutoring"
    ],
    "wof:name":"Read Institute",
    "wof:placetype":"venue"
},
  "geometry": {"coordinates":[-122.902271,42.369778],"type":"Point"}
}