{
  "type": "Feature",
  "properties": {
    "addr:full":"26510 State Hwy 99 Monroe OR 97456",
    "addr:housenumber":"26510",
    "addr:postcode":"97456",
    "addr:street":"State Hwy 99",
    "iso:country":"US",
    "sg:address":"26510 State Hwy 99",
    "sg:city":"Monroe",
    "sg:classifiers":[
        {
            "category":"Farming",
            "subcategory":"Dairy Farm",
            "type":"Manufacturing & Wholesale Goods"
        }
    ],
    "sg:phone":"+1 541 847 5597",
    "sg:postcode":"97456",
    "sg:province":"OR",
    "wof:name":"Horning Brothers Dairy",
    "wof:placetype":"venue"
},
  "geometry": {"coordinates":[-123.29372100000001,44.353257],"type":"Point"}
}