{
  "type": "Feature",
  "properties": {
    "iso:country":"US",
    "sg:address":"18052 S Wesley Ln",
    "sg:city":"Oregon City",
    "sg:classifiers":[
        {
            "category":"Manufacturing",
            "subcategory":"Buildings",
            "type":"Manufacturing & Wholesale Goods"
        }
    ],
    "sg:phone":"+1 503 631 7473",
    "sg:postcode":"97045",
    "sg:province":"OR",
    "sg:tags":[
        "home",
        "restoration",
        "log"
    ],
    "wof:name":"Exterior Woodcare",
    "wof:placetype":"venue"
},
  "geometry": {"coordinates":[-122.499573,45.343145],"type":"Point"}
}