{
  "type": "Feature",
  "properties": {
    "addr:full":"1165 Newmark Ave Coos Bay OR 97420",
    "addr:housenumber":"1165",
    "addr:postcode":"97420",
    "addr:street":"Newmark Ave",
    "iso:country":"US",
    "sg:address":"1165 Newmark Ave",
    "sg:city":"Coos Bay",
    "sg:classifiers":[
        {
            "category":"Personal",
            "subcategory":"Beauty Salon",
            "type":"Services"
        }
    ],
    "sg:phone":"+1 541 888 0355",
    "sg:postcode":"97420",
    "sg:province":"OR",
    "wof:name":"Hair Creations",
    "wof:placetype":"venue"
},
  "geometry": {"coordinates":[-124.26747,43.391673],"type":"Point"}
}