{
  "type": "Feature",
  "properties": {
    "iso:country":"US",
    "sg:address":"233 S Main St",
    "sg:city":"Pendleton",
    "sg:classifiers":[
        {
            "category":"Shopping",
            "subcategory":"Clothing, Apparel, & Fashions",
            "type":"Retail Goods"
        }
    ],
    "sg:phone":"+1 541 278 1404",
    "sg:postcode":"97801",
    "sg:province":"OR",
    "sg:tags":[
        "western"
    ],
    "sg:website":"www.redsclothingco.com",
    "wof:name":"Red's Clothing Co",
    "wof:placetype":"venue"
},
  "geometry": {"coordinates":[-118.787389,45.672305],"type":"Point"}
}