{
  "type": "Feature",
  "properties": {
    "addr:full":"504 E 9th St Newberg OR 97132",
    "addr:housenumber":"504",
    "addr:postcode":"97132",
    "addr:street":"E 9Th St",
    "iso:country":"US",
    "sg:address":"504 E 9th St",
    "sg:city":"Newberg",
    "sg:classifiers":[
        {
            "category":"Retail",
            "subcategory":"Repair Shop",
            "type":"Services"
        }
    ],
    "sg:phone":"+1 503 554 5983",
    "sg:postcode":"97132",
    "sg:province":"OR",
    "wof:name":"Orourke Cleaning",
    "wof:placetype":"venue"
},
  "geometry": {"coordinates":[-122.975179,45.292734],"type":"Point"}
}