{
  "type": "Feature",
  "properties": {
    "iso:country":"US",
    "sg:address":"9201 S Kraxberger Rd",
    "sg:city":"Canby",
    "sg:classifiers":[
        {
            "category":"Building & Trades",
            "subcategory":"Construction",
            "type":"Services"
        }
    ],
    "sg:phone":"+1 503 266 3184",
    "sg:postcode":"97013",
    "sg:province":"OR",
    "sg:tags":[
        "plating"
    ],
    "sg:website":"http://www.precisionmetalfinishing.net",
    "wof:name":"Precision Metal Finishing Inc",
    "wof:placetype":"venue"
},
  "geometry": {"coordinates":[-122.679401,45.226843],"type":"Point"}
}