{
  "type": "Feature",
  "properties": {
    "addr:full":"4712 SW California St Portland OR 97219",
    "addr:housenumber":"4712",
    "addr:postcode":"97219",
    "addr:street":"Sw California St",
    "iso:country":"US",
    "sg:address":"4712 SW California St",
    "sg:city":"Portland",
    "sg:classifiers":[
        {
            "category":"Building & Trades",
            "subcategory":"Locksmith",
            "type":"Services"
        }
    ],
    "sg:phone":"+1 503 899 4108",
    "sg:postcode":"97219",
    "sg:province":"OR",
    "sg:tags":[
        "key"
    ],
    "wof:name":"A A A Locksmith A 24 Hour",
    "wof:placetype":"venue"
},
  "geometry": {"coordinates":[-122.724329,45.474919],"type":"Point"}
}