{
  "type": "Feature",
  "properties": {
    "iso:country":"US",
    "sg:address":"88266 Huston Rd",
    "sg:city":"Veneta",
    "sg:classifiers":[
        {
            "category":"Retail",
            "subcategory":"Storage",
            "type":"Services"
        }
    ],
    "sg:phone":"+1 541 953 2015",
    "sg:postcode":"97487",
    "sg:province":"OR",
    "sg:tags":[
        "household",
        "commercial"
    ],
    "wof:name":"Emerald Secure Storage",
    "wof:placetype":"venue"
},
  "geometry": {"coordinates":[-123.33024,44.054466],"type":"Point"}
}