{
  "type": "Feature",
  "properties": {
    "iso:country":"US",
    "sg:address":"6125 SW Boundary St",
    "sg:city":"Portland",
    "sg:classifiers":[
        {
            "category":"Home & Garden",
            "subcategory":"Furniture",
            "type":"Retail Goods"
        }
    ],
    "sg:phone":"+1 503 245 5927",
    "sg:postcode":"97221",
    "sg:province":"OR",
    "sg:tags":[
        "store"
    ],
    "wof:name":"Golberg Pavel & Sofa",
    "wof:placetype":"venue"
},
  "geometry": {"coordinates":[-122.73967399999999,45.485835],"type":"Point"}
}