{
  "type": "Feature",
  "properties": {
    "addr:full":"175 S Danebo Ave Eugene OR 97402",
    "addr:housenumber":"175",
    "addr:postcode":"97402",
    "addr:street":"S Danebo Ave",
    "iso:country":"US",
    "sg:address":"175 S Danebo Ave",
    "sg:city":"Eugene",
    "sg:classifiers":[
        {
            "category":"Manufacturing",
            "subcategory":"Tools & Machinery",
            "type":"Manufacturing & Wholesale Goods"
        }
    ],
    "sg:phone":"+1 541 485 6059",
    "sg:postcode":"97402",
    "sg:province":"OR",
    "sg:tags":[
        "machine",
        "shop"
    ],
    "wof:name":"Harco Machine Inc",
    "wof:placetype":"venue"
},
  "geometry": {"coordinates":[-123.178258,44.057407],"type":"Point"}
}