{
  "type": "Feature",
  "properties": {
    "addr:full":"609 SW Washington St Portland OR 97205",
    "addr:housenumber":"609",
    "addr:postcode":"97205",
    "addr:street":"Sw Washington St",
    "iso:country":"US",
    "sg:address":"609 SW Washington St",
    "sg:city":"Portland",
    "sg:classifiers":[
        {
            "category":"Personal",
            "subcategory":"Barber",
            "type":"Services"
        }
    ],
    "sg:phone":"+1 503 467 4667",
    "sg:postcode":"97205",
    "sg:province":"OR",
    "sg:website":"www.y-chromebarbering.com",
    "wof:name":"Y-Chrome",
    "wof:placetype":"venue"
},
  "geometry": {"coordinates":[-122.6782,45.52053],"type":"Point"}
}