{
  "type": "Feature",
  "properties": {
    "addr:full":"502 W Main St Ste 102 Medford OR 97501",
    "addr:housenumber":"502",
    "addr:postcode":"97501",
    "addr:street":"W Main St Ste 102",
    "iso:country":"US",
    "sg:address":"502 W Main St Ste 102",
    "sg:city":"Medford",
    "sg:classifiers":[
        {
            "category":"Professional",
            "subcategory":"Lawyer & Legal Services",
            "type":"Services"
        }
    ],
    "sg:phone":"+1 541 772 1977",
    "sg:postcode":"97501",
    "sg:province":"OR",
    "sg:tags":[
        "litigation"
    ],
    "wof:name":"Huycke O'connor & Jarvis Llp",
    "wof:placetype":"venue"
},
  "geometry": {"coordinates":[-122.87799800000001,42.323799],"type":"Point"}
}