{
  "type": "Feature",
  "properties": {
    "iso:country":"US",
    "sg:address":"2460 SE Larkspur Ct",
    "sg:city":"Hillsboro",
    "sg:classifiers":[
        {
            "category":"Manufacturing",
            "subcategory":"Tools & Machinery",
            "type":"Manufacturing & Wholesale Goods"
        }
    ],
    "sg:phone":"+1 503 598 4357",
    "sg:postcode":"97123",
    "sg:province":"OR",
    "sg:tags":[
        "manufacture",
        "equipment",
        "electrical",
        "supply"
    ],
    "wof:name":"Ceo",
    "wof:placetype":"venue"
},
  "geometry": {"coordinates":[-122.957781,45.501182],"type":"Point"}
}