{
  "type": "Feature",
  "properties": {
    "addr:full":"6850 SE Savanna St Portland OR 97267",
    "addr:housenumber":"6850",
    "addr:postcode":"97267",
    "addr:street":"Se;St",
    "iso:country":"US",
    "sg:address":"6850 SE Savanna St",
    "sg:city":"Portland",
    "sg:phone":"+1 503 654 8969",
    "sg:postcode":"97267",
    "sg:province":"OR",
    "wof:name":"Pacific Northwest Locating",
    "wof:placetype":"venue"
},
  "geometry": {"coordinates":[-122.59285800000001,45.42159],"type":"Point"}
}