{
  "type": "Feature",
  "properties": {
    "iso:country":"US",
    "sg:address":"13815 SW Pacific Hwy Ste 100",
    "sg:city":"Portland",
    "sg:classifiers":[
        {
            "category":"Deli",
            "type":"Food & Drink"
        },
        {
            "category":"Food & Beverages",
            "subcategory":"Bakery",
            "type":"Retail Goods"
        }
    ],
    "sg:phone":"+1 503 670 1873",
    "sg:postcode":"97223",
    "sg:province":"OR",
    "sg:tags":[
        "sandwich"
    ],
    "wof:name":"Windfall Deli the",
    "wof:placetype":"venue"
},
  "geometry": {"coordinates":[-122.786266,45.419911],"type":"Point"}
}