{
  "type": "Feature",
  "properties": {
    "iso:country":"US",
    "sg:address":"28000 S Dryland Rd",
    "sg:city":"Canby",
    "sg:classifiers":[
        {
            "category":"Manufacturing",
            "subcategory":"Furniture",
            "type":"Manufacturing & Wholesale Goods"
        }
    ],
    "sg:phone":"+1 503 266 6275",
    "sg:postcode":"97013",
    "sg:province":"OR",
    "sg:tags":[
        "bedding",
        "supply"
    ],
    "wof:name":"Pine Creek Bedding Co",
    "wof:placetype":"venue"
},
  "geometry": {"coordinates":[-122.66118,45.201418],"type":"Point"}
}