{
  "type": "Feature",
  "properties": {
    "addr:full":"406 SE Rose St Roseburg OR 97470",
    "addr:housenumber":"406",
    "addr:postcode":"97470",
    "addr:street":"Se Rose St",
    "iso:country":"US",
    "sg:address":"406 SE Rose St",
    "sg:city":"Roseburg",
    "sg:classifiers":[
        {
            "category":"Food & Beverages",
            "subcategory":"Groceries & Convenience Stores",
            "type":"Retail Goods"
        }
    ],
    "sg:phone":"+1 541 672 6432",
    "sg:postcode":"97470",
    "sg:province":"OR",
    "sg:tags":[
        "grocer"
    ],
    "wof:name":"Safeway",
    "wof:placetype":"venue"
},
  "geometry": {"coordinates":[-123.343774,43.211075],"type":"Point"}
}