{
  "type": "Feature",
  "properties": {
    "iso:country":"US",
    "sg:address":"14060 SW Maverick Ct",
    "sg:city":"Beaverton",
    "sg:classifiers":[
        {
            "category":"Professional",
            "subcategory":"Business Services",
            "type":"Services"
        }
    ],
    "sg:phone":"+1 503 644 1027",
    "sg:postcode":"97008",
    "sg:province":"OR",
    "sg:tags":[
        "arbitration"
    ],
    "wof:name":"Gloria Bryen Mediation LLC",
    "wof:placetype":"venue"
},
  "geometry": {"coordinates":[-122.82184599999999,45.458811],"type":"Point"}
}