{
  "type": "Feature",
  "properties": {
    "iso:country":"US",
    "sg:address":"702 W 10th St",
    "sg:city":"The Dalles",
    "sg:classifiers":[
        {
            "category":"Professional",
            "subcategory":"Management & Consulting",
            "type":"Services"
        }
    ],
    "sg:phone":"+1 541 296 5560",
    "sg:postcode":"97058",
    "sg:province":"OR",
    "wof:name":"All World Brands",
    "wof:placetype":"venue"
},
  "geometry": {"coordinates":[-121.19720700000001,45.601068],"type":"Point"}
}