{
  "type": "Feature",
  "properties": {
    "addr:full":"11300 NE Halsey St Portland OR 97220",
    "addr:housenumber":"11300",
    "addr:postcode":"97220",
    "addr:street":"Ne Halsey St",
    "iso:country":"US",
    "sg:address":"11300 NE Halsey St",
    "sg:city":"Portland",
    "sg:classifiers":[
        {
            "category":"Professional",
            "subcategory":"Accounting & Tax Preparation",
            "type":"Services"
        }
    ],
    "sg:phone":"+1 503 257 9611",
    "sg:postcode":"97220",
    "sg:province":"OR",
    "sg:tags":[
        "accountant"
    ],
    "wof:name":"Corzatt Alan D CPA",
    "wof:placetype":"venue"
},
  "geometry": {"coordinates":[-122.545833,45.532975],"type":"Point"}
}