{
  "type": "Feature",
  "properties": {
    "addr:full":"18277 SW Boones Ferry Road Portland OR 97224",
    "addr:housenumber":"18277",
    "addr:postcode":"97224",
    "addr:street":"Sw Boones Ferry Road",
    "iso:country":"US",
    "sg:address":"18277 SW Boones Ferry Road",
    "sg:city":"Portland",
    "sg:classifiers":[
        {
            "category":"Professional",
            "subcategory":"Computer Services",
            "type":"Services"
        }
    ],
    "sg:phone":"+1 503 684 2200",
    "sg:postcode":"97224",
    "sg:province":"OR",
    "sg:tags":[
        "repair"
    ],
    "wof:name":"Cyberrep",
    "wof:placetype":"venue"
},
  "geometry": {"coordinates":[-122.757311,45.386638],"type":"Point"}
}