{
  "type": "Feature",
  "properties": {
    "iso:country":"US",
    "sg:address":"1349 Heritage Loop",
    "sg:city":"Stayton",
    "sg:classifiers":[
        {
            "category":"Professional",
            "type":"Services"
        }
    ],
    "sg:phone":"+1 503 769 3982",
    "sg:postcode":"97383",
    "sg:province":"OR",
    "wof:name":"Ixtapa Salem Inc",
    "wof:placetype":"venue"
},
  "geometry": {"coordinates":[-122.80553999999999,44.80258],"type":"Point"}
}