{
  "type": "Feature",
  "properties": {
    "addr:full":"923 S 55th Pl Springfield OR 97478",
    "addr:housenumber":"923",
    "addr:postcode":"97478",
    "addr:street":"S 55Th Pl",
    "iso:country":"US",
    "sg:address":"923 S 55th Pl",
    "sg:city":"Springfield",
    "sg:classifiers":[
        {
            "category":"Manufacturing",
            "subcategory":"Buildings",
            "type":"Manufacturing & Wholesale Goods"
        },
        {
            "category":"Building & Trades",
            "subcategory":"Construction",
            "type":"Services"
        }
    ],
    "sg:phone":"+1 541 469 6517",
    "sg:postcode":"97478",
    "sg:province":"OR",
    "sg:tags":[
        "home",
        "builder",
        "contractor"
    ],
    "wof:name":"Plane And Custom Construction",
    "wof:placetype":"venue"
},
  "geometry": {"coordinates":[-122.931296,44.038115],"type":"Point"}
}