{
  "type": "Feature",
  "properties": {
    "iso:country":"US",
    "sg:address":"706 Main St",
    "sg:city":"Oregon City",
    "sg:classifiers":[
        {
            "category":"Government",
            "subcategory":"Office",
            "type":"Public Place"
        }
    ],
    "sg:phone":"+1 503 657 4370",
    "sg:postcode":"97045",
    "sg:province":"OR",
    "sg:tags":[
        "executive"
    ],
    "wof:name":"Karen Brisbin",
    "wof:placetype":"venue"
},
  "geometry": {"coordinates":[-122.607935,45.35799],"type":"Point"}
}