{
  "type": "Feature",
  "properties": {
    "addr:full":"79828 Dodson Rd Tygh Valley OR 97063",
    "addr:housenumber":"79828",
    "addr:postcode":"97063",
    "addr:street":"Dodson Rd",
    "iso:country":"US",
    "sg:address":"79828 Dodson Rd",
    "sg:city":"Tygh Valley",
    "sg:classifiers":[
        {
            "category":"Organizations",
            "subcategory":"Community Association",
            "type":"Services"
        }
    ],
    "sg:phone":"+1 541 544 3371",
    "sg:postcode":"97063",
    "sg:province":"OR",
    "sg:tags":[
        "club"
    ],
    "wof:name":"3 Mile Archery Club",
    "wof:placetype":"venue"
},
  "geometry": {"coordinates":[-121.29057400000001,45.229792],"type":"Point"}
}