{
  "type": "Feature",
  "properties": {
    "iso:country":"US",
    "sg:address":"10350 SE Holgate Boulevard",
    "sg:city":"Portland",
    "sg:classifiers":[
        {
            "category":"Food & Beverages",
            "subcategory":"Groceries & Convenience Stores",
            "type":"Retail Goods"
        }
    ],
    "sg:phone":"+1 503 760 8027",
    "sg:postcode":"97266",
    "sg:province":"OR",
    "wof:name":"Plaid Pantry Markets",
    "wof:placetype":"venue"
},
  "geometry": {"coordinates":[-122.556347,45.489681],"type":"Point"}
}