{
  "type": "Feature",
  "properties": {
    "addr:full":"7625 SE McBride St Portland OR 97222",
    "addr:housenumber":"7625",
    "addr:postcode":"97222",
    "addr:street":"Se Mcbride St",
    "iso:country":"US",
    "sg:address":"7625 SE McBride St",
    "sg:city":"Portland",
    "sg:classifiers":[
        {
            "category":"Shopping",
            "subcategory":"Florist",
            "type":"Retail Goods"
        }
    ],
    "sg:phone":"+1 503 654 6049",
    "sg:postcode":"97222",
    "sg:province":"OR",
    "wof:name":"Joanie's Bloomers",
    "wof:placetype":"venue"
},
  "geometry": {"coordinates":[-122.581453,45.435721],"type":"Point"}
}