{
  "type": "Feature",
  "properties": {
    "iso:country":"US",
    "sg:address":"323 Hatton Ln",
    "sg:city":"Junction City",
    "sg:classifiers":[
        {
            "category":"Wholesale",
            "subcategory":"Auto Parts",
            "type":"Manufacturing & Wholesale Goods"
        }
    ],
    "sg:phone":"+1 541 998 6882",
    "sg:postcode":"97448",
    "sg:province":"OR",
    "wof:name":"Car Quest of Junction City",
    "wof:placetype":"venue"
},
  "geometry": {"coordinates":[-123.20394400000001,44.207363],"type":"Point"}
}