{
  "type": "Feature",
  "properties": {
    "addr:full":"250 Church St SE Salem OR 97301",
    "addr:housenumber":"250",
    "addr:postcode":"97301",
    "addr:street":"Church St Se",
    "iso:country":"US",
    "sg:address":"250 Church St SE",
    "sg:city":"Salem",
    "sg:classifiers":[
        {
            "category":"Banks & Credit Unions",
            "subcategory":"Investment Brokerage",
            "type":"Services"
        }
    ],
    "sg:phone":"+1 503 581 1511",
    "sg:postcode":"97301",
    "sg:province":"OR",
    "sg:tags":[
        "stock",
        "bond"
    ],
    "sg:website":"www.smithbarney.com",
    "wof:name":"Smith Barney",
    "wof:placetype":"venue"
},
  "geometry": {"coordinates":[-123.03632399999999,44.93769],"type":"Point"}
}