{
  "type": "Feature",
  "properties": {
    "addr:full":"6429 N Fork Siuslaw Rd Florence OR 97439",
    "addr:housenumber":"6429",
    "addr:postcode":"97439",
    "addr:street":"N;Siuslaw Rd",
    "iso:country":"US",
    "sg:address":"6429 N Fork Siuslaw Rd",
    "sg:city":"Florence",
    "sg:classifiers":[
        {
            "category":"Building & Trades",
            "subcategory":"Landscaping Services",
            "type":"Services"
        }
    ],
    "sg:phone":"+1 541 997 2977",
    "sg:postcode":"97439",
    "sg:province":"OR",
    "sg:tags":[
        "lawn",
        "maintenance"
    ],
    "wof:name":"Charlie Creek Environmental",
    "wof:placetype":"venue"
},
  "geometry": {"coordinates":[-124.060339,44.018661],"type":"Point"}
}