{
  "type": "Feature",
  "properties": {
    "iso:country":"US",
    "sg:address":"234 Laurel Dr",
    "sg:city":"Roseburg",
    "sg:classifiers":[
        {
            "category":"Professional",
            "subcategory":"Business Services",
            "type":"Services"
        }
    ],
    "sg:phone":"+1 541 672 5576",
    "sg:postcode":"97470",
    "sg:province":"OR",
    "wof:name":"Dittman Enterprises",
    "wof:placetype":"venue"
},
  "geometry": {"coordinates":[-123.423491,43.24018],"type":"Point"}
}