{
  "type": "Feature",
  "properties": {
    "iso:country":"US",
    "sg:address":"28925 SW Fernhollow Ln",
    "sg:city":"Hillsboro",
    "sg:classifiers":[
        {
            "category":"Professional",
            "subcategory":"Computer Services",
            "type":"Services"
        }
    ],
    "sg:phone":"+1 503 628 0643",
    "sg:postcode":"97123",
    "sg:province":"OR",
    "sg:tags":[
        "physical",
        "commercial",
        "related",
        "research"
    ],
    "wof:name":"Avsys Corporation",
    "wof:placetype":"venue"
},
  "geometry": {"coordinates":[-122.974017,45.390796],"type":"Point"}
}