{
  "type": "Feature",
  "properties": {
    "addr:full":"9644 SW Washington Square Road Portland OR 97223",
    "addr:housenumber":"9644",
    "addr:postcode":"97223",
    "addr:street":"Sw Washington Square Road",
    "iso:country":"US",
    "sg:address":"9644 SW Washington Square Road",
    "sg:city":"Portland",
    "sg:classifiers":[
        {
            "category":"Manufacturing",
            "subcategory":"Leather Goods",
            "type":"Manufacturing & Wholesale Goods"
        }
    ],
    "sg:phone":"+1 503 639 6020",
    "sg:postcode":"97223",
    "sg:province":"OR",
    "wof:name":"Brighton Collectables",
    "wof:placetype":"venue"
},
  "geometry": {"coordinates":[-122.78246799999999,45.447267],"type":"Point"}
}