{
  "type": "Feature",
  "properties": {
    "addr:full":"1904 2nd St Tillamook OR 97141",
    "addr:housenumber":"1904",
    "addr:postcode":"97141",
    "addr:street":"2Nd St",
    "iso:country":"US",
    "sg:address":"1904 2nd St",
    "sg:city":"Tillamook",
    "sg:classifiers":[
        {
            "category":"Professional",
            "subcategory":"Accounting & Tax Preparation",
            "type":"Services"
        }
    ],
    "sg:phone":"+1 503 842 7141",
    "sg:postcode":"97141",
    "sg:province":"OR",
    "sg:tags":[
        "return",
        "filing"
    ],
    "wof:name":"J L Steele's Taxes & Bkpg",
    "wof:placetype":"venue"
},
  "geometry": {"coordinates":[-123.844325,45.457139],"type":"Point"}
}