{
  "type": "Feature",
  "properties": {
    "iso:country":"US",
    "sg:address":"1308 Wallace Rd NW",
    "sg:city":"Salem",
    "sg:classifiers":[
        {
            "category":"Professional",
            "type":"Services"
        }
    ],
    "sg:phone":"+1 503 363 9379",
    "sg:postcode":"97304",
    "sg:province":"OR",
    "wof:name":"Kristy Boucher",
    "wof:placetype":"venue"
},
  "geometry": {"coordinates":[-123.052829,44.954613],"type":"Point"}
}