{
  "type": "Feature",
  "properties": {
    "iso:country":"US",
    "sg:address":"77684 State Hwy 99",
    "sg:city":"Cottage Grove",
    "sg:classifiers":[
        {
            "category":"Manufacturing",
            "subcategory":"Tools & Machinery",
            "type":"Manufacturing & Wholesale Goods"
        }
    ],
    "sg:phone":"+1 541 942 4491",
    "sg:postcode":"97424",
    "sg:province":"OR",
    "sg:tags":[
        "woodworking"
    ],
    "sg:website":"www.kimwood.com",
    "wof:name":"Kimwood Corp",
    "wof:placetype":"venue"
},
  "geometry": {"coordinates":[-123.079248,43.770025],"type":"Point"}
}