{
  "type": "Feature",
  "properties": {
    "iso:country":"US",
    "sg:address":"6933 N Lombard Street",
    "sg:city":"Portland",
    "sg:classifiers":[
        {
            "category":"Fast Food",
            "type":"Food & Drink"
        },
        {
            "category":"Restaurant",
            "type":"Food & Drink"
        }
    ],
    "sg:phone":"+1 503 289 7318",
    "sg:postcode":"97203",
    "sg:province":"OR",
    "sg:tags":[
        "dessert",
        "american",
        "take"
    ],
    "sg:website":"www.dairyqueen.com",
    "wof:name":"Dairy Queen",
    "wof:placetype":"venue"
},
  "geometry": {"coordinates":[-122.73898699999999,45.586952],"type":"Point"}
}