{
  "type": "Feature",
  "properties": {
    "addr:full":"75 NW 158th Ave Beaverton OR 97006",
    "addr:housenumber":"75",
    "addr:postcode":"97006",
    "addr:street":"Nw 158Th Ave",
    "iso:country":"US",
    "sg:address":"75 NW 158th Ave",
    "sg:city":"Beaverton",
    "sg:classifiers":[
        {
            "category":"Autos & Motor Vehicles",
            "subcategory":"Fuel & Gas Station",
            "type":"Retail Goods"
        }
    ],
    "sg:phone":"+1 503 531 0404",
    "sg:postcode":"97006",
    "sg:province":"OR",
    "sg:tags":[
        "oil"
    ],
    "wof:name":"Tosco Northwest Co",
    "wof:placetype":"venue"
},
  "geometry": {"coordinates":[-122.839675,45.518105],"type":"Point"}
}