{
  "type": "Feature",
  "properties": {
    "iso:country":"US",
    "sg:address":"835 NW Adams St",
    "sg:city":"Mcminnville",
    "sg:phone":"+1 503 474 1234",
    "sg:postcode":"97128",
    "sg:province":"OR",
    "sg:website":"http://www.windermerepcr.com",
    "wof:name":"Windemere Pacific Crest Realty",
    "wof:placetype":"venue"
},
  "geometry": {"coordinates":[-123.114285,45.246617],"type":"Point"}
}