{
  "type": "Feature",
  "properties": {
    "addr:full":"3135 Santiam Hwy SE Albany OR 97322",
    "addr:postcode":"3135;97322",
    "addr:street":"Santiam Hwy Se",
    "iso:country":"US",
    "sg:address":"3135 Santiam Hwy SE",
    "sg:city":"Albany",
    "sg:classifiers":[
        {
            "category":"Autos & Motor Vehicles",
            "subcategory":"Fuel & Gas Station",
            "type":"Retail Goods"
        }
    ],
    "sg:phone":"+1 541 908 3102",
    "sg:postcode":"97322",
    "sg:province":"OR",
    "sg:tags":[
        "gasoline"
    ],
    "wof:name":"Danny 76",
    "wof:placetype":"venue"
},
  "geometry": {"coordinates":[-123.066452,44.630624],"type":"Point"}
}