{
  "type": "Feature",
  "properties": {
    "iso:country":"US",
    "sg:address":"940 NE Circle Blvd",
    "sg:city":"Corvallis",
    "sg:classifiers":[
        {
            "category":"Professional",
            "type":"Services"
        }
    ],
    "sg:phone":"+1 541 752 8932",
    "sg:postcode":"97330",
    "sg:province":"OR",
    "sg:tags":[
        "establishment"
    ],
    "wof:name":"IDC",
    "wof:placetype":"venue"
},
  "geometry": {"coordinates":[-123.24795899999999,44.588838],"type":"Point"}
}