{
  "type": "Feature",
  "properties": {
    "iso:country":"US",
    "sg:address":"1237 Jantzen Beach Center",
    "sg:city":"Portland",
    "sg:classifiers":[
        {
            "category":"Shopping",
            "subcategory":"Jewelry",
            "type":"Retail Goods"
        }
    ],
    "sg:phone":"+1 503 285 6999",
    "sg:postcode":"97217",
    "sg:province":"OR",
    "sg:tags":[
        "jeweler"
    ],
    "wof:name":"Fred Meyer Jewelers",
    "wof:placetype":"venue"
},
  "geometry": {"coordinates":[-122.686801,45.613318],"type":"Point"}
}