{
  "type": "Feature",
  "properties": {
    "iso:country":"US",
    "sg:address":"3350 NW Helmholtz Way",
    "sg:city":"Redmond",
    "sg:classifiers":[
        {
            "category":"Farming",
            "subcategory":"Farm",
            "type":"Manufacturing & Wholesale Goods"
        }
    ],
    "sg:phone":"+1 541 548 8528",
    "sg:postcode":"97756",
    "sg:province":"OR",
    "sg:tags":[
        "crop",
        "general"
    ],
    "wof:name":"Windy Ridge Farm",
    "wof:placetype":"venue"
},
  "geometry": {"coordinates":[-121.219009,44.304787],"type":"Point"}
}