{
  "type": "Feature",
  "properties": {
    "iso:country":"US",
    "sg:address":"4955 SW Main Ave",
    "sg:city":"Beaverton",
    "sg:classifiers":[
        {
            "category":"Building & Trades",
            "subcategory":"Locksmith",
            "type":"Services"
        }
    ],
    "sg:phone":"+1 503 715 3870",
    "sg:postcode":"97005",
    "sg:province":"OR",
    "sg:tags":[
        "key"
    ],
    "wof:name":"Am Pm Locksmith",
    "wof:placetype":"venue"
},
  "geometry": {"coordinates":[-122.808899,45.484145],"type":"Point"}
}