{
  "type": "Feature",
  "properties": {
    "iso:country":"US",
    "sg:address":"155 Culver Ln S",
    "sg:city":"Salem",
    "sg:classifiers":[
        {
            "category":"Professional",
            "subcategory":"Lawyer & Legal Services",
            "type":"Services"
        }
    ],
    "sg:phone":"+1 503 371 3644",
    "sg:postcode":"97302",
    "sg:province":"OR",
    "sg:tags":[
        "attorney"
    ],
    "wof:name":"Elizabeth J Large",
    "wof:placetype":"venue"
},
  "geometry": {"coordinates":[-123.048169,44.915351],"type":"Point"}
}