{
  "type": "Feature",
  "properties": {
    "iso:country":"US",
    "sg:address":"3811 SE Gladstone St",
    "sg:city":"Portland",
    "sg:classifiers":[
        {
            "category":"Personal",
            "subcategory":"Barber",
            "type":"Services"
        }
    ],
    "sg:phone":"+1 503 517 0700",
    "sg:postcode":"97202",
    "sg:province":"OR",
    "wof:name":"Barber Dan's Gladstone Street Barber Shop",
    "wof:placetype":"venue"
},
  "geometry": {"coordinates":[-122.623377,45.493585],"type":"Point"}
}