{
  "type": "Feature",
  "properties": {
    "iso:country":"US",
    "sg:address":"99174 Winchuck River Rd",
    "sg:city":"Brookings",
    "sg:classifiers":[
        {
            "category":"Restaurant",
            "type":"Food & Drink"
        }
    ],
    "sg:phone":"+1 541 469 6706",
    "sg:postcode":"97415",
    "sg:province":"OR",
    "sg:tags":[
        "eating"
    ],
    "wof:name":"Coffee Breakers",
    "wof:placetype":"venue"
},
  "geometry": {"coordinates":[-124.211598,42.009097],"type":"Point"}
}