{
  "type": "Feature",
  "properties": {
    "addr:full":"9260 SE 74th Avenue Portland OR 97206",
    "addr:housenumber":"9260",
    "addr:postcode":"97206",
    "addr:street":"Se 74Th Avenue",
    "iso:country":"US",
    "sg:address":"9260 SE 74th Avenue",
    "sg:city":"Portland",
    "sg:classifiers":[
        {
            "category":"Retail",
            "subcategory":"Repair Shop",
            "type":"Services"
        }
    ],
    "sg:phone":"+1 503 775 1940",
    "sg:postcode":"97206",
    "sg:province":"OR",
    "sg:tags":[
        "reupholstery",
        "furniture"
    ],
    "wof:name":"Darrell Upholstery",
    "wof:placetype":"venue"
},
  "geometry": {"coordinates":[-122.588065,45.456188],"type":"Point"}
}