{
  "type": "Feature",
  "properties": {
    "iso:country":"US",
    "sg:address":"5606 SE Westfork St",
    "sg:city":"Portland",
    "sg:classifiers":[
        {
            "category":"Building & Trades",
            "subcategory":"Construction",
            "type":"Services"
        }
    ],
    "sg:phone":"+1 503 722 5267",
    "sg:postcode":"97206",
    "sg:province":"OR",
    "sg:tags":[
        "wallcoverings-installation",
        "wallpaper",
        "painting",
        "contractor"
    ],
    "wof:name":"Barrett Painting Inc",
    "wof:placetype":"venue"
},
  "geometry": {"coordinates":[-122.60569099999999,45.459586],"type":"Point"}
}