{
  "type": "Feature",
  "properties": {
    "addr:full":"10147 N Mohawk Ave Portland OR 97203",
    "addr:housenumber":"10147",
    "addr:postcode":"97203",
    "addr:street":"N Mohawk Ave",
    "iso:country":"US",
    "sg:address":"10147 N Mohawk Ave",
    "sg:city":"Portland",
    "sg:classifiers":[
        {
            "category":"Shopping",
            "subcategory":"Beauty & Cosmetics",
            "type":"Retail Goods"
        }
    ],
    "sg:phone":"+1 503 286 0377",
    "sg:postcode":"97203",
    "sg:province":"OR",
    "sg:tags":[
        "merchandise"
    ],
    "wof:name":"Penwell Merle M Irene N",
    "wof:placetype":"venue"
},
  "geometry": {"coordinates":[-122.744142,45.5975],"type":"Point"}
}