{
  "type": "Feature",
  "properties": {
    "iso:country":"US",
    "sg:address":"2301 NW Thurman St",
    "sg:city":"Portland",
    "sg:classifiers":[
        {
            "category":"Health Services",
            "subcategory":"Chiropractor",
            "type":"Services"
        }
    ],
    "sg:phone":"+1 503 228 2225",
    "sg:postcode":"97210",
    "sg:province":"OR",
    "wof:name":"North Hlls Chiropractic Clinic",
    "wof:placetype":"venue"
},
  "geometry": {"coordinates":[-122.69983999999999,45.535472],"type":"Point"}
}