{
  "type": "Feature",
  "properties": {
    "iso:country":"US",
    "sg:address":"288 NW Pacific Grove Dr",
    "sg:city":"Beaverton",
    "sg:classifiers":[
        {
            "category":"Shopping",
            "subcategory":"Books",
            "type":"Retail Goods"
        }
    ],
    "sg:phone":"+1 503 614 9819",
    "sg:postcode":"97006",
    "sg:province":"OR",
    "wof:name":"Books N Such",
    "wof:placetype":"venue"
},
  "geometry": {"coordinates":[-122.848401,45.521254],"type":"Point"}
}