{
  "type": "Feature",
  "properties": {
    "addr:full":"4635 SE Lee Ave Lincoln City OR 97367",
    "addr:housenumber":"4635",
    "addr:postcode":"97367",
    "addr:street":"Se Lee Ave",
    "iso:country":"US",
    "sg:address":"4635 SE Lee Ave",
    "sg:city":"Lincoln City",
    "sg:classifiers":[
        {
            "category":"Social Services",
            "subcategory":"Adult Care",
            "type":"Services"
        }
    ],
    "sg:phone":"+1 541 994 6007",
    "sg:postcode":"97367",
    "sg:province":"OR",
    "sg:tags":[
        "home",
        "group"
    ],
    "wof:name":"Shangri-LA Corp",
    "wof:placetype":"venue"
},
  "geometry": {"coordinates":[-124.012351,44.931063],"type":"Point"}
}