{
  "type": "Feature",
  "properties": {
    "addr:full":"412 NE Oak Ct Sheridan OR 97378",
    "addr:housenumber":"412",
    "addr:postcode":"97378",
    "addr:street":"Ne Oak Ct",
    "iso:country":"US",
    "sg:address":"412 NE Oak Ct",
    "sg:city":"Sheridan",
    "sg:classifiers":[
        {
            "category":"Retail",
            "subcategory":"Repair Shop",
            "type":"Services"
        }
    ],
    "sg:phone":"+1 503 435 8707",
    "sg:postcode":"97378",
    "sg:province":"OR",
    "wof:name":"Northwest Heavy Equipment",
    "wof:placetype":"venue"
},
  "geometry": {"coordinates":[-123.38976700000001,45.101939],"type":"Point"}
}