{
  "type": "Feature",
  "properties": {
    "iso:country":"US",
    "sg:address":"1004 Marine Dr",
    "sg:city":"Astoria",
    "sg:classifiers":[
        {
            "category":"Shopping",
            "subcategory":"Gifts & Souvenirs",
            "type":"Retail Goods"
        }
    ],
    "sg:phone":"+1 503 325 6600",
    "sg:postcode":"97103",
    "sg:province":"OR",
    "wof:name":"Cellar On 10th",
    "wof:placetype":"venue"
},
  "geometry": {"coordinates":[-123.832676,46.189814],"type":"Point"}
}