{
  "type": "Feature",
  "properties": {
    "iso:country":"US",
    "sg:address":"PO Box 10558",
    "sg:city":"Portland",
    "sg:classifiers":[
        {
            "category":"Food & Beverages",
            "subcategory":"Liquor & Beverages",
            "type":"Retail Goods"
        }
    ],
    "sg:phone":"+1 503 223 8709",
    "sg:postcode":"97296",
    "sg:province":"OR",
    "sg:tags":[
        "beer",
        "spirit",
        "wine"
    ],
    "wof:name":"Pope Rigging Loft Inc",
    "wof:placetype":"venue"
},
  "geometry": {"coordinates":[-122.700996,45.534801],"type":"Point"}
}