{
  "type": "Feature",
  "properties": {
    "addr:full":"475 N 2nd Ave Stayton OR 97383",
    "addr:housenumber":"475",
    "addr:postcode":"97383",
    "addr:street":"N 2Nd Ave",
    "iso:country":"US",
    "sg:address":"475 N 2nd Ave",
    "sg:city":"Stayton",
    "sg:classifiers":[
        {
            "category":"Utilities",
            "subcategory":"Cable",
            "type":"Services"
        }
    ],
    "sg:phone":"+1 503 769 6817",
    "sg:postcode":"97383",
    "sg:province":"OR",
    "sg:tags":[
        "television"
    ],
    "wof:name":"Uvision LLC",
    "wof:placetype":"venue"
},
  "geometry": {"coordinates":[-122.793375,44.7983],"type":"Point"}
}