{
  "type": "Feature",
  "properties": {
    "iso:country":"US",
    "sg:address":"544 SE Eastwood St",
    "sg:city":"Roseburg",
    "sg:classifiers":[
        {
            "category":"Building & Trades",
            "subcategory":"Landscaping Services",
            "type":"Services"
        }
    ],
    "sg:phone":"+1 541 440 0156",
    "sg:postcode":"97470",
    "sg:province":"OR",
    "wof:name":"Pro Mow Plus",
    "wof:placetype":"venue"
},
  "geometry": {"coordinates":[-123.326937,43.206504],"type":"Point"}
}