{
  "type": "Feature",
  "properties": {
    "iso:country":"US",
    "sg:address":"3026 Hwy 20",
    "sg:city":"Sweet Home",
    "sg:classifiers":[
        {
            "category":"Travel",
            "subcategory":"Hotels & Motels",
            "type":"Entertainment"
        }
    ],
    "sg:phone":"+1 541 367 2205",
    "sg:postcode":"97386",
    "sg:province":"OR",
    "sg:tags":[
        "operation"
    ],
    "wof:name":"Sun Motel",
    "wof:placetype":"venue"
},
  "geometry": {"coordinates":[-122.713021,44.400592],"type":"Point"}
}