{
  "type": "Feature",
  "properties": {
    "iso:country":"US",
    "sg:address":"15828 SE McLoughlin Blvd",
    "sg:city":"Portland",
    "sg:classifiers":[
        {
            "category":"Shopping",
            "subcategory":"Department Store",
            "type":"Retail Goods"
        }
    ],
    "sg:phone":"+1 503 654 7900",
    "sg:postcode":"97267",
    "sg:province":"OR",
    "sg:tags":[
        "shop"
    ],
    "wof:name":"Bargain City",
    "wof:placetype":"venue"
},
  "geometry": {"coordinates":[-122.625286,45.407612],"type":"Point"}
}