{
  "type": "Feature",
  "properties": {
    "iso:country":"US",
    "sg:address":"70050 Paulina City Rd",
    "sg:city":"Paulina",
    "sg:classifiers":[
        {
            "category":"Education",
            "subcategory":"School",
            "type":"Public Place"
        }
    ],
    "sg:phone":"+1 541 477 3182",
    "sg:postcode":"97751",
    "sg:province":"OR",
    "wof:name":"Paulina Elementary School",
    "wof:placetype":"venue"
},
  "geometry": {"coordinates":[-119.963662,44.132906],"type":"Point"}
}