{
  "type": "Feature",
  "properties": {
    "iso:country":"US",
    "sg:address":"1040 Green Acres Rd",
    "sg:city":"Eugene",
    "sg:classifiers":[
        {
            "category":"Restaurant",
            "type":"Food & Drink"
        }
    ],
    "sg:menulink":"http://www.allmenus.com/or/eugene-springfield/201084-mcdonalds/menu/",
    "sg:postcode":"97408",
    "sg:province":"OR",
    "sg:tags":[
        "burger",
        "american"
    ],
    "wof:name":"McDonald's",
    "wof:placetype":"venue"
},
  "geometry": {"coordinates":[-123.095809,44.093516],"type":"Point"}
}