{
  "type": "Feature",
  "properties": {
    "iso:country":"US",
    "sg:address":"4697 Cedar St",
    "sg:city":"Astoria",
    "sg:classifiers":[
        {
            "category":"Recreation",
            "type":"Entertainment"
        }
    ],
    "sg:phone":"+1 503 325 5079",
    "sg:postcode":"97103",
    "sg:province":"OR",
    "sg:tags":[
        "parks"
    ],
    "wof:name":"OSU Fish & Wildlife",
    "wof:placetype":"venue"
},
  "geometry": {"coordinates":[-123.78939099999999,46.194864],"type":"Point"}
}