{
  "type": "Feature",
  "properties": {
    "iso:country":"US",
    "sg:address":"5441 Kafir Dr NE",
    "sg:city":"Keizer",
    "sg:classifiers":[
        {
            "category":"Retail",
            "subcategory":"Auto Repair",
            "type":"Services"
        }
    ],
    "sg:phone":"+1 503 463 5253",
    "sg:postcode":"97303",
    "sg:province":"OR",
    "sg:tags":[
        "repairing",
        "automobile"
    ],
    "wof:name":"Fleetwise Services",
    "wof:placetype":"venue"
},
  "geometry": {"coordinates":[-123.013967,45.002956],"type":"Point"}
}