{
  "type": "Feature",
  "properties": {
    "addr:full":"5441 Kafir Dr NE Keizer OR 97303",
    "addr:housenumber":"5441",
    "addr:postcode":"97303",
    "addr:street":"Kafir Dr Ne",
    "iso:country":"US",
    "sg:address":"5441 Kafir Dr NE",
    "sg:city":"Keizer",
    "sg:classifiers":[
        {
            "category":"Retail",
            "subcategory":"Auto Repair",
            "type":"Services"
        }
    ],
    "sg:phone":"+1 503 463 5253",
    "sg:postcode":"97303",
    "sg:province":"OR",
    "sg:tags":[
        "repairing",
        "automobile"
    ],
    "wof:name":"Fleetwise Services",
    "wof:placetype":"venue"
},
  "geometry": {"coordinates":[-123.01396699999999,45.002956],"type":"Point"}
}