{
  "type": "Feature",
  "properties": {
    "iso:country":"US",
    "sg:address":"89935 Territorial Rd",
    "sg:city":"Elmira",
    "sg:classifiers":[
        {
            "category":"Health Services",
            "subcategory":"Doctor",
            "type":"Services"
        }
    ],
    "sg:phone":"+1 541 935 3557",
    "sg:postcode":"97437",
    "sg:province":"OR",
    "sg:tags":[
        "medicine",
        "physician",
        "practice",
        "surgeons",
        "family"
    ],
    "wof:name":"Peter J & Pamela J Cary M",
    "wof:placetype":"venue"
},
  "geometry": {"coordinates":[-123.332204,44.099728],"type":"Point"}
}