{
  "type": "Feature",
  "properties": {
    "iso:country":"US",
    "sg:address":"16515 Reed Rd",
    "sg:city":"La Pine",
    "sg:classifiers":[
        {
            "category":"Autos & Motor Vehicles",
            "subcategory":"Fuel & Gas Station",
            "type":"Retail Goods"
        }
    ],
    "sg:phone":"+1 541 536 5205",
    "sg:postcode":"97739",
    "sg:province":"OR",
    "sg:tags":[
        "oil"
    ],
    "wof:name":"LA Pine Chevron",
    "wof:placetype":"venue"
},
  "geometry": {"coordinates":[-121.49835,43.674582],"type":"Point"}
}