{
  "type": "Feature",
  "properties": {
    "iso:country":"US",
    "sg:address":"79746 Territorial Rd",
    "sg:city":"Lorane",
    "sg:classifiers":[
        {
            "category":"Manufacturing",
            "subcategory":"Wood Products",
            "type":"Manufacturing & Wholesale Goods"
        }
    ],
    "sg:phone":"+1 541 954 6653",
    "sg:postcode":"97451",
    "sg:province":"OR",
    "sg:tags":[
        "carving"
    ],
    "wof:name":"Turning Crazy Woodwork",
    "wof:placetype":"venue"
},
  "geometry": {"coordinates":[-123.23595,43.822023],"type":"Point"}
}