{
  "type": "Feature",
  "properties": {
    "addr:full":"8720 SE Sunnybrook Blvd Clackamas OR 97015",
    "addr:housenumber":"8720",
    "addr:postcode":"97015",
    "addr:street":"Se Sunnybrook Blvd",
    "iso:country":"US",
    "sg:address":"8720 SE Sunnybrook Blvd",
    "sg:city":"Clackamas",
    "sg:classifiers":[
        {
            "category":"Sports & Exercise",
            "subcategory":"Gym",
            "type":"Entertainment"
        }
    ],
    "sg:phone":"+1 503 653 0300",
    "sg:postcode":"97015",
    "sg:province":"OR",
    "sg:website":"www.24hourfitness.com",
    "wof:name":"24 Hour Fitness",
    "wof:placetype":"venue"
},
  "geometry": {"coordinates":[-122.57283,45.429261],"type":"Point"}
}