{
  "type": "Feature",
  "properties": {
    "iso:country":"US",
    "sg:address":"18494 S Windy City Rd",
    "sg:city":"Mulino",
    "sg:classifiers":[
        {
            "category":"Shopping",
            "subcategory":"Bicycles & Sporting Goods",
            "type":"Retail Goods"
        }
    ],
    "sg:phone":"+1 503 632 3984",
    "sg:postcode":"97042",
    "sg:province":"OR",
    "wof:name":"On Target Firearms Training",
    "wof:placetype":"venue"
},
  "geometry": {"coordinates":[-122.494098,45.213253],"type":"Point"}
}