{
  "type": "Feature",
  "properties": {
    "addr:full":"15234 Butsch Ln NE Mount Angel OR 97362",
    "addr:postcode":"15234;97362",
    "addr:street":"Butsch Ln Ne",
    "iso:country":"US",
    "sg:address":"15234 Butsch Ln NE",
    "sg:city":"Mount Angel",
    "sg:phone":"+1 503 845 2485",
    "sg:postcode":"97362",
    "sg:province":"OR",
    "sg:tags":[
        "farm",
        "field",
        "wheat",
        "crop"
    ],
    "wof:name":"4 B Farms Inc",
    "wof:placetype":"venue"
},
  "geometry": {"coordinates":[-122.746735,45.081003],"type":"Point"}
}