{
  "type": "Feature",
  "properties": {
    "iso:country":"US",
    "sg:address":"3101 S 6th St",
    "sg:city":"Klamath Falls",
    "sg:classifiers":[
        {
            "category":"Wholesale",
            "subcategory":"Machinery & Supplies",
            "type":"Manufacturing & Wholesale Goods"
        }
    ],
    "sg:phone":"+1 541 882 5378",
    "sg:postcode":"97603",
    "sg:province":"OR",
    "sg:tags":[
        "cleaners",
        "vacuum"
    ],
    "wof:name":"High Desert Vacuflo",
    "wof:placetype":"venue"
},
  "geometry": {"coordinates":[-121.75146599999999,42.208577],"type":"Point"}
}