{
  "type": "Feature",
  "properties": {
    "iso:country":"US",
    "sg:address":"1805 NE Kane Dr",
    "sg:city":"Gresham",
    "sg:classifiers":[
        {
            "category":"Building & Trades",
            "subcategory":"Construction",
            "type":"Services"
        }
    ],
    "sg:phone":"+1 503 618 1800",
    "sg:postcode":"97030",
    "sg:province":"OR",
    "sg:tags":[
        "repairing",
        "remodeling",
        "contractor"
    ],
    "wof:name":"Sunwest Inc",
    "wof:placetype":"venue"
},
  "geometry": {"coordinates":[-122.400047,45.509856],"type":"Point"}
}