{
  "type": "Feature",
  "properties": {
    "addr:full":"1551 Satellite Dr Medford OR 97504",
    "addr:housenumber":"1551",
    "addr:postcode":"97504",
    "addr:street":"Satellite Dr",
    "iso:country":"US",
    "sg:address":"1551 Satellite Dr",
    "sg:city":"Medford",
    "sg:classifiers":[
        {
            "category":"Professional",
            "subcategory":"Management & Consulting",
            "type":"Services"
        }
    ],
    "sg:phone":"+1 541 772 0825",
    "sg:postcode":"97504",
    "sg:province":"OR",
    "sg:tags":[
        "business"
    ],
    "wof:name":"Dlk Consultants",
    "wof:placetype":"venue"
},
  "geometry": {"coordinates":[-122.798937,42.342412],"type":"Point"}
}