{
  "type": "Feature",
  "properties": {
    "iso:country":"US",
    "sg:address":"777 NE 8th St Ofc",
    "sg:city":"Gresham",
    "sg:classifiers":[
        {
            "category":"Real Estate",
            "subcategory":"Real Estate Services",
            "type":"Services"
        },
        {
            "category":"Real Estate",
            "subcategory":"Real Estate Operator",
            "type":"Services"
        }
    ],
    "sg:phone":"+1 503 491 9661",
    "sg:postcode":"97030",
    "sg:province":"OR",
    "sg:tags":[
        "management",
        "vacancy",
        "apartment",
        "listing",
        "rental",
        "finder"
    ],
    "wof:name":"Central Station Apartments",
    "wof:placetype":"venue"
},
  "geometry": {"coordinates":[-122.42300299999999,45.502981],"type":"Point"}
}