{
  "type": "Feature",
  "properties": {
    "iso:country":"US",
    "sg:address":"3839 SW Golf Course Rd",
    "sg:city":"Cornelius",
    "sg:classifiers":[
        {
            "category":"Wholesale",
            "subcategory":"Plants",
            "type":"Manufacturing & Wholesale Goods"
        },
        {
            "category":"Farming",
            "subcategory":"Nursery",
            "type":"Manufacturing & Wholesale Goods"
        }
    ],
    "sg:phone":"+1 503 357 2904",
    "sg:postcode":"97113",
    "sg:province":"OR",
    "sg:tags":[
        "growing",
        "bedding",
        "tree"
    ],
    "sg:website":"www.bloomingnursery.com",
    "wof:name":"Blooming Nursery Inc",
    "wof:placetype":"venue"
},
  "geometry": {"coordinates":[-123.050156,45.492422],"type":"Point"}
}