{
  "type": "Feature",
  "properties": {
    "addr:full":"2950 NW 29th Ave Portland OR 97210",
    "addr:housenumber":"2950",
    "addr:postcode":"97210",
    "addr:street":"Nw 29Th Ave",
    "iso:country":"US",
    "sg:address":"2950 NW 29th Ave",
    "sg:city":"Portland",
    "sg:classifiers":[
        {
            "category":"Food & Beverages",
            "subcategory":"Liquor & Beverages",
            "type":"Retail Goods"
        },
        {
            "category":"Wholesale",
            "subcategory":"Wine & Distilled Alcoholic Beverages",
            "type":"Manufacturing & Wholesale Goods"
        }
    ],
    "sg:phone":"+1 503 220 0037",
    "sg:postcode":"97210",
    "sg:province":"OR",
    "sg:tags":[
        "broker"
    ],
    "wof:name":"Devine Wine",
    "wof:placetype":"venue"
},
  "geometry": {"coordinates":[-122.710949,45.543827],"type":"Point"}
}