{
  "type": "Feature",
  "properties": {
    "addr:full":"13090 SE Normandy Dr Clackamas OR 97015",
    "addr:postcode":"13090;97015",
    "addr:street":"Se Normandy Dr",
    "iso:country":"US",
    "sg:address":"13090 SE Normandy Dr",
    "sg:city":"Clackamas",
    "sg:classifiers":[
        {
            "category":"Shopping",
            "subcategory":"Used Merchandise",
            "type":"Retail Goods"
        }
    ],
    "sg:phone":"+1 503 698 8918",
    "sg:postcode":"97015",
    "sg:province":"OR",
    "sg:tags":[
        "antique"
    ],
    "wof:name":"Kin Folk Comforts",
    "wof:placetype":"venue"
},
  "geometry": {"coordinates":[-122.53022199999999,45.422681],"type":"Point"}
}