{
  "type": "Feature",
  "properties": {
    "addr:full":"2425 W 18th Ave Eugene OR 97402",
    "addr:housenumber":"2425",
    "addr:postcode":"97402",
    "addr:street":"W 18Th Ave",
    "iso:country":"US",
    "sg:address":"2425 W 18th Ave",
    "sg:city":"Eugene",
    "sg:classifiers":[
        {
            "category":"Food & Beverages",
            "subcategory":"Specialty",
            "type":"Retail Goods"
        }
    ],
    "sg:phone":"+1 541 687 6853",
    "sg:postcode":"97402",
    "sg:province":"OR",
    "sg:tags":[
        "specializing",
        "gourmet",
        "product"
    ],
    "wof:name":"Earth Gourmet Foods",
    "wof:placetype":"venue"
},
  "geometry": {"coordinates":[-123.131085,44.040642],"type":"Point"}
}