{
  "type": "Feature",
  "properties": {
    "iso:country":"US",
    "sg:address":"9221 SW Barbur Blvd. #303",
    "sg:city":"Portland",
    "sg:classifiers":[
        {
            "category":"Communications",
            "subcategory":"Newspaper",
            "type":"Services"
        }
    ],
    "sg:phone":"+1 503 620 0770",
    "sg:postcode":"97219",
    "sg:province":"OR",
    "sg:tags":[
        "print",
        "medium"
    ],
    "sg:website":"www.marcopdx.com",
    "wof:name":"MARCO Ideas Unlimited",
    "wof:placetype":"venue"
},
  "geometry": {"coordinates":[-122.710444,45.458761],"type":"Point"}
}