{
  "type": "Feature",
  "properties": {
    "addr:full":"23175 NW Bennett St Hillsboro OR 97124",
    "addr:housenumber":"23175",
    "addr:postcode":"97124",
    "addr:street":"Nw Bennett St",
    "iso:country":"US",
    "sg:address":"23175 NW Bennett St",
    "sg:city":"Hillsboro",
    "sg:classifiers":[
        {
            "category":"Manufacturing",
            "subcategory":"Motor Vehicles & Parts",
            "type":"Manufacturing & Wholesale Goods"
        }
    ],
    "sg:phone":"+1 503 844 5025",
    "sg:postcode":"97124",
    "sg:province":"OR",
    "sg:tags":[
        "car",
        "mfg"
    ],
    "wof:name":"General Motors",
    "wof:placetype":"venue"
},
  "geometry": {"coordinates":[-122.917615,45.554838],"type":"Point"}
}