{
  "type": "Feature",
  "properties": {
    "addr:full":"1120 Wallace Rd NW Salem OR 97304",
    "addr:housenumber":"1120",
    "addr:postcode":"97304",
    "addr:street":"Wallace Rd Nw",
    "iso:country":"US",
    "sg:address":"1120 Wallace Rd NW",
    "sg:city":"Salem",
    "sg:classifiers":[
        {
            "category":"Restaurant",
            "type":"Food & Drink"
        }
    ],
    "sg:menulink":"http://www.allmenus.com/or/salem/170573-burger-king/menu/",
    "sg:phone":"+1 503 585 1952",
    "sg:postcode":"97304",
    "sg:province":"OR",
    "sg:tags":[
        "burger",
        "american"
    ],
    "wof:name":"Burger King",
    "wof:placetype":"venue"
},
  "geometry": {"coordinates":[-123.051393,44.951216],"type":"Point"}
}