{
  "type": "Feature",
  "properties": {
    "iso:country":"US",
    "sg:address":"1465 Amberland Ave",
    "sg:city":"Eugene",
    "sg:classifiers":[
        {
            "category":"Shopping",
            "subcategory":"Optical Goods",
            "type":"Retail Goods"
        }
    ],
    "sg:phone":"+1 541 342 2889",
    "sg:postcode":"97401",
    "sg:province":"OR",
    "sg:tags":[
        "sun",
        "goggles",
        "sunglasses"
    ],
    "wof:name":"Glitter Glasses",
    "wof:placetype":"venue"
},
  "geometry": {"coordinates":[-123.08951,44.082138],"type":"Point"}
}