{
  "type": "Feature",
  "properties": {
    "addr:full":"1017 1st Ave E Albany OR 97321",
    "addr:housenumber":"1017",
    "addr:postcode":"97321",
    "addr:street":"1St Ave E",
    "iso:country":"US",
    "sg:address":"1017 1st Ave E",
    "sg:city":"Albany",
    "sg:classifiers":[
        {
            "category":"Retail",
            "subcategory":"Auto Repair",
            "type":"Services"
        }
    ],
    "sg:phone":"+1 541 926 7312",
    "sg:postcode":"97321",
    "sg:province":"OR",
    "sg:tags":[
        "repairing",
        "automobile",
        "transmission",
        "automotive"
    ],
    "wof:name":"Cordray's Transmission Inc",
    "wof:placetype":"venue"
},
  "geometry": {"coordinates":[-123.092431,44.638895],"type":"Point"}
}