{
  "type": "Feature",
  "properties": {
    "addr:full":"8900 SW Hall Blvd Portland OR 97223",
    "addr:housenumber":"8900",
    "addr:postcode":"97223",
    "addr:street":"Sw Hall Blvd",
    "iso:country":"US",
    "sg:address":"8900 SW Hall Blvd",
    "sg:city":"Portland",
    "sg:classifiers":[
        {
            "category":"Health Services",
            "subcategory":"Dentist",
            "type":"Services"
        }
    ],
    "sg:phone":"+1 503 644 2446",
    "sg:postcode":"97223",
    "sg:province":"OR",
    "wof:name":"Kim Eric N PC",
    "wof:placetype":"venue"
},
  "geometry": {"coordinates":[-122.78800200000001,45.458801],"type":"Point"}
}