{
  "type": "Feature",
  "properties": {
    "iso:country":"US",
    "sg:address":"8427 N Central St",
    "sg:city":"Portland",
    "sg:classifiers":[
        {
            "category":"Recreation",
            "type":"Entertainment"
        }
    ],
    "sg:phone":"+1 503 823 3192",
    "sg:postcode":"97203",
    "sg:province":"OR",
    "sg:tags":[
        "hall",
        "auditorium"
    ],
    "sg:website":"www.portlandparks.org",
    "wof:name":"St Johns Community Ctr",
    "wof:placetype":"venue"
},
  "geometry": {"coordinates":[-122.752441,45.591872],"type":"Point"}
}