{
  "type": "Feature",
  "properties": {
    "iso:country":"US",
    "sg:address":"6722 SW Capitol Hwy",
    "sg:city":"Portland",
    "sg:classifiers":[
        {
            "category":"Building & Trades",
            "subcategory":"Locksmith",
            "type":"Services"
        }
    ],
    "sg:phone":"+1 503 205 6128",
    "sg:postcode":"97219",
    "sg:province":"OR",
    "sg:tags":[
        "key"
    ],
    "wof:name":"1 Alpha Lock and Key of or",
    "wof:placetype":"venue"
},
  "geometry": {"coordinates":[-122.706784,45.475836],"type":"Point"}
}