{
  "type": "Feature",
  "properties": {
    "iso:country":"US",
    "sg:address":"427 SW 8th St",
    "sg:city":"Redmond",
    "sg:classifiers":[
        {
            "category":"Food & Beverages",
            "subcategory":"Specialty",
            "type":"Retail Goods"
        }
    ],
    "sg:phone":"+1 541 923 8870",
    "sg:postcode":"97756",
    "sg:province":"OR",
    "sg:tags":[
        "tea",
        "coffee"
    ],
    "wof:name":"Mocha Moose",
    "wof:placetype":"venue"
},
  "geometry": {"coordinates":[-121.17648699999999,44.273286],"type":"Point"}
}