{
  "type": "Feature",
  "properties": {
    "iso:country":"US",
    "sg:address":"406 SW 2nd Ave",
    "sg:city":"Estacada",
    "sg:classifiers":[
        {
            "category":"Professional",
            "subcategory":"Business Services",
            "type":"Services"
        }
    ],
    "sg:phone":"+1 503 630 4229",
    "sg:postcode":"97023",
    "sg:province":"OR",
    "sg:tags":[
        "embroidery"
    ],
    "wof:name":"Threads Of Gold Embroidery",
    "wof:placetype":"venue"
},
  "geometry": {"coordinates":[-122.338594,45.288689],"type":"Point"}
}