{
  "type": "Feature",
  "properties": {
    "iso:country":"US",
    "sg:address":"3664 Meadow Park Loop NE",
    "sg:city":"Salem",
    "sg:classifiers":[
        {
            "category":"Manufacturing",
            "subcategory":"Tools & Machinery",
            "type":"Manufacturing & Wholesale Goods"
        }
    ],
    "sg:phone":"+1 503 393 1922",
    "sg:postcode":"97305",
    "sg:province":"OR",
    "sg:tags":[
        "machine",
        "shop"
    ],
    "sg:website":"www.cpmachining.com",
    "wof:name":"Carr' Precision Machining",
    "wof:placetype":"venue"
},
  "geometry": {"coordinates":[-122.988457,44.985166],"type":"Point"}
}