{
  "type": "Feature",
  "properties": {
    "iso:country":"US",
    "sg:address":"17300 Grandview Ct",
    "sg:city":"Lake Oswego",
    "sg:classifiers":[
        {
            "category":"Professional",
            "subcategory":"Computer Services",
            "type":"Services"
        }
    ],
    "sg:phone":"+1 503 635 2199",
    "sg:postcode":"97034",
    "sg:province":"OR",
    "sg:tags":[
        "content",
        "training",
        "produce",
        "develop",
        "software"
    ],
    "wof:name":"Northwest Education Training A",
    "wof:placetype":"venue"
},
  "geometry": {"coordinates":[-122.661465,45.399512],"type":"Point"}
}