{
  "type": "Feature",
  "properties": {
    "addr:full":"115 Anderson Ave Coos Bay OR 97420",
    "addr:housenumber":"115",
    "addr:postcode":"97420",
    "addr:street":"Anderson Ave",
    "iso:country":"US",
    "sg:address":"115 Anderson Ave",
    "sg:city":"Coos Bay",
    "sg:classifiers":[
        {
            "category":"Shopping",
            "subcategory":"Gifts & Souvenirs",
            "type":"Retail Goods"
        }
    ],
    "sg:phone":"+1 541 266 9886",
    "sg:postcode":"97420",
    "sg:province":"OR",
    "wof:name":"Now & Then This & That Gifts",
    "wof:placetype":"venue"
},
  "geometry": {"coordinates":[-124.21381700000001,43.367142],"type":"Point"}
}