{
  "type": "Feature",
  "properties": {
    "iso:country":"US",
    "sg:address":"1012 NW Wall St",
    "sg:city":"Bend",
    "sg:classifiers":[
        {
            "category":"Organizations",
            "subcategory":"Religious Organization",
            "type":"Services"
        }
    ],
    "sg:phone":"+1 541 389 1580",
    "sg:postcode":"97701",
    "sg:province":"OR",
    "sg:tags":[
        "church"
    ],
    "sg:website":"www.comc.us",
    "wof:name":"Central Oregon Miracles Ctr",
    "wof:placetype":"venue"
},
  "geometry": {"coordinates":[-121.312652,44.060214],"type":"Point"}
}