{
  "type": "Feature",
  "properties": {
    "iso:country":"US",
    "sg:address":"13986 Majestic Ct",
    "sg:city":"Lake Oswego",
    "sg:classifiers":[
        {
            "category":"Wholesale",
            "subcategory":"Electrical",
            "type":"Manufacturing & Wholesale Goods"
        }
    ],
    "sg:phone":"+1 503 635 5161",
    "sg:postcode":"97035",
    "sg:province":"OR",
    "sg:tags":[
        "telecommunication"
    ],
    "wof:name":"Maulin Inc",
    "wof:placetype":"venue"
},
  "geometry": {"coordinates":[-122.709574,45.424573],"type":"Point"}
}