{
  "type": "Feature",
  "properties": {
    "iso:country":"US",
    "sg:address":"353 W Madrone St",
    "sg:city":"Roseburg",
    "sg:classifiers":[
        {
            "category":"Organizations",
            "subcategory":"Community Association",
            "type":"Services"
        }
    ],
    "sg:phone":"+1 541 673 7166",
    "sg:postcode":"97470",
    "sg:province":"OR",
    "sg:tags":[
        "fraternal"
    ],
    "wof:name":"Loyal Order Of Moose",
    "wof:placetype":"venue"
},
  "geometry": {"coordinates":[-123.350323,43.215773],"type":"Point"}
}