{
  "type": "Feature",
  "properties": {
    "iso:country":"US",
    "sg:address":"115 N College St",
    "sg:city":"Newberg",
    "sg:classifiers":[
        {
            "category":"Retail",
            "subcategory":"Repair Shop",
            "type":"Services"
        }
    ],
    "sg:phone":"+1 503 538 0888",
    "sg:postcode":"97132",
    "sg:province":"OR",
    "sg:tags":[
        "picture",
        "art",
        "framing",
        "gallery"
    ],
    "wof:name":"Newberg Frame and Gallery",
    "wof:placetype":"venue"
},
  "geometry": {"coordinates":[-122.972874,45.301019],"type":"Point"}
}