{
  "type": "Feature",
  "properties": {
    "iso:country":"US",
    "sg:address":"1421 N Myrtle Rd",
    "sg:city":"Myrtle Creek",
    "sg:classifiers":[
        {
            "category":"Building & Trades",
            "subcategory":"Construction",
            "type":"Services"
        },
        {
            "category":"Retail",
            "subcategory":"Auto Repair",
            "type":"Services"
        }
    ],
    "sg:phone":"+1 541 860 5472",
    "sg:postcode":"97457",
    "sg:province":"OR",
    "sg:tags":[
        "body",
        "automobile",
        "painting",
        "contractor"
    ],
    "wof:name":"Michael's Automotive & Truck",
    "wof:placetype":"venue"
},
  "geometry": {"coordinates":[-123.272621,43.033941],"type":"Point"}
}