{
  "type": "Feature",
  "properties": {
    "iso:country":"US",
    "sg:address":"1800 Coburg Rd",
    "sg:city":"Eugene",
    "sg:classifiers":[
        {
            "category":"Health Services",
            "subcategory":"Doctor",
            "type":"Services"
        }
    ],
    "sg:phone":"+1 541 687 6380",
    "sg:postcode":"97401",
    "sg:province":"OR",
    "sg:tags":[
        "medical"
    ],
    "wof:name":"William P McWhorter",
    "wof:placetype":"venue"
},
  "geometry": {"coordinates":[-123.067584,44.084101],"type":"Point"}
}