{
  "type": "Feature",
  "properties": {
    "addr:full":"1390 Walnut Rd Springfield OR 97477",
    "addr:housenumber":"1390",
    "addr:postcode":"97477",
    "addr:street":"Walnut Rd",
    "iso:country":"US",
    "sg:address":"1390 Walnut Rd",
    "sg:city":"Springfield",
    "sg:classifiers":[
        {
            "category":"Building & Trades",
            "subcategory":"Pest Control",
            "type":"Services"
        }
    ],
    "sg:phone":"+1 541 747 4669",
    "sg:postcode":"97477",
    "sg:province":"OR",
    "wof:name":"Victory Weed Control",
    "wof:placetype":"venue"
},
  "geometry": {"coordinates":[-123.045205,44.049384],"type":"Point"}
}