{
  "type": "Feature",
  "properties": {
    "iso:country":"US",
    "sg:address":"29550 Hwy 50",
    "sg:city":"Merrill",
    "sg:classifiers":[
        {
            "category":"Farming",
            "subcategory":"Dairy Farm",
            "type":"Manufacturing & Wholesale Goods"
        }
    ],
    "sg:phone":"+1 541 723 3466",
    "sg:postcode":"97633",
    "sg:province":"OR",
    "wof:name":"Hastings Dairy",
    "wof:placetype":"venue"
},
  "geometry": {"coordinates":[-121.431093,42.013046],"type":"Point"}
}