{
  "type": "Feature",
  "properties": {
    "iso:country":"US",
    "sg:address":"396 E 18th Ave",
    "sg:city":"Eugene",
    "sg:classifiers":[
        {
            "category":"Personal",
            "type":"Services"
        }
    ],
    "sg:phone":"+1 541 342 8025",
    "sg:postcode":"97401",
    "sg:province":"OR",
    "sg:tags":[
        "therapist",
        "massage"
    ],
    "wof:name":"A Touch Of Tranquility",
    "wof:placetype":"venue"
},
  "geometry": {"coordinates":[-123.08738700000001,44.03996],"type":"Point"}
}