{
  "type": "Feature",
  "properties": {
    "iso:country":"US",
    "sg:address":"760 S Main St",
    "sg:city":"Myrtle Creek",
    "sg:classifiers":[
        {
            "category":"Autos & Motor Vehicles",
            "subcategory":"Auto Supplies",
            "type":"Retail Goods"
        }
    ],
    "sg:phone":"+1 541 863 4216",
    "sg:postcode":"97457",
    "sg:province":"OR",
    "sg:tags":[
        "automobile",
        "parts"
    ],
    "wof:name":"NAPA Auto Parts",
    "wof:placetype":"venue"
},
  "geometry": {"coordinates":[-123.29346099999999,43.020712],"type":"Point"}
}