{
  "type": "Feature",
  "properties": {
    "addr:full":"13775 SE McLoughlin Boulevard Portland OR 97222",
    "addr:postcode":"13775;97222",
    "addr:street":"Se Mcloughlin Boulevard",
    "iso:country":"US",
    "sg:address":"13775 SE McLoughlin Boulevard",
    "sg:city":"Portland",
    "sg:classifiers":[
        {
            "category":"Restaurant",
            "type":"Food & Drink"
        }
    ],
    "sg:phone":"+1 503 659 6445",
    "sg:postcode":"97222",
    "sg:province":"OR",
    "sg:tags":[
        "mexican"
    ],
    "wof:name":"La Mexicana Variety Store",
    "wof:placetype":"venue"
},
  "geometry": {"coordinates":[-122.633476,45.42395],"type":"Point"}
}