{
  "type": "Feature",
  "properties": {
    "iso:country":"US",
    "sg:address":"8550 SW Apple Way",
    "sg:city":"Portland",
    "sg:classifiers":[
        {
            "category":"Wholesale",
            "subcategory":"Non-durable Goods",
            "type":"Manufacturing & Wholesale Goods"
        }
    ],
    "sg:phone":"+1 503 291 5261",
    "sg:postcode":"97225",
    "sg:province":"OR",
    "sg:tags":[
        "supplies-wholesale",
        "salons-equipment",
        "beauty",
        "manufacturer"
    ],
    "wof:name":"Maly's",
    "wof:placetype":"venue"
},
  "geometry": {"coordinates":[-122.764061,45.48581],"type":"Point"}
}