{
  "type": "Feature",
  "properties": {
    "addr:full":"1532 Siskiyou Blvd Ashland OR 97520",
    "addr:housenumber":"1532",
    "addr:postcode":"97520",
    "addr:street":"Siskiyou Blvd",
    "iso:country":"US",
    "sg:address":"1532 Siskiyou Blvd",
    "sg:city":"Ashland",
    "sg:classifiers":[
        {
            "category":"Health Services",
            "subcategory":"Doctor",
            "type":"Services"
        }
    ],
    "sg:phone":"+1 541 482 8700",
    "sg:postcode":"97520",
    "sg:province":"OR",
    "sg:tags":[
        "clinic"
    ],
    "wof:name":"Planned Parenthood",
    "wof:placetype":"venue"
},
  "geometry": {"coordinates":[-122.68920199999999,42.184043],"type":"Point"}
}