{
  "type": "Feature",
  "properties": {
    "addr:full":"2006 SW Salmon Ave Redmond OR 97756",
    "addr:housenumber":"2006",
    "addr:postcode":"97756",
    "addr:street":"Sw Salmon Ave",
    "iso:country":"US",
    "sg:address":"2006 SW Salmon Ave",
    "sg:city":"Redmond",
    "sg:classifiers":[
        {
            "category":"Building & Trades",
            "subcategory":"Plumbing",
            "type":"Services"
        }
    ],
    "sg:phone":"+1 541 504 1988",
    "sg:postcode":"97756",
    "sg:province":"OR",
    "sg:tags":[
        "contractor"
    ],
    "wof:name":"Coreys Plumbing LLC",
    "wof:placetype":"venue"
},
  "geometry": {"coordinates":[-121.189804,44.254701],"type":"Point"}
}