{
  "type": "Feature",
  "properties": {
    "addr:full":"1120 SW 3rd Ave Portland OR 97204",
    "addr:housenumber":"1120",
    "addr:postcode":"97204",
    "addr:street":"Sw 3Rd Ave",
    "iso:country":"US",
    "sg:address":"1120 SW 3rd Ave",
    "sg:city":"Portland",
    "sg:classifiers":[
        {
            "category":"Government",
            "subcategory":"Office",
            "type":"Public Place"
        }
    ],
    "sg:phone":"+1 503 248 3689",
    "sg:postcode":"97204",
    "sg:province":"OR",
    "wof:name":"Multnomah County Justice Ctr",
    "wof:placetype":"venue"
},
  "geometry": {"coordinates":[-122.676981,45.515426],"type":"Point"}
}