{
  "type": "Feature",
  "properties": {
    "iso:country":"US",
    "sg:address":"101 SW Main St",
    "sg:city":"Portland",
    "sg:classifiers":[
        {
            "category":"Professional",
            "subcategory":"Business Services",
            "type":"Services"
        }
    ],
    "sg:phone":"+1 503 224 5450",
    "sg:postcode":"97204",
    "sg:province":"OR",
    "wof:name":"Madrona Venture Group",
    "wof:placetype":"venue"
},
  "geometry": {"coordinates":[-122.675282,45.515139],"type":"Point"}
}