{
  "type": "Feature",
  "properties": {
    "iso:country":"US",
    "sg:address":"39933 Fish Hatchery Dr",
    "sg:city":"Scio",
    "sg:classifiers":[
        {
            "category":"Shopping",
            "subcategory":"Catalog Store",
            "type":"Retail Goods"
        }
    ],
    "sg:phone":"+1 503 394 4008",
    "sg:postcode":"97374",
    "sg:province":"OR",
    "sg:tags":[
        "mail",
        "house"
    ],
    "wof:name":"Pinecroft International",
    "wof:placetype":"venue"
},
  "geometry": {"coordinates":[-122.805745,44.638909],"type":"Point"}
}