{
  "type": "Feature",
  "properties": {
    "iso:country":"US",
    "sg:address":"310 River Rd",
    "sg:city":"Eugene",
    "sg:classifiers":[
        {
            "category":"Insurance",
            "subcategory":"Insurance Agent",
            "type":"Services"
        },
        {
            "category":"Insurance",
            "subcategory":"Hazard Insurance",
            "type":"Services"
        },
        {
            "category":"Insurance",
            "subcategory":"Title Insurance",
            "type":"Services"
        }
    ],
    "sg:phone":"+1 541 461 1383",
    "sg:postcode":"97404",
    "sg:province":"OR",
    "sg:tags":[
        "auto",
        "homeowner"
    ],
    "sg:website":"http://apps.amfam.com/agentlocator/VABERNAT?sourceid=yp3",
    "wof:name":"American Family Insurance- Valerie Lodge",
    "wof:placetype":"venue"
},
  "geometry": {"coordinates":[-123.117372,44.065182],"type":"Point"}
}