{
  "type": "Feature",
  "properties": {
    "iso:country":"US",
    "sg:address":"121 SW Salmon St Ste 210",
    "sg:city":"Portland",
    "sg:classifiers":[
        {
            "category":"Organizations",
            "subcategory":"Non-profit Organization",
            "type":"Services"
        }
    ],
    "sg:phone":"+1 503 279 9383",
    "sg:postcode":"97204",
    "sg:province":"OR",
    "sg:tags":[
        "charity",
        "foundations-educational",
        "philanthropic",
        "research"
    ],
    "wof:name":"Zero Waste Alliance",
    "wof:placetype":"venue"
},
  "geometry": {"coordinates":[-122.674893,45.5158],"type":"Point"}
}