{
  "type": "Feature",
  "properties": {
    "iso:country":"US",
    "sg:address":"1894 N Teakwood St",
    "sg:city":"Canby",
    "sg:classifiers":[
        {
            "category":"Shopping",
            "subcategory":"Clothing, Apparel, & Fashions",
            "type":"Retail Goods"
        }
    ],
    "sg:phone":"+1 503 263 2531",
    "sg:postcode":"97013",
    "sg:province":"OR",
    "sg:tags":[
        "sportswear"
    ],
    "wof:name":"Varsity Spirit Fashions Inc",
    "wof:placetype":"venue"
},
  "geometry": {"coordinates":[-122.671785,45.277744],"type":"Point"}
}