{
  "type": "Feature",
  "properties": {
    "iso:country":"US",
    "sg:address":"755 SE Alethea Way",
    "sg:city":"Mcminnville",
    "sg:classifiers":[
        {
            "category":"Building & Trades",
            "subcategory":"Construction",
            "type":"Services"
        }
    ],
    "sg:phone":"+1 503 472 5893",
    "sg:postcode":"97128",
    "sg:province":"OR",
    "sg:tags":[
        "general",
        "contractor"
    ],
    "wof:name":"Dix Builders Inc",
    "wof:placetype":"venue"
},
  "geometry": {"coordinates":[-123.191451,45.194734],"type":"Point"}
}