{
  "type": "Feature",
  "properties": {
    "addr:full":"1585 Juniper St Junction City OR 97448",
    "addr:housenumber":"1585",
    "addr:postcode":"97448",
    "addr:street":"Juniper St",
    "iso:country":"US",
    "sg:address":"1585 Juniper St",
    "sg:city":"Junction City",
    "sg:classifiers":[
        {
            "category":"Wholesale",
            "subcategory":"Construction Materials",
            "type":"Manufacturing & Wholesale Goods"
        },
        {
            "category":"Shopping",
            "subcategory":"Hobbies, Toys, & Games",
            "type":"Retail Goods"
        }
    ],
    "sg:phone":"+1 541 998 2297",
    "sg:postcode":"97448",
    "sg:province":"OR",
    "sg:tags":[
        "equipment",
        "ceramic",
        "supply"
    ],
    "wof:name":"Clarke's Ceramics",
    "wof:placetype":"venue"
},
  "geometry": {"coordinates":[-123.20625,44.22704],"type":"Point"}
}