{
  "type": "Feature",
  "properties": {
    "iso:country":"US",
    "sg:address":"693 Washington St",
    "sg:city":"Ashland",
    "sg:classifiers":[
        {
            "category":"Social Services",
            "type":"Services"
        }
    ],
    "sg:phone":"+1 541 488 2870",
    "sg:postcode":"97520",
    "sg:province":"OR",
    "sg:tags":[
        "organization",
        "welfare"
    ],
    "wof:name":"Advocates-Severely Handicapped",
    "wof:placetype":"venue"
},
  "geometry": {"coordinates":[-122.66397499999999,42.180261],"type":"Point"}
}