{
  "type": "Feature",
  "properties": {
    "addr:full":"19425 SW Madeline St Beaverton OR 97007",
    "addr:housenumber":"19425",
    "addr:postcode":"97007",
    "addr:street":"Sw Madeline St",
    "iso:country":"US",
    "sg:address":"19425 SW Madeline St",
    "sg:city":"Beaverton",
    "sg:classifiers":[
        {
            "category":"Building & Trades",
            "subcategory":"Landscaping Services",
            "type":"Services"
        }
    ],
    "sg:phone":"+1 503 649 2406",
    "sg:postcode":"97007",
    "sg:province":"OR",
    "wof:name":"Borderline Curbs",
    "wof:placetype":"venue"
},
  "geometry": {"coordinates":[-122.876069,45.481095],"type":"Point"}
}