{
  "type": "Feature",
  "properties": {
    "iso:country":"US",
    "sg:address":"19425 SW Madeline St",
    "sg:city":"Beaverton",
    "sg:classifiers":[
        {
            "category":"Building & Trades",
            "subcategory":"Landscaping Services",
            "type":"Services"
        }
    ],
    "sg:phone":"+1 503 649 2406",
    "sg:postcode":"97007",
    "sg:province":"OR",
    "wof:name":"Borderline Curbs",
    "wof:placetype":"venue"
},
  "geometry": {"coordinates":[-122.876069,45.481095],"type":"Point"}
}