{
  "type": "Feature",
  "properties": {
    "iso:country":"US",
    "sg:address":"809 SW Court Ave",
    "sg:city":"Pendleton",
    "sg:classifiers":[
        {
            "category":"Health Services",
            "subcategory":"Doctor",
            "type":"Services"
        }
    ],
    "sg:phone":"+1 541 276 3241",
    "sg:postcode":"97801",
    "sg:province":"OR",
    "sg:tags":[
        "dental",
        "clinic",
        "dentist"
    ],
    "wof:name":"Robert D Johnson",
    "wof:placetype":"venue"
},
  "geometry": {"coordinates":[-118.795074,45.670357],"type":"Point"}
}