{
  "type": "Feature",
  "properties": {
    "addr:full":"145 Abegg Rd Merlin OR 97526",
    "addr:housenumber":"145",
    "addr:postcode":"97526",
    "addr:street":"Abegg Rd",
    "iso:country":"US",
    "sg:address":"145 Abegg Rd",
    "sg:city":"Merlin",
    "sg:classifiers":[
        {
            "category":"Social Services",
            "type":"Services"
        }
    ],
    "sg:phone":"+1 541 474 0028",
    "sg:postcode":"97526",
    "sg:province":"OR",
    "wof:name":"Wings To Ride",
    "wof:placetype":"venue"
},
  "geometry": {"coordinates":[-123.444534,42.516981],"type":"Point"}
}