{
  "type": "Feature",
  "properties": {
    "iso:country":"US",
    "sg:address":"18610 NW Cornell Rd",
    "sg:city":"Hillsboro",
    "sg:classifiers":[
        {
            "category":"Health Services",
            "subcategory":"Doctor",
            "type":"Services"
        }
    ],
    "sg:phone":"+1 503 690 0707",
    "sg:postcode":"97124",
    "sg:province":"OR",
    "sg:tags":[
        "cardiologist",
        "pediatrician"
    ],
    "sg:website":"www.vrpediatrics.com",
    "wof:name":"Jack A Rosenberg MD",
    "wof:placetype":"venue"
},
  "geometry": {"coordinates":[-122.86952599999999,45.534189],"type":"Point"}
}