{
  "type": "Feature",
  "properties": {
    "addr:full":"16055 SW Walker Rd Beaverton OR 97006",
    "addr:housenumber":"16055",
    "addr:postcode":"97006",
    "addr:street":"Sw Walker Rd",
    "iso:country":"US",
    "sg:address":"16055 SW Walker Rd",
    "sg:city":"Beaverton",
    "sg:classifiers":[
        {
            "category":"Building & Trades",
            "subcategory":"Locksmith",
            "type":"Services"
        }
    ],
    "sg:phone":"+1 503 206 0729",
    "sg:postcode":"97006",
    "sg:province":"OR",
    "sg:tags":[
        "key"
    ],
    "wof:name":"A Res & Comm Locksmith",
    "wof:placetype":"venue"
},
  "geometry": {"coordinates":[-122.842097,45.517734],"type":"Point"}
}