{
  "type": "Feature",
  "properties": {
    "addr:full":"6700 SW 105th Ave Beaverton OR 97008",
    "addr:housenumber":"6700",
    "addr:postcode":"97008",
    "addr:street":"Sw 105Th Ave",
    "iso:country":"US",
    "sg:address":"6700 SW 105th Ave",
    "sg:city":"Beaverton",
    "sg:classifiers":[
        {
            "category":"Professional",
            "subcategory":"Management & Consulting",
            "type":"Services"
        }
    ],
    "sg:phone":"+1 503 643 5454",
    "sg:postcode":"97008",
    "sg:province":"OR",
    "sg:tags":[
        "consultant",
        "medical"
    ],
    "sg:website":"www.genexservices.com",
    "wof:name":"Genex Services Inc",
    "wof:placetype":"venue"
},
  "geometry": {"coordinates":[-122.784958,45.470515],"type":"Point"}
}