{
  "type": "Feature",
  "properties": {
    "iso:country":"US",
    "sg:address":"6829 SE 82nd",
    "sg:city":"Portland",
    "sg:classifiers":[
        {
            "category":"Food & Beverages",
            "subcategory":"Meat & Fish",
            "type":"Retail Goods"
        }
    ],
    "sg:phone":"+1 503 995 3096",
    "sg:postcode":"97206",
    "sg:province":"OR",
    "sg:tags":[
        "hot",
        "dog"
    ],
    "sg:website":"frankiesfranks.tripod.com/",
    "wof:name":"Frankies Franks",
    "wof:placetype":"venue"
},
  "geometry": {"coordinates":[-122.579391,45.473076],"type":"Point"}
}