{
  "type": "Feature",
  "properties": {
    "iso:country":"US",
    "sg:address":"2306 NE Glisan St",
    "sg:city":"Portland",
    "sg:classifiers":[
        {
            "category":"Retail",
            "subcategory":"Repair Shop",
            "type":"Services"
        }
    ],
    "sg:phone":"+1 503 238 1995",
    "sg:postcode":"97232",
    "sg:province":"OR",
    "sg:tags":[
        "watch",
        "jewelry"
    ],
    "wof:name":"Clock Works",
    "wof:placetype":"venue"
},
  "geometry": {"coordinates":[-122.643035,45.526492],"type":"Point"}
}