{
  "type": "Feature",
  "properties": {
    "iso:country":"US",
    "sg:address":"1550 NW Eastman Pkwy",
    "sg:city":"Gresham",
    "sg:classifiers":[
        {
            "category":"Health Services",
            "subcategory":"Doctor",
            "type":"Services"
        }
    ],
    "sg:phone":"+1 503 665 0495",
    "sg:postcode":"97030",
    "sg:province":"OR",
    "sg:tags":[
        "dentist"
    ],
    "wof:name":"Endodontic Specialty Group",
    "wof:placetype":"venue"
},
  "geometry": {"coordinates":[-122.435209,45.505858],"type":"Point"}
}