{
  "type": "Feature",
  "properties": {
    "addr:full":"9150 SW Pioneer Ct #T Wilsonville OR 97070",
    "addr:housenumber":"9150",
    "addr:postcode":"97070",
    "addr:street":"Sw Pioneer Ct # T",
    "iso:country":"US",
    "sg:address":"9150 SW Pioneer Ct #T",
    "sg:city":"Wilsonville",
    "sg:classifiers":[
        {
            "category":"Home & Garden",
            "subcategory":"Furniture",
            "type":"Retail Goods"
        },
        {
            "category":"Home & Garden",
            "subcategory":"Building Materials",
            "type":"Retail Goods"
        },
        {
            "category":"Building & Trades",
            "subcategory":"Construction",
            "type":"Services"
        },
        {
            "category":"Wholesale",
            "subcategory":"Home Furnishings",
            "type":"Manufacturing & Wholesale Goods"
        }
    ],
    "sg:phone":"+1 503 582 8068",
    "sg:postcode":"97070",
    "sg:province":"OR",
    "sg:tags":[
        "cabinet",
        "equipment-wholesale",
        "top",
        "counter",
        "kitchen",
        "equipment-household",
        "altering",
        "planning",
        "contractor",
        "remodeling",
        "maker",
        "manufacturer"
    ],
    "sg:website":"http://www.jckitchencabinets.com",
    "wof:name":"JC Kitchen & Bath Cabinets",
    "wof:placetype":"venue"
},
  "geometry": {"coordinates":[-122.772532,45.338931],"type":"Point"}
}