{
  "type": "Feature",
  "properties": {
    "iso:country":"US",
    "sg:address":"9150 NE Fremont Street Ofc",
    "sg:city":"Portland",
    "sg:classifiers":[
        {
            "category":"Education",
            "subcategory":"School",
            "type":"Public Place"
        },
        {
            "category":"Education",
            "subcategory":"University",
            "type":"Public Place"
        }
    ],
    "sg:phone":"+1 503 255 3540",
    "sg:postcode":"97220",
    "sg:province":"OR",
    "sg:tags":[
        "college"
    ],
    "sg:website":"www.clti.org",
    "wof:name":"Portland Bible College",
    "wof:placetype":"venue"
},
  "geometry": {"coordinates":[-122.568686,45.548917],"type":"Point"}
}