{
  "type": "Feature",
  "properties": {
    "addr:full":"2705 Molalla Rd Woodburn OR 97071",
    "addr:housenumber":"2705",
    "addr:postcode":"97071",
    "addr:street":"Molalla Rd",
    "iso:country":"US",
    "sg:address":"2705 Molalla Rd",
    "sg:city":"Woodburn",
    "sg:classifiers":[
        {
            "category":"Farming",
            "subcategory":"Nursery",
            "type":"Manufacturing & Wholesale Goods"
        }
    ],
    "sg:phone":"+1 503 981 8020",
    "sg:postcode":"97071",
    "sg:province":"OR",
    "sg:tags":[
        "ornamental"
    ],
    "wof:name":"Herbert Koening",
    "wof:placetype":"venue"
},
  "geometry": {"coordinates":[-122.80971099999999,45.151256],"type":"Point"}
}