{
  "type": "Feature",
  "properties": {
    "iso:country":"US",
    "sg:address":"1255 N Main Ave",
    "sg:city":"Gresham",
    "sg:classifiers":[
        {
            "category":"Restaurant",
            "type":"Food & Drink"
        }
    ],
    "sg:phone":"+1 503 465 0665",
    "sg:postcode":"97030",
    "sg:province":"OR",
    "wof:name":"Grotto",
    "wof:placetype":"venue"
},
  "geometry": {"coordinates":[-122.43106400000001,45.50603],"type":"Point"}
}