{
  "type": "Feature",
  "properties": {
    "iso:country":"US",
    "sg:address":"34 NW Broadway",
    "sg:city":"Portland",
    "sg:classifiers":[
        {
            "category":"Shopping",
            "subcategory":"Computers & Home Electronics",
            "type":"Retail Goods"
        }
    ],
    "sg:phone":"+1 503 227 1668",
    "sg:postcode":"97209",
    "sg:province":"OR",
    "sg:tags":[
        "merchandise"
    ],
    "wof:name":"Car Stereo City Inc",
    "wof:placetype":"venue"
},
  "geometry": {"coordinates":[-122.677376,45.523522],"type":"Point"}
}