{
  "type": "Feature",
  "properties": {
    "iso:country":"US",
    "sg:address":"4840 NW Bethany Blvd",
    "sg:city":"Portland",
    "sg:classifiers":[
        {
            "category":"Restaurant",
            "type":"Food & Drink"
        }
    ],
    "sg:phone":"+1 503 439 8898",
    "sg:postcode":"97229",
    "sg:province":"OR",
    "sg:tags":[
        "chinese"
    ],
    "wof:name":"Chen's Dynasty Restaurant",
    "wof:placetype":"venue"
},
  "geometry": {"coordinates":[-122.83667800000001,45.556597],"type":"Point"}
}