{
  "type": "Feature",
  "properties": {
    "addr:full":"4801 SE Hawthorne Blvd Portland OR 97215",
    "addr:housenumber":"4801",
    "addr:postcode":"97215",
    "addr:street":"Se Hawthorne Blvd",
    "iso:country":"US",
    "sg:address":"4801 SE Hawthorne Blvd",
    "sg:city":"Portland",
    "sg:classifiers":[
        {
            "category":"Bars & Pubs",
            "type":"Food & Drink"
        }
    ],
    "sg:phone":"+1 503 232 2037",
    "sg:postcode":"97215",
    "sg:province":"OR",
    "sg:tags":[
        "diva"
    ],
    "sg:website":"www.barofthegods.com/",
    "wof:name":"Bar of the Gods",
    "wof:placetype":"venue"
},
  "geometry": {"coordinates":[-122.612921,45.512267],"type":"Point"}
}