{
  "type": "Feature",
  "properties": {
    "addr:full":"12570 SW Center Street Beaverton OR 97005",
    "addr:housenumber":"12570",
    "addr:postcode":"97005",
    "addr:street":"Sw Center Street",
    "iso:country":"US",
    "sg:address":"12570 SW Center Street",
    "sg:city":"Beaverton",
    "sg:classifiers":[
        {
            "category":"Restaurant",
            "type":"Food & Drink"
        }
    ],
    "sg:phone":"+1 503 626 0763",
    "sg:postcode":"97005",
    "sg:province":"OR",
    "sg:tags":[
        "buffet",
        "japanese",
        "chinese"
    ],
    "wof:name":"Buffet Palace",
    "wof:placetype":"venue"
},
  "geometry": {"coordinates":[-122.806203,45.493271],"type":"Point"}
}