{
  "type": "Feature",
  "properties": {
    "iso:country":"US",
    "sg:address":"7773 SW Ashford St",
    "sg:city":"Portland",
    "sg:classifiers":[
        {
            "category":"Professional",
            "subcategory":"Management & Consulting",
            "type":"Services"
        }
    ],
    "sg:phone":"+1 503 670 9817",
    "sg:postcode":"97224",
    "sg:province":"OR",
    "wof:name":"Vertical Path Strategies",
    "wof:placetype":"venue"
},
  "geometry": {"coordinates":[-122.757088,45.408353],"type":"Point"}
}