{
  "type": "Feature",
  "properties": {
    "iso:country":"US",
    "sg:address":"9376 SE Church St",
    "sg:city":"Clackamas",
    "sg:classifiers":[
        {
            "category":"Retail",
            "subcategory":"Auto Repair",
            "type":"Services"
        }
    ],
    "sg:phone":"+1 503 657 5306",
    "sg:postcode":"97015",
    "sg:province":"OR",
    "wof:name":"Rob's Automotive & Fleet",
    "wof:placetype":"venue"
},
  "geometry": {"coordinates":[-122.568001,45.411499],"type":"Point"}
}