{
  "type": "Feature",
  "properties": {
    "addr:full":"15106 SE McLoughlin Boulevard Portland OR 97267",
    "addr:postcode":"15106;97267",
    "addr:street":"Se Mcloughlin Boulevard",
    "iso:country":"US",
    "sg:address":"15106 SE McLoughlin Boulevard",
    "sg:city":"Portland",
    "sg:classifiers":[
        {
            "category":"Shopping",
            "subcategory":"Pets & Pet Supplies",
            "type":"Retail Goods"
        }
    ],
    "sg:phone":"+1 503 653 1779",
    "sg:postcode":"97267",
    "sg:province":"OR",
    "sg:tags":[
        "store"
    ],
    "wof:name":"Creature Comforts",
    "wof:placetype":"venue"
},
  "geometry": {"coordinates":[-122.63057000000001,45.414059],"type":"Point"}
}