{
  "type": "Feature",
  "properties": {
    "iso:country":"US",
    "sg:address":"92433 Ward Creek Ln",
    "sg:city":"Myrtle Point",
    "sg:classifiers":[
        {
            "category":"Farming",
            "subcategory":"Livestock Farm",
            "type":"Manufacturing & Wholesale Goods"
        }
    ],
    "sg:phone":"+1 541 572 2596",
    "sg:postcode":"97458",
    "sg:province":"OR",
    "sg:tags":[
        "beef",
        "feedlot",
        "cattle"
    ],
    "wof:name":"Hermann King Ranchers",
    "wof:placetype":"venue"
},
  "geometry": {"coordinates":[-124.235001,43.037843],"type":"Point"}
}