{
  "type": "Feature",
  "properties": {
    "iso:country":"US",
    "sg:address":"4792 Herman St",
    "sg:city":"Eugene",
    "sg:classifiers":[
        {
            "category":"Professional",
            "subcategory":"Computer Services",
            "type":"Services"
        }
    ],
    "sg:phone":"+1 541 510 0362",
    "sg:postcode":"97404",
    "sg:province":"OR",
    "sg:tags":[
        "programing",
        "custom"
    ],
    "wof:name":"Professional Tech Work",
    "wof:placetype":"venue"
},
  "geometry": {"coordinates":[-123.131934,44.128307],"type":"Point"}
}