{
  "type": "Feature",
  "properties": {
    "addr:full":"3118 Washburn Way Klamath Falls OR 97603",
    "addr:housenumber":"3118",
    "addr:postcode":"97603",
    "addr:street":"Washburn Way",
    "iso:country":"US",
    "sg:address":"3118 Washburn Way",
    "sg:city":"Klamath Falls",
    "sg:classifiers":[
        {
            "category":"Autos & Motor Vehicles",
            "subcategory":"Automobile Sales",
            "type":"Retail Goods"
        }
    ],
    "sg:phone":"+1 541 882 9761",
    "sg:postcode":"97603",
    "sg:province":"OR",
    "sg:tags":[
        "used"
    ],
    "wof:name":"Can AM Motors",
    "wof:placetype":"venue"
},
  "geometry": {"coordinates":[-121.75721,42.198149],"type":"Point"}
}