{
  "type": "Feature",
  "properties": {
    "iso:country":"US",
    "sg:address":"2168 Geary St SE",
    "sg:city":"Albany",
    "sg:classifiers":[
        {
            "category":"Airport",
            "type":"Transportation"
        }
    ],
    "sg:phone":"+1 541 928 9060",
    "sg:postcode":"97322",
    "sg:province":"OR",
    "wof:name":"1 Step Cleaning",
    "wof:placetype":"venue"
},
  "geometry": {"coordinates":[-123.083168,44.620918],"type":"Point"}
}