{
  "type": "Feature",
  "properties": {
    "iso:country":"US",
    "sg:address":"6728 SW 204th Ave",
    "sg:city":"Beaverton",
    "sg:classifiers":[
        {
            "category":"Building & Trades",
            "subcategory":"Construction",
            "type":"Services"
        }
    ],
    "sg:phone":"+1 503 201 1326",
    "sg:postcode":"97007",
    "sg:province":"OR",
    "sg:tags":[
        "floor",
        "laying",
        "housekeeping",
        "contractor"
    ],
    "wof:name":"Berts Carpet Installers",
    "wof:placetype":"venue"
},
  "geometry": {"coordinates":[-122.887482,45.469966],"type":"Point"}
}