{
  "type": "Feature",
  "properties": {
    "iso:country":"US",
    "sg:address":"10525 SW 69th Ave",
    "sg:city":"Portland",
    "sg:classifiers":[
        {
            "category":"Building & Trades",
            "subcategory":"Construction",
            "type":"Services"
        }
    ],
    "sg:phone":"+1 503 288 0759",
    "sg:postcode":"97223",
    "sg:province":"OR",
    "sg:tags":[
        "hanging",
        "contractor"
    ],
    "wof:name":"Kathleen Swanberg Designs",
    "wof:placetype":"venue"
},
  "geometry": {"coordinates":[-122.747483,45.443846],"type":"Point"}
}