{
  "type": "Feature",
  "properties": {
    "iso:country":"US",
    "sg:address":"34414 Plainview Dr",
    "sg:city":"Shedd",
    "sg:classifiers":[
        {
            "category":"Organizations",
            "subcategory":"Religious Organization",
            "type":"Services"
        }
    ],
    "sg:phone":"+1 541 451 5683",
    "sg:postcode":"97377",
    "sg:province":"OR",
    "sg:tags":[
        "church"
    ],
    "wof:name":"Plainview Mennonite Church",
    "wof:placetype":"venue"
},
  "geometry": {"coordinates":[-123.01833999999999,44.483089],"type":"Point"}
}