{
  "type": "Feature",
  "properties": {
    "iso:country":"US",
    "sg:address":"722 NW Beach Dr",
    "sg:city":"Newport",
    "sg:classifiers":[
        {
            "category":"Bars & Pubs",
            "type":"Food & Drink"
        }
    ],
    "sg:phone":"+1 541 265 6032",
    "sg:postcode":"97365",
    "sg:province":"OR",
    "sg:tags":[
        "drinking"
    ],
    "wof:name":"Sandbar & Grill",
    "wof:placetype":"venue"
},
  "geometry": {"coordinates":[-124.061638,44.638971],"type":"Point"}
}