{
  "type": "Feature",
  "properties": {
    "addr:full":"4153 W 18th Ave Apt 120 Eugene OR 97402",
    "addr:housenumber":"4153;120",
    "addr:postcode":"97402",
    "addr:street":"W 18Th Ave Apt",
    "iso:country":"US",
    "sg:address":"4153 W 18th Ave Apt 120",
    "sg:city":"Eugene",
    "sg:classifiers":[
        {
            "category":"Health Services",
            "subcategory":"Hospital",
            "type":"Services"
        },
        {
            "category":"Community Center",
            "type":"Public Place"
        }
    ],
    "sg:phone":"+1 541 905 1808",
    "sg:postcode":"97402",
    "sg:province":"OR",
    "sg:tags":[
        "medical"
    ],
    "wof:name":"Freedom Project For Chronically Ill Single Mothers, Inc.",
    "wof:placetype":"venue"
},
  "geometry": {"coordinates":[-123.16359300000001,44.03837],"type":"Point"}
}