{
  "type": "Feature",
  "properties": {
    "iso:country":"US",
    "sg:address":"7165 SW Fir Loop",
    "sg:city":"Portland",
    "sg:classifiers":[
        {
            "category":"Health Services",
            "subcategory":"Health Practitioner",
            "type":"Services"
        }
    ],
    "sg:phone":"+1 503 624 0600",
    "sg:postcode":"97223",
    "sg:province":"OR",
    "wof:name":"Cedar Bend Clinic PC",
    "wof:placetype":"venue"
},
  "geometry": {"coordinates":[-122.750992,45.423367],"type":"Point"}
}