{
  "type": "Feature",
  "properties": {
    "addr:full":"220 Fir St La Grande OR 97850",
    "addr:housenumber":"220",
    "addr:postcode":"97850",
    "addr:street":"Fir St;Grande",
    "iso:country":"US",
    "sg:address":"220 Fir St",
    "sg:city":"La Grande",
    "sg:classifiers":[
        {
            "category":"Real Estate",
            "subcategory":"Real Estate Agent",
            "type":"Services"
        }
    ],
    "sg:phone":"+1 541 963 6304",
    "sg:postcode":"97850",
    "sg:province":"OR",
    "sg:tags":[
        "management"
    ],
    "wof:name":"Burrough's Properties",
    "wof:placetype":"venue"
},
  "geometry": {"coordinates":[-118.091784,45.327888],"type":"Point"}
}