{
  "type": "Feature",
  "properties": {
    "iso:country":"US",
    "sg:address":"441 N. Killingsworth St",
    "sg:city":"Portland",
    "sg:classifiers":[
        {
            "category":"Coffee & Tea",
            "type":"Food & Drink"
        }
    ],
    "sg:postcode":"97217",
    "sg:province":"OR",
    "sg:website":"www.facebook.com/profile.php?id=...",
    "wof:name":"Tuff Luck Cafe & Deli",
    "wof:placetype":"venue"
},
  "geometry": {"coordinates":[-122.671075,45.562875],"type":"Point"}
}