{
  "type": "Feature",
  "properties": {
    "iso:country":"US",
    "sg:address":"119 W Chocktoot St",
    "sg:city":"Chiloquin",
    "sg:classifiers":[
        {
            "category":"Professional",
            "subcategory":"Computer Services",
            "type":"Services"
        }
    ],
    "sg:phone":"+1 541 783 7550",
    "sg:postcode":"97624",
    "sg:province":"OR",
    "sg:tags":[
        "internet"
    ],
    "wof:name":"Always On Network Inc",
    "wof:placetype":"venue"
},
  "geometry": {"coordinates":[-121.862188,42.57664],"type":"Point"}
}