{
  "type": "Feature",
  "properties": {
    "addr:full":"635 Kourt Dr Eugene OR 97404",
    "addr:housenumber":"635",
    "addr:postcode":"97404",
    "addr:street":"Kourt Dr",
    "iso:country":"US",
    "sg:address":"635 Kourt Dr",
    "sg:city":"Eugene",
    "sg:classifiers":[
        {
            "category":"Building & Trades",
            "subcategory":"Cleaning & Sanitation",
            "type":"Services"
        }
    ],
    "sg:phone":"+1 541 689 3650",
    "sg:postcode":"97404",
    "sg:province":"OR",
    "sg:tags":[
        "janitor"
    ],
    "wof:name":"Ninfa's Elite Janitorial Svc",
    "wof:placetype":"venue"
},
  "geometry": {"coordinates":[-123.13756600000001,44.09272],"type":"Point"}
}