{
  "type": "Feature",
  "properties": {
    "iso:country":"US",
    "sg:address":"670 S 16th St",
    "sg:city":"Lebanon",
    "sg:classifiers":[
        {
            "category":"Building & Trades",
            "subcategory":"Construction",
            "type":"Services"
        }
    ],
    "sg:phone":"+1 541 497 3721",
    "sg:postcode":"97355",
    "sg:province":"OR",
    "sg:tags":[
        "wallcoverings-installation",
        "wallpaper",
        "painting",
        "contractor"
    ],
    "wof:name":"Fresh Coat Painting",
    "wof:placetype":"venue"
},
  "geometry": {"coordinates":[-122.927809,44.538987],"type":"Point"}
}