{
  "type": "Feature",
  "properties": {
    "iso:country":"US",
    "sg:address":"965 NE 22nd St",
    "sg:city":"Gresham",
    "sg:classifiers":[
        {
            "category":"Social Services",
            "subcategory":"Child Care",
            "type":"Services"
        }
    ],
    "sg:phone":"+1 503 666 8785",
    "sg:postcode":"97030",
    "sg:province":"OR",
    "sg:tags":[
        "day"
    ],
    "wof:name":"Diane Carbone",
    "wof:placetype":"venue"
},
  "geometry": {"coordinates":[-122.42134,45.512041],"type":"Point"}
}