{
  "type": "Feature",
  "properties": {
    "iso:country":"US",
    "sg:address":"93256 Holland Ln",
    "sg:city":"Marcola",
    "sg:classifiers":[
        {
            "category":"Autos & Motor Vehicles",
            "subcategory":"Auto Supplies",
            "type":"Retail Goods"
        },
        {
            "category":"Retail",
            "subcategory":"Auto Repair",
            "type":"Services"
        }
    ],
    "sg:phone":"+1 541 933 2880",
    "sg:postcode":"97454",
    "sg:province":"OR",
    "sg:tags":[
        "automobile",
        "parts",
        "accessory",
        "part",
        "accessories-wholesale",
        "manufacturer"
    ],
    "sg:website":"http://www.britautoparts.com",
    "wof:name":"British Auto Parts Ltd",
    "wof:placetype":"venue"
},
  "geometry": {"coordinates":[-122.81524899999999,44.203014],"type":"Point"}
}