{
  "type": "Feature",
  "properties": {
    "iso:country":"US",
    "sg:address":"4354 Averill Dr",
    "sg:city":"Grants Pass",
    "sg:classifiers":[
        {
            "category":"Manufacturing",
            "subcategory":"Lumber",
            "type":"Manufacturing & Wholesale Goods"
        }
    ],
    "sg:phone":"+1 541 479 2291",
    "sg:postcode":"97526",
    "sg:province":"OR",
    "sg:tags":[
        "company",
        "logging"
    ],
    "wof:name":"Brecount Brothers",
    "wof:placetype":"venue"
},
  "geometry": {"coordinates":[-123.251305,42.426198],"type":"Point"}
}