{
  "type": "Feature",
  "properties": {
    "iso:country":"US",
    "sg:address":"140 NE 116th Ave",
    "sg:city":"Portland",
    "sg:classifiers":[
        {
            "category":"Professional",
            "subcategory":"Management & Consulting",
            "type":"Services"
        }
    ],
    "sg:phone":"+1 503 252 1347",
    "sg:postcode":"97220",
    "sg:province":"OR",
    "sg:tags":[
        "business"
    ],
    "wof:name":"Bjk Consulting",
    "wof:placetype":"venue"
},
  "geometry": {"coordinates":[-122.54388,45.524308],"type":"Point"}
}