{
  "type": "Feature",
  "properties": {
    "iso:country":"US",
    "sg:address":"1923 SW 6th Ave",
    "sg:city":"Portland",
    "sg:classifiers":[
        {
            "category":"Restaurant",
            "type":"Food & Drink"
        }
    ],
    "sg:phone":"+1 503 228 0360",
    "sg:postcode":"97201",
    "sg:province":"OR",
    "sg:tags":[
        "sandwich",
        "eating"
    ],
    "sg:website":"www.bigtownhero.com",
    "wof:name":"Big Town Hero",
    "wof:placetype":"venue"
},
  "geometry": {"coordinates":[-122.682999,45.509998],"type":"Point"}
}