{
  "type": "Feature",
  "properties": {
    "iso:country":"US",
    "sg:address":"263 E Barnett Rd",
    "sg:city":"Medford",
    "sg:classifiers":[
        {
            "category":"Shopping",
            "subcategory":"Discount & Variety Stores",
            "type":"Retail Goods"
        }
    ],
    "sg:phone":"+1 541 770 2064",
    "sg:postcode":"97501",
    "sg:province":"OR",
    "wof:name":"Super Dollar",
    "wof:placetype":"venue"
},
  "geometry": {"coordinates":[-122.859437,42.315838],"type":"Point"}
}