{
  "type": "Feature",
  "properties": {
    "iso:country":"US",
    "sg:address":"414 Chocktoot St",
    "sg:city":"Chiloquin",
    "sg:classifiers":[
        {
            "category":"Real Estate",
            "subcategory":"Real Estate Services",
            "type":"Services"
        },
        {
            "category":"Real Estate",
            "subcategory":"Real Estate Agent",
            "type":"Services"
        }
    ],
    "sg:phone":"+1 541 783 2022",
    "sg:postcode":"97624",
    "sg:province":"OR",
    "sg:tags":[
        "management"
    ],
    "wof:name":"Fine Books & ..",
    "wof:placetype":"venue"
},
  "geometry": {"coordinates":[-121.86725800000001,42.57836],"type":"Point"}
}