{
  "type": "Feature",
  "properties": {
    "iso:country":"US",
    "sg:address":"21000 NW Evergreen Pkwy",
    "sg:city":"Hillsboro",
    "sg:classifiers":[
        {
            "category":"Banks & Credit Unions",
            "subcategory":"Bank",
            "type":"Services"
        }
    ],
    "sg:phone":"+1 503 531 4100",
    "sg:postcode":"97124",
    "sg:province":"OR",
    "sg:tags":[
        "state",
        "commercial"
    ],
    "wof:name":"Bank of Amer/Nwrpc 2828",
    "wof:placetype":"venue"
},
  "geometry": {"coordinates":[-122.89273300000001,45.545679],"type":"Point"}
}