{
  "type": "Feature",
  "properties": {
    "addr:full":"2059 Lars Way Medford OR 97501",
    "addr:housenumber":"2059",
    "addr:postcode":"97501",
    "addr:street":"Lars Way",
    "iso:country":"US",
    "sg:address":"2059 Lars Way",
    "sg:city":"Medford",
    "sg:classifiers":[
        {
            "category":"Wholesale",
            "subcategory":"Hardware",
            "type":"Manufacturing & Wholesale Goods"
        }
    ],
    "sg:phone":"+1 541 734 4304",
    "sg:postcode":"97501",
    "sg:province":"OR",
    "sg:tags":[
        "air",
        "parts",
        "conditioning",
        "supply"
    ],
    "wof:name":"Rsd/Total Control",
    "wof:placetype":"venue"
},
  "geometry": {"coordinates":[-122.899349,42.344296],"type":"Point"}
}