{
  "type": "Feature",
  "properties": {
    "addr:full":"2895 Chad Dr Eugene OR 97408",
    "addr:housenumber":"2895",
    "addr:postcode":"97408",
    "addr:street":"Chad Dr",
    "iso:country":"US",
    "sg:address":"2895 Chad Dr",
    "sg:city":"Eugene",
    "sg:classifiers":[
        {
            "category":"Manufacturing",
            "subcategory":"Printing",
            "type":"Manufacturing & Wholesale Goods"
        }
    ],
    "sg:phone":"+1 541 687 0103",
    "sg:postcode":"97408",
    "sg:province":"OR",
    "sg:tags":[
        "printer"
    ],
    "sg:website":"www.koke.com",
    "wof:name":"IP/Koke Printing Co",
    "wof:placetype":"venue"
},
  "geometry": {"coordinates":[-123.063557,44.090099],"type":"Point"}
}