{
  "type": "Feature",
  "properties": {
    "iso:country":"US",
    "sg:address":"5130 N Lombard Street",
    "sg:city":"Portland",
    "sg:classifiers":[
        {
            "category":"Personal",
            "subcategory":"Barber",
            "type":"Services"
        }
    ],
    "sg:phone":"+1 503 285 1884",
    "sg:postcode":"97203",
    "sg:province":"OR",
    "wof:name":"Hairport of Portland",
    "wof:placetype":"venue"
},
  "geometry": {"coordinates":[-122.721085,45.581508],"type":"Point"}
}