{
  "type": "Feature",
  "properties": {
    "addr:full":"1622 Coburg Rd Eugene OR 97401",
    "addr:housenumber":"1622",
    "addr:postcode":"97401",
    "addr:street":"Coburg Rd",
    "iso:country":"US",
    "sg:address":"1622 Coburg Rd",
    "sg:city":"Eugene",
    "sg:classifiers":[
        {
            "category":"Restaurant",
            "type":"Food & Drink"
        }
    ],
    "sg:menulink":"http://www.allmenus.com/or/eugene-springfield/256592-super-suppers/menu/",
    "sg:phone":"+1 541 344 3590",
    "sg:postcode":"97401",
    "sg:province":"OR",
    "sg:tags":[
        "new",
        "american"
    ],
    "wof:name":"Super Suppers",
    "wof:placetype":"venue"
},
  "geometry": {"coordinates":[-123.067725,44.080734],"type":"Point"}
}