{
  "type": "Feature",
  "properties": {
    "addr:full":"3732 Peppertree Dr Eugene OR 97402",
    "addr:housenumber":"3732",
    "addr:postcode":"97402",
    "addr:street":"Peppertree Dr",
    "iso:country":"US",
    "sg:address":"3732 Peppertree Dr",
    "sg:city":"Eugene",
    "sg:classifiers":[
        {
            "category":"Professional",
            "subcategory":"Business Services",
            "type":"Services"
        }
    ],
    "sg:phone":"+1 541 345 6515",
    "sg:postcode":"97402",
    "sg:province":"OR",
    "wof:name":"Star Traders",
    "wof:placetype":"venue"
},
  "geometry": {"coordinates":[-123.152494,44.04153],"type":"Point"}
}