{
  "type": "Feature",
  "properties": {
    "addr:full":"7227 N Leadbetter Rd Portland OR 97203",
    "addr:housenumber":"7227",
    "addr:postcode":"97203",
    "addr:street":"N Leadbetter Rd",
    "iso:country":"US",
    "sg:address":"7227 N Leadbetter Rd",
    "sg:city":"Portland",
    "sg:classifiers":[
        {
            "category":"Manufacturing",
            "subcategory":"Metals",
            "type":"Manufacturing & Wholesale Goods"
        },
        {
            "category":"Wholesale",
            "subcategory":"Metals & Minerals",
            "type":"Manufacturing & Wholesale Goods"
        }
    ],
    "sg:phone":"+1 503 286 0300",
    "sg:postcode":"97203",
    "sg:province":"OR",
    "sg:tags":[
        "steel",
        "flat",
        "rolled",
        "processing",
        "distributor",
        "mill",
        "processor"
    ],
    "sg:website":"http://www.oregonmetal.com",
    "wof:name":"Oregon Metal Slitters, Inc.",
    "wof:placetype":"venue"
},
  "geometry": {"coordinates":[-122.749224,45.629082],"type":"Point"}
}