{
  "type": "Feature",
  "properties": {
    "iso:country":"US",
    "sg:address":"15223 S Henrici Rd",
    "sg:city":"Oregon City",
    "sg:classifiers":[
        {
            "category":"Utilities",
            "subcategory":"Telephone",
            "type":"Services"
        }
    ],
    "sg:phone":"+1 503 632 3113",
    "sg:postcode":"97045",
    "sg:province":"OR",
    "sg:tags":[
        "company"
    ],
    "sg:website":"www.bctelco.com",
    "wof:name":"BEAVER Creek Telephone",
    "wof:placetype":"venue"
},
  "geometry": {"coordinates":[-122.555103,45.309383],"type":"Point"}
}