{
  "type": "Feature",
  "properties": {
    "iso:country":"US",
    "sg:address":"1910 E 15th Ave",
    "sg:city":"Eugene",
    "sg:classifiers":[
        {
            "category":"Wholesale",
            "subcategory":"Home Furnishings",
            "type":"Manufacturing & Wholesale Goods"
        }
    ],
    "sg:phone":"+1 541 345 1712",
    "sg:postcode":"97403",
    "sg:province":"OR",
    "wof:name":"Club Mud Ceramics Co-Op",
    "wof:placetype":"venue"
},
  "geometry": {"coordinates":[-123.06397800000001,44.043218],"type":"Point"}
}