{
  "type": "Feature",
  "properties": {
    "iso:country":"US",
    "sg:address":"368 NE Autumn Rose Way",
    "sg:city":"Hillsboro",
    "sg:classifiers":[
        {
            "category":"Professional",
            "subcategory":"Research",
            "type":"Services"
        }
    ],
    "sg:phone":"+1 503 844 5836",
    "sg:postcode":"97124",
    "sg:province":"OR",
    "sg:tags":[
        "commercial",
        "physical"
    ],
    "wof:name":"Research System Designs Inc",
    "wof:placetype":"venue"
},
  "geometry": {"coordinates":[-122.989108,45.5387],"type":"Point"}
}