{
  "type": "Feature",
  "properties": {
    "addr:full":"580 S Main St Lebanon OR 97355",
    "addr:housenumber":"580",
    "addr:postcode":"97355",
    "addr:street":"S Main St",
    "iso:country":"US",
    "sg:address":"580 S Main St",
    "sg:city":"Lebanon",
    "sg:classifiers":[
        {
            "category":"Shopping",
            "subcategory":"Hobbies, Toys, & Games",
            "type":"Retail Goods"
        }
    ],
    "sg:phone":"+1 541 258 4440",
    "sg:postcode":"97355",
    "sg:province":"OR",
    "sg:tags":[
        "gun",
        "gunsmith"
    ],
    "wof:name":"Straight Shooter's Sporting Goods",
    "wof:placetype":"venue"
},
  "geometry": {"coordinates":[-122.90706900000001,44.540187],"type":"Point"}
}