{
  "type": "Feature",
  "properties": {
    "iso:country":"US",
    "sg:address":"325 SW 27th Way",
    "sg:city":"Troutdale",
    "sg:classifiers":[
        {
            "category":"Restaurant",
            "type":"Food & Drink"
        }
    ],
    "sg:phone":"+1 503 492 9847",
    "sg:postcode":"97060",
    "sg:province":"OR",
    "sg:tags":[
        "eating"
    ],
    "wof:name":"Plenty Buffet",
    "wof:placetype":"venue"
},
  "geometry": {"coordinates":[-122.39198399999999,45.522251],"type":"Point"}
}