{
  "type": "Feature",
  "properties": {
    "iso:country":"US",
    "sg:address":"1005 Industrial Pkwy",
    "sg:city":"Newberg",
    "sg:classifiers":[
        {
            "category":"Home & Garden",
            "subcategory":"Household Appliances",
            "type":"Retail Goods"
        },
        {
            "category":"Building & Trades",
            "subcategory":"Construction",
            "type":"Services"
        },
        {
            "category":"Building & Trades",
            "subcategory":"Electrical",
            "type":"Services"
        }
    ],
    "sg:phone":"+1 503 538 1950",
    "sg:postcode":"97132",
    "sg:province":"OR",
    "sg:tags":[
        "repair",
        "specialty",
        "furnaces-heating",
        "system",
        "pump",
        "heating",
        "contractor",
        "heat",
        "air conditioning"
    ],
    "sg:website":"http://www.fourseasonsheatair.com",
    "wof:name":"Four Seasons Heating & Air Conditioning Inc",
    "wof:placetype":"venue"
},
  "geometry": {"coordinates":[-122.95031299999999,45.291802],"type":"Point"}
}