{
  "type": "Feature",
  "properties": {
    "iso:country":"US",
    "sg:address":"1825 NW 167th Pl",
    "sg:city":"Beaverton",
    "sg:classifiers":[
        {
            "category":"Manufacturing",
            "subcategory":"Tools & Machinery",
            "type":"Manufacturing & Wholesale Goods"
        }
    ],
    "sg:phone":"+1 503 629 5088",
    "sg:postcode":"97006",
    "sg:province":"OR",
    "sg:tags":[
        "computer"
    ],
    "sg:website":"www.c-cor.com",
    "wof:name":"C-Cor",
    "wof:placetype":"venue"
},
  "geometry": {"coordinates":[-122.848994,45.532981],"type":"Point"}
}