{
  "type": "Feature",
  "properties": {
    "iso:country":"US",
    "sg:address":"315 W Main St",
    "sg:city":"John Day",
    "sg:classifiers":[
        {
            "category":"Travel",
            "subcategory":"Hotels & Motels",
            "type":"Entertainment"
        }
    ],
    "sg:phone":"+1 541 575 1700",
    "sg:postcode":"97845",
    "sg:province":"OR",
    "sg:tags":[
        "operation"
    ],
    "wof:name":"Best Western Inn",
    "wof:placetype":"venue"
},
  "geometry": {"coordinates":[-118.95518199999999,44.416533],"type":"Point"}
}