{
  "type": "Feature",
  "properties": {
    "addr:full":"6469 SE 134th Ave Portland OR 97236",
    "addr:housenumber":"6469",
    "addr:postcode":"97236",
    "addr:street":"Se 134Th Ave",
    "iso:country":"US",
    "sg:address":"6469 SE 134th Ave",
    "sg:city":"Portland",
    "sg:classifiers":[
        {
            "category":"Building & Trades",
            "subcategory":"Plumbing",
            "type":"Services"
        }
    ],
    "sg:phone":"+1 503 761 2270",
    "sg:postcode":"97236",
    "sg:province":"OR",
    "sg:tags":[
        "contractor"
    ],
    "wof:name":"Tri-Star Western Inc",
    "wof:placetype":"venue"
},
  "geometry": {"coordinates":[-122.526143,45.475499],"type":"Point"}
}