{
  "type": "Feature",
  "properties": {
    "addr:full":"11953 SE Powell Blvd Portland OR 97266",
    "addr:postcode":"11953;97266",
    "addr:street":"Se Powell Blvd",
    "iso:country":"US",
    "sg:address":"11953 SE Powell Blvd",
    "sg:city":"Portland",
    "sg:classifiers":[
        {
            "category":"Shopping",
            "subcategory":"Florist",
            "type":"Retail Goods"
        }
    ],
    "sg:phone":"+1 503 760 1148",
    "sg:postcode":"97266",
    "sg:province":"OR",
    "wof:name":"Diannes",
    "wof:placetype":"venue"
},
  "geometry": {"coordinates":[-122.539669,45.497091],"type":"Point"}
}