{
  "type": "Feature",
  "properties": {
    "addr:full":"1565 N Pacific Hwy Woodburn OR 97071",
    "addr:housenumber":"1565",
    "addr:postcode":"97071",
    "addr:street":"N Pacific Hwy",
    "iso:country":"US",
    "sg:address":"1565 N Pacific Hwy",
    "sg:city":"Woodburn",
    "sg:classifiers":[
        {
            "category":"Restaurant",
            "type":"Food & Drink"
        }
    ],
    "sg:phone":"+1 503 982 9600",
    "sg:postcode":"97071",
    "sg:province":"OR",
    "wof:name":"Los Cabos Mexican Restaurant",
    "wof:placetype":"venue"
},
  "geometry": {"coordinates":[-122.832476,45.149877],"type":"Point"}
}