{
  "type": "Feature",
  "properties": {
    "addr:full":"675 Hansen Ave S Salem OR 97302",
    "addr:housenumber":"675",
    "addr:postcode":"97302",
    "addr:street":"Hansen Ave S",
    "iso:country":"US",
    "sg:address":"675 Hansen Ave S",
    "sg:city":"Salem",
    "sg:classifiers":[
        {
            "category":"Professional",
            "subcategory":"Business Services",
            "type":"Services"
        }
    ],
    "sg:phone":"+1 503 588 2560",
    "sg:postcode":"97302",
    "sg:province":"OR",
    "wof:name":"Abacus Design LLC",
    "wof:placetype":"venue"
},
  "geometry": {"coordinates":[-123.053528,44.912244],"type":"Point"}
}