{
  "type": "Feature",
  "properties": {
    "iso:country":"US",
    "sg:address":"351 NE Billinger Dr",
    "sg:city":"Portland",
    "sg:classifiers":[
        {
            "category":"Building & Trades",
            "subcategory":"Construction",
            "type":"Services"
        }
    ],
    "sg:phone":"+1 503 262 8975",
    "sg:postcode":"97220",
    "sg:province":"OR",
    "sg:tags":[
        "house"
    ],
    "wof:name":"Rehlin Construction",
    "wof:placetype":"venue"
},
  "geometry": {"coordinates":[-122.574461,45.525348],"type":"Point"}
}