{
  "type": "Feature",
  "properties": {
    "iso:country":"US",
    "sg:address":"9700 NW Cornell Rd",
    "sg:city":"Portland",
    "sg:classifiers":[
        {
            "category":"Building & Trades",
            "subcategory":"Construction",
            "type":"Services"
        }
    ],
    "sg:phone":"+1 503 297 7158",
    "sg:postcode":"97229",
    "sg:province":"OR",
    "sg:tags":[
        "altering",
        "consultant",
        "remodeling",
        "contractor"
    ],
    "wof:name":"General Maintenance Co",
    "wof:placetype":"venue"
},
  "geometry": {"coordinates":[-122.777199,45.527489],"type":"Point"}
}