{
  "type": "Feature",
  "properties": {
    "iso:country":"US",
    "sg:address":"716 NW Beach Dr",
    "sg:city":"Newport",
    "sg:classifiers":[
        {
            "category":"Food & Beverages",
            "subcategory":"Specialty",
            "type":"Retail Goods"
        }
    ],
    "sg:phone":"+1 541 574 0545",
    "sg:postcode":"97365",
    "sg:province":"OR",
    "sg:tags":[
        "tea",
        "coffee"
    ],
    "wof:name":"Tea Party",
    "wof:placetype":"venue"
},
  "geometry": {"coordinates":[-124.061751,44.638973],"type":"Point"}
}