{
  "type": "Feature",
  "properties": {
    "iso:country":"US",
    "sg:address":"16124 SE Alder St Apt 9",
    "sg:city":"Portland",
    "sg:classifiers":[
        {
            "category":"Animal Shelter",
            "type":"Public Place"
        }
    ],
    "sg:phone":"+1 503 505 8266",
    "sg:postcode":"97233",
    "sg:province":"OR",
    "wof:name":"Zomi Association Of Usa",
    "wof:placetype":"venue"
},
  "geometry": {"coordinates":[-122.497488,45.517349],"type":"Point"}
}