{
  "type": "Feature",
  "properties": {
    "addr:full":"7269 SW Deerhaven Dr Corvallis OR 97333",
    "addr:housenumber":"7269",
    "addr:postcode":"97333",
    "addr:street":"Sw Deerhaven Dr",
    "iso:country":"US",
    "sg:address":"7269 SW Deerhaven Dr",
    "sg:city":"Corvallis",
    "sg:classifiers":[
        {
            "category":"Retail",
            "subcategory":"Repair Shop",
            "type":"Services"
        }
    ],
    "sg:phone":"+1 541 758 1456",
    "sg:postcode":"97333",
    "sg:province":"OR",
    "sg:tags":[
        "electronic",
        "business",
        "mfg"
    ],
    "wof:name":"Steves Locksmith Service",
    "wof:placetype":"venue"
},
  "geometry": {"coordinates":[-123.345221,44.499017],"type":"Point"}
}