{
  "type": "Feature",
  "properties": {
    "iso:country":"US",
    "sg:address":"287 Lappland Dr",
    "sg:city":"Grants Pass",
    "sg:classifiers":[
        {
            "category":"Building & Trades",
            "subcategory":"Construction",
            "type":"Services"
        }
    ],
    "sg:phone":"+1 541 479 2758",
    "sg:postcode":"97527",
    "sg:province":"OR",
    "sg:tags":[
        "well",
        "drilling"
    ],
    "wof:name":"Applegate Water Well Drilling",
    "wof:placetype":"venue"
},
  "geometry": {"coordinates":[-123.47456,42.417653],"type":"Point"}
}