{
  "type": "Feature",
  "properties": {
    "addr:full":"9020 SW Washington Square Rd Portland OR 97223",
    "addr:housenumber":"9020",
    "addr:postcode":"97223",
    "addr:street":"Sw Washington Square Rd",
    "iso:country":"US",
    "sg:address":"9020 SW Washington Square Rd",
    "sg:city":"Portland",
    "sg:classifiers":[
        {
            "category":"Professional",
            "subcategory":"Management & Consulting",
            "type":"Services"
        }
    ],
    "sg:phone":"+1 503 641 4300",
    "sg:postcode":"97223",
    "sg:province":"OR",
    "sg:tags":[
        "consultant",
        "business"
    ],
    "sg:website":"www.cadencemc.com",
    "wof:name":"Cadence Management Corp",
    "wof:placetype":"venue"
},
  "geometry": {"coordinates":[-122.78237300000001,45.455424],"type":"Point"}
}