{
  "type": "Feature",
  "properties": {
    "iso:country":"US",
    "sg:address":"1235 SE Division St",
    "sg:city":"Portland",
    "sg:classifiers":[
        {
            "category":"Banks & Credit Unions",
            "subcategory":"Financial Services",
            "type":"Services"
        }
    ],
    "sg:phone":"+1 503 488 5674",
    "sg:postcode":"97202",
    "sg:province":"OR",
    "sg:tags":[
        "broker",
        "mortgage"
    ],
    "wof:name":"First Priority Financial",
    "wof:placetype":"venue"
},
  "geometry": {"coordinates":[-122.652961,45.505167],"type":"Point"}
}