{
  "type": "Feature",
  "properties": {
    "iso:country":"US",
    "sg:address":"1824 Tiffany St",
    "sg:city":"Klamath Falls",
    "sg:classifiers":[
        {
            "category":"Shopping",
            "subcategory":"Musical Instruments",
            "type":"Retail Goods"
        }
    ],
    "sg:phone":"+1 541 884 5318",
    "sg:postcode":"97601",
    "sg:province":"OR",
    "wof:name":"TNT Custom Guitars",
    "wof:placetype":"venue"
},
  "geometry": {"coordinates":[-121.778424,42.244346],"type":"Point"}
}