{
  "type": "Feature",
  "properties": {
    "addr:full":"725 Hoyt St SE Salem OR 97302",
    "addr:housenumber":"725",
    "addr:postcode":"97302",
    "addr:street":"Hoyt St Se",
    "iso:country":"US",
    "sg:address":"725 Hoyt St SE",
    "sg:city":"Salem",
    "sg:classifiers":[
        {
            "category":"Shopping",
            "type":"Retail Goods"
        }
    ],
    "sg:phone":"+1 503 399 1964",
    "sg:postcode":"97302",
    "sg:province":"OR",
    "sg:tags":[
        "art",
        "gallery",
        "dealer"
    ],
    "wof:name":"T K Art Unltd",
    "wof:placetype":"venue"
},
  "geometry": {"coordinates":[-123.038246,44.919257],"type":"Point"}
}