{
  "type": "Feature",
  "properties": {
    "addr:full":"10005 SW Lancaster Rd Portland OR 97219",
    "addr:housenumber":"10005",
    "addr:postcode":"97219",
    "addr:street":"Sw Lancaster Rd",
    "iso:country":"US",
    "sg:address":"10005 SW Lancaster Rd",
    "sg:city":"Portland",
    "sg:classifiers":[
        {
            "category":"Insurance",
            "subcategory":"Insurance Agent",
            "type":"Services"
        }
    ],
    "sg:phone":"+1 503 246 5518",
    "sg:postcode":"97219",
    "sg:province":"OR",
    "wof:name":"Thornton & Assoc Inc",
    "wof:placetype":"venue"
},
  "geometry": {"coordinates":[-122.700215,45.454346],"type":"Point"}
}