{
  "type": "Feature",
  "properties": {
    "iso:country":"US",
    "sg:address":"10100 NE Prescott St",
    "sg:city":"Portland",
    "sg:classifiers":[
        {
            "category":"Government",
            "subcategory":"Office",
            "type":"Public Place"
        }
    ],
    "sg:phone":"+1 503 255 9805",
    "sg:postcode":"97220",
    "sg:province":"OR",
    "sg:tags":[
        "village"
    ],
    "wof:name":"Maywood Park City Office",
    "wof:placetype":"venue"
},
  "geometry": {"coordinates":[-122.559198,45.555314],"type":"Point"}
}