{
  "type": "Feature",
  "properties": {
    "addr:full":"3719 Pringle Rd SE Salem OR 97302",
    "addr:housenumber":"3719",
    "addr:postcode":"97302",
    "addr:street":"Pringle Rd Se",
    "iso:country":"US",
    "sg:address":"3719 Pringle Rd SE",
    "sg:city":"Salem",
    "sg:classifiers":[
        {
            "category":"Shopping",
            "subcategory":"Crafts & Fabrics",
            "type":"Retail Goods"
        }
    ],
    "sg:phone":"+1 503 364 6062",
    "sg:postcode":"97302",
    "sg:province":"OR",
    "sg:tags":[
        "sewing"
    ],
    "wof:name":"Hens Nest",
    "wof:placetype":"venue"
},
  "geometry": {"coordinates":[-123.026017,44.901783],"type":"Point"}
}