{
  "type": "Feature",
  "properties": {
    "addr:full":"2166 Vine St Grants Pass OR 97526",
    "addr:housenumber":"2166",
    "addr:postcode":"97526",
    "addr:street":"Vine St",
    "iso:country":"US",
    "sg:address":"2166 Vine St",
    "sg:city":"Grants Pass",
    "sg:classifiers":[
        {
            "category":"Social Services",
            "type":"Services"
        }
    ],
    "sg:phone":"+1 541 474 3110",
    "sg:postcode":"97526",
    "sg:province":"OR",
    "sg:tags":[
        "organization",
        "welfare"
    ],
    "wof:name":"Rogue Valley Council Of Govt",
    "wof:placetype":"venue"
},
  "geometry": {"coordinates":[-123.324898,42.464811],"type":"Point"}
}