{
  "type": "Feature",
  "properties": {
    "addr:full":"13106 NE Eugene St Portland OR 97230",
    "addr:housenumber":"13106",
    "addr:postcode":"97230",
    "addr:street":"Ne Eugene St",
    "iso:country":"US",
    "sg:address":"13106 NE Eugene St",
    "sg:city":"Portland",
    "sg:classifiers":[
        {
            "category":"Building & Trades",
            "subcategory":"Locksmith",
            "type":"Services"
        }
    ],
    "sg:phone":"+1 503 473 0156",
    "sg:postcode":"97230",
    "sg:province":"OR",
    "sg:tags":[
        "key"
    ],
    "wof:name":"Local 24 Locksmith",
    "wof:placetype":"venue"
},
  "geometry": {"coordinates":[-122.527624,45.53843],"type":"Point"}
}