{
  "type": "Feature",
  "properties": {
    "addr:full":"18500 SE Stark St Portland OR 97233",
    "addr:postcode":"18500;97233",
    "addr:street":"Se Stark St",
    "iso:country":"US",
    "sg:address":"18500 SE Stark St",
    "sg:city":"Portland",
    "sg:classifiers":[
        {
            "category":"Sports & Exercise",
            "subcategory":"Bowling",
            "type":"Entertainment"
        }
    ],
    "sg:phone":"+1 503 665 2123",
    "sg:postcode":"97233",
    "sg:province":"OR",
    "sg:tags":[
        "alley"
    ],
    "wof:name":"AMF",
    "wof:placetype":"venue"
},
  "geometry": {"coordinates":[-122.47066,45.519135],"type":"Point"}
}