{
  "type": "Feature",
  "properties": {
    "addr:full":"10618 SW 25th Ave Portland OR 97219",
    "addr:housenumber":"10618",
    "addr:postcode":"97219",
    "addr:street":"Sw 25Th Ave",
    "iso:country":"US",
    "sg:address":"10618 SW 25th Ave",
    "sg:city":"Portland",
    "sg:classifiers":[
        {
            "category":"Manufacturing",
            "subcategory":"Pottery",
            "type":"Manufacturing & Wholesale Goods"
        }
    ],
    "sg:phone":"+1 503 246 1430",
    "sg:postcode":"97219",
    "sg:province":"OR",
    "wof:name":"Grannie Anie Inc",
    "wof:placetype":"venue"
},
  "geometry": {"coordinates":[-122.702493,45.448504],"type":"Point"}
}