{
  "type": "Feature",
  "properties": {
    "iso:country":"US",
    "sg:address":"252 Queen Ave SE",
    "sg:city":"Albany",
    "sg:classifiers":[
        {
            "category":"Retail",
            "subcategory":"Auto Repair",
            "type":"Services"
        }
    ],
    "sg:phone":"+1 541 928 6353",
    "sg:postcode":"97322",
    "sg:province":"OR",
    "sg:tags":[
        "repairing",
        "automobile",
        "general",
        "automotive"
    ],
    "wof:name":"Continental Transmission RPS",
    "wof:placetype":"venue"
},
  "geometry": {"coordinates":[-123.099969,44.624941],"type":"Point"}
}