{
  "type": "Feature",
  "properties": {
    "addr:full":"1024 NW Cooke Ave Grants Pass OR 97526",
    "addr:housenumber":"1024",
    "addr:postcode":"97526",
    "addr:street":"Nw Cooke Ave",
    "iso:country":"US",
    "sg:address":"1024 NW Cooke Ave",
    "sg:city":"Grants Pass",
    "sg:classifiers":[
        {
            "category":"Real Estate",
            "subcategory":"Real Estate Operator",
            "type":"Services"
        }
    ],
    "sg:phone":"+1 541 479 2431",
    "sg:postcode":"97526",
    "sg:province":"OR",
    "sg:tags":[
        "property",
        "lessor"
    ],
    "wof:name":"Atlas Management",
    "wof:placetype":"venue"
},
  "geometry": {"coordinates":[-123.33354300000001,42.462681],"type":"Point"}
}