{
  "type": "Feature",
  "properties": {
    "addr:full":"7028 SW Nyberg St Tualatin OR 97062",
    "addr:housenumber":"7028",
    "addr:postcode":"97062",
    "addr:street":"Sw Nyberg St",
    "iso:country":"US",
    "sg:address":"7028 SW Nyberg St",
    "sg:city":"Tualatin",
    "sg:classifiers":[
        {
            "category":"Restaurant",
            "type":"Food & Drink"
        }
    ],
    "sg:phone":"+1 503 692 1390",
    "sg:postcode":"97062",
    "sg:province":"OR",
    "wof:name":"El Sol De Mexico",
    "wof:placetype":"venue"
},
  "geometry": {"coordinates":[-122.74900100000001,45.382801],"type":"Point"}
}