{
  "type": "Feature",
  "properties": {
    "addr:full":"9422 SW Washington Dr Portland OR 97223",
    "addr:housenumber":"9422",
    "addr:postcode":"97223",
    "addr:street":"Sw Washington Dr",
    "iso:country":"US",
    "sg:address":"9422 SW Washington Dr",
    "sg:city":"Portland",
    "sg:classifiers":[
        {
            "category":"Shopping",
            "subcategory":"Luggage & Leather Goods",
            "type":"Retail Goods"
        }
    ],
    "sg:phone":"+1 503 639 5066",
    "sg:postcode":"97223",
    "sg:province":"OR",
    "wof:name":"Latitudes",
    "wof:placetype":"venue"
},
  "geometry": {"coordinates":[-122.76589,45.452329],"type":"Point"}
}