{
  "type": "Feature",
  "properties": {
    "addr:full":"253 Marcy Loop Rd Grants Pass OR 97527",
    "addr:housenumber":"253",
    "addr:postcode":"97527",
    "addr:street":"Marcy Loop Rd",
    "iso:country":"US",
    "sg:address":"253 Marcy Loop Rd",
    "sg:city":"Grants Pass",
    "sg:classifiers":[
        {
            "category":"Professional",
            "subcategory":"Art Services",
            "type":"Services"
        }
    ],
    "sg:phone":"+1 541 476 9074",
    "sg:postcode":"97527",
    "sg:province":"OR",
    "sg:tags":[
        "commercial",
        "design"
    ],
    "wof:name":"Rose Cassano",
    "wof:placetype":"venue"
},
  "geometry": {"coordinates":[-123.483414,42.418544],"type":"Point"}
}