{
  "type": "Feature",
  "properties": {
    "iso:country":"US",
    "sg:address":"2522 SW Marshall Ave",
    "sg:city":"Pendleton",
    "sg:classifiers":[
        {
            "category":"Social Services",
            "subcategory":"Child Care",
            "type":"Services"
        }
    ],
    "sg:phone":"+1 541 276 1634",
    "sg:postcode":"97801",
    "sg:province":"OR",
    "sg:tags":[
        "day"
    ],
    "wof:name":"Magic Years Day Care",
    "wof:placetype":"venue"
},
  "geometry": {"coordinates":[-118.808806,45.654445],"type":"Point"}
}