{
  "type": "Feature",
  "properties": {
    "iso:country":"US",
    "sg:address":"4715 NE 106th Ave",
    "sg:city":"Portland",
    "sg:classifiers":[
        {
            "category":"Place Of Worship",
            "subcategory":"Church",
            "type":"Public Place"
        },
        {
            "category":"Place Of Worship",
            "type":"Public Place"
        }
    ],
    "sg:phone":"+1 503 253 5457",
    "sg:postcode":"97220",
    "sg:province":"OR",
    "sg:tags":[
        "testament",
        "christ-new",
        "christ",
        "churches-church"
    ],
    "wof:name":"Parkrose Cmnty Untd Ch Chri",
    "wof:placetype":"venue"
},
  "geometry": {"coordinates":[-122.55371100000001,45.557314],"type":"Point"}
}