{
  "type": "Feature",
  "properties": {
    "iso:country":"US",
    "sg:address":"548 NE 24th St",
    "sg:city":"Gresham",
    "sg:classifiers":[
        {
            "category":"Manufacturing",
            "subcategory":"Jewelry",
            "type":"Manufacturing & Wholesale Goods"
        }
    ],
    "sg:phone":"+1 503 319 0401",
    "sg:postcode":"97030",
    "sg:province":"OR",
    "sg:tags":[
        "custom"
    ],
    "wof:name":"Swiss Lock Inc",
    "wof:placetype":"venue"
},
  "geometry": {"coordinates":[-122.42564900000001,45.513592],"type":"Point"}
}