{
  "type": "Feature",
  "properties": {
    "addr:full":"8585 SW Hall Blvd Beaverton OR 97008",
    "addr:housenumber":"8585",
    "addr:postcode":"97008",
    "addr:street":"Sw Hall Blvd",
    "iso:country":"US",
    "sg:address":"8585 SW Hall Blvd",
    "sg:city":"Beaverton",
    "sg:classifiers":[
        {
            "category":"Wholesale",
            "subcategory":"Toys & Hobbies",
            "type":"Manufacturing & Wholesale Goods"
        }
    ],
    "sg:phone":"+1 503 293 8466",
    "sg:postcode":"97008",
    "sg:province":"OR",
    "wof:name":"Mattel Inc",
    "wof:placetype":"venue"
},
  "geometry": {"coordinates":[-122.788471,45.459136],"type":"Point"}
}