{
  "type": "Feature",
  "properties": {
    "addr:full":"15450 Boones Ferry Rd Lake Oswego OR 97035",
    "addr:housenumber":"15450",
    "addr:postcode":"97035",
    "addr:street":"Boones Ferry Rd",
    "iso:country":"US",
    "sg:address":"15450 Boones Ferry Rd",
    "sg:city":"Lake Oswego",
    "sg:phone":"+1 503 675 1955",
    "sg:postcode":"97035",
    "sg:province":"OR",
    "sg:tags":[
        "food"
    ],
    "wof:name":"Hybrid Marketing & Dist",
    "wof:placetype":"venue"
},
  "geometry": {"coordinates":[-122.71682199999999,45.413593],"type":"Point"}
}