{
  "type": "Feature",
  "properties": {
    "addr:full":"2000 Table Rock Rd Medford OR 97501",
    "addr:housenumber":"2000",
    "addr:postcode":"97501",
    "addr:street":"Table Rock Rd",
    "iso:country":"US",
    "sg:address":"2000 Table Rock Rd",
    "sg:city":"Medford",
    "sg:classifiers":[
        {
            "category":"Organizations",
            "subcategory":"Community Association",
            "type":"Services"
        }
    ],
    "sg:phone":"+1 541 773 9056",
    "sg:postcode":"97501",
    "sg:province":"OR",
    "wof:name":"Foe 2093",
    "wof:placetype":"venue"
},
  "geometry": {"coordinates":[-122.88284899999999,42.347085],"type":"Point"}
}