{
  "type": "Feature",
  "properties": {
    "iso:country":"US",
    "sg:address":"8000 SE 13th Ave",
    "sg:city":"Portland",
    "sg:classifiers":[
        {
            "category":"Food & Beverages",
            "subcategory":"Specialty",
            "type":"Retail Goods"
        },
        {
            "category":"Restaurant",
            "type":"Food & Drink"
        }
    ],
    "sg:phone":"+1 503 238 7255",
    "sg:postcode":"97202",
    "sg:province":"OR",
    "sg:tags":[
        "gluten-free",
        "pizza"
    ],
    "wof:name":"Picazzo's Gourmet Pizza and Salads",
    "wof:placetype":"venue"
},
  "geometry": {"coordinates":[-122.65268399999999,45.465603],"type":"Point"}
}