{
  "type": "Feature",
  "properties": {
    "addr:full":"51187 Blue River Dr Vida OR 97488",
    "addr:housenumber":"51187",
    "addr:postcode":"97488",
    "addr:street":"Blue River Dr",
    "iso:country":"US",
    "sg:address":"51187 Blue River Dr",
    "sg:city":"Vida",
    "sg:classifiers":[
        {
            "category":"Education",
            "subcategory":"School",
            "type":"Public Place"
        }
    ],
    "sg:phone":"+1 541 822 3315",
    "sg:postcode":"97488",
    "sg:province":"OR",
    "sg:tags":[
        "elementary"
    ],
    "wof:name":"Mc Kenzie Elementary School",
    "wof:placetype":"venue"
},
  "geometry": {"coordinates":[-122.361762,44.151817],"type":"Point"}
}