{
  "type": "Feature",
  "properties": {
    "iso:country":"US",
    "sg:address":"1833 N Sumner St",
    "sg:city":"Portland",
    "sg:classifiers":[
        {
            "category":"Wholesale",
            "subcategory":"Non-durable Goods",
            "type":"Manufacturing & Wholesale Goods"
        }
    ],
    "sg:phone":"+1 503 289 4210",
    "sg:postcode":"97217",
    "sg:province":"OR",
    "sg:tags":[
        "shop",
        "gift"
    ],
    "wof:name":"Eclectic Collage",
    "wof:placetype":"venue"
},
  "geometry": {"coordinates":[-122.685974,45.560549],"type":"Point"}
}