{
  "type": "Feature",
  "properties": {
    "addr:full":"973 Morton St Ashland OR 97520",
    "addr:housenumber":"973",
    "addr:postcode":"97520",
    "addr:street":"Morton St",
    "iso:country":"US",
    "sg:address":"973 Morton St",
    "sg:city":"Ashland",
    "sg:classifiers":[
        {
            "category":"Professional",
            "subcategory":"Management & Consulting",
            "type":"Services"
        }
    ],
    "sg:phone":"+1 541 552 0772",
    "sg:postcode":"97520",
    "sg:province":"OR",
    "sg:tags":[
        "travel",
        "agency"
    ],
    "wof:name":"Journeybound LLC",
    "wof:placetype":"venue"
},
  "geometry": {"coordinates":[-122.707365,42.180233],"type":"Point"}
}