{
  "type": "Feature",
  "properties": {
    "iso:country":"US",
    "sg:address":"4000 SW Fairview Blvd",
    "sg:city":"Portland",
    "sg:classifiers":[
        {
            "category":"Park",
            "type":"Public Place"
        },
        {
            "category":"Museum",
            "subcategory":"Botanical Garden",
            "type":"Entertainment"
        }
    ],
    "sg:phone":"+1 503 865 8733",
    "sg:postcode":"97221",
    "sg:province":"OR",
    "sg:website":"www.hoytarboretum.org",
    "wof:name":"Hoyt Arboretum",
    "wof:placetype":"venue"
},
  "geometry": {"coordinates":[-122.716003,45.516499],"type":"Point"}
}