{
  "type": "Feature",
  "properties": {
    "iso:country":"US",
    "sg:address":"14905 Butteville Rd NE",
    "sg:city":"Gervais",
    "sg:classifiers":[
        {
            "category":"Farming",
            "subcategory":"Livestock Farm",
            "type":"Manufacturing & Wholesale Goods"
        }
    ],
    "sg:phone":"+1 503 792 4760",
    "sg:postcode":"97026",
    "sg:province":"OR",
    "sg:tags":[
        "ranch"
    ],
    "wof:name":"Flying W Ranch",
    "wof:placetype":"venue"
},
  "geometry": {"coordinates":[-122.89748400000001,45.137705],"type":"Point"}
}