{
  "type": "Feature",
  "properties": {
    "iso:country":"US",
    "sg:address":"152 Arthur St",
    "sg:city":"Woodburn",
    "sg:classifiers":[
        {
            "category":"Education",
            "subcategory":"Special Training",
            "type":"Public Place"
        }
    ],
    "sg:phone":"+1 503 981 5746",
    "sg:postcode":"97071",
    "sg:province":"OR",
    "wof:name":"Arthur Academy Pub Chrtr Schl",
    "wof:placetype":"venue"
},
  "geometry": {"coordinates":[-122.85785799999999,45.141939],"type":"Point"}
}