{
  "type": "Feature",
  "properties": {
    "addr:full":"1420 NW Lovejoy Street Portland OR 97209",
    "addr:housenumber":"1420",
    "addr:postcode":"97209",
    "addr:street":"Nw Lovejoy Street",
    "iso:country":"US",
    "sg:address":"1420 NW Lovejoy Street",
    "sg:city":"Portland",
    "sg:classifiers":[
        {
            "category":"Health Services",
            "subcategory":"Doctor",
            "type":"Services"
        }
    ],
    "sg:phone":"+1 503 223 2493",
    "sg:postcode":"97209",
    "sg:province":"OR",
    "sg:tags":[
        "psychiatrist"
    ],
    "wof:name":"Lahn Patti Msw",
    "wof:placetype":"venue"
},
  "geometry": {"coordinates":[-122.685609,45.530007],"type":"Point"}
}