{
  "type": "Feature",
  "properties": {
    "iso:country":"US",
    "sg:address":"8455 SW Beaverton Hillsdale",
    "sg:city":"Portland",
    "sg:classifiers":[
        {
            "category":"Professional",
            "subcategory":"Computer Services",
            "type":"Services"
        }
    ],
    "sg:phone":"+1 503 297 8486",
    "sg:postcode":"97225",
    "sg:province":"OR",
    "sg:tags":[
        "repair"
    ],
    "wof:name":"Quality Office Systems",
    "wof:placetype":"venue"
},
  "geometry": {"coordinates":[-122.76366299999999,45.486166],"type":"Point"}
}