{
  "type": "Feature",
  "properties": {
    "iso:country":"US",
    "sg:address":"24235 SE Stark St",
    "sg:city":"Gresham",
    "sg:classifiers":[
        {
            "category":"Food & Beverages",
            "subcategory":"Groceries & Convenience Stores",
            "type":"Retail Goods"
        }
    ],
    "sg:phone":"+1 503 492 3956",
    "sg:postcode":"97030",
    "sg:province":"OR",
    "wof:name":"AM PM Mini Mart",
    "wof:placetype":"venue"
},
  "geometry": {"coordinates":[-122.410861,45.519128],"type":"Point"}
}