{
  "type": "Feature",
  "properties": {
    "iso:country":"US",
    "sg:address":"6047 SW 185th Ave",
    "sg:city":"Beaverton",
    "sg:classifiers":[
        {
            "category":"Fast Food",
            "type":"Food & Drink"
        },
        {
            "category":"Restaurant",
            "type":"Food & Drink"
        },
        {
            "category":"Professional",
            "type":"Services"
        }
    ],
    "sg:phone":"+1 503 591 9564",
    "sg:postcode":"97007",
    "sg:province":"OR",
    "sg:tags":[
        "delivery",
        "pizza",
        "take",
        "italian"
    ],
    "sg:website":"www.pizzahut.com",
    "wof:name":"Pizza Hut",
    "wof:placetype":"venue"
},
  "geometry": {"coordinates":[-122.867724,45.475721],"type":"Point"}
}