{
  "type": "Feature",
  "properties": {
    "iso:country":"US",
    "sg:address":"2588 Cubit St",
    "sg:city":"Eugene",
    "sg:classifiers":[
        {
            "category":"Recreation",
            "type":"Entertainment"
        }
    ],
    "sg:phone":"+1 541 688 3459",
    "sg:postcode":"97402",
    "sg:province":"OR",
    "sg:tags":[
        "club",
        "membership"
    ],
    "wof:name":"Bell Ringers Bowling League",
    "wof:placetype":"venue"
},
  "geometry": {"coordinates":[-123.169517,44.091616],"type":"Point"}
}