{
  "type": "Feature",
  "properties": {
    "addr:full":"638 NW 23rd Ave Portland OR 97255",
    "addr:housenumber":"638",
    "addr:postcode":"97255",
    "addr:street":"Nw 23Rd Ave",
    "iso:country":"US",
    "sg:address":"638 NW 23rd Ave",
    "sg:city":"Portland",
    "sg:classifiers":[
        {
            "category":"Wholesale",
            "subcategory":"Stationery",
            "type":"Manufacturing & Wholesale Goods"
        }
    ],
    "sg:phone":"+1 503 226 8000",
    "sg:postcode":"97255",
    "sg:province":"OR",
    "sg:tags":[
        "card"
    ],
    "sg:website":"www.paper-source.com/cgi-bin/pap...",
    "wof:name":"Paper Source",
    "wof:placetype":"venue"
},
  "geometry": {"coordinates":[-122.69852299999999,45.527481],"type":"Point"}
}