{
  "type": "Feature",
  "properties": {
    "addr:full":"331 S Main St Winston OR 97496",
    "addr:housenumber":"331",
    "addr:postcode":"97496",
    "addr:street":"S Main St",
    "iso:country":"US",
    "sg:address":"331 S Main St",
    "sg:city":"Winston",
    "sg:classifiers":[
        {
            "category":"Organizations",
            "subcategory":"Religious Organization",
            "type":"Services"
        }
    ],
    "sg:phone":"+1 541 679 3174",
    "sg:postcode":"97496",
    "sg:province":"OR",
    "sg:website":"www.lspmrc.org",
    "wof:name":"Living Stones Prison Ministrie",
    "wof:placetype":"venue"
},
  "geometry": {"coordinates":[-123.41461099999999,43.117298],"type":"Point"}
}