{
  "type": "Feature",
  "properties": {
    "iso:country":"US",
    "sg:address":"17752 Schalit Way",
    "sg:city":"Lake Oswego",
    "sg:classifiers":[
        {
            "category":"Professional",
            "subcategory":"Art Services",
            "type":"Services"
        }
    ],
    "sg:phone":"+1 503 816 7672",
    "sg:postcode":"97035",
    "sg:province":"OR",
    "sg:tags":[
        "commercial",
        "design"
    ],
    "wof:name":"Mentor Graphics",
    "wof:placetype":"venue"
},
  "geometry": {"coordinates":[-122.727543,45.399353],"type":"Point"}
}