{
  "type": "Feature",
  "properties": {
    "iso:country":"US",
    "sg:address":"839 SE 209th Ave",
    "sg:city":"Gresham",
    "sg:classifiers":[
        {
            "category":"Professional",
            "subcategory":"Management & Consulting",
            "type":"Services"
        }
    ],
    "sg:phone":"+1 503 666 4431",
    "sg:postcode":"97030",
    "sg:province":"OR",
    "sg:tags":[
        "business"
    ],
    "wof:name":"David Greenman",
    "wof:placetype":"venue"
},
  "geometry": {"coordinates":[-122.448614,45.514946],"type":"Point"}
}