{
  "type": "Feature",
  "properties": {
    "iso:country":"US",
    "sg:address":"14495 SW Beef Bend Road",
    "sg:city":"Portland",
    "sg:classifiers":[
        {
            "category":"Real Estate",
            "subcategory":"Real Estate Operator",
            "type":"Services"
        }
    ],
    "sg:phone":"+1 503 590 8585",
    "sg:postcode":"97224",
    "sg:province":"OR",
    "sg:tags":[
        "apartment"
    ],
    "wof:name":"Oakmont Apartments",
    "wof:placetype":"venue"
},
  "geometry": {"coordinates":[-122.826024,45.402117],"type":"Point"}
}