{
  "type": "Feature",
  "properties": {
    "iso:country":"US",
    "sg:address":"3940 SE 26th Ave",
    "sg:city":"Portland",
    "sg:classifiers":[
        {
            "category":"Health Services",
            "subcategory":"Health Practitioner",
            "type":"Services"
        }
    ],
    "sg:phone":"+1 503 892 2835",
    "sg:postcode":"97202",
    "sg:province":"OR",
    "wof:name":"Heather Teach Reiki Teacher",
    "wof:placetype":"venue"
},
  "geometry": {"coordinates":[-122.639516,45.493658],"type":"Point"}
}