{
  "type": "Feature",
  "properties": {
    "iso:country":"US",
    "sg:address":"449 Willamette St",
    "sg:city":"Eugene",
    "sg:classifiers":[
        {
            "category":"Real Estate",
            "subcategory":"Architect",
            "type":"Services"
        }
    ],
    "sg:phone":"+1 541 683 8661",
    "sg:postcode":"97401",
    "sg:province":"OR",
    "wof:name":"Bergsund Delaney Architecture",
    "wof:placetype":"venue"
},
  "geometry": {"coordinates":[-123.092652,44.054633],"type":"Point"}
}