{
  "type": "Feature",
  "properties": {
    "iso:country":"US",
    "sg:address":"9115 NE Airport Way",
    "sg:city":"Portland",
    "sg:classifiers":[
        {
            "category":"Retail",
            "subcategory":"Auto Rental",
            "type":"Services"
        }
    ],
    "sg:phone":"+1 503 282 2084",
    "sg:postcode":"97220",
    "sg:province":"OR",
    "sg:tags":[
        "car"
    ],
    "wof:name":"Cendant Car Rental Group Corporate",
    "wof:placetype":"venue"
},
  "geometry": {"coordinates":[-122.56890799999999,45.579864],"type":"Point"}
}