{
  "type": "Feature",
  "properties": {
    "iso:country":"US",
    "sg:address":"837 E Powell Blvd",
    "sg:city":"Gresham",
    "sg:classifiers":[
        {
            "category":"Health Services",
            "subcategory":"Chiropractor",
            "type":"Services"
        }
    ],
    "sg:phone":"+1 503 669 9495",
    "sg:postcode":"97030",
    "sg:province":"OR",
    "wof:name":"Advanced Care Chiropractic",
    "wof:placetype":"venue"
},
  "geometry": {"coordinates":[-122.421259,45.498093],"type":"Point"}
}