{
  "type": "Feature",
  "properties": {
    "addr:full":"10755 SW Beaverton Hillsdale Hwy # H Beaverton OR 97005",
    "addr:housenumber":"10755",
    "addr:postcode":"97005",
    "addr:street":"Sw Beaverton Hillsdale Hwy # H",
    "iso:country":"US",
    "sg:address":"10755 SW Beaverton Hillsdale Hwy # H",
    "sg:city":"Beaverton",
    "sg:classifiers":[
        {
            "category":"Personal",
            "subcategory":"Beauty Salon",
            "type":"Services"
        },
        {
            "category":"Personal",
            "subcategory":"Barber",
            "type":"Services"
        }
    ],
    "sg:phone":"+1 503 641 5308",
    "sg:postcode":"97005",
    "sg:province":"OR",
    "sg:tags":[
        "hair",
        "accessory",
        "stylist",
        "supply"
    ],
    "sg:website":"http://www.greatclips.com/",
    "wof:name":"Great Clips",
    "wof:placetype":"venue"
},
  "geometry": {"coordinates":[-122.787395,45.486576],"type":"Point"}
}