{
  "type": "Feature",
  "properties": {
    "addr:full":"1314 NW Glisan St Portland OR 97209",
    "addr:housenumber":"1314",
    "addr:postcode":"97209",
    "addr:street":"Nw Glisan St",
    "iso:country":"US",
    "sg:address":"1314 NW Glisan St",
    "sg:city":"Portland",
    "sg:classifiers":[
        {
            "category":"Shopping",
            "subcategory":"Used Merchandise",
            "type":"Retail Goods"
        }
    ],
    "sg:phone":"+1 503 274 0912",
    "sg:postcode":"97209",
    "sg:province":"OR",
    "sg:tags":[
        "antique"
    ],
    "wof:name":"V George Antiques",
    "wof:placetype":"venue"
},
  "geometry": {"coordinates":[-122.68518899999999,45.526395],"type":"Point"}
}