{
  "type": "Feature",
  "properties": {
    "iso:country":"US",
    "sg:address":"2474 Sand Creek Rd",
    "sg:city":"Grants Pass",
    "sg:classifiers":[
        {
            "category":"Shopping",
            "subcategory":"Catalog Store",
            "type":"Retail Goods"
        }
    ],
    "sg:phone":"+1 541 956 9943",
    "sg:postcode":"97527",
    "sg:province":"OR",
    "sg:tags":[
        "mail",
        "house"
    ],
    "wof:name":"W S Enterprises",
    "wof:placetype":"venue"
},
  "geometry": {"coordinates":[-123.378333,42.404233],"type":"Point"}
}