{
  "type": "Feature",
  "properties": {
    "addr:full":"30119 Berlin Rd Lebanon OR 97355",
    "addr:postcode":"30119;97355",
    "addr:street":"Berlin Rd",
    "iso:country":"US",
    "sg:address":"30119 Berlin Rd",
    "sg:city":"Lebanon",
    "sg:classifiers":[
        {
            "category":"Building & Trades",
            "subcategory":"Electrical",
            "type":"Services"
        }
    ],
    "sg:phone":"+1 541 451 2799",
    "sg:postcode":"97355",
    "sg:province":"OR",
    "sg:tags":[
        "electrical",
        "contractor"
    ],
    "wof:name":"Kendall R Evenhus",
    "wof:placetype":"venue"
},
  "geometry": {"coordinates":[-122.74664,44.474323],"type":"Point"}
}