{
  "type": "Feature",
  "properties": {
    "addr:full":"16850 NW Stoller Dr Portland OR 97229",
    "addr:housenumber":"16850",
    "addr:postcode":"97229",
    "addr:street":"Nw Stoller Dr",
    "iso:country":"US",
    "sg:address":"16850 NW Stoller Dr",
    "sg:city":"Portland",
    "sg:classifiers":[
        {
            "category":"Professional",
            "type":"Services"
        }
    ],
    "sg:phone":"+1 503 531 0915",
    "sg:postcode":"97229",
    "sg:province":"OR",
    "wof:name":"Dbimage",
    "wof:placetype":"venue"
},
  "geometry": {"coordinates":[-122.84998,45.553898],"type":"Point"}
}