{
  "type": "Feature",
  "properties": {
    "iso:country":"US",
    "sg:address":"125 N Spruceway Dr",
    "sg:city":"Waldport",
    "sg:classifiers":[
        {
            "category":"Real Estate",
            "subcategory":"Real Estate Services",
            "type":"Services"
        }
    ],
    "sg:phone":"+1 541 563 2722",
    "sg:postcode":"97394",
    "sg:province":"OR",
    "sg:tags":[
        "company",
        "title"
    ],
    "wof:name":"Western Title & Escrow Co",
    "wof:placetype":"venue"
},
  "geometry": {"coordinates":[-124.03175299999999,44.457791],"type":"Point"}
}