{
  "type": "Feature",
  "properties": {
    "iso:country":"US",
    "sg:address":"2020 SW 4th Ave Ste 190",
    "sg:city":"Portland",
    "sg:classifiers":[
        {
            "category":"Real Estate",
            "subcategory":"Real Estate Services",
            "type":"Services"
        },
        {
            "category":"Real Estate",
            "subcategory":"Real Estate Agent",
            "type":"Services"
        }
    ],
    "sg:phone":"+1 503 497 1031",
    "sg:postcode":"97201",
    "sg:province":"OR",
    "sg:tags":[
        "buyer",
        "consultant",
        "broker"
    ],
    "wof:name":"Asset Preservation, Inc.",
    "wof:placetype":"venue"
},
  "geometry": {"coordinates":[-122.68186799999999,45.508579],"type":"Point"}
}