{
  "type": "Feature",
  "properties": {
    "iso:country":"US",
    "sg:address":"1155 Darlene Ln",
    "sg:city":"Eugene",
    "sg:classifiers":[
        {
            "category":"Social Services",
            "subcategory":"Adult Care",
            "type":"Services"
        }
    ],
    "sg:phone":"+1 541 338 8780",
    "sg:postcode":"97401",
    "sg:province":"OR",
    "sg:tags":[
        "residential"
    ],
    "wof:name":"Sawyer House",
    "wof:placetype":"venue"
},
  "geometry": {"coordinates":[-123.11120699999999,44.084018],"type":"Point"}
}