{
  "type": "Feature",
  "properties": {
    "iso:country":"US",
    "sg:address":"11904 NE Halsey St",
    "sg:city":"Portland",
    "sg:classifiers":[
        {
            "category":"Autos & Motor Vehicles",
            "subcategory":"Auto Supplies",
            "type":"Retail Goods"
        }
    ],
    "sg:phone":"+1 503 252 9310",
    "sg:postcode":"97220",
    "sg:province":"OR",
    "sg:tags":[
        "automobile",
        "stereo",
        "radio"
    ],
    "wof:name":"NBA Car Stereos",
    "wof:placetype":"venue"
},
  "geometry": {"coordinates":[-122.540269,45.533472],"type":"Point"}
}