{
  "type": "Feature",
  "properties": {
    "iso:country":"US",
    "sg:address":"2981 Madison St",
    "sg:city":"Eugene",
    "sg:classifiers":[
        {
            "category":"Professional",
            "subcategory":"Computer Services",
            "type":"Services"
        }
    ],
    "sg:phone":"+1 541 687 0885",
    "sg:postcode":"97405",
    "sg:province":"OR",
    "sg:tags":[
        "consultant",
        "designer",
        "system",
        "repair"
    ],
    "sg:website":"http://www.sysresource.com",
    "wof:name":"Systems Resource Inc",
    "wof:placetype":"venue"
},
  "geometry": {"coordinates":[-123.10237499999999,44.024681],"type":"Point"}
}