{
  "type": "Feature",
  "properties": {
    "addr:full":"212 SW 3rd St Corvallis OR 97333",
    "addr:housenumber":"212",
    "addr:postcode":"97333",
    "addr:street":"Sw 3Rd St",
    "iso:country":"US",
    "sg:address":"212 SW 3rd St",
    "sg:city":"Corvallis",
    "sg:classifiers":[
        {
            "category":"Shopping",
            "subcategory":"Crafts & Fabrics",
            "type":"Retail Goods"
        }
    ],
    "sg:phone":"+1 541 752 4820",
    "sg:postcode":"97333",
    "sg:province":"OR",
    "sg:tags":[
        "material",
        "quilting",
        "supply"
    ],
    "wof:name":"Quiltwork Patches",
    "wof:placetype":"venue"
},
  "geometry": {"coordinates":[-123.26153100000001,44.563282],"type":"Point"}
}