{
  "type": "Feature",
  "properties": {
    "addr:full":"2411 5th St Tillamook OR 97141",
    "addr:housenumber":"2411",
    "addr:postcode":"97141",
    "addr:street":"5Th St",
    "iso:country":"US",
    "sg:address":"2411 5th St",
    "sg:city":"Tillamook",
    "sg:classifiers":[
        {
            "category":"Organizations",
            "subcategory":"Religious Organization",
            "type":"Services"
        }
    ],
    "sg:phone":"+1 503 842 6647",
    "sg:postcode":"97141",
    "sg:province":"OR",
    "sg:website":"www.sacredhearttillamook.org",
    "wof:name":"Sacred Heart Catholic Church",
    "wof:placetype":"venue"
},
  "geometry": {"coordinates":[-123.839935,45.454708],"type":"Point"}
}