{
  "type": "Feature",
  "properties": {
    "addr:full":"163 Taft Dr Roseburg OR 97470",
    "addr:housenumber":"163",
    "addr:postcode":"97470",
    "addr:street":"Taft Dr",
    "iso:country":"US",
    "sg:address":"163 Taft Dr",
    "sg:city":"Roseburg",
    "sg:classifiers":[
        {
            "category":"Building & Trades",
            "subcategory":"Construction",
            "type":"Services"
        }
    ],
    "sg:phone":"+1 541 673 6529",
    "sg:postcode":"97470",
    "sg:province":"OR",
    "wof:name":"Gausnell Rueben Grant",
    "wof:placetype":"venue"
},
  "geometry": {"coordinates":[-123.35039999999999,43.269733],"type":"Point"}
}