{
  "type": "Feature",
  "properties": {
    "addr:full":"84385 Keepers Rd Pleasant Hill OR 97455",
    "addr:postcode":"84385;97455",
    "addr:street":"Keepers Rd",
    "iso:country":"US",
    "sg:address":"84385 Keepers Rd",
    "sg:city":"Pleasant Hill",
    "sg:classifiers":[
        {
            "category":"Home & Garden",
            "subcategory":"Furniture",
            "type":"Retail Goods"
        }
    ],
    "sg:phone":"+1 541 747 5624",
    "sg:postcode":"97455",
    "sg:province":"OR",
    "wof:name":"Keepers Cabinets",
    "wof:placetype":"venue"
},
  "geometry": {"coordinates":[-122.89013799999999,43.956081],"type":"Point"}
}