{
  "type": "Feature",
  "properties": {
    "iso:country":"US",
    "sg:address":"1040 Commercial St SE",
    "sg:city":"Salem",
    "sg:classifiers":[
        {
            "category":"Professional",
            "subcategory":"Computer Services",
            "type":"Services"
        }
    ],
    "sg:phone":"+1 503 391 7009",
    "sg:postcode":"97302",
    "sg:province":"OR",
    "sg:tags":[
        "repair"
    ],
    "wof:name":"Cyber Help 4u",
    "wof:placetype":"venue"
},
  "geometry": {"coordinates":[-123.044014,44.930627],"type":"Point"}
}