{
  "type": "Feature",
  "properties": {
    "iso:country":"US",
    "sg:address":"880 S Front St",
    "sg:city":"Central Point",
    "sg:classifiers":[
        {
            "category":"Home & Garden",
            "subcategory":"Building Materials",
            "type":"Retail Goods"
        }
    ],
    "sg:phone":"+1 541 779 5775",
    "sg:postcode":"97502",
    "sg:province":"OR",
    "sg:tags":[
        "plywood",
        "veneer"
    ],
    "wof:name":"Cashway Plywood Ctr",
    "wof:placetype":"venue"
},
  "geometry": {"coordinates":[-122.912173,42.367114],"type":"Point"}
}