{
  "type": "Feature",
  "properties": {
    "addr:full":"2525 W Harvard Ave Roseburg OR 97470",
    "addr:housenumber":"2525",
    "addr:postcode":"97470",
    "addr:street":"W Harvard Ave",
    "iso:country":"US",
    "sg:address":"2525 W Harvard Ave",
    "sg:city":"Roseburg",
    "sg:classifiers":[
        {
            "category":"Food & Beverages",
            "subcategory":"Groceries & Convenience Stores",
            "type":"Retail Goods"
        }
    ],
    "sg:phone":"+1 541 673 4482",
    "sg:postcode":"97470",
    "sg:province":"OR",
    "sg:tags":[
        "grocer"
    ],
    "wof:name":"Michael's IGA",
    "wof:placetype":"venue"
},
  "geometry": {"coordinates":[-123.381191,43.214076],"type":"Point"}
}