{
  "type": "Feature",
  "properties": {
    "addr:full":"9400 SW Barbur Boulevard Portland OR 97219",
    "addr:housenumber":"9400",
    "addr:postcode":"97219",
    "addr:street":"Sw Barbur Boulevard",
    "iso:country":"US",
    "sg:address":"9400 SW Barbur Boulevard",
    "sg:city":"Portland",
    "sg:classifiers":[
        {
            "category":"Building & Trades",
            "subcategory":"Construction",
            "type":"Services"
        }
    ],
    "sg:phone":"+1 503 768 3017",
    "sg:postcode":"97219",
    "sg:province":"OR",
    "sg:tags":[
        "contractor"
    ],
    "wof:name":"Whitaker Ellis",
    "wof:placetype":"venue"
},
  "geometry": {"coordinates":[-122.71194300000001,45.45755],"type":"Point"}
}