{
  "type": "Feature",
  "properties": {
    "addr:full":"2660 Hastings St Eugene OR 97404",
    "addr:housenumber":"2660",
    "addr:postcode":"97404",
    "addr:street":"Hastings St",
    "iso:country":"US",
    "sg:address":"2660 Hastings St",
    "sg:city":"Eugene",
    "sg:classifiers":[
        {
            "category":"Banks & Credit Unions",
            "subcategory":"Investment Brokerage",
            "type":"Services"
        }
    ],
    "sg:phone":"+1 541 342 2790",
    "sg:postcode":"97404",
    "sg:province":"OR",
    "sg:tags":[
        "security"
    ],
    "wof:name":"Scherer Portfolio Management",
    "wof:placetype":"venue"
},
  "geometry": {"coordinates":[-123.14196,44.103104],"type":"Point"}
}