{
  "type": "Feature",
  "properties": {
    "iso:country":"US",
    "sg:address":"9650 SW Washington Square Rd",
    "sg:city":"Tigard",
    "sg:classifiers":[
        {
            "category":"Shopping",
            "subcategory":"Jewelry",
            "type":"Retail Goods"
        }
    ],
    "sg:phone":"+1 503 620 2678",
    "sg:postcode":"97223",
    "sg:province":"OR",
    "sg:tags":[
        "jeweler"
    ],
    "sg:website":"www.friedlanders.com",
    "wof:name":"Friedlander's Jewelers",
    "wof:placetype":"venue"
},
  "geometry": {"coordinates":[-122.78231,45.44774],"type":"Point"}
}