{
  "type": "Feature",
  "properties": {
    "iso:country":"US",
    "sg:address":"18841 S Cate Ln",
    "sg:city":"Beavercreek",
    "sg:classifiers":[
        {
            "category":"Professional",
            "subcategory":"Business Services",
            "type":"Services"
        }
    ],
    "sg:phone":"+1 503 632 3449",
    "sg:postcode":"97004",
    "sg:province":"OR",
    "wof:name":"Rlh2 Limited Partnership",
    "wof:placetype":"venue"
},
  "geometry": {"coordinates":[-122.479843,45.253248],"type":"Point"}
}