{
  "type": "Feature",
  "properties": {
    "addr:full":"3007 Pacific Ave Forest Grove OR 97116",
    "addr:housenumber":"3007",
    "addr:postcode":"97116",
    "addr:street":"Pacific Ave",
    "iso:country":"US",
    "sg:address":"3007 Pacific Ave",
    "sg:city":"Forest Grove",
    "sg:classifiers":[
        {
            "category":"Bars & Pubs",
            "type":"Food & Drink"
        }
    ],
    "sg:phone":"+1 503 357 4700",
    "sg:postcode":"97116",
    "sg:province":"OR",
    "wof:name":"Circle Inn Tavern",
    "wof:placetype":"venue"
},
  "geometry": {"coordinates":[-123.093728,45.520272],"type":"Point"}
}