{
  "type": "Feature",
  "properties": {
    "addr:full":"6620 NE 79th Ct Portland OR 97218",
    "addr:housenumber":"6620",
    "addr:postcode":"97218",
    "addr:street":"Ne 79Th Ct",
    "iso:country":"US",
    "sg:address":"6620 NE 79th Ct",
    "sg:city":"Portland",
    "sg:classifiers":[
        {
            "category":"Building & Trades",
            "subcategory":"Locksmith",
            "type":"Services"
        }
    ],
    "sg:phone":"+1 503 914 4378",
    "sg:postcode":"97218",
    "sg:province":"OR",
    "sg:tags":[
        "key"
    ],
    "wof:name":"A 1 Portland Locksmith",
    "wof:placetype":"venue"
},
  "geometry": {"coordinates":[-122.581024,45.571863],"type":"Point"}
}