{
  "type": "Feature",
  "properties": {
    "iso:country":"US",
    "sg:address":"8205 SW Creekside Pl",
    "sg:city":"Beaverton",
    "sg:classifiers":[
        {
            "category":"Building & Trades",
            "subcategory":"Construction",
            "type":"Services"
        }
    ],
    "sg:phone":"+1 503 641 8354",
    "sg:postcode":"97008",
    "sg:province":"OR",
    "sg:tags":[
        "general",
        "contractor"
    ],
    "wof:name":"Commercial Contractors Inc",
    "wof:placetype":"venue"
},
  "geometry": {"coordinates":[-122.792882,45.459299],"type":"Point"}
}