{
  "type": "Feature",
  "properties": {
    "iso:country":"US",
    "sg:address":"421 SW 10th Ave",
    "sg:city":"Portland",
    "sg:classifiers":[
        {
            "category":"Restaurant",
            "type":"Food & Drink"
        }
    ],
    "sg:phone":"+1 503 222 6551",
    "sg:postcode":"97253",
    "sg:province":"OR",
    "sg:tags":[
        "sandwich",
        "eating"
    ],
    "wof:name":"Pita Pit",
    "wof:placetype":"venue"
},
  "geometry": {"coordinates":[-122.68109200000001,45.521879],"type":"Point"}
}