{
  "type": "Feature",
  "properties": {
    "addr:full":"138 7th Ave SW Albany OR 97321",
    "addr:housenumber":"138",
    "addr:postcode":"97321",
    "addr:street":"7Th Ave Sw",
    "iso:country":"US",
    "sg:address":"138 7th Ave SW",
    "sg:city":"Albany",
    "sg:classifiers":[
        {
            "category":"Professional",
            "subcategory":"Lawyer & Legal Services",
            "type":"Services"
        }
    ],
    "sg:phone":"+1 541 928 7741",
    "sg:postcode":"97321",
    "sg:province":"OR",
    "sg:tags":[
        "attorney"
    ],
    "wof:name":"Donald P Reiling Law Office",
    "wof:placetype":"venue"
},
  "geometry": {"coordinates":[-123.104292,44.63259],"type":"Point"}
}