{
  "type": "Feature",
  "properties": {
    "addr:full":"870 Morton Pl Lebanon OR 97355",
    "addr:housenumber":"870",
    "addr:postcode":"97355",
    "addr:street":"Morton Pl",
    "iso:country":"US",
    "sg:address":"870 Morton Pl",
    "sg:city":"Lebanon",
    "sg:classifiers":[
        {
            "category":"Freight",
            "type":"Transportation"
        }
    ],
    "sg:phone":"+1 541 258 5962",
    "sg:postcode":"97355",
    "sg:province":"OR",
    "sg:tags":[
        "car",
        "pilot"
    ],
    "wof:name":"PDQ Pilot Car Inc",
    "wof:placetype":"venue"
},
  "geometry": {"coordinates":[-122.919152,44.545898],"type":"Point"}
}