{
  "type": "Feature",
  "properties": {
    "iso:country":"US",
    "sg:address":"10525 SW Lucas Ct",
    "sg:city":"Tualatin",
    "sg:classifiers":[
        {
            "category":"Wholesale",
            "subcategory":"Durable Goods & Equipment",
            "type":"Manufacturing & Wholesale Goods"
        }
    ],
    "sg:phone":"+1 503 691 8578",
    "sg:postcode":"97062",
    "sg:province":"OR",
    "sg:tags":[
        "professional"
    ],
    "wof:name":"American Optical",
    "wof:placetype":"venue"
},
  "geometry": {"coordinates":[-122.786173,45.392913],"type":"Point"}
}