{
  "type": "Feature",
  "properties": {
    "iso:country":"US",
    "sg:address":"10895 SW Avocet Ct",
    "sg:city":"Beaverton",
    "sg:classifiers":[
        {
            "category":"Building & Trades",
            "subcategory":"Construction",
            "type":"Services"
        }
    ],
    "sg:phone":"+1 503 590 1873",
    "sg:postcode":"97007",
    "sg:province":"OR",
    "sg:tags":[
        "speculative",
        "builder"
    ],
    "wof:name":"Williamsons Homes LLC",
    "wof:placetype":"venue"
},
  "geometry": {"coordinates":[-122.84582,45.441794],"type":"Point"}
}