{
  "type": "Feature",
  "properties": {
    "iso:country":"US",
    "sg:address":"5264 N Willis Blvd",
    "sg:city":"Portland",
    "sg:classifiers":[
        {
            "category":"Banks & Credit Unions",
            "subcategory":"Financial Services",
            "type":"Services"
        }
    ],
    "sg:phone":"+1 503 285 5755",
    "sg:postcode":"97203",
    "sg:province":"OR",
    "sg:tags":[
        "finance",
        "investment"
    ],
    "wof:name":"Gof Holdings LLC",
    "wof:placetype":"venue"
},
  "geometry": {"coordinates":[-122.722525,45.584295],"type":"Point"}
}