{
  "type": "Feature",
  "properties": {
    "iso:country":"US",
    "sg:address":"447 SE Baseline St",
    "sg:city":"Hillsboro",
    "sg:classifiers":[
        {
            "category":"Social Services",
            "type":"Services"
        }
    ],
    "sg:phone":"+1 503 640 4222",
    "sg:postcode":"97123",
    "sg:province":"OR",
    "sg:tags":[
        "counseling"
    ],
    "sg:website":"www.youthcontact.org",
    "wof:name":"Youth Contact",
    "wof:placetype":"venue"
},
  "geometry": {"coordinates":[-122.983296,45.520138],"type":"Point"}
}