{
  "type": "Feature",
  "properties": {
    "iso:country":"US",
    "sg:address":"6700 SW Oak St",
    "sg:city":"Portland",
    "sg:classifiers":[
        {
            "category":"Government",
            "subcategory":"Office",
            "type":"Public Place"
        }
    ],
    "sg:phone":"+1 503 229 5168",
    "sg:postcode":"97223",
    "sg:province":"OR",
    "sg:tags":[
        "national",
        "recruiting",
        "center",
        "guard",
        "army"
    ],
    "wof:name":"Army Nat Guard Recruiting Ctr",
    "wof:placetype":"venue"
},
  "geometry": {"coordinates":[-122.74588,45.444725],"type":"Point"}
}