{
  "type": "Feature",
  "properties": {
    "addr:full":"444 N Holly St Canby OR 97013",
    "addr:housenumber":"444",
    "addr:postcode":"97013",
    "addr:street":"N Holly St",
    "iso:country":"US",
    "sg:address":"444 N Holly St",
    "sg:city":"Canby",
    "sg:classifiers":[
        {
            "category":"Organizations",
            "subcategory":"Religious Organization",
            "type":"Services"
        }
    ],
    "sg:phone":"+1 503 266 4018",
    "sg:postcode":"97013",
    "sg:province":"OR",
    "sg:tags":[
        "churches-christian",
        "church"
    ],
    "sg:website":"http://www.canbychristian.org",
    "wof:name":"Canby Christian Church",
    "wof:placetype":"venue"
},
  "geometry": {"coordinates":[-122.695813,45.265134],"type":"Point"}
}