{
  "type": "Feature",
  "properties": {
    "iso:country":"US",
    "sg:address":"49576 Highway 101",
    "sg:city":"Bandon",
    "sg:classifiers":[
        {
            "category":"Farming",
            "subcategory":"Farm",
            "type":"Manufacturing & Wholesale Goods"
        }
    ],
    "sg:phone":"+1 541 404 1368",
    "sg:postcode":"97411",
    "sg:province":"OR",
    "wof:name":"Jim Craig Feed And Farm Supply",
    "wof:placetype":"venue"
},
  "geometry": {"coordinates":[-124.398453,43.123499],"type":"Point"}
}