{
  "type": "Feature",
  "properties": {
    "addr:full":"1577 Glide Loop Dr Glide OR 97443",
    "addr:housenumber":"1577",
    "addr:postcode":"97443",
    "addr:street":"Glide Loop Dr",
    "iso:country":"US",
    "sg:address":"1577 Glide Loop Dr",
    "sg:city":"Glide",
    "sg:classifiers":[
        {
            "category":"Manufacturing",
            "subcategory":"Lumber",
            "type":"Manufacturing & Wholesale Goods"
        }
    ],
    "sg:phone":"+1 541 496 3571",
    "sg:postcode":"97443",
    "sg:province":"OR",
    "sg:tags":[
        "sawmill"
    ],
    "wof:name":"Glide Lumber Products Co",
    "wof:placetype":"venue"
},
  "geometry": {"coordinates":[-123.091447,43.308012],"type":"Point"}
}