{
  "type": "Feature",
  "properties": {
    "iso:country":"US",
    "sg:address":"28378 N Umpqua Hwy",
    "sg:city":"Idleyld Park",
    "sg:classifiers":[
        {
            "category":"Building & Trades",
            "subcategory":"Plumbing",
            "type":"Services"
        }
    ],
    "sg:phone":"+1 541 496 0397",
    "sg:postcode":"97447",
    "sg:province":"OR",
    "sg:tags":[
        "tank",
        "septic"
    ],
    "wof:name":"Honey Creek Logging & Excvtn",
    "wof:placetype":"venue"
},
  "geometry": {"coordinates":[-122.956561,43.305011],"type":"Point"}
}