{
  "type": "Feature",
  "properties": {
    "iso:country":"US",
    "sg:address":"1515 SW 5th Ave Ste 1020",
    "sg:city":"Portland",
    "sg:classifiers":[
        {
            "category":"Professional",
            "subcategory":"Lawyer & Legal Services",
            "type":"Services"
        }
    ],
    "sg:phone":"+1 503 222 4070",
    "sg:postcode":"97201",
    "sg:province":"OR",
    "sg:tags":[
        "personal",
        "injury"
    ],
    "wof:name":"Jackson Kathryn Attorney At Law",
    "wof:placetype":"venue"
},
  "geometry": {"coordinates":[-122.681,45.513401],"type":"Point"}
}