{
  "type": "Feature",
  "properties": {
    "iso:country":"US",
    "sg:address":"1060 W 8th Ave",
    "sg:city":"Eugene",
    "sg:classifiers":[
        {
            "category":"Professional",
            "subcategory":"Business Services",
            "type":"Services"
        }
    ],
    "sg:phone":"+1 541 485 5377",
    "sg:postcode":"97402",
    "sg:province":"OR",
    "wof:name":"Jme Design",
    "wof:placetype":"venue"
},
  "geometry": {"coordinates":[-123.108723,44.050831],"type":"Point"}
}