{
  "type": "Feature",
  "properties": {
    "iso:country":"US",
    "sg:address":"14071 NE Arndt Rd",
    "sg:city":"Aurora",
    "sg:classifiers":[
        {
            "category":"Wholesale",
            "subcategory":"Plants",
            "type":"Manufacturing & Wholesale Goods"
        }
    ],
    "sg:phone":"+1 503 678 5600",
    "sg:postcode":"97002",
    "sg:province":"OR",
    "sg:tags":[
        "florist"
    ],
    "wof:name":"Florexpo",
    "wof:placetype":"venue"
},
  "geometry": {"coordinates":[-122.778853,45.259637],"type":"Point"}
}