{
  "type": "Feature",
  "properties": {
    "iso:country":"US",
    "sg:address":"151 E Columbia River Hwy",
    "sg:city":"Troutdale",
    "sg:classifiers":[
        {
            "category":"Insurance",
            "subcategory":"Insurance Agent",
            "type":"Services"
        }
    ],
    "sg:phone":"+1 503 665 5597",
    "sg:postcode":"97060",
    "sg:province":"OR",
    "wof:name":"Farmers Insurance Group",
    "wof:placetype":"venue"
},
  "geometry": {"coordinates":[-122.38770100000001,45.540824],"type":"Point"}
}