{
  "type": "Feature",
  "properties": {
    "iso:country":"US",
    "sg:address":"15683 SE Hugh Ave",
    "sg:city":"Portland",
    "sg:classifiers":[
        {
            "category":"Building & Trades",
            "subcategory":"Construction",
            "type":"Services"
        }
    ],
    "sg:phone":"+1 503 653 2812",
    "sg:postcode":"97267",
    "sg:province":"OR",
    "sg:tags":[
        "electrical",
        "contractor"
    ],
    "wof:name":"Century Cable TV Service Inc",
    "wof:placetype":"venue"
},
  "geometry": {"coordinates":[-122.638425,45.408985],"type":"Point"}
}