{
  "type": "Feature",
  "properties": {
    "iso:country":"US",
    "sg:address":"1050 NE 3rd St",
    "sg:city":"Prineville",
    "sg:classifiers":[
        {
            "category":"Travel",
            "subcategory":"Hotels & Motels",
            "type":"Entertainment"
        }
    ],
    "sg:phone":"+1 541 447 4152",
    "sg:postcode":"97754",
    "sg:province":"OR",
    "sg:tags":[
        "breakfast",
        "apartment",
        "inn",
        "bed"
    ],
    "wof:name":"Executive Inn",
    "wof:placetype":"venue"
},
  "geometry": {"coordinates":[-120.834328,44.302921],"type":"Point"}
}