{
  "type": "Feature",
  "properties": {
    "iso:country":"US",
    "sg:address":"3677 SE Monroe St",
    "sg:city":"Milwaukie",
    "sg:classifiers":[
        {
            "category":"Real Estate",
            "subcategory":"Real Estate Agent",
            "type":"Services"
        }
    ],
    "sg:phone":"+1 503 653 3571",
    "sg:postcode":"97222",
    "sg:province":"OR",
    "sg:tags":[
        "management"
    ],
    "wof:name":"Noble House",
    "wof:placetype":"venue"
},
  "geometry": {"coordinates":[-122.626304,45.445332],"type":"Point"}
}