{
  "type": "Feature",
  "properties": {
    "addr:full":"565 W Hermiston Ave Hermiston OR 97838",
    "addr:housenumber":"565",
    "addr:postcode":"97838",
    "addr:street":"W Hermiston Ave",
    "iso:country":"US",
    "sg:address":"565 W Hermiston Ave",
    "sg:city":"Hermiston",
    "sg:classifiers":[
        {
            "category":"Social Services",
            "type":"Services"
        }
    ],
    "sg:phone":"+1 541 567 0888",
    "sg:postcode":"97838",
    "sg:province":"OR",
    "sg:tags":[
        "pregnancy",
        "counseling",
        "information"
    ],
    "wof:name":"PCS Womens Care Ctr",
    "wof:placetype":"venue"
},
  "geometry": {"coordinates":[-119.297363,45.840451],"type":"Point"}
}