{
  "type": "Feature",
  "properties": {
    "iso:country":"US",
    "sg:address":"490 NE 219th Ave",
    "sg:city":"Gresham",
    "sg:classifiers":[
        {
            "category":"Professional",
            "subcategory":"Management & Consulting",
            "type":"Services"
        }
    ],
    "sg:phone":"+1 503 661 7562",
    "sg:postcode":"97030",
    "sg:province":"OR",
    "sg:tags":[
        "consultant",
        "business"
    ],
    "wof:name":"Alexander Manufacturing",
    "wof:placetype":"venue"
},
  "geometry": {"coordinates":[-122.437221,45.527742],"type":"Point"}
}