{
  "type": "Feature",
  "properties": {
    "iso:country":"US",
    "sg:address":"2699 W Main St",
    "sg:city":"Medford",
    "sg:classifiers":[
        {
            "category":"Restaurant",
            "type":"Food & Drink"
        }
    ],
    "sg:menulink":"http://www.allmenus.com/or/medford/235973-original-roadhouse-grill/menu/",
    "sg:phone":"+1 541 776 3050",
    "sg:postcode":"97501",
    "sg:province":"OR",
    "sg:tags":[
        "american"
    ],
    "wof:name":"Original Roadhouse Grill",
    "wof:placetype":"venue"
},
  "geometry": {"coordinates":[-122.907312,42.32373],"type":"Point"}
}