{
  "type": "Feature",
  "properties": {
    "addr:full":"502 NW Mawrcrest Pl Gresham OR 97030",
    "addr:housenumber":"502",
    "addr:postcode":"97030",
    "addr:street":"Nw Mawrcrest Pl",
    "iso:country":"US",
    "sg:address":"502 NW Mawrcrest Pl",
    "sg:city":"Gresham",
    "sg:classifiers":[
        {
            "category":"Professional",
            "type":"Services"
        }
    ],
    "sg:phone":"+1 503 665 0923",
    "sg:postcode":"97030",
    "sg:province":"OR",
    "wof:name":"Wellington House Inc",
    "wof:placetype":"venue"
},
  "geometry": {"coordinates":[-122.455725,45.501264],"type":"Point"}
}