{
  "type": "Feature",
  "properties": {
    "addr:full":"4209 Birdhaven Loop Newberg OR 97132",
    "addr:housenumber":"4209",
    "addr:postcode":"97132",
    "addr:street":"Birdhaven Loop",
    "iso:country":"US",
    "sg:address":"4209 Birdhaven Loop",
    "sg:city":"Newberg",
    "sg:classifiers":[
        {
            "category":"Professional",
            "type":"Services"
        }
    ],
    "sg:phone":"+1 503 554 1164",
    "sg:postcode":"97132",
    "sg:province":"OR",
    "wof:name":"Inflow Systems",
    "wof:placetype":"venue"
},
  "geometry": {"coordinates":[-122.933403,45.314626],"type":"Point"}
}