{
  "type": "Feature",
  "properties": {
    "addr:full":"11370 SE 82nd Ave Portland OR 97255",
    "addr:postcode":"11370;97255",
    "addr:street":"Se 82Nd Ave",
    "iso:country":"US",
    "sg:address":"11370 SE 82nd Ave",
    "sg:city":"Portland",
    "sg:classifiers":[
        {
            "category":"Shopping",
            "type":"Retail Goods"
        }
    ],
    "sg:phone":"+1 503 653 7913",
    "sg:postcode":"97255",
    "sg:province":"OR",
    "sg:website":"www.tjmaxx.com/search_results.as...",
    "wof:name":"TJ Maxx",
    "wof:placetype":"venue"
},
  "geometry": {"coordinates":[-122.579052,45.461159],"type":"Point"}
}