{
  "type": "Feature",
  "properties": {
    "iso:country":"US",
    "sg:address":"3198 S 6th St",
    "sg:city":"Klamath Falls",
    "sg:classifiers":[
        {
            "category":"Shopping",
            "subcategory":"Shoes",
            "type":"Retail Goods"
        }
    ],
    "sg:phone":"+1 541 882 3255",
    "sg:postcode":"97603",
    "sg:province":"OR",
    "sg:tags":[
        "family"
    ],
    "wof:name":"House Of Shoes",
    "wof:placetype":"venue"
},
  "geometry": {"coordinates":[-121.750574,42.207982],"type":"Point"}
}