{
  "type": "Feature",
  "properties": {
    "addr:full":"217 5th St Silverton OR 97381",
    "addr:housenumber":"217",
    "addr:postcode":"97381",
    "addr:street":"5Th St",
    "iso:country":"US",
    "sg:address":"217 5th St",
    "sg:city":"Silverton",
    "sg:classifiers":[
        {
            "category":"Arts & Performance",
            "subcategory":"Theater",
            "type":"Entertainment"
        }
    ],
    "sg:phone":"+1 503 873 6054",
    "sg:postcode":"97381",
    "sg:province":"OR",
    "sg:tags":[
        "group"
    ],
    "wof:name":"Jimnalan",
    "wof:placetype":"venue"
},
  "geometry": {"coordinates":[-122.77701,45.007429],"type":"Point"}
}