{
  "type": "Feature",
  "properties": {
    "addr:full":"705 NE Circle Blvd Corvallis OR 97330",
    "addr:housenumber":"705",
    "addr:postcode":"97330",
    "addr:street":"Ne Circle Blvd",
    "iso:country":"US",
    "sg:address":"705 NE Circle Blvd",
    "sg:city":"Corvallis",
    "sg:classifiers":[
        {
            "category":"Home & Garden",
            "subcategory":"Carpets & Floor Coverings",
            "type":"Retail Goods"
        }
    ],
    "sg:phone":"+1 541 753 0755",
    "sg:postcode":"97330",
    "sg:province":"OR",
    "wof:name":"Northwest Floors Carpets Plus",
    "wof:placetype":"venue"
},
  "geometry": {"coordinates":[-123.251301,44.588939],"type":"Point"}
}