{
  "type": "Feature",
  "properties": {
    "iso:country":"US",
    "sg:address":"220 SW 6th St",
    "sg:city":"Grants Pass",
    "sg:classifiers":[
        {
            "category":"Shopping",
            "subcategory":"Gifts & Souvenirs",
            "type":"Retail Goods"
        }
    ],
    "sg:phone":"+1 541 474 6666",
    "sg:postcode":"97526",
    "sg:province":"OR",
    "sg:tags":[
        "shop"
    ],
    "wof:name":"Blue Moon",
    "wof:placetype":"venue"
},
  "geometry": {"coordinates":[-123.327528,42.438377],"type":"Point"}
}