{
  "type": "Feature",
  "properties": {
    "iso:country":"US",
    "sg:address":"405 W Arlington St",
    "sg:city":"Gladstone",
    "sg:classifiers":[
        {
            "category":"Social Services",
            "type":"Services"
        }
    ],
    "sg:phone":"+1 503 656 7207",
    "sg:postcode":"97027",
    "sg:province":"OR",
    "sg:tags":[
        "child",
        "referral",
        "care"
    ],
    "wof:name":"Acts Oregon",
    "wof:placetype":"venue"
},
  "geometry": {"coordinates":[-122.599479,45.376214],"type":"Point"}
}