{
  "type": "Feature",
  "properties": {
    "iso:country":"US",
    "sg:address":"12389 SW Millview Ct",
    "sg:city":"Portland",
    "sg:classifiers":[
        {
            "category":"Professional",
            "type":"Services"
        }
    ],
    "sg:phone":"+1 503 590 2495",
    "sg:postcode":"97223",
    "sg:province":"OR",
    "wof:name":"Fham International",
    "wof:placetype":"venue"
},
  "geometry": {"coordinates":[-122.803957,45.438298],"type":"Point"}
}