{
  "type": "Feature",
  "properties": {
    "iso:country":"US",
    "sg:address":"16700 Stagestop Dr",
    "sg:city":"Bend",
    "sg:classifiers":[
        {
            "category":"Professional",
            "subcategory":"Management & Consulting",
            "type":"Services"
        }
    ],
    "sg:phone":"+1 541 593 8932",
    "sg:postcode":"97707",
    "sg:province":"OR",
    "wof:name":"PM Associates",
    "wof:placetype":"venue"
},
  "geometry": {"coordinates":[-121.491529,43.823351],"type":"Point"}
}