{
  "type": "Feature",
  "properties": {
    "iso:country":"US",
    "sg:address":"4260 SE Hawthorne Blvd",
    "sg:city":"Portland",
    "sg:classifiers":[
        {
            "category":"Bars & Pubs",
            "type":"Food & Drink"
        }
    ],
    "sg:menulink":"http://www.allmenus.com/or/portland/6589-the-empire-room-bistro--bar/menu/",
    "sg:phone":"+1 503 231 9225",
    "sg:postcode":"97215",
    "sg:province":"OR",
    "sg:tags":[
        "american"
    ],
    "wof:name":"The Empire Room Bistro & Bar",
    "wof:placetype":"venue"
},
  "geometry": {"coordinates":[-122.61870999999999,45.512043],"type":"Point"}
}