{
  "type": "Feature",
  "properties": {
    "addr:full":"1870 Saint Helens St St Helens OR 97051",
    "addr:housenumber":"1870",
    "addr:postcode":"97051",
    "addr:street":"Saint Helens St",
    "iso:country":"US",
    "sg:address":"1870 Saint Helens St",
    "sg:city":"St Helens",
    "sg:classifiers":[
        {
            "category":"Health Services",
            "subcategory":"Doctor",
            "type":"Services"
        }
    ],
    "sg:phone":"+1 503 397 9038",
    "sg:postcode":"97051",
    "sg:province":"OR",
    "sg:tags":[
        "physician",
        "surgeon"
    ],
    "wof:name":"Paul L Tesar MD",
    "wof:placetype":"venue"
},
  "geometry": {"coordinates":[-122.816513,45.86008],"type":"Point"}
}