{
  "type": "Feature",
  "properties": {
    "iso:country":"US",
    "sg:address":"2245 NE 10th Ave",
    "sg:city":"Hillsboro",
    "sg:classifiers":[
        {
            "category":"Professional",
            "subcategory":"Detective & Security Services",
            "type":"Services"
        }
    ],
    "sg:phone":"+1 503 380 3234",
    "sg:postcode":"97124",
    "sg:province":"OR",
    "sg:tags":[
        "information",
        "bureau"
    ],
    "wof:name":"Pdx Marketing & Services",
    "wof:placetype":"venue"
},
  "geometry": {"coordinates":[-122.972748,45.540567],"type":"Point"}
}