{
  "type": "Feature",
  "properties": {
    "iso:country":"US",
    "sg:address":"9125 SW 26th Ave",
    "sg:city":"Portland",
    "sg:classifiers":[
        {
            "category":"Wholesale",
            "subcategory":"Construction Materials",
            "type":"Manufacturing & Wholesale Goods"
        }
    ],
    "sg:phone":"+1 503 244 7264",
    "sg:postcode":"97219",
    "sg:province":"OR",
    "wof:name":"Global Homes Inc",
    "wof:placetype":"venue"
},
  "geometry": {"coordinates":[-122.70372500000001,45.459558],"type":"Point"}
}