{
  "type": "Feature",
  "properties": {
    "iso:country":"US",
    "sg:address":"2217 NW Johnson Street",
    "sg:city":"Portland",
    "sg:classifiers":[
        {
            "category":"Real Estate",
            "subcategory":"Architect",
            "type":"Services"
        }
    ],
    "sg:phone":"+1 503 223 8082",
    "sg:postcode":"97210",
    "sg:province":"OR",
    "wof:name":"Genasci & Associates",
    "wof:placetype":"venue"
},
  "geometry": {"coordinates":[-122.69703,45.528286],"type":"Point"}
}