{
  "type": "Feature",
  "properties": {
    "iso:country":"US",
    "sg:address":"16834 Stellar Dr",
    "sg:city":"Sherwood",
    "sg:classifiers":[
        {
            "category":"Banks & Credit Unions",
            "subcategory":"Bank",
            "type":"Services"
        }
    ],
    "sg:phone":"+1 503 381 0464",
    "sg:postcode":"97140",
    "sg:province":"OR",
    "sg:tags":[
        "mortgage"
    ],
    "wof:name":"Barnes Serenity Inc",
    "wof:placetype":"venue"
},
  "geometry": {"coordinates":[-122.850777,45.352353],"type":"Point"}
}