{
  "type": "Feature",
  "properties": {
    "iso:country":"US",
    "sg:address":"6513 SE Apple St",
    "sg:city":"Portland",
    "sg:classifiers":[
        {
            "category":"Manufacturing",
            "subcategory":"Chemicals & Compounds",
            "type":"Manufacturing & Wholesale Goods"
        }
    ],
    "sg:phone":"+1 503 786 3807",
    "sg:postcode":"97222",
    "sg:province":"OR",
    "sg:tags":[
        "resin"
    ],
    "wof:name":"Heavy Resin Productions",
    "wof:placetype":"venue"
},
  "geometry": {"coordinates":[-122.59541400000001,45.435989],"type":"Point"}
}