{
  "type": "Feature",
  "properties": {
    "addr:full":"3375 SE Woodward St Portland OR 97202",
    "addr:housenumber":"3375",
    "addr:postcode":"97202",
    "addr:street":"Se Woodward St",
    "iso:country":"US",
    "sg:address":"3375 SE Woodward St",
    "sg:city":"Portland",
    "sg:classifiers":[
        {
            "category":"Professional",
            "subcategory":"Management & Consulting",
            "type":"Services"
        }
    ],
    "sg:phone":"+1 503 233 3859",
    "sg:postcode":"97202",
    "sg:province":"OR",
    "sg:tags":[
        "consultant",
        "business"
    ],
    "wof:name":"Unlimited Potentials",
    "wof:placetype":"venue"
},
  "geometry": {"coordinates":[-122.62992800000001,45.502015],"type":"Point"}
}