{
  "type": "Feature",
  "properties": {
    "iso:country":"US",
    "sg:address":"183 Nob Hill Rd",
    "sg:city":"Roseburg",
    "sg:classifiers":[
        {
            "category":"Building & Trades",
            "subcategory":"Construction",
            "type":"Services"
        }
    ],
    "sg:phone":"+1 541 673 7854",
    "sg:postcode":"97470",
    "sg:province":"OR",
    "sg:tags":[
        "house",
        "contractor"
    ],
    "wof:name":"Jenkins Construction Co",
    "wof:placetype":"venue"
},
  "geometry": {"coordinates":[-123.47945,43.250401],"type":"Point"}
}