{
  "type": "Feature",
  "properties": {
    "addr:full":"2004 NW 36th St Lincoln City OR 97367",
    "addr:housenumber":"2004",
    "addr:postcode":"97367",
    "addr:street":"Nw 36Th St",
    "iso:country":"US",
    "sg:address":"2004 NW 36th St",
    "sg:city":"Lincoln City",
    "sg:classifiers":[
        {
            "category":"Banks & Credit Unions",
            "subcategory":"Bank",
            "type":"Services"
        }
    ],
    "sg:phone":"+1 541 994 9889",
    "sg:postcode":"97367",
    "sg:province":"OR",
    "wof:name":"TLC Federal Credit Union",
    "wof:placetype":"venue"
},
  "geometry": {"coordinates":[-124.00644699999999,44.992615],"type":"Point"}
}