{
  "type": "Feature",
  "properties": {
    "iso:country":"US",
    "sg:address":"1103 NW Stannium Rd",
    "sg:city":"Bend",
    "sg:classifiers":[
        {
            "category":"Professional",
            "subcategory":"Accounting & Tax Preparation",
            "type":"Services"
        }
    ],
    "sg:phone":"+1 541 388 1284",
    "sg:postcode":"97701",
    "sg:province":"OR",
    "wof:name":"Solomon Small Business Service",
    "wof:placetype":"venue"
},
  "geometry": {"coordinates":[-121.337923,44.058937],"type":"Point"}
}