{
  "type": "Feature",
  "properties": {
    "addr:full":"19335 Willamette Dr West Linn OR 97068",
    "addr:housenumber":"19335",
    "addr:postcode":"97068",
    "addr:street":"Willamette Dr",
    "iso:country":"US",
    "sg:address":"19335 Willamette Dr",
    "sg:city":"West Linn",
    "sg:classifiers":[
        {
            "category":"Retail",
            "subcategory":"Portrait Studio",
            "type":"Services"
        }
    ],
    "sg:phone":"+1 503 697 7999",
    "sg:postcode":"97068",
    "sg:province":"OR",
    "sg:tags":[
        "photography",
        "store"
    ],
    "wof:name":"Ollar Photography",
    "wof:placetype":"venue"
},
  "geometry": {"coordinates":[-122.639,45.385101],"type":"Point"}
}