{
  "type": "Feature",
  "properties": {
    "addr:full":"9300 NE Halsey St Portland OR 97220",
    "addr:housenumber":"9300",
    "addr:postcode":"97220",
    "addr:street":"Ne Halsey St",
    "iso:country":"US",
    "sg:address":"9300 NE Halsey St",
    "sg:city":"Portland",
    "sg:classifiers":[
        {
            "category":"Building & Trades",
            "subcategory":"Plumbing",
            "type":"Services"
        }
    ],
    "sg:phone":"+1 503 661 6097",
    "sg:postcode":"97220",
    "sg:province":"OR",
    "sg:tags":[
        "air",
        "heating",
        "conditioning",
        "contractor"
    ],
    "sg:website":"www.theheatingspecialist.com",
    "wof:name":"Heating Specialist Inc",
    "wof:placetype":"venue"
},
  "geometry": {"coordinates":[-122.567778,45.533395],"type":"Point"}
}