{
  "type": "Feature",
  "properties": {
    "addr:full":"63378 Nels Anderson Rd Bend OR 97701",
    "addr:postcode":"63378;97701",
    "addr:street":"Nels Anderson Rd",
    "iso:country":"US",
    "sg:address":"63378 Nels Anderson Rd",
    "sg:city":"Bend",
    "sg:classifiers":[
        {
            "category":"Recreation",
            "subcategory":"Water Park",
            "type":"Entertainment"
        },
        {
            "category":"Sports & Exercise",
            "subcategory":"Gym",
            "type":"Entertainment"
        },
        {
            "category":"Personal",
            "subcategory":"Day Spa",
            "type":"Services"
        }
    ],
    "sg:phone":"+1 541 388 7963",
    "sg:postcode":"97701",
    "sg:province":"OR",
    "sg:tags":[
        "supply",
        "fitness",
        "equipment",
        "hot",
        "tubs-wholesale",
        "skiing",
        "tub",
        "manufacturer"
    ],
    "wof:name":"Cascade Spa Covers",
    "wof:placetype":"venue"
},
  "geometry": {"coordinates":[-121.29752000000001,44.101511],"type":"Point"}
}