{
  "type": "Feature",
  "properties": {
    "iso:country":"US",
    "sg:address":"4620 SE 67th Ave",
    "sg:city":"Portland",
    "sg:classifiers":[
        {
            "category":"Education",
            "subcategory":"University",
            "type":"Public Place"
        }
    ],
    "sg:phone":"+1 503 788 3101",
    "sg:postcode":"97206",
    "sg:province":"OR",
    "sg:tags":[
        "college"
    ],
    "sg:website":"www.cascademedicalschool.com",
    "wof:name":"Cascade Medical School",
    "wof:placetype":"venue"
},
  "geometry": {"coordinates":[-122.594104,45.489447],"type":"Point"}
}