{
  "type": "Feature",
  "properties": {
    "addr:full":"465 NE Chestnut Ave Roseburg OR 97470",
    "addr:housenumber":"465",
    "addr:postcode":"97470",
    "addr:street":"Ne Chestnut Ave",
    "iso:country":"US",
    "sg:address":"465 NE Chestnut Ave",
    "sg:city":"Roseburg",
    "sg:classifiers":[
        {
            "category":"Wholesale",
            "subcategory":"Furniture",
            "type":"Manufacturing & Wholesale Goods"
        }
    ],
    "sg:phone":"+1 541 440 9421",
    "sg:postcode":"97470",
    "sg:province":"OR",
    "wof:name":"Supply Partners",
    "wof:placetype":"venue"
},
  "geometry": {"coordinates":[-123.350523,43.222938],"type":"Point"}
}