{
  "type": "Feature",
  "properties": {
    "iso:country":"US",
    "sg:address":"12085 SW Lincoln Ave",
    "sg:city":"Portland",
    "sg:classifiers":[
        {
            "category":"Building & Trades",
            "subcategory":"Landscaping Services",
            "type":"Services"
        }
    ],
    "sg:phone":"+1 503 624 3704",
    "sg:postcode":"97223",
    "sg:province":"OR",
    "sg:tags":[
        "gardener"
    ],
    "wof:name":"Trees R Us Tree Service",
    "wof:placetype":"venue"
},
  "geometry": {"coordinates":[-122.772549,45.432856],"type":"Point"}
}