{
  "type": "Feature",
  "properties": {
    "addr:full":"4301 Hwy 39 Klamath Falls OR 97603",
    "addr:housenumber":"4301",
    "addr:postcode":"97603",
    "addr:street":"Hwy 39",
    "iso:country":"US",
    "sg:address":"4301 Hwy 39",
    "sg:city":"Klamath Falls",
    "sg:classifiers":[
        {
            "category":"Home & Garden",
            "subcategory":"Garden Supply",
            "type":"Retail Goods"
        }
    ],
    "sg:phone":"+1 541 884 2283",
    "sg:postcode":"97603",
    "sg:province":"OR",
    "sg:tags":[
        "nurseryman"
    ],
    "wof:name":"Plantscapes Of Oregon",
    "wof:placetype":"venue"
},
  "geometry": {"coordinates":[-121.698026,42.188223],"type":"Point"}
}