{
  "type": "Feature",
  "properties": {
    "addr:full":"1900 SW River Dr Unit 1001 Portland OR 97201",
    "addr:housenumber":"1900;1001",
    "addr:postcode":"97201",
    "addr:street":"Sw River Dr Unit",
    "iso:country":"US",
    "sg:address":"1900 SW River Dr Unit 1001",
    "sg:city":"Portland",
    "sg:classifiers":[
        {
            "category":"Banks & Credit Unions",
            "subcategory":"Investment Brokerage",
            "type":"Services"
        }
    ],
    "sg:phone":"+1 503 246 8249",
    "sg:postcode":"97201",
    "sg:province":"OR",
    "sg:tags":[
        "trust"
    ],
    "wof:name":"Gearhart Land & Capital",
    "wof:placetype":"venue"
},
  "geometry": {"coordinates":[-122.67363899999999,45.50833],"type":"Point"}
}