{
  "type": "Feature",
  "properties": {
    "addr:full":"720 S 73rd St Springfield OR 97478",
    "addr:housenumber":"720",
    "addr:postcode":"97478",
    "addr:street":"S 73Rd St",
    "iso:country":"US",
    "sg:address":"720 S 73rd St",
    "sg:city":"Springfield",
    "sg:classifiers":[
        {
            "category":"Building & Trades",
            "subcategory":"Construction",
            "type":"Services"
        }
    ],
    "sg:phone":"+1 541 746 7951",
    "sg:postcode":"97478",
    "sg:province":"OR",
    "sg:tags":[
        "house"
    ],
    "wof:name":"Nowak Builders",
    "wof:placetype":"venue"
},
  "geometry": {"coordinates":[-122.895095,44.040341],"type":"Point"}
}