{
  "type": "Feature",
  "properties": {
    "iso:country":"US",
    "sg:address":"640 Mason Way",
    "sg:city":"Medford",
    "sg:classifiers":[
        {
            "category":"Retail",
            "subcategory":"Auto Repair",
            "type":"Services"
        }
    ],
    "sg:phone":"+1 541 772 8400",
    "sg:postcode":"97501",
    "sg:province":"OR",
    "sg:tags":[
        "body",
        "painting",
        "repairing",
        "automobile"
    ],
    "wof:name":"Lane Auto Body",
    "wof:placetype":"venue"
},
  "geometry": {"coordinates":[-122.89833900000001,42.348161],"type":"Point"}
}