{
  "type": "Feature",
  "properties": {
    "iso:country":"US",
    "sg:address":"205 NE Ford St",
    "sg:city":"Mcminnville",
    "sg:classifiers":[
        {
            "category":"Health Services",
            "subcategory":"Health Practitioner",
            "type":"Services"
        }
    ],
    "sg:phone":"+1 503 474 9218",
    "sg:postcode":"97128",
    "sg:province":"OR",
    "sg:tags":[
        "psychologist"
    ],
    "wof:name":"Peter Carey PHD",
    "wof:placetype":"venue"
},
  "geometry": {"coordinates":[-123.193383,45.209992],"type":"Point"}
}