{
  "type": "Feature",
  "properties": {
    "iso:country":"US",
    "sg:address":"860 Molalla Ave",
    "sg:city":"Oregon City",
    "sg:classifiers":[
        {
            "category":"Autos & Motor Vehicles",
            "subcategory":"Fuel & Gas Station",
            "type":"Retail Goods"
        }
    ],
    "sg:phone":"+1 503 657 0158",
    "sg:postcode":"97045",
    "sg:province":"OR",
    "sg:tags":[
        "oil"
    ],
    "wof:name":"Hilltop Chevron",
    "wof:placetype":"venue"
},
  "geometry": {"coordinates":[-122.596006,45.343638],"type":"Point"}
}