{
  "type": "Feature",
  "properties": {
    "addr:full":"14377 US Hwy 101 Brookings OR 97415",
    "addr:postcode":"14377;97415",
    "addr:street":"Us Hwy 101",
    "iso:country":"US",
    "sg:address":"14377 US Hwy 101",
    "sg:city":"Brookings",
    "sg:classifiers":[
        {
            "category":"Professional",
            "subcategory":"Advertising",
            "type":"Services"
        }
    ],
    "sg:phone":"+1 541 412 9075",
    "sg:postcode":"97415",
    "sg:province":"OR",
    "sg:tags":[
        "distribution"
    ],
    "wof:name":"Big Wave Power",
    "wof:placetype":"venue"
},
  "geometry": {"coordinates":[-124.20836300000001,41.999686],"type":"Point"}
}