{
  "type": "Feature",
  "properties": {
    "addr:full":"293 SW 1st Ave Canby OR 97013",
    "addr:housenumber":"293",
    "addr:postcode":"97013",
    "addr:street":"Sw 1St Ave",
    "iso:country":"US",
    "sg:address":"293 SW 1st Ave",
    "sg:city":"Canby",
    "sg:classifiers":[
        {
            "category":"Autos & Motor Vehicles",
            "subcategory":"Fuel & Gas Station",
            "type":"Retail Goods"
        }
    ],
    "sg:phone":"+1 503 266 8595",
    "sg:postcode":"97013",
    "sg:province":"OR",
    "sg:tags":[
        "station",
        "gasoline",
        "oil"
    ],
    "wof:name":"Canby's Texaco",
    "wof:placetype":"venue"
},
  "geometry": {"coordinates":[-122.69460100000001,45.261313],"type":"Point"}
}