{
  "type": "Feature",
  "properties": {
    "iso:country":"US",
    "sg:address":"415 Washington St",
    "sg:city":"The Dalles",
    "sg:classifiers":[
        {
            "category":"Health Services",
            "subcategory":"Optometrist",
            "type":"Services"
        }
    ],
    "sg:phone":"+1 541 296 2911",
    "sg:postcode":"97058",
    "sg:province":"OR",
    "wof:name":"Mid-Columbia Vision Ctr",
    "wof:placetype":"venue"
},
  "geometry": {"coordinates":[-121.18267299999999,45.600611],"type":"Point"}
}