{
  "type": "Feature",
  "properties": {
    "iso:country":"US",
    "sg:address":"55750 Timber Rd",
    "sg:city":"Vernonia",
    "sg:classifiers":[
        {
            "category":"Manufacturing",
            "subcategory":"Lumber",
            "type":"Manufacturing & Wholesale Goods"
        }
    ],
    "sg:phone":"+1 503 429 7694",
    "sg:postcode":"97064",
    "sg:province":"OR",
    "sg:tags":[
        "operator",
        "logging",
        "local",
        "trucking"
    ],
    "wof:name":"Bergerson Brothers",
    "wof:placetype":"venue"
},
  "geometry": {"coordinates":[-123.27733600000001,45.805134],"type":"Point"}
}