{
  "type": "Feature",
  "properties": {
    "iso:country":"US",
    "sg:address":"2110 W 6th Ave",
    "sg:city":"Eugene",
    "sg:classifiers":[
        {
            "category":"Retail",
            "subcategory":"Self-service Laundry",
            "type":"Services"
        }
    ],
    "sg:phone":"+1 541 344 2501",
    "sg:postcode":"97402",
    "sg:province":"OR",
    "sg:tags":[
        "dry",
        "cleaner",
        "coin",
        "commercial"
    ],
    "wof:name":"Big Y Laundry Services Inc",
    "wof:placetype":"venue"
},
  "geometry": {"coordinates":[-123.1246,44.053652],"type":"Point"}
}