{
  "type": "Feature",
  "properties": {
    "iso:country":"US",
    "sg:address":"2729 NE 6th St",
    "sg:city":"Gresham",
    "sg:classifiers":[
        {
            "category":"Professional",
            "type":"Services"
        }
    ],
    "sg:phone":"+1 503 666 4884",
    "sg:postcode":"97030",
    "sg:province":"OR",
    "wof:name":"Everyday Essentials",
    "wof:placetype":"venue"
},
  "geometry": {"coordinates":[-122.403327,45.501952],"type":"Point"}
}