{
  "type": "Feature",
  "properties": {
    "addr:full":"40011 Lacomb Dr Lebanon OR 97355",
    "addr:postcode":"40011;97355",
    "addr:street":"Lacomb Dr",
    "iso:country":"US",
    "sg:address":"40011 Lacomb Dr",
    "sg:city":"Lebanon",
    "sg:classifiers":[
        {
            "category":"Building & Trades",
            "subcategory":"Construction",
            "type":"Services"
        }
    ],
    "sg:phone":"+1 541 259 1080",
    "sg:postcode":"97355",
    "sg:province":"OR",
    "sg:tags":[
        "house",
        "floor",
        "flo",
        "covering"
    ],
    "wof:name":"Home Energy Products",
    "wof:placetype":"venue"
},
  "geometry": {"coordinates":[-122.80342400000001,44.577247],"type":"Point"}
}