{
  "type": "Feature",
  "properties": {
    "iso:country":"US",
    "sg:address":"3015 NE 62nd Avenue",
    "sg:city":"Portland",
    "sg:classifiers":[
        {
            "category":"Health Services",
            "subcategory":"Health Practitioner",
            "type":"Services"
        }
    ],
    "sg:phone":"+1 503 281 6080",
    "sg:postcode":"97213",
    "sg:province":"OR",
    "sg:tags":[
        "nutritionist"
    ],
    "wof:name":"Diabetes & Heart Wellness Clinic",
    "wof:placetype":"venue"
},
  "geometry": {"coordinates":[-122.5994,45.544409],"type":"Point"}
}