{
  "type": "Feature",
  "properties": {
    "iso:country":"US",
    "sg:address":"547 NE Bellevue Dr",
    "sg:city":"Bend",
    "sg:classifiers":[
        {
            "category":"Utilities",
            "subcategory":"Mobile Phone",
            "type":"Services"
        }
    ],
    "sg:phone":"+1 541 617 1865",
    "sg:postcode":"97701",
    "sg:province":"OR",
    "sg:tags":[
        "telephone",
        "cellular"
    ],
    "wof:name":"Get Wireless",
    "wof:placetype":"venue"
},
  "geometry": {"coordinates":[-121.26183,44.055661],"type":"Point"}
}