{
  "type": "Feature",
  "properties": {
    "iso:country":"US",
    "sg:address":"1585 SW Marlow Ave",
    "sg:city":"Portland",
    "sg:classifiers":[
        {
            "category":"Health Services",
            "subcategory":"Doctor",
            "type":"Services"
        },
        {
            "category":"Personal",
            "type":"Services"
        },
        {
            "category":"Health Services",
            "subcategory":"Health Practitioner",
            "type":"Services"
        }
    ],
    "sg:phone":"+1 503 292 1573",
    "sg:postcode":"97225",
    "sg:province":"OR",
    "sg:tags":[
        "physician",
        "surgeons",
        "counselors-licensed",
        "abuse",
        "drug",
        "medicine",
        "professional",
        "addiction"
    ],
    "wof:name":"Pacific Alcohol & Drug Treatment Counseling Incorporated",
    "wof:placetype":"venue"
},
  "geometry": {"coordinates":[-122.78421299999999,45.508038],"type":"Point"}
}