{
  "type": "Feature",
  "properties": {
    "iso:country":"US",
    "sg:address":"52405 Pine Dr",
    "sg:city":"La Pine",
    "sg:classifiers":[
        {
            "category":"Retail",
            "subcategory":"Repair Shop",
            "type":"Services"
        }
    ],
    "sg:phone":"+1 541 536 7924",
    "sg:postcode":"97739",
    "sg:province":"OR",
    "sg:tags":[
        "welding"
    ],
    "wof:name":"Specialty Welding",
    "wof:placetype":"venue"
},
  "geometry": {"coordinates":[-121.486205,43.714113],"type":"Point"}
}