{
  "type": "Feature",
  "properties": {
    "addr:full":"614 Maple St Myrtle Point OR 97458",
    "addr:housenumber":"614",
    "addr:postcode":"97458",
    "addr:street":"Maple St",
    "iso:country":"US",
    "sg:address":"614 Maple St",
    "sg:city":"Myrtle Point",
    "sg:classifiers":[
        {
            "category":"Professional",
            "subcategory":"Accounting & Tax Preparation",
            "type":"Services"
        }
    ],
    "sg:phone":"+1 541 572 2373",
    "sg:postcode":"97458",
    "sg:province":"OR",
    "sg:tags":[
        "bookkeeping",
        "general"
    ],
    "wof:name":"Coquille Valley Accounting Svc",
    "wof:placetype":"venue"
},
  "geometry": {"coordinates":[-124.140979,43.06414],"type":"Point"}
}