{
  "type": "Feature",
  "properties": {
    "iso:country":"US",
    "sg:address":"3204 SE Hawthorne Blvd",
    "sg:city":"Portland",
    "sg:classifiers":[
        {
            "category":"Shopping",
            "subcategory":"Used Merchandise",
            "type":"Retail Goods"
        }
    ],
    "sg:phone":"+1 503 231 7116",
    "sg:postcode":"97214",
    "sg:province":"OR",
    "sg:tags":[
        "consignment",
        "clothing",
        "accessory"
    ],
    "sg:website":"www.savvyplus.com/",
    "wof:name":"Savvy Plus",
    "wof:placetype":"venue"
},
  "geometry": {"coordinates":[-122.63200399999999,45.511902],"type":"Point"}
}