{
  "type": "Feature",
  "properties": {
    "iso:country":"US",
    "sg:address":"1830 Avalon Way",
    "sg:city":"Hood River",
    "sg:classifiers":[
        {
            "category":"Building & Trades",
            "subcategory":"Plumbing",
            "type":"Services"
        }
    ],
    "sg:phone":"+1 541 386 5951",
    "sg:postcode":"97031",
    "sg:province":"OR",
    "sg:tags":[
        "contractor"
    ],
    "wof:name":"Bell Court Irrigatn Usrs",
    "wof:placetype":"venue"
},
  "geometry": {"coordinates":[-121.530183,45.696931],"type":"Point"}
}