{
  "type": "Feature",
  "properties": {
    "iso:country":"US",
    "sg:address":"925 Country Club Rd",
    "sg:city":"Eugene",
    "sg:classifiers":[
        {
            "category":"Professional",
            "subcategory":"Accounting & Tax Preparation",
            "type":"Services"
        }
    ],
    "sg:phone":"+1 541 345 3900",
    "sg:postcode":"97401",
    "sg:province":"OR",
    "sg:tags":[
        "accountant"
    ],
    "wof:name":"William Maas CPA",
    "wof:placetype":"venue"
},
  "geometry": {"coordinates":[-123.098653,44.065433],"type":"Point"}
}