{
  "type": "Feature",
  "properties": {
    "iso:country":"US",
    "sg:address":"2058 Primrose Rd",
    "sg:city":"Adrian",
    "sg:classifiers":[
        {
            "category":"Building & Trades",
            "subcategory":"Construction",
            "type":"Services"
        }
    ],
    "sg:phone":"+1 541 724 5998",
    "sg:postcode":"97901",
    "sg:province":"OR",
    "sg:tags":[
        "excavation",
        "contractor"
    ],
    "wof:name":"Carroll Backhoe",
    "wof:placetype":"venue"
},
  "geometry": {"coordinates":[-117.04569100000001,43.72893],"type":"Point"}
}