{
  "type": "Feature",
  "properties": {
    "addr:full":"540 E Dutton Rd Eagle Point OR 97524",
    "addr:housenumber":"540",
    "addr:postcode":"97524",
    "addr:street":"E Dutton Rd",
    "iso:country":"US",
    "sg:address":"540 E Dutton Rd",
    "sg:city":"Eagle Point",
    "sg:classifiers":[
        {
            "category":"Recreation",
            "type":"Entertainment"
        }
    ],
    "sg:phone":"+1 541 826 8599",
    "sg:postcode":"97524",
    "sg:province":"OR",
    "sg:tags":[
        "martial",
        "arts",
        "instruction"
    ],
    "wof:name":"Sun & Moon Karate",
    "wof:placetype":"venue"
},
  "geometry": {"coordinates":[-122.820916,42.443501],"type":"Point"}
}