{
  "type": "Feature",
  "properties": {
    "addr:full":"391 NE Yamhill St Willamina OR 97396",
    "addr:housenumber":"391",
    "addr:postcode":"97396",
    "addr:street":"Ne Yamhill St",
    "iso:country":"US",
    "sg:address":"391 NE Yamhill St",
    "sg:city":"Willamina",
    "sg:classifiers":[
        {
            "category":"Freight",
            "type":"Transportation"
        }
    ],
    "sg:phone":"+1 503 876 2628",
    "sg:postcode":"97396",
    "sg:province":"OR",
    "sg:tags":[
        "operator",
        "local",
        "trucking"
    ],
    "wof:name":"Richard Ray Trucking",
    "wof:placetype":"venue"
},
  "geometry": {"coordinates":[-123.48119,45.07862],"type":"Point"}
}