{
  "type": "Feature",
  "properties": {
    "iso:country":"US",
    "sg:address":"1588 Iler St S",
    "sg:city":"Salem",
    "sg:classifiers":[
        {
            "category":"Building & Trades",
            "subcategory":"Construction",
            "type":"Services"
        }
    ],
    "sg:phone":"+1 503 364 0320",
    "sg:postcode":"97302",
    "sg:province":"OR",
    "sg:tags":[
        "dry wall",
        "contractor"
    ],
    "wof:name":"Salem Drywall Inc",
    "wof:placetype":"venue"
},
  "geometry": {"coordinates":[-123.071235,44.894101],"type":"Point"}
}