{
  "type": "Feature",
  "properties": {
    "iso:country":"US",
    "sg:address":"45 Hawthorne St",
    "sg:city":"Medford",
    "sg:classifiers":[
        {
            "category":"Real Estate",
            "subcategory":"Architect",
            "type":"Services"
        }
    ],
    "sg:phone":"+1 541 772 5203",
    "sg:postcode":"97504",
    "sg:province":"OR",
    "sg:tags":[
        "planner",
        "architectural"
    ],
    "wof:name":"Snider Douglas S Architect",
    "wof:placetype":"venue"
},
  "geometry": {"coordinates":[-122.866997,42.328899],"type":"Point"}
}