{
  "type": "Feature",
  "properties": {
    "addr:full":"1620 Olmar Dr NW Grants Pass OR 97526",
    "addr:housenumber":"1620",
    "addr:postcode":"97526",
    "addr:street":"Olmar Dr Nw",
    "iso:country":"US",
    "sg:address":"1620 Olmar Dr NW",
    "sg:city":"Grants Pass",
    "sg:classifiers":[
        {
            "category":"Building & Trades",
            "subcategory":"Cleaning & Sanitation",
            "type":"Services"
        }
    ],
    "sg:phone":"+1 541 474 1935",
    "sg:postcode":"97526",
    "sg:province":"OR",
    "sg:tags":[
        "maintenance"
    ],
    "wof:name":"Classic Enterprises",
    "wof:placetype":"venue"
},
  "geometry": {"coordinates":[-123.34158100000001,42.448495],"type":"Point"}
}