{
  "type": "Feature",
  "properties": {
    "iso:country":"US",
    "sg:address":"340 Cabbage Ln",
    "sg:city":"Phoenix",
    "sg:classifiers":[
        {
            "category":"Retail",
            "subcategory":"Animal Services",
            "type":"Services"
        }
    ],
    "sg:phone":"+1 541 535 2376",
    "sg:postcode":"97535",
    "sg:province":"OR",
    "wof:name":"Oregon Retrievers",
    "wof:placetype":"venue"
},
  "geometry": {"coordinates":[-122.798305,42.264145],"type":"Point"}
}