{
  "type": "Feature",
  "properties": {
    "iso:country":"US",
    "sg:address":"1940 S 6th St",
    "sg:city":"Klamath Falls",
    "sg:classifiers":[
        {
            "category":"Professional",
            "subcategory":"Management & Consulting",
            "type":"Services"
        }
    ],
    "sg:phone":"+1 541 850 2050",
    "sg:postcode":"97603",
    "sg:province":"OR",
    "sg:tags":[
        "consultant",
        "business"
    ],
    "sg:website":"www.businessocnnection.ws",
    "wof:name":"Business Connection",
    "wof:placetype":"venue"
},
  "geometry": {"coordinates":[-121.76786300000001,42.216654],"type":"Point"}
}