{
  "type": "Feature",
  "properties": {
    "addr:full":"2882 Country Ln Eugene OR 97401",
    "addr:housenumber":"2882",
    "addr:postcode":"97401",
    "addr:street":"Country Ln",
    "iso:country":"US",
    "sg:address":"2882 Country Ln",
    "sg:city":"Eugene",
    "sg:classifiers":[
        {
            "category":"Cinema",
            "subcategory":"Movie Rental",
            "type":"Entertainment"
        }
    ],
    "sg:phone":"+1 541 484 3781",
    "sg:postcode":"97401",
    "sg:province":"OR",
    "sg:tags":[
        "video",
        "tape"
    ],
    "wof:name":"Video Memories By Sherry Peter",
    "wof:placetype":"venue"
},
  "geometry": {"coordinates":[-123.063749,44.063373],"type":"Point"}
}