{
  "type": "Feature",
  "properties": {
    "iso:country":"US",
    "sg:address":"2225 SW US Hwy 101",
    "sg:city":"Albany",
    "sg:classifiers":[
        {
            "category":"Real Estate",
            "subcategory":"Real Estate Agent",
            "type":"Services"
        }
    ],
    "sg:phone":"+1 541 926 8349",
    "sg:postcode":"97367",
    "sg:province":"OR",
    "wof:name":"Scheele Team Inc",
    "wof:placetype":"venue"
},
  "geometry": {"coordinates":[-124.01392,44.951446],"type":"Point"}
}