{
  "type": "Feature",
  "properties": {
    "iso:country":"US",
    "sg:address":"1020 Green Acres Rd Ste 7",
    "sg:city":"Eugene",
    "sg:classifiers":[
        {
            "category":"Personal",
            "subcategory":"Beauty Salon",
            "type":"Services"
        }
    ],
    "sg:phone":"+1 541 485 6982",
    "sg:postcode":"97408",
    "sg:province":"OR",
    "wof:name":"Jacob Miller",
    "wof:placetype":"venue"
},
  "geometry": {"coordinates":[-123.097005,44.093898],"type":"Point"}
}