{
  "type": "Feature",
  "properties": {
    "addr:full":"8419 SW 39th Ave Portland OR 97219",
    "addr:housenumber":"8419",
    "addr:postcode":"97219",
    "addr:street":"Sw 39Th Ave",
    "iso:country":"US",
    "sg:address":"8419 SW 39th Ave",
    "sg:city":"Portland",
    "sg:classifiers":[
        {
            "category":"Building & Trades",
            "subcategory":"Locksmith",
            "type":"Services"
        }
    ],
    "sg:phone":"+1 503 205 1110",
    "sg:postcode":"97219",
    "sg:province":"OR",
    "sg:tags":[
        "key"
    ],
    "wof:name":"0 A A A 24 A Locksmith",
    "wof:placetype":"venue"
},
  "geometry": {"coordinates":[-122.71688,45.4642],"type":"Point"}
}