{
  "type": "Feature",
  "properties": {
    "iso:country":"US",
    "sg:address":"16365 Highway 101 S",
    "sg:city":"Brookings",
    "sg:classifiers":[
        {
            "category":"Autos & Motor Vehicles",
            "subcategory":"Automobile Sales",
            "type":"Retail Goods"
        }
    ],
    "sg:phone":"+1 541 469 7055",
    "sg:postcode":"97415",
    "sg:province":"OR",
    "sg:tags":[
        "used",
        "car",
        "dealers-used",
        "new",
        "cars-wholesale"
    ],
    "sg:website":"http://www.kempauto.com",
    "wof:name":"Kemp Auto Sales",
    "wof:placetype":"venue"
},
  "geometry": {"coordinates":[-124.227136,42.023153],"type":"Point"}
}