{
  "type": "Feature",
  "properties": {
    "iso:country":"US",
    "sg:address":"110 Stillwell Ave",
    "sg:city":"Tillamook",
    "sg:classifiers":[
        {
            "category":"Home & Garden",
            "subcategory":"Building Materials",
            "type":"Retail Goods"
        }
    ],
    "sg:phone":"+1 503 842 6114",
    "sg:postcode":"97141",
    "sg:province":"OR",
    "sg:tags":[
        "h",
        "floor",
        "covering"
    ],
    "wof:name":"Webbery",
    "wof:placetype":"venue"
},
  "geometry": {"coordinates":[-123.846142,45.457733],"type":"Point"}
}