{
  "type": "Feature",
  "properties": {
    "addr:full":"4835 NE Sandy Blvd Portland OR 97213",
    "addr:housenumber":"4835",
    "addr:postcode":"97213",
    "addr:street":"Ne Sandy Blvd",
    "iso:country":"US",
    "sg:address":"4835 NE Sandy Blvd",
    "sg:city":"Portland",
    "sg:classifiers":[
        {
            "category":"Restaurant",
            "type":"Food & Drink"
        }
    ],
    "sg:menulink":"http://www.allmenus.com/or/portland/211208-kfc---kentucky-fried-chicken/menu/",
    "sg:phone":"+1 503 282 5556",
    "sg:postcode":"97213",
    "sg:province":"OR",
    "sg:tags":[
        "american",
        "chicken"
    ],
    "wof:name":"KFC - Kentucky Fried Chicken",
    "wof:placetype":"venue"
},
  "geometry": {"coordinates":[-122.613649,45.539258],"type":"Point"}
}