{
  "type": "Feature",
  "properties": {
    "addr:full":"2301 NW Savier St Portland OR 97210",
    "addr:housenumber":"2301",
    "addr:postcode":"97210",
    "addr:street":"Nw Savier St",
    "iso:country":"US",
    "sg:address":"2301 NW Savier St",
    "sg:city":"Portland",
    "sg:classifiers":[
        {
            "category":"Restaurant",
            "type":"Food & Drink"
        }
    ],
    "sg:menulink":"http://www.allmenus.com/or/portland/26567-besaws/menu/",
    "sg:phone":"+1 503 228 2619",
    "sg:postcode":"97210",
    "sg:province":"OR",
    "sg:tags":[
        "american"
    ],
    "wof:name":"Besaws",
    "wof:placetype":"venue"
},
  "geometry": {"coordinates":[-122.698915,45.534784],"type":"Point"}
}