{
  "type": "Feature",
  "properties": {
    "iso:country":"US",
    "sg:address":"1765 S Red Soils Ct",
    "sg:city":"Oregon City",
    "sg:classifiers":[
        {
            "category":"Manufacturing",
            "subcategory":"Metals",
            "type":"Manufacturing & Wholesale Goods"
        }
    ],
    "sg:phone":"+1 503 655 1880",
    "sg:postcode":"97045",
    "sg:province":"OR",
    "sg:tags":[
        "coating",
        "allied",
        "finisher"
    ],
    "wof:name":"Excel Finishing Inc",
    "wof:placetype":"venue"
},
  "geometry": {"coordinates":[-122.594937,45.332657],"type":"Point"}
}