{
  "type": "Feature",
  "properties": {
    "addr:full":"19241 SW Martinazzi Ave Tualatin OR 97062",
    "addr:housenumber":"19241",
    "addr:postcode":"97062",
    "addr:street":"Sw Martinazzi Ave",
    "iso:country":"US",
    "sg:address":"19241 SW Martinazzi Ave",
    "sg:city":"Tualatin",
    "sg:classifiers":[
        {
            "category":"Shopping",
            "subcategory":"Mobile Phones",
            "type":"Retail Goods"
        }
    ],
    "sg:phone":"+1 503 692 0860",
    "sg:postcode":"97062",
    "sg:province":"OR",
    "sg:website":"www.radioshack.com",
    "wof:name":"Radioshack",
    "wof:placetype":"venue"
},
  "geometry": {"coordinates":[-122.75900300000001,45.380901],"type":"Point"}
}