{
  "type": "Feature",
  "properties": {
    "addr:full":"3000 Frontage Rd Reedsport OR 97467",
    "addr:housenumber":"3000",
    "addr:postcode":"97467",
    "addr:street":"Frontage Rd",
    "iso:country":"US",
    "sg:address":"3000 Frontage Rd",
    "sg:city":"Reedsport",
    "sg:classifiers":[
        {
            "category":"Shopping",
            "subcategory":"Bicycles & Sporting Goods",
            "type":"Retail Goods"
        }
    ],
    "sg:phone":"+1 541 271 2698",
    "sg:postcode":"97467",
    "sg:province":"OR",
    "sg:tags":[
        "equipment",
        "golf",
        "supply"
    ],
    "wof:name":"Mr P's Clubhouse",
    "wof:placetype":"venue"
},
  "geometry": {"coordinates":[-124.132121,43.692629],"type":"Point"}
}