{
  "type": "Feature",
  "properties": {
    "iso:country":"US",
    "sg:address":"2365 Hoyt St SE",
    "sg:city":"Salem",
    "sg:classifiers":[
        {
            "category":"Home & Garden",
            "subcategory":"Carpets & Floor Coverings",
            "type":"Retail Goods"
        }
    ],
    "sg:phone":"+1 503 362 2600",
    "sg:postcode":"97302",
    "sg:province":"OR",
    "sg:tags":[
        "dealer",
        "rug"
    ],
    "wof:name":"Carpet Brokers",
    "wof:placetype":"venue"
},
  "geometry": {"coordinates":[-123.014185,44.919207],"type":"Point"}
}