{
  "type": "Feature",
  "properties": {
    "iso:country":"US",
    "sg:address":"4836 SE Glenwood St",
    "sg:city":"Portland",
    "sg:classifiers":[
        {
            "category":"Organizations",
            "subcategory":"Membership Organization",
            "type":"Services"
        }
    ],
    "sg:phone":"+1 503 775 4689",
    "sg:postcode":"97206",
    "sg:province":"OR",
    "wof:name":"Mycrosoft Network",
    "wof:placetype":"venue"
},
  "geometry": {"coordinates":[-122.611672,45.474335],"type":"Point"}
}