{
  "type": "Feature",
  "properties": {
    "iso:country":"US",
    "sg:address":"3373 Videra Dr",
    "sg:city":"Eugene",
    "sg:classifiers":[
        {
            "category":"Organizations",
            "subcategory":"Religious Organization",
            "type":"Services"
        }
    ],
    "sg:phone":"+1 541 686 5630",
    "sg:postcode":"97405",
    "sg:province":"OR",
    "wof:name":"Truth or Tabloid",
    "wof:placetype":"venue"
},
  "geometry": {"coordinates":[-123.143784,44.026874],"type":"Point"}
}