{
  "type": "Feature",
  "properties": {
    "addr:full":"225 W Main St Medford OR 97501",
    "addr:housenumber":"225",
    "addr:postcode":"97501",
    "addr:street":"W Main St",
    "iso:country":"US",
    "sg:address":"225 W Main St",
    "sg:city":"Medford",
    "sg:classifiers":[
        {
            "category":"Professional",
            "subcategory":"Lawyer & Legal Services",
            "type":"Services"
        }
    ],
    "sg:phone":"+1 541 779 7291",
    "sg:postcode":"97501",
    "sg:province":"OR",
    "wof:name":"Legal Services",
    "wof:placetype":"venue"
},
  "geometry": {"coordinates":[-122.87599899999999,42.3246],"type":"Point"}
}