{
  "type": "Feature",
  "properties": {
    "iso:country":"US",
    "sg:address":"9650 SW Herman Rd",
    "sg:city":"Tualatin",
    "sg:classifiers":[
        {
            "category":"Professional",
            "subcategory":"Printing & Photocopies",
            "type":"Services"
        }
    ],
    "sg:phone":"+1 503 454 2200",
    "sg:postcode":"97062",
    "sg:province":"OR",
    "wof:name":"A K A Direct",
    "wof:placetype":"venue"
},
  "geometry": {"coordinates":[-122.77800000000001,45.3867],"type":"Point"}
}