{
  "type": "Feature",
  "properties": {
    "addr:full":"310 SW Cedar Ave Warrenton OR 97146",
    "addr:housenumber":"310",
    "addr:postcode":"97146",
    "addr:street":"Sw Cedar Ave",
    "iso:country":"US",
    "sg:address":"310 SW Cedar Ave",
    "sg:city":"Warrenton",
    "sg:classifiers":[
        {
            "category":"Manufacturing",
            "subcategory":"Watercraft",
            "type":"Manufacturing & Wholesale Goods"
        }
    ],
    "sg:phone":"+1 503 861 1388",
    "sg:postcode":"97146",
    "sg:province":"OR",
    "sg:tags":[
        "commercial",
        "fishing"
    ],
    "wof:name":"Fv Sea Blazer Inc",
    "wof:placetype":"venue"
},
  "geometry": {"coordinates":[-123.932087,46.164097],"type":"Point"}
}