{
  "type": "Feature",
  "properties": {
    "addr:full":"8134 SW 8th Ave Portland OR 97219",
    "addr:housenumber":"8134",
    "addr:postcode":"97219",
    "addr:street":"Sw 8Th Ave",
    "iso:country":"US",
    "sg:address":"8134 SW 8th Ave",
    "sg:city":"Portland",
    "sg:classifiers":[
        {
            "category":"Building & Trades",
            "subcategory":"Cleaning & Sanitation",
            "type":"Services"
        }
    ],
    "sg:phone":"+1 503 245 2450",
    "sg:postcode":"97219",
    "sg:province":"OR",
    "sg:tags":[
        "maintenance"
    ],
    "wof:name":"Plover Janitorial",
    "wof:placetype":"venue"
},
  "geometry": {"coordinates":[-122.68666,45.466366],"type":"Point"}
}