{
  "type": "Feature",
  "properties": {
    "addr:full":"3333 NE 8th St Gresham OR 97030",
    "addr:housenumber":"3333",
    "addr:postcode":"97030",
    "addr:street":"Ne 8Th St",
    "iso:country":"US",
    "sg:address":"3333 NE 8th St",
    "sg:city":"Gresham",
    "sg:classifiers":[
        {
            "category":"Education",
            "subcategory":"School",
            "type":"Public Place"
        }
    ],
    "sg:phone":"+1 503 661 5632",
    "sg:postcode":"97030",
    "sg:province":"OR",
    "sg:website":"www.phonicsphactory.com",
    "wof:name":"Phonics Phactory",
    "wof:placetype":"venue"
},
  "geometry": {"coordinates":[-122.398431,45.503454],"type":"Point"}
}