{
  "type": "Feature",
  "properties": {
    "addr:full":"1643 Brittany St Eugene OR 97402",
    "addr:housenumber":"1643",
    "addr:postcode":"97402",
    "addr:street":"Brittany St",
    "iso:country":"US",
    "sg:address":"1643 Brittany St",
    "sg:city":"Eugene",
    "sg:classifiers":[
        {
            "category":"Professional",
            "subcategory":"Accounting & Tax Preparation",
            "type":"Services"
        }
    ],
    "sg:phone":"+1 541 345 8510",
    "sg:postcode":"97402",
    "sg:province":"OR",
    "sg:tags":[
        "repair",
        "computer",
        "income"
    ],
    "wof:name":"Anaheim Hills Business Cons",
    "wof:placetype":"venue"
},
  "geometry": {"coordinates":[-123.142112,44.041997],"type":"Point"}
}