{
  "type": "Feature",
  "properties": {
    "addr:full":"3635 SW Dosch Road Portland OR 97239",
    "addr:housenumber":"3635",
    "addr:postcode":"97239",
    "addr:street":"Sw Dosch Road",
    "iso:country":"US",
    "sg:address":"3635 SW Dosch Road",
    "sg:city":"Portland",
    "sg:classifiers":[
        {
            "category":"Professional",
            "subcategory":"Lawyer & Legal Services",
            "type":"Services"
        }
    ],
    "sg:phone":"+1 503 224 7730",
    "sg:postcode":"97239",
    "sg:province":"OR",
    "wof:name":"Fisher George P Atty",
    "wof:placetype":"venue"
},
  "geometry": {"coordinates":[-122.711721,45.496598],"type":"Point"}
}