{
  "type": "Feature",
  "properties": {
    "addr:full":"11520 SW Bel Aire Ln Beaverton OR 97008",
    "addr:housenumber":"11520",
    "addr:postcode":"97008",
    "addr:street":"Sw Bel Aire Ln",
    "iso:country":"US",
    "sg:address":"11520 SW Bel Aire Ln",
    "sg:city":"Beaverton",
    "sg:classifiers":[
        {
            "category":"Professional",
            "type":"Services"
        }
    ],
    "sg:phone":"+1 503 626 0422",
    "sg:postcode":"97008",
    "sg:province":"OR",
    "wof:name":"Ruby E Brazelton",
    "wof:placetype":"venue"
},
  "geometry": {"coordinates":[-122.79337200000001,45.463193],"type":"Point"}
}