{
  "type": "Feature",
  "properties": {
    "addr:full":"3906 Century Dr Eugene OR 97402",
    "addr:housenumber":"3906",
    "addr:postcode":"97402",
    "addr:street":"Century Dr",
    "iso:country":"US",
    "sg:address":"3906 Century Dr",
    "sg:city":"Eugene",
    "sg:classifiers":[
        {
            "category":"Food & Beverages",
            "subcategory":"Bakery",
            "type":"Retail Goods"
        }
    ],
    "sg:phone":"+1 541 484 2780",
    "sg:postcode":"97402",
    "sg:province":"OR",
    "sg:tags":[
        "doughnut"
    ],
    "wof:name":"Dunkin Donuts",
    "wof:placetype":"venue"
},
  "geometry": {"coordinates":[-123.16031700000001,44.087691],"type":"Point"}
}