{
  "type": "Feature",
  "properties": {
    "iso:country":"US",
    "sg:address":"6320 SW Elm Ave",
    "sg:city":"Beaverton",
    "sg:classifiers":[
        {
            "category":"Professional",
            "subcategory":"Management & Consulting",
            "type":"Services"
        }
    ],
    "sg:phone":"+1 503 292 2174",
    "sg:postcode":"97005",
    "sg:province":"OR",
    "sg:tags":[
        "business"
    ],
    "wof:name":"Carol Allen Consultation",
    "wof:placetype":"venue"
},
  "geometry": {"coordinates":[-122.77440799999999,45.473298],"type":"Point"}
}