{
  "type": "Feature",
  "properties": {
    "addr:full":"74845 Reservoir Rd Cottage Grove OR 97424",
    "addr:housenumber":"74845",
    "addr:postcode":"97424",
    "addr:street":"Reservoir Rd",
    "iso:country":"US",
    "sg:address":"74845 Reservoir Rd",
    "sg:city":"Cottage Grove",
    "sg:classifiers":[
        {
            "category":"Professional",
            "subcategory":"Management & Consulting",
            "type":"Services"
        }
    ],
    "sg:phone":"+1 541 767 2100",
    "sg:postcode":"97424",
    "sg:province":"OR",
    "sg:tags":[
        "consultant"
    ],
    "wof:name":"TBS Consultants",
    "wof:placetype":"venue"
},
  "geometry": {"coordinates":[-123.06622400000001,43.690688],"type":"Point"}
}