{
  "type": "Feature",
  "properties": {
    "iso:country":"US",
    "sg:address":"5125 SW Macadam Ave",
    "sg:city":"Portland",
    "sg:classifiers":[
        {
            "category":"Professional",
            "subcategory":"Lawyer & Legal Services",
            "type":"Services"
        }
    ],
    "sg:phone":"+1 503 223 7555",
    "sg:postcode":"97219",
    "sg:province":"OR",
    "wof:name":"Robert McGaughey",
    "wof:placetype":"venue"
},
  "geometry": {"coordinates":[-122.675516,45.485897],"type":"Point"}
}