{
  "type": "Feature",
  "properties": {
    "iso:country":"US",
    "sg:address":"1975 NW Everett St # 410",
    "sg:city":"Portland",
    "sg:classifiers":[
        {
            "category":"Wholesale",
            "subcategory":"Home Furnishings",
            "type":"Manufacturing & Wholesale Goods"
        }
    ],
    "sg:phone":"+1 503 954 3831",
    "sg:postcode":"97209",
    "sg:province":"OR",
    "sg:tags":[
        "chair"
    ],
    "wof:name":"Fifty Chairs",
    "wof:placetype":"venue"
},
  "geometry": {"coordinates":[-122.69182000000001,45.524931],"type":"Point"}
}