{
  "type": "Feature",
  "properties": {
    "iso:country":"US",
    "sg:address":"5721 NE M L King Blvd",
    "sg:city":"Portland",
    "sg:classifiers":[
        {
            "category":"Restaurant",
            "type":"Food & Drink"
        }
    ],
    "sg:menulink":"http://www.allmenus.com/or/portland/211212-kfc---kentucky-fried-chicken/menu/",
    "sg:phone":"+1 503 283 1363",
    "sg:postcode":"97211",
    "sg:province":"OR",
    "sg:tags":[
        "american",
        "chicken"
    ],
    "wof:name":"KFC - Kentucky Fried Chicken",
    "wof:placetype":"venue"
},
  "geometry": {"coordinates":[-122.66154400000001,45.564312],"type":"Point"}
}