{
  "type": "Feature",
  "properties": {
    "addr:full":"248 NW 1st Ave Canby OR 97013",
    "addr:housenumber":"248",
    "addr:postcode":"97013",
    "addr:street":"Nw 1St Ave",
    "iso:country":"US",
    "sg:address":"248 NW 1st Ave",
    "sg:city":"Canby",
    "sg:classifiers":[
        {
            "category":"Food & Beverages",
            "subcategory":"Specialty",
            "type":"Retail Goods"
        }
    ],
    "sg:phone":"+1 503 266 4306",
    "sg:postcode":"97013",
    "sg:province":"OR",
    "sg:tags":[
        "tea",
        "coffee"
    ],
    "wof:name":"Francesca's Coffee House",
    "wof:placetype":"venue"
},
  "geometry": {"coordinates":[-122.694852,45.262317],"type":"Point"}
}