{
  "type": "Feature",
  "properties": {
    "addr:full":"7960 Sunset Dr Nehalem OR 97131",
    "addr:housenumber":"7960",
    "addr:postcode":"97131",
    "addr:street":"Sunset Dr",
    "iso:country":"US",
    "sg:address":"7960 Sunset Dr",
    "sg:city":"Nehalem",
    "sg:classifiers":[
        {
            "category":"Building & Trades",
            "subcategory":"Construction",
            "type":"Services"
        }
    ],
    "sg:phone":"+1 503 368 4161",
    "sg:postcode":"97131",
    "sg:province":"OR",
    "sg:tags":[
        "contractor"
    ],
    "wof:name":"Mark W McCorkle",
    "wof:placetype":"venue"
},
  "geometry": {"coordinates":[-123.943091,45.736337],"type":"Point"}
}