{
  "type": "Feature",
  "properties": {
    "addr:full":"2130 Amirante St Eugene OR 97402",
    "addr:postcode":"2130;97402",
    "addr:street":"Amirante St",
    "iso:country":"US",
    "sg:address":"2130 Amirante St",
    "sg:city":"Eugene",
    "sg:classifiers":[
        {
            "category":"Shopping",
            "subcategory":"Beauty & Cosmetics",
            "type":"Retail Goods"
        },
        {
            "category":"Shopping",
            "subcategory":"Catalog Store",
            "type":"Retail Goods"
        }
    ],
    "sg:phone":"+1 541 688 2927",
    "sg:postcode":"97402",
    "sg:province":"OR",
    "sg:tags":[
        "mail",
        "online",
        "order",
        "perfume"
    ],
    "sg:website":"http://www.avon.com",
    "wof:name":"Avon Independant Sales Patty R",
    "wof:placetype":"venue"
},
  "geometry": {"coordinates":[-123.19126900000001,44.088181],"type":"Point"}
}