{
  "type": "Feature",
  "properties": {
    "addr:full":"216 Cedar Ave Tillamook OR 97141",
    "addr:housenumber":"216",
    "addr:postcode":"97141",
    "addr:street":"Cedar Ave",
    "iso:country":"US",
    "sg:address":"216 Cedar Ave",
    "sg:city":"Tillamook",
    "sg:classifiers":[
        {
            "category":"Health Services",
            "subcategory":"Health Practitioner",
            "type":"Services"
        }
    ],
    "sg:phone":"+1 503 842 3661",
    "sg:postcode":"97141",
    "sg:province":"OR",
    "sg:tags":[
        "nurse"
    ],
    "wof:name":"Coastal Health Ctr",
    "wof:placetype":"venue"
},
  "geometry": {"coordinates":[-123.851416,45.456954],"type":"Point"}
}