{
  "type": "Feature",
  "properties": {
    "iso:country":"US",
    "sg:address":"24709 Demming Ridge Rd",
    "sg:city":"Elmira",
    "sg:classifiers":[
        {
            "category":"Professional",
            "subcategory":"Engineering",
            "type":"Services"
        }
    ],
    "sg:phone":"+1 541 935 0859",
    "sg:postcode":"97437",
    "sg:province":"OR",
    "sg:tags":[
        "aircraft",
        "maintenance"
    ],
    "wof:name":"Ultra Tech Repair",
    "wof:placetype":"venue"
},
  "geometry": {"coordinates":[-123.36937,44.109982],"type":"Point"}
}