{
  "type": "Feature",
  "properties": {
    "addr:full":"513 E Pine St Central Point OR 97502",
    "addr:housenumber":"513",
    "addr:postcode":"97502",
    "addr:street":"E Pine St",
    "iso:country":"US",
    "sg:address":"513 E Pine St",
    "sg:city":"Central Point",
    "sg:classifiers":[
        {
            "category":"Organizations",
            "subcategory":"Religious Organization",
            "type":"Services"
        }
    ],
    "sg:phone":"+1 541 664 3226",
    "sg:postcode":"97502",
    "sg:province":"OR",
    "sg:tags":[
        "church"
    ],
    "wof:name":"Calvary Temple",
    "wof:placetype":"venue"
},
  "geometry": {"coordinates":[-122.91293400000001,42.376505],"type":"Point"}
}