{
  "type": "Feature",
  "properties": {
    "addr:full":"17665 Pilkington Rd Lake Oswego OR 97035",
    "addr:housenumber":"17665",
    "addr:postcode":"97035",
    "addr:street":"Pilkington Rd",
    "iso:country":"US",
    "sg:address":"17665 Pilkington Rd",
    "sg:city":"Lake Oswego",
    "sg:classifiers":[
        {
            "category":"Health Services",
            "subcategory":"Medical Lab",
            "type":"Services"
        }
    ],
    "sg:phone":"+1 503 636 4720",
    "sg:postcode":"97035",
    "sg:province":"OR",
    "sg:tags":[
        "laboratory",
        "dental"
    ],
    "wof:name":"Genesis Dental Lab",
    "wof:placetype":"venue"
},
  "geometry": {"coordinates":[-122.733501,45.398891],"type":"Point"}
}