{
  "type": "Feature",
  "properties": {
    "iso:country":"US",
    "sg:address":"2111 Roberts Rd",
    "sg:city":"Medford",
    "sg:classifiers":[
        {
            "category":"Retail",
            "subcategory":"Laundry & Dry Cleaning",
            "type":"Services"
        }
    ],
    "sg:phone":"+1 541 773 9886",
    "sg:postcode":"97504",
    "sg:province":"OR",
    "sg:tags":[
        "cleaners"
    ],
    "wof:name":"Excellence Laundromat & Dry",
    "wof:placetype":"venue"
},
  "geometry": {"coordinates":[-122.854717,42.351153],"type":"Point"}
}