{
  "type": "Feature",
  "properties": {
    "iso:country":"US",
    "sg:address":"1666 W 12th Ave",
    "sg:city":"Eugene",
    "sg:classifiers":[
        {
            "category":"Government",
            "subcategory":"Office",
            "type":"Public Place"
        }
    ],
    "sg:phone":"+1 541 988 0121",
    "sg:postcode":"97402",
    "sg:province":"OR",
    "sg:tags":[
        "military",
        "training",
        "school"
    ],
    "wof:name":"Pioneer Youth Corps of Oregon",
    "wof:placetype":"venue"
},
  "geometry": {"coordinates":[-123.11668,44.046559],"type":"Point"}
}