{
  "type": "Feature",
  "properties": {
    "addr:full":"27621 SE Haley Rd Boring OR 97009",
    "addr:postcode":"27621;97009",
    "addr:street":"Se Haley Rd",
    "iso:country":"US",
    "sg:address":"27621 SE Haley Rd",
    "sg:city":"Boring",
    "sg:classifiers":[
        {
            "category":"Building & Trades",
            "subcategory":"Construction",
            "type":"Services"
        }
    ],
    "sg:phone":"+1 503 663 3410",
    "sg:postcode":"97009",
    "sg:province":"OR",
    "sg:tags":[
        "repairing",
        "remodeling",
        "contractor"
    ],
    "wof:name":"Anderton Construction Inc",
    "wof:placetype":"venue"
},
  "geometry": {"coordinates":[-122.377661,45.44343],"type":"Point"}
}