{
  "type": "Feature",
  "properties": {
    "addr:full":"691 NE Berry St Sublimity OR 97385",
    "addr:housenumber":"691",
    "addr:postcode":"97385",
    "addr:street":"Ne Berry St",
    "iso:country":"US",
    "sg:address":"691 NE Berry St",
    "sg:city":"Sublimity",
    "sg:classifiers":[
        {
            "category":"Real Estate",
            "subcategory":"Real Estate Agent",
            "type":"Services"
        }
    ],
    "sg:phone":"+1 503 769 3333",
    "sg:postcode":"97385",
    "sg:province":"OR",
    "wof:name":"Denson Enterprises",
    "wof:placetype":"venue"
},
  "geometry": {"coordinates":[-122.78451,44.83616],"type":"Point"}
}