{
  "type": "Feature",
  "properties": {
    "iso:country":"US",
    "sg:address":"716 NW 3rd Dr",
    "sg:city":"Pendleton",
    "sg:phone":"+1 541 276 2769",
    "sg:postcode":"97801",
    "sg:province":"OR",
    "sg:tags":[
        "farm",
        "field",
        "crop"
    ],
    "wof:name":"Corr Gren LLP",
    "wof:placetype":"venue"
},
  "geometry": {"coordinates":[-118.79039400000001,45.679385],"type":"Point"}
}