{
  "type": "Feature",
  "properties": {
    "iso:country":"US",
    "sg:address":"38751 N Main St",
    "sg:city":"Scio",
    "sg:classifiers":[
        {
            "category":"Real Estate",
            "subcategory":"Real Estate Agent",
            "type":"Services"
        }
    ],
    "sg:phone":"+1 503 394 4100",
    "sg:postcode":"97374",
    "sg:province":"OR",
    "wof:name":"Affordable Housing",
    "wof:placetype":"venue"
},
  "geometry": {"coordinates":[-122.848813,44.705693],"type":"Point"}
}