{
  "type": "Feature",
  "properties": {
    "addr:full":"33976 Colorado Lake Dr. Corvallis OR 97333",
    "addr:housenumber":"33976",
    "addr:postcode":"97333",
    "addr:street":"Colorado Lake Dr.",
    "iso:country":"US",
    "sg:address":"33976 Colorado Lake Dr.",
    "sg:city":"Corvallis",
    "sg:classifiers":[
        {
            "category":"Professional",
            "subcategory":"Computer Services",
            "type":"Services"
        }
    ],
    "sg:postcode":"97333",
    "sg:province":"OR",
    "sg:website":"http://writewith.com/",
    "wof:name":"writewith",
    "wof:placetype":"venue"
},
  "geometry": {"coordinates":[-123.208123,44.566479],"type":"Point"}
}