{
  "type": "Feature",
  "properties": {
    "addr:full":"425 SE Main St Canyonville OR 97417",
    "addr:housenumber":"425",
    "addr:postcode":"97417",
    "addr:street":"Se Main St",
    "iso:country":"US",
    "sg:address":"425 SE Main St",
    "sg:city":"Canyonville",
    "sg:classifiers":[
        {
            "category":"Shopping",
            "subcategory":"Used Merchandise",
            "type":"Retail Goods"
        }
    ],
    "sg:phone":"+1 541 839 4717",
    "sg:postcode":"97417",
    "sg:province":"OR",
    "sg:tags":[
        "antique"
    ],
    "wof:name":"Country Livin'",
    "wof:placetype":"venue"
},
  "geometry": {"coordinates":[-123.278661,42.92689],"type":"Point"}
}