{
  "type": "Feature",
  "properties": {
    "addr:full":"9438 SW Tigard St Portland OR 97223",
    "addr:housenumber":"9438",
    "addr:postcode":"97223",
    "addr:street":"Sw Tigard St",
    "iso:country":"US",
    "sg:address":"9438 SW Tigard St",
    "sg:city":"Portland",
    "sg:classifiers":[
        {
            "category":"Shopping",
            "subcategory":"Gifts & Souvenirs",
            "type":"Retail Goods"
        }
    ],
    "sg:phone":"+1 503 620 1382",
    "sg:postcode":"97223",
    "sg:province":"OR",
    "wof:name":"Bruce D Roberts",
    "wof:placetype":"venue"
},
  "geometry": {"coordinates":[-122.774517,45.431921],"type":"Point"}
}