{
  "type": "Feature",
  "properties": {
    "iso:country":"US",
    "sg:address":"4805 NE Glisan Street",
    "sg:city":"Portland",
    "sg:classifiers":[
        {
            "category":"Health Services",
            "subcategory":"Hospital",
            "type":"Services"
        }
    ],
    "sg:phone":"+1 503 215 7080",
    "sg:postcode":"97213",
    "sg:province":"OR",
    "wof:name":"Providence Mental Health & Chemical Dependency Services",
    "wof:placetype":"venue"
},
  "geometry": {"coordinates":[-122.613468,45.526594],"type":"Point"}
}