{
  "type": "Feature",
  "properties": {
    "iso:country":"US",
    "sg:address":"408 SW Monroe Ave",
    "sg:city":"Corvallis",
    "sg:classifiers":[
        {
            "category":"Government",
            "subcategory":"Office",
            "type":"Public Place"
        }
    ],
    "sg:phone":"+1 541 757 6851",
    "sg:postcode":"97330",
    "sg:province":"OR",
    "sg:tags":[
        "program",
        "administration",
        "social"
    ],
    "wof:name":"Cascades W Council Government",
    "wof:placetype":"venue"
},
  "geometry": {"coordinates":[-123.26299,44.564822],"type":"Point"}
}