{
  "type": "Feature",
  "properties": {
    "iso:country":"US",
    "sg:address":"360 High St NE",
    "sg:city":"Salem",
    "sg:classifiers":[
        {
            "category":"Restaurant",
            "type":"Food & Drink"
        }
    ],
    "sg:phone":"+1 503 566 6860",
    "sg:postcode":"97301",
    "sg:province":"OR",
    "sg:tags":[
        "eating"
    ],
    "wof:name":"Young's Teriyaki",
    "wof:placetype":"venue"
},
  "geometry": {"coordinates":[-123.035775,44.942457],"type":"Point"}
}