{
  "type": "Feature",
  "properties": {
    "addr:full":"91984 River Rd Junction City OR 97448",
    "addr:housenumber":"91984",
    "addr:postcode":"97448",
    "addr:street":"River Rd",
    "iso:country":"US",
    "sg:address":"91984 River Rd",
    "sg:city":"Junction City",
    "sg:classifiers":[
        {
            "category":"Farming",
            "subcategory":"Farm",
            "type":"Manufacturing & Wholesale Goods"
        }
    ],
    "sg:phone":"+1 541 688 1846",
    "sg:postcode":"97448",
    "sg:province":"OR",
    "sg:tags":[
        "crop",
        "general"
    ],
    "wof:name":"Leslie Harwood Farms",
    "wof:placetype":"venue"
},
  "geometry": {"coordinates":[-123.158062,44.161196],"type":"Point"}
}