{
  "type": "Feature",
  "properties": {
    "addr:full":"2718 Locust St Springfield OR 97477",
    "addr:housenumber":"2718",
    "addr:postcode":"97477",
    "addr:street":"Locust St",
    "iso:country":"US",
    "sg:address":"2718 Locust St",
    "sg:city":"Springfield",
    "sg:classifiers":[
        {
            "category":"Professional",
            "subcategory":"Business Services",
            "type":"Services"
        }
    ],
    "sg:phone":"+1 541 726 3039",
    "sg:postcode":"97477",
    "sg:province":"OR",
    "sg:tags":[
        "auction"
    ],
    "wof:name":"Arthur Wayne Pitts",
    "wof:placetype":"venue"
},
  "geometry": {"coordinates":[-122.990601,44.074888],"type":"Point"}
}