{
  "type": "Feature",
  "properties": {
    "iso:country":"US",
    "sg:address":"3230 Croisan Creek Rd S",
    "sg:city":"Salem",
    "sg:classifiers":[
        {
            "category":"Professional",
            "subcategory":"Art Services",
            "type":"Services"
        }
    ],
    "sg:phone":"+1 503 585 8074",
    "sg:postcode":"97302",
    "sg:province":"OR",
    "sg:tags":[
        "graphic",
        "commercial",
        "designer",
        "artist"
    ],
    "wof:name":"City Street Graphics",
    "wof:placetype":"venue"
},
  "geometry": {"coordinates":[-123.07191899999999,44.908891],"type":"Point"}
}