{
  "type": "Feature",
  "properties": {
    "iso:country":"US",
    "sg:address":"2136 E Burnside St",
    "sg:city":"Portland",
    "sg:classifiers":[
        {
            "category":"Shopping",
            "type":"Retail Goods"
        }
    ],
    "sg:phone":"+1 503 548 4390",
    "sg:postcode":"97214",
    "sg:province":"OR",
    "sg:website":"www.localgoodsllc.com",
    "wof:name":"Local Goods Llc",
    "wof:placetype":"venue"
},
  "geometry": {"coordinates":[-122.644079,45.522723],"type":"Point"}
}