{
  "type": "Feature",
  "properties": {
    "iso:country":"US",
    "sg:address":"3769 Market St NE",
    "sg:city":"Salem",
    "sg:classifiers":[
        {
            "category":"Manufacturing",
            "subcategory":"Glass & Minerals",
            "type":"Manufacturing & Wholesale Goods"
        },
        {
            "category":"Retail",
            "subcategory":"Auto Repair",
            "type":"Services"
        }
    ],
    "sg:phone":"+1 503 375 3000",
    "sg:postcode":"97301",
    "sg:province":"OR",
    "sg:tags":[
        "plate",
        "window",
        "windshield",
        "glass-auto"
    ],
    "sg:website":"http://www.actionautoglass.com",
    "wof:name":"Action Auto Glass",
    "wof:placetype":"venue"
},
  "geometry": {"coordinates":[-122.986857,44.950175],"type":"Point"}
}