{
  "type": "Feature",
  "properties": {
    "iso:country":"US",
    "sg:address":"203 Kit Ln",
    "sg:city":"Sutherlin",
    "sg:classifiers":[
        {
            "category":"Autos & Motor Vehicles",
            "subcategory":"Motorcycle Sales",
            "type":"Retail Goods"
        }
    ],
    "sg:phone":"+1 541 459 2123",
    "sg:postcode":"97479",
    "sg:province":"OR",
    "sg:tags":[
        "accessory"
    ],
    "wof:name":"Richard B Chase",
    "wof:placetype":"venue"
},
  "geometry": {"coordinates":[-123.357946,43.390783],"type":"Point"}
}