{
  "type": "Feature",
  "properties": {
    "addr:full":"812 7th Ave SE Albany OR 97321",
    "addr:housenumber":"812",
    "addr:postcode":"97321",
    "addr:street":"7Th Ave Se",
    "iso:country":"US",
    "sg:address":"812 7th Ave SE",
    "sg:city":"Albany",
    "sg:classifiers":[
        {
            "category":"Building & Trades",
            "subcategory":"Electrical",
            "type":"Services"
        }
    ],
    "sg:phone":"+1 541 791 1115",
    "sg:postcode":"97321",
    "sg:province":"OR",
    "sg:tags":[
        "electric",
        "contractor"
    ],
    "wof:name":"Rayco Electric",
    "wof:placetype":"venue"
},
  "geometry": {"coordinates":[-123.093926,44.633745],"type":"Point"}
}