{
  "type": "Feature",
  "properties": {
    "addr:full":"13739 SW Lauren Ln Portland OR 97223",
    "addr:housenumber":"13739",
    "addr:postcode":"97223",
    "addr:street":"Sw Lauren Ln",
    "iso:country":"US",
    "sg:address":"13739 SW Lauren Ln",
    "sg:city":"Portland",
    "sg:classifiers":[
        {
            "category":"Building & Trades",
            "subcategory":"Construction",
            "type":"Services"
        }
    ],
    "sg:phone":"+1 503 579 4092",
    "sg:postcode":"97223",
    "sg:province":"OR",
    "sg:tags":[
        "house"
    ],
    "wof:name":"Emanuel Leascu",
    "wof:placetype":"venue"
},
  "geometry": {"coordinates":[-122.818831,45.425387],"type":"Point"}
}