{
  "type": "Feature",
  "properties": {
    "iso:country":"US",
    "sg:address":"1120 Campbell St",
    "sg:city":"Baker City",
    "sg:classifiers":[
        {
            "category":"Food & Beverages",
            "subcategory":"Groceries & Convenience Stores",
            "type":"Retail Goods"
        }
    ],
    "sg:phone":"+1 541 524 0412",
    "sg:postcode":"97814",
    "sg:province":"OR",
    "sg:tags":[
        "supermarket",
        "chain"
    ],
    "wof:name":"Albertsons 262",
    "wof:placetype":"venue"
},
  "geometry": {"coordinates":[-117.819422,44.781728],"type":"Point"}
}