{
  "type": "Feature",
  "properties": {
    "iso:country":"US",
    "sg:address":"1001 SW 5th Ave",
    "sg:city":"Portland",
    "sg:classifiers":[
        {
            "category":"Banks & Credit Unions",
            "subcategory":"Bank",
            "type":"Services"
        }
    ],
    "sg:phone":"+1 503 220 1630",
    "sg:postcode":"97204",
    "sg:province":"OR",
    "sg:tags":[
        "mortgage"
    ],
    "wof:name":"American First RE Svcs",
    "wof:placetype":"venue"
},
  "geometry": {"coordinates":[-122.679023,45.516141],"type":"Point"}
}