{
  "type": "Feature",
  "properties": {
    "iso:country":"US",
    "sg:address":"5501 NE 30th Ave",
    "sg:city":"Portland",
    "sg:classifiers":[
        {
            "category":"Personal",
            "subcategory":"Beauty Salon",
            "type":"Services"
        }
    ],
    "sg:phone":"+1 503 493 4040",
    "sg:postcode":"97211",
    "sg:province":"OR",
    "sg:tags":[
        "shop"
    ],
    "wof:name":"It's About Hair",
    "wof:placetype":"venue"
},
  "geometry": {"coordinates":[-122.63493099999999,45.564447],"type":"Point"}
}