{
  "type": "Feature",
  "properties": {
    "addr:full":"300 Ave A Seaside OR 97138",
    "addr:housenumber":"300",
    "addr:postcode":"97138",
    "addr:street":"Ave A",
    "iso:country":"US",
    "sg:address":"300 Ave A",
    "sg:city":"Seaside",
    "sg:classifiers":[
        {
            "category":"Government",
            "subcategory":"Post Office",
            "type":"Public Place"
        }
    ],
    "sg:phone":"+1 503 738 5190",
    "sg:postcode":"97138",
    "sg:province":"OR",
    "sg:tags":[
        "postal",
        "us"
    ],
    "wof:name":"US Post Office",
    "wof:placetype":"venue"
},
  "geometry": {"coordinates":[-123.927273,45.992281],"type":"Point"}
}