{
  "type": "Feature",
  "properties": {
    "iso:country":"US",
    "sg:address":"7640 N Jersey St",
    "sg:city":"Portland",
    "sg:classifiers":[
        {
            "category":"Professional",
            "subcategory":"Accounting & Tax Preparation",
            "type":"Services"
        }
    ],
    "sg:phone":"+1 503 286 6511",
    "sg:postcode":"97203",
    "sg:province":"OR",
    "sg:tags":[
        "accountant"
    ],
    "wof:name":"Leo Kahn PC",
    "wof:placetype":"venue"
},
  "geometry": {"coordinates":[-122.745271,45.586801],"type":"Point"}
}