{
  "type": "Feature",
  "properties": {
    "addr:full":"1147 Main St Springfield OR 97477",
    "addr:housenumber":"1147",
    "addr:postcode":"97477",
    "addr:street":"Main St",
    "iso:country":"US",
    "sg:address":"1147 Main St",
    "sg:city":"Springfield",
    "sg:classifiers":[
        {
            "category":"Retail",
            "subcategory":"Auto Repair",
            "type":"Services"
        }
    ],
    "sg:phone":"+1 541 726 4773",
    "sg:postcode":"97477",
    "sg:province":"OR",
    "sg:tags":[
        "repairing",
        "automobile",
        "general"
    ],
    "wof:name":"Greg Cochran Motorsports",
    "wof:placetype":"venue"
},
  "geometry": {"coordinates":[-123.009688,44.04587],"type":"Point"}
}