{
  "type": "Feature",
  "properties": {
    "addr:full":"24225 SW Durdel Dr Sherwood OR 97140",
    "addr:housenumber":"24225",
    "addr:postcode":"97140",
    "addr:street":"Sw Durdel Dr",
    "iso:country":"US",
    "sg:address":"24225 SW Durdel Dr",
    "sg:city":"Sherwood",
    "sg:classifiers":[
        {
            "category":"Personal",
            "subcategory":"Beauty Salon",
            "type":"Services"
        }
    ],
    "sg:phone":"+1 503 625 5000",
    "sg:postcode":"97140",
    "sg:province":"OR",
    "wof:name":"City Looks Salon",
    "wof:placetype":"venue"
},
  "geometry": {"coordinates":[-122.906898,45.343541],"type":"Point"}
}