{
  "type": "Feature",
  "properties": {
    "addr:full":"734 NE Knoll Ave Roseburg OR 97470",
    "addr:housenumber":"734",
    "addr:postcode":"97470",
    "addr:street":"Ne Knoll Ave",
    "iso:country":"US",
    "sg:address":"734 NE Knoll Ave",
    "sg:city":"Roseburg",
    "sg:classifiers":[
        {
            "category":"Professional",
            "type":"Services"
        }
    ],
    "sg:phone":"+1 541 672 0715",
    "sg:postcode":"97470",
    "sg:province":"OR",
    "wof:name":"Martch Innovations",
    "wof:placetype":"venue"
},
  "geometry": {"coordinates":[-123.34672399999999,43.245917],"type":"Point"}
}