{
  "type": "Feature",
  "properties": {
    "iso:country":"US",
    "sg:address":"12056 SE Sunnyside Rd",
    "sg:city":"Clackamas",
    "sg:classifiers":[
        {
            "category":"Bars & Pubs",
            "subcategory":"Lounge",
            "type":"Food & Drink"
        },
        {
            "category":"Personal",
            "type":"Services"
        }
    ],
    "sg:phone":"+1 503 698 5411",
    "sg:postcode":"97015",
    "sg:province":"OR",
    "sg:tags":[
        "party",
        "planning",
        "event",
        "cocktail"
    ],
    "sg:website":"www.ceramicafenw.com",
    "wof:name":"Ceramicafe Art Lounge",
    "wof:placetype":"venue"
},
  "geometry": {"coordinates":[-122.540001,45.429501],"type":"Point"}
}