{
  "type": "Feature",
  "properties": {
    "addr:full":"4867 NE Martin Luther King Jr. Blvd. Portland OR 97211",
    "addr:housenumber":"4867",
    "addr:postcode":"97211",
    "addr:street":"Ne Martin Luther King Jr. Blvd.",
    "iso:country":"US",
    "sg:address":"4867 NE Martin Luther King Jr. Blvd.",
    "sg:city":"Portland",
    "sg:classifiers":[
        {
            "category":"Personal",
            "subcategory":"Massage",
            "type":"Services"
        },
        {
            "category":"Health Services",
            "subcategory":"Clinic",
            "type":"Services"
        }
    ],
    "sg:phone":"+1 503 288 5579",
    "sg:postcode":"97211",
    "sg:province":"OR",
    "sg:tags":[
        "cannabis"
    ],
    "sg:website":"www.altmedchoices.com",
    "wof:name":"Alternative Medical Choices",
    "wof:placetype":"venue"
},
  "geometry": {"coordinates":[-122.661619,45.557552],"type":"Point"}
}