{
  "type": "Feature",
  "properties": {
    "iso:country":"US",
    "sg:address":"44829 Quartzville Dr",
    "sg:city":"Foster",
    "sg:classifiers":[
        {
            "category":"Social Services",
            "subcategory":"Child Care",
            "type":"Services"
        }
    ],
    "sg:phone":"+1 541 367 8070",
    "sg:postcode":"97345",
    "sg:province":"OR",
    "sg:tags":[
        "kindergarten",
        "academic",
        "school"
    ],
    "wof:name":"Sunnyside Head Start Preschool",
    "wof:placetype":"venue"
},
  "geometry": {"coordinates":[-122.613017,44.430283],"type":"Point"}
}