{
  "type": "Feature",
  "properties": {
    "addr:full":"4531 SW Idaho Dr Portland OR 97221",
    "addr:housenumber":"4531",
    "addr:postcode":"97221",
    "addr:street":"Sw Idaho Dr",
    "iso:country":"US",
    "sg:address":"4531 SW Idaho Dr",
    "sg:city":"Portland",
    "sg:classifiers":[
        {
            "category":"Professional",
            "subcategory":"Computer Services",
            "type":"Services"
        }
    ],
    "sg:phone":"+1 503 490 6633",
    "sg:postcode":"97221",
    "sg:province":"OR",
    "sg:tags":[
        "consulting",
        "it"
    ],
    "wof:name":"Zone Intergration Group LLC",
    "wof:placetype":"venue"
},
  "geometry": {"coordinates":[-122.725151,45.476771],"type":"Point"}
}