{
  "type": "Feature",
  "properties": {
    "addr:full":"16200 NE Glisan St Portland OR 97230",
    "addr:housenumber":"16200",
    "addr:postcode":"97230",
    "addr:street":"Ne Glisan St",
    "iso:country":"US",
    "sg:address":"16200 NE Glisan St",
    "sg:city":"Portland",
    "sg:classifiers":[
        {
            "category":"Retail",
            "subcategory":"Portrait Studio",
            "type":"Services"
        },
        {
            "category":"Shopping",
            "subcategory":"Pharmacy",
            "type":"Retail Goods"
        }
    ],
    "sg:phone":"+1 503 251 8995",
    "sg:postcode":"97230",
    "sg:province":"OR",
    "sg:tags":[
        "photography",
        "drugstore",
        "store"
    ],
    "sg:website":"www.walgreens.com",
    "wof:name":"Walgreens",
    "wof:placetype":"venue"
},
  "geometry": {"coordinates":[-122.495214,45.525808],"type":"Point"}
}