{
  "type": "Feature",
  "properties": {
    "addr:full":"5482 Valleywood Dr Klamath Falls OR 97603",
    "addr:housenumber":"5482",
    "addr:postcode":"97603",
    "addr:street":"Valleywood Dr",
    "iso:country":"US",
    "sg:address":"5482 Valleywood Dr",
    "sg:city":"Klamath Falls",
    "sg:classifiers":[
        {
            "category":"Wholesale",
            "subcategory":"Groceries",
            "type":"Manufacturing & Wholesale Goods"
        }
    ],
    "sg:phone":"+1 541 884 2411",
    "sg:postcode":"97603",
    "sg:province":"OR",
    "sg:tags":[
        "food",
        "snack"
    ],
    "wof:name":"Finley Distribution",
    "wof:placetype":"venue"
},
  "geometry": {"coordinates":[-121.73191199999999,42.175263],"type":"Point"}
}