{
  "type": "Feature",
  "properties": {
    "addr:full":"20580 Bowery Ln Bend OR 97701",
    "addr:postcode":"20580;97701",
    "addr:street":"Bowery Ln",
    "iso:country":"US",
    "sg:address":"20580 Bowery Ln",
    "sg:city":"Bend",
    "sg:classifiers":[
        {
            "category":"Building & Trades",
            "subcategory":"Landscaping Services",
            "type":"Services"
        }
    ],
    "sg:phone":"+1 541 330 6249",
    "sg:postcode":"97701",
    "sg:province":"OR",
    "sg:tags":[
        "landscape",
        "contractor"
    ],
    "wof:name":"Seven Seasons Landscape Svcs",
    "wof:placetype":"venue"
},
  "geometry": {"coordinates":[-121.295655,44.120195],"type":"Point"}
}