{
  "type": "Feature",
  "properties": {
    "addr:full":"741 W Central Ave Sutherlin OR 97479",
    "addr:housenumber":"741",
    "addr:postcode":"97479",
    "addr:street":"W Central Ave",
    "iso:country":"US",
    "sg:address":"741 W Central Ave",
    "sg:city":"Sutherlin",
    "sg:classifiers":[
        {
            "category":"Education",
            "subcategory":"School",
            "type":"Public Place"
        }
    ],
    "sg:phone":"+1 541 459 9706",
    "sg:postcode":"97479",
    "sg:province":"OR",
    "wof:name":"Seventh-Day Adventist School",
    "wof:placetype":"venue"
},
  "geometry": {"coordinates":[-123.32381599999999,43.388386],"type":"Point"}
}