{
  "type": "Feature",
  "properties": {
    "iso:country":"US",
    "sg:address":"3460 N Holly St",
    "sg:city":"Canby",
    "sg:classifiers":[
        {
            "category":"Farming",
            "subcategory":"Nursery",
            "type":"Manufacturing & Wholesale Goods"
        }
    ],
    "sg:phone":"+1 503 266 6355",
    "sg:postcode":"97013",
    "sg:province":"OR",
    "sg:tags":[
        "ornamental"
    ],
    "wof:name":"Parker Nursery",
    "wof:placetype":"venue"
},
  "geometry": {"coordinates":[-122.696985,45.293096],"type":"Point"}
}