{
  "type": "Feature",
  "properties": {
    "addr:full":"31018 Vail Creek Rd Lebanon OR 97355",
    "addr:housenumber":"31018",
    "addr:postcode":"97355",
    "addr:street":"Vail Creek Rd",
    "iso:country":"US",
    "sg:address":"31018 Vail Creek Rd",
    "sg:city":"Lebanon",
    "sg:classifiers":[
        {
            "category":"Building & Trades",
            "subcategory":"Construction",
            "type":"Services"
        }
    ],
    "sg:phone":"+1 541 259 3436",
    "sg:postcode":"97355",
    "sg:province":"OR",
    "sg:tags":[
        "house"
    ],
    "wof:name":"Stewart Underground Const",
    "wof:placetype":"venue"
},
  "geometry": {"coordinates":[-122.827504,44.492057],"type":"Point"}
}