{
  "type": "Feature",
  "properties": {
    "addr:full":"3821 Matheny Rd NE Gervais OR 97026",
    "addr:housenumber":"3821",
    "addr:postcode":"97026",
    "addr:street":"Matheny Rd Ne",
    "iso:country":"US",
    "sg:address":"3821 Matheny Rd NE",
    "sg:city":"Gervais",
    "sg:classifiers":[
        {
            "category":"Food & Beverages",
            "subcategory":"Candy",
            "type":"Retail Goods"
        }
    ],
    "sg:phone":"+1 503 393 4232",
    "sg:postcode":"97026",
    "sg:province":"OR",
    "sg:tags":[
        "nut"
    ],
    "wof:name":"Hunt's Hazelnuts",
    "wof:placetype":"venue"
},
  "geometry": {"coordinates":[-122.983254,45.092405],"type":"Point"}
}