{
  "type": "Feature",
  "properties": {
    "iso:country":"US",
    "sg:address":"505 27th Ave SE",
    "sg:city":"Albany",
    "sg:classifiers":[
        {
            "category":"Real Estate",
            "subcategory":"Real Estate Operator",
            "type":"Services"
        }
    ],
    "sg:phone":"+1 503 581 9317",
    "sg:postcode":"97322",
    "sg:province":"OR",
    "sg:tags":[
        "building",
        "apartment"
    ],
    "wof:name":"American Village Of Albany",
    "wof:placetype":"venue"
},
  "geometry": {"coordinates":[-123.096356,44.615461],"type":"Point"}
}