{
  "type": "Feature",
  "properties": {
    "iso:country":"US",
    "sg:address":"2200 6th Ave W",
    "sg:city":"Vale",
    "sg:classifiers":[
        {
            "category":"Restaurant",
            "type":"Food & Drink"
        }
    ],
    "sg:phone":"+1 541 473 3365",
    "sg:postcode":"97918",
    "sg:province":"OR",
    "wof:name":"Jeffrey T Romans",
    "wof:placetype":"venue"
},
  "geometry": {"coordinates":[-117.332047,44.069111],"type":"Point"}
}