{
  "type": "Feature",
  "properties": {
    "addr:full":"95109 Myrtle Wood Ln Coos Bay OR 97420",
    "addr:housenumber":"95109",
    "addr:postcode":"97420",
    "addr:street":"Myrtle Wood Ln",
    "iso:country":"US",
    "sg:address":"95109 Myrtle Wood Ln",
    "sg:city":"Coos Bay",
    "sg:classifiers":[
        {
            "category":"Retail",
            "subcategory":"Auto Repair",
            "type":"Services"
        }
    ],
    "sg:phone":"+1 541 267 0452",
    "sg:postcode":"97420",
    "sg:province":"OR",
    "sg:tags":[
        "general"
    ],
    "wof:name":"Johns Auto Rv",
    "wof:placetype":"venue"
},
  "geometry": {"coordinates":[-124.151973,43.371155],"type":"Point"}
}