{
  "type": "Feature",
  "properties": {
    "addr:full":"2544 Manor Dr Springfield OR 97477",
    "addr:housenumber":"2544",
    "addr:postcode":"97477",
    "addr:street":"Manor Dr",
    "iso:country":"US",
    "sg:address":"2544 Manor Dr",
    "sg:city":"Springfield",
    "sg:classifiers":[
        {
            "category":"Professional",
            "subcategory":"Advertising",
            "type":"Services"
        }
    ],
    "sg:phone":"+1 541 746 6886",
    "sg:postcode":"97477",
    "sg:province":"OR",
    "sg:tags":[
        "agency"
    ],
    "wof:name":"Ad Ltd",
    "wof:placetype":"venue"
},
  "geometry": {"coordinates":[-123.026704,44.071212],"type":"Point"}
}