{
  "type": "Feature",
  "properties": {
    "iso:country":"US",
    "sg:address":"8 Coburg Rd",
    "sg:city":"Eugene",
    "sg:classifiers":[
        {
            "category":"Retail",
            "subcategory":"Laundry & Dry Cleaning",
            "type":"Services"
        }
    ],
    "sg:phone":"+1 541 485 7949",
    "sg:postcode":"97401",
    "sg:province":"OR",
    "wof:name":"Emerald Valley Carpet Care",
    "wof:placetype":"venue"
},
  "geometry": {"coordinates":[-123.08009,44.062363],"type":"Point"}
}