{
  "type": "Feature",
  "properties": {
    "addr:full":"4010 SE Cirrus Ave Mcminnville OR 97128",
    "addr:housenumber":"4010",
    "addr:postcode":"97128",
    "addr:street":"Se Cirrus Ave",
    "iso:country":"US",
    "sg:address":"4010 SE Cirrus Ave",
    "sg:city":"Mcminnville",
    "sg:classifiers":[
        {
            "category":"Retail",
            "subcategory":"Repair Shop",
            "type":"Services"
        }
    ],
    "sg:phone":"+1 503 864 2012",
    "sg:postcode":"97128",
    "sg:province":"OR",
    "wof:name":"Daves Avionics",
    "wof:placetype":"venue"
},
  "geometry": {"coordinates":[-123.13902899999999,45.199663],"type":"Point"}
}