{
  "type": "Feature",
  "properties": {
    "iso:country":"US",
    "sg:address":"1263 Main St",
    "sg:city":"Springfield",
    "sg:classifiers":[
        {
            "category":"Real Estate",
            "subcategory":"Real Estate Operator",
            "type":"Services"
        }
    ],
    "sg:phone":"+1 541 746 6321",
    "sg:postcode":"97477",
    "sg:province":"OR",
    "sg:tags":[
        "mobile",
        "home",
        "site"
    ],
    "wof:name":"Springfield Mobile Home Park",
    "wof:placetype":"venue"
},
  "geometry": {"coordinates":[-123.00559,44.045812],"type":"Point"}
}