{
  "type": "Feature",
  "properties": {
    "addr:full":"12300 SE Mallard Way Milwaukie OR 97222",
    "addr:postcode":"12300;97222",
    "addr:street":"Se Mallard Way",
    "iso:country":"US",
    "sg:address":"12300 SE Mallard Way",
    "sg:city":"Milwaukie",
    "sg:classifiers":[
        {
            "category":"Organizations",
            "subcategory":"Professional Association",
            "type":"Services"
        },
        {
            "category":"Organizations",
            "subcategory":"Community Association",
            "type":"Services"
        }
    ],
    "sg:phone":"+1 503 653 1197",
    "sg:postcode":"97222",
    "sg:province":"OR",
    "sg:tags":[
        "civic",
        "social"
    ],
    "wof:name":"North Clackamas Education Assn",
    "wof:placetype":"venue"
},
  "geometry": {"coordinates":[-122.61018799999999,45.435513],"type":"Point"}
}