{
  "type": "Feature",
  "properties": {
    "iso:country":"US",
    "sg:address":"1936 N Danebo Ave",
    "sg:city":"Eugene",
    "sg:classifiers":[
        {
            "category":"Organizations",
            "subcategory":"Professional Association",
            "type":"Services"
        }
    ],
    "sg:phone":"+1 541 689 2190",
    "sg:postcode":"97402",
    "sg:province":"OR",
    "sg:tags":[
        "business"
    ],
    "wof:name":"Day Sailer Association",
    "wof:placetype":"venue"
},
  "geometry": {"coordinates":[-123.178861,44.081354],"type":"Point"}
}