{
  "type": "Feature",
  "properties": {
    "addr:full":"1708 NE 138th Pl Portland OR 97230",
    "addr:housenumber":"1708",
    "addr:postcode":"97230",
    "addr:street":"Ne 138Th Pl",
    "iso:country":"US",
    "sg:address":"1708 NE 138th Pl",
    "sg:city":"Portland",
    "sg:classifiers":[
        {
            "category":"Building & Trades",
            "subcategory":"Locksmith",
            "type":"Services"
        }
    ],
    "sg:phone":"+1 503 473 0155",
    "sg:postcode":"97230",
    "sg:province":"OR",
    "sg:tags":[
        "key"
    ],
    "wof:name":"Locks 1 2 3 Locksmith",
    "wof:placetype":"venue"
},
  "geometry": {"coordinates":[-122.520301,45.535191],"type":"Point"}
}