{
  "type": "Feature",
  "properties": {
    "addr:full":"75694 Wicks Rd Dorena OR 97434",
    "addr:postcode":"75694;97434",
    "addr:street":"Wicks Rd",
    "iso:country":"US",
    "sg:address":"75694 Wicks Rd",
    "sg:city":"Dorena",
    "sg:classifiers":[
        {
            "category":"Government",
            "subcategory":"Post Office",
            "type":"Public Place"
        }
    ],
    "sg:phone":"+1 541 946 1616",
    "sg:postcode":"97434",
    "sg:province":"OR",
    "wof:name":"US Post Office",
    "wof:placetype":"venue"
},
  "geometry": {"coordinates":[-122.863789,43.719526],"type":"Point"}
}