{
  "type": "Feature",
  "properties": {
    "iso:country":"US",
    "sg:address":"3298 Jack St N",
    "sg:city":"Keizer",
    "sg:classifiers":[
        {
            "category":"Building & Trades",
            "subcategory":"Landscaping Services",
            "type":"Services"
        }
    ],
    "sg:phone":"+1 503 390 0211",
    "sg:postcode":"97303",
    "sg:province":"OR",
    "sg:tags":[
        "landscape",
        "contractor"
    ],
    "wof:name":"D C Fountains & Ponds",
    "wof:placetype":"venue"
},
  "geometry": {"coordinates":[-123.03268,44.97287],"type":"Point"}
}