{
  "type": "Feature",
  "properties": {
    "iso:country":"US",
    "sg:address":"11740 Meadowlark",
    "sg:city":"Prineville",
    "sg:classifiers":[
        {
            "category":"Autos & Motor Vehicles",
            "subcategory":"Auto Supplies",
            "type":"Retail Goods"
        }
    ],
    "sg:phone":"+1 541 416 8481",
    "sg:postcode":"97754",
    "sg:province":"OR",
    "wof:name":"Adaptive Off Road Adventures",
    "wof:placetype":"venue"
},
  "geometry": {"coordinates":[-120.759469,44.19304],"type":"Point"}
}