{
  "type": "Feature",
  "properties": {
    "addr:full":"3521 Gateway St Springfield OR 97477",
    "addr:housenumber":"3521",
    "addr:postcode":"97477",
    "addr:street":"Gateway St",
    "iso:country":"US",
    "sg:address":"3521 Gateway St",
    "sg:city":"Springfield",
    "sg:classifiers":[
        {
            "category":"Food & Beverages",
            "subcategory":"Groceries & Convenience Stores",
            "type":"Retail Goods"
        }
    ],
    "sg:phone":"+1 541 747 3242",
    "sg:postcode":"97477",
    "sg:province":"OR",
    "wof:name":"AM PM Mini Mart",
    "wof:placetype":"venue"
},
  "geometry": {"coordinates":[-123.042073,44.085612],"type":"Point"}
}