{
  "type": "Feature",
  "properties": {
    "iso:country":"US",
    "sg:address":"808 NE 162nd Ave",
    "sg:city":"Portland",
    "sg:classifiers":[
        {
            "category":"Building & Trades",
            "subcategory":"Cleaning & Sanitation",
            "type":"Services"
        }
    ],
    "sg:phone":"+1 503 231 5060",
    "sg:postcode":"97230",
    "sg:province":"OR",
    "sg:tags":[
        "maintenance"
    ],
    "wof:name":"Mop & Bucket",
    "wof:placetype":"venue"
},
  "geometry": {"coordinates":[-122.496295,45.528364],"type":"Point"}
}