{
  "type": "Feature",
  "properties": {
    "iso:country":"US",
    "sg:address":"699 Jumpoff Joe Creek Rd",
    "sg:city":"Grants Pass",
    "sg:classifiers":[
        {
            "category":"Shopping",
            "subcategory":"Used Merchandise",
            "type":"Retail Goods"
        }
    ],
    "sg:phone":"+1 541 956 8688",
    "sg:postcode":"97526",
    "sg:province":"OR",
    "wof:name":"Pack Rats Antiques Zebras",
    "wof:placetype":"venue"
},
  "geometry": {"coordinates":[-123.364392,42.571892],"type":"Point"}
}