{
  "type": "Feature",
  "properties": {
    "iso:country":"US",
    "sg:address":"8445 SW Hemlock St",
    "sg:city":"Portland",
    "sg:classifiers":[
        {
            "category":"Health Services",
            "subcategory":"Nursing And Care Facility",
            "type":"Services"
        }
    ],
    "sg:phone":"+1 503 245 8985",
    "sg:postcode":"97223",
    "sg:province":"OR",
    "sg:tags":[
        "intermediate"
    ],
    "wof:name":"Park Place",
    "wof:placetype":"venue"
},
  "geometry": {"coordinates":[-122.762369,45.449365],"type":"Point"}
}