{
  "type": "Feature",
  "properties": {
    "iso:country":"US",
    "sg:address":"7930 SW 77th St",
    "sg:city":"Redmond",
    "sg:classifiers":[
        {
            "category":"Shopping",
            "subcategory":"Gifts & Souvenirs",
            "type":"Retail Goods"
        },
        {
            "category":"Shopping",
            "subcategory":"Crafts & Fabrics",
            "type":"Retail Goods"
        },
        {
            "category":"Retail",
            "subcategory":"Storage",
            "type":"Services"
        }
    ],
    "sg:phone":"+1 541 382 5574",
    "sg:postcode":"97756",
    "sg:province":"OR",
    "sg:tags":[
        "shop",
        "rock",
        "art",
        "supply"
    ],
    "wof:name":"Petersen Rock Garden & Museum",
    "wof:placetype":"venue"
},
  "geometry": {"coordinates":[-121.263564,44.202225],"type":"Point"}
}