{
  "type": "Feature",
  "properties": {
    "iso:country":"US",
    "sg:address":"355 NW 7th St",
    "sg:city":"Corvallis",
    "sg:classifiers":[
        {
            "category":"Organizations",
            "subcategory":"Community Association",
            "type":"Services"
        }
    ],
    "sg:phone":"+1 541 753 2199",
    "sg:postcode":"97330",
    "sg:province":"OR",
    "sg:tags":[
        "environmental",
        "org"
    ],
    "sg:website":"www.nwhi.org",
    "wof:name":"Northwest Habitat Institute",
    "wof:placetype":"venue"
},
  "geometry": {"coordinates":[-123.26378099999999,44.567812],"type":"Point"}
}