{
  "type": "Feature",
  "properties": {
    "iso:country":"US",
    "sg:address":"540 E Vilas Rd",
    "sg:city":"Central Point",
    "sg:classifiers":[
        {
            "category":"Communications",
            "type":"Services"
        }
    ],
    "sg:phone":"+1 541 664 3069",
    "sg:postcode":"97502",
    "sg:province":"OR",
    "wof:name":"Ironwood Communications",
    "wof:placetype":"venue"
},
  "geometry": {"coordinates":[-122.873086,42.389226],"type":"Point"}
}