{
  "type": "Feature",
  "properties": {
    "iso:country":"US",
    "sg:address":"8250 SW Nimbus Ave",
    "sg:city":"Beaverton",
    "sg:classifiers":[
        {
            "category":"Wholesale",
            "subcategory":"Apparel",
            "type":"Manufacturing & Wholesale Goods"
        }
    ],
    "sg:phone":"+1 503 641 1120",
    "sg:postcode":"97008",
    "sg:province":"OR",
    "sg:tags":[
        "fabrics-wholesale",
        "piece",
        "manufacturer"
    ],
    "wof:name":"S K Fabrics Inc",
    "wof:placetype":"venue"
},
  "geometry": {"coordinates":[-122.789312,45.459796],"type":"Point"}
}