{
  "type": "Feature",
  "properties": {
    "iso:country":"US",
    "sg:address":"4415 SW Fairview Blvd",
    "sg:city":"Portland",
    "sg:classifiers":[
        {
            "category":"Health Services",
            "subcategory":"Doctor",
            "type":"Services"
        }
    ],
    "sg:phone":"+1 503 223 0125",
    "sg:postcode":"97221",
    "sg:province":"OR",
    "sg:tags":[
        "physician",
        "surgeon"
    ],
    "wof:name":"William M Rosenbaum MD",
    "wof:placetype":"venue"
},
  "geometry": {"coordinates":[-122.72224900000001,45.514526],"type":"Point"}
}