{
  "type": "Feature",
  "properties": {
    "iso:country":"US",
    "sg:address":"8481 SE Jannsen Rd",
    "sg:city":"Clackamas",
    "sg:classifiers":[
        {
            "category":"Farming",
            "subcategory":"Farm",
            "type":"Manufacturing & Wholesale Goods"
        }
    ],
    "sg:phone":"+1 503 655 1297",
    "sg:postcode":"97015",
    "sg:province":"OR",
    "sg:tags":[
        "crop",
        "general"
    ],
    "wof:name":"Hartnell Farms",
    "wof:placetype":"venue"
},
  "geometry": {"coordinates":[-122.57547099999999,45.41303],"type":"Point"}
}