{
  "type": "Feature",
  "properties": {
    "iso:country":"US",
    "sg:address":"6855 S Prairie Rd",
    "sg:city":"Tillamook",
    "sg:classifiers":[
        {
            "category":"Professional",
            "subcategory":"Management & Consulting",
            "type":"Services"
        }
    ],
    "sg:phone":"+1 503 842 4212",
    "sg:postcode":"97141",
    "sg:province":"OR",
    "sg:tags":[
        "consultant",
        "educational"
    ],
    "wof:name":"Smart",
    "wof:placetype":"venue"
},
  "geometry": {"coordinates":[-123.820145,45.407046],"type":"Point"}
}