{
  "type": "Feature",
  "properties": {
    "iso:country":"US",
    "sg:address":"1380 W 5th Ave",
    "sg:city":"Eugene",
    "sg:classifiers":[
        {
            "category":"Travel",
            "subcategory":"Travel Agent",
            "type":"Entertainment"
        }
    ],
    "sg:phone":"+1 541 686 3038",
    "sg:postcode":"97402",
    "sg:province":"OR",
    "sg:tags":[
        "operator",
        "tour"
    ],
    "wof:name":"Rv Caravan Tours",
    "wof:placetype":"venue"
},
  "geometry": {"coordinates":[-123.112809,44.054283],"type":"Point"}
}