{
  "type": "Feature",
  "properties": {
    "iso:country":"US",
    "sg:address":"19545 NW Von Neumann Dr",
    "sg:city":"Beaverton",
    "sg:classifiers":[
        {
            "category":"Wholesale",
            "subcategory":"Medical Equipment & Supplies",
            "type":"Manufacturing & Wholesale Goods"
        }
    ],
    "sg:phone":"+1 503 748 1400",
    "sg:postcode":"97006",
    "sg:province":"OR",
    "sg:tags":[
        "physician",
        "surgeon"
    ],
    "sg:website":"www.modocarts.com",
    "wof:name":"Modo Inc",
    "wof:placetype":"venue"
},
  "geometry": {"coordinates":[-122.88067,45.530741],"type":"Point"}
}