{
  "type": "Feature",
  "properties": {
    "addr:full":"8187 SW Tualatin Sherwood Rd Tualatin OR 97062",
    "addr:housenumber":"8187",
    "addr:postcode":"97062",
    "addr:street":"Sw Tualatin Sherwood Rd",
    "iso:country":"US",
    "sg:address":"8187 SW Tualatin Sherwood Rd",
    "sg:city":"Tualatin",
    "sg:classifiers":[
        {
            "category":"Building & Trades",
            "subcategory":"Locksmith",
            "type":"Services"
        }
    ],
    "sg:phone":"+1 503 404 0458",
    "sg:postcode":"97062",
    "sg:province":"OR",
    "sg:tags":[
        "key"
    ],
    "wof:name":"1 After Dringking Locksmith Rescue",
    "wof:placetype":"venue"
},
  "geometry": {"coordinates":[-122.76000999999999,45.381471],"type":"Point"}
}