{
  "type": "Feature",
  "properties": {
    "iso:country":"US",
    "sg:address":"1417 Birch Ave",
    "sg:city":"Cottage Grove",
    "sg:classifiers":[
        {
            "category":"Banks & Credit Unions",
            "subcategory":"Investment Brokerage",
            "type":"Services"
        }
    ],
    "sg:phone":"+1 541 942 6188",
    "sg:postcode":"97424",
    "sg:province":"OR",
    "sg:tags":[
        "consultant",
        "planning",
        "financial"
    ],
    "wof:name":"Lusk Financial Svc",
    "wof:placetype":"venue"
},
  "geometry": {"coordinates":[-123.072423,43.799209],"type":"Point"}
}