{
  "type": "Feature",
  "properties": {
    "iso:country":"US",
    "sg:address":"38751 E Cedar Flat Rd",
    "sg:city":"Springfield",
    "sg:classifiers":[
        {
            "category":"Home & Garden",
            "subcategory":"Building Materials",
            "type":"Retail Goods"
        },
        {
            "category":"Building & Trades",
            "subcategory":"Construction",
            "type":"Services"
        }
    ],
    "sg:phone":"+1 541 744 0577",
    "sg:postcode":"97478",
    "sg:province":"OR",
    "sg:tags":[
        "concrete",
        "fence-sales",
        "contractor"
    ],
    "wof:name":"Wall To Wall Construction",
    "wof:placetype":"venue"
},
  "geometry": {"coordinates":[-122.832032,44.04612],"type":"Point"}
}