{
  "type": "Feature",
  "properties": {
    "iso:country":"US",
    "sg:address":"56825 Venture Ln",
    "sg:city":"Bend",
    "sg:classifiers":[
        {
            "category":"Wholesale",
            "subcategory":"Medical Equipment & Supplies",
            "type":"Manufacturing & Wholesale Goods"
        }
    ],
    "sg:phone":"+1 541 593 2923",
    "sg:postcode":"97707",
    "sg:province":"OR",
    "sg:tags":[
        "physician",
        "surgeon"
    ],
    "wof:name":"Oregon Medical Rentals",
    "wof:placetype":"venue"
},
  "geometry": {"coordinates":[-121.435906,43.864394],"type":"Point"}
}