{
  "type": "Feature",
  "properties": {
    "addr:full":"5456 Adams Rd Talent OR 97540",
    "addr:housenumber":"5456",
    "addr:postcode":"97540",
    "addr:street":"Adams Rd",
    "iso:country":"US",
    "sg:address":"5456 Adams Rd",
    "sg:city":"Talent",
    "sg:classifiers":[
        {
            "category":"Museum",
            "subcategory":"Botanical Garden",
            "type":"Entertainment"
        }
    ],
    "sg:phone":"+1 541 535 2863",
    "sg:postcode":"97540",
    "sg:province":"OR",
    "sg:tags":[
        "surveying"
    ],
    "wof:name":"Scott Loring",
    "wof:placetype":"venue"
},
  "geometry": {"coordinates":[-122.818549,42.249325],"type":"Point"}
}