{
  "type": "Feature",
  "properties": {
    "iso:country":"US",
    "sg:address":"375 E Oregon Ave",
    "sg:city":"Creswell",
    "sg:classifiers":[
        {
            "category":"Tea Room",
            "subcategory":"None",
            "type":"Food & Drink"
        },
        {
            "category":"Coffee & Tea",
            "type":"Food & Drink"
        },
        {
            "category":"Restaurant",
            "type":"Food & Drink"
        }
    ],
    "sg:phone":"+1 541 895 8905",
    "sg:postcode":"97426",
    "sg:province":"OR",
    "sg:tags":[
        "shop",
        "espresso"
    ],
    "wof:name":"Bean Hopper",
    "wof:placetype":"venue"
},
  "geometry": {"coordinates":[-123.015304,43.917934],"type":"Point"}
}