{
  "type": "Feature",
  "properties": {
    "iso:country":"US",
    "sg:address":"7265 SW Trinity Pl",
    "sg:city":"Cornelius",
    "sg:classifiers":[
        {
            "category":"Organizations",
            "subcategory":"Religious Organization",
            "type":"Services"
        }
    ],
    "sg:phone":"+1 503 648 7802",
    "sg:postcode":"97113",
    "sg:province":"OR",
    "wof:name":"Overflow Ministries",
    "wof:placetype":"venue"
},
  "geometry": {"coordinates":[-123.006026,45.466919],"type":"Point"}
}