{
  "type": "Feature",
  "properties": {
    "iso:country":"US",
    "sg:address":"2189 14th Ave SE",
    "sg:city":"Albany",
    "sg:classifiers":[
        {
            "category":"Real Estate",
            "subcategory":"Real Estate Services",
            "type":"Services"
        },
        {
            "category":"Real Estate",
            "subcategory":"Real Estate Agent",
            "type":"Services"
        }
    ],
    "sg:phone":"+1 541 928 1277",
    "sg:postcode":"97322",
    "sg:province":"OR",
    "sg:tags":[
        "buyer",
        "broker"
    ],
    "wof:name":"Era Ransom & Smith Realty Inc",
    "wof:placetype":"venue"
},
  "geometry": {"coordinates":[-123.078557,44.628683],"type":"Point"}
}