{
  "type": "Feature",
  "properties": {
    "iso:country":"US",
    "sg:address":"513 NW 23rd Ave",
    "sg:city":"Portland",
    "sg:classifiers":[
        {
            "category":"Personal",
            "subcategory":"Beauty Salon",
            "type":"Services"
        }
    ],
    "sg:phone":"+1 503 227 3390",
    "sg:postcode":"97210",
    "sg:province":"OR",
    "sg:tags":[
        "shop",
        "makeup",
        "artist",
        "care",
        "skin"
    ],
    "sg:website":"www.blushbeautybar247.com",
    "wof:name":"Blush Beauty Bar",
    "wof:placetype":"venue"
},
  "geometry": {"coordinates":[-122.698914,45.526579],"type":"Point"}
}