{
  "type": "Feature",
  "properties": {
    "iso:country":"US",
    "sg:address":"2260 Three Lakes Rd SE",
    "sg:city":"Albany",
    "sg:classifiers":[
        {
            "category":"Utilities",
            "type":"Services"
        }
    ],
    "sg:phone":"+1 541 917 6696",
    "sg:postcode":"97322",
    "sg:province":"OR",
    "sg:tags":[
        "environmental",
        "consulting"
    ],
    "wof:name":"Cowlitz Clean Sweep CCS",
    "wof:placetype":"venue"
},
  "geometry": {"coordinates":[-123.05598500000001,44.620697],"type":"Point"}
}