{
  "type": "Feature",
  "properties": {
    "iso:country":"US",
    "sg:address":"210 SW 150th Ave",
    "sg:city":"Beaverton",
    "sg:classifiers":[
        {
            "category":"Social Services",
            "subcategory":"Adult Care",
            "type":"Services"
        }
    ],
    "sg:phone":"+1 503 626 9617",
    "sg:postcode":"97006",
    "sg:province":"OR",
    "sg:tags":[
        "residential",
        "foster"
    ],
    "wof:name":"Virgie's Adult Foster Home",
    "wof:placetype":"venue"
},
  "geometry": {"coordinates":[-122.83121199999999,45.517356],"type":"Point"}
}