{
  "type": "Feature",
  "properties": {
    "addr:full":"1310 SE Armour Rd Bend OR 97702",
    "addr:housenumber":"1310",
    "addr:postcode":"97702",
    "addr:street":"Se Armour Rd",
    "iso:country":"US",
    "sg:address":"1310 SE Armour Rd",
    "sg:city":"Bend",
    "sg:classifiers":[
        {
            "category":"Manufacturing",
            "subcategory":"Metals",
            "type":"Manufacturing & Wholesale Goods"
        },
        {
            "category":"Building & Trades",
            "subcategory":"Construction",
            "type":"Services"
        }
    ],
    "sg:phone":"+1 541 318 8080",
    "sg:postcode":"97702",
    "sg:province":"OR",
    "sg:tags":[
        "ornamental",
        "work",
        "contractor"
    ],
    "wof:name":"Raven Forge",
    "wof:placetype":"venue"
},
  "geometry": {"coordinates":[-121.28792300000001,44.046564],"type":"Point"}
}