{
  "type": "Feature",
  "properties": {
    "iso:country":"US",
    "sg:address":"4795 Rogue River Dr",
    "sg:city":"Eagle Point",
    "sg:classifiers":[
        {
            "category":"Building & Trades",
            "subcategory":"Construction",
            "type":"Services"
        }
    ],
    "sg:phone":"+1 541 878 7665",
    "sg:postcode":"97524",
    "sg:province":"OR",
    "sg:tags":[
        "contractor"
    ],
    "wof:name":"Superior Pools of Oregon",
    "wof:placetype":"venue"
},
  "geometry": {"coordinates":[-122.840929,42.588044],"type":"Point"}
}