{
  "type": "Feature",
  "properties": {
    "iso:country":"US",
    "sg:address":"810 14th St",
    "sg:city":"La Grande",
    "sg:classifiers":[
        {
            "category":"Social Services",
            "subcategory":"Child Care",
            "type":"Services"
        }
    ],
    "sg:phone":"+1 541 963 4611",
    "sg:postcode":"97850",
    "sg:province":"OR",
    "sg:tags":[
        "kindergarten",
        "academic",
        "school"
    ],
    "wof:name":"Eastern Oregon Head Start",
    "wof:placetype":"venue"
},
  "geometry": {"coordinates":[-118.083984,45.31928],"type":"Point"}
}