{
  "type": "Feature",
  "properties": {
    "iso:country":"US",
    "sg:address":"9655 SW Sunshine Ct # 700",
    "sg:city":"Beaverton",
    "sg:phone":"+1 503 643 2351",
    "sg:postcode":"97005",
    "sg:province":"OR",
    "sg:website":"http://www.nwsbm.com",
    "wof:name":"Northwest Specialty Baking Mixes",
    "wof:placetype":"venue"
},
  "geometry": {"coordinates":[-122.777129,45.474131],"type":"Point"}
}