{
  "type": "Feature",
  "properties": {
    "addr:full":"1800 Lakewood Ct Eugene OR 97402",
    "addr:housenumber":"1800",
    "addr:postcode":"97402",
    "addr:street":"Lakewood Ct",
    "iso:country":"US",
    "sg:address":"1800 Lakewood Ct",
    "sg:city":"Eugene",
    "sg:classifiers":[
        {
            "category":"Health Services",
            "subcategory":"Doctor",
            "type":"Services"
        }
    ],
    "sg:phone":"+1 541 689 6277",
    "sg:postcode":"97402",
    "sg:province":"OR",
    "sg:tags":[
        "physician",
        "surgeon"
    ],
    "wof:name":"Warren & Faye Weiseth Md",
    "wof:placetype":"venue"
},
  "geometry": {"coordinates":[-123.15164900000001,44.080399],"type":"Point"}
}