{
  "type": "Feature",
  "properties": {
    "iso:country":"US",
    "sg:address":"10260 SW Greenburg Rd",
    "sg:city":"Portland",
    "sg:classifiers":[
        {
            "category":"Wholesale",
            "subcategory":"Machinery & Supplies",
            "type":"Manufacturing & Wholesale Goods"
        }
    ],
    "sg:phone":"+1 503 624 6500",
    "sg:postcode":"97223",
    "sg:province":"OR",
    "sg:tags":[
        "equipment",
        "industrial",
        "specially",
        "designed"
    ],
    "wof:name":"I-Mx",
    "wof:placetype":"venue"
},
  "geometry": {"coordinates":[-122.77643999999999,45.445953],"type":"Point"}
}