{
  "type": "Feature",
  "properties": {
    "iso:country":"US",
    "sg:address":"32823 Delaney St",
    "sg:city":"Coburg",
    "sg:classifiers":[
        {
            "category":"Retail",
            "subcategory":"Auto Repair",
            "type":"Services"
        }
    ],
    "sg:phone":"+1 541 431 1024",
    "sg:postcode":"97408",
    "sg:province":"OR",
    "sg:tags":[
        "wrecker"
    ],
    "wof:name":"Coburg Auto Parts & Towing",
    "wof:placetype":"venue"
},
  "geometry": {"coordinates":[-123.062179,44.136055],"type":"Point"}
}