{
  "type": "Feature",
  "properties": {
    "addr:full":"7076 Bluebelle Way Springfield OR 97478",
    "addr:housenumber":"7076",
    "addr:postcode":"97478",
    "addr:street":"Bluebelle Way",
    "iso:country":"US",
    "sg:address":"7076 Bluebelle Way",
    "sg:city":"Springfield",
    "sg:classifiers":[
        {
            "category":"Building & Trades",
            "subcategory":"Construction",
            "type":"Services"
        },
        {
            "category":"Manufacturing",
            "subcategory":"Building Materials",
            "type":"Manufacturing & Wholesale Goods"
        }
    ],
    "sg:phone":"+1 541 747 9588",
    "sg:postcode":"97478",
    "sg:province":"OR",
    "sg:tags":[
        "roofing",
        "sheet",
        "work",
        "metal",
        "contractor",
        "siding"
    ],
    "wof:name":"All Phase Roofing & Construction, Inc",
    "wof:placetype":"venue"
},
  "geometry": {"coordinates":[-122.899447,44.043261],"type":"Point"}
}