{
  "type": "Feature",
  "properties": {
    "addr:full":"1814 SE Bybee Blvd Portland OR 97202",
    "addr:housenumber":"1814",
    "addr:postcode":"97202",
    "addr:street":"Se Bybee Blvd",
    "iso:country":"US",
    "sg:address":"1814 SE Bybee Blvd",
    "sg:city":"Portland",
    "sg:classifiers":[
        {
            "category":"Organizations",
            "subcategory":"Religious Organization",
            "type":"Services"
        }
    ],
    "sg:phone":"+1 503 234 8404",
    "sg:postcode":"97202",
    "sg:province":"OR",
    "sg:website":"www.morelandpresbyterian.com",
    "wof:name":"Moreland Presbyterian Church",
    "wof:placetype":"venue"
},
  "geometry": {"coordinates":[-122.645836,45.473817],"type":"Point"}
}