{
  "type": "Feature",
  "properties": {
    "addr:full":"1720 NE 169th Ave Portland OR 97230",
    "addr:housenumber":"1720",
    "addr:postcode":"97230",
    "addr:street":"Ne 169Th Ave",
    "iso:country":"US",
    "sg:address":"1720 NE 169th Ave",
    "sg:city":"Portland",
    "sg:classifiers":[
        {
            "category":"Home & Garden",
            "subcategory":"Household Appliances",
            "type":"Retail Goods"
        }
    ],
    "sg:phone":"+1 503 255 2117",
    "sg:postcode":"97230",
    "sg:province":"OR",
    "wof:name":"Raquel Bensene",
    "wof:placetype":"venue"
},
  "geometry": {"coordinates":[-122.48916,45.537957],"type":"Point"}
}