{
  "type": "Feature",
  "properties": {
    "iso:country":"US",
    "sg:address":"4715 Cordon Rd NE",
    "sg:city":"Salem",
    "sg:classifiers":[
        {
            "category":"Building & Trades",
            "subcategory":"Construction",
            "type":"Services"
        }
    ],
    "sg:phone":"+1 503 585 8431",
    "sg:postcode":"97305",
    "sg:province":"OR",
    "sg:tags":[
        "house"
    ],
    "wof:name":"Shattuck Construction",
    "wof:placetype":"venue"
},
  "geometry": {"coordinates":[-122.953395,44.993657],"type":"Point"}
}