{
  "type": "Feature",
  "properties": {
    "iso:country":"US",
    "sg:address":"8711 N Crawford St",
    "sg:city":"Portland",
    "sg:classifiers":[
        {
            "category":"Travel",
            "subcategory":"Travel Agent",
            "type":"Entertainment"
        }
    ],
    "sg:phone":"+1 503 737 1409",
    "sg:postcode":"97203",
    "sg:province":"OR",
    "sg:tags":[
        "agency"
    ],
    "wof:name":"Overboard Cruises",
    "wof:placetype":"venue"
},
  "geometry": {"coordinates":[-122.760043,45.587925],"type":"Point"}
}