{
  "type": "Feature",
  "properties": {
    "addr:full":"8711 N Crawford St Portland OR 97203",
    "addr:housenumber":"8711",
    "addr:postcode":"97203",
    "addr:street":"N Crawford St",
    "iso:country":"US",
    "sg:address":"8711 N Crawford St",
    "sg:city":"Portland",
    "sg:classifiers":[
        {
            "category":"Travel",
            "subcategory":"Travel Agent",
            "type":"Entertainment"
        }
    ],
    "sg:phone":"+1 503 737 1409",
    "sg:postcode":"97203",
    "sg:province":"OR",
    "sg:tags":[
        "agency"
    ],
    "wof:name":"Overboard Cruises",
    "wof:placetype":"venue"
},
  "geometry": {"coordinates":[-122.760043,45.587925],"type":"Point"}
}