{
  "type": "Feature",
  "properties": {
    "iso:country":"US",
    "sg:address":"11 W Jackson St",
    "sg:city":"Medford",
    "sg:classifiers":[
        {
            "category":"Professional",
            "subcategory":"Employment Agencies",
            "type":"Services"
        }
    ],
    "sg:phone":"+1 541 772 3300",
    "sg:postcode":"97501",
    "sg:province":"OR",
    "sg:website":"www.goodwill.org",
    "wof:name":"Goodwill",
    "wof:placetype":"venue"
},
  "geometry": {"coordinates":[-122.87799800000001,42.331001],"type":"Point"}
}