{
  "type": "Feature",
  "properties": {
    "iso:country":"US",
    "sg:address":"203 Bel Air Dr",
    "sg:city":"Clatskanie",
    "sg:classifiers":[
        {
            "category":"Health Services",
            "subcategory":"Nursing And Care Facility",
            "type":"Services"
        }
    ],
    "sg:phone":"+1 503 728 2992",
    "sg:postcode":"97016",
    "sg:province":"OR",
    "sg:tags":[
        "adult"
    ],
    "wof:name":"Clatskanie Care Ctr",
    "wof:placetype":"venue"
},
  "geometry": {"coordinates":[-123.210392,46.104469],"type":"Point"}
}