{
  "type": "Feature",
  "properties": {
    "iso:country":"US",
    "sg:address":"401 Crater Lake Ave. #3",
    "sg:city":"Medford",
    "sg:classifiers":[
        {
            "category":"Personal",
            "subcategory":"Beauty Salon",
            "type":"Services"
        },
        {
            "category":"Personal",
            "subcategory":"Barber",
            "type":"Services"
        }
    ],
    "sg:phone":"+1 541 772 8979",
    "sg:postcode":"97504",
    "sg:province":"OR",
    "sg:tags":[
        "hair",
        "makeup",
        "artist"
    ],
    "sg:website":"www.sanctussalonllc.com",
    "wof:name":"Sanctus Salon",
    "wof:placetype":"venue"
},
  "geometry": {"coordinates":[-122.862723,42.332691],"type":"Point"}
}