{
  "type": "Feature",
  "properties": {
    "iso:country":"US",
    "sg:address":"838 NW Bond St",
    "sg:city":"Bend",
    "sg:classifiers":[
        {
            "category":"Professional",
            "subcategory":"Engineering",
            "type":"Services"
        },
        {
            "category":"Real Estate",
            "subcategory":"Surveying",
            "type":"Services"
        }
    ],
    "sg:phone":"+1 541 647 2672",
    "sg:postcode":"97701",
    "sg:province":"OR",
    "sg:tags":[
        "civil",
        "surveyor",
        "land",
        "engineer",
        "contractor"
    ],
    "wof:name":"Mackay & Sposito Inc",
    "wof:placetype":"venue"
},
  "geometry": {"coordinates":[-121.31367299999999,44.057736],"type":"Point"}
}