{
  "type": "Feature",
  "properties": {
    "iso:country":"US",
    "sg:address":"215 Coachman Dr",
    "sg:city":"Jacksonville",
    "sg:classifiers":[
        {
            "category":"Insurance",
            "subcategory":"Life Insurance",
            "type":"Services"
        }
    ],
    "sg:phone":"+1 541 899 7285",
    "sg:postcode":"97530",
    "sg:province":"OR",
    "sg:tags":[
        "establishment"
    ],
    "wof:name":"Sons of Norway International",
    "wof:placetype":"venue"
},
  "geometry": {"coordinates":[-122.959905,42.309966],"type":"Point"}
}