{
  "type": "Feature",
  "properties": {
    "iso:country":"US",
    "sg:address":"25101 SE Stark St",
    "sg:city":"Troutdale",
    "sg:classifiers":[
        {
            "category":"Home & Garden",
            "subcategory":"Building Materials",
            "type":"Retail Goods"
        }
    ],
    "sg:phone":"+1 503 674 3944",
    "sg:postcode":"97060",
    "sg:province":"OR",
    "wof:name":"Home Depot",
    "wof:placetype":"venue"
},
  "geometry": {"coordinates":[-122.401138,45.519065],"type":"Point"}
}