{
  "type": "Feature",
  "properties": {
    "iso:country":"US",
    "sg:address":"350 Winter St NE",
    "sg:city":"Salem",
    "sg:classifiers":[
        {
            "category":"Government",
            "subcategory":"Office",
            "type":"Public Place"
        }
    ],
    "sg:phone":"+1 503 378 4100",
    "sg:postcode":"97301",
    "sg:province":"OR",
    "sg:website":"www.cbs.state.or.us",
    "wof:name":"Consumer & Business Svc Dept",
    "wof:placetype":"venue"
},
  "geometry": {"coordinates":[-123.030827,44.94107],"type":"Point"}
}