{
  "type": "Feature",
  "properties": {
    "addr:full":"1035 Oregon Ave Vernonia OR 97064",
    "addr:housenumber":"1035",
    "addr:postcode":"97064",
    "addr:street":"Oregon Ave",
    "iso:country":"US",
    "sg:address":"1035 Oregon Ave",
    "sg:city":"Vernonia",
    "sg:classifiers":[
        {
            "category":"Professional",
            "subcategory":"Business Services",
            "type":"Services"
        }
    ],
    "sg:phone":"+1 503 550 8817",
    "sg:postcode":"97064",
    "sg:province":"OR",
    "sg:tags":[
        "consultant",
        "coach"
    ],
    "wof:name":"Dba Scentsy Consultant",
    "wof:placetype":"venue"
},
  "geometry": {"coordinates":[-123.182877,45.860298],"type":"Point"}
}