{
  "type": "Feature",
  "properties": {
    "iso:country":"US",
    "sg:address":"7155 SW East Lake Ct",
    "sg:city":"Wilsonville",
    "sg:classifiers":[
        {
            "category":"Professional",
            "subcategory":"Lawyer & Legal Services",
            "type":"Services"
        }
    ],
    "sg:phone":"+1 503 694 5029",
    "sg:postcode":"97070",
    "sg:province":"OR",
    "sg:tags":[
        "attorney",
        "practice"
    ],
    "wof:name":"Ellinghouse, Jerry W Law Offices Of",
    "wof:placetype":"venue"
},
  "geometry": {"coordinates":[-122.75170900000001,45.288442],"type":"Point"}
}