{
  "type": "Feature",
  "properties": {
    "addr:full":"3925 Fairview Industrial Dr SE Salem OR 97302",
    "addr:housenumber":"3925",
    "addr:postcode":"97302",
    "addr:street":"Fairview Industrial Dr Se",
    "iso:country":"US",
    "sg:address":"3925 Fairview Industrial Dr SE",
    "sg:city":"Salem",
    "sg:classifiers":[
        {
            "category":"Wholesale",
            "subcategory":"Construction Materials",
            "type":"Manufacturing & Wholesale Goods"
        },
        {
            "category":"Wholesale",
            "subcategory":"Machinery & Supplies",
            "type":"Manufacturing & Wholesale Goods"
        }
    ],
    "sg:phone":"+1 503 585 5504",
    "sg:postcode":"97302",
    "sg:province":"OR",
    "sg:tags":[
        "concrete",
        "industrial",
        "form"
    ],
    "wof:name":"Masons Supply Company",
    "wof:placetype":"venue"
},
  "geometry": {"coordinates":[-123.01559399999999,44.902465],"type":"Point"}
}