{
  "type": "Feature",
  "properties": {
    "addr:full":"6950 SW Hampton St Tigard OR 97223",
    "addr:housenumber":"6950",
    "addr:postcode":"97223",
    "addr:street":"Sw Hampton St",
    "iso:country":"US",
    "sg:address":"6950 SW Hampton St",
    "sg:city":"Tigard",
    "sg:classifiers":[
        {
            "category":"Professional",
            "subcategory":"Secretarial Services",
            "type":"Services"
        }
    ],
    "sg:phone":"+1 503 620 8118",
    "sg:postcode":"97223",
    "sg:province":"OR",
    "sg:tags":[
        "processing",
        "word"
    ],
    "wof:name":"Best Office Svc",
    "wof:placetype":"venue"
},
  "geometry": {"coordinates":[-122.748414,45.42743],"type":"Point"}
}