{
  "type": "Feature",
  "properties": {
    "addr:full":"24700 Daisy Dr Philomath OR 97370",
    "addr:housenumber":"24700",
    "addr:postcode":"97370",
    "addr:street":"Daisy Dr",
    "iso:country":"US",
    "sg:address":"24700 Daisy Dr",
    "sg:city":"Philomath",
    "sg:classifiers":[
        {
            "category":"Farming",
            "subcategory":"Farm",
            "type":"Manufacturing & Wholesale Goods"
        }
    ],
    "sg:phone":"+1 541 929 6043",
    "sg:postcode":"97370",
    "sg:province":"OR",
    "sg:tags":[
        "crop",
        "general"
    ],
    "wof:name":"B B B Farm",
    "wof:placetype":"venue"
},
  "geometry": {"coordinates":[-123.389261,44.563304],"type":"Point"}
}