{
  "type": "Feature",
  "properties": {
    "addr:full":"4383 Shoreline Dr N Salem OR 97303",
    "addr:housenumber":"4383",
    "addr:postcode":"97303",
    "addr:street":"Shoreline Dr N",
    "iso:country":"US",
    "sg:address":"4383 Shoreline Dr N",
    "sg:city":"Salem",
    "sg:classifiers":[
        {
            "category":"Real Estate",
            "subcategory":"Real Estate Agent",
            "type":"Services"
        }
    ],
    "sg:phone":"+1 503 932 1912",
    "sg:postcode":"97303",
    "sg:province":"OR",
    "wof:name":"Karm LLC",
    "wof:placetype":"venue"
},
  "geometry": {"coordinates":[-123.037229,44.988229],"type":"Point"}
}