{
  "type": "Feature",
  "properties": {
    "iso:country":"US",
    "sg:address":"16196 SE Clare Ct",
    "sg:city":"Portland",
    "sg:classifiers":[
        {
            "category":"Home & Garden",
            "subcategory":"Building Materials",
            "type":"Retail Goods"
        }
    ],
    "sg:phone":"+1 503 513 7120",
    "sg:postcode":"97267",
    "sg:province":"OR",
    "wof:name":"Renew It",
    "wof:placetype":"venue"
},
  "geometry": {"coordinates":[-122.584423,45.405559],"type":"Point"}
}