{
  "type": "Feature",
  "properties": {
    "addr:full":"1234 N Rhododendron Dr Florence OR 97439",
    "addr:housenumber":"1234",
    "addr:postcode":"97439",
    "addr:street":"N Rhododendron Dr",
    "iso:country":"US",
    "sg:address":"1234 N Rhododendron Dr",
    "sg:city":"Florence",
    "sg:classifiers":[
        {
            "category":"Professional",
            "subcategory":"Business Services",
            "type":"Services"
        }
    ],
    "sg:phone":"+1 541 997 7088",
    "sg:postcode":"97439",
    "sg:province":"OR",
    "wof:name":"Hickson Development Group Inc",
    "wof:placetype":"venue"
},
  "geometry": {"coordinates":[-124.120014,43.977382],"type":"Point"}
}