{
  "type": "Feature",
  "properties": {
    "addr:full":"2401 NE Cornell Rd Hillsboro OR 97124",
    "addr:housenumber":"2401",
    "addr:postcode":"97124",
    "addr:street":"Ne Cornell Rd",
    "iso:country":"US",
    "sg:address":"2401 NE Cornell Rd",
    "sg:city":"Hillsboro",
    "sg:phone":"+1 503 648 4366",
    "sg:postcode":"97124",
    "sg:province":"OR",
    "sg:website":"http://www.sushinmakior.com",
    "wof:name":"Sushi & Maki Japanese Cuisine - Portland, OR/Hillsboro",
    "wof:placetype":"venue"
},
  "geometry": {"coordinates":[-122.95787,45.53067],"type":"Point"}
}