{
  "type": "Feature",
  "properties": {
    "iso:country":"US",
    "sg:address":"6517 N Interstate Ave",
    "sg:city":"Portland",
    "sg:classifiers":[
        {
            "category":"Shopping",
            "subcategory":"Mobile Phones",
            "type":"Retail Goods"
        }
    ],
    "sg:postcode":"97217",
    "sg:province":"OR",
    "sg:website":"www.fadigear.com/",
    "wof:name":"FadiGear",
    "wof:placetype":"venue"
},
  "geometry": {"coordinates":[-122.68235900000001,45.570306],"type":"Point"}
}