{
  "type": "Feature",
  "properties": {
    "addr:full":"27350 SW 95th Ave Wilsonville OR 97070",
    "addr:housenumber":"27350",
    "addr:postcode":"97070",
    "addr:street":"Sw 95Th Ave",
    "iso:country":"US",
    "sg:address":"27350 SW 95th Ave",
    "sg:city":"Wilsonville",
    "sg:classifiers":[
        {
            "category":"Professional",
            "subcategory":"Business Services",
            "type":"Services"
        }
    ],
    "sg:phone":"+1 503 682 6082",
    "sg:postcode":"97070",
    "sg:province":"OR",
    "sg:tags":[
        "advertising",
        "promotional"
    ],
    "wof:name":"Silhouette Marketing Services",
    "wof:placetype":"venue"
},
  "geometry": {"coordinates":[-122.77234,45.323008],"type":"Point"}
}