{
  "type": "Feature",
  "properties": {
    "iso:country":"US",
    "sg:address":"1604 Tamera Dr",
    "sg:city":"Klamath Falls",
    "sg:classifiers":[
        {
            "category":"Home & Garden",
            "subcategory":"Mobile Homes",
            "type":"Retail Goods"
        }
    ],
    "sg:phone":"+1 541 885 2064",
    "sg:postcode":"97603",
    "sg:province":"OR",
    "wof:name":"U-Wanna Manufactured Homes",
    "wof:placetype":"venue"
},
  "geometry": {"coordinates":[-121.707337,42.214941],"type":"Point"}
}