{
  "type": "Feature",
  "properties": {
    "iso:country":"US",
    "sg:address":"4330 NW Visitation Rd",
    "sg:city":"Forest Grove",
    "sg:classifiers":[
        {
            "category":"Building & Trades",
            "subcategory":"Construction",
            "type":"Services"
        }
    ],
    "sg:phone":"+1 503 357 7169",
    "sg:postcode":"97116",
    "sg:province":"OR",
    "sg:tags":[
        "house",
        "carpentry",
        "contractor"
    ],
    "wof:name":"Roger Sohler Construction",
    "wof:placetype":"venue"
},
  "geometry": {"coordinates":[-123.08523,45.552395],"type":"Point"}
}