{
  "type": "Feature",
  "properties": {
    "iso:country":"US",
    "sg:address":"17900 NE Everett Ct",
    "sg:city":"Portland",
    "sg:phone":"+1 503 492 2800",
    "sg:postcode":"97230",
    "sg:province":"OR",
    "sg:tags":[
        "fixture",
        "store"
    ],
    "wof:name":"Consolidated Video",
    "wof:placetype":"venue"
},
  "geometry": {"coordinates":[-122.478932,45.52427],"type":"Point"}
}