{
  "type": "Feature",
  "properties": {
    "iso:country":"US",
    "sg:address":"3000 Market St NE",
    "sg:city":"Salem",
    "sg:classifiers":[
        {
            "category":"Utilities",
            "subcategory":"Telephone",
            "type":"Services"
        }
    ],
    "sg:phone":"+1 503 977 9710",
    "sg:postcode":"97301",
    "sg:province":"OR",
    "sg:tags":[
        "sales",
        "for"
    ],
    "wof:name":"Unicom",
    "wof:placetype":"venue"
},
  "geometry": {"coordinates":[-122.996281,44.950114],"type":"Point"}
}