{
  "type": "Feature",
  "properties": {
    "iso:country":"US",
    "sg:address":"1300 SW Oak St",
    "sg:city":"Hillsboro",
    "sg:classifiers":[
        {
            "category":"Shopping",
            "subcategory":"Music",
            "type":"Retail Goods"
        },
        {
            "category":"Shopping",
            "subcategory":"Musical Instruments",
            "type":"Retail Goods"
        }
    ],
    "sg:phone":"+1 503 640 0777",
    "sg:postcode":"97123",
    "sg:province":"OR",
    "sg:tags":[
        "dealer"
    ],
    "wof:name":"La India Bonita",
    "wof:placetype":"venue"
},
  "geometry": {"coordinates":[-123.006672,45.519786],"type":"Point"}
}