{
  "type": "Feature",
  "properties": {
    "iso:country":"US",
    "sg:address":"105 S Water St",
    "sg:city":"Silverton",
    "sg:classifiers":[
        {
            "category":"Professional",
            "subcategory":"Accounting & Tax Preparation",
            "type":"Services"
        }
    ],
    "sg:phone":"+1 503 874 9300",
    "sg:postcode":"97381",
    "sg:province":"OR",
    "sg:tags":[
        "accountant"
    ],
    "wof:name":"Gary T Field CPA",
    "wof:placetype":"venue"
},
  "geometry": {"coordinates":[-122.783032,45.005164],"type":"Point"}
}