{
  "type": "Feature",
  "properties": {
    "addr:full":"337 Conser St Jefferson OR 97352",
    "addr:housenumber":"337",
    "addr:postcode":"97352",
    "addr:street":"Conser St",
    "iso:country":"US",
    "sg:address":"337 Conser St",
    "sg:city":"Jefferson",
    "sg:classifiers":[
        {
            "category":"Bus Charters",
            "type":"Transportation"
        }
    ],
    "sg:phone":"+1 541 327 2845",
    "sg:postcode":"97352",
    "sg:province":"OR",
    "sg:tags":[
        "rental"
    ],
    "wof:name":"Laidlaw Transit Inc",
    "wof:placetype":"venue"
},
  "geometry": {"coordinates":[-123.00754000000001,44.72538],"type":"Point"}
}