{
  "type": "Feature",
  "properties": {
    "iso:country":"US",
    "sg:address":"345 36th St",
    "sg:city":"Springfield",
    "sg:classifiers":[
        {
            "category":"Building & Trades",
            "subcategory":"Construction",
            "type":"Services"
        }
    ],
    "sg:phone":"+1 541 747 5631",
    "sg:postcode":"97478",
    "sg:province":"OR",
    "sg:tags":[
        "roofing",
        "contractor"
    ],
    "wof:name":"Canterbury Roofing & Cons",
    "wof:placetype":"venue"
},
  "geometry": {"coordinates":[-122.974602,44.047369],"type":"Point"}
}