{
  "type": "Feature",
  "properties": {
    "iso:country":"US",
    "sg:address":"13375 SW Canyon Rd",
    "sg:city":"Beaverton",
    "sg:classifiers":[
        {
            "category":"Retail",
            "subcategory":"Car Wash",
            "type":"Services"
        }
    ],
    "sg:phone":"+1 503 643 2982",
    "sg:postcode":"97005",
    "sg:province":"OR",
    "sg:website":"www.carriagehousecarwash.com/ind...",
    "wof:name":"Carriage House Car Wash",
    "wof:placetype":"venue"
},
  "geometry": {"coordinates":[-122.814003,45.488201],"type":"Point"}
}