{
  "type": "Feature",
  "properties": {
    "addr:full":"4535 SE 17th Ave Portland OR 97202",
    "addr:housenumber":"4535",
    "addr:postcode":"97202",
    "addr:street":"Se 17Th Ave",
    "iso:country":"US",
    "sg:address":"4535 SE 17th Ave",
    "sg:city":"Portland",
    "sg:classifiers":[
        {
            "category":"Building & Trades",
            "subcategory":"Construction",
            "type":"Services"
        }
    ],
    "sg:phone":"+1 503 234 0361",
    "sg:postcode":"97202",
    "sg:province":"OR",
    "sg:tags":[
        "engineering",
        "industrial",
        "w"
    ],
    "wof:name":"Ararad Corporation",
    "wof:placetype":"venue"
},
  "geometry": {"coordinates":[-122.648409,45.489851],"type":"Point"}
}