{
  "type": "Feature",
  "properties": {
    "iso:country":"US",
    "sg:address":"2201 E Barnett Rd",
    "sg:city":"Medford",
    "sg:classifiers":[
        {
            "category":"Health Services",
            "subcategory":"Doctor",
            "type":"Services"
        }
    ],
    "sg:phone":"+1 541 776 5271",
    "sg:postcode":"97504",
    "sg:province":"OR",
    "wof:name":"Kevin Wu DDS",
    "wof:placetype":"venue"
},
  "geometry": {"coordinates":[-122.844088,42.315931],"type":"Point"}
}