{
  "type": "Feature",
  "properties": {
    "iso:country":"US",
    "sg:address":"325 5th St",
    "sg:city":"Brookings",
    "sg:classifiers":[
        {
            "category":"Coffee & Tea",
            "type":"Food & Drink"
        }
    ],
    "sg:menulink":"http://www.allmenus.com/or/brookings/119398-starbucks-coffee/menu/",
    "sg:phone":"+1 541 469 1610",
    "sg:postcode":"97415",
    "sg:province":"OR",
    "sg:tags":[
        "american"
    ],
    "wof:name":"Starbucks Coffee",
    "wof:placetype":"venue"
},
  "geometry": {"coordinates":[-124.28796199999999,42.055123],"type":"Point"}
}