{
  "type": "Feature",
  "properties": {
    "addr:full":"9290 SE Sunnybrook Blvd Clackamas OR 97015",
    "addr:housenumber":"9290",
    "addr:postcode":"97015",
    "addr:street":"Se Sunnybrook Blvd",
    "iso:country":"US",
    "sg:address":"9290 SE Sunnybrook Blvd",
    "sg:city":"Clackamas",
    "sg:classifiers":[
        {
            "category":"Health Services",
            "subcategory":"Doctor",
            "type":"Services"
        }
    ],
    "sg:phone":"+1 503 786 2000",
    "sg:postcode":"97015",
    "sg:province":"OR",
    "sg:tags":[
        "medical"
    ],
    "wof:name":"Weresch Joseph M MD",
    "wof:placetype":"venue"
},
  "geometry": {"coordinates":[-122.57014599999999,45.429768],"type":"Point"}
}