{
  "type": "Feature",
  "properties": {
    "addr:full":"800 Elk Creek Rd Trail OR 97541",
    "addr:housenumber":"800",
    "addr:postcode":"97541",
    "addr:street":"Elk Creek Rd Trail",
    "iso:country":"US",
    "sg:address":"800 Elk Creek Rd",
    "sg:city":"Trail",
    "sg:classifiers":[
        {
            "category":"Organizations",
            "subcategory":"Religious Organization",
            "type":"Services"
        }
    ],
    "sg:phone":"+1 541 878 8281",
    "sg:postcode":"97541",
    "sg:province":"OR",
    "sg:tags":[
        "animal"
    ],
    "wof:name":"Saint Brnard Rescue Foundation",
    "wof:placetype":"venue"
},
  "geometry": {"coordinates":[-122.754757,42.664045],"type":"Point"}
}