{
  "type": "Feature",
  "properties": {
    "iso:country":"US",
    "sg:address":"1525 SW Taylors Ferry Rd",
    "sg:city":"Portland",
    "sg:classifiers":[
        {
            "category":"Communications",
            "subcategory":"Film & Video Production",
            "type":"Services"
        },
        {
            "category":"Shopping",
            "subcategory":"Computers & Home Electronics",
            "type":"Retail Goods"
        }
    ],
    "sg:phone":"+1 503 245 1536",
    "sg:postcode":"97219",
    "sg:province":"OR",
    "sg:tags":[
        "stereo",
        "record",
        "tapes-wholesale",
        "cd's",
        "equipment-dealers",
        "audio",
        "manufacturer"
    ],
    "wof:name":"Cd Forge",
    "wof:placetype":"venue"
},
  "geometry": {"coordinates":[-122.69319,45.45831],"type":"Point"}
}