{
  "type": "Feature",
  "properties": {
    "iso:country":"US",
    "sg:address":"507 S Canyon Blvd",
    "sg:city":"John Day",
    "sg:classifiers":[
        {
            "category":"Education",
            "subcategory":"Library",
            "type":"Public Place"
        }
    ],
    "sg:phone":"+1 541 575 1992",
    "sg:postcode":"97845",
    "sg:province":"OR",
    "sg:tags":[
        "executive"
    ],
    "wof:name":"Grant County Library",
    "wof:placetype":"venue"
},
  "geometry": {"coordinates":[-118.952429,44.410043],"type":"Point"}
}