{
  "type": "Feature",
  "properties": {
    "iso:country":"US",
    "sg:address":"8125 Windsor Island Rd N",
    "sg:city":"Salem",
    "sg:classifiers":[
        {
            "category":"Wholesale",
            "subcategory":"Plants",
            "type":"Manufacturing & Wholesale Goods"
        }
    ],
    "sg:phone":"+1 503 390 8619",
    "sg:postcode":"97303",
    "sg:province":"OR",
    "sg:tags":[
        "supply"
    ],
    "wof:name":"Youngblood Nursery",
    "wof:placetype":"venue"
},
  "geometry": {"coordinates":[-123.050875,45.037181],"type":"Point"}
}