{
  "type": "Feature",
  "properties": {
    "addr:full":"331 NW Davis St Portland OR 97209",
    "addr:housenumber":"331",
    "addr:postcode":"97209",
    "addr:street":"Nw Davis St",
    "iso:country":"US",
    "sg:address":"331 NW Davis St",
    "sg:city":"Portland",
    "sg:classifiers":[
        {
            "category":"Restaurant",
            "type":"Food & Drink"
        }
    ],
    "sg:phone":"+1 503 228 9898",
    "sg:postcode":"97209",
    "sg:province":"OR",
    "sg:tags":[
        "dim",
        "sum",
        "chinese"
    ],
    "wof:name":"House of Louie",
    "wof:placetype":"venue"
},
  "geometry": {"coordinates":[-122.674004,45.524399],"type":"Point"}
}