{
  "type": "Feature",
  "properties": {
    "iso:country":"US",
    "sg:address":"8955 N Haven Ave",
    "sg:city":"Portland",
    "sg:classifiers":[
        {
            "category":"Wholesale",
            "subcategory":"Office Equipment",
            "type":"Manufacturing & Wholesale Goods"
        }
    ],
    "sg:phone":"+1 503 289 8884",
    "sg:postcode":"97203",
    "sg:province":"OR",
    "sg:tags":[
        "product",
        "register",
        "cash",
        "sales",
        "computer",
        "electronic"
    ],
    "wof:name":"Lucky Cash Register",
    "wof:placetype":"venue"
},
  "geometry": {"coordinates":[-122.71848900000001,45.587221],"type":"Point"}
}