{
  "type": "Feature",
  "properties": {
    "iso:country":"US",
    "sg:address":"279 N Central St",
    "sg:city":"Coquille",
    "sg:classifiers":[
        {
            "category":"Health Services",
            "subcategory":"Health Practitioner",
            "type":"Services"
        }
    ],
    "sg:phone":"+1 541 396 3341",
    "sg:postcode":"97423",
    "sg:province":"OR",
    "sg:tags":[
        "therapist",
        "physical"
    ],
    "wof:name":"Southwest Physical Therapy",
    "wof:placetype":"venue"
},
  "geometry": {"coordinates":[-124.1891,43.176123],"type":"Point"}
}