{
  "type": "Feature",
  "properties": {
    "addr:full":"377 E Main St Hillsboro OR 97123",
    "addr:housenumber":"377",
    "addr:postcode":"97123",
    "addr:street":"E Main St",
    "iso:country":"US",
    "sg:address":"377 E Main St",
    "sg:city":"Hillsboro",
    "sg:classifiers":[
        {
            "category":"Food & Beverages",
            "subcategory":"Specialty",
            "type":"Retail Goods"
        }
    ],
    "sg:phone":"+1 503 681 9140",
    "sg:postcode":"97123",
    "sg:province":"OR",
    "wof:name":"Natural Nutrition",
    "wof:placetype":"venue"
},
  "geometry": {"coordinates":[-122.98544,45.522688],"type":"Point"}
}