{
  "type": "Feature",
  "properties": {
    "iso:country":"US",
    "sg:address":"5495 SW Main Ave",
    "sg:city":"Beaverton",
    "sg:classifiers":[
        {
            "category":"Shopping",
            "subcategory":"Books",
            "type":"Retail Goods"
        },
        {
            "category":"Wholesale",
            "subcategory":"Books, Periodicals, & Newspapers",
            "type":"Manufacturing & Wholesale Goods"
        }
    ],
    "sg:phone":"+1 503 646 4465",
    "sg:postcode":"97005",
    "sg:province":"OR",
    "sg:tags":[
        "books-wholesale",
        "store",
        "manufacturer"
    ],
    "wof:name":"Bad Dog Books",
    "wof:placetype":"venue"
},
  "geometry": {"coordinates":[-122.808004,45.479604],"type":"Point"}
}