{
  "type": "Feature",
  "properties": {
    "iso:country":"US",
    "sg:address":"9115 SW Oleson Rd",
    "sg:city":"Portland",
    "sg:classifiers":[
        {
            "category":"Insurance",
            "subcategory":"Insurance Agent",
            "type":"Services"
        }
    ],
    "sg:phone":"+1 503 353 0231",
    "sg:postcode":"97223",
    "sg:province":"OR",
    "wof:name":"An Insurance Store",
    "wof:placetype":"venue"
},
  "geometry": {"coordinates":[-122.772214,45.454367],"type":"Point"}
}