{
  "type": "Feature",
  "properties": {
    "iso:country":"US",
    "sg:address":"5709 SE Madison St",
    "sg:city":"Portland",
    "sg:classifiers":[
        {
            "category":"Professional",
            "subcategory":"Business Services",
            "type":"Services"
        }
    ],
    "sg:phone":"+1 503 231 0625",
    "sg:postcode":"97215",
    "sg:province":"OR",
    "wof:name":"Larkspur Group LLC",
    "wof:placetype":"venue"
},
  "geometry": {"coordinates":[-122.60368099999999,45.512963],"type":"Point"}
}