{
  "type": "Feature",
  "properties": {
    "iso:country":"US",
    "sg:address":"4876 NW Bethany Blvd Ste L4",
    "sg:city":"Portland",
    "sg:classifiers":[
        {
            "category":"Sports & Exercise",
            "subcategory":"Gym",
            "type":"Entertainment"
        }
    ],
    "sg:phone":"+1 503 372 9825",
    "sg:postcode":"97229",
    "sg:province":"OR",
    "sg:tags":[
        "yoga"
    ],
    "sg:website":"www.santoshaforeverybody.com",
    "wof:name":"Santosha Yoga",
    "wof:placetype":"venue"
},
  "geometry": {"coordinates":[-122.83650400000001,45.554742],"type":"Point"}
}