{
  "type": "Feature",
  "properties": {
    "iso:country":"US",
    "sg:address":"91114 N Harrison St",
    "sg:city":"Eugene",
    "sg:classifiers":[
        {
            "category":"Professional",
            "subcategory":"Art Services",
            "type":"Services"
        }
    ],
    "sg:phone":"+1 541 344 7449",
    "sg:postcode":"97408",
    "sg:province":"OR",
    "sg:tags":[
        "graphic",
        "designer"
    ],
    "wof:name":"Treemen Design",
    "wof:placetype":"venue"
},
  "geometry": {"coordinates":[-123.066929,44.140769],"type":"Point"}
}