{
  "type": "Feature",
  "properties": {
    "addr:full":"1895 Parliament St Eugene OR 97405",
    "addr:housenumber":"1895",
    "addr:postcode":"97405",
    "addr:street":"Parliament St",
    "iso:country":"US",
    "sg:address":"1895 Parliament St",
    "sg:city":"Eugene",
    "sg:classifiers":[
        {
            "category":"Shopping",
            "subcategory":"Books",
            "type":"Retail Goods"
        }
    ],
    "sg:phone":"+1 541 342 4120",
    "sg:postcode":"97405",
    "sg:province":"OR",
    "sg:tags":[
        "dealer"
    ],
    "wof:name":"Unique Book Marks",
    "wof:placetype":"venue"
},
  "geometry": {"coordinates":[-123.15898199999999,44.038299],"type":"Point"}
}