{
  "type": "Feature",
  "properties": {
    "addr:full":"1021 NE 6th St Grants Pass OR 97526",
    "addr:housenumber":"1021",
    "addr:postcode":"97526",
    "addr:street":"Ne 6Th St",
    "iso:country":"US",
    "sg:address":"1021 NE 6th St",
    "sg:city":"Grants Pass",
    "sg:classifiers":[
        {
            "category":"Health Services",
            "subcategory":"Doctor",
            "type":"Services"
        }
    ],
    "sg:phone":"+1 541 479 6696",
    "sg:postcode":"97526",
    "sg:province":"OR",
    "sg:tags":[
        "dentist"
    ],
    "wof:name":"Bright Now Dental",
    "wof:placetype":"venue"
},
  "geometry": {"coordinates":[-123.32243,42.448318],"type":"Point"}
}