{
  "type": "Feature",
  "properties": {
    "iso:country":"US",
    "sg:address":"9530 SE Lawnfield Rd",
    "sg:city":"Clackamas",
    "sg:classifiers":[
        {
            "category":"Health Services",
            "subcategory":"Health Practitioner",
            "type":"Services"
        }
    ],
    "sg:phone":"+1 503 794 9500",
    "sg:postcode":"97015",
    "sg:province":"OR",
    "sg:tags":[
        "nutritionist"
    ],
    "wof:name":"Vital Nutrition",
    "wof:placetype":"venue"
},
  "geometry": {"coordinates":[-122.568583,45.419015],"type":"Point"}
}