{
  "type": "Feature",
  "properties": {
    "addr:full":"1500 N Riverside Ave Medford OR 97501",
    "addr:housenumber":"1500",
    "addr:postcode":"97501",
    "addr:street":"N Riverside Ave",
    "iso:country":"US",
    "sg:address":"1500 N Riverside Ave",
    "sg:city":"Medford",
    "sg:phone":"+1 866 319 6859",
    "sg:postcode":"97501",
    "sg:province":"OR",
    "sg:website":"http://national.citysearch.com/profile/external/46618834/medford_or/jcpenney_custom_decorating.html?publisher=yellowpages&reference_id=1&placement=ypwebsitemip",
    "wof:name":"JCPenney Custom Decorating",
    "wof:placetype":"venue"
},
  "geometry": {"coordinates":[-122.877678,42.341129],"type":"Point"}
}