{
  "type": "Feature",
  "properties": {
    "iso:country":"US",
    "sg:address":"5050 NE Hoyt St",
    "sg:city":"Portland",
    "sg:classifiers":[
        {
            "category":"Shopping",
            "subcategory":"Optical Goods",
            "type":"Retail Goods"
        }
    ],
    "sg:phone":"+1 503 231 0166",
    "sg:postcode":"97213",
    "sg:province":"OR",
    "wof:name":"Laird Robert J MD",
    "wof:placetype":"venue"
},
  "geometry": {"coordinates":[-122.611074,45.527144],"type":"Point"}
}