{
  "type": "Feature",
  "properties": {
    "addr:full":"17281 Stellar Dr Sherwood OR 97140",
    "addr:housenumber":"17281",
    "addr:postcode":"97140",
    "addr:street":"Stellar Dr",
    "iso:country":"US",
    "sg:address":"17281 Stellar Dr",
    "sg:city":"Sherwood",
    "sg:classifiers":[
        {
            "category":"Retail",
            "subcategory":"Laundry & Dry Cleaning",
            "type":"Services"
        }
    ],
    "sg:phone":"+1 503 925 0797",
    "sg:postcode":"97140",
    "sg:province":"OR",
    "sg:tags":[
        "cleaners"
    ],
    "wof:name":"Dry Cleaning To Your Door",
    "wof:placetype":"venue"
},
  "geometry": {"coordinates":[-122.856358,45.354918],"type":"Point"}
}