{
  "type": "Feature",
  "properties": {
    "iso:country":"US",
    "sg:address":"3000 Gateway St",
    "sg:city":"Springfield",
    "sg:classifiers":[
        {
            "category":"Wholesale",
            "subcategory":"Machinery & Supplies",
            "type":"Manufacturing & Wholesale Goods"
        }
    ],
    "sg:phone":"+1 541 747 1195",
    "sg:postcode":"97477",
    "sg:province":"OR",
    "sg:tags":[
        "equipment",
        "establishment"
    ],
    "wof:name":"Pro Beauty Supply",
    "wof:placetype":"venue"
},
  "geometry": {"coordinates":[-123.04234599999999,44.074205],"type":"Point"}
}