{
  "type": "Feature",
  "properties": {
    "iso:country":"US",
    "sg:address":"1007 SE Clatsop Street",
    "sg:city":"Portland",
    "sg:classifiers":[
        {
            "category":"Personal",
            "type":"Services"
        },
        {
            "category":"Social Services",
            "subcategory":"Child Care",
            "type":"Services"
        }
    ],
    "sg:phone":"+1 503 234 1883",
    "sg:postcode":"97202",
    "sg:province":"OR",
    "sg:tags":[
        "party",
        "planning",
        "day",
        "event"
    ],
    "wof:name":"Tumble Bus",
    "wof:placetype":"venue"
},
  "geometry": {"coordinates":[-122.634838,45.484716],"type":"Point"}
}