{
  "type": "Feature",
  "properties": {
    "addr:full":"2222 NW Lovejoy St Ste 510 Portland OR 97210",
    "addr:housenumber":"2222",
    "addr:postcode":"97210",
    "addr:street":"Nw Lovejoy St Ste 510",
    "iso:country":"US",
    "sg:address":"2222 NW Lovejoy St Ste 510",
    "sg:city":"Portland",
    "sg:classifiers":[
        {
            "category":"Health Services",
            "subcategory":"Doctor",
            "type":"Services"
        }
    ],
    "sg:phone":"+1 503 221 1581",
    "sg:postcode":"97210",
    "sg:province":"OR",
    "sg:tags":[
        "podiatrist"
    ],
    "sg:website":"www.drjaygoldstein.com",
    "wof:name":"Jay C. Goldstein, DPM, MS",
    "wof:placetype":"venue"
},
  "geometry": {"coordinates":[-122.697008,45.52917],"type":"Point"}
}