{
  "type": "Feature",
  "properties": {
    "iso:country":"US",
    "sg:address":"1445 Kimberly Dr",
    "sg:city":"Klamath Falls",
    "sg:classifiers":[
        {
            "category":"Building & Trades",
            "subcategory":"Landscaping Services",
            "type":"Services"
        }
    ],
    "sg:phone":"+1 541 884 3969",
    "sg:postcode":"97603",
    "sg:province":"OR",
    "sg:tags":[
        "tree",
        "trimming"
    ],
    "wof:name":"AA Tree Service LLC",
    "wof:placetype":"venue"
},
  "geometry": {"coordinates":[-121.705395,42.216116],"type":"Point"}
}