{
  "type": "Feature",
  "properties": {
    "iso:country":"US",
    "sg:address":"1300 SW 5th Ave Ste 3500",
    "sg:city":"Portland",
    "sg:phone":"+1 503 224 4100",
    "sg:postcode":"97201",
    "sg:province":"OR",
    "wof:name":"Gates Jennifer L",
    "wof:placetype":"venue"
},
  "geometry": {"coordinates":[-122.67971799999999,45.514809],"type":"Point"}
}