{
  "type": "Feature",
  "properties": {
    "iso:country":"US",
    "sg:address":"1212 NE Fogarty St",
    "sg:city":"Newport",
    "sg:classifiers":[
        {
            "category":"Recreation",
            "type":"Entertainment"
        }
    ],
    "sg:phone":"+1 541 265 7770",
    "sg:postcode":"97365",
    "sg:province":"OR",
    "sg:tags":[
        "pool",
        "swimming"
    ],
    "wof:name":"Newport Swimming Pool",
    "wof:placetype":"venue"
},
  "geometry": {"coordinates":[-124.045734,44.646814],"type":"Point"}
}