{
  "type": "Feature",
  "properties": {
    "addr:full":"2866 SE Harrison St Portland OR 97214",
    "addr:housenumber":"2866",
    "addr:postcode":"97214",
    "addr:street":"Se Harrison St",
    "iso:country":"US",
    "sg:address":"2866 SE Harrison St",
    "sg:city":"Portland",
    "sg:classifiers":[
        {
            "category":"Building & Trades",
            "subcategory":"Construction",
            "type":"Services"
        }
    ],
    "sg:phone":"+1 503 504 1448",
    "sg:postcode":"97214",
    "sg:province":"OR",
    "sg:tags":[
        "painter"
    ],
    "sg:website":"www.roberttilley.net",
    "wof:name":"Tilley Enterprises",
    "wof:placetype":"venue"
},
  "geometry": {"coordinates":[-122.636235,45.50826],"type":"Point"}
}