{
  "type": "Feature",
  "properties": {
    "iso:country":"US",
    "sg:address":"810 SE 26th Ave Ste A",
    "sg:city":"Portland",
    "sg:classifiers":[
        {
            "category":"Insurance",
            "subcategory":"Hazard Insurance",
            "type":"Services"
        }
    ],
    "sg:phone":"+1 877 514 9015",
    "sg:postcode":"97214",
    "sg:province":"OR",
    "sg:tags":[
        "commercial",
        "business"
    ],
    "sg:website":"http://www.completeinssolutions.com",
    "wof:name":"Complete Insurance Solutions",
    "wof:placetype":"venue"
},
  "geometry": {"coordinates":[-122.639129,45.516908],"type":"Point"}
}