{
  "type": "Feature",
  "properties": {
    "addr:full":"1350 W Main St Sheridan OR 97378",
    "addr:housenumber":"1350",
    "addr:postcode":"97378",
    "addr:street":"W Main St",
    "iso:country":"US",
    "sg:address":"1350 W Main St",
    "sg:city":"Sheridan",
    "sg:classifiers":[
        {
            "category":"Social Services",
            "subcategory":"Adult Care",
            "type":"Services"
        }
    ],
    "sg:phone":"+1 503 843 7799",
    "sg:postcode":"97378",
    "sg:province":"OR",
    "sg:tags":[
        "home",
        "residential"
    ],
    "sg:website":"www.deermeadowalf.com",
    "wof:name":"Deer Meadow Assisted Living",
    "wof:placetype":"venue"
},
  "geometry": {"coordinates":[-123.419873,45.097295],"type":"Point"}
}