{
  "type": "Feature",
  "properties": {
    "iso:country":"US",
    "sg:address":"20 Centennial Loop",
    "sg:city":"Eugene",
    "sg:classifiers":[
        {
            "category":"Bars & Pubs",
            "type":"Food & Drink"
        }
    ],
    "sg:menulink":"http://www.allmenus.com/or/eugene-springfield/44908-the-cooler-bar--grill/menu/",
    "sg:phone":"+1 541 484 4355",
    "sg:postcode":"97401",
    "sg:province":"OR",
    "sg:tags":[
        "american"
    ],
    "wof:name":"The Cooler Bar & Grill",
    "wof:placetype":"venue"
},
  "geometry": {"coordinates":[-123.08018,44.060186],"type":"Point"}
}