{
  "type": "Feature",
  "properties": {
    "addr:full":"53877 Old Dufur Ln Milton Freewater OR 97862",
    "addr:housenumber":"53877",
    "addr:postcode":"97862",
    "addr:street":"Old Dufur Ln;Freewater",
    "iso:country":"US",
    "sg:address":"53877 Old Dufur Ln",
    "sg:city":"Milton Freewater",
    "sg:classifiers":[
        {
            "category":"Retail",
            "subcategory":"Repair Shop",
            "type":"Services"
        }
    ],
    "sg:phone":"+1 541 938 3993",
    "sg:postcode":"97862",
    "sg:province":"OR",
    "wof:name":"Carney Upholstery",
    "wof:placetype":"venue"
},
  "geometry": {"coordinates":[-118.38820699999999,45.963249],"type":"Point"}
}