{
  "type": "Feature",
  "properties": {
    "iso:country":"US",
    "sg:address":"520 SW Yamhill Street",
    "sg:city":"Portland",
    "sg:classifiers":[
        {
            "category":"Personal",
            "subcategory":"Barber",
            "type":"Services"
        }
    ],
    "sg:phone":"+1 503 223 8002",
    "sg:postcode":"97204",
    "sg:province":"OR",
    "wof:name":"Your Barber Shop",
    "wof:placetype":"venue"
},
  "geometry": {"coordinates":[-122.678158,45.518173],"type":"Point"}
}