{
  "type": "Feature",
  "properties": {
    "addr:full":"820 NE 23rd St Gresham OR 97030",
    "addr:housenumber":"820",
    "addr:postcode":"97030",
    "addr:street":"Ne 23Rd St",
    "iso:country":"US",
    "sg:address":"820 NE 23rd St",
    "sg:city":"Gresham",
    "sg:classifiers":[
        {
            "category":"Wholesale",
            "subcategory":"Vending Machines",
            "type":"Manufacturing & Wholesale Goods"
        }
    ],
    "sg:phone":"+1 503 666 4118",
    "sg:postcode":"97030",
    "sg:province":"OR",
    "sg:tags":[
        "operator"
    ],
    "wof:name":"Unique Vending",
    "wof:placetype":"venue"
},
  "geometry": {"coordinates":[-122.422213,45.513329],"type":"Point"}
}