{
  "type": "Feature",
  "properties": {
    "iso:country":"US",
    "sg:address":"27220 Huey Ln",
    "sg:city":"Eugene",
    "sg:classifiers":[
        {
            "category":"Building & Trades",
            "subcategory":"Landscaping Services",
            "type":"Services"
        }
    ],
    "sg:phone":"+1 541 461 3899",
    "sg:postcode":"97402",
    "sg:province":"OR",
    "wof:name":"Precision Lawn Maintenance",
    "wof:placetype":"venue"
},
  "geometry": {"coordinates":[-123.27160000000001,44.111386],"type":"Point"}
}