{
  "type": "Feature",
  "properties": {
    "iso:country":"US",
    "sg:address":"425 SW Morrison St",
    "sg:city":"Portland",
    "sg:classifiers":[
        {
            "category":"Shopping",
            "type":"Retail Goods"
        }
    ],
    "sg:phone":"+1 503 721 1558",
    "sg:postcode":"97204",
    "sg:province":"OR",
    "sg:tags":[
        "sunglasses"
    ],
    "wof:name":"Sunglass Hut 1710",
    "wof:placetype":"venue"
},
  "geometry": {"coordinates":[-122.67737700000001,45.518803],"type":"Point"}
}