{
  "type": "Feature",
  "properties": {
    "iso:country":"US",
    "sg:address":"2386 NW Hoyt Street",
    "sg:city":"Portland",
    "sg:classifiers":[
        {
            "category":"Health Services",
            "subcategory":"Doctor",
            "type":"Services"
        },
        {
            "category":"Health Services",
            "subcategory":"Health Practitioner",
            "type":"Services"
        }
    ],
    "sg:phone":"+1 503 228 5909",
    "sg:postcode":"97210",
    "sg:province":"OR",
    "sg:tags":[
        "acupuncture",
        "psychiatrist"
    ],
    "wof:name":"Hoyt Street Physicians",
    "wof:placetype":"venue"
},
  "geometry": {"coordinates":[-122.70024600000001,45.52702],"type":"Point"}
}