{
  "type": "Feature",
  "properties": {
    "addr:full":"15 82nd Dr Ste 110 Gladstone OR 97027",
    "addr:housenumber":"15",
    "addr:postcode":"97027",
    "addr:street":"82Nd Dr Ste 110",
    "iso:country":"US",
    "sg:address":"15 82nd Dr Ste 110",
    "sg:city":"Gladstone",
    "sg:classifiers":[
        {
            "category":"Building & Trades",
            "subcategory":"Construction",
            "type":"Services"
        }
    ],
    "sg:phone":"+1 503 257 9904",
    "sg:postcode":"97027",
    "sg:province":"OR",
    "sg:tags":[
        "remodeling",
        "altering",
        "wallcoverings-installation",
        "wallpaper",
        "contractor",
        "painting"
    ],
    "wof:name":"Kowalkowski Custom Painting",
    "wof:placetype":"venue"
},
  "geometry": {"coordinates":[-122.584352,45.379429],"type":"Point"}
}