{
  "type": "Feature",
  "properties": {
    "iso:country":"US",
    "sg:address":"1511 Adams Ave",
    "sg:city":"La Grande",
    "sg:classifiers":[
        {
            "category":"Shopping",
            "subcategory":"Clothing, Apparel, & Fashions",
            "type":"Retail Goods"
        }
    ],
    "sg:phone":"+1 541 962 0960",
    "sg:postcode":"97850",
    "sg:province":"OR",
    "sg:tags":[
        "bridal",
        "boutique"
    ],
    "wof:name":"Serendipty- A Bridal and Forma",
    "wof:placetype":"venue"
},
  "geometry": {"coordinates":[-118.09048900000001,45.326199],"type":"Point"}
}