{
  "type": "Feature",
  "properties": {
    "iso:country":"US",
    "sg:address":"1980 State St",
    "sg:city":"Salem",
    "sg:classifiers":[
        {
            "category":"Restaurant",
            "type":"Food & Drink"
        }
    ],
    "sg:phone":"+1 503 588 1710",
    "sg:postcode":"97301",
    "sg:province":"OR",
    "sg:tags":[
        "mexican"
    ],
    "wof:name":"Muchas Gracias Mexican Food",
    "wof:placetype":"venue"
},
  "geometry": {"coordinates":[-123.01743399999999,44.934519],"type":"Point"}
}