{
  "type": "Feature",
  "properties": {
    "iso:country":"US",
    "sg:address":"414 Broadway St",
    "sg:city":"Seaside",
    "sg:classifiers":[
        {
            "category":"Restaurant",
            "type":"Food & Drink"
        }
    ],
    "sg:phone":"+1 503 738 7006",
    "sg:postcode":"97138",
    "sg:province":"OR",
    "wof:name":"Dundee's Bar & Grill",
    "wof:placetype":"venue"
},
  "geometry": {"coordinates":[-123.925912,45.993237],"type":"Point"}
}