{
  "type": "Feature",
  "properties": {
    "addr:full":"3701 SE Division St Portland OR 97202",
    "addr:housenumber":"3701",
    "addr:postcode":"97202",
    "addr:street":"Se Division St",
    "iso:country":"US",
    "sg:address":"3701 SE Division St",
    "sg:city":"Portland",
    "sg:classifiers":[
        {
            "category":"Bars & Pubs",
            "type":"Food & Drink"
        }
    ],
    "sg:phone":"+1 503 236 8689",
    "sg:postcode":"97202",
    "sg:province":"OR",
    "sg:tags":[
        "lounge",
        "gay",
        "cocktail"
    ],
    "wof:name":"Egyptian Club",
    "wof:placetype":"venue"
},
  "geometry": {"coordinates":[-122.62599899999999,45.504902],"type":"Point"}
}