{
  "type": "Feature",
  "properties": {
    "iso:country":"US",
    "sg:address":"2175 S 6th St",
    "sg:city":"Klamath Falls",
    "sg:classifiers":[
        {
            "category":"Restaurant",
            "type":"Food & Drink"
        }
    ],
    "sg:phone":"+1 541 884 8300",
    "sg:postcode":"97601",
    "sg:province":"OR",
    "wof:name":"David's Restaurant",
    "wof:placetype":"venue"
},
  "geometry": {"coordinates":[-121.76416399999999,42.214974],"type":"Point"}
}