{
  "type": "Feature",
  "properties": {
    "addr:full":"4145 Silverton Rd NE Salem OR 97305",
    "addr:housenumber":"4145",
    "addr:postcode":"97305",
    "addr:street":"Silverton Rd Ne",
    "iso:country":"US",
    "sg:address":"4145 Silverton Rd NE",
    "sg:city":"Salem",
    "sg:classifiers":[
        {
            "category":"Retail",
            "subcategory":"Auto Repair",
            "type":"Services"
        }
    ],
    "sg:phone":"+1 503 362 3737",
    "sg:postcode":"97305",
    "sg:province":"OR",
    "sg:tags":[
        "general"
    ],
    "wof:name":"Silverton Road Automotive",
    "wof:placetype":"venue"
},
  "geometry": {"coordinates":[-122.98025199999999,44.96966],"type":"Point"}
}