{
  "type": "Feature",
  "properties": {
    "iso:country":"US",
    "sg:address":"33620 Brewster Rd",
    "sg:city":"Lebanon",
    "sg:classifiers":[
        {
            "category":"Shopping",
            "subcategory":"Shoes",
            "type":"Retail Goods"
        }
    ],
    "sg:phone":"+1 541 451 1404",
    "sg:postcode":"97355",
    "sg:province":"OR",
    "wof:name":"D & D Foot & Etc",
    "wof:placetype":"venue"
},
  "geometry": {"coordinates":[-122.876389,44.562702],"type":"Point"}
}