{
  "type": "Feature",
  "properties": {
    "iso:country":"US",
    "sg:address":"34 S Coast Hwy",
    "sg:city":"Newport",
    "sg:classifiers":[
        {
            "category":"Retail",
            "subcategory":"Repair Shop",
            "type":"Services"
        }
    ],
    "sg:phone":"+1 541 265 9315",
    "sg:postcode":"97365",
    "sg:province":"OR",
    "sg:tags":[
        "upholsterer"
    ],
    "wof:name":"Caldwell's Upholstery",
    "wof:placetype":"venue"
},
  "geometry": {"coordinates":[-124.05320399999999,44.636182],"type":"Point"}
}