{
  "type": "Feature",
  "properties": {
    "addr:full":"38954 Proctor Blvd 346 Sandy OR 97055",
    "addr:housenumber":"38954;346",
    "addr:postcode":"97055",
    "addr:street":"Proctor Blvd",
    "iso:country":"US",
    "sg:address":"38954 Proctor Blvd 346",
    "sg:city":"Sandy",
    "sg:classifiers":[
        {
            "category":"Structure",
            "subcategory":"Warehouse",
            "type":"Public Place"
        }
    ],
    "sg:phone":"+1 503 780 1872",
    "sg:postcode":"97055",
    "sg:province":"OR",
    "sg:tags":[
        "warehouses-merchandise",
        "warehouses-public-commercial"
    ],
    "wof:name":"Hutchison Constructors",
    "wof:placetype":"venue"
},
  "geometry": {"coordinates":[-122.26232899999999,45.397275],"type":"Point"}
}