{
  "type": "Feature",
  "properties": {
    "iso:country":"US",
    "sg:address":"28414 Parkdale Rd",
    "sg:city":"Rainier",
    "sg:classifiers":[
        {
            "category":"Animal Shelter",
            "type":"Public Place"
        },
        {
            "category":"Shopping",
            "subcategory":"Pets & Pet Supplies",
            "type":"Retail Goods"
        },
        {
            "category":"Retail",
            "subcategory":"Animal Services",
            "type":"Services"
        },
        {
            "category":"Retail",
            "subcategory":"Pet Boarding",
            "type":"Services"
        }
    ],
    "sg:phone":"+1 503 556 4210",
    "sg:postcode":"97048",
    "sg:province":"OR",
    "sg:tags":[
        "grooming",
        "dog",
        "kennel",
        "cat"
    ],
    "sg:website":"http://www.parkdalekennels.com",
    "wof:name":"Parkdale Kennels",
    "wof:placetype":"venue"
},
  "geometry": {"coordinates":[-122.98162499999999,46.087741],"type":"Point"}
}