{
  "type": "Feature",
  "properties": {
    "iso:country":"US",
    "sg:address":"120 SW Avery Ave",
    "sg:city":"Corvallis",
    "sg:classifiers":[
        {
            "category":"Building & Trades",
            "subcategory":"Cleaning & Sanitation",
            "type":"Services"
        }
    ],
    "sg:phone":"+1 541 753 5622",
    "sg:postcode":"97333",
    "sg:province":"OR",
    "sg:tags":[
        "janitor"
    ],
    "wof:name":"Fresh Start House Cleaning",
    "wof:placetype":"venue"
},
  "geometry": {"coordinates":[-123.265394,44.551842],"type":"Point"}
}