{
  "type": "Feature",
  "properties": {
    "iso:country":"US",
    "sg:address":"12020 SW Garden Pl",
    "sg:city":"Portland",
    "sg:classifiers":[
        {
            "category":"Professional",
            "subcategory":"Computer Services",
            "type":"Services"
        }
    ],
    "sg:phone":"+1 503 684 1118",
    "sg:postcode":"97223",
    "sg:province":"OR",
    "sg:tags":[
        "design",
        "system"
    ],
    "wof:name":"IKON Office Solutions",
    "wof:placetype":"venue"
},
  "geometry": {"coordinates":[-122.762753,45.433564],"type":"Point"}
}