{
  "type": "Feature",
  "properties": {
    "iso:country":"US",
    "sg:address":"95829 Howard Ln",
    "sg:city":"Junction City",
    "sg:classifiers":[
        {
            "category":"Wholesale",
            "subcategory":"Non-durable Goods",
            "type":"Manufacturing & Wholesale Goods"
        }
    ],
    "sg:phone":"+1 541 998 6612",
    "sg:postcode":"97448",
    "sg:province":"OR",
    "wof:name":"Princess House",
    "wof:placetype":"venue"
},
  "geometry": {"coordinates":[-123.209198,44.262674],"type":"Point"}
}