{
  "type": "Feature",
  "properties": {
    "addr:full":"56880 Venture Ln Sunriver OR 97707",
    "addr:postcode":"56880;97707",
    "addr:street":"Venture Ln",
    "iso:country":"US",
    "sg:address":"56880 Venture Ln",
    "sg:city":"Sunriver",
    "sg:classifiers":[
        {
            "category":"Restaurant",
            "type":"Food & Drink"
        }
    ],
    "sg:phone":"+1 541 593 6577",
    "sg:postcode":"97707",
    "sg:province":"OR",
    "wof:name":"R J B's Restaurant & Sports",
    "wof:placetype":"venue"
},
  "geometry": {"coordinates":[-121.435337,43.866492],"type":"Point"}
}