{
  "type": "Feature",
  "properties": {
    "iso:country":"US",
    "sg:address":"19285 Dusty Loop",
    "sg:city":"Bend",
    "sg:classifiers":[
        {
            "category":"Farming",
            "subcategory":"Livestock Farm",
            "type":"Manufacturing & Wholesale Goods"
        }
    ],
    "sg:phone":"+1 541 389 3860",
    "sg:postcode":"97701",
    "sg:province":"OR",
    "wof:name":"Silhouette Sheep",
    "wof:placetype":"venue"
},
  "geometry": {"coordinates":[-121.348928,44.209663],"type":"Point"}
}