{
  "type": "Feature",
  "properties": {
    "iso:country":"US",
    "sg:address":"655 N 1st St",
    "sg:city":"Hermiston",
    "sg:classifiers":[
        {
            "category":"Travel",
            "subcategory":"Hotels & Motels",
            "type":"Entertainment"
        }
    ],
    "sg:phone":"+1 541 567 7777",
    "sg:postcode":"97838",
    "sg:province":"OR",
    "sg:tags":[
        "lodging"
    ],
    "sg:website":"http://www.motel6.com",
    "wof:name":"Motel 6",
    "wof:placetype":"venue"
},
  "geometry": {"coordinates":[-119.290199,45.844678],"type":"Point"}
}