{
  "type": "Feature",
  "properties": {
    "iso:country":"US",
    "sg:address":"2625 SE Stark St",
    "sg:city":"Portland",
    "sg:classifiers":[
        {
            "category":"Home & Garden",
            "subcategory":"Hardware",
            "type":"Retail Goods"
        }
    ],
    "sg:phone":"+1 503 231 4089",
    "sg:postcode":"97214",
    "sg:province":"OR",
    "sg:website":"www.houseofantiquehardware.com",
    "wof:name":"House Of Antique Hardware",
    "wof:placetype":"venue"
},
  "geometry": {"coordinates":[-122.638389,45.519392],"type":"Point"}
}