{
  "type": "Feature",
  "properties": {
    "addr:full":"3841 SE 149th Ave Portland OR 97236",
    "addr:housenumber":"3841",
    "addr:postcode":"97236",
    "addr:street":"Se 149Th Ave",
    "iso:country":"US",
    "sg:address":"3841 SE 149th Ave",
    "sg:city":"Portland",
    "sg:classifiers":[
        {
            "category":"Building & Trades",
            "subcategory":"Construction",
            "type":"Services"
        }
    ],
    "sg:phone":"+1 503 761 9021",
    "sg:postcode":"97236",
    "sg:province":"OR",
    "sg:tags":[
        "concrete",
        "staining",
        "contractor"
    ],
    "wof:name":"James Cross",
    "wof:placetype":"venue"
},
  "geometry": {"coordinates":[-122.509738,45.494477],"type":"Point"}
}