{
  "type": "Feature",
  "properties": {
    "iso:country":"US",
    "sg:address":"13135 SW Cottontail Ln",
    "sg:city":"Beaverton",
    "sg:classifiers":[
        {
            "category":"Restaurant",
            "type":"Food & Drink"
        }
    ],
    "sg:phone":"+1 503 268 1103",
    "sg:postcode":"97008",
    "sg:province":"OR",
    "sg:tags":[
        "eating"
    ],
    "wof:name":"Happy Garden Rest & Lounge",
    "wof:placetype":"venue"
},
  "geometry": {"coordinates":[-122.811976,45.443755],"type":"Point"}
}