{
  "type": "Feature",
  "properties": {
    "iso:country":"US",
    "sg:address":"101 SW Main Street Suite 2000",
    "sg:city":"Portland",
    "sg:classifiers":[
        {
            "category":"Professional",
            "subcategory":"Lawyer & Legal Services",
            "type":"Services"
        }
    ],
    "sg:phone":"+1 503 221 1011",
    "sg:postcode":"97204",
    "sg:province":"OR",
    "wof:name":"Mitchell Smith Attys",
    "wof:placetype":"venue"
},
  "geometry": {"coordinates":[-122.67552999999999,45.515228],"type":"Point"}
}