{
  "type": "Feature",
  "properties": {
    "addr:full":"60 5th St Ashland OR 97520",
    "addr:housenumber":"60",
    "addr:postcode":"97520",
    "addr:street":"5Th St",
    "iso:country":"US",
    "sg:address":"60 5th St",
    "sg:city":"Ashland",
    "sg:classifiers":[
        {
            "category":"Building & Trades",
            "subcategory":"Construction",
            "type":"Services"
        }
    ],
    "sg:phone":"+1 541 482 4829",
    "sg:postcode":"97520",
    "sg:province":"OR",
    "sg:tags":[
        "carpentry",
        "contractor"
    ],
    "wof:name":"Thom Phillips",
    "wof:placetype":"venue"
},
  "geometry": {"coordinates":[-122.707065,42.194416],"type":"Point"}
}