{
  "type": "Feature",
  "properties": {
    "addr:full":"9620 SW Tualatin Sherwood Rd Tualatin OR 97062",
    "addr:housenumber":"9620",
    "addr:postcode":"97062",
    "addr:street":"Sw Tualatin Sherwood Rd",
    "iso:country":"US",
    "sg:address":"9620 SW Tualatin Sherwood Rd",
    "sg:city":"Tualatin",
    "sg:classifiers":[
        {
            "category":"Wholesale",
            "subcategory":"Auto Parts",
            "type":"Manufacturing & Wholesale Goods"
        }
    ],
    "sg:phone":"+1 503 692 6044",
    "sg:postcode":"97062",
    "sg:province":"OR",
    "sg:tags":[
        "recreational",
        "vehicle"
    ],
    "wof:name":"Rv Parts Outlet",
    "wof:placetype":"venue"
},
  "geometry": {"coordinates":[-122.777435,45.378319],"type":"Point"}
}