{
  "type": "Feature",
  "properties": {
    "addr:full":"4461 Satter Pl NE Salem OR 97305",
    "addr:housenumber":"4461",
    "addr:postcode":"97305",
    "addr:street":"Satter Pl Ne",
    "iso:country":"US",
    "sg:address":"4461 Satter Pl NE",
    "sg:city":"Salem",
    "sg:classifiers":[
        {
            "category":"Shopping",
            "subcategory":"Florist",
            "type":"Retail Goods"
        }
    ],
    "sg:phone":"+1 503 463 1487",
    "sg:postcode":"97305",
    "sg:province":"OR",
    "wof:name":"Wonderful Garden",
    "wof:placetype":"venue"
},
  "geometry": {"coordinates":[-122.9751,44.980868],"type":"Point"}
}