{
  "type": "Feature",
  "properties": {
    "addr:full":"8940 SW Hall Blvd Portland OR 97223",
    "addr:housenumber":"8940",
    "addr:postcode":"97223",
    "addr:street":"Sw Hall Blvd",
    "iso:country":"US",
    "sg:address":"8940 SW Hall Blvd",
    "sg:city":"Portland",
    "sg:classifiers":[
        {
            "category":"Coffee & Tea",
            "type":"Food & Drink"
        }
    ],
    "sg:postcode":"97223",
    "sg:province":"OR",
    "sg:website":"DutchBros.com",
    "wof:name":"Dutch Brothers",
    "wof:placetype":"venue"
},
  "geometry": {"coordinates":[-122.77981800000001,45.455544],"type":"Point"}
}