{
  "type": "Feature",
  "properties": {
    "iso:country":"US",
    "sg:address":"40598 Cole School Rd",
    "sg:city":"Scio",
    "sg:classifiers":[
        {
            "category":"Farming",
            "subcategory":"Farm",
            "type":"Manufacturing & Wholesale Goods"
        }
    ],
    "sg:phone":"+1 503 769 3417",
    "sg:postcode":"97374",
    "sg:province":"OR",
    "sg:tags":[
        "crop",
        "general"
    ],
    "wof:name":"Sawyer Farms",
    "wof:placetype":"venue"
},
  "geometry": {"coordinates":[-122.804448,44.751606],"type":"Point"}
}