{
  "type": "Feature",
  "properties": {
    "addr:full":"17756 NE San Rafael St Portland OR 97230",
    "addr:housenumber":"17756",
    "addr:postcode":"97230",
    "addr:street":"Ne San Rafael St",
    "iso:country":"US",
    "sg:address":"17756 NE San Rafael St",
    "sg:city":"Portland",
    "sg:classifiers":[
        {
            "category":"Banks & Credit Unions",
            "subcategory":"Bank",
            "type":"Services"
        }
    ],
    "sg:phone":"+1 503 252 7060",
    "sg:postcode":"97230",
    "sg:province":"OR",
    "sg:tags":[
        "loan"
    ],
    "wof:name":"United Auto Credit Corp",
    "wof:placetype":"venue"
},
  "geometry": {"coordinates":[-122.479568,45.537061],"type":"Point"}
}