{
  "type": "Feature",
  "properties": {
    "iso:country":"US",
    "sg:address":"805 SW Industrial Way # 201",
    "sg:city":"Bend",
    "sg:classifiers":[
        {
            "category":"Professional",
            "subcategory":"Lawyer & Legal Services",
            "type":"Services"
        }
    ],
    "sg:phone":"+1 541 617 0707",
    "sg:postcode":"97702",
    "sg:province":"OR",
    "sg:tags":[
        "attorney",
        "practice",
        "plan"
    ],
    "wof:name":"Ambrose Law Group",
    "wof:placetype":"venue"
},
  "geometry": {"coordinates":[-121.317796,44.050461],"type":"Point"}
}