{
  "type": "Feature",
  "properties": {
    "iso:country":"US",
    "sg:address":"920 SE 69th Ave",
    "sg:city":"Portland",
    "sg:classifiers":[
        {
            "category":"Building & Trades",
            "subcategory":"Landscaping Services",
            "type":"Services"
        }
    ],
    "sg:phone":"+1 503 239 1074",
    "sg:postcode":"97215",
    "sg:province":"OR",
    "sg:website":"www.hedgehogtree.com",
    "wof:name":"Hedgehog Tree Care",
    "wof:placetype":"venue"
},
  "geometry": {"coordinates":[-122.592133,45.516322],"type":"Point"}
}