{
  "type": "Feature",
  "properties": {
    "iso:country":"US",
    "sg:address":"7973 SE 7th Ave",
    "sg:city":"Portland",
    "sg:classifiers":[
        {
            "category":"Building & Trades",
            "subcategory":"Locksmith",
            "type":"Services"
        }
    ],
    "sg:phone":"+1 503 937 0084",
    "sg:postcode":"97202",
    "sg:province":"OR",
    "sg:tags":[
        "key"
    ],
    "wof:name":"A Locksmith A 24 Hour",
    "wof:placetype":"venue"
},
  "geometry": {"coordinates":[-122.65918600000001,45.466326],"type":"Point"}
}