{
  "type": "Feature",
  "properties": {
    "addr:full":"337 E 13th Ave Eugene OR 97401",
    "addr:housenumber":"337",
    "addr:postcode":"97401",
    "addr:street":"E 13Th Ave",
    "iso:country":"US",
    "sg:address":"337 E 13th Ave",
    "sg:city":"Eugene",
    "sg:classifiers":[
        {
            "category":"Personal",
            "type":"Services"
        }
    ],
    "sg:phone":"+1 541 484 6184",
    "sg:postcode":"97401",
    "sg:province":"OR",
    "sg:tags":[
        "handyman"
    ],
    "wof:name":"David F Capps",
    "wof:placetype":"venue"
},
  "geometry": {"coordinates":[-123.087793,44.04559],"type":"Point"}
}