{
  "type": "Feature",
  "properties": {
    "addr:full":"920 SW Frazer Ave Pendleton OR 97801",
    "addr:housenumber":"920",
    "addr:postcode":"97801",
    "addr:street":"Sw Frazer Ave",
    "iso:country":"US",
    "sg:address":"920 SW Frazer Ave",
    "sg:city":"Pendleton",
    "sg:classifiers":[
        {
            "category":"Social Services",
            "type":"Services"
        }
    ],
    "sg:phone":"+1 541 276 1916",
    "sg:postcode":"97801",
    "sg:province":"OR",
    "sg:tags":[
        "counselor",
        "marriage",
        "family"
    ],
    "wof:name":"Holly Thau",
    "wof:placetype":"venue"
},
  "geometry": {"coordinates":[-118.794173,45.666884],"type":"Point"}
}