{
  "type": "Feature",
  "properties": {
    "iso:country":"US",
    "sg:address":"2389 Sherman Ave",
    "sg:city":"North Bend",
    "sg:classifiers":[
        {
            "category":"Social Services",
            "type":"Services"
        }
    ],
    "sg:phone":"+1 541 751 7886",
    "sg:postcode":"97459",
    "sg:province":"OR",
    "sg:tags":[
        "youth",
        "organization",
        "center"
    ],
    "wof:name":"Bay Area Together For Youth",
    "wof:placetype":"venue"
},
  "geometry": {"coordinates":[-124.223981,43.401082],"type":"Point"}
}