{
  "type": "Feature",
  "properties": {
    "addr:full":"318 SE Grand Ave Portland OR 97214",
    "addr:housenumber":"318",
    "addr:postcode":"97214",
    "addr:street":"Se Grand Ave",
    "iso:country":"US",
    "sg:address":"318 SE Grand Ave",
    "sg:city":"Portland",
    "sg:classifiers":[
        {
            "category":"Restaurant",
            "type":"Food & Drink"
        }
    ],
    "sg:menulink":"http://www.allmenus.com/or/portland/6490-nicholas-restaurant/menu/",
    "sg:phone":"+1 503 235 5123",
    "sg:postcode":"97214",
    "sg:province":"OR",
    "sg:tags":[
        "middle",
        "eastern"
    ],
    "wof:name":"Nicholas Restaurant",
    "wof:placetype":"venue"
},
  "geometry": {"coordinates":[-122.66074,45.520608],"type":"Point"}
}