{
  "type": "Feature",
  "properties": {
    "iso:country":"US",
    "sg:address":"29646 S Matthew Ln",
    "sg:city":"Mulino",
    "sg:classifiers":[
        {
            "category":"Professional",
            "subcategory":"Business Services",
            "type":"Services"
        }
    ],
    "sg:phone":"+1 503 829 9930",
    "sg:postcode":"97042",
    "sg:province":"OR",
    "wof:name":"NW Service Enterprises",
    "wof:placetype":"venue"
},
  "geometry": {"coordinates":[-122.522945,45.178418],"type":"Point"}
}