{
  "type": "Feature",
  "properties": {
    "iso:country":"US",
    "sg:address":"570 SE 3rd Ave",
    "sg:city":"Hillsboro",
    "sg:classifiers":[
        {
            "category":"Wholesale",
            "subcategory":"Groceries",
            "type":"Manufacturing & Wholesale Goods"
        }
    ],
    "sg:phone":"+1 503 844 3866",
    "sg:postcode":"97123",
    "sg:province":"OR",
    "sg:tags":[
        "tortilla"
    ],
    "wof:name":"Tortilleria 4 Hermanas",
    "wof:placetype":"venue"
},
  "geometry": {"coordinates":[-122.98621300000001,45.516524],"type":"Point"}
}