{
  "type": "Feature",
  "properties": {
    "iso:country":"US",
    "sg:address":"16800 SW Netarts Pl",
    "sg:city":"Beaverton",
    "sg:classifiers":[
        {
            "category":"Building & Trades",
            "subcategory":"Landscaping Services",
            "type":"Services"
        }
    ],
    "sg:phone":"+1 503 642 4713",
    "sg:postcode":"97007",
    "sg:province":"OR",
    "wof:name":"Bk Landscape Maintenance",
    "wof:placetype":"venue"
},
  "geometry": {"coordinates":[-122.85017499999999,45.471731],"type":"Point"}
}