{
  "type": "Feature",
  "properties": {
    "iso:country":"US",
    "sg:address":"SW 6th and Yamhill",
    "sg:city":"Portland",
    "sg:classifiers":[
        {
            "category":"Restaurant",
            "type":"Food & Drink"
        }
    ],
    "sg:postcode":"97205",
    "sg:province":"OR",
    "sg:tags":[
        "mexican"
    ],
    "wof:name":"Fuego",
    "wof:placetype":"venue"
},
  "geometry": {"coordinates":[-122.678954,45.518401],"type":"Point"}
}