{
  "type": "Feature",
  "properties": {
    "addr:full":"2415 NW Kings Blvd Corvallis OR 97330",
    "addr:housenumber":"2415",
    "addr:postcode":"97330",
    "addr:street":"Nw Kings Blvd",
    "iso:country":"US",
    "sg:address":"2415 NW Kings Blvd",
    "sg:city":"Corvallis",
    "sg:classifiers":[
        {
            "category":"Shopping",
            "subcategory":"Clothing, Apparel, & Fashions",
            "type":"Retail Goods"
        }
    ],
    "sg:phone":"+1 541 758 1072",
    "sg:postcode":"97330",
    "sg:province":"OR",
    "sg:tags":[
        "clothing",
        "store"
    ],
    "sg:website":"http://www.rossstores.com",
    "wof:name":"Ross Dress For Less",
    "wof:placetype":"venue"
},
  "geometry": {"coordinates":[-123.276053,44.59084],"type":"Point"}
}