{
  "type": "Feature",
  "properties": {
    "iso:country":"US",
    "sg:address":"205 SE Dorion Ave",
    "sg:city":"Pendleton",
    "sg:classifiers":[
        {
            "category":"Travel",
            "subcategory":"Hotels & Motels",
            "type":"Entertainment"
        }
    ],
    "sg:phone":"+1 541 276 3293",
    "sg:postcode":"97801",
    "sg:province":"OR",
    "wof:name":"Let Er' Buck Motel",
    "wof:placetype":"venue"
},
  "geometry": {"coordinates":[-118.784924,45.67224],"type":"Point"}
}