{
  "type": "Feature",
  "properties": {
    "iso:country":"US",
    "sg:address":"201 SW 2nd St",
    "sg:city":"Corvallis",
    "sg:classifiers":[
        {
            "category":"Food & Beverages",
            "subcategory":"Liquor & Beverages",
            "type":"Retail Goods"
        }
    ],
    "sg:phone":"+1 541 752 7418",
    "sg:postcode":"97333",
    "sg:province":"OR",
    "sg:tags":[
        "alcoholic"
    ],
    "wof:name":"Avalon Inc",
    "wof:placetype":"venue"
},
  "geometry": {"coordinates":[-123.260362,44.563106],"type":"Point"}
}