{
  "type": "Feature",
  "properties": {
    "addr:full":"19330 NW Sauvie Island Rd Portland OR 97231",
    "addr:housenumber":"19330",
    "addr:postcode":"97231",
    "addr:street":"Nw Sauvie Island Rd",
    "iso:country":"US",
    "sg:address":"19330 NW Sauvie Island Rd",
    "sg:city":"Portland",
    "sg:classifiers":[
        {
            "category":"Professional",
            "subcategory":"Computer Services",
            "type":"Services"
        }
    ],
    "sg:phone":"+1 503 621 3461",
    "sg:postcode":"97231",
    "sg:province":"OR",
    "sg:tags":[
        "related"
    ],
    "wof:name":"ATHENA Programming Inc",
    "wof:placetype":"venue"
},
  "geometry": {"coordinates":[-122.836607,45.657133],"type":"Point"}
}