{
  "type": "Feature",
  "properties": {
    "iso:country":"US",
    "sg:address":"2427 19th Ave",
    "sg:city":"Forest Grove",
    "sg:classifiers":[
        {
            "category":"Building & Trades",
            "subcategory":"Cleaning & Sanitation",
            "type":"Services"
        }
    ],
    "sg:phone":"+1 503 357 4820",
    "sg:postcode":"97116",
    "sg:province":"OR",
    "sg:tags":[
        "janitor"
    ],
    "wof:name":"Madeline's Cleaning & Mntnc",
    "wof:placetype":"venue"
},
  "geometry": {"coordinates":[-123.10338900000001,45.518418],"type":"Point"}
}