{
  "type": "Feature",
  "properties": {
    "addr:full":"2721 NW 9th St Corvallis OR 97330",
    "addr:housenumber":"2721",
    "addr:postcode":"97330",
    "addr:street":"Nw 9Th St",
    "iso:country":"US",
    "sg:address":"2721 NW 9th St",
    "sg:city":"Corvallis",
    "sg:classifiers":[
        {
            "category":"Communications",
            "subcategory":"Radio Station",
            "type":"Services"
        }
    ],
    "sg:phone":"+1 541 758 4687",
    "sg:postcode":"97330",
    "sg:province":"OR",
    "sg:tags":[
        "broadcast"
    ],
    "wof:name":"Heaven & Home Hour",
    "wof:placetype":"venue"
},
  "geometry": {"coordinates":[-123.251266,44.59522],"type":"Point"}
}