{
  "type": "Feature",
  "properties": {
    "addr:full":"10469 Se Issac Happy Valley OR 97086",
    "addr:postcode":"10469;97086",
    "addr:street":"Se",
    "iso:country":"US",
    "sg:address":"10469 Se Issac",
    "sg:city":"Happy Valley",
    "sg:classifiers":[
        {
            "category":"Autos & Motor Vehicles",
            "subcategory":"Automobile Sales",
            "type":"Retail Goods"
        }
    ],
    "sg:phone":"+1 503 860 1554",
    "sg:postcode":"97086",
    "sg:province":"OR",
    "sg:tags":[
        "automotive"
    ],
    "wof:name":"Nelson's Mobile Oil Change",
    "wof:placetype":"venue"
},
  "geometry": {"coordinates":[-122.536428,45.447621],"type":"Point"}
}