{
  "type": "Feature",
  "properties": {
    "addr:full":"658 W Fairview Dr Springfield OR 97477",
    "addr:housenumber":"658",
    "addr:postcode":"97477",
    "addr:street":"W Fairview Dr",
    "iso:country":"US",
    "sg:address":"658 W Fairview Dr",
    "sg:city":"Springfield",
    "sg:classifiers":[
        {
            "category":"Utilities",
            "subcategory":"Refuse",
            "type":"Services"
        }
    ],
    "sg:phone":"+1 541 726 8452",
    "sg:postcode":"97477",
    "sg:province":"OR",
    "sg:tags":[
        "system"
    ],
    "wof:name":"Gly Tech Recovery LLC",
    "wof:placetype":"venue"
},
  "geometry": {"coordinates":[-123.03572,44.060861],"type":"Point"}
}