{
  "type": "Feature",
  "properties": {
    "iso:country":"US",
    "sg:address":"207 NW 6th St",
    "sg:city":"Redmond",
    "sg:classifiers":[
        {
            "category":"Health Services",
            "subcategory":"Dentist",
            "type":"Services"
        }
    ],
    "sg:phone":"+1 541 548 3896",
    "sg:postcode":"97756",
    "sg:province":"OR",
    "wof:name":"Clark Family Dentistry",
    "wof:placetype":"venue"
},
  "geometry": {"coordinates":[-121.174301,44.277494],"type":"Point"}
}