{
  "type": "Feature",
  "properties": {
    "iso:country":"US",
    "sg:address":"21331 State Hwy 62",
    "sg:city":"Shady Cove",
    "sg:classifiers":[
        {
            "category":"Restaurant",
            "type":"Food & Drink"
        }
    ],
    "sg:phone":"+1 541 878 1476",
    "sg:postcode":"97539",
    "sg:province":"OR",
    "sg:tags":[
        "eating"
    ],
    "wof:name":"Carlottas Dining & Catering",
    "wof:placetype":"venue"
},
  "geometry": {"coordinates":[-122.81406699999999,42.609305],"type":"Point"}
}