{
  "type": "Feature",
  "properties": {
    "iso:country":"US",
    "sg:address":"16004 SW Tualatin Sherwood Rd",
    "sg:city":"Sherwood",
    "sg:classifiers":[
        {
            "category":"Shopping",
            "subcategory":"Gifts & Souvenirs",
            "type":"Retail Goods"
        }
    ],
    "sg:phone":"+1 503 925 1228",
    "sg:postcode":"97140",
    "sg:province":"OR",
    "sg:tags":[
        "shop"
    ],
    "wof:name":"Starwind",
    "wof:placetype":"venue"
},
  "geometry": {"coordinates":[-122.84087,45.368502],"type":"Point"}
}