{
  "type": "Feature",
  "properties": {
    "iso:country":"US",
    "sg:address":"329 1st St",
    "sg:city":"Lake Oswego",
    "sg:classifiers":[
        {
            "category":"Building & Trades",
            "subcategory":"Construction",
            "type":"Services"
        }
    ],
    "sg:phone":"+1 503 675 1343",
    "sg:postcode":"97034",
    "sg:province":"OR",
    "sg:tags":[
        "contractor"
    ],
    "wof:name":"Marion Construction",
    "wof:placetype":"venue"
},
  "geometry": {"coordinates":[-122.664211,45.418988],"type":"Point"}
}