{
  "type": "Feature",
  "properties": {
    "iso:country":"US",
    "sg:address":"1010 NE 3rd Ave",
    "sg:city":"Milton Freewater",
    "sg:classifiers":[
        {
            "category":"Health Services",
            "subcategory":"Clinic",
            "type":"Services"
        }
    ],
    "sg:phone":"+1 541 938 3714",
    "sg:postcode":"97862",
    "sg:province":"OR",
    "wof:name":"Evergreen Health & Rehab",
    "wof:placetype":"venue"
},
  "geometry": {"coordinates":[-118.384336,45.939242],"type":"Point"}
}