{
  "type": "Feature",
  "properties": {
    "iso:country":"US",
    "sg:address":"106 W Q St",
    "sg:city":"Springfield",
    "sg:classifiers":[
        {
            "category":"Education",
            "subcategory":"Special Training",
            "type":"Public Place"
        }
    ],
    "sg:phone":"+1 541 868 1999",
    "sg:postcode":"97477",
    "sg:province":"OR",
    "sg:tags":[
        "educational"
    ],
    "wof:name":"Us Education Corp",
    "wof:placetype":"venue"
},
  "geometry": {"coordinates":[-123.027548,44.06218],"type":"Point"}
}