{
  "type": "Feature",
  "properties": {
    "iso:country":"US",
    "sg:address":"1211 E Powell Blvd",
    "sg:city":"Gresham",
    "sg:classifiers":[
        {
            "category":"Personal",
            "subcategory":"Beauty Salon",
            "type":"Services"
        }
    ],
    "sg:phone":"+1 503 667 8163",
    "sg:postcode":"97030",
    "sg:province":"OR",
    "sg:tags":[
        "shop"
    ],
    "wof:name":"Scandia Beauty Salon",
    "wof:placetype":"venue"
},
  "geometry": {"coordinates":[-122.41970999999999,45.498084],"type":"Point"}
}