{
  "type": "Feature",
  "properties": {
    "addr:full":"9205 S Kraxberger Rd Canby OR 97013",
    "addr:housenumber":"9205",
    "addr:postcode":"97013",
    "addr:street":"S Kraxberger Rd",
    "iso:country":"US",
    "sg:address":"9205 S Kraxberger Rd",
    "sg:city":"Canby",
    "sg:classifiers":[
        {
            "category":"Wholesale",
            "subcategory":"Farm Supplies",
            "type":"Manufacturing & Wholesale Goods"
        }
    ],
    "sg:phone":"+1 503 266 4610",
    "sg:postcode":"97013",
    "sg:province":"OR",
    "sg:tags":[
        "fertilizer"
    ],
    "wof:name":"Stutzman Farms Fertilizer Plnt",
    "wof:placetype":"venue"
},
  "geometry": {"coordinates":[-122.679519,45.2268],"type":"Point"}
}