{
  "type": "Feature",
  "properties": {
    "addr:full":"4080 US Hwy 101 N Yachats OR 97498",
    "addr:housenumber":"4080",
    "addr:postcode":"97498",
    "addr:street":"Us Hwy 101 N",
    "iso:country":"US",
    "sg:address":"4080 US Hwy 101 N",
    "sg:city":"Yachats",
    "sg:classifiers":[
        {
            "category":"Manufacturing",
            "subcategory":"Toys & Sporting Goods",
            "type":"Manufacturing & Wholesale Goods"
        }
    ],
    "sg:phone":"+1 541 547 4665",
    "sg:postcode":"97498",
    "sg:province":"OR",
    "sg:tags":[
        "mfg"
    ],
    "wof:name":"2 Putt Custom Clubmaking",
    "wof:placetype":"venue"
},
  "geometry": {"coordinates":[-124.09662400000001,44.339094],"type":"Point"}
}