{
  "type": "Feature",
  "properties": {
    "iso:country":"US",
    "sg:address":"12475 SW 124th Ave",
    "sg:city":"Portland",
    "sg:classifiers":[
        {
            "category":"Real Estate",
            "subcategory":"Real Estate Agent",
            "type":"Services"
        }
    ],
    "sg:phone":"+1 503 524 6950",
    "sg:postcode":"97223",
    "sg:province":"OR",
    "wof:name":"Pecunia Investments",
    "wof:placetype":"venue"
},
  "geometry": {"coordinates":[-122.803409,45.429876],"type":"Point"}
}