{
  "type": "Feature",
  "properties": {
    "iso:country":"US",
    "sg:address":"2340 NW 15th St",
    "sg:city":"Redmond",
    "sg:classifiers":[
        {
            "category":"Building & Trades",
            "subcategory":"Construction",
            "type":"Services"
        }
    ],
    "sg:phone":"+1 541 548 3301",
    "sg:postcode":"97756",
    "sg:province":"OR",
    "sg:tags":[
        "heavy"
    ],
    "wof:name":"H&R Engnring For Ntral Rsurces",
    "wof:placetype":"venue"
},
  "geometry": {"coordinates":[-121.183902,44.297671],"type":"Point"}
}