{
  "type": "Feature",
  "properties": {
    "iso:country":"US",
    "sg:address":"20080 McConnell Dr",
    "sg:city":"Bend",
    "sg:classifiers":[
        {
            "category":"Food & Beverages",
            "subcategory":"Specialty",
            "type":"Retail Goods"
        }
    ],
    "sg:phone":"+1 541 382 7411",
    "sg:postcode":"97701",
    "sg:province":"OR",
    "sg:tags":[
        "water",
        "bulk",
        "company"
    ],
    "wof:name":"Pronghorn Springs Bottled Wtr",
    "wof:placetype":"venue"
},
  "geometry": {"coordinates":[-121.317848,44.212751],"type":"Point"}
}