{
  "type": "Feature",
  "properties": {
    "iso:country":"US",
    "sg:address":"89299 Fir Butte Rd",
    "sg:city":"Eugene",
    "sg:classifiers":[
        {
            "category":"Real Estate",
            "subcategory":"Real Estate Operator",
            "type":"Services"
        }
    ],
    "sg:phone":"+1 541 689 0706",
    "sg:postcode":"97402",
    "sg:province":"OR",
    "sg:tags":[
        "park",
        "trailer"
    ],
    "wof:name":"Westwood Trailer Park",
    "wof:placetype":"venue"
},
  "geometry": {"coordinates":[-123.234609,44.081486],"type":"Point"}
}