{
  "type": "Feature",
  "properties": {
    "iso:country":"US",
    "sg:address":"8945 SW Cashmur Lane",
    "sg:city":"Portland",
    "sg:classifiers":[
        {
            "category":"Retail",
            "subcategory":"Auto Repair",
            "type":"Services"
        }
    ],
    "sg:phone":"+1 503 297 3281",
    "sg:postcode":"97225",
    "sg:province":"OR",
    "wof:name":"Jozsi's Import Car Repair",
    "wof:placetype":"venue"
},
  "geometry": {"coordinates":[-122.76884699999999,45.49612],"type":"Point"}
}