{
  "type": "Feature",
  "properties": {
    "iso:country":"US",
    "sg:address":"9155 SW Barnes Rd",
    "sg:city":"Portland",
    "sg:classifiers":[
        {
            "category":"Health Services",
            "subcategory":"Doctor",
            "type":"Services"
        }
    ],
    "sg:phone":"+1 503 935 8100",
    "sg:postcode":"97225",
    "sg:province":"OR",
    "wof:name":"Edsel Kim MD",
    "wof:placetype":"venue"
},
  "geometry": {"coordinates":[-122.770162,45.508904],"type":"Point"}
}