{
  "type": "Feature",
  "properties": {
    "iso:country":"US",
    "sg:address":"16016 SE Division St",
    "sg:city":"Portland",
    "sg:classifiers":[
        {
            "category":"Building & Trades",
            "subcategory":"Construction",
            "type":"Services"
        }
    ],
    "sg:phone":"+1 503 658 6810",
    "sg:postcode":"97236",
    "sg:province":"OR",
    "wof:name":"Well Built Utility Cnstr",
    "wof:placetype":"venue"
},
  "geometry": {"coordinates":[-122.49698600000001,45.504479],"type":"Point"}
}