{
  "type": "Feature",
  "properties": {
    "addr:full":"555 Liberty St SE Rm 100 Salem OR 97301",
    "addr:housenumber":"555;100",
    "addr:postcode":"97301",
    "addr:street":"Liberty St Se Rm",
    "iso:country":"US",
    "sg:address":"555 Liberty St SE Rm 100",
    "sg:city":"Salem",
    "sg:classifiers":[
        {
            "category":"Government",
            "subcategory":"Police Station",
            "type":"Public Place"
        },
        {
            "category":"Professional",
            "subcategory":"Detective & Security Services",
            "type":"Services"
        }
    ],
    "sg:phone":"+1 503 588 6072",
    "sg:postcode":"97301",
    "sg:province":"OR",
    "sg:tags":[
        "enforcement",
        "law",
        "agencies-government",
        "rescue"
    ],
    "wof:name":"Drug Enforcement Divsion",
    "wof:placetype":"venue"
},
  "geometry": {"coordinates":[-123.041124,44.935437],"type":"Point"}
}