{
  "type": "Feature",
  "properties": {
    "iso:country":"US",
    "sg:address":"14255 SW Pacific Hwy",
    "sg:city":"Portland",
    "sg:classifiers":[
        {
            "category":"Home & Garden",
            "subcategory":"Furniture",
            "type":"Retail Goods"
        }
    ],
    "sg:phone":"+1 503 598 9009",
    "sg:postcode":"97224",
    "sg:province":"OR",
    "sg:tags":[
        "store"
    ],
    "wof:name":"America's Mattress",
    "wof:placetype":"venue"
},
  "geometry": {"coordinates":[-122.789542,45.416645],"type":"Point"}
}