{
  "type": "Feature",
  "properties": {
    "iso:country":"US",
    "sg:address":"10245 NW Royal Rose Ct",
    "sg:city":"Portland",
    "sg:classifiers":[
        {
            "category":"Social Services",
            "subcategory":"Child Care",
            "type":"Services"
        }
    ],
    "sg:phone":"+1 503 297 9593",
    "sg:postcode":"97229",
    "sg:province":"OR",
    "wof:name":"Morning Star Child Care",
    "wof:placetype":"venue"
},
  "geometry": {"coordinates":[-122.78435,45.5295],"type":"Point"}
}