{
  "type": "Feature",
  "properties": {
    "iso:country":"US",
    "sg:address":"20595 SW Tualatin Valley Hwy",
    "sg:city":"Beaverton",
    "sg:classifiers":[
        {
            "category":"Wholesale",
            "subcategory":"Electrical",
            "type":"Manufacturing & Wholesale Goods"
        }
    ],
    "sg:phone":"+1 503 591 0647",
    "sg:postcode":"97006",
    "sg:province":"OR",
    "sg:tags":[
        "electronic"
    ],
    "wof:name":"Cain-Sweet Co",
    "wof:placetype":"venue"
},
  "geometry": {"coordinates":[-122.89084200000001,45.49638],"type":"Point"}
}