{
  "type": "Feature",
  "properties": {
    "iso:country":"US",
    "sg:address":"201 W Main St Ste 5A",
    "sg:city":"Medford",
    "sg:classifiers":[
        {
            "category":"Professional",
            "subcategory":"Lawyer & Legal Services",
            "type":"Services"
        }
    ],
    "sg:phone":"+1 541 772 7123",
    "sg:postcode":"97501",
    "sg:province":"OR",
    "sg:tags":[
        "litigation"
    ],
    "wof:name":"Grkng Tmthy C Brphy MLS Schmr Grkng & Brphy Llp",
    "wof:placetype":"venue"
},
  "geometry": {"coordinates":[-122.878998,42.317299],"type":"Point"}
}