{
  "type": "Feature",
  "properties": {
    "iso:country":"US",
    "sg:address":"2997 Pennington Dr",
    "sg:city":"Medford",
    "sg:classifiers":[
        {
            "category":"Building & Trades",
            "subcategory":"Landscaping Services",
            "type":"Services"
        }
    ],
    "sg:phone":"+1 541 858 7938",
    "sg:postcode":"97504",
    "sg:province":"OR",
    "sg:tags":[
        "landscape"
    ],
    "wof:name":"Advanced Landscape Concepts",
    "wof:placetype":"venue"
},
  "geometry": {"coordinates":[-122.836634,42.355348],"type":"Point"}
}