{
  "type": "Feature",
  "properties": {
    "addr:full":"10105 SW Heather Ln Beaverton OR 97008",
    "addr:housenumber":"10105",
    "addr:postcode":"97008",
    "addr:street":"Sw Heather Ln",
    "iso:country":"US",
    "sg:address":"10105 SW Heather Ln",
    "sg:city":"Beaverton",
    "sg:classifiers":[
        {
            "category":"Shopping",
            "subcategory":"Jewelry",
            "type":"Retail Goods"
        }
    ],
    "sg:phone":"+1 503 641 8693",
    "sg:postcode":"97008",
    "sg:province":"OR",
    "wof:name":"C R Charms",
    "wof:placetype":"venue"
},
  "geometry": {"coordinates":[-122.781125,45.467741],"type":"Point"}
}