{
  "type": "Feature",
  "properties": {
    "iso:country":"US",
    "sg:address":"4325 N Commerce St Ste 100",
    "sg:city":"Portland",
    "sg:classifiers":[
        {
            "category":"Personal",
            "type":"Services"
        }
    ],
    "sg:phone":"+1 503 445 7701",
    "sg:postcode":"97217",
    "sg:province":"OR",
    "sg:tags":[
        "local"
    ],
    "sg:website":"www.enviroshrednw.com",
    "wof:name":"EnviroShred NW",
    "wof:placetype":"venue"
},
  "geometry": {"coordinates":[-122.71196399999999,45.561012],"type":"Point"}
}