{
  "type": "Feature",
  "properties": {
    "iso:country":"US",
    "sg:address":"17600 NE North Valley Rd",
    "sg:city":"Newberg",
    "sg:classifiers":[
        {
            "category":"Education",
            "subcategory":"School",
            "type":"Public Place"
        }
    ],
    "sg:phone":"+1 503 554 4750",
    "sg:postcode":"97132",
    "sg:province":"OR",
    "sg:website":"www.newberg.k12.or.us",
    "wof:name":"Ewing Young Elementary School",
    "wof:placetype":"venue"
},
  "geometry": {"coordinates":[-123.058392,45.330594],"type":"Point"}
}