{
  "type": "Feature",
  "properties": {
    "iso:country":"US",
    "sg:address":"335 E 6th St",
    "sg:city":"Mcminnville",
    "sg:classifiers":[
        {
            "category":"Professional",
            "subcategory":"Lawyer & Legal Services",
            "type":"Services"
        }
    ],
    "sg:phone":"+1 503 472 0687",
    "sg:postcode":"97128",
    "sg:province":"OR",
    "wof:name":"Gray & Mercer PC Attys",
    "wof:placetype":"venue"
},
  "geometry": {"coordinates":[-123.195986,45.212238],"type":"Point"}
}