{
  "type": "Feature",
  "properties": {
    "iso:country":"US",
    "sg:address":"4660 Long Prairie Rd",
    "sg:city":"Tillamook",
    "sg:classifiers":[
        {
            "category":"Personal",
            "subcategory":"Beauty Salon",
            "type":"Services"
        }
    ],
    "sg:phone":"+1 503 842 4253",
    "sg:postcode":"97141",
    "sg:province":"OR",
    "sg:tags":[
        "shop"
    ],
    "wof:name":"Jos Home Salon",
    "wof:placetype":"venue"
},
  "geometry": {"coordinates":[-123.81823900000001,45.426949],"type":"Point"}
}