{
  "type": "Feature",
  "properties": {
    "addr:full":"1032 SE 35th Ave Portland OR 97214",
    "addr:housenumber":"1032",
    "addr:postcode":"97214",
    "addr:street":"Se 35Th Ave",
    "iso:country":"US",
    "sg:address":"1032 SE 35th Ave",
    "sg:city":"Portland",
    "sg:classifiers":[
        {
            "category":"Social Services",
            "subcategory":"Job Training",
            "type":"Services"
        }
    ],
    "sg:phone":"+1 503 239 0132",
    "sg:postcode":"97214",
    "sg:province":"OR",
    "sg:tags":[
        "rehabilitation"
    ],
    "wof:name":"Indochinese Socialization Ctr",
    "wof:placetype":"venue"
},
  "geometry": {"coordinates":[-122.628123,45.515257],"type":"Point"}
}