{
  "type": "Feature",
  "properties": {
    "addr:full":"1510 SW Carey Ln Portland OR 97219",
    "addr:housenumber":"1510",
    "addr:postcode":"97219",
    "addr:street":"Sw Carey Ln",
    "iso:country":"US",
    "sg:address":"1510 SW Carey Ln",
    "sg:city":"Portland",
    "sg:classifiers":[
        {
            "category":"Real Estate",
            "subcategory":"Real Estate Agent",
            "type":"Services"
        }
    ],
    "sg:phone":"+1 503 636 1755",
    "sg:postcode":"97219",
    "sg:province":"OR",
    "wof:name":"Hoss Properties",
    "wof:placetype":"venue"
},
  "geometry": {"coordinates":[-122.663365,45.449305],"type":"Point"}
}