{
  "type": "Feature",
  "properties": {
    "iso:country":"US",
    "sg:address":"134 Hansen Ln",
    "sg:city":"Eugene",
    "sg:classifiers":[
        {
            "category":"Recreation",
            "type":"Entertainment"
        }
    ],
    "sg:phone":"+1 541 607 8825",
    "sg:postcode":"97404",
    "sg:province":"OR",
    "wof:name":"Kung Fu Design",
    "wof:placetype":"venue"
},
  "geometry": {"coordinates":[-123.12244800000001,44.068744],"type":"Point"}
}