{
  "type": "Feature",
  "properties": {
    "iso:country":"US",
    "sg:address":"1962 McCarter Ln",
    "sg:city":"Grants Pass",
    "sg:classifiers":[
        {
            "category":"Shopping",
            "subcategory":"Discount & Variety Stores",
            "type":"Retail Goods"
        }
    ],
    "sg:phone":"+1 541 956 7696",
    "sg:postcode":"97527",
    "sg:province":"OR",
    "wof:name":"Yet Another Idea",
    "wof:placetype":"venue"
},
  "geometry": {"coordinates":[-123.345939,42.416943],"type":"Point"}
}