{
  "type": "Feature",
  "properties": {
    "iso:country":"US",
    "sg:address":"555 Welter Cir",
    "sg:city":"Gladstone",
    "sg:classifiers":[
        {
            "category":"Real Estate",
            "subcategory":"Real Estate Agent",
            "type":"Services"
        }
    ],
    "sg:phone":"+1 503 656 4407",
    "sg:postcode":"97027",
    "sg:province":"OR",
    "wof:name":"John A Varner",
    "wof:placetype":"venue"
},
  "geometry": {"coordinates":[-122.605511,45.384159],"type":"Point"}
}