{
  "type": "Feature",
  "properties": {
    "addr:full":"7420 SE Woodstock Blvd Portland OR 97206",
    "addr:housenumber":"7420",
    "addr:postcode":"97206",
    "addr:street":"Se Woodstock Blvd",
    "iso:country":"US",
    "sg:address":"7420 SE Woodstock Blvd",
    "sg:city":"Portland",
    "sg:classifiers":[
        {
            "category":"Manufacturing",
            "subcategory":"Printing",
            "type":"Manufacturing & Wholesale Goods"
        }
    ],
    "sg:phone":"+1 503 771 8564",
    "sg:postcode":"97206",
    "sg:province":"OR",
    "sg:tags":[
        "commercial"
    ],
    "wof:name":"Executive Workshop",
    "wof:placetype":"venue"
},
  "geometry": {"coordinates":[-122.584273,45.479525],"type":"Point"}
}