{
  "type": "Feature",
  "properties": {
    "iso:country":"US",
    "sg:address":"24850 SE Stark St Ste 180",
    "sg:city":"Gresham",
    "sg:phone":"+1 503 492 6510",
    "sg:postcode":"97030",
    "sg:province":"OR",
    "wof:name":"The Center for Men's and Women's Urology",
    "wof:placetype":"venue"
},
  "geometry": {"coordinates":[-122.40766499999999,45.519051],"type":"Point"}
}