{
  "type": "Feature",
  "properties": {
    "iso:country":"US",
    "sg:address":"62730 Hurricane Creek Rd",
    "sg:city":"Joseph",
    "sg:classifiers":[
        {
            "category":"Building & Trades",
            "subcategory":"Construction",
            "type":"Services"
        }
    ],
    "sg:phone":"+1 541 432 4965",
    "sg:postcode":"97846",
    "sg:province":"OR",
    "sg:tags":[
        "general",
        "contractor"
    ],
    "wof:name":"David Zimmer Construction Inc",
    "wof:placetype":"venue"
},
  "geometry": {"coordinates":[-117.27142000000001,45.352085],"type":"Point"}
}