{
  "type": "Feature",
  "properties": {
    "iso:country":"US",
    "sg:address":"164 Carly Cir",
    "sg:city":"Medford",
    "sg:classifiers":[
        {
            "category":"Building & Trades",
            "subcategory":"Construction",
            "type":"Services"
        }
    ],
    "sg:phone":"+1 541 776 1245",
    "sg:postcode":"97504",
    "sg:province":"OR",
    "sg:tags":[
        "residential"
    ],
    "wof:name":"Michael A Susi",
    "wof:placetype":"venue"
},
  "geometry": {"coordinates":[-122.80730800000001,42.335816],"type":"Point"}
}