{
  "type": "Feature",
  "properties": {
    "addr:full":"29 SE Dorion Ave Pendleton OR 97801",
    "addr:housenumber":"29",
    "addr:postcode":"97801",
    "addr:street":"Se Dorion Ave",
    "iso:country":"US",
    "sg:address":"29 SE Dorion Ave",
    "sg:city":"Pendleton",
    "sg:classifiers":[
        {
            "category":"Home & Garden",
            "subcategory":"Home Furnishings",
            "type":"Retail Goods"
        }
    ],
    "sg:phone":"+1 541 276 4974",
    "sg:postcode":"97801",
    "sg:province":"OR",
    "sg:tags":[
        "housewares"
    ],
    "sg:website":"www.sunshinegourmetshoppe.com",
    "wof:name":"Sunshine Gourmet Shoppe",
    "wof:placetype":"venue"
},
  "geometry": {"coordinates":[-118.78619,45.67194],"type":"Point"}
}