{
  "type": "Feature",
  "properties": {
    "iso:country":"US",
    "sg:address":"6015 NW Rosewood Dr",
    "sg:city":"Corvallis",
    "sg:classifiers":[
        {
            "category":"Professional",
            "subcategory":"Business Services",
            "type":"Services"
        }
    ],
    "sg:phone":"+1 541 745 2002",
    "sg:postcode":"97330",
    "sg:province":"OR",
    "wof:name":"Franklin Conklin Foundation",
    "wof:placetype":"venue"
},
  "geometry": {"coordinates":[-123.27829,44.635127],"type":"Point"}
}