{
  "type": "Feature",
  "properties": {
    "iso:country":"US",
    "sg:address":"1924 SE Risley Ave",
    "sg:city":"Portland",
    "sg:classifiers":[
        {
            "category":"Real Estate",
            "subcategory":"Real Estate Operator",
            "type":"Services"
        }
    ],
    "sg:phone":"+1 503 654 3429",
    "sg:postcode":"97267",
    "sg:province":"OR",
    "sg:tags":[
        "mobile",
        "manufactured",
        "housing-communities",
        "site",
        "home"
    ],
    "wof:name":"Young's Mobile Estates",
    "wof:placetype":"venue"
},
  "geometry": {"coordinates":[-122.64252500000001,45.404656],"type":"Point"}
}