{
  "type": "Feature",
  "properties": {
    "addr:full":"2975 River Rd S Salem OR 97302",
    "addr:housenumber":"2975",
    "addr:postcode":"97302",
    "addr:street":"River Rd",
    "iso:country":"US",
    "sg:address":"2975 River Rd S",
    "sg:city":"Salem",
    "sg:classifiers":[
        {
            "category":"Personal",
            "subcategory":"Beauty Salon",
            "type":"Services"
        }
    ],
    "sg:phone":"+1 503 362 6621",
    "sg:postcode":"97302",
    "sg:province":"OR",
    "sg:tags":[
        "shop"
    ],
    "wof:name":"Headlines Styling Studio",
    "wof:placetype":"venue"
},
  "geometry": {"coordinates":[-123.068466,44.912777],"type":"Point"}
}