{
  "type": "Feature",
  "properties": {
    "addr:full":"4100 Westcliff Dr Hood River OR 97031",
    "addr:housenumber":"4100",
    "addr:postcode":"97031",
    "addr:street":"Westcliff Dr",
    "iso:country":"US",
    "sg:address":"4100 Westcliff Dr",
    "sg:city":"Hood River",
    "sg:classifiers":[
        {
            "category":"Restaurant",
            "type":"Food & Drink"
        }
    ],
    "sg:phone":"+1 541 386 3101",
    "sg:postcode":"97031",
    "sg:province":"OR",
    "wof:name":"Charburger Country",
    "wof:placetype":"venue"
},
  "geometry": {"coordinates":[-121.55759500000001,45.709877],"type":"Point"}
}