{
  "type": "Feature",
  "properties": {
    "iso:country":"US",
    "sg:address":"34100 Sky Way Dr",
    "sg:city":"Scappoose",
    "sg:classifiers":[
        {
            "category":"Manufacturing",
            "subcategory":"Aerospace",
            "type":"Manufacturing & Wholesale Goods"
        }
    ],
    "sg:phone":"+1 503 543 4004",
    "sg:postcode":"97056",
    "sg:province":"OR",
    "sg:tags":[
        "mfg",
        "equipment",
        "aircraft",
        "part",
        "supplies-wholesale",
        "manufacturer"
    ],
    "sg:website":"http://www.sherpaaircraft.com",
    "wof:name":"Sherpa Aircraft Mfg, Inc",
    "wof:placetype":"venue"
},
  "geometry": {"coordinates":[-122.866586,45.775548],"type":"Point"}
}