{
  "type": "Feature",
  "properties": {
    "addr:full":"2400 SE 83rd Ave Portland OR 97216",
    "addr:housenumber":"2400",
    "addr:postcode":"97216",
    "addr:street":"Se 83Rd Ave",
    "iso:country":"US",
    "sg:address":"2400 SE 83rd Ave",
    "sg:city":"Portland",
    "sg:classifiers":[
        {
            "category":"Retail",
            "subcategory":"Auto Repair",
            "type":"Services"
        }
    ],
    "sg:phone":"+1 503 774 8524",
    "sg:postcode":"97216",
    "sg:province":"OR",
    "sg:tags":[
        "automotive"
    ],
    "wof:name":"Hisham Ayach",
    "wof:placetype":"venue"
},
  "geometry": {"coordinates":[-122.577476,45.505243],"type":"Point"}
}