{
  "type": "Feature",
  "properties": {
    "addr:full":"8196 SW Hall Blvd Beaverton OR 97008",
    "addr:housenumber":"8196",
    "addr:postcode":"97008",
    "addr:street":"Sw Hall Blvd",
    "iso:country":"US",
    "sg:address":"8196 SW Hall Blvd",
    "sg:city":"Beaverton",
    "sg:classifiers":[
        {
            "category":"Professional",
            "subcategory":"Engineering",
            "type":"Services"
        }
    ],
    "sg:phone":"+1 503 469 1213",
    "sg:postcode":"97008",
    "sg:province":"OR",
    "sg:tags":[
        "engineer"
    ],
    "wof:name":"S R Design",
    "wof:placetype":"venue"
},
  "geometry": {"coordinates":[-122.794555,45.46092],"type":"Point"}
}