{
  "type": "Feature",
  "properties": {
    "iso:country":"US",
    "sg:address":"9343 SW Diamond View Way",
    "sg:city":"Beaverton",
    "sg:classifiers":[
        {
            "category":"Professional",
            "subcategory":"Business Services",
            "type":"Services"
        }
    ],
    "sg:phone":"+1 503 941 9547",
    "sg:postcode":"97007",
    "sg:province":"OR",
    "sg:tags":[
        "organizing",
        "services-household"
    ],
    "wof:name":"S J Shane Property Management",
    "wof:placetype":"venue"
},
  "geometry": {"coordinates":[-122.843673,45.452101],"type":"Point"}
}