{
  "type": "Feature",
  "properties": {
    "iso:country":"US",
    "sg:address":"13815 SW Pacific Hwy Ste 10",
    "sg:city":"Portland",
    "sg:classifiers":[
        {
            "category":"Shopping",
            "subcategory":"Used Merchandise",
            "type":"Retail Goods"
        }
    ],
    "sg:phone":"+1 503 639 8439",
    "sg:postcode":"97223",
    "sg:province":"OR",
    "sg:tags":[
        "vintage",
        "consignment"
    ],
    "wof:name":"Baby & Me",
    "wof:placetype":"venue"
},
  "geometry": {"coordinates":[-122.786266,45.419911],"type":"Point"}
}