{
  "type": "Feature",
  "properties": {
    "iso:country":"US",
    "sg:address":"6225 NE 42nd Ave",
    "sg:city":"Portland",
    "sg:classifiers":[
        {
            "category":"Social Services",
            "type":"Services"
        },
        {
            "category":"Professional",
            "subcategory":"Employment Agencies",
            "type":"Services"
        }
    ],
    "sg:phone":"+1 503 287 0090",
    "sg:postcode":"97218",
    "sg:province":"OR",
    "sg:tags":[
        "workers'",
        "placement",
        "volunteer"
    ],
    "wof:name":"Turning Point Foundation",
    "wof:placetype":"venue"
},
  "geometry": {"coordinates":[-122.620413,45.568191],"type":"Point"}
}