{
  "type": "Feature",
  "properties": {
    "iso:country":"US",
    "sg:address":"1100 SW 6th Ave Ste 1425",
    "sg:city":"Portland",
    "sg:classifiers":[
        {
            "category":"Professional",
            "subcategory":"Advertising",
            "type":"Services"
        },
        {
            "category":"Professional",
            "subcategory":"Business Services",
            "type":"Services"
        }
    ],
    "sg:phone":"+1 503 294 9120",
    "sg:postcode":"97204",
    "sg:province":"OR",
    "sg:tags":[
        "marketing",
        "relation",
        "public"
    ],
    "sg:website":"www.cfm-online.com",
    "wof:name":"CFM Strategic Communications",
    "wof:placetype":"venue"
},
  "geometry": {"coordinates":[-122.679733,45.515945],"type":"Point"}
}