{
  "type": "Feature",
  "properties": {
    "iso:country":"US",
    "sg:address":"401 Center St NE",
    "sg:city":"Salem",
    "sg:classifiers":[
        {
            "category":"Shopping",
            "subcategory":"Gifts & Souvenirs",
            "type":"Retail Goods"
        }
    ],
    "sg:phone":"+1 503 399 7612",
    "sg:postcode":"97301",
    "sg:province":"OR",
    "sg:tags":[
        "shop"
    ],
    "wof:name":"Spencer Gifts",
    "wof:placetype":"venue"
},
  "geometry": {"coordinates":[-123.03552999999999,44.94289],"type":"Point"}
}