{
  "type": "Feature",
  "properties": {
    "iso:country":"US",
    "sg:address":"4543 S Pacific Hwy",
    "sg:city":"Phoenix",
    "sg:classifiers":[
        {
            "category":"Home & Garden",
            "subcategory":"Garden Supply",
            "type":"Retail Goods"
        }
    ],
    "sg:phone":"+1 541 535 1134",
    "sg:postcode":"97535",
    "sg:province":"OR",
    "sg:tags":[
        "center"
    ],
    "wof:name":"Phoenix Organic Garden & Farm",
    "wof:placetype":"venue"
},
  "geometry": {"coordinates":[-122.809551,42.268489],"type":"Point"}
}