{
  "type": "Feature",
  "properties": {
    "iso:country":"US",
    "sg:address":"6620 SW Princess Ave",
    "sg:city":"Beaverton",
    "sg:classifiers":[
        {
            "category":"Building & Trades",
            "subcategory":"Landscaping Services",
            "type":"Services"
        }
    ],
    "sg:phone":"+1 503 734 6544",
    "sg:postcode":"97008",
    "sg:province":"OR",
    "wof:name":"Mikes Landscape Construction",
    "wof:placetype":"venue"
},
  "geometry": {"coordinates":[-122.79398399999999,45.470357],"type":"Point"}
}