{
  "type": "Feature",
  "properties": {
    "addr:full":"5019 Williams Hwy Grants Pass OR 97527",
    "addr:housenumber":"5019",
    "addr:postcode":"97527",
    "addr:street":"Williams Hwy",
    "iso:country":"US",
    "sg:address":"5019 Williams Hwy",
    "sg:city":"Grants Pass",
    "sg:classifiers":[
        {
            "category":"Organizations",
            "subcategory":"Community Association",
            "type":"Services"
        }
    ],
    "sg:phone":"+1 541 862 2048",
    "sg:postcode":"97527",
    "sg:province":"OR",
    "wof:name":"Subdivision Asso",
    "wof:placetype":"venue"
},
  "geometry": {"coordinates":[-123.334677,42.368588],"type":"Point"}
}