{
  "type": "Feature",
  "properties": {
    "addr:full":"2467 SE Ochoco St Portland OR 97222",
    "addr:housenumber":"2467",
    "addr:postcode":"97222",
    "addr:street":"Se Ochoco St",
    "iso:country":"US",
    "sg:address":"2467 SE Ochoco St",
    "sg:city":"Portland",
    "sg:classifiers":[
        {
            "category":"Manufacturing",
            "subcategory":"Metals",
            "type":"Manufacturing & Wholesale Goods"
        }
    ],
    "sg:phone":"+1 503 513 7118",
    "sg:postcode":"97222",
    "sg:province":"OR",
    "sg:tags":[
        "cutting",
        "forging",
        "gear",
        "mfg"
    ],
    "sg:website":"http://sites.google.com/site/standardgearinc/",
    "wof:name":"Standard Gear Manufacturing, Inc.",
    "wof:placetype":"venue"
},
  "geometry": {"coordinates":[-122.63724499999999,45.458763],"type":"Point"}
}