{
  "type": "Feature",
  "properties": {
    "iso:country":"US",
    "sg:address":"569 N Main St",
    "sg:city":"Ashland",
    "sg:classifiers":[
        {
            "category":"Professional",
            "subcategory":"Engineering",
            "type":"Services"
        }
    ],
    "sg:phone":"+1 541 482 7204",
    "sg:postcode":"97520",
    "sg:province":"OR",
    "sg:tags":[
        "engineer"
    ],
    "wof:name":"Arcsine Engineering",
    "wof:placetype":"venue"
},
  "geometry": {"coordinates":[-122.720984,42.205808],"type":"Point"}
}