{
  "type": "Feature",
  "properties": {
    "iso:country":"US",
    "sg:address":"950 SW 21st Ave",
    "sg:city":"Portland",
    "sg:classifiers":[
        {
            "category":"Professional",
            "subcategory":"Business Services",
            "type":"Services"
        }
    ],
    "sg:phone":"+1 503 973 9363",
    "sg:postcode":"97205",
    "sg:province":"OR",
    "wof:name":"Celia Varain Interior Design",
    "wof:placetype":"venue"
},
  "geometry": {"coordinates":[-122.69415499999999,45.521271],"type":"Point"}
}