{
  "type": "Feature",
  "properties": {
    "iso:country":"US",
    "sg:address":"7456 W Baseline Rd PMB 122",
    "sg:city":"Hillsboro",
    "sg:classifiers":[
        {
            "category":"Farming",
            "subcategory":"Nursery",
            "type":"Manufacturing & Wholesale Goods"
        },
        {
            "category":"Shopping",
            "subcategory":"Crafts & Fabrics",
            "type":"Retail Goods"
        }
    ],
    "sg:phone":"+1 503 756 6117",
    "sg:postcode":"97123",
    "sg:province":"OR",
    "sg:tags":[
        "supplies-wholesale",
        "florists'",
        "grower",
        "nursery-wholesale",
        "manufacturer"
    ],
    "sg:website":"http://www.drkatieevans.com",
    "wof:name":"Dr. Katie Evans Inc",
    "wof:placetype":"venue"
},
  "geometry": {"coordinates":[-122.90269000000001,45.51569],"type":"Point"}
}