{
  "type": "Feature",
  "properties": {
    "iso:country":"US",
    "sg:address":"9222 NE Glisan St",
    "sg:city":"Portland",
    "sg:classifiers":[
        {
            "category":"Building & Trades",
            "subcategory":"Cleaning & Sanitation",
            "type":"Services"
        }
    ],
    "sg:phone":"+1 503 252 8850",
    "sg:postcode":"97220",
    "sg:province":"OR",
    "sg:tags":[
        "janitor"
    ],
    "wof:name":"Cleaner Image Maintenance Inc",
    "wof:placetype":"venue"
},
  "geometry": {"coordinates":[-122.56864899999999,45.526347],"type":"Point"}
}