{
  "type": "Feature",
  "properties": {
    "iso:country":"US",
    "sg:address":"10378 SW Davies Rd",
    "sg:city":"Beaverton",
    "sg:classifiers":[
        {
            "category":"Personal",
            "type":"Services"
        }
    ],
    "sg:phone":"+1 503 524 1959",
    "sg:postcode":"97008",
    "sg:province":"OR",
    "wof:name":"Fix It Please Inc",
    "wof:placetype":"venue"
},
  "geometry": {"coordinates":[-122.82078799999999,45.444572],"type":"Point"}
}