{
  "type": "Feature",
  "properties": {
    "iso:country":"US",
    "sg:address":"1770 NW Valley View Dr",
    "sg:city":"Roseburg",
    "sg:classifiers":[
        {
            "category":"Health Services",
            "subcategory":"Nursing And Care Facility",
            "type":"Services"
        }
    ],
    "sg:phone":"+1 541 673 3900",
    "sg:postcode":"97470",
    "sg:province":"OR",
    "sg:tags":[
        "home",
        "convalescent"
    ],
    "wof:name":"Callahan Court Memory Care",
    "wof:placetype":"venue"
},
  "geometry": {"coordinates":[-123.381683,43.234376],"type":"Point"}
}