{
  "type": "Feature",
  "properties": {
    "addr:full":"9115 NE Hoyt St Portland OR 97220",
    "addr:housenumber":"9115",
    "addr:postcode":"97220",
    "addr:street":"Ne Hoyt St",
    "iso:country":"US",
    "sg:address":"9115 NE Hoyt St",
    "sg:city":"Portland",
    "sg:classifiers":[
        {
            "category":"Organizations",
            "subcategory":"Religious Organization",
            "type":"Services"
        }
    ],
    "sg:phone":"+1 503 253 3103",
    "sg:postcode":"97220",
    "sg:province":"OR",
    "wof:name":"Lion of Judah Congregation",
    "wof:placetype":"venue"
},
  "geometry": {"coordinates":[-122.569497,45.527142],"type":"Point"}
}