{
  "type": "Feature",
  "properties": {
    "addr:full":"33 NW 9th Ave Portland OR 97209",
    "addr:housenumber":"33",
    "addr:postcode":"97209",
    "addr:street":"Nw 9Th Ave",
    "iso:country":"US",
    "sg:address":"33 NW 9th Ave",
    "sg:city":"Portland",
    "sg:phone":"+1 503 227 5882",
    "sg:postcode":"97209",
    "sg:province":"OR",
    "wof:name":"Candy",
    "wof:placetype":"venue"
},
  "geometry": {"coordinates":[-122.680086,45.52323],"type":"Point"}
}