{
  "type": "Feature",
  "properties": {
    "iso:country":"US",
    "sg:address":"394 Blair Blvd",
    "sg:city":"Eugene",
    "sg:classifiers":[
        {
            "category":"Bars & Pubs",
            "type":"Food & Drink"
        },
        {
            "category":"Restaurant",
            "type":"Food & Drink"
        }
    ],
    "sg:menulink":"http://www.allmenus.com/or/eugene-springfield/279936-tiny-tavern/menu/",
    "sg:phone":"+1 541 687 8383",
    "sg:postcode":"97402",
    "sg:province":"OR",
    "sg:tags":[
        "american"
    ],
    "wof:name":"Tiny Tavern",
    "wof:placetype":"venue"
},
  "geometry": {"coordinates":[-123.109408,44.055502],"type":"Point"}
}