{
  "type": "Feature",
  "properties": {
    "iso:country":"US",
    "sg:address":"605 W 3rd St",
    "sg:city":"Wallowa",
    "sg:classifiers":[
        {
            "category":"Retail",
            "subcategory":"Repair Shop",
            "type":"Services"
        }
    ],
    "sg:phone":"+1 541 886 0142",
    "sg:postcode":"97885",
    "sg:province":"OR",
    "sg:tags":[
        "electrical"
    ],
    "wof:name":"Blake Electronics",
    "wof:placetype":"venue"
},
  "geometry": {"coordinates":[-117.535847,45.571983],"type":"Point"}
}