{
  "type": "Feature",
  "properties": {
    "iso:country":"US",
    "sg:address":"425 NW Harrison Blvd",
    "sg:city":"Corvallis",
    "sg:classifiers":[
        {
            "category":"Food & Beverages",
            "subcategory":"Specialty",
            "type":"Retail Goods"
        }
    ],
    "sg:phone":"+1 541 738 7110",
    "sg:postcode":"97330",
    "sg:province":"OR",
    "sg:tags":[
        "shop",
        "bar",
        "coffee",
        "espresso"
    ],
    "wof:name":"Corvallis Dutch Bros",
    "wof:placetype":"venue"
},
  "geometry": {"coordinates":[-123.26072000000001,44.567631],"type":"Point"}
}