{
  "type": "Feature",
  "properties": {
    "iso:country":"US",
    "sg:address":"6420 SE 110th Dr",
    "sg:city":"Portland",
    "sg:classifiers":[
        {
            "category":"Professional",
            "type":"Services"
        }
    ],
    "sg:phone":"+1 503 760 1032",
    "sg:postcode":"97266",
    "sg:province":"OR",
    "wof:name":"Forbidden Body Art",
    "wof:placetype":"venue"
},
  "geometry": {"coordinates":[-122.549211,45.475577],"type":"Point"}
}