{
  "type": "Feature",
  "properties": {
    "addr:full":"1925 SE Jefferson St Milwaukie OR 97222",
    "addr:housenumber":"1925",
    "addr:postcode":"97222",
    "addr:street":"Se Jefferson St",
    "iso:country":"US",
    "sg:address":"1925 SE Jefferson St",
    "sg:city":"Milwaukie",
    "sg:classifiers":[
        {
            "category":"Personal",
            "subcategory":"Barber",
            "type":"Services"
        }
    ],
    "sg:phone":"+1 503 654 0330",
    "sg:postcode":"97222",
    "sg:province":"OR",
    "sg:tags":[
        "shop"
    ],
    "wof:name":"Barber Shop",
    "wof:placetype":"venue"
},
  "geometry": {"coordinates":[-122.641268,45.443306],"type":"Point"}
}