{
  "type": "Feature",
  "properties": {
    "iso:country":"US",
    "sg:address":"555 NW 9th St",
    "sg:city":"Ontario",
    "sg:classifiers":[
        {
            "category":"Real Estate",
            "subcategory":"Real Estate Operator",
            "type":"Services"
        }
    ],
    "sg:phone":"+1 541 889 7412",
    "sg:postcode":"97914",
    "sg:province":"OR",
    "sg:tags":[
        "building",
        "apartment"
    ],
    "wof:name":"Fair View Apartments",
    "wof:placetype":"venue"
},
  "geometry": {"coordinates":[-116.973156,44.033107],"type":"Point"}
}