{
  "type": "Feature",
  "properties": {
    "addr:full":"7136 SE 87th Ave Portland OR 97266",
    "addr:housenumber":"7136",
    "addr:postcode":"97266",
    "addr:street":"Se 87Th Ave",
    "iso:country":"US",
    "sg:address":"7136 SE 87th Ave",
    "sg:city":"Portland",
    "sg:classifiers":[
        {
            "category":"Professional",
            "type":"Services"
        },
        {
            "category":"Personal",
            "type":"Services"
        }
    ],
    "sg:phone":"+1 503 200 3054",
    "sg:postcode":"97266",
    "sg:province":"OR",
    "sg:tags":[
        "mover",
        "material",
        "moving",
        "services-labor"
    ],
    "sg:website":"http://www.searchmagnetlocal.com/Move_It_or_Lose_It_Moving_Company_Portland_Oregon-2574.html",
    "wof:name":"Move It or Lose It Moving Company Portland Oregon",
    "wof:placetype":"venue"
},
  "geometry": {"coordinates":[-122.573921,45.471312],"type":"Point"}
}