{
  "type": "Feature",
  "properties": {
    "iso:country":"US",
    "sg:address":"4416 SE Woodstock Blvd",
    "sg:city":"Portland",
    "sg:classifiers":[
        {
            "category":"Shopping",
            "subcategory":"Clothing, Apparel, & Fashions",
            "type":"Retail Goods"
        },
        {
            "category":"Shopping",
            "subcategory":"Baby Store",
            "type":"Retail Goods"
        },
        {
            "category":"Shopping",
            "subcategory":"Thrift Store",
            "type":"Retail Goods"
        },
        {
            "category":"Shopping",
            "subcategory":"Used Merchandise",
            "type":"Retail Goods"
        }
    ],
    "sg:phone":"+1 503 505 5045",
    "sg:postcode":"97206",
    "sg:province":"OR",
    "sg:tags":[
        "shop",
        "infant",
        "resale",
        "children's",
        "maternity",
        "wear",
        "clothes"
    ],
    "sg:website":"www.piccolinaresale.com",
    "wof:name":"Piccolina",
    "wof:placetype":"venue"
},
  "geometry": {"coordinates":[-122.617064,45.47894],"type":"Point"}
}