{
  "type": "Feature",
  "properties": {
    "addr:full":"51 S State St Lake Oswego OR 97034",
    "addr:housenumber":"51",
    "addr:postcode":"97034",
    "addr:street":"S State St",
    "iso:country":"US",
    "sg:address":"51 S State St",
    "sg:city":"Lake Oswego",
    "sg:classifiers":[
        {
            "category":"Restaurant",
            "type":"Food & Drink"
        }
    ],
    "sg:phone":"+1 503 635 5535",
    "sg:postcode":"97034",
    "sg:province":"OR",
    "sg:tags":[
        "eating"
    ],
    "wof:name":"Jamba Juice",
    "wof:placetype":"venue"
},
  "geometry": {"coordinates":[-122.66372800000001,45.415245],"type":"Point"}
}