{
  "type": "Feature",
  "properties": {
    "iso:country":"US",
    "sg:address":"5131 SE 40th Ave",
    "sg:city":"Portland",
    "sg:classifiers":[
        {
            "category":"Building & Trades",
            "subcategory":"Construction",
            "type":"Services"
        }
    ],
    "sg:phone":"+1 503 771 9281",
    "sg:postcode":"97202",
    "sg:province":"OR",
    "sg:tags":[
        "hanging",
        "contractor"
    ],
    "wof:name":"Robert Lake",
    "wof:placetype":"venue"
},
  "geometry": {"coordinates":[-122.621707,45.485578],"type":"Point"}
}