{
  "type": "Feature",
  "properties": {
    "addr:full":"86 Tanglewood Dr Lake Oswego OR 97035",
    "addr:housenumber":"86",
    "addr:postcode":"97035",
    "addr:street":"Tanglewood Dr",
    "iso:country":"US",
    "sg:address":"86 Tanglewood Dr",
    "sg:city":"Lake Oswego",
    "sg:classifiers":[
        {
            "category":"Freight",
            "type":"Transportation"
        }
    ],
    "sg:phone":"+1 503 675 0180",
    "sg:postcode":"97035",
    "sg:province":"OR",
    "sg:tags":[
        "trucking"
    ],
    "wof:name":"Mountain Coast Transport Inc",
    "wof:placetype":"venue"
},
  "geometry": {"coordinates":[-122.71129500000001,45.428529],"type":"Point"}
}