{
  "type": "Feature",
  "properties": {
    "addr:full":"122 1st Ave W Albany OR 97321",
    "addr:housenumber":"122",
    "addr:postcode":"97321",
    "addr:street":"1St Ave W",
    "iso:country":"US",
    "sg:address":"122 1st Ave W",
    "sg:city":"Albany",
    "sg:classifiers":[
        {
            "category":"Organizations",
            "subcategory":"Professional Association",
            "type":"Services"
        }
    ],
    "sg:phone":"+1 541 926 5451",
    "sg:postcode":"97321",
    "sg:province":"OR",
    "wof:name":"Albany Partnership-Housing",
    "wof:placetype":"venue"
},
  "geometry": {"coordinates":[-123.105187,44.637317],"type":"Point"}
}