{
  "type": "Feature",
  "properties": {
    "iso:country":"US",
    "sg:address":"23327 E Wildwood Ave",
    "sg:city":"Welches",
    "sg:classifiers":[
        {
            "category":"Retail",
            "subcategory":"Repair Shop",
            "type":"Services"
        }
    ],
    "sg:phone":"+1 503 622 6984",
    "sg:postcode":"97067",
    "sg:province":"OR",
    "wof:name":"Calvins Repair",
    "wof:placetype":"venue"
},
  "geometry": {"coordinates":[-121.9796,45.355004],"type":"Point"}
}