{
  "type": "Feature",
  "properties": {
    "addr:full":"11695 SW 66th Ave Portland OR 97223",
    "addr:housenumber":"11695",
    "addr:postcode":"97223",
    "addr:street":"Sw 66Th Ave",
    "iso:country":"US",
    "sg:address":"11695 SW 66th Ave",
    "sg:city":"Portland",
    "sg:classifiers":[
        {
            "category":"Banks & Credit Unions",
            "subcategory":"Bank",
            "type":"Services"
        }
    ],
    "sg:phone":"+1 503 726 1826",
    "sg:postcode":"97223",
    "sg:province":"OR",
    "wof:name":"State National Co",
    "wof:placetype":"venue"
},
  "geometry": {"coordinates":[-122.744694,45.436692],"type":"Point"}
}