{
  "type": "Feature",
  "properties": {
    "iso:country":"US",
    "sg:address":"1140 Main St",
    "sg:city":"Baker City",
    "sg:classifiers":[
        {
            "category":"Organizations",
            "subcategory":"Community Association",
            "type":"Services"
        }
    ],
    "sg:phone":"+1 541 523 9778",
    "sg:postcode":"97814",
    "sg:province":"OR",
    "wof:name":"Intl Assoc of Lions",
    "wof:placetype":"venue"
},
  "geometry": {"coordinates":[-117.829567,44.769941],"type":"Point"}
}