{
  "type": "Feature",
  "properties": {
    "iso:country":"US",
    "sg:address":"208 SE Vine Ln",
    "sg:city":"Bend",
    "sg:classifiers":[
        {
            "category":"Wholesale",
            "subcategory":"Non-durable Goods",
            "type":"Manufacturing & Wholesale Goods"
        }
    ],
    "sg:phone":"+1 541 389 0995",
    "sg:postcode":"97702",
    "sg:province":"OR",
    "sg:tags":[
        "advertising"
    ],
    "wof:name":"Cameron Productions",
    "wof:placetype":"venue"
},
  "geometry": {"coordinates":[-121.30354699999999,44.046471],"type":"Point"}
}