{
  "type": "Feature",
  "properties": {
    "iso:country":"US",
    "sg:address":"95702 Skyview Ranch Rd",
    "sg:city":"Gold Beach",
    "sg:classifiers":[
        {
            "category":"Farming",
            "subcategory":"Livestock Farm",
            "type":"Manufacturing & Wholesale Goods"
        }
    ],
    "sg:phone":"+1 541 247 7990",
    "sg:postcode":"97444",
    "sg:province":"OR",
    "sg:tags":[
        "animal",
        "general"
    ],
    "wof:name":"Skyview Ranch",
    "wof:placetype":"venue"
},
  "geometry": {"coordinates":[-124.37949,42.579632],"type":"Point"}
}