{
  "type": "Feature",
  "properties": {
    "iso:country":"US",
    "sg:address":"999 N 1st St",
    "sg:city":"Silverton",
    "sg:classifiers":[
        {
            "category":"Professional",
            "subcategory":"Business Services",
            "type":"Services"
        }
    ],
    "sg:phone":"+1 503 873 4409",
    "sg:postcode":"97381",
    "sg:province":"OR",
    "sg:tags":[
        "interior",
        "consultant",
        "design",
        "decorator"
    ],
    "wof:name":"Paint Rite",
    "wof:placetype":"venue"
},
  "geometry": {"coordinates":[-122.785111,45.011967],"type":"Point"}
}