{
  "type": "Feature",
  "properties": {
    "addr:full":"2347 SW Highway 97 Madras OR 97741",
    "addr:housenumber":"2347",
    "addr:postcode":"97741",
    "addr:street":"Sw Highway 97",
    "iso:country":"US",
    "sg:address":"2347 SW Highway 97",
    "sg:city":"Madras",
    "sg:classifiers":[
        {
            "category":"Wholesale",
            "subcategory":"Farm Supplies",
            "type":"Manufacturing & Wholesale Goods"
        },
        {
            "category":"Home & Garden",
            "subcategory":"Garden Supply",
            "type":"Retail Goods"
        },
        {
            "category":"Wholesale",
            "subcategory":"Machinery & Supplies",
            "type":"Manufacturing & Wholesale Goods"
        }
    ],
    "sg:phone":"+1 541 475 6116",
    "sg:postcode":"97741",
    "sg:province":"OR",
    "sg:tags":[
        "baling",
        "equipment",
        "lawn",
        "mower"
    ],
    "wof:name":"Floyd A. Boyd Co.",
    "wof:placetype":"venue"
},
  "geometry": {"coordinates":[-121.142128,44.601339],"type":"Point"}
}