{
  "type": "Feature",
  "properties": {
    "iso:country":"US",
    "sg:address":"2990 25th St SE",
    "sg:city":"Salem",
    "sg:classifiers":[
        {
            "category":"Retail",
            "subcategory":"Auto Rental",
            "type":"Services"
        }
    ],
    "sg:phone":"+1 503 362 0041",
    "sg:postcode":"97301",
    "sg:province":"OR",
    "sg:tags":[
        "passenger",
        "car"
    ],
    "wof:name":"Budget Rent-A-Car",
    "wof:placetype":"venue"
},
  "geometry": {"coordinates":[-123.010209,44.911251],"type":"Point"}
}