{
  "type": "Feature",
  "properties": {
    "iso:country":"US",
    "sg:address":"2816 SW Goodwin Ave",
    "sg:city":"Pendleton",
    "sg:classifiers":[
        {
            "category":"Personal",
            "type":"Services"
        }
    ],
    "sg:phone":"+1 541 278 0360",
    "sg:postcode":"97801",
    "sg:province":"OR",
    "wof:name":"Color 1 Associates",
    "wof:placetype":"venue"
},
  "geometry": {"coordinates":[-118.811611,45.662294],"type":"Point"}
}