{
  "type": "Feature",
  "properties": {
    "iso:country":"US",
    "sg:address":"220 Redwood Hwy",
    "sg:city":"Grants Pass",
    "sg:classifiers":[
        {
            "category":"Home & Garden",
            "subcategory":"Furniture",
            "type":"Retail Goods"
        }
    ],
    "sg:phone":"+1 541 476 7083",
    "sg:postcode":"97527",
    "sg:province":"OR",
    "sg:tags":[
        "antique"
    ],
    "wof:name":"Parker's Bargain House",
    "wof:placetype":"venue"
},
  "geometry": {"coordinates":[-123.33284999999999,42.425027],"type":"Point"}
}