{
  "type": "Feature",
  "properties": {
    "addr:full":"5235 Primrose Ln Klamath Falls OR 97601",
    "addr:housenumber":"5235",
    "addr:postcode":"97601",
    "addr:street":"Primrose Ln",
    "iso:country":"US",
    "sg:address":"5235 Primrose Ln",
    "sg:city":"Klamath Falls",
    "sg:classifiers":[
        {
            "category":"Building & Trades",
            "subcategory":"Construction",
            "type":"Services"
        }
    ],
    "sg:phone":"+1 541 884 1399",
    "sg:postcode":"97601",
    "sg:province":"OR",
    "sg:tags":[
        "concrete",
        "contractor"
    ],
    "wof:name":"Viking Concrete Cutting",
    "wof:placetype":"venue"
},
  "geometry": {"coordinates":[-121.82346200000001,42.19776],"type":"Point"}
}