{
  "type": "Feature",
  "properties": {
    "iso:country":"US",
    "sg:address":"2182 NE Edgewood St",
    "sg:city":"Bend",
    "sg:classifiers":[
        {
            "category":"Shopping",
            "subcategory":"Clothing, Apparel, & Fashions",
            "type":"Retail Goods"
        }
    ],
    "sg:phone":"+1 541 382 5001",
    "sg:postcode":"97701",
    "sg:province":"OR",
    "wof:name":"My Three Sons Ltd",
    "wof:placetype":"venue"
},
  "geometry": {"coordinates":[-121.28479400000001,44.070848],"type":"Point"}
}