{
  "type": "Feature",
  "properties": {
    "addr:full":"845 N Adair St Cornelius OR 97113",
    "addr:housenumber":"845",
    "addr:postcode":"97113",
    "addr:street":"N Adair St",
    "iso:country":"US",
    "sg:address":"845 N Adair St",
    "sg:city":"Cornelius",
    "sg:classifiers":[
        {
            "category":"Autos & Motor Vehicles",
            "subcategory":"Fuel & Gas Station",
            "type":"Retail Goods"
        }
    ],
    "sg:phone":"+1 503 992 8900",
    "sg:postcode":"97113",
    "sg:province":"OR",
    "sg:tags":[
        "oil"
    ],
    "wof:name":"EATA LLC",
    "wof:placetype":"venue"
},
  "geometry": {"coordinates":[-123.061328,45.520853],"type":"Point"}
}