{
  "type": "Feature",
  "properties": {
    "iso:country":"US",
    "sg:address":"3114 NE 45th Ave",
    "sg:city":"Portland",
    "sg:classifiers":[
        {
            "category":"Professional",
            "subcategory":"Research",
            "type":"Services"
        }
    ],
    "sg:phone":"+1 503 493 9681",
    "sg:postcode":"97213",
    "sg:province":"OR",
    "sg:tags":[
        "development",
        "laboratory",
        "commercial",
        "physical"
    ],
    "wof:name":"Renewable Products Dev Lab",
    "wof:placetype":"venue"
},
  "geometry": {"coordinates":[-122.616665,45.546851],"type":"Point"}
}