{
  "type": "Feature",
  "properties": {
    "addr:full":"2036 SE Clatsop St Portland OR 97202",
    "addr:housenumber":"2036",
    "addr:postcode":"97202",
    "addr:street":"Se Clatsop St",
    "iso:country":"US",
    "sg:address":"2036 SE Clatsop St",
    "sg:city":"Portland",
    "sg:classifiers":[
        {
            "category":"Real Estate",
            "subcategory":"Real Estate Services",
            "type":"Services"
        },
        {
            "category":"Real Estate",
            "subcategory":"Real Estate Agent",
            "type":"Services"
        }
    ],
    "sg:phone":"+1 503 239 8882",
    "sg:postcode":"97202",
    "sg:province":"OR",
    "sg:tags":[
        "buyer",
        "broker"
    ],
    "wof:name":"Golden Rule Real Estate",
    "wof:placetype":"venue"
},
  "geometry": {"coordinates":[-122.643674,45.460756],"type":"Point"}
}