{
  "type": "Feature",
  "properties": {
    "iso:country":"US",
    "sg:address":"7070 SE 16th Avenue",
    "sg:city":"Portland",
    "sg:classifiers":[
        {
            "category":"Sports & Exercise",
            "subcategory":"Gym",
            "type":"Entertainment"
        }
    ],
    "sg:phone":"+1 503 232 9642",
    "sg:postcode":"97202",
    "sg:province":"OR",
    "sg:tags":[
        "instruction",
        "yoga"
    ],
    "wof:name":"Bikram's Yoga College of India",
    "wof:placetype":"venue"
},
  "geometry": {"coordinates":[-122.650125,45.473151],"type":"Point"}
}