{
  "type": "Feature",
  "properties": {
    "iso:country":"US",
    "sg:address":"16580 SW 85th Ave",
    "sg:city":"Portland",
    "sg:classifiers":[
        {
            "category":"Government",
            "subcategory":"Office",
            "type":"Public Place"
        }
    ],
    "sg:phone":"+1 503 684 4600",
    "sg:postcode":"97224",
    "sg:province":"OR",
    "sg:tags":[
        "parish",
        "government-county"
    ],
    "wof:name":"Washington County Government Of Clean Water Se",
    "wof:placetype":"venue"
},
  "geometry": {"coordinates":[-122.764549,45.400128],"type":"Point"}
}