{
  "type": "Feature",
  "properties": {
    "addr:full":"3011 SW Evelyn St Portland OR 97219",
    "addr:housenumber":"3011",
    "addr:postcode":"97219",
    "addr:street":"Sw Evelyn St",
    "iso:country":"US",
    "sg:address":"3011 SW Evelyn St",
    "sg:city":"Portland",
    "sg:classifiers":[
        {
            "category":"Building & Trades",
            "subcategory":"Cleaning & Sanitation",
            "type":"Services"
        },
        {
            "category":"Retail",
            "subcategory":"Repair Shop",
            "type":"Services"
        },
        {
            "category":"Retail",
            "subcategory":"Laundry & Dry Cleaning",
            "type":"Services"
        },
        {
            "category":"Home & Garden",
            "subcategory":"Carpets & Floor Coverings",
            "type":"Retail Goods"
        }
    ],
    "sg:phone":"+1 503 245 5277",
    "sg:postcode":"97219",
    "sg:province":"OR",
    "sg:tags":[
        "cleaner",
        "upholstery",
        "upholsterer",
        "refinish",
        "material",
        "rug",
        "furniture"
    ],
    "sg:website":"www.neatnixcarpetcare.com",
    "wof:name":"Neatnix Carpet Care",
    "wof:placetype":"venue"
},
  "geometry": {"coordinates":[-122.707757,45.454011],"type":"Point"}
}