{
  "type": "Feature",
  "properties": {
    "iso:country":"US",
    "sg:address":"232 SE Oak St",
    "sg:city":"Portland",
    "sg:classifiers":[
        {
            "category":"Insurance",
            "subcategory":"Insurance Agent",
            "type":"Services"
        }
    ],
    "sg:phone":"+1 503 233 9588",
    "sg:postcode":"97214",
    "sg:province":"OR",
    "wof:name":"McKenzie Insurance Agency",
    "wof:placetype":"venue"
},
  "geometry": {"coordinates":[-122.66296,45.520012],"type":"Point"}
}