{
  "type": "Feature",
  "properties": {
    "iso:country":"US",
    "sg:address":"16165 SW Regatta Ln Ste 800",
    "sg:city":"Beaverton",
    "sg:classifiers":[
        {
            "category":"Health Services",
            "subcategory":"Chiropractor",
            "type":"Services"
        }
    ],
    "sg:phone":"+1 503 439 9494",
    "sg:postcode":"97006",
    "sg:province":"OR",
    "sg:website":"www.walkerroadchiro.com",
    "wof:name":"Walker Road Chiropractic PC",
    "wof:placetype":"venue"
},
  "geometry": {"coordinates":[-122.843002,45.517101],"type":"Point"}
}