{
  "type": "Feature",
  "properties": {
    "iso:country":"US",
    "sg:address":"602 SE Byers Ave",
    "sg:city":"Pendleton",
    "sg:classifiers":[
        {
            "category":"Health Services",
            "subcategory":"Doctor",
            "type":"Services"
        }
    ],
    "sg:phone":"+1 541 966 8551",
    "sg:postcode":"97801",
    "sg:province":"OR",
    "sg:tags":[
        "physician",
        "family",
        "practice",
        "surgeons",
        "medicine",
        "surgeon"
    ],
    "wof:name":"Eastern Oregon Dermatology Clinic",
    "wof:placetype":"venue"
},
  "geometry": {"coordinates":[-118.781657,45.675141],"type":"Point"}
}