{
  "type": "Feature",
  "properties": {
    "iso:country":"US",
    "sg:address":"852 W Stewart Ave",
    "sg:city":"Medford",
    "sg:classifiers":[
        {
            "category":"Wholesale",
            "subcategory":"Non-durable Goods",
            "type":"Manufacturing & Wholesale Goods"
        }
    ],
    "sg:phone":"+1 541 261 3047",
    "sg:postcode":"97501",
    "sg:province":"OR",
    "wof:name":"Early Bird Distribution",
    "wof:placetype":"venue"
},
  "geometry": {"coordinates":[-122.880436,42.312955],"type":"Point"}
}