{
  "type": "Feature",
  "properties": {
    "iso:country":"US",
    "sg:address":"17010 SW Weir Rd",
    "sg:city":"Beaverton",
    "sg:classifiers":[
        {
            "category":"Real Estate",
            "subcategory":"Real Estate Services",
            "type":"Services"
        }
    ],
    "sg:phone":"+1 503 706 3595",
    "sg:postcode":"97007",
    "sg:province":"OR",
    "sg:tags":[
        "management"
    ],
    "wof:name":"Clay",
    "wof:placetype":"venue"
},
  "geometry": {"coordinates":[-122.85161600000001,45.447688],"type":"Point"}
}