{
  "type": "Feature",
  "properties": {
    "iso:country":"US",
    "sg:address":"2082 W Main St",
    "sg:city":"Medford",
    "sg:classifiers":[
        {
            "category":"Professional",
            "subcategory":"Detective & Security Services",
            "type":"Services"
        }
    ],
    "sg:phone":"+1 541 776 7376",
    "sg:postcode":"97501",
    "sg:province":"OR",
    "sg:tags":[
        "system"
    ],
    "wof:name":"Eye Spy Security Systems Inc",
    "wof:placetype":"venue"
},
  "geometry": {"coordinates":[-122.895859,42.323656],"type":"Point"}
}