{
  "type": "Feature",
  "properties": {
    "addr:full":"9921 SE Stark St Portland OR 97216",
    "addr:housenumber":"9921",
    "addr:postcode":"97216",
    "addr:street":"Se Stark St",
    "iso:country":"US",
    "sg:address":"9921 SE Stark St",
    "sg:city":"Portland",
    "sg:classifiers":[
        {
            "category":"Shopping",
            "subcategory":"Bicycles & Sporting Goods",
            "type":"Retail Goods"
        }
    ],
    "sg:phone":"+1 503 251 0065",
    "sg:postcode":"97216",
    "sg:province":"OR",
    "wof:name":"Adrenaline Sportz Inc",
    "wof:placetype":"venue"
},
  "geometry": {"coordinates":[-122.560585,45.519122],"type":"Point"}
}