{
  "type": "Feature",
  "properties": {
    "iso:country":"US",
    "sg:address":"1260 SW 3rd St",
    "sg:city":"Corvallis",
    "sg:phone":"+1 541 752 1555",
    "sg:postcode":"97333",
    "sg:province":"OR",
    "sg:tags":[
        "oil"
    ],
    "sg:website":"www.obersonoil.com",
    "wof:name":"Fred Price Fuel Oil",
    "wof:placetype":"venue"
},
  "geometry": {"coordinates":[-123.265145,44.552622],"type":"Point"}
}