{
  "type": "Feature",
  "properties": {
    "iso:country":"US",
    "sg:address":"2104 NE 45th Ave",
    "sg:city":"Portland",
    "sg:classifiers":[
        {
            "category":"Real Estate",
            "subcategory":"Architect",
            "type":"Services"
        }
    ],
    "sg:phone":"+1 503 281 3313",
    "sg:postcode":"97213",
    "sg:province":"OR",
    "wof:name":"John Hasenberg Architects",
    "wof:placetype":"venue"
},
  "geometry": {"coordinates":[-122.616856,45.539009],"type":"Point"}
}