{
  "type": "Feature",
  "properties": {
    "addr:full":"915 NW Witham Dr Corvallis OR 97330",
    "addr:housenumber":"915",
    "addr:postcode":"97330",
    "addr:street":"Nw Witham Dr",
    "iso:country":"US",
    "sg:address":"915 NW Witham Dr",
    "sg:city":"Corvallis",
    "sg:classifiers":[
        {
            "category":"Professional",
            "type":"Services"
        }
    ],
    "sg:phone":"+1 541 753 6873",
    "sg:postcode":"97330",
    "sg:province":"OR",
    "wof:name":"Elias Sabry",
    "wof:placetype":"venue"
},
  "geometry": {"coordinates":[-123.292058,44.575726],"type":"Point"}
}