{
  "type": "Feature",
  "properties": {
    "addr:full":"412 NW Couch St Portland OR 97209",
    "addr:housenumber":"412",
    "addr:postcode":"97209",
    "addr:street":"Nw Couch St",
    "iso:country":"US",
    "sg:address":"412 NW Couch St",
    "sg:city":"Portland",
    "sg:classifiers":[
        {
            "category":"Shopping",
            "subcategory":"Clothing, Apparel, & Fashions",
            "type":"Retail Goods"
        },
        {
            "category":"Home & Garden",
            "subcategory":"Home Furnishings",
            "type":"Retail Goods"
        }
    ],
    "sg:phone":"+1 503 575 9455",
    "sg:postcode":"97209",
    "sg:province":"OR",
    "sg:tags":[
        "decor",
        "men's",
        "clothing"
    ],
    "sg:website":"www.sevenplanet.com",
    "wof:name":"Seven Planet",
    "wof:placetype":"venue"
},
  "geometry": {"coordinates":[-122.674922,45.523728],"type":"Point"}
}