{
  "type": "Feature",
  "properties": {
    "iso:country":"US",
    "sg:address":"4234 S 6th St",
    "sg:city":"Klamath Falls",
    "sg:classifiers":[
        {
            "category":"Wholesale",
            "subcategory":"Hardware",
            "type":"Manufacturing & Wholesale Goods"
        }
    ],
    "sg:phone":"+1 541 850 8686",
    "sg:postcode":"97603",
    "sg:province":"OR",
    "sg:tags":[
        "water",
        "treatment"
    ],
    "wof:name":"Aqua Center",
    "wof:placetype":"venue"
},
  "geometry": {"coordinates":[-121.736444,42.206412],"type":"Point"}
}