{
  "type": "Feature",
  "properties": {
    "iso:country":"US",
    "sg:address":"8626 N Van Houten Ave",
    "sg:city":"Portland",
    "sg:classifiers":[
        {
            "category":"Bars & Pubs",
            "type":"Food & Drink"
        }
    ],
    "sg:phone":"+1 503 230 8535",
    "sg:postcode":"97203",
    "sg:province":"OR",
    "sg:tags":[
        "drinking"
    ],
    "wof:name":"Morrison Street Pub Inc",
    "wof:placetype":"venue"
},
  "geometry": {"coordinates":[-122.72352100000001,45.585499],"type":"Point"}
}