{
  "type": "Feature",
  "properties": {
    "iso:country":"US",
    "sg:address":"1401 Market St",
    "sg:city":"Springfield",
    "sg:classifiers":[
        {
            "category":"Health Services",
            "subcategory":"Hospital",
            "type":"Services"
        }
    ],
    "sg:phone":"+1 541 746 4041",
    "sg:postcode":"97477",
    "sg:province":"OR",
    "sg:tags":[
        "medical",
        "specialty"
    ],
    "wof:name":"Aces Counseling Center",
    "wof:placetype":"venue"
},
  "geometry": {"coordinates":[-123.003383,44.058001],"type":"Point"}
}