{
  "type": "Feature",
  "properties": {
    "iso:country":"US",
    "sg:address":"41225 SW Edna Ln",
    "sg:city":"Gaston",
    "sg:phone":"+1 503 985 0352",
    "sg:postcode":"97119",
    "sg:province":"OR",
    "sg:tags":[
        "farm"
    ],
    "wof:name":"Gales Peak Angus Ran",
    "wof:placetype":"venue"
},
  "geometry": {"coordinates":[-123.10199900000001,45.43246],"type":"Point"}
}