{
  "type": "Feature",
  "properties": {
    "iso:country":"US",
    "sg:address":"7799 SW Montclair Dr",
    "sg:city":"Portland",
    "sg:classifiers":[
        {
            "category":"Real Estate",
            "subcategory":"Real Estate Agent",
            "type":"Services"
        }
    ],
    "sg:phone":"+1 503 292 2238",
    "sg:postcode":"97225",
    "sg:province":"OR",
    "wof:name":"Hollywood Realty Inc",
    "wof:placetype":"venue"
},
  "geometry": {"coordinates":[-122.756811,45.482203],"type":"Point"}
}