{
  "type": "Feature",
  "properties": {
    "iso:country":"US",
    "sg:address":"1510 Division St",
    "sg:city":"Oregon City",
    "sg:classifiers":[
        {
            "category":"Health Services",
            "subcategory":"Doctor",
            "type":"Services"
        }
    ],
    "sg:phone":"+1 503 655 9868",
    "sg:postcode":"97045",
    "sg:province":"OR",
    "sg:tags":[
        "physician",
        "surgeon"
    ],
    "wof:name":"Oregon Neurology",
    "wof:placetype":"venue"
},
  "geometry": {"coordinates":[-122.588276,45.356733],"type":"Point"}
}