{
  "type": "Feature",
  "properties": {
    "addr:full":"2048 NW Stucki Ave Hillsboro OR 97124",
    "addr:housenumber":"2048",
    "addr:postcode":"97124",
    "addr:street":"Nw Stucki Ave",
    "iso:country":"US",
    "sg:address":"2048 NW Stucki Ave",
    "sg:city":"Hillsboro",
    "sg:classifiers":[
        {
            "category":"Restaurant",
            "type":"Food & Drink"
        }
    ],
    "sg:phone":"+1 503 533 0275",
    "sg:postcode":"97124",
    "sg:province":"OR",
    "sg:tags":[
        "mexican"
    ],
    "sg:website":"www.chipotle.com",
    "wof:name":"Chipotle",
    "wof:placetype":"venue"
},
  "geometry": {"coordinates":[-122.876999,45.5355],"type":"Point"}
}