{
  "type": "Feature",
  "properties": {
    "iso:country":"US",
    "sg:address":"13440 SW Tapadera St",
    "sg:city":"Beaverton",
    "sg:classifiers":[
        {
            "category":"Real Estate",
            "subcategory":"Surveying",
            "type":"Services"
        }
    ],
    "sg:phone":"+1 503 524 9991",
    "sg:postcode":"97008",
    "sg:province":"OR",
    "wof:name":"Integrated Images",
    "wof:placetype":"venue"
},
  "geometry": {"coordinates":[-122.81506,45.456593],"type":"Point"}
}