{
  "type": "Feature",
  "properties": {
    "iso:country":"US",
    "sg:address":"14841 SW Tualatin Sherwood Rd",
    "sg:city":"Sherwood",
    "sg:classifiers":[
        {
            "category":"Retail",
            "subcategory":"Auto Repair",
            "type":"Services"
        }
    ],
    "sg:phone":"+1 503 925 1441",
    "sg:postcode":"97140",
    "sg:province":"OR",
    "sg:tags":[
        "automobile",
        "restoration",
        "classic"
    ],
    "wof:name":"Corvette Specialties Inc",
    "wof:placetype":"venue"
},
  "geometry": {"coordinates":[-122.829671,45.367768],"type":"Point"}
}