{
  "type": "Feature",
  "properties": {
    "iso:country":"US",
    "sg:address":"1161 US Hwy 101",
    "sg:city":"Florence",
    "sg:classifiers":[
        {
            "category":"Bars & Pubs",
            "type":"Food & Drink"
        }
    ],
    "sg:phone":"+1 541 997 1027",
    "sg:postcode":"97439",
    "sg:province":"OR",
    "wof:name":"Seagull Tavern",
    "wof:placetype":"venue"
},
  "geometry": {"coordinates":[-124.10250000000001,43.975622],"type":"Point"}
}