{
  "type": "Feature",
  "properties": {
    "addr:full":"3327 SE 50th Ave Portland OR 97206",
    "addr:housenumber":"3327",
    "addr:postcode":"97206",
    "addr:street":"Se 50Th Ave",
    "iso:country":"US",
    "sg:address":"3327 SE 50th Ave",
    "sg:city":"Portland",
    "sg:classifiers":[
        {
            "category":"Real Estate",
            "subcategory":"Real Estate Agent",
            "type":"Services"
        }
    ],
    "sg:phone":"+1 503 775 6725",
    "sg:postcode":"97206",
    "sg:province":"OR",
    "sg:tags":[
        "broker",
        "mortgage"
    ],
    "wof:name":"Fairfield Financial",
    "wof:placetype":"venue"
},
  "geometry": {"coordinates":[-122.61142700000001,45.498412],"type":"Point"}
}