{
  "type": "Feature",
  "properties": {
    "addr:full":"5691 SE International Way Milwaukie OR 97222",
    "addr:housenumber":"5691",
    "addr:postcode":"97222",
    "addr:street":"Se International Way",
    "iso:country":"US",
    "sg:address":"5691 SE International Way",
    "sg:city":"Milwaukie",
    "sg:classifiers":[
        {
            "category":"Wholesale",
            "subcategory":"Machinery & Supplies",
            "type":"Manufacturing & Wholesale Goods"
        }
    ],
    "sg:phone":"+1 503 653 3935",
    "sg:postcode":"97222",
    "sg:province":"OR",
    "sg:tags":[
        "pump"
    ],
    "wof:name":"Heiden Industrial Pumps",
    "wof:placetype":"venue"
},
  "geometry": {"coordinates":[-122.604512,45.431021],"type":"Point"}
}