{
  "type": "Feature",
  "properties": {
    "iso:country":"US",
    "sg:address":"431 Patterson Bridge Rd",
    "sg:city":"John Day",
    "sg:classifiers":[
        {
            "category":"Recreation",
            "type":"Entertainment"
        }
    ],
    "sg:phone":"+1 541 575 0721",
    "sg:postcode":"97845",
    "sg:province":"OR",
    "sg:tags":[
        "parks"
    ],
    "wof:name":"National Park Svc",
    "wof:placetype":"venue"
},
  "geometry": {"coordinates":[-118.97101499999999,44.423967],"type":"Point"}
}