{
  "type": "Feature",
  "properties": {
    "addr:full":"156 SW Oak St Dallas OR 97338",
    "addr:housenumber":"156",
    "addr:postcode":"97338",
    "addr:street":"Sw Oak St",
    "iso:country":"US",
    "sg:address":"156 SW Oak St",
    "sg:city":"Dallas",
    "sg:classifiers":[
        {
            "category":"Insurance",
            "subcategory":"Insurance Agent",
            "type":"Services"
        }
    ],
    "sg:phone":"+1 503 831 0134",
    "sg:postcode":"97338",
    "sg:province":"OR",
    "wof:name":"Farmers Insurance Group",
    "wof:placetype":"venue"
},
  "geometry": {"coordinates":[-123.31773099999999,44.92265],"type":"Point"}
}