{
  "type": "Feature",
  "properties": {
    "iso:country":"US",
    "sg:address":"1020 SW Taylor St Ste 820",
    "sg:city":"Portland",
    "sg:classifiers":[
        {
            "category":"Health Services",
            "subcategory":"Health Practitioner",
            "type":"Services"
        }
    ],
    "sg:phone":"+1 503 224 0114",
    "sg:postcode":"97205",
    "sg:province":"OR",
    "sg:tags":[
        "psychotherapist"
    ],
    "wof:name":"Brian H Farr Ma Counselor",
    "wof:placetype":"venue"
},
  "geometry": {"coordinates":[-122.683055,45.518742],"type":"Point"}
}