{
  "type": "Feature",
  "properties": {
    "iso:country":"US",
    "sg:address":"17527 Elk Creek Rd",
    "sg:city":"Trail",
    "sg:classifiers":[
        {
            "category":"Building & Trades",
            "subcategory":"Construction",
            "type":"Services"
        }
    ],
    "sg:phone":"+1 541 878 4328",
    "sg:postcode":"97541",
    "sg:province":"OR",
    "wof:name":"Sugar Kat Inc",
    "wof:placetype":"venue"
},
  "geometry": {"coordinates":[-122.60038900000001,42.772206],"type":"Point"}
}