{
  "type": "Feature",
  "properties": {
    "iso:country":"US",
    "sg:address":"4515 SW Corbett Avenue",
    "sg:city":"Portland",
    "sg:classifiers":[
        {
            "category":"Health Services",
            "subcategory":"Chiropractor",
            "type":"Services"
        }
    ],
    "sg:phone":"+1 503 224 5464",
    "sg:postcode":"97239",
    "sg:province":"OR",
    "wof:name":"King Valerie Bs DC",
    "wof:placetype":"venue"
},
  "geometry": {"coordinates":[-122.67625700000001,45.490779],"type":"Point"}
}