{
  "type": "Feature",
  "properties": {
    "iso:country":"US",
    "sg:address":"88680 McVay Hwy",
    "sg:city":"Eugene",
    "sg:classifiers":[
        {
            "category":"Restaurant",
            "type":"Food & Drink"
        }
    ],
    "sg:phone":"+1 541 746 9591",
    "sg:postcode":"97405",
    "sg:province":"OR",
    "sg:tags":[
        "eating"
    ],
    "wof:name":"On Go Espresso",
    "wof:placetype":"venue"
},
  "geometry": {"coordinates":[-123.025462,44.017484],"type":"Point"}
}