{
  "type": "Feature",
  "properties": {
    "addr:full":"7340 Bewley Creek Rd Tillamook OR 97141",
    "addr:housenumber":"7340",
    "addr:postcode":"97141",
    "addr:street":"Bewley Creek Rd",
    "iso:country":"US",
    "sg:address":"7340 Bewley Creek Rd",
    "sg:city":"Tillamook",
    "sg:classifiers":[
        {
            "category":"Manufacturing",
            "subcategory":"Lumber",
            "type":"Manufacturing & Wholesale Goods"
        }
    ],
    "sg:phone":"+1 503 842 5901",
    "sg:postcode":"97141",
    "sg:province":"OR",
    "sg:tags":[
        "company",
        "logging"
    ],
    "wof:name":"Fallon Logging Co Inc",
    "wof:placetype":"venue"
},
  "geometry": {"coordinates":[-123.824652,45.40351],"type":"Point"}
}