{
  "type": "Feature",
  "properties": {
    "iso:country":"US",
    "sg:address":"17 SW Frazer Ave",
    "sg:city":"Pendleton",
    "sg:classifiers":[
        {
            "category":"Professional",
            "subcategory":"Detective & Security Services",
            "type":"Services"
        },
        {
            "category":"Insurance",
            "subcategory":"Insurance Agent",
            "type":"Services"
        }
    ],
    "sg:phone":"+1 541 276 8000",
    "sg:postcode":"97801",
    "sg:province":"OR",
    "sg:tags":[
        "car",
        "adjuster"
    ],
    "wof:name":"P AC Adjusting & Investigative",
    "wof:placetype":"venue"
},
  "geometry": {"coordinates":[-118.785961,45.669982],"type":"Point"}
}