{
  "type": "Feature",
  "properties": {
    "iso:country":"US",
    "sg:address":"488 SE Floed Ave",
    "sg:city":"Roseburg",
    "sg:classifiers":[
        {
            "category":"Shopping",
            "subcategory":"Gifts & Souvenirs",
            "type":"Retail Goods"
        }
    ],
    "sg:phone":"+1 541 673 9748",
    "sg:postcode":"97470",
    "sg:province":"OR",
    "sg:tags":[
        "shop"
    ],
    "wof:name":"Gifts By Jim",
    "wof:placetype":"venue"
},
  "geometry": {"coordinates":[-123.35124,43.205745],"type":"Point"}
}