{
  "type": "Feature",
  "properties": {
    "iso:country":"US",
    "sg:address":"550 S Pacific Hwy",
    "sg:city":"Talent",
    "sg:classifiers":[
        {
            "category":"Personal",
            "subcategory":"Beauty Salon",
            "type":"Services"
        }
    ],
    "sg:phone":"+1 541 535 7794",
    "sg:postcode":"97540",
    "sg:province":"OR",
    "sg:tags":[
        "shop"
    ],
    "wof:name":"Oregon Institute Aesthetics",
    "wof:placetype":"venue"
},
  "geometry": {"coordinates":[-122.775093,42.240232],"type":"Point"}
}