{
  "type": "Feature",
  "properties": {
    "addr:full":"15140 SE 82nd Dr Clackamas OR 97015",
    "addr:postcode":"15140;97015",
    "addr:street":"Se 82Nd Dr",
    "iso:country":"US",
    "sg:address":"15140 SE 82nd Dr",
    "sg:city":"Clackamas",
    "sg:classifiers":[
        {
            "category":"Local Transit",
            "type":"Transportation"
        }
    ],
    "sg:phone":"+1 503 742 1723",
    "sg:postcode":"97015",
    "sg:province":"OR",
    "sg:tags":[
        "ambulance"
    ],
    "wof:name":"Noble Ambulance",
    "wof:placetype":"venue"
},
  "geometry": {"coordinates":[-122.568489,45.413959],"type":"Point"}
}