{
  "type": "Feature",
  "properties": {
    "addr:full":"20550 Murphy Rd Bend OR 97702",
    "addr:housenumber":"20550",
    "addr:postcode":"97702",
    "addr:street":"Murphy Rd",
    "iso:country":"US",
    "sg:address":"20550 Murphy Rd",
    "sg:city":"Bend",
    "sg:classifiers":[
        {
            "category":"Social Services",
            "subcategory":"Child Care",
            "type":"Services"
        }
    ],
    "sg:phone":"+1 541 388 1391",
    "sg:postcode":"97702",
    "sg:province":"OR",
    "sg:tags":[
        "day"
    ],
    "wof:name":"Kids Inc",
    "wof:placetype":"venue"
},
  "geometry": {"coordinates":[-121.294712,44.019014],"type":"Point"}
}