{
  "type": "Feature",
  "properties": {
    "iso:country":"US",
    "sg:address":"2475 NW Vaughn St",
    "sg:city":"Portland",
    "sg:classifiers":[
        {
            "category":"Manufacturing",
            "subcategory":"Metals",
            "type":"Manufacturing & Wholesale Goods"
        },
        {
            "category":"Manufacturing",
            "subcategory":"Building Materials",
            "type":"Manufacturing & Wholesale Goods"
        }
    ],
    "sg:phone":"+1 716 681 4200",
    "sg:postcode":"97210",
    "sg:province":"OR",
    "sg:tags":[
        "product",
        "aluminum"
    ],
    "wof:name":"Samuel Specialty Metals Inc.",
    "wof:placetype":"venue"
},
  "geometry": {"coordinates":[-122.70236199999999,45.536829],"type":"Point"}
}