{
  "type": "Feature",
  "properties": {
    "iso:country":"US",
    "sg:address":"88922 Fir Butte Rd",
    "sg:city":"Eugene",
    "sg:classifiers":[
        {
            "category":"Building & Trades",
            "subcategory":"Construction",
            "type":"Services"
        }
    ],
    "sg:phone":"+1 541 688 8333",
    "sg:postcode":"97402",
    "sg:province":"OR",
    "sg:tags":[
        "house",
        "builder",
        "operative"
    ],
    "wof:name":"C M Cogswell Construction Co",
    "wof:placetype":"venue"
},
  "geometry": {"coordinates":[-123.23470399999999,44.078696],"type":"Point"}
}