{
  "type": "Feature",
  "properties": {
    "iso:country":"US",
    "sg:address":"1940 Cavitt Creek Rd",
    "sg:city":"Glide",
    "sg:classifiers":[
        {
            "category":"Building & Trades",
            "subcategory":"Construction",
            "type":"Services"
        }
    ],
    "sg:phone":"+1 541 496 0362",
    "sg:postcode":"97443",
    "sg:province":"OR",
    "sg:tags":[
        "house"
    ],
    "wof:name":"Schenider Built",
    "wof:placetype":"venue"
},
  "geometry": {"coordinates":[-123.018775,43.223071],"type":"Point"}
}