{
  "type": "Feature",
  "properties": {
    "addr:full":"2121 SW Broadway Ste 130 Portland OR 97201",
    "addr:housenumber":"2121",
    "addr:postcode":"97201",
    "addr:street":"Sw Broadway Ste 130",
    "iso:country":"US",
    "sg:address":"2121 SW Broadway Ste 130",
    "sg:city":"Portland",
    "sg:classifiers":[
        {
            "category":"Professional",
            "subcategory":"Lawyer & Legal Services",
            "type":"Services"
        }
    ],
    "sg:phone":"+1 503 223 1708",
    "sg:postcode":"97201",
    "sg:province":"OR",
    "sg:website":"www.mcvealw.com",
    "wof:name":"Gibbs McVea Llp",
    "wof:placetype":"venue"
},
  "geometry": {"coordinates":[-122.685667,45.50769],"type":"Point"}
}