{
  "type": "Feature",
  "properties": {
    "iso:country":"US",
    "sg:address":"1565 S 4th St",
    "sg:city":"Cottage Grove",
    "sg:classifiers":[
        {
            "category":"Social Services",
            "subcategory":"Child Care",
            "type":"Services"
        }
    ],
    "sg:phone":"+1 541 942 5565",
    "sg:postcode":"97424",
    "sg:province":"OR",
    "sg:tags":[
        "day"
    ],
    "wof:name":"Head Start of Lane County",
    "wof:placetype":"venue"
},
  "geometry": {"coordinates":[-123.064454,43.783438],"type":"Point"}
}