{
  "type": "Feature",
  "properties": {
    "addr:full":"3682 SW 37th Ct Pendleton OR 97801",
    "addr:housenumber":"3682",
    "addr:postcode":"97801",
    "addr:street":"Sw 37Th Ct",
    "iso:country":"US",
    "sg:address":"3682 SW 37th Ct",
    "sg:city":"Pendleton",
    "sg:classifiers":[
        {
            "category":"Retail",
            "subcategory":"Animal Services",
            "type":"Services"
        }
    ],
    "sg:phone":"+1 541 278 0708",
    "sg:postcode":"97801",
    "sg:province":"OR",
    "sg:tags":[
        "pet",
        "boarding",
        "sitting"
    ],
    "wof:name":"Paws & Claws",
    "wof:placetype":"venue"
},
  "geometry": {"coordinates":[-118.820438,45.651328],"type":"Point"}
}