{
  "type": "Feature",
  "properties": {
    "addr:full":"231 N Hemlock St Cannon Beach OR 97110",
    "addr:housenumber":"231",
    "addr:postcode":"97110",
    "addr:street":"N Hemlock St",
    "iso:country":"US",
    "sg:address":"231 N Hemlock St",
    "sg:city":"Cannon Beach",
    "sg:classifiers":[
        {
            "category":"Personal",
            "subcategory":"Nail Salon",
            "type":"Services"
        }
    ],
    "sg:phone":"+1 503 436 0431",
    "sg:postcode":"97110",
    "sg:province":"OR",
    "wof:name":"Panache",
    "wof:placetype":"venue"
},
  "geometry": {"coordinates":[-123.960729,45.89858],"type":"Point"}
}