{
  "type": "Feature",
  "properties": {
    "addr:full":"1586 S Redwood St Canby OR 97013",
    "addr:housenumber":"1586",
    "addr:postcode":"97013",
    "addr:street":"S Redwood St",
    "iso:country":"US",
    "sg:address":"1586 S Redwood St",
    "sg:city":"Canby",
    "sg:classifiers":[
        {
            "category":"Real Estate",
            "subcategory":"Real Estate Agent",
            "type":"Services"
        }
    ],
    "sg:phone":"+1 503 263 2995",
    "sg:postcode":"97013",
    "sg:province":"OR",
    "wof:name":"Renaissance Development Co",
    "wof:placetype":"venue"
},
  "geometry": {"coordinates":[-122.676734,45.249429],"type":"Point"}
}