{
  "type": "Feature",
  "properties": {
    "iso:country":"US",
    "sg:address":"2615 SW Morris Ave",
    "sg:city":"Corvallis",
    "sg:classifiers":[
        {
            "category":"Building & Trades",
            "subcategory":"Landscaping Services",
            "type":"Services"
        }
    ],
    "sg:phone":"+1 541 757 7729",
    "sg:postcode":"97333",
    "sg:province":"OR",
    "sg:tags":[
        "tree"
    ],
    "wof:name":"Corvallis Commercial Sprayers",
    "wof:placetype":"venue"
},
  "geometry": {"coordinates":[-123.28304,44.555807],"type":"Point"}
}