{
  "type": "Feature",
  "properties": {
    "iso:country":"US",
    "sg:address":"22995 Redwood Hwy",
    "sg:city":"Kerby",
    "sg:classifiers":[
        {
            "category":"Farming",
            "subcategory":"Farm",
            "type":"Manufacturing & Wholesale Goods"
        }
    ],
    "sg:phone":"+1 541 592 2762",
    "sg:postcode":"97531",
    "sg:province":"OR",
    "wof:name":"Keith Nelsen Farm",
    "wof:placetype":"venue"
},
  "geometry": {"coordinates":[-123.64818099999999,42.217167],"type":"Point"}
}