{
  "type": "Feature",
  "properties": {
    "iso:country":"US",
    "sg:address":"4700 SW Fairmount Dr",
    "sg:city":"Beaverton",
    "sg:classifiers":[
        {
            "category":"Professional",
            "subcategory":"Computer Services",
            "type":"Services"
        }
    ],
    "sg:phone":"+1 503 381 5999",
    "sg:postcode":"97005",
    "sg:province":"OR",
    "sg:tags":[
        "development",
        "software"
    ],
    "wof:name":"Antix Technology Inc",
    "wof:placetype":"venue"
},
  "geometry": {"coordinates":[-122.81490700000001,45.485259],"type":"Point"}
}