{
  "type": "Feature",
  "properties": {
    "addr:full":"4640 Dogwood Dr Lake Oswego OR 97035",
    "addr:housenumber":"4640",
    "addr:postcode":"97035",
    "addr:street":"Dogwood Dr",
    "iso:country":"US",
    "sg:address":"4640 Dogwood Dr",
    "sg:city":"Lake Oswego",
    "sg:classifiers":[
        {
            "category":"Organizations",
            "subcategory":"Religious Organization",
            "type":"Services"
        }
    ],
    "sg:phone":"+1 503 639 1017",
    "sg:postcode":"97035",
    "sg:province":"OR",
    "wof:name":"Mount Crmel Evang Lthran Chrch",
    "wof:placetype":"venue"
},
  "geometry": {"coordinates":[-122.722989,45.383575],"type":"Point"}
}