{
  "type": "Feature",
  "properties": {
    "iso:country":"US",
    "sg:address":"13784 Keno Worden Rd",
    "sg:city":"Klamath Falls",
    "sg:classifiers":[
        {
            "category":"Banks & Credit Unions",
            "subcategory":"Financial Services",
            "type":"Services"
        }
    ],
    "sg:phone":"+1 541 884 9458",
    "sg:postcode":"97603",
    "sg:province":"OR",
    "sg:tags":[
        "trust",
        "investment",
        "real estate"
    ],
    "wof:name":"Mac Investment Corp",
    "wof:placetype":"venue"
},
  "geometry": {"coordinates":[-121.911729,42.09905],"type":"Point"}
}