{
  "type": "Feature",
  "properties": {
    "addr:full":"6635 N Baltimore Ave Portland OR 97203",
    "addr:housenumber":"6635",
    "addr:postcode":"97203",
    "addr:street":"N Baltimore Ave",
    "iso:country":"US",
    "sg:address":"6635 N Baltimore Ave",
    "sg:city":"Portland",
    "sg:classifiers":[
        {
            "category":"Professional",
            "subcategory":"Business Services",
            "type":"Services"
        }
    ],
    "sg:phone":"+1 503 283 2953",
    "sg:postcode":"97203",
    "sg:province":"OR",
    "wof:name":"Raw Design",
    "wof:placetype":"venue"
},
  "geometry": {"coordinates":[-122.761106,45.588648],"type":"Point"}
}