{
  "type": "Feature",
  "properties": {
    "addr:full":"307 Q St Springfield OR 97477",
    "addr:housenumber":"307",
    "addr:postcode":"97477",
    "addr:street":"Q St",
    "iso:country":"US",
    "sg:address":"307 Q St",
    "sg:city":"Springfield",
    "sg:classifiers":[
        {
            "category":"Personal",
            "subcategory":"Beauty Salon",
            "type":"Services"
        }
    ],
    "sg:phone":"+1 541 746 4473",
    "sg:postcode":"97477",
    "sg:province":"OR",
    "sg:tags":[
        "school"
    ],
    "wof:name":"AArt/ Sprngfield College Buty",
    "wof:placetype":"venue"
},
  "geometry": {"coordinates":[-123.02023,44.062015],"type":"Point"}
}