{
  "type": "Feature",
  "properties": {
    "addr:full":"9390 SW Tigard St Tigard OR 97223",
    "addr:housenumber":"9390",
    "addr:postcode":"97223",
    "addr:street":"Sw Tigard St",
    "iso:country":"US",
    "sg:address":"9390 SW Tigard St",
    "sg:city":"Tigard",
    "sg:classifiers":[
        {
            "category":"Building & Trades",
            "subcategory":"Construction",
            "type":"Services"
        }
    ],
    "sg:phone":"+1 503 598 7404",
    "sg:postcode":"97223",
    "sg:province":"OR",
    "sg:tags":[
        "contractor"
    ],
    "sg:website":"www.allsurfacepdx.com/contact-us/",
    "wof:name":"All Surface Roofing and Construction",
    "wof:placetype":"venue"
},
  "geometry": {"coordinates":[-122.773248,45.43159],"type":"Point"}
}