{
  "type": "Feature",
  "properties": {
    "addr:full":"1011 SW Emkay Dr Bend OR 97702",
    "addr:housenumber":"1011",
    "addr:postcode":"97702",
    "addr:street":"Sw Emkay Dr",
    "iso:country":"US",
    "sg:address":"1011 SW Emkay Dr",
    "sg:city":"Bend",
    "sg:classifiers":[
        {
            "category":"Wholesale",
            "subcategory":"Computers",
            "type":"Manufacturing & Wholesale Goods"
        }
    ],
    "sg:phone":"+1 541 388 2735",
    "sg:postcode":"97702",
    "sg:province":"OR",
    "wof:name":"Intel",
    "wof:placetype":"venue"
},
  "geometry": {"coordinates":[-121.326161,44.044769],"type":"Point"}
}