{
  "type": "Feature",
  "properties": {
    "iso:country":"US",
    "sg:address":"276 W 2nd Place Cir",
    "sg:city":"Lafayette",
    "sg:classifiers":[
        {
            "category":"Manufacturing",
            "subcategory":"Retail Goods",
            "type":"Manufacturing & Wholesale Goods"
        }
    ],
    "sg:phone":"+1 503 864 3369",
    "sg:postcode":"97127",
    "sg:province":"OR",
    "sg:tags":[
        "product",
        "mfg"
    ],
    "wof:name":"Noche Buena Wreaths",
    "wof:placetype":"venue"
},
  "geometry": {"coordinates":[-123.120257,45.24439],"type":"Point"}
}