{
  "type": "Feature",
  "properties": {
    "iso:country":"US",
    "sg:address":"1511 NE 181st Ave",
    "sg:city":"Portland",
    "sg:classifiers":[
        {
            "category":"Banks & Credit Unions",
            "subcategory":"Bank",
            "type":"Services"
        }
    ],
    "sg:phone":"+1 503 465 6527",
    "sg:postcode":"97230",
    "sg:province":"OR",
    "sg:tags":[
        "depository",
        "banking"
    ],
    "wof:name":"Loan Mart 3641",
    "wof:placetype":"venue"
},
  "geometry": {"coordinates":[-122.47730900000001,45.533975],"type":"Point"}
}