{
  "type": "Feature",
  "properties": {
    "iso:country":"US",
    "sg:address":"10819 SE Stark St Ste 200",
    "sg:city":"Portland",
    "sg:classifiers":[
        {
            "category":"Health Services",
            "subcategory":"Optometrist",
            "type":"Services"
        }
    ],
    "sg:phone":"+1 503 255 2291",
    "sg:postcode":"97216",
    "sg:province":"OR",
    "wof:name":"Kim Shane MD",
    "wof:placetype":"venue"
},
  "geometry": {"coordinates":[-122.551802,45.519158],"type":"Point"}
}