{
  "type": "Feature",
  "properties": {
    "iso:country":"US",
    "sg:address":"429 Court St NE",
    "sg:city":"Salem",
    "sg:classifiers":[
        {
            "category":"Professional",
            "subcategory":"Lawyer & Legal Services",
            "type":"Services"
        }
    ],
    "sg:phone":"+1 503 585 2450",
    "sg:postcode":"97301",
    "sg:province":"OR",
    "sg:tags":[
        "attorney",
        "practice"
    ],
    "sg:website":"http://www.lafky.com",
    "wof:name":"Lafky & Lafky",
    "wof:placetype":"venue"
},
  "geometry": {"coordinates":[-123.03783199999999,44.940956],"type":"Point"}
}