{
  "type": "Feature",
  "properties": {
    "addr:full":"15595 SE Lower Island Rd Dayton OR 97114",
    "addr:postcode":"15595;97114",
    "addr:street":"Se Lower Island Rd",
    "iso:country":"US",
    "sg:address":"15595 SE Lower Island Rd",
    "sg:city":"Dayton",
    "sg:phone":"+1 503 868 7233",
    "sg:postcode":"97114",
    "sg:province":"OR",
    "sg:tags":[
        "farm",
        "corn",
        "grain",
        "cash"
    ],
    "wof:name":"Finnicum Farms",
    "wof:placetype":"venue"
},
  "geometry": {"coordinates":[-123.03901,45.146162],"type":"Point"}
}