{
  "type": "Feature",
  "properties": {
    "addr:full":"29608 Cemetery Rd Unity OR 97884",
    "addr:housenumber":"29608",
    "addr:postcode":"97884",
    "addr:street":"Cemetery Rd",
    "iso:country":"US",
    "sg:address":"29608 Cemetery Rd",
    "sg:city":"Unity",
    "sg:phone":"+1 541 446 3391",
    "sg:postcode":"97884",
    "sg:province":"OR",
    "sg:tags":[
        "oil"
    ],
    "wof:name":"Burnt River Oil LLC",
    "wof:placetype":"venue"
},
  "geometry": {"coordinates":[-118.23361,44.470888],"type":"Point"}
}