{
  "type": "Feature",
  "properties": {
    "iso:country":"US",
    "sg:address":"226 S Main St",
    "sg:city":"Independence",
    "sg:classifiers":[
        {
            "category":"Professional",
            "subcategory":"Computer Services",
            "type":"Services"
        }
    ],
    "sg:phone":"+1 503 606 9120",
    "sg:postcode":"97351",
    "sg:province":"OR",
    "wof:name":"Coefficient",
    "wof:placetype":"venue"
},
  "geometry": {"coordinates":[-123.18465,44.851824],"type":"Point"}
}