{
  "type": "Feature",
  "properties": {
    "iso:country":"US",
    "sg:address":"203 SE Alder St Ste 202",
    "sg:city":"Portland",
    "sg:classifiers":[
        {
            "category":"Shopping",
            "subcategory":"Pets & Pet Supplies",
            "type":"Retail Goods"
        }
    ],
    "sg:phone":"+1 503 239 4266",
    "sg:postcode":"97214",
    "sg:province":"OR",
    "sg:tags":[
        "store"
    ],
    "wof:name":"Eagle Pacific Inc",
    "wof:placetype":"venue"
},
  "geometry": {"coordinates":[-122.663702,45.51796],"type":"Point"}
}