{
  "type": "Feature",
  "properties": {
    "iso:country":"US",
    "sg:address":"252 Madison Ave",
    "sg:city":"Astoria",
    "sg:classifiers":[
        {
            "category":"Recreation",
            "type":"Entertainment"
        }
    ],
    "sg:phone":"+1 503 338 3387",
    "sg:postcode":"97103",
    "sg:province":"OR",
    "wof:name":"Oregon Brazilian Jiu-Jitsu",
    "wof:placetype":"venue"
},
  "geometry": {"coordinates":[-123.840754,46.182203],"type":"Point"}
}