{
  "type": "Feature",
  "properties": {
    "iso:country":"US",
    "sg:address":"485 N Douglas St",
    "sg:city":"Canby",
    "sg:classifiers":[
        {
            "category":"Personal",
            "type":"Services"
        }
    ],
    "sg:phone":"+1 503 263 8085",
    "sg:postcode":"97013",
    "sg:province":"OR",
    "wof:name":"Professional Handyman Service",
    "wof:placetype":"venue"
},
  "geometry": {"coordinates":[-122.701364,45.263657],"type":"Point"}
}