{
  "type": "Feature",
  "properties": {
    "addr:full":"503 Spruce St Myrtle Point OR 97458",
    "addr:housenumber":"503",
    "addr:postcode":"97458",
    "addr:street":"Spruce St",
    "iso:country":"US",
    "sg:address":"503 Spruce St",
    "sg:city":"Myrtle Point",
    "sg:classifiers":[
        {
            "category":"Banks & Credit Unions",
            "subcategory":"Bank",
            "type":"Services"
        }
    ],
    "sg:phone":"+1 541 572 2301",
    "sg:postcode":"97458",
    "sg:province":"OR",
    "wof:name":"Oregon First Comm Credit Union",
    "wof:placetype":"venue"
},
  "geometry": {"coordinates":[-124.14187200000001,43.065133],"type":"Point"}
}