{
  "type": "Feature",
  "properties": {
    "iso:country":"US",
    "sg:address":"811 NW 20th Ave",
    "sg:city":"Portland",
    "sg:classifiers":[
        {
            "category":"Social Services",
            "type":"Services"
        }
    ],
    "sg:phone":"+1 503 228 9208",
    "sg:postcode":"97209",
    "sg:province":"OR",
    "sg:tags":[
        "counselor",
        "marriage",
        "family"
    ],
    "wof:name":"Joell Hyman",
    "wof:placetype":"venue"
},
  "geometry": {"coordinates":[-122.69257,45.529113],"type":"Point"}
}