{
  "type": "Feature",
  "properties": {
    "iso:country":"US",
    "sg:address":"15405 SW 116th Avenue",
    "sg:city":"Portland",
    "sg:classifiers":[
        {
            "category":"Health Services",
            "subcategory":"Dentist",
            "type":"Services"
        }
    ],
    "sg:phone":"+1 503 684 0507",
    "sg:postcode":"97224",
    "sg:province":"OR",
    "wof:name":"Chessar John R DDS",
    "wof:placetype":"venue"
},
  "geometry": {"coordinates":[-122.795817,45.408213],"type":"Point"}
}