{
  "type": "Feature",
  "properties": {
    "iso:country":"US",
    "sg:address":"22470 SW Bennette Rd",
    "sg:city":"Mcminnville",
    "sg:classifiers":[
        {
            "category":"Professional",
            "type":"Services"
        }
    ],
    "sg:phone":"+1 503 434 9025",
    "sg:postcode":"97128",
    "sg:province":"OR",
    "wof:name":"Linda Lindsay",
    "wof:placetype":"venue"
},
  "geometry": {"coordinates":[-123.346965,45.212001],"type":"Point"}
}