{
  "type": "Feature",
  "properties": {
    "iso:country":"US",
    "sg:address":"4702 SW Scholls Ferry Rd",
    "sg:city":"Portland",
    "sg:classifiers":[
        {
            "category":"Wholesale",
            "subcategory":"Electrical",
            "type":"Manufacturing & Wholesale Goods"
        }
    ],
    "sg:phone":"+1 503 245 2443",
    "sg:postcode":"97225",
    "sg:province":"OR",
    "sg:tags":[
        "control",
        "security",
        "system"
    ],
    "wof:name":"Simple Security Inc",
    "wof:placetype":"venue"
},
  "geometry": {"coordinates":[-122.750469,45.485387],"type":"Point"}
}