{
  "type": "Feature",
  "properties": {
    "addr:full":"124 S 3rd St St Helens OR 97051",
    "addr:housenumber":"124",
    "addr:postcode":"97051",
    "addr:street":"S 3Rd St",
    "iso:country":"US",
    "sg:address":"124 S 3rd St",
    "sg:city":"St Helens",
    "sg:classifiers":[
        {
            "category":"Building & Trades",
            "subcategory":"Construction",
            "type":"Services"
        }
    ],
    "sg:phone":"+1 503 397 5698",
    "sg:postcode":"97051",
    "sg:province":"OR",
    "sg:tags":[
        "general",
        "contractor"
    ],
    "wof:name":"Under Construction",
    "wof:placetype":"venue"
},
  "geometry": {"coordinates":[-122.801112,45.864917],"type":"Point"}
}