{
  "type": "Feature",
  "properties": {
    "iso:country":"US",
    "sg:address":"2966 Ave A",
    "sg:city":"White City",
    "sg:classifiers":[
        {
            "category":"Restaurant",
            "type":"Food & Drink"
        }
    ],
    "sg:phone":"+1 541 830 4538",
    "sg:postcode":"97503",
    "sg:province":"OR",
    "wof:name":"Expresso Fix",
    "wof:placetype":"venue"
},
  "geometry": {"coordinates":[-122.837667,42.425444],"type":"Point"}
}