{
  "type": "Feature",
  "properties": {
    "iso:country":"US",
    "sg:address":"9 Hawthorne St",
    "sg:city":"Medford",
    "sg:classifiers":[
        {
            "category":"Education",
            "subcategory":"Dance Studio",
            "type":"Public Place"
        },
        {
            "category":"Shopping",
            "subcategory":"Clothing, Apparel, & Fashions",
            "type":"Retail Goods"
        }
    ],
    "sg:phone":"+1 541 772 1362",
    "sg:postcode":"97504",
    "sg:province":"OR",
    "sg:tags":[
        "instruction",
        "dancing"
    ],
    "wof:name":"Dance Arts Academy",
    "wof:placetype":"venue"
},
  "geometry": {"coordinates":[-122.86736500000001,42.330098],"type":"Point"}
}