{
  "type": "Feature",
  "properties": {
    "addr:full":"1801 NW Upshur Street Portland OR 97209",
    "addr:housenumber":"1801",
    "addr:postcode":"97209",
    "addr:street":"Nw Upshur Street",
    "iso:country":"US",
    "sg:address":"1801 NW Upshur Street",
    "sg:city":"Portland",
    "sg:classifiers":[
        {
            "category":"Building & Trades",
            "subcategory":"Construction",
            "type":"Services"
        }
    ],
    "sg:phone":"+1 503 242 3898",
    "sg:postcode":"97209",
    "sg:province":"OR",
    "sg:tags":[
        "contractor"
    ],
    "wof:name":"Kifton Development",
    "wof:placetype":"venue"
},
  "geometry": {"coordinates":[-122.68971999999999,45.536398],"type":"Point"}
}