{
  "type": "Feature",
  "properties": {
    "iso:country":"US",
    "sg:address":"30742 Venell Pl",
    "sg:city":"Corvallis",
    "sg:classifiers":[
        {
            "category":"Wholesale",
            "subcategory":"Farm Supplies",
            "type":"Manufacturing & Wholesale Goods"
        }
    ],
    "sg:phone":"+1 541 752 2408",
    "sg:postcode":"97333",
    "sg:province":"OR",
    "sg:tags":[
        "bulb",
        "seed",
        "grass"
    ],
    "wof:name":"Mid Valley Agricultural Prods",
    "wof:placetype":"venue"
},
  "geometry": {"coordinates":[-123.306692,44.474711],"type":"Point"}
}