{
  "type": "Feature",
  "properties": {
    "iso:country":"US",
    "sg:address":"10101 SW Barbur Blvd # 200",
    "sg:city":"Portland",
    "sg:classifiers":[
        {
            "category":"Health Services",
            "subcategory":"Medical Lab",
            "type":"Services"
        }
    ],
    "sg:phone":"+1 503 206 4989",
    "sg:postcode":"97219",
    "sg:province":"OR",
    "sg:tags":[
        "laboratories-pathological",
        "laboratory"
    ],
    "sg:website":"http://www.kashilab.com",
    "wof:name":"Kashi Clinical Laboratories, Inc.",
    "wof:placetype":"venue"
},
  "geometry": {"coordinates":[-122.723561,45.452604],"type":"Point"}
}