{
  "type": "Feature",
  "properties": {
    "iso:country":"US",
    "sg:address":"700 Nobility Dr",
    "sg:city":"Medford",
    "sg:classifiers":[
        {
            "category":"Building & Trades",
            "subcategory":"Landscaping Services",
            "type":"Services"
        }
    ],
    "sg:phone":"+1 541 773 1985",
    "sg:postcode":"97501",
    "sg:province":"OR",
    "sg:tags":[
        "landscape"
    ],
    "wof:name":"Precision Landscaping",
    "wof:placetype":"venue"
},
  "geometry": {"coordinates":[-122.875304,42.301159],"type":"Point"}
}