{
  "type": "Feature",
  "properties": {
    "iso:country":"US",
    "sg:address":"4685 Portland Rd NE",
    "sg:city":"Salem",
    "sg:classifiers":[
        {
            "category":"Restaurant",
            "type":"Food & Drink"
        },
        {
            "category":"Bakery",
            "type":"Food & Drink"
        }
    ],
    "sg:menulink":"http://www.allmenus.com/or/salem/116497-the-original-pancake-house/menu/",
    "sg:phone":"+1 503 393 9124",
    "sg:postcode":"97305",
    "sg:province":"OR",
    "sg:tags":[
        "bakery",
        "american",
        "pastry",
        "diner"
    ],
    "wof:name":"The Original Pancake House",
    "wof:placetype":"venue"
},
  "geometry": {"coordinates":[-122.987973,44.989454],"type":"Point"}
}