{
  "type": "Feature",
  "properties": {
    "iso:country":"US",
    "sg:address":"135 NE Terry Ln",
    "sg:city":"Grants Pass",
    "sg:classifiers":[
        {
            "category":"Shopping",
            "subcategory":"Optical Goods",
            "type":"Retail Goods"
        }
    ],
    "sg:phone":"+1 541 471 1120",
    "sg:postcode":"97526",
    "sg:province":"OR",
    "sg:tags":[
        "center"
    ],
    "wof:name":"National Vision",
    "wof:placetype":"venue"
},
  "geometry": {"coordinates":[-123.302785,42.438417],"type":"Point"}
}