{
  "type": "Feature",
  "properties": {
    "iso:country":"US",
    "sg:address":"18687 SW Tualatin Valley Hwy",
    "sg:city":"Beaverton",
    "sg:classifiers":[
        {
            "category":"Banks & Credit Unions",
            "subcategory":"Bank",
            "type":"Services"
        }
    ],
    "sg:phone":"+1 503 649 3518",
    "sg:postcode":"97006",
    "sg:province":"OR",
    "sg:tags":[
        "loan"
    ],
    "wof:name":"Continental Loans",
    "wof:placetype":"venue"
},
  "geometry": {"coordinates":[-122.86739799999999,45.494178],"type":"Point"}
}