{
  "type": "Feature",
  "properties": {
    "iso:country":"US",
    "sg:address":"2016 US Hwy 101",
    "sg:city":"Florence",
    "sg:classifiers":[
        {
            "category":"Home & Garden",
            "subcategory":"Household Appliances",
            "type":"Retail Goods"
        }
    ],
    "sg:phone":"+1 503 497 4848",
    "sg:postcode":"97439",
    "sg:province":"OR",
    "sg:tags":[
        "stereo",
        "television"
    ],
    "wof:name":"Oldfields Showroom",
    "wof:placetype":"venue"
},
  "geometry": {"coordinates":[-124.101236,43.984903],"type":"Point"}
}