{
  "type": "Feature",
  "properties": {
    "iso:country":"US",
    "sg:address":"3710 17th St",
    "sg:city":"Baker City",
    "sg:classifiers":[
        {
            "category":"Freight",
            "type":"Transportation"
        }
    ],
    "sg:phone":"+1 541 523 2116",
    "sg:postcode":"97814",
    "sg:province":"OR",
    "sg:tags":[
        "distance",
        "long",
        "trucking"
    ],
    "wof:name":"Warren Crane Trking",
    "wof:placetype":"venue"
},
  "geometry": {"coordinates":[-117.849782,44.79276],"type":"Point"}
}