{
  "type": "Feature",
  "properties": {
    "iso:country":"US",
    "sg:address":"39330 Proctor Blvd",
    "sg:city":"Sandy",
    "sg:classifiers":[
        {
            "category":"Professional",
            "type":"Services"
        }
    ],
    "sg:phone":"+1 503 668 0565",
    "sg:postcode":"97055",
    "sg:province":"OR",
    "wof:name":"Franklin Hall of Gold",
    "wof:placetype":"venue"
},
  "geometry": {"coordinates":[-122.258409,45.397205],"type":"Point"}
}