{
  "type": "Feature",
  "properties": {
    "iso:country":"US",
    "sg:address":"5241 NW Skycrest Pkwy",
    "sg:city":"Portland",
    "sg:classifiers":[
        {
            "category":"Manufacturing",
            "subcategory":"Tools & Machinery",
            "type":"Manufacturing & Wholesale Goods"
        }
    ],
    "sg:phone":"+1 503 533 8091",
    "sg:postcode":"97229",
    "sg:province":"OR",
    "sg:tags":[
        "process",
        "control",
        "mfg",
        "instrument"
    ],
    "wof:name":"Oregon Water Works",
    "wof:placetype":"venue"
},
  "geometry": {"coordinates":[-122.82538099999999,45.558638],"type":"Point"}
}