{
  "type": "Feature",
  "properties": {
    "addr:full":"32225 SE Pipeline Rd Gresham OR 97080",
    "addr:postcode":"32225;97080",
    "addr:street":"Se Pipeline Rd",
    "iso:country":"US",
    "sg:address":"32225 SE Pipeline Rd",
    "sg:city":"Gresham",
    "sg:classifiers":[
        {
            "category":"Autos & Motor Vehicles",
            "subcategory":"Automobile Sales",
            "type":"Retail Goods"
        },
        {
            "category":"Utilities",
            "subcategory":"Refuse",
            "type":"Services"
        },
        {
            "category":"Utilities",
            "subcategory":"Recycling",
            "type":"Services"
        },
        {
            "category":"Wholesale",
            "subcategory":"Scrap",
            "type":"Manufacturing & Wholesale Goods"
        },
        {
            "category":"Building & Trades",
            "subcategory":"Cleaning & Sanitation",
            "type":"Services"
        }
    ],
    "sg:phone":"+1 503 313 9455",
    "sg:postcode":"97080",
    "sg:province":"OR",
    "sg:tags":[
        "control",
        "junk",
        "site-clean-up",
        "garbage",
        "disposal",
        "hazardous",
        "material",
        "collection",
        "removal",
        "equipment",
        "construction",
        "waste",
        "salvage"
    ],
    "sg:website":"http://mikeanddadshaulingllc.com",
    "wof:name":"Mike & Dad's Hauling LLC - Garbage and Junk Removal Portland",
    "wof:placetype":"venue"
},
  "geometry": {"coordinates":[-122.327642,45.482074],"type":"Point"}
}