{
  "type": "Feature",
  "properties": {
    "iso:country":"US",
    "sg:address":"145 Helman St",
    "sg:city":"Ashland",
    "sg:classifiers":[
        {
            "category":"Professional",
            "subcategory":"Business Services",
            "type":"Services"
        }
    ],
    "sg:phone":"+1 541 488 9570",
    "sg:postcode":"97520",
    "sg:province":"OR",
    "wof:name":"Healthy Building Solutions",
    "wof:placetype":"venue"
},
  "geometry": {"coordinates":[-122.71557799999999,42.200344],"type":"Point"}
}