{
  "type": "Feature",
  "properties": {
    "iso:country":"US",
    "sg:address":"2316 S 6th St",
    "sg:city":"Klamath Falls",
    "sg:classifiers":[
        {
            "category":"Banks & Credit Unions",
            "subcategory":"Bank",
            "type":"Services"
        }
    ],
    "sg:phone":"+1 541 882 3333",
    "sg:postcode":"97603",
    "sg:province":"OR",
    "sg:tags":[
        "financing"
    ],
    "wof:name":"United Finance Co",
    "wof:placetype":"venue"
},
  "geometry": {"coordinates":[-121.761787,42.213563],"type":"Point"}
}