{
  "type": "Feature",
  "properties": {
    "iso:country":"US",
    "sg:address":"33838 SE Kelso Rd",
    "sg:city":"Boring",
    "sg:phone":"+1 503 668 7942",
    "sg:postcode":"97009",
    "sg:province":"OR",
    "wof:name":"Truck Design Auto Body & Paint",
    "wof:placetype":"venue"
},
  "geometry": {"coordinates":[-122.316074,45.418353],"type":"Point"}
}