{
  "type": "Feature",
  "properties": {
    "addr:full":"6495 SE Tualatin Valley Hwy Hillsboro OR 97123",
    "addr:housenumber":"6495",
    "addr:postcode":"97123",
    "addr:street":"Se Tualatin Valley Hwy",
    "iso:country":"US",
    "sg:address":"6495 SE Tualatin Valley Hwy",
    "sg:city":"Hillsboro",
    "sg:classifiers":[
        {
            "category":"Restaurant",
            "type":"Food & Drink"
        }
    ],
    "sg:phone":"+1 503 591 9400",
    "sg:postcode":"97123",
    "sg:province":"OR",
    "sg:tags":[
        "barbecue",
        "hawaiian"
    ],
    "wof:name":"Hawaiian Kine Bar B Q",
    "wof:placetype":"venue"
},
  "geometry": {"coordinates":[-122.914852,45.498792],"type":"Point"}
}