{
  "type": "Feature",
  "properties": {
    "addr:full":"6491 SW Capitol Hwy Portland OR 97239",
    "addr:housenumber":"6491",
    "addr:postcode":"97239",
    "addr:street":"Sw Capitol Hwy",
    "iso:country":"US",
    "sg:address":"6491 SW Capitol Hwy",
    "sg:city":"Portland",
    "sg:classifiers":[
        {
            "category":"Health Services",
            "subcategory":"Health Practitioner",
            "type":"Services"
        }
    ],
    "sg:phone":"+1 503 422 1665",
    "sg:postcode":"97239",
    "sg:province":"OR",
    "wof:name":"Marla Rogers Lac",
    "wof:placetype":"venue"
},
  "geometry": {"coordinates":[-122.69999,45.477691],"type":"Point"}
}