{
  "type": "Feature",
  "properties": {
    "addr:full":"751 Bills Rd Myrtle Creek OR 97457",
    "addr:housenumber":"751",
    "addr:postcode":"97457",
    "addr:street":"Bills Rd",
    "iso:country":"US",
    "sg:address":"751 Bills Rd",
    "sg:city":"Myrtle Creek",
    "sg:classifiers":[
        {
            "category":"Wholesale",
            "subcategory":"Farm Supplies",
            "type":"Manufacturing & Wholesale Goods"
        }
    ],
    "sg:phone":"+1 541 863 4751",
    "sg:postcode":"97457",
    "sg:province":"OR",
    "sg:tags":[
        "livestock"
    ],
    "wof:name":"Arlan & Betty C Weaver",
    "wof:placetype":"venue"
},
  "geometry": {"coordinates":[-123.33135299999999,42.966351],"type":"Point"}
}