{
  "type": "Feature",
  "properties": {
    "iso:country":"US",
    "sg:address":"2608 NW Vaughn Street",
    "sg:city":"Portland",
    "sg:classifiers":[
        {
            "category":"Bars & Pubs",
            "subcategory":"Nightclub",
            "type":"Food & Drink"
        }
    ],
    "sg:phone":"+1 503 294 2190",
    "sg:postcode":"97210",
    "sg:province":"OR",
    "sg:tags":[
        "nightlife"
    ],
    "wof:name":"Panama Red Room Lounge",
    "wof:placetype":"venue"
},
  "geometry": {"coordinates":[-122.70568400000001,45.536907],"type":"Point"}
}