{
  "type": "Feature",
  "properties": {
    "iso:country":"US",
    "sg:address":"16838 NE Couch Ct",
    "sg:city":"Portland",
    "sg:classifiers":[
        {
            "category":"Arts & Performance",
            "subcategory":"Theater",
            "type":"Entertainment"
        }
    ],
    "sg:phone":"+1 503 286 6487",
    "sg:postcode":"97230",
    "sg:province":"OR",
    "sg:tags":[
        "group"
    ],
    "wof:name":"Exotic Entertainment Inc",
    "wof:placetype":"venue"
},
  "geometry": {"coordinates":[-122.48896999999999,45.523023],"type":"Point"}
}