{
  "type": "Feature",
  "properties": {
    "addr:full":"4231 N Interstate Ave Portland OR 97217",
    "addr:housenumber":"4231",
    "addr:postcode":"97217",
    "addr:street":"N Interstate Ave",
    "iso:country":"US",
    "sg:address":"4231 N Interstate Ave",
    "sg:city":"Portland",
    "sg:classifiers":[
        {
            "category":"Arts & Performance",
            "subcategory":"Arts Center",
            "type":"Entertainment"
        }
    ],
    "sg:phone":"+1 503 249 9009",
    "sg:postcode":"97217",
    "sg:province":"OR",
    "sg:tags":[
        "performing"
    ],
    "wof:name":"Yeates Academy",
    "wof:placetype":"venue"
},
  "geometry": {"coordinates":[-122.68221800000001,45.554265],"type":"Point"}
}