{
  "type": "Feature",
  "properties": {
    "iso:country":"US",
    "sg:address":"1512 Clydesdale Dr SE",
    "sg:city":"Salem",
    "sg:classifiers":[
        {
            "category":"Building & Trades",
            "subcategory":"Construction",
            "type":"Services"
        }
    ],
    "sg:phone":"+1 503 364 2774",
    "sg:postcode":"97317",
    "sg:province":"OR",
    "sg:tags":[
        "general",
        "contractor"
    ],
    "wof:name":"H & R Construction",
    "wof:placetype":"venue"
},
  "geometry": {"coordinates":[-122.96454,44.912459],"type":"Point"}
}