{
  "type": "Feature",
  "properties": {
    "iso:country":"US",
    "sg:address":"350 Pearl St",
    "sg:city":"Eugene",
    "sg:classifiers":[
        {
            "category":"Health Services",
            "subcategory":"Nursing And Care Facility",
            "type":"Services"
        }
    ],
    "sg:phone":"+1 541 342 5329",
    "sg:postcode":"97401",
    "sg:province":"OR",
    "sg:tags":[
        "home",
        "retirement",
        "community"
    ],
    "sg:website":"www.yapoah.com",
    "wof:name":"Ya-Po-Ah Terrace",
    "wof:placetype":"venue"
},
  "geometry": {"coordinates":[-123.089729,44.056037],"type":"Point"}
}