{
  "type": "Feature",
  "properties": {
    "iso:country":"US",
    "sg:address":"25780 S Jewell Rd",
    "sg:city":"Beavercreek",
    "sg:classifiers":[
        {
            "category":"Building & Trades",
            "subcategory":"Construction",
            "type":"Services"
        }
    ],
    "sg:phone":"+1 503 632 3732",
    "sg:postcode":"97004",
    "sg:province":"OR",
    "sg:tags":[
        "woodworker"
    ],
    "sg:website":"www.shamblesworkshops.com",
    "wof:name":"Shambles Workshops",
    "wof:placetype":"venue"
},
  "geometry": {"coordinates":[-122.444958,45.232094],"type":"Point"}
}