{
  "type": "Feature",
  "properties": {
    "iso:country":"US",
    "sg:address":"280 S Main St",
    "sg:city":"Toledo",
    "sg:classifiers":[
        {
            "category":"Home & Garden",
            "subcategory":"Furniture",
            "type":"Retail Goods"
        }
    ],
    "sg:phone":"+1 541 336 2433",
    "sg:postcode":"97391",
    "sg:province":"OR",
    "wof:name":"Merit Woodcrafting",
    "wof:placetype":"venue"
},
  "geometry": {"coordinates":[-123.93731,44.619138],"type":"Point"}
}