{
  "type": "Feature",
  "properties": {
    "addr:full":"1102 W Central Ave Sutherlin OR 97479",
    "addr:housenumber":"1102",
    "addr:postcode":"97479",
    "addr:street":"W Central Ave",
    "iso:country":"US",
    "sg:address":"1102 W Central Ave",
    "sg:city":"Sutherlin",
    "sg:classifiers":[
        {
            "category":"Restaurant",
            "type":"Food & Drink"
        }
    ],
    "sg:phone":"+1 541 459 9393",
    "sg:postcode":"97479",
    "sg:province":"OR",
    "wof:name":"Hong Kong Restaurant",
    "wof:placetype":"venue"
},
  "geometry": {"coordinates":[-123.329077,43.387343],"type":"Point"}
}