{
  "type": "Feature",
  "properties": {
    "addr:full":"2001 NE Lafayette Ave Mcminnville OR 97128",
    "addr:housenumber":"2001",
    "addr:postcode":"97128",
    "addr:street":"Ne Lafayette Ave",
    "iso:country":"US",
    "sg:address":"2001 NE Lafayette Ave",
    "sg:city":"Mcminnville",
    "sg:classifiers":[
        {
            "category":"Retail",
            "subcategory":"Animal Services",
            "type":"Services"
        }
    ],
    "sg:phone":"+1 503 472 5932",
    "sg:postcode":"97128",
    "sg:province":"OR",
    "wof:name":"Amberwood Grooming",
    "wof:placetype":"venue"
},
  "geometry": {"coordinates":[-123.17768599999999,45.22196],"type":"Point"}
}