{
  "type": "Feature",
  "properties": {
    "addr:full":"393 N State St Lake Oswego OR 97034",
    "addr:housenumber":"393",
    "addr:postcode":"97034",
    "addr:street":"N State St",
    "iso:country":"US",
    "sg:address":"393 N State St",
    "sg:city":"Lake Oswego",
    "sg:classifiers":[
        {
            "category":"Professional",
            "subcategory":"Computer Services",
            "type":"Services"
        }
    ],
    "sg:phone":"+1 503 387 5730",
    "sg:postcode":"97034",
    "sg:province":"OR",
    "sg:tags":[
        "repair"
    ],
    "sg:website":"www.kevinthegeek.com",
    "wof:name":"Lake Oswego Computer Repair",
    "wof:placetype":"venue"
},
  "geometry": {"coordinates":[-122.662646,45.419255],"type":"Point"}
}