{
  "type": "Feature",
  "properties": {
    "addr:full":"16146 Boones Ferry Rd Lake Oswego OR 97035",
    "addr:housenumber":"16146",
    "addr:postcode":"97035",
    "addr:street":"Boones Ferry Rd",
    "iso:country":"US",
    "sg:address":"16146 Boones Ferry Rd",
    "sg:city":"Lake Oswego",
    "sg:classifiers":[
        {
            "category":"Home & Garden",
            "subcategory":"Building Materials",
            "type":"Retail Goods"
        },
        {
            "category":"Professional",
            "subcategory":"Business Services",
            "type":"Services"
        }
    ],
    "sg:phone":"+1 503 636 0511",
    "sg:postcode":"97035",
    "sg:province":"OR",
    "sg:tags":[
        "consultant",
        "wallpaper",
        "paint",
        "window",
        "design",
        "decorator",
        "interior",
        "drapery",
        "furnishing"
    ],
    "wof:name":"Interior Showcase Inc",
    "wof:placetype":"venue"
},
  "geometry": {"coordinates":[-122.722702,45.408833],"type":"Point"}
}