{
  "type": "Feature",
  "properties": {
    "addr:full":"915 NW 57th St Redmond OR 97756",
    "addr:housenumber":"915",
    "addr:postcode":"97756",
    "addr:street":"Nw 57Th St",
    "iso:country":"US",
    "sg:address":"915 NW 57th St",
    "sg:city":"Redmond",
    "sg:classifiers":[
        {
            "category":"Freight",
            "type":"Transportation"
        }
    ],
    "sg:phone":"+1 541 548 5060",
    "sg:postcode":"97756",
    "sg:province":"OR",
    "sg:tags":[
        "operator",
        "delivery",
        "local",
        "trucking"
    ],
    "wof:name":"Cascade Delivery Service LLC",
    "wof:placetype":"venue"
},
  "geometry": {"coordinates":[-121.237072,44.282486],"type":"Point"}
}