{
  "type": "Feature",
  "properties": {
    "iso:country":"US",
    "sg:address":"9400 SW Barber St",
    "sg:city":"Wilsonville",
    "sg:classifiers":[
        {
            "category":"Wholesale",
            "subcategory":"Machinery & Supplies",
            "type":"Manufacturing & Wholesale Goods"
        },
        {
            "category":"Manufacturing",
            "subcategory":"Tools & Machinery",
            "type":"Manufacturing & Wholesale Goods"
        }
    ],
    "sg:phone":"+1 503 682 2726",
    "sg:postcode":"97070",
    "sg:province":"OR",
    "sg:tags":[
        "control",
        "equipment",
        "industrial"
    ],
    "wof:name":"Dynamic Control Designs",
    "wof:placetype":"venue"
},
  "geometry": {"coordinates":[-122.774659,45.310185],"type":"Point"}
}