{
  "type": "Feature",
  "properties": {
    "iso:country":"US",
    "sg:address":"94261 Moore St",
    "sg:city":"Gold Beach",
    "sg:classifiers":[
        {
            "category":"Organizations",
            "subcategory":"Religious Organization",
            "type":"Services"
        }
    ],
    "sg:phone":"+1 541 247 7878",
    "sg:postcode":"97444",
    "sg:province":"OR",
    "sg:tags":[
        "church"
    ],
    "wof:name":"St Matthews Episcopal Church",
    "wof:placetype":"venue"
},
  "geometry": {"coordinates":[-124.418389,42.417005],"type":"Point"}
}