{
  "type": "Feature",
  "properties": {
    "iso:country":"US",
    "sg:address":"45 W Cherry Ave",
    "sg:city":"Hermiston",
    "sg:classifiers":[
        {
            "category":"Organizations",
            "subcategory":"Community Association",
            "type":"Services"
        }
    ],
    "sg:phone":"+1 541 567 6219",
    "sg:postcode":"97838",
    "sg:province":"OR",
    "wof:name":"Veterans Foreign War Post 4",
    "wof:placetype":"venue"
},
  "geometry": {"coordinates":[-119.29077700000001,45.848121],"type":"Point"}
}