{
  "type": "Feature",
  "properties": {
    "addr:full":"33031 Witt Dr Tangent OR 97389",
    "addr:housenumber":"33031",
    "addr:postcode":"97389",
    "addr:street":"Witt Dr",
    "iso:country":"US",
    "sg:address":"33031 Witt Dr",
    "sg:city":"Tangent",
    "sg:classifiers":[
        {
            "category":"Retail",
            "subcategory":"Repair Shop",
            "type":"Services"
        }
    ],
    "sg:phone":"+1 541 928 3732",
    "sg:postcode":"97389",
    "sg:province":"OR",
    "sg:tags":[
        "antique",
        "restoring"
    ],
    "wof:name":"Conrad's Country Wood Shop",
    "wof:placetype":"venue"
},
  "geometry": {"coordinates":[-123.07755,44.491829],"type":"Point"}
}