{
  "type": "Feature",
  "properties": {
    "addr:full":"90 SE Bridgeford Blvd Bend OR 97702",
    "addr:housenumber":"90",
    "addr:postcode":"97702",
    "addr:street":"Se Bridgeford Blvd",
    "iso:country":"US",
    "sg:address":"90 SE Bridgeford Blvd",
    "sg:city":"Bend",
    "sg:classifiers":[
        {
            "category":"Building & Trades",
            "subcategory":"Plumbing",
            "type":"Services"
        }
    ],
    "sg:phone":"+1 541 388 3116",
    "sg:postcode":"97702",
    "sg:province":"OR",
    "sg:tags":[
        "plumbing",
        "contractor"
    ],
    "wof:name":"Lee Ramsey Plumbing",
    "wof:placetype":"venue"
},
  "geometry": {"coordinates":[-121.29164299999999,44.049248],"type":"Point"}
}