{
  "type": "Feature",
  "properties": {
    "addr:full":"4001 NE Halsey #100 Portland OR 97232",
    "addr:housenumber":"4001",
    "addr:postcode":"97232",
    "addr:street":"Ne Halsey # 100",
    "iso:country":"US",
    "sg:address":"4001 NE Halsey #100",
    "sg:city":"Portland",
    "sg:classifiers":[
        {
            "category":"Real Estate",
            "subcategory":"Real Estate Agent",
            "type":"Services"
        }
    ],
    "sg:phone":"+1 503 913 1103",
    "sg:postcode":"97232",
    "sg:province":"OR",
    "sg:website":"www.welcometopdx.com",
    "wof:name":"Deb Counts-Tabor Oregon Realty",
    "wof:placetype":"venue"
},
  "geometry": {"coordinates":[-122.621977,45.534042],"type":"Point"}
}