{
  "type": "Feature",
  "properties": {
    "addr:full":"624 NW 8th St Redmond OR 97756",
    "addr:housenumber":"624",
    "addr:postcode":"97756",
    "addr:street":"Nw 8Th St",
    "iso:country":"US",
    "sg:address":"624 NW 8th St",
    "sg:city":"Redmond",
    "sg:classifiers":[
        {
            "category":"Recreation",
            "type":"Entertainment"
        }
    ],
    "sg:phone":"+1 541 548 8027",
    "sg:postcode":"97756",
    "sg:province":"OR",
    "wof:name":"Sugano Dale",
    "wof:placetype":"venue"
},
  "geometry": {"coordinates":[-121.176374,44.28178],"type":"Point"}
}