{
  "type": "Feature",
  "properties": {
    "iso:country":"US",
    "sg:address":"539 US Hwy 101",
    "sg:city":"Florence",
    "sg:classifiers":[
        {
            "category":"Retail",
            "subcategory":"Repair Shop",
            "type":"Services"
        }
    ],
    "sg:phone":"+1 541 997 7676",
    "sg:postcode":"97439",
    "sg:province":"OR",
    "sg:tags":[
        "jewelry"
    ],
    "wof:name":"Coast Jewelers",
    "wof:placetype":"venue"
},
  "geometry": {"coordinates":[-124.105529,43.971425],"type":"Point"}
}