{
  "type": "Feature",
  "properties": {
    "addr:full":"570 SE Juniper St Prineville OR 97754",
    "addr:housenumber":"570",
    "addr:postcode":"97754",
    "addr:street":"Se Juniper St",
    "iso:country":"US",
    "sg:address":"570 SE Juniper St",
    "sg:city":"Prineville",
    "sg:classifiers":[
        {
            "category":"Personal",
            "subcategory":"Beauty Salon",
            "type":"Services"
        },
        {
            "category":"Personal",
            "subcategory":"Barber",
            "type":"Services"
        }
    ],
    "sg:phone":"+1 541 447 6520",
    "sg:postcode":"97754",
    "sg:province":"OR",
    "sg:tags":[
        "shop"
    ],
    "wof:name":"Janie's Cutting Edge",
    "wof:placetype":"venue"
},
  "geometry": {"coordinates":[-120.836369,44.296748],"type":"Point"}
}