{
  "type": "Feature",
  "properties": {
    "iso:country":"US",
    "sg:address":"580 E Dutton Rd",
    "sg:city":"Eagle Point",
    "sg:classifiers":[
        {
            "category":"Building & Trades",
            "subcategory":"Construction",
            "type":"Services"
        }
    ],
    "sg:phone":"+1 541 830 8678",
    "sg:postcode":"97524",
    "sg:province":"OR",
    "sg:tags":[
        "contractor"
    ],
    "sg:website":"www.kci.nu",
    "wof:name":"Keith Construction",
    "wof:placetype":"venue"
},
  "geometry": {"coordinates":[-122.82054,42.443501],"type":"Point"}
}