{
  "type": "Feature",
  "properties": {
    "iso:country":"US",
    "sg:address":"315 SW 4th Avenue",
    "sg:city":"Portland",
    "sg:classifiers":[
        {
            "category":"Organizations",
            "subcategory":"Non-profit Organization",
            "type":"Services"
        }
    ],
    "sg:phone":"+1 503 223 8757",
    "sg:postcode":"97204",
    "sg:province":"OR",
    "sg:tags":[
        "service/non-profit",
        "community"
    ],
    "wof:name":"Ibd",
    "wof:placetype":"venue"
},
  "geometry": {"coordinates":[-122.675009,45.521084],"type":"Point"}
}