{
  "type": "Feature",
  "properties": {
    "iso:country":"US",
    "sg:address":"629 NW Kingwood Ave",
    "sg:city":"Redmond",
    "sg:classifiers":[
        {
            "category":"Home & Garden",
            "subcategory":"Mobile Homes",
            "type":"Retail Goods"
        },
        {
            "category":"Building & Trades",
            "subcategory":"Construction",
            "type":"Services"
        }
    ],
    "sg:phone":"+1 541 923 5656",
    "sg:postcode":"97756",
    "sg:province":"OR",
    "sg:tags":[
        "builder"
    ],
    "wof:name":"Nelmstar Homes",
    "wof:placetype":"venue"
},
  "geometry": {"coordinates":[-121.174324,44.287443],"type":"Point"}
}