{
  "type": "Feature",
  "properties": {
    "addr:full":"303 Klahanie Ln Idleyld Park OR 97447",
    "addr:housenumber":"303",
    "addr:postcode":"97447",
    "addr:street":"Klahanie Ln",
    "iso:country":"US",
    "sg:address":"303 Klahanie Ln",
    "sg:city":"Idleyld Park",
    "sg:classifiers":[
        {
            "category":"Wholesale",
            "subcategory":"Hardware",
            "type":"Manufacturing & Wholesale Goods"
        }
    ],
    "sg:phone":"+1 541 496 3987",
    "sg:postcode":"97447",
    "sg:province":"OR",
    "sg:tags":[
        "equipment",
        "energy",
        "solar"
    ],
    "wof:name":"Energy Independence Co",
    "wof:placetype":"venue"
},
  "geometry": {"coordinates":[-123.014978,43.33377],"type":"Point"}
}