{
  "type": "Feature",
  "properties": {
    "addr:full":"16350 SE Bel Air Dr Damascus OR 97089",
    "addr:postcode":"16350;97089",
    "addr:street":"Se Bel Air Dr",
    "iso:country":"US",
    "sg:address":"16350 SE Bel Air Dr",
    "sg:city":"Damascus",
    "sg:classifiers":[
        {
            "category":"Building & Trades",
            "subcategory":"Construction",
            "type":"Services"
        }
    ],
    "sg:phone":"+1 503 658 8754",
    "sg:postcode":"97089",
    "sg:province":"OR",
    "sg:tags":[
        "system",
        "specialty",
        "heating",
        "contractor",
        "air conditioning"
    ],
    "wof:name":"John R Ross And Associates",
    "wof:placetype":"venue"
},
  "geometry": {"coordinates":[-122.480604,45.404785],"type":"Point"}
}