{
  "type": "Feature",
  "properties": {
    "addr:full":"209 College Dr Grants Pass OR 97527",
    "addr:housenumber":"209",
    "addr:postcode":"97527",
    "addr:street":"College Dr",
    "iso:country":"US",
    "sg:address":"209 College Dr",
    "sg:city":"Grants Pass",
    "sg:classifiers":[
        {
            "category":"Building & Trades",
            "subcategory":"Construction",
            "type":"Services"
        }
    ],
    "sg:phone":"+1 541 479 4253",
    "sg:postcode":"97527",
    "sg:province":"OR",
    "sg:tags":[
        "residential",
        "remodel",
        "contractor"
    ],
    "wof:name":"Gene Venekamp",
    "wof:placetype":"venue"
},
  "geometry": {"coordinates":[-123.391373,42.407989],"type":"Point"}
}