{
  "type": "Feature",
  "properties": {
    "iso:country":"US",
    "sg:address":"57437 Hwy 204",
    "sg:city":"Weston",
    "sg:classifiers":[
        {
            "category":"Wholesale",
            "subcategory":"Sporting Goods",
            "type":"Manufacturing & Wholesale Goods"
        }
    ],
    "sg:phone":"+1 541 566 3269",
    "sg:postcode":"97886",
    "sg:province":"OR",
    "wof:name":"Wholesale Warehouse Net",
    "wof:placetype":"venue"
},
  "geometry": {"coordinates":[-118.270352,45.789881],"type":"Point"}
}