{
  "type": "Feature",
  "properties": {
    "iso:country":"US",
    "sg:address":"1408 Arthur St",
    "sg:city":"Klamath Falls",
    "sg:classifiers":[
        {
            "category":"Retail",
            "subcategory":"Portrait Studio",
            "type":"Services"
        }
    ],
    "sg:phone":"+1 541 273 6337",
    "sg:postcode":"97603",
    "sg:province":"OR",
    "sg:tags":[
        "photo"
    ],
    "wof:name":"Portraits By Rivka Portraits O",
    "wof:placetype":"venue"
},
  "geometry": {"coordinates":[-121.749095,42.215002],"type":"Point"}
}