{
  "type": "Feature",
  "properties": {
    "iso:country":"US",
    "sg:address":"1645 NW Baker Creek Rd",
    "sg:city":"Mcminnville",
    "sg:classifiers":[
        {
            "category":"Organizations",
            "subcategory":"Religious Organization",
            "type":"Services"
        }
    ],
    "sg:phone":"+1 503 472 5825",
    "sg:postcode":"97128",
    "sg:province":"OR",
    "wof:name":"Church of Jesus Christ of Latt",
    "wof:placetype":"venue"
},
  "geometry": {"coordinates":[-123.21551100000001,45.226261],"type":"Point"}
}