{
  "type": "Feature",
  "properties": {
    "iso:country":"US",
    "sg:address":"2598 Willamette St",
    "sg:city":"Eugene",
    "sg:classifiers":[
        {
            "category":"Shopping",
            "subcategory":"Bicycles & Sporting Goods",
            "type":"Retail Goods"
        }
    ],
    "sg:phone":"+1 541 342 4041",
    "sg:postcode":"97405",
    "sg:province":"OR",
    "wof:name":"Play It Again Sports",
    "wof:placetype":"venue"
},
  "geometry": {"coordinates":[-123.09071299999999,44.031282],"type":"Point"}
}