{
  "type": "Feature",
  "properties": {
    "iso:country":"US",
    "sg:address":"495 Wallace Ln",
    "sg:city":"Springfield",
    "sg:classifiers":[
        {
            "category":"Personal",
            "type":"Services"
        }
    ],
    "sg:phone":"+1 541 746 1759",
    "sg:postcode":"97477",
    "sg:province":"OR",
    "sg:tags":[
        "merchandise"
    ],
    "wof:name":"Mary Kay Consultant",
    "wof:placetype":"venue"
},
  "geometry": {"coordinates":[-123.03283500000001,44.055233],"type":"Point"}
}