{
  "type": "Feature",
  "properties": {
    "addr:full":"47815 Floras Lake Loop Langlois OR 97450",
    "addr:postcode":"47815;97450",
    "addr:street":"Floras Lake Loop",
    "iso:country":"US",
    "sg:address":"47815 Floras Lake Loop",
    "sg:city":"Langlois",
    "sg:classifiers":[
        {
            "category":"Farming",
            "subcategory":"Berry Farm",
            "type":"Manufacturing & Wholesale Goods"
        }
    ],
    "sg:phone":"+1 541 348 2564",
    "sg:postcode":"97450",
    "sg:province":"OR",
    "sg:tags":[
        "crop"
    ],
    "wof:name":"Marsh Haven Farm",
    "wof:placetype":"venue"
},
  "geometry": {"coordinates":[-124.46817,42.909044],"type":"Point"}
}