{
  "type": "Feature",
  "properties": {
    "addr:full":"12500 SW Broadway St Beaverton OR 97005",
    "addr:housenumber":"12500",
    "addr:postcode":"97005",
    "addr:street":"Sw Broadway St",
    "iso:country":"US",
    "sg:address":"12500 SW Broadway St",
    "sg:city":"Beaverton",
    "sg:classifiers":[
        {
            "category":"Professional",
            "subcategory":"Employment Agencies",
            "type":"Services"
        }
    ],
    "sg:phone":"+1 503 626 1716",
    "sg:postcode":"97005",
    "sg:province":"OR",
    "sg:tags":[
        "building",
        "help",
        "maintenance",
        "supply"
    ],
    "wof:name":"Maids The",
    "wof:placetype":"venue"
},
  "geometry": {"coordinates":[-122.80593,45.487342],"type":"Point"}
}