{
  "type": "Feature",
  "properties": {
    "iso:country":"US",
    "sg:address":"625 Franquette St Ste B",
    "sg:city":"Medford",
    "sg:classifiers":[
        {
            "category":"Shopping",
            "subcategory":"Catalog Store",
            "type":"Retail Goods"
        }
    ],
    "sg:phone":"+1 541 770 6700",
    "sg:postcode":"97501",
    "sg:province":"OR",
    "sg:tags":[
        "mail",
        "order",
        "online"
    ],
    "sg:website":"http://www.sanayaroman.com",
    "wof:name":"Luminessence Creations",
    "wof:placetype":"venue"
},
  "geometry": {"coordinates":[-122.865262,42.321787],"type":"Point"}
}