{
  "type": "Feature",
  "properties": {
    "addr:full":"1551 SE Lyle St Dallas OR 97338",
    "addr:housenumber":"1551",
    "addr:postcode":"97338",
    "addr:street":"Se Lyle St",
    "iso:country":"US",
    "sg:address":"1551 SE Lyle St",
    "sg:city":"Dallas",
    "sg:classifiers":[
        {
            "category":"Manufacturing",
            "subcategory":"Paper Products",
            "type":"Manufacturing & Wholesale Goods"
        }
    ],
    "sg:phone":"+1 503 623 2351",
    "sg:postcode":"97338",
    "sg:province":"OR",
    "sg:tags":[
        "corrugated",
        "solid",
        "fiber",
        "box"
    ],
    "wof:name":"Weyerhaeuser Co",
    "wof:placetype":"venue"
},
  "geometry": {"coordinates":[-123.31333600000001,44.915549],"type":"Point"}
}