{
  "type": "Feature",
  "properties": {
    "iso:country":"US",
    "sg:address":"9330 SE 242nd Ave",
    "sg:city":"Gresham",
    "sg:classifiers":[
        {
            "category":"Real Estate",
            "subcategory":"Real Estate Operator",
            "type":"Services"
        }
    ],
    "sg:phone":"+1 503 666 1036",
    "sg:postcode":"97089",
    "sg:province":"OR",
    "sg:tags":[
        "mobile",
        "home",
        "site"
    ],
    "wof:name":"Thunderbird Mobile Estate",
    "wof:placetype":"venue"
},
  "geometry": {"coordinates":[-122.412927,45.521158],"type":"Point"}
}