{
  "type": "Feature",
  "properties": {
    "iso:country":"US",
    "sg:address":"8260 SW 154th Ave",
    "sg:city":"Beaverton",
    "sg:classifiers":[
        {
            "category":"Professional",
            "subcategory":"Management & Consulting",
            "type":"Services"
        }
    ],
    "sg:phone":"+1 503 644 6201",
    "sg:postcode":"97007",
    "sg:province":"OR",
    "sg:tags":[
        "business"
    ],
    "wof:name":"Wilson Consulting",
    "wof:placetype":"venue"
},
  "geometry": {"coordinates":[-122.834633,45.460293],"type":"Point"}
}