{
  "type": "Feature",
  "properties": {
    "addr:full":"1800 NW 169th Pl Beaverton OR 97006",
    "addr:housenumber":"1800",
    "addr:postcode":"97006",
    "addr:street":"Nw 169Th Pl",
    "iso:country":"US",
    "sg:address":"1800 NW 169th Pl",
    "sg:city":"Beaverton",
    "sg:classifiers":[
        {
            "category":"Banks & Credit Unions",
            "subcategory":"Financial Services",
            "type":"Services"
        }
    ],
    "sg:phone":"+1 503 690 1970",
    "sg:postcode":"97006",
    "sg:province":"OR",
    "sg:tags":[
        "broker",
        "mortgage"
    ],
    "wof:name":"New England Financial",
    "wof:placetype":"venue"
},
  "geometry": {"coordinates":[-122.86199999999999,45.5186],"type":"Point"}
}