{
  "type": "Feature",
  "properties": {
    "iso:country":"US",
    "sg:address":"5050 NE Hoyt St Ste 655",
    "sg:city":"Portland",
    "sg:classifiers":[
        {
            "category":"Health Services",
            "subcategory":"Doctor",
            "type":"Services"
        }
    ],
    "sg:phone":"+1 503 238 0402",
    "sg:postcode":"97213",
    "sg:province":"OR",
    "sg:tags":[
        "physician",
        "pediatrics-otorhinolaryngology",
        "surgeons",
        "otorhinolaryngology",
        "nose",
        "throat",
        "surgeon",
        "ear"
    ],
    "wof:name":"Dr Andrew Pedersen",
    "wof:placetype":"venue"
},
  "geometry": {"coordinates":[-122.61135,45.52721],"type":"Point"}
}