{
  "type": "Feature",
  "properties": {
    "addr:full":"519 S Central Ave Medford OR 97501",
    "addr:housenumber":"519",
    "addr:postcode":"97501",
    "addr:street":"S Central Ave",
    "iso:country":"US",
    "sg:address":"519 S Central Ave",
    "sg:city":"Medford",
    "sg:classifiers":[
        {
            "category":"Home & Garden",
            "subcategory":"Furniture",
            "type":"Retail Goods"
        }
    ],
    "sg:phone":"+1 541 282 9673",
    "sg:postcode":"97501",
    "sg:province":"OR",
    "sg:tags":[
        "store"
    ],
    "wof:name":"Muebleria Uruapan",
    "wof:placetype":"venue"
},
  "geometry": {"coordinates":[-122.86799600000001,42.322201],"type":"Point"}
}