{
  "type": "Feature",
  "properties": {
    "iso:country":"US",
    "sg:address":"11882 SW Tallwood dr",
    "sg:city":"Tigard",
    "sg:classifiers":[
        {
            "category":"Professional",
            "subcategory":"Advertising",
            "type":"Services"
        }
    ],
    "sg:phone":"+1 503 701 8256",
    "sg:postcode":"97223",
    "sg:province":"OR",
    "sg:tags":[
        "marketing"
    ],
    "sg:website":"www.emagine.cc/index.html",
    "wof:name":"eMagine",
    "wof:placetype":"venue"
},
  "geometry": {"coordinates":[-122.820108,45.434025],"type":"Point"}
}