{
  "type": "Feature",
  "properties": {
    "iso:country":"US",
    "sg:address":"675 S Springbrook Rd B",
    "sg:city":"Newberg",
    "sg:classifiers":[
        {
            "category":"Building & Trades",
            "subcategory":"Construction",
            "type":"Services"
        }
    ],
    "sg:phone":"+1 503 538 4012",
    "sg:postcode":"97132",
    "sg:province":"OR",
    "sg:tags":[
        "painting",
        "contractor"
    ],
    "wof:name":"Top Coat Professional Painting",
    "wof:placetype":"venue"
},
  "geometry": {"coordinates":[-122.947013,45.295745],"type":"Point"}
}