{
  "type": "Feature",
  "properties": {
    "iso:country":"US",
    "sg:address":"260 SW Adams Ave",
    "sg:city":"Hillsboro",
    "sg:classifiers":[
        {
            "category":"Government",
            "subcategory":"Office",
            "type":"Public Place"
        }
    ],
    "sg:phone":"+1 503 846 8818",
    "sg:postcode":"97123",
    "sg:province":"OR",
    "sg:tags":[
        "parish",
        "government-county"
    ],
    "wof:name":"Washington County Government Community Corrections Probation & Parole",
    "wof:placetype":"venue"
},
  "geometry": {"coordinates":[-122.99124,45.520639],"type":"Point"}
}