{
  "type": "Feature",
  "properties": {
    "addr:full":"197 NE Milne Rd Hillsboro OR 97124",
    "addr:housenumber":"197",
    "addr:postcode":"97124",
    "addr:street":"Ne Milne Rd",
    "iso:country":"US",
    "sg:address":"197 NE Milne Rd",
    "sg:city":"Hillsboro",
    "sg:classifiers":[
        {
            "category":"Manufacturing",
            "subcategory":"Tools & Machinery",
            "type":"Manufacturing & Wholesale Goods"
        }
    ],
    "sg:phone":"+1 503 681 6864",
    "sg:postcode":"97124",
    "sg:province":"OR",
    "sg:tags":[
        "computer",
        "electronic",
        "mfg"
    ],
    "wof:name":"Intergrated Devised Technolgy",
    "wof:placetype":"venue"
},
  "geometry": {"coordinates":[-122.994705,45.548704],"type":"Point"}
}