{
  "type": "Feature",
  "properties": {
    "addr:full":"571 W 8th Ave Eugene OR 97401",
    "addr:housenumber":"571",
    "addr:postcode":"97401",
    "addr:street":"W 8Th Ave",
    "iso:country":"US",
    "sg:address":"571 W 8th Ave",
    "sg:city":"Eugene",
    "sg:classifiers":[
        {
            "category":"Professional",
            "subcategory":"Business Services",
            "type":"Services"
        }
    ],
    "sg:phone":"+1 541 683 4330",
    "sg:postcode":"97401",
    "sg:province":"OR",
    "wof:name":"Eclectic Tracks Co",
    "wof:placetype":"venue"
},
  "geometry": {"coordinates":[-123.101005,44.050985],"type":"Point"}
}