{
  "type": "Feature",
  "properties": {
    "iso:country":"US",
    "sg:address":"15047 SE 152nd Ave",
    "sg:city":"Clackamas",
    "sg:classifiers":[
        {
            "category":"Building & Trades",
            "subcategory":"Landscaping Services",
            "type":"Services"
        }
    ],
    "sg:phone":"+1 503 658 7781",
    "sg:postcode":"97015",
    "sg:province":"OR",
    "wof:name":"Commercial Landscape Maint",
    "wof:placetype":"venue"
},
  "geometry": {"coordinates":[-122.50594,45.412912],"type":"Point"}
}