{
  "type": "Feature",
  "properties": {
    "iso:country":"US",
    "sg:address":"1833 Tamarack St",
    "sg:city":"Florence",
    "sg:classifiers":[
        {
            "category":"Organizations",
            "subcategory":"Religious Organization",
            "type":"Services"
        }
    ],
    "sg:phone":"+1 541 997 3133",
    "sg:postcode":"97439",
    "sg:province":"OR",
    "wof:name":"Church Of Christ",
    "wof:placetype":"venue"
},
  "geometry": {"coordinates":[-124.097598,43.982794],"type":"Point"}
}