{
  "type": "Feature",
  "properties": {
    "iso:country":"US",
    "sg:address":"211 S Main St",
    "sg:city":"Condon",
    "sg:classifiers":[
        {
            "category":"Coffee & Tea",
            "type":"Food & Drink"
        },
        {
            "category":"Restaurant",
            "type":"Food & Drink"
        }
    ],
    "sg:phone":"+1 541 384 5100",
    "sg:postcode":"97823",
    "sg:province":"OR",
    "sg:tags":[
        "espresso"
    ],
    "wof:name":"Cowboy Up Cafe",
    "wof:placetype":"venue"
},
  "geometry": {"coordinates":[-120.18480700000001,45.236026],"type":"Point"}
}