{
  "type": "Feature",
  "properties": {
    "iso:country":"US",
    "sg:address":"2221 W Main St",
    "sg:city":"Medford",
    "sg:classifiers":[
        {
            "category":"Restaurant",
            "type":"Food & Drink"
        }
    ],
    "sg:phone":"+1 541 773 2230",
    "sg:postcode":"97501",
    "sg:province":"OR",
    "sg:tags":[
        "italian"
    ],
    "sg:website":"rosariosmedford.com/",
    "wof:name":"Rosario's Italian Restaurant",
    "wof:placetype":"venue"
},
  "geometry": {"coordinates":[-122.89821000000001,42.323293],"type":"Point"}
}