{
  "type": "Feature",
  "properties": {
    "addr:full":"3732 SE Glenwood St Portland OR 97202",
    "addr:housenumber":"3732",
    "addr:postcode":"97202",
    "addr:street":"Se Glenwood St",
    "iso:country":"US",
    "sg:address":"3732 SE Glenwood St",
    "sg:city":"Portland",
    "sg:classifiers":[
        {
            "category":"Professional",
            "type":"Services"
        }
    ],
    "sg:phone":"+1 503 771 6326",
    "sg:postcode":"97202",
    "sg:province":"OR",
    "sg:tags":[
        "publication",
        "editorial"
    ],
    "wof:name":"Shera Lee Connors",
    "wof:placetype":"venue"
},
  "geometry": {"coordinates":[-122.624166,45.474689],"type":"Point"}
}