{
  "type": "Feature",
  "properties": {
    "addr:full":"10040 SW Highland Dr Portland OR 97224",
    "addr:housenumber":"10040",
    "addr:postcode":"97224",
    "addr:street":"Sw Highland Dr",
    "iso:country":"US",
    "sg:address":"10040 SW Highland Dr",
    "sg:city":"Portland",
    "sg:classifiers":[
        {
            "category":"Home & Garden",
            "subcategory":"Furniture",
            "type":"Retail Goods"
        }
    ],
    "sg:phone":"+1 503 644 0442",
    "sg:postcode":"97224",
    "sg:province":"OR",
    "sg:tags":[
        "store"
    ],
    "wof:name":"Bud Built Co",
    "wof:placetype":"venue"
},
  "geometry": {"coordinates":[-122.780518,45.40802],"type":"Point"}
}