{
  "type": "Feature",
  "properties": {
    "iso:country":"US",
    "sg:address":"1036 NW Hoyt St",
    "sg:city":"Portland",
    "sg:classifiers":[
        {
            "category":"Bars & Pubs",
            "type":"Food & Drink"
        },
        {
            "category":"Bars & Pubs",
            "subcategory":"Lounge",
            "type":"Food & Drink"
        }
    ],
    "sg:menulink":"http://www.allmenus.com/or/portland/26537-low-brow-lounge/menu/",
    "sg:phone":"+1 503 226 0200",
    "sg:postcode":"97209",
    "sg:province":"OR",
    "sg:tags":[
        "american"
    ],
    "wof:name":"Low Brow Lounge",
    "wof:placetype":"venue"
},
  "geometry": {"coordinates":[-122.681648,45.527252],"type":"Point"}
}