{
  "type": "Feature",
  "properties": {
    "iso:country":"US",
    "sg:address":"4201 NE Fremont St",
    "sg:city":"Portland",
    "sg:classifiers":[
        {
            "category":"Shopping",
            "subcategory":"Florist",
            "type":"Retail Goods"
        }
    ],
    "sg:phone":"+1 503 281 5501",
    "sg:postcode":"97213",
    "sg:province":"OR",
    "wof:name":"Beaumont Florist",
    "wof:placetype":"venue"
},
  "geometry": {"coordinates":[-122.620003,45.548401],"type":"Point"}
}