{
  "type": "Feature",
  "properties": {
    "iso:country":"US",
    "sg:address":"19612 S Ferguson Rd",
    "sg:city":"Oregon City",
    "sg:classifiers":[
        {
            "category":"Real Estate",
            "subcategory":"Real Estate Agent",
            "type":"Services"
        }
    ],
    "sg:phone":"+1 503 632 7753",
    "sg:postcode":"97045",
    "sg:province":"OR",
    "wof:name":"Kneisel Realty",
    "wof:placetype":"venue"
},
  "geometry": {"coordinates":[-122.52765100000001,45.321945],"type":"Point"}
}