{
  "type": "Feature",
  "properties": {
    "iso:country":"US",
    "sg:address":"69873 Summerville Rd",
    "sg:city":"Summerville",
    "sg:classifiers":[
        {
            "category":"Building & Trades",
            "subcategory":"Plumbing",
            "type":"Services"
        }
    ],
    "sg:phone":"+1 541 534 5411",
    "sg:postcode":"97876",
    "sg:province":"OR",
    "sg:tags":[
        "contractor"
    ],
    "wof:name":"Howard Butts Plumbing",
    "wof:placetype":"venue"
},
  "geometry": {"coordinates":[-118.025324,45.541649],"type":"Point"}
}