{
  "type": "Feature",
  "properties": {
    "iso:country":"US",
    "sg:address":"17233 SE Mill St",
    "sg:city":"Portland",
    "sg:classifiers":[
        {
            "category":"Building & Trades",
            "subcategory":"Plumbing",
            "type":"Services"
        }
    ],
    "sg:phone":"+1 503 762 2474",
    "sg:postcode":"97233",
    "sg:province":"OR",
    "sg:tags":[
        "contractor"
    ],
    "wof:name":"Performance Mech Htg & Coolg",
    "wof:placetype":"venue"
},
  "geometry": {"coordinates":[-122.484872,45.511034],"type":"Point"}
}