{
  "type": "Feature",
  "properties": {
    "addr:full":"90241 Greenwood Dr Walterville OR 97489",
    "addr:housenumber":"90241",
    "addr:postcode":"97489",
    "addr:street":"Greenwood Dr Walterville",
    "iso:country":"US",
    "sg:address":"90241 Greenwood Dr",
    "sg:city":"Walterville",
    "sg:classifiers":[
        {
            "category":"Professional",
            "subcategory":"Secretarial Services",
            "type":"Services"
        }
    ],
    "sg:phone":"+1 541 896 3033",
    "sg:postcode":"97489",
    "sg:province":"OR",
    "sg:tags":[
        "clerk",
        "court"
    ],
    "wof:name":"Pamela Reim",
    "wof:placetype":"venue"
},
  "geometry": {"coordinates":[-122.635839,44.117056],"type":"Point"}
}