{
  "type": "Feature",
  "properties": {
    "addr:full":"1215 W 6th St The Dalles OR 97058",
    "addr:housenumber":"1215",
    "addr:postcode":"97058",
    "addr:street":"W 6Th St",
    "iso:country":"US",
    "sg:address":"1215 W 6th St",
    "sg:city":"The Dalles",
    "sg:classifiers":[
        {
            "category":"Shopping",
            "subcategory":"Department Store",
            "type":"Retail Goods"
        }
    ],
    "sg:phone":"+1 541 296 1748",
    "sg:postcode":"97058",
    "sg:province":"OR",
    "wof:name":"Fred Meyer",
    "wof:placetype":"venue"
},
  "geometry": {"coordinates":[-121.203193,45.608452],"type":"Point"}
}