{
  "type": "Feature",
  "properties": {
    "iso:country":"US",
    "sg:address":"6680 Thurston Rd",
    "sg:city":"Springfield",
    "sg:classifiers":[
        {
            "category":"Organizations",
            "subcategory":"Religious Organization",
            "type":"Services"
        }
    ],
    "sg:phone":"+1 541 746 4228",
    "sg:postcode":"97478",
    "sg:province":"OR",
    "sg:tags":[
        "church"
    ],
    "wof:name":"Christian Thurston Church",
    "wof:placetype":"venue"
},
  "geometry": {"coordinates":[-122.907825,44.053665],"type":"Point"}
}