{
  "type": "Feature",
  "properties": {
    "iso:country":"US",
    "sg:address":"1200 NW Saint Andrews Pt",
    "sg:city":"Mcminnville",
    "sg:classifiers":[
        {
            "category":"Shopping",
            "subcategory":"Catalog Store",
            "type":"Retail Goods"
        }
    ],
    "sg:phone":"+1 503 472 6454",
    "sg:postcode":"97128",
    "sg:province":"OR",
    "sg:tags":[
        "marketing",
        "direct",
        "oregon",
        "online",
        "mail",
        "order",
        "wine"
    ],
    "sg:website":"http://www.oregonwines.com",
    "wof:name":"Oregon Wine Co",
    "wof:placetype":"venue"
},
  "geometry": {"coordinates":[-123.212273,45.223209],"type":"Point"}
}