{
  "type": "Feature",
  "properties": {
    "iso:country":"US",
    "sg:address":"2149 Dewey St",
    "sg:city":"Eugene",
    "sg:classifiers":[
        {
            "category":"Education",
            "subcategory":"Junior College",
            "type":"Public Place"
        }
    ],
    "sg:phone":"+1 541 688 2923",
    "sg:postcode":"97402",
    "sg:province":"OR",
    "wof:name":"Compu Help",
    "wof:placetype":"venue"
},
  "geometry": {"coordinates":[-123.179515,44.087776],"type":"Point"}
}