{
  "type": "Feature",
  "properties": {
    "iso:country":"US",
    "sg:address":"18615 SW Longacre St",
    "sg:city":"Beaverton",
    "sg:classifiers":[
        {
            "category":"Banks & Credit Unions",
            "subcategory":"Bank",
            "type":"Services"
        }
    ],
    "sg:phone":"+1 503 642 0159",
    "sg:postcode":"97006",
    "sg:province":"OR",
    "sg:tags":[
        "institution",
        "business"
    ],
    "wof:name":"Caterpillar",
    "wof:placetype":"venue"
},
  "geometry": {"coordinates":[-122.8707,45.511311],"type":"Point"}
}