{
  "type": "Feature",
  "properties": {
    "addr:full":"2028 Steele Rd The Dalles OR 97058",
    "addr:housenumber":"2028",
    "addr:postcode":"97058",
    "addr:street":"Steele Rd",
    "iso:country":"US",
    "sg:address":"2028 Steele Rd",
    "sg:city":"The Dalles",
    "sg:classifiers":[
        {
            "category":"Freight",
            "type":"Transportation"
        }
    ],
    "sg:phone":"+1 541 296 6945",
    "sg:postcode":"97058",
    "sg:province":"OR",
    "sg:tags":[
        "local",
        "storage",
        "trucking"
    ],
    "wof:name":"D A Phetteplace",
    "wof:placetype":"venue"
},
  "geometry": {"coordinates":[-121.16557899999999,45.576505],"type":"Point"}
}