{
  "type": "Feature",
  "properties": {
    "addr:full":"10540 SW Tualatin Sherwood Rd Tualatin OR 97062",
    "addr:housenumber":"10540",
    "addr:postcode":"97062",
    "addr:street":"Sw Tualatin Sherwood Rd",
    "iso:country":"US",
    "sg:address":"10540 SW Tualatin Sherwood Rd",
    "sg:city":"Tualatin",
    "sg:classifiers":[
        {
            "category":"Building & Trades",
            "subcategory":"Equipment Rental",
            "type":"Services"
        }
    ],
    "sg:phone":"+1 503 885 9611",
    "sg:postcode":"97062",
    "sg:province":"OR",
    "sg:tags":[
        "yard"
    ],
    "wof:name":"Hertz Equipment Rental",
    "wof:placetype":"venue"
},
  "geometry": {"coordinates":[-122.788348,45.374782],"type":"Point"}
}