{
  "type": "Feature",
  "properties": {
    "addr:full":"3113 Crestview Dr Newberg OR 97132",
    "addr:housenumber":"3113",
    "addr:postcode":"97132",
    "addr:street":"Crestview Dr",
    "iso:country":"US",
    "sg:address":"3113 Crestview Dr",
    "sg:city":"Newberg",
    "sg:classifiers":[
        {
            "category":"Banks & Credit Unions",
            "subcategory":"Financial Services",
            "type":"Services"
        }
    ],
    "sg:phone":"+1 503 537 1000",
    "sg:postcode":"97132",
    "sg:province":"OR",
    "sg:tags":[
        "company",
        "holding"
    ],
    "wof:name":"Austin Industries",
    "wof:placetype":"venue"
},
  "geometry": {"coordinates":[-122.946139,45.315097],"type":"Point"}
}