{
  "type": "Feature",
  "properties": {
    "iso:country":"US",
    "sg:address":"505 SW Birdsdale Dr",
    "sg:city":"Gresham",
    "sg:classifiers":[
        {
            "category":"Education",
            "subcategory":"School",
            "type":"Public Place"
        }
    ],
    "sg:phone":"+1 503 661 6226",
    "sg:postcode":"97080",
    "sg:province":"OR",
    "wof:name":"Hollydale Elementary School",
    "wof:placetype":"venue"
},
  "geometry": {"coordinates":[-122.454006,45.493411],"type":"Point"}
}