{
  "type": "Feature",
  "properties": {
    "addr:full":"505 SW Birdsdale Dr Gresham OR 97080",
    "addr:housenumber":"505",
    "addr:postcode":"97080",
    "addr:street":"Sw Birdsdale Dr",
    "iso:country":"US",
    "sg:address":"505 SW Birdsdale Dr",
    "sg:city":"Gresham",
    "sg:classifiers":[
        {
            "category":"Education",
            "subcategory":"School",
            "type":"Public Place"
        }
    ],
    "sg:phone":"+1 503 661 6226",
    "sg:postcode":"97080",
    "sg:province":"OR",
    "wof:name":"Hollydale Elementary School",
    "wof:placetype":"venue"
},
  "geometry": {"coordinates":[-122.45400600000001,45.493411],"type":"Point"}
}