{
  "type": "Feature",
  "properties": {
    "addr:full":"32198 E Punkin Center Rd Hermiston OR 97838",
    "addr:housenumber":"32198",
    "addr:postcode":"97838",
    "addr:street":"E Punkin Center Rd",
    "iso:country":"US",
    "sg:address":"32198 E Punkin Center Rd",
    "sg:city":"Hermiston",
    "sg:classifiers":[
        {
            "category":"Freight",
            "type":"Transportation"
        }
    ],
    "sg:phone":"+1 541 564 8855",
    "sg:postcode":"97838",
    "sg:province":"OR",
    "sg:tags":[
        "operator",
        "local",
        "trucking"
    ],
    "wof:name":"Ramirez Gerardo Trucking",
    "wof:placetype":"venue"
},
  "geometry": {"coordinates":[-119.243453,45.864402],"type":"Point"}
}