{
  "type": "Feature",
  "properties": {
    "iso:country":"US",
    "sg:address":"312 SE 205th Pl",
    "sg:city":"Gresham",
    "sg:classifiers":[
        {
            "category":"Restaurant",
            "type":"Food & Drink"
        }
    ],
    "sg:phone":"+1 503 665 6398",
    "sg:postcode":"97030",
    "sg:province":"OR",
    "sg:tags":[
        "eating"
    ],
    "wof:name":"Mjs Deli",
    "wof:placetype":"venue"
},
  "geometry": {"coordinates":[-122.451193,45.519241],"type":"Point"}
}