{
  "type": "Feature",
  "properties": {
    "addr:full":"4035 SE Division St Portland OR 97202",
    "addr:housenumber":"4035",
    "addr:postcode":"97202",
    "addr:street":"Se Division St",
    "iso:country":"US",
    "sg:address":"4035 SE Division St",
    "sg:city":"Portland",
    "sg:classifiers":[
        {
            "category":"Retail",
            "subcategory":"Repair Shop",
            "type":"Services"
        }
    ],
    "sg:phone":"+1 503 234 0873",
    "sg:postcode":"97202",
    "sg:province":"OR",
    "sg:tags":[
        "appliance"
    ],
    "wof:name":"Division Appliance Svc Co",
    "wof:placetype":"venue"
},
  "geometry": {"coordinates":[-122.620634,45.50486],"type":"Point"}
}