{
  "type": "Feature",
  "properties": {
    "addr:full":"636 SE 10th Ave Portland OR 97214",
    "addr:housenumber":"636",
    "addr:postcode":"97214",
    "addr:street":"Se 10Th Ave",
    "iso:country":"US",
    "sg:address":"636 SE 10th Ave",
    "sg:city":"Portland",
    "sg:classifiers":[
        {
            "category":"Wholesale",
            "subcategory":"Auto Parts",
            "type":"Manufacturing & Wholesale Goods"
        }
    ],
    "sg:phone":"+1 503 232 9557",
    "sg:postcode":"97214",
    "sg:province":"OR",
    "sg:tags":[
        "automobile",
        "supply"
    ],
    "sg:website":"http://www.worldpac.com",
    "wof:name":"World Pack",
    "wof:placetype":"venue"
},
  "geometry": {"coordinates":[-122.655663,45.518382],"type":"Point"}
}