{
  "type": "Feature",
  "properties": {
    "addr:full":"10250 SW Greenburg Rd Portland OR 97223",
    "addr:housenumber":"10250",
    "addr:postcode":"97223",
    "addr:street":"Sw Greenburg Rd",
    "iso:country":"US",
    "sg:address":"10250 SW Greenburg Rd",
    "sg:city":"Portland",
    "sg:classifiers":[
        {
            "category":"Professional",
            "subcategory":"Accounting & Tax Preparation",
            "type":"Services"
        }
    ],
    "sg:phone":"+1 503 246 2567",
    "sg:postcode":"97223",
    "sg:province":"OR",
    "sg:tags":[
        "payment",
        "freight"
    ],
    "wof:name":"Software Sltions Unlimited Inc",
    "wof:placetype":"venue"
},
  "geometry": {"coordinates":[-122.777022,45.444231],"type":"Point"}
}