{
  "type": "Feature",
  "properties": {
    "iso:country":"US",
    "sg:address":"1414 Adams Ave",
    "sg:city":"La Grande",
    "sg:classifiers":[
        {
            "category":"Shopping",
            "subcategory":"Florist",
            "type":"Retail Goods"
        }
    ],
    "sg:phone":"+1 541 963 2126",
    "sg:postcode":"97850",
    "sg:province":"OR",
    "sg:website":"www.fitzgeraldflowers.com",
    "wof:name":"Fitzgerald Flowers",
    "wof:placetype":"venue"
},
  "geometry": {"coordinates":[-118.09226099999999,45.327102],"type":"Point"}
}