{
  "type": "Feature",
  "properties": {
    "iso:country":"US",
    "sg:address":"67804 Promise Rd",
    "sg:city":"Wallowa",
    "sg:phone":"+1 541 886 9435",
    "sg:postcode":"97885",
    "sg:province":"OR",
    "sg:tags":[
        "beef",
        "farm",
        "crop",
        "field",
        "cattle",
        "feedlot"
    ],
    "wof:name":"Walking Cane Ranch",
    "wof:placetype":"venue"
},
  "geometry": {"coordinates":[-117.558757,45.612419],"type":"Point"}
}