{
  "type": "Feature",
  "properties": {
    "iso:country":"US",
    "sg:address":"924 Bellview Ave",
    "sg:city":"Ashland",
    "sg:classifiers":[
        {
            "category":"Professional",
            "subcategory":"Accounting & Tax Preparation",
            "type":"Services"
        }
    ],
    "sg:phone":"+1 541 482 2211",
    "sg:postcode":"97520",
    "sg:province":"OR",
    "sg:tags":[
        "accountant"
    ],
    "wof:name":"Virginia L Vogel CPA PC",
    "wof:placetype":"venue"
},
  "geometry": {"coordinates":[-122.673081,42.175525],"type":"Point"}
}