{
  "type": "Feature",
  "properties": {
    "iso:country":"US",
    "sg:address":"1001 SE Water Ave",
    "sg:city":"Portland",
    "sg:classifiers":[
        {
            "category":"Professional",
            "subcategory":"Computer Services",
            "type":"Services"
        }
    ],
    "sg:phone":"+1 503 232 2555",
    "sg:postcode":"97214",
    "sg:province":"OR",
    "sg:tags":[
        "programing",
        "custom"
    ],
    "wof:name":"Origin Inc",
    "wof:placetype":"venue"
},
  "geometry": {"coordinates":[-122.66583,45.515104],"type":"Point"}
}