{
  "type": "Feature",
  "properties": {
    "iso:country":"US",
    "sg:address":"10822 SE Bush St",
    "sg:city":"Portland",
    "sg:classifiers":[
        {
            "category":"Education",
            "subcategory":"School",
            "type":"Public Place"
        }
    ],
    "sg:phone":"+1 503 256 6554",
    "sg:postcode":"97266",
    "sg:province":"OR",
    "sg:tags":[
        "high",
        "middle",
        "elementary"
    ],
    "wof:name":"Schools Public",
    "wof:placetype":"venue"
},
  "geometry": {"coordinates":[-122.55242800000001,45.494783],"type":"Point"}
}