{
  "type": "Feature",
  "properties": {
    "addr:full":"3673 SW Hall Blvd Beaverton OR 97005",
    "addr:housenumber":"3673",
    "addr:postcode":"97005",
    "addr:street":"Sw Hall Blvd",
    "iso:country":"US",
    "sg:address":"3673 SW Hall Blvd",
    "sg:city":"Beaverton",
    "sg:classifiers":[
        {
            "category":"Personal",
            "subcategory":"Beauty Salon",
            "type":"Services"
        }
    ],
    "sg:phone":"+1 503 646 7727",
    "sg:postcode":"97005",
    "sg:province":"OR",
    "sg:tags":[
        "hair"
    ],
    "wof:name":"Jeanne Salon",
    "wof:placetype":"venue"
},
  "geometry": {"coordinates":[-122.807478,45.493353],"type":"Point"}
}