{
  "type": "Feature",
  "properties": {
    "addr:full":"1124 SE 11th Ave Portland OR 97214",
    "addr:housenumber":"1124",
    "addr:postcode":"97214",
    "addr:street":"Se 11Th Ave",
    "iso:country":"US",
    "sg:address":"1124 SE 11th Ave",
    "sg:city":"Portland",
    "sg:classifiers":[
        {
            "category":"Manufacturing",
            "subcategory":"Metals",
            "type":"Manufacturing & Wholesale Goods"
        }
    ],
    "sg:phone":"+1 503 234 6995",
    "sg:postcode":"97214",
    "sg:province":"OR",
    "sg:tags":[
        "finisher"
    ],
    "wof:name":"Precision Electro Coat Inc",
    "wof:placetype":"venue"
},
  "geometry": {"coordinates":[-122.654602,45.514528],"type":"Point"}
}