{
  "type": "Feature",
  "properties": {
    "iso:country":"US",
    "sg:address":"26298 S Jones Rd",
    "sg:city":"Beavercreek",
    "sg:classifiers":[
        {
            "category":"Building & Trades",
            "subcategory":"Plumbing",
            "type":"Services"
        }
    ],
    "sg:phone":"+1 503 632 3882",
    "sg:postcode":"97004",
    "sg:province":"OR",
    "sg:tags":[
        "contractor"
    ],
    "wof:name":"Pats Pumps & Whatever",
    "wof:placetype":"venue"
},
  "geometry": {"coordinates":[-122.523042,45.2273],"type":"Point"}
}