{
  "type": "Feature",
  "properties": {
    "iso:country":"US",
    "sg:address":"8010 SW Nimbus Ave",
    "sg:city":"Beaverton",
    "sg:classifiers":[
        {
            "category":"Shopping",
            "subcategory":"Computers & Home Electronics",
            "type":"Retail Goods"
        }
    ],
    "sg:phone":"+1 503 641 3510",
    "sg:postcode":"97008",
    "sg:province":"OR",
    "sg:tags":[
        "equipment",
        "audio",
        "video"
    ],
    "wof:name":"Chelsea Audio Video",
    "wof:placetype":"venue"
},
  "geometry": {"coordinates":[-122.78858,45.461129],"type":"Point"}
}