{
  "type": "Feature",
  "properties": {
    "iso:country":"US",
    "sg:address":"32380 Eric Todd Ln",
    "sg:city":"Creswell",
    "sg:classifiers":[
        {
            "category":"Building & Trades",
            "subcategory":"Construction",
            "type":"Services"
        }
    ],
    "sg:phone":"+1 541 895 3762",
    "sg:postcode":"97426",
    "sg:province":"OR",
    "sg:tags":[
        "water",
        "well",
        "drilling"
    ],
    "wof:name":"White Water Well Drilling Inc",
    "wof:placetype":"venue"
},
  "geometry": {"coordinates":[-123.06650399999999,43.895512],"type":"Point"}
}