{
  "type": "Feature",
  "properties": {
    "iso:country":"US",
    "sg:address":"5026 NE 31st Ave-32nd Ave Aly",
    "sg:city":"Portland",
    "sg:classifiers":[
        {
            "category":"Personal",
            "subcategory":"Beauty Salon",
            "type":"Services"
        }
    ],
    "sg:phone":"+1 503 493 7373",
    "sg:postcode":"97211",
    "sg:province":"OR",
    "sg:tags":[
        "shop"
    ],
    "wof:name":"Headtrip Salon",
    "wof:placetype":"venue"
},
  "geometry": {"coordinates":[-122.633371,45.560128],"type":"Point"}
}