{
  "type": "Feature",
  "properties": {
    "iso:country":"US",
    "sg:address":"2591 Conser Rd NE",
    "sg:city":"Albany",
    "sg:classifiers":[
        {
            "category":"Building & Trades",
            "subcategory":"Construction",
            "type":"Services"
        }
    ],
    "sg:phone":"+1 541 928 6807",
    "sg:postcode":"97321",
    "sg:province":"OR",
    "sg:tags":[
        "wallcoverings-installation",
        "wallpaper",
        "painting",
        "contractor"
    ],
    "wof:name":"Jb Painting",
    "wof:placetype":"venue"
},
  "geometry": {"coordinates":[-123.07322600000001,44.681111],"type":"Point"}
}