{
  "type": "Feature",
  "properties": {
    "iso:country":"US",
    "sg:address":"5602 Goodrich Hwy",
    "sg:city":"Oakland",
    "sg:classifiers":[
        {
            "category":"Banks & Credit Unions",
            "subcategory":"Bank",
            "type":"Services"
        }
    ],
    "sg:phone":"+1 541 459 4949",
    "sg:postcode":"97462",
    "sg:province":"OR",
    "sg:tags":[
        "loan",
        "real estate"
    ],
    "wof:name":"Marquise Mortgage",
    "wof:placetype":"venue"
},
  "geometry": {"coordinates":[-123.28936299999999,43.508792],"type":"Point"}
}