{
  "type": "Feature",
  "properties": {
    "iso:country":"US",
    "sg:address":"3330 NW Yeon Ave",
    "sg:city":"Portland",
    "sg:classifiers":[
        {
            "category":"Professional",
            "type":"Services"
        },
        {
            "category":"Restaurant",
            "type":"Food & Drink"
        },
        {
            "category":"Food & Beverages",
            "subcategory":"Bakery",
            "type":"Retail Goods"
        }
    ],
    "sg:phone":"+1 503 225 1300",
    "sg:postcode":"97210",
    "sg:province":"OR",
    "sg:tags":[
        "breakfast",
        "sandwich",
        "brunch",
        "caterer"
    ],
    "wof:name":"Tubby's Deli",
    "wof:placetype":"venue"
},
  "geometry": {"coordinates":[-122.70716899999999,45.545447],"type":"Point"}
}