{
  "type": "Feature",
  "properties": {
    "iso:country":"US",
    "sg:address":"3988 Hwy 201",
    "sg:city":"Ontario",
    "sg:classifiers":[
        {
            "category":"Retail",
            "subcategory":"Auto Repair",
            "type":"Services"
        }
    ],
    "sg:phone":"+1 541 889 6161",
    "sg:postcode":"97914",
    "sg:province":"OR",
    "sg:tags":[
        "towing",
        "crane",
        "salvage"
    ],
    "wof:name":"Treasure Valley Salvage Co",
    "wof:placetype":"venue"
},
  "geometry": {"coordinates":[-117.00529899999999,44.00883],"type":"Point"}
}