{
  "type": "Feature",
  "properties": {
    "iso:country":"US",
    "sg:address":"1548 Hallet Ct NW",
    "sg:city":"Salem",
    "sg:classifiers":[
        {
            "category":"Social Services",
            "subcategory":"Adult Care",
            "type":"Services"
        }
    ],
    "sg:phone":"+1 503 371 7354",
    "sg:postcode":"97304",
    "sg:province":"OR",
    "sg:tags":[
        "home",
        "residential"
    ],
    "wof:name":"Four Seasons Residential Care",
    "wof:placetype":"venue"
},
  "geometry": {"coordinates":[-123.074736,44.956713],"type":"Point"}
}