{
  "type": "Feature",
  "properties": {
    "iso:country":"US",
    "sg:address":"2451 SE Salmon St",
    "sg:city":"Portland",
    "sg:classifiers":[
        {
            "category":"Professional",
            "subcategory":"Business Services",
            "type":"Services"
        },
        {
            "category":"Insurance",
            "subcategory":"Health Insurance",
            "type":"Services"
        }
    ],
    "sg:phone":"+1 503 312 0596",
    "sg:postcode":"97214",
    "sg:province":"OR",
    "sg:tags":[
        "food",
        "delivery",
        "market"
    ],
    "sg:website":"ourcommunitypantry.com",
    "wof:name":"Our Community Pantry",
    "wof:placetype":"venue"
},
  "geometry": {"coordinates":[-122.64036400000001,45.51453],"type":"Point"}
}