{
  "type": "Feature",
  "properties": {
    "iso:country":"US",
    "sg:address":"700 Hodgdon Rd",
    "sg:city":"Tillamook",
    "sg:classifiers":[
        {
            "category":"Farming",
            "subcategory":"Dairy Farm",
            "type":"Manufacturing & Wholesale Goods"
        }
    ],
    "sg:phone":"+1 503 842 5305",
    "sg:postcode":"97141",
    "sg:province":"OR",
    "wof:name":"Shady Oak Dairy",
    "wof:placetype":"venue"
},
  "geometry": {"coordinates":[-123.770833,45.453893],"type":"Point"}
}