{
  "type": "Feature",
  "properties": {
    "addr:full":"1618 NW Kingston Ave Bend OR 97701",
    "addr:housenumber":"1618",
    "addr:postcode":"97701",
    "addr:street":"Nw Kingston Ave",
    "iso:country":"US",
    "sg:address":"1618 NW Kingston Ave",
    "sg:city":"Bend",
    "sg:classifiers":[
        {
            "category":"Professional",
            "type":"Services"
        }
    ],
    "sg:phone":"+1 541 330 9760",
    "sg:postcode":"97701",
    "sg:province":"OR",
    "wof:name":"Facials By M",
    "wof:placetype":"venue"
},
  "geometry": {"coordinates":[-121.336719,44.058288],"type":"Point"}
}