{
  "type": "Feature",
  "properties": {
    "iso:country":"US",
    "sg:address":"900 SW 5th Ave Ste 2600",
    "sg:city":"Portland",
    "sg:classifiers":[
        {
            "category":"Professional",
            "subcategory":"Lawyer & Legal Services",
            "type":"Services"
        }
    ],
    "sg:phone":"+1 503 224 3380",
    "sg:postcode":"97204",
    "sg:province":"OR",
    "wof:name":"Panarella Lili R Atty Stoel Rives Llp Attys",
    "wof:placetype":"venue"
},
  "geometry": {"coordinates":[-122.675003,45.5187],"type":"Point"}
}