{
  "type": "Feature",
  "properties": {
    "iso:country":"US",
    "sg:address":"12265 NW Marshall St",
    "sg:city":"Portland",
    "sg:classifiers":[
        {
            "category":"Building & Trades",
            "subcategory":"Construction",
            "type":"Services"
        }
    ],
    "sg:phone":"+1 503 626 6819",
    "sg:postcode":"97229",
    "sg:province":"OR",
    "sg:tags":[
        "improvement",
        "tenant",
        "contractor"
    ],
    "wof:name":"Arsch Consulting & Cnstr Bus",
    "wof:placetype":"venue"
},
  "geometry": {"coordinates":[-122.802999,45.531106],"type":"Point"}
}