{
  "type": "Feature",
  "properties": {
    "iso:country":"US",
    "sg:address":"68890 Nicolai Rd",
    "sg:city":"Rainier",
    "sg:classifiers":[
        {
            "category":"Real Estate",
            "subcategory":"Real Estate Agent",
            "type":"Services"
        }
    ],
    "sg:phone":"+1 503 556 4107",
    "sg:postcode":"97048",
    "sg:province":"OR",
    "sg:tags":[
        "inspection"
    ],
    "sg:website":"www.justicehomeinspections.com",
    "wof:name":"Justice Home Inspections",
    "wof:placetype":"venue"
},
  "geometry": {"coordinates":[-122.91644700000001,45.996354],"type":"Point"}
}