{
  "type": "Feature",
  "properties": {
    "iso:country":"US",
    "sg:address":"9427 SW Barnes Road Suite 498",
    "sg:city":"Portland",
    "sg:classifiers":[
        {
            "category":"Health Services",
            "subcategory":"Doctor",
            "type":"Services"
        }
    ],
    "sg:phone":"+1 503 297 6234",
    "sg:postcode":"97225",
    "sg:province":"OR",
    "sg:tags":[
        "cardiologist"
    ],
    "wof:name":"Columbia Cardiology Associates",
    "wof:placetype":"venue"
},
  "geometry": {"coordinates":[-122.77247,45.509103],"type":"Point"}
}