{
  "type": "Feature",
  "properties": {
    "iso:country":"US",
    "sg:address":"983 Lloyd Center",
    "sg:city":"Portland",
    "sg:classifiers":[
        {
            "category":"Shopping",
            "subcategory":"Hobbies, Toys, & Games",
            "type":"Retail Goods"
        }
    ],
    "sg:phone":"+1 503 284 2997",
    "sg:postcode":"97232",
    "sg:province":"OR",
    "sg:tags":[
        "item"
    ],
    "wof:name":"Kb Toys",
    "wof:placetype":"venue"
},
  "geometry": {"coordinates":[-122.65200299999999,45.531977],"type":"Point"}
}