{
  "type": "Feature",
  "properties": {
    "addr:full":"5758 NW Deschutes Dr Portland OR 97229",
    "addr:housenumber":"5758",
    "addr:postcode":"97229",
    "addr:street":"Nw Deschutes Dr",
    "iso:country":"US",
    "sg:address":"5758 NW Deschutes Dr",
    "sg:city":"Portland",
    "sg:classifiers":[
        {
            "category":"Professional",
            "subcategory":"Management & Consulting",
            "type":"Services"
        }
    ],
    "sg:phone":"+1 503 690 6585",
    "sg:postcode":"97229",
    "sg:province":"OR",
    "wof:name":"Human Resources Partners",
    "wof:placetype":"venue"
},
  "geometry": {"coordinates":[-122.892599,45.560634],"type":"Point"}
}