{
  "type": "Feature",
  "properties": {
    "addr:full":"5976 Park Ct SE Salem OR 97306",
    "addr:housenumber":"5976",
    "addr:postcode":"97306",
    "addr:street":"Park Ct Se",
    "iso:country":"US",
    "sg:address":"5976 Park Ct SE",
    "sg:city":"Salem",
    "sg:classifiers":[
        {
            "category":"Food & Beverages",
            "subcategory":"Bakery",
            "type":"Retail Goods"
        }
    ],
    "sg:phone":"+1 503 581 8746",
    "sg:postcode":"97306",
    "sg:province":"OR",
    "sg:tags":[
        "grocery"
    ],
    "wof:name":"Bread Baron",
    "wof:placetype":"venue"
},
  "geometry": {"coordinates":[-123.02432399999999,44.868898],"type":"Point"}
}