{
  "type": "Feature",
  "properties": {
    "iso:country":"US",
    "sg:address":"3350 Crestview Dr S",
    "sg:city":"Salem",
    "sg:classifiers":[
        {
            "category":"Professional",
            "subcategory":"Business Services",
            "type":"Services"
        }
    ],
    "sg:phone":"+1 503 930 5220",
    "sg:postcode":"97302",
    "sg:province":"OR",
    "sg:tags":[
        "freelance",
        "corporate",
        "public",
        "relations",
        "writing"
    ],
    "wof:name":"Cruz Communications",
    "wof:placetype":"venue"
},
  "geometry": {"coordinates":[-123.059111,44.905638],"type":"Point"}
}