{
  "type": "Feature",
  "properties": {
    "iso:country":"US",
    "sg:address":"4550 Kruse Way",
    "sg:city":"Lake Oswego",
    "sg:classifiers":[
        {
            "category":"Health Services",
            "subcategory":"Health Practitioner",
            "type":"Services"
        }
    ],
    "sg:phone":"+1 503 635 2489",
    "sg:postcode":"97035",
    "sg:province":"OR",
    "wof:name":"Hank Robb PHD",
    "wof:placetype":"venue"
},
  "geometry": {"coordinates":[-122.722897,45.417775],"type":"Point"}
}