{
  "type": "Feature",
  "properties": {
    "iso:country":"US",
    "sg:address":"178 S Main St",
    "sg:city":"Milton Freewater",
    "sg:classifiers":[
        {
            "category":"Real Estate",
            "subcategory":"Real Estate Services",
            "type":"Services"
        }
    ],
    "sg:phone":"+1 541 938 3327",
    "sg:postcode":"97862",
    "sg:province":"OR",
    "sg:tags":[
        "company",
        "title"
    ],
    "wof:name":"Pioneer Escrow",
    "wof:placetype":"venue"
},
  "geometry": {"coordinates":[-118.389083,45.933913],"type":"Point"}
}