{
  "type": "Feature",
  "properties": {
    "iso:country":"US",
    "sg:address":"3280 SW 185th Ave",
    "sg:city":"Beaverton",
    "sg:classifiers":[
        {
            "category":"Personal",
            "subcategory":"Beauty Salon",
            "type":"Services"
        }
    ],
    "sg:phone":"+1 503 629 2000",
    "sg:postcode":"97006",
    "sg:province":"OR",
    "sg:tags":[
        "shop"
    ],
    "wof:name":"Copage Salon & Beauty Products",
    "wof:placetype":"venue"
},
  "geometry": {"coordinates":[-122.867135,45.497418],"type":"Point"}
}