{
  "type": "Feature",
  "properties": {
    "iso:country":"US",
    "sg:address":"8401 NE Halsey St",
    "sg:city":"Portland",
    "sg:classifiers":[
        {
            "category":"Shopping",
            "subcategory":"Computers & Home Electronics",
            "type":"Retail Goods"
        }
    ],
    "sg:phone":"+1 503 255 7555",
    "sg:postcode":"97220",
    "sg:province":"OR",
    "sg:tags":[
        "equipment",
        "electronic",
        "supply"
    ],
    "wof:name":"Radio Shack",
    "wof:placetype":"venue"
},
  "geometry": {"coordinates":[-122.57590500000001,45.533567],"type":"Point"}
}