{
  "type": "Feature",
  "properties": {
    "iso:country":"US",
    "sg:address":"5200 SW Macadam Ave",
    "sg:city":"Portland",
    "sg:classifiers":[
        {
            "category":"Banks & Credit Unions",
            "subcategory":"Investment Brokerage",
            "type":"Services"
        }
    ],
    "sg:phone":"+1 503 241 4949",
    "sg:postcode":"97219",
    "sg:province":"OR",
    "sg:tags":[
        "stock",
        "bond"
    ],
    "wof:name":"Brookstreet Securities",
    "wof:placetype":"venue"
},
  "geometry": {"coordinates":[-122.67525500000001,45.485341],"type":"Point"}
}