{
  "type": "Feature",
  "properties": {
    "iso:country":"US",
    "sg:address":"2630 Lone Oak Way",
    "sg:city":"Eugene",
    "sg:classifiers":[
        {
            "category":"Social Services",
            "type":"Services"
        }
    ],
    "sg:phone":"+1 541 607 5025",
    "sg:postcode":"97404",
    "sg:province":"OR",
    "sg:tags":[
        "senior",
        "citizen"
    ],
    "sg:website":"www.goodneighbor.com",
    "wof:name":"Good Neighbor Care",
    "wof:placetype":"venue"
},
  "geometry": {"coordinates":[-123.12466499999999,44.100397],"type":"Point"}
}