{
  "type": "Feature",
  "properties": {
    "iso:country":"US",
    "sg:address":"9002 N Sever Ct",
    "sg:city":"Portland",
    "sg:classifiers":[
        {
            "category":"Manufacturing",
            "subcategory":"Motor Vehicles & Parts",
            "type":"Manufacturing & Wholesale Goods"
        }
    ],
    "sg:phone":"+1 503 285 3515",
    "sg:postcode":"97203",
    "sg:province":"OR",
    "sg:tags":[
        "manufacturer"
    ],
    "wof:name":"Boydstun Metal Works Inc",
    "wof:placetype":"venue"
},
  "geometry": {"coordinates":[-122.770791,45.609169],"type":"Point"}
}