{
  "type": "Feature",
  "properties": {
    "iso:country":"US",
    "sg:address":"170 E 2nd St",
    "sg:city":"Ione",
    "sg:classifiers":[
        {
            "category":"Travel",
            "subcategory":"Hotels & Motels",
            "type":"Entertainment"
        }
    ],
    "sg:phone":"+1 541 422 7218",
    "sg:postcode":"97843",
    "sg:province":"OR",
    "sg:tags":[
        "breakfast",
        "accommodation",
        "bed"
    ],
    "wof:name":"Woolery House Bed & Breakfast",
    "wof:placetype":"venue"
},
  "geometry": {"coordinates":[-119.825356,45.500486],"type":"Point"}
}