{
  "type": "Feature",
  "properties": {
    "iso:country":"US",
    "sg:address":"144 SE 2nd Ave",
    "sg:city":"Canby",
    "sg:classifiers":[
        {
            "category":"Shopping",
            "subcategory":"Used Merchandise",
            "type":"Retail Goods"
        }
    ],
    "sg:phone":"+1 503 263 5151",
    "sg:postcode":"97013",
    "sg:province":"OR",
    "sg:tags":[
        "flea",
        "market"
    ],
    "wof:name":"Canby Saturday Market",
    "wof:placetype":"venue"
},
  "geometry": {"coordinates":[-122.691007,45.261959],"type":"Point"}
}