{
  "type": "Feature",
  "properties": {
    "iso:country":"US",
    "sg:address":"15920 SE Division St",
    "sg:city":"Portland",
    "sg:classifiers":[
        {
            "category":"Restaurant",
            "type":"Food & Drink"
        }
    ],
    "sg:phone":"+1 503 760 7315",
    "sg:postcode":"97236",
    "sg:province":"OR",
    "sg:tags":[
        "eating"
    ],
    "wof:name":"Ranchouse Bar & Grill",
    "wof:placetype":"venue"
},
  "geometry": {"coordinates":[-122.498915,45.504422],"type":"Point"}
}