{
  "type": "Feature",
  "properties": {
    "addr:full":"1981 Mapleleaf Rd Lake Oswego OR 97034",
    "addr:housenumber":"1981",
    "addr:postcode":"97034",
    "addr:street":"Mapleleaf Rd",
    "iso:country":"US",
    "sg:address":"1981 Mapleleaf Rd",
    "sg:city":"Lake Oswego",
    "sg:classifiers":[
        {
            "category":"Real Estate",
            "subcategory":"Architect",
            "type":"Services"
        }
    ],
    "sg:phone":"+1 503 635 5369",
    "sg:postcode":"97034",
    "sg:province":"OR",
    "sg:tags":[
        "architectural"
    ],
    "wof:name":"Eagleone Inc",
    "wof:placetype":"venue"
},
  "geometry": {"coordinates":[-122.69741399999999,45.4006],"type":"Point"}
}