{
  "type": "Feature",
  "properties": {
    "iso:country":"US",
    "sg:address":"1204 35th Ave NW",
    "sg:city":"Salem",
    "sg:classifiers":[
        {
            "category":"Manufacturing",
            "subcategory":"Apparel",
            "type":"Manufacturing & Wholesale Goods"
        },
        {
            "category":"Home & Garden",
            "subcategory":"Home Furnishings",
            "type":"Retail Goods"
        }
    ],
    "sg:phone":"+1 503 362 9619",
    "sg:postcode":"97304",
    "sg:province":"OR",
    "sg:tags":[
        "curtain",
        "made",
        "drapery",
        "mfg"
    ],
    "wof:name":"Grant's Draperies",
    "wof:placetype":"venue"
},
  "geometry": {"coordinates":[-123.101473,44.954563],"type":"Point"}
}