{
  "type": "Feature",
  "properties": {
    "addr:full":"629 Hemlock St Brookings OR 97415",
    "addr:housenumber":"629",
    "addr:postcode":"97415",
    "addr:street":"Hemlock St",
    "iso:country":"US",
    "sg:address":"629 Hemlock St",
    "sg:city":"Brookings",
    "sg:classifiers":[
        {
            "category":"Building & Trades",
            "subcategory":"Construction",
            "type":"Services"
        }
    ],
    "sg:phone":"+1 541 469 3997",
    "sg:postcode":"97415",
    "sg:province":"OR",
    "sg:tags":[
        "painter"
    ],
    "wof:name":"Clint's Custom Colors",
    "wof:placetype":"venue"
},
  "geometry": {"coordinates":[-124.282033,42.050934],"type":"Point"}
}