{
  "type": "Feature",
  "properties": {
    "iso:country":"US",
    "sg:address":"14850 SW Beard Rd",
    "sg:city":"Beaverton",
    "sg:classifiers":[
        {
            "category":"Insurance",
            "subcategory":"Insurance Agent",
            "type":"Services"
        }
    ],
    "sg:phone":"+1 503 579 6354",
    "sg:postcode":"97007",
    "sg:province":"OR",
    "wof:name":"Cw Home Ins & Remodel",
    "wof:placetype":"venue"
},
  "geometry": {"coordinates":[-122.827701,45.45295],"type":"Point"}
}