{
  "type": "Feature",
  "properties": {
    "iso:country":"US",
    "sg:address":"16611 NE Russell St",
    "sg:city":"Portland",
    "sg:classifiers":[
        {
            "category":"Wholesale",
            "subcategory":"Vending Machines",
            "type":"Manufacturing & Wholesale Goods"
        }
    ],
    "sg:phone":"+1 503 514 1938",
    "sg:postcode":"97230",
    "sg:province":"OR",
    "sg:tags":[
        "operator"
    ],
    "wof:name":"Quarter Vending",
    "wof:placetype":"venue"
},
  "geometry": {"coordinates":[-122.49006199999999,45.540199],"type":"Point"}
}