{
  "type": "Feature",
  "properties": {
    "iso:country":"US",
    "sg:address":"1756 Tolman Creek Rd",
    "sg:city":"Ashland",
    "sg:classifiers":[
        {
            "category":"Wholesale",
            "subcategory":"Construction Materials",
            "type":"Manufacturing & Wholesale Goods"
        }
    ],
    "sg:phone":"+1 541 210 0009",
    "sg:postcode":"97520",
    "sg:province":"OR",
    "sg:tags":[
        "sand",
        "gravel"
    ],
    "wof:name":"Sojourn Enterprises Inc",
    "wof:placetype":"venue"
},
  "geometry": {"coordinates":[-122.670733,42.159058],"type":"Point"}
}