{
  "type": "Feature",
  "properties": {
    "iso:country":"US",
    "sg:address":"4087 Woodland Park Rd",
    "sg:city":"Grants Pass",
    "sg:classifiers":[
        {
            "category":"Freight",
            "type":"Transportation"
        }
    ],
    "sg:phone":"+1 541 471 9031",
    "sg:postcode":"97527",
    "sg:province":"OR",
    "sg:tags":[
        "operator",
        "local",
        "trucking"
    ],
    "wof:name":"Chad Hansen Logging and Hlg",
    "wof:placetype":"venue"
},
  "geometry": {"coordinates":[-123.430608,42.38438],"type":"Point"}
}