{
  "type": "Feature",
  "properties": {
    "iso:country":"US",
    "sg:address":"1252 W McAndrews Rd",
    "sg:city":"Medford",
    "sg:classifiers":[
        {
            "category":"Retail",
            "subcategory":"Laundry & Dry Cleaning",
            "type":"Services"
        }
    ],
    "sg:phone":"+1 541 732 0181",
    "sg:postcode":"97501",
    "sg:province":"OR",
    "sg:tags":[
        "cleaners",
        "rug",
        "carpet"
    ],
    "wof:name":"CIS/Cleaning & Insallation",
    "wof:placetype":"venue"
},
  "geometry": {"coordinates":[-122.896013,42.328757],"type":"Point"}
}