{
  "type": "Feature",
  "properties": {
    "addr:full":"8725 SW Hall Blvd Tigard OR 97223",
    "addr:housenumber":"8725",
    "addr:postcode":"97223",
    "addr:street":"Sw Hall Blvd",
    "iso:country":"US",
    "sg:address":"8725 SW Hall Blvd",
    "sg:city":"Tigard",
    "sg:classifiers":[
        {
            "category":"Autos & Motor Vehicles",
            "subcategory":"Fuel & Gas Station",
            "type":"Retail Goods"
        }
    ],
    "sg:phone":"+1 503 641 3403",
    "sg:postcode":"97223",
    "sg:province":"OR",
    "sg:tags":[
        "oil"
    ],
    "wof:name":"Shell",
    "wof:placetype":"venue"
},
  "geometry": {"coordinates":[-122.78175899999999,45.456524],"type":"Point"}
}