{
  "type": "Feature",
  "properties": {
    "iso:country":"US",
    "sg:address":"1020 Green Acres Rd",
    "sg:city":"Eugene",
    "sg:classifiers":[
        {
            "category":"Wholesale",
            "subcategory":"Electrical",
            "type":"Manufacturing & Wholesale Goods"
        }
    ],
    "sg:phone":"+1 541 302 1804",
    "sg:postcode":"97408",
    "sg:province":"OR",
    "sg:tags":[
        "control",
        "security",
        "system"
    ],
    "wof:name":"Dish Network By Linkus",
    "wof:placetype":"venue"
},
  "geometry": {"coordinates":[-123.094288,44.093242],"type":"Point"}
}