{
  "type": "Feature",
  "properties": {
    "iso:country":"US",
    "sg:address":"1310 SE 50th Ave",
    "sg:city":"Portland",
    "sg:classifiers":[
        {
            "category":"Manufacturing",
            "subcategory":"Chemicals & Compounds",
            "type":"Manufacturing & Wholesale Goods"
        }
    ],
    "sg:phone":"+1 503 246 3107",
    "sg:postcode":"97215",
    "sg:province":"OR",
    "sg:tags":[
        "equipment",
        "plant",
        "supply"
    ],
    "wof:name":"The New Viking Co",
    "wof:placetype":"venue"
},
  "geometry": {"coordinates":[-122.61143199999999,45.513468],"type":"Point"}
}