{
  "type": "Feature",
  "properties": {
    "addr:full":"16080 Storey Rd Monmouth OR 97361",
    "addr:housenumber":"16080",
    "addr:postcode":"97361",
    "addr:street":"Storey Rd",
    "iso:country":"US",
    "sg:address":"16080 Storey Rd",
    "sg:city":"Monmouth",
    "sg:classifiers":[
        {
            "category":"Professional",
            "subcategory":"Computer Services",
            "type":"Services"
        }
    ],
    "sg:phone":"+1 503 838 1223",
    "sg:postcode":"97361",
    "sg:province":"OR",
    "sg:tags":[
        "consultant",
        "designer"
    ],
    "sg:website":"www.cyberbrick.org",
    "wof:name":"Information Architecture",
    "wof:placetype":"venue"
},
  "geometry": {"coordinates":[-123.353042,44.732134],"type":"Point"}
}