{
  "type": "Feature",
  "properties": {
    "iso:country":"US",
    "sg:address":"2095 Corey Rd",
    "sg:city":"Central Point",
    "sg:classifiers":[
        {
            "category":"Retail",
            "subcategory":"Auto Repair",
            "type":"Services"
        }
    ],
    "sg:phone":"+1 541 826 4210",
    "sg:postcode":"97502",
    "sg:province":"OR",
    "sg:tags":[
        "body",
        "automobile",
        "painting"
    ],
    "wof:name":"Commercial Collision & Paint",
    "wof:placetype":"venue"
},
  "geometry": {"coordinates":[-122.847227,42.414746],"type":"Point"}
}