{
  "type": "Feature",
  "properties": {
    "iso:country":"US",
    "sg:address":"1575 Pinecrest Ter",
    "sg:city":"Grants Pass",
    "sg:classifiers":[
        {
            "category":"Shopping",
            "type":"Retail Goods"
        }
    ],
    "sg:phone":"+1 541 474 9418",
    "sg:postcode":"97520",
    "sg:province":"OR",
    "sg:tags":[
        "merchandise"
    ],
    "wof:name":"Medorigin LLC",
    "wof:placetype":"venue"
},
  "geometry": {"coordinates":[-122.689071,42.176861],"type":"Point"}
}