{
  "type": "Feature",
  "properties": {
    "iso:country":"US",
    "sg:address":"321 1st Ave E Suite #1-A",
    "sg:city":"Albany",
    "sg:classifiers":[
        {
            "category":"Professional",
            "subcategory":"Accounting & Tax Preparation",
            "type":"Services"
        },
        {
            "category":"Professional",
            "subcategory":"Employment Agencies",
            "type":"Services"
        }
    ],
    "sg:phone":"+1 541 928 4130",
    "sg:postcode":"97321",
    "sg:province":"OR",
    "sg:tags":[
        "opportunity",
        "payroll"
    ],
    "sg:website":"http://www.barrettbusiness.com",
    "wof:name":"Barrett Business Services, Inc.",
    "wof:placetype":"venue"
},
  "geometry": {"coordinates":[-123.102116,44.637732],"type":"Point"}
}