{
  "type": "Feature",
  "properties": {
    "iso:country":"US",
    "sg:address":"10990 SE 362nd Ave",
    "sg:city":"Boring",
    "sg:classifiers":[
        {
            "category":"Wholesale",
            "subcategory":"Plants",
            "type":"Manufacturing & Wholesale Goods"
        },
        {
            "category":"Farming",
            "subcategory":"Nursery",
            "type":"Manufacturing & Wholesale Goods"
        }
    ],
    "sg:phone":"+1 503 663 6731",
    "sg:postcode":"97009",
    "sg:province":"OR",
    "sg:tags":[
        "ornamental",
        "tree"
    ],
    "wof:name":"Krueger's Nursery",
    "wof:placetype":"venue"
},
  "geometry": {"coordinates":[-122.290531,45.444038],"type":"Point"}
}