{
  "type": "Feature",
  "properties": {
    "iso:country":"US",
    "sg:address":"1338 Jefferson St",
    "sg:city":"Eugene",
    "sg:classifiers":[
        {
            "category":"Social Services",
            "type":"Services"
        }
    ],
    "sg:phone":"+1 541 344 4156",
    "sg:postcode":"97402",
    "sg:province":"OR",
    "sg:tags":[
        "child",
        "day",
        "care"
    ],
    "wof:name":"Childrens Hour",
    "wof:placetype":"venue"
},
  "geometry": {"coordinates":[-123.10135,44.043455],"type":"Point"}
}