{
  "type": "Feature",
  "properties": {
    "iso:country":"US",
    "sg:address":"2730 Pacific Blvd SE",
    "sg:city":"Albany",
    "sg:classifiers":[
        {
            "category":"Manufacturing",
            "subcategory":"Lumber",
            "type":"Manufacturing & Wholesale Goods"
        }
    ],
    "sg:phone":"+1 541 926 7771",
    "sg:postcode":"97321",
    "sg:province":"OR",
    "sg:tags":[
        "logging"
    ],
    "sg:website":"www.weyerhaeuser.com",
    "wof:name":"Weyerhaeuser Co",
    "wof:placetype":"venue"
},
  "geometry": {"coordinates":[-123.072199,44.637782],"type":"Point"}
}