{
  "type": "Feature",
  "properties": {
    "iso:country":"US",
    "sg:address":"243 Commercial Ave",
    "sg:city":"Coos Bay",
    "sg:classifiers":[
        {
            "category":"Professional",
            "type":"Services"
        }
    ],
    "sg:phone":"+1 541 269 5566",
    "sg:postcode":"97420",
    "sg:province":"OR",
    "wof:name":"Gordon A Joelson PC",
    "wof:placetype":"venue"
},
  "geometry": {"coordinates":[-124.21477400000001,43.368593],"type":"Point"}
}