{
  "type": "Feature",
  "properties": {
    "iso:country":"US",
    "sg:address":"347 W Broccoli St",
    "sg:city":"Roseburg",
    "sg:classifiers":[
        {
            "category":"Building & Trades",
            "subcategory":"Cleaning & Sanitation",
            "type":"Services"
        }
    ],
    "sg:phone":"+1 541 672 8890",
    "sg:postcode":"97470",
    "sg:province":"OR",
    "sg:tags":[
        "maintenance"
    ],
    "wof:name":"Handy Helpers",
    "wof:placetype":"venue"
},
  "geometry": {"coordinates":[-123.382806,43.217127],"type":"Point"}
}