{
  "type": "Feature",
  "properties": {
    "iso:country":"US",
    "sg:address":"18051 NW Dustin Ln",
    "sg:city":"Beaverton",
    "sg:classifiers":[
        {
            "category":"Professional",
            "subcategory":"Business Services",
            "type":"Services"
        }
    ],
    "sg:phone":"+1 503 372 9593",
    "sg:postcode":"97006",
    "sg:province":"OR",
    "wof:name":"Rose City Accents",
    "wof:placetype":"venue"
},
  "geometry": {"coordinates":[-122.86328,45.523869],"type":"Point"}
}