{
  "type": "Feature",
  "properties": {
    "iso:country":"US",
    "sg:address":"4918 Grassland Ct NE",
    "sg:city":"Salem",
    "sg:classifiers":[
        {
            "category":"Restaurant",
            "type":"Food & Drink"
        }
    ],
    "sg:phone":"+1 503 315 2298",
    "sg:postcode":"97305",
    "sg:province":"OR",
    "sg:tags":[
        "asian",
        "chinese",
        "pan"
    ],
    "wof:name":"Ming Fa, Inc.",
    "wof:placetype":"venue"
},
  "geometry": {"coordinates":[-122.962389,44.965433],"type":"Point"}
}