{
  "type": "Feature",
  "properties": {
    "iso:country":"US",
    "sg:address":"2240 Tower E",
    "sg:city":"Medford",
    "sg:classifiers":[
        {
            "category":"Real Estate",
            "subcategory":"Real Estate Services",
            "type":"Services"
        }
    ],
    "sg:phone":"+1 541 690 1300",
    "sg:postcode":"97504",
    "sg:province":"OR",
    "sg:tags":[
        "management",
        "property"
    ],
    "wof:name":"Northwood's Property Management",
    "wof:placetype":"venue"
},
  "geometry": {"coordinates":[-122.853481,42.368815],"type":"Point"}
}