{
  "type": "Feature",
  "properties": {
    "addr:full":"1745 Barnes Ave SE Salem OR 97306",
    "addr:housenumber":"1745",
    "addr:postcode":"97306",
    "addr:street":"Barnes Ave Se",
    "iso:country":"US",
    "sg:address":"1745 Barnes Ave SE",
    "sg:city":"Salem",
    "sg:classifiers":[
        {
            "category":"Building & Trades",
            "subcategory":"Construction",
            "type":"Services"
        }
    ],
    "sg:phone":"+1 503 364 0652",
    "sg:postcode":"97306",
    "sg:province":"OR",
    "sg:tags":[
        "pavement",
        "marking"
    ],
    "wof:name":"A-1 Straight Line Striping Co",
    "wof:placetype":"venue"
},
  "geometry": {"coordinates":[-123.019503,44.881043],"type":"Point"}
}