{
  "type": "Feature",
  "properties": {
    "addr:full":"216 Scenic Dr Ashland OR 97520",
    "addr:housenumber":"216",
    "addr:postcode":"97520",
    "addr:street":"Scenic Dr",
    "iso:country":"US",
    "sg:address":"216 Scenic Dr",
    "sg:city":"Ashland",
    "sg:classifiers":[
        {
            "category":"Professional",
            "subcategory":"Management & Consulting",
            "type":"Services"
        }
    ],
    "sg:phone":"+1 541 488 8780",
    "sg:postcode":"97520",
    "sg:province":"OR",
    "sg:tags":[
        "marketing",
        "consultant"
    ],
    "wof:name":"Andrew Hollowell & Assoc",
    "wof:placetype":"venue"
},
  "geometry": {"coordinates":[-122.722825,42.200447],"type":"Point"}
}