{
  "type": "Feature",
  "properties": {
    "iso:country":"US",
    "sg:address":"266 SW Central Ave",
    "sg:city":"Grants Pass",
    "sg:classifiers":[
        {
            "category":"Shopping",
            "subcategory":"Clothing, Apparel, & Fashions",
            "type":"Retail Goods"
        }
    ],
    "sg:phone":"+1 541 471 1589",
    "sg:postcode":"97526",
    "sg:province":"OR",
    "wof:name":"Harmony Uniform",
    "wof:placetype":"venue"
},
  "geometry": {"coordinates":[-123.336851,42.432471],"type":"Point"}
}