{
  "type": "Feature",
  "properties": {
    "iso:country":"US",
    "sg:address":"12855 SW 20th Ct",
    "sg:city":"Beaverton",
    "sg:classifiers":[
        {
            "category":"Communications",
            "subcategory":"Film & Video Production",
            "type":"Services"
        }
    ],
    "sg:phone":"+1 503 626 9638",
    "sg:postcode":"97008",
    "sg:province":"OR",
    "sg:tags":[
        "motion",
        "tv",
        "radio",
        "companies-film"
    ],
    "sg:website":"http://www.high-five.com",
    "wof:name":"High Five Challenge",
    "wof:placetype":"venue"
},
  "geometry": {"coordinates":[-122.80908100000001,45.472747],"type":"Point"}
}