{
  "type": "Feature",
  "properties": {
    "iso:country":"US",
    "sg:address":"1844 Columbia Blvd",
    "sg:city":"St Helens",
    "sg:classifiers":[
        {
            "category":"Banks & Credit Unions",
            "subcategory":"Bank",
            "type":"Services"
        }
    ],
    "sg:phone":"+1 503 397 3116",
    "sg:postcode":"97051",
    "sg:province":"OR",
    "sg:tags":[
        "loan",
        "real estate"
    ],
    "wof:name":"All Right Mortgage",
    "wof:placetype":"venue"
},
  "geometry": {"coordinates":[-122.816271,45.859009],"type":"Point"}
}