{
  "type": "Feature",
  "properties": {
    "addr:full":"247 1st St Elkton OR 97436",
    "addr:housenumber":"247",
    "addr:postcode":"97436",
    "addr:street":"1St St",
    "iso:country":"US",
    "sg:address":"247 1st St",
    "sg:city":"Elkton",
    "sg:classifiers":[
        {
            "category":"Organizations",
            "subcategory":"Community Association",
            "type":"Services"
        }
    ],
    "sg:phone":"+1 541 584 2500",
    "sg:postcode":"97436",
    "sg:province":"OR",
    "wof:name":"Elkton Masonic Lodge",
    "wof:placetype":"venue"
},
  "geometry": {"coordinates":[-123.566806,43.635846],"type":"Point"}
}