{
  "type": "Feature",
  "properties": {
    "addr:full":"539 Highway 99 N Eugene OR 97402",
    "addr:housenumber":"539",
    "addr:postcode":"97402",
    "addr:street":"Highway 99 N",
    "iso:country":"US",
    "sg:address":"539 Highway 99 N",
    "sg:city":"Eugene",
    "sg:classifiers":[
        {
            "category":"Autos & Motor Vehicles",
            "subcategory":"Auto Supplies",
            "type":"Retail Goods"
        },
        {
            "category":"Wholesale",
            "subcategory":"Electrical",
            "type":"Manufacturing & Wholesale Goods"
        }
    ],
    "sg:phone":"+1 541 689 9134",
    "sg:postcode":"97402",
    "sg:province":"OR",
    "sg:tags":[
        "battery",
        "automobile",
        "part",
        "batteries-storage-wholesale",
        "batteries-storage",
        "manufacturer"
    ],
    "sg:website":"http://www.batteryxchange.com",
    "wof:name":"Battery Exchange",
    "wof:placetype":"venue"
},
  "geometry": {"coordinates":[-123.20031,44.145378],"type":"Point"}
}