{
  "type": "Feature",
  "properties": {
    "iso:country":"US",
    "sg:address":"275 W 10th Ave",
    "sg:city":"Eugene",
    "sg:classifiers":[
        {
            "category":"Government",
            "subcategory":"Office",
            "type":"Public Place"
        }
    ],
    "sg:phone":"+1 541 687 4234",
    "sg:postcode":"97401",
    "sg:province":"OR",
    "wof:name":"Lane County Elections",
    "wof:placetype":"venue"
},
  "geometry": {"coordinates":[-123.096957,44.048893],"type":"Point"}
}