{
  "type": "Feature",
  "properties": {
    "iso:country":"US",
    "sg:address":"2209 NE 29th St",
    "sg:city":"Lincoln City",
    "sg:classifiers":[
        {
            "category":"Professional",
            "subcategory":"Business Services",
            "type":"Services"
        }
    ],
    "sg:phone":"+1 541 994 5497",
    "sg:postcode":"97367",
    "sg:province":"OR",
    "wof:name":"L&W Sales",
    "wof:placetype":"venue"
},
  "geometry": {"coordinates":[-124.005589,44.986544],"type":"Point"}
}