{
  "type": "Feature",
  "properties": {
    "iso:country":"US",
    "sg:address":"45 NW 101st Ave",
    "sg:city":"Portland",
    "sg:classifiers":[
        {
            "category":"Building & Trades",
            "subcategory":"Landscaping Services",
            "type":"Services"
        }
    ],
    "sg:phone":"+1 503 291 7943",
    "sg:postcode":"97229",
    "sg:province":"OR",
    "sg:tags":[
        "landscape",
        "contractor"
    ],
    "wof:name":"Robert B Kapela",
    "wof:placetype":"venue"
},
  "geometry": {"coordinates":[-122.78053300000001,45.519855],"type":"Point"}
}