{
  "type": "Feature",
  "properties": {
    "iso:country":"US",
    "sg:address":"105 E Main St",
    "sg:city":"Molalla",
    "sg:classifiers":[
        {
            "category":"Freight",
            "type":"Transportation"
        }
    ],
    "sg:phone":"+1 503 829 9060",
    "sg:postcode":"97038",
    "sg:province":"OR",
    "sg:tags":[
        "consultant"
    ],
    "wof:name":"TCI-Transportation Concepts",
    "wof:placetype":"venue"
},
  "geometry": {"coordinates":[-122.577057,45.14761],"type":"Point"}
}