{
  "type": "Feature",
  "properties": {
    "addr:full":"200 E Main St Enterprise OR 97828",
    "addr:housenumber":"200",
    "addr:postcode":"97828",
    "addr:street":"E Main St",
    "iso:country":"US",
    "sg:address":"200 E Main St",
    "sg:city":"Enterprise",
    "sg:classifiers":[
        {
            "category":"Building & Trades",
            "subcategory":"Construction",
            "type":"Services"
        }
    ],
    "sg:phone":"+1 541 568 7737",
    "sg:postcode":"97828",
    "sg:province":"OR",
    "sg:tags":[
        "insulation",
        "heat",
        "contractor"
    ],
    "wof:name":"Grande Ronde Installation",
    "wof:placetype":"venue"
},
  "geometry": {"coordinates":[-117.274986,45.425506],"type":"Point"}
}