{
  "type": "Feature",
  "properties": {
    "iso:country":"US",
    "sg:address":"5933 NE Win Sivers Dr Ste 250",
    "sg:city":"Portland",
    "sg:classifiers":[
        {
            "category":"Professional",
            "subcategory":"Lawyer & Legal Services",
            "type":"Services"
        }
    ],
    "sg:phone":"+1 503 546 3452",
    "sg:postcode":"97220",
    "sg:province":"OR",
    "wof:name":"Baumgartner Patient Law",
    "wof:placetype":"venue"
},
  "geometry": {"coordinates":[-122.53812600000001,45.565411],"type":"Point"}
}