{
  "type": "Feature",
  "properties": {
    "iso:country":"US",
    "sg:address":"5327 SE Henry St",
    "sg:city":"Portland",
    "sg:classifiers":[
        {
            "category":"Building & Trades",
            "subcategory":"Locksmith",
            "type":"Services"
        }
    ],
    "sg:phone":"+1 503 715 3781",
    "sg:postcode":"97206",
    "sg:province":"OR",
    "sg:tags":[
        "key"
    ],
    "wof:name":"A-1 Locksmith",
    "wof:placetype":"venue"
},
  "geometry": {"coordinates":[-122.607855,45.476677],"type":"Point"}
}