{
  "type": "Feature",
  "properties": {
    "iso:country":"US",
    "sg:address":"682 NW 3rd St",
    "sg:city":"Prineville",
    "sg:classifiers":[
        {
            "category":"Building & Trades",
            "subcategory":"Construction",
            "type":"Services"
        }
    ],
    "sg:phone":"+1 541 447 6312",
    "sg:postcode":"97754",
    "sg:province":"OR",
    "sg:tags":[
        "general",
        "contractor"
    ],
    "wof:name":"Bobby Kennedy Construction Co",
    "wof:placetype":"venue"
},
  "geometry": {"coordinates":[-120.85344000000001,44.302866],"type":"Point"}
}