{
  "type": "Feature",
  "properties": {
    "addr:full":"11596 SW Pacific Hwy Portland OR 97223",
    "addr:housenumber":"11596",
    "addr:postcode":"97223",
    "addr:street":"Sw Pacific Hwy",
    "iso:country":"US",
    "sg:address":"11596 SW Pacific Hwy",
    "sg:city":"Portland",
    "sg:classifiers":[
        {
            "category":"Retail",
            "subcategory":"Auto Repair",
            "type":"Services"
        }
    ],
    "sg:phone":"+1 503 639 1106",
    "sg:postcode":"97223",
    "sg:province":"OR",
    "sg:tags":[
        "repairing",
        "automobile",
        "r",
        "automotive",
        "supply"
    ],
    "sg:website":"http://www.napaautocare.com/",
    "wof:name":"Tigard Tire & Auto Service",
    "wof:placetype":"venue"
},
  "geometry": {"coordinates":[-122.75299800000001,45.4389],"type":"Point"}
}