{
  "type": "Feature",
  "properties": {
    "iso:country":"US",
    "sg:address":"61090 Parrell Rd",
    "sg:city":"Bend",
    "sg:classifiers":[
        {
            "category":"Home & Garden",
            "subcategory":"Home Furnishings",
            "type":"Retail Goods"
        }
    ],
    "sg:phone":"+1 541 382 0035",
    "sg:postcode":"97702",
    "sg:province":"OR",
    "sg:tags":[
        "window",
        "covering"
    ],
    "wof:name":"Phil's Window & Design",
    "wof:placetype":"venue"
},
  "geometry": {"coordinates":[-121.32315800000001,44.007594],"type":"Point"}
}