{
  "type": "Feature",
  "properties": {
    "iso:country":"US",
    "sg:address":"16450 Boones Ferry Rd",
    "sg:city":"Lake Oswego",
    "sg:classifiers":[
        {
            "category":"Social Services",
            "subcategory":"Child Care",
            "type":"Services"
        }
    ],
    "sg:phone":"+1 503 697 3618",
    "sg:postcode":"97035",
    "sg:province":"OR",
    "sg:tags":[
        "day"
    ],
    "wof:name":"Exploration Learning Preschool",
    "wof:placetype":"venue"
},
  "geometry": {"coordinates":[-122.725038,45.407529],"type":"Point"}
}