{
  "type": "Feature",
  "properties": {
    "addr:full":"92560 Goldson Rd Cheshire OR 97419",
    "addr:postcode":"92560;97419",
    "addr:street":"Goldson Rd",
    "iso:country":"US",
    "sg:address":"92560 Goldson Rd",
    "sg:city":"Cheshire",
    "sg:classifiers":[
        {
            "category":"Farming",
            "subcategory":"Livestock Farm",
            "type":"Manufacturing & Wholesale Goods"
        },
        {
            "category":"Farming",
            "subcategory":"Farm & Veterinary Services",
            "type":"Manufacturing & Wholesale Goods"
        }
    ],
    "sg:phone":"+1 541 998 6988",
    "sg:postcode":"97419",
    "sg:province":"OR",
    "sg:tags":[
        "breeder"
    ],
    "wof:name":"Clearwater Farms",
    "wof:placetype":"venue"
},
  "geometry": {"coordinates":[-123.363812,44.170316],"type":"Point"}
}