{
  "type": "Feature",
  "properties": {
    "addr:full":"2350 Oakmont Way Eugene OR 97401",
    "addr:housenumber":"2350",
    "addr:postcode":"97401",
    "addr:street":"Oakmont Way",
    "iso:country":"US",
    "sg:address":"2350 Oakmont Way",
    "sg:city":"Eugene",
    "sg:classifiers":[
        {
            "category":"Insurance",
            "subcategory":"Insurance Agent",
            "type":"Services"
        }
    ],
    "sg:phone":"+1 541 434 2468",
    "sg:postcode":"97401",
    "sg:province":"OR",
    "wof:name":"American Family Life Insurance",
    "wof:placetype":"venue"
},
  "geometry": {"coordinates":[-123.077581,44.067622],"type":"Point"}
}