{
  "type": "Feature",
  "properties": {
    "addr:full":"4206 Franklin Blvd Eugene OR 97403",
    "addr:housenumber":"4206",
    "addr:postcode":"97403",
    "addr:street":"Franklin Blvd",
    "iso:country":"US",
    "sg:address":"4206 Franklin Blvd",
    "sg:city":"Eugene",
    "sg:classifiers":[
        {
            "category":"Insurance",
            "subcategory":"Insurance Agent",
            "type":"Services"
        }
    ],
    "sg:phone":"+1 541 726 7821",
    "sg:postcode":"97403",
    "sg:province":"OR",
    "wof:name":"Blue Cross & Blue Shield",
    "wof:placetype":"venue"
},
  "geometry": {"coordinates":[-123.03194999999999,44.044352],"type":"Point"}
}