{
  "type": "Feature",
  "properties": {
    "addr:full":"9415 S Highway 97 Redmond OR 97756",
    "addr:housenumber":"9415",
    "addr:postcode":"97756",
    "addr:street":"S Highway 97",
    "iso:country":"US",
    "sg:address":"9415 S Highway 97",
    "sg:city":"Redmond",
    "sg:classifiers":[
        {
            "category":"Shopping",
            "subcategory":"Crafts & Fabrics",
            "type":"Retail Goods"
        }
    ],
    "sg:phone":"+1 541 389 5659",
    "sg:postcode":"97756",
    "sg:province":"OR",
    "sg:tags":[
        "shop",
        "knit"
    ],
    "wof:name":"Black Rock Ranch",
    "wof:placetype":"venue"
},
  "geometry": {"coordinates":[-121.244535,44.180554],"type":"Point"}
}