{
  "type": "Feature",
  "properties": {
    "iso:country":"US",
    "sg:address":"415 NW 11th Ave",
    "sg:city":"Portland",
    "sg:classifiers":[
        {
            "category":"Real Estate",
            "subcategory":"Architect",
            "type":"Services"
        }
    ],
    "sg:phone":"+1 503 528 9711",
    "sg:postcode":"97209",
    "sg:province":"OR",
    "sg:website":"www.erezrussoarchitect.com",
    "wof:name":"Russo Erez Architect",
    "wof:placetype":"venue"
},
  "geometry": {"coordinates":[-122.682249,45.526034],"type":"Point"}
}