{
  "type": "Feature",
  "properties": {
    "iso:country":"US",
    "sg:address":"11687 NE Glisan Street",
    "sg:city":"Portland",
    "sg:classifiers":[
        {
            "category":"Education",
            "subcategory":"School",
            "type":"Public Place"
        }
    ],
    "sg:phone":"+1 503 252 5389",
    "sg:postcode":"97220",
    "sg:province":"OR",
    "wof:name":"New Song School of Music",
    "wof:placetype":"venue"
},
  "geometry": {"coordinates":[-122.542483,45.526402],"type":"Point"}
}