{
  "type": "Feature",
  "properties": {
    "iso:country":"US",
    "sg:address":"49985 Mckenzie Hwy",
    "sg:city":"Vida",
    "sg:classifiers":[
        {
            "category":"Building & Trades",
            "subcategory":"Plumbing",
            "type":"Services"
        },
        {
            "category":"Building & Trades",
            "subcategory":"Cleaning & Sanitation",
            "type":"Services"
        }
    ],
    "sg:phone":"+1 541 822 3129",
    "sg:postcode":"97488",
    "sg:province":"OR",
    "sg:tags":[
        "plumber",
        "industrial",
        "septic",
        "supply",
        "tanks-treatment",
        "contractors-commercial"
    ],
    "sg:website":"http://www.juza.com",
    "wof:name":"Mckenzie Septic Service",
    "wof:placetype":"venue"
},
  "geometry": {"coordinates":[-122.406301,44.1233],"type":"Point"}
}