{
  "type": "Feature",
  "properties": {
    "addr:full":"511 SW 10th Avenue Portland OR 97205",
    "addr:housenumber":"511",
    "addr:postcode":"97205",
    "addr:street":"Sw 10Th Avenue",
    "iso:country":"US",
    "sg:address":"511 SW 10th Avenue",
    "sg:city":"Portland",
    "sg:classifiers":[
        {
            "category":"Health Services",
            "subcategory":"Chiropractor",
            "type":"Services"
        }
    ],
    "sg:phone":"+1 503 224 3898",
    "sg:postcode":"97205",
    "sg:province":"OR",
    "wof:name":"Whittaker Justin Dr",
    "wof:placetype":"venue"
},
  "geometry": {"coordinates":[-122.681434,45.52129],"type":"Point"}
}