{
  "type": "Feature",
  "properties": {
    "iso:country":"US",
    "sg:address":"6250 SE 111th Ave",
    "sg:city":"Portland",
    "sg:classifiers":[
        {
            "category":"Building & Trades",
            "subcategory":"Locksmith",
            "type":"Services"
        }
    ],
    "sg:phone":"+1 971 925 3427",
    "sg:postcode":"97266",
    "sg:province":"OR",
    "sg:tags":[
        "key"
    ],
    "wof:name":"Emergency Portland Locksmith",
    "wof:placetype":"venue"
},
  "geometry": {"coordinates":[-122.548805,45.476942],"type":"Point"}
}