{
  "type": "Feature",
  "properties": {
    "addr:full":"12805 SE 27th Place Portland OR 97222",
    "addr:housenumber":"12805",
    "addr:postcode":"97222",
    "addr:street":"Se 27Th Place",
    "iso:country":"US",
    "sg:address":"12805 SE 27th Place",
    "sg:city":"Portland",
    "sg:classifiers":[
        {
            "category":"Shopping",
            "subcategory":"Computers & Home Electronics",
            "type":"Retail Goods"
        }
    ],
    "sg:phone":"+1 503 654 5466",
    "sg:postcode":"97222",
    "sg:province":"OR",
    "wof:name":"Tech Audio",
    "wof:placetype":"venue"
},
  "geometry": {"coordinates":[-122.635243,45.429763],"type":"Point"}
}