{
  "type": "Feature",
  "properties": {
    "iso:country":"US",
    "sg:address":"409 Main Ave",
    "sg:city":"Tillamook",
    "sg:classifiers":[
        {
            "category":"Retail",
            "subcategory":"Auto Repair",
            "type":"Services"
        }
    ],
    "sg:phone":"+1 503 842 2632",
    "sg:postcode":"97141",
    "sg:province":"OR",
    "sg:tags":[
        "repairing",
        "automobile"
    ],
    "wof:name":"Denny Green Radiator",
    "wof:placetype":"venue"
},
  "geometry": {"coordinates":[-123.84389,45.455542],"type":"Point"}
}