{
  "type": "Feature",
  "properties": {
    "addr:full":"5850 McEwan Rd Lake Oswego OR 97035",
    "addr:housenumber":"5850",
    "addr:postcode":"97035",
    "addr:street":"Mcewan Rd",
    "iso:country":"US",
    "sg:address":"5850 McEwan Rd",
    "sg:city":"Lake Oswego",
    "sg:classifiers":[
        {
            "category":"Education",
            "subcategory":"School",
            "type":"Public Place"
        }
    ],
    "sg:phone":"+1 503 534 2363",
    "sg:postcode":"97035",
    "sg:province":"OR",
    "sg:tags":[
        "high",
        "middle",
        "elementary"
    ],
    "wof:name":"Schools Public",
    "wof:placetype":"venue"
},
  "geometry": {"coordinates":[-122.736665,45.389688],"type":"Point"}
}