{
  "type": "Feature",
  "properties": {
    "addr:full":"22280 SW Washington St Sherwood OR 97140",
    "addr:housenumber":"22280",
    "addr:postcode":"97140",
    "addr:street":"Sw Washington St",
    "iso:country":"US",
    "sg:address":"22280 SW Washington St",
    "sg:city":"Sherwood",
    "sg:classifiers":[
        {
            "category":"Place Of Worship",
            "subcategory":"Church",
            "type":"Public Place"
        },
        {
            "category":"Place Of Worship",
            "type":"Public Place"
        }
    ],
    "sg:phone":"+1 503 625 7115",
    "sg:postcode":"97140",
    "sg:province":"OR",
    "sg:tags":[
        "churches-methodist"
    ],
    "wof:name":"Sherwood United Methodist Church Inc",
    "wof:placetype":"venue"
},
  "geometry": {"coordinates":[-122.84580800000001,45.358149],"type":"Point"}
}