{
  "type": "Feature",
  "properties": {
    "addr:full":"4513 18th Ave NE Salem OR 97303",
    "addr:housenumber":"4513",
    "addr:postcode":"97303",
    "addr:street":"18Th Ave Ne",
    "iso:country":"US",
    "sg:address":"4513 18th Ave NE",
    "sg:city":"Salem",
    "sg:classifiers":[
        {
            "category":"Shopping",
            "subcategory":"Clothing, Apparel, & Fashions",
            "type":"Retail Goods"
        }
    ],
    "sg:phone":"+1 503 390 1923",
    "sg:postcode":"97303",
    "sg:province":"OR",
    "wof:name":"I Black Racing",
    "wof:placetype":"venue"
},
  "geometry": {"coordinates":[-123.00973500000001,44.990032],"type":"Point"}
}