{
  "type": "Feature",
  "properties": {
    "iso:country":"US",
    "sg:address":"955 N Phoenix Rd",
    "sg:city":"Medford",
    "sg:classifiers":[
        {
            "category":"Place Of Worship",
            "subcategory":"Church",
            "type":"Public Place"
        },
        {
            "category":"Place Of Worship",
            "type":"Public Place"
        }
    ],
    "sg:phone":"+1 541 951 9901",
    "sg:postcode":"97504",
    "sg:province":"OR",
    "sg:tags":[
        "churches-interdenominational",
        "denomination",
        "churches-various",
        "churches-non-denominational"
    ],
    "sg:website":"http://www.gracebiblechurch.net",
    "wof:name":"Grace Bible Church",
    "wof:placetype":"venue"
},
  "geometry": {"coordinates":[-122.814049,42.317341],"type":"Point"}
}