{
  "type": "Feature",
  "properties": {
    "addr:full":"975 SW Colorado Ave Bend OR 97702",
    "addr:housenumber":"975",
    "addr:postcode":"97702",
    "addr:street":"Sw Colorado Ave",
    "iso:country":"US",
    "sg:address":"975 SW Colorado Ave",
    "sg:city":"Bend",
    "sg:classifiers":[
        {
            "category":"Insurance",
            "subcategory":"Insurance Agent",
            "type":"Services"
        }
    ],
    "sg:phone":"+1 541 389 3000",
    "sg:postcode":"97702",
    "sg:province":"OR",
    "sg:website":"www.farmers.com",
    "wof:name":"Farmers Insurance Group",
    "wof:placetype":"venue"
},
  "geometry": {"coordinates":[-121.32304499999999,44.04753],"type":"Point"}
}