{
  "type": "Feature",
  "properties": {
    "addr:full":"12725 SW 66th Ave Portland OR 97223",
    "addr:housenumber":"12725",
    "addr:postcode":"97223",
    "addr:street":"Sw 66Th Ave",
    "iso:country":"US",
    "sg:address":"12725 SW 66th Ave",
    "sg:city":"Portland",
    "sg:classifiers":[
        {
            "category":"Professional",
            "type":"Services"
        },
        {
            "category":"Shopping",
            "subcategory":"Computers & Home Electronics",
            "type":"Retail Goods"
        }
    ],
    "sg:phone":"+1 503 352 0988",
    "sg:postcode":"97223",
    "sg:province":"OR",
    "sg:tags":[
        "software"
    ],
    "sg:website":"www.aivea.com",
    "wof:name":"Aivea Corp",
    "wof:placetype":"venue"
},
  "geometry": {"coordinates":[-122.74480800000001,45.429777],"type":"Point"}
}