{
  "type": "Feature",
  "properties": {
    "iso:country":"US",
    "sg:address":"521 Hemlock St",
    "sg:city":"Brookings",
    "sg:classifiers":[
        {
            "category":"Professional",
            "type":"Services"
        }
    ],
    "sg:phone":"+1 541 469 7172",
    "sg:postcode":"97415",
    "sg:province":"OR",
    "sg:tags":[
        "establishment"
    ],
    "wof:name":"Tommy E Short Charitable",
    "wof:placetype":"venue"
},
  "geometry": {"coordinates":[-124.278587,42.05196],"type":"Point"}
}