{
  "type": "Feature",
  "properties": {
    "addr:full":"12937 NE David Cir Portland OR 97230",
    "addr:housenumber":"12937",
    "addr:postcode":"97230",
    "addr:street":"Ne David Cir",
    "iso:country":"US",
    "sg:address":"12937 NE David Cir",
    "sg:city":"Portland",
    "sg:classifiers":[
        {
            "category":"Manufacturing",
            "subcategory":"Food",
            "type":"Manufacturing & Wholesale Goods"
        }
    ],
    "sg:phone":"+1 503 253 1655",
    "sg:postcode":"97230",
    "sg:province":"OR",
    "sg:tags":[
        "cookie",
        "cracker"
    ],
    "wof:name":"Mother's Cake & Cookie Co",
    "wof:placetype":"venue"
},
  "geometry": {"coordinates":[-122.52787499999999,45.5601],"type":"Point"}
}