{
  "type": "Feature",
  "properties": {
    "addr:full":"7908 Ajax St White City OR 97503",
    "addr:housenumber":"7908",
    "addr:postcode":"97503",
    "addr:street":"Ajax St",
    "iso:country":"US",
    "sg:address":"7908 Ajax St",
    "sg:city":"White City",
    "sg:classifiers":[
        {
            "category":"Shopping",
            "subcategory":"Bicycles & Sporting Goods",
            "type":"Retail Goods"
        }
    ],
    "sg:phone":"+1 541 830 8559",
    "sg:postcode":"97503",
    "sg:province":"OR",
    "wof:name":"Anchors & Sinkers Away",
    "wof:placetype":"venue"
},
  "geometry": {"coordinates":[-122.84344900000001,42.43125],"type":"Point"}
}