{
  "type": "Feature",
  "properties": {
    "iso:country":"US",
    "sg:address":"12098 State Hwy 211",
    "sg:city":"Molalla",
    "sg:classifiers":[
        {
            "category":"Building & Trades",
            "subcategory":"Construction",
            "type":"Services"
        }
    ],
    "sg:phone":"+1 503 829 8549",
    "sg:postcode":"97038",
    "sg:province":"OR",
    "sg:tags":[
        "heavy"
    ],
    "wof:name":"M&M Cutting Inc",
    "wof:placetype":"venue"
},
  "geometry": {"coordinates":[-122.615307,45.149696],"type":"Point"}
}