{
  "type": "Feature",
  "properties": {
    "addr:full":"31021 SE Bluff Rd Gresham OR 97080",
    "addr:postcode":"31021;97080",
    "addr:street":"Se Bluff Rd",
    "iso:country":"US",
    "sg:address":"31021 SE Bluff Rd",
    "sg:city":"Gresham",
    "sg:classifiers":[
        {
            "category":"Organizations",
            "subcategory":"Community Association",
            "type":"Services"
        }
    ],
    "sg:phone":"+1 503 663 4037",
    "sg:postcode":"97080",
    "sg:province":"OR",
    "wof:name":"Children of Mexico",
    "wof:placetype":"venue"
},
  "geometry": {"coordinates":[-122.346587,45.465832],"type":"Point"}
}