{
  "type": "Feature",
  "properties": {
    "addr:full":"27155 NW Truitt Rd North Plains OR 97133",
    "addr:housenumber":"27155",
    "addr:postcode":"97133",
    "addr:street":"Nw Truitt Rd",
    "iso:country":"US",
    "sg:address":"27155 NW Truitt Rd",
    "sg:city":"North Plains",
    "sg:classifiers":[
        {
            "category":"Farming",
            "subcategory":"Livestock Farm",
            "type":"Manufacturing & Wholesale Goods"
        }
    ],
    "sg:phone":"+1 541 544 2094",
    "sg:postcode":"97133",
    "sg:province":"OR",
    "sg:tags":[
        "hay",
        "ranch",
        "seed",
        "cattle"
    ],
    "wof:name":"Rocky Ridge Ranch Inc",
    "wof:placetype":"venue"
},
  "geometry": {"coordinates":[-122.96347799999999,45.635853],"type":"Point"}
}