{
  "type": "Feature",
  "properties": {
    "iso:country":"US",
    "sg:address":"16165 SW Regatta Ln",
    "sg:city":"Beaverton",
    "sg:classifiers":[
        {
            "category":"Food & Beverages",
            "subcategory":"Specialty",
            "type":"Retail Goods"
        },
        {
            "category":"Restaurant",
            "type":"Food & Drink"
        }
    ],
    "sg:phone":"+1 503 626 4067",
    "sg:postcode":"97006",
    "sg:province":"OR",
    "sg:tags":[
        "mexican"
    ],
    "wof:name":"Aguilar Tienda Mexicana",
    "wof:placetype":"venue"
},
  "geometry": {"coordinates":[-122.843771,45.517155],"type":"Point"}
}