{
  "type": "Feature",
  "properties": {
    "addr:full":"49 W 29th Ave Eugene OR 97405",
    "addr:housenumber":"49",
    "addr:postcode":"97405",
    "addr:street":"W 29Th Ave",
    "iso:country":"US",
    "sg:address":"49 W 29th Ave",
    "sg:city":"Eugene",
    "sg:classifiers":[
        {
            "category":"Restaurant",
            "type":"Food & Drink"
        }
    ],
    "sg:phone":"+1 541 686 9463",
    "sg:postcode":"97405",
    "sg:province":"OR",
    "sg:website":"www.ofgrapeandgrain.com",
    "wof:name":"Of Grape & Grain",
    "wof:placetype":"venue"
},
  "geometry": {"coordinates":[-123.094521,44.026185],"type":"Point"}
}