{
  "type": "Feature",
  "properties": {
    "addr:full":"1645 High St Eugene OR 97401",
    "addr:housenumber":"1645",
    "addr:postcode":"97401",
    "addr:street":"High St",
    "iso:country":"US",
    "sg:address":"1645 High St",
    "sg:city":"Eugene",
    "sg:classifiers":[
        {
            "category":"Recreation",
            "type":"Entertainment"
        },
        {
            "category":"Organizations",
            "subcategory":"Community Association",
            "type":"Services"
        }
    ],
    "sg:phone":"+1 541 485 6452",
    "sg:postcode":"97401",
    "sg:province":"OR",
    "sg:tags":[
        "club",
        "bridge"
    ],
    "wof:name":"Eugene Duplicate Bridge Club",
    "wof:placetype":"venue"
},
  "geometry": {"coordinates":[-123.088128,44.04162],"type":"Point"}
}