{
  "type": "Feature",
  "properties": {
    "iso:country":"US",
    "sg:address":"10350 N Vancouver Way",
    "sg:city":"Portland",
    "sg:classifiers":[
        {
            "category":"Shopping",
            "subcategory":"Antiques",
            "type":"Retail Goods"
        },
        {
            "category":"Shopping",
            "type":"Retail Goods"
        }
    ],
    "sg:phone":"+1 503 258 1078",
    "sg:postcode":"97217",
    "sg:province":"OR",
    "sg:tags":[
        "collectible"
    ],
    "wof:name":"Kristos Trading",
    "wof:placetype":"venue"
},
  "geometry": {"coordinates":[-122.67073600000001,45.597502],"type":"Point"}
}