{
  "type": "Feature",
  "properties": {
    "iso:country":"US",
    "sg:address":"53945 Hwy 86",
    "sg:city":"Halfway",
    "sg:classifiers":[
        {
            "category":"Restaurant",
            "type":"Food & Drink"
        }
    ],
    "sg:phone":"+1 541 785 3383",
    "sg:postcode":"97834",
    "sg:province":"OR",
    "wof:name":"Hells Canyon Inn",
    "wof:placetype":"venue"
},
  "geometry": {"coordinates":[-116.878077,44.946442],"type":"Point"}
}