{
  "type": "Feature",
  "properties": {
    "iso:country":"US",
    "sg:address":"7595 SW Dunsmuir Ln",
    "sg:city":"Beaverton",
    "sg:classifiers":[
        {
            "category":"Personal",
            "subcategory":"Beauty Salon",
            "type":"Services"
        }
    ],
    "sg:phone":"+1 503 574 3018",
    "sg:postcode":"97007",
    "sg:province":"OR",
    "sg:tags":[
        "shop"
    ],
    "wof:name":"Connies Mobile Hair Service",
    "wof:placetype":"venue"
},
  "geometry": {"coordinates":[-122.83005,45.464681],"type":"Point"}
}