{
  "type": "Feature",
  "properties": {
    "addr:full":"508 NE Winchester St Roseburg OR 97470",
    "addr:housenumber":"508",
    "addr:postcode":"97470",
    "addr:street":"Ne Winchester St",
    "iso:country":"US",
    "sg:address":"508 NE Winchester St",
    "sg:city":"Roseburg",
    "sg:classifiers":[
        {
            "category":"Food & Beverages",
            "subcategory":"Groceries & Convenience Stores",
            "type":"Retail Goods"
        }
    ],
    "sg:phone":"+1 541 673 7052",
    "sg:postcode":"97470",
    "sg:province":"OR",
    "wof:name":"Winchester Street Market",
    "wof:placetype":"venue"
},
  "geometry": {"coordinates":[-123.342061,43.217761],"type":"Point"}
}