{
  "type": "Feature",
  "properties": {
    "addr:full":"1368 Bay St Florence OR 97439",
    "addr:housenumber":"1368",
    "addr:postcode":"97439",
    "addr:street":"Bay St",
    "iso:country":"US",
    "sg:address":"1368 Bay St",
    "sg:city":"Florence",
    "sg:classifiers":[
        {
            "category":"Shopping",
            "subcategory":"Clothing, Apparel, & Fashions",
            "type":"Retail Goods"
        }
    ],
    "sg:phone":"+1 541 902 2829",
    "sg:postcode":"97439",
    "sg:province":"OR",
    "wof:name":"Coastal Casuals",
    "wof:placetype":"venue"
},
  "geometry": {"coordinates":[-124.104708,43.966772],"type":"Point"}
}