{
  "type": "Feature",
  "properties": {
    "addr:full":"888 SW 5th Ave Portland OR 97204",
    "addr:housenumber":"888",
    "addr:postcode":"97204",
    "addr:street":"Sw 5Th Ave",
    "iso:country":"US",
    "sg:address":"888 SW 5th Ave",
    "sg:city":"Portland",
    "sg:classifiers":[
        {
            "category":"Real Estate",
            "subcategory":"Real Estate Agent",
            "type":"Services"
        }
    ],
    "sg:phone":"+1 503 226 4000",
    "sg:postcode":"97204",
    "sg:province":"OR",
    "sg:tags":[
        "management"
    ],
    "sg:website":"www.pioneerplace.com",
    "wof:name":"Rouse Office Management",
    "wof:placetype":"venue"
},
  "geometry": {"coordinates":[-122.678015,45.518021],"type":"Point"}
}