{
  "type": "Feature",
  "properties": {
    "iso:country":"US",
    "sg:address":"347 SE 30th Ave",
    "sg:city":"Hillsboro",
    "sg:classifiers":[
        {
            "category":"Professional",
            "subcategory":"Business Services",
            "type":"Services"
        }
    ],
    "sg:phone":"+1 503 648 4652",
    "sg:postcode":"97123",
    "sg:province":"OR",
    "wof:name":"T&M Development Group",
    "wof:placetype":"venue"
},
  "geometry": {"coordinates":[-122.952543,45.519702],"type":"Point"}
}