{
  "type": "Feature",
  "properties": {
    "addr:full":"138 SE 80th Avenue Portland OR 97215",
    "addr:housenumber":"138",
    "addr:postcode":"97215",
    "addr:street":"Se 80Th Avenue",
    "iso:country":"US",
    "sg:address":"138 SE 80th Avenue",
    "sg:city":"Portland",
    "sg:classifiers":[
        {
            "category":"Health Services",
            "subcategory":"Dentist",
            "type":"Services"
        }
    ],
    "sg:phone":"+1 503 256 7917",
    "sg:postcode":"97215",
    "sg:province":"OR",
    "wof:name":"Purvine Gerald DMD Mt",
    "wof:placetype":"venue"
},
  "geometry": {"coordinates":[-122.581593,45.521236],"type":"Point"}
}