{
  "type": "Feature",
  "properties": {
    "iso:country":"US",
    "sg:address":"10940 SW Barnes Rd Ste 333",
    "sg:city":"Portland",
    "sg:classifiers":[
        {
            "category":"Shopping",
            "subcategory":"Party Supplies",
            "type":"Retail Goods"
        },
        {
            "category":"Personal",
            "type":"Services"
        }
    ],
    "sg:phone":"+1 503 488 5678",
    "sg:postcode":"97225",
    "sg:province":"OR",
    "sg:tags":[
        "planning",
        "event"
    ],
    "sg:website":"www.portlandsearchlights.com",
    "wof:name":"Portland Searchlights",
    "wof:placetype":"venue"
},
  "geometry": {"coordinates":[-122.78958900000001,45.515254],"type":"Point"}
}