{
  "type": "Feature",
  "properties": {
    "iso:country":"US",
    "sg:address":"10200 Mount Ashland Ski Rd",
    "sg:city":"Ashland",
    "sg:classifiers":[
        {
            "category":"Building & Trades",
            "subcategory":"Construction",
            "type":"Services"
        }
    ],
    "sg:phone":"+1 541 482 6574",
    "sg:postcode":"97520",
    "sg:province":"OR",
    "sg:tags":[
        "house"
    ],
    "wof:name":"Fiore Construction",
    "wof:placetype":"venue"
},
  "geometry": {"coordinates":[-122.610045,42.065814],"type":"Point"}
}