{
  "type": "Feature",
  "properties": {
    "addr:full":"3305 Place St Baker City OR 97814",
    "addr:housenumber":"3305",
    "addr:postcode":"97814",
    "addr:street":"Place St",
    "iso:country":"US",
    "sg:address":"3305 Place St",
    "sg:city":"Baker City",
    "sg:classifiers":[
        {
            "category":"Manufacturing",
            "subcategory":"Jewelry",
            "type":"Manufacturing & Wholesale Goods"
        }
    ],
    "sg:phone":"+1 541 523 9732",
    "sg:postcode":"97814",
    "sg:province":"OR",
    "sg:tags":[
        "smith",
        "silver"
    ],
    "wof:name":"Stringer S Diamond Cut Buckle",
    "wof:placetype":"venue"
},
  "geometry": {"coordinates":[-117.847274,44.773444],"type":"Point"}
}