{
  "type": "Feature",
  "properties": {
    "addr:full":"2225 Pacific Blvd SE Albany OR 97321",
    "addr:housenumber":"2225",
    "addr:postcode":"97321",
    "addr:street":"Pacific Blvd Se",
    "iso:country":"US",
    "sg:address":"2225 Pacific Blvd SE",
    "sg:city":"Albany",
    "sg:classifiers":[
        {
            "category":"Real Estate",
            "subcategory":"Real Estate Agent",
            "type":"Services"
        }
    ],
    "sg:phone":"+1 541 928 6317",
    "sg:postcode":"97321",
    "sg:province":"OR",
    "sg:website":"www.valleybrokers.com",
    "wof:name":"Coldwell Banker",
    "wof:placetype":"venue"
},
  "geometry": {"coordinates":[-123.076528,44.636456],"type":"Point"}
}