{
  "type": "Feature",
  "properties": {
    "addr:full":"309 Avalon Dr Ashland OR 97520",
    "addr:housenumber":"309",
    "addr:postcode":"97520",
    "addr:street":"Avalon Dr",
    "iso:country":"US",
    "sg:address":"309 Avalon Dr",
    "sg:city":"Ashland",
    "sg:classifiers":[
        {
            "category":"Building & Trades",
            "subcategory":"Construction",
            "type":"Services"
        }
    ],
    "sg:phone":"+1 541 482 0854",
    "sg:postcode":"97520",
    "sg:province":"OR",
    "sg:tags":[
        "new",
        "home"
    ],
    "wof:name":"Bear Creek Construction",
    "wof:placetype":"venue"
},
  "geometry": {"coordinates":[-122.730142,42.243597],"type":"Point"}
}