{
  "type": "Feature",
  "properties": {
    "iso:country":"US",
    "sg:address":"2715 N Oregon St",
    "sg:city":"Ontario",
    "sg:classifiers":[
        {
            "category":"Personal",
            "type":"Services"
        }
    ],
    "sg:phone":"+1 541 889 3098",
    "sg:postcode":"97914",
    "sg:province":"OR",
    "wof:name":"Wonkas Storage",
    "wof:placetype":"venue"
},
  "geometry": {"coordinates":[-116.975722,44.051719],"type":"Point"}
}