{
  "type": "Feature",
  "properties": {
    "addr:full":"1111 SW Broadway Portland OR 97253",
    "addr:housenumber":"1111",
    "addr:postcode":"97253",
    "addr:street":"Sw Broadway",
    "iso:country":"US",
    "sg:address":"1111 SW Broadway",
    "sg:city":"Portland",
    "sg:classifiers":[
        {
            "category":"Bars & Pubs",
            "type":"Food & Drink"
        }
    ],
    "sg:phone":"+1 503 432 2905",
    "sg:postcode":"97253",
    "sg:province":"OR",
    "sg:website":"www.pcpa.com/out/cafe.php",
    "wof:name":"Art Bar & Bistro",
    "wof:placetype":"venue"
},
  "geometry": {"coordinates":[-122.68113700000001,45.516556],"type":"Point"}
}