{
  "type": "Feature",
  "properties": {
    "addr:full":"3470 SW 185th Ave Beaverton OR 97006",
    "addr:housenumber":"3470",
    "addr:postcode":"97006",
    "addr:street":"Sw 185Th Ave",
    "iso:country":"US",
    "sg:address":"3470 SW 185th Ave",
    "sg:city":"Beaverton",
    "sg:classifiers":[
        {
            "category":"Home & Garden",
            "subcategory":"Hardware",
            "type":"Retail Goods"
        }
    ],
    "sg:phone":"+1 503 649 5555",
    "sg:postcode":"97006",
    "sg:province":"OR",
    "sg:tags":[
        "store"
    ],
    "sg:website":"www.acehardware.com",
    "wof:name":"Suburban Ace Hardware Inc",
    "wof:placetype":"venue"
},
  "geometry": {"coordinates":[-122.866997,45.494701],"type":"Point"}
}