{
  "type": "Feature",
  "properties": {
    "iso:country":"US",
    "sg:address":"1614 NE Vine St",
    "sg:city":"Roseburg",
    "sg:classifiers":[
        {
            "category":"Real Estate",
            "subcategory":"Real Estate Agent",
            "type":"Services"
        }
    ],
    "sg:phone":"+1 541 672 2109",
    "sg:postcode":"97470",
    "sg:province":"OR",
    "wof:name":"Linda R Jones Realty",
    "wof:placetype":"venue"
},
  "geometry": {"coordinates":[-123.347194,43.22965],"type":"Point"}
}