{
  "type": "Feature",
  "properties": {
    "iso:country":"US",
    "sg:address":"2011 Union Ave",
    "sg:city":"North Bend",
    "sg:classifiers":[
        {
            "category":"Building & Trades",
            "subcategory":"Electrical",
            "type":"Services"
        }
    ],
    "sg:phone":"+1 541 756 0581",
    "sg:postcode":"97459",
    "sg:province":"OR",
    "sg:tags":[
        "electric",
        "contractor"
    ],
    "sg:website":"www.reeseelectric.com",
    "wof:name":"Reese Electric",
    "wof:placetype":"venue"
},
  "geometry": {"coordinates":[-124.225039,43.406473],"type":"Point"}
}