{
  "type": "Feature",
  "properties": {
    "iso:country":"US",
    "sg:address":"134750 Shotgun Rd",
    "sg:city":"Post",
    "sg:classifiers":[
        {
            "category":"Farming",
            "subcategory":"Livestock Farm",
            "type":"Manufacturing & Wholesale Goods"
        }
    ],
    "sg:phone":"+1 541 477 3513",
    "sg:postcode":"97752",
    "sg:province":"OR",
    "sg:tags":[
        "beef",
        "feedlot",
        "cattle"
    ],
    "wof:name":"M E Tweedt",
    "wof:placetype":"venue"
},
  "geometry": {"coordinates":[-120.33611999999999,44.12187],"type":"Point"}
}