{
  "type": "Feature",
  "properties": {
    "addr:full":"1620 W Airway Rd Lebanon OR 97355",
    "addr:housenumber":"1620",
    "addr:postcode":"97355",
    "addr:street":"W Airway Rd",
    "iso:country":"US",
    "sg:address":"1620 W Airway Rd",
    "sg:city":"Lebanon",
    "sg:classifiers":[
        {
            "category":"Home & Garden",
            "subcategory":"Furniture",
            "type":"Retail Goods"
        }
    ],
    "sg:phone":"+1 541 258 6800",
    "sg:postcode":"97355",
    "sg:province":"OR",
    "sg:tags":[
        "fur",
        "mfg",
        "wood",
        "real estate"
    ],
    "wof:name":"Valley Cabinet Works",
    "wof:placetype":"venue"
},
  "geometry": {"coordinates":[-122.927854,44.53082],"type":"Point"}
}