{
  "type": "Feature",
  "properties": {
    "iso:country":"US",
    "sg:address":"1200 Merlin Rd",
    "sg:city":"Grants Pass",
    "sg:classifiers":[
        {
            "category":"Travel",
            "subcategory":"Campground",
            "type":"Entertainment"
        }
    ],
    "sg:phone":"+1 541 479 7445",
    "sg:postcode":"97526",
    "sg:province":"OR",
    "sg:tags":[
        "trailer"
    ],
    "wof:name":"Beavercreek Rv Resort",
    "wof:placetype":"venue"
},
  "geometry": {"coordinates":[-123.414168,42.512287],"type":"Point"}
}