{
  "type": "Feature",
  "properties": {
    "iso:country":"US",
    "sg:address":"4010 Aerial Way",
    "sg:city":"Eugene",
    "sg:classifiers":[
        {
            "category":"Health Services",
            "subcategory":"Health Practitioner",
            "type":"Services"
        }
    ],
    "sg:phone":"+1 541 242 8410",
    "sg:postcode":"97402",
    "sg:province":"OR",
    "wof:name":"Barger Physical Therapy",
    "wof:placetype":"venue"
},
  "geometry": {"coordinates":[-123.162049,44.086153],"type":"Point"}
}