{
  "type": "Feature",
  "properties": {
    "addr:full":"6475 SW Borland Rd Tualatin OR 97062",
    "addr:housenumber":"6475",
    "addr:postcode":"97062",
    "addr:street":"Sw Borland Rd",
    "iso:country":"US",
    "sg:address":"6475 SW Borland Rd",
    "sg:city":"Tualatin",
    "sg:classifiers":[
        {
            "category":"Professional",
            "subcategory":"Business Services",
            "type":"Services"
        }
    ],
    "sg:phone":"+1 503 885 0164",
    "sg:postcode":"97062",
    "sg:province":"OR",
    "sg:tags":[
        "medical"
    ],
    "wof:name":"Joanne C Rudoff",
    "wof:placetype":"venue"
},
  "geometry": {"coordinates":[-122.742307,45.376798],"type":"Point"}
}