{
  "type": "Feature",
  "properties": {
    "iso:country":"US",
    "sg:address":"765 NW Joy Avenue",
    "sg:city":"Portland",
    "sg:classifiers":[
        {
            "category":"Personal",
            "subcategory":"Tattoo Parlor",
            "type":"Services"
        },
        {
            "category":"Personal",
            "subcategory":"Piercing",
            "type":"Services"
        }
    ],
    "sg:phone":"+1 503 643 8917",
    "sg:postcode":"97229",
    "sg:province":"OR",
    "sg:tags":[
        "body"
    ],
    "wof:name":"Acme Tattoo",
    "wof:placetype":"venue"
},
  "geometry": {"coordinates":[-122.813937,45.525049],"type":"Point"}
}