{
  "type": "Feature",
  "properties": {
    "iso:country":"US",
    "sg:address":"202 Talent Ave",
    "sg:city":"Talent",
    "sg:classifiers":[
        {
            "category":"Insurance",
            "subcategory":"Hazard Insurance",
            "type":"Services"
        }
    ],
    "sg:phone":"+1 541 535 5505",
    "sg:postcode":"97540",
    "sg:province":"OR",
    "sg:website":"http://statefarm.mqgroup.com/url.asp?usr=372253",
    "wof:name":"State Farm Insurance Agent-Brad Linnell",
    "wof:placetype":"venue"
},
  "geometry": {"coordinates":[-122.786278,42.243858],"type":"Point"}
}