{
  "type": "Feature",
  "properties": {
    "addr:full":"14275 SW Mistletoe Dr Portland OR 97223",
    "addr:housenumber":"14275",
    "addr:postcode":"97223",
    "addr:street":"Sw Mistletoe Dr",
    "iso:country":"US",
    "sg:address":"14275 SW Mistletoe Dr",
    "sg:city":"Portland",
    "sg:classifiers":[
        {
            "category":"Wholesale",
            "subcategory":"Electrical",
            "type":"Manufacturing & Wholesale Goods"
        }
    ],
    "sg:phone":"+1 503 590 9046",
    "sg:postcode":"97223",
    "sg:province":"OR",
    "sg:tags":[
        "electronic",
        "component"
    ],
    "wof:name":"Bolotin Associates Inc",
    "wof:placetype":"venue"
},
  "geometry": {"coordinates":[-122.824158,45.419959],"type":"Point"}
}