{
  "type": "Feature",
  "properties": {
    "iso:country":"US",
    "sg:address":"9150 SE Division St",
    "sg:city":"Portland",
    "sg:classifiers":[
        {
            "category":"Autos & Motor Vehicles",
            "subcategory":"Fuel & Gas Station",
            "type":"Retail Goods"
        }
    ],
    "sg:phone":"+1 503 775 5276",
    "sg:postcode":"97266",
    "sg:province":"OR",
    "sg:tags":[
        "oil"
    ],
    "wof:name":"Chevron Station Inc",
    "wof:placetype":"venue"
},
  "geometry": {"coordinates":[-122.568868,45.504479],"type":"Point"}
}