{
  "type": "Feature",
  "properties": {
    "addr:full":"309 SW Roosevelt Ave Bend OR 97702",
    "addr:housenumber":"309",
    "addr:postcode":"97702",
    "addr:street":"Sw Roosevelt Ave",
    "iso:country":"US",
    "sg:address":"309 SW Roosevelt Ave",
    "sg:city":"Bend",
    "sg:classifiers":[
        {
            "category":"Organizations",
            "subcategory":"Non-profit Organization",
            "type":"Services"
        }
    ],
    "sg:phone":"+1 541 382 5076",
    "sg:postcode":"97702",
    "sg:province":"OR",
    "sg:tags":[
        "fund",
        "counselor",
        "raising"
    ],
    "wof:name":"Win Win Resource Development",
    "wof:placetype":"venue"
},
  "geometry": {"coordinates":[-121.313419,44.042416],"type":"Point"}
}