{
  "type": "Feature",
  "properties": {
    "iso:country":"US",
    "sg:address":"34924 Seavey Loop Rd",
    "sg:city":"Eugene",
    "sg:classifiers":[
        {
            "category":"Wholesale",
            "subcategory":"Motor Vehicles",
            "type":"Manufacturing & Wholesale Goods"
        },
        {
            "category":"Travel",
            "subcategory":"Travel Agent",
            "type":"Entertainment"
        },
        {
            "category":"Building & Trades",
            "subcategory":"Construction",
            "type":"Services"
        }
    ],
    "sg:phone":"+1 541 726 1290",
    "sg:postcode":"97405",
    "sg:province":"OR",
    "sg:tags":[
        "campers-wholesale",
        "manufactured",
        "housing-communities",
        "recreational",
        "trailer",
        "manufacturer"
    ],
    "wof:name":"Gooden's Trailer Court",
    "wof:placetype":"venue"
},
  "geometry": {"coordinates":[-123.00392600000001,44.000242],"type":"Point"}
}