{
  "type": "Feature",
  "properties": {
    "addr:full":"304 Quail Dr Newberg OR 97132",
    "addr:housenumber":"304",
    "addr:postcode":"97132",
    "addr:street":"Quail Dr",
    "iso:country":"US",
    "sg:address":"304 Quail Dr",
    "sg:city":"Newberg",
    "sg:classifiers":[
        {
            "category":"Professional",
            "subcategory":"Accounting & Tax Preparation",
            "type":"Services"
        }
    ],
    "sg:phone":"+1 503 537 0545",
    "sg:postcode":"97132",
    "sg:province":"OR",
    "wof:name":"Gb Eagle Service",
    "wof:placetype":"venue"
},
  "geometry": {"coordinates":[-122.97720200000001,45.323229],"type":"Point"}
}