{
  "type": "Feature",
  "properties": {
    "iso:country":"US",
    "sg:address":"115 E Highland Ave",
    "sg:city":"Hermiston",
    "sg:classifiers":[
        {
            "category":"Cinema",
            "subcategory":"Movie Rental",
            "type":"Entertainment"
        }
    ],
    "sg:phone":"+1 541 567 0201",
    "sg:postcode":"97838",
    "sg:province":"OR",
    "sg:tags":[
        "video"
    ],
    "wof:name":"Hollywood Video",
    "wof:placetype":"venue"
},
  "geometry": {"coordinates":[-119.29010599999999,45.835131],"type":"Point"}
}