{
  "type": "Feature",
  "properties": {
    "iso:country":"US",
    "sg:address":"3678 SE Daren Dr",
    "sg:city":"Hillsboro",
    "sg:classifiers":[
        {
            "category":"Building & Trades",
            "subcategory":"Construction",
            "type":"Services"
        }
    ],
    "sg:phone":"+1 503 693 9007",
    "sg:postcode":"97123",
    "sg:province":"OR",
    "sg:tags":[
        "house"
    ],
    "wof:name":"Milam Construction",
    "wof:placetype":"venue"
},
  "geometry": {"coordinates":[-122.96277000000001,45.493004],"type":"Point"}
}