{
  "type": "Feature",
  "properties": {
    "addr:full":"613 NE Hwy 11 Pendleton OR 97801",
    "addr:housenumber":"613",
    "addr:postcode":"97801",
    "addr:street":"Ne Hwy 11",
    "iso:country":"US",
    "sg:address":"613 NE Hwy 11",
    "sg:city":"Pendleton",
    "sg:classifiers":[
        {
            "category":"Retail",
            "subcategory":"Auto Repair",
            "type":"Services"
        }
    ],
    "sg:phone":"+1 541 276 0823",
    "sg:postcode":"97801",
    "sg:province":"OR",
    "sg:tags":[
        "body"
    ],
    "wof:name":"Gaines Auto Body & Glass",
    "wof:placetype":"venue"
},
  "geometry": {"coordinates":[-118.754835,45.677997],"type":"Point"}
}