{
  "type": "Feature",
  "properties": {
    "iso:country":"US",
    "sg:address":"20843 Solstice Dr",
    "sg:city":"Bend",
    "sg:classifiers":[
        {
            "category":"Building & Trades",
            "subcategory":"Construction",
            "type":"Services"
        }
    ],
    "sg:phone":"+1 541 382 2557",
    "sg:postcode":"97701",
    "sg:province":"OR",
    "sg:tags":[
        "contractor",
        "material",
        "carpenter",
        "carpentry"
    ],
    "wof:name":"Creative Carpentry Associates",
    "wof:placetype":"venue"
},
  "geometry": {"coordinates":[-121.281158,44.155704],"type":"Point"}
}