{
  "type": "Feature",
  "properties": {
    "iso:country":"US",
    "sg:address":"4605 NE Fremont St 201B",
    "sg:city":"Portland",
    "sg:classifiers":[
        {
            "category":"Shopping",
            "subcategory":"Pets & Pet Supplies",
            "type":"Retail Goods"
        }
    ],
    "sg:phone":"+1 503 517 2104",
    "sg:postcode":"97213",
    "sg:province":"OR",
    "sg:tags":[
        "feed"
    ],
    "wof:name":"Proteus Commodities Inc.",
    "wof:placetype":"venue"
},
  "geometry": {"coordinates":[-122.615723,45.54829],"type":"Point"}
}