{
  "type": "Feature",
  "properties": {
    "iso:country":"US",
    "sg:address":"417 SW 117th Avenue Suite 200",
    "sg:city":"Portland",
    "sg:classifiers":[
        {
            "category":"Health Services",
            "subcategory":"Doctor",
            "type":"Services"
        }
    ],
    "sg:phone":"+1 503 216 9400",
    "sg:postcode":"97225",
    "sg:province":"OR",
    "sg:tags":[
        "dermatologist"
    ],
    "wof:name":"Luu Vein Thao MD",
    "wof:placetype":"venue"
},
  "geometry": {"coordinates":[-122.796554,45.517068],"type":"Point"}
}