{
  "type": "Feature",
  "properties": {
    "iso:country":"US",
    "sg:address":"2625 SE Hawthorne Boulevard",
    "sg:city":"Portland",
    "sg:classifiers":[
        {
            "category":"Health Services",
            "subcategory":"Chiropractor",
            "type":"Services"
        }
    ],
    "sg:phone":"+1 503 238 9788",
    "sg:postcode":"97214",
    "sg:province":"OR",
    "wof:name":"Hirsch Surah H DC",
    "wof:placetype":"venue"
},
  "geometry": {"coordinates":[-122.638486,45.512168],"type":"Point"}
}