{
  "type": "Feature",
  "properties": {
    "iso:country":"US",
    "sg:address":"2865 Daggett Ave",
    "sg:city":"Klamath Falls",
    "sg:classifiers":[
        {
            "category":"Health Services",
            "subcategory":"Hospital",
            "type":"Services"
        }
    ],
    "sg:phone":"+1 541 882 6311",
    "sg:postcode":"97601",
    "sg:province":"OR",
    "wof:name":"Merle West Medical Center",
    "wof:placetype":"venue"
},
  "geometry": {"coordinates":[-121.787226,42.252713],"type":"Point"}
}