{
  "type": "Feature",
  "properties": {
    "iso:country":"US",
    "sg:address":"10890 SW Highland Dr",
    "sg:city":"Portland",
    "sg:classifiers":[
        {
            "category":"Building & Trades",
            "subcategory":"Construction",
            "type":"Services"
        }
    ],
    "sg:phone":"+1 503 598 4551",
    "sg:postcode":"97224",
    "sg:province":"OR",
    "sg:tags":[
        "wallcoverings-installation",
        "wallpaper",
        "painting",
        "contractor"
    ],
    "wof:name":"Walloch Painting Co",
    "wof:placetype":"venue"
},
  "geometry": {"coordinates":[-122.788719,45.407066],"type":"Point"}
}