{
  "type": "Feature",
  "properties": {
    "iso:country":"US",
    "sg:address":"20350 Derrick Rd",
    "sg:city":"Pacific City",
    "sg:classifiers":[
        {
            "category":"Recreation",
            "type":"Entertainment"
        }
    ],
    "sg:phone":"+1 503 965 6326",
    "sg:postcode":"97112",
    "sg:province":"OR",
    "sg:tags":[
        "stable"
    ],
    "wof:name":"Into The Sunset",
    "wof:placetype":"venue"
},
  "geometry": {"coordinates":[-123.936852,45.309036],"type":"Point"}
}