{
  "type": "Feature",
  "properties": {
    "iso:country":"US",
    "sg:address":"904 NW 14th Ave",
    "sg:city":"Portland",
    "sg:classifiers":[
        {
            "category":"Building & Trades",
            "subcategory":"Locksmith",
            "type":"Services"
        }
    ],
    "sg:phone":"+1 503 715 2869",
    "sg:postcode":"97209",
    "sg:province":"OR",
    "sg:tags":[
        "key"
    ],
    "wof:name":"A Locksmith Service",
    "wof:placetype":"venue"
},
  "geometry": {"coordinates":[-122.685185,45.529361],"type":"Point"}
}