{
  "type": "Feature",
  "properties": {
    "addr:full":"61550 American Ln Unit 1 Bend OR 97702",
    "addr:housenumber":"61550;unit 1",
    "addr:postcode":"97702",
    "addr:street":"American Ln",
    "iso:country":"US",
    "sg:address":"61550 American Ln Unit 1",
    "sg:city":"Bend",
    "sg:classifiers":[
        {
            "category":"Shopping",
            "subcategory":"Clothing, Apparel, & Fashions",
            "type":"Retail Goods"
        }
    ],
    "sg:phone":"+1 541 318 4250",
    "sg:postcode":"97702",
    "sg:province":"OR",
    "sg:tags":[
        "t-shirt",
        "clothing",
        "store"
    ],
    "sg:website":"http://www.eyeoftheneedle.biz",
    "wof:name":"Eye Of The Needle",
    "wof:placetype":"venue"
},
  "geometry": {"coordinates":[-121.291298,44.035226],"type":"Point"}
}