{
  "type": "Feature",
  "properties": {
    "iso:country":"US",
    "sg:address":"545 Woodcrest Dr",
    "sg:city":"Myrtle Creek",
    "sg:classifiers":[
        {
            "category":"Freight",
            "type":"Transportation"
        }
    ],
    "sg:phone":"+1 541 863 4301",
    "sg:postcode":"97457",
    "sg:province":"OR",
    "sg:tags":[
        "operator",
        "local",
        "trucking"
    ],
    "wof:name":"Earl L Bumgarner Inc",
    "wof:placetype":"venue"
},
  "geometry": {"coordinates":[-123.30547,42.992042],"type":"Point"}
}