{
  "type": "Feature",
  "properties": {
    "iso:country":"US",
    "sg:address":"4701 SE 24th ave",
    "sg:city":"Portland",
    "sg:classifiers":[
        {
            "category":"Home & Garden",
            "subcategory":"Furniture",
            "type":"Retail Goods"
        }
    ],
    "sg:phone":"+1 503 317 7009",
    "sg:postcode":"97202",
    "sg:province":"OR",
    "sg:tags":[
        "store"
    ],
    "sg:website":"www.thegoodmod.com/",
    "wof:name":"The Good Mod",
    "wof:placetype":"venue"
},
  "geometry": {"coordinates":[-122.642156,45.488419],"type":"Point"}
}