{
  "type": "Feature",
  "properties": {
    "iso:country":"US",
    "sg:address":"1931 SE Powell Blvd",
    "sg:city":"Portland",
    "sg:classifiers":[
        {
            "category":"Professional",
            "subcategory":"Computer Services",
            "type":"Services"
        }
    ],
    "sg:phone":"+1 503 290 8195",
    "sg:postcode":"97020",
    "sg:province":"OR",
    "sg:tags":[
        "search-engine-optimization",
        "seo",
        "web-design",
        "web-development"
    ],
    "sg:website":"http://www.portlandwebdesignanddevelopment.com",
    "wof:name":"Azunga Marketing",
    "wof:placetype":"venue"
},
  "geometry": {"coordinates":[-122.41255700000001,45.497188],"type":"Point"}
}