{
  "type": "Feature",
  "properties": {
    "addr:full":"13645 NW Science Park Dr Portland OR 97229",
    "addr:housenumber":"13645",
    "addr:postcode":"97229",
    "addr:street":"Nw Science Park Dr",
    "iso:country":"US",
    "sg:address":"13645 NW Science Park Dr",
    "sg:city":"Portland",
    "sg:classifiers":[
        {
            "category":"Retail",
            "subcategory":"Auto Repair",
            "type":"Services"
        }
    ],
    "sg:phone":"+1 503 646 3368",
    "sg:postcode":"97229",
    "sg:province":"OR",
    "sg:tags":[
        "body",
        "automobile",
        "painting"
    ],
    "sg:website":"www.autobodybeautiful.com",
    "wof:name":"Auto Body Beautiful Sunset",
    "wof:placetype":"venue"
},
  "geometry": {"coordinates":[-122.817275,45.525446],"type":"Point"}
}