{
  "type": "Feature",
  "properties": {
    "iso:country":"US",
    "sg:address":"15956 SW Westminster Dr",
    "sg:city":"Portland",
    "sg:classifiers":[
        {
            "category":"Professional",
            "type":"Services"
        }
    ],
    "sg:phone":"+1 503 590 4002",
    "sg:postcode":"97224",
    "sg:province":"OR",
    "wof:name":"Quality Systems Services",
    "wof:placetype":"venue"
},
  "geometry": {"coordinates":[-122.82433399999999,45.404869],"type":"Point"}
}