{
  "type": "Feature",
  "properties": {
    "iso:country":"US",
    "sg:address":"1120 Boone Rd S",
    "sg:city":"Salem",
    "sg:classifiers":[
        {
            "category":"Health Services",
            "subcategory":"Clinic",
            "type":"Services"
        }
    ],
    "sg:phone":"+1 503 371 4066",
    "sg:postcode":"97306",
    "sg:province":"OR",
    "sg:tags":[
        "welfare"
    ],
    "wof:name":"A Touch Of Health",
    "wof:placetype":"venue"
},
  "geometry": {"coordinates":[-123.062342,44.885481],"type":"Point"}
}