{
  "type": "Feature",
  "properties": {
    "iso:country":"US",
    "sg:address":"2310 Commercial St NE",
    "sg:city":"Salem",
    "sg:classifiers":[
        {
            "category":"Wholesale",
            "subcategory":"Office Equipment",
            "type":"Manufacturing & Wholesale Goods"
        }
    ],
    "sg:phone":"+1 503 364 0444",
    "sg:postcode":"97301",
    "sg:province":"OR",
    "sg:tags":[
        "machine",
        "repair",
        "fax",
        "copy"
    ],
    "sg:website":"www.cbm4you.com",
    "wof:name":"Commercial Business Machines",
    "wof:placetype":"venue"
},
  "geometry": {"coordinates":[-123.03263699999999,44.963147],"type":"Point"}
}