{
  "type": "Feature",
  "properties": {
    "addr:full":"47022 Airport Rd Oakridge OR 97463",
    "addr:housenumber":"47022",
    "addr:postcode":"97463",
    "addr:street":"Airport Rd",
    "iso:country":"US",
    "sg:address":"47022 Airport Rd",
    "sg:city":"Oakridge",
    "sg:classifiers":[
        {
            "category":"Shopping",
            "subcategory":"Gifts & Souvenirs",
            "type":"Retail Goods"
        }
    ],
    "sg:phone":"+1 541 782 3908",
    "sg:postcode":"97463",
    "sg:province":"OR",
    "sg:tags":[
        "shop"
    ],
    "wof:name":"Christel's Import",
    "wof:placetype":"venue"
},
  "geometry": {"coordinates":[-122.496258,43.75185],"type":"Point"}
}