{
  "type": "Feature",
  "properties": {
    "addr:full":"1200 NE Baker St Mcminnville OR 97128",
    "addr:housenumber":"1200",
    "addr:postcode":"97128",
    "addr:street":"Ne Baker St",
    "iso:country":"US",
    "sg:address":"1200 NE Baker St",
    "sg:city":"Mcminnville",
    "sg:classifiers":[
        {
            "category":"Restaurant",
            "type":"Food & Drink"
        }
    ],
    "sg:menulink":"http://www.allmenus.com/or/mcminnville/100370-sharis-restaurant/menu/",
    "sg:phone":"+1 503 472 0561",
    "sg:postcode":"97128",
    "sg:province":"OR",
    "sg:tags":[
        "american"
    ],
    "wof:name":"Shari's Restaurant",
    "wof:placetype":"venue"
},
  "geometry": {"coordinates":[-123.197857,45.216628],"type":"Point"}
}