{
  "type": "Feature",
  "properties": {
    "iso:country":"US",
    "sg:address":"2722 SW Clara Ct",
    "sg:city":"Troutdale",
    "sg:classifiers":[
        {
            "category":"Wholesale",
            "subcategory":"Home Furnishings",
            "type":"Manufacturing & Wholesale Goods"
        }
    ],
    "sg:phone":"+1 503 669 5151",
    "sg:postcode":"97060",
    "sg:province":"OR",
    "sg:tags":[
        "house",
        "construction"
    ],
    "wof:name":"Shaw Properties",
    "wof:placetype":"venue"
},
  "geometry": {"coordinates":[-122.392386,45.521325],"type":"Point"}
}