{
  "type": "Feature",
  "properties": {
    "addr:full":"2717 Lancaster Dr NE Salem OR 97305",
    "addr:housenumber":"2717",
    "addr:postcode":"97305",
    "addr:street":"Lancaster Dr Ne",
    "iso:country":"US",
    "sg:address":"2717 Lancaster Dr NE",
    "sg:city":"Salem",
    "sg:classifiers":[
        {
            "category":"Shopping",
            "subcategory":"Bicycles & Sporting Goods",
            "type":"Retail Goods"
        }
    ],
    "sg:phone":"+1 503 315 2255",
    "sg:postcode":"97305",
    "sg:province":"OR",
    "wof:name":"Gart Sports",
    "wof:placetype":"venue"
},
  "geometry": {"coordinates":[-122.98363500000001,44.962413],"type":"Point"}
}