{
  "type": "Feature",
  "properties": {
    "iso:country":"US",
    "sg:address":"13535 SE 145th Ave",
    "sg:city":"Clackamas",
    "sg:classifiers":[
        {
            "category":"Building & Trades",
            "subcategory":"Construction",
            "type":"Services"
        }
    ],
    "sg:phone":"+1 503 658 6605",
    "sg:postcode":"97015",
    "sg:province":"OR",
    "sg:tags":[
        "contractor"
    ],
    "sg:website":"www.portland-rental.com",
    "wof:name":"Gold Star Home",
    "wof:placetype":"venue"
},
  "geometry": {"coordinates":[-122.514961,45.423645],"type":"Point"}
}