{
  "type": "Feature",
  "properties": {
    "iso:country":"US",
    "sg:address":"555 NW 3rd St",
    "sg:city":"Prineville",
    "sg:classifiers":[
        {
            "category":"Banks & Credit Unions",
            "subcategory":"Bank",
            "type":"Services"
        }
    ],
    "sg:phone":"+1 541 447 4105",
    "sg:postcode":"97754",
    "sg:province":"OR",
    "sg:website":"www.cfbnk.com",
    "wof:name":"Community First Bank",
    "wof:placetype":"venue"
},
  "geometry": {"coordinates":[-120.85147,44.303016],"type":"Point"}
}