{
  "type": "Feature",
  "properties": {
    "addr:full":"12360 E Burnside St Portland OR 97233",
    "addr:housenumber":"12360",
    "addr:postcode":"97233",
    "addr:street":"E Burnside St",
    "iso:country":"US",
    "sg:address":"12360 E Burnside St",
    "sg:city":"Portland",
    "sg:classifiers":[
        {
            "category":"Real Estate",
            "subcategory":"Real Estate Services",
            "type":"Services"
        }
    ],
    "sg:phone":"+1 503 256 7400",
    "sg:postcode":"97233",
    "sg:province":"OR",
    "sg:tags":[
        "company",
        "title"
    ],
    "sg:website":"www.landam.com",
    "wof:name":"Land America Transnation Title",
    "wof:placetype":"venue"
},
  "geometry": {"coordinates":[-122.536591,45.522561],"type":"Point"}
}