{
  "type": "Feature",
  "properties": {
    "iso:country":"US",
    "sg:address":"1803 SW Hawthorne Ter",
    "sg:city":"Portland",
    "sg:classifiers":[
        {
            "category":"Shopping",
            "subcategory":"Gifts & Souvenirs",
            "type":"Retail Goods"
        },
        {
            "category":"Manufacturing",
            "subcategory":"Paper Products",
            "type":"Manufacturing & Wholesale Goods"
        }
    ],
    "sg:phone":"+1 503 223 4226",
    "sg:postcode":"97201",
    "sg:province":"OR",
    "sg:tags":[
        "manufacturer",
        "greeting",
        "card",
        "cards-wholesale"
    ],
    "wof:name":"Teripteron",
    "wof:placetype":"venue"
},
  "geometry": {"coordinates":[-122.69812,45.507489],"type":"Point"}
}