{
  "type": "Feature",
  "properties": {
    "iso:country":"US",
    "sg:address":"1020 SW Taylor St",
    "sg:city":"Portland",
    "sg:classifiers":[
        {
            "category":"Health Services",
            "subcategory":"Health Practitioner",
            "type":"Services"
        }
    ],
    "sg:phone":"+1 503 222 4056",
    "sg:postcode":"97205",
    "sg:province":"OR",
    "sg:tags":[
        "psychologist",
        "clinical"
    ],
    "wof:name":"Candace Young PHD",
    "wof:placetype":"venue"
},
  "geometry": {"coordinates":[-122.68371999999999,45.518824],"type":"Point"}
}