{
  "type": "Feature",
  "properties": {
    "addr:full":"230 NE 9th St Bend OR 97701",
    "addr:housenumber":"230",
    "addr:postcode":"97701",
    "addr:street":"Ne 9Th St",
    "iso:country":"US",
    "sg:address":"230 NE 9th St",
    "sg:city":"Bend",
    "sg:classifiers":[
        {
            "category":"Social Services",
            "subcategory":"Child Care",
            "type":"Services"
        }
    ],
    "sg:phone":"+1 541 318 5551",
    "sg:postcode":"97701",
    "sg:province":"OR",
    "sg:tags":[
        "kindergarten",
        "day",
        "preschool"
    ],
    "sg:website":"http://www.sunrisebend.wordpress.com",
    "wof:name":"Sunrise Preschool",
    "wof:placetype":"venue"
},
  "geometry": {"coordinates":[-121.292878,44.052951],"type":"Point"}
}