{
  "type": "Feature",
  "properties": {
    "iso:country":"US",
    "sg:address":"5440 NE Columbia Boulevard",
    "sg:city":"Portland",
    "sg:classifiers":[
        {
            "category":"Home & Garden",
            "subcategory":"Hardware",
            "type":"Retail Goods"
        }
    ],
    "sg:phone":"+1 503 288 2152",
    "sg:postcode":"97218",
    "sg:province":"OR",
    "sg:tags":[
        "store"
    ],
    "wof:name":"Northside Truck Body & Equipment",
    "wof:placetype":"venue"
},
  "geometry": {"coordinates":[-122.606582,45.569557],"type":"Point"}
}