{
  "type": "Feature",
  "properties": {
    "iso:country":"US",
    "sg:address":"2502 E L Ave",
    "sg:city":"La Grande",
    "sg:classifiers":[
        {
            "category":"Building & Trades",
            "subcategory":"Electrical",
            "type":"Services"
        }
    ],
    "sg:phone":"+1 541 963 9445",
    "sg:postcode":"97850",
    "sg:province":"OR",
    "sg:tags":[
        "electrical",
        "contractor"
    ],
    "wof:name":"Bud Hill Electric",
    "wof:placetype":"venue"
},
  "geometry": {"coordinates":[-118.071016,45.321548],"type":"Point"}
}