{
  "type": "Feature",
  "properties": {
    "addr:full":"7053 SE Madison St Hillsboro OR 97123",
    "addr:housenumber":"7053",
    "addr:postcode":"97123",
    "addr:street":"Se Madison St",
    "iso:country":"US",
    "sg:address":"7053 SE Madison St",
    "sg:city":"Hillsboro",
    "sg:classifiers":[
        {
            "category":"Insurance",
            "subcategory":"Insurance Agent",
            "type":"Services"
        }
    ],
    "sg:phone":"+1 503 259 0343",
    "sg:postcode":"97123",
    "sg:province":"OR",
    "wof:name":"Allstate",
    "wof:placetype":"venue"
},
  "geometry": {"coordinates":[-122.90778299999999,45.515729],"type":"Point"}
}