{
  "type": "Feature",
  "properties": {
    "addr:full":"2150 W 19th Pl Eugene OR 97405",
    "addr:housenumber":"2150",
    "addr:postcode":"97405",
    "addr:street":"W 19Th Pl",
    "iso:country":"US",
    "sg:address":"2150 W 19th Pl",
    "sg:city":"Eugene",
    "sg:classifiers":[
        {
            "category":"Health Services",
            "subcategory":"Health Practitioner",
            "type":"Services"
        }
    ],
    "sg:phone":"+1 541 685 9980",
    "sg:postcode":"97405",
    "sg:province":"OR",
    "sg:tags":[
        "personal"
    ],
    "wof:name":"Plant Bonnie M Lmt",
    "wof:placetype":"venue"
},
  "geometry": {"coordinates":[-123.124514,44.038326],"type":"Point"}
}