{
  "type": "Feature",
  "properties": {
    "iso:country":"US",
    "sg:address":"610 Redwood Hwy",
    "sg:city":"Grants Pass",
    "sg:classifiers":[
        {
            "category":"Retail",
            "subcategory":"Auto Repair",
            "type":"Services"
        }
    ],
    "sg:phone":"+1 541 471 4383",
    "sg:postcode":"97527",
    "sg:province":"OR",
    "sg:tags":[
        "general"
    ],
    "wof:name":"Paul S Card Auto Repair",
    "wof:placetype":"venue"
},
  "geometry": {"coordinates":[-123.33885600000001,42.423879],"type":"Point"}
}