{
  "type": "Feature",
  "properties": {
    "iso:country":"US",
    "sg:address":"9640 SW Tigard St.",
    "sg:city":"Tigard",
    "sg:classifiers":[
        {
            "category":"Shopping",
            "subcategory":"Discount & Variety Stores",
            "type":"Retail Goods"
        },
        {
            "category":"Home & Garden",
            "subcategory":"Furniture",
            "type":"Retail Goods"
        }
    ],
    "sg:phone":"+1 503 960 8599",
    "sg:postcode":"97223",
    "sg:province":"OR",
    "sg:tags":[
        "wholesale"
    ],
    "sg:website":"www.furnitureurway.com/",
    "wof:name":"Furniture Ur Way",
    "wof:placetype":"venue"
},
  "geometry": {"coordinates":[-122.77525300000001,45.432279],"type":"Point"}
}