{
  "type": "Feature",
  "properties": {
    "addr:full":"1150 Willow Ln Vale OR 97918",
    "addr:housenumber":"1150",
    "addr:postcode":"97918",
    "addr:street":"Willow Ln",
    "iso:country":"US",
    "sg:address":"1150 Willow Ln",
    "sg:city":"Vale",
    "sg:phone":"+1 541 473 2363",
    "sg:postcode":"97918",
    "sg:province":"OR",
    "sg:tags":[
        "farm",
        "field",
        "crop"
    ],
    "wof:name":"Frank Gardner",
    "wof:placetype":"venue"
},
  "geometry": {"coordinates":[-117.139954,44.024951],"type":"Point"}
}