{
  "type": "Feature",
  "properties": {
    "iso:country":"US",
    "sg:address":"6134 NE Alameda St",
    "sg:city":"Portland",
    "sg:classifiers":[
        {
            "category":"Professional",
            "subcategory":"Employment Agencies",
            "type":"Services"
        }
    ],
    "sg:phone":"+1 541 980 9984",
    "sg:postcode":"97213",
    "sg:province":"OR",
    "sg:tags":[
        "employer"
    ],
    "wof:name":"Peter O'hanley",
    "wof:placetype":"venue"
},
  "geometry": {"coordinates":[-122.600116,45.542253],"type":"Point"}
}