{
  "type": "Feature",
  "properties": {
    "addr:full":"908 Madison St Silverton OR 97381",
    "addr:housenumber":"908",
    "addr:postcode":"97381",
    "addr:street":"Madison St",
    "iso:country":"US",
    "sg:address":"908 Madison St",
    "sg:city":"Silverton",
    "sg:classifiers":[
        {
            "category":"Building & Trades",
            "subcategory":"Construction",
            "type":"Services"
        }
    ],
    "sg:phone":"+1 503 873 7074",
    "sg:postcode":"97381",
    "sg:province":"OR",
    "sg:tags":[
        "contractor"
    ],
    "wof:name":"Mike Tappan Masonry",
    "wof:placetype":"venue"
},
  "geometry": {"coordinates":[-122.77785799999999,44.997453],"type":"Point"}
}