{
  "type": "Feature",
  "properties": {
    "iso:country":"US",
    "sg:address":"191 NW Dogwood Dr",
    "sg:city":"Dundee",
    "sg:classifiers":[
        {
            "category":"Shopping",
            "subcategory":"Books",
            "type":"Retail Goods"
        }
    ],
    "sg:phone":"+1 503 538 8132",
    "sg:postcode":"97115",
    "sg:province":"OR",
    "wof:name":"Aslan Books",
    "wof:placetype":"venue"
},
  "geometry": {"coordinates":[-123.01496400000001,45.285241],"type":"Point"}
}