{
  "type": "Feature",
  "properties": {
    "iso:country":"US",
    "sg:address":"191 SE 2nd Ave",
    "sg:city":"Canby",
    "sg:classifiers":[
        {
            "category":"Utilities",
            "subcategory":"Cable",
            "type":"Services"
        }
    ],
    "sg:phone":"+1 503 982 4085",
    "sg:postcode":"97013",
    "sg:province":"OR",
    "sg:tags":[
        "television"
    ],
    "wof:name":"Broad Bent",
    "wof:placetype":"venue"
},
  "geometry": {"coordinates":[-122.691486,45.261608],"type":"Point"}
}