{
  "type": "Feature",
  "properties": {
    "iso:country":"US",
    "sg:address":"14736 Monitor McKee Rd NE",
    "sg:city":"Mount Angel",
    "sg:classifiers":[
        {
            "category":"Home & Garden",
            "subcategory":"Garden Supply",
            "type":"Retail Goods"
        }
    ],
    "sg:phone":"+1 503 634 2391",
    "sg:postcode":"97362",
    "sg:province":"OR",
    "wof:name":"Monitor Nursery",
    "wof:placetype":"venue"
},
  "geometry": {"coordinates":[-122.760727,45.10192],"type":"Point"}
}