{
  "type": "Feature",
  "properties": {
    "iso:country":"US",
    "sg:address":"29799 SW Town Center Loop E",
    "sg:city":"Wilsonville",
    "sg:classifiers":[
        {
            "category":"Government",
            "subcategory":"Court House",
            "type":"Public Place"
        }
    ],
    "sg:phone":"+1 503 570 1587",
    "sg:postcode":"97070",
    "sg:province":"OR",
    "sg:tags":[
        "justice"
    ],
    "wof:name":"Wilsonville Municipal Court",
    "wof:placetype":"venue"
},
  "geometry": {"coordinates":[-122.75942499999999,45.304514],"type":"Point"}
}