{
  "type": "Feature",
  "properties": {
    "iso:country":"US",
    "sg:address":"33602 SE Santosh St",
    "sg:city":"Scappoose",
    "sg:classifiers":[
        {
            "category":"Retail",
            "subcategory":"Auto Repair",
            "type":"Services"
        }
    ],
    "sg:phone":"+1 503 543 7420",
    "sg:postcode":"97056",
    "sg:province":"OR",
    "sg:tags":[
        "repairing",
        "automobile"
    ],
    "wof:name":"J & J Automotive Svc",
    "wof:placetype":"venue"
},
  "geometry": {"coordinates":[-122.875809,45.753617],"type":"Point"}
}