{
  "type": "Feature",
  "properties": {
    "addr:full":"235 NE Norton Ln Mcminnville OR 97128",
    "addr:housenumber":"235",
    "addr:postcode":"97128",
    "addr:street":"Ne Norton Ln",
    "iso:country":"US",
    "sg:address":"235 NE Norton Ln",
    "sg:city":"Mcminnville",
    "sg:classifiers":[
        {
            "category":"Health Services",
            "subcategory":"Doctor",
            "type":"Services"
        }
    ],
    "sg:phone":"+1 503 472 4688",
    "sg:postcode":"97128",
    "sg:province":"OR",
    "sg:tags":[
        "ophthalmologist"
    ],
    "wof:name":"Eye Clinic",
    "wof:placetype":"venue"
},
  "geometry": {"coordinates":[-123.166634,45.202311],"type":"Point"}
}