{
  "type": "Feature",
  "properties": {
    "iso:country":"US",
    "sg:address":"35825 Sprague River Rd",
    "sg:city":"Sprague River",
    "sg:classifiers":[
        {
            "category":"Freight",
            "type":"Transportation"
        }
    ],
    "sg:phone":"+1 541 533 2537",
    "sg:postcode":"97639",
    "sg:province":"OR",
    "sg:tags":[
        "operator",
        "trucking"
    ],
    "wof:name":"John C Gallagher",
    "wof:placetype":"venue"
},
  "geometry": {"coordinates":[-121.355097,42.410222],"type":"Point"}
}