{
  "type": "Feature",
  "properties": {
    "iso:country":"US",
    "sg:address":"1982 NE 25th Ave",
    "sg:city":"Hillsboro",
    "sg:classifiers":[
        {
            "category":"Manufacturing",
            "subcategory":"Tools & Machinery",
            "type":"Manufacturing & Wholesale Goods"
        }
    ],
    "sg:phone":"+1 503 640 1607",
    "sg:postcode":"97124",
    "sg:province":"OR",
    "sg:tags":[
        "control",
        "industrial",
        "relay"
    ],
    "wof:name":"Ortech Industries",
    "wof:placetype":"venue"
},
  "geometry": {"coordinates":[-122.957019,45.539574],"type":"Point"}
}