{
  "type": "Feature",
  "properties": {
    "iso:country":"US",
    "sg:address":"2323 NE Multnomah St",
    "sg:city":"Portland",
    "sg:classifiers":[
        {
            "category":"Professional",
            "subcategory":"Business Services",
            "type":"Services"
        }
    ],
    "sg:phone":"+1 503 704 0405",
    "sg:postcode":"97232",
    "sg:province":"OR",
    "sg:tags":[
        "interior",
        "designer",
        "design",
        "decorator"
    ],
    "wof:name":"Fortin/Humphrey Design",
    "wof:placetype":"venue"
},
  "geometry": {"coordinates":[-122.64188799999999,45.531448],"type":"Point"}
}