{
  "type": "Feature",
  "properties": {
    "iso:country":"US",
    "sg:address":"55290 King Rd E",
    "sg:city":"Blue River",
    "sg:classifiers":[
        {
            "category":"Professional",
            "type":"Services"
        }
    ],
    "sg:phone":"+1 541 822 3181",
    "sg:postcode":"97413",
    "sg:province":"OR",
    "wof:name":"Stillwater Sciences",
    "wof:placetype":"venue"
},
  "geometry": {"coordinates":[-122.227984,44.167294],"type":"Point"}
}