{
  "type": "Feature",
  "properties": {
    "iso:country":"US",
    "sg:address":"1962 NW Kearney St # 206",
    "sg:city":"Portland",
    "sg:classifiers":[
        {
            "category":"Health Services",
            "subcategory":"Hospital",
            "type":"Services"
        },
        {
            "category":"Health Services",
            "subcategory":"Nursing And Care Facility",
            "type":"Services"
        }
    ],
    "sg:phone":"+1 503 221 8707",
    "sg:postcode":"97209",
    "sg:province":"OR",
    "sg:tags":[
        "nurse",
        "registry",
        "nurses-advanced",
        "practice-arnp"
    ],
    "wof:name":"Paul Kohn Pmhnp",
    "wof:placetype":"venue"
},
  "geometry": {"coordinates":[-122.691759,45.529152],"type":"Point"}
}