{
  "type": "Feature",
  "properties": {
    "addr:full":"17685 NE Leander Dr Sherwood OR 97140",
    "addr:housenumber":"17685",
    "addr:postcode":"97140",
    "addr:street":"Ne Leander Dr",
    "iso:country":"US",
    "sg:address":"17685 NE Leander Dr",
    "sg:city":"Sherwood",
    "sg:classifiers":[
        {
            "category":"Building & Trades",
            "subcategory":"Construction",
            "type":"Services"
        }
    ],
    "sg:phone":"+1 503 625 2896",
    "sg:postcode":"97140",
    "sg:province":"OR",
    "sg:tags":[
        "painting",
        "contractor"
    ],
    "wof:name":"A-1 Custom Paint Removal Inc",
    "wof:placetype":"venue"
},
  "geometry": {"coordinates":[-122.91923,45.34384],"type":"Point"}
}