{
  "type": "Feature",
  "properties": {
    "addr:full":"11800 SW Beaverton Hillsdale Hwy Beaverton OR 97005",
    "addr:housenumber":"11800",
    "addr:postcode":"97005",
    "addr:street":"Sw Beaverton Hillsdale Hwy",
    "iso:country":"US",
    "sg:address":"11800 SW Beaverton Hillsdale Hwy",
    "sg:city":"Beaverton",
    "sg:phone":"+1 503 646 5181",
    "sg:postcode":"97005",
    "sg:province":"OR",
    "sg:website":"http://www.heitzmanbodyandpaint.com",
    "wof:name":"Heitzman Body & Paint Shop",
    "wof:placetype":"venue"
},
  "geometry": {"coordinates":[-122.797398,45.486554],"type":"Point"}
}