{
  "type": "Feature",
  "properties": {
    "iso:country":"US",
    "sg:address":"6244 SW Orchid Dr",
    "sg:city":"Portland",
    "sg:classifiers":[
        {
            "category":"Manufacturing",
            "subcategory":"Printing",
            "type":"Manufacturing & Wholesale Goods"
        }
    ],
    "sg:phone":"+1 503 892 2922",
    "sg:postcode":"97219",
    "sg:province":"OR",
    "sg:tags":[
        "periodical"
    ],
    "wof:name":"Pocket Press",
    "wof:placetype":"venue"
},
  "geometry": {"coordinates":[-122.741328,45.458894],"type":"Point"}
}