{
  "type": "Feature",
  "properties": {
    "iso:country":"US",
    "sg:address":"4720 Spyglass Ct",
    "sg:city":"Medford",
    "sg:classifiers":[
        {
            "category":"Professional",
            "subcategory":"Business Services",
            "type":"Services"
        }
    ],
    "sg:phone":"+1 541 512 8888",
    "sg:postcode":"97504",
    "sg:province":"OR",
    "wof:name":"Aaker Paralegal Services",
    "wof:placetype":"venue"
},
  "geometry": {"coordinates":[-122.786463,42.333533],"type":"Point"}
}