{
  "type": "Feature",
  "properties": {
    "iso:country":"US",
    "sg:address":"9300 NE Parrett Mountain Rd",
    "sg:city":"Newberg",
    "sg:classifiers":[
        {
            "category":"Retail",
            "subcategory":"Repair Shop",
            "type":"Services"
        }
    ],
    "sg:phone":"+1 503 625 2058",
    "sg:postcode":"97132",
    "sg:province":"OR",
    "sg:tags":[
        "welding"
    ],
    "wof:name":"Frost Red Welding",
    "wof:placetype":"venue"
},
  "geometry": {"coordinates":[-122.867836,45.28063],"type":"Point"}
}