{
  "type": "Feature",
  "properties": {
    "addr:full":"1111 Netherland Rd Trail OR 97541",
    "addr:housenumber":"1111",
    "addr:postcode":"97541",
    "addr:street":"Netherland Rd Trail",
    "iso:country":"US",
    "sg:address":"1111 Netherland Rd",
    "sg:city":"Trail",
    "sg:classifiers":[
        {
            "category":"Professional",
            "subcategory":"Business Services",
            "type":"Services"
        }
    ],
    "sg:phone":"+1 541 878 3206",
    "sg:postcode":"97541",
    "sg:province":"OR",
    "wof:name":"Hunts Partnership Caretakers",
    "wof:placetype":"venue"
},
  "geometry": {"coordinates":[-122.67481100000001,42.636144],"type":"Point"}
}