{
  "type": "Feature",
  "properties": {
    "addr:full":"2850 SE 82nd Ave Ste #1 Portland OR 97266",
    "addr:housenumber":"2850",
    "addr:postcode":"97266",
    "addr:street":"Se 82Nd Ave Ste # 1",
    "iso:country":"US",
    "sg:address":"2850 SE 82nd Ave Ste #1",
    "sg:city":"Portland",
    "sg:classifiers":[
        {
            "category":"Coffee & Tea",
            "type":"Food & Drink"
        },
        {
            "category":"Restaurant",
            "type":"Food & Drink"
        }
    ],
    "sg:phone":"+1 503 445 6818",
    "sg:postcode":"97266",
    "sg:province":"OR",
    "sg:tags":[
        "taiwanese"
    ],
    "sg:website":"www.bubblebubbletea.com",
    "wof:name":"Bubble Bubble Tea",
    "wof:placetype":"venue"
},
  "geometry": {"coordinates":[-122.576761,45.501652],"type":"Point"}
}