{
  "type": "Feature",
  "properties": {
    "iso:country":"US",
    "sg:address":"26293 Foster Rd",
    "sg:city":"Monroe",
    "sg:classifiers":[
        {
            "category":"Wholesale",
            "subcategory":"Farm Supplies",
            "type":"Manufacturing & Wholesale Goods"
        }
    ],
    "sg:phone":"+1 541 847 2070",
    "sg:postcode":"97456",
    "sg:province":"OR",
    "sg:tags":[
        "livestock"
    ],
    "wof:name":"Crooked Gate Ranch LLC",
    "wof:placetype":"venue"
},
  "geometry": {"coordinates":[-123.37593200000001,44.352759],"type":"Point"}
}