{
  "type": "Feature",
  "properties": {
    "addr:full":"1540 Main St Sweet Home OR 97386",
    "addr:housenumber":"1540",
    "addr:postcode":"97386",
    "addr:street":"Main St",
    "iso:country":"US",
    "sg:address":"1540 Main St",
    "sg:city":"Sweet Home",
    "sg:classifiers":[
        {
            "category":"Food & Beverages",
            "subcategory":"Groceries & Convenience Stores",
            "type":"Retail Goods"
        }
    ],
    "sg:phone":"+1 541 367 3784",
    "sg:postcode":"97386",
    "sg:province":"OR",
    "sg:tags":[
        "supermarket"
    ],
    "wof:name":"Safeway",
    "wof:placetype":"venue"
},
  "geometry": {"coordinates":[-122.72347000000001,44.398876],"type":"Point"}
}