{
  "type": "Feature",
  "properties": {
    "iso:country":"US",
    "sg:address":"4425 SE Woodstock Blvd",
    "sg:city":"Portland",
    "sg:classifiers":[
        {
            "category":"Personal",
            "subcategory":"Nail Salon",
            "type":"Services"
        }
    ],
    "sg:phone":"+1 503 777 2570",
    "sg:postcode":"97206",
    "sg:province":"OR",
    "wof:name":"At Your Fingertips",
    "wof:placetype":"venue"
},
  "geometry": {"coordinates":[-122.61677,45.47943],"type":"Point"}
}