{
  "type": "Feature",
  "properties": {
    "iso:country":"US",
    "sg:address":"90 5th St",
    "sg:city":"Ashland",
    "sg:classifiers":[
        {
            "category":"Home & Garden",
            "subcategory":"Home Furnishings",
            "type":"Retail Goods"
        },
        {
            "category":"Real Estate",
            "subcategory":"Architect",
            "type":"Services"
        }
    ],
    "sg:phone":"+1 541 482 3231",
    "sg:postcode":"97520",
    "sg:province":"OR",
    "sg:tags":[
        "planning",
        "residential",
        "designer",
        "design"
    ],
    "wof:name":"Emerson Design",
    "wof:placetype":"venue"
},
  "geometry": {"coordinates":[-122.706824,42.195389],"type":"Point"}
}