{
  "type": "Feature",
  "properties": {
    "addr:full":"50 SW Gleneagles Way Bend OR 97702",
    "addr:housenumber":"50",
    "addr:postcode":"97702",
    "addr:street":"Sw Gleneagles Way",
    "iso:country":"US",
    "sg:address":"50 SW Gleneagles Way",
    "sg:city":"Bend",
    "sg:classifiers":[
        {
            "category":"Home & Garden",
            "subcategory":"Furniture",
            "type":"Retail Goods"
        }
    ],
    "sg:phone":"+1 541 389 0569",
    "sg:postcode":"97702",
    "sg:province":"OR",
    "sg:tags":[
        "store"
    ],
    "wof:name":"Domani",
    "wof:placetype":"venue"
},
  "geometry": {"coordinates":[-121.34163599999999,44.050818],"type":"Point"}
}