{
  "type": "Feature",
  "properties": {
    "iso:country":"US",
    "sg:address":"1215 NW 23rd Ave",
    "sg:city":"Portland",
    "sg:classifiers":[
        {
            "category":"Building & Trades",
            "subcategory":"Locksmith",
            "type":"Services"
        }
    ],
    "sg:phone":"+1 503 914 1113",
    "sg:postcode":"97210",
    "sg:province":"OR",
    "sg:tags":[
        "key"
    ],
    "wof:name":"A 1 Portland Locksmith",
    "wof:placetype":"venue"
},
  "geometry": {"coordinates":[-122.69884999999999,45.531316],"type":"Point"}
}