{
  "type": "Feature",
  "properties": {
    "addr:full":"90567 Lure Ln Walterville OR 97489",
    "addr:postcode":"90567;97489",
    "addr:street":"Lure Ln",
    "iso:country":"US",
    "sg:address":"90567 Lure Ln",
    "sg:city":"Walterville",
    "sg:classifiers":[
        {
            "category":"Banks & Credit Unions",
            "subcategory":"Bank",
            "type":"Services"
        }
    ],
    "sg:phone":"+1 541 896 3266",
    "sg:postcode":"97489",
    "sg:province":"OR",
    "sg:tags":[
        "loan",
        "real estate"
    ],
    "wof:name":"Banner Mortgage",
    "wof:placetype":"venue"
},
  "geometry": {"coordinates":[-122.611239,44.132733],"type":"Point"}
}