{
  "type": "Feature",
  "properties": {
    "iso:country":"US",
    "sg:address":"76 NE Goodfellow St",
    "sg:city":"Ontario",
    "sg:classifiers":[
        {
            "category":"Restaurant",
            "type":"Food & Drink"
        }
    ],
    "sg:phone":"+1 541 889 7802",
    "sg:postcode":"97914",
    "sg:province":"OR",
    "sg:tags":[
        "style",
        "family",
        "lunch",
        "american",
        "brunch",
        "breakfast"
    ],
    "sg:website":"http://www.dennys.com",
    "wof:name":"Denny's",
    "wof:placetype":"venue"
},
  "geometry": {"coordinates":[-116.94349699999999,44.025341],"type":"Point"}
}