{
  "type": "Feature",
  "properties": {
    "addr:full":"1400 NW Irving St Portland OR 97209",
    "addr:housenumber":"1400",
    "addr:postcode":"97209",
    "addr:street":"Nw Irving St",
    "iso:country":"US",
    "sg:address":"1400 NW Irving St",
    "sg:city":"Portland",
    "sg:classifiers":[
        {
            "category":"Building & Trades",
            "subcategory":"Locksmith",
            "type":"Services"
        }
    ],
    "sg:phone":"+1 503 715 3810",
    "sg:postcode":"97209",
    "sg:province":"OR",
    "sg:tags":[
        "key"
    ],
    "wof:name":"23 7 Locksmith",
    "wof:placetype":"venue"
},
  "geometry": {"coordinates":[-122.684788,45.527774],"type":"Point"}
}