{
  "type": "Feature",
  "properties": {
    "iso:country":"US",
    "sg:address":"633 NE 3rd St",
    "sg:city":"Newport",
    "sg:classifiers":[
        {
            "category":"Education",
            "subcategory":"School",
            "type":"Public Place"
        }
    ],
    "sg:phone":"+1 541 574 2238",
    "sg:postcode":"97365",
    "sg:province":"OR",
    "wof:name":"Art-Science-Tech School",
    "wof:placetype":"venue"
},
  "geometry": {"coordinates":[-124.044076,44.638258],"type":"Point"}
}