{
  "type": "Feature",
  "properties": {
    "iso:country":"US",
    "sg:address":"450 N Buena Vista Ave",
    "sg:city":"Burns",
    "sg:classifiers":[
        {
            "category":"Government",
            "subcategory":"Court House",
            "type":"Public Place"
        }
    ],
    "sg:phone":"+1 541 573 5207",
    "sg:postcode":"97720",
    "sg:province":"OR",
    "sg:tags":[
        "justice",
        "county",
        "state",
        "system"
    ],
    "wof:name":"Harney County Circuit Court",
    "wof:placetype":"venue"
},
  "geometry": {"coordinates":[-119.056549,43.589468],"type":"Point"}
}