{
  "type": "Feature",
  "properties": {
    "iso:country":"US",
    "sg:address":"4665 NW Rosemarie Pl",
    "sg:city":"Corvallis",
    "sg:classifiers":[
        {
            "category":"Restaurant",
            "type":"Food & Drink"
        }
    ],
    "sg:phone":"+1 541 757 8088",
    "sg:postcode":"97330",
    "sg:province":"OR",
    "sg:tags":[
        "asian",
        "chinese",
        "pan"
    ],
    "wof:name":"China Blue Rest Corvallis",
    "wof:placetype":"venue"
},
  "geometry": {"coordinates":[-123.306521,44.596355],"type":"Point"}
}