{
  "type": "Feature",
  "properties": {
    "addr:full":"2412 NE Snow Willow Ct Bend OR 97701",
    "addr:housenumber":"2412",
    "addr:postcode":"97701",
    "addr:street":"Ne;Willow Ct",
    "iso:country":"US",
    "sg:address":"2412 NE Snow Willow Ct",
    "sg:city":"Bend",
    "sg:classifiers":[
        {
            "category":"Building & Trades",
            "subcategory":"Cleaning & Sanitation",
            "type":"Services"
        }
    ],
    "sg:phone":"+1 541 388 7566",
    "sg:postcode":"97701",
    "sg:province":"OR",
    "sg:tags":[
        "new",
        "construction",
        "cleanup",
        "janitorial"
    ],
    "wof:name":"Lisa Maries Cleaning",
    "wof:placetype":"venue"
},
  "geometry": {"coordinates":[-121.267713,44.083357],"type":"Point"}
}