{
  "type": "Feature",
  "properties": {
    "iso:country":"US",
    "sg:address":"32410 Hwy 99E",
    "sg:city":"Tangent",
    "sg:classifiers":[
        {
            "category":"Farming",
            "subcategory":"Farm & Veterinary Services",
            "type":"Manufacturing & Wholesale Goods"
        }
    ],
    "sg:phone":"+1 541 926 1114",
    "sg:postcode":"97389",
    "sg:province":"OR",
    "sg:tags":[
        "seed",
        "grain",
        "cleaning"
    ],
    "wof:name":"Montgomery Warehouse",
    "wof:placetype":"venue"
},
  "geometry": {"coordinates":[-123.11017,44.525899],"type":"Point"}
}