{
  "type": "Feature",
  "properties": {
    "iso:country":"US",
    "sg:address":"115 Conestoga Way",
    "sg:city":"Eugene",
    "sg:classifiers":[
        {
            "category":"Professional",
            "subcategory":"Management & Consulting",
            "type":"Services"
        }
    ],
    "sg:phone":"+1 541 343 3402",
    "sg:postcode":"97401",
    "sg:province":"OR",
    "sg:tags":[
        "business"
    ],
    "wof:name":"Heatherly Consulting LLC",
    "wof:placetype":"venue"
},
  "geometry": {"coordinates":[-123.05638,44.064227],"type":"Point"}
}