{
  "type": "Feature",
  "properties": {
    "iso:country":"US",
    "sg:address":"24990 State Hwy 62",
    "sg:city":"Trail",
    "sg:classifiers":[
        {
            "category":"Recreation",
            "type":"Entertainment"
        }
    ],
    "sg:phone":"+1 541 878 2004",
    "sg:postcode":"97541",
    "sg:province":"OR",
    "wof:name":"Grieve Kern & Sons Guide Svc",
    "wof:placetype":"venue"
},
  "geometry": {"coordinates":[-122.797737,42.649046],"type":"Point"}
}