{
  "type": "Feature",
  "properties": {
    "iso:country":"US",
    "sg:address":"11535 SW Durham Rd",
    "sg:city":"Portland",
    "sg:classifiers":[
        {
            "category":"Retail",
            "subcategory":"Animal Services",
            "type":"Services"
        }
    ],
    "sg:phone":"+1 503 684 5580",
    "sg:postcode":"97224",
    "sg:province":"OR",
    "sg:tags":[
        "pet",
        "grooming",
        "washing"
    ],
    "wof:name":"Lucky Dog Grooming & Daycare",
    "wof:placetype":"venue"
},
  "geometry": {"coordinates":[-122.796541,45.404447],"type":"Point"}
}