{
  "type": "Feature",
  "properties": {
    "addr:full":"88525 Sharktail Dr Florence OR 97439",
    "addr:postcode":"88525;97439",
    "addr:street":"Sharktail Dr",
    "iso:country":"US",
    "sg:address":"88525 Sharktail Dr",
    "sg:city":"Florence",
    "sg:classifiers":[
        {
            "category":"Professional",
            "subcategory":"Art Services",
            "type":"Services"
        }
    ],
    "sg:phone":"+1 541 997 1374",
    "sg:postcode":"97439",
    "sg:province":"OR",
    "sg:tags":[
        "designer",
        "display",
        "producer"
    ],
    "sg:website":"http://www.stainedglassfantasy.com",
    "wof:name":"Staine Glass Designs By Evelyn",
    "wof:placetype":"venue"
},
  "geometry": {"coordinates":[-124.127287,44.039935],"type":"Point"}
}