{
  "type": "Feature",
  "properties": {
    "iso:country":"US",
    "sg:address":"2600 Center St NE",
    "sg:city":"Salem",
    "sg:classifiers":[
        {
            "category":"Social Services",
            "subcategory":"Adult Care",
            "type":"Services"
        }
    ],
    "sg:phone":"+1 503 945 2911",
    "sg:postcode":"97301",
    "sg:province":"OR",
    "sg:tags":[
        "rehabilitation",
        "facility"
    ],
    "wof:name":"Vocational Services Department",
    "wof:placetype":"venue"
},
  "geometry": {"coordinates":[-123.00212500000001,44.939911],"type":"Point"}
}