{
  "type": "Feature",
  "properties": {
    "iso:country":"US",
    "sg:address":"2410 SE 121st Ave Suite 204",
    "sg:city":"Portland",
    "sg:classifiers":[
        {
            "category":"Health Services",
            "subcategory":"Medical Lab",
            "type":"Services"
        }
    ],
    "sg:phone":"+1 503 760 4500",
    "sg:postcode":"97216",
    "sg:province":"OR",
    "sg:tags":[
        "transcription"
    ],
    "sg:website":"http://www.automatedtyping.com",
    "wof:name":"Automated Typing Services Inc",
    "wof:placetype":"venue"
},
  "geometry": {"coordinates":[-122.53894,45.504789],"type":"Point"}
}