{
  "type": "Feature",
  "properties": {
    "iso:country":"US",
    "sg:address":"1644 E Burnside St",
    "sg:city":"Portland",
    "sg:classifiers":[
        {
            "category":"Shopping",
            "subcategory":"Pharmacy",
            "type":"Retail Goods"
        }
    ],
    "sg:phone":"+1 503 233 5217",
    "sg:postcode":"97214",
    "sg:province":"OR",
    "wof:name":"Pharmacare",
    "wof:placetype":"venue"
},
  "geometry": {"coordinates":[-122.648853,45.522817],"type":"Point"}
}