{
  "type": "Feature",
  "properties": {
    "addr:full":"12384 Mt Angel Gervais Rd NE Mount Angel OR 97362",
    "addr:housenumber":"12384",
    "addr:postcode":"97362",
    "addr:street":"Mt Angel Gervais Rd Ne",
    "iso:country":"US",
    "sg:address":"12384 Mt Angel Gervais Rd NE",
    "sg:city":"Mount Angel",
    "sg:classifiers":[
        {
            "category":"Farming",
            "subcategory":"Berry Farm",
            "type":"Manufacturing & Wholesale Goods"
        }
    ],
    "sg:phone":"+1 503 845 6545",
    "sg:postcode":"97362",
    "sg:province":"OR",
    "sg:tags":[
        "crop"
    ],
    "wof:name":"Guadalupe Guerrero",
    "wof:placetype":"venue"
},
  "geometry": {"coordinates":[-122.81027,45.072094],"type":"Point"}
}