{
  "type": "Feature",
  "properties": {
    "iso:country":"US",
    "sg:address":"1430 E Cleveland St",
    "sg:city":"Woodburn",
    "sg:classifiers":[
        {
            "category":"Organizations",
            "subcategory":"Religious Organization",
            "type":"Services"
        }
    ],
    "sg:phone":"+1 503 981 8042",
    "sg:postcode":"97071",
    "sg:province":"OR",
    "sg:tags":[
        "church"
    ],
    "wof:name":"House Of Zion Lutheran Church",
    "wof:placetype":"venue"
},
  "geometry": {"coordinates":[-122.846324,45.136053],"type":"Point"}
}