{
  "type": "Feature",
  "properties": {
    "iso:country":"US",
    "sg:address":"1795 Broadway St NE",
    "sg:city":"Salem",
    "sg:classifiers":[
        {
            "category":"Organizations",
            "subcategory":"Religious Organization",
            "type":"Services"
        }
    ],
    "sg:phone":"+1 503 362 5004",
    "sg:postcode":"97301",
    "sg:province":"OR",
    "wof:name":"Salem Jewish Congregation",
    "wof:placetype":"venue"
},
  "geometry": {"coordinates":[-123.029332,44.95541],"type":"Point"}
}