{
  "type": "Feature",
  "properties": {
    "iso:country":"US",
    "sg:address":"210 E Main St",
    "sg:city":"Mt Vernon",
    "sg:classifiers":[
        {
            "category":"Professional",
            "subcategory":"Engineering",
            "type":"Services"
        }
    ],
    "sg:phone":"+1 541 932 4520",
    "sg:postcode":"97865",
    "sg:province":"OR",
    "sg:tags":[
        "engineer"
    ],
    "wof:name":"Ferguson Surveying & Engrg",
    "wof:placetype":"venue"
},
  "geometry": {"coordinates":[-119.10879799999999,44.417856],"type":"Point"}
}