{
  "type": "Feature",
  "properties": {
    "iso:country":"US",
    "sg:address":"42 SW C St",
    "sg:city":"Madras",
    "sg:classifiers":[
        {
            "category":"Banks & Credit Unions",
            "subcategory":"Bank",
            "type":"Services"
        }
    ],
    "sg:phone":"+1 541 475 3811",
    "sg:postcode":"97741",
    "sg:province":"OR",
    "sg:tags":[
        "commercial",
        "saving"
    ],
    "sg:website":"http://www.firstar.com",
    "wof:name":"Us Bank",
    "wof:placetype":"venue"
},
  "geometry": {"coordinates":[-121.13047299999999,44.634641],"type":"Point"}
}