{
  "type": "Feature",
  "properties": {
    "iso:country":"US",
    "sg:address":"367 Myrtlewood Dr",
    "sg:city":"Selma",
    "sg:classifiers":[
        {
            "category":"Shopping",
            "subcategory":"Bicycles & Sporting Goods",
            "type":"Retail Goods"
        }
    ],
    "sg:phone":"+1 541 597 4833",
    "sg:postcode":"97538",
    "sg:province":"OR",
    "wof:name":"Vintage Scuba Supply",
    "wof:placetype":"venue"
},
  "geometry": {"coordinates":[-123.563224,42.22947],"type":"Point"}
}