{
  "type": "Feature",
  "properties": {
    "addr:full":"6235 E Burnside st Portland OR 97213",
    "addr:housenumber":"6235",
    "addr:postcode":"97213",
    "addr:street":"E Burnside St",
    "iso:country":"US",
    "sg:address":"6235 E Burnside st",
    "sg:city":"Portland",
    "sg:classifiers":[
        {
            "category":"Health Services",
            "subcategory":"Clinic",
            "type":"Services"
        }
    ],
    "sg:phone":"+1 503 984 4748",
    "sg:postcode":"97213",
    "sg:province":"OR",
    "sg:tags":[
        "medical"
    ],
    "sg:website":"mttaboracupuncture.com",
    "wof:name":"Jen Conjerti Acupuncturist",
    "wof:placetype":"venue"
},
  "geometry": {"coordinates":[-122.598803,45.523093],"type":"Point"}
}