{
  "type": "Feature",
  "properties": {
    "iso:country":"US",
    "sg:address":"3659 Wallace Rd NW",
    "sg:city":"Salem",
    "sg:classifiers":[
        {
            "category":"Shopping",
            "subcategory":"Bicycles & Sporting Goods",
            "type":"Retail Goods"
        }
    ],
    "sg:phone":"+1 503 588 9676",
    "sg:postcode":"97304",
    "sg:province":"OR",
    "sg:tags":[
        "tackle",
        "fishing"
    ],
    "wof:name":"Oregon Bait",
    "wof:placetype":"venue"
},
  "geometry": {"coordinates":[-123.077161,44.983343],"type":"Point"}
}