{
  "type": "Feature",
  "properties": {
    "iso:country":"US",
    "sg:address":"1000 SW Broadway",
    "sg:city":"Portland",
    "sg:classifiers":[
        {
            "category":"Wholesale",
            "subcategory":"Computers",
            "type":"Manufacturing & Wholesale Goods"
        },
        {
            "category":"Shopping",
            "subcategory":"Computers & Home Electronics",
            "type":"Retail Goods"
        }
    ],
    "sg:phone":"+1 503 228 7435",
    "sg:postcode":"97205",
    "sg:province":"OR",
    "sg:tags":[
        "equipment",
        "dealer"
    ],
    "wof:name":"Hitachi Data Systems Corp",
    "wof:placetype":"venue"
},
  "geometry": {"coordinates":[-122.681066,45.516681],"type":"Point"}
}