{
  "type": "Feature",
  "properties": {
    "iso:country":"US",
    "sg:address":"1006 Church St",
    "sg:city":"Cove",
    "sg:classifiers":[
        {
            "category":"Professional",
            "subcategory":"Business Services",
            "type":"Services"
        }
    ],
    "sg:phone":"+1 541 568 4514",
    "sg:postcode":"97824",
    "sg:province":"OR",
    "sg:tags":[
        "conference",
        "center"
    ],
    "wof:name":"Ascension School-Camp & Ctr",
    "wof:placetype":"venue"
},
  "geometry": {"coordinates":[-117.813604,45.298643],"type":"Point"}
}