{
  "type": "Feature",
  "properties": {
    "iso:country":"US",
    "sg:address":"7941 SE Steele St Ste 4",
    "sg:city":"Portland",
    "sg:classifiers":[
        {
            "category":"Manufacturing",
            "subcategory":"Wood Products",
            "type":"Manufacturing & Wholesale Goods"
        },
        {
            "category":"Building & Trades",
            "subcategory":"Construction",
            "type":"Services"
        }
    ],
    "sg:phone":"+1 503 284 5500",
    "sg:postcode":"97206",
    "sg:province":"OR",
    "sg:tags":[
        "millwork-wholesale",
        "manufacturer",
        "carpenter",
        "millwork"
    ],
    "wof:name":"R W Desch Woodworking Inc",
    "wof:placetype":"venue"
},
  "geometry": {"coordinates":[-122.5817,45.484544],"type":"Point"}
}