{
  "type": "Feature",
  "properties": {
    "iso:country":"US",
    "sg:address":"2119 10th St",
    "sg:city":"Baker City",
    "sg:classifiers":[
        {
            "category":"Shopping",
            "subcategory":"Computers & Home Electronics",
            "type":"Retail Goods"
        }
    ],
    "sg:phone":"+1 541 523 6135",
    "sg:postcode":"97814",
    "sg:province":"OR",
    "sg:tags":[
        "equipment"
    ],
    "wof:name":"Johns Computer Depot Inc",
    "wof:placetype":"venue"
},
  "geometry": {"coordinates":[-117.841247,44.778609],"type":"Point"}
}