{
  "type": "Feature",
  "properties": {
    "iso:country":"US",
    "sg:address":"16055 SW Regatta Ln",
    "sg:city":"Beaverton",
    "sg:classifiers":[
        {
            "category":"Health Services",
            "subcategory":"Dentist",
            "type":"Services"
        }
    ],
    "sg:phone":"+1 503 614 0454",
    "sg:postcode":"97006",
    "sg:province":"OR",
    "wof:name":"Waterhouse Family Dental",
    "wof:placetype":"venue"
},
  "geometry": {"coordinates":[-122.843002,45.516899],"type":"Point"}
}