{
  "type": "Feature",
  "properties": {
    "iso:country":"US",
    "sg:address":"10509 SE Knight St",
    "sg:city":"Portland",
    "sg:classifiers":[
        {
            "category":"Building & Trades",
            "subcategory":"Construction",
            "type":"Services"
        }
    ],
    "sg:phone":"+1 503 775 0196",
    "sg:postcode":"97266",
    "sg:province":"OR",
    "sg:tags":[
        "excavation",
        "excavating",
        "contractor"
    ],
    "wof:name":"N T A Contracting Inc",
    "wof:placetype":"venue"
},
  "geometry": {"coordinates":[-122.55219099999999,45.479709],"type":"Point"}
}