{
  "type": "Feature",
  "properties": {
    "iso:country":"US",
    "sg:address":"7475 SW Oleson Rd",
    "sg:city":"Portland",
    "sg:classifiers":[
        {
            "category":"Education",
            "subcategory":"School",
            "type":"Public Place"
        }
    ],
    "sg:phone":"+1 503 452 9272",
    "sg:postcode":"97223",
    "sg:province":"OR",
    "sg:tags":[
        "kindergarten"
    ],
    "wof:name":"Small Friends",
    "wof:placetype":"venue"
},
  "geometry": {"coordinates":[-122.751467,45.467524],"type":"Point"}
}