{
  "type": "Feature",
  "properties": {
    "iso:country":"US",
    "sg:address":"1727 NW Hill St",
    "sg:city":"Bend",
    "sg:classifiers":[
        {
            "category":"Real Estate",
            "subcategory":"Real Estate Agent",
            "type":"Services"
        }
    ],
    "sg:phone":"+1 541 617 1234",
    "sg:postcode":"97701",
    "sg:province":"OR",
    "wof:name":"Bend Direct Realty",
    "wof:placetype":"venue"
},
  "geometry": {"coordinates":[-121.30882699999999,44.067406],"type":"Point"}
}