{
  "type": "Feature",
  "properties": {
    "iso:country":"US",
    "sg:address":"2025 NW Overton St",
    "sg:city":"Portland",
    "sg:classifiers":[
        {
            "category":"Food & Beverages",
            "subcategory":"Groceries & Convenience Stores",
            "type":"Retail Goods"
        }
    ],
    "sg:phone":"+1 503 459 4304",
    "sg:postcode":"97209",
    "sg:province":"OR",
    "sg:tags":[
        "product"
    ],
    "wof:name":"Real Food For Real People",
    "wof:placetype":"venue"
},
  "geometry": {"coordinates":[-122.69428600000001,45.532086],"type":"Point"}
}