{
  "type": "Feature",
  "properties": {
    "iso:country":"US",
    "sg:address":"2165 Winchester Ave",
    "sg:city":"Reedsport",
    "sg:classifiers":[
        {
            "category":"Restaurant",
            "type":"Food & Drink"
        }
    ],
    "sg:phone":"+1 541 271 3131",
    "sg:postcode":"97467",
    "sg:province":"OR",
    "sg:tags":[
        "beer",
        "wine"
    ],
    "wof:name":"Pizza-Rays & Suzys Inc",
    "wof:placetype":"venue"
},
  "geometry": {"coordinates":[-124.12239,43.695303],"type":"Point"}
}