{
  "type": "Feature",
  "properties": {
    "addr:full":"44750 Camp Morrison Dr Scio OR 97374",
    "addr:housenumber":"44750",
    "addr:postcode":"97374",
    "addr:street":"Camp Morrison Dr",
    "iso:country":"US",
    "sg:address":"44750 Camp Morrison Dr",
    "sg:city":"Scio",
    "sg:classifiers":[
        {
            "category":"Social Services",
            "type":"Services"
        }
    ],
    "sg:phone":"+1 503 394 2228",
    "sg:postcode":"97374",
    "sg:province":"OR",
    "wof:name":"Camp Morrison",
    "wof:placetype":"venue"
},
  "geometry": {"coordinates":[-122.64605400000001,44.680828],"type":"Point"}
}