{
  "type": "Feature",
  "properties": {
    "addr:full":"1370 6th St Umatilla OR 97882",
    "addr:housenumber":"1370",
    "addr:postcode":"97882",
    "addr:street":"6Th St",
    "iso:country":"US",
    "sg:address":"1370 6th St",
    "sg:city":"Umatilla",
    "sg:classifiers":[
        {
            "category":"Travel",
            "subcategory":"Hotels & Motels",
            "type":"Entertainment"
        }
    ],
    "sg:phone":"+1 541 922 3271",
    "sg:postcode":"97882",
    "sg:province":"OR",
    "wof:name":"Umatilla Inn & Suites",
    "wof:placetype":"venue"
},
  "geometry": {"coordinates":[-119.335925,45.918263],"type":"Point"}
}