{
  "type": "Feature",
  "properties": {
    "iso:country":"US",
    "sg:address":"9900 SW Greenburg Rd",
    "sg:city":"Portland",
    "sg:classifiers":[
        {
            "category":"Professional",
            "subcategory":"Business Services",
            "type":"Services"
        }
    ],
    "sg:phone":"+1 503 624 1816",
    "sg:postcode":"97223",
    "sg:province":"OR",
    "wof:name":"Edwards Realty Group",
    "wof:placetype":"venue"
},
  "geometry": {"coordinates":[-122.775281,45.448737],"type":"Point"}
}