{
  "type": "Feature",
  "properties": {
    "iso:country":"US",
    "sg:address":"21140 Sholes Rd",
    "sg:city":"Bend",
    "sg:classifiers":[
        {
            "category":"Building & Trades",
            "subcategory":"Construction",
            "type":"Services"
        }
    ],
    "sg:phone":"+1 541 388 3150",
    "sg:postcode":"97702",
    "sg:province":"OR",
    "sg:tags":[
        "excavation",
        "contractor"
    ],
    "wof:name":"ISE LLC",
    "wof:placetype":"venue"
},
  "geometry": {"coordinates":[-121.26714699999999,43.997882],"type":"Point"}
}