{
  "type": "Feature",
  "properties": {
    "addr:full":"1162 HIGHWAY 99 N EUGENE OR 97402",
    "addr:housenumber":"1162",
    "addr:postcode":"97402",
    "addr:street":"Highway 99 N",
    "iso:country":"US",
    "sg:address":"1162 HIGHWAY 99 N",
    "sg:city":"EUGENE",
    "sg:classifiers":[
        {
            "category":"Home & Garden",
            "subcategory":"Household Appliances",
            "type":"Retail Goods"
        },
        {
            "category":"Communications",
            "subcategory":"Radio Station",
            "type":"Services"
        },
        {
            "category":"Shopping",
            "subcategory":"Computers & Home Electronics",
            "type":"Retail Goods"
        },
        {
            "category":"Home & Garden",
            "subcategory":"Furniture",
            "type":"Retail Goods"
        }
    ],
    "sg:phone":"+1 541 688 2121",
    "sg:postcode":"97402",
    "sg:province":"OR",
    "sg:tags":[
        "renting",
        "television",
        "leasing",
        "radio-renting",
        "equipment",
        "rental"
    ],
    "sg:website":"http://www.rentacenter.com/",
    "wof:name":"Rent-A-Center",
    "wof:placetype":"venue"
},
  "geometry": {"coordinates":[-123.200367,44.14756],"type":"Point"}
}