{
  "type": "Feature",
  "properties": {
    "iso:country":"US",
    "sg:address":"368 NE Fern Ave",
    "sg:city":"Dallas",
    "sg:classifiers":[
        {
            "category":"Personal",
            "subcategory":"Beauty Salon",
            "type":"Services"
        }
    ],
    "sg:phone":"+1 503 623 5865",
    "sg:postcode":"97338",
    "sg:province":"OR",
    "wof:name":"Jazzy Beadazzles",
    "wof:placetype":"venue"
},
  "geometry": {"coordinates":[-123.306867,44.936328],"type":"Point"}
}