{
  "type": "Feature",
  "properties": {
    "iso:country":"US",
    "sg:address":"1871 SW Edgewood Ct",
    "sg:city":"Beaverton",
    "sg:classifiers":[
        {
            "category":"Professional",
            "type":"Services"
        }
    ],
    "sg:phone":"+1 503 646 3587",
    "sg:postcode":"97005",
    "sg:province":"OR",
    "sg:tags":[
        "home",
        "convalescent",
        "nursing"
    ],
    "wof:name":"Eldercare Home Inc",
    "wof:placetype":"venue"
},
  "geometry": {"coordinates":[-122.81389299999999,45.506172],"type":"Point"}
}