{
  "type": "Feature",
  "properties": {
    "addr:full":"1400 S Bertelsen Rd Eugene OR 97402",
    "addr:housenumber":"1400",
    "addr:postcode":"97402",
    "addr:street":"S Bertelsen Rd",
    "iso:country":"US",
    "sg:address":"1400 S Bertelsen Rd",
    "sg:city":"Eugene",
    "sg:classifiers":[
        {
            "category":"Professional",
            "type":"Services"
        },
        {
            "category":"Retail",
            "subcategory":"Auto Rental",
            "type":"Services"
        },
        {
            "category":"Building & Trades",
            "subcategory":"Equipment Rental",
            "type":"Services"
        },
        {
            "category":"Retail",
            "subcategory":"Storage",
            "type":"Services"
        }
    ],
    "sg:phone":"+1 866 205 7339",
    "sg:postcode":"97402",
    "sg:province":"OR",
    "sg:tags":[
        "renting",
        "moving-self",
        "leasing",
        "material",
        "moving",
        "services-labor",
        "truck",
        "trailer"
    ],
    "sg:website":"http://www.pensketruckrental.com/personal_rental/?cid=Yptmlist",
    "wof:name":"Penske Truck Rental",
    "wof:placetype":"venue"
},
  "geometry": {"coordinates":[-123.162458,44.043679],"type":"Point"}
}