{
  "type": "Feature",
  "properties": {
    "addr:full":"2555 NW Nicolai St Portland OR 97210",
    "addr:housenumber":"2555",
    "addr:postcode":"97210",
    "addr:street":"Nw Nicolai St",
    "iso:country":"US",
    "sg:address":"2555 NW Nicolai St",
    "sg:city":"Portland",
    "sg:classifiers":[
        {
            "category":"Manufacturing",
            "subcategory":"Metals",
            "type":"Manufacturing & Wholesale Goods"
        },
        {
            "category":"Home & Garden",
            "subcategory":"Hardware",
            "type":"Retail Goods"
        }
    ],
    "sg:phone":"+1 503 248 1622",
    "sg:postcode":"97210",
    "sg:province":"OR",
    "sg:tags":[
        "steel",
        "warehouse",
        "distributor",
        "metal-wholesale",
        "store",
        "manufacturer"
    ],
    "sg:website":"http://www.westcoastmet.com",
    "wof:name":"West Coast Metals Inc",
    "wof:placetype":"venue"
},
  "geometry": {"coordinates":[-122.70403899999999,45.540298],"type":"Point"}
}