{
  "type": "Feature",
  "properties": {
    "addr:full":"12990 SW Pacific Hwy Portland OR 97223",
    "addr:housenumber":"12990",
    "addr:postcode":"97223",
    "addr:street":"Sw Pacific Hwy",
    "iso:country":"US",
    "sg:address":"12990 SW Pacific Hwy",
    "sg:city":"Portland",
    "sg:classifiers":[
        {
            "category":"Building & Trades",
            "subcategory":"Construction",
            "type":"Services"
        }
    ],
    "sg:phone":"+1 503 620 0260",
    "sg:postcode":"97223",
    "sg:province":"OR",
    "sg:tags":[
        "roofing",
        "contractor"
    ],
    "wof:name":"Arthur Train Roofing",
    "wof:placetype":"venue"
},
  "geometry": {"coordinates":[-122.77936099999999,45.426198],"type":"Point"}
}