{
  "type": "Feature",
  "properties": {
    "iso:country":"US",
    "sg:address":"4330 SE Division St",
    "sg:city":"Portland",
    "sg:classifiers":[
        {
            "category":"Wholesale",
            "subcategory":"Construction Materials",
            "type":"Manufacturing & Wholesale Goods"
        }
    ],
    "sg:phone":"+1 503 235 4188",
    "sg:postcode":"97206",
    "sg:province":"OR",
    "sg:tags":[
        "fence",
        "contractor"
    ],
    "sg:website":"www.foxfencenw.com/",
    "wof:name":"Fox Fence",
    "wof:placetype":"venue"
},
  "geometry": {"coordinates":[-122.617456,45.505109],"type":"Point"}
}