{
  "type": "Feature",
  "properties": {
    "iso:country":"US",
    "sg:address":"3250 NW Saint Helens Rd",
    "sg:city":"Portland",
    "sg:classifiers":[
        {
            "category":"Transit Center",
            "subcategory":"Freight",
            "type":"Transportation"
        },
        {
            "category":"Freight",
            "type":"Transportation"
        }
    ],
    "sg:phone":"+1 503 227 0561",
    "sg:postcode":"97210",
    "sg:province":"OR",
    "sg:tags":[
        "trucking",
        "trucking-heavy",
        "local",
        "trucking-motor",
        "hauling"
    ],
    "sg:website":"http://www.wilhelmtruck.com",
    "wof:name":"Wilhelm Trucking And Rigging",
    "wof:placetype":"venue"
},
  "geometry": {"coordinates":[-122.722487,45.544843],"type":"Point"}
}