{
  "type": "Feature",
  "properties": {
    "iso:country":"US",
    "sg:address":"804 Pearl St",
    "sg:city":"Eugene",
    "sg:classifiers":[
        {
            "category":"Professional",
            "subcategory":"Lawyer & Legal Services",
            "type":"Services"
        }
    ],
    "sg:phone":"+1 541 344 6484",
    "sg:postcode":"97401",
    "sg:province":"OR",
    "wof:name":"Dorothy Morey Attorney",
    "wof:placetype":"venue"
},
  "geometry": {"coordinates":[-123.089756,44.050513],"type":"Point"}
}