{
  "type": "Feature",
  "properties": {
    "iso:country":"US",
    "sg:address":"3200 N Oregon St",
    "sg:city":"Ontario",
    "sg:classifiers":[
        {
            "category":"Real Estate",
            "subcategory":"Developer",
            "type":"Services"
        },
        {
            "category":"Real Estate",
            "subcategory":"Real Estate Operator",
            "type":"Services"
        }
    ],
    "sg:phone":"+1 541 881 1544",
    "sg:postcode":"97914",
    "sg:province":"OR",
    "sg:tags":[
        "mobile",
        "home",
        "site"
    ],
    "wof:name":"River Village Mobile Home Park",
    "wof:placetype":"venue"
},
  "geometry": {"coordinates":[-116.979212,44.056619],"type":"Point"}
}