{
  "type": "Feature",
  "properties": {
    "addr:full":"8229 E Langell Valley Rd Bonanza OR 97623",
    "addr:housenumber":"8229",
    "addr:postcode":"97623",
    "addr:street":"E Langell Valley Rd",
    "iso:country":"US",
    "sg:address":"8229 E Langell Valley Rd",
    "sg:city":"Bonanza",
    "sg:classifiers":[
        {
            "category":"Farming",
            "subcategory":"Livestock Farm",
            "type":"Manufacturing & Wholesale Goods"
        }
    ],
    "sg:phone":"+1 541 545 6908",
    "sg:postcode":"97623",
    "sg:province":"OR",
    "sg:tags":[
        "beef",
        "feedlot",
        "cattle"
    ],
    "wof:name":"Z Lazy S Ranch",
    "wof:placetype":"venue"
},
  "geometry": {"coordinates":[-121.304773,42.147965],"type":"Point"}
}