{
  "type": "Feature",
  "properties": {
    "addr:full":"30 E Broadway Eugene OR 97401",
    "addr:housenumber":"30",
    "addr:postcode":"97401",
    "addr:street":"E Broadway",
    "iso:country":"US",
    "sg:address":"30 E Broadway",
    "sg:city":"Eugene",
    "sg:classifiers":[
        {
            "category":"Arts & Performance",
            "subcategory":"Theater",
            "type":"Entertainment"
        }
    ],
    "sg:phone":"+1 541 345 6648",
    "sg:postcode":"97401",
    "sg:province":"OR",
    "sg:tags":[
        "bureau",
        "concert"
    ],
    "wof:name":"Oregon Mozart Players",
    "wof:placetype":"venue"
},
  "geometry": {"coordinates":[-123.09247000000001,44.049843],"type":"Point"}
}