{
  "type": "Feature",
  "properties": {
    "addr:full":"2673 Willamette St Eugene OR 97405",
    "addr:housenumber":"2673",
    "addr:postcode":"97405",
    "addr:street":"Willamette St",
    "iso:country":"US",
    "sg:address":"2673 Willamette St",
    "sg:city":"Eugene",
    "sg:classifiers":[
        {
            "category":"Restaurant",
            "type":"Food & Drink"
        }
    ],
    "sg:menulink":"http://www.allmenus.com/or/eugene-springfield/42158-pizza-petes-italian-kitchen/menu/",
    "sg:phone":"+1 541 484 0996",
    "sg:postcode":"97405",
    "sg:province":"OR",
    "sg:tags":[
        "italian"
    ],
    "wof:name":"Pizza Pete's Italian Kitchen",
    "wof:placetype":"venue"
},
  "geometry": {"coordinates":[-123.090728,44.029431],"type":"Point"}
}