{
  "type": "Feature",
  "properties": {
    "addr:full":"297 SE Palmblad Dr Gresham OR 97080",
    "addr:housenumber":"297",
    "addr:postcode":"97080",
    "addr:street":"Se Palmblad Dr",
    "iso:country":"US",
    "sg:address":"297 SE Palmblad Dr",
    "sg:city":"Gresham",
    "sg:classifiers":[
        {
            "category":"Professional",
            "subcategory":"Management & Consulting",
            "type":"Services"
        }
    ],
    "sg:phone":"+1 503 666 7669",
    "sg:postcode":"97080",
    "sg:province":"OR",
    "sg:tags":[
        "consultant",
        "training"
    ],
    "wof:name":"Native Wellness Institute",
    "wof:placetype":"venue"
},
  "geometry": {"coordinates":[-122.40317400000001,45.496364],"type":"Point"}
}