{
  "type": "Feature",
  "properties": {
    "iso:country":"US",
    "sg:address":"1017 Kashmir Dr S",
    "sg:city":"Salem",
    "sg:classifiers":[
        {
            "category":"Professional",
            "subcategory":"Computer Services",
            "type":"Services"
        }
    ],
    "sg:phone":"+1 503 390 6023",
    "sg:postcode":"97306",
    "sg:province":"OR",
    "sg:tags":[
        "website",
        "design"
    ],
    "sg:website":"www.thekylepages.com",
    "wof:name":"M & M Web Innovations",
    "wof:placetype":"venue"
},
  "geometry": {"coordinates":[-123.061943,44.881383],"type":"Point"}
}