{
  "type": "Feature",
  "properties": {
    "addr:full":"1145 Madrona Ave S Salem OR 97302",
    "addr:housenumber":"1145",
    "addr:postcode":"97302",
    "addr:street":"Madrona Ave S",
    "iso:country":"US",
    "sg:address":"1145 Madrona Ave S",
    "sg:city":"Salem",
    "sg:classifiers":[
        {
            "category":"Farming",
            "subcategory":"Farm",
            "type":"Manufacturing & Wholesale Goods"
        }
    ],
    "sg:phone":"+1 503 581 9064",
    "sg:postcode":"97302",
    "sg:province":"OR",
    "sg:tags":[
        "crop",
        "general"
    ],
    "wof:name":"D G B Farms",
    "wof:placetype":"venue"
},
  "geometry": {"coordinates":[-123.063777,44.903759],"type":"Point"}
}