{
  "type": "Feature",
  "properties": {
    "addr:full":"6320 S 6th St Klamath Falls OR 97603",
    "addr:housenumber":"6320",
    "addr:postcode":"97603",
    "addr:street":"S 6Th St",
    "iso:country":"US",
    "sg:address":"6320 S 6th St",
    "sg:city":"Klamath Falls",
    "sg:classifiers":[
        {
            "category":"Home & Garden",
            "subcategory":"Furniture",
            "type":"Retail Goods"
        }
    ],
    "sg:phone":"+1 541 882 8811",
    "sg:postcode":"97603",
    "sg:province":"OR",
    "wof:name":"Mc Mahans Furniture Stores",
    "wof:placetype":"venue"
},
  "geometry": {"coordinates":[-121.711416,42.205231],"type":"Point"}
}