{
  "type": "Feature",
  "properties": {
    "iso:country":"US",
    "sg:address":"19 S Orange St",
    "sg:city":"Medford",
    "sg:classifiers":[
        {
            "category":"Professional",
            "subcategory":"Lawyer & Legal Services",
            "type":"Services"
        }
    ],
    "sg:phone":"+1 541 734 4093",
    "sg:postcode":"97501",
    "sg:province":"OR",
    "sg:tags":[
        "attorney",
        "criminal",
        "estate",
        "wills",
        "practice",
        "planning",
        "trust",
        "law"
    ],
    "sg:website":"http://www.robstonelaw.com",
    "wof:name":"Robert M. Stone",
    "wof:placetype":"venue"
},
  "geometry": {"coordinates":[-122.88141,42.32349],"type":"Point"}
}