{
  "type": "Feature",
  "properties": {
    "iso:country":"US",
    "sg:address":"1120 SW 3rd Ave",
    "sg:city":"Portland",
    "sg:classifiers":[
        {
            "category":"Government",
            "subcategory":"Jail",
            "type":"Public Place"
        }
    ],
    "sg:phone":"+1 503 988 3051",
    "sg:postcode":"97204",
    "sg:province":"OR",
    "sg:tags":[
        "county",
        "govt",
        "institution"
    ],
    "sg:website":"www.sheriff-mcso.org",
    "wof:name":"Multnomah County Corrections",
    "wof:placetype":"venue"
},
  "geometry": {"coordinates":[-122.676981,45.515426],"type":"Point"}
}