{
  "type": "Feature",
  "properties": {
    "addr:full":"341 NE Greenwood Ave Bend OR 97701",
    "addr:housenumber":"341",
    "addr:postcode":"97701",
    "addr:street":"Ne Greenwood Ave",
    "iso:country":"US",
    "sg:address":"341 NE Greenwood Ave",
    "sg:city":"Bend",
    "sg:classifiers":[
        {
            "category":"Real Estate",
            "subcategory":"Real Estate Agent",
            "type":"Services"
        }
    ],
    "sg:phone":"+1 541 382 7727",
    "sg:postcode":"97701",
    "sg:province":"OR",
    "wof:name":"Bend Property Management Inc",
    "wof:placetype":"venue"
},
  "geometry": {"coordinates":[-121.301873,44.059864],"type":"Point"}
}