{
  "type": "Feature",
  "properties": {
    "iso:country":"US",
    "sg:address":"520 SW 6th Avenue Suite 920",
    "sg:city":"Portland",
    "sg:classifiers":[
        {
            "category":"Professional",
            "subcategory":"Lawyer & Legal Services",
            "type":"Services"
        }
    ],
    "sg:phone":"+1 503 224 6602",
    "sg:postcode":"97204",
    "sg:province":"OR",
    "wof:name":"Paul & Sugerman",
    "wof:placetype":"venue"
},
  "geometry": {"coordinates":[-122.678116,45.519959],"type":"Point"}
}