{
  "type": "Feature",
  "properties": {
    "iso:country":"US",
    "sg:address":"3778 Little River Rd",
    "sg:city":"Glide",
    "sg:classifiers":[
        {
            "category":"Farming",
            "subcategory":"Livestock Farm",
            "type":"Manufacturing & Wholesale Goods"
        }
    ],
    "sg:phone":"+1 541 496 3435",
    "sg:postcode":"97443",
    "sg:province":"OR",
    "sg:tags":[
        "animal",
        "general"
    ],
    "wof:name":"Neil Talcott",
    "wof:placetype":"venue"
},
  "geometry": {"coordinates":[-123.062864,43.269858],"type":"Point"}
}