{
  "type": "Feature",
  "properties": {
    "iso:country":"US",
    "sg:address":"40 N Main St",
    "sg:city":"Ashland",
    "sg:classifiers":[
        {
            "category":"Recreation",
            "type":"Entertainment"
        }
    ],
    "sg:phone":"+1 541 488 2819",
    "sg:postcode":"97520",
    "sg:province":"OR",
    "sg:tags":[
        "amusement"
    ],
    "sg:website":"www.raftingtours.com",
    "wof:name":"Adventure Center",
    "wof:placetype":"venue"
},
  "geometry": {"coordinates":[-122.715625,42.197938],"type":"Point"}
}