{
  "type": "Feature",
  "properties": {
    "addr:full":"4514 SE 31st Ct Gresham OR 97080",
    "addr:housenumber":"4514",
    "addr:postcode":"97080",
    "addr:street":"Se 31St Ct",
    "iso:country":"US",
    "sg:address":"4514 SE 31st Ct",
    "sg:city":"Gresham",
    "sg:classifiers":[
        {
            "category":"Wholesale",
            "subcategory":"Jewelry",
            "type":"Manufacturing & Wholesale Goods"
        }
    ],
    "sg:phone":"+1 503 663 6605",
    "sg:postcode":"97080",
    "sg:province":"OR",
    "sg:tags":[
        "stone"
    ],
    "wof:name":"D & L Design",
    "wof:placetype":"venue"
},
  "geometry": {"coordinates":[-122.387456,45.47496],"type":"Point"}
}