{
  "type": "Feature",
  "properties": {
    "iso:country":"US",
    "sg:address":"1520 Pacific Blvd SE",
    "sg:city":"Albany",
    "sg:classifiers":[
        {
            "category":"Food & Beverages",
            "subcategory":"Liquor & Beverages",
            "type":"Retail Goods"
        }
    ],
    "sg:phone":"+1 541 967 3472",
    "sg:postcode":"97321",
    "sg:province":"OR",
    "sg:tags":[
        "alcoholic"
    ],
    "wof:name":"One Wine Bar",
    "wof:placetype":"venue"
},
  "geometry": {"coordinates":[-123.087211,44.63368],"type":"Point"}
}