{
  "type": "Feature",
  "properties": {
    "addr:full":"7197 S Tull Rd Canby OR 97013",
    "addr:housenumber":"7197",
    "addr:postcode":"97013",
    "addr:street":"S Tull Rd",
    "iso:country":"US",
    "sg:address":"7197 S Tull Rd",
    "sg:city":"Canby",
    "sg:classifiers":[
        {
            "category":"Wholesale",
            "subcategory":"Machinery & Supplies",
            "type":"Manufacturing & Wholesale Goods"
        }
    ],
    "sg:phone":"+1 503 263 6880",
    "sg:postcode":"97013",
    "sg:province":"OR",
    "sg:tags":[
        "contractor"
    ],
    "wof:name":"Dick Gross Equipment Inc",
    "wof:placetype":"venue"
},
  "geometry": {"coordinates":[-122.71769399999999,45.250097],"type":"Point"}
}