{
  "type": "Feature",
  "properties": {
    "iso:country":"US",
    "sg:address":"157 A St",
    "sg:city":"Ashland",
    "sg:classifiers":[
        {
            "category":"Shopping",
            "subcategory":"Florist",
            "type":"Retail Goods"
        }
    ],
    "sg:phone":"+1 541 488 9173",
    "sg:postcode":"97520",
    "sg:province":"OR",
    "wof:name":"Enchanted Florist",
    "wof:placetype":"venue"
},
  "geometry": {"coordinates":[-122.712062,42.199771],"type":"Point"}
}