{
  "type": "Feature",
  "properties": {
    "iso:country":"US",
    "sg:address":"4235 Fir Rest Way NE",
    "sg:city":"Salem",
    "sg:classifiers":[
        {
            "category":"Real Estate",
            "subcategory":"Real Estate Operator",
            "type":"Services"
        }
    ],
    "sg:phone":"+1 503 581 0322",
    "sg:postcode":"97303",
    "sg:province":"OR",
    "sg:tags":[
        "building",
        "apartment"
    ],
    "wof:name":"Summerwood Apartments",
    "wof:placetype":"venue"
},
  "geometry": {"coordinates":[-122.995457,44.979561],"type":"Point"}
}