{
  "type": "Feature",
  "properties": {
    "addr:full":"1038 Main St Klamath Falls OR 97601",
    "addr:housenumber":"1038",
    "addr:postcode":"97601",
    "addr:street":"Main St",
    "iso:country":"US",
    "sg:address":"1038 Main St",
    "sg:city":"Klamath Falls",
    "sg:classifiers":[
        {
            "category":"Shopping",
            "subcategory":"Used Merchandise",
            "type":"Retail Goods"
        }
    ],
    "sg:phone":"+1 541 885 7752",
    "sg:postcode":"97601",
    "sg:province":"OR",
    "wof:name":"Bear Mountain Mercantile",
    "wof:placetype":"venue"
},
  "geometry": {"coordinates":[-121.77927,42.22728],"type":"Point"}
}