{
  "type": "Feature",
  "properties": {
    "iso:country":"US",
    "sg:address":"724 SW Harrison St",
    "sg:city":"Portland",
    "sg:classifiers":[
        {
            "category":"Education",
            "subcategory":"University",
            "type":"Public Place"
        }
    ],
    "sg:phone":"+1 503 725 3000",
    "sg:postcode":"97201",
    "sg:province":"OR",
    "sg:tags":[
        "college"
    ],
    "sg:website":"www.pdx.edu/",
    "wof:name":"Portland State University",
    "wof:placetype":"venue"
},
  "geometry": {"coordinates":[-122.683998,45.511501],"type":"Point"}
}