{
  "type": "Feature",
  "properties": {
    "iso:country":"US",
    "sg:address":"2121 NE Jack London St",
    "sg:city":"Corvallis",
    "sg:classifiers":[
        {
            "category":"Manufacturing",
            "subcategory":"Tools & Machinery",
            "type":"Manufacturing & Wholesale Goods"
        }
    ],
    "sg:phone":"+1 541 758 3329",
    "sg:postcode":"97330",
    "sg:province":"OR",
    "sg:tags":[
        "mfg",
        "robotic",
        "system",
        "automated"
    ],
    "wof:name":"ATS Systems Oregon",
    "wof:placetype":"venue"
},
  "geometry": {"coordinates":[-123.24702000000001,44.589537],"type":"Point"}
}