{
  "type": "Feature",
  "properties": {
    "iso:country":"US",
    "sg:address":"7606 SE Lambert St",
    "sg:city":"Portland",
    "sg:classifiers":[
        {
            "category":"Personal",
            "type":"Services"
        }
    ],
    "sg:phone":"+1 503 788 2900",
    "sg:postcode":"97206",
    "sg:province":"OR",
    "sg:tags":[
        "therapist",
        "massage"
    ],
    "wof:name":"Christian Massage Therapy",
    "wof:placetype":"venue"
},
  "geometry": {"coordinates":[-122.585267,45.466787],"type":"Point"}
}