{
  "type": "Feature",
  "properties": {
    "addr:full":"8152 SW Hall Blvd Beaverton OR 97008",
    "addr:housenumber":"8152",
    "addr:postcode":"97008",
    "addr:street":"Sw Hall Blvd",
    "iso:country":"US",
    "sg:address":"8152 SW Hall Blvd",
    "sg:city":"Beaverton",
    "sg:classifiers":[
        {
            "category":"Building & Trades",
            "subcategory":"Locksmith",
            "type":"Services"
        }
    ],
    "sg:phone":"+1 503 447 5726",
    "sg:postcode":"97008",
    "sg:province":"OR",
    "sg:tags":[
        "key"
    ],
    "wof:name":"Locksmith 24 Hour",
    "wof:placetype":"venue"
},
  "geometry": {"coordinates":[-122.794748,45.461033],"type":"Point"}
}