{
  "type": "Feature",
  "properties": {
    "iso:country":"US",
    "sg:address":"18645 SW Farmington Rd",
    "sg:city":"Aloha",
    "sg:classifiers":[
        {
            "category":"Restaurant",
            "type":"Food & Drink"
        },
        {
            "category":"Food & Beverages",
            "subcategory":"Meat & Fish",
            "type":"Retail Goods"
        }
    ],
    "sg:phone":"+1 503 356 9718",
    "sg:postcode":"97007",
    "sg:province":"OR",
    "sg:tags":[
        "shop"
    ],
    "wof:name":"Northwest Grilling Steak & Seafood Inc",
    "wof:placetype":"venue"
},
  "geometry": {"coordinates":[-122.86900300000001,45.474499],"type":"Point"}
}