{
  "type": "Feature",
  "properties": {
    "addr:full":"1628 SW Jefferson Street Portland OR 97201",
    "addr:housenumber":"1628",
    "addr:postcode":"97201",
    "addr:street":"Sw Jefferson Street",
    "iso:country":"US",
    "sg:address":"1628 SW Jefferson Street",
    "sg:city":"Portland",
    "sg:classifiers":[
        {
            "category":"Professional",
            "type":"Services"
        }
    ],
    "sg:phone":"+1 503 226 6266",
    "sg:postcode":"97201",
    "sg:province":"OR",
    "sg:tags":[
        "caterer"
    ],
    "wof:name":"Yours Truly",
    "wof:placetype":"venue"
},
  "geometry": {"coordinates":[-122.690647,45.517764],"type":"Point"}
}