{
  "type": "Feature",
  "properties": {
    "iso:country":"US",
    "sg:address":"2028 Main St",
    "sg:city":"Forest Grove",
    "sg:classifiers":[
        {
            "category":"Personal",
            "subcategory":"Beauty Salon",
            "type":"Services"
        }
    ],
    "sg:phone":"+1 503 357 6806",
    "sg:postcode":"97116",
    "sg:province":"OR",
    "sg:tags":[
        "shop"
    ],
    "wof:name":"Brass Comb",
    "wof:placetype":"venue"
},
  "geometry": {"coordinates":[-123.112127,45.520575],"type":"Point"}
}