{
  "type": "Feature",
  "properties": {
    "addr:full":"4023 Commercial St SE Salem OR 97302",
    "addr:housenumber":"4023",
    "addr:postcode":"97302",
    "addr:street":"Commercial St Se",
    "iso:country":"US",
    "sg:address":"4023 Commercial St SE",
    "sg:city":"Salem",
    "sg:classifiers":[
        {
            "category":"Restaurant",
            "type":"Food & Drink"
        },
        {
            "category":"Ice Cream",
            "type":"Food & Drink"
        }
    ],
    "sg:menulink":"http://www.allmenus.com/or/salem/175827-dairy-queen/menu/",
    "sg:phone":"+1 503 581 4598",
    "sg:postcode":"97302",
    "sg:province":"OR",
    "sg:tags":[
        "burger",
        "american",
        "ice",
        "cream"
    ],
    "wof:name":"Dairy Queen",
    "wof:placetype":"venue"
},
  "geometry": {"coordinates":[-123.038515,44.898362],"type":"Point"}
}