{
  "type": "Feature",
  "properties": {
    "iso:country":"US",
    "sg:address":"1440 NW Overton St",
    "sg:city":"Portland",
    "sg:classifiers":[
        {
            "category":"Professional",
            "subcategory":"Business Services",
            "type":"Services"
        }
    ],
    "sg:phone":"+1 503 274 2211",
    "sg:postcode":"97209",
    "sg:province":"OR",
    "sg:tags":[
        "translator",
        "interpreter"
    ],
    "wof:name":"We Localize",
    "wof:placetype":"venue"
},
  "geometry": {"coordinates":[-122.685784,45.532093],"type":"Point"}
}