{
  "type": "Feature",
  "properties": {
    "iso:country":"US",
    "sg:address":"218 NE Hillwood Dr",
    "sg:city":"Hillsboro",
    "sg:classifiers":[
        {
            "category":"Building & Trades",
            "subcategory":"Construction",
            "type":"Services"
        }
    ],
    "sg:phone":"+1 503 648 0609",
    "sg:postcode":"97124",
    "sg:province":"OR",
    "sg:tags":[
        "masonry",
        "contractor"
    ],
    "wof:name":"Hillsboro Masonry Inc",
    "wof:placetype":"venue"
},
  "geometry": {"coordinates":[-122.966479,45.524082],"type":"Point"}
}