{
  "type": "Feature",
  "properties": {
    "addr:full":"14625 SW Moet Ct Portland OR 97224",
    "addr:housenumber":"14625",
    "addr:postcode":"97224",
    "addr:street":"Sw Moet Ct",
    "iso:country":"US",
    "sg:address":"14625 SW Moet Ct",
    "sg:city":"Portland",
    "sg:classifiers":[
        {
            "category":"Real Estate",
            "subcategory":"Real Estate Operator",
            "type":"Services"
        }
    ],
    "sg:phone":"+1 503 579 8520",
    "sg:postcode":"97224",
    "sg:province":"OR",
    "sg:tags":[
        "building",
        "nonresidential"
    ],
    "wof:name":"Diamond Head Properties LLC",
    "wof:placetype":"venue"
},
  "geometry": {"coordinates":[-122.82727300000001,45.412813],"type":"Point"}
}