{
  "type": "Feature",
  "properties": {
    "addr:full":"1563 SW Alder Street Portland OR 97205",
    "addr:housenumber":"1563",
    "addr:postcode":"97205",
    "addr:street":"Sw Alder Street",
    "iso:country":"US",
    "sg:address":"1563 SW Alder Street",
    "sg:city":"Portland",
    "sg:classifiers":[
        {
            "category":"Retail",
            "subcategory":"Auto Repair",
            "type":"Services"
        }
    ],
    "sg:phone":"+1 503 222 7378",
    "sg:postcode":"97205",
    "sg:province":"OR",
    "sg:tags":[
        "detailing"
    ],
    "wof:name":"Uptown Auto Detail",
    "wof:placetype":"venue"
},
  "geometry": {"coordinates":[-122.687394,45.522075],"type":"Point"}
}