{
  "type": "Feature",
  "properties": {
    "addr:full":"13150 Clackamas River Dr Oregon City OR 97045",
    "addr:housenumber":"13150",
    "addr:postcode":"97045",
    "addr:street":"Clackamas River Dr",
    "iso:country":"US",
    "sg:address":"13150 Clackamas River Dr",
    "sg:city":"Oregon City",
    "sg:classifiers":[
        {
            "category":"Building & Trades",
            "subcategory":"Electrical",
            "type":"Services"
        }
    ],
    "sg:phone":"+1 503 557 0230",
    "sg:postcode":"97045",
    "sg:province":"OR",
    "sg:tags":[
        "installation"
    ],
    "wof:name":"First Call Installation",
    "wof:placetype":"venue"
},
  "geometry": {"coordinates":[-122.581564,45.377381],"type":"Point"}
}