{
  "type": "Feature",
  "properties": {
    "addr:full":"6510 N Greeley Avenue Portland OR 97217",
    "addr:housenumber":"6510",
    "addr:postcode":"97217",
    "addr:street":"N Greeley Avenue",
    "iso:country":"US",
    "sg:address":"6510 N Greeley Avenue",
    "sg:city":"Portland",
    "sg:classifiers":[
        {
            "category":"Food & Beverages",
            "subcategory":"Groceries & Convenience Stores",
            "type":"Retail Goods"
        }
    ],
    "sg:phone":"+1 503 285 2111",
    "sg:postcode":"97217",
    "sg:province":"OR",
    "wof:name":"Plaid Pantry Markets",
    "wof:placetype":"venue"
},
  "geometry": {"coordinates":[-122.69539,45.570136],"type":"Point"}
}