{
  "type": "Feature",
  "properties": {
    "addr:full":"601 N 1st Ave Stayton OR 97383",
    "addr:housenumber":"601",
    "addr:postcode":"97383",
    "addr:street":"N 1St Ave",
    "iso:country":"US",
    "sg:address":"601 N 1st Ave",
    "sg:city":"Stayton",
    "sg:classifiers":[
        {
            "category":"Insurance",
            "subcategory":"Insurance Agent",
            "type":"Services"
        }
    ],
    "sg:phone":"+1 503 769 7520",
    "sg:postcode":"97383",
    "sg:province":"OR",
    "wof:name":"Country Insurance & Financial",
    "wof:placetype":"venue"
},
  "geometry": {"coordinates":[-122.79434999999999,44.798619],"type":"Point"}
}