{
  "type": "Feature",
  "properties": {
    "addr:full":"1206 12th St Hood River OR 97031",
    "addr:housenumber":"1206",
    "addr:postcode":"97031",
    "addr:street":"12Th St",
    "iso:country":"US",
    "sg:address":"1206 12th St",
    "sg:city":"Hood River",
    "sg:classifiers":[
        {
            "category":"Banks & Credit Unions",
            "subcategory":"Bank",
            "type":"Services"
        }
    ],
    "sg:phone":"+1 541 387 9297",
    "sg:postcode":"97031",
    "sg:province":"OR",
    "sg:tags":[
        "federal"
    ],
    "sg:website":"www.cascadecentral.com",
    "wof:name":"Cascade Central Credit UNION",
    "wof:placetype":"venue"
},
  "geometry": {"coordinates":[-121.523717,45.70159],"type":"Point"}
}