{
  "type": "Feature",
  "properties": {
    "addr:full":"10530 SW Laurel Rd Beaverton OR 97005",
    "addr:housenumber":"10530",
    "addr:postcode":"97005",
    "addr:street":"Sw Laurel Rd",
    "iso:country":"US",
    "sg:address":"10530 SW Laurel Rd",
    "sg:city":"Beaverton",
    "sg:classifiers":[
        {
            "category":"Building & Trades",
            "subcategory":"Construction",
            "type":"Services"
        }
    ],
    "sg:phone":"+1 503 644 8558",
    "sg:postcode":"97005",
    "sg:province":"OR",
    "sg:tags":[
        "home",
        "builder",
        "contractor",
        "residential"
    ],
    "wof:name":"Rising Sun Construction",
    "wof:placetype":"venue"
},
  "geometry": {"coordinates":[-122.785042,45.487673],"type":"Point"}
}