{
  "type": "Feature",
  "properties": {
    "iso:country":"US",
    "sg:address":"3630 9th Dr",
    "sg:city":"Baker City",
    "sg:classifiers":[
        {
            "category":"Utilities",
            "type":"Services"
        }
    ],
    "sg:phone":"+1 541 523 5917",
    "sg:postcode":"97814",
    "sg:province":"OR",
    "sg:tags":[
        "sanitary"
    ],
    "wof:name":"Dales Snow Plowing",
    "wof:placetype":"venue"
},
  "geometry": {"coordinates":[-117.839233,44.792124],"type":"Point"}
}