{
  "type": "Feature",
  "properties": {
    "addr:full":"3630 9th Dr Baker City OR 97814",
    "addr:housenumber":"3630",
    "addr:postcode":"97814",
    "addr:street":"9Th Dr",
    "iso:country":"US",
    "sg:address":"3630 9th Dr",
    "sg:city":"Baker City",
    "sg:classifiers":[
        {
            "category":"Utilities",
            "type":"Services"
        }
    ],
    "sg:phone":"+1 541 523 5917",
    "sg:postcode":"97814",
    "sg:province":"OR",
    "sg:tags":[
        "sanitary"
    ],
    "wof:name":"Dales Snow Plowing",
    "wof:placetype":"venue"
},
  "geometry": {"coordinates":[-117.83923299999999,44.792124],"type":"Point"}
}