{
  "type": "Feature",
  "properties": {
    "addr:full":"3324 NE 61st Ave Portland OR 97213",
    "addr:housenumber":"3324",
    "addr:postcode":"97213",
    "addr:street":"Ne 61St Ave",
    "iso:country":"US",
    "sg:address":"3324 NE 61st Ave",
    "sg:city":"Portland",
    "sg:classifiers":[
        {
            "category":"Health Services",
            "subcategory":"Clinic",
            "type":"Services"
        }
    ],
    "sg:phone":"+1 503 750 5124",
    "sg:postcode":"97213",
    "sg:province":"OR",
    "sg:tags":[
        "medical"
    ],
    "sg:website":"www.massagebalance.com/",
    "wof:name":"Massage Balance",
    "wof:placetype":"venue"
},
  "geometry": {"coordinates":[-122.600123,45.547322],"type":"Point"}
}