{
  "type": "Feature",
  "properties": {
    "iso:country":"US",
    "sg:address":"235 SW Oak St",
    "sg:city":"Hillsboro",
    "sg:classifiers":[
        {
            "category":"Autos & Motor Vehicles",
            "subcategory":"Auto Supplies",
            "type":"Retail Goods"
        }
    ],
    "sg:phone":"+1 503 648 2196",
    "sg:postcode":"97123",
    "sg:province":"OR",
    "sg:tags":[
        "automobile",
        "parts"
    ],
    "wof:name":"Hillsboro Carquest",
    "wof:placetype":"venue"
},
  "geometry": {"coordinates":[-122.991326,45.518926],"type":"Point"}
}