{
  "type": "Feature",
  "properties": {
    "iso:country":"US",
    "sg:address":"67173 Harrington Loop Rd",
    "sg:city":"Bend",
    "sg:classifiers":[
        {
            "category":"Building & Trades",
            "subcategory":"Construction",
            "type":"Services"
        }
    ],
    "sg:phone":"+1 541 389 7822",
    "sg:postcode":"97701",
    "sg:province":"OR",
    "sg:tags":[
        "house"
    ],
    "wof:name":"Scott Brockway Construction",
    "wof:placetype":"venue"
},
  "geometry": {"coordinates":[-121.476772,44.233162],"type":"Point"}
}