{
  "type": "Feature",
  "properties": {
    "addr:full":"1135 NE Broadway Street Portland OR 97232",
    "addr:housenumber":"1135",
    "addr:postcode":"97232",
    "addr:street":"Ne Broadway Street",
    "iso:country":"US",
    "sg:address":"1135 NE Broadway Street",
    "sg:city":"Portland",
    "sg:classifiers":[
        {
            "category":"Personal",
            "subcategory":"Hair Removal",
            "type":"Services"
        },
        {
            "category":"Personal",
            "subcategory":"Day Spa",
            "type":"Services"
        },
        {
            "category":"Personal",
            "subcategory":"Nail Salon",
            "type":"Services"
        }
    ],
    "sg:phone":"+1 503 288 9099",
    "sg:postcode":"97232",
    "sg:province":"OR",
    "wof:name":"New Identity",
    "wof:placetype":"venue"
},
  "geometry": {"coordinates":[-122.654258,45.535165],"type":"Point"}
}