{
  "type": "Feature",
  "properties": {
    "addr:full":"1104 SW Ardmore Ave Portland OR 97205",
    "addr:housenumber":"1104",
    "addr:postcode":"97205",
    "addr:street":"Sw Ardmore Ave",
    "iso:country":"US",
    "sg:address":"1104 SW Ardmore Ave",
    "sg:city":"Portland",
    "sg:classifiers":[
        {
            "category":"Shopping",
            "subcategory":"Used Merchandise",
            "type":"Retail Goods"
        }
    ],
    "sg:phone":"+1 503 224 0616",
    "sg:postcode":"97205",
    "sg:province":"OR",
    "wof:name":"Sandras Cedar Chest",
    "wof:placetype":"venue"
},
  "geometry": {"coordinates":[-122.699122,45.520613],"type":"Point"}
}