{
  "type": "Feature",
  "properties": {
    "addr:full":"1473 NW Lewis St Bend OR 97701",
    "addr:housenumber":"1473",
    "addr:postcode":"97701",
    "addr:street":"Nw Lewis St",
    "iso:country":"US",
    "sg:address":"1473 NW Lewis St",
    "sg:city":"Bend",
    "sg:classifiers":[
        {
            "category":"Retail",
            "subcategory":"Laundry & Dry Cleaning",
            "type":"Services"
        },
        {
            "category":"Building & Trades",
            "subcategory":"Cleaning & Sanitation",
            "type":"Services"
        }
    ],
    "sg:phone":"+1 541 382 4326",
    "sg:postcode":"97701",
    "sg:province":"OR",
    "sg:tags":[
        "cleaner",
        "upholstery",
        "rug",
        "carpet"
    ],
    "wof:name":"Ecosafe Carpet Cleaning",
    "wof:placetype":"venue"
},
  "geometry": {"coordinates":[-121.35333300000001,44.064066],"type":"Point"}
}