{
  "type": "Feature",
  "properties": {
    "addr:full":"721 Black Oak Dr Medford OR 97504",
    "addr:housenumber":"721",
    "addr:postcode":"97504",
    "addr:street":"Black Oak Dr",
    "iso:country":"US",
    "sg:address":"721 Black Oak Dr",
    "sg:city":"Medford",
    "sg:classifiers":[
        {
            "category":"Food & Beverages",
            "subcategory":"Bakery",
            "type":"Retail Goods"
        }
    ],
    "sg:phone":"+1 541 770 7422",
    "sg:postcode":"97504",
    "sg:province":"OR",
    "sg:tags":[
        "bagel"
    ],
    "wof:name":"Black Oak Deli & Bagel",
    "wof:placetype":"venue"
},
  "geometry": {"coordinates":[-122.83559,42.313938],"type":"Point"}
}