{
  "type": "Feature",
  "properties": {
    "iso:country":"US",
    "sg:address":"2932 NE Stephens St",
    "sg:city":"Roseburg",
    "sg:classifiers":[
        {
            "category":"Restaurant",
            "type":"Food & Drink"
        }
    ],
    "sg:phone":"+1 541 440 2885",
    "sg:postcode":"97470",
    "sg:province":"OR",
    "sg:tags":[
        "sport",
        "bar"
    ],
    "wof:name":"O'Farrell's Food & Spirits",
    "wof:placetype":"venue"
},
  "geometry": {"coordinates":[-123.35289899999999,43.244085],"type":"Point"}
}