{
  "type": "Feature",
  "properties": {
    "addr:full":"4271 SW Plumeria Way Beaverton OR 97007",
    "addr:housenumber":"4271",
    "addr:postcode":"97007",
    "addr:street":"Sw Plumeria Way",
    "iso:country":"US",
    "sg:address":"4271 SW Plumeria Way",
    "sg:city":"Beaverton",
    "sg:classifiers":[
        {
            "category":"Shopping",
            "subcategory":"Catalog Store",
            "type":"Retail Goods"
        },
        {
            "category":"Shopping",
            "subcategory":"Gifts & Souvenirs",
            "type":"Retail Goods"
        }
    ],
    "sg:phone":"+1 503 848 9064",
    "sg:postcode":"97007",
    "sg:province":"OR",
    "sg:tags":[
        "house",
        "mail",
        "collectible"
    ],
    "wof:name":"Charles Collectibles & Stuff",
    "wof:placetype":"venue"
},
  "geometry": {"coordinates":[-122.88201100000001,45.488416],"type":"Point"}
}