{
  "type": "Feature",
  "properties": {
    "iso:country":"US",
    "sg:address":"10316 NW Thompson Rd",
    "sg:city":"Portland",
    "sg:classifiers":[
        {
            "category":"Professional",
            "subcategory":"Art Services",
            "type":"Services"
        },
        {
            "category":"Professional",
            "subcategory":"Printing & Photocopies",
            "type":"Services"
        }
    ],
    "sg:phone":"+1 503 223 4573",
    "sg:postcode":"97229",
    "sg:province":"OR",
    "sg:tags":[
        "graphic",
        "designer",
        "duplicating",
        "copying"
    ],
    "sg:website":"http://www.gowansphoto.com",
    "wof:name":"Infini Photo",
    "wof:placetype":"venue"
},
  "geometry": {"coordinates":[-122.78282799999999,45.546646],"type":"Point"}
}