{
  "type": "Feature",
  "properties": {
    "iso:country":"US",
    "sg:address":"183 S G St",
    "sg:city":"Lakeview",
    "sg:classifiers":[
        {
            "category":"Organizations",
            "subcategory":"Religious Organization",
            "type":"Services"
        }
    ],
    "sg:phone":"+1 541 947 3875",
    "sg:postcode":"97630",
    "sg:province":"OR",
    "sg:tags":[
        "church"
    ],
    "wof:name":"St Patrick's Parish Hall",
    "wof:placetype":"venue"
},
  "geometry": {"coordinates":[-120.34691599999999,42.187326],"type":"Point"}
}