{
  "type": "Feature",
  "properties": {
    "addr:full":"160 SW Madison Ave Corvallis OR 97333",
    "addr:housenumber":"160",
    "addr:postcode":"97333",
    "addr:street":"Sw Madison Ave",
    "iso:country":"US",
    "sg:address":"160 SW Madison Ave",
    "sg:city":"Corvallis",
    "sg:classifiers":[
        {
            "category":"Social Services",
            "type":"Services"
        }
    ],
    "sg:phone":"+1 541 752 1947",
    "sg:postcode":"97333",
    "sg:province":"OR",
    "wof:name":"Yarwood Jill Rn MN Pmhm",
    "wof:placetype":"venue"
},
  "geometry": {"coordinates":[-123.259918,44.562865],"type":"Point"}
}