{
  "type": "Feature",
  "properties": {
    "iso:country":"US",
    "sg:address":"410 White Oak Dr",
    "sg:city":"Cave Junction",
    "sg:classifiers":[
        {
            "category":"Wholesale",
            "subcategory":"Non-durable Goods",
            "type":"Manufacturing & Wholesale Goods"
        }
    ],
    "sg:phone":"+1 541 592 4221",
    "sg:postcode":"97523",
    "sg:province":"OR",
    "wof:name":"Artisan Light Works",
    "wof:placetype":"venue"
},
  "geometry": {"coordinates":[-123.65712499999999,42.12012],"type":"Point"}
}