{
  "type": "Feature",
  "properties": {
    "addr:full":"495 State Hwy 99 N Eugene OR 97402",
    "addr:housenumber":"495",
    "addr:postcode":"97402",
    "addr:street":"State Hwy 99 N",
    "iso:country":"US",
    "sg:address":"495 State Hwy 99 N",
    "sg:city":"Eugene",
    "sg:classifiers":[
        {
            "category":"Shopping",
            "subcategory":"Bicycles & Sporting Goods",
            "type":"Retail Goods"
        }
    ],
    "sg:phone":"+1 541 689 5326",
    "sg:postcode":"97402",
    "sg:province":"OR",
    "sg:tags":[
        "gun",
        "gunsmith"
    ],
    "wof:name":"Four Corners Buy & Sell",
    "wof:placetype":"venue"
},
  "geometry": {"coordinates":[-123.138738,44.065702],"type":"Point"}
}