{
  "type": "Feature",
  "properties": {
    "addr:full":"10500 SW Allen Blvd Beaverton OR 97005",
    "addr:housenumber":"10500",
    "addr:postcode":"97005",
    "addr:street":"Sw Allen Blvd",
    "iso:country":"US",
    "sg:address":"10500 SW Allen Blvd",
    "sg:city":"Beaverton",
    "sg:classifiers":[
        {
            "category":"Real Estate",
            "subcategory":"Real Estate Agent",
            "type":"Services"
        }
    ],
    "sg:phone":"+1 503 646 4451",
    "sg:postcode":"97005",
    "sg:province":"OR",
    "wof:name":"Oregon First Inc",
    "wof:placetype":"venue"
},
  "geometry": {"coordinates":[-122.785343,45.476539],"type":"Point"}
}