{
  "type": "Feature",
  "properties": {
    "iso:country":"US",
    "sg:address":"301 A St E",
    "sg:city":"Vale",
    "sg:classifiers":[
        {
            "category":"Professional",
            "subcategory":"Lawyer & Legal Services",
            "type":"Services"
        }
    ],
    "sg:phone":"+1 541 473 3470",
    "sg:postcode":"97918",
    "sg:province":"OR",
    "sg:tags":[
        "attorney"
    ],
    "wof:name":"Fuson Law Offices",
    "wof:placetype":"venue"
},
  "geometry": {"coordinates":[-117.237161,43.981863],"type":"Point"}
}