{
  "type": "Feature",
  "properties": {
    "addr:full":"3203 SE Woodstock Blvd Portland OR 97202",
    "addr:housenumber":"3203",
    "addr:postcode":"97202",
    "addr:street":"Se Woodstock Blvd",
    "iso:country":"US",
    "sg:address":"3203 SE Woodstock Blvd",
    "sg:city":"Portland",
    "sg:classifiers":[
        {
            "category":"Professional",
            "subcategory":"Business Services",
            "type":"Services"
        }
    ],
    "sg:phone":"+1 503 517 7306",
    "sg:postcode":"97202",
    "sg:province":"OR",
    "sg:tags":[
        "professor"
    ],
    "wof:name":"Netusil Noelwah",
    "wof:placetype":"venue"
},
  "geometry": {"coordinates":[-122.62941499999999,45.479254],"type":"Point"}
}