{
  "type": "Feature",
  "properties": {
    "iso:country":"US",
    "sg:address":"21969 S Woodland Way",
    "sg:city":"Estacada",
    "sg:classifiers":[
        {
            "category":"Organizations",
            "subcategory":"Community Association",
            "type":"Services"
        }
    ],
    "sg:phone":"+1 503 630 3611",
    "sg:postcode":"97023",
    "sg:province":"OR",
    "wof:name":"Springwater Ests Homeowners",
    "wof:placetype":"venue"
},
  "geometry": {"coordinates":[-122.369383,45.28911],"type":"Point"}
}