{
  "type": "Feature",
  "properties": {
    "iso:country":"US",
    "sg:address":"90923 Prairie Rd",
    "sg:city":"Eugene",
    "sg:classifiers":[
        {
            "category":"Professional",
            "type":"Services"
        }
    ],
    "sg:phone":"+1 541 689 7789",
    "sg:postcode":"97402",
    "sg:province":"OR",
    "wof:name":"Hollywood Kustoms",
    "wof:placetype":"venue"
},
  "geometry": {"coordinates":[-123.16817,44.129412],"type":"Point"}
}