{
  "type": "Feature",
  "properties": {
    "iso:country":"US",
    "sg:address":"790 Harrison Ave",
    "sg:city":"Astoria",
    "sg:classifiers":[
        {
            "category":"Recreation",
            "type":"Entertainment"
        }
    ],
    "sg:phone":"+1 503 325 1415",
    "sg:postcode":"97103",
    "sg:province":"OR",
    "wof:name":"Scott McMullen",
    "wof:placetype":"venue"
},
  "geometry": {"coordinates":[-123.835168,46.185673],"type":"Point"}
}