{
  "type": "Feature",
  "properties": {
    "iso:country":"US",
    "sg:address":"300 N Mill St",
    "sg:city":"Creswell",
    "sg:classifiers":[
        {
            "category":"Food & Beverages",
            "subcategory":"Specialty",
            "type":"Retail Goods"
        }
    ],
    "sg:phone":"+1 541 895 8910",
    "sg:postcode":"97426",
    "sg:province":"OR",
    "sg:tags":[
        "vitamin"
    ],
    "sg:website":"www.biocodexusa.com",
    "wof:name":"Biocodex",
    "wof:placetype":"venue"
},
  "geometry": {"coordinates":[-123.017689,43.918691],"type":"Point"}
}