{
  "type": "Feature",
  "properties": {
    "iso:country":"US",
    "sg:address":"981 Orchardview Ave NW",
    "sg:city":"Salem",
    "sg:classifiers":[
        {
            "category":"Building & Trades",
            "subcategory":"Construction",
            "type":"Services"
        }
    ],
    "sg:phone":"+1 503 361 8576",
    "sg:postcode":"97304",
    "sg:province":"OR",
    "sg:tags":[
        "home",
        "custom",
        "remodeling",
        "residential"
    ],
    "wof:name":"Barker Bros Inc",
    "wof:placetype":"venue"
},
  "geometry": {"coordinates":[-123.05887199999999,44.96609],"type":"Point"}
}