{
  "type": "Feature",
  "properties": {
    "addr:full":"7446 SW Fulton Park Blvd Portland OR 97219",
    "addr:housenumber":"7446",
    "addr:postcode":"97219",
    "addr:street":"Sw Fulton Park Blvd",
    "iso:country":"US",
    "sg:address":"7446 SW Fulton Park Blvd",
    "sg:city":"Portland",
    "sg:classifiers":[
        {
            "category":"Professional",
            "subcategory":"Detective & Security Services",
            "type":"Services"
        }
    ],
    "sg:phone":"+1 503 892 2332",
    "sg:postcode":"97219",
    "sg:province":"OR",
    "sg:tags":[
        "investigator"
    ],
    "wof:name":"CTG & Assoc",
    "wof:placetype":"venue"
},
  "geometry": {"coordinates":[-122.67406099999999,45.47005],"type":"Point"}
}