{
  "type": "Feature",
  "properties": {
    "addr:full":"10325 SW 103rd Ct Tualatin OR 97062",
    "addr:housenumber":"10325",
    "addr:postcode":"97062",
    "addr:street":"Sw 103Rd Ct",
    "iso:country":"US",
    "sg:address":"10325 SW 103rd Ct",
    "sg:city":"Tualatin",
    "sg:classifiers":[
        {
            "category":"Professional",
            "type":"Services"
        }
    ],
    "sg:phone":"+1 503 885 0487",
    "sg:postcode":"97062",
    "sg:province":"OR",
    "wof:name":"Kanyit Explorations",
    "wof:placetype":"venue"
},
  "geometry": {"coordinates":[-122.78309299999999,45.365648],"type":"Point"}
}