{
  "type": "Feature",
  "properties": {
    "iso:country":"US",
    "sg:address":"10270 SW Walnut St",
    "sg:city":"Portland",
    "sg:classifiers":[
        {
            "category":"Building & Trades",
            "subcategory":"Construction",
            "type":"Services"
        }
    ],
    "sg:phone":"+1 503 968 9073",
    "sg:postcode":"97223",
    "sg:province":"OR",
    "sg:tags":[
        "plastering",
        "contractor"
    ],
    "wof:name":"Tinsley Plastering",
    "wof:placetype":"venue"
},
  "geometry": {"coordinates":[-122.780924,45.427958],"type":"Point"}
}