{
  "type": "Feature",
  "properties": {
    "iso:country":"US",
    "sg:address":"85436 Teague Loop",
    "sg:city":"Eugene",
    "sg:classifiers":[
        {
            "category":"Restaurant",
            "type":"Food & Drink"
        }
    ],
    "sg:phone":"+1 541 345 8439",
    "sg:postcode":"97405",
    "sg:province":"OR",
    "sg:tags":[
        "eating"
    ],
    "wof:name":"Tsunami Sushi & Laughing",
    "wof:placetype":"venue"
},
  "geometry": {"coordinates":[-123.062558,43.982419],"type":"Point"}
}