{
  "type": "Feature",
  "properties": {
    "addr:full":"35915 7th St Nehalem OR 97131",
    "addr:housenumber":"35915",
    "addr:postcode":"97131",
    "addr:street":"7Th St",
    "iso:country":"US",
    "sg:address":"35915 7th St",
    "sg:city":"Nehalem",
    "sg:classifiers":[
        {
            "category":"Retail",
            "subcategory":"Animal Services",
            "type":"Services"
        }
    ],
    "sg:phone":"+1 503 368 3647",
    "sg:postcode":"97131",
    "sg:province":"OR",
    "sg:tags":[
        "pet",
        "grooming",
        "washing"
    ],
    "wof:name":"Clipper Snip Dog Grooming",
    "wof:placetype":"venue"
},
  "geometry": {"coordinates":[-123.894121,45.717568],"type":"Point"}
}