{
  "type": "Feature",
  "properties": {
    "iso:country":"US",
    "sg:address":"380 SE 3rd St",
    "sg:city":"Bend",
    "sg:classifiers":[
        {
            "category":"Wholesale",
            "subcategory":"Electrical",
            "type":"Manufacturing & Wholesale Goods"
        }
    ],
    "sg:phone":"+1 541 382 7777",
    "sg:postcode":"97702",
    "sg:province":"OR",
    "sg:tags":[
        "control",
        "security",
        "system"
    ],
    "wof:name":"Atlas Security LLC",
    "wof:placetype":"venue"
},
  "geometry": {"coordinates":[-121.302408,44.046508],"type":"Point"}
}