{
  "type": "Feature",
  "properties": {
    "iso:country":"US",
    "sg:address":"225 River St",
    "sg:city":"Saint Helens",
    "sg:classifiers":[
        {
            "category":"Real Estate",
            "subcategory":"Real Estate Agent",
            "type":"Services"
        }
    ],
    "sg:phone":"+1 503 397 4883",
    "sg:postcode":"97051",
    "sg:province":"OR",
    "wof:name":"Purkerson Property Management",
    "wof:placetype":"venue"
},
  "geometry": {"coordinates":[-122.799004,45.866683],"type":"Point"}
}