{
  "type": "Feature",
  "properties": {
    "iso:country":"US",
    "sg:address":"9353 SE Alansa Dr Ste B",
    "sg:city":"Clackamas",
    "sg:classifiers":[
        {
            "category":"Manufacturing",
            "subcategory":"Tools & Machinery",
            "type":"Manufacturing & Wholesale Goods"
        },
        {
            "category":"Wholesale",
            "subcategory":"Machinery & Supplies",
            "type":"Manufacturing & Wholesale Goods"
        }
    ],
    "sg:phone":"+1 503 723 5021",
    "sg:postcode":"97015",
    "sg:province":"OR",
    "sg:tags":[
        "pumps-wholesale",
        "pump",
        "manufacturer"
    ],
    "wof:name":"Pumps Of Division Of Hydro",
    "wof:placetype":"venue"
},
  "geometry": {"coordinates":[-122.568054,45.408828],"type":"Point"}
}