{
  "type": "Feature",
  "properties": {
    "addr:full":"749 River Ave Eugene OR 97404",
    "addr:housenumber":"749",
    "addr:postcode":"97404",
    "addr:street":"River Ave",
    "iso:country":"US",
    "sg:address":"749 River Ave",
    "sg:city":"Eugene",
    "sg:classifiers":[
        {
            "category":"Autos & Motor Vehicles",
            "subcategory":"Automobile Sales",
            "type":"Retail Goods"
        }
    ],
    "sg:phone":"+1 541 461 8494",
    "sg:postcode":"97404",
    "sg:province":"OR",
    "wof:name":"Theresa Bick Apprasials",
    "wof:placetype":"venue"
},
  "geometry": {"coordinates":[-123.11237300000001,44.096718],"type":"Point"}
}