{
  "type": "Feature",
  "properties": {
    "addr:full":"575 SW Washington Ave Corvallis OR 97333",
    "addr:housenumber":"575",
    "addr:postcode":"97333",
    "addr:street":"Sw Washington Ave",
    "iso:country":"US",
    "sg:address":"575 SW Washington Ave",
    "sg:city":"Corvallis",
    "sg:classifiers":[
        {
            "category":"Food & Beverages",
            "subcategory":"Liquor & Beverages",
            "type":"Retail Goods"
        }
    ],
    "sg:phone":"+1 541 753 7998",
    "sg:postcode":"97333",
    "sg:province":"OR",
    "sg:tags":[
        "store"
    ],
    "wof:name":"Washington Street Liquor",
    "wof:placetype":"venue"
},
  "geometry": {"coordinates":[-123.265846,44.561149],"type":"Point"}
}