{
  "type": "Feature",
  "properties": {
    "iso:country":"US",
    "sg:address":"5400 SE 22nd St",
    "sg:city":"Gresham",
    "sg:classifiers":[
        {
            "category":"Home & Garden",
            "subcategory":"Carpets & Floor Coverings",
            "type":"Retail Goods"
        }
    ],
    "sg:phone":"+1 503 663 3605",
    "sg:postcode":"97080",
    "sg:province":"OR",
    "sg:tags":[
        "flooring",
        "contractor"
    ],
    "wof:name":"Rick Broms Subflooring",
    "wof:placetype":"venue"
},
  "geometry": {"coordinates":[-122.378984,45.480759],"type":"Point"}
}