{
  "type": "Feature",
  "properties": {
    "iso:country":"US",
    "sg:address":"1530 Coburg Rd",
    "sg:city":"Eugene",
    "sg:classifiers":[
        {
            "category":"Wholesale",
            "subcategory":"Machinery & Supplies",
            "type":"Manufacturing & Wholesale Goods"
        }
    ],
    "sg:phone":"+1 541 685 0677",
    "sg:postcode":"97401",
    "sg:province":"OR",
    "sg:tags":[
        "equipment",
        "industrial"
    ],
    "wof:name":"Woodcraft",
    "wof:placetype":"venue"
},
  "geometry": {"coordinates":[-123.06867099999999,44.078434],"type":"Point"}
}