{
  "type": "Feature",
  "properties": {
    "addr:full":"178 Commercial Ave Coos Bay OR 97420",
    "addr:housenumber":"178",
    "addr:postcode":"97420",
    "addr:street":"Commercial Ave",
    "iso:country":"US",
    "sg:address":"178 Commercial Ave",
    "sg:city":"Coos Bay",
    "sg:classifiers":[
        {
            "category":"Health Services",
            "subcategory":"Medical Lab",
            "type":"Services"
        }
    ],
    "sg:phone":"+1 541 267 7853",
    "sg:postcode":"97420",
    "sg:province":"OR",
    "sg:tags":[
        "laboratory"
    ],
    "wof:name":"D H Mc Cowan Medical Labs",
    "wof:placetype":"venue"
},
  "geometry": {"coordinates":[-124.21355,43.368743],"type":"Point"}
}