{
  "type": "Feature",
  "properties": {
    "iso:country":"US",
    "sg:address":"61334 S Highway 97",
    "sg:city":"Bend",
    "sg:classifiers":[
        {
            "category":"Shopping",
            "subcategory":"Clothing, Apparel, & Fashions",
            "type":"Retail Goods"
        },
        {
            "category":"Shopping",
            "subcategory":"Party Supplies",
            "type":"Retail Goods"
        }
    ],
    "sg:phone":"+1 541 382 7091",
    "sg:postcode":"97702",
    "sg:province":"OR",
    "sg:tags":[
        "favors",
        "costume"
    ],
    "sg:website":"http://www.spirithalloween.com/StoreLocation.aspx?state=OR",
    "wof:name":"Spirit",
    "wof:placetype":"venue"
},
  "geometry": {"coordinates":[-121.313168,44.027947],"type":"Point"}
}