{
  "type": "Feature",
  "properties": {
    "iso:country":"US",
    "sg:address":"3031 Killdeer Ave",
    "sg:city":"Albany",
    "sg:classifiers":[
        {
            "category":"Shopping",
            "subcategory":"Discount & Variety Stores",
            "type":"Retail Goods"
        }
    ],
    "sg:phone":"+1 541 918 7044",
    "sg:postcode":"97322",
    "sg:province":"OR",
    "sg:tags":[
        "merchandise",
        "general"
    ],
    "wof:name":"Costco Wholesale Corporation",
    "wof:placetype":"venue"
},
  "geometry": {"coordinates":[-123.06349,44.639259],"type":"Point"}
}