{
  "type": "Feature",
  "properties": {
    "iso:country":"US",
    "sg:address":"16200 SW Pacific Hwy Ste G1",
    "sg:city":"Portland",
    "sg:classifiers":[
        {
            "category":"Wholesale",
            "subcategory":"Stationery",
            "type":"Manufacturing & Wholesale Goods"
        }
    ],
    "sg:phone":"+1 503 684 3232",
    "sg:postcode":"97224",
    "sg:province":"OR",
    "sg:tags":[
        "card"
    ],
    "wof:name":"Cardworks",
    "wof:placetype":"venue"
},
  "geometry": {"coordinates":[-122.796504,45.403773],"type":"Point"}
}