{
  "type": "Feature",
  "properties": {
    "iso:country":"US",
    "sg:address":"815 SW Cozine Ln Apt 3",
    "sg:city":"Mcminnville",
    "sg:classifiers":[
        {
            "category":"Real Estate",
            "subcategory":"Real Estate Operator",
            "type":"Services"
        }
    ],
    "sg:phone":"+1 503 435 2770",
    "sg:postcode":"97128",
    "sg:province":"OR",
    "sg:tags":[
        "apartment"
    ],
    "wof:name":"Meadow Creek Apartments",
    "wof:placetype":"venue"
},
  "geometry": {"coordinates":[-123.205856,45.198772],"type":"Point"}
}