{
  "type": "Feature",
  "properties": {
    "addr:full":"4832 NE 21st Ave Portland OR 97211",
    "addr:housenumber":"4832",
    "addr:postcode":"97211",
    "addr:street":"Ne 21St Ave",
    "iso:country":"US",
    "sg:address":"4832 NE 21st Ave",
    "sg:city":"Portland",
    "sg:classifiers":[
        {
            "category":"Banks & Credit Unions",
            "subcategory":"Investment Brokerage",
            "type":"Services"
        }
    ],
    "sg:phone":"+1 503 944 9356",
    "sg:postcode":"97211",
    "sg:province":"OR",
    "sg:tags":[
        "advisory"
    ],
    "wof:name":"Note Finder And Investor",
    "wof:placetype":"venue"
},
  "geometry": {"coordinates":[-122.643866,45.557897],"type":"Point"}
}