{
  "type": "Feature",
  "properties": {
    "addr:full":"1510 Division St Oregon City OR 97045",
    "addr:housenumber":"1510",
    "addr:postcode":"97045",
    "addr:street":"Division St",
    "iso:country":"US",
    "sg:address":"1510 Division St",
    "sg:city":"Oregon City",
    "sg:classifiers":[
        {
            "category":"Health Services",
            "subcategory":"Doctor",
            "type":"Services"
        }
    ],
    "sg:phone":"+1 503 692 1470",
    "sg:postcode":"97045",
    "sg:province":"OR",
    "sg:tags":[
        "physician",
        "surgeon"
    ],
    "wof:name":"Michael P Gardner MD",
    "wof:placetype":"venue"
},
  "geometry": {"coordinates":[-122.58827599999999,45.356733],"type":"Point"}
}