{
  "type": "Feature",
  "properties": {
    "addr:full":"1211 SW 5th Avenue Suite 1600 Portland OR 97204",
    "addr:housenumber":"1211",
    "addr:postcode":"97204",
    "addr:street":"Sw 5Th Avenue Suite 1600",
    "iso:country":"US",
    "sg:address":"1211 SW 5th Avenue Suite 1600",
    "sg:city":"Portland",
    "sg:classifiers":[
        {
            "category":"Professional",
            "subcategory":"Lawyer & Legal Services",
            "type":"Services"
        }
    ],
    "sg:phone":"+1 503 222 9981",
    "sg:postcode":"97204",
    "sg:province":"OR",
    "wof:name":"Loiselle Darien S",
    "wof:placetype":"venue"
},
  "geometry": {"coordinates":[-122.676698,45.519339],"type":"Point"}
}