{
  "type": "Feature",
  "properties": {
    "iso:country":"US",
    "sg:address":"1366 SW 216th Pl",
    "sg:city":"Beaverton",
    "sg:classifiers":[
        {
            "category":"Shopping",
            "subcategory":"Stationery & Office Supplies",
            "type":"Retail Goods"
        },
        {
            "category":"Manufacturing",
            "subcategory":"Printing",
            "type":"Manufacturing & Wholesale Goods"
        },
        {
            "category":"Retail",
            "subcategory":"Repair Shop",
            "type":"Services"
        }
    ],
    "sg:phone":"+1 503 681 2679",
    "sg:postcode":"97006",
    "sg:province":"OR",
    "sg:tags":[
        "copier",
        "machine",
        "equipment",
        "copy",
        "supplies-wholesale",
        "manufacturer"
    ],
    "wof:name":"Copy Machine Specialists-Cms",
    "wof:placetype":"venue"
},
  "geometry": {"coordinates":[-122.89885200000001,45.510056],"type":"Point"}
}