{
  "type": "Feature",
  "properties": {
    "iso:country":"US",
    "sg:address":"3728 NE 113th Ave",
    "sg:city":"Portland",
    "sg:classifiers":[
        {
            "category":"Home & Garden",
            "subcategory":"Home Furnishings",
            "type":"Retail Goods"
        }
    ],
    "sg:phone":"+1 503 254 6244",
    "sg:postcode":"97220",
    "sg:province":"OR",
    "wof:name":"Maidenhair Glass",
    "wof:placetype":"venue"
},
  "geometry": {"coordinates":[-122.546257,45.548567],"type":"Point"}
}