{
  "type": "Feature",
  "properties": {
    "addr:full":"200 Hemlock St Ste 3 Seaside OR 97138",
    "addr:housenumber":"200",
    "addr:postcode":"97138",
    "addr:street":"Hemlock St Ste 3",
    "iso:country":"US",
    "sg:address":"200 Hemlock St Ste 3",
    "sg:city":"Seaside",
    "sg:phone":"+1 503 436 9717",
    "sg:postcode":"97138",
    "sg:province":"OR",
    "sg:website":"http://www.fultanos.com",
    "wof:name":"Fultano's Pizza",
    "wof:placetype":"venue"
},
  "geometry": {"coordinates":[-123.90696699999999,45.991749],"type":"Point"}
}