{
  "type": "Feature",
  "properties": {
    "iso:country":"US",
    "sg:address":"32553 E Punkin Center Rd",
    "sg:city":"Hermiston",
    "sg:classifiers":[
        {
            "category":"Autos & Motor Vehicles",
            "subcategory":"Fuel & Gas Station",
            "type":"Retail Goods"
        },
        {
            "category":"Food & Beverages",
            "subcategory":"Specialty",
            "type":"Retail Goods"
        },
        {
            "category":"Food & Beverages",
            "subcategory":"Groceries & Convenience Stores",
            "type":"Retail Goods"
        }
    ],
    "sg:phone":"+1 541 567 9590",
    "sg:postcode":"97838",
    "sg:province":"OR",
    "sg:tags":[
        "grocers-specialty"
    ],
    "wof:name":"Short Stop 1",
    "wof:placetype":"venue"
},
  "geometry": {"coordinates":[-119.22969399999999,45.86441],"type":"Point"}
}