{
  "type": "Feature",
  "properties": {
    "iso:country":"US",
    "sg:address":"800 NE 8th St",
    "sg:city":"Mcminnville",
    "sg:classifiers":[
        {
            "category":"Personal",
            "subcategory":"Beauty Salon",
            "type":"Services"
        }
    ],
    "sg:phone":"+1 503 472 3097",
    "sg:postcode":"97128",
    "sg:province":"OR",
    "wof:name":"Urban Bliss Salon & Spa",
    "wof:placetype":"venue"
},
  "geometry": {"coordinates":[-123.189718,45.213121],"type":"Point"}
}