{
  "type": "Feature",
  "properties": {
    "iso:country":"US",
    "sg:address":"2323 NW Lakeside Pl",
    "sg:city":"Bend",
    "sg:classifiers":[
        {
            "category":"Professional",
            "type":"Services"
        }
    ],
    "sg:phone":"+1 541 593 4381",
    "sg:postcode":"97701",
    "sg:province":"OR",
    "wof:name":"Collage Studio",
    "wof:placetype":"venue"
},
  "geometry": {"coordinates":[-121.309231,44.072627],"type":"Point"}
}