{
  "type": "Feature",
  "properties": {
    "iso:country":"US",
    "sg:address":"120 S Bridge St",
    "sg:city":"Sheridan",
    "sg:classifiers":[
        {
            "category":"Social Services",
            "type":"Services"
        }
    ],
    "sg:phone":"+1 503 843 7777",
    "sg:postcode":"97378",
    "sg:province":"OR",
    "sg:tags":[
        "organization",
        "welfare"
    ],
    "wof:name":"Grand Sheramina Community Svc",
    "wof:placetype":"venue"
},
  "geometry": {"coordinates":[-123.395267,45.099165],"type":"Point"}
}