{
  "type": "Feature",
  "properties": {
    "iso:country":"US",
    "sg:address":"Fubon Shopping Center 2850 SE 82nd Ave Ste 9",
    "sg:city":"Portland",
    "sg:classifiers":[
        {
            "category":"Personal",
            "subcategory":"Massage",
            "type":"Services"
        }
    ],
    "sg:phone":"+1 503 901 3269",
    "sg:postcode":"97266",
    "sg:province":"OR",
    "wof:name":"Health Spa",
    "wof:placetype":"venue"
},
  "geometry": {"coordinates":[-122.577322,45.501771],"type":"Point"}
}