{
  "type": "Feature",
  "properties": {
    "addr:full":"4901 SE 24th Avenue Portland OR 97202",
    "addr:housenumber":"4901",
    "addr:postcode":"97202",
    "addr:street":"Se 24Th Avenue",
    "iso:country":"US",
    "sg:address":"4901 SE 24th Avenue",
    "sg:city":"Portland",
    "sg:classifiers":[
        {
            "category":"Food & Beverages",
            "subcategory":"Groceries & Convenience Stores",
            "type":"Retail Goods"
        }
    ],
    "sg:phone":"+1 503 230 2883",
    "sg:postcode":"97202",
    "sg:province":"OR",
    "wof:name":"Alpine Food Distributing",
    "wof:placetype":"venue"
},
  "geometry": {"coordinates":[-122.641368,45.487439],"type":"Point"}
}