{
  "type": "Feature",
  "properties": {
    "addr:full":"384 1st Ave Gold Hill OR 97525",
    "addr:housenumber":"384",
    "addr:postcode":"97525",
    "addr:street":"1St Ave",
    "iso:country":"US",
    "sg:address":"384 1st Ave",
    "sg:city":"Gold Hill",
    "sg:classifiers":[
        {
            "category":"Personal",
            "subcategory":"Beauty Salon",
            "type":"Services"
        }
    ],
    "sg:phone":"+1 541 855 5332",
    "sg:postcode":"97525",
    "sg:province":"OR",
    "wof:name":"Gorgeous",
    "wof:placetype":"venue"
},
  "geometry": {"coordinates":[-123.04767,42.4301],"type":"Point"}
}