{
  "type": "Feature",
  "properties": {
    "addr:full":"8665 SW Canyon Ln Apt 6 Portland OR 97225",
    "addr:housenumber":"8665;6",
    "addr:postcode":"97225",
    "addr:street":"Sw Canyon Ln Apt",
    "iso:country":"US",
    "sg:address":"8665 SW Canyon Ln Apt 6",
    "sg:city":"Portland",
    "sg:classifiers":[
        {
            "category":"Recreation",
            "type":"Entertainment"
        }
    ],
    "sg:phone":"+1 503 297 3335",
    "sg:postcode":"97225",
    "sg:province":"OR",
    "sg:tags":[
        "entertainers-family",
        "business"
    ],
    "wof:name":"City Limits Band",
    "wof:placetype":"venue"
},
  "geometry": {"coordinates":[-122.766181,45.499254],"type":"Point"}
}