{
  "type": "Feature",
  "properties": {
    "iso:country":"US",
    "sg:address":"1828 NE D St",
    "sg:city":"Grants Pass",
    "sg:classifiers":[
        {
            "category":"Building & Trades",
            "subcategory":"Cleaning & Sanitation",
            "type":"Services"
        }
    ],
    "sg:phone":"+1 541 474 7903",
    "sg:postcode":"97526",
    "sg:province":"OR",
    "sg:tags":[
        "maintenance"
    ],
    "wof:name":"Affordable Cleaning Service",
    "wof:placetype":"venue"
},
  "geometry": {"coordinates":[-123.303215,42.440164],"type":"Point"}
}