{
  "type": "Feature",
  "properties": {
    "addr:full":"10435 SE 42nd Ave Portland OR 97222",
    "addr:postcode":"10435;97222",
    "addr:street":"Se 42Nd Ave",
    "iso:country":"US",
    "sg:address":"10435 SE 42nd Ave",
    "sg:city":"Portland",
    "sg:classifiers":[
        {
            "category":"Food & Beverages",
            "subcategory":"Groceries & Convenience Stores",
            "type":"Retail Goods"
        }
    ],
    "sg:phone":"+1 503 654 1733",
    "sg:postcode":"97222",
    "sg:province":"OR",
    "wof:name":"7 Eleven Food Stores",
    "wof:placetype":"venue"
},
  "geometry": {"coordinates":[-122.61900300000001,45.447601],"type":"Point"}
}