{
  "type": "Feature",
  "properties": {
    "iso:country":"US",
    "sg:address":"7965 SW 186th Ave",
    "sg:city":"Beaverton",
    "sg:classifiers":[
        {
            "category":"Professional",
            "type":"Services"
        }
    ],
    "sg:phone":"+1 503 591 1610",
    "sg:postcode":"97007",
    "sg:province":"OR",
    "wof:name":"S P Woods",
    "wof:placetype":"venue"
},
  "geometry": {"coordinates":[-122.868585,45.462206],"type":"Point"}
}