{
  "type": "Feature",
  "properties": {
    "iso:country":"US",
    "sg:address":"15207 E Burnside St",
    "sg:city":"Portland",
    "sg:classifiers":[
        {
            "category":"Building & Trades",
            "subcategory":"Plumbing",
            "type":"Services"
        }
    ],
    "sg:phone":"+1 503 252 8013",
    "sg:postcode":"97233",
    "sg:province":"OR",
    "sg:tags":[
        "plumbing",
        "contractor"
    ],
    "wof:name":"Rupic Plumbing",
    "wof:placetype":"venue"
},
  "geometry": {"coordinates":[-122.50709500000001,45.522398],"type":"Point"}
}