{
  "type": "Feature",
  "properties": {
    "iso:country":"US",
    "sg:address":"410 Main St E",
    "sg:city":"Monmouth",
    "sg:classifiers":[
        {
            "category":"Shopping",
            "subcategory":"Florist",
            "type":"Retail Goods"
        }
    ],
    "sg:phone":"+1 503 838 0782",
    "sg:postcode":"97361",
    "sg:province":"OR",
    "wof:name":"Red Vase",
    "wof:placetype":"venue"
},
  "geometry": {"coordinates":[-123.231722,44.848599],"type":"Point"}
}