{
  "type": "Feature",
  "properties": {
    "iso:country":"US",
    "sg:address":"20160 NE Interlachen Ln",
    "sg:city":"Fairview",
    "sg:classifiers":[
        {
            "category":"Banks & Credit Unions",
            "subcategory":"Investment Brokerage",
            "type":"Services"
        }
    ],
    "sg:phone":"+1 503 667 0318",
    "sg:postcode":"97024",
    "sg:province":"OR",
    "sg:tags":[
        "security"
    ],
    "wof:name":"Dinero Darlins",
    "wof:placetype":"venue"
},
  "geometry": {"coordinates":[-122.441692,45.552525],"type":"Point"}
}