{
  "type": "Feature",
  "properties": {
    "iso:country":"US",
    "sg:address":"173 SE 16th St",
    "sg:city":"Madras",
    "sg:classifiers":[
        {
            "category":"Professional",
            "type":"Services"
        }
    ],
    "sg:phone":"+1 541 475 1074",
    "sg:postcode":"97741",
    "sg:province":"OR",
    "wof:name":"Bill R Walker",
    "wof:placetype":"venue"
},
  "geometry": {"coordinates":[-121.11768,44.633774],"type":"Point"}
}