{
  "type": "Feature",
  "properties": {
    "iso:country":"US",
    "sg:address":"11415 SE Beckman Ave",
    "sg:city":"Milwaukie",
    "sg:classifiers":[
        {
            "category":"Building & Trades",
            "subcategory":"Construction",
            "type":"Services"
        }
    ],
    "sg:phone":"+1 503 659 0028",
    "sg:postcode":"97222",
    "sg:province":"OR",
    "sg:tags":[
        "hanging",
        "marking",
        "parking",
        "maintenance",
        "contractor"
    ],
    "wof:name":"Masons Pavement Markings Inc",
    "wof:placetype":"venue"
},
  "geometry": {"coordinates":[-122.60718,45.438808],"type":"Point"}
}