{
  "type": "Feature",
  "properties": {
    "addr:full":"58481 Old Portland Rd St Helens OR 97051",
    "addr:housenumber":"58481",
    "addr:postcode":"97051",
    "addr:street":"Old Portland Rd",
    "iso:country":"US",
    "sg:address":"58481 Old Portland Rd",
    "sg:city":"St Helens",
    "sg:classifiers":[
        {
            "category":"Home & Garden",
            "subcategory":"Household Appliances",
            "type":"Retail Goods"
        },
        {
            "category":"Retail",
            "subcategory":"Repair Shop",
            "type":"Services"
        }
    ],
    "sg:phone":"+1 503 397 5510",
    "sg:postcode":"97051",
    "sg:province":"OR",
    "sg:tags":[
        "used",
        "merchandise"
    ],
    "wof:name":"Stan's Refrigeration & Appl",
    "wof:placetype":"venue"
},
  "geometry": {"coordinates":[-122.820718,45.846246],"type":"Point"}
}