{
  "type": "Feature",
  "properties": {
    "iso:country":"US",
    "sg:address":"4120 SE International Way",
    "sg:city":"Portland",
    "sg:classifiers":[
        {
            "category":"Professional",
            "subcategory":"Lawyer & Legal Services",
            "type":"Services"
        }
    ],
    "sg:phone":"+1 503 654 1388",
    "sg:postcode":"97222",
    "sg:province":"OR",
    "sg:tags":[
        "attorney"
    ],
    "wof:name":"Jodie Polich Law Office",
    "wof:placetype":"venue"
},
  "geometry": {"coordinates":[-122.618745,45.439095],"type":"Point"}
}