{
  "type": "Feature",
  "properties": {
    "iso:country":"US",
    "sg:address":"3190 NW 185th Ave",
    "sg:city":"Portland",
    "sg:classifiers":[
        {
            "category":"Restaurant",
            "type":"Food & Drink"
        }
    ],
    "sg:phone":"+1 503 292 2222",
    "sg:postcode":"97229",
    "sg:province":"OR",
    "sg:tags":[
        "pizza"
    ],
    "wof:name":"Pizza Hut",
    "wof:placetype":"venue"
},
  "geometry": {"coordinates":[-122.865791,45.542753],"type":"Point"}
}