{
  "type": "Feature",
  "properties": {
    "iso:country":"US",
    "sg:address":"4720 NE 135th Ave",
    "sg:city":"Portland",
    "sg:classifiers":[
        {
            "category":"Manufacturing",
            "subcategory":"Tools & Machinery",
            "type":"Manufacturing & Wholesale Goods"
        }
    ],
    "sg:phone":"+1 503 253 9072",
    "sg:postcode":"97230",
    "sg:province":"OR",
    "sg:tags":[
        "shop",
        "die"
    ],
    "wof:name":"M K Tooling Inc",
    "wof:placetype":"venue"
},
  "geometry": {"coordinates":[-122.523779,45.55572],"type":"Point"}
}