{
  "type": "Feature",
  "properties": {
    "iso:country":"US",
    "sg:address":"31070 SW Riverlane Rd",
    "sg:city":"Oregon City",
    "sg:classifiers":[
        {
            "category":"Shopping",
            "subcategory":"Stationery & Office Supplies",
            "type":"Retail Goods"
        }
    ],
    "sg:phone":"+1 503 656 7015",
    "sg:postcode":"97068",
    "sg:province":"OR",
    "wof:name":"Fernlund Paper Station Inc",
    "wof:placetype":"venue"
},
  "geometry": {"coordinates":[-122.67907,45.295654],"type":"Point"}
}