{
  "type": "Feature",
  "properties": {
    "iso:country":"US",
    "sg:address":"9800 SE Mcbrod Ave",
    "sg:city":"Portland",
    "sg:classifiers":[
        {
            "category":"Health Services",
            "subcategory":"Hospital",
            "type":"Services"
        }
    ],
    "sg:phone":"+1 503 659 8892",
    "sg:postcode":"97222",
    "sg:province":"OR",
    "sg:tags":[
        "ambulance"
    ],
    "wof:name":"American Medical Response, Inc.",
    "wof:placetype":"venue"
},
  "geometry": {"coordinates":[-122.64455,45.451783],"type":"Point"}
}