{
  "type": "Feature",
  "properties": {
    "iso:country":"US",
    "sg:address":"3300 NW 185th Ave",
    "sg:city":"Portland",
    "sg:classifiers":[
        {
            "category":"Professional",
            "subcategory":"Management & Consulting",
            "type":"Services"
        }
    ],
    "sg:phone":"+1 503 740 1749",
    "sg:postcode":"97229",
    "sg:province":"OR",
    "sg:tags":[
        "contracting",
        "training"
    ],
    "wof:name":"Icct Corp",
    "wof:placetype":"venue"
},
  "geometry": {"coordinates":[-122.867457,45.544943],"type":"Point"}
}