{
  "type": "Feature",
  "properties": {
    "iso:country":"US",
    "sg:address":"3300 Memorial Dr",
    "sg:city":"Klamath Falls",
    "sg:classifiers":[
        {
            "category":"Wholesale",
            "subcategory":"Construction Materials",
            "type":"Manufacturing & Wholesale Goods"
        }
    ],
    "sg:phone":"+1 541 884 3611",
    "sg:postcode":"97601",
    "sg:province":"OR",
    "sg:tags":[
        "lumber"
    ],
    "wof:name":"J & P Wholesale",
    "wof:placetype":"venue"
},
  "geometry": {"coordinates":[-121.789502,42.18605],"type":"Point"}
}