{
  "type": "Feature",
  "properties": {
    "iso:country":"US",
    "sg:address":"612 NE 24th Ave",
    "sg:city":"Hillsboro",
    "sg:classifiers":[
        {
            "category":"Professional",
            "type":"Services"
        }
    ],
    "sg:phone":"+1 503 846 9546",
    "sg:postcode":"97124",
    "sg:province":"OR",
    "sg:tags":[
        "establishment"
    ],
    "wof:name":"Grant Park Oxford House",
    "wof:placetype":"venue"
},
  "geometry": {"coordinates":[-122.95851500000001,45.528578],"type":"Point"}
}