{
  "type": "Feature",
  "properties": {
    "iso:country":"US",
    "sg:address":"3332 Lancaster Dr NE",
    "sg:city":"Salem",
    "sg:classifiers":[
        {
            "category":"Shopping",
            "subcategory":"Discount & Variety Stores",
            "type":"Retail Goods"
        }
    ],
    "sg:phone":"+1 503 588 4494",
    "sg:postcode":"97305",
    "sg:province":"OR",
    "wof:name":"Santiam Drug Inc",
    "wof:placetype":"venue"
},
  "geometry": {"coordinates":[-122.9834,44.968432],"type":"Point"}
}