{
  "type": "Feature",
  "properties": {
    "iso:country":"US",
    "sg:address":"2525 SW Beaverton Hillsdale Hwy",
    "sg:city":"Portland",
    "sg:classifiers":[
        {
            "category":"Health Services",
            "subcategory":"Health Practitioner",
            "type":"Services"
        }
    ],
    "sg:phone":"+1 503 740 3999",
    "sg:postcode":"97239",
    "sg:province":"OR",
    "sg:tags":[
        "control",
        "weight"
    ],
    "wof:name":"Fitmeals",
    "wof:placetype":"venue"
},
  "geometry": {"coordinates":[-122.702574,45.480045],"type":"Point"}
}