{
  "type": "Feature",
  "properties": {
    "iso:country":"US",
    "sg:address":"304 Trail St",
    "sg:city":"Gaston",
    "sg:classifiers":[
        {
            "category":"Manufacturing",
            "subcategory":"Buildings",
            "type":"Manufacturing & Wholesale Goods"
        },
        {
            "category":"Building & Trades",
            "subcategory":"Construction",
            "type":"Services"
        }
    ],
    "sg:phone":"+1 503 985 7203",
    "sg:postcode":"97119",
    "sg:province":"OR",
    "sg:tags":[
        "home",
        "builder",
        "contractor"
    ],
    "wof:name":"Sanow Step",
    "wof:placetype":"venue"
},
  "geometry": {"coordinates":[-123.146089,45.435932],"type":"Point"}
}