{
  "type": "Feature",
  "properties": {
    "addr:full":"7907 SE 46th Ave Portland OR 97206",
    "addr:housenumber":"7907",
    "addr:postcode":"97206",
    "addr:street":"Se 46Th Ave",
    "iso:country":"US",
    "sg:address":"7907 SE 46th Ave",
    "sg:city":"Portland",
    "sg:classifiers":[
        {
            "category":"Real Estate",
            "subcategory":"Real Estate Operator",
            "type":"Services"
        }
    ],
    "sg:phone":"+1 503 771 7225",
    "sg:postcode":"97206",
    "sg:province":"OR",
    "sg:tags":[
        "property",
        "lessor"
    ],
    "wof:name":"Kenneth C Snow & Frances",
    "wof:placetype":"venue"
},
  "geometry": {"coordinates":[-122.615291,45.465565],"type":"Point"}
}