{
  "type": "Feature",
  "properties": {
    "iso:country":"US",
    "sg:address":"3313 SE 148th Ave",
    "sg:city":"Portland",
    "sg:classifiers":[
        {
            "category":"Social Services",
            "subcategory":"Child Care",
            "type":"Services"
        }
    ],
    "sg:phone":"+1 503 762 3223",
    "sg:postcode":"97236",
    "sg:province":"OR",
    "sg:tags":[
        "day"
    ],
    "wof:name":"Samon Indepedent Seven Day Ad",
    "wof:placetype":"venue"
},
  "geometry": {"coordinates":[-122.510524,45.500372],"type":"Point"}
}