{
  "type": "Feature",
  "properties": {
    "addr:full":"14676 SE 82nd Dr Clackamas OR 97015",
    "addr:housenumber":"14676",
    "addr:postcode":"97015",
    "addr:street":"Se 82Nd Dr",
    "iso:country":"US",
    "sg:address":"14676 SE 82nd Dr",
    "sg:city":"Clackamas",
    "sg:classifiers":[
        {
            "category":"Shopping",
            "subcategory":"Clothing, Apparel, & Fashions",
            "type":"Retail Goods"
        }
    ],
    "sg:phone":"+1 503 657 5694",
    "sg:postcode":"97015",
    "sg:province":"OR",
    "sg:tags":[
        "uniforms-accessories",
        "uniform"
    ],
    "sg:website":"http://www.ragmanamerica.com",
    "wof:name":"Rag Man Inc",
    "wof:placetype":"venue"
},
  "geometry": {"coordinates":[-122.57022000000001,45.416462],"type":"Point"}
}