{
  "type": "Feature",
  "properties": {
    "iso:country":"US",
    "sg:address":"105 SE Jones St",
    "sg:city":"Madras",
    "sg:classifiers":[
        {
            "category":"Manufacturing",
            "subcategory":"Apparel",
            "type":"Manufacturing & Wholesale Goods"
        }
    ],
    "sg:phone":"+1 541 475 7650",
    "sg:postcode":"97741",
    "sg:province":"OR",
    "sg:tags":[
        "textile",
        "bag",
        "business",
        "mfg"
    ],
    "wof:name":"Stewart Of Oregon",
    "wof:placetype":"venue"
},
  "geometry": {"coordinates":[-121.12499099999999,44.616529],"type":"Point"}
}