{
  "type": "Feature",
  "properties": {
    "iso:country":"US",
    "sg:address":"1620 SW Taylor St",
    "sg:city":"Portland",
    "sg:classifiers":[
        {
            "category":"Banks & Credit Unions",
            "subcategory":"Bank",
            "type":"Services"
        }
    ],
    "sg:phone":"+1 503 243 2674",
    "sg:postcode":"97205",
    "sg:province":"OR",
    "sg:tags":[
        "mortgage"
    ],
    "wof:name":"Rcbc Mortgage",
    "wof:placetype":"venue"
},
  "geometry": {"coordinates":[-122.689741,45.520435],"type":"Point"}
}