{
  "type": "Feature",
  "properties": {
    "addr:full":"339 S Township Rd Canby OR 97013",
    "addr:housenumber":"339",
    "addr:postcode":"97013",
    "addr:street":"S Township Rd",
    "iso:country":"US",
    "sg:address":"339 S Township Rd",
    "sg:city":"Canby",
    "sg:classifiers":[
        {
            "category":"Organizations",
            "subcategory":"Religious Organization",
            "type":"Services"
        }
    ],
    "sg:phone":"+1 503 266 9112",
    "sg:postcode":"97013",
    "sg:province":"OR",
    "sg:tags":[
        "church"
    ],
    "wof:name":"Canby Evangelical Church",
    "wof:placetype":"venue"
},
  "geometry": {"coordinates":[-122.686824,45.259353],"type":"Point"}
}