{
  "type": "Feature",
  "properties": {
    "iso:country":"US",
    "sg:address":"3282 Silverton Rd NE",
    "sg:city":"Salem",
    "sg:classifiers":[
        {
            "category":"Autos & Motor Vehicles",
            "subcategory":"Auto Supplies",
            "type":"Retail Goods"
        },
        {
            "category":"Autos & Motor Vehicles",
            "subcategory":"Recreational Vehicle Sales",
            "type":"Retail Goods"
        }
    ],
    "sg:phone":"+1 503 585 7713",
    "sg:postcode":"97301",
    "sg:province":"OR",
    "sg:tags":[
        "home",
        "camper",
        "trailer",
        "utility"
    ],
    "sg:website":"http://www.wagersrv.com",
    "wof:name":"Wagers Trailer Sales",
    "wof:placetype":"venue"
},
  "geometry": {"coordinates":[-122.99353000000001,44.967745],"type":"Point"}
}