{
  "type": "Feature",
  "properties": {
    "iso:country":"US",
    "sg:address":"160 Greenvale Dr",
    "sg:city":"Springfield",
    "sg:classifiers":[
        {
            "category":"Building & Trades",
            "subcategory":"Construction",
            "type":"Services"
        }
    ],
    "sg:phone":"+1 541 746 7101",
    "sg:postcode":"97477",
    "sg:province":"OR",
    "sg:tags":[
        "work",
        "carpentry"
    ],
    "wof:name":"Wilcoxson Brothers Inc",
    "wof:placetype":"venue"
},
  "geometry": {"coordinates":[-123.025494,44.070086],"type":"Point"}
}