{
  "type": "Feature",
  "properties": {
    "iso:country":"US",
    "sg:address":"4901 NE Glisan Street",
    "sg:city":"Portland",
    "sg:classifiers":[
        {
            "category":"Health Services",
            "subcategory":"Dentist",
            "type":"Services"
        }
    ],
    "sg:phone":"+1 503 231 1644",
    "sg:postcode":"97213",
    "sg:province":"OR",
    "wof:name":"Jeffery C Spathas, DMD",
    "wof:placetype":"venue"
},
  "geometry": {"coordinates":[-122.61275000000001,45.526531],"type":"Point"}
}