{
  "type": "Feature",
  "properties": {
    "addr:full":"600 16th St NE Salem OR 97301",
    "addr:housenumber":"600",
    "addr:postcode":"97301",
    "addr:street":"16Th St Ne",
    "iso:country":"US",
    "sg:address":"600 16th St NE",
    "sg:city":"Salem",
    "sg:classifiers":[
        {
            "category":"Organizations",
            "subcategory":"Religious Organization",
            "type":"Services"
        }
    ],
    "sg:phone":"+1 503 362 4321",
    "sg:postcode":"97301",
    "sg:province":"OR",
    "wof:name":"Harvest Time Pntecostal Church",
    "wof:placetype":"venue"
},
  "geometry": {"coordinates":[-123.01808,44.942479],"type":"Point"}
}