{
  "type": "Feature",
  "properties": {
    "iso:country":"US",
    "sg:address":"9015 SW 19th Ave",
    "sg:city":"Portland",
    "sg:classifiers":[
        {
            "category":"Health Services",
            "subcategory":"Nursing And Care Facility",
            "type":"Services"
        },
        {
            "category":"Social Services",
            "subcategory":"Retirement Home",
            "type":"Services"
        }
    ],
    "sg:phone":"+1 503 246 3973",
    "sg:postcode":"97219",
    "sg:province":"OR",
    "sg:tags":[
        "personal",
        "convalescent"
    ],
    "wof:name":"Zr Pacific Care",
    "wof:placetype":"venue"
},
  "geometry": {"coordinates":[-122.697318,45.46038],"type":"Point"}
}