{
  "type": "Feature",
  "properties": {
    "iso:country":"US",
    "sg:address":"7715 NE 21st Ave",
    "sg:city":"Portland",
    "sg:classifiers":[
        {
            "category":"Banks & Credit Unions",
            "subcategory":"Investment Brokerage",
            "type":"Services"
        },
        {
            "category":"Professional",
            "subcategory":"Business Services",
            "type":"Services"
        }
    ],
    "sg:phone":"+1 503 232 1046",
    "sg:postcode":"97211",
    "sg:province":"OR",
    "sg:tags":[
        "broker",
        "commodity"
    ],
    "wof:name":"S A S",
    "wof:placetype":"venue"
},
  "geometry": {"coordinates":[-122.64390299999999,45.578962],"type":"Point"}
}