{
  "type": "Feature",
  "properties": {
    "addr:full":"379 E Main St Hillsboro OR 97123",
    "addr:housenumber":"379",
    "addr:postcode":"97123",
    "addr:street":"E Main St",
    "iso:country":"US",
    "sg:address":"379 E Main St",
    "sg:city":"Hillsboro",
    "sg:classifiers":[
        {
            "category":"Restaurant",
            "type":"Food & Drink"
        }
    ],
    "sg:phone":"+1 503 693 0890",
    "sg:postcode":"97123",
    "sg:province":"OR",
    "wof:name":"Mexican Deli",
    "wof:placetype":"venue"
},
  "geometry": {"coordinates":[-122.985466,45.522689],"type":"Point"}
}