{
  "type": "Feature",
  "properties": {
    "addr:full":"21234 Gift Rd Bend OR 97701",
    "addr:postcode":"21234;97701",
    "addr:street":"Gift Rd",
    "iso:country":"US",
    "sg:address":"21234 Gift Rd",
    "sg:city":"Bend",
    "sg:classifiers":[
        {
            "category":"Professional",
            "type":"Services"
        }
    ],
    "sg:phone":"+1 541 330 6149",
    "sg:postcode":"97701",
    "sg:province":"OR",
    "wof:name":"Mind Body & Soul",
    "wof:placetype":"venue"
},
  "geometry": {"coordinates":[-121.261714,44.183537],"type":"Point"}
}