{
  "type": "Feature",
  "properties": {
    "iso:country":"US",
    "sg:address":"601 NE Greenwood Ave",
    "sg:city":"Bend",
    "sg:classifiers":[
        {
            "category":"Restaurant",
            "type":"Food & Drink"
        }
    ],
    "sg:phone":"+1 541 383 1402",
    "sg:postcode":"97701",
    "sg:province":"OR",
    "sg:tags":[
        "eating"
    ],
    "wof:name":"Los Jalapenos",
    "wof:placetype":"venue"
},
  "geometry": {"coordinates":[-121.297214,44.059958],"type":"Point"}
}