{
  "type": "Feature",
  "properties": {
    "iso:country":"US",
    "sg:address":"17280 Timothy Way",
    "sg:city":"Portland",
    "sg:classifiers":[
        {
            "category":"Building & Trades",
            "subcategory":"Construction",
            "type":"Services"
        }
    ],
    "sg:phone":"+1 503 557 7857",
    "sg:postcode":"97201",
    "sg:province":"OR",
    "sg:tags":[
        "contractor"
    ],
    "wof:name":"Prime Properties Inc",
    "wof:placetype":"venue"
},
  "geometry": {"coordinates":[-122.580849,45.39699],"type":"Point"}
}