{
  "type": "Feature",
  "properties": {
    "iso:country":"US",
    "sg:address":"12700 NW Barnes Rd",
    "sg:city":"Portland",
    "sg:classifiers":[
        {
            "category":"Wholesale",
            "subcategory":"Hardware",
            "type":"Manufacturing & Wholesale Goods"
        },
        {
            "category":"Building & Trades",
            "subcategory":"Equipment Rental",
            "type":"Services"
        }
    ],
    "sg:phone":"+1 503 644 9101",
    "sg:postcode":"97229",
    "sg:province":"OR",
    "sg:tags":[
        "hardware-builders",
        "leasing",
        "yard",
        "store"
    ],
    "wof:name":"Cedar Mill Lumber",
    "wof:placetype":"venue"
},
  "geometry": {"coordinates":[-122.8066,45.523368],"type":"Point"}
}