{
  "type": "Feature",
  "properties": {
    "iso:country":"US",
    "sg:address":"1860 Eola Dr NW",
    "sg:city":"Salem",
    "sg:classifiers":[
        {
            "category":"Building & Trades",
            "subcategory":"Landscaping Services",
            "type":"Services"
        }
    ],
    "sg:phone":"+1 503 930 0336",
    "sg:postcode":"97304",
    "sg:province":"OR",
    "sg:tags":[
        "tree"
    ],
    "wof:name":"Salem Tree Care Inc",
    "wof:placetype":"venue"
},
  "geometry": {"coordinates":[-123.06464099999999,44.937331],"type":"Point"}
}