{
  "type": "Feature",
  "properties": {
    "addr:full":"200 NW 53rd St Corvallis OR 97330",
    "addr:housenumber":"200",
    "addr:postcode":"97330",
    "addr:street":"Nw 53Rd St",
    "iso:country":"US",
    "sg:address":"200 NW 53rd St",
    "sg:city":"Corvallis",
    "sg:classifiers":[
        {
            "category":"Building & Trades",
            "subcategory":"Construction",
            "type":"Services"
        }
    ],
    "sg:phone":"+1 541 760 7553",
    "sg:postcode":"97330",
    "sg:province":"OR",
    "sg:tags":[
        "builder",
        "repairer",
        "chimney"
    ],
    "wof:name":"Historical Chimney",
    "wof:placetype":"venue"
},
  "geometry": {"coordinates":[-123.312118,44.564749],"type":"Point"}
}