{
  "type": "Feature",
  "properties": {
    "iso:country":"US",
    "sg:address":"7000 NE Airport Way",
    "sg:city":"Portland",
    "sg:classifiers":[
        {
            "category":"Shopping",
            "subcategory":"Stationery & Office Supplies",
            "type":"Retail Goods"
        }
    ],
    "sg:phone":"+1 503 335 3339",
    "sg:postcode":"97218",
    "sg:province":"OR",
    "sg:tags":[
        "stationer"
    ],
    "wof:name":"Paper Station",
    "wof:placetype":"venue"
},
  "geometry": {"coordinates":[-122.58622099999999,45.586528],"type":"Point"}
}