{
  "type": "Feature",
  "properties": {
    "addr:full":"19221 SW Martinazzi Ave Tualatin OR 97062",
    "addr:housenumber":"19221",
    "addr:postcode":"97062",
    "addr:street":"Sw Martinazzi Ave",
    "iso:country":"US",
    "sg:address":"19221 SW Martinazzi Ave",
    "sg:city":"Tualatin",
    "sg:phone":"+1 503 692 9112",
    "sg:postcode":"97062",
    "sg:province":"OR",
    "sg:website":"http://www.schlotzskys.com",
    "wof:name":"Schlotzsky's",
    "wof:placetype":"venue"
},
  "geometry": {"coordinates":[-122.759038,45.380292],"type":"Point"}
}