{
  "type": "Feature",
  "properties": {
    "addr:full":"707 NE Fremont St Portland OR 97212",
    "addr:housenumber":"707",
    "addr:postcode":"97212",
    "addr:street":"Ne Fremont St",
    "iso:country":"US",
    "sg:address":"707 NE Fremont St",
    "sg:city":"Portland",
    "sg:classifiers":[
        {
            "category":"Home & Garden",
            "subcategory":"Home Furnishings",
            "type":"Retail Goods"
        },
        {
            "category":"Shopping",
            "subcategory":"Thrift Store",
            "type":"Retail Goods"
        },
        {
            "category":"Shopping",
            "subcategory":"Used Merchandise",
            "type":"Retail Goods"
        }
    ],
    "sg:phone":"+1 503 517 3786",
    "sg:postcode":"97212",
    "sg:province":"OR",
    "sg:tags":[
        "vintage",
        "decor",
        "consignment"
    ],
    "sg:website":"www.portlandrerun.com",
    "wof:name":"Rerun",
    "wof:placetype":"venue"
},
  "geometry": {"coordinates":[-122.658455,45.548271],"type":"Point"}
}