{
  "type": "Feature",
  "properties": {
    "iso:country":"US",
    "sg:address":"820 Crater Lake Ave Ste 209",
    "sg:city":"Medford",
    "sg:classifiers":[
        {
            "category":"Utilities",
            "type":"Services"
        }
    ],
    "sg:phone":"+1 541 858 2171",
    "sg:postcode":"97504",
    "sg:province":"OR",
    "sg:tags":[
        "provider",
        "internet"
    ],
    "wof:name":"Grr Technology Inc",
    "wof:placetype":"venue"
},
  "geometry": {"coordinates":[-122.860759,42.337317],"type":"Point"}
}