{
  "type": "Feature",
  "properties": {
    "addr:full":"1960 NW 113th Ave Portland OR 97229",
    "addr:housenumber":"1960",
    "addr:postcode":"97229",
    "addr:street":"Nw 113Th Ave",
    "iso:country":"US",
    "sg:address":"1960 NW 113th Ave",
    "sg:city":"Portland",
    "sg:classifiers":[
        {
            "category":"Home & Garden",
            "subcategory":"Garden Supply",
            "type":"Retail Goods"
        }
    ],
    "sg:phone":"+1 503 516 2395",
    "sg:postcode":"97229",
    "sg:province":"OR",
    "sg:tags":[
        "nursery",
        "gardening"
    ],
    "sg:website":"www.cedarmillbamboo.com",
    "wof:name":"Cedar Mill Bamboo",
    "wof:placetype":"venue"
},
  "geometry": {"coordinates":[-122.79224499999999,45.533753],"type":"Point"}
}