{
  "type": "Feature",
  "properties": {
    "iso:country":"US",
    "sg:address":"11740 SE Ash St",
    "sg:city":"Portland",
    "sg:classifiers":[
        {
            "category":"Shopping",
            "subcategory":"Catalog Store",
            "type":"Retail Goods"
        },
        {
            "category":"Shopping",
            "subcategory":"Gifts & Souvenirs",
            "type":"Retail Goods"
        }
    ],
    "sg:phone":"+1 503 255 1534",
    "sg:postcode":"97216",
    "sg:province":"OR",
    "sg:tags":[
        "mail",
        "order"
    ],
    "wof:name":"Robert's Gift Outlet",
    "wof:placetype":"venue"
},
  "geometry": {"coordinates":[-122.540728,45.521004],"type":"Point"}
}