{
  "type": "Feature",
  "properties": {
    "iso:country":"US",
    "sg:address":"32341 Hwy 34",
    "sg:city":"Tangent",
    "sg:classifiers":[
        {
            "category":"Freight",
            "type":"Transportation"
        }
    ],
    "sg:phone":"+1 541 928 1131",
    "sg:postcode":"97389",
    "sg:province":"OR",
    "sg:tags":[
        "trucking"
    ],
    "wof:name":"Fruitt Trucking",
    "wof:placetype":"venue"
},
  "geometry": {"coordinates":[-123.10128,44.559228],"type":"Point"}
}