{
  "type": "Feature",
  "properties": {
    "addr:full":"117 Hansen Ln Eugene OR 97404",
    "addr:housenumber":"117",
    "addr:postcode":"97404",
    "addr:street":"Hansen Ln",
    "iso:country":"US",
    "sg:address":"117 Hansen Ln",
    "sg:city":"Eugene",
    "sg:classifiers":[
        {
            "category":"Personal",
            "type":"Services"
        }
    ],
    "sg:phone":"+1 541 689 6516",
    "sg:postcode":"97404",
    "sg:province":"OR",
    "wof:name":"Thai Goods Trading Co",
    "wof:placetype":"venue"
},
  "geometry": {"coordinates":[-123.118143,44.06872],"type":"Point"}
}