{
  "type": "Feature",
  "properties": {
    "iso:country":"US",
    "sg:address":"325 Galice Rd",
    "sg:city":"Merlin",
    "sg:classifiers":[
        {
            "category":"Autos & Motor Vehicles",
            "subcategory":"Boat Sales",
            "type":"Retail Goods"
        }
    ],
    "sg:phone":"+1 541 479 9554",
    "sg:postcode":"97532",
    "sg:province":"OR",
    "sg:tags":[
        "rafts"
    ],
    "wof:name":"Rogue Wilderness Inc",
    "wof:placetype":"venue"
},
  "geometry": {"coordinates":[-123.42417,42.517133],"type":"Point"}
}