{
  "type": "Feature",
  "properties": {
    "addr:full":"4384 Commerce St Eugene OR 97402",
    "addr:housenumber":"4384",
    "addr:postcode":"97402",
    "addr:street":"Commerce St",
    "iso:country":"US",
    "sg:address":"4384 Commerce St",
    "sg:city":"Eugene",
    "sg:classifiers":[
        {
            "category":"Restaurant",
            "type":"Food & Drink"
        }
    ],
    "sg:menulink":"http://www.allmenus.com/or/eugene-springfield/180577-jack-in-the-box/menu/",
    "sg:phone":"+1 541 343 4114",
    "sg:postcode":"97402",
    "sg:province":"OR",
    "sg:tags":[
        "burger",
        "american"
    ],
    "wof:name":"Jack in the Box",
    "wof:placetype":"venue"
},
  "geometry": {"coordinates":[-123.16887699999999,44.048333],"type":"Point"}
}