{
  "type": "Feature",
  "properties": {
    "iso:country":"US",
    "sg:address":"4708 SW Scholls Ferry Road",
    "sg:city":"Portland",
    "sg:classifiers":[
        {
            "category":"Retail",
            "subcategory":"Laundry & Dry Cleaning",
            "type":"Services"
        }
    ],
    "sg:phone":"+1 503 292 4251",
    "sg:postcode":"97225",
    "sg:province":"OR",
    "sg:tags":[
        "cleaner",
        "drapery",
        "curtain"
    ],
    "wof:name":"Raleigh Hills Cleaners II",
    "wof:placetype":"venue"
},
  "geometry": {"coordinates":[-122.750264,45.48569],"type":"Point"}
}