{
  "type": "Feature",
  "properties": {
    "iso:country":"US",
    "sg:address":"30410 Lindsay Dr",
    "sg:city":"Shedd",
    "sg:classifiers":[
        {
            "category":"Farming",
            "subcategory":"Farm & Veterinary Services",
            "type":"Manufacturing & Wholesale Goods"
        }
    ],
    "sg:phone":"+1 541 491 3986",
    "sg:postcode":"97377",
    "sg:province":"OR",
    "sg:tags":[
        "preparation",
        "crop",
        "for",
        "market"
    ],
    "wof:name":"Wayne A Spletstoser",
    "wof:placetype":"venue"
},
  "geometry": {"coordinates":[-123.17005899999999,44.497763],"type":"Point"}
}