{
  "type": "Feature",
  "properties": {
    "iso:country":"US",
    "sg:address":"35887 Knox Butte Rd E",
    "sg:city":"Albany",
    "sg:classifiers":[
        {
            "category":"Building & Trades",
            "subcategory":"Construction",
            "type":"Services"
        }
    ],
    "sg:phone":"+1 541 926 1282",
    "sg:postcode":"97322",
    "sg:province":"OR",
    "sg:tags":[
        "concrete",
        "contractor"
    ],
    "wof:name":"Pro Construction & Handyman",
    "wof:placetype":"venue"
},
  "geometry": {"coordinates":[-122.953185,44.630648],"type":"Point"}
}