{
  "type": "Feature",
  "properties": {
    "addr:full":"10643 NE Siskiyou St Portland OR 97220",
    "addr:housenumber":"10643",
    "addr:postcode":"97220",
    "addr:street":"Ne Siskiyou St",
    "iso:country":"US",
    "sg:address":"10643 NE Siskiyou St",
    "sg:city":"Portland",
    "sg:classifiers":[
        {
            "category":"Building & Trades",
            "subcategory":"Electrical",
            "type":"Services"
        }
    ],
    "sg:phone":"+1 503 408 0300",
    "sg:postcode":"97220",
    "sg:province":"OR",
    "sg:tags":[
        "electrical",
        "contractor"
    ],
    "wof:name":"Advocate Sound",
    "wof:placetype":"venue"
},
  "geometry": {"coordinates":[-122.55267600000001,45.544543],"type":"Point"}
}