{
  "type": "Feature",
  "properties": {
    "iso:country":"US",
    "sg:address":"2351 SW Borland Rd",
    "sg:city":"West Linn",
    "sg:classifiers":[
        {
            "category":"Home & Garden",
            "subcategory":"Building Materials",
            "type":"Retail Goods"
        }
    ],
    "sg:phone":"+1 503 638 7575",
    "sg:postcode":"97068",
    "sg:province":"OR",
    "sg:tags":[
        "lumber",
        "supply"
    ],
    "sg:website":"www.parr.com",
    "wof:name":"Parr Lumber Co",
    "wof:placetype":"venue"
},
  "geometry": {"coordinates":[-122.701169,45.374079],"type":"Point"}
}