{
  "type": "Feature",
  "properties": {
    "iso:country":"US",
    "sg:address":"2055 Exchange St Ste 270",
    "sg:city":"Astoria",
    "sg:classifiers":[
        {
            "category":"Health Services",
            "subcategory":"Doctor",
            "type":"Services"
        }
    ],
    "sg:phone":"+1 503 325 9597",
    "sg:postcode":"97103",
    "sg:province":"OR",
    "sg:tags":[
        "physician",
        "surgeon",
        "surgeons",
        "surgery-general"
    ],
    "wof:name":"Robert Wayne Md",
    "wof:placetype":"venue"
},
  "geometry": {"coordinates":[-123.81971799999999,46.188455],"type":"Point"}
}