{
  "type": "Feature",
  "properties": {
    "addr:full":"403 Main St Klamath Falls OR 97601",
    "addr:housenumber":"403",
    "addr:postcode":"97601",
    "addr:street":"Main St",
    "iso:country":"US",
    "sg:address":"403 Main St",
    "sg:city":"Klamath Falls",
    "sg:classifiers":[
        {
            "category":"Real Estate",
            "subcategory":"Real Estate Agent",
            "type":"Services"
        }
    ],
    "sg:phone":"+1 541 884 1717",
    "sg:postcode":"97601",
    "sg:province":"OR",
    "sg:website":"www.realtor.com",
    "wof:name":"Fischer Nicholson Realty LLC",
    "wof:placetype":"venue"
},
  "geometry": {"coordinates":[-121.783343,42.224081],"type":"Point"}
}