{
  "type": "Feature",
  "properties": {
    "iso:country":"US",
    "sg:address":"2101 Bailey Hill Rd K",
    "sg:city":"Eugene",
    "sg:classifiers":[
        {
            "category":"Insurance",
            "subcategory":"Insurance Agent",
            "type":"Services"
        },
        {
            "category":"Insurance",
            "subcategory":"Hazard Insurance",
            "type":"Services"
        },
        {
            "category":"Insurance",
            "subcategory":"Title Insurance",
            "type":"Services"
        },
        {
            "category":"Insurance",
            "subcategory":"Life Insurance",
            "type":"Services"
        }
    ],
    "sg:phone":"+1 541 687 0884",
    "sg:postcode":"97405",
    "sg:province":"OR",
    "sg:tags":[
        "auto",
        "commercial",
        "business",
        "homeowner"
    ],
    "sg:website":"http://www.farmersagent.com/glumsden/",
    "wof:name":"Greg Lumsden - Farmers Insurance",
    "wof:placetype":"venue"
},
  "geometry": {"coordinates":[-123.15239699999999,44.035919],"type":"Point"}
}