{
  "type": "Feature",
  "properties": {
    "iso:country":"US",
    "sg:address":"3423 SE Belmont St",
    "sg:city":"Portland",
    "sg:classifiers":[
        {
            "category":"Shopping",
            "subcategory":"Clothing, Apparel, & Fashions",
            "type":"Retail Goods"
        }
    ],
    "sg:phone":"+1 503 230 9072",
    "sg:postcode":"97214",
    "sg:province":"OR",
    "sg:tags":[
        "designer"
    ],
    "wof:name":"Cooler Than You",
    "wof:placetype":"venue"
},
  "geometry": {"coordinates":[-122.62840799999999,45.516524],"type":"Point"}
}