{
  "type": "Feature",
  "properties": {
    "addr:full":"1520 Elm St Forest Grove OR 97116",
    "addr:housenumber":"1520",
    "addr:postcode":"97116",
    "addr:street":"Elm St",
    "iso:country":"US",
    "sg:address":"1520 Elm St",
    "sg:city":"Forest Grove",
    "sg:classifiers":[
        {
            "category":"Building & Trades",
            "subcategory":"Construction",
            "type":"Services"
        }
    ],
    "sg:phone":"+1 503 357 5891",
    "sg:postcode":"97116",
    "sg:province":"OR",
    "sg:tags":[
        "contractor",
        "masonry",
        "industrial",
        "general"
    ],
    "wof:name":"Boldon Construction Co Inc",
    "wof:placetype":"venue"
},
  "geometry": {"coordinates":[-123.10306199999999,45.513307],"type":"Point"}
}