{
  "type": "Feature",
  "properties": {
    "addr:full":"38434 Elkhorn Estates Rd Baker City OR 97814",
    "addr:housenumber":"38434",
    "addr:postcode":"97814",
    "addr:street":"Elkhorn Estates Rd",
    "iso:country":"US",
    "sg:address":"38434 Elkhorn Estates Rd",
    "sg:city":"Baker City",
    "sg:classifiers":[
        {
            "category":"Health Services",
            "subcategory":"Clinic",
            "type":"Services"
        }
    ],
    "sg:phone":"+1 541 894 0211",
    "sg:postcode":"97814",
    "sg:province":"OR",
    "sg:tags":[
        "home",
        "datum",
        "care"
    ],
    "wof:name":"Real People Organization",
    "wof:placetype":"venue"
},
  "geometry": {"coordinates":[-118.07555499999999,44.691411],"type":"Point"}
}