{
  "type": "Feature",
  "properties": {
    "iso:country":"US",
    "sg:address":"1015 NW Wade St",
    "sg:city":"Estacada",
    "sg:phone":"+1 503 630 3785",
    "sg:postcode":"97023",
    "sg:province":"OR",
    "sg:website":"http://www.uhaul.com/Locations/Rentals-near-Estacada-OR-97023/047637",
    "wof:name":"U-Haul Neighborhood Dealer - Currin Creek Rentals",
    "wof:placetype":"venue"
},
  "geometry": {"coordinates":[-122.33805599999999,45.298082],"type":"Point"}
}