{
  "type": "Feature",
  "properties": {
    "addr:full":"1412 W 7th Ave Eugene OR 97402",
    "addr:housenumber":"1412",
    "addr:postcode":"97402",
    "addr:street":"W 7Th Ave",
    "iso:country":"US",
    "sg:address":"1412 W 7th Ave",
    "sg:city":"Eugene",
    "sg:classifiers":[
        {
            "category":"Retail",
            "subcategory":"Photofinishing",
            "type":"Services"
        }
    ],
    "sg:phone":"+1 541 686 2183",
    "sg:postcode":"97402",
    "sg:province":"OR",
    "sg:tags":[
        "process",
        "print",
        "film"
    ],
    "wof:name":"Evergreen Film Service Inc",
    "wof:placetype":"venue"
},
  "geometry": {"coordinates":[-123.115183,44.052083],"type":"Point"}
}