{
  "type": "Feature",
  "properties": {
    "addr:full":"8560 SW Salish Ln Wilsonville OR 97070",
    "addr:housenumber":"8560",
    "addr:postcode":"97070",
    "addr:street":"Sw Salish Ln",
    "iso:country":"US",
    "sg:address":"8560 SW Salish Ln",
    "sg:city":"Wilsonville",
    "sg:classifiers":[
        {
            "category":"Wholesale",
            "subcategory":"Construction Materials",
            "type":"Manufacturing & Wholesale Goods"
        },
        {
            "category":"Manufacturing",
            "subcategory":"Metals",
            "type":"Manufacturing & Wholesale Goods"
        }
    ],
    "sg:phone":"+1 503 582 9078",
    "sg:postcode":"97070",
    "sg:province":"OR",
    "sg:tags":[
        "steel"
    ],
    "wof:name":"SMI Joist",
    "wof:placetype":"venue"
},
  "geometry": {"coordinates":[-122.765113,45.338188],"type":"Point"}
}