{
  "type": "Feature",
  "properties": {
    "addr:full":"13180 SW Butner Ct Beaverton OR 97005",
    "addr:housenumber":"13180",
    "addr:postcode":"97005",
    "addr:street":"Sw Butner Ct",
    "iso:country":"US",
    "sg:address":"13180 SW Butner Ct",
    "sg:city":"Beaverton",
    "sg:classifiers":[
        {
            "category":"Freight",
            "type":"Transportation"
        }
    ],
    "sg:phone":"+1 503 644 2708",
    "sg:postcode":"97005",
    "sg:province":"OR",
    "sg:tags":[
        "operator",
        "local",
        "trucking"
    ],
    "wof:name":"Brad Carter Trucking",
    "wof:placetype":"venue"
},
  "geometry": {"coordinates":[-122.811412,45.51472],"type":"Point"}
}