{
  "type": "Feature",
  "properties": {
    "iso:country":"US",
    "sg:address":"263 N Front St",
    "sg:city":"Woodburn",
    "sg:classifiers":[
        {
            "category":"Retail",
            "subcategory":"Laundry & Dry Cleaning",
            "type":"Services"
        }
    ],
    "sg:phone":"+1 503 981 4111",
    "sg:postcode":"97071",
    "sg:province":"OR",
    "sg:tags":[
        "cleaners"
    ],
    "wof:name":"Woodburn Cleaners",
    "wof:placetype":"venue"
},
  "geometry": {"coordinates":[-122.857022,45.142123],"type":"Point"}
}