{
  "type": "Feature",
  "properties": {
    "addr:full":"325 11th Ave SE Albany OR 97322",
    "addr:housenumber":"325",
    "addr:postcode":"97322",
    "addr:street":"11Th Ave Se",
    "iso:country":"US",
    "sg:address":"325 11th Ave SE",
    "sg:city":"Albany",
    "sg:classifiers":[
        {
            "category":"Home & Garden",
            "subcategory":"Building Materials",
            "type":"Retail Goods"
        }
    ],
    "sg:phone":"+1 541 928 6227",
    "sg:postcode":"97322",
    "sg:province":"OR",
    "sg:tags":[
        "glass",
        "window",
        "plate"
    ],
    "wof:name":"Albany Auto Glass",
    "wof:placetype":"venue"
},
  "geometry": {"coordinates":[-123.098232,44.629974],"type":"Point"}
}