{
  "type": "Feature",
  "properties": {
    "addr:full":"343 E Main St Hillsboro OR 97123",
    "addr:housenumber":"343",
    "addr:postcode":"97123",
    "addr:street":"E Main St",
    "iso:country":"US",
    "sg:address":"343 E Main St",
    "sg:city":"Hillsboro",
    "sg:classifiers":[
        {
            "category":"Travel",
            "subcategory":"Travel Agent",
            "type":"Entertainment"
        }
    ],
    "sg:phone":"+1 503 648 3179",
    "sg:postcode":"97123",
    "sg:province":"OR",
    "sg:tags":[
        "agency"
    ],
    "wof:name":"World Wide Adventures",
    "wof:placetype":"venue"
},
  "geometry": {"coordinates":[-122.98499700000001,45.522678],"type":"Point"}
}