{
  "type": "Feature",
  "properties": {
    "addr:full":"9774 Mount Angel Gervais Rd NE Gervais OR 97026",
    "addr:housenumber":"9774",
    "addr:postcode":"97026",
    "addr:street":"Gervais Rd Ne",
    "iso:country":"US",
    "sg:address":"9774 Mount Angel Gervais Rd NE",
    "sg:city":"Gervais",
    "sg:classifiers":[
        {
            "category":"Farming",
            "subcategory":"Nursery",
            "type":"Manufacturing & Wholesale Goods"
        }
    ],
    "sg:phone":"+1 503 982 3683",
    "sg:postcode":"97026",
    "sg:province":"OR",
    "sg:tags":[
        "ornamental"
    ],
    "wof:name":"Ezdokyia D CAM",
    "wof:placetype":"venue"
},
  "geometry": {"coordinates":[-122.861831,45.091154],"type":"Point"}
}