{
  "type": "Feature",
  "properties": {
    "iso:country":"US",
    "sg:address":"1706 SE 23rd Ave",
    "sg:city":"Portland",
    "sg:classifiers":[
        {
            "category":"Building & Trades",
            "subcategory":"Landscaping Services",
            "type":"Services"
        }
    ],
    "sg:phone":"+1 503 239 9909",
    "sg:postcode":"97214",
    "sg:province":"OR",
    "sg:tags":[
        "designer",
        "landscape"
    ],
    "wof:name":"Carolyn Gregg Landscape Design",
    "wof:placetype":"venue"
},
  "geometry": {"coordinates":[-122.642109,45.509748],"type":"Point"}
}