{
  "type": "Feature",
  "properties": {
    "addr:full":"16172 S Henrici Rd Oregon City OR 97045",
    "addr:housenumber":"16172",
    "addr:postcode":"97045",
    "addr:street":"S Henrici Rd",
    "iso:country":"US",
    "sg:address":"16172 S Henrici Rd",
    "sg:city":"Oregon City",
    "sg:classifiers":[
        {
            "category":"Building & Trades",
            "subcategory":"Cleaning & Sanitation",
            "type":"Services"
        }
    ],
    "sg:phone":"+1 503 632 8004",
    "sg:postcode":"97045",
    "sg:province":"OR",
    "sg:tags":[
        "maintenance"
    ],
    "wof:name":"A Cleaner Image",
    "wof:placetype":"venue"
},
  "geometry": {"coordinates":[-122.532506,45.309577],"type":"Point"}
}