{
  "type": "Feature",
  "properties": {
    "iso:country":"US",
    "sg:address":"17711 Weddle Rd SE",
    "sg:city":"Jefferson",
    "sg:classifiers":[
        {
            "category":"Food & Beverages",
            "subcategory":"Fruits & Vegetables",
            "type":"Retail Goods"
        }
    ],
    "sg:phone":"+1 541 327 2238",
    "sg:postcode":"97352",
    "sg:province":"OR",
    "wof:name":"Jason Laube Farms",
    "wof:placetype":"venue"
},
  "geometry": {"coordinates":[-123.01113700000001,44.699128],"type":"Point"}
}