{
  "type": "Feature",
  "properties": {
    "iso:country":"US",
    "sg:address":"2122 SE 57th Ave",
    "sg:city":"Portland",
    "sg:classifiers":[
        {
            "category":"Food & Beverages",
            "subcategory":"Fruits & Vegetables",
            "type":"Retail Goods"
        }
    ],
    "sg:phone":"+1 503 236 1203",
    "sg:postcode":"97215",
    "sg:province":"OR",
    "wof:name":"Produce Basket",
    "wof:placetype":"venue"
},
  "geometry": {"coordinates":[-122.604845,45.50689],"type":"Point"}
}