{
  "type": "Feature",
  "properties": {
    "iso:country":"US",
    "sg:address":"15798 SE 114th Ave",
    "sg:city":"Clackamas",
    "sg:classifiers":[
        {
            "category":"Wholesale",
            "subcategory":"Machinery & Supplies",
            "type":"Manufacturing & Wholesale Goods"
        },
        {
            "category":"Wholesale",
            "subcategory":"Durable Goods & Equipment",
            "type":"Manufacturing & Wholesale Goods"
        }
    ],
    "sg:phone":"+1 503 656 2178",
    "sg:postcode":"97015",
    "sg:province":"OR",
    "sg:tags":[
        "control",
        "valve",
        "system",
        "pump",
        "representative",
        "manufacturer"
    ],
    "wof:name":"Murrell-Hickey & Assoc LLC",
    "wof:placetype":"venue"
},
  "geometry": {"coordinates":[-122.551896,45.408024],"type":"Point"}
}