{
  "type": "Feature",
  "properties": {
    "iso:country":"US",
    "sg:address":"4908 River Rd N",
    "sg:city":"Keizer",
    "sg:classifiers":[
        {
            "category":"Shopping",
            "subcategory":"Books",
            "type":"Retail Goods"
        }
    ],
    "sg:phone":"+1 503 393 2899",
    "sg:postcode":"97303",
    "sg:province":"OR",
    "sg:tags":[
        "new",
        "used",
        "dealer"
    ],
    "wof:name":"Booksmart",
    "wof:placetype":"venue"
},
  "geometry": {"coordinates":[-123.026563,44.996699],"type":"Point"}
}