{
  "type": "Feature",
  "properties": {
    "addr:full":"3405 NE Multnomah St Portland OR 97232",
    "addr:housenumber":"3405",
    "addr:postcode":"97232",
    "addr:street":"Ne Multnomah St",
    "iso:country":"US",
    "sg:address":"3405 NE Multnomah St",
    "sg:city":"Portland",
    "sg:classifiers":[
        {
            "category":"Arts & Performance",
            "subcategory":"Theater",
            "type":"Entertainment"
        }
    ],
    "sg:phone":"+1 503 230 8812",
    "sg:postcode":"97232",
    "sg:province":"OR",
    "sg:tags":[
        "band",
        "orchestra"
    ],
    "wof:name":"Sterling Talent",
    "wof:placetype":"venue"
},
  "geometry": {"coordinates":[-122.62831799999999,45.531599],"type":"Point"}
}