{
  "type": "Feature",
  "properties": {
    "iso:country":"US",
    "sg:address":"3405 NE Multnomah St",
    "sg:city":"Portland",
    "sg:classifiers":[
        {
            "category":"Arts & Performance",
            "subcategory":"Theater",
            "type":"Entertainment"
        }
    ],
    "sg:phone":"+1 503 230 8812",
    "sg:postcode":"97232",
    "sg:province":"OR",
    "sg:tags":[
        "band",
        "orchestra"
    ],
    "wof:name":"Sterling Talent",
    "wof:placetype":"venue"
},
  "geometry": {"coordinates":[-122.628318,45.531599],"type":"Point"}
}