{
  "type": "Feature",
  "properties": {
    "addr:full":"1733 Lansing Ave NE Salem OR 97301",
    "addr:housenumber":"1733",
    "addr:postcode":"97301",
    "addr:street":"Lansing Ave Ne",
    "iso:country":"US",
    "sg:address":"1733 Lansing Ave NE",
    "sg:city":"Salem",
    "sg:classifiers":[
        {
            "category":"Cinema",
            "subcategory":"Movie Rental",
            "type":"Entertainment"
        }
    ],
    "sg:phone":"+1 503 373 9884",
    "sg:postcode":"97301",
    "sg:province":"OR",
    "sg:tags":[
        "leasing",
        "video",
        "disc",
        "tape"
    ],
    "wof:name":"Tienda Y Video El Palmar",
    "wof:placetype":"venue"
},
  "geometry": {"coordinates":[-122.99785900000001,44.951158],"type":"Point"}
}