{
  "type": "Feature",
  "properties": {
    "addr:full":"12045 SW Hall Blvd Tigard OR 97223",
    "addr:housenumber":"12045",
    "addr:postcode":"97223",
    "addr:street":"Sw Hall Blvd",
    "iso:country":"US",
    "sg:address":"12045 SW Hall Blvd",
    "sg:city":"Tigard",
    "sg:classifiers":[
        {
            "category":"Building & Trades",
            "subcategory":"Locksmith",
            "type":"Services"
        }
    ],
    "sg:phone":"+1 503 867 8216",
    "sg:postcode":"97223",
    "sg:province":"OR",
    "sg:tags":[
        "key"
    ],
    "wof:name":"24 Hour Emergency Locksmith",
    "wof:placetype":"venue"
},
  "geometry": {"coordinates":[-122.764934,45.432737],"type":"Point"}
}