{
  "type": "Feature",
  "properties": {
    "iso:country":"US",
    "sg:address":"6039 NE 30th Ave",
    "sg:city":"Portland",
    "sg:classifiers":[
        {
            "category":"Professional",
            "type":"Services"
        }
    ],
    "sg:phone":"+1 503 280 8874",
    "sg:postcode":"97211",
    "sg:province":"OR",
    "wof:name":"Graphix 2000 Inc",
    "wof:placetype":"venue"
},
  "geometry": {"coordinates":[-122.635007,45.566524],"type":"Point"}
}