{
  "type": "Feature",
  "properties": {
    "iso:country":"US",
    "sg:address":"4515 SE Woodstock Blvd",
    "sg:city":"Portland",
    "sg:classifiers":[
        {
            "category":"Banks & Credit Unions",
            "subcategory":"Bank",
            "type":"Services"
        }
    ],
    "sg:phone":"+1 503 788 0053",
    "sg:postcode":"97206",
    "sg:province":"OR",
    "sg:website":"www.wellsfargo.com",
    "wof:name":"Wells Fargo",
    "wof:placetype":"venue"
},
  "geometry": {"coordinates":[-122.616204,45.479907],"type":"Point"}
}