{
  "type": "Feature",
  "properties": {
    "iso:country":"US",
    "sg:address":"1211 SW 5th Ave",
    "sg:city":"Portland",
    "sg:classifiers":[
        {
            "category":"Banks & Credit Unions",
            "subcategory":"Investment Brokerage",
            "type":"Services"
        },
        {
            "category":"Banks & Credit Unions",
            "subcategory":"Financial Services",
            "type":"Services"
        }
    ],
    "sg:phone":"+1 503 223 1334",
    "sg:postcode":"97204",
    "sg:province":"OR",
    "wof:name":"Criterion Investment Company",
    "wof:placetype":"venue"
},
  "geometry": {"coordinates":[-122.679794,45.5149],"type":"Point"}
}