{
  "type": "Feature",
  "properties": {
    "addr:full":"4023 SE Ivon St Portland OR 97202",
    "addr:housenumber":"4023",
    "addr:postcode":"97202",
    "addr:street":"Se Ivon St",
    "iso:country":"US",
    "sg:address":"4023 SE Ivon St",
    "sg:city":"Portland",
    "sg:classifiers":[
        {
            "category":"Professional",
            "subcategory":"Business Services",
            "type":"Services"
        }
    ],
    "sg:phone":"+1 503 231 7330",
    "sg:postcode":"97202",
    "sg:province":"OR",
    "wof:name":"Bonefish Enterprises",
    "wof:placetype":"venue"
},
  "geometry": {"coordinates":[-122.62137,45.504149],"type":"Point"}
}