{
  "type": "Feature",
  "properties": {
    "iso:country":"US",
    "sg:address":"3387 Highway 101 N",
    "sg:city":"Gearhart",
    "sg:classifiers":[
        {
            "category":"Ice Cream",
            "type":"Food & Drink"
        }
    ],
    "sg:menulink":"http://www.allmenus.com/or/astoria/175823-dairy-queen/menu/",
    "sg:phone":"+1 503 738 7711",
    "sg:postcode":"97138",
    "sg:province":"OR",
    "sg:tags":[
        "burger",
        "american"
    ],
    "wof:name":"Dairy Queen",
    "wof:placetype":"venue"
},
  "geometry": {"coordinates":[-123.91125099999999,46.022962],"type":"Point"}
}