{
  "type": "Feature",
  "properties": {
    "iso:country":"US",
    "sg:address":"2500 NE 201st Ave Ste 8",
    "sg:city":"Fairview",
    "sg:classifiers":[
        {
            "category":"Building & Trades",
            "subcategory":"Equipment Rental",
            "type":"Services"
        },
        {
            "category":"Building & Trades",
            "subcategory":"Construction",
            "type":"Services"
        }
    ],
    "sg:phone":"+1 503 665 0854",
    "sg:postcode":"97024",
    "sg:province":"OR",
    "sg:tags":[
        "mobile",
        "manufactured",
        "housing-communities",
        "homes-rent",
        "lease"
    ],
    "wof:name":"Cherry Blossom Mobile Home Pk",
    "wof:placetype":"venue"
},
  "geometry": {"coordinates":[-122.456642,45.541168],"type":"Point"}
}