{
  "type": "Feature",
  "properties": {
    "addr:full":"212 Spruce St Myrtle Point OR 97458",
    "addr:housenumber":"212",
    "addr:postcode":"97458",
    "addr:street":"Spruce St",
    "iso:country":"US",
    "sg:address":"212 Spruce St",
    "sg:city":"Myrtle Point",
    "sg:classifiers":[
        {
            "category":"Education",
            "subcategory":"School",
            "type":"Public Place"
        }
    ],
    "sg:phone":"+1 541 572 2811",
    "sg:postcode":"97458",
    "sg:province":"OR",
    "wof:name":"Bridge Elementary School",
    "wof:placetype":"venue"
},
  "geometry": {"coordinates":[-124.144705,43.06532],"type":"Point"}
}