{
  "type": "Feature",
  "properties": {
    "iso:country":"US",
    "sg:address":"2400 SE Mailwell Dr",
    "sg:city":"Milwaukie",
    "sg:classifiers":[
        {
            "category":"Freight",
            "type":"Transportation"
        }
    ],
    "sg:phone":"+1 503 786 7037",
    "sg:postcode":"97222",
    "sg:province":"OR",
    "sg:tags":[
        "trucking"
    ],
    "wof:name":"One Stop Logistics",
    "wof:placetype":"venue"
},
  "geometry": {"coordinates":[-122.637928,45.454498],"type":"Point"}
}