{
  "type": "Feature",
  "properties": {
    "addr:full":"4409 NE 80th Ave Portland OR 97218",
    "addr:housenumber":"4409",
    "addr:postcode":"97218",
    "addr:street":"Ne 80Th Ave",
    "iso:country":"US",
    "sg:address":"4409 NE 80th Ave",
    "sg:city":"Portland",
    "sg:classifiers":[
        {
            "category":"Wholesale",
            "subcategory":"Jewelry",
            "type":"Manufacturing & Wholesale Goods"
        },
        {
            "category":"Shopping",
            "subcategory":"Crafts & Fabrics",
            "type":"Retail Goods"
        }
    ],
    "sg:phone":"+1 503 282 0653",
    "sg:postcode":"97218",
    "sg:province":"OR",
    "sg:tags":[
        "bead",
        "beads-wholesale",
        "manufacturer"
    ],
    "wof:name":"Portland Bead Society",
    "wof:placetype":"venue"
},
  "geometry": {"coordinates":[-122.580629,45.554742],"type":"Point"}
}