{
  "type": "Feature",
  "properties": {
    "iso:country":"US",
    "sg:address":"7871 SW Capitol Hwy",
    "sg:city":"Portland",
    "sg:classifiers":[
        {
            "category":"Shopping",
            "subcategory":"Jewelry",
            "type":"Retail Goods"
        },
        {
            "category":"Wholesale",
            "subcategory":"Apparel",
            "type":"Manufacturing & Wholesale Goods"
        },
        {
            "category":"Shopping",
            "subcategory":"Shoes",
            "type":"Retail Goods"
        }
    ],
    "sg:phone":"+1 503 445 4585",
    "sg:postcode":"97219",
    "sg:province":"OR",
    "sg:tags":[
        "shoes-wholesale",
        "store",
        "manufacturer"
    ],
    "sg:website":"switch-shoes.com",
    "wof:name":"Switch Shoes",
    "wof:placetype":"venue"
},
  "geometry": {"coordinates":[-122.71439599999999,45.467724],"type":"Point"}
}