{
  "type": "Feature",
  "properties": {
    "iso:country":"US",
    "sg:address":"463 Slide Creek Rd",
    "sg:city":"Myrtle Creek",
    "sg:classifiers":[
        {
            "category":"Farming",
            "subcategory":"Farm",
            "type":"Manufacturing & Wholesale Goods"
        }
    ],
    "sg:phone":"+1 541 863 7779",
    "sg:postcode":"97457",
    "sg:province":"OR",
    "sg:tags":[
        "crop",
        "general"
    ],
    "wof:name":"Natures Own Farm",
    "wof:placetype":"venue"
},
  "geometry": {"coordinates":[-123.11970100000001,43.106151],"type":"Point"}
}