{
  "type": "Feature",
  "properties": {
    "addr:full":"444 SW 4th St Ontario OR 97914",
    "addr:housenumber":"444",
    "addr:postcode":"97914",
    "addr:street":"Sw 4Th St",
    "iso:country":"US",
    "sg:address":"444 SW 4th St",
    "sg:city":"Ontario",
    "sg:classifiers":[
        {
            "category":"Government",
            "subcategory":"Office",
            "type":"Public Place"
        }
    ],
    "sg:phone":"+1 541 881 3236",
    "sg:postcode":"97914",
    "sg:province":"OR",
    "sg:tags":[
        "village"
    ],
    "wof:name":"Ontario Engineering Div",
    "wof:placetype":"venue"
},
  "geometry": {"coordinates":[-116.96914200000001,44.023496],"type":"Point"}
}