{
  "type": "Feature",
  "properties": {
    "iso:country":"US",
    "sg:address":"422 SE 69th Ave",
    "sg:city":"Portland",
    "sg:classifiers":[
        {
            "category":"Arena",
            "subcategory":"Sports Club",
            "type":"Entertainment"
        }
    ],
    "sg:phone":"+1 971 506 6690",
    "sg:postcode":"97215",
    "sg:province":"OR",
    "wof:name":"Primera Events",
    "wof:placetype":"venue"
},
  "geometry": {"coordinates":[-122.592145,45.519456],"type":"Point"}
}