{
  "type": "Feature",
  "properties": {
    "iso:country":"US",
    "sg:address":"1701 Copping St",
    "sg:city":"Eugene",
    "sg:classifiers":[
        {
            "category":"Building & Trades",
            "subcategory":"Pest Control",
            "type":"Services"
        }
    ],
    "sg:phone":"+1 541 461 1295",
    "sg:postcode":"97404",
    "sg:province":"OR",
    "wof:name":"ABC Industries",
    "wof:placetype":"venue"
},
  "geometry": {"coordinates":[-123.118899,44.092088],"type":"Point"}
}