{
  "type": "Feature",
  "properties": {
    "iso:country":"US",
    "sg:address":"14400 NW Greenbrier Pkwy",
    "sg:city":"Beaverton",
    "sg:classifiers":[
        {
            "category":"Shopping",
            "subcategory":"Bicycles & Sporting Goods",
            "type":"Retail Goods"
        }
    ],
    "sg:phone":"+1 503 526 1400",
    "sg:postcode":"97006",
    "sg:province":"OR",
    "sg:website":"www.leupold.com",
    "wof:name":"Leupold & Stevens",
    "wof:placetype":"venue"
},
  "geometry": {"coordinates":[-122.825996,45.5247],"type":"Point"}
}