{
  "type": "Feature",
  "properties": {
    "iso:country":"US",
    "sg:address":"4317 S 6th St",
    "sg:city":"Klamath Falls",
    "sg:classifiers":[
        {
            "category":"Food & Beverages",
            "subcategory":"Groceries & Convenience Stores",
            "type":"Retail Goods"
        }
    ],
    "sg:phone":"+1 541 884 1358",
    "sg:postcode":"97603",
    "sg:province":"OR",
    "wof:name":"Murphy's Market",
    "wof:placetype":"venue"
},
  "geometry": {"coordinates":[-121.735603,42.206492],"type":"Point"}
}