{
  "type": "Feature",
  "properties": {
    "addr:full":"6795 SW Juniper Ter Beaverton OR 97008",
    "addr:housenumber":"6795",
    "addr:postcode":"97008",
    "addr:street":"Sw Juniper Ter",
    "iso:country":"US",
    "sg:address":"6795 SW Juniper Ter",
    "sg:city":"Beaverton",
    "sg:classifiers":[
        {
            "category":"Building & Trades",
            "subcategory":"Construction",
            "type":"Services"
        }
    ],
    "sg:phone":"+1 503 646 8919",
    "sg:postcode":"97008",
    "sg:province":"OR",
    "sg:tags":[
        "contractor"
    ],
    "wof:name":"Prime Roofing",
    "wof:placetype":"venue"
},
  "geometry": {"coordinates":[-122.807631,45.471317],"type":"Point"}
}