{
  "type": "Feature",
  "properties": {
    "iso:country":"US",
    "sg:address":"900 Madison Ave",
    "sg:city":"Vernonia",
    "sg:classifiers":[
        {
            "category":"Travel",
            "subcategory":"Hotels & Motels",
            "type":"Entertainment"
        }
    ],
    "sg:phone":"+1 503 429 4006",
    "sg:postcode":"97064",
    "sg:province":"OR",
    "sg:tags":[
        "operation",
        "lodging"
    ],
    "wof:name":"Vernonia Inn",
    "wof:placetype":"venue"
},
  "geometry": {"coordinates":[-123.19528200000001,45.85939],"type":"Point"}
}