{
  "type": "Feature",
  "properties": {
    "iso:country":"US",
    "sg:address":"401 Main Ave",
    "sg:city":"Tillamook",
    "sg:classifiers":[
        {
            "category":"Shopping",
            "subcategory":"Computers & Home Electronics",
            "type":"Retail Goods"
        },
        {
            "category":"Professional",
            "subcategory":"Computer Services",
            "type":"Services"
        }
    ],
    "sg:phone":"+1 503 842 5512",
    "sg:postcode":"97141",
    "sg:province":"OR",
    "sg:tags":[
        "equipment",
        "dealer"
    ],
    "wof:name":"Tillamook Computers & Service",
    "wof:placetype":"venue"
},
  "geometry": {"coordinates":[-123.843965,45.455602],"type":"Point"}
}