{
  "type": "Feature",
  "properties": {
    "iso:country":"US",
    "sg:address":"11565 SW Pacific Hwy",
    "sg:city":"Portland",
    "sg:classifiers":[
        {
            "category":"Shopping",
            "subcategory":"Department Store",
            "type":"Retail Goods"
        }
    ],
    "sg:phone":"+1 503 293 7053",
    "sg:postcode":"97223",
    "sg:province":"OR",
    "sg:website":"www.fredmeyer.com",
    "wof:name":"Fred Meyer One Stop Shopping",
    "wof:placetype":"venue"
},
  "geometry": {"coordinates":[-122.75095,45.440084],"type":"Point"}
}