{
  "type": "Feature",
  "properties": {
    "iso:country":"US",
    "sg:address":"1215 SW 4th Ave",
    "sg:city":"Ontario",
    "sg:classifiers":[
        {
            "category":"Organizations",
            "subcategory":"Non-profit Organization",
            "type":"Services"
        }
    ],
    "sg:phone":"+1 541 881 1271",
    "sg:postcode":"97914",
    "sg:province":"OR",
    "sg:tags":[
        "info",
        "addiction",
        "abuse",
        "treatment",
        "drug"
    ],
    "wof:name":"Drug Abuse & Treatment",
    "wof:placetype":"venue"
},
  "geometry": {"coordinates":[-116.982912,44.024866],"type":"Point"}
}