{
  "type": "Feature",
  "properties": {
    "iso:country":"US",
    "sg:address":"3677 S Stage Rd",
    "sg:city":"Medford",
    "sg:classifiers":[
        {
            "category":"Organizations",
            "subcategory":"Religious Organization",
            "type":"Services"
        }
    ],
    "sg:phone":"+1 541 773 6097",
    "sg:postcode":"97501",
    "sg:province":"OR",
    "sg:tags":[
        "church"
    ],
    "sg:website":"www.vvsda.org",
    "wof:name":"Valley View Seventh-Day Advent",
    "wof:placetype":"venue"
},
  "geometry": {"coordinates":[-122.926202,42.302306],"type":"Point"}
}