{
  "type": "Feature",
  "properties": {
    "addr:full":"20554 NW Lapine Way Portland OR 97229",
    "addr:housenumber":"20554",
    "addr:postcode":"97229",
    "addr:street":"Nw Lapine Way",
    "iso:country":"US",
    "sg:address":"20554 NW Lapine Way",
    "sg:city":"Portland",
    "sg:classifiers":[
        {
            "category":"Real Estate",
            "subcategory":"Real Estate Operator",
            "type":"Services"
        }
    ],
    "sg:phone":"+1 503 645 9127",
    "sg:postcode":"97229",
    "sg:province":"OR",
    "sg:tags":[
        "building",
        "apartment"
    ],
    "wof:name":"Rock Creek Duplexes",
    "wof:placetype":"venue"
},
  "geometry": {"coordinates":[-122.890692,45.555885],"type":"Point"}
}