{
  "type": "Feature",
  "properties": {
    "addr:full":"1429 SW 14th Ave Apt 406 Portland OR 97201",
    "addr:housenumber":"1429;406",
    "addr:postcode":"97201",
    "addr:street":"Sw 14Th Ave Apt",
    "iso:country":"US",
    "sg:address":"1429 SW 14th Ave Apt 406",
    "sg:city":"Portland",
    "sg:classifiers":[
        {
            "category":"Professional",
            "subcategory":"Detective & Security Services",
            "type":"Services"
        }
    ],
    "sg:phone":"+1 843 425 6686",
    "sg:postcode":"97201",
    "sg:province":"OR",
    "sg:tags":[
        "information",
        "bureau"
    ],
    "wof:name":"Marina Drazba",
    "wof:placetype":"venue"
},
  "geometry": {"coordinates":[-122.689035,45.515937],"type":"Point"}
}