{
  "type": "Feature",
  "properties": {
    "addr:full":"3562 N River Rd Gold Hill OR 97525",
    "addr:housenumber":"3562",
    "addr:postcode":"97525",
    "addr:street":"N River Rd",
    "iso:country":"US",
    "sg:address":"3562 N River Rd",
    "sg:city":"Gold Hill",
    "sg:classifiers":[
        {
            "category":"Professional",
            "type":"Services"
        }
    ],
    "sg:phone":"+1 541 582 8850",
    "sg:postcode":"97525",
    "sg:province":"OR",
    "wof:name":"Don & Catherine Green",
    "wof:placetype":"venue"
},
  "geometry": {"coordinates":[-123.14222599999999,42.410548],"type":"Point"}
}