{
  "type": "Feature",
  "properties": {
    "iso:country":"US",
    "sg:address":"509 NW Franklin Ave",
    "sg:city":"Bend",
    "sg:classifiers":[
        {
            "category":"Personal",
            "subcategory":"Beauty Salon",
            "type":"Services"
        }
    ],
    "sg:phone":"+1 541 382 7434",
    "sg:postcode":"97701",
    "sg:province":"OR",
    "wof:name":"Classic Hair Design",
    "wof:placetype":"venue"
},
  "geometry": {"coordinates":[-121.312974,44.05676],"type":"Point"}
}