{
  "type": "Feature",
  "properties": {
    "addr:full":"1605 Siskiyou Blvd Ashland OR 97520",
    "addr:housenumber":"1605",
    "addr:postcode":"97520",
    "addr:street":"Siskiyou Blvd",
    "iso:country":"US",
    "sg:address":"1605 Siskiyou Blvd",
    "sg:city":"Ashland",
    "sg:classifiers":[
        {
            "category":"Health Services",
            "subcategory":"Chiropractor",
            "type":"Services"
        }
    ],
    "sg:phone":"+1 541 482 3492",
    "sg:postcode":"97520",
    "sg:province":"OR",
    "wof:name":"Cynthia DC",
    "wof:placetype":"venue"
},
  "geometry": {"coordinates":[-122.687032,42.183131],"type":"Point"}
}