{
  "type": "Feature",
  "properties": {
    "addr:full":"514 N Broadway Coos Bay OR 97420",
    "addr:housenumber":"514",
    "addr:postcode":"97420",
    "addr:street":"N Broadway",
    "iso:country":"US",
    "sg:address":"514 N Broadway",
    "sg:city":"Coos Bay",
    "sg:classifiers":[
        {
            "category":"Insurance",
            "subcategory":"Insurance Agent",
            "type":"Services"
        }
    ],
    "sg:phone":"+1 541 266 0199",
    "sg:postcode":"97420",
    "sg:province":"OR",
    "wof:name":"AFLAC",
    "wof:placetype":"venue"
},
  "geometry": {"coordinates":[-124.213075,43.37125],"type":"Point"}
}