{
  "type": "Feature",
  "properties": {
    "iso:country":"US",
    "sg:address":"3136 NW 35th Ave",
    "sg:city":"Portland",
    "sg:classifiers":[
        {
            "category":"Manufacturing",
            "subcategory":"Lumber",
            "type":"Manufacturing & Wholesale Goods"
        }
    ],
    "sg:phone":"+1 503 223 3692",
    "sg:postcode":"97210",
    "sg:province":"OR",
    "sg:tags":[
        "mill",
        "pulp"
    ],
    "wof:name":"Weyerhauser Quality Sort Ctr",
    "wof:placetype":"venue"
},
  "geometry": {"coordinates":[-122.718863,45.544953],"type":"Point"}
}