{
  "type": "Feature",
  "properties": {
    "addr:full":"50776 Dike Rd Scappoose OR 97056",
    "addr:postcode":"50776;97056",
    "addr:street":"Dike Rd",
    "iso:country":"US",
    "sg:address":"50776 Dike Rd",
    "sg:city":"Scappoose",
    "sg:classifiers":[
        {
            "category":"Recreation",
            "subcategory":"Marina",
            "type":"Entertainment"
        }
    ],
    "sg:phone":"+1 503 543 6882",
    "sg:postcode":"97056",
    "sg:province":"OR",
    "sg:tags":[
        "operation"
    ],
    "wof:name":"Dikeside Moorage Inc",
    "wof:placetype":"venue"
},
  "geometry": {"coordinates":[-122.858717,45.732633],"type":"Point"}
}