{
  "type": "Feature",
  "properties": {
    "iso:country":"US",
    "sg:address":"505 S Sherwood Blvd",
    "sg:city":"Sherwood",
    "sg:classifiers":[
        {
            "category":"Building & Trades",
            "subcategory":"Construction",
            "type":"Services"
        }
    ],
    "sg:phone":"+1 503 554 1732",
    "sg:postcode":"97140",
    "sg:province":"OR",
    "sg:tags":[
        "dry wall",
        "contractor"
    ],
    "wof:name":"Allphase Matlock Drywall",
    "wof:placetype":"venue"
},
  "geometry": {"coordinates":[-122.841458,45.353817],"type":"Point"}
}