{
  "type": "Feature",
  "properties": {
    "iso:country":"US",
    "sg:address":"22665 S Central Point Rd",
    "sg:city":"Canby",
    "sg:classifiers":[
        {
            "category":"Retail",
            "subcategory":"Animal Services",
            "type":"Services"
        }
    ],
    "sg:phone":"+1 503 651 3418",
    "sg:postcode":"97013",
    "sg:province":"OR",
    "wof:name":"Oz Inc",
    "wof:placetype":"venue"
},
  "geometry": {"coordinates":[-122.63035000000001,45.278023],"type":"Point"}
}