{
  "type": "Feature",
  "properties": {
    "addr:full":"111 SW Columbia Street Suite 500 Portland OR 97201",
    "addr:housenumber":"111",
    "addr:postcode":"97201",
    "addr:street":"Sw Columbia Street Suite 500",
    "iso:country":"US",
    "sg:address":"111 SW Columbia Street Suite 500",
    "sg:city":"Portland",
    "sg:classifiers":[
        {
            "category":"Insurance",
            "subcategory":"Hazard Insurance",
            "type":"Services"
        }
    ],
    "sg:phone":"+1 503 248 6400",
    "sg:postcode":"97201",
    "sg:province":"OR",
    "wof:name":"Marsh",
    "wof:placetype":"venue"
},
  "geometry": {"coordinates":[-122.67622,45.51312],"type":"Point"}
}