{
  "type": "Feature",
  "properties": {
    "addr:full":"916 W 10th St Medford OR 97501",
    "addr:housenumber":"916",
    "addr:postcode":"97501",
    "addr:street":"W 10Th St",
    "iso:country":"US",
    "sg:address":"916 W 10th St",
    "sg:city":"Medford",
    "sg:classifiers":[
        {
            "category":"Professional",
            "subcategory":"Lawyer & Legal Services",
            "type":"Services"
        }
    ],
    "sg:phone":"+1 541 773 7025",
    "sg:postcode":"97501",
    "sg:province":"OR",
    "sg:tags":[
        "attorney"
    ],
    "wof:name":"David L Miller",
    "wof:placetype":"venue"
},
  "geometry": {"coordinates":[-122.88124999999999,42.321304],"type":"Point"}
}