{
  "type": "Feature",
  "properties": {
    "iso:country":"US",
    "sg:address":"9070 Wallace Rd NW",
    "sg:city":"Salem",
    "sg:classifiers":[
        {
            "category":"Building & Trades",
            "subcategory":"Construction",
            "type":"Services"
        }
    ],
    "sg:phone":"+1 503 399 9729",
    "sg:postcode":"97304",
    "sg:province":"OR",
    "sg:tags":[
        "roofing",
        "consultant",
        "contractor"
    ],
    "wof:name":"Glass Magnem Of Salem",
    "wof:placetype":"venue"
},
  "geometry": {"coordinates":[-123.07259500000001,45.070183],"type":"Point"}
}