{
  "type": "Feature",
  "properties": {
    "iso:country":"US",
    "sg:address":"9760 Portland Rd NE",
    "sg:city":"Salem",
    "sg:classifiers":[
        {
            "category":"Building & Trades",
            "subcategory":"Construction",
            "type":"Services"
        }
    ],
    "sg:phone":"+1 503 393 0664",
    "sg:postcode":"97305",
    "sg:province":"OR",
    "sg:tags":[
        "manufactured",
        "housing-communities"
    ],
    "wof:name":"Chaparral Mobile Ranch",
    "wof:placetype":"venue"
},
  "geometry": {"coordinates":[-122.94370499999999,45.060055],"type":"Point"}
}