{
  "type": "Feature",
  "properties": {
    "addr:full":"14083 Triumph Rd SE Sublimity OR 97385",
    "addr:housenumber":"14083",
    "addr:postcode":"97385",
    "addr:street":"Triumph Rd Se",
    "iso:country":"US",
    "sg:address":"14083 Triumph Rd SE",
    "sg:city":"Sublimity",
    "sg:classifiers":[
        {
            "category":"Real Estate",
            "subcategory":"Real Estate Operator",
            "type":"Services"
        }
    ],
    "sg:phone":"+1 503 769 2487",
    "sg:postcode":"97385",
    "sg:province":"OR",
    "sg:tags":[
        "property",
        "lessor"
    ],
    "wof:name":"Gerald Heuberger",
    "wof:placetype":"venue"
},
  "geometry": {"coordinates":[-122.770809,44.844365],"type":"Point"}
}