{
  "type": "Feature",
  "properties": {
    "iso:country":"US",
    "sg:address":"66 E 6th Ave",
    "sg:city":"Eugene",
    "sg:classifiers":[
        {
            "category":"Personal",
            "subcategory":"Beauty Salon",
            "type":"Services"
        }
    ],
    "sg:phone":"+1 541 687 9379",
    "sg:postcode":"97401",
    "sg:province":"OR",
    "wof:name":"Answer For Hair",
    "wof:placetype":"venue"
},
  "geometry": {"coordinates":[-123.092386,44.053156],"type":"Point"}
}