{
  "type": "Feature",
  "properties": {
    "iso:country":"US",
    "sg:address":"1257 Siskiyou Blvd 1149",
    "sg:city":"Ashland",
    "sg:classifiers":[
        {
            "category":"Manufacturing",
            "subcategory":"Lumber",
            "type":"Manufacturing & Wholesale Goods"
        }
    ],
    "sg:phone":"+1 541 840 6490",
    "sg:postcode":"97520",
    "sg:province":"OR",
    "sg:tags":[
        "logging"
    ],
    "wof:name":"Morlog Corp",
    "wof:placetype":"venue"
},
  "geometry": {"coordinates":[-122.693834,42.186528],"type":"Point"}
}