{
  "type": "Feature",
  "properties": {
    "iso:country":"US",
    "sg:address":"1286 NE Morning Sun Dr",
    "sg:city":"Hillsboro",
    "sg:classifiers":[
        {
            "category":"Professional",
            "subcategory":"Computer Services",
            "type":"Services"
        }
    ],
    "sg:phone":"+1 503 844 2984",
    "sg:postcode":"97124",
    "sg:province":"OR",
    "sg:tags":[
        "consulting",
        "e",
        "network"
    ],
    "wof:name":"Cypace Inc",
    "wof:placetype":"venue"
},
  "geometry": {"coordinates":[-122.97064899999999,45.540439],"type":"Point"}
}