{
  "type": "Feature",
  "properties": {
    "iso:country":"US",
    "sg:address":"333 S State St",
    "sg:city":"Lake Oswego",
    "sg:classifiers":[
        {
            "category":"Personal",
            "type":"Services"
        }
    ],
    "sg:phone":"+1 503 281 3766",
    "sg:postcode":"97034",
    "sg:province":"OR",
    "wof:name":"Illumination Tans",
    "wof:placetype":"venue"
},
  "geometry": {"coordinates":[-122.664154,45.413274],"type":"Point"}
}