{
  "type": "Feature",
  "properties": {
    "addr:full":"14685 N Umpqua Hwy Roseburg OR 97470",
    "addr:housenumber":"14685",
    "addr:postcode":"97470",
    "addr:street":"N Umpqua Hwy",
    "iso:country":"US",
    "sg:address":"14685 N Umpqua Hwy",
    "sg:city":"Roseburg",
    "sg:classifiers":[
        {
            "category":"Building & Trades",
            "subcategory":"Construction",
            "type":"Services"
        }
    ],
    "sg:phone":"+1 541 672 0082",
    "sg:postcode":"97470",
    "sg:province":"OR",
    "sg:tags":[
        "contractor"
    ],
    "wof:name":"Arm & Hammer Construction",
    "wof:placetype":"venue"
},
  "geometry": {"coordinates":[-123.17389799999999,43.298177],"type":"Point"}
}