{
  "type": "Feature",
  "properties": {
    "iso:country":"US",
    "sg:address":"22151 S Saling Rd",
    "sg:city":"Estacada",
    "sg:classifiers":[
        {
            "category":"Building & Trades",
            "subcategory":"Construction",
            "type":"Services"
        }
    ],
    "sg:phone":"+1 503 630 2877",
    "sg:postcode":"97023",
    "sg:province":"OR",
    "sg:tags":[
        "general",
        "contractor"
    ],
    "wof:name":"Akins Construction",
    "wof:placetype":"venue"
},
  "geometry": {"coordinates":[-122.348119,45.285966],"type":"Point"}
}