{
  "type": "Feature",
  "properties": {
    "iso:country":"US",
    "sg:address":"3131 SW Willamette Ave",
    "sg:city":"Corvallis",
    "sg:classifiers":[
        {
            "category":"Professional",
            "subcategory":"Engineering",
            "type":"Services"
        }
    ],
    "sg:phone":"+1 541 754 0139",
    "sg:postcode":"97333",
    "sg:province":"OR",
    "wof:name":"Al Levno",
    "wof:placetype":"venue"
},
  "geometry": {"coordinates":[-123.28406099999999,44.546744],"type":"Point"}
}