{
  "type": "Feature",
  "properties": {
    "iso:country":"US",
    "sg:address":"605 NW 22nd St",
    "sg:city":"Redmond",
    "sg:classifiers":[
        {
            "category":"Building & Trades",
            "subcategory":"Construction",
            "type":"Services"
        }
    ],
    "sg:phone":"+1 541 504 0346",
    "sg:postcode":"97756",
    "sg:province":"OR",
    "sg:tags":[
        "house"
    ],
    "wof:name":"Duvall Construction LLC",
    "wof:placetype":"venue"
},
  "geometry": {"coordinates":[-121.193551,44.283234],"type":"Point"}
}