{
  "type": "Feature",
  "properties": {
    "iso:country":"US",
    "sg:address":"15819 NE Becke Rd",
    "sg:city":"Aurora",
    "sg:classifiers":[
        {
            "category":"Farming",
            "subcategory":"Nursery",
            "type":"Manufacturing & Wholesale Goods"
        }
    ],
    "sg:phone":"+1 503 678 1685",
    "sg:postcode":"97002",
    "sg:province":"OR",
    "sg:tags":[
        "ornamental"
    ],
    "wof:name":"Daisugi America Inc",
    "wof:placetype":"venue"
},
  "geometry": {"coordinates":[-122.737748,45.290524],"type":"Point"}
}