{
  "type": "Feature",
  "properties": {
    "iso:country":"US",
    "sg:address":"821 Ave C",
    "sg:city":"Seaside",
    "sg:classifiers":[
        {
            "category":"Retail",
            "subcategory":"Auto Repair",
            "type":"Services"
        }
    ],
    "sg:phone":"+1 503 717 9409",
    "sg:postcode":"97138",
    "sg:province":"OR",
    "sg:tags":[
        "general"
    ],
    "wof:name":"Rob McBrides Auto Service",
    "wof:placetype":"venue"
},
  "geometry": {"coordinates":[-123.92257600000001,45.991269],"type":"Point"}
}