{
  "type": "Feature",
  "properties": {
    "iso:country":"US",
    "sg:address":"1998 Sky Park Dr",
    "sg:city":"Medford",
    "sg:classifiers":[
        {
            "category":"Professional",
            "subcategory":"Business Services",
            "type":"Services"
        },
        {
            "category":"Insurance",
            "subcategory":"Insurance Agent",
            "type":"Services"
        }
    ],
    "sg:phone":"+1 541 608 8181",
    "sg:postcode":"97504",
    "sg:province":"OR",
    "wof:name":"Standard Financial Solutions",
    "wof:placetype":"venue"
},
  "geometry": {"coordinates":[-122.855658,42.358005],"type":"Point"}
}