{
  "type": "Feature",
  "properties": {
    "addr:full":"7112 NE Glisan St Portland OR 97213",
    "addr:housenumber":"7112",
    "addr:postcode":"97213",
    "addr:street":"Ne Glisan St",
    "iso:country":"US",
    "sg:address":"7112 NE Glisan St",
    "sg:city":"Portland",
    "sg:classifiers":[
        {
            "category":"Shopping",
            "subcategory":"Gifts & Souvenirs",
            "type":"Retail Goods"
        },
        {
            "category":"Shopping",
            "subcategory":"Crafts & Fabrics",
            "type":"Retail Goods"
        }
    ],
    "sg:phone":"+1 503 254 6297",
    "sg:postcode":"97213",
    "sg:province":"OR",
    "sg:tags":[
        "shop",
        "instruction"
    ],
    "wof:name":"Wood Horse, The",
    "wof:placetype":"venue"
},
  "geometry": {"coordinates":[-122.589716,45.526451],"type":"Point"}
}