{
  "type": "Feature",
  "properties": {
    "iso:country":"US",
    "sg:address":"16953 NE Davis St",
    "sg:city":"Portland",
    "sg:classifiers":[
        {
            "category":"Shopping",
            "subcategory":"Clothing, Apparel, & Fashions",
            "type":"Retail Goods"
        }
    ],
    "sg:phone":"+1 503 255 9911",
    "sg:postcode":"97230",
    "sg:province":"OR",
    "sg:tags":[
        "family"
    ],
    "wof:name":"Outpost Traders",
    "wof:placetype":"venue"
},
  "geometry": {"coordinates":[-122.489121,45.524086],"type":"Point"}
}