{
  "type": "Feature",
  "properties": {
    "iso:country":"US",
    "sg:address":"22100 SW Grahams Ferry Rd",
    "sg:city":"Tualatin",
    "sg:classifiers":[
        {
            "category":"Place Of Worship",
            "subcategory":"Church",
            "type":"Public Place"
        },
        {
            "category":"Place Of Worship",
            "type":"Public Place"
        }
    ],
    "sg:phone":"+1 503 885 8839",
    "sg:postcode":"97062",
    "sg:province":"OR",
    "sg:tags":[
        "christ",
        "churches-reformed",
        "churches-christian-reformed",
        "churches-community"
    ],
    "sg:website":"http://www.crchurchtualatin.com",
    "wof:name":"Christ Community Church",
    "wof:placetype":"venue"
},
  "geometry": {"coordinates":[-122.779746,45.358879],"type":"Point"}
}