{
  "type": "Feature",
  "properties": {
    "iso:country":"US",
    "sg:address":"205 N Bay Dr",
    "sg:city":"North Bend",
    "sg:classifiers":[
        {
            "category":"Social Services",
            "subcategory":"Child Care",
            "type":"Services"
        }
    ],
    "sg:phone":"+1 541 756 1051",
    "sg:postcode":"97459",
    "sg:province":"OR",
    "sg:tags":[
        "day"
    ],
    "wof:name":"Glasgow Day Care Center",
    "wof:placetype":"venue"
},
  "geometry": {"coordinates":[-124.217417,43.440099],"type":"Point"}
}