{
  "type": "Feature",
  "properties": {
    "addr:full":"3140 22nd St SE Salem OR 97302",
    "addr:housenumber":"3140",
    "addr:postcode":"97302",
    "addr:street":"22Nd St Se",
    "iso:country":"US",
    "sg:address":"3140 22nd St SE",
    "sg:city":"Salem",
    "sg:classifiers":[
        {
            "category":"Building & Trades",
            "subcategory":"Electrical",
            "type":"Services"
        }
    ],
    "sg:phone":"+1 503 373 9677",
    "sg:postcode":"97302",
    "sg:province":"OR",
    "sg:tags":[
        "electrical",
        "contractor"
    ],
    "wof:name":"Farnham Electric Co",
    "wof:placetype":"venue"
},
  "geometry": {"coordinates":[-123.017251,44.910078],"type":"Point"}
}