{
  "type": "Feature",
  "properties": {
    "iso:country":"US",
    "sg:address":"34129 Tennessee Rd",
    "sg:city":"Lebanon",
    "sg:phone":"+1 541 258 3890",
    "sg:postcode":"97355",
    "sg:province":"OR",
    "sg:tags":[
        "farm",
        "corn"
    ],
    "wof:name":"Gary Hull",
    "wof:placetype":"venue"
},
  "geometry": {"coordinates":[-122.897195,44.587801],"type":"Point"}
}