{
  "type": "Feature",
  "properties": {
    "addr:full":"12220 SW Summer St Portland OR 97223",
    "addr:housenumber":"12220",
    "addr:postcode":"97223",
    "addr:street":"Sw Summer St",
    "iso:country":"US",
    "sg:address":"12220 SW Summer St",
    "sg:city":"Portland",
    "sg:classifiers":[
        {
            "category":"Shopping",
            "subcategory":"Computers & Home Electronics",
            "type":"Retail Goods"
        }
    ],
    "sg:phone":"+1 503 579 2781",
    "sg:postcode":"97223",
    "sg:province":"OR",
    "sg:tags":[
        "software"
    ],
    "wof:name":"Circuit One Computer Cnsltng",
    "wof:placetype":"venue"
},
  "geometry": {"coordinates":[-122.802567,45.437217],"type":"Point"}
}