{
  "type": "Feature",
  "properties": {
    "iso:country":"US",
    "sg:address":"7035 SW Brenne Ln",
    "sg:city":"Portland",
    "sg:classifiers":[
        {
            "category":"Real Estate",
            "subcategory":"Real Estate Operator",
            "type":"Services"
        }
    ],
    "sg:phone":"+1 503 297 3883",
    "sg:postcode":"97225",
    "sg:province":"OR",
    "sg:tags":[
        "investment"
    ],
    "wof:name":"Empire Commerce Co",
    "wof:placetype":"venue"
},
  "geometry": {"coordinates":[-122.749275,45.491388],"type":"Point"}
}