{
  "type": "Feature",
  "properties": {
    "iso:country":"US",
    "sg:address":"306 Maple St",
    "sg:city":"Myrtle Point",
    "sg:classifiers":[
        {
            "category":"Professional",
            "subcategory":"Business Services",
            "type":"Services"
        }
    ],
    "sg:phone":"+1 541 572 0422",
    "sg:postcode":"97458",
    "sg:province":"OR",
    "sg:tags":[
        "auctioneer"
    ],
    "wof:name":"Mahon Auctioneers",
    "wof:placetype":"venue"
},
  "geometry": {"coordinates":[-124.143914,43.064513],"type":"Point"}
}