{
  "type": "Feature",
  "properties": {
    "iso:country":"US",
    "sg:address":"1678 Burroughs Rd",
    "sg:city":"Adrian",
    "sg:classifiers":[
        {
            "category":"Farming",
            "subcategory":"Livestock Farm",
            "type":"Manufacturing & Wholesale Goods"
        }
    ],
    "sg:phone":"+1 541 339 3999",
    "sg:postcode":"97901",
    "sg:province":"OR",
    "sg:tags":[
        "sheep",
        "raising"
    ],
    "wof:name":"Ewing LIVestock&forage",
    "wof:placetype":"venue"
},
  "geometry": {"coordinates":[-117.035759,43.676954],"type":"Point"}
}