{
  "type": "Feature",
  "properties": {
    "addr:full":"5000 N Willamette Blvd Portland OR 97203",
    "addr:housenumber":"5000",
    "addr:postcode":"97203",
    "addr:street":"N Willamette Blvd",
    "iso:country":"US",
    "sg:address":"5000 N Willamette Blvd",
    "sg:city":"Portland",
    "sg:classifiers":[
        {
            "category":"Education",
            "subcategory":"College",
            "type":"Public Place"
        }
    ],
    "sg:phone":"+1 503 943 8000",
    "sg:postcode":"97203",
    "sg:province":"OR",
    "sg:tags":[
        "university"
    ],
    "wof:name":"The University of Portland",
    "wof:placetype":"venue"
},
  "geometry": {"coordinates":[-122.72621599999999,45.575075],"type":"Point"}
}