{
  "type": "Feature",
  "properties": {
    "iso:country":"US",
    "sg:address":"18624 NW Walker Rd",
    "sg:city":"Beaverton",
    "sg:classifiers":[
        {
            "category":"Education",
            "subcategory":"Vocational School",
            "type":"Public Place"
        },
        {
            "category":"Education",
            "subcategory":"University",
            "type":"Public Place"
        }
    ],
    "sg:phone":"+1 503 533 2700",
    "sg:postcode":"97006",
    "sg:province":"OR",
    "sg:tags":[
        "technical",
        "industrial",
        "college",
        "trade"
    ],
    "sg:website":"http://www.pcc.edu",
    "wof:name":"Portland Community College",
    "wof:placetype":"venue"
},
  "geometry": {"coordinates":[-122.86900300000001,45.528301],"type":"Point"}
}