{
  "type": "Feature",
  "properties": {
    "iso:country":"US",
    "sg:address":"607 7th St",
    "sg:city":"Springfield",
    "sg:classifiers":[
        {
            "category":"Farming",
            "subcategory":"Farm",
            "type":"Manufacturing & Wholesale Goods"
        }
    ],
    "sg:phone":"+1 541 741 6841",
    "sg:postcode":"97477",
    "sg:province":"OR",
    "sg:tags":[
        "crop",
        "general"
    ],
    "wof:name":"J W Wyme",
    "wof:placetype":"venue"
},
  "geometry": {"coordinates":[-123.016713,44.051398],"type":"Point"}
}