{
  "type": "Feature",
  "properties": {
    "iso:country":"US",
    "sg:address":"667 A St",
    "sg:city":"Ashland",
    "sg:classifiers":[
        {
            "category":"Insurance",
            "subcategory":"Insurance Agent",
            "type":"Services"
        },
        {
            "category":"Insurance",
            "subcategory":"Hazard Insurance",
            "type":"Services"
        },
        {
            "category":"Insurance",
            "subcategory":"Title Insurance",
            "type":"Services"
        }
    ],
    "sg:phone":"+1 541 488 0301",
    "sg:postcode":"97520",
    "sg:province":"OR",
    "sg:tags":[
        "auto",
        "homeowner"
    ],
    "sg:website":"http://apps.amfam.com/agentlocator/?sourceid=yp3",
    "wof:name":"American Family Insurance- Ed Steffens",
    "wof:placetype":"venue"
},
  "geometry": {"coordinates":[-122.704975,42.197746],"type":"Point"}
}