{
  "type": "Feature",
  "properties": {
    "iso:country":"US",
    "sg:address":"38906 Proctor Blvd",
    "sg:city":"Sandy",
    "sg:classifiers":[
        {
            "category":"Shopping",
            "subcategory":"Florist",
            "type":"Retail Goods"
        }
    ],
    "sg:phone":"+1 503 668 5220",
    "sg:postcode":"97055",
    "sg:province":"OR",
    "wof:name":"Peddle Pusher",
    "wof:placetype":"venue"
},
  "geometry": {"coordinates":[-122.263054,45.397229],"type":"Point"}
}