{
  "type": "Feature",
  "properties": {
    "addr:full":"11200 SW Allen Blvd Ste 100 Beaverton OR 97005",
    "addr:housenumber":"11200",
    "addr:postcode":"97005",
    "addr:street":"Sw Allen Blvd Ste 100",
    "iso:country":"US",
    "sg:address":"11200 SW Allen Blvd Ste 100",
    "sg:city":"Beaverton",
    "sg:classifiers":[
        {
            "category":"Professional",
            "subcategory":"Accounting & Tax Preparation",
            "type":"Services"
        }
    ],
    "sg:phone":"+1 503 646 4800",
    "sg:postcode":"97005",
    "sg:province":"OR",
    "sg:tags":[
        "accountant"
    ],
    "wof:name":"Young & Justrom Llc",
    "wof:placetype":"venue"
},
  "geometry": {"coordinates":[-122.792,45.476601],"type":"Point"}
}