{
  "type": "Feature",
  "properties": {
    "iso:country":"US",
    "sg:address":"2780 Olive St",
    "sg:city":"Eugene",
    "sg:classifiers":[
        {
            "category":"Professional",
            "type":"Services"
        }
    ],
    "sg:phone":"+1 541 302 8031",
    "sg:postcode":"97405",
    "sg:province":"OR",
    "sg:tags":[
        "bagel"
    ],
    "wof:name":"Northwest Bagel Boys",
    "wof:placetype":"venue"
},
  "geometry": {"coordinates":[-123.094917,44.028324],"type":"Point"}
}