{
  "type": "Feature",
  "properties": {
    "iso:country":"US",
    "sg:address":"825 NE Multnomah St",
    "sg:city":"Portland",
    "sg:classifiers":[
        {
            "category":"Shopping",
            "type":"Retail Goods"
        }
    ],
    "sg:phone":"+1 503 239 4668",
    "sg:postcode":"97232",
    "sg:province":"OR",
    "sg:tags":[
        "aids",
        "hearing"
    ],
    "wof:name":"Sonus",
    "wof:placetype":"venue"
},
  "geometry": {"coordinates":[-122.65748,45.531572],"type":"Point"}
}