{
  "type": "Feature",
  "properties": {
    "iso:country":"US",
    "sg:address":"495 Holly St",
    "sg:city":"Junction City",
    "sg:classifiers":[
        {
            "category":"Restaurant",
            "type":"Food & Drink"
        }
    ],
    "sg:phone":"+1 541 998 2341",
    "sg:postcode":"97448",
    "sg:province":"OR",
    "wof:name":"Pancake & Steak Depot",
    "wof:placetype":"venue"
},
  "geometry": {"coordinates":[-123.203613,44.217484],"type":"Point"}
}