{
  "type": "Feature",
  "properties": {
    "iso:country":"US",
    "sg:address":"22777 N Poe Valley Rd",
    "sg:city":"Klamath Falls",
    "sg:classifiers":[
        {
            "category":"Manufacturing",
            "subcategory":"Glass & Minerals",
            "type":"Manufacturing & Wholesale Goods"
        }
    ],
    "sg:phone":"+1 541 882 6360",
    "sg:postcode":"97603",
    "sg:province":"OR",
    "sg:tags":[
        "concrete",
        "mfg"
    ],
    "wof:name":"D & V Enterprises",
    "wof:placetype":"venue"
},
  "geometry": {"coordinates":[-121.50553600000001,42.168029],"type":"Point"}
}