{
  "type": "Feature",
  "properties": {
    "iso:country":"US",
    "sg:address":"5722 SE Johnson Creek Blvd",
    "sg:city":"Portland",
    "sg:classifiers":[
        {
            "category":"Manufacturing",
            "subcategory":"Metals",
            "type":"Manufacturing & Wholesale Goods"
        }
    ],
    "sg:phone":"+1 503 774 4940",
    "sg:postcode":"97206",
    "sg:province":"OR",
    "sg:tags":[
        "steel",
        "fabrication"
    ],
    "wof:name":"Hogan Fab Inc",
    "wof:placetype":"venue"
},
  "geometry": {"coordinates":[-122.604291,45.457853],"type":"Point"}
}