{
  "type": "Feature",
  "properties": {
    "iso:country":"US",
    "sg:address":"200 E Powell Blvd",
    "sg:city":"Gresham",
    "sg:classifiers":[
        {
            "category":"Insurance",
            "subcategory":"Insurance Agent",
            "type":"Services"
        },
        {
            "category":"Insurance",
            "subcategory":"Hazard Insurance",
            "type":"Services"
        },
        {
            "category":"Insurance",
            "subcategory":"Title Insurance",
            "type":"Services"
        }
    ],
    "sg:phone":"+1 503 489 2087",
    "sg:postcode":"97030",
    "sg:province":"OR",
    "sg:tags":[
        "auto",
        "homeowner"
    ],
    "sg:website":"http://apps.amfam.com/agentlocator/?sourceid=yp3",
    "wof:name":"American Family Insurance- Philip Dalton",
    "wof:placetype":"venue"
},
  "geometry": {"coordinates":[-122.42913799999999,45.498001],"type":"Point"}
}