{
  "type": "Feature",
  "properties": {
    "addr:full":"8435 NE Glisan St Portland OR 97220",
    "addr:housenumber":"8435",
    "addr:postcode":"97220",
    "addr:street":"Ne Glisan St",
    "iso:country":"US",
    "sg:address":"8435 NE Glisan St",
    "sg:city":"Portland",
    "sg:classifiers":[
        {
            "category":"Shopping",
            "subcategory":"Books",
            "type":"Retail Goods"
        }
    ],
    "sg:phone":"+1 503 251 5383",
    "sg:postcode":"97220",
    "sg:province":"OR",
    "sg:tags":[
        "dealer"
    ],
    "wof:name":"Window's Book Sellers",
    "wof:placetype":"venue"
},
  "geometry": {"coordinates":[-122.57699,45.526408],"type":"Point"}
}