{
  "type": "Feature",
  "properties": {
    "iso:country":"US",
    "sg:address":"2791 Pence Loop SE",
    "sg:city":"Salem",
    "sg:classifiers":[
        {
            "category":"Home & Garden",
            "subcategory":"Building Materials",
            "type":"Retail Goods"
        }
    ],
    "sg:phone":"+1 503 365 8438",
    "sg:postcode":"97302",
    "sg:province":"OR",
    "sg:tags":[
        "screen",
        "window"
    ],
    "wof:name":"On-Site Screens & Doors Inc",
    "wof:placetype":"venue"
},
  "geometry": {"coordinates":[-123.021219,44.911835],"type":"Point"}
}