{
  "type": "Feature",
  "properties": {
    "iso:country":"US",
    "sg:address":"7688 SW Capitol Hwy",
    "sg:city":"Portland",
    "sg:classifiers":[
        {
            "category":"Health Services",
            "subcategory":"Doctor",
            "type":"Services"
        },
        {
            "category":"Community Center",
            "type":"Public Place"
        }
    ],
    "sg:phone":"+1 503 977 0733",
    "sg:postcode":"97219",
    "sg:province":"OR",
    "sg:tags":[
        "medical",
        "practice",
        "family"
    ],
    "sg:website":"www.swchc-pdx.org",
    "wof:name":"Southwest Community Health Center",
    "wof:placetype":"venue"
},
  "geometry": {"coordinates":[-122.709802,45.468629],"type":"Point"}
}