{
  "type": "Feature",
  "properties": {
    "iso:country":"US",
    "sg:address":"9816 N Whitaker Rd",
    "sg:city":"Portland",
    "sg:classifiers":[
        {
            "category":"Restaurant",
            "type":"Food & Drink"
        }
    ],
    "sg:menulink":"http://www.allmenus.com/or/portland/170570-burger-king/menu/",
    "sg:phone":"+1 503 283 2440",
    "sg:postcode":"97217",
    "sg:province":"OR",
    "sg:tags":[
        "burger",
        "american"
    ],
    "wof:name":"Burger King",
    "wof:placetype":"venue"
},
  "geometry": {"coordinates":[-122.681417,45.593731],"type":"Point"}
}