{
  "type": "Feature",
  "properties": {
    "iso:country":"US",
    "sg:address":"2364 NW Amberbrook Dr",
    "sg:city":"Beaverton",
    "sg:classifiers":[
        {
            "category":"Restaurant",
            "type":"Food & Drink"
        }
    ],
    "sg:phone":"+1 503 213 3923",
    "sg:postcode":"97006",
    "sg:province":"OR",
    "sg:tags":[
        "italian",
        "pizza"
    ],
    "sg:website":"http://www.bugattisrestaurant.com/bugattis_index.html",
    "wof:name":"Bugatti's Hillsboro / Tanasbourne",
    "wof:placetype":"venue"
},
  "geometry": {"coordinates":[-122.884456,45.536567],"type":"Point"}
}