{
  "type": "Feature",
  "properties": {
    "iso:country":"US",
    "sg:address":"530 S Airport Rd",
    "sg:city":"Lebanon",
    "sg:classifiers":[
        {
            "category":"Social Services",
            "subcategory":"Adult Care",
            "type":"Services"
        }
    ],
    "sg:phone":"+1 541 258 1710",
    "sg:postcode":"97355",
    "sg:province":"OR",
    "sg:tags":[
        "residential"
    ],
    "wof:name":"Judys Care Home",
    "wof:placetype":"venue"
},
  "geometry": {"coordinates":[-122.91436400000001,44.526678],"type":"Point"}
}