{
  "type": "Feature",
  "properties": {
    "iso:country":"US",
    "sg:address":"60035 Latigo Ln",
    "sg:city":"Joseph",
    "sg:classifiers":[
        {
            "category":"Autos & Motor Vehicles",
            "subcategory":"Auto Supplies",
            "type":"Retail Goods"
        }
    ],
    "sg:phone":"+1 541 432 8455",
    "sg:postcode":"97846",
    "sg:province":"OR",
    "wof:name":"Kilgores Auto Parts Inc",
    "wof:placetype":"venue"
},
  "geometry": {"coordinates":[-117.24426099999999,45.38544],"type":"Point"}
}