{
  "type": "Feature",
  "properties": {
    "iso:country":"US",
    "sg:address":"16785 Pine Pl",
    "sg:city":"La Pine",
    "sg:classifiers":[
        {
            "category":"Building & Trades",
            "subcategory":"Plumbing",
            "type":"Services"
        }
    ],
    "sg:phone":"+1 541 536 7687",
    "sg:postcode":"97739",
    "sg:province":"OR",
    "sg:tags":[
        "contractor"
    ],
    "wof:name":"Bb Plumbing LLC",
    "wof:placetype":"venue"
},
  "geometry": {"coordinates":[-121.489744,43.71248],"type":"Point"}
}