{
  "type": "Feature",
  "properties": {
    "iso:country":"US",
    "sg:address":"3855 SW 153rd Dr",
    "sg:city":"Beaverton",
    "sg:classifiers":[
        {
            "category":"Building & Trades",
            "subcategory":"Construction",
            "type":"Services"
        }
    ],
    "sg:phone":"+1 503 473 5703",
    "sg:postcode":"97006",
    "sg:province":"OR",
    "sg:tags":[
        "contractor"
    ],
    "wof:name":"Sitka Projects",
    "wof:placetype":"venue"
},
  "geometry": {"coordinates":[-122.83287199999999,45.49207],"type":"Point"}
}