{
  "type": "Feature",
  "properties": {
    "iso:country":"US",
    "sg:address":"1755 Coburg Rd Ste 6",
    "sg:city":"Eugene",
    "sg:classifiers":[
        {
            "category":"Health Services",
            "subcategory":"Doctor",
            "type":"Services"
        },
        {
            "category":"Health Services",
            "subcategory":"Clinic",
            "type":"Services"
        }
    ],
    "sg:phone":"+1 541 344 8225",
    "sg:postcode":"97401",
    "sg:province":"OR",
    "sg:tags":[
        "physician",
        "surgeon",
        "osteopathic"
    ],
    "wof:name":"Lebow John R DO",
    "wof:placetype":"venue"
},
  "geometry": {"coordinates":[-123.067509,44.080849],"type":"Point"}
}