{
  "type": "Feature",
  "properties": {
    "iso:country":"US",
    "sg:address":"8180 SW Nimbus Ave",
    "sg:city":"Beaverton",
    "sg:classifiers":[
        {
            "category":"Wholesale",
            "subcategory":"Computers",
            "type":"Manufacturing & Wholesale Goods"
        }
    ],
    "sg:phone":"+1 503 626 9953",
    "sg:postcode":"97008",
    "sg:province":"OR",
    "wof:name":"Able Computer Systems Inc",
    "wof:placetype":"venue"
},
  "geometry": {"coordinates":[-122.78883999999999,45.460497],"type":"Point"}
}