{
  "type": "Feature",
  "properties": {
    "addr:full":"33679 E Progress Rd Hermiston OR 97838",
    "addr:housenumber":"33679",
    "addr:postcode":"97838",
    "addr:street":"E Progress Rd",
    "iso:country":"US",
    "sg:address":"33679 E Progress Rd",
    "sg:city":"Hermiston",
    "sg:classifiers":[
        {
            "category":"Home & Garden",
            "subcategory":"Home Furnishings",
            "type":"Retail Goods"
        }
    ],
    "sg:phone":"+1 541 567 5685",
    "sg:postcode":"97838",
    "sg:province":"OR",
    "sg:tags":[
        "kitchenware"
    ],
    "wof:name":"Elegant Kitchen",
    "wof:placetype":"venue"
},
  "geometry": {"coordinates":[-119.16891,45.893189],"type":"Point"}
}