{
  "type": "Feature",
  "properties": {
    "iso:country":"US",
    "sg:address":"2376 N Pacific Hwy",
    "sg:city":"Medford",
    "sg:classifiers":[
        {
            "category":"Retail",
            "subcategory":"Auto Repair",
            "type":"Services"
        }
    ],
    "sg:phone":"+1 541 770 5181",
    "sg:postcode":"97501",
    "sg:province":"OR",
    "sg:tags":[
        "body",
        "automobile",
        "painting"
    ],
    "wof:name":"Prestige Auto Body",
    "wof:placetype":"venue"
},
  "geometry": {"coordinates":[-122.88710399999999,42.347608],"type":"Point"}
}