{
  "type": "Feature",
  "properties": {
    "addr:full":"1485 Mill St SE Salem OR 97301",
    "addr:housenumber":"1485",
    "addr:postcode":"97301",
    "addr:street":"Mill St Se",
    "iso:country":"US",
    "sg:address":"1485 Mill St SE",
    "sg:city":"Salem",
    "sg:classifiers":[
        {
            "category":"Organizations",
            "subcategory":"Religious Organization",
            "type":"Services"
        }
    ],
    "sg:phone":"+1 503 362 7790",
    "sg:postcode":"97301",
    "sg:province":"OR",
    "sg:tags":[
        "church"
    ],
    "wof:name":"God's House United Pentecostal",
    "wof:placetype":"venue"
},
  "geometry": {"coordinates":[-123.025547,44.933399],"type":"Point"}
}