{
  "type": "Feature",
  "properties": {
    "addr:full":"2931 NE 34th Ave Portland OR 97212",
    "addr:housenumber":"2931",
    "addr:postcode":"97212",
    "addr:street":"Ne 34Th Ave",
    "iso:country":"US",
    "sg:address":"2931 NE 34th Ave",
    "sg:city":"Portland",
    "sg:classifiers":[
        {
            "category":"Building & Trades",
            "subcategory":"Locksmith",
            "type":"Services"
        }
    ],
    "sg:phone":"+1 503 715 3779",
    "sg:postcode":"97212",
    "sg:province":"OR",
    "sg:tags":[
        "key"
    ],
    "wof:name":"Citywide Locksmith",
    "wof:placetype":"venue"
},
  "geometry": {"coordinates":[-122.629856,45.543956],"type":"Point"}
}