{
  "type": "Feature",
  "properties": {
    "iso:country":"US",
    "sg:address":"99889 Winchuck River Rd",
    "sg:city":"Brookings",
    "sg:classifiers":[
        {
            "category":"Manufacturing",
            "subcategory":"Toys & Sporting Goods",
            "type":"Manufacturing & Wholesale Goods"
        }
    ],
    "sg:phone":"+1 541 469 2316",
    "sg:postcode":"97415",
    "sg:province":"OR",
    "sg:tags":[
        "athletic"
    ],
    "wof:name":"Good Stuff",
    "wof:placetype":"venue"
},
  "geometry": {"coordinates":[-124.181787,42.024893],"type":"Point"}
}