{
  "type": "Feature",
  "properties": {
    "iso:country":"US",
    "sg:address":"4370 NE Halsey St",
    "sg:city":"Portland",
    "sg:classifiers":[
        {
            "category":"Professional",
            "subcategory":"Management & Consulting",
            "type":"Services"
        }
    ],
    "sg:phone":"+1 503 280 8751",
    "sg:postcode":"97213",
    "sg:province":"OR",
    "sg:tags":[
        "consultant",
        "business"
    ],
    "wof:name":"EOS Consulting",
    "wof:placetype":"venue"
},
  "geometry": {"coordinates":[-122.61697599999999,45.5337],"type":"Point"}
}