{
  "type": "Feature",
  "properties": {
    "iso:country":"US",
    "sg:address":"876 NE Hood St",
    "sg:city":"Hillsboro",
    "sg:classifiers":[
        {
            "category":"Home & Garden",
            "subcategory":"Building Materials",
            "type":"Retail Goods"
        },
        {
            "category":"Professional",
            "subcategory":"Printing & Photocopies",
            "type":"Services"
        },
        {
            "category":"Manufacturing",
            "subcategory":"Building Materials",
            "type":"Manufacturing & Wholesale Goods"
        },
        {
            "category":"Building & Trades",
            "subcategory":"Locksmith",
            "type":"Services"
        }
    ],
    "sg:phone":"+1 503 640 6084",
    "sg:postcode":"97124",
    "sg:province":"OR",
    "sg:tags":[
        "repair",
        "industrial-sales",
        "door",
        "garage",
        "doors-commercial",
        "opener",
        "device",
        "door-overhead",
        "type",
        "doors-operating"
    ],
    "sg:website":"http://www.geniepro.com",
    "wof:name":"Muhly's Garage Doors",
    "wof:placetype":"venue"
},
  "geometry": {"coordinates":[-122.976197,45.535061],"type":"Point"}
}