{
  "type": "Feature",
  "properties": {
    "iso:country":"US",
    "sg:address":"12370 SW 1st St",
    "sg:city":"Beaverton",
    "sg:classifiers":[
        {
            "category":"Health Services",
            "subcategory":"Optometrist",
            "type":"Services"
        }
    ],
    "sg:phone":"+1 503 644 3614",
    "sg:postcode":"97005",
    "sg:province":"OR",
    "wof:name":"McBride David R Optmtrst",
    "wof:placetype":"venue"
},
  "geometry": {"coordinates":[-122.804001,45.486301],"type":"Point"}
}