{
  "type": "Feature",
  "properties": {
    "iso:country":"US",
    "sg:address":"3620 Hayden Bridge Rd",
    "sg:city":"Springfield",
    "sg:classifiers":[
        {
            "category":"Building & Trades",
            "subcategory":"Construction",
            "type":"Services"
        }
    ],
    "sg:phone":"+1 541 726 8693",
    "sg:postcode":"97477",
    "sg:province":"OR",
    "sg:tags":[
        "layer",
        "carpet"
    ],
    "wof:name":"Burgess Carpet Svc",
    "wof:placetype":"venue"
},
  "geometry": {"coordinates":[-122.973215,44.07607],"type":"Point"}
}