{
  "type": "Feature",
  "properties": {
    "iso:country":"US",
    "sg:address":"160 S Sunshine Ln",
    "sg:city":"West Linn",
    "sg:classifiers":[
        {
            "category":"Professional",
            "subcategory":"Business Services",
            "type":"Services"
        }
    ],
    "sg:phone":"+1 503 656 1113",
    "sg:postcode":"97068",
    "sg:province":"OR",
    "wof:name":"Lb Enterprises",
    "wof:placetype":"venue"
},
  "geometry": {"coordinates":[-122.672085,45.382234],"type":"Point"}
}