{
  "type": "Feature",
  "properties": {
    "iso:country":"US",
    "sg:address":"7397 SW Bridgeport Rd",
    "sg:city":"Portland",
    "sg:classifiers":[
        {
            "category":"Shopping",
            "subcategory":"Clothing, Apparel, & Fashions",
            "type":"Retail Goods"
        }
    ],
    "sg:phone":"+1 503 598 7414",
    "sg:postcode":"97224",
    "sg:province":"OR",
    "sg:tags":[
        "apparel",
        "clothing",
        "boys'",
        "store",
        "women's"
    ],
    "sg:website":"http://Jcrew.com",
    "wof:name":"J. Crew Inc.",
    "wof:placetype":"venue"
},
  "geometry": {"coordinates":[-122.752342,45.394567],"type":"Point"}
}