{
  "type": "Feature",
  "properties": {
    "addr:full":"4225 NE Cully Blvd Portland OR 97218",
    "addr:housenumber":"4225",
    "addr:postcode":"97218",
    "addr:street":"Ne Cully Blvd",
    "iso:country":"US",
    "sg:address":"4225 NE Cully Blvd",
    "sg:city":"Portland",
    "sg:classifiers":[
        {
            "category":"Retail",
            "subcategory":"Auto Repair",
            "type":"Services"
        }
    ],
    "sg:phone":"+1 503 281 2711",
    "sg:postcode":"97218",
    "sg:province":"OR",
    "sg:tags":[
        "body",
        "automobile",
        "painting",
        "repairing"
    ],
    "wof:name":"Blue Ribbon Auto Body Inc",
    "wof:placetype":"venue"
},
  "geometry": {"coordinates":[-122.60263999999999,45.553356],"type":"Point"}
}