{
  "type": "Feature",
  "properties": {
    "iso:country":"US",
    "sg:address":"5114 SW Scholls Ferry Rd",
    "sg:city":"Portland",
    "sg:phone":"+1 503 292 2095",
    "sg:postcode":"97225",
    "sg:province":"OR",
    "sg:website":"http://www.raleighschollsapts.com",
    "wof:name":"Raleigh Scholls Apartments",
    "wof:placetype":"venue"
},
  "geometry": {"coordinates":[-122.755658,45.483051],"type":"Point"}
}