{
  "type": "Feature",
  "properties": {
    "iso:country":"US",
    "sg:address":"10431 Blackwell Rd",
    "sg:city":"Central Point",
    "sg:classifiers":[
        {
            "category":"Communications",
            "type":"Services"
        }
    ],
    "sg:phone":"+1 541 855 7484",
    "sg:postcode":"97502",
    "sg:province":"OR",
    "sg:tags":[
        "recording",
        "rehearsal",
        "studio"
    ],
    "sg:website":"www.phylcoaudio.com",
    "wof:name":"Phylco Audio Duplication",
    "wof:placetype":"venue"
},
  "geometry": {"coordinates":[-123.010745,42.418414],"type":"Point"}
}