{
  "type": "Feature",
  "properties": {
    "iso:country":"US",
    "sg:address":"254 NE Wilcox St",
    "sg:city":"Hillsboro",
    "sg:classifiers":[
        {
            "category":"Professional",
            "subcategory":"Management & Consulting",
            "type":"Services"
        }
    ],
    "sg:phone":"+1 503 693 4685",
    "sg:postcode":"97124",
    "sg:province":"OR",
    "sg:tags":[
        "employee",
        "counseling"
    ],
    "wof:name":"Concera Corporation",
    "wof:placetype":"venue"
},
  "geometry": {"coordinates":[-122.99119,45.549285],"type":"Point"}
}