{
  "type": "Feature",
  "properties": {
    "addr:full":"5298 Nonpareil Rd Sutherlin OR 97479",
    "addr:housenumber":"5298",
    "addr:postcode":"97479",
    "addr:street":"Nonpareil Rd",
    "iso:country":"US",
    "sg:address":"5298 Nonpareil Rd",
    "sg:city":"Sutherlin",
    "sg:classifiers":[
        {
            "category":"Professional",
            "type":"Services"
        }
    ],
    "sg:phone":"+1 541 459 6067",
    "sg:postcode":"97479",
    "sg:province":"OR",
    "wof:name":"Dale Eugene Yarbrough",
    "wof:placetype":"venue"
},
  "geometry": {"coordinates":[-123.228616,43.410816],"type":"Point"}
}