{
  "type": "Feature",
  "properties": {
    "iso:country":"US",
    "sg:address":"525 NE Revere Ave",
    "sg:city":"Bend",
    "sg:classifiers":[
        {
            "category":"Wholesale",
            "subcategory":"Books, Periodicals, & Newspapers",
            "type":"Manufacturing & Wholesale Goods"
        }
    ],
    "sg:phone":"+1 541 382 2728",
    "sg:postcode":"97701",
    "sg:province":"OR",
    "sg:tags":[
        "dealer"
    ],
    "wof:name":"Maverick Distributors",
    "wof:placetype":"venue"
},
  "geometry": {"coordinates":[-121.298565,44.067573],"type":"Point"}
}