{
  "type": "Feature",
  "properties": {
    "addr:full":"468 W Arlington St Gladstone OR 97027",
    "addr:housenumber":"468",
    "addr:postcode":"97027",
    "addr:street":"W Arlington St",
    "iso:country":"US",
    "sg:address":"468 W Arlington St",
    "sg:city":"Gladstone",
    "sg:classifiers":[
        {
            "category":"Building & Trades",
            "subcategory":"Construction",
            "type":"Services"
        }
    ],
    "sg:phone":"+1 503 557 7013",
    "sg:postcode":"97027",
    "sg:province":"OR",
    "sg:tags":[
        "woodworker"
    ],
    "wof:name":"Hammerhead Woodworking",
    "wof:placetype":"venue"
},
  "geometry": {"coordinates":[-122.60158800000001,45.375739],"type":"Point"}
}