{
  "type": "Feature",
  "properties": {
    "iso:country":"US",
    "sg:address":"906 Lloyd Center",
    "sg:city":"Portland",
    "sg:classifiers":[
        {
            "category":"Shopping",
            "subcategory":"Mobile Phones",
            "type":"Retail Goods"
        }
    ],
    "sg:phone":"+1 503 331 0470",
    "sg:postcode":"97232",
    "sg:province":"OR",
    "sg:website":"www.activatecellular.com",
    "wof:name":"Activate Cellular Sales",
    "wof:placetype":"venue"
},
  "geometry": {"coordinates":[-122.65441,45.531509],"type":"Point"}
}