{
  "type": "Feature",
  "properties": {
    "iso:country":"US",
    "sg:address":"1717 NE Alberta St",
    "sg:city":"Portland",
    "sg:classifiers":[
        {
            "category":"Organizations",
            "subcategory":"Religious Organization",
            "type":"Services"
        }
    ],
    "sg:phone":"+1 503 287 9567",
    "sg:postcode":"97211",
    "sg:province":"OR",
    "sg:tags":[
        "church"
    ],
    "wof:name":"Highland United Chr Of Christ",
    "wof:placetype":"venue"
},
  "geometry": {"coordinates":[-122.646896,45.559155],"type":"Point"}
}