{
  "type": "Feature",
  "properties": {
    "iso:country":"US",
    "sg:address":"1644 NE Eastwood Dr",
    "sg:city":"Bend",
    "sg:classifiers":[
        {
            "category":"Shopping",
            "subcategory":"Clothing, Apparel, & Fashions",
            "type":"Retail Goods"
        }
    ],
    "sg:phone":"+1 541 383 8009",
    "sg:postcode":"97701",
    "sg:province":"OR",
    "sg:tags":[
        "apparel",
        "women's"
    ],
    "wof:name":"Voila Fashions",
    "wof:placetype":"venue"
},
  "geometry": {"coordinates":[-121.28218699999999,44.066563],"type":"Point"}
}