{
  "type": "Feature",
  "properties": {
    "iso:country":"US",
    "sg:address":"463 W Pine St",
    "sg:city":"Central Point",
    "sg:classifiers":[
        {
            "category":"Retail",
            "subcategory":"Repair Shop",
            "type":"Services"
        }
    ],
    "sg:phone":"+1 541 664 8135",
    "sg:postcode":"97502",
    "sg:province":"OR",
    "sg:tags":[
        "welding"
    ],
    "wof:name":"Gudzan Welding & Repair",
    "wof:placetype":"venue"
},
  "geometry": {"coordinates":[-122.924545,42.370382],"type":"Point"}
}