{
  "type": "Feature",
  "properties": {
    "addr:full":"1581 NE 156th Ave Portland OR 97230",
    "addr:housenumber":"1581",
    "addr:postcode":"97230",
    "addr:street":"Ne 156Th Ave",
    "iso:country":"US",
    "sg:address":"1581 NE 156th Ave",
    "sg:city":"Portland",
    "sg:classifiers":[
        {
            "category":"Shopping",
            "subcategory":"Gifts & Souvenirs",
            "type":"Retail Goods"
        }
    ],
    "sg:phone":"+1 503 262 6996",
    "sg:postcode":"97230",
    "sg:province":"OR",
    "wof:name":"Looneyjunies",
    "wof:placetype":"venue"
},
  "geometry": {"coordinates":[-122.502582,45.536138],"type":"Point"}
}