{
  "type": "Feature",
  "properties": {
    "addr:full":"3990 NE 2nd St Gresham OR 97030",
    "addr:housenumber":"3990",
    "addr:postcode":"97030",
    "addr:street":"Ne 2Nd St",
    "iso:country":"US",
    "sg:address":"3990 NE 2nd St",
    "sg:city":"Gresham",
    "sg:classifiers":[
        {
            "category":"Building & Trades",
            "subcategory":"Construction",
            "type":"Services"
        }
    ],
    "sg:phone":"+1 503 665 5289",
    "sg:postcode":"97030",
    "sg:province":"OR",
    "sg:tags":[
        "house"
    ],
    "wof:name":"Jpb Construction LLC",
    "wof:placetype":"venue"
},
  "geometry": {"coordinates":[-122.39125,45.498366],"type":"Point"}
}