{
  "type": "Feature",
  "properties": {
    "addr:full":"7717 SE Lincoln St Portland OR 97215",
    "addr:housenumber":"7717",
    "addr:postcode":"97215",
    "addr:street":"Se Lincoln St",
    "iso:country":"US",
    "sg:address":"7717 SE Lincoln St",
    "sg:city":"Portland",
    "sg:classifiers":[
        {
            "category":"Banks & Credit Unions",
            "subcategory":"Financial Services",
            "type":"Services"
        }
    ],
    "sg:phone":"+1 503 771 0009",
    "sg:postcode":"97215",
    "sg:province":"OR",
    "sg:tags":[
        "management",
        "investment"
    ],
    "wof:name":"Als Investment Company",
    "wof:placetype":"venue"
},
  "geometry": {"coordinates":[-122.58357599999999,45.507881],"type":"Point"}
}