{
  "type": "Feature",
  "properties": {
    "iso:country":"US",
    "sg:address":"830 Lawnsdale Rd",
    "sg:city":"Medford",
    "sg:classifiers":[
        {
            "category":"Freight",
            "type":"Transportation"
        }
    ],
    "sg:phone":"+1 541 772 7257",
    "sg:postcode":"97504",
    "sg:province":"OR",
    "sg:tags":[
        "broker",
        "trucking"
    ],
    "wof:name":"Premier Freight Corp",
    "wof:placetype":"venue"
},
  "geometry": {"coordinates":[-122.878243,42.363367],"type":"Point"}
}