{
  "type": "Feature",
  "properties": {
    "addr:full":"6135 NE 80th Ave Portland OR 97218",
    "addr:housenumber":"6135",
    "addr:postcode":"97218",
    "addr:street":"Ne 80Th Ave",
    "iso:country":"US",
    "sg:address":"6135 NE 80th Ave",
    "sg:city":"Portland",
    "sg:classifiers":[
        {
            "category":"Banks & Credit Unions",
            "subcategory":"Bank",
            "type":"Services"
        }
    ],
    "sg:phone":"+1 503 253 8302",
    "sg:postcode":"97218",
    "sg:province":"OR",
    "sg:tags":[
        "financing"
    ],
    "wof:name":"Mercedes-Benz Credit Corp",
    "wof:placetype":"venue"
},
  "geometry": {"coordinates":[-122.580541,45.566081],"type":"Point"}
}