{
  "type": "Feature",
  "properties": {
    "addr:full":"380 N Central St Coquille OR 97423",
    "addr:housenumber":"380",
    "addr:postcode":"97423",
    "addr:street":"N Central St",
    "iso:country":"US",
    "sg:address":"380 N Central St",
    "sg:city":"Coquille",
    "sg:classifiers":[
        {
            "category":"Government",
            "subcategory":"Office",
            "type":"Public Place"
        }
    ],
    "sg:phone":"+1 541 396 4323",
    "sg:postcode":"97423",
    "sg:province":"OR",
    "sg:tags":[
        "federal"
    ],
    "wof:name":"US Consolidated Farm Svc Agcy",
    "wof:placetype":"venue"
},
  "geometry": {"coordinates":[-124.188926,43.177153],"type":"Point"}
}