{
  "type": "Feature",
  "properties": {
    "addr:full":"1566 Coburg Rd Eugene OR 97401",
    "addr:housenumber":"1566",
    "addr:postcode":"97401",
    "addr:street":"Coburg Rd",
    "iso:country":"US",
    "sg:address":"1566 Coburg Rd",
    "sg:city":"Eugene",
    "sg:classifiers":[
        {
            "category":"Food & Beverages",
            "subcategory":"Bakery",
            "type":"Retail Goods"
        }
    ],
    "sg:phone":"+1 541 687 1179",
    "sg:postcode":"97401",
    "sg:province":"OR",
    "sg:tags":[
        "product"
    ],
    "wof:name":"Humble Bagel Co Inc",
    "wof:placetype":"venue"
},
  "geometry": {"coordinates":[-123.06916,44.077913],"type":"Point"}
}