{
  "type": "Feature",
  "properties": {
    "addr:full":"10180 SW Nimbus Ave Portland OR 97223",
    "addr:housenumber":"10180",
    "addr:postcode":"97223",
    "addr:street":"Sw Nimbus Ave",
    "iso:country":"US",
    "sg:address":"10180 SW Nimbus Ave",
    "sg:city":"Portland",
    "sg:classifiers":[
        {
            "category":"Professional",
            "subcategory":"Management & Consulting",
            "type":"Services"
        }
    ],
    "sg:phone":"+1 503 624 5750",
    "sg:postcode":"97223",
    "sg:province":"OR",
    "sg:tags":[
        "environmental",
        "research"
    ],
    "wof:name":"Cooper Environmental Svcs LLC",
    "wof:placetype":"venue"
},
  "geometry": {"coordinates":[-122.789451,45.447099],"type":"Point"}
}