{
  "type": "Feature",
  "properties": {
    "addr:full":"838 SW 4th Ave Portland OR 97204",
    "addr:housenumber":"838",
    "addr:postcode":"97204",
    "addr:street":"Sw 4Th Ave",
    "iso:country":"US",
    "sg:address":"838 SW 4th Ave",
    "sg:city":"Portland",
    "sg:classifiers":[
        {
            "category":"Food & Beverages",
            "subcategory":"Specialty",
            "type":"Retail Goods"
        }
    ],
    "sg:phone":"+1 503 222 0996",
    "sg:postcode":"97204",
    "sg:province":"OR",
    "sg:tags":[
        "vitamin"
    ],
    "wof:name":"Vitamin Shoppe",
    "wof:placetype":"venue"
},
  "geometry": {"coordinates":[-122.67690399999999,45.517808],"type":"Point"}
}