{
  "type": "Feature",
  "properties": {
    "iso:country":"US",
    "sg:address":"1500 SW 1st Ave",
    "sg:city":"Portland",
    "sg:classifiers":[
        {
            "category":"Real Estate",
            "subcategory":"Developer",
            "type":"Services"
        }
    ],
    "sg:phone":"+1 503 916 8963",
    "sg:postcode":"97201",
    "sg:province":"OR",
    "sg:website":"http://www.opuscorp.com",
    "wof:name":"Opus National",
    "wof:placetype":"venue"
},
  "geometry": {"coordinates":[-122.676483,45.512402],"type":"Point"}
}