{
  "type": "Feature",
  "properties": {
    "addr:full":"11533 SW Hall Boulevard Portland OR 97223",
    "addr:housenumber":"11533",
    "addr:postcode":"97223",
    "addr:street":"Sw Hall Boulevard",
    "iso:country":"US",
    "sg:address":"11533 SW Hall Boulevard",
    "sg:city":"Portland",
    "sg:classifiers":[
        {
            "category":"Social Services",
            "subcategory":"Child Care",
            "type":"Services"
        },
        {
            "category":"Education",
            "subcategory":"Preschool",
            "type":"Public Place"
        },
        {
            "category":"Education",
            "subcategory":"School",
            "type":"Public Place"
        }
    ],
    "sg:phone":"+1 503 639 8530",
    "sg:postcode":"97223",
    "sg:province":"OR",
    "sg:tags":[
        "elementary",
        "day"
    ],
    "wof:name":"Kindercare Learning Centers",
    "wof:placetype":"venue"
},
  "geometry": {"coordinates":[-122.765162,45.43595],"type":"Point"}
}