{
  "type": "Feature",
  "properties": {
    "addr:full":"29323 SW Ladd Hill Rd Sherwood OR 97140",
    "addr:housenumber":"29323",
    "addr:postcode":"97140",
    "addr:street":"Sw Ladd Hill Rd",
    "iso:country":"US",
    "sg:address":"29323 SW Ladd Hill Rd",
    "sg:city":"Sherwood",
    "sg:classifiers":[
        {
            "category":"Farming",
            "subcategory":"Livestock Farm",
            "type":"Manufacturing & Wholesale Goods"
        }
    ],
    "sg:phone":"+1 503 625 6691",
    "sg:postcode":"97140",
    "sg:province":"OR",
    "wof:name":"Northwest Shropshire Breeders",
    "wof:placetype":"venue"
},
  "geometry": {"coordinates":[-122.83966599999999,45.307246],"type":"Point"}
}