{
  "type": "Feature",
  "properties": {
    "iso:country":"US",
    "sg:address":"18823 Roundtree Dr",
    "sg:city":"Oregon City",
    "sg:classifiers":[
        {
            "category":"Home & Garden",
            "subcategory":"Building Materials",
            "type":"Retail Goods"
        }
    ],
    "sg:phone":"+1 503 656 9920",
    "sg:postcode":"97045",
    "sg:province":"OR",
    "sg:tags":[
        "glass",
        "window",
        "plate"
    ],
    "wof:name":"Delta Auto Glass",
    "wof:placetype":"venue"
},
  "geometry": {"coordinates":[-122.61051399999999,45.332969],"type":"Point"}
}