{
  "type": "Feature",
  "properties": {
    "addr:full":"421 SW 6th Ave Portland OR 97204",
    "addr:housenumber":"421",
    "addr:postcode":"97204",
    "addr:street":"Sw 6Th Ave",
    "iso:country":"US",
    "sg:address":"421 SW 6th Ave",
    "sg:city":"Portland",
    "sg:classifiers":[
        {
            "category":"Real Estate",
            "subcategory":"Architect",
            "type":"Services"
        }
    ],
    "sg:phone":"+1 503 473 8477",
    "sg:postcode":"97204",
    "sg:province":"OR",
    "sg:tags":[
        "engineering",
        "architectural"
    ],
    "wof:name":"Bratslvsky Cnsulting Engineers",
    "wof:placetype":"venue"
},
  "geometry": {"coordinates":[-122.677897,45.520569],"type":"Point"}
}