{
  "type": "Feature",
  "properties": {
    "iso:country":"US",
    "sg:address":"7718 SE 13th Avenue",
    "sg:city":"Portland",
    "sg:classifiers":[
        {
            "category":"Home & Garden",
            "subcategory":"Furniture",
            "type":"Retail Goods"
        }
    ],
    "sg:phone":"+1 503 231 5508",
    "sg:postcode":"97202",
    "sg:province":"OR",
    "sg:tags":[
        "store"
    ],
    "wof:name":"Southern Accents Home Gallery",
    "wof:placetype":"venue"
},
  "geometry": {"coordinates":[-122.65315200000001,45.469076],"type":"Point"}
}