{
  "type": "Feature",
  "properties": {
    "iso:country":"US",
    "sg:address":"16325 Boones Ferry Rd Ste 201",
    "sg:city":"Lake Oswego",
    "sg:classifiers":[
        {
            "category":"Insurance",
            "subcategory":"Hazard Insurance",
            "type":"Services"
        }
    ],
    "sg:phone":"+1 503 636 2112",
    "sg:postcode":"97035",
    "sg:province":"OR",
    "sg:website":"www.dibroker.com",
    "wof:name":"Dibroker",
    "wof:placetype":"venue"
},
  "geometry": {"coordinates":[-122.724013,45.408314],"type":"Point"}
}