{
  "type": "Feature",
  "properties": {
    "iso:country":"US",
    "sg:address":"519 S 5th St",
    "sg:city":"Jefferson",
    "sg:classifiers":[
        {
            "category":"Professional",
            "subcategory":"Business Services",
            "type":"Services"
        }
    ],
    "sg:phone":"+1 541 327 8358",
    "sg:postcode":"97352",
    "sg:province":"OR",
    "wof:name":"Kq Enterprises",
    "wof:placetype":"venue"
},
  "geometry": {"coordinates":[-123.00499499999999,44.712659],"type":"Point"}
}