{
  "type": "Feature",
  "properties": {
    "iso:country":"US",
    "sg:address":"201 Ingram Dr",
    "sg:city":"Roseburg",
    "sg:classifiers":[
        {
            "category":"Wholesale",
            "subcategory":"Books, Periodicals, & Newspapers",
            "type":"Manufacturing & Wholesale Goods"
        }
    ],
    "sg:phone":"+1 541 679 3779",
    "sg:postcode":"97470",
    "sg:province":"OR",
    "sg:tags":[
        "distribution"
    ],
    "wof:name":"AmazonCom",
    "wof:placetype":"venue"
},
  "geometry": {"coordinates":[-123.36214,43.159112],"type":"Point"}
}