{
  "type": "Feature",
  "properties": {
    "iso:country":"US",
    "sg:address":"73188 London Rd",
    "sg:city":"Cottage Grove",
    "sg:classifiers":[
        {
            "category":"Autos & Motor Vehicles",
            "subcategory":"Automobile Sales",
            "type":"Retail Goods"
        }
    ],
    "sg:phone":"+1 541 746 8181",
    "sg:postcode":"97424",
    "sg:province":"OR",
    "sg:tags":[
        "car",
        "dealer"
    ],
    "wof:name":"Affordable Auto Credit Inc",
    "wof:placetype":"venue"
},
  "geometry": {"coordinates":[-123.084429,43.645126],"type":"Point"}
}