{
  "type": "Feature",
  "properties": {
    "iso:country":"US",
    "sg:address":"2535 Jorie Ln NE",
    "sg:city":"Salem",
    "sg:classifiers":[
        {
            "category":"Fast Food",
            "type":"Food & Drink"
        },
        {
            "category":"Restaurant",
            "type":"Food & Drink"
        },
        {
            "category":"Food & Beverages",
            "subcategory":"Groceries & Convenience Stores",
            "type":"Retail Goods"
        }
    ],
    "sg:phone":"+1 503 485 0341",
    "sg:postcode":"97303",
    "sg:province":"OR",
    "sg:tags":[
        "shop",
        "american",
        "sandwich",
        "take"
    ],
    "sg:website":"http://www.subway.com",
    "wof:name":"Subway",
    "wof:placetype":"venue"
},
  "geometry": {"coordinates":[-123.00054900000001,45.007191],"type":"Point"}
}