{
  "type": "Feature",
  "properties": {
    "iso:country":"US",
    "sg:address":"61906 Dufur Gap Rd",
    "sg:city":"Dufur",
    "sg:classifiers":[
        {
            "category":"Travel",
            "subcategory":"Campground",
            "type":"Entertainment"
        }
    ],
    "sg:phone":"+1 541 467 2415",
    "sg:postcode":"97021",
    "sg:province":"OR",
    "sg:tags":[
        "ranch"
    ],
    "wof:name":"Half Circle F Ranch",
    "wof:placetype":"venue"
},
  "geometry": {"coordinates":[-121.155413,45.388315],"type":"Point"}
}