{
  "type": "Feature",
  "properties": {
    "addr:full":"810 E 29th Ave Eugene OR 97405",
    "addr:housenumber":"810",
    "addr:postcode":"97405",
    "addr:street":"E 29Th Ave",
    "iso:country":"US",
    "sg:address":"810 E 29th Ave",
    "sg:city":"Eugene",
    "sg:classifiers":[
        {
            "category":"Shopping",
            "subcategory":"Computers & Home Electronics",
            "type":"Retail Goods"
        }
    ],
    "sg:phone":"+1 541 302 3297",
    "sg:postcode":"97405",
    "sg:province":"OR",
    "sg:tags":[
        "software"
    ],
    "sg:website":"www.inventoryanalyst.com",
    "wof:name":"Logictools Inc",
    "wof:placetype":"venue"
},
  "geometry": {"coordinates":[-123.079869,44.025591],"type":"Point"}
}