{
  "type": "Feature",
  "properties": {
    "addr:full":"9236 SW Beaverton Hillsdale Hwy Beaverton OR 97005",
    "addr:housenumber":"9236",
    "addr:postcode":"97005",
    "addr:street":"Sw Beaverton Hillsdale Hwy",
    "iso:country":"US",
    "sg:address":"9236 SW Beaverton Hillsdale Hwy",
    "sg:city":"Beaverton",
    "sg:classifiers":[
        {
            "category":"Retail",
            "subcategory":"Laundry & Dry Cleaning",
            "type":"Services"
        }
    ],
    "sg:phone":"+1 503 292 8017",
    "sg:postcode":"97005",
    "sg:province":"OR",
    "sg:tags":[
        "operated",
        "dryer",
        "laundries-self",
        "washer",
        "coin"
    ],
    "wof:name":"Country Club Cleaners & Laundromat",
    "wof:placetype":"venue"
},
  "geometry": {"coordinates":[-122.77204999999999,45.486424],"type":"Point"}
}