{
  "type": "Feature",
  "properties": {
    "addr:full":"1904 NE Alberta St Portland OR 97211",
    "addr:housenumber":"1904",
    "addr:postcode":"97211",
    "addr:street":"Ne Alberta St",
    "iso:country":"US",
    "sg:address":"1904 NE Alberta St",
    "sg:city":"Portland",
    "sg:classifiers":[
        {
            "category":"Restaurant",
            "type":"Food & Drink"
        }
    ],
    "sg:phone":"+1 503 753 0868",
    "sg:postcode":"97211",
    "sg:province":"OR",
    "sg:tags":[
        "barbeque"
    ],
    "wof:name":"Dixon's Rib Pit",
    "wof:placetype":"venue"
},
  "geometry": {"coordinates":[-122.64552,45.558861],"type":"Point"}
}