{
  "type": "Feature",
  "properties": {
    "addr:full":"1044 Lancaster Dr NE Salem OR 97301",
    "addr:housenumber":"1044",
    "addr:postcode":"97301",
    "addr:street":"Lancaster Dr Ne",
    "iso:country":"US",
    "sg:address":"1044 Lancaster Dr NE",
    "sg:city":"Salem",
    "sg:classifiers":[
        {
            "category":"Personal",
            "subcategory":"Beauty Salon",
            "type":"Services"
        }
    ],
    "sg:phone":"+1 503 581 1776",
    "sg:postcode":"97301",
    "sg:province":"OR",
    "sg:tags":[
        "shop",
        "manicuring"
    ],
    "wof:name":"Van's Nail & Skin Care",
    "wof:placetype":"venue"
},
  "geometry": {"coordinates":[-122.983362,44.943873],"type":"Point"}
}