{
  "type": "Feature",
  "properties": {
    "addr:full":"9168 Silver Falls Hwy SE Aumsville OR 97325",
    "addr:housenumber":"9168",
    "addr:postcode":"97325",
    "addr:street":"Silver Falls Hwy Se",
    "iso:country":"US",
    "sg:address":"9168 Silver Falls Hwy SE",
    "sg:city":"Aumsville",
    "sg:classifiers":[
        {
            "category":"Organizations",
            "subcategory":"Religious Organization",
            "type":"Services"
        }
    ],
    "sg:phone":"+1 503 362 6159",
    "sg:postcode":"97325",
    "sg:province":"OR",
    "sg:tags":[
        "church"
    ],
    "wof:name":"St Mary's Catholic Church",
    "wof:placetype":"venue"
},
  "geometry": {"coordinates":[-122.873311,44.872836],"type":"Point"}
}