{
  "type": "Feature",
  "properties": {
    "iso:country":"US",
    "sg:address":"905 Main St",
    "sg:city":"Klamath Falls",
    "sg:classifiers":[
        {
            "category":"Personal",
            "type":"Services"
        },
        {
            "category":"Personal",
            "subcategory":"Beauty Salon",
            "type":"Services"
        }
    ],
    "sg:phone":"+1 541 883 4050",
    "sg:postcode":"97601",
    "sg:province":"OR",
    "sg:tags":[
        "shop",
        "electrolysis"
    ],
    "wof:name":"Electrolysis By Karen",
    "wof:placetype":"venue"
},
  "geometry": {"coordinates":[-121.779993,42.227043],"type":"Point"}
}