{
  "type": "Feature",
  "properties": {
    "addr:full":"7163 Conifer St NE Salem OR 97317",
    "addr:housenumber":"7163",
    "addr:postcode":"97317",
    "addr:street":"Conifer St Ne",
    "iso:country":"US",
    "sg:address":"7163 Conifer St NE",
    "sg:city":"Salem",
    "sg:classifiers":[
        {
            "category":"Travel",
            "subcategory":"Hotels & Motels",
            "type":"Entertainment"
        }
    ],
    "sg:phone":"+1 503 585 9028",
    "sg:postcode":"97317",
    "sg:province":"OR",
    "sg:tags":[
        "operation"
    ],
    "wof:name":"Cat Cottages",
    "wof:placetype":"venue"
},
  "geometry": {"coordinates":[-122.913679,44.945184],"type":"Point"}
}