{
  "type": "Feature",
  "properties": {
    "iso:country":"US",
    "sg:address":"10011 SE Division St",
    "sg:city":"Portland",
    "sg:classifiers":[
        {
            "category":"Professional",
            "subcategory":"Detective & Security Services",
            "type":"Services"
        }
    ],
    "sg:phone":"+1 503 252 9535",
    "sg:postcode":"97266",
    "sg:province":"OR",
    "sg:tags":[
        "car"
    ],
    "wof:name":"Rovers Security",
    "wof:placetype":"venue"
},
  "geometry": {"coordinates":[-122.559972,45.504417],"type":"Point"}
}