{
  "type": "Feature",
  "properties": {
    "iso:country":"US",
    "sg:address":"14573 Evans Valley Rd NE",
    "sg:city":"Silverton",
    "sg:classifiers":[
        {
            "category":"Manufacturing",
            "subcategory":"Metals",
            "type":"Manufacturing & Wholesale Goods"
        }
    ],
    "sg:phone":"+1 503 873 3112",
    "sg:postcode":"97381",
    "sg:province":"OR",
    "sg:tags":[
        "mfg",
        "tool",
        "edge",
        "hand"
    ],
    "sg:website":"www.bitsbits.com",
    "wof:name":"Bits & Bits Co",
    "wof:placetype":"venue"
},
  "geometry": {"coordinates":[-122.763058,45.004005],"type":"Point"}
}