{
  "type": "Feature",
  "properties": {
    "addr:full":"1650 US Hwy 101 Brookings OR 97415",
    "addr:housenumber":"1650",
    "addr:postcode":"97415",
    "addr:street":"Us Hwy 101",
    "iso:country":"US",
    "sg:address":"1650 US Hwy 101",
    "sg:city":"Brookings",
    "sg:classifiers":[
        {
            "category":"Professional",
            "subcategory":"Business Services",
            "type":"Services"
        }
    ],
    "sg:phone":"+1 541 469 4117",
    "sg:postcode":"97415",
    "sg:province":"OR",
    "wof:name":"Soobrookings Welcome Center",
    "wof:placetype":"venue"
},
  "geometry": {"coordinates":[-124.30086799999999,42.06138],"type":"Point"}
}