{
  "type": "Feature",
  "properties": {
    "iso:country":"US",
    "sg:address":"10 S Oakdale Ave",
    "sg:city":"Medford",
    "sg:classifiers":[
        {
            "category":"Government",
            "subcategory":"Office",
            "type":"Public Place"
        }
    ],
    "sg:phone":"+1 541 774 6541",
    "sg:postcode":"97501",
    "sg:province":"OR",
    "sg:tags":[
        "county",
        "taxation"
    ],
    "wof:name":"Jackson County Finance Dept",
    "wof:placetype":"venue"
},
  "geometry": {"coordinates":[-122.876014,42.321915],"type":"Point"}
}