{
  "type": "Feature",
  "properties": {
    "addr:full":"16280 NW Bethany Ct Beaverton OR 97006",
    "addr:housenumber":"16280",
    "addr:postcode":"97006",
    "addr:street":"Nw Bethany Ct",
    "iso:country":"US",
    "sg:address":"16280 NW Bethany Ct",
    "sg:city":"Beaverton",
    "sg:classifiers":[
        {
            "category":"Shopping",
            "subcategory":"Pets & Pet Supplies",
            "type":"Retail Goods"
        }
    ],
    "sg:phone":"+1 503 645 6800",
    "sg:postcode":"97006",
    "sg:province":"OR",
    "sg:tags":[
        "store"
    ],
    "wof:name":"Sage Unlimited",
    "wof:placetype":"venue"
},
  "geometry": {"coordinates":[-122.843412,45.529198],"type":"Point"}
}