{
  "type": "Feature",
  "properties": {
    "iso:country":"US",
    "sg:address":"22169 Nelson Rd",
    "sg:city":"Bend",
    "sg:classifiers":[
        {
            "category":"Building & Trades",
            "subcategory":"Construction",
            "type":"Services"
        }
    ],
    "sg:phone":"+1 541 382 0787",
    "sg:postcode":"97701",
    "sg:province":"OR",
    "sg:tags":[
        "excavation",
        "contractor"
    ],
    "wof:name":"Dan Thompson Excavation Inc",
    "wof:placetype":"venue"
},
  "geometry": {"coordinates":[-121.203399,44.087393],"type":"Point"}
}