{
  "type": "Feature",
  "properties": {
    "addr:full":"201 S Holladay Dr Seaside OR 97138",
    "addr:housenumber":"201",
    "addr:postcode":"97138",
    "addr:street":"S Holladay Dr",
    "iso:country":"US",
    "sg:address":"201 S Holladay Dr",
    "sg:city":"Seaside",
    "sg:classifiers":[
        {
            "category":"Shopping",
            "subcategory":"Used Merchandise",
            "type":"Retail Goods"
        }
    ],
    "sg:phone":"+1 503 717 1903",
    "sg:postcode":"97138",
    "sg:province":"OR",
    "sg:tags":[
        "shop",
        "thrift"
    ],
    "wof:name":"Restoration House Thrift Store",
    "wof:placetype":"venue"
},
  "geometry": {"coordinates":[-123.92312,45.992377],"type":"Point"}
}