{
  "type": "Feature",
  "properties": {
    "iso:country":"US",
    "sg:address":"10255 SW Park Way",
    "sg:city":"Portland",
    "sg:classifiers":[
        {
            "category":"Professional",
            "subcategory":"Accounting & Tax Preparation",
            "type":"Services"
        }
    ],
    "sg:phone":"+1 503 297 2610",
    "sg:postcode":"97225",
    "sg:province":"OR",
    "sg:tags":[
        "accountant"
    ],
    "wof:name":"Carl W Foster CPA",
    "wof:placetype":"venue"
},
  "geometry": {"coordinates":[-122.782298,45.508285],"type":"Point"}
}