{
  "type": "Feature",
  "properties": {
    "iso:country":"US",
    "sg:address":"106 Elm St",
    "sg:city":"La Grande",
    "sg:classifiers":[
        {
            "category":"Shopping",
            "subcategory":"Florist",
            "type":"Retail Goods"
        }
    ],
    "sg:phone":"+1 541 963 7191",
    "sg:postcode":"97850",
    "sg:province":"OR",
    "wof:name":"Cherry's Florists",
    "wof:placetype":"venue"
},
  "geometry": {"coordinates":[-118.093502,45.327958],"type":"Point"}
}