{
  "type": "Feature",
  "properties": {
    "iso:country":"US",
    "sg:address":"810 W 3rd Ave",
    "sg:city":"Eugene",
    "sg:classifiers":[
        {
            "category":"Organizations",
            "subcategory":"Religious Organization",
            "type":"Services"
        }
    ],
    "sg:phone":"+1 541 343 3190",
    "sg:postcode":"97402",
    "sg:province":"OR",
    "sg:tags":[
        "church"
    ],
    "wof:name":"New Life Apostolic Tabernacle",
    "wof:placetype":"venue"
},
  "geometry": {"coordinates":[-123.106314,44.056466],"type":"Point"}
}