{
  "type": "Feature",
  "properties": {
    "iso:country":"US",
    "sg:address":"1630 NE Halsey St",
    "sg:city":"Portland",
    "sg:classifiers":[
        {
            "category":"Education",
            "subcategory":"Special Training",
            "type":"Public Place"
        }
    ],
    "sg:phone":"+1 503 493 8424",
    "sg:postcode":"97232",
    "sg:province":"OR",
    "sg:tags":[
        "school",
        "care",
        "day",
        "language",
        "child"
    ],
    "wof:name":"Kids Like Languages",
    "wof:placetype":"venue"
},
  "geometry": {"coordinates":[-122.649152,45.533625],"type":"Point"}
}