{
  "type": "Feature",
  "properties": {
    "addr:full":"2319 Ranch Rd Ashland OR 97520",
    "addr:housenumber":"2319",
    "addr:postcode":"97520",
    "addr:street":"Ranch Rd",
    "iso:country":"US",
    "sg:address":"2319 Ranch Rd",
    "sg:city":"Ashland",
    "sg:classifiers":[
        {
            "category":"Retail",
            "subcategory":"Repair Shop",
            "type":"Services"
        }
    ],
    "sg:phone":"+1 541 482 8365",
    "sg:postcode":"97520",
    "sg:province":"OR",
    "wof:name":"Titus Technical Service",
    "wof:placetype":"venue"
},
  "geometry": {"coordinates":[-122.674995,42.169664],"type":"Point"}
}