{
  "type": "Feature",
  "properties": {
    "iso:country":"US",
    "sg:address":"17564 Blue Heron Ct",
    "sg:city":"Lake Oswego",
    "sg:classifiers":[
        {
            "category":"Shopping",
            "subcategory":"Computers & Home Electronics",
            "type":"Retail Goods"
        }
    ],
    "sg:phone":"+1 503 697 3698",
    "sg:postcode":"97034",
    "sg:province":"OR",
    "sg:tags":[
        "design",
        "system"
    ],
    "wof:name":"QCSL",
    "wof:placetype":"venue"
},
  "geometry": {"coordinates":[-122.712416,45.397583],"type":"Point"}
}