{
  "type": "Feature",
  "properties": {
    "addr:full":"3532 Chicago St SE Albany OR 97322",
    "addr:housenumber":"3532",
    "addr:postcode":"97322",
    "addr:street":"Chicago St Se",
    "iso:country":"US",
    "sg:address":"3532 Chicago St SE",
    "sg:city":"Albany",
    "sg:classifiers":[
        {
            "category":"Manufacturing",
            "subcategory":"Metals",
            "type":"Manufacturing & Wholesale Goods"
        }
    ],
    "sg:phone":"+1 541 926 6346",
    "sg:postcode":"97322",
    "sg:province":"OR",
    "sg:tags":[
        "blast",
        "furnace",
        "works"
    ],
    "wof:name":"Robs Rails",
    "wof:placetype":"venue"
},
  "geometry": {"coordinates":[-123.081328,44.609936],"type":"Point"}
}