{
  "type": "Feature",
  "properties": {
    "addr:full":"648 SW Sunwood Way Grants Pass OR 97526",
    "addr:housenumber":"648",
    "addr:postcode":"97526",
    "addr:street":"Sw Sunwood Way",
    "iso:country":"US",
    "sg:address":"648 SW Sunwood Way",
    "sg:city":"Grants Pass",
    "sg:classifiers":[
        {
            "category":"Professional",
            "subcategory":"Management & Consulting",
            "type":"Services"
        }
    ],
    "sg:phone":"+1 541 474 2165",
    "sg:postcode":"97526",
    "sg:province":"OR",
    "sg:tags":[
        "business"
    ],
    "wof:name":"Phoenix Equities LLC",
    "wof:placetype":"venue"
},
  "geometry": {"coordinates":[-123.346975,42.436076],"type":"Point"}
}