{
  "type": "Feature",
  "properties": {
    "iso:country":"US",
    "sg:address":"3275 NE Killingsworth Street",
    "sg:city":"Portland",
    "sg:classifiers":[
        {
            "category":"Food & Beverages",
            "subcategory":"Groceries & Convenience Stores",
            "type":"Retail Goods"
        }
    ],
    "sg:phone":"+1 503 281 8489",
    "sg:postcode":"97211",
    "sg:province":"OR",
    "wof:name":"J's Food Mart",
    "wof:placetype":"venue"
},
  "geometry": {"coordinates":[-122.630835,45.562828],"type":"Point"}
}