{
  "type": "Feature",
  "properties": {
    "iso:country":"US",
    "sg:address":"23 W 6th Ave",
    "sg:city":"Eugene",
    "sg:classifiers":[
        {
            "category":"Arts & Performance",
            "subcategory":"Theater",
            "type":"Entertainment"
        }
    ],
    "sg:phone":"+1 541 434 1111",
    "sg:postcode":"97401",
    "sg:province":"OR",
    "sg:tags":[
        "live",
        "music"
    ],
    "wof:name":"Annex",
    "wof:placetype":"venue"
},
  "geometry": {"coordinates":[-123.093975,44.05331],"type":"Point"}
}