{
  "type": "Feature",
  "properties": {
    "iso:country":"US",
    "sg:address":"1930 SE Monroe St",
    "sg:city":"Portland",
    "sg:classifiers":[
        {
            "category":"Wholesale",
            "subcategory":"Apparel",
            "type":"Manufacturing & Wholesale Goods"
        }
    ],
    "sg:phone":"+1 503 655 5769",
    "sg:postcode":"97222",
    "sg:province":"OR",
    "sg:tags":[
        "athletic",
        "screened",
        "silk",
        "clothing",
        "retail"
    ],
    "wof:name":"Four Seasons Screen Printing",
    "wof:placetype":"venue"
},
  "geometry": {"coordinates":[-122.641468,45.443908],"type":"Point"}
}