{
  "type": "Feature",
  "properties": {
    "addr:full":"11492 Buckhorn Rd Glide OR 97443",
    "addr:housenumber":"11492",
    "addr:postcode":"97443",
    "addr:street":"Buckhorn Rd",
    "iso:country":"US",
    "sg:address":"11492 Buckhorn Rd",
    "sg:city":"Glide",
    "sg:classifiers":[
        {
            "category":"Restaurant",
            "type":"Food & Drink"
        }
    ],
    "sg:phone":"+1 541 496 0134",
    "sg:postcode":"97443",
    "sg:province":"OR",
    "sg:tags":[
        "eating"
    ],
    "wof:name":"Van Slykes Beanery & Deli",
    "wof:placetype":"venue"
},
  "geometry": {"coordinates":[-123.10083400000001,43.259605],"type":"Point"}
}