{
  "type": "Feature",
  "properties": {
    "iso:country":"US",
    "sg:address":"3319 Carnes Rd",
    "sg:city":"Roseburg",
    "sg:classifiers":[
        {
            "category":"Professional",
            "subcategory":"Business Services",
            "type":"Services"
        }
    ],
    "sg:phone":"+1 541 784 0123",
    "sg:postcode":"97470",
    "sg:province":"OR",
    "sg:tags":[
        "auctioneer"
    ],
    "wof:name":"Green Auction",
    "wof:placetype":"venue"
},
  "geometry": {"coordinates":[-123.370711,43.166113],"type":"Point"}
}