{
  "type": "Feature",
  "properties": {
    "addr:full":"5737 SW 18th Dr Portland OR 97239",
    "addr:housenumber":"5737",
    "addr:postcode":"97239",
    "addr:street":"Sw 18Th Dr",
    "iso:country":"US",
    "sg:address":"5737 SW 18th Dr",
    "sg:city":"Portland",
    "sg:classifiers":[
        {
            "category":"Manufacturing",
            "subcategory":"Pottery",
            "type":"Manufacturing & Wholesale Goods"
        }
    ],
    "sg:phone":"+1 503 246 5685",
    "sg:postcode":"97239",
    "sg:province":"OR",
    "sg:tags":[
        "pottery-wholesale",
        "manufacturer"
    ],
    "wof:name":"Swissgarten",
    "wof:placetype":"venue"
},
  "geometry": {"coordinates":[-122.69634499999999,45.481727],"type":"Point"}
}