{
  "type": "Feature",
  "properties": {
    "addr:full":"13800 SE Webster Road Portland OR 97267",
    "addr:housenumber":"13800",
    "addr:postcode":"97267",
    "addr:street":"Se Webster Road",
    "iso:country":"US",
    "sg:address":"13800 SE Webster Road",
    "sg:city":"Portland",
    "sg:classifiers":[
        {
            "category":"Professional",
            "subcategory":"Accounting & Tax Preparation",
            "type":"Services"
        }
    ],
    "sg:phone":"+1 503 659 9434",
    "sg:postcode":"97267",
    "sg:province":"OR",
    "sg:tags":[
        "accountant"
    ],
    "wof:name":"Summers Alan L CPA",
    "wof:placetype":"venue"
},
  "geometry": {"coordinates":[-122.593412,45.422508],"type":"Point"}
}