{
  "type": "Feature",
  "properties": {
    "addr:full":"14945 SW Sequoia Parkway Suite 170 Portland OR 97224",
    "addr:housenumber":"14945",
    "addr:postcode":"97224",
    "addr:street":"Sw Sequoia Parkway Suite 170",
    "iso:country":"US",
    "sg:address":"14945 SW Sequoia Parkway Suite 170",
    "sg:city":"Portland",
    "sg:classifiers":[
        {
            "category":"Building & Trades",
            "subcategory":"Construction",
            "type":"Services"
        }
    ],
    "sg:phone":"+1 503 297 2200",
    "sg:postcode":"97224",
    "sg:province":"OR",
    "sg:tags":[
        "contractor"
    ],
    "sg:website":"www.jcreeves.com",
    "wof:name":"Jc Reeves Corporation",
    "wof:placetype":"venue"
},
  "geometry": {"coordinates":[-122.746925,45.412227],"type":"Point"}
}