{
  "type": "Feature",
  "properties": {
    "addr:full":"2690 Roberts Creek Rd Roseburg OR 97470",
    "addr:housenumber":"2690",
    "addr:postcode":"97470",
    "addr:street":"Roberts Creek Rd",
    "iso:country":"US",
    "sg:address":"2690 Roberts Creek Rd",
    "sg:city":"Roseburg",
    "sg:classifiers":[
        {
            "category":"Home & Garden",
            "subcategory":"Garden Supply",
            "type":"Retail Goods"
        }
    ],
    "sg:phone":"+1 541 679 3544",
    "sg:postcode":"97470",
    "sg:province":"OR",
    "sg:tags":[
        "operation",
        "tract",
        "timber"
    ],
    "wof:name":"Mignola Farms",
    "wof:placetype":"venue"
},
  "geometry": {"coordinates":[-123.34750099999999,43.126129],"type":"Point"}
}