{
  "type": "Feature",
  "properties": {
    "iso:country":"US",
    "sg:address":"3385 Triangle Dr SE",
    "sg:city":"Salem",
    "sg:classifiers":[
        {
            "category":"Retail",
            "subcategory":"Auto Repair",
            "type":"Services"
        }
    ],
    "sg:phone":"+1 503 877 3979",
    "sg:postcode":"97302",
    "sg:province":"OR",
    "sg:tags":[
        "automobile",
        "brake",
        "electric"
    ],
    "sg:website":"http://www.trinitysqualityautocare.com",
    "wof:name":"Trinitys Auto Care",
    "wof:placetype":"venue"
},
  "geometry": {"coordinates":[-123.043149,44.906675],"type":"Point"}
}