{
  "type": "Feature",
  "properties": {
    "addr:full":"19417 Seminole Cir Bend OR 97702",
    "addr:housenumber":"19417",
    "addr:postcode":"97702",
    "addr:street":"Seminole Cir",
    "iso:country":"US",
    "sg:address":"19417 Seminole Cir",
    "sg:city":"Bend",
    "sg:classifiers":[
        {
            "category":"Professional",
            "subcategory":"Computer Services",
            "type":"Services"
        }
    ],
    "sg:phone":"+1 541 382 6650",
    "sg:postcode":"97702",
    "sg:province":"OR",
    "sg:website":"www.cascadechips.com",
    "wof:name":"Cascade Chips",
    "wof:placetype":"venue"
},
  "geometry": {"coordinates":[-121.354714,43.968529],"type":"Point"}
}