{
  "type": "Feature",
  "properties": {
    "iso:country":"US",
    "sg:address":"61255 Sarah Dr",
    "sg:city":"Bend",
    "sg:classifiers":[
        {
            "category":"Restaurant",
            "type":"Food & Drink"
        }
    ],
    "sg:phone":"+1 541 317 9712",
    "sg:postcode":"97702",
    "sg:province":"OR",
    "sg:tags":[
        "eating"
    ],
    "wof:name":"Tidal Raves Inc",
    "wof:placetype":"venue"
},
  "geometry": {"coordinates":[-121.271694,44.023318],"type":"Point"}
}