{
  "type": "Feature",
  "properties": {
    "addr:full":"2308 1st St Tillamook OR 97141",
    "addr:housenumber":"2308",
    "addr:postcode":"97141",
    "addr:street":"1St St",
    "iso:country":"US",
    "sg:address":"2308 1st St",
    "sg:city":"Tillamook",
    "sg:classifiers":[
        {
            "category":"Manufacturing",
            "subcategory":"Lumber",
            "type":"Manufacturing & Wholesale Goods"
        }
    ],
    "sg:phone":"+1 503 842 3180",
    "sg:postcode":"97141",
    "sg:province":"OR",
    "sg:tags":[
        "forester"
    ],
    "wof:name":"Green Diamond Resource Co",
    "wof:placetype":"venue"
},
  "geometry": {"coordinates":[-123.84093300000001,45.457334],"type":"Point"}
}