{
  "type": "Feature",
  "properties": {
    "iso:country":"US",
    "sg:address":"2308 1st St",
    "sg:city":"Tillamook",
    "sg:classifiers":[
        {
            "category":"Manufacturing",
            "subcategory":"Lumber",
            "type":"Manufacturing & Wholesale Goods"
        }
    ],
    "sg:phone":"+1 503 842 3180",
    "sg:postcode":"97141",
    "sg:province":"OR",
    "sg:tags":[
        "forester"
    ],
    "wof:name":"Green Diamond Resource Co",
    "wof:placetype":"venue"
},
  "geometry": {"coordinates":[-123.840933,45.457334],"type":"Point"}
}