{
  "type": "Feature",
  "properties": {
    "iso:country":"US",
    "sg:address":"16304 SW Estuary Dr",
    "sg:city":"Beaverton",
    "sg:classifiers":[
        {
            "category":"Real Estate",
            "subcategory":"Real Estate Agent",
            "type":"Services"
        }
    ],
    "sg:phone":"+1 503 629 5824",
    "sg:postcode":"97006",
    "sg:province":"OR",
    "wof:name":"Jane Apartments",
    "wof:placetype":"venue"
},
  "geometry": {"coordinates":[-122.844713,45.513774],"type":"Point"}
}