{
  "type": "Feature",
  "properties": {
    "iso:country":"US",
    "sg:address":"423 N 10th Ave",
    "sg:city":"Cornelius",
    "sg:classifiers":[
        {
            "category":"Organizations",
            "subcategory":"Religious Organization",
            "type":"Services"
        }
    ],
    "sg:phone":"+1 503 359 4288",
    "sg:postcode":"97113",
    "sg:province":"OR",
    "sg:tags":[
        "church"
    ],
    "sg:website":"www.realife4u.org",
    "wof:name":"Real Life Christian Church",
    "wof:placetype":"venue"
},
  "geometry": {"coordinates":[-123.059532,45.5239],"type":"Point"}
}