{
  "type": "Feature",
  "properties": {
    "iso:country":"US",
    "sg:address":"258 A St",
    "sg:city":"Ashland",
    "sg:classifiers":[
        {
            "category":"Wholesale",
            "subcategory":"Apparel",
            "type":"Manufacturing & Wholesale Goods"
        }
    ],
    "sg:phone":"+1 541 482 5020",
    "sg:postcode":"97520",
    "sg:province":"OR",
    "sg:tags":[
        "zipper"
    ],
    "wof:name":"ZRK Enterprises",
    "wof:placetype":"venue"
},
  "geometry": {"coordinates":[-122.710531,42.198817],"type":"Point"}
}