{
  "type": "Feature",
  "properties": {
    "iso:country":"US",
    "sg:address":"7325 SE 20th Ave",
    "sg:city":"Portland",
    "sg:classifiers":[
        {
            "category":"Professional",
            "subcategory":"Research",
            "type":"Services"
        }
    ],
    "sg:phone":"+1 503 236 8178",
    "sg:postcode":"97202",
    "sg:province":"OR",
    "sg:tags":[
        "economic",
        "analysis"
    ],
    "wof:name":"Balducci Consulting Services",
    "wof:placetype":"venue"
},
  "geometry": {"coordinates":[-122.64452,45.472005],"type":"Point"}
}