{
  "type": "Feature",
  "properties": {
    "addr:full":"65686 Cline Falls Rd Bend OR 97701",
    "addr:postcode":"65686;97701",
    "addr:street":"Cline Falls Rd",
    "iso:country":"US",
    "sg:address":"65686 Cline Falls Rd",
    "sg:city":"Bend",
    "sg:classifiers":[
        {
            "category":"Professional",
            "subcategory":"Management & Consulting",
            "type":"Services"
        },
        {
            "category":"Building & Trades",
            "subcategory":"Construction",
            "type":"Services"
        }
    ],
    "sg:phone":"+1 541 389 9399",
    "sg:postcode":"97701",
    "sg:province":"OR",
    "sg:tags":[
        "roofing",
        "consultant",
        "contractor"
    ],
    "wof:name":"Roberts & Son Roofing Company",
    "wof:placetype":"venue"
},
  "geometry": {"coordinates":[-121.323757,44.183723],"type":"Point"}
}