{
  "type": "Feature",
  "properties": {
    "iso:country":"US",
    "sg:address":"1910 S 9th St",
    "sg:city":"Lebanon",
    "sg:classifiers":[
        {
            "category":"Shopping",
            "type":"Retail Goods"
        }
    ],
    "sg:phone":"+1 541 258 8159",
    "sg:postcode":"97355",
    "sg:province":"OR",
    "sg:tags":[
        "hearing",
        "equipment",
        "supply",
        "impaired"
    ],
    "wof:name":"Oregon Hearing Health Service",
    "wof:placetype":"venue"
},
  "geometry": {"coordinates":[-122.918602,44.527557],"type":"Point"}
}