{
  "type": "Feature",
  "properties": {
    "iso:country":"US",
    "sg:address":"140 SE Roberts Ave",
    "sg:city":"Gresham",
    "sg:classifiers":[
        {
            "category":"Building & Trades",
            "subcategory":"Construction",
            "type":"Services"
        }
    ],
    "sg:phone":"+1 503 666 9017",
    "sg:postcode":"97080",
    "sg:province":"OR",
    "sg:tags":[
        "residential"
    ],
    "wof:name":"CAM Development",
    "wof:placetype":"venue"
},
  "geometry": {"coordinates":[-122.428691,45.497085],"type":"Point"}
}