{
  "type": "Feature",
  "properties": {
    "iso:country":"US",
    "sg:address":"1800 SE M L King Blvd",
    "sg:city":"Portland",
    "sg:classifiers":[
        {
            "category":"Retail",
            "subcategory":"Auto Rental",
            "type":"Services"
        }
    ],
    "sg:phone":"+1 503 233 2492",
    "sg:postcode":"97214",
    "sg:province":"OR",
    "sg:tags":[
        "passenger",
        "car"
    ],
    "wof:name":"Rent-A-Wreck",
    "wof:placetype":"venue"
},
  "geometry": {"coordinates":[-122.661881,45.509384],"type":"Point"}
}