{
  "type": "Feature",
  "properties": {
    "addr:full":"5270 SW Franklin Ave Beaverton OR 97005",
    "addr:housenumber":"5270",
    "addr:postcode":"97005",
    "addr:street":"Sw Franklin Ave",
    "iso:country":"US",
    "sg:address":"5270 SW Franklin Ave",
    "sg:city":"Beaverton",
    "sg:classifiers":[
        {
            "category":"Professional",
            "type":"Services"
        }
    ],
    "sg:phone":"+1 503 520 9017",
    "sg:postcode":"97005",
    "sg:province":"OR",
    "sg:tags":[
        "establishment"
    ],
    "wof:name":"All American Inc",
    "wof:placetype":"venue"
},
  "geometry": {"coordinates":[-122.801835,45.48294],"type":"Point"}
}