{
  "type": "Feature",
  "properties": {
    "iso:country":"US",
    "sg:address":"709 Lawnsdale Rd",
    "sg:city":"Medford",
    "sg:classifiers":[
        {
            "category":"Personal",
            "subcategory":"Beauty Salon",
            "type":"Services"
        }
    ],
    "sg:phone":"+1 541 773 2284",
    "sg:postcode":"97504",
    "sg:province":"OR",
    "sg:tags":[
        "shop"
    ],
    "wof:name":"Style Master Salon",
    "wof:placetype":"venue"
},
  "geometry": {"coordinates":[-122.876766,42.363509],"type":"Point"}
}