{
  "type": "Feature",
  "properties": {
    "iso:country":"US",
    "sg:address":"304 NE Agness Ave",
    "sg:city":"Grants Pass",
    "sg:classifiers":[
        {
            "category":"Shopping",
            "subcategory":"Discount & Variety Stores",
            "type":"Retail Goods"
        }
    ],
    "sg:phone":"+1 541 956 6151",
    "sg:postcode":"97526",
    "sg:province":"OR",
    "wof:name":"Big Lots",
    "wof:placetype":"venue"
},
  "geometry": {"coordinates":[-123.298091,42.434724],"type":"Point"}
}