{
  "type": "Feature",
  "properties": {
    "iso:country":"US",
    "sg:address":"921 SW Morrison St Ste 431",
    "sg:city":"Portland",
    "sg:classifiers":[
        {
            "category":"Organizations",
            "subcategory":"Community Association",
            "type":"Services"
        }
    ],
    "sg:phone":"+1 503 241 3630",
    "sg:postcode":"97205",
    "sg:province":"OR",
    "wof:name":"Made In Oregon",
    "wof:placetype":"venue"
},
  "geometry": {"coordinates":[-122.681326,45.519796],"type":"Point"}
}