{
  "type": "Feature",
  "properties": {
    "iso:country":"US",
    "sg:address":"1001 4th St",
    "sg:city":"La Grande",
    "sg:classifiers":[
        {
            "category":"Government",
            "subcategory":"Office",
            "type":"Public Place"
        }
    ],
    "sg:phone":"+1 541 963 1014",
    "sg:postcode":"97850",
    "sg:province":"OR",
    "wof:name":"Union County Planning Comm",
    "wof:placetype":"venue"
},
  "geometry": {"coordinates":[-118.096529,45.321208],"type":"Point"}
}