{
  "type": "Feature",
  "properties": {
    "addr:full":"5295 Dark Hollow Rd Medford OR 97501",
    "addr:housenumber":"5295",
    "addr:postcode":"97501",
    "addr:street":"Dark Hollow Rd",
    "iso:country":"US",
    "sg:address":"5295 Dark Hollow Rd",
    "sg:city":"Medford",
    "sg:classifiers":[
        {
            "category":"Building & Trades",
            "subcategory":"Construction",
            "type":"Services"
        }
    ],
    "sg:phone":"+1 541 734 9090",
    "sg:postcode":"97501",
    "sg:province":"OR",
    "sg:tags":[
        "general",
        "contractor"
    ],
    "wof:name":"Stan Harris Construction Inc",
    "wof:placetype":"venue"
},
  "geometry": {"coordinates":[-122.890631,42.263064],"type":"Point"}
}