{
  "type": "Feature",
  "properties": {
    "iso:country":"US",
    "sg:address":"11795 SW Greenburg Rd",
    "sg:city":"Tigard",
    "sg:classifiers":[
        {
            "category":"Health Services",
            "subcategory":"Dentist",
            "type":"Services"
        }
    ],
    "sg:phone":"+1 503 639 4201",
    "sg:postcode":"97223",
    "sg:province":"OR",
    "wof:name":"Black Steven W DDS",
    "wof:placetype":"venue"
},
  "geometry": {"coordinates":[-122.769581,45.434644],"type":"Point"}
}