{
  "type": "Feature",
  "properties": {
    "addr:full":"252 S Date Ave Burns OR 97720",
    "addr:housenumber":"252",
    "addr:postcode":"97720",
    "addr:street":"S Date Ave",
    "iso:country":"US",
    "sg:address":"252 S Date Ave",
    "sg:city":"Burns",
    "sg:classifiers":[
        {
            "category":"Government",
            "subcategory":"Office",
            "type":"Public Place"
        }
    ],
    "sg:phone":"+1 541 573 6019",
    "sg:postcode":"97720",
    "sg:province":"OR",
    "sg:tags":[
        "transportation"
    ],
    "wof:name":"Driver & Motor Vhcl Svcs Ore",
    "wof:placetype":"venue"
},
  "geometry": {"coordinates":[-119.050438,43.583448],"type":"Point"}
}