{
  "type": "Feature",
  "properties": {
    "addr:full":"6039 NE Win Sivers Dr Portland OR 97220",
    "addr:housenumber":"6039",
    "addr:postcode":"97220",
    "addr:street":"Ne Win Sivers Dr",
    "iso:country":"US",
    "sg:address":"6039 NE Win Sivers Dr",
    "sg:city":"Portland",
    "sg:classifiers":[
        {
            "category":"Building & Trades",
            "subcategory":"Locksmith",
            "type":"Services"
        }
    ],
    "sg:phone":"+1 503 205 6795",
    "sg:postcode":"97220",
    "sg:province":"OR",
    "sg:tags":[
        "key"
    ],
    "wof:name":"1 Action 7 Day Lock Service",
    "wof:placetype":"venue"
},
  "geometry": {"coordinates":[-122.537882,45.566634],"type":"Point"}
}