{
  "type": "Feature",
  "properties": {
    "addr:full":"560 NE F St Grants Pass OR 97526",
    "addr:housenumber":"560",
    "addr:postcode":"97526",
    "addr:street":"Ne F St",
    "iso:country":"US",
    "sg:address":"560 NE F St",
    "sg:city":"Grants Pass",
    "sg:classifiers":[
        {
            "category":"Building & Trades",
            "subcategory":"Construction",
            "type":"Services"
        }
    ],
    "sg:phone":"+1 541 944 9697",
    "sg:postcode":"97526",
    "sg:province":"OR",
    "sg:tags":[
        "concrete",
        "framing",
        "block"
    ],
    "wof:name":"Greg Bounds Construction",
    "wof:placetype":"venue"
},
  "geometry": {"coordinates":[-123.316985,42.438521],"type":"Point"}
}