{
  "type": "Feature",
  "properties": {
    "iso:country":"US",
    "sg:address":"17930 Parkway Ln",
    "sg:city":"Bend",
    "sg:classifiers":[
        {
            "category":"Professional",
            "subcategory":"Accounting & Tax Preparation",
            "type":"Services"
        }
    ],
    "sg:phone":"+1 541 317 3434",
    "sg:postcode":"97701",
    "sg:province":"OR",
    "sg:tags":[
        "accountant"
    ],
    "wof:name":"Dasenko & Brooks",
    "wof:placetype":"venue"
},
  "geometry": {"coordinates":[-121.44596799999999,44.230611],"type":"Point"}
}