{
  "type": "Feature",
  "properties": {
    "iso:country":"US",
    "sg:address":"22021 NW Kutch Rd",
    "sg:city":"Yamhill",
    "sg:classifiers":[
        {
            "category":"Manufacturing",
            "subcategory":"Lumber",
            "type":"Manufacturing & Wholesale Goods"
        }
    ],
    "sg:phone":"+1 503 852 7390",
    "sg:postcode":"97148",
    "sg:province":"OR",
    "sg:tags":[
        "operation",
        "timber",
        "tract"
    ],
    "wof:name":"Dale Thornton",
    "wof:placetype":"venue"
},
  "geometry": {"coordinates":[-123.344246,45.326961],"type":"Point"}
}