{
  "type": "Feature",
  "properties": {
    "iso:country":"US",
    "sg:address":"115 S 19th St",
    "sg:city":"Philomath",
    "sg:classifiers":[
        {
            "category":"Professional",
            "type":"Services"
        }
    ],
    "sg:phone":"+1 541 929 4340",
    "sg:postcode":"97370",
    "sg:province":"OR",
    "wof:name":"Mucho Gracias",
    "wof:placetype":"venue"
},
  "geometry": {"coordinates":[-123.35889899999999,44.539961],"type":"Point"}
}