{
  "type": "Feature",
  "properties": {
    "iso:country":"US",
    "sg:address":"1374 Willamette St",
    "sg:city":"Eugene",
    "sg:classifiers":[
        {
            "category":"Arts & Performance",
            "subcategory":"Theater",
            "type":"Entertainment"
        }
    ],
    "sg:phone":"+1 541 484 0951",
    "sg:postcode":"97401",
    "sg:province":"OR",
    "sg:tags":[
        "group"
    ],
    "wof:name":"Musicians Mutual Assn",
    "wof:placetype":"venue"
},
  "geometry": {"coordinates":[-123.092822,44.04525],"type":"Point"}
}