{
  "type": "Feature",
  "properties": {
    "addr:full":"20465 SW Johnson St Beaverton OR 97006",
    "addr:housenumber":"20465",
    "addr:postcode":"97006",
    "addr:street":"Sw Johnson St",
    "iso:country":"US",
    "sg:address":"20465 SW Johnson St",
    "sg:city":"Beaverton",
    "sg:classifiers":[
        {
            "category":"Wholesale",
            "subcategory":"Vending Machines",
            "type":"Manufacturing & Wholesale Goods"
        }
    ],
    "sg:phone":"+1 503 649 3478",
    "sg:postcode":"97006",
    "sg:province":"OR",
    "sg:tags":[
        "operator"
    ],
    "wof:name":"B P G Enterprises",
    "wof:placetype":"venue"
},
  "geometry": {"coordinates":[-122.89108,45.500639],"type":"Point"}
}