{
  "type": "Feature",
  "properties": {
    "iso:country":"US",
    "sg:address":"1247 NE Medical Center Dr Ste 3",
    "sg:city":"Bend",
    "sg:classifiers":[
        {
            "category":"Health Services",
            "subcategory":"Doctor",
            "type":"Services"
        }
    ],
    "sg:phone":"+1 541 318 4249",
    "sg:postcode":"97701",
    "sg:province":"OR",
    "sg:tags":[
        "physician",
        "family",
        "endocrinology",
        "practice",
        "surgeons",
        "metabolism",
        "manipulative",
        "osteopathic",
        "treatment",
        "medicine",
        "surgeon",
        "internal",
        "diabetes"
    ],
    "sg:website":"http://www.highlakeshealthcare.com",
    "wof:name":"High Lakes Health Care",
    "wof:placetype":"venue"
},
  "geometry": {"coordinates":[-121.264279,44.062935],"type":"Point"}
}