{
  "type": "Feature",
  "properties": {
    "addr:full":"1170 Bellview Ave Ashland OR 97520",
    "addr:housenumber":"1170",
    "addr:postcode":"97520",
    "addr:street":"Bellview Ave",
    "iso:country":"US",
    "sg:address":"1170 Bellview Ave",
    "sg:city":"Ashland",
    "sg:classifiers":[
        {
            "category":"Professional",
            "subcategory":"Management & Consulting",
            "type":"Services"
        }
    ],
    "sg:phone":"+1 541 488 2414",
    "sg:postcode":"97520",
    "sg:province":"OR",
    "sg:tags":[
        "business"
    ],
    "wof:name":"Development Consulting Svc",
    "wof:placetype":"venue"
},
  "geometry": {"coordinates":[-122.674952,42.172427],"type":"Point"}
}