{
  "type": "Feature",
  "properties": {
    "iso:country":"US",
    "sg:address":"3611 State St",
    "sg:city":"Salem",
    "sg:classifiers":[
        {
            "category":"Wholesale",
            "subcategory":"Groceries",
            "type":"Manufacturing & Wholesale Goods"
        }
    ],
    "sg:phone":"+1 503 588 3403",
    "sg:postcode":"97301",
    "sg:province":"OR",
    "sg:tags":[
        "store"
    ],
    "wof:name":"West Coast Cash and Carry",
    "wof:placetype":"venue"
},
  "geometry": {"coordinates":[-122.989276,44.927999],"type":"Point"}
}