{
  "type": "Feature",
  "properties": {
    "iso:country":"US",
    "sg:address":"326 SW Broadway Suite 400",
    "sg:city":"Portland",
    "sg:classifiers":[
        {
            "category":"Manufacturing",
            "subcategory":"Electronics",
            "type":"Manufacturing & Wholesale Goods"
        }
    ],
    "sg:phone":"+1 503 227 7600",
    "sg:postcode":"97205",
    "sg:province":"OR",
    "sg:website":"https://www.chockstone.com/",
    "wof:name":"Chockstone",
    "wof:placetype":"venue"
},
  "geometry": {"coordinates":[-122.67840099999999,45.521496],"type":"Point"}
}