{
  "type": "Feature",
  "properties": {
    "iso:country":"US",
    "sg:address":"29441 Ellensburg Ave",
    "sg:city":"Gold Beach",
    "sg:classifiers":[
        {
            "category":"Real Estate",
            "subcategory":"Real Estate Agent",
            "type":"Services"
        }
    ],
    "sg:phone":"+1 541 247 4518",
    "sg:postcode":"97444",
    "sg:province":"OR",
    "wof:name":"Whitehead Real Estate",
    "wof:placetype":"venue"
},
  "geometry": {"coordinates":[-124.421211,42.406648],"type":"Point"}
}