{
  "type": "Feature",
  "properties": {
    "addr:full":"4721 SE Division St Portland OR 97206",
    "addr:housenumber":"4721",
    "addr:postcode":"97206",
    "addr:street":"Se Division St",
    "iso:country":"US",
    "sg:address":"4721 SE Division St",
    "sg:city":"Portland",
    "sg:classifiers":[
        {
            "category":"Professional",
            "type":"Services"
        }
    ],
    "sg:phone":"+1 503 233 8538",
    "sg:postcode":"97206",
    "sg:province":"OR",
    "wof:name":"Gardenbox Co",
    "wof:placetype":"venue"
},
  "geometry": {"coordinates":[-122.61321,45.505295],"type":"Point"}
}