{
  "type": "Feature",
  "properties": {
    "addr:full":"14805 SE Megan Way Clackamas OR 97015",
    "addr:postcode":"14805;97015",
    "addr:street":"Se Megan Way",
    "iso:country":"US",
    "sg:address":"14805 SE Megan Way",
    "sg:city":"Clackamas",
    "sg:classifiers":[
        {
            "category":"Wholesale",
            "subcategory":"Durable Goods & Equipment",
            "type":"Manufacturing & Wholesale Goods"
        }
    ],
    "sg:phone":"+1 503 698 2267",
    "sg:postcode":"97015",
    "sg:province":"OR",
    "wof:name":"JD Auto Wholesale",
    "wof:placetype":"venue"
},
  "geometry": {"coordinates":[-122.525865,45.414736],"type":"Point"}
}