{
  "type": "Feature",
  "properties": {
    "iso:country":"US",
    "sg:address":"4300 SE 82nd Ave",
    "sg:city":"Portland",
    "sg:classifiers":[
        {
            "category":"Banks & Credit Unions",
            "subcategory":"Bank",
            "type":"Services"
        }
    ],
    "sg:phone":"+1 503 775 3918",
    "sg:postcode":"97266",
    "sg:province":"OR",
    "sg:website":"www.usbanks.com",
    "wof:name":"US Bank",
    "wof:placetype":"venue"
},
  "geometry": {"coordinates":[-122.579002,45.491299],"type":"Point"}
}