{
  "type": "Feature",
  "properties": {
    "iso:country":"US",
    "sg:address":"12571 SW Main St",
    "sg:city":"Portland",
    "sg:classifiers":[
        {
            "category":"Professional",
            "subcategory":"Research",
            "type":"Services"
        }
    ],
    "sg:phone":"+1 503 598 8766",
    "sg:postcode":"97223",
    "sg:province":"OR",
    "sg:tags":[
        "agricultural",
        "laboratories-agricultural"
    ],
    "sg:website":"http://www.aveslab.com",
    "wof:name":"Aves Laboratories",
    "wof:placetype":"venue"
},
  "geometry": {"coordinates":[-122.774643,45.428902],"type":"Point"}
}