{
  "type": "Feature",
  "properties": {
    "iso:country":"US",
    "sg:address":"10265 SW Melnore St",
    "sg:city":"Portland",
    "sg:classifiers":[
        {
            "category":"Professional",
            "subcategory":"Management & Consulting",
            "type":"Services"
        }
    ],
    "sg:phone":"+1 503 297 4787",
    "sg:postcode":"97225",
    "sg:province":"OR",
    "sg:tags":[
        "business"
    ],
    "wof:name":"Lloyd Thacker MA",
    "wof:placetype":"venue"
},
  "geometry": {"coordinates":[-122.780755,45.501348],"type":"Point"}
}