{
  "type": "Feature",
  "properties": {
    "iso:country":"US",
    "sg:address":"1293 Cow Hollow Rd",
    "sg:city":"Nyssa",
    "sg:classifiers":[
        {
            "category":"Professional",
            "type":"Services"
        }
    ],
    "sg:phone":"+1 541 372 2443",
    "sg:postcode":"97913",
    "sg:province":"OR",
    "wof:name":"Velma N Widmer",
    "wof:placetype":"venue"
},
  "geometry": {"coordinates":[-117.174392,43.837485],"type":"Point"}
}