{
  "type": "Feature",
  "properties": {
    "iso:country":"US",
    "sg:address":"6655 SW Scholls Ferry Rd",
    "sg:city":"Beaverton",
    "sg:classifiers":[
        {
            "category":"Retail",
            "subcategory":"Auto Repair",
            "type":"Services"
        }
    ],
    "sg:phone":"+1 503 246 9781",
    "sg:postcode":"97008",
    "sg:province":"OR",
    "wof:name":"Scholls Ferry Automotive",
    "wof:placetype":"venue"
},
  "geometry": {"coordinates":[-122.774002,45.471802],"type":"Point"}
}