{
  "type": "Feature",
  "properties": {
    "addr:full":"86 SW Century Dr Bend OR 97702",
    "addr:housenumber":"86",
    "addr:postcode":"97702",
    "addr:street":"Sw Century Dr",
    "iso:country":"US",
    "sg:address":"86 SW Century Dr",
    "sg:city":"Bend",
    "sg:classifiers":[
        {
            "category":"Professional",
            "subcategory":"Computer Services",
            "type":"Services"
        }
    ],
    "sg:phone":"+1 541 382 4360",
    "sg:postcode":"97702",
    "sg:province":"OR",
    "sg:tags":[
        "datum"
    ],
    "wof:name":"Redhawk Network Engineering",
    "wof:placetype":"venue"
},
  "geometry": {"coordinates":[-121.331757,44.049623],"type":"Point"}
}