{
  "type": "Feature",
  "properties": {
    "iso:country":"US",
    "sg:address":"5420 Windsor Island Rd N",
    "sg:city":"Salem",
    "sg:classifiers":[
        {
            "category":"Home & Garden",
            "subcategory":"Garden Supply",
            "type":"Retail Goods"
        }
    ],
    "sg:phone":"+1 503 390 8005",
    "sg:postcode":"97303",
    "sg:province":"OR",
    "wof:name":"L J Mowers",
    "wof:placetype":"venue"
},
  "geometry": {"coordinates":[-123.044149,45.002365],"type":"Point"}
}