{
  "type": "Feature",
  "properties": {
    "iso:country":"US",
    "sg:address":"32395 Lynx Hollow Rd",
    "sg:city":"Creswell",
    "sg:classifiers":[
        {
            "category":"Farming",
            "subcategory":"Livestock Farm",
            "type":"Manufacturing & Wholesale Goods"
        }
    ],
    "sg:phone":"+1 541 942 3209",
    "sg:postcode":"97426",
    "sg:province":"OR",
    "sg:tags":[
        "animal",
        "general"
    ],
    "wof:name":"No B Ranch LLC",
    "wof:placetype":"venue"
},
  "geometry": {"coordinates":[-123.069977,43.861723],"type":"Point"}
}