{
  "type": "Feature",
  "properties": {
    "addr:full":"733 SW 10th Ave Portland OR 97205",
    "addr:housenumber":"733",
    "addr:postcode":"97205",
    "addr:street":"Sw 10Th Ave",
    "iso:country":"US",
    "sg:address":"733 SW 10th Ave",
    "sg:city":"Portland",
    "sg:classifiers":[
        {
            "category":"Shopping",
            "subcategory":"Musical Instruments",
            "type":"Retail Goods"
        }
    ],
    "sg:phone":"+1 503 228 6659",
    "sg:postcode":"97205",
    "sg:province":"OR",
    "wof:name":"Music Center",
    "wof:placetype":"venue"
},
  "geometry": {"coordinates":[-122.682462,45.519556],"type":"Point"}
}