{
  "type": "Feature",
  "properties": {
    "iso:country":"US",
    "sg:address":"4840 Noren Ave NE",
    "sg:city":"Keizer",
    "sg:classifiers":[
        {
            "category":"Social Services",
            "type":"Services"
        }
    ],
    "sg:phone":"+1 503 304 1313",
    "sg:postcode":"97303",
    "sg:province":"OR",
    "sg:tags":[
        "youth",
        "organization",
        "center"
    ],
    "wof:name":"Boys & Girls Clubs Of Salem",
    "wof:placetype":"venue"
},
  "geometry": {"coordinates":[-123.008197,44.995418],"type":"Point"}
}