{
  "type": "Feature",
  "properties": {
    "addr:full":"6441 SE 82nd Ave Portland OR 97266",
    "addr:housenumber":"6441",
    "addr:postcode":"97266",
    "addr:street":"Se 82Nd Ave",
    "iso:country":"US",
    "sg:address":"6441 SE 82nd Ave",
    "sg:city":"Portland",
    "sg:classifiers":[
        {
            "category":"Retail",
            "subcategory":"Auto Repair",
            "type":"Services"
        }
    ],
    "sg:phone":"+1 503 775 2499",
    "sg:postcode":"97266",
    "sg:province":"OR",
    "sg:tags":[
        "muffler",
        "exhaust",
        "system"
    ],
    "wof:name":"Discount Muffler",
    "wof:placetype":"venue"
},
  "geometry": {"coordinates":[-122.57914,45.476239],"type":"Point"}
}