{
  "type": "Feature",
  "properties": {
    "addr:full":"3961 Corey Rd Central Point OR 97502",
    "addr:housenumber":"3961",
    "addr:postcode":"97502",
    "addr:street":"Corey Rd",
    "iso:country":"US",
    "sg:address":"3961 Corey Rd",
    "sg:city":"Central Point",
    "sg:classifiers":[
        {
            "category":"Building & Trades",
            "subcategory":"Construction",
            "type":"Services"
        }
    ],
    "sg:phone":"+1 541 951 3207",
    "sg:postcode":"97502",
    "sg:province":"OR",
    "sg:tags":[
        "demolition",
        "contractor"
    ],
    "wof:name":"Ray's Demolition Svc",
    "wof:placetype":"venue"
},
  "geometry": {"coordinates":[-122.82697400000001,42.414714],"type":"Point"}
}