{
  "type": "Feature",
  "properties": {
    "iso:country":"US",
    "sg:address":"2480 Queen St",
    "sg:city":"Seaside",
    "sg:classifiers":[
        {
            "category":"Professional",
            "subcategory":"Accounting & Tax Preparation",
            "type":"Services"
        }
    ],
    "sg:phone":"+1 503 738 5225",
    "sg:postcode":"97138",
    "sg:province":"OR",
    "sg:tags":[
        "auditing",
        "bookkeeping"
    ],
    "wof:name":"Carmichiel Tax Service",
    "wof:placetype":"venue"
},
  "geometry": {"coordinates":[-123.91289999999999,46.010738],"type":"Point"}
}