{
  "type": "Feature",
  "properties": {
    "iso:country":"US",
    "sg:address":"2510 NW Medical Park Dr",
    "sg:city":"Roseburg",
    "sg:classifiers":[
        {
            "category":"Health Services",
            "subcategory":"Doctor",
            "type":"Services"
        }
    ],
    "sg:phone":"+1 541 673 5517",
    "sg:postcode":"97470",
    "sg:province":"OR",
    "sg:tags":[
        "medical"
    ],
    "wof:name":"Timothy J Powell MD",
    "wof:placetype":"venue"
},
  "geometry": {"coordinates":[-123.371544,43.238248],"type":"Point"}
}