{
  "type": "Feature",
  "properties": {
    "addr:full":"1585 SW Marlow Ave Ste 101 Suite 101 Portland OR 97225",
    "addr:housenumber":"1585",
    "addr:postcode":"97225",
    "addr:street":"Sw Marlow Ave Ste 101 Suite 101",
    "iso:country":"US",
    "sg:address":"1585 SW Marlow Ave Ste 101 Suite 101",
    "sg:city":"Portland",
    "sg:classifiers":[
        {
            "category":"Health Services",
            "subcategory":"Health Practitioner",
            "type":"Services"
        }
    ],
    "sg:phone":"+1 503 292 3583",
    "sg:postcode":"97225",
    "sg:province":"OR",
    "sg:tags":[
        "therapy",
        "physical"
    ],
    "sg:website":"www.therapeuticassociates.com",
    "wof:name":"Therapeutic Associates",
    "wof:placetype":"venue"
},
  "geometry": {"coordinates":[-122.78399,45.508309],"type":"Point"}
}