{
  "type": "Feature",
  "properties": {
    "iso:country":"US",
    "sg:address":"1627 NW 14th Ave",
    "sg:city":"Portland",
    "sg:classifiers":[
        {
            "category":"Building & Trades",
            "subcategory":"Construction",
            "type":"Services"
        }
    ],
    "sg:phone":"+1 503 914 5936",
    "sg:postcode":"97209",
    "sg:province":"OR",
    "sg:tags":[
        "interior",
        "design"
    ],
    "sg:website":"www.intrinsic-design.com",
    "wof:name":"Intrinsic Design",
    "wof:placetype":"venue"
},
  "geometry": {"coordinates":[-122.686104,45.534661],"type":"Point"}
}