{
  "type": "Feature",
  "properties": {
    "iso:country":"US",
    "sg:address":"115 Warren St",
    "sg:city":"Oregon City",
    "sg:classifiers":[
        {
            "category":"Social Services",
            "subcategory":"Child Care",
            "type":"Services"
        }
    ],
    "sg:phone":"+1 503 650 8752",
    "sg:postcode":"97045",
    "sg:province":"OR",
    "sg:tags":[
        "day"
    ],
    "wof:name":"Gramma Donnas Daycare",
    "wof:placetype":"venue"
},
  "geometry": {"coordinates":[-122.594819,45.350966],"type":"Point"}
}