{
  "type": "Feature",
  "properties": {
    "iso:country":"US",
    "sg:address":"124 E Main St",
    "sg:city":"Sheridan",
    "sg:classifiers":[
        {
            "category":"Restaurant",
            "type":"Food & Drink"
        }
    ],
    "sg:phone":"+1 503 843 3090",
    "sg:postcode":"97378",
    "sg:province":"OR",
    "wof:name":"Sheridan Pizza Co",
    "wof:placetype":"venue"
},
  "geometry": {"coordinates":[-123.394137,45.099431],"type":"Point"}
}