{
  "type": "Feature",
  "properties": {
    "iso:country":"US",
    "sg:address":"421 W Main St",
    "sg:city":"Athena",
    "sg:classifiers":[
        {
            "category":"Health Services",
            "subcategory":"Medical Lab",
            "type":"Services"
        },
        {
            "category":"Insurance",
            "subcategory":"Health Insurance",
            "type":"Services"
        }
    ],
    "sg:phone":"+1 541 566 3813",
    "sg:postcode":"97813",
    "sg:province":"OR",
    "sg:tags":[
        "maintenance"
    ],
    "wof:name":"East Umatilla County Health District",
    "wof:placetype":"venue"
},
  "geometry": {"coordinates":[-118.497292,45.811741],"type":"Point"}
}