{
  "type": "Feature",
  "properties": {
    "iso:country":"US",
    "sg:address":"34024 Twin Buttes Rd",
    "sg:city":"Eugene",
    "sg:classifiers":[
        {
            "category":"Manufacturing",
            "subcategory":"Jewelry",
            "type":"Manufacturing & Wholesale Goods"
        }
    ],
    "sg:phone":"+1 541 746 0866",
    "sg:postcode":"97405",
    "sg:province":"OR",
    "sg:tags":[
        "precious",
        "metal",
        "mfg"
    ],
    "wof:name":"Kindred Hearts",
    "wof:placetype":"venue"
},
  "geometry": {"coordinates":[-123.014245,44.002966],"type":"Point"}
}