{
  "type": "Feature",
  "properties": {
    "addr:full":"300 Flower Ln Dayton OR 97114",
    "addr:housenumber":"300",
    "addr:postcode":"97114",
    "addr:street":"Flower Ln",
    "iso:country":"US",
    "sg:address":"300 Flower Ln",
    "sg:city":"Dayton",
    "sg:classifiers":[
        {
            "category":"Organizations",
            "subcategory":"Religious Organization",
            "type":"Services"
        }
    ],
    "sg:phone":"+1 503 864 2474",
    "sg:postcode":"97114",
    "sg:province":"OR",
    "sg:tags":[
        "church"
    ],
    "wof:name":"First Baptist Church Dayton",
    "wof:placetype":"venue"
},
  "geometry": {"coordinates":[-123.09206,45.214423],"type":"Point"}
}