{
  "type": "Feature",
  "properties": {
    "iso:country":"US",
    "sg:address":"26255 High Pass Rd",
    "sg:city":"Junction City",
    "sg:classifiers":[
        {
            "category":"Building & Trades",
            "subcategory":"Landscaping Services",
            "type":"Services"
        }
    ],
    "sg:phone":"+1 541 998 6742",
    "sg:postcode":"97448",
    "sg:province":"OR",
    "sg:tags":[
        "lawn",
        "highway",
        "maintenance"
    ],
    "wof:name":"Oregon Innovative Products",
    "wof:placetype":"venue"
},
  "geometry": {"coordinates":[-123.31287500000001,44.214273],"type":"Point"}
}