{
  "type": "Feature",
  "properties": {
    "addr:full":"3122 NE 54th Ave Portland OR 97213",
    "addr:housenumber":"3122",
    "addr:postcode":"97213",
    "addr:street":"Ne 54Th Ave",
    "iso:country":"US",
    "sg:address":"3122 NE 54th Ave",
    "sg:city":"Portland",
    "sg:classifiers":[
        {
            "category":"Building & Trades",
            "subcategory":"Locksmith",
            "type":"Services"
        }
    ],
    "sg:phone":"+1 503 821 0956",
    "sg:postcode":"97213",
    "sg:province":"OR",
    "sg:tags":[
        "key"
    ],
    "wof:name":"Locksmith All Night",
    "wof:placetype":"venue"
},
  "geometry": {"coordinates":[-122.60741299999999,45.54556],"type":"Point"}
}