{
  "type": "Feature",
  "properties": {
    "addr:full":"11165 SE 23rd Ave Milwaukie OR 97222",
    "addr:housenumber":"11165",
    "addr:postcode":"97222",
    "addr:street":"Se 23Rd Ave",
    "iso:country":"US",
    "sg:address":"11165 SE 23rd Ave",
    "sg:city":"Milwaukie",
    "sg:classifiers":[
        {
            "category":"Building & Trades",
            "subcategory":"Locksmith",
            "type":"Services"
        }
    ],
    "sg:phone":"+1 503 715 2011",
    "sg:postcode":"97222",
    "sg:province":"OR",
    "sg:tags":[
        "key"
    ],
    "wof:name":"123 24 7 Locksmith",
    "wof:placetype":"venue"
},
  "geometry": {"coordinates":[-122.63845600000001,45.442088],"type":"Point"}
}