{
  "type": "Feature",
  "properties": {
    "addr:full":"375 Taybin Rd NW Salem OR 97304",
    "addr:housenumber":"375",
    "addr:postcode":"97304",
    "addr:street":"Taybin Rd Nw",
    "iso:country":"US",
    "sg:address":"375 Taybin Rd NW",
    "sg:city":"Salem",
    "sg:classifiers":[
        {
            "category":"Government",
            "subcategory":"Office",
            "type":"Public Place"
        }
    ],
    "sg:phone":"+1 503 585 1380",
    "sg:postcode":"97304",
    "sg:province":"OR",
    "sg:tags":[
        "housing",
        "program"
    ],
    "wof:name":"Housing Authority Polk County",
    "wof:placetype":"venue"
},
  "geometry": {"coordinates":[-123.050079,44.951995],"type":"Point"}
}