{
  "type": "Feature",
  "properties": {
    "iso:country":"US",
    "sg:address":"549 E Vilas Rd",
    "sg:city":"Central Point",
    "sg:classifiers":[
        {
            "category":"Retail",
            "subcategory":"Repair Shop",
            "type":"Services"
        },
        {
            "category":"Manufacturing",
            "subcategory":"Tools & Machinery",
            "type":"Manufacturing & Wholesale Goods"
        }
    ],
    "sg:phone":"+1 541 734 8808",
    "sg:postcode":"97502",
    "sg:province":"OR",
    "sg:tags":[
        "woodworking",
        "equipment",
        "industrial",
        "supply"
    ],
    "wof:name":"Bonfield Industrial Services",
    "wof:placetype":"venue"
},
  "geometry": {"coordinates":[-122.873247,42.389377],"type":"Point"}
}