{
  "type": "Feature",
  "properties": {
    "addr:full":"711 NW 11th Ave Portland OR 97209",
    "addr:housenumber":"711",
    "addr:postcode":"97209",
    "addr:street":"Nw 11Th Ave",
    "iso:country":"US",
    "sg:address":"711 NW 11th Ave",
    "sg:city":"Portland",
    "sg:classifiers":[
        {
            "category":"Personal",
            "subcategory":"Beauty Salon",
            "type":"Services"
        },
        {
            "category":"Personal",
            "subcategory":"Barber",
            "type":"Services"
        }
    ],
    "sg:phone":"+1 503 224 8711",
    "sg:postcode":"97209",
    "sg:province":"OR",
    "sg:tags":[
        "hair",
        "braiding",
        "stylist"
    ],
    "sg:website":"www.glowboutiquesalon.com",
    "wof:name":"Glow Boutique Salon",
    "wof:placetype":"venue"
},
  "geometry": {"coordinates":[-122.68249299999999,45.528142],"type":"Point"}
}