{
  "type": "Feature",
  "properties": {
    "iso:country":"US",
    "sg:address":"3598 Brannon Dr",
    "sg:city":"Medford",
    "sg:classifiers":[
        {
            "category":"Building & Trades",
            "subcategory":"Construction",
            "type":"Services"
        }
    ],
    "sg:phone":"+1 541 772 4497",
    "sg:postcode":"97504",
    "sg:province":"OR",
    "sg:tags":[
        "contractor"
    ],
    "wof:name":"Britt Gutters",
    "wof:placetype":"venue"
},
  "geometry": {"coordinates":[-122.815512,42.319908],"type":"Point"}
}