{
  "type": "Feature",
  "properties": {
    "addr:full":"1003 Logsden Rd Logsden OR 97380",
    "addr:housenumber":"1003",
    "addr:postcode":"97380",
    "addr:street":"Logsden Rd",
    "iso:country":"US",
    "sg:address":"1003 Logsden Rd",
    "sg:city":"Logsden",
    "sg:classifiers":[
        {
            "category":"Building & Trades",
            "subcategory":"Construction",
            "type":"Services"
        }
    ],
    "sg:phone":"+1 541 444 2190",
    "sg:postcode":"97380",
    "sg:province":"OR",
    "sg:tags":[
        "roofing",
        "contractor"
    ],
    "wof:name":"Jim Jackson Construction",
    "wof:placetype":"venue"
},
  "geometry": {"coordinates":[-123.900277,44.716976],"type":"Point"}
}