{
  "type": "Feature",
  "properties": {
    "addr:full":"21010 Coburg Rd Harrisburg OR 97446",
    "addr:postcode":"21010;97446",
    "addr:street":"Coburg Rd",
    "iso:country":"US",
    "sg:address":"21010 Coburg Rd",
    "sg:city":"Harrisburg",
    "sg:classifiers":[
        {
            "category":"Professional",
            "subcategory":"Detective & Security Services",
            "type":"Services"
        }
    ],
    "sg:phone":"+1 541 995 8022",
    "sg:postcode":"97446",
    "sg:province":"OR",
    "sg:tags":[
        "car",
        "investigator"
    ],
    "wof:name":"Ware J Investigations",
    "wof:placetype":"venue"
},
  "geometry": {"coordinates":[-123.125102,44.210407],"type":"Point"}
}