{
  "type": "Feature",
  "properties": {
    "iso:country":"US",
    "sg:address":"357 E Main St",
    "sg:city":"Ashland",
    "sg:classifiers":[
        {
            "category":"Home & Garden",
            "subcategory":"Furniture",
            "type":"Retail Goods"
        }
    ],
    "sg:phone":"+1 541 488 3734",
    "sg:postcode":"97520",
    "sg:province":"OR",
    "wof:name":"Ancient Of Days Gallery",
    "wof:placetype":"venue"
},
  "geometry": {"coordinates":[-122.710687,42.194953],"type":"Point"}
}