{
  "type": "Feature",
  "properties": {
    "addr:full":"4985 Battle Creek Rd SE Salem OR 97302",
    "addr:housenumber":"4985",
    "addr:postcode":"97302",
    "addr:street":"Battle Creek Rd Se",
    "iso:country":"US",
    "sg:address":"4985 Battle Creek Rd SE",
    "sg:city":"Salem",
    "sg:classifiers":[
        {
            "category":"Building & Trades",
            "subcategory":"Cleaning & Sanitation",
            "type":"Services"
        }
    ],
    "sg:phone":"+1 503 540 9149",
    "sg:postcode":"97302",
    "sg:province":"OR",
    "sg:tags":[
        "maintenance"
    ],
    "wof:name":"Abacus Building Services",
    "wof:placetype":"venue"
},
  "geometry": {"coordinates":[-123.01237399999999,44.884117],"type":"Point"}
}