{
  "type": "Feature",
  "properties": {
    "addr:full":"10451 NE Weidler St Portland OR 97220",
    "addr:housenumber":"10451",
    "addr:postcode":"97220",
    "addr:street":"Ne Weidler St",
    "iso:country":"US",
    "sg:address":"10451 NE Weidler St",
    "sg:city":"Portland",
    "sg:classifiers":[
        {
            "category":"Arts & Performance",
            "subcategory":"Theater",
            "type":"Entertainment"
        }
    ],
    "sg:phone":"+1 503 261 1822",
    "sg:postcode":"97220",
    "sg:province":"OR",
    "sg:tags":[
        "group"
    ],
    "wof:name":"Cliff S Class Act Casino",
    "wof:placetype":"venue"
},
  "geometry": {"coordinates":[-122.553871,45.534238],"type":"Point"}
}