{
  "type": "Feature",
  "properties": {
    "addr:full":"1475 Siskiyou Blvd Ashland OR 97520",
    "addr:housenumber":"1475",
    "addr:postcode":"97520",
    "addr:street":"Siskiyou Blvd",
    "iso:country":"US",
    "sg:address":"1475 Siskiyou Blvd",
    "sg:city":"Ashland",
    "sg:classifiers":[
        {
            "category":"Food & Beverages",
            "subcategory":"Groceries & Convenience Stores",
            "type":"Retail Goods"
        }
    ],
    "sg:phone":"+1 541 488 2773",
    "sg:postcode":"97520",
    "sg:province":"OR",
    "wof:name":"Market Of Choice",
    "wof:placetype":"venue"
},
  "geometry": {"coordinates":[-122.689759,42.184419],"type":"Point"}
}