{
  "type": "Feature",
  "properties": {
    "addr:full":"861 Pacific Dr Hammond OR 97121",
    "addr:housenumber":"861",
    "addr:postcode":"97121",
    "addr:street":"Pacific Dr",
    "iso:country":"US",
    "sg:address":"861 Pacific Dr",
    "sg:city":"Hammond",
    "sg:classifiers":[
        {
            "category":"Education",
            "subcategory":"Library",
            "type":"Public Place"
        }
    ],
    "sg:phone":"+1 503 861 3919",
    "sg:postcode":"97121",
    "sg:province":"OR",
    "wof:name":"Warrenton Community Library",
    "wof:placetype":"venue"
},
  "geometry": {"coordinates":[-123.948294,46.199306],"type":"Point"}
}