{
  "type": "Feature",
  "properties": {
    "iso:country":"US",
    "sg:address":"652 W Umpqua St",
    "sg:city":"Roseburg",
    "sg:classifiers":[
        {
            "category":"Insurance",
            "subcategory":"Insurance Agent",
            "type":"Services"
        },
        {
            "category":"Insurance",
            "subcategory":"Hazard Insurance",
            "type":"Services"
        },
        {
            "category":"Insurance",
            "subcategory":"Title Insurance",
            "type":"Services"
        },
        {
            "category":"Insurance",
            "subcategory":"Life Insurance",
            "type":"Services"
        }
    ],
    "sg:phone":"+1 541 672 4004",
    "sg:postcode":"97471",
    "sg:province":"OR",
    "sg:tags":[
        "auto",
        "commercial",
        "business",
        "homeowner"
    ],
    "sg:website":"http://www.farmersagent.com/jmurphy1/",
    "wof:name":"John Murphy - Farmers Insurance",
    "wof:placetype":"venue"
},
  "geometry": {"coordinates":[-123.359144,43.2134],"type":"Point"}
}