{
  "type": "Feature",
  "properties": {
    "addr:full":"325 2nd St SE Bandon OR 97411",
    "addr:housenumber":"325",
    "addr:postcode":"bandon or 97411",
    "addr:street":"2Nd St Se",
    "iso:country":"US",
    "sg:address":"325 2nd St SE",
    "sg:city":"Bandon",
    "sg:classifiers":[
        {
            "category":"Shopping",
            "subcategory":"Gifts & Souvenirs",
            "type":"Retail Goods"
        }
    ],
    "sg:phone":"+1 541 347 6092",
    "sg:postcode":"97411",
    "sg:province":"OR",
    "sg:tags":[
        "shop"
    ],
    "wof:name":"Brass Rose",
    "wof:placetype":"venue"
},
  "geometry": {"coordinates":[-124.412111,43.119151],"type":"Point"}
}