{
  "type": "Feature",
  "properties": {
    "iso:country":"US",
    "sg:address":"28000 SE Fern Dr",
    "sg:city":"Boring",
    "sg:classifiers":[
        {
            "category":"Retail",
            "subcategory":"Auto Repair",
            "type":"Services"
        }
    ],
    "sg:phone":"+1 503 663 5111",
    "sg:postcode":"97009",
    "sg:province":"OR",
    "sg:tags":[
        "body",
        "automobile",
        "painting"
    ],
    "wof:name":"Terry's Body Shop",
    "wof:placetype":"venue"
},
  "geometry": {"coordinates":[-122.375765,45.408942],"type":"Point"}
}