{
  "type": "Feature",
  "properties": {
    "addr:full":"255 SW 9th St Newport OR 97365",
    "addr:housenumber":"255",
    "addr:postcode":"97365",
    "addr:street":"Sw 9Th St",
    "iso:country":"US",
    "sg:address":"255 SW 9th St",
    "sg:city":"Newport",
    "sg:classifiers":[
        {
            "category":"Shopping",
            "subcategory":"Hobbies, Toys, & Games",
            "type":"Retail Goods"
        }
    ],
    "sg:phone":"+1 541 574 1901",
    "sg:postcode":"97365",
    "sg:province":"OR",
    "wof:name":"Sandcastle Toys",
    "wof:placetype":"venue"
},
  "geometry": {"coordinates":[-124.054134,44.633517],"type":"Point"}
}