{
  "type": "Feature",
  "properties": {
    "addr:full":"8316 N Lombard St Ste 326 Portland OR 97203",
    "addr:housenumber":"8316",
    "addr:postcode":"97203",
    "addr:street":"N Lombard St Ste 326",
    "iso:country":"US",
    "sg:address":"8316 N Lombard St Ste 326",
    "sg:city":"Portland",
    "sg:classifiers":[
        {
            "category":"Wholesale",
            "subcategory":"Durable Goods & Equipment",
            "type":"Manufacturing & Wholesale Goods"
        }
    ],
    "sg:phone":"+1 360 666 5331",
    "sg:postcode":"97203",
    "sg:province":"OR",
    "sg:tags":[
        "merchandise-wholesale",
        "store",
        "variety"
    ],
    "wof:name":"Saint John's Value Giant",
    "wof:placetype":"venue"
},
  "geometry": {"coordinates":[-122.75214099999999,45.589347],"type":"Point"}
}