{
  "type": "Feature",
  "properties": {
    "addr:full":"6126 SE Duke St Portland OR 97206",
    "addr:housenumber":"6126",
    "addr:postcode":"97206",
    "addr:street":"Se Duke St",
    "iso:country":"US",
    "sg:address":"6126 SE Duke St",
    "sg:city":"Portland",
    "sg:classifiers":[
        {
            "category":"Professional",
            "subcategory":"Accounting & Tax Preparation",
            "type":"Services"
        }
    ],
    "sg:phone":"+1 503 772 1544",
    "sg:postcode":"97206",
    "sg:province":"OR",
    "wof:name":"Reyes Falviano Sr CPA",
    "wof:placetype":"venue"
},
  "geometry": {"coordinates":[-122.600548,45.475749],"type":"Point"}
}