{
  "type": "Feature",
  "properties": {
    "iso:country":"US",
    "sg:address":"7895 Portland Rd NE",
    "sg:city":"Salem",
    "sg:classifiers":[
        {
            "category":"Freight",
            "type":"Transportation"
        },
        {
            "category":"Building & Trades",
            "subcategory":"Construction",
            "type":"Services"
        }
    ],
    "sg:phone":"+1 503 393 7699",
    "sg:postcode":"97305",
    "sg:province":"OR",
    "sg:tags":[
        "excavating",
        "excavation",
        "storage",
        "contractor",
        "trucking",
        "local"
    ],
    "wof:name":"Mike Herberger Trucking Inc",
    "wof:placetype":"venue"
},
  "geometry": {"coordinates":[-122.96614,45.034929],"type":"Point"}
}