{
  "type": "Feature",
  "properties": {
    "iso:country":"US",
    "sg:address":"809 Quail Dr",
    "sg:city":"Newberg",
    "sg:classifiers":[
        {
            "category":"Taxi",
            "type":"Transportation"
        }
    ],
    "sg:phone":"+1 503 554 0005",
    "sg:postcode":"97132",
    "sg:province":"OR",
    "sg:tags":[
        "taxicab"
    ],
    "wof:name":"Mehregani, Habid",
    "wof:placetype":"venue"
},
  "geometry": {"coordinates":[-122.971799,45.323169],"type":"Point"}
}