{
  "type": "Feature",
  "properties": {
    "iso:country":"US",
    "sg:address":"30627 Stanclift Ln",
    "sg:city":"Burns",
    "sg:classifiers":[
        {
            "category":"Building & Trades",
            "subcategory":"Electrical",
            "type":"Services"
        }
    ],
    "sg:phone":"+1 541 573 7793",
    "sg:postcode":"97720",
    "sg:province":"OR",
    "sg:tags":[
        "electrician"
    ],
    "wof:name":"Flash Electric, Inc.",
    "wof:placetype":"venue"
},
  "geometry": {"coordinates":[-119.046525,43.607504],"type":"Point"}
}