{
  "type": "Feature",
  "properties": {
    "iso:country":"US",
    "sg:address":"4844 SW Scholls Ferry Rd",
    "sg:city":"Portland",
    "sg:classifiers":[
        {
            "category":"Building & Trades",
            "subcategory":"Construction",
            "type":"Services"
        }
    ],
    "sg:phone":"+1 503 291 1905",
    "sg:postcode":"97225",
    "sg:province":"OR",
    "sg:tags":[
        "general",
        "contractor"
    ],
    "wof:name":"Denali Construction",
    "wof:placetype":"venue"
},
  "geometry": {"coordinates":[-122.749281,45.485984],"type":"Point"}
}