{
  "type": "Feature",
  "properties": {
    "iso:country":"US",
    "sg:address":"2299 NE 28th St",
    "sg:city":"Lincoln City",
    "sg:classifiers":[
        {
            "category":"Building & Trades",
            "subcategory":"Construction",
            "type":"Services"
        }
    ],
    "sg:phone":"+1 541 996 8780",
    "sg:postcode":"97367",
    "sg:province":"OR",
    "sg:tags":[
        "house"
    ],
    "wof:name":"Everyware Construction",
    "wof:placetype":"venue"
},
  "geometry": {"coordinates":[-124.00337500000001,44.985381],"type":"Point"}
}