{
  "type": "Feature",
  "properties": {
    "addr:full":"4230 NE Fremont St Portland OR 97213",
    "addr:housenumber":"4230",
    "addr:postcode":"97213",
    "addr:street":"Ne Fremont St",
    "iso:country":"US",
    "sg:address":"4230 NE Fremont St",
    "sg:city":"Portland",
    "sg:classifiers":[
        {
            "category":"Real Estate",
            "subcategory":"Surveying",
            "type":"Services"
        }
    ],
    "sg:phone":"+1 503 284 5896",
    "sg:postcode":"97213",
    "sg:province":"OR",
    "sg:tags":[
        "civil",
        "surveyor",
        "engineering",
        "land"
    ],
    "sg:website":"www.wbwells.com",
    "wof:name":"W B Wells & Associates Inc",
    "wof:placetype":"venue"
},
  "geometry": {"coordinates":[-122.61954299999999,45.548225],"type":"Point"}
}