{
  "type": "Feature",
  "properties": {
    "iso:country":"US",
    "sg:address":"167 NE Chancellor Ct",
    "sg:city":"Hillsboro",
    "sg:classifiers":[
        {
            "category":"Organizations",
            "subcategory":"Religious Organization",
            "type":"Services"
        }
    ],
    "sg:phone":"+1 503 648 1247",
    "sg:postcode":"97124",
    "sg:province":"OR",
    "wof:name":"Corporation of President of Th",
    "wof:placetype":"venue"
},
  "geometry": {"coordinates":[-122.992537,45.540097],"type":"Point"}
}