{
  "type": "Feature",
  "properties": {
    "iso:country":"US",
    "sg:address":"62778 Monroe Ln",
    "sg:city":"La Grande",
    "sg:classifiers":[
        {
            "category":"Farming",
            "subcategory":"Farm",
            "type":"Manufacturing & Wholesale Goods"
        }
    ],
    "sg:phone":"+1 541 963 3880",
    "sg:postcode":"97850",
    "sg:province":"OR",
    "sg:tags":[
        "crop",
        "general"
    ],
    "wof:name":"Gary Webster",
    "wof:placetype":"venue"
},
  "geometry": {"coordinates":[-118.046054,45.423861],"type":"Point"}
}