{
  "type": "Feature",
  "properties": {
    "iso:country":"US",
    "sg:address":"827 SW 2nd Ave",
    "sg:city":"Portland",
    "sg:classifiers":[
        {
            "category":"Restaurant",
            "type":"Food & Drink"
        }
    ],
    "sg:phone":"+1 503 241 7695",
    "sg:postcode":"97204",
    "sg:province":"OR",
    "sg:tags":[
        "vietnamese"
    ],
    "sg:website":"www.phopdx.com",
    "wof:name":"Pho PDX",
    "wof:placetype":"venue"
},
  "geometry": {"coordinates":[-122.67544100000001,45.516992],"type":"Point"}
}