{
  "type": "Feature",
  "properties": {
    "iso:country":"US",
    "sg:address":"1209 Bridge St",
    "sg:city":"Vernonia",
    "sg:classifiers":[
        {
            "category":"Government",
            "subcategory":"Office",
            "type":"Public Place"
        }
    ],
    "sg:phone":"+1 503 429 0720",
    "sg:postcode":"97064",
    "sg:province":"OR",
    "sg:tags":[
        "development"
    ],
    "wof:name":"Vernonia Community Development",
    "wof:placetype":"venue"
},
  "geometry": {"coordinates":[-123.200058,45.858727],"type":"Point"}
}