{
  "type": "Feature",
  "properties": {
    "iso:country":"US",
    "sg:address":"120 SE 172nd Ave",
    "sg:city":"Portland",
    "sg:classifiers":[
        {
            "category":"Organizations",
            "subcategory":"Religious Organization",
            "type":"Services"
        }
    ],
    "sg:phone":"+1 503 252 3595",
    "sg:postcode":"97233",
    "sg:province":"OR",
    "wof:name":"Rockford Worship Center",
    "wof:placetype":"venue"
},
  "geometry": {"coordinates":[-122.48607,45.521036],"type":"Point"}
}