{
  "type": "Feature",
  "properties": {
    "iso:country":"US",
    "sg:address":"5555 NE 18th Ave",
    "sg:city":"Portland",
    "sg:classifiers":[
        {
            "category":"Retail",
            "subcategory":"Portrait Studio",
            "type":"Services"
        }
    ],
    "sg:phone":"+1 503 284 5674",
    "sg:postcode":"97211",
    "sg:province":"OR",
    "sg:tags":[
        "photo",
        "photography",
        "commercial"
    ],
    "wof:name":"Photography By Steve Slocum",
    "wof:placetype":"venue"
},
  "geometry": {"coordinates":[-122.647088,45.564188],"type":"Point"}
}