{
  "type": "Feature",
  "properties": {
    "iso:country":"US",
    "sg:address":"17925 SW Rosa Rd",
    "sg:city":"Aloha",
    "sg:classifiers":[
        {
            "category":"Real Estate",
            "subcategory":"Real Estate Operator",
            "type":"Services"
        }
    ],
    "sg:phone":"+1 503 642 5243",
    "sg:postcode":"97007",
    "sg:province":"OR",
    "sg:tags":[
        "building",
        "apartment"
    ],
    "wof:name":"Tapiola Manor",
    "wof:placetype":"venue"
},
  "geometry": {"coordinates":[-122.861576,45.478654],"type":"Point"}
}