{
  "type": "Feature",
  "properties": {
    "iso:country":"US",
    "sg:address":"18500 SW 108th Ave",
    "sg:city":"Tualatin",
    "sg:classifiers":[
        {
            "category":"Autos & Motor Vehicles",
            "subcategory":"Automobile Sales",
            "type":"Retail Goods"
        }
    ],
    "sg:phone":"+1 503 638 6400",
    "sg:postcode":"97062",
    "sg:province":"OR",
    "sg:tags":[
        "car",
        "dealer"
    ],
    "wof:name":"Invision Outdoor Living",
    "wof:placetype":"venue"
},
  "geometry": {"coordinates":[-122.78763,45.385571],"type":"Point"}
}