{
  "type": "Feature",
  "properties": {
    "iso:country":"US",
    "sg:address":"2215 NE 45th Ave",
    "sg:city":"Portland",
    "sg:classifiers":[
        {
            "category":"Professional",
            "subcategory":"Management & Consulting",
            "type":"Services"
        }
    ],
    "sg:phone":"+1 503 284 9282",
    "sg:postcode":"97213",
    "sg:province":"OR",
    "sg:tags":[
        "product",
        "requirement",
        "integration",
        "system",
        "interface",
        "usability",
        "engineer"
    ],
    "wof:name":"David D Stubbs Consulting",
    "wof:placetype":"venue"
},
  "geometry": {"coordinates":[-122.616924,45.538507],"type":"Point"}
}