{
  "type": "Feature",
  "properties": {
    "iso:country":"US",
    "sg:address":"2327 SE Powell Blvd",
    "sg:city":"Portland",
    "sg:classifiers":[
        {
            "category":"Retail",
            "subcategory":"Auto Repair",
            "type":"Services"
        }
    ],
    "sg:phone":"+1 503 233 4809",
    "sg:postcode":"97202",
    "sg:province":"OR",
    "sg:tags":[
        "repairing",
        "automobile"
    ],
    "sg:website":"www.heckmannthiemann.com/",
    "wof:name":"Heckmann & Thiemann Motors",
    "wof:placetype":"venue"
},
  "geometry": {"coordinates":[-122.64196699999999,45.498895],"type":"Point"}
}