{
  "type": "Feature",
  "properties": {
    "addr:full":"1258 S Riverside Ave Medford OR 97501",
    "addr:housenumber":"1258",
    "addr:postcode":"97501",
    "addr:street":"S Riverside Ave",
    "iso:country":"US",
    "sg:address":"1258 S Riverside Ave",
    "sg:city":"Medford",
    "sg:classifiers":[
        {
            "category":"Autos & Motor Vehicles",
            "subcategory":"Automobile Sales",
            "type":"Retail Goods"
        }
    ],
    "sg:phone":"+1 541 734 4944",
    "sg:postcode":"97501",
    "sg:province":"OR",
    "sg:tags":[
        "car",
        "dealer"
    ],
    "wof:name":"Wolfy's Auto Sales",
    "wof:placetype":"venue"
},
  "geometry": {"coordinates":[-122.861875,42.315152],"type":"Point"}
}