{
  "type": "Feature",
  "properties": {
    "addr:full":"595 SW Division St Sherwood OR 97140",
    "addr:housenumber":"595",
    "addr:postcode":"97140",
    "addr:street":"Sw Division St",
    "iso:country":"US",
    "sg:address":"595 SW Division St",
    "sg:city":"Sherwood",
    "sg:classifiers":[
        {
            "category":"Autos & Motor Vehicles",
            "subcategory":"Automobile Sales",
            "type":"Retail Goods"
        }
    ],
    "sg:phone":"+1 503 625 6020",
    "sg:postcode":"97140",
    "sg:province":"OR",
    "sg:tags":[
        "used"
    ],
    "wof:name":"Korbad & Assoc",
    "wof:placetype":"venue"
},
  "geometry": {"coordinates":[-122.84122000000001,45.35328],"type":"Point"}
}