{
  "type": "Feature",
  "properties": {
    "iso:country":"US",
    "sg:address":"34254 Millard Rd",
    "sg:city":"Warren",
    "sg:classifiers":[
        {
            "category":"Home & Garden",
            "subcategory":"Furniture",
            "type":"Retail Goods"
        }
    ],
    "sg:phone":"+1 503 397 1369",
    "sg:postcode":"97053",
    "sg:province":"OR",
    "sg:tags":[
        "floor",
        "laying",
        "contractor"
    ],
    "wof:name":"Jack Broders Installer",
    "wof:placetype":"venue"
},
  "geometry": {"coordinates":[-122.862159,45.840832],"type":"Point"}
}