{
  "type": "Feature",
  "properties": {
    "iso:country":"US",
    "sg:address":"2630 US Hwy 101",
    "sg:city":"Florence",
    "sg:classifiers":[
        {
            "category":"Autos & Motor Vehicles",
            "subcategory":"Automobile Sales",
            "type":"Retail Goods"
        }
    ],
    "sg:phone":"+1 541 997 7101",
    "sg:postcode":"97439",
    "sg:province":"OR",
    "sg:tags":[
        "car",
        "dealer"
    ],
    "sg:website":"www.dunhammotors.com",
    "wof:name":"Dunham Motors Chevrolet Buick",
    "wof:placetype":"venue"
},
  "geometry": {"coordinates":[-124.101304,43.989893],"type":"Point"}
}