{
  "type": "Feature",
  "properties": {
    "iso:country":"US",
    "sg:address":"2378 State St",
    "sg:city":"Salem",
    "sg:classifiers":[
        {
            "category":"Education",
            "subcategory":"Special Training",
            "type":"Public Place"
        }
    ],
    "sg:phone":"+1 503 363 0993",
    "sg:postcode":"97301",
    "sg:province":"OR",
    "sg:tags":[
        "reading",
        "instruction",
        "improvement"
    ],
    "wof:name":"SPNC Education Annex",
    "wof:placetype":"venue"
},
  "geometry": {"coordinates":[-123.012106,44.933032],"type":"Point"}
}