{
  "type": "Feature",
  "properties": {
    "iso:country":"US",
    "sg:address":"63043 Plateau Dr",
    "sg:city":"Bend",
    "sg:classifiers":[
        {
            "category":"Retail",
            "subcategory":"Car Wash",
            "type":"Services"
        }
    ],
    "sg:phone":"+1 541 317 0992",
    "sg:postcode":"97701",
    "sg:province":"OR",
    "sg:tags":[
        "automobile",
        "detail",
        "clean"
    ],
    "wof:name":"Rods Automotive Detailing",
    "wof:placetype":"venue"
},
  "geometry": {"coordinates":[-121.29311199999999,44.087524],"type":"Point"}
}