{
  "type": "Feature",
  "properties": {
    "iso:country":"US",
    "sg:address":"27350 SW 95th Ave",
    "sg:city":"Wilsonville",
    "sg:classifiers":[
        {
            "category":"Airline",
            "type":"Transportation"
        },
        {
            "category":"Travel",
            "subcategory":"Travel Agent",
            "type":"Entertainment"
        }
    ],
    "sg:phone":"+1 503 682 6800",
    "sg:postcode":"97070",
    "sg:province":"OR",
    "sg:tags":[
        "ticket",
        "agency",
        "services-commercial"
    ],
    "wof:name":"Uniglobe Panorama Travel",
    "wof:placetype":"venue"
},
  "geometry": {"coordinates":[-122.77243300000001,45.322157],"type":"Point"}
}