{
  "type": "Feature",
  "properties": {
    "addr:full":"4784 S Hwy 97 Redmond OR 97756",
    "addr:housenumber":"4784",
    "addr:postcode":"97756",
    "addr:street":"S Hwy 97",
    "iso:country":"US",
    "sg:address":"4784 S Hwy 97",
    "sg:city":"Redmond",
    "sg:classifiers":[
        {
            "category":"Professional",
            "subcategory":"Management & Consulting",
            "type":"Services"
        }
    ],
    "sg:phone":"+1 541 316 4800",
    "sg:postcode":"97756",
    "sg:province":"OR",
    "sg:tags":[
        "consultant",
        "educational"
    ],
    "sg:website":"www.sagewalk.com",
    "wof:name":"Sagewalk-Wilderness School",
    "wof:placetype":"venue"
},
  "geometry": {"coordinates":[-121.203536,44.231567],"type":"Point"}
}