{
  "type": "Feature",
  "properties": {
    "iso:country":"US",
    "sg:address":"4714 SE 82nd Ave",
    "sg:city":"Portland",
    "sg:classifiers":[
        {
            "category":"Autos & Motor Vehicles",
            "subcategory":"Automobile Sales",
            "type":"Retail Goods"
        }
    ],
    "sg:phone":"+1 503 777 4646",
    "sg:postcode":"97266",
    "sg:province":"OR",
    "sg:tags":[
        "car",
        "dealer"
    ],
    "wof:name":"Steve's Auto Sales",
    "wof:placetype":"venue"
},
  "geometry": {"coordinates":[-122.578739,45.489625],"type":"Point"}
}