{
  "type": "Feature",
  "properties": {
    "addr:full":"16026 SE Stark St Portland OR 97233",
    "addr:postcode":"16026;97233",
    "addr:street":"Se Stark St",
    "iso:country":"US",
    "sg:address":"16026 SE Stark St",
    "sg:city":"Portland",
    "sg:classifiers":[
        {
            "category":"Shopping",
            "subcategory":"Department Store",
            "type":"Retail Goods"
        }
    ],
    "sg:phone":"+1 503 255 1717",
    "sg:postcode":"97233",
    "sg:province":"OR",
    "wof:name":"Dollar Planet",
    "wof:placetype":"venue"
},
  "geometry": {"coordinates":[-122.49841000000001,45.519079],"type":"Point"}
}