{
  "type": "Feature",
  "properties": {
    "iso:country":"US",
    "sg:address":"3160 SW Dover Ln",
    "sg:city":"Madras",
    "sg:classifiers":[
        {
            "category":"Farming",
            "subcategory":"Livestock Farm",
            "type":"Manufacturing & Wholesale Goods"
        }
    ],
    "sg:phone":"+1 541 546 5563",
    "sg:postcode":"97741",
    "sg:province":"OR",
    "sg:tags":[
        "horse",
        "breed"
    ],
    "wof:name":"Janis Dinkel",
    "wof:placetype":"venue"
},
  "geometry": {"coordinates":[-121.193664,44.592035],"type":"Point"}
}