{
  "type": "Feature",
  "properties": {
    "addr:full":"11945 SW Pacific Hwy Portland OR 97223",
    "addr:housenumber":"11945",
    "addr:postcode":"97223",
    "addr:street":"Sw Pacific Hwy",
    "iso:country":"US",
    "sg:address":"11945 SW Pacific Hwy",
    "sg:city":"Portland",
    "sg:classifiers":[
        {
            "category":"Shopping",
            "subcategory":"Crafts & Fabrics",
            "type":"Retail Goods"
        }
    ],
    "sg:phone":"+1 503 684 4851",
    "sg:postcode":"97223",
    "sg:province":"OR",
    "sg:tags":[
        "knitting",
        "supply"
    ],
    "sg:website":"http://www.allaboutyarn.net",
    "wof:name":"All About Yarn",
    "wof:placetype":"venue"
},
  "geometry": {"coordinates":[-122.76559399999999,45.433784],"type":"Point"}
}