{
  "type": "Feature",
  "properties": {
    "iso:country":"US",
    "sg:address":"744 Amhurst Way",
    "sg:city":"Medford",
    "sg:classifiers":[
        {
            "category":"Building & Trades",
            "subcategory":"Construction",
            "type":"Services"
        }
    ],
    "sg:phone":"+1 541 778 1532",
    "sg:postcode":"97504",
    "sg:province":"OR",
    "sg:tags":[
        "wallcoverings-installation",
        "wallpaper",
        "painting",
        "contractor"
    ],
    "wof:name":"Nancy Painter",
    "wof:placetype":"venue"
},
  "geometry": {"coordinates":[-122.814165,42.315055],"type":"Point"}
}