{
  "type": "Feature",
  "properties": {
    "iso:country":"US",
    "sg:address":"28500 SE Orient Dr",
    "sg:city":"Gresham",
    "sg:classifiers":[
        {
            "category":"Manufacturing",
            "subcategory":"Chemicals & Compounds",
            "type":"Manufacturing & Wholesale Goods"
        }
    ],
    "sg:phone":"+1 503 663 0164",
    "sg:postcode":"97080",
    "sg:province":"OR",
    "sg:tags":[
        "fertilizer",
        "mixing",
        "only"
    ],
    "wof:name":"United Horticultural Supply",
    "wof:placetype":"venue"
},
  "geometry": {"coordinates":[-122.36424,45.470611],"type":"Point"}
}