{
  "type": "Feature",
  "properties": {
    "iso:country":"US",
    "sg:address":"3833 NE M L King Blvd",
    "sg:city":"Portland",
    "sg:classifiers":[
        {
            "category":"Restaurant",
            "type":"Food & Drink"
        }
    ],
    "sg:phone":"+1 503 284 3134",
    "sg:postcode":"97212",
    "sg:province":"OR",
    "wof:name":"Aunt's Kitchen",
    "wof:placetype":"venue"
},
  "geometry": {"coordinates":[-122.661647,45.549948],"type":"Point"}
}