{
  "type": "Feature",
  "properties": {
    "addr:full":"811 E Burnside St Portland OR 97214",
    "addr:housenumber":"811",
    "addr:postcode":"97214",
    "addr:street":"E Burnside St",
    "iso:country":"US",
    "sg:address":"811 E Burnside St",
    "sg:city":"Portland",
    "sg:classifiers":[
        {
            "category":"Building & Trades",
            "subcategory":"Construction",
            "type":"Services"
        }
    ],
    "sg:phone":"+1 503 236 4500",
    "sg:postcode":"97214",
    "sg:province":"OR",
    "sg:tags":[
        "general",
        "contractor"
    ],
    "wof:name":"Adaptive Construction",
    "wof:placetype":"venue"
},
  "geometry": {"coordinates":[-122.656721,45.522993],"type":"Point"}
}