{
  "type": "Feature",
  "properties": {
    "addr:full":"2125 SE Main St Portland OR 97214",
    "addr:housenumber":"2125",
    "addr:postcode":"97214",
    "addr:street":"Se Main St",
    "iso:country":"US",
    "sg:address":"2125 SE Main St",
    "sg:city":"Portland",
    "sg:classifiers":[
        {
            "category":"Real Estate",
            "subcategory":"Architect",
            "type":"Services"
        }
    ],
    "sg:phone":"+1 503 230 2842",
    "sg:postcode":"97214",
    "sg:province":"OR",
    "sg:tags":[
        "architects'",
        "builders'",
        "model",
        "architectural",
        "maker"
    ],
    "sg:website":"http://www.architectural-prototypes.com",
    "wof:name":"Architectural Prototypes",
    "wof:placetype":"venue"
},
  "geometry": {"coordinates":[-122.644319,45.513607],"type":"Point"}
}