{
  "type": "Feature",
  "properties": {
    "iso:country":"US",
    "sg:address":"110 SE 16th Ave",
    "sg:city":"Portland",
    "sg:classifiers":[
        {
            "category":"Health Services",
            "subcategory":"Clinic",
            "type":"Services"
        }
    ],
    "sg:phone":"+1 503 957 3391",
    "sg:postcode":"97214",
    "sg:province":"OR",
    "sg:tags":[
        "counseling",
        "mental"
    ],
    "sg:website":"markgundry.com",
    "wof:name":"Portland Therapy - Mark Gundry, MA, PhD",
    "wof:placetype":"venue"
},
  "geometry": {"coordinates":[-122.649535,45.522115],"type":"Point"}
}