{
  "type": "Feature",
  "properties": {
    "iso:country":"US",
    "sg:address":"20235 Silver Sage St",
    "sg:city":"Bend",
    "sg:classifiers":[
        {
            "category":"Building & Trades",
            "subcategory":"Cleaning & Sanitation",
            "type":"Services"
        },
        {
            "category":"Building & Trades",
            "subcategory":"Construction",
            "type":"Services"
        }
    ],
    "sg:phone":"+1 541 382 8033",
    "sg:postcode":"97702",
    "sg:province":"OR",
    "sg:tags":[
        "handyman",
        "maintenance"
    ],
    "wof:name":"Doug's Home Maintenance & Rpr",
    "wof:placetype":"venue"
},
  "geometry": {"coordinates":[-121.31297,44.021153],"type":"Point"}
}