{
  "type": "Feature",
  "properties": {
    "addr:full":"207 8th St Oregon City OR 97045",
    "addr:housenumber":"207",
    "addr:postcode":"97045",
    "addr:street":"8Th St",
    "iso:country":"US",
    "sg:address":"207 8th St",
    "sg:city":"Oregon City",
    "sg:classifiers":[
        {
            "category":"Home & Garden",
            "subcategory":"Carpets & Floor Coverings",
            "type":"Retail Goods"
        }
    ],
    "sg:phone":"+1 503 656 2376",
    "sg:postcode":"97045",
    "sg:province":"OR",
    "sg:tags":[
        "tile",
        "vinyl",
        "install"
    ],
    "wof:name":"Carpet Den Inc",
    "wof:placetype":"venue"
},
  "geometry": {"coordinates":[-122.606809,45.357881],"type":"Point"}
}