{
  "type": "Feature",
  "properties": {
    "addr:full":"13050 Kirkwood Rd NW Salem OR 97304",
    "addr:housenumber":"13050",
    "addr:postcode":"97304",
    "addr:street":"Kirkwood Rd Nw",
    "iso:country":"US",
    "sg:address":"13050 Kirkwood Rd NW",
    "sg:city":"Salem",
    "sg:classifiers":[
        {
            "category":"Home & Garden",
            "subcategory":"Garden Supply",
            "type":"Retail Goods"
        }
    ],
    "sg:phone":"+1 503 868 7249",
    "sg:postcode":"97304",
    "sg:province":"OR",
    "wof:name":"Gypsy Spirit Nursery",
    "wof:placetype":"venue"
},
  "geometry": {"coordinates":[-123.104372,45.078863],"type":"Point"}
}