{
  "type": "Feature",
  "properties": {
    "iso:country":"US",
    "sg:address":"1155 Santiam Hwy SE",
    "sg:city":"Albany",
    "sg:classifiers":[
        {
            "category":"Personal",
            "subcategory":"Tanning Parlor",
            "type":"Services"
        }
    ],
    "sg:phone":"+1 541 917 0009",
    "sg:postcode":"97321",
    "sg:province":"OR",
    "sg:tags":[
        "salon"
    ],
    "wof:name":"Rasta Tan",
    "wof:placetype":"venue"
},
  "geometry": {"coordinates":[-123.091199,44.636676],"type":"Point"}
}