{
  "type": "Feature",
  "properties": {
    "iso:country":"US",
    "sg:address":"30549 Camas Swale Rd",
    "sg:city":"Creswell",
    "sg:classifiers":[
        {
            "category":"Retail",
            "subcategory":"Animal Services",
            "type":"Services"
        }
    ],
    "sg:phone":"+1 541 895 3699",
    "sg:postcode":"97426",
    "sg:province":"OR",
    "wof:name":"Chanson Dusoir Farms",
    "wof:placetype":"venue"
},
  "geometry": {"coordinates":[-123.138419,43.917525],"type":"Point"}
}