{
  "type": "Feature",
  "properties": {
    "iso:country":"US",
    "sg:address":"8464 N Hendricks St",
    "sg:city":"Portland",
    "sg:classifiers":[
        {
            "category":"Professional",
            "type":"Services"
        }
    ],
    "sg:phone":"+1 503 286 1451",
    "sg:postcode":"97203",
    "sg:province":"OR",
    "sg:tags":[
        "establishment"
    ],
    "wof:name":"Host Developement Inc",
    "wof:placetype":"venue"
},
  "geometry": {"coordinates":[-122.748407,45.600659],"type":"Point"}
}