{
  "type": "Feature",
  "properties": {
    "addr:full":"1708 S Sandoz Rd Newberg OR 97132",
    "addr:housenumber":"1708",
    "addr:postcode":"97132",
    "addr:street":"S Sandoz Rd",
    "iso:country":"US",
    "sg:address":"1708 S Sandoz Rd",
    "sg:city":"Newberg",
    "sg:classifiers":[
        {
            "category":"Building & Trades",
            "subcategory":"Construction",
            "type":"Services"
        }
    ],
    "sg:phone":"+1 503 538 1919",
    "sg:postcode":"97132",
    "sg:province":"OR",
    "sg:tags":[
        "concrete",
        "contractor"
    ],
    "wof:name":"Salmon Concrete",
    "wof:placetype":"venue"
},
  "geometry": {"coordinates":[-122.94795999999999,45.287215],"type":"Point"}
}