{
  "type": "Feature",
  "properties": {
    "iso:country":"US",
    "sg:address":"114 W Main St",
    "sg:city":"Enterprise",
    "sg:classifiers":[
        {
            "category":"Shopping",
            "subcategory":"Florist",
            "type":"Retail Goods"
        }
    ],
    "sg:phone":"+1 541 426 3060",
    "sg:postcode":"97828",
    "sg:province":"OR",
    "wof:name":"Candy Bouquet",
    "wof:placetype":"venue"
},
  "geometry": {"coordinates":[-117.27874,45.425438],"type":"Point"}
}