{
  "type": "Feature",
  "properties": {
    "addr:full":"215 E Beacon Dr Eugene OR 97404",
    "addr:housenumber":"215",
    "addr:postcode":"97404",
    "addr:street":"E Beacon Dr",
    "iso:country":"US",
    "sg:address":"215 E Beacon Dr",
    "sg:city":"Eugene",
    "sg:classifiers":[
        {
            "category":"Professional",
            "subcategory":"Management & Consulting",
            "type":"Services"
        }
    ],
    "sg:phone":"+1 541 689 2813",
    "sg:postcode":"97404",
    "sg:province":"OR",
    "sg:tags":[
        "selling",
        "establishment",
        "direct"
    ],
    "wof:name":"Shaklee Authorized Distr",
    "wof:placetype":"venue"
},
  "geometry": {"coordinates":[-123.140314,44.131988],"type":"Point"}
}