{
  "type": "Feature",
  "properties": {
    "iso:country":"US",
    "sg:address":"8580 NE 47th Ave",
    "sg:city":"Portland",
    "sg:classifiers":[
        {
            "category":"Airline",
            "type":"Transportation"
        }
    ],
    "sg:phone":"+1 503 280 0306",
    "sg:postcode":"97218",
    "sg:province":"OR",
    "sg:tags":[
        "cargo",
        "air"
    ],
    "sg:website":"www.ameriflight.com",
    "wof:name":"Ameriflight",
    "wof:placetype":"venue"
},
  "geometry": {"coordinates":[-122.61506900000001,45.58146],"type":"Point"}
}