{
  "type": "Feature",
  "properties": {
    "iso:country":"US",
    "sg:address":"202 NE 181st Ave",
    "sg:city":"Portland",
    "sg:classifiers":[
        {
            "category":"Professional",
            "subcategory":"Management & Consulting",
            "type":"Services"
        }
    ],
    "sg:phone":"+1 503 666 8538",
    "sg:postcode":"97230",
    "sg:province":"OR",
    "sg:tags":[
        "marketing",
        "consultant"
    ],
    "wof:name":"Peniche & Assoc",
    "wof:placetype":"venue"
},
  "geometry": {"coordinates":[-122.47699799999999,45.52419],"type":"Point"}
}