{
  "type": "Feature",
  "properties": {
    "addr:full":"34330 NE Wilsonville Rd Newberg OR 97132",
    "addr:housenumber":"34330",
    "addr:postcode":"97132",
    "addr:street":"Ne Wilsonville Rd",
    "iso:country":"US",
    "sg:address":"34330 NE Wilsonville Rd",
    "sg:city":"Newberg",
    "sg:classifiers":[
        {
            "category":"Professional",
            "subcategory":"Computer Services",
            "type":"Services"
        }
    ],
    "sg:phone":"+1 503 625 6318",
    "sg:postcode":"97132",
    "sg:province":"OR",
    "sg:tags":[
        "prepackaged",
        "software"
    ],
    "wof:name":"Cinnamon Software",
    "wof:placetype":"venue"
},
  "geometry": {"coordinates":[-122.885233,45.258666],"type":"Point"}
}