{
  "type": "Feature",
  "properties": {
    "iso:country":"US",
    "sg:address":"8303 SE Powell Blvd",
    "sg:city":"Portland",
    "sg:classifiers":[
        {
            "category":"Restaurant",
            "type":"Food & Drink"
        },
        {
            "category":"Food & Beverages",
            "subcategory":"Bakery",
            "type":"Retail Goods"
        }
    ],
    "sg:phone":"+1 503 788 3098",
    "sg:postcode":"97253",
    "sg:province":"OR",
    "sg:tags":[
        "sandwich",
        "vietnamese"
    ],
    "sg:website":"www.thebestbaguette.com",
    "wof:name":"Best Baguette",
    "wof:placetype":"venue"
},
  "geometry": {"coordinates":[-122.57751,45.497401],"type":"Point"}
}