{
  "type": "Feature",
  "properties": {
    "iso:country":"US",
    "sg:address":"59410 Seven Devils Rd",
    "sg:city":"Bandon",
    "sg:classifiers":[
        {
            "category":"Travel",
            "subcategory":"Travel Agent",
            "type":"Entertainment"
        }
    ],
    "sg:phone":"+1 541 347 4436",
    "sg:postcode":"97411",
    "sg:province":"OR",
    "sg:tags":[
        "agency",
        "bureau"
    ],
    "wof:name":"Bandon By The Sea Travel",
    "wof:placetype":"venue"
},
  "geometry": {"coordinates":[-124.384739,43.23412],"type":"Point"}
}