{
  "type": "Feature",
  "properties": {
    "addr:full":"17111 NE Sandy Blvd Portland OR 97230",
    "addr:housenumber":"17111",
    "addr:postcode":"97230",
    "addr:street":"Ne Sandy Blvd",
    "iso:country":"US",
    "sg:address":"17111 NE Sandy Blvd",
    "sg:city":"Portland",
    "sg:classifiers":[
        {
            "category":"Museum",
            "type":"Entertainment"
        }
    ],
    "sg:phone":"+1 503 261 8078",
    "sg:postcode":"97230",
    "sg:province":"OR",
    "wof:name":"Frw Historical Society",
    "wof:placetype":"venue"
},
  "geometry": {"coordinates":[-122.488243,45.548199],"type":"Point"}
}