{
  "type": "Feature",
  "properties": {
    "addr:city":"Portland",
    "addr:full":"17111 Ne Sandy Blvd Portland, Or 97230",
    "addr:house_number":"17111",
    "addr:housenumber":"17111",
    "addr:phone":"+1 503-261-8078",
    "addr:postcode":"97230",
    "addr:road":"Ne Sandy Blvd",
    "addr:state":"OR",
    "addr:street":"Ne Sandy Blvd",
    "iso:country":"US",
    "sg:address":"17111 NE Sandy Blvd",
    "sg:city":"Portland",
    "sg:classifiers":[
        {
            "category":"Museum",
            "type":"Entertainment"
        }
    ],
    "sg:phone":"+1 503 261 8078",
    "sg:postcode":"97230",
    "sg:province":"OR",
    "wof:airports":[
        102532251
    ],
    "wof:name":"Frw Historical Society",
    "wof:placetype":"venue"
},
  "geometry": {"coordinates":[-122.48684,45.54787],"type":"Point"}
}