{
  "type": "Feature",
  "properties": {
    "iso:country":"US",
    "sg:address":"17185 SE McLoughlin Blvd",
    "sg:city":"Portland",
    "sg:classifiers":[
        {
            "category":"Government",
            "subcategory":"Office",
            "type":"Public Place"
        }
    ],
    "sg:phone":"+1 503 654 5335",
    "sg:postcode":"97267",
    "sg:province":"OR",
    "sg:tags":[
        "recruiting"
    ],
    "wof:name":"Air Force Recruiter",
    "wof:placetype":"venue"
},
  "geometry": {"coordinates":[-122.620276,45.401592],"type":"Point"}
}