{
  "type": "Feature",
  "properties": {
    "iso:country":"US",
    "sg:address":"4095 NW Susbauer Rd",
    "sg:city":"Cornelius",
    "sg:classifiers":[
        {
            "category":"Professional",
            "subcategory":"Research",
            "type":"Services"
        }
    ],
    "sg:phone":"+1 503 693 7111",
    "sg:postcode":"97113",
    "sg:province":"OR",
    "sg:tags":[
        "ergonomics"
    ],
    "wof:name":"Varchan Environmental Constr",
    "wof:placetype":"venue"
},
  "geometry": {"coordinates":[-123.038034,45.548648],"type":"Point"}
}