{
  "type": "Feature",
  "properties": {
    "addr:full":"14600 SE Sunnyside Rd Clackamas OR 97015",
    "addr:postcode":"14600;97015",
    "addr:street":"Se Sunnyside Rd",
    "iso:country":"US",
    "sg:address":"14600 SE Sunnyside Rd",
    "sg:city":"Clackamas",
    "sg:classifiers":[
        {
            "category":"Restaurant",
            "type":"Food & Drink"
        }
    ],
    "sg:phone":"+1 503 658 3863",
    "sg:postcode":"97015",
    "sg:province":"OR",
    "sg:tags":[
        "style",
        "family"
    ],
    "wof:name":"Ils Wayport",
    "wof:placetype":"venue"
},
  "geometry": {"coordinates":[-122.513096,45.424853],"type":"Point"}
}