{
  "type": "Feature",
  "properties": {
    "addr:full":"33500 E Columbia Ave Scappoose OR 97056",
    "addr:housenumber":"33500",
    "addr:postcode":"97056",
    "addr:street":"E Columbia Ave",
    "iso:country":"US",
    "sg:address":"33500 E Columbia Ave",
    "sg:city":"Scappoose",
    "sg:classifiers":[
        {
            "category":"Shopping",
            "subcategory":"Used Merchandise",
            "type":"Retail Goods"
        },
        {
            "category":"Professional",
            "type":"Services"
        }
    ],
    "sg:phone":"+1 503 543 2006",
    "sg:postcode":"97056",
    "sg:province":"OR",
    "sg:tags":[
        "antique"
    ],
    "wof:name":"Floeters Attic",
    "wof:placetype":"venue"
},
  "geometry": {"coordinates":[-122.877548,45.757723],"type":"Point"}
}