{
  "type": "Feature",
  "properties": {
    "iso:country":"US",
    "sg:address":"13880 SW Pacific Hwy",
    "sg:city":"Portland",
    "sg:classifiers":[
        {
            "category":"Retail",
            "subcategory":"Auto Repair",
            "type":"Services"
        }
    ],
    "sg:phone":"+1 503 639 4100",
    "sg:postcode":"97223",
    "sg:province":"OR",
    "wof:name":"Nelsen's Complete Auto Care",
    "wof:placetype":"venue"
},
  "geometry": {"coordinates":[-122.786659,45.419427],"type":"Point"}
}