{
  "type": "Feature",
  "properties": {
    "addr:full":"31001 Willoway Dr SW Albany OR 97321",
    "addr:postcode":"31001;97321",
    "addr:street":"Willoway Dr Sw",
    "iso:country":"US",
    "sg:address":"31001 Willoway Dr SW",
    "sg:city":"Albany",
    "sg:classifiers":[
        {
            "category":"Recreation",
            "type":"Entertainment"
        }
    ],
    "sg:phone":"+1 541 928 1484",
    "sg:postcode":"97321",
    "sg:province":"OR",
    "sg:tags":[
        "stable"
    ],
    "wof:name":"Holifield Equestrian Ctr",
    "wof:placetype":"venue"
},
  "geometry": {"coordinates":[-123.14655,44.595622],"type":"Point"}
}