{
  "type": "Feature",
  "properties": {
    "iso:country":"US",
    "sg:address":"3500 N Victory Blvd",
    "sg:city":"Portland",
    "sg:classifiers":[
        {
            "category":"Sports & Exercise",
            "subcategory":"Golf",
            "type":"Entertainment"
        }
    ],
    "sg:phone":"+1 503 289 1818",
    "sg:postcode":"97217",
    "sg:province":"OR",
    "sg:website":"heronlakesgolf.com",
    "wof:name":"Heron Lakes Golf Course",
    "wof:placetype":"venue"
},
  "geometry": {"coordinates":[-122.699136,45.601365],"type":"Point"}
}