{
  "type": "Feature",
  "properties": {
    "iso:country":"US",
    "sg:address":"1915 Hazel St",
    "sg:city":"Medford",
    "sg:classifiers":[
        {
            "category":"Education",
            "subcategory":"Library",
            "type":"Public Place"
        }
    ],
    "sg:phone":"+1 541 776 7293",
    "sg:postcode":"97501",
    "sg:province":"OR",
    "sg:tags":[
        "executive"
    ],
    "wof:name":"Jackson County Library System",
    "wof:placetype":"venue"
},
  "geometry": {"coordinates":[-122.886774,42.347229],"type":"Point"}
}