{
  "type": "Feature",
  "properties": {
    "addr:full":"580 SE 1st St Toledo OR 97391",
    "addr:housenumber":"580",
    "addr:postcode":"97391",
    "addr:street":"Se 1St St",
    "iso:country":"US",
    "sg:address":"580 SE 1st St",
    "sg:city":"Toledo",
    "sg:classifiers":[
        {
            "category":"Wholesale",
            "subcategory":"Construction Materials",
            "type":"Manufacturing & Wholesale Goods"
        }
    ],
    "sg:phone":"+1 541 336 3819",
    "sg:postcode":"97391",
    "sg:province":"OR",
    "sg:tags":[
        "timberland",
        "company",
        "timber"
    ],
    "wof:name":"Timber Co",
    "wof:placetype":"venue"
},
  "geometry": {"coordinates":[-123.931496,44.619833],"type":"Point"}
}