{
  "type": "Feature",
  "properties": {
    "addr:full":"1515 N Pacific Hwy Woodburn OR 97071",
    "addr:housenumber":"1515",
    "addr:postcode":"97071",
    "addr:street":"N Pacific Hwy",
    "iso:country":"US",
    "sg:address":"1515 N Pacific Hwy",
    "sg:city":"Woodburn",
    "sg:classifiers":[
        {
            "category":"Utilities",
            "subcategory":"Mobile Phone",
            "type":"Services"
        },
        {
            "category":"Shopping",
            "subcategory":"Mobile Phones",
            "type":"Retail Goods"
        },
        {
            "category":"Utilities",
            "subcategory":"Telephone",
            "type":"Services"
        },
        {
            "category":"Professional",
            "subcategory":"Computer Services",
            "type":"Services"
        }
    ],
    "sg:phone":"+1 503 982 5115",
    "sg:postcode":"97071",
    "sg:province":"OR",
    "sg:tags":[
        "telecommunication",
        "supply",
        "communication",
        "system",
        "wireless",
        "equipment",
        "cellular"
    ],
    "sg:website":"http://clickserve.dartsearch.net/link/click?lid=43000000308049899",
    "wof:name":"T-Mobile",
    "wof:placetype":"venue"
},
  "geometry": {"coordinates":[-122.832954,45.149341],"type":"Point"}
}