{
  "type": "Feature",
  "properties": {
    "iso:country":"US",
    "sg:address":"10123 SE Market St",
    "sg:city":"Portland",
    "sg:classifiers":[
        {
            "category":"Health Services",
            "subcategory":"Doctor",
            "type":"Services"
        },
        {
            "category":"Health Services",
            "subcategory":"Clinic",
            "type":"Services"
        },
        {
            "category":"Community Center",
            "type":"Public Place"
        }
    ],
    "sg:phone":"+1 503 251 6305",
    "sg:postcode":"97216",
    "sg:province":"OR",
    "sg:tags":[
        "physician",
        "oncology",
        "surgeons",
        "medical",
        "radiation",
        "osteopathic",
        "surgeon",
        "gynecologic"
    ],
    "wof:name":"Adventist Medical Center-Radiation Oncology Department",
    "wof:placetype":"venue"
},
  "geometry": {"coordinates":[-122.559708,45.511292],"type":"Point"}
}