{
  "type": "Feature",
  "properties": {
    "iso:country":"US",
    "sg:address":"2740 S 6th St",
    "sg:city":"Klamath Falls",
    "sg:classifiers":[
        {
            "category":"Coffee & Tea",
            "type":"Food & Drink"
        }
    ],
    "sg:menulink":"http://www.allmenus.com/or/klamath-falls/119383-starbucks-coffee/menu/",
    "sg:phone":"+1 541 273 3510",
    "sg:postcode":"97603",
    "sg:province":"OR",
    "sg:tags":[
        "american"
    ],
    "wof:name":"Starbucks Coffee",
    "wof:placetype":"venue"
},
  "geometry": {"coordinates":[-121.75553499999999,42.210504],"type":"Point"}
}