{
  "type": "Feature",
  "properties": {
    "iso:country":"US",
    "sg:address":"9185 SW 91st Ave",
    "sg:city":"Portland",
    "sg:classifiers":[
        {
            "category":"Professional",
            "subcategory":"Management & Consulting",
            "type":"Services"
        }
    ],
    "sg:phone":"+1 503 892 1824",
    "sg:postcode":"97223",
    "sg:province":"OR",
    "wof:name":"Internet Marketing Results",
    "wof:placetype":"venue"
},
  "geometry": {"coordinates":[-122.770672,45.454867],"type":"Point"}
}