{
  "type": "Feature",
  "properties": {
    "iso:country":"US",
    "sg:address":"14333 SE Wagner Lane",
    "sg:city":"Portland",
    "sg:classifiers":[
        {
            "category":"Shopping",
            "subcategory":"Antiques",
            "type":"Retail Goods"
        }
    ],
    "sg:phone":"+1 503 653 2605",
    "sg:postcode":"97267",
    "sg:province":"OR",
    "wof:name":"Vanderpool Paul",
    "wof:placetype":"venue"
},
  "geometry": {"coordinates":[-122.65265599999999,45.417724],"type":"Point"}
}