{
  "type": "Feature",
  "properties": {
    "iso:country":"US",
    "sg:address":"17496 SE Hemrick Rd",
    "sg:city":"Damascus",
    "sg:classifiers":[
        {
            "category":"Farming",
            "subcategory":"Livestock Farm",
            "type":"Manufacturing & Wholesale Goods"
        }
    ],
    "sg:phone":"+1 503 658 7603",
    "sg:postcode":"97089",
    "sg:province":"OR",
    "sg:tags":[
        "beekeeper",
        "specialty",
        "animal"
    ],
    "wof:name":"Bee Way Honey Pollination",
    "wof:placetype":"venue"
},
  "geometry": {"coordinates":[-122.482693,45.446621],"type":"Point"}
}