{
  "type": "Feature",
  "properties": {
    "addr:full":"38374 Highway 226 Scio OR 97374",
    "addr:housenumber":"38374",
    "addr:postcode":"97374",
    "addr:street":"Highway 226",
    "iso:country":"US",
    "sg:address":"38374 Highway 226",
    "sg:city":"Scio",
    "sg:classifiers":[
        {
            "category":"Building & Trades",
            "subcategory":"Construction",
            "type":"Services"
        }
    ],
    "sg:phone":"+1 503 394 2689",
    "sg:postcode":"97374",
    "sg:province":"OR",
    "sg:tags":[
        "system",
        "specialty",
        "heating",
        "contractor",
        "air conditioning"
    ],
    "sg:website":"http://www.chrishickok.com",
    "wof:name":"A C & Heating By Chris Hickok",
    "wof:placetype":"venue"
},
  "geometry": {"coordinates":[-122.844915,44.6783],"type":"Point"}
}