{
  "type": "Feature",
  "properties": {
    "iso:country":"US",
    "sg:address":"818 NW 17th Ave",
    "sg:city":"Portland",
    "sg:classifiers":[
        {
            "category":"Social Services",
            "type":"Services"
        }
    ],
    "sg:phone":"+1 503 222 1407",
    "sg:postcode":"97209",
    "sg:province":"OR",
    "sg:tags":[
        "health"
    ],
    "wof:name":"Joan Behn Dayger PHD",
    "wof:placetype":"venue"
},
  "geometry": {"coordinates":[-122.688362,45.529134],"type":"Point"}
}