{
  "type": "Feature",
  "properties": {
    "addr:full":"14633 S Holcomb Blvd Oregon City OR 97045",
    "addr:housenumber":"14633",
    "addr:postcode":"97045",
    "addr:street":"S Holcomb Blvd",
    "iso:country":"US",
    "sg:address":"14633 S Holcomb Blvd",
    "sg:city":"Oregon City",
    "sg:classifiers":[
        {
            "category":"Building & Trades",
            "subcategory":"Cleaning & Sanitation",
            "type":"Services"
        }
    ],
    "sg:phone":"+1 503 650 6181",
    "sg:postcode":"97045",
    "sg:province":"OR",
    "sg:tags":[
        "maintenance"
    ],
    "wof:name":"R & Js Cleaning Service",
    "wof:placetype":"venue"
},
  "geometry": {"coordinates":[-122.565107,45.372366],"type":"Point"}
}