{
  "type": "Feature",
  "properties": {
    "addr:full":"15608 SE Morrison St Portland OR 97233",
    "addr:postcode":"15608;97233",
    "addr:street":"Se Morrison St",
    "iso:country":"US",
    "sg:address":"15608 SE Morrison St",
    "sg:city":"Portland",
    "sg:classifiers":[
        {
            "category":"Home & Garden",
            "subcategory":"Carpets & Floor Coverings",
            "type":"Retail Goods"
        }
    ],
    "sg:phone":"+1 503 253 6264",
    "sg:postcode":"97233",
    "sg:province":"OR",
    "wof:name":"Gentle Giant Cus Carpets",
    "wof:placetype":"venue"
},
  "geometry": {"coordinates":[-122.502683,45.516628],"type":"Point"}
}