{
  "type": "Feature",
  "properties": {
    "iso:country":"US",
    "sg:address":"1611 SE Lava Dr",
    "sg:city":"Portland",
    "sg:classifiers":[
        {
            "category":"Real Estate",
            "subcategory":"Real Estate Operator",
            "type":"Services"
        }
    ],
    "sg:phone":"+1 503 659 2777",
    "sg:postcode":"97222",
    "sg:province":"OR",
    "sg:tags":[
        "apartment"
    ],
    "sg:website":"www.bobcarlsonroofing.com",
    "wof:name":"Waverly Property Management",
    "wof:placetype":"venue"
},
  "geometry": {"coordinates":[-122.643907,45.447453],"type":"Point"}
}