{
  "type": "Feature",
  "properties": {
    "addr:full":"319 Pruett Rd Eagle Point OR 97524",
    "addr:housenumber":"319",
    "addr:postcode":"97524",
    "addr:street":"Pruett Rd",
    "iso:country":"US",
    "sg:address":"319 Pruett Rd",
    "sg:city":"Eagle Point",
    "sg:classifiers":[
        {
            "category":"Social Services",
            "subcategory":"Adult Care",
            "type":"Services"
        }
    ],
    "sg:phone":"+1 541 826 1474",
    "sg:postcode":"97524",
    "sg:province":"OR",
    "sg:tags":[
        "residential"
    ],
    "wof:name":"Foster Sweethome Care",
    "wof:placetype":"venue"
},
  "geometry": {"coordinates":[-122.85226400000001,42.451035],"type":"Point"}
}