{
  "type": "Feature",
  "properties": {
    "addr:full":"323 NE 7th St Grants Pass OR 97526",
    "addr:housenumber":"323",
    "addr:postcode":"97526",
    "addr:street":"Ne 7Th St",
    "iso:country":"US",
    "sg:address":"323 NE 7th St",
    "sg:city":"Grants Pass",
    "sg:classifiers":[
        {
            "category":"Insurance",
            "subcategory":"Insurance Agent",
            "type":"Services"
        }
    ],
    "sg:phone":"+1 541 479 3339",
    "sg:postcode":"97526",
    "sg:province":"OR",
    "wof:name":"Bill Thorp Insurance",
    "wof:placetype":"venue"
},
  "geometry": {"coordinates":[-123.324645,42.44047],"type":"Point"}
}