{
  "type": "Feature",
  "properties": {
    "addr:full":"2752 Eola Dr NW Salem OR 97304",
    "addr:housenumber":"2752",
    "addr:postcode":"97304",
    "addr:street":"Eola Dr Nw",
    "iso:country":"US",
    "sg:address":"2752 Eola Dr NW",
    "sg:city":"Salem",
    "sg:classifiers":[
        {
            "category":"Home & Garden",
            "subcategory":"Household Appliances",
            "type":"Retail Goods"
        }
    ],
    "sg:phone":"+1 503 399 7008",
    "sg:postcode":"97304",
    "sg:province":"OR",
    "sg:tags":[
        "cleaners",
        "vacuum"
    ],
    "wof:name":"Westfall Central Vacuums",
    "wof:placetype":"venue"
},
  "geometry": {"coordinates":[-123.08822600000001,44.942896],"type":"Point"}
}