{
  "type": "Feature",
  "properties": {
    "addr:full":"20505 Murphy Rd Bend OR 97702",
    "addr:housenumber":"20505",
    "addr:postcode":"97702",
    "addr:street":"Murphy Rd",
    "iso:country":"US",
    "sg:address":"20505 Murphy Rd",
    "sg:city":"Bend",
    "sg:classifiers":[
        {
            "category":"Real Estate",
            "subcategory":"Developer",
            "type":"Services"
        }
    ],
    "sg:phone":"+1 541 382 0491",
    "sg:postcode":"97702",
    "sg:province":"OR",
    "sg:tags":[
        "land"
    ],
    "wof:name":"Mountain High Golf Course",
    "wof:placetype":"venue"
},
  "geometry": {"coordinates":[-121.298733,44.018834],"type":"Point"}
}