{
  "type": "Feature",
  "properties": {
    "iso:country":"US",
    "sg:address":"8005 SE Taylor Ct",
    "sg:city":"Portland",
    "sg:classifiers":[
        {
            "category":"Building & Trades",
            "subcategory":"Construction",
            "type":"Services"
        }
    ],
    "sg:phone":"+1 503 256 0211",
    "sg:postcode":"97215",
    "sg:province":"OR",
    "sg:tags":[
        "wallcoverings-installation",
        "wallpaper",
        "painting",
        "contractor"
    ],
    "wof:name":"River City Painting & Dctg",
    "wof:placetype":"venue"
},
  "geometry": {"coordinates":[-122.58137600000001,45.514839],"type":"Point"}
}