{
  "type": "Feature",
  "properties": {
    "addr:full":"812 NW 17th Ave Portland OR 97209",
    "addr:housenumber":"812",
    "addr:postcode":"97209",
    "addr:street":"Nw 17Th Ave",
    "iso:country":"US",
    "sg:address":"812 NW 17th Ave",
    "sg:city":"Portland",
    "sg:classifiers":[
        {
            "category":"Real Estate",
            "subcategory":"Architect",
            "type":"Services"
        }
    ],
    "sg:phone":"+1 503 226 9891",
    "sg:postcode":"97209",
    "sg:province":"OR",
    "wof:name":"Salauddin Khan",
    "wof:placetype":"venue"
},
  "geometry": {"coordinates":[-122.688363,45.529177],"type":"Point"}
}