{
  "type": "Feature",
  "properties": {
    "addr:full":"20675 Ferry Rd SE Stayton OR 97383",
    "addr:housenumber":"20675",
    "addr:postcode":"97383",
    "addr:street":"Ferry Rd Se",
    "iso:country":"US",
    "sg:address":"20675 Ferry Rd SE",
    "sg:city":"Stayton",
    "sg:classifiers":[
        {
            "category":"Building & Trades",
            "subcategory":"Construction",
            "type":"Services"
        }
    ],
    "sg:phone":"+1 503 859 3330",
    "sg:postcode":"97383",
    "sg:province":"OR",
    "sg:tags":[
        "system",
        "specialty",
        "heating",
        "contractor",
        "air conditioning"
    ],
    "sg:website":"http://www.kurtcarpenter.com",
    "wof:name":"Carpenter's Plumbing",
    "wof:placetype":"venue"
},
  "geometry": {"coordinates":[-122.638767,44.789423],"type":"Point"}
}