{
  "type": "Feature",
  "properties": {
    "addr:full":"8830 SE 45th Ave Portland OR 97222",
    "addr:housenumber":"8830",
    "addr:postcode":"97222",
    "addr:street":"Se 45Th Ave",
    "iso:country":"US",
    "sg:address":"8830 SE 45th Ave",
    "sg:city":"Portland",
    "sg:classifiers":[
        {
            "category":"Retail",
            "subcategory":"Car Wash",
            "type":"Services"
        }
    ],
    "sg:postcode":"97222",
    "sg:province":"OR",
    "sg:website":"www.purdyscarwash.com/index.html",
    "wof:name":"Purdy's Car Wash",
    "wof:placetype":"venue"
},
  "geometry": {"coordinates":[-122.61676300000001,45.457831],"type":"Point"}
}