{
  "type": "Feature",
  "properties": {
    "addr:full":"3895 SW 185th Ave Beaverton OR 97007",
    "addr:housenumber":"3895",
    "addr:postcode":"97007",
    "addr:street":"Sw 185Th Ave",
    "iso:country":"US",
    "sg:address":"3895 SW 185th Ave",
    "sg:city":"Beaverton",
    "sg:classifiers":[
        {
            "category":"Health Services",
            "subcategory":"Dentist",
            "type":"Services"
        }
    ],
    "sg:phone":"+1 503 649 9698",
    "sg:postcode":"97007",
    "sg:province":"OR",
    "wof:name":"Westside Dental Emergency Service",
    "wof:placetype":"venue"
},
  "geometry": {"coordinates":[-122.86737599999999,45.49142],"type":"Point"}
}