{
  "type": "Feature",
  "properties": {
    "iso:country":"US",
    "sg:address":"10755 SW Naeve St",
    "sg:city":"Portland",
    "sg:classifiers":[
        {
            "category":"Manufacturing",
            "subcategory":"Metals",
            "type":"Manufacturing & Wholesale Goods"
        }
    ],
    "sg:phone":"+1 503 245 6111",
    "sg:postcode":"97224",
    "sg:province":"OR",
    "sg:tags":[
        "specialty"
    ],
    "wof:name":"Pacific Cross International Corp",
    "wof:placetype":"venue"
},
  "geometry": {"coordinates":[-122.787966,45.408119],"type":"Point"}
}