{
  "type": "Feature",
  "properties": {
    "iso:country":"US",
    "sg:address":"660 NW Harrison Blvd",
    "sg:city":"Corvallis",
    "sg:classifiers":[
        {
            "category":"Banks & Credit Unions",
            "subcategory":"Investment Brokerage",
            "type":"Services"
        },
        {
            "category":"Professional",
            "subcategory":"Management & Consulting",
            "type":"Services"
        }
    ],
    "sg:phone":"+1 541 753 2262",
    "sg:postcode":"97330",
    "sg:province":"OR",
    "sg:tags":[
        "advisory",
        "financial"
    ],
    "wof:name":"Turman Financial Srv",
    "wof:placetype":"venue"
},
  "geometry": {"coordinates":[-123.263149,44.568137],"type":"Point"}
}