{
  "type": "Feature",
  "properties": {
    "addr:full":"730 Conger St Eugene OR 97402",
    "addr:housenumber":"730",
    "addr:postcode":"97402",
    "addr:street":"Conger St",
    "iso:country":"US",
    "sg:address":"730 Conger St",
    "sg:city":"Eugene",
    "sg:classifiers":[
        {
            "category":"Wholesale",
            "subcategory":"Hardware",
            "type":"Manufacturing & Wholesale Goods"
        }
    ],
    "sg:phone":"+1 541 684 0925",
    "sg:postcode":"97402",
    "sg:province":"OR",
    "sg:tags":[
        "fastener"
    ],
    "wof:name":"Fastenal Co",
    "wof:placetype":"venue"
},
  "geometry": {"coordinates":[-123.134152,44.049415],"type":"Point"}
}