{
  "type": "Feature",
  "properties": {
    "addr:full":"400 N 3rd Ave Rockaway Beach OR 97136",
    "addr:housenumber":"400",
    "addr:postcode":"97136",
    "addr:street":"N 3Rd Ave",
    "iso:country":"US",
    "sg:address":"400 N 3rd Ave",
    "sg:city":"Rockaway Beach",
    "sg:classifiers":[
        {
            "category":"Organizations",
            "subcategory":"Religious Organization",
            "type":"Services"
        }
    ],
    "sg:phone":"+1 503 355 2581",
    "sg:postcode":"97136",
    "sg:province":"OR",
    "sg:tags":[
        "church"
    ],
    "wof:name":"Rockaway Community Church",
    "wof:placetype":"venue"
},
  "geometry": {"coordinates":[-123.94110499999999,45.61499],"type":"Point"}
}