{
  "type": "Feature",
  "properties": {
    "iso:country":"US",
    "sg:address":"1750 SW Skyline Blvd",
    "sg:city":"Portland",
    "sg:classifiers":[
        {
            "category":"Organizations",
            "subcategory":"Non-profit Organization",
            "type":"Services"
        }
    ],
    "sg:phone":"+1 503 291 1982",
    "sg:postcode":"97221",
    "sg:province":"OR",
    "sg:tags":[
        "charitable",
        "institution"
    ],
    "sg:website":"www.vvomf.org",
    "wof:name":"Vietnam Veterans Of Oregon",
    "wof:placetype":"venue"
},
  "geometry": {"coordinates":[-122.735326,45.510058],"type":"Point"}
}