{
  "type": "Feature",
  "properties": {
    "iso:country":"US",
    "sg:address":"22500 Alfalfa Market Rd",
    "sg:city":"Bend",
    "sg:classifiers":[
        {
            "category":"Manufacturing",
            "subcategory":"Glass & Minerals",
            "type":"Manufacturing & Wholesale Goods"
        }
    ],
    "sg:phone":"+1 541 325 6180",
    "sg:postcode":"97701",
    "sg:province":"OR",
    "sg:tags":[
        "plate",
        "window",
        "glass-auto"
    ],
    "wof:name":"Northwest Windshield Repair",
    "wof:placetype":"venue"
},
  "geometry": {"coordinates":[-121.20056200000001,44.06562],"type":"Point"}
}