{
  "type": "Feature",
  "properties": {
    "addr:full":"2834 Pacific Ave Forest Grove OR 97116",
    "addr:housenumber":"2834",
    "addr:postcode":"97116",
    "addr:street":"Pacific Ave",
    "iso:country":"US",
    "sg:address":"2834 Pacific Ave",
    "sg:city":"Forest Grove",
    "sg:classifiers":[
        {
            "category":"Restaurant",
            "type":"Food & Drink"
        }
    ],
    "sg:phone":"+1 503 359 5405",
    "sg:postcode":"97116",
    "sg:province":"OR",
    "sg:tags":[
        "eating"
    ],
    "wof:name":"Godfather's Pizza",
    "wof:placetype":"venue"
},
  "geometry": {"coordinates":[-123.095122,45.520121],"type":"Point"}
}