{
  "type": "Feature",
  "properties": {
    "addr:full":"694 SE 3rd St Bend OR 97702",
    "addr:housenumber":"694",
    "addr:postcode":"97702",
    "addr:street":"Se 3Rd St",
    "iso:country":"US",
    "sg:address":"694 SE 3rd St",
    "sg:city":"Bend",
    "sg:classifiers":[
        {
            "category":"Shopping",
            "subcategory":"Gifts & Souvenirs",
            "type":"Retail Goods"
        }
    ],
    "sg:phone":"+1 541 382 0790",
    "sg:postcode":"97702",
    "sg:province":"OR",
    "sg:tags":[
        "shop"
    ],
    "sg:website":"www.tuesdaymorning.com",
    "wof:name":"Tuesday Morning",
    "wof:placetype":"venue"
},
  "geometry": {"coordinates":[-121.30240000000001,44.043427],"type":"Point"}
}