{
  "type": "Feature",
  "properties": {
    "iso:country":"US",
    "sg:address":"2710 NE 14th Ave",
    "sg:city":"Portland",
    "sg:classifiers":[
        {
            "category":"Place Of Worship",
            "subcategory":"Church",
            "type":"Public Place"
        },
        {
            "category":"Place Of Worship",
            "type":"Public Place"
        }
    ],
    "sg:phone":"+1 503 288 6174",
    "sg:postcode":"97212",
    "sg:province":"OR",
    "sg:tags":[
        "lutheran",
        "america",
        "churches-lutheran",
        "churches-lutheran-evangelical"
    ],
    "sg:website":"http://www.kingofkingslutheran.org",
    "wof:name":"Augustana Lutheran Church",
    "wof:placetype":"venue"
},
  "geometry": {"coordinates":[-122.65145099999999,45.542171],"type":"Point"}
}