{
  "type": "Feature",
  "properties": {
    "iso:country":"US",
    "sg:address":"2450 Lancaster Dr NE",
    "sg:city":"Salem",
    "sg:classifiers":[
        {
            "category":"Health Services",
            "subcategory":"Doctor",
            "type":"Services"
        }
    ],
    "sg:phone":"+1 503 362 9548",
    "sg:postcode":"97305",
    "sg:province":"OR",
    "sg:tags":[
        "dentist"
    ],
    "wof:name":"K R Greenbaum DDS",
    "wof:placetype":"venue"
},
  "geometry": {"coordinates":[-122.983527,44.959857],"type":"Point"}
}