{
  "type": "Feature",
  "properties": {
    "iso:country":"US",
    "sg:address":"7941 SW 64th Ave",
    "sg:city":"Portland",
    "sg:classifiers":[
        {
            "category":"Building & Trades",
            "subcategory":"Construction",
            "type":"Services"
        }
    ],
    "sg:phone":"+1 503 245 9693",
    "sg:postcode":"97219",
    "sg:province":"OR",
    "sg:tags":[
        "house"
    ],
    "wof:name":"Usher Gordon",
    "wof:placetype":"venue"
},
  "geometry": {"coordinates":[-122.742923,45.465744],"type":"Point"}
}