{
  "type": "Feature",
  "properties": {
    "iso:country":"US",
    "sg:address":"1001 SE Tualatin Valley Hwy",
    "sg:city":"Hillsboro",
    "sg:classifiers":[
        {
            "category":"Personal",
            "type":"Services"
        }
    ],
    "sg:phone":"+1 503 640 1838",
    "sg:postcode":"97123",
    "sg:province":"OR",
    "sg:tags":[
        "wear",
        "formal"
    ],
    "wof:name":"Mr Formal 08",
    "wof:placetype":"venue"
},
  "geometry": {"coordinates":[-122.97391,45.512834],"type":"Point"}
}