{
  "type": "Feature",
  "properties": {
    "addr:full":"6710 SW Montgomery Way Wilsonville OR 97070",
    "addr:housenumber":"6710",
    "addr:postcode":"97070",
    "addr:street":"Sw Montgomery Way",
    "iso:country":"US",
    "sg:address":"6710 SW Montgomery Way",
    "sg:city":"Wilsonville",
    "sg:classifiers":[
        {
            "category":"Travel",
            "subcategory":"Travel Agent",
            "type":"Entertainment"
        }
    ],
    "sg:phone":"+1 503 570 7626",
    "sg:postcode":"97070",
    "sg:province":"OR",
    "sg:tags":[
        "agency",
        "bureau"
    ],
    "wof:name":"Travel Services Intl",
    "wof:placetype":"venue"
},
  "geometry": {"coordinates":[-122.74683400000001,45.301567],"type":"Point"}
}