{
  "type": "Feature",
  "properties": {
    "addr:full":"440 NW Burnside Rd Gresham OR 97030",
    "addr:housenumber":"440",
    "addr:postcode":"97030",
    "addr:street":"Nw Burnside Rd",
    "iso:country":"US",
    "sg:address":"440 NW Burnside Rd",
    "sg:city":"Gresham",
    "sg:classifiers":[
        {
            "category":"Retail",
            "subcategory":"Portrait Studio",
            "type":"Services"
        }
    ],
    "sg:phone":"+1 503 667 3380",
    "sg:postcode":"97030",
    "sg:province":"OR",
    "wof:name":"PCA International Inc",
    "wof:placetype":"venue"
},
  "geometry": {"coordinates":[-122.439266,45.511134],"type":"Point"}
}