{
  "type": "Feature",
  "properties": {
    "addr:full":"811 SW 6th Ave Portland OR 97204",
    "addr:housenumber":"811",
    "addr:postcode":"97204",
    "addr:street":"Sw 6Th Ave",
    "iso:country":"US",
    "sg:address":"811 SW 6th Ave",
    "sg:city":"Portland",
    "sg:classifiers":[
        {
            "category":"Government",
            "subcategory":"Office",
            "type":"Public Place"
        }
    ],
    "sg:phone":"+1 503 229 5913",
    "sg:postcode":"97204",
    "sg:province":"OR",
    "sg:tags":[
        "state",
        "program"
    ],
    "wof:name":"Waste Management & Cleanup Div",
    "wof:placetype":"venue"
},
  "geometry": {"coordinates":[-122.679366,45.517836],"type":"Point"}
}