{
  "type": "Feature",
  "properties": {
    "iso:country":"US",
    "sg:address":"1575 Dewey Ave",
    "sg:city":"Baker City",
    "sg:classifiers":[
        {
            "category":"Government",
            "subcategory":"Office",
            "type":"Public Place"
        }
    ],
    "sg:phone":"+1 541 523 6331",
    "sg:postcode":"97814",
    "sg:province":"OR",
    "sg:tags":[
        "state",
        "employment"
    ],
    "wof:name":"Employment Oregon Department",
    "wof:placetype":"venue"
},
  "geometry": {"coordinates":[-117.830688,44.772829],"type":"Point"}
}