{
  "type": "Feature",
  "properties": {
    "addr:full":"1420 NW Everett St Portland OR 97209",
    "addr:housenumber":"1420",
    "addr:postcode":"97209",
    "addr:street":"Nw Everett St",
    "iso:country":"US",
    "sg:address":"1420 NW Everett St",
    "sg:city":"Portland",
    "sg:classifiers":[
        {
            "category":"Retail",
            "subcategory":"Auto Repair",
            "type":"Services"
        }
    ],
    "sg:phone":"+1 503 226 4031",
    "sg:postcode":"97209",
    "sg:province":"OR",
    "sg:tags":[
        "automotive"
    ],
    "wof:name":"City Radiator Inc",
    "wof:placetype":"venue"
},
  "geometry": {"coordinates":[-122.686106,45.524948],"type":"Point"}
}