{
  "type": "Feature",
  "properties": {
    "iso:country":"US",
    "sg:address":"3440 Alva Ave",
    "sg:city":"Klamath Falls",
    "sg:classifiers":[
        {
            "category":"Professional",
            "subcategory":"Business Services",
            "type":"Services"
        }
    ],
    "sg:phone":"+1 541 273 8770",
    "sg:postcode":"97603",
    "sg:province":"OR",
    "wof:name":"Hald Enterprises",
    "wof:placetype":"venue"
},
  "geometry": {"coordinates":[-121.747,42.212006],"type":"Point"}
}