{
  "type": "Feature",
  "properties": {
    "addr:full":"19425 SW 89th Ave Tualatin OR 97062",
    "addr:housenumber":"19425",
    "addr:postcode":"97062",
    "addr:street":"Sw 89Th Ave",
    "iso:country":"US",
    "sg:address":"19425 SW 89th Ave",
    "sg:city":"Tualatin",
    "sg:classifiers":[
        {
            "category":"Retail",
            "subcategory":"Auto Repair",
            "type":"Services"
        }
    ],
    "sg:phone":"+1 503 885 9577",
    "sg:postcode":"97062",
    "sg:province":"OR",
    "sg:tags":[
        "body"
    ],
    "wof:name":"M D V M Inc",
    "wof:placetype":"venue"
},
  "geometry": {"coordinates":[-122.76845,45.379804],"type":"Point"}
}