{
  "type": "Feature",
  "properties": {
    "iso:country":"US",
    "sg:address":"18002 Tupper Rd",
    "sg:city":"Sandy",
    "sg:classifiers":[
        {
            "category":"Home & Garden",
            "subcategory":"Carpets & Floor Coverings",
            "type":"Retail Goods"
        }
    ],
    "sg:phone":"+1 503 668 3176",
    "sg:postcode":"97055",
    "sg:province":"OR",
    "wof:name":"Rugs R US Inc",
    "wof:placetype":"venue"
},
  "geometry": {"coordinates":[-122.26510399999999,45.393229],"type":"Point"}
}