{
  "type": "Feature",
  "properties": {
    "iso:country":"US",
    "sg:address":"4429 NE 148th Ave",
    "sg:city":"Portland",
    "sg:classifiers":[
        {
            "category":"Building & Trades",
            "subcategory":"Electrical",
            "type":"Services"
        }
    ],
    "sg:phone":"+1 503 257 9800",
    "sg:postcode":"97230",
    "sg:province":"OR",
    "sg:tags":[
        "electric",
        "contractor"
    ],
    "wof:name":"Horner Trucking Inc",
    "wof:placetype":"venue"
},
  "geometry": {"coordinates":[-122.510375,45.556301],"type":"Point"}
}