{
  "type": "Feature",
  "properties": {
    "iso:country":"US",
    "sg:address":"5699 SE International Way",
    "sg:city":"Portland",
    "sg:classifiers":[
        {
            "category":"Manufacturing",
            "subcategory":"Food",
            "type":"Manufacturing & Wholesale Goods"
        }
    ],
    "sg:phone":"+1 503 653 6877",
    "sg:postcode":"97222",
    "sg:province":"OR",
    "sg:tags":[
        "bakery"
    ],
    "wof:name":"Peggys Breads",
    "wof:placetype":"venue"
},
  "geometry": {"coordinates":[-122.604598,45.431025],"type":"Point"}
}