{
  "type": "Feature",
  "properties": {
    "iso:country":"US",
    "sg:address":"8705 SW Nimbus Ave",
    "sg:city":"Beaverton",
    "sg:classifiers":[
        {
            "category":"Real Estate",
            "subcategory":"Architect",
            "type":"Services"
        }
    ],
    "sg:phone":"+1 503 968 5434",
    "sg:postcode":"97008",
    "sg:province":"OR",
    "wof:name":"Network Computing Architects",
    "wof:placetype":"venue"
},
  "geometry": {"coordinates":[-122.789001,45.4524],"type":"Point"}
}