{
  "type": "Feature",
  "properties": {
    "addr:full":"1377 Redwood Ave Grants Pass OR 97527",
    "addr:housenumber":"1377",
    "addr:postcode":"97527",
    "addr:street":"Redwood Ave",
    "iso:country":"US",
    "sg:address":"1377 Redwood Ave",
    "sg:city":"Grants Pass",
    "sg:classifiers":[
        {
            "category":"Autos & Motor Vehicles",
            "subcategory":"Motorcycle Sales",
            "type":"Retail Goods"
        }
    ],
    "sg:phone":"+1 541 956 8701",
    "sg:postcode":"97527",
    "sg:province":"OR",
    "sg:tags":[
        "scooter"
    ],
    "wof:name":"Hawg Wildcustom Motorcycles",
    "wof:placetype":"venue"
},
  "geometry": {"coordinates":[-123.354799,42.422381],"type":"Point"}
}