{
  "type": "Feature",
  "properties": {
    "addr:full":"5836 SE Foster Rd Portland OR 97206",
    "addr:housenumber":"5836",
    "addr:postcode":"97206",
    "addr:street":"Se Foster Rd",
    "iso:country":"US",
    "sg:address":"5836 SE Foster Rd",
    "sg:city":"Portland",
    "sg:classifiers":[
        {
            "category":"Retail",
            "subcategory":"Repair Shop",
            "type":"Services"
        }
    ],
    "sg:phone":"+1 503 777 1043",
    "sg:postcode":"97206",
    "sg:province":"OR",
    "sg:tags":[
        "antique",
        "reupholstery",
        "restoration",
        "upholsterer",
        "furniture"
    ],
    "wof:name":"J T Upholstery",
    "wof:placetype":"venue"
},
  "geometry": {"coordinates":[-122.602886,45.492495],"type":"Point"}
}