{
  "type": "Feature",
  "properties": {
    "addr:full":"4545 SW Watson Ave Beaverton OR 97005",
    "addr:housenumber":"4545",
    "addr:postcode":"97005",
    "addr:street":"Sw Watson Ave",
    "iso:country":"US",
    "sg:address":"4545 SW Watson Ave",
    "sg:city":"Beaverton",
    "sg:classifiers":[
        {
            "category":"Restaurant",
            "type":"Food & Drink"
        }
    ],
    "sg:menulink":"http://www.allmenus.com/or/beaverton-hillsboro/279941-decarli-restaurant/menu/",
    "sg:phone":"+1 503 641 3223",
    "sg:postcode":"97005",
    "sg:province":"OR",
    "sg:tags":[
        "american"
    ],
    "wof:name":"Decarli Restaurant",
    "wof:placetype":"venue"
},
  "geometry": {"coordinates":[-122.80626599999999,45.486803],"type":"Point"}
}