{
  "type": "Feature",
  "properties": {
    "iso:country":"US",
    "sg:address":"15450 Boones Ferry Rd",
    "sg:city":"Lake Oswego",
    "sg:classifiers":[
        {
            "category":"Wholesale",
            "subcategory":"Machinery & Supplies",
            "type":"Manufacturing & Wholesale Goods"
        }
    ],
    "sg:phone":"+1 503 699 2910",
    "sg:postcode":"97035",
    "sg:province":"OR",
    "sg:tags":[
        "carpet",
        "cleaning",
        "rug"
    ],
    "wof:name":"Active Mold Control",
    "wof:placetype":"venue"
},
  "geometry": {"coordinates":[-122.71682199999999,45.413593],"type":"Point"}
}