{
  "type": "Feature",
  "properties": {
    "addr:full":"1606 SW Custer St. Portland OR 97219",
    "addr:housenumber":"1606",
    "addr:postcode":"97219",
    "addr:street":"Sw Custer St.",
    "iso:country":"US",
    "sg:address":"1606 SW Custer St.",
    "sg:city":"Portland",
    "sg:classifiers":[
        {
            "category":"Building & Trades",
            "subcategory":"Construction",
            "type":"Services"
        }
    ],
    "sg:phone":"+1 503 701 6985",
    "sg:postcode":"97219",
    "sg:province":"OR",
    "sg:tags":[
        "interior",
        "design",
        "contractor"
    ],
    "sg:website":"www.sparcdesigns.com/",
    "wof:name":"Interior Designer in Portland, Sparc Designs",
    "wof:placetype":"venue"
},
  "geometry": {"coordinates":[-122.69444300000001,45.469496],"type":"Point"}
}