{
  "type": "Feature",
  "properties": {
    "iso:country":"US",
    "sg:address":"1257 Siskiyou Blvd",
    "sg:city":"Ashland",
    "sg:classifiers":[
        {
            "category":"Professional",
            "subcategory":"Computer Services",
            "type":"Services"
        }
    ],
    "sg:phone":"+1 541 488 7803",
    "sg:postcode":"97520",
    "sg:province":"OR",
    "sg:tags":[
        "datum"
    ],
    "wof:name":"Concept Labs",
    "wof:placetype":"venue"
},
  "geometry": {"coordinates":[-122.69378500000001,42.186519],"type":"Point"}
}