{
  "type": "Feature",
  "properties": {
    "iso:country":"US",
    "sg:address":"6506 SE Foster Rd",
    "sg:city":"Portland",
    "sg:classifiers":[
        {
            "category":"Food & Beverages",
            "subcategory":"Specialty",
            "type":"Retail Goods"
        }
    ],
    "sg:phone":"+1 503 774 4516",
    "sg:postcode":"97206",
    "sg:province":"OR",
    "wof:name":"Yolas Foster Rd Coffeehouse",
    "wof:placetype":"venue"
},
  "geometry": {"coordinates":[-122.5955,45.489029],"type":"Point"}
}