{
  "type": "Feature",
  "properties": {
    "iso:country":"US",
    "sg:address":"122 S Oregon St",
    "sg:city":"Ontario",
    "sg:classifiers":[
        {
            "category":"Shopping",
            "subcategory":"Florist",
            "type":"Retail Goods"
        }
    ],
    "sg:phone":"+1 541 889 3193",
    "sg:postcode":"97914",
    "sg:province":"OR",
    "wof:name":"Flower Trunk",
    "wof:placetype":"venue"
},
  "geometry": {"coordinates":[-116.963264,44.025523],"type":"Point"}
}