{
  "type": "Feature",
  "properties": {
    "addr:full":"12020 NE Stag Hollow Rd Carlton OR 97148",
    "addr:housenumber":"12020",
    "addr:postcode":"97148",
    "addr:street":"Ne Stag Hollow Rd",
    "iso:country":"US",
    "sg:address":"12020 NE Stag Hollow Rd",
    "sg:city":"Carlton",
    "sg:classifiers":[
        {
            "category":"Farming",
            "subcategory":"Vineyard",
            "type":"Manufacturing & Wholesale Goods"
        }
    ],
    "sg:phone":"+1 503 852 7788",
    "sg:postcode":"97148",
    "sg:province":"OR",
    "wof:name":"Cornucopia Vineyards LTD",
    "wof:placetype":"venue"
},
  "geometry": {"coordinates":[-123.129532,45.305518],"type":"Point"}
}