{
  "type": "Feature",
  "properties": {
    "iso:country":"US",
    "sg:address":"3535 del Webb Ave NE",
    "sg:city":"Salem",
    "sg:classifiers":[
        {
            "category":"Building & Trades",
            "subcategory":"Electrical",
            "type":"Services"
        }
    ],
    "sg:phone":"+1 503 363 2301",
    "sg:postcode":"97301",
    "sg:province":"OR",
    "sg:tags":[
        "electric",
        "contractor"
    ],
    "wof:name":"A C & E Electric Co",
    "wof:placetype":"venue"
},
  "geometry": {"coordinates":[-123.016069,44.974418],"type":"Point"}
}