{
  "type": "Feature",
  "properties": {
    "addr:full":"605 NW 11th Ave Portland OR 97209",
    "addr:housenumber":"605",
    "addr:postcode":"97209",
    "addr:street":"Nw 11Th Ave",
    "iso:country":"US",
    "sg:address":"605 NW 11th Ave",
    "sg:city":"Portland",
    "sg:classifiers":[
        {
            "category":"Professional",
            "subcategory":"Management & Consulting",
            "type":"Services"
        },
        {
            "category":"Banks & Credit Unions",
            "subcategory":"Investment Brokerage",
            "type":"Services"
        },
        {
            "category":"Banks & Credit Unions",
            "subcategory":"Bank",
            "type":"Services"
        },
        {
            "category":"Banks & Credit Unions",
            "subcategory":"Financial Services",
            "type":"Services"
        }
    ],
    "sg:phone":"+1 503 229 4400",
    "sg:postcode":"97209",
    "sg:province":"OR",
    "sg:tags":[
        "financing",
        "consultant",
        "broker",
        "planning",
        "security",
        "bond",
        "stock"
    ],
    "sg:website":"http://www.veber.com",
    "wof:name":"Veber Partners",
    "wof:placetype":"venue"
},
  "geometry": {"coordinates":[-122.682283,45.52727],"type":"Point"}
}