{
  "type": "Feature",
  "properties": {
    "iso:country":"US",
    "sg:address":"714 NE Holland St",
    "sg:city":"Portland",
    "sg:classifiers":[
        {
            "category":"Building & Trades",
            "subcategory":"Construction",
            "type":"Services"
        }
    ],
    "sg:phone":"+1 503 283 0849",
    "sg:postcode":"97211",
    "sg:province":"OR",
    "sg:tags":[
        "concrete",
        "contractor"
    ],
    "wof:name":"Spm Concrete",
    "wof:placetype":"venue"
},
  "geometry": {"coordinates":[-122.657788,45.575729],"type":"Point"}
}