{
  "type": "Feature",
  "properties": {
    "iso:country":"US",
    "sg:address":"3468 Peck Ave SE",
    "sg:city":"Salem",
    "sg:classifiers":[
        {
            "category":"Manufacturing",
            "subcategory":"Musical Instruments",
            "type":"Manufacturing & Wholesale Goods"
        }
    ],
    "sg:phone":"+1 503 588 4001",
    "sg:postcode":"97302",
    "sg:province":"OR",
    "sg:tags":[
        "mfg"
    ],
    "wof:name":"Instrument Covers By Jill",
    "wof:placetype":"venue"
},
  "geometry": {"coordinates":[-123.034085,44.907082],"type":"Point"}
}