{
  "type": "Feature",
  "properties": {
    "iso:country":"US",
    "sg:address":"1133 S Riverside Ave",
    "sg:city":"Medford",
    "sg:classifiers":[
        {
            "category":"Building & Trades",
            "subcategory":"Construction",
            "type":"Services"
        }
    ],
    "sg:phone":"+1 541 878 7834",
    "sg:postcode":"97501",
    "sg:province":"OR",
    "sg:tags":[
        "floor",
        "laying",
        "contractor"
    ],
    "wof:name":"David Tanskley",
    "wof:placetype":"venue"
},
  "geometry": {"coordinates":[-122.86083499999999,42.313381],"type":"Point"}
}