{
  "type": "Feature",
  "properties": {
    "addr:full":"10260 SW Greenburg Rd Portland OR 97223",
    "addr:housenumber":"10260",
    "addr:postcode":"97223",
    "addr:street":"Sw Greenburg Rd",
    "iso:country":"US",
    "sg:address":"10260 SW Greenburg Rd",
    "sg:city":"Portland",
    "sg:classifiers":[
        {
            "category":"Professional",
            "subcategory":"Employment Agencies",
            "type":"Services"
        }
    ],
    "sg:phone":"+1 503 293 8444",
    "sg:postcode":"97223",
    "sg:province":"OR",
    "sg:tags":[
        "consulting",
        "it"
    ],
    "wof:name":"Enpria Inc",
    "wof:placetype":"venue"
},
  "geometry": {"coordinates":[-122.776932,45.444277],"type":"Point"}
}