{
  "type": "Feature",
  "properties": {
    "addr:full":"411 SW 16th St Pendleton OR 97801",
    "addr:housenumber":"411",
    "addr:postcode":"97801",
    "addr:street":"Sw 16Th St",
    "iso:country":"US",
    "sg:address":"411 SW 16th St",
    "sg:city":"Pendleton",
    "sg:classifiers":[
        {
            "category":"Wholesale",
            "subcategory":"Construction Materials",
            "type":"Manufacturing & Wholesale Goods"
        }
    ],
    "sg:phone":"+1 541 276 8520",
    "sg:postcode":"97801",
    "sg:province":"OR",
    "sg:tags":[
        "fence"
    ],
    "wof:name":"Zig Zag Fencing",
    "wof:placetype":"venue"
},
  "geometry": {"coordinates":[-118.80120100000001,45.665897],"type":"Point"}
}