{
  "type": "Feature",
  "properties": {
    "iso:country":"US",
    "sg:address":"9600 SW Barnes Rd Ste 150",
    "sg:city":"Portland",
    "sg:classifiers":[
        {
            "category":"Insurance",
            "subcategory":"Title Insurance",
            "type":"Services"
        }
    ],
    "sg:phone":"+1 503 297 8084",
    "sg:postcode":"97225",
    "sg:province":"OR",
    "sg:tags":[
        "mortgage"
    ],
    "wof:name":"Oregon Title Insurance Co",
    "wof:placetype":"venue"
},
  "geometry": {"coordinates":[-122.774704,45.509568],"type":"Point"}
}