{
  "type": "Feature",
  "properties": {
    "iso:country":"US",
    "sg:address":"15295 SE Amisigger Rd",
    "sg:city":"Boring",
    "sg:classifiers":[
        {
            "category":"Wholesale",
            "subcategory":"Plants",
            "type":"Manufacturing & Wholesale Goods"
        }
    ],
    "sg:phone":"+1 503 663 0213",
    "sg:postcode":"97009",
    "sg:province":"OR",
    "sg:tags":[
        "supply"
    ],
    "wof:name":"Bithell Nursery Inc",
    "wof:placetype":"venue"
},
  "geometry": {"coordinates":[-122.383085,45.415473],"type":"Point"}
}