{
  "type": "Feature",
  "properties": {
    "iso:country":"US",
    "sg:address":"17309 NE Glisan St",
    "sg:city":"Portland",
    "sg:classifiers":[
        {
            "category":"Social Services",
            "subcategory":"Adult Care",
            "type":"Services"
        }
    ],
    "sg:phone":"+1 503 253 4920",
    "sg:postcode":"97230",
    "sg:province":"OR",
    "sg:tags":[
        "home",
        "residential"
    ],
    "sg:website":"www.srg-llc.com",
    "wof:name":"Legacy St Aidan's Place",
    "wof:placetype":"venue"
},
  "geometry": {"coordinates":[-122.48309399999999,45.526486],"type":"Point"}
}