{
  "type": "Feature",
  "properties": {
    "iso:country":"US",
    "sg:address":"28961 S Salo Rd",
    "sg:city":"Mulino",
    "sg:classifiers":[
        {
            "category":"Professional",
            "subcategory":"Business Services",
            "type":"Services"
        }
    ],
    "sg:phone":"+1 503 759 4610",
    "sg:postcode":"97042",
    "sg:province":"OR",
    "wof:name":"Doug Furlow",
    "wof:placetype":"venue"
},
  "geometry": {"coordinates":[-122.527402,45.183384],"type":"Point"}
}