{
  "type": "Feature",
  "properties": {
    "iso:country":"US",
    "sg:address":"2261 5th St",
    "sg:city":"Springfield",
    "sg:classifiers":[
        {
            "category":"Wholesale",
            "subcategory":"Non-durable Goods",
            "type":"Manufacturing & Wholesale Goods"
        }
    ],
    "sg:phone":"+1 541 747 6206",
    "sg:postcode":"97477",
    "sg:province":"OR",
    "wof:name":"Locklear Leatherworks",
    "wof:placetype":"venue"
},
  "geometry": {"coordinates":[-123.019237,44.067927],"type":"Point"}
}