{
  "type": "Feature",
  "properties": {
    "iso:country":"US",
    "sg:address":"3520 Pine St SE",
    "sg:city":"Albany",
    "sg:classifiers":[
        {
            "category":"Building & Trades",
            "subcategory":"Cleaning & Sanitation",
            "type":"Services"
        }
    ],
    "sg:phone":"+1 541 926 5194",
    "sg:postcode":"97322",
    "sg:province":"OR",
    "sg:tags":[
        "janitor",
        "cleaners-interior"
    ],
    "wof:name":"Rhodaback & Son Janitorial",
    "wof:placetype":"venue"
},
  "geometry": {"coordinates":[-123.08413,44.609473],"type":"Point"}
}