{
  "type": "Feature",
  "properties": {
    "iso:country":"US",
    "sg:address":"12215 Ballston Rd",
    "sg:city":"Amity",
    "sg:classifiers":[
        {
            "category":"Farming",
            "subcategory":"Farm & Veterinary Services",
            "type":"Manufacturing & Wholesale Goods"
        }
    ],
    "sg:phone":"+1 503 843 4775",
    "sg:postcode":"97101",
    "sg:province":"OR",
    "sg:tags":[
        "seed",
        "grain",
        "cleaning"
    ],
    "wof:name":"T & W Seeds LLC",
    "wof:placetype":"venue"
},
  "geometry": {"coordinates":[-123.280018,45.069176],"type":"Point"}
}