{
  "type": "Feature",
  "properties": {
    "iso:country":"US",
    "sg:address":"5050 SW Griffith Dr",
    "sg:city":"Beaverton",
    "sg:classifiers":[
        {
            "category":"Professional",
            "subcategory":"Business Services",
            "type":"Services"
        }
    ],
    "sg:phone":"+1 503 574 4486",
    "sg:postcode":"97005",
    "sg:province":"OR",
    "wof:name":"Columbia Benefits Group",
    "wof:placetype":"venue"
},
  "geometry": {"coordinates":[-122.79463,45.483497],"type":"Point"}
}