{
  "type": "Feature",
  "properties": {
    "addr:full":"38475 River Dr Lebanon OR 97355",
    "addr:housenumber":"38475",
    "addr:postcode":"97355",
    "addr:street":"River Dr",
    "iso:country":"US",
    "sg:address":"38475 River Dr",
    "sg:city":"Lebanon",
    "sg:classifiers":[
        {
            "category":"Building & Trades",
            "subcategory":"Plumbing",
            "type":"Services"
        }
    ],
    "sg:phone":"+1 541 451 3001",
    "sg:postcode":"97355",
    "sg:province":"OR",
    "sg:tags":[
        "plumbing",
        "contractor"
    ],
    "wof:name":"M & M Plumbing Contractors",
    "wof:placetype":"venue"
},
  "geometry": {"coordinates":[-122.859739,44.513443],"type":"Point"}
}