{
  "type": "Feature",
  "properties": {
    "addr:full":"1925 NE 42nd Ave Ste E Portland OR 97213",
    "addr:housenumber":"1925",
    "addr:postcode":"97213",
    "addr:street":"Ne 42Nd Ave Ste E",
    "iso:country":"US",
    "sg:address":"1925 NE 42nd Ave Ste E",
    "sg:city":"Portland",
    "sg:classifiers":[
        {
            "category":"Professional",
            "subcategory":"Business Services",
            "type":"Services"
        }
    ],
    "sg:phone":"+1 503 956 5957",
    "sg:postcode":"97213",
    "sg:province":"OR",
    "sg:tags":[
        "development",
        "plan"
    ],
    "wof:name":"Innovative Fiber Resources Inc",
    "wof:placetype":"venue"
},
  "geometry": {"coordinates":[-122.61992600000001,45.536671],"type":"Point"}
}