{
  "type": "Feature",
  "properties": {
    "iso:country":"US",
    "sg:address":"35068 Fremont Ave",
    "sg:city":"Eugene",
    "sg:classifiers":[
        {
            "category":"Building & Trades",
            "subcategory":"Construction",
            "type":"Services"
        }
    ],
    "sg:phone":"+1 541 988 5815",
    "sg:postcode":"97405",
    "sg:province":"OR",
    "sg:tags":[
        "concrete",
        "contractor"
    ],
    "wof:name":"Griffiths Enterprises Inc",
    "wof:placetype":"venue"
},
  "geometry": {"coordinates":[-122.968443,43.98777],"type":"Point"}
}