{
  "type": "Feature",
  "properties": {
    "addr:full":"1801 NW Upshur St Ste 190 Portland OR 97209",
    "addr:housenumber":"1801",
    "addr:postcode":"97209",
    "addr:street":"Nw Upshur St Ste 190",
    "iso:country":"US",
    "sg:address":"1801 NW Upshur St Ste 190",
    "sg:city":"Portland",
    "sg:classifiers":[
        {
            "category":"Shopping",
            "subcategory":"Florist",
            "type":"Retail Goods"
        }
    ],
    "sg:phone":"+1 503 652 9991",
    "sg:postcode":"97209",
    "sg:province":"OR",
    "wof:name":"Clackamas Florist",
    "wof:placetype":"venue"
},
  "geometry": {"coordinates":[-122.69004,45.536592],"type":"Point"}
}