{
  "type": "Feature",
  "properties": {
    "iso:country":"US",
    "sg:address":"14740 NW Cornell Rd Ste 80",
    "sg:city":"Portland",
    "sg:classifiers":[
        {
            "category":"Bars & Pubs",
            "type":"Food & Drink"
        },
        {
            "category":"Restaurant",
            "type":"Food & Drink"
        }
    ],
    "sg:phone":"+1 503 645 0286",
    "sg:postcode":"97229",
    "sg:province":"OR",
    "sg:website":"mcmenamins.com/index.php?loc=41&...",
    "wof:name":"McMenamins Oak Hills Brewpub",
    "wof:placetype":"venue"
},
  "geometry": {"coordinates":[-122.829002,45.5317],"type":"Point"}
}