{
  "type": "Feature",
  "properties": {
    "iso:country":"US",
    "sg:address":"10260 SW Greenburg Road Suite 250",
    "sg:city":"Portland",
    "sg:classifiers":[
        {
            "category":"Banks & Credit Unions",
            "subcategory":"Financial Services",
            "type":"Services"
        }
    ],
    "sg:phone":"+1 503 892 2310",
    "sg:postcode":"97223",
    "sg:province":"OR",
    "sg:tags":[
        "broker",
        "mortgage"
    ],
    "wof:name":"Response Mortgage Services",
    "wof:placetype":"venue"
},
  "geometry": {"coordinates":[-122.776447,45.445783],"type":"Point"}
}