{
  "type": "Feature",
  "properties": {
    "iso:country":"US",
    "sg:address":"925 NE Jackson School Rd",
    "sg:city":"Hillsboro",
    "sg:classifiers":[
        {
            "category":"Professional",
            "type":"Services"
        }
    ],
    "sg:phone":"+1 503 640 6114",
    "sg:postcode":"97124",
    "sg:province":"OR",
    "wof:name":"Jeannette Hamby",
    "wof:placetype":"venue"
},
  "geometry": {"coordinates":[-122.979736,45.532169],"type":"Point"}
}