{
  "type": "Feature",
  "properties": {
    "iso:country":"US",
    "sg:address":"3138 SE Powell Blvd",
    "sg:city":"Portland",
    "sg:classifiers":[
        {
            "category":"Retail",
            "subcategory":"Auto Repair",
            "type":"Services"
        }
    ],
    "sg:phone":"+1 503 234 6940",
    "sg:postcode":"97202",
    "sg:province":"OR",
    "sg:tags":[
        "repairing",
        "automobile"
    ],
    "wof:name":"Fine Tune Auto Svc",
    "wof:placetype":"venue"
},
  "geometry": {"coordinates":[-122.632775,45.496809],"type":"Point"}
}