{
  "type": "Feature",
  "properties": {
    "iso:country":"US",
    "sg:address":"26291 NE Butteville Rd",
    "sg:city":"Aurora",
    "sg:classifiers":[
        {
            "category":"Building & Trades",
            "subcategory":"Plumbing",
            "type":"Services"
        },
        {
            "category":"Building & Trades",
            "subcategory":"Construction",
            "type":"Services"
        }
    ],
    "sg:phone":"+1 503 694 2011",
    "sg:postcode":"97002",
    "sg:province":"OR",
    "sg:tags":[
        "plumber",
        "industrial",
        "system",
        "specialty",
        "heating",
        "contractors-commercial",
        "contractor",
        "air conditioning"
    ],
    "wof:name":"Babbitt Plumbing Incorporated",
    "wof:placetype":"venue"
},
  "geometry": {"coordinates":[-122.77288799999999,45.288362],"type":"Point"}
}