{
  "type": "Feature",
  "properties": {
    "iso:country":"US",
    "sg:address":"1807 SE Powell Blvd",
    "sg:city":"Portland",
    "sg:classifiers":[
        {
            "category":"Retail",
            "subcategory":"Auto Repair",
            "type":"Services"
        }
    ],
    "sg:phone":"+1 503 902 1348",
    "sg:postcode":"97202",
    "sg:province":"OR",
    "sg:tags":[
        "exhaust",
        "car",
        "system",
        "equipment",
        "brake",
        "automobile",
        "muffler",
        "performance",
        "sport",
        "racing"
    ],
    "sg:website":"http://www.tomtracker.com/redirect.cfm?bID=4837&hID=111353",
    "wof:name":"Meineke Car Care Center",
    "wof:placetype":"venue"
},
  "geometry": {"coordinates":[-122.64742699999999,45.499975],"type":"Point"}
}