{
  "type": "Feature",
  "properties": {
    "iso:country":"US",
    "sg:address":"8266 NE Quaale Rd",
    "sg:city":"Madras",
    "sg:classifiers":[
        {
            "category":"Farming",
            "subcategory":"Livestock Farm",
            "type":"Manufacturing & Wholesale Goods"
        }
    ],
    "sg:phone":"+1 541 475 3324",
    "sg:postcode":"97741",
    "sg:province":"OR",
    "sg:tags":[
        "beef",
        "feedlot",
        "cattle"
    ],
    "wof:name":"Martin Cattle Co",
    "wof:placetype":"venue"
},
  "geometry": {"coordinates":[-121.046966,44.751644],"type":"Point"}
}