{
  "type": "Feature",
  "properties": {
    "iso:country":"US",
    "sg:address":"1020 SW Taylor St Ste 275",
    "sg:city":"Portland",
    "sg:classifiers":[
        {
            "category":"Arts & Performance",
            "subcategory":"Music",
            "type":"Entertainment"
        }
    ],
    "sg:phone":"+1 503 222 6000",
    "sg:postcode":"97205",
    "sg:province":"OR",
    "sg:tags":[
        "band",
        "orchestra"
    ],
    "wof:name":"Portland Baroque Orchestra",
    "wof:placetype":"venue"
},
  "geometry": {"coordinates":[-122.683055,45.518742],"type":"Point"}
}