{
  "type": "Feature",
  "properties": {
    "addr:full":"16575 SE McLoughlin Boulevard Portland OR 97267",
    "addr:housenumber":"16575",
    "addr:postcode":"97267",
    "addr:street":"Se Mcloughlin Boulevard",
    "iso:country":"US",
    "sg:address":"16575 SE McLoughlin Boulevard",
    "sg:city":"Portland",
    "sg:classifiers":[
        {
            "category":"Manufacturing",
            "subcategory":"Tobacco Products",
            "type":"Manufacturing & Wholesale Goods"
        },
        {
            "category":"Shopping",
            "subcategory":"Tobacco",
            "type":"Retail Goods"
        }
    ],
    "sg:phone":"+1 503 656 4682",
    "sg:postcode":"97267",
    "sg:province":"OR",
    "sg:tags":[
        "shop",
        "cigar",
        "tobacco-wholesale",
        "cigarette",
        "manufacturer"
    ],
    "wof:name":"Tobacco Town",
    "wof:placetype":"venue"
},
  "geometry": {"coordinates":[-122.622478,45.403966],"type":"Point"}
}