{
  "type": "Feature",
  "properties": {
    "iso:country":"US",
    "sg:address":"3030 SW 2nd Ave",
    "sg:city":"Portland",
    "sg:classifiers":[
        {
            "category":"Organizations",
            "subcategory":"Non-profit Organization",
            "type":"Services"
        }
    ],
    "sg:phone":"+1 503 222 5006",
    "sg:postcode":"97201",
    "sg:province":"OR",
    "sg:tags":[
        "religious"
    ],
    "wof:name":"National Council of Jewish Women",
    "wof:placetype":"venue"
},
  "geometry": {"coordinates":[-122.67946600000001,45.501128],"type":"Point"}
}