{
  "type": "Feature",
  "properties": {
    "addr:full":"25057 Springer Rd Sweet Home OR 97386",
    "addr:housenumber":"25057",
    "addr:postcode":"97386",
    "addr:street":"Springer Rd",
    "iso:country":"US",
    "sg:address":"25057 Springer Rd",
    "sg:city":"Sweet Home",
    "sg:classifiers":[
        {
            "category":"Wholesale",
            "subcategory":"Meat",
            "type":"Manufacturing & Wholesale Goods"
        }
    ],
    "sg:phone":"+1 541 367 8867",
    "sg:postcode":"97386",
    "sg:province":"OR",
    "sg:tags":[
        "packer"
    ],
    "wof:name":"Chucky's In Holley-Woods Cstm",
    "wof:placetype":"venue"
},
  "geometry": {"coordinates":[-122.759961,44.333987],"type":"Point"}
}