{
  "type": "Feature",
  "properties": {
    "addr:full":"18555 Portland Ave Gladstone OR 97027",
    "addr:housenumber":"18555",
    "addr:postcode":"97027",
    "addr:street":"Portland Ave",
    "iso:country":"US",
    "sg:address":"18555 Portland Ave",
    "sg:city":"Gladstone",
    "sg:classifiers":[
        {
            "category":"Personal",
            "subcategory":"Beauty Salon",
            "type":"Services"
        }
    ],
    "sg:phone":"+1 503 723 6710",
    "sg:postcode":"97027",
    "sg:province":"OR",
    "sg:tags":[
        "shop"
    ],
    "wof:name":"Candy's Cutting Corner",
    "wof:placetype":"venue"
},
  "geometry": {"coordinates":[-122.59996599999999,45.388207],"type":"Point"}
}