{
  "type": "Feature",
  "properties": {
    "iso:country":"US",
    "sg:address":"3125 SE 90th Pl",
    "sg:city":"Portland",
    "sg:classifiers":[
        {
            "category":"Building & Trades",
            "subcategory":"Construction",
            "type":"Services"
        },
        {
            "category":"Manufacturing",
            "subcategory":"Building Materials",
            "type":"Manufacturing & Wholesale Goods"
        }
    ],
    "sg:phone":"+1 503 774 1299",
    "sg:postcode":"97266",
    "sg:province":"OR",
    "sg:tags":[
        "roofing",
        "industrial",
        "sheet",
        "altering",
        "work",
        "metal",
        "contractor",
        "siding",
        "contractors-commercial",
        "remodeling"
    ],
    "sg:website":"http://www.alleagleroofing.com",
    "wof:name":"All Roofing Eagle Construction Services",
    "wof:placetype":"venue"
},
  "geometry": {"coordinates":[-122.569703,45.500584],"type":"Point"}
}