{
  "type": "Feature",
  "properties": {
    "addr:full":"1000 SE Lake Rd Redmond OR 97756",
    "addr:housenumber":"1000",
    "addr:postcode":"97756",
    "addr:street":"Se Lake Rd",
    "iso:country":"US",
    "sg:address":"1000 SE Lake Rd",
    "sg:city":"Redmond",
    "sg:classifiers":[
        {
            "category":"Manufacturing",
            "subcategory":"Building Materials",
            "type":"Manufacturing & Wholesale Goods"
        }
    ],
    "sg:phone":"+1 541 923 2759",
    "sg:postcode":"97756",
    "sg:province":"OR",
    "sg:tags":[
        "truss"
    ],
    "wof:name":"Quality Truss Co",
    "wof:placetype":"venue"
},
  "geometry": {"coordinates":[-121.168369,44.266909],"type":"Point"}
}