{
  "type": "Feature",
  "properties": {
    "addr:full":"77242 Circling Hawk Ln Cottage Grove OR 97424",
    "addr:postcode":"77242;97424",
    "addr:street":"Circling Hawk Ln",
    "iso:country":"US",
    "sg:address":"77242 Circling Hawk Ln",
    "sg:city":"Cottage Grove",
    "sg:classifiers":[
        {
            "category":"Wholesale",
            "subcategory":"Groceries",
            "type":"Manufacturing & Wholesale Goods"
        }
    ],
    "sg:phone":"+1 541 767 0022",
    "sg:postcode":"97424",
    "sg:province":"OR",
    "wof:name":"Johnnys Original Sauces",
    "wof:placetype":"venue"
},
  "geometry": {"coordinates":[-122.89522100000001,43.758536],"type":"Point"}
}