{
  "type": "Feature",
  "properties": {
    "iso:country":"US",
    "sg:address":"3647 Westleigh St",
    "sg:city":"Eugene",
    "sg:classifiers":[
        {
            "category":"Arts & Performance",
            "subcategory":"Theater",
            "type":"Entertainment"
        }
    ],
    "sg:phone":"+1 541 434 6728",
    "sg:postcode":"97405",
    "sg:province":"OR",
    "sg:tags":[
        "group"
    ],
    "wof:name":"Z Musikmakers",
    "wof:placetype":"venue"
},
  "geometry": {"coordinates":[-123.147604,44.038],"type":"Point"}
}