{
  "type": "Feature",
  "properties": {
    "iso:country":"US",
    "sg:address":"1111 NW Davis",
    "sg:city":"Portland",
    "sg:classifiers":[
        {
            "category":"Parking",
            "type":"Transportation"
        }
    ],
    "sg:phone":"+1 503 221 3414",
    "sg:postcode":"97209",
    "sg:province":"OR",
    "sg:website":"www.citycenterparking.com/lots/p...",
    "wof:name":"Pearl Garage",
    "wof:placetype":"venue"
},
  "geometry": {"coordinates":[-122.682686,45.5246],"type":"Point"}
}