{
  "type": "Feature",
  "properties": {
    "iso:country":"US",
    "sg:address":"1622 W Jones Creek Rd",
    "sg:city":"Grants Pass",
    "sg:classifiers":[
        {
            "category":"Building & Trades",
            "subcategory":"Landscaping Services",
            "type":"Services"
        }
    ],
    "sg:phone":"+1 541 476 9824",
    "sg:postcode":"97526",
    "sg:province":"OR",
    "sg:tags":[
        "landscape",
        "contractor"
    ],
    "wof:name":"Dayspring Landscapes",
    "wof:placetype":"venue"
},
  "geometry": {"coordinates":[-123.293171,42.467052],"type":"Point"}
}