{
  "type": "Feature",
  "properties": {
    "iso:country":"US",
    "sg:address":"249 Coos Bay Wagon Rd",
    "sg:city":"Roseburg",
    "sg:classifiers":[
        {
            "category":"Organizations",
            "subcategory":"Religious Organization",
            "type":"Services"
        }
    ],
    "sg:phone":"+1 541 679 7282",
    "sg:postcode":"97470",
    "sg:province":"OR",
    "sg:tags":[
        "church"
    ],
    "wof:name":"Looking Glass Community Church",
    "wof:placetype":"venue"
},
  "geometry": {"coordinates":[-123.488925,43.178207],"type":"Point"}
}