{
  "type": "Feature",
  "properties": {
    "addr:full":"1325 N Manzanita St Canby OR 97013",
    "addr:housenumber":"1325",
    "addr:postcode":"97013",
    "addr:street":"N Manzanita St",
    "iso:country":"US",
    "sg:address":"1325 N Manzanita St",
    "sg:city":"Canby",
    "sg:classifiers":[
        {
            "category":"Building & Trades",
            "subcategory":"Electrical",
            "type":"Services"
        }
    ],
    "sg:phone":"+1 503 266 5006",
    "sg:postcode":"97013",
    "sg:province":"OR",
    "sg:tags":[
        "electrical",
        "contractor"
    ],
    "wof:name":"Cg Systems",
    "wof:placetype":"venue"
},
  "geometry": {"coordinates":[-122.688298,45.272877],"type":"Point"}
}