{
  "type": "Feature",
  "properties": {
    "addr:full":"83442 Rodgers Rd Creswell OR 97426",
    "addr:postcode":"83442;97426",
    "addr:street":"Rodgers Rd",
    "iso:country":"US",
    "sg:address":"83442 Rodgers Rd",
    "sg:city":"Creswell",
    "sg:classifiers":[
        {
            "category":"Farming",
            "subcategory":"Nursery",
            "type":"Manufacturing & Wholesale Goods"
        }
    ],
    "sg:phone":"+1 541 895 2269",
    "sg:postcode":"97426",
    "sg:province":"OR",
    "sg:tags":[
        "ornamental"
    ],
    "wof:name":"Blondies Blooms",
    "wof:placetype":"venue"
},
  "geometry": {"coordinates":[-122.966036,43.932902],"type":"Point"}
}