{
  "type": "Feature",
  "properties": {
    "iso:country":"US",
    "sg:address":"755 Antelope Rd",
    "sg:city":"White City",
    "sg:classifiers":[
        {
            "category":"Manufacturing",
            "subcategory":"Tools & Machinery",
            "type":"Manufacturing & Wholesale Goods"
        }
    ],
    "sg:phone":"+1 541 826 2988",
    "sg:postcode":"97503",
    "sg:province":"OR",
    "sg:tags":[
        "machine",
        "shop"
    ],
    "wof:name":"Pacific Gundrill & Machine",
    "wof:placetype":"venue"
},
  "geometry": {"coordinates":[-122.881335,42.427458],"type":"Point"}
}