{
  "type": "Feature",
  "properties": {
    "addr:full":"7855 SW Alameda Ln Beaverton OR 97007",
    "addr:housenumber":"7855",
    "addr:postcode":"97007",
    "addr:street":"Sw Alameda Ln",
    "iso:country":"US",
    "sg:address":"7855 SW Alameda Ln",
    "sg:city":"Beaverton",
    "sg:classifiers":[
        {
            "category":"Building & Trades",
            "subcategory":"Cleaning & Sanitation",
            "type":"Services"
        }
    ],
    "sg:phone":"+1 503 526 2967",
    "sg:postcode":"97007",
    "sg:province":"OR",
    "sg:tags":[
        "maintenance"
    ],
    "wof:name":"Minodora Cleaning Service",
    "wof:placetype":"venue"
},
  "geometry": {"coordinates":[-122.82677200000001,45.463225],"type":"Point"}
}