{
  "type": "Feature",
  "properties": {
    "iso:country":"US",
    "sg:address":"7855 SW Alameda Ln",
    "sg:city":"Beaverton",
    "sg:classifiers":[
        {
            "category":"Building & Trades",
            "subcategory":"Cleaning & Sanitation",
            "type":"Services"
        }
    ],
    "sg:phone":"+1 503 526 2967",
    "sg:postcode":"97007",
    "sg:province":"OR",
    "sg:tags":[
        "maintenance"
    ],
    "wof:name":"Minodora Cleaning Service",
    "wof:placetype":"venue"
},
  "geometry": {"coordinates":[-122.826772,45.463225],"type":"Point"}
}