{
  "type": "Feature",
  "properties": {
    "addr:full":"21430 Morrill Rd Bend OR 97701",
    "addr:postcode":"21430;97701",
    "addr:street":"Morrill Rd",
    "iso:country":"US",
    "sg:address":"21430 Morrill Rd",
    "sg:city":"Bend",
    "sg:classifiers":[
        {
            "category":"Farming",
            "subcategory":"Livestock Farm",
            "type":"Manufacturing & Wholesale Goods"
        }
    ],
    "sg:phone":"+1 541 317 9306",
    "sg:postcode":"97701",
    "sg:province":"OR",
    "sg:tags":[
        "beef",
        "feedlot",
        "cattle"
    ],
    "wof:name":"Central Cattle Ranch",
    "wof:placetype":"venue"
},
  "geometry": {"coordinates":[-121.251441,44.159383],"type":"Point"}
}