{
  "type": "Feature",
  "properties": {
    "iso:country":"US",
    "sg:address":"1578 Cleveland Hill Rd",
    "sg:city":"Roseburg",
    "sg:classifiers":[
        {
            "category":"Food & Beverages",
            "subcategory":"Groceries & Convenience Stores",
            "type":"Retail Goods"
        }
    ],
    "sg:phone":"+1 541 440 2227",
    "sg:postcode":"97470",
    "sg:province":"OR",
    "wof:name":"Coffee Creek Deli",
    "wof:placetype":"venue"
},
  "geometry": {"coordinates":[-123.466024,43.267106],"type":"Point"}
}