{
  "type": "Feature",
  "properties": {
    "iso:country":"US",
    "sg:address":"27820 Fern Ridge Rd",
    "sg:city":"Sweet Home",
    "sg:classifiers":[
        {
            "category":"Freight",
            "type":"Transportation"
        }
    ],
    "sg:phone":"+1 541 367 7342",
    "sg:postcode":"97386",
    "sg:province":"OR",
    "sg:tags":[
        "operator",
        "local",
        "trucking"
    ],
    "wof:name":"Alan Cowan Trucking",
    "wof:placetype":"venue"
},
  "geometry": {"coordinates":[-122.767743,44.399635],"type":"Point"}
}