{
  "type": "Feature",
  "properties": {
    "addr:full":"740 N 5th St Jacksonville OR 97530",
    "addr:housenumber":"740",
    "addr:postcode":"97530",
    "addr:street":"N 5Th St",
    "iso:country":"US",
    "sg:address":"740 N 5th St",
    "sg:city":"Jacksonville",
    "sg:classifiers":[
        {
            "category":"Shopping",
            "subcategory":"Used Merchandise",
            "type":"Retail Goods"
        }
    ],
    "sg:phone":"+1 541 899 2070",
    "sg:postcode":"97530",
    "sg:province":"OR",
    "sg:tags":[
        "antique"
    ],
    "wof:name":"Cottage Antiques",
    "wof:placetype":"venue"
},
  "geometry": {"coordinates":[-122.959999,42.318501],"type":"Point"}
}