{
  "type": "Feature",
  "properties": {
    "iso:country":"US",
    "sg:address":"830 NE Holladay St",
    "sg:city":"Portland",
    "sg:classifiers":[
        {
            "category":"Health Services",
            "subcategory":"Clinic",
            "type":"Services"
        }
    ],
    "sg:phone":"+1 503 872 8791",
    "sg:postcode":"97232",
    "sg:province":"OR",
    "sg:tags":[
        "home",
        "agency",
        "employment",
        "care"
    ],
    "wof:name":"Adams & Gray Home Care Inc",
    "wof:placetype":"venue"
},
  "geometry": {"coordinates":[-122.656775,45.529967],"type":"Point"}
}