{
  "type": "Feature",
  "properties": {
    "iso:country":"US",
    "sg:address":"2336 NW 21st Ave",
    "sg:city":"Portland",
    "sg:classifiers":[
        {
            "category":"Wholesale",
            "subcategory":"Construction Materials",
            "type":"Manufacturing & Wholesale Goods"
        }
    ],
    "sg:phone":"+1 503 226 8169",
    "sg:postcode":"97210",
    "sg:province":"OR",
    "sg:tags":[
        "lumber"
    ],
    "wof:name":"Moxon Hardwoods",
    "wof:placetype":"venue"
},
  "geometry": {"coordinates":[-122.694822,45.539166],"type":"Point"}
}