{
  "type": "Feature",
  "properties": {
    "iso:country":"US",
    "sg:address":"SE 21 St and SE Clinton St",
    "sg:city":"Portland",
    "sg:classifiers":[
        {
            "category":"Restaurant",
            "type":"Food & Drink"
        }
    ],
    "sg:postcode":"97255",
    "sg:province":"OR",
    "wof:name":"Clinton Street Cafe",
    "wof:placetype":"venue"
},
  "geometry": {"coordinates":[-122.644621,45.503398],"type":"Point"}
}