{
  "type": "Feature",
  "properties": {
    "iso:country":"US",
    "sg:address":"1988 NE 19th Ave",
    "sg:city":"Canby",
    "sg:classifiers":[
        {
            "category":"Travel",
            "subcategory":"Campground",
            "type":"Entertainment"
        }
    ],
    "sg:phone":"+1 503 266 3837",
    "sg:postcode":"97013",
    "sg:province":"OR",
    "sg:tags":[
        "recreational",
        "park",
        "vehicle"
    ],
    "wof:name":"Mountain Shadow Rv Village",
    "wof:placetype":"venue"
},
  "geometry": {"coordinates":[-122.671798,45.278953],"type":"Point"}
}