{
  "type": "Feature",
  "properties": {
    "iso:country":"US",
    "sg:address":"2395 Redwood Ave",
    "sg:city":"Grants Pass",
    "sg:classifiers":[
        {
            "category":"Professional",
            "type":"Services"
        }
    ],
    "sg:phone":"+1 541 476 6407",
    "sg:postcode":"97527",
    "sg:province":"OR",
    "wof:name":"Outlaw Guide Service",
    "wof:placetype":"venue"
},
  "geometry": {"coordinates":[-123.37477,42.422287],"type":"Point"}
}