{
  "type": "Feature",
  "properties": {
    "iso:country":"US",
    "sg:address":"75288 Troy Rd",
    "sg:city":"Wallowa",
    "sg:classifiers":[
        {
            "category":"Building & Trades",
            "subcategory":"Construction",
            "type":"Services"
        }
    ],
    "sg:phone":"+1 541 663 9663",
    "sg:postcode":"97885",
    "sg:province":"OR",
    "sg:tags":[
        "resurfacing",
        "laying",
        "refinishing",
        "floor"
    ],
    "wof:name":"Western Hardwoods",
    "wof:placetype":"venue"
},
  "geometry": {"coordinates":[-117.493329,45.654277],"type":"Point"}
}