{
  "type": "Feature",
  "properties": {
    "iso:country":"US",
    "sg:address":"7855 SW Dartmouth Road",
    "sg:city":"Portland",
    "sg:classifiers":[
        {
            "category":"Shopping",
            "subcategory":"Optician",
            "type":"Retail Goods"
        }
    ],
    "sg:phone":"+1 503 639 0929",
    "sg:postcode":"97223",
    "sg:province":"OR",
    "sg:tags":[
        "eyewear"
    ],
    "wof:name":"Costco Wholesale Optical",
    "wof:placetype":"venue"
},
  "geometry": {"coordinates":[-122.756343,45.436828],"type":"Point"}
}