{
  "type": "Feature",
  "properties": {
    "addr:full":"549 N 6th St Harrisburg OR 97446",
    "addr:housenumber":"549",
    "addr:postcode":"97446",
    "addr:street":"N 6Th St",
    "iso:country":"US",
    "sg:address":"549 N 6th St",
    "sg:city":"Harrisburg",
    "sg:classifiers":[
        {
            "category":"Social Services",
            "subcategory":"Child Care",
            "type":"Services"
        }
    ],
    "sg:phone":"+1 541 995 1074",
    "sg:postcode":"97446",
    "sg:province":"OR",
    "sg:tags":[
        "day"
    ],
    "wof:name":"In Home Daycare",
    "wof:placetype":"venue"
},
  "geometry": {"coordinates":[-123.16623800000001,44.276427],"type":"Point"}
}