{
  "type": "Feature",
  "properties": {
    "iso:country":"US",
    "sg:address":"5025 NE Cleveland Ave",
    "sg:city":"Portland",
    "sg:classifiers":[
        {
            "category":"Shopping",
            "type":"Retail Goods"
        }
    ],
    "sg:phone":"+1 503 544 7745",
    "sg:postcode":"97211",
    "sg:province":"OR",
    "sg:tags":[
        "merchandise"
    ],
    "wof:name":"Beekay Global Enterprises, Inc.",
    "wof:placetype":"venue"
},
  "geometry": {"coordinates":[-122.665817,45.559278],"type":"Point"}
}