{
  "type": "Feature",
  "properties": {
    "addr:full":"958 NE Kelly Ave Gresham OR 97030",
    "addr:housenumber":"958",
    "addr:postcode":"97030",
    "addr:street":"Ne Kelly Ave",
    "iso:country":"US",
    "sg:address":"958 NE Kelly Ave",
    "sg:city":"Gresham",
    "sg:classifiers":[
        {
            "category":"Military Area",
            "type":"Public Place"
        }
    ],
    "sg:phone":"+1 503 661 7050",
    "sg:postcode":"97030",
    "sg:province":"OR",
    "sg:tags":[
        "force",
        "armed",
        "recruiting"
    ],
    "wof:name":"Oregon Army National Guard",
    "wof:placetype":"venue"
},
  "geometry": {"coordinates":[-122.426135,45.503727],"type":"Point"}
}