{
  "type": "Feature",
  "properties": {
    "iso:country":"US",
    "sg:address":"2043 Old Town Loop Rd",
    "sg:city":"Oakland",
    "sg:classifiers":[
        {
            "category":"Organizations",
            "subcategory":"Non-profit Organization",
            "type":"Services"
        }
    ],
    "sg:phone":"+1 541 459 1440",
    "sg:postcode":"97462",
    "sg:province":"OR",
    "sg:tags":[
        "alternative",
        "abortion"
    ],
    "wof:name":"Right-To-Life",
    "wof:placetype":"venue"
},
  "geometry": {"coordinates":[-123.29530099999999,43.428181],"type":"Point"}
}