{
  "type": "Feature",
  "properties": {
    "addr:full":"34081 Lawrence Rd Deer Island OR 97054",
    "addr:housenumber":"34081",
    "addr:postcode":"97054",
    "addr:street":"Lawrence Rd",
    "iso:country":"US",
    "sg:address":"34081 Lawrence Rd",
    "sg:city":"Deer Island",
    "sg:classifiers":[
        {
            "category":"Arts & Performance",
            "subcategory":"Theater",
            "type":"Entertainment"
        }
    ],
    "sg:phone":"+1 503 397 2224",
    "sg:postcode":"97054",
    "sg:province":"OR",
    "sg:tags":[
        "group"
    ],
    "wof:name":"U B A Star Kareoke Inc",
    "wof:placetype":"venue"
},
  "geometry": {"coordinates":[-122.863916,45.936753],"type":"Point"}
}