{
  "type": "Feature",
  "properties": {
    "iso:country":"US",
    "sg:address":"11125 SW 93rd Ave",
    "sg:city":"Portland",
    "sg:classifiers":[
        {
            "category":"Professional",
            "type":"Services"
        }
    ],
    "sg:phone":"+1 503 620 3307",
    "sg:postcode":"97223",
    "sg:province":"OR",
    "wof:name":"Joel Pena",
    "wof:placetype":"venue"
},
  "geometry": {"coordinates":[-122.773167,45.439399],"type":"Point"}
}