{
  "type": "Feature",
  "properties": {
    "iso:country":"US",
    "sg:address":"2487 Lancaster Dr NE",
    "sg:city":"Salem",
    "sg:classifiers":[
        {
            "category":"Organizations",
            "subcategory":"Religious Organization",
            "type":"Services"
        }
    ],
    "sg:phone":"+1 503 363 8491",
    "sg:postcode":"97305",
    "sg:province":"OR",
    "sg:tags":[
        "church"
    ],
    "sg:website":"www.pfm.org",
    "wof:name":"Prison Fellowship",
    "wof:placetype":"venue"
},
  "geometry": {"coordinates":[-122.983678,44.959803],"type":"Point"}
}