{
  "type": "Feature",
  "properties": {
    "iso:country":"US",
    "sg:address":"3221 W 10th St",
    "sg:city":"The Dalles",
    "sg:classifiers":[
        {
            "category":"Social Services",
            "type":"Services"
        }
    ],
    "sg:phone":"+1 541 298 5104",
    "sg:postcode":"97058",
    "sg:province":"OR",
    "sg:tags":[
        "counselor",
        "marriage",
        "family"
    ],
    "wof:name":"Mid-Columbia Child & Family",
    "wof:placetype":"venue"
},
  "geometry": {"coordinates":[-121.224286,45.621086],"type":"Point"}
}