{
  "type": "Feature",
  "properties": {
    "iso:country":"US",
    "sg:address":"3925 NE 37th Ave",
    "sg:city":"Portland",
    "sg:classifiers":[
        {
            "category":"Professional",
            "subcategory":"Business Services",
            "type":"Services"
        }
    ],
    "sg:phone":"+1 503 281 0475",
    "sg:postcode":"97212",
    "sg:province":"OR",
    "wof:name":"Crest Rutherford & Associates",
    "wof:placetype":"venue"
},
  "geometry": {"coordinates":[-122.625601,45.551037],"type":"Point"}
}