{
  "type": "Feature",
  "properties": {
    "iso:country":"US",
    "sg:address":"1450 W Powell Blvd",
    "sg:city":"Gresham",
    "sg:classifiers":[
        {
            "category":"Health Services",
            "subcategory":"Hospital",
            "type":"Services"
        }
    ],
    "sg:phone":"+1 503 665 5193",
    "sg:postcode":"97030",
    "sg:province":"OR",
    "sg:tags":[
        "mental"
    ],
    "wof:name":"Hoodview Residential Care Ctr",
    "wof:placetype":"venue"
},
  "geometry": {"coordinates":[-122.446257,45.497035],"type":"Point"}
}