{
  "type": "Feature",
  "properties": {
    "iso:country":"US",
    "sg:address":"3401 River Rd N",
    "sg:city":"Salem",
    "sg:classifiers":[
        {
            "category":"Autos & Motor Vehicles",
            "subcategory":"Fuel & Gas Station",
            "type":"Retail Goods"
        }
    ],
    "sg:phone":"+1 503 463 6399",
    "sg:postcode":"97303",
    "sg:province":"OR",
    "sg:tags":[
        "station",
        "gasoline"
    ],
    "wof:name":"Texaco",
    "wof:placetype":"venue"
},
  "geometry": {"coordinates":[-123.02715000000001,44.97576],"type":"Point"}
}