{
  "type": "Feature",
  "properties": {
    "addr:full":"12430 NE Glisan St Portland OR 97230",
    "addr:housenumber":"12430",
    "addr:postcode":"97230",
    "addr:street":"Ne Glisan St",
    "iso:country":"US",
    "sg:address":"12430 NE Glisan St",
    "sg:city":"Portland",
    "sg:classifiers":[
        {
            "category":"Real Estate",
            "subcategory":"Real Estate Operator",
            "type":"Services"
        }
    ],
    "sg:phone":"+1 503 408 5208",
    "sg:postcode":"97230",
    "sg:province":"OR",
    "sg:tags":[
        "apartment"
    ],
    "wof:name":"Fairway Apartments",
    "wof:placetype":"venue"
},
  "geometry": {"coordinates":[-122.535561,45.526239],"type":"Point"}
}