{
  "type": "Feature",
  "properties": {
    "addr:full":"1628 Holly Ave Eugene OR 97408",
    "addr:housenumber":"1628",
    "addr:postcode":"97408",
    "addr:street":"Holly Ave",
    "iso:country":"US",
    "sg:address":"1628 Holly Ave",
    "sg:city":"Eugene",
    "sg:classifiers":[
        {
            "category":"Communications",
            "type":"Services"
        }
    ],
    "sg:phone":"+1 541 484 0994",
    "sg:postcode":"97408",
    "sg:province":"OR",
    "sg:tags":[
        "communication"
    ],
    "wof:name":"Sparrow Communications",
    "wof:placetype":"venue"
},
  "geometry": {"coordinates":[-123.087177,44.091777],"type":"Point"}
}