{
  "type": "Feature",
  "properties": {
    "iso:country":"US",
    "sg:address":"27469 Snyder Rd",
    "sg:city":"Junction City",
    "sg:classifiers":[
        {
            "category":"Farming",
            "subcategory":"Livestock Farm",
            "type":"Manufacturing & Wholesale Goods"
        }
    ],
    "sg:phone":"+1 541 689 1434",
    "sg:postcode":"97448",
    "sg:province":"OR",
    "sg:tags":[
        "beef",
        "feedlot",
        "cattle"
    ],
    "wof:name":"Edward Haag",
    "wof:placetype":"venue"
},
  "geometry": {"coordinates":[-123.263632,44.114008],"type":"Point"}
}