{
  "type": "Feature",
  "properties": {
    "addr:full":"61020 SE 27th St Bend OR 97702",
    "addr:postcode":"61020;97702",
    "addr:street":"Se 27Th St",
    "iso:country":"US",
    "sg:address":"61020 SE 27th St",
    "sg:city":"Bend",
    "sg:classifiers":[
        {
            "category":"Utilities",
            "subcategory":"Recycling",
            "type":"Services"
        }
    ],
    "sg:phone":"+1 541 388 1910",
    "sg:postcode":"97702",
    "sg:province":"OR",
    "wof:name":"Deschutes Recycling",
    "wof:placetype":"venue"
},
  "geometry": {"coordinates":[-121.25909,44.015525],"type":"Point"}
}