{
  "type": "Feature",
  "properties": {
    "addr:full":"1052 Commercial St Astoria OR 97103",
    "addr:housenumber":"1052",
    "addr:postcode":"97103",
    "addr:street":"Commercial St",
    "iso:country":"US",
    "sg:address":"1052 Commercial St",
    "sg:city":"Astoria",
    "sg:classifiers":[
        {
            "category":"Shopping",
            "subcategory":"Used Merchandise",
            "type":"Retail Goods"
        }
    ],
    "sg:phone":"+1 503 325 9722",
    "sg:postcode":"97103",
    "sg:province":"OR",
    "sg:tags":[
        "book"
    ],
    "wof:name":"Backroom Bookstore",
    "wof:placetype":"venue"
},
  "geometry": {"coordinates":[-123.832367,46.189117],"type":"Point"}
}