{
  "type": "Feature",
  "properties": {
    "addr:full":"223 N Spring St Klamath Falls OR 97601",
    "addr:housenumber":"223",
    "addr:postcode":"97601",
    "addr:street":"N Spring St",
    "iso:country":"US",
    "sg:address":"223 N Spring St",
    "sg:city":"Klamath Falls",
    "sg:classifiers":[
        {
            "category":"Building & Trades",
            "subcategory":"Construction",
            "type":"Services"
        }
    ],
    "sg:phone":"+1 541 880 0574",
    "sg:postcode":"97601",
    "sg:province":"OR",
    "wof:name":"National Paving",
    "wof:placetype":"venue"
},
  "geometry": {"coordinates":[-121.775558,42.230479],"type":"Point"}
}