{
  "type": "Feature",
  "properties": {
    "iso:country":"US",
    "sg:address":"3526 NE 57th Ave",
    "sg:city":"Portland",
    "sg:classifiers":[
        {
            "category":"Health Services",
            "subcategory":"Health Practitioner",
            "type":"Services"
        }
    ],
    "sg:phone":"+1 503 281 0030",
    "sg:postcode":"97213",
    "sg:province":"OR",
    "sg:tags":[
        "acupuncture"
    ],
    "wof:name":"Lisa Tongel",
    "wof:placetype":"venue"
},
  "geometry": {"coordinates":[-122.604451,45.548767],"type":"Point"}
}