{
  "type": "Feature",
  "properties": {
    "addr:full":"2780 Canterbury Ln Medford OR 97504",
    "addr:housenumber":"2780",
    "addr:postcode":"97504",
    "addr:street":"Canterbury Ln",
    "iso:country":"US",
    "sg:address":"2780 Canterbury Ln",
    "sg:city":"Medford",
    "sg:classifiers":[
        {
            "category":"Professional",
            "type":"Services"
        },
        {
            "category":"Shopping",
            "subcategory":"Clothing, Apparel, & Fashions",
            "type":"Retail Goods"
        }
    ],
    "sg:phone":"+1 541 773 7048",
    "sg:postcode":"97504",
    "sg:province":"OR",
    "sg:tags":[
        "dressmaker"
    ],
    "wof:name":"Candy's Creations",
    "wof:placetype":"venue"
},
  "geometry": {"coordinates":[-122.839606,42.354906],"type":"Point"}
}