{
  "type": "Feature",
  "properties": {
    "iso:country":"US",
    "sg:address":"920 N Pacific Hwy",
    "sg:city":"Woodburn",
    "sg:classifiers":[
        {
            "category":"Shopping",
            "subcategory":"Clothing, Apparel, & Fashions",
            "type":"Retail Goods"
        }
    ],
    "sg:phone":"+1 503 982 3885",
    "sg:postcode":"97071",
    "sg:province":"OR",
    "wof:name":"Best Clothing",
    "wof:placetype":"venue"
},
  "geometry": {"coordinates":[-122.837895,45.143633],"type":"Point"}
}