{
  "type": "Feature",
  "properties": {
    "iso:country":"US",
    "sg:address":"16880 SE Foster Rd",
    "sg:city":"Portland",
    "sg:classifiers":[
        {
            "category":"Food & Beverages",
            "subcategory":"Specialty",
            "type":"Retail Goods"
        },
        {
            "category":"Food & Beverages",
            "subcategory":"Groceries & Convenience Stores",
            "type":"Retail Goods"
        }
    ],
    "sg:phone":"+1 503 667 0147",
    "sg:postcode":"97236",
    "sg:province":"OR",
    "sg:tags":[
        "grocers-specialty"
    ],
    "wof:name":"Pleasant Valley Market",
    "wof:placetype":"venue"
},
  "geometry": {"coordinates":[-122.514565,45.47719],"type":"Point"}
}