{
  "type": "Feature",
  "properties": {
    "addr:full":"1150 Knutson Ave Ste 10 Medford OR 97504",
    "addr:housenumber":"1150;10",
    "addr:postcode":"97504",
    "addr:street":"Knutson Ave Ste",
    "iso:country":"US",
    "sg:address":"1150 Knutson Ave Ste 10",
    "sg:city":"Medford",
    "sg:classifiers":[
        {
            "category":"Manufacturing",
            "subcategory":"Electronics",
            "type":"Manufacturing & Wholesale Goods"
        },
        {
            "category":"Utilities",
            "subcategory":"Telephone",
            "type":"Services"
        },
        {
            "category":"Communications",
            "type":"Services"
        }
    ],
    "sg:phone":"+1 541 842 1000",
    "sg:postcode":"97504",
    "sg:province":"OR",
    "sg:tags":[
        "equipment",
        "telecommunications-equipment",
        "system",
        "systems-repair",
        "supply"
    ],
    "sg:website":"http://www.callbesttel.com",
    "wof:name":"Best Tel",
    "wof:placetype":"venue"
},
  "geometry": {"coordinates":[-122.872361,42.357471],"type":"Point"}
}