{
  "type": "Feature",
  "properties": {
    "iso:country":"US",
    "sg:address":"202 W Front St",
    "sg:city":"Merrill",
    "sg:classifiers":[
        {
            "category":"Shopping",
            "subcategory":"Musical Instruments",
            "type":"Retail Goods"
        }
    ],
    "sg:phone":"+1 541 798 1002",
    "sg:postcode":"97633",
    "sg:province":"OR",
    "sg:tags":[
        "music",
        "dealer"
    ],
    "wof:name":"Music Store",
    "wof:placetype":"venue"
},
  "geometry": {"coordinates":[-121.601506,42.024083],"type":"Point"}
}