{
  "type": "Feature",
  "properties": {
    "iso:country":"US",
    "sg:address":"560 Irvington Dr",
    "sg:city":"Eugene",
    "sg:classifiers":[
        {
            "category":"Education",
            "subcategory":"School",
            "type":"Public Place"
        }
    ],
    "sg:phone":"+1 541 687 3313",
    "sg:postcode":"97404",
    "sg:province":"OR",
    "wof:name":"Spring Creek Elementary School",
    "wof:placetype":"venue"
},
  "geometry": {"coordinates":[-123.14388,44.115633],"type":"Point"}
}