{
  "type": "Feature",
  "properties": {
    "iso:country":"US",
    "sg:address":"1940 Breyman St NE",
    "sg:city":"Salem",
    "sg:classifiers":[
        {
            "category":"Health Services",
            "subcategory":"Health Practitioner",
            "type":"Services"
        }
    ],
    "sg:phone":"+1 503 581 6512",
    "sg:postcode":"97301",
    "sg:province":"OR",
    "sg:tags":[
        "consulting",
        "management"
    ],
    "wof:name":"Polarity Center of Salem",
    "wof:placetype":"venue"
},
  "geometry": {"coordinates":[-123.015062,44.938256],"type":"Point"}
}