{
  "type": "Feature",
  "properties": {
    "iso:country":"US",
    "sg:address":"90 Country Hill Dr",
    "sg:city":"Roseburg",
    "sg:classifiers":[
        {
            "category":"Professional",
            "subcategory":"Business Services",
            "type":"Services"
        }
    ],
    "sg:phone":"+1 541 672 5408",
    "sg:postcode":"97470",
    "sg:province":"OR",
    "wof:name":"Junker Enterprises Inc",
    "wof:placetype":"venue"
},
  "geometry": {"coordinates":[-123.39902600000001,43.285149],"type":"Point"}
}