{
  "type": "Feature",
  "properties": {
    "addr:full":"6663 SW Beaverton-Hillsdale Hwy Suite 255 Portland OR 97225",
    "addr:housenumber":"6663",
    "addr:postcode":"97225",
    "addr:street":"Sw Beaverton-Hillsdale Hwy Suite 255",
    "iso:country":"US",
    "sg:address":"6663 SW Beaverton-Hillsdale Hwy Suite 255",
    "sg:city":"Portland",
    "sg:classifiers":[
        {
            "category":"Shopping",
            "subcategory":"Pets & Pet Supplies",
            "type":"Retail Goods"
        },
        {
            "category":"Retail",
            "subcategory":"Pet Boarding",
            "type":"Services"
        }
    ],
    "sg:phone":"+1 503 720 4923",
    "sg:postcode":"97225",
    "sg:province":"OR",
    "sg:tags":[
        "walker",
        "dog",
        "boarding/pet",
        "sitting"
    ],
    "sg:website":"www.k-9to5petsitting.com",
    "wof:name":"K-9 to 5 Pet Sitting Service, Inc.",
    "wof:placetype":"venue"
},
  "geometry": {"coordinates":[-122.745302,45.486977],"type":"Point"}
}