{
  "type": "Feature",
  "properties": {
    "iso:country":"US",
    "sg:address":"36590 State Hwy 53",
    "sg:city":"Nehalem",
    "sg:classifiers":[
        {
            "category":"Professional",
            "type":"Services"
        }
    ],
    "sg:phone":"+1 503 368 6950",
    "sg:postcode":"97131",
    "sg:province":"OR",
    "sg:tags":[
        "establishment"
    ],
    "wof:name":"Myers Brothers",
    "wof:placetype":"venue"
},
  "geometry": {"coordinates":[-123.852179,45.721793],"type":"Point"}
}