{
  "type": "Feature",
  "properties": {
    "iso:country":"US",
    "sg:address":"234 S Main St",
    "sg:city":"Condon",
    "sg:classifiers":[
        {
            "category":"Manufacturing",
            "subcategory":"Printing",
            "type":"Manufacturing & Wholesale Goods"
        }
    ],
    "sg:phone":"+1 541 384 3214",
    "sg:postcode":"97823",
    "sg:province":"OR",
    "sg:tags":[
        "screen"
    ],
    "wof:name":"Shirt Shoppe",
    "wof:placetype":"venue"
},
  "geometry": {"coordinates":[-120.184868,45.235797],"type":"Point"}
}