{
  "type": "Feature",
  "properties": {
    "addr:full":"10700 SW Beaverton Hillsdale Hwy Ste 113 Beaverton OR 97005",
    "addr:housenumber":"10700",
    "addr:postcode":"97005",
    "addr:street":"Sw Beaverton Hillsdale Hwy Ste 113",
    "iso:country":"US",
    "sg:address":"10700 SW Beaverton Hillsdale Hwy Ste 113",
    "sg:city":"Beaverton",
    "sg:classifiers":[
        {
            "category":"Health Services",
            "subcategory":"Doctor",
            "type":"Services"
        }
    ],
    "sg:phone":"+1 503 643 1113",
    "sg:postcode":"97005",
    "sg:province":"OR",
    "sg:tags":[
        "surgeon",
        "oral"
    ],
    "wof:name":"Stratford E Wayne DDS",
    "wof:placetype":"venue"
},
  "geometry": {"coordinates":[-122.78719100000001,45.486515],"type":"Point"}
}