{
  "type": "Feature",
  "properties": {
    "iso:country":"US",
    "sg:address":"945 Scepter Ct NE",
    "sg:city":"Salem",
    "sg:classifiers":[
        {
            "category":"Banks & Credit Unions",
            "subcategory":"Bank",
            "type":"Services"
        }
    ],
    "sg:phone":"+1 503 588 7171",
    "sg:postcode":"97301",
    "sg:province":"OR",
    "wof:name":"Fifth Pockets",
    "wof:placetype":"venue"
},
  "geometry": {"coordinates":[-122.970437,44.942251],"type":"Point"}
}