{
  "type": "Feature",
  "properties": {
    "iso:country":"US",
    "sg:address":"8195 Sunnyside Rd SE",
    "sg:city":"Salem",
    "sg:classifiers":[
        {
            "category":"Retail",
            "subcategory":"Portrait Studio",
            "type":"Services"
        }
    ],
    "sg:phone":"+1 503 588 5442",
    "sg:postcode":"97306",
    "sg:province":"OR",
    "sg:tags":[
        "photo"
    ],
    "sg:website":"www.sunnysidestudio.com",
    "wof:name":"Sunnyside Studio",
    "wof:placetype":"venue"
},
  "geometry": {"coordinates":[-123.018978,44.836303],"type":"Point"}
}