{
  "type": "Feature",
  "properties": {
    "iso:country":"US",
    "sg:address":"201 Highway 82",
    "sg:city":"Enterprise",
    "sg:classifiers":[
        {
            "category":"Shopping",
            "subcategory":"Beauty & Cosmetics",
            "type":"Retail Goods"
        },
        {
            "category":"Shopping",
            "subcategory":"Pharmacy",
            "type":"Retail Goods"
        }
    ],
    "sg:phone":"+1 541 426 0320",
    "sg:postcode":"97828",
    "sg:province":"OR",
    "sg:tags":[
        "perfume",
        "salons-equipment",
        "supply"
    ],
    "wof:name":"Ed Staub & Sons",
    "wof:placetype":"venue"
},
  "geometry": {"coordinates":[-117.274777,45.420172],"type":"Point"}
}