{
  "type": "Feature",
  "properties": {
    "addr:full":"6012 N Umpqua Hwy Roseburg OR 97470",
    "addr:housenumber":"6012",
    "addr:postcode":"97470",
    "addr:street":"N Umpqua Hwy",
    "iso:country":"US",
    "sg:address":"6012 N Umpqua Hwy",
    "sg:city":"Roseburg",
    "sg:classifiers":[
        {
            "category":"Travel",
            "subcategory":"Campground",
            "type":"Entertainment"
        }
    ],
    "sg:phone":"+1 541 672 0016",
    "sg:postcode":"97470",
    "sg:province":"OR",
    "sg:tags":[
        "trailer"
    ],
    "wof:name":"Coning Rv Storage",
    "wof:placetype":"venue"
},
  "geometry": {"coordinates":[-123.262801,43.212406],"type":"Point"}
}