{
  "type": "Feature",
  "properties": {
    "addr:full":"484 NW 1st St Canyonville OR 97417",
    "addr:housenumber":"484",
    "addr:postcode":"97417",
    "addr:street":"Nw 1St St",
    "iso:country":"US",
    "sg:address":"484 NW 1st St",
    "sg:city":"Canyonville",
    "sg:classifiers":[
        {
            "category":"Personal",
            "type":"Services"
        },
        {
            "category":"Retail",
            "subcategory":"Auto Rental",
            "type":"Services"
        },
        {
            "category":"Retail",
            "subcategory":"Storage",
            "type":"Services"
        }
    ],
    "sg:phone":"+1 541 839 4721",
    "sg:postcode":"97417",
    "sg:province":"OR",
    "sg:tags":[
        "renting",
        "moving-self",
        "leasing",
        "truck",
        "mover",
        "trailer"
    ],
    "sg:website":"http://www.uhaul.com/Locations/Rentals-near-Canyonville-OR-97417/036159",
    "wof:name":"U-Haul Neighborhood Dealer - Bills Tires Towing&automotive",
    "wof:placetype":"venue"
},
  "geometry": {"coordinates":[-123.28256,42.926773],"type":"Point"}
}