{
  "type": "Feature",
  "properties": {
    "addr:full":"327 SW Pine St Portland OR 97204",
    "addr:housenumber":"327",
    "addr:postcode":"97204",
    "addr:street":"Sw Pine St",
    "iso:country":"US",
    "sg:address":"327 SW Pine St",
    "sg:city":"Portland",
    "sg:classifiers":[
        {
            "category":"Personal",
            "subcategory":"Beauty Salon",
            "type":"Services"
        }
    ],
    "sg:phone":"+1 503 228 0389",
    "sg:postcode":"97204",
    "sg:province":"OR",
    "sg:tags":[
        "shop",
        "spa",
        "day"
    ],
    "sg:website":"http://www.salonnyla.com",
    "wof:name":"Salon Nyla The Day Spa",
    "wof:placetype":"venue"
},
  "geometry": {"coordinates":[-122.674021,45.521665],"type":"Point"}
}