{
  "type": "Feature",
  "properties": {
    "iso:country":"US",
    "sg:address":"16981 NW Countryridge Dr",
    "sg:city":"Portland",
    "sg:classifiers":[
        {
            "category":"Professional",
            "subcategory":"Computer Services",
            "type":"Services"
        }
    ],
    "sg:phone":"+1 503 645 0475",
    "sg:postcode":"97229",
    "sg:province":"OR",
    "sg:tags":[
        "development",
        "software"
    ],
    "wof:name":"Turing Solutions Intl LLC",
    "wof:placetype":"venue"
},
  "geometry": {"coordinates":[-122.851535,45.554873],"type":"Point"}
}