{
  "type": "Feature",
  "properties": {
    "addr:full":"10149 SW Barbur Blvd Portland OR 97219",
    "addr:housenumber":"10149",
    "addr:postcode":"97219",
    "addr:street":"Sw Barbur Blvd",
    "iso:country":"US",
    "sg:address":"10149 SW Barbur Blvd",
    "sg:city":"Portland",
    "sg:classifiers":[
        {
            "category":"Shopping",
            "subcategory":"Computers & Home Electronics",
            "type":"Retail Goods"
        }
    ],
    "sg:phone":"+1 503 452 0591",
    "sg:postcode":"97219",
    "sg:province":"OR",
    "sg:tags":[
        "equipment",
        "dealer"
    ],
    "wof:name":"Asci Inc",
    "wof:placetype":"venue"
},
  "geometry": {"coordinates":[-122.725138,45.452096],"type":"Point"}
}