{
  "type": "Feature",
  "properties": {
    "iso:country":"US",
    "sg:address":"811 E Main St",
    "sg:city":"Cottage Grove",
    "sg:classifiers":[
        {
            "category":"Wholesale",
            "subcategory":"Farm Supplies",
            "type":"Manufacturing & Wholesale Goods"
        }
    ],
    "sg:phone":"+1 541 942 3663",
    "sg:postcode":"97424",
    "sg:province":"OR",
    "sg:tags":[
        "bulb",
        "seed"
    ],
    "wof:name":"Bejoseeds Inc",
    "wof:placetype":"venue"
},
  "geometry": {"coordinates":[-123.059956,43.797172],"type":"Point"}
}