{
  "type": "Feature",
  "properties": {
    "addr:full":"673 E Main St Hillsboro OR 97123",
    "addr:housenumber":"673",
    "addr:postcode":"97123",
    "addr:street":"E Main St",
    "iso:country":"US",
    "sg:address":"673 E Main St",
    "sg:city":"Hillsboro",
    "sg:classifiers":[
        {
            "category":"Building & Trades",
            "subcategory":"Construction",
            "type":"Services"
        }
    ],
    "sg:phone":"+1 503 648 7605",
    "sg:postcode":"97123",
    "sg:province":"OR",
    "sg:tags":[
        "painter"
    ],
    "wof:name":"Everett's Quality Painting Inc",
    "wof:placetype":"venue"
},
  "geometry": {"coordinates":[-122.98074,45.522563],"type":"Point"}
}