{
  "type": "Feature",
  "properties": {
    "iso:country":"US",
    "sg:address":"5001 SE Brooklyn St",
    "sg:city":"Portland",
    "sg:classifiers":[
        {
            "category":"Professional",
            "subcategory":"Art Services",
            "type":"Services"
        }
    ],
    "sg:phone":"+1 503 231 0307",
    "sg:postcode":"97206",
    "sg:province":"OR",
    "sg:tags":[
        "photography",
        "commercial"
    ],
    "wof:name":"Art",
    "wof:placetype":"venue"
},
  "geometry": {"coordinates":[-122.610096,45.500972],"type":"Point"}
}