{
  "type": "Feature",
  "properties": {
    "iso:country":"US",
    "sg:address":"52499 Columbia River Hwy",
    "sg:city":"Scappoose",
    "sg:classifiers":[
        {
            "category":"Bars & Pubs",
            "type":"Food & Drink"
        }
    ],
    "sg:phone":"+1 503 543 8362",
    "sg:postcode":"97056",
    "sg:province":"OR",
    "wof:name":"Wig Wam Tavern",
    "wof:placetype":"venue"
},
  "geometry": {"coordinates":[-122.878142,45.757505],"type":"Point"}
}