{
  "type": "Feature",
  "properties": {
    "iso:country":"US",
    "sg:address":"485 S Main St",
    "sg:city":"Banks",
    "sg:classifiers":[
        {
            "category":"Shopping",
            "subcategory":"Computers & Home Electronics",
            "type":"Retail Goods"
        }
    ],
    "sg:phone":"+1 503 324 1009",
    "sg:postcode":"97106",
    "sg:province":"OR",
    "wof:name":"Randall Stenlund",
    "wof:placetype":"venue"
},
  "geometry": {"coordinates":[-123.114524,45.614008],"type":"Point"}
}