{
  "type": "Feature",
  "properties": {
    "iso:country":"US",
    "sg:address":"40 SW Williams Dr",
    "sg:city":"Beaverton",
    "sg:classifiers":[
        {
            "category":"Shopping",
            "type":"Retail Goods"
        }
    ],
    "sg:phone":"+1 503 310 7215",
    "sg:postcode":"97005",
    "sg:province":"OR",
    "sg:tags":[
        "merchandise"
    ],
    "wof:name":"Air Depot",
    "wof:placetype":"venue"
},
  "geometry": {"coordinates":[-122.812791,45.519721],"type":"Point"}
}