{
  "type": "Feature",
  "properties": {
    "iso:country":"US",
    "sg:address":"5932 SE 92nd Ave",
    "sg:city":"Portland",
    "sg:classifiers":[
        {
            "category":"Communications",
            "type":"Services"
        }
    ],
    "sg:phone":"+1 503 914 6279",
    "sg:postcode":"97266",
    "sg:province":"OR",
    "wof:name":"Mod Media",
    "wof:placetype":"venue"
},
  "geometry": {"coordinates":[-122.568611,45.479568],"type":"Point"}
}