{
  "type": "Feature",
  "properties": {
    "iso:country":"US",
    "sg:address":"1805 X Ave",
    "sg:city":"La Grande",
    "sg:classifiers":[
        {
            "category":"Freight",
            "type":"Transportation"
        }
    ],
    "sg:phone":"+1 541 963 4256",
    "sg:postcode":"97850",
    "sg:province":"OR",
    "sg:tags":[
        "operator",
        "local",
        "trucking"
    ],
    "wof:name":"Todd Stone Trucking",
    "wof:placetype":"venue"
},
  "geometry": {"coordinates":[-118.081356,45.334938],"type":"Point"}
}