{
  "type": "Feature",
  "properties": {
    "addr:full":"7025 SW Macadam Ave Portland OR 97219",
    "addr:housenumber":"7025",
    "addr:postcode":"97219",
    "addr:street":"Sw Macadam Ave",
    "iso:country":"US",
    "sg:address":"7025 SW Macadam Ave",
    "sg:city":"Portland",
    "sg:classifiers":[
        {
            "category":"Professional",
            "subcategory":"Business Services",
            "type":"Services"
        }
    ],
    "sg:phone":"+1 503 244 0633",
    "sg:postcode":"97219",
    "sg:province":"OR",
    "wof:name":"L Decor",
    "wof:placetype":"venue"
},
  "geometry": {"coordinates":[-122.671572,45.473096],"type":"Point"}
}