{
  "type": "Feature",
  "properties": {
    "iso:country":"US",
    "sg:address":"197 A St E",
    "sg:city":"Vale",
    "sg:classifiers":[
        {
            "category":"Restaurant",
            "type":"Food & Drink"
        }
    ],
    "sg:phone":"+1 541 473 3777",
    "sg:postcode":"97918",
    "sg:province":"OR",
    "sg:tags":[
        "house",
        "steak",
        "barbecue"
    ],
    "wof:name":"Sagebrush Saloon & Bbq",
    "wof:placetype":"venue"
},
  "geometry": {"coordinates":[-117.239103,43.98188],"type":"Point"}
}