{
  "type": "Feature",
  "properties": {
    "iso:country":"US",
    "sg:address":"84455 Hwy 11",
    "sg:city":"Milton Freewater",
    "sg:classifiers":[
        {
            "category":"Retail",
            "subcategory":"Auto Repair",
            "type":"Services"
        }
    ],
    "sg:phone":"+1 541 938 3875",
    "sg:postcode":"97862",
    "sg:province":"OR",
    "sg:tags":[
        "engine",
        "diesel"
    ],
    "wof:name":"Wentland Diesel Service Inc",
    "wof:placetype":"venue"
},
  "geometry": {"coordinates":[-118.387145,45.969889],"type":"Point"}
}