{
  "type": "Feature",
  "properties": {
    "iso:country":"US",
    "sg:address":"545 W Umpqua St",
    "sg:city":"Roseburg",
    "sg:classifiers":[
        {
            "category":"Health Services",
            "subcategory":"Doctor",
            "type":"Services"
        }
    ],
    "sg:phone":"+1 541 673 2267",
    "sg:postcode":"97470",
    "sg:province":"OR",
    "sg:tags":[
        "medical"
    ],
    "wof:name":"Patrice McGowan MD",
    "wof:placetype":"venue"
},
  "geometry": {"coordinates":[-123.359022,43.215297],"type":"Point"}
}