{
  "type": "Feature",
  "properties": {
    "iso:country":"US",
    "sg:address":"31217 SW Metolius Ct",
    "sg:city":"Wilsonville",
    "sg:classifiers":[
        {
            "category":"Manufacturing",
            "subcategory":"Buildings",
            "type":"Manufacturing & Wholesale Goods"
        },
        {
            "category":"Building & Trades",
            "subcategory":"Construction",
            "type":"Services"
        }
    ],
    "sg:phone":"+1 503 570 0738",
    "sg:postcode":"97070",
    "sg:province":"OR",
    "sg:tags":[
        "home",
        "builder",
        "contractor"
    ],
    "wof:name":"G & B Industries",
    "wof:placetype":"venue"
},
  "geometry": {"coordinates":[-122.766257,45.294135],"type":"Point"}
}