{
  "type": "Feature",
  "properties": {
    "iso:country":"US",
    "sg:address":"3424 S Pacific Hwy",
    "sg:city":"Medford",
    "sg:classifiers":[
        {
            "category":"Home & Garden",
            "subcategory":"Furniture",
            "type":"Retail Goods"
        }
    ],
    "sg:phone":"+1 541 535 8300",
    "sg:postcode":"97501",
    "sg:province":"OR",
    "wof:name":"R Furniture Inc",
    "wof:placetype":"venue"
},
  "geometry": {"coordinates":[-122.83674000000001,42.290101],"type":"Point"}
}