{
  "type": "Feature",
  "properties": {
    "addr:full":"4630 Sussex St Depoe Bay OR 97341",
    "addr:housenumber":"4630",
    "addr:postcode":"97341",
    "addr:street":"Sussex St",
    "iso:country":"US",
    "sg:address":"4630 Sussex St",
    "sg:city":"Depoe Bay",
    "sg:classifiers":[
        {
            "category":"Building & Trades",
            "subcategory":"Construction",
            "type":"Services"
        }
    ],
    "sg:phone":"+1 541 764 2576",
    "sg:postcode":"97341",
    "sg:province":"OR",
    "sg:tags":[
        "house",
        "general",
        "contractor"
    ],
    "wof:name":"Daniel W Nelson Construction",
    "wof:placetype":"venue"
},
  "geometry": {"coordinates":[-124.042024,44.856445],"type":"Point"}
}