{
  "type": "Feature",
  "properties": {
    "addr:full":"1990 Echo Hollow Rd Eugene OR 97402",
    "addr:housenumber":"1990",
    "addr:postcode":"97402",
    "addr:street":"Echo Hollow Rd",
    "iso:country":"US",
    "sg:address":"1990 Echo Hollow Rd",
    "sg:city":"Eugene",
    "sg:classifiers":[
        {
            "category":"Shopping",
            "subcategory":"Discount & Variety Stores",
            "type":"Retail Goods"
        }
    ],
    "sg:phone":"+1 541 689 9362",
    "sg:postcode":"97402",
    "sg:province":"OR",
    "wof:name":"Dollar Store 902",
    "wof:placetype":"venue"
},
  "geometry": {"coordinates":[-123.16796100000001,44.082677],"type":"Point"}
}