{
  "type": "Feature",
  "properties": {
    "iso:country":"US",
    "sg:address":"1228 Sears Dr",
    "sg:city":"Ontario",
    "sg:classifiers":[
        {
            "category":"Retail",
            "subcategory":"Repair Shop",
            "type":"Services"
        }
    ],
    "sg:phone":"+1 541 889 7943",
    "sg:postcode":"97914",
    "sg:province":"OR",
    "wof:name":"Autosound Excellence",
    "wof:placetype":"venue"
},
  "geometry": {"coordinates":[-116.981649,44.029904],"type":"Point"}
}