{
  "type": "Feature",
  "properties": {
    "addr:full":"10848 SE Oak Street Portland OR 97222",
    "addr:housenumber":"10848",
    "addr:postcode":"97222",
    "addr:street":"Se Oak Street",
    "iso:country":"US",
    "sg:address":"10848 SE Oak Street",
    "sg:city":"Portland",
    "sg:classifiers":[
        {
            "category":"Cinema",
            "subcategory":"Movie Rental",
            "type":"Entertainment"
        }
    ],
    "sg:phone":"+1 503 659 6884",
    "sg:postcode":"97222",
    "sg:province":"OR",
    "sg:tags":[
        "game",
        "video"
    ],
    "sg:website":"www.blockbuster.com",
    "wof:name":"Blockbuster Video",
    "wof:placetype":"venue"
},
  "geometry": {"coordinates":[-122.628917,45.444448],"type":"Point"}
}