{
  "type": "Feature",
  "properties": {
    "iso:country":"US",
    "sg:address":"550 NW Franklin St., Suite 200",
    "sg:city":"Bend",
    "sg:classifiers":[
        {
            "category":"Professional",
            "subcategory":"Computer Services",
            "type":"Services"
        }
    ],
    "sg:phone":"+1 541 306 3374",
    "sg:postcode":"97701",
    "sg:province":"OR",
    "sg:tags":[
        "online-marketing",
        "local-search",
        "local-online-marketing",
        "local-internet-search",
        "local-internet-marketing",
        "senior-housing-online-marketing",
        "self-storage-online-marketing",
        "student-housing-online-marketing",
        "multi-family-online-marketing",
        "local-marketing-solut"
    ],
    "sg:website":"http://www.g5platform.com",
    "wof:name":"G5",
    "wof:placetype":"venue"
},
  "geometry": {"coordinates":[-121.312568,44.056752],"type":"Point"}
}