{
  "type": "Feature",
  "properties": {
    "iso:country":"US",
    "sg:address":"326 Kennet St",
    "sg:city":"Medford",
    "sg:classifiers":[
        {
            "category":"Banks & Credit Unions",
            "subcategory":"Bank",
            "type":"Services"
        }
    ],
    "sg:phone":"+1 541 858 5626",
    "sg:postcode":"97501",
    "sg:province":"OR",
    "sg:tags":[
        "broker",
        "mortgage"
    ],
    "wof:name":"Rennett Kae and Associates",
    "wof:placetype":"venue"
},
  "geometry": {"coordinates":[-122.87908299999999,42.341877],"type":"Point"}
}