{
  "type": "Feature",
  "properties": {
    "addr:full":"8310 N Interstate Pl Portland OR 97217",
    "addr:housenumber":"8310",
    "addr:postcode":"97217",
    "addr:street":"N Interstate Pl",
    "iso:country":"US",
    "sg:address":"8310 N Interstate Pl",
    "sg:city":"Portland",
    "sg:classifiers":[
        {
            "category":"Travel",
            "subcategory":"Hotels & Motels",
            "type":"Entertainment"
        },
        {
            "category":"Real Estate",
            "subcategory":"Real Estate Operator",
            "type":"Services"
        }
    ],
    "sg:phone":"+1 503 285 4626",
    "sg:postcode":"97217",
    "sg:province":"OR",
    "sg:tags":[
        "apartment"
    ],
    "wof:name":"City of Roses Motel",
    "wof:placetype":"venue"
},
  "geometry": {"coordinates":[-122.682694,45.583214],"type":"Point"}
}