{
  "type": "Feature",
  "properties": {
    "iso:country":"US",
    "sg:address":"15203 NW Burlington Ct",
    "sg:city":"Portland",
    "sg:classifiers":[
        {
            "category":"Building & Trades",
            "subcategory":"Construction",
            "type":"Services"
        }
    ],
    "sg:phone":"+1 503 621 3767",
    "sg:postcode":"97231",
    "sg:province":"OR",
    "sg:tags":[
        "house",
        "nonresidential"
    ],
    "wof:name":"In The Works Cnstr & Design",
    "wof:placetype":"venue"
},
  "geometry": {"coordinates":[-122.834085,45.657908],"type":"Point"}
}