{
  "type": "Feature",
  "properties": {
    "iso:country":"US",
    "sg:address":"836 NW 11th St",
    "sg:city":"Corvallis",
    "sg:classifiers":[
        {
            "category":"Education",
            "subcategory":"School",
            "type":"Public Place"
        }
    ],
    "sg:phone":"+1 541 757 5871",
    "sg:postcode":"97330",
    "sg:province":"OR",
    "sg:tags":[
        "business",
        "association"
    ],
    "sg:website":"www.corvallis.k12.or.us",
    "wof:name":"Corvallis High School",
    "wof:placetype":"venue"
},
  "geometry": {"coordinates":[-123.265831,44.573818],"type":"Point"}
}