{
  "type": "Feature",
  "properties": {
    "addr:full":"1107 NE Stephens St Roseburg OR 97470",
    "addr:housenumber":"1107",
    "addr:postcode":"97470",
    "addr:street":"Ne Stephens St",
    "iso:country":"US",
    "sg:address":"1107 NE Stephens St",
    "sg:city":"Roseburg",
    "sg:classifiers":[
        {
            "category":"Travel",
            "subcategory":"Hotels & Motels",
            "type":"Entertainment"
        }
    ],
    "sg:phone":"+1 541 673 5569",
    "sg:postcode":"97470",
    "sg:province":"OR",
    "wof:name":"Casa Loma Motel",
    "wof:placetype":"venue"
},
  "geometry": {"coordinates":[-123.347145,43.223878],"type":"Point"}
}