{
  "type": "Feature",
  "properties": {
    "addr:full":"1201 NE Lloyd Blvd Portland OR 97232",
    "addr:housenumber":"1201",
    "addr:postcode":"97232",
    "addr:street":"Ne Lloyd Blvd",
    "iso:country":"US",
    "sg:address":"1201 NE Lloyd Blvd",
    "sg:city":"Portland",
    "sg:classifiers":[
        {
            "category":"Parking",
            "type":"Transportation"
        }
    ],
    "sg:phone":"+1 503 460 0246",
    "sg:postcode":"97232",
    "sg:province":"OR",
    "wof:name":"City Center Parking",
    "wof:placetype":"venue"
},
  "geometry": {"coordinates":[-122.65366299999999,45.529417],"type":"Point"}
}