{
  "type": "Feature",
  "properties": {
    "iso:country":"US",
    "sg:address":"939 Sherwood Pl",
    "sg:city":"Eugene",
    "sg:classifiers":[
        {
            "category":"Education",
            "subcategory":"Special Training",
            "type":"Public Place"
        }
    ],
    "sg:phone":"+1 541 953 7072",
    "sg:postcode":"97401",
    "sg:province":"OR",
    "sg:tags":[
        "educational"
    ],
    "sg:website":"http://www.oregonadventure.com",
    "wof:name":"Oregon Adventure Student Exch",
    "wof:placetype":"venue"
},
  "geometry": {"coordinates":[-123.10397399999999,44.076702],"type":"Point"}
}