{
  "type": "Feature",
  "properties": {
    "addr:full":"507 N 19th Ave Unit 87 Cornelius OR 97113",
    "addr:housenumber":"507;87",
    "addr:postcode":"97113",
    "addr:street":"N 19Th Ave Unit",
    "iso:country":"US",
    "sg:address":"507 N 19th Ave Unit 87",
    "sg:city":"Cornelius",
    "sg:classifiers":[
        {
            "category":"Building & Trades",
            "subcategory":"Construction",
            "type":"Services"
        }
    ],
    "sg:phone":"+1 503 359 4318",
    "sg:postcode":"97113",
    "sg:province":"OR",
    "sg:tags":[
        "manufactured",
        "housing-communities"
    ],
    "wof:name":"Smoketree Mobile Park",
    "wof:placetype":"venue"
},
  "geometry": {"coordinates":[-123.04827899999999,45.524131],"type":"Point"}
}