{
  "type": "Feature",
  "properties": {
    "iso:country":"US",
    "sg:address":"5501 SE 71st Ave",
    "sg:city":"Portland",
    "sg:classifiers":[
        {
            "category":"Building & Trades",
            "subcategory":"Locksmith",
            "type":"Services"
        }
    ],
    "sg:phone":"+1 503 937 0083",
    "sg:postcode":"97206",
    "sg:province":"OR",
    "sg:tags":[
        "key"
    ],
    "wof:name":"A Locksmith A 24 Hour",
    "wof:placetype":"venue"
},
  "geometry": {"coordinates":[-122.590476,45.483062],"type":"Point"}
}