{
  "type": "Feature",
  "properties": {
    "iso:country":"US",
    "sg:address":"17070 SW 72nd Ave",
    "sg:city":"Portland",
    "sg:classifiers":[
        {
            "category":"Building & Trades",
            "subcategory":"Locksmith",
            "type":"Services"
        }
    ],
    "sg:phone":"+1 503 207 0826",
    "sg:postcode":"97224",
    "sg:province":"OR",
    "sg:tags":[
        "key"
    ],
    "wof:name":"0 Hassle Locksmith Service",
    "wof:placetype":"venue"
},
  "geometry": {"coordinates":[-122.749745,45.39674],"type":"Point"}
}