{
  "type": "Feature",
  "properties": {
    "addr:full":"280 Nebesna Street Cannon Beach OR 97138",
    "addr:housenumber":"280",
    "addr:postcode":"97138",
    "addr:street":"Nebesna Street",
    "iso:country":"US",
    "sg:address":"280 Nebesna Street",
    "sg:city":"Cannon Beach",
    "sg:classifiers":[
        {
            "category":"Travel",
            "subcategory":"Hotels & Motels",
            "type":"Entertainment"
        },
        {
            "category":"Travel",
            "subcategory":"Travel Agent",
            "type":"Entertainment"
        }
    ],
    "sg:phone":"+1 503 436 2266",
    "sg:postcode":"97138",
    "sg:province":"OR",
    "sg:tags":[
        "rental",
        "vacation"
    ],
    "sg:website":"www.seasprite.com",
    "wof:name":"Sea Sprite at Haystack Rock",
    "wof:placetype":"venue"
},
  "geometry": {"coordinates":[-123.961957,45.877773],"type":"Point"}
}