{
  "type": "Feature",
  "properties": {
    "addr:full":"1389 Old River Rd NE Siletz OR 97380",
    "addr:housenumber":"1389",
    "addr:postcode":"97380",
    "addr:street":"Old River Rd Ne",
    "iso:country":"US",
    "sg:address":"1389 Old River Rd NE",
    "sg:city":"Siletz",
    "sg:classifiers":[
        {
            "category":"Manufacturing",
            "subcategory":"Glass & Minerals",
            "type":"Manufacturing & Wholesale Goods"
        }
    ],
    "sg:phone":"+1 541 444 2972",
    "sg:postcode":"97380",
    "sg:province":"OR",
    "sg:tags":[
        "mfg"
    ],
    "wof:name":"Carlson Art Glass",
    "wof:placetype":"venue"
},
  "geometry": {"coordinates":[-123.908975,44.738462],"type":"Point"}
}