{
  "type": "Feature",
  "properties": {
    "iso:country":"US",
    "sg:address":"652 SE Baseline St",
    "sg:city":"Hillsboro",
    "sg:classifiers":[
        {
            "category":"Building & Trades",
            "subcategory":"Construction",
            "type":"Services"
        }
    ],
    "sg:phone":"+1 503 681 8392",
    "sg:postcode":"97123",
    "sg:province":"OR",
    "sg:tags":[
        "repairing",
        "remodeling",
        "contractor"
    ],
    "wof:name":"Bryant Windows",
    "wof:placetype":"venue"
},
  "geometry": {"coordinates":[-122.979783,45.519954],"type":"Point"}
}