{
  "type": "Feature",
  "properties": {
    "iso:country":"US",
    "sg:address":"44065 Anderson Ln",
    "sg:city":"Astoria",
    "sg:classifiers":[
        {
            "category":"Farming",
            "subcategory":"Farm",
            "type":"Manufacturing & Wholesale Goods"
        }
    ],
    "sg:phone":"+1 503 458 5620",
    "sg:postcode":"97103",
    "sg:province":"OR",
    "sg:tags":[
        "crop",
        "general"
    ],
    "wof:name":"Autio Family Farm LLC",
    "wof:placetype":"venue"
},
  "geometry": {"coordinates":[-123.508691,46.19987],"type":"Point"}
}