{
  "type": "Feature",
  "properties": {
    "iso:country":"US",
    "sg:address":"5221 SW Corbett Ave",
    "sg:city":"Portland",
    "sg:classifiers":[
        {
            "category":"Building & Trades",
            "subcategory":"Plumbing",
            "type":"Services"
        }
    ],
    "sg:phone":"+1 503 224 5221",
    "sg:postcode":"97239",
    "sg:province":"OR",
    "sg:tags":[
        "mechanical",
        "contractor"
    ],
    "wof:name":"Kinetic Systems Inc",
    "wof:placetype":"venue"
},
  "geometry": {"coordinates":[-122.676852,45.485453],"type":"Point"}
}