{
  "type": "Feature",
  "properties": {
    "iso:country":"US",
    "sg:address":"34900 5th St",
    "sg:city":"Pacific City",
    "sg:classifiers":[
        {
            "category":"Travel",
            "subcategory":"Campground",
            "type":"Entertainment"
        }
    ],
    "sg:phone":"+1 503 965 6820",
    "sg:postcode":"97135",
    "sg:province":"OR",
    "wof:name":"Pacific City Trailer Park",
    "wof:placetype":"venue"
},
  "geometry": {"coordinates":[-123.960114,45.202521],"type":"Point"}
}