{
  "type": "Feature",
  "properties": {
    "iso:country":"US",
    "sg:address":"1336 Madrone St",
    "sg:city":"Ashland",
    "sg:classifiers":[
        {
            "category":"Building & Trades",
            "subcategory":"Construction",
            "type":"Services"
        }
    ],
    "sg:phone":"+1 541 488 2017",
    "sg:postcode":"97520",
    "sg:province":"OR",
    "sg:tags":[
        "contractor"
    ],
    "wof:name":"Jerry Nutter",
    "wof:placetype":"venue"
},
  "geometry": {"coordinates":[-122.692302,42.183876],"type":"Point"}
}