{
  "type": "Feature",
  "properties": {
    "addr:full":"7430 SW Cherry Dr Portland OR 97223",
    "addr:housenumber":"7430",
    "addr:postcode":"97223",
    "addr:street":"Sw Cherry Dr",
    "iso:country":"US",
    "sg:address":"7430 SW Cherry Dr",
    "sg:city":"Portland",
    "sg:classifiers":[
        {
            "category":"Organizations",
            "subcategory":"Community Association",
            "type":"Services"
        }
    ],
    "sg:phone":"+1 503 620 3613",
    "sg:postcode":"97223",
    "sg:province":"OR",
    "wof:name":"Fernview Summer Home Asso",
    "wof:placetype":"venue"
},
  "geometry": {"coordinates":[-122.75190600000001,45.421663],"type":"Point"}
}