{
  "type": "Feature",
  "properties": {
    "iso:country":"US",
    "sg:address":"7310 SW 104th Ave",
    "sg:city":"Beaverton",
    "sg:classifiers":[
        {
            "category":"Restaurant",
            "type":"Food & Drink"
        }
    ],
    "sg:phone":"+1 503 520 9780",
    "sg:postcode":"97008",
    "sg:province":"OR",
    "sg:tags":[
        "asian",
        "pan",
        "japanese"
    ],
    "wof:name":"Kaze Japanese Restaurant",
    "wof:placetype":"venue"
},
  "geometry": {"coordinates":[-122.783413,45.46734],"type":"Point"}
}