{
  "type": "Feature",
  "properties": {
    "iso:country":"US",
    "sg:address":"34420 SE Jarl Rd",
    "sg:city":"Boring",
    "sg:classifiers":[
        {
            "category":"Building & Trades",
            "subcategory":"Construction",
            "type":"Services"
        }
    ],
    "sg:phone":"+1 503 668 7456",
    "sg:postcode":"97009",
    "sg:province":"OR",
    "sg:tags":[
        "general",
        "contractor"
    ],
    "wof:name":"Trimble Construction Co",
    "wof:placetype":"venue"
},
  "geometry": {"coordinates":[-122.307914,45.409259],"type":"Point"}
}