{
  "type": "Feature",
  "properties": {
    "iso:country":"US",
    "sg:address":"2201 N Killingsworth St",
    "sg:city":"Portland",
    "sg:classifiers":[
        {
            "category":"Restaurant",
            "type":"Food & Drink"
        }
    ],
    "sg:phone":"+1 503 735 4652",
    "sg:postcode":"97217",
    "sg:province":"OR",
    "sg:tags":[
        "breakfast",
        "eating",
        "brunch"
    ],
    "sg:website":"www.beaterville.com",
    "wof:name":"Beaterville Cafe",
    "wof:placetype":"venue"
},
  "geometry": {"coordinates":[-122.689605,45.562862],"type":"Point"}
}