{
  "type": "Feature",
  "properties": {
    "iso:country":"US",
    "sg:address":"88493 US Hwy 101",
    "sg:city":"Florence",
    "sg:classifiers":[
        {
            "category":"Professional",
            "subcategory":"Engineering",
            "type":"Services"
        }
    ],
    "sg:phone":"+1 541 997 3677",
    "sg:postcode":"97439",
    "sg:province":"OR",
    "sg:tags":[
        "engineer"
    ],
    "wof:name":"Robert Manseth PE",
    "wof:placetype":"venue"
},
  "geometry": {"coordinates":[-124.099119,44.041458],"type":"Point"}
}