{
  "type": "Feature",
  "properties": {
    "iso:country":"US",
    "sg:address":"25804 Wiggins Ln",
    "sg:city":"Veneta",
    "sg:classifiers":[
        {
            "category":"Building & Trades",
            "subcategory":"Construction",
            "type":"Services"
        },
        {
            "category":"Utilities",
            "type":"Services"
        }
    ],
    "sg:phone":"+1 541 935 3844",
    "sg:postcode":"97487",
    "sg:province":"OR",
    "sg:tags":[
        "sweeping",
        "contractor"
    ],
    "wof:name":"Parkin' Lot Cleaners",
    "wof:placetype":"venue"
},
  "geometry": {"coordinates":[-123.32331000000001,44.060664],"type":"Point"}
}