{
  "type": "Feature",
  "properties": {
    "iso:country":"US",
    "sg:address":"524 NW 14th Ave",
    "sg:city":"Portland",
    "sg:classifiers":[
        {
            "category":"Restaurant",
            "type":"Food & Drink"
        }
    ],
    "sg:phone":"+1 503 916 0099",
    "sg:postcode":"97209",
    "sg:province":"OR",
    "wof:name":"Holden's Bistro",
    "wof:placetype":"venue"
},
  "geometry": {"coordinates":[-122.685239,45.527007],"type":"Point"}
}