{
  "type": "Feature",
  "properties": {
    "addr:full":"6140 Crooked Stick Loop SE Salem OR 97306",
    "addr:housenumber":"6140",
    "addr:postcode":"97306",
    "addr:street":"Crooked Stick Loop Se",
    "iso:country":"US",
    "sg:address":"6140 Crooked Stick Loop SE",
    "sg:city":"Salem",
    "sg:classifiers":[
        {
            "category":"Travel",
            "subcategory":"Travel Agent",
            "type":"Entertainment"
        },
        {
            "category":"Marine",
            "type":"Transportation"
        }
    ],
    "sg:phone":"+1 503 585 4411",
    "sg:postcode":"97306",
    "sg:province":"OR",
    "sg:tags":[
        "agency",
        "services-commercial",
        "steamship"
    ],
    "wof:name":"Top Dog Travel",
    "wof:placetype":"venue"
},
  "geometry": {"coordinates":[-123.035662,44.868337],"type":"Point"}
}