{
  "type": "Feature",
  "properties": {
    "iso:country":"US",
    "sg:address":"48127 Hwy 58",
    "sg:city":"Oakridge",
    "sg:classifiers":[
        {
            "category":"Restaurant",
            "type":"Food & Drink"
        }
    ],
    "sg:phone":"+1 541 782 2051",
    "sg:postcode":"97463",
    "sg:province":"OR",
    "wof:name":"Sportsman's Cafe",
    "wof:placetype":"venue"
},
  "geometry": {"coordinates":[-122.462779,43.742962],"type":"Point"}
}