{
  "type": "Feature",
  "properties": {
    "iso:country":"US",
    "sg:address":"2516 SE 8th Ave",
    "sg:city":"Portland",
    "sg:classifiers":[
        {
            "category":"Manufacturing",
            "subcategory":"Textiles",
            "type":"Manufacturing & Wholesale Goods"
        },
        {
            "category":"Building & Trades",
            "subcategory":"Construction",
            "type":"Services"
        }
    ],
    "sg:phone":"+1 503 230 9500",
    "sg:postcode":"97202",
    "sg:province":"OR",
    "sg:tags":[
        "tile-wholesale",
        "manufacturer",
        "tile-contractors"
    ],
    "wof:name":"Portland Direct Tile & Marble",
    "wof:placetype":"venue"
},
  "geometry": {"coordinates":[-122.657791,45.503962],"type":"Point"}
}