{
  "type": "Feature",
  "properties": {
    "iso:country":"US",
    "sg:address":"259 6th St",
    "sg:city":"Port Orford",
    "sg:classifiers":[
        {
            "category":"Restaurant",
            "type":"Food & Drink"
        }
    ],
    "sg:phone":"+1 541 332 8601",
    "sg:postcode":"97465",
    "sg:province":"OR",
    "wof:name":"Crazy Norwegians",
    "wof:placetype":"venue"
},
  "geometry": {"coordinates":[-124.493822,42.74361],"type":"Point"}
}