{
  "type": "Feature",
  "properties": {
    "iso:country":"US",
    "sg:address":"320 SE 16th Avenue",
    "sg:city":"Portland",
    "sg:classifiers":[
        {
            "category":"Education",
            "subcategory":"School",
            "type":"Public Place"
        }
    ],
    "sg:phone":"+1 503 916 6230",
    "sg:postcode":"97214",
    "sg:province":"OR",
    "wof:name":"Schools Public",
    "wof:placetype":"venue"
},
  "geometry": {"coordinates":[-122.649564,45.520615],"type":"Point"}
}