{
  "type": "Feature",
  "properties": {
    "addr:full":"427 N Skidmore St Portland OR 97217",
    "addr:housenumber":"427",
    "addr:postcode":"97217",
    "addr:street":"N Skidmore St",
    "iso:country":"US",
    "sg:address":"427 N Skidmore St",
    "sg:city":"Portland",
    "sg:classifiers":[
        {
            "category":"Professional",
            "type":"Services"
        }
    ],
    "sg:phone":"+1 503 351 8621",
    "sg:postcode":"97217",
    "sg:province":"OR",
    "wof:name":"Watchdoublescom",
    "wof:placetype":"venue"
},
  "geometry": {"coordinates":[-122.670445,45.554652],"type":"Point"}
}