{
  "type": "Feature",
  "properties": {
    "iso:country":"US",
    "sg:address":"0106 SW Gibbs Street",
    "sg:city":"Portland",
    "sg:classifiers":[
        {
            "category":"Real Estate",
            "subcategory":"Architect",
            "type":"Services"
        }
    ],
    "sg:phone":"+1 503 224 5936",
    "sg:postcode":"97239",
    "sg:province":"OR",
    "wof:name":"Di Benedetto-Thomson Livingston Architects PC",
    "wof:placetype":"venue"
},
  "geometry": {"coordinates":[-122.6768,45.499493],"type":"Point"}
}