{
  "type": "Feature",
  "properties": {
    "iso:country":"US",
    "sg:address":"8245 S Vale Garden Rd",
    "sg:city":"Canby",
    "sg:classifiers":[
        {
            "category":"Manufacturing",
            "subcategory":"Retail Goods",
            "type":"Manufacturing & Wholesale Goods"
        }
    ],
    "sg:phone":"+1 503 266 9039",
    "sg:postcode":"97013",
    "sg:province":"OR",
    "sg:tags":[
        "product",
        "mfg"
    ],
    "wof:name":"A & Z Enterprises",
    "wof:placetype":"venue"
},
  "geometry": {"coordinates":[-122.689831,45.239617],"type":"Point"}
}