{
  "type": "Feature",
  "properties": {
    "iso:country":"US",
    "sg:address":"3520 SE Yamhill St",
    "sg:city":"Portland",
    "sg:classifiers":[
        {
            "category":"Education",
            "subcategory":"Special Training",
            "type":"Public Place"
        }
    ],
    "sg:phone":"+1 503 234 6141",
    "sg:postcode":"97214",
    "sg:province":"OR",
    "sg:tags":[
        "center"
    ],
    "wof:name":"For The Kids Co-Op Learning",
    "wof:placetype":"venue"
},
  "geometry": {"coordinates":[-122.627025,45.51566],"type":"Point"}
}