{
  "type": "Feature",
  "properties": {
    "addr:full":"1600 Executive Pkwy Eugene OR 97401",
    "addr:housenumber":"1600",
    "addr:postcode":"97401",
    "addr:street":"Executive Pkwy",
    "iso:country":"US",
    "sg:address":"1600 Executive Pkwy",
    "sg:city":"Eugene",
    "sg:classifiers":[
        {
            "category":"Professional",
            "subcategory":"Accounting & Tax Preparation",
            "type":"Services"
        }
    ],
    "sg:phone":"+1 541 342 5111",
    "sg:postcode":"97401",
    "sg:province":"OR",
    "sg:tags":[
        "accountant"
    ],
    "wof:name":"Duncan & Duncan",
    "wof:placetype":"venue"
},
  "geometry": {"coordinates":[-123.108136,44.06995],"type":"Point"}
}