{
  "type": "Feature",
  "properties": {
    "addr:full":"11008 S Mulino Rd Canby OR 97013",
    "addr:housenumber":"11008",
    "addr:postcode":"97013",
    "addr:street":"S Mulino Rd",
    "iso:country":"US",
    "sg:address":"11008 S Mulino Rd",
    "sg:city":"Canby",
    "sg:classifiers":[
        {
            "category":"Home & Garden",
            "subcategory":"Garden Supply",
            "type":"Retail Goods"
        }
    ],
    "sg:phone":"+1 503 651 2022",
    "sg:postcode":"97013",
    "sg:province":"OR",
    "sg:tags":[
        "farm",
        "tree",
        "christmas"
    ],
    "wof:name":"Yellowdog Nursery",
    "wof:placetype":"venue"
},
  "geometry": {"coordinates":[-122.640691,45.241088],"type":"Point"}
}