{
  "type": "Feature",
  "properties": {
    "addr:full":"1375 N 10th Ave Stayton OR 97383",
    "addr:housenumber":"1375",
    "addr:postcode":"97383",
    "addr:street":"N 10Th Ave",
    "iso:country":"US",
    "sg:address":"1375 N 10th Ave",
    "sg:city":"Stayton",
    "sg:classifiers":[
        {
            "category":"Health Services",
            "subcategory":"Doctor",
            "type":"Services"
        }
    ],
    "sg:phone":"+1 503 769 2641",
    "sg:postcode":"97383",
    "sg:province":"OR",
    "sg:tags":[
        "physician",
        "family",
        "gynecology",
        "practice",
        "surgeons",
        "medicine",
        "obstetrics",
        "dermatology",
        "surgeon",
        "sport"
    ],
    "sg:website":"http://www.yeagerfamilypractice.com",
    "wof:name":"Stayton Family Practice",
    "wof:placetype":"venue"
},
  "geometry": {"coordinates":[-122.784147,44.80464],"type":"Point"}
}