{
  "type": "Feature",
  "properties": {
    "addr:full":"3524 NE 76th Ave Portland OR 97213",
    "addr:housenumber":"3524",
    "addr:postcode":"97213",
    "addr:street":"Ne 76Th Ave",
    "iso:country":"US",
    "sg:address":"3524 NE 76th Ave",
    "sg:city":"Portland",
    "sg:classifiers":[
        {
            "category":"Farming",
            "subcategory":"Fish & Marine Products",
            "type":"Manufacturing & Wholesale Goods"
        }
    ],
    "sg:phone":"+1 503 287 9732",
    "sg:postcode":"97213",
    "sg:province":"OR",
    "sg:tags":[
        "processors'",
        "equipment"
    ],
    "wof:name":"Seventy-Sixth Avenue Press",
    "wof:placetype":"venue"
},
  "geometry": {"coordinates":[-122.58481999999999,45.548365],"type":"Point"}
}