{
  "type": "Feature",
  "properties": {
    "iso:country":"US",
    "sg:address":"119 2nd St SE",
    "sg:city":"Bandon",
    "sg:classifiers":[
        {
            "category":"Restaurant",
            "type":"Food & Drink"
        }
    ],
    "sg:phone":"+1 541 347 4211",
    "sg:postcode":"97411",
    "sg:province":"OR",
    "wof:name":"Lloyd's Of Bandon",
    "wof:placetype":"venue"
},
  "geometry": {"coordinates":[-124.414324,43.119141],"type":"Point"}
}