{
  "type": "Feature",
  "properties": {
    "addr:full":"63455 N Hwy 97 Bend OR 97701",
    "addr:housenumber":"63455",
    "addr:postcode":"97701",
    "addr:street":"N Hwy 97",
    "iso:country":"US",
    "sg:address":"63455 N Hwy 97",
    "sg:city":"Bend",
    "sg:classifiers":[
        {
            "category":"Shopping",
            "subcategory":"Computers & Home Electronics",
            "type":"Retail Goods"
        }
    ],
    "sg:phone":"+1 541 383 5850",
    "sg:postcode":"97701",
    "sg:province":"OR",
    "sg:tags":[
        "equipment",
        "electronic",
        "supply"
    ],
    "wof:name":"Best Buy",
    "wof:placetype":"venue"
},
  "geometry": {"coordinates":[-121.296262,44.107551],"type":"Point"}
}