{
  "type": "Feature",
  "properties": {
    "iso:country":"US",
    "sg:address":"1647 SW Fellows St",
    "sg:city":"Mcminnville",
    "sg:classifiers":[
        {
            "category":"Real Estate",
            "subcategory":"Real Estate Operator",
            "type":"Services"
        }
    ],
    "sg:phone":"+1 503 472 4720",
    "sg:postcode":"97128",
    "sg:province":"OR",
    "sg:tags":[
        "apartment"
    ],
    "wof:name":"Tall Oaks Estates",
    "wof:placetype":"venue"
},
  "geometry": {"coordinates":[-123.21860599999999,45.20185],"type":"Point"}
}