{
  "type": "Feature",
  "properties": {
    "iso:country":"US",
    "sg:address":"14381 SE Charjan St",
    "sg:city":"Clackamas",
    "sg:classifiers":[
        {
            "category":"Professional",
            "type":"Services"
        }
    ],
    "sg:phone":"+1 503 658 6441",
    "sg:postcode":"97015",
    "sg:province":"OR",
    "wof:name":"Don Giles",
    "wof:placetype":"venue"
},
  "geometry": {"coordinates":[-122.51490200000001,45.417032],"type":"Point"}
}