{
  "type": "Feature",
  "properties": {
    "addr:full":"10801 Main St NE Aurora OR 97020",
    "addr:housenumber":"10801",
    "addr:postcode":"97020",
    "addr:street":"Main St Ne",
    "iso:country":"US",
    "sg:address":"10801 Main St NE",
    "sg:city":"Aurora",
    "sg:classifiers":[
        {
            "category":"Real Estate",
            "subcategory":"Real Estate Agent",
            "type":"Services"
        }
    ],
    "sg:phone":"+1 503 678 2136",
    "sg:postcode":"97020",
    "sg:province":"OR",
    "sg:tags":[
        "management"
    ],
    "wof:name":"Rental Housing Maintenance Svc",
    "wof:placetype":"venue"
},
  "geometry": {"coordinates":[-122.83920000000001,45.222529],"type":"Point"}
}