{
  "type": "Feature",
  "properties": {
    "iso:country":"US",
    "sg:address":"5041 D St",
    "sg:city":"Springfield",
    "sg:classifiers":[
        {
            "category":"Building & Trades",
            "subcategory":"Plumbing",
            "type":"Services"
        }
    ],
    "sg:phone":"+1 541 485 1146",
    "sg:postcode":"97478",
    "sg:province":"OR",
    "sg:tags":[
        "plumbing",
        "contractor"
    ],
    "wof:name":"Custom Plumbing",
    "wof:placetype":"venue"
},
  "geometry": {"coordinates":[-122.94333,44.049693],"type":"Point"}
}