{
  "type": "Feature",
  "properties": {
    "iso:country":"US",
    "sg:address":"55996 Remington Dr",
    "sg:city":"Bend",
    "sg:classifiers":[
        {
            "category":"Shopping",
            "subcategory":"Computers & Home Electronics",
            "type":"Retail Goods"
        }
    ],
    "sg:phone":"+1 541 593 7529",
    "sg:postcode":"97707",
    "sg:province":"OR",
    "wof:name":"Performance Computer Technolog",
    "wof:placetype":"venue"
},
  "geometry": {"coordinates":[-121.48639,43.837379],"type":"Point"}
}