{
  "type": "Feature",
  "properties": {
    "addr:full":"4407 SW Corbett Ave Portland OR 97239",
    "addr:housenumber":"4407",
    "addr:postcode":"97239",
    "addr:street":"Sw Corbett Ave",
    "iso:country":"US",
    "sg:address":"4407 SW Corbett Ave",
    "sg:city":"Portland",
    "sg:classifiers":[
        {
            "category":"Retail",
            "subcategory":"Veterinary Services",
            "type":"Services"
        }
    ],
    "sg:phone":"+1 503 892 6452",
    "sg:postcode":"97239",
    "sg:province":"OR",
    "sg:tags":[
        "veterinarian"
    ],
    "sg:website":"www.thecatdoctor.net",
    "wof:name":"The Cat Doctor",
    "wof:placetype":"venue"
},
  "geometry": {"coordinates":[-122.676688,45.491502],"type":"Point"}
}