{
  "type": "Feature",
  "properties": {
    "iso:country":"US",
    "sg:address":"2920 NE Sandy Blvd",
    "sg:city":"Portland",
    "sg:classifiers":[
        {
            "category":"Restaurant",
            "type":"Food & Drink"
        }
    ],
    "sg:menulink":"http://www.allmenus.com/or/portland/164491-wendys/menu/",
    "sg:phone":"+1 503 239 7063",
    "sg:postcode":"97232",
    "sg:province":"OR",
    "sg:tags":[
        "burger",
        "american",
        "soup"
    ],
    "wof:name":"Wendy's",
    "wof:placetype":"venue"
},
  "geometry": {"coordinates":[-122.635368,45.529546],"type":"Point"}
}