{
  "type": "Feature",
  "properties": {
    "iso:country":"US",
    "sg:address":"5530 NE 122nd Ave",
    "sg:city":"Portland",
    "sg:classifiers":[
        {
            "category":"Restaurant",
            "type":"Food & Drink"
        }
    ],
    "sg:phone":"+1 503 262 8652",
    "sg:postcode":"97230",
    "sg:province":"OR",
    "wof:name":"Thai 122",
    "wof:placetype":"venue"
},
  "geometry": {"coordinates":[-122.534711,45.563568],"type":"Point"}
}