{
  "type": "Feature",
  "properties": {
    "iso:country":"US",
    "sg:address":"805 Long St",
    "sg:city":"Sweet Home",
    "sg:classifiers":[
        {
            "category":"Travel",
            "subcategory":"Hotels & Motels",
            "type":"Entertainment"
        }
    ],
    "sg:phone":"+1 541 367 5137",
    "sg:postcode":"97386",
    "sg:province":"OR",
    "wof:name":"Sweet Home Inn Inc",
    "wof:placetype":"venue"
},
  "geometry": {"coordinates":[-122.733341,44.396159],"type":"Point"}
}