{
  "type": "Feature",
  "properties": {
    "iso:country":"US",
    "sg:address":"3030 Hollywood Dr NE",
    "sg:city":"Salem",
    "sg:classifiers":[
        {
            "category":"Real Estate",
            "subcategory":"Real Estate Operator",
            "type":"Services"
        }
    ],
    "sg:phone":"+1 503 362 6262",
    "sg:postcode":"97305",
    "sg:province":"OR",
    "sg:tags":[
        "mobile",
        "home",
        "site"
    ],
    "wof:name":"Hollyridge Estates",
    "wof:placetype":"venue"
},
  "geometry": {"coordinates":[-122.976631,44.96528],"type":"Point"}
}