{
  "type": "Feature",
  "properties": {
    "addr:full":"5840 SW Erickson Ave Beaverton OR 97005",
    "addr:housenumber":"5840",
    "addr:postcode":"97005",
    "addr:street":"Sw Erickson Ave",
    "iso:country":"US",
    "sg:address":"5840 SW Erickson Ave",
    "sg:city":"Beaverton",
    "sg:classifiers":[
        {
            "category":"Professional",
            "subcategory":"Research",
            "type":"Services"
        }
    ],
    "sg:phone":"+1 503 202 0124",
    "sg:postcode":"97005",
    "sg:province":"OR",
    "sg:tags":[
        "environmental",
        "ecological"
    ],
    "wof:name":"Environmental Control",
    "wof:placetype":"venue"
},
  "geometry": {"coordinates":[-122.81187199999999,45.477674],"type":"Point"}
}