{
  "type": "Feature",
  "properties": {
    "addr:full":"401 S Canyon Blvd John Day OR 97845",
    "addr:housenumber":"401",
    "addr:postcode":"97845",
    "addr:street":"S Canyon Blvd",
    "iso:country":"US",
    "sg:address":"401 S Canyon Blvd",
    "sg:city":"John Day",
    "sg:classifiers":[
        {
            "category":"Education",
            "subcategory":"Special Training",
            "type":"Public Place"
        }
    ],
    "sg:phone":"+1 541 575 1006",
    "sg:postcode":"97845",
    "sg:province":"OR",
    "wof:name":"Families First Grant Cnty Inc",
    "wof:placetype":"venue"
},
  "geometry": {"coordinates":[-118.952893,44.411812],"type":"Point"}
}