{
  "type": "Feature",
  "properties": {
    "addr:full":"14188 N Umpqua Hwy Roseburg OR 97470",
    "addr:housenumber":"14188",
    "addr:postcode":"97470",
    "addr:street":"N Umpqua Hwy",
    "iso:country":"US",
    "sg:address":"14188 N Umpqua Hwy",
    "sg:city":"Roseburg",
    "sg:classifiers":[
        {
            "category":"Food & Beverages",
            "subcategory":"Groceries & Convenience Stores",
            "type":"Retail Goods"
        },
        {
            "category":"Autos & Motor Vehicles",
            "subcategory":"Fuel & Gas Station",
            "type":"Retail Goods"
        }
    ],
    "sg:phone":"+1 541 673 7640",
    "sg:postcode":"97470",
    "sg:province":"OR",
    "sg:tags":[
        "grocer",
        "station"
    ],
    "wof:name":"Whistler's Park Mercantile",
    "wof:placetype":"venue"
},
  "geometry": {"coordinates":[-123.17968399999999,43.291302],"type":"Point"}
}