{
  "type": "Feature",
  "properties": {
    "addr:full":"525 25th Ave SW Albany OR 97321",
    "addr:housenumber":"525",
    "addr:postcode":"97321",
    "addr:street":"25Th Ave Sw",
    "iso:country":"US",
    "sg:address":"525 25th Ave SW",
    "sg:city":"Albany",
    "sg:classifiers":[
        {
            "category":"Manufacturing",
            "subcategory":"Food",
            "type":"Manufacturing & Wholesale Goods"
        }
    ],
    "sg:phone":"+1 541 926 6001",
    "sg:postcode":"97321",
    "sg:province":"OR",
    "sg:tags":[
        "vegetable",
        "fruit"
    ],
    "sg:website":"www.ofd.com",
    "wof:name":"Oregon Freeze Dry Inc",
    "wof:placetype":"venue"
},
  "geometry": {"coordinates":[-123.10551100000001,44.61646],"type":"Point"}
}