{
  "type": "Feature",
  "properties": {
    "iso:country":"US",
    "sg:address":"12854 State Hwy 234",
    "sg:city":"Gold Hill",
    "sg:classifiers":[
        {
            "category":"Retail",
            "subcategory":"Auto Repair",
            "type":"Services"
        }
    ],
    "sg:phone":"+1 541 855 5514",
    "sg:postcode":"97525",
    "sg:province":"OR",
    "sg:tags":[
        "general"
    ],
    "wof:name":"Dodge Diesel Performance",
    "wof:placetype":"venue"
},
  "geometry": {"coordinates":[-123.027176,42.45853],"type":"Point"}
}