{
  "type": "Feature",
  "properties": {
    "iso:country":"US",
    "sg:address":"16729 NE Eugene Ct",
    "sg:city":"Portland",
    "sg:classifiers":[
        {
            "category":"Building & Trades",
            "subcategory":"Construction",
            "type":"Services"
        }
    ],
    "sg:phone":"+1 503 663 7820",
    "sg:postcode":"97230",
    "sg:province":"OR",
    "sg:tags":[
        "residential"
    ],
    "wof:name":"Veritas Realty Investors Inc",
    "wof:placetype":"venue"
},
  "geometry": {"coordinates":[-122.490081,45.539037],"type":"Point"}
}