{
  "type": "Feature",
  "properties": {
    "iso:country":"US",
    "sg:address":"5901 SW Macadam Ave",
    "sg:city":"Portland",
    "sg:classifiers":[
        {
            "category":"Communications",
            "type":"Services"
        }
    ],
    "sg:phone":"+1 800 845 4432",
    "sg:postcode":"97239",
    "sg:province":"OR",
    "sg:tags":[
        "paging",
        "signaling"
    ],
    "wof:name":"Westlink Paging",
    "wof:placetype":"venue"
},
  "geometry": {"coordinates":[-122.673401,45.481121],"type":"Point"}
}