{
  "type": "Feature",
  "properties": {
    "addr:full":"10961 Hwy 202 Clatskanie OR 97016",
    "addr:housenumber":"10961",
    "addr:postcode":"97016",
    "addr:street":"Hwy 202",
    "iso:country":"US",
    "sg:address":"10961 Hwy 202",
    "sg:city":"Clatskanie",
    "sg:classifiers":[
        {
            "category":"Manufacturing",
            "subcategory":"Lumber",
            "type":"Manufacturing & Wholesale Goods"
        }
    ],
    "sg:phone":"+1 503 755 2409",
    "sg:postcode":"97016",
    "sg:province":"OR",
    "sg:tags":[
        "logging"
    ],
    "wof:name":"Allied Logging Co",
    "wof:placetype":"venue"
},
  "geometry": {"coordinates":[-123.34160300000001,45.986437],"type":"Point"}
}