{
  "type": "Feature",
  "properties": {
    "addr:full":"14646 SE 82nd Dr Clackamas OR 97015",
    "addr:postcode":"14646;97015",
    "addr:street":"Se 82Nd Dr",
    "iso:country":"US",
    "sg:address":"14646 SE 82nd Dr",
    "sg:city":"Clackamas",
    "sg:classifiers":[
        {
            "category":"Professional",
            "subcategory":"Computer Services",
            "type":"Services"
        }
    ],
    "sg:phone":"+1 503 657 9236",
    "sg:postcode":"97015",
    "sg:province":"OR",
    "sg:tags":[
        "software",
        "printing",
        "offset",
        "developing"
    ],
    "wof:name":"Imagery Press",
    "wof:placetype":"venue"
},
  "geometry": {"coordinates":[-122.56914999999999,45.414975],"type":"Point"}
}