{
  "type": "Feature",
  "properties": {
    "addr:full":"15757 SW 74th Ave Ste 570 Portland OR 97224",
    "addr:housenumber":"15757",
    "addr:postcode":"97224",
    "addr:street":"Sw 74Th Ave Ste 570",
    "iso:country":"US",
    "sg:address":"15757 SW 74th Ave Ste 570",
    "sg:city":"Portland",
    "sg:classifiers":[
        {
            "category":"Home & Garden",
            "subcategory":"Furniture",
            "type":"Retail Goods"
        }
    ],
    "sg:phone":"+1 503 684 0495",
    "sg:postcode":"97224",
    "sg:province":"OR",
    "sg:tags":[
        "renting",
        "leasing"
    ],
    "sg:website":"http://www.convenienthousewares.com",
    "wof:name":"Convenient Housewares",
    "wof:placetype":"venue"
},
  "geometry": {"coordinates":[-122.752476,45.404078],"type":"Point"}
}