{
  "type": "Feature",
  "properties": {
    "iso:country":"US",
    "sg:address":"6606 SW Capitol Hwy",
    "sg:city":"Portland",
    "sg:classifiers":[
        {
            "category":"Real Estate",
            "subcategory":"Real Estate Services",
            "type":"Services"
        },
        {
            "category":"Structure",
            "subcategory":"Office Building",
            "type":"Public Place"
        },
        {
            "category":"Real Estate",
            "subcategory":"Real Estate Agent",
            "type":"Services"
        }
    ],
    "sg:phone":"+1 503 246 1451",
    "sg:postcode":"97239",
    "sg:province":"OR",
    "sg:tags":[
        "management",
        "park"
    ],
    "wof:name":"Ticket Properties",
    "wof:placetype":"venue"
},
  "geometry": {"coordinates":[-122.701992,45.476442],"type":"Point"}
}