{
  "type": "Feature",
  "properties": {
    "addr:full":"5633 SE Division St Portland OR 97206",
    "addr:housenumber":"5633",
    "addr:postcode":"97206",
    "addr:street":"Se Division St",
    "iso:country":"US",
    "sg:address":"5633 SE Division St",
    "sg:city":"Portland",
    "sg:classifiers":[
        {
            "category":"Coffee & Tea",
            "type":"Food & Drink"
        }
    ],
    "sg:postcode":"97206",
    "sg:province":"OR",
    "sg:website":"www.cafeauplay.org",
    "wof:name":"Cafe au Play",
    "wof:placetype":"venue"
},
  "geometry": {"coordinates":[-122.605182,45.505567],"type":"Point"}
}