{
  "type": "Feature",
  "properties": {
    "addr:full":"10855 SW Cascade Ave Portland OR 97223",
    "addr:housenumber":"10855",
    "addr:postcode":"97223",
    "addr:street":"Sw Cascade Ave",
    "iso:country":"US",
    "sg:address":"10855 SW Cascade Ave",
    "sg:city":"Portland",
    "sg:classifiers":[
        {
            "category":"Building & Trades",
            "subcategory":"Equipment Rental",
            "type":"Services"
        },
        {
            "category":"Professional",
            "subcategory":"Printing & Photocopies",
            "type":"Services"
        }
    ],
    "sg:phone":"+1 503 620 3691",
    "sg:postcode":"97223",
    "sg:province":"OR",
    "sg:tags":[
        "blueprinting",
        "architectural",
        "supply"
    ],
    "sg:website":"http://www.rtangle.net",
    "wof:name":"Right Angle Digital Print-Supl",
    "wof:placetype":"venue"
},
  "geometry": {"coordinates":[-122.77916,45.441738],"type":"Point"}
}