{
  "type": "Feature",
  "properties": {
    "addr:full":"18156 Hwy 36 Blachly OR 97412",
    "addr:housenumber":"18156",
    "addr:postcode":"97412",
    "addr:street":"Hwy 36",
    "iso:country":"US",
    "sg:address":"18156 Hwy 36",
    "sg:city":"Blachly",
    "sg:classifiers":[
        {
            "category":"Professional",
            "subcategory":"Research",
            "type":"Services"
        }
    ],
    "sg:phone":"+1 541 927 6134",
    "sg:postcode":"97412",
    "sg:province":"OR",
    "sg:tags":[
        "commercial",
        "physical"
    ],
    "wof:name":"I D E",
    "wof:placetype":"venue"
},
  "geometry": {"coordinates":[-123.62261100000001,44.121966],"type":"Point"}
}