{
  "type": "Feature",
  "properties": {
    "addr:full":"1982 NE 25th Ave Hillsboro OR 97124",
    "addr:housenumber":"1982",
    "addr:postcode":"97124",
    "addr:street":"Ne 25Th Ave",
    "iso:country":"US",
    "sg:address":"1982 NE 25th Ave",
    "sg:city":"Hillsboro",
    "sg:classifiers":[
        {
            "category":"Manufacturing",
            "subcategory":"Printing",
            "type":"Manufacturing & Wholesale Goods"
        }
    ],
    "sg:phone":"+1 503 693 0866",
    "sg:postcode":"97124",
    "sg:province":"OR",
    "sg:tags":[
        "book"
    ],
    "wof:name":"Blue Hair Books",
    "wof:placetype":"venue"
},
  "geometry": {"coordinates":[-122.957019,45.539574],"type":"Point"}
}