{
  "type": "Feature",
  "properties": {
    "iso:country":"US",
    "sg:address":"4814 Sams Creek Rd",
    "sg:city":"Toledo",
    "sg:classifiers":[
        {
            "category":"Building & Trades",
            "subcategory":"Construction",
            "type":"Services"
        }
    ],
    "sg:phone":"+1 541 875 2301",
    "sg:postcode":"97391",
    "sg:province":"OR",
    "sg:tags":[
        "contractor"
    ],
    "wof:name":"Tom Nickerson Construction",
    "wof:placetype":"venue"
},
  "geometry": {"coordinates":[-123.846244,44.685258],"type":"Point"}
}