{
  "type": "Feature",
  "properties": {
    "iso:country":"US",
    "sg:address":"2900 NE 132nd Ave",
    "sg:city":"Portland",
    "sg:classifiers":[
        {
            "category":"Recreation",
            "type":"Entertainment"
        }
    ],
    "sg:phone":"+1 503 629 9435",
    "sg:postcode":"97230",
    "sg:province":"OR",
    "wof:name":"Chiro Cafe The",
    "wof:placetype":"venue"
},
  "geometry": {"coordinates":[-122.526919,45.543423],"type":"Point"}
}