{
  "type": "Feature",
  "properties": {
    "addr:full":"2900 NE 132nd Ave Portland OR 97230",
    "addr:housenumber":"2900",
    "addr:postcode":"97230",
    "addr:street":"Ne 132Nd Ave",
    "iso:country":"US",
    "sg:address":"2900 NE 132nd Ave",
    "sg:city":"Portland",
    "sg:classifiers":[
        {
            "category":"Recreation",
            "type":"Entertainment"
        }
    ],
    "sg:phone":"+1 503 629 9435",
    "sg:postcode":"97230",
    "sg:province":"OR",
    "wof:name":"Chiro Cafe The",
    "wof:placetype":"venue"
},
  "geometry": {"coordinates":[-122.52691900000001,45.543423],"type":"Point"}
}