{
  "type": "Feature",
  "properties": {
    "iso:country":"US",
    "sg:address":"240 Finch Rd",
    "sg:city":"Kerby",
    "sg:classifiers":[
        {
            "category":"Manufacturing",
            "subcategory":"Motor Vehicles & Parts",
            "type":"Manufacturing & Wholesale Goods"
        }
    ],
    "sg:phone":"+1 541 592 6972",
    "sg:postcode":"97531",
    "sg:province":"OR",
    "sg:tags":[
        "body",
        "truck"
    ],
    "sg:website":"www.roguetruckbody.com",
    "wof:name":"Rogue Truck Body",
    "wof:placetype":"venue"
},
  "geometry": {"coordinates":[-123.652597,42.194202],"type":"Point"}
}