{
  "type": "Feature",
  "properties": {
    "iso:country":"US",
    "sg:address":"4733 Liberty Rd S",
    "sg:city":"Salem",
    "sg:classifiers":[
        {
            "category":"Retail",
            "subcategory":"Laundry & Dry Cleaning",
            "type":"Services"
        }
    ],
    "sg:phone":"+1 503 362 3562",
    "sg:postcode":"97306",
    "sg:province":"OR",
    "sg:tags":[
        "cleaners",
        "self"
    ],
    "wof:name":"Sunnyslope Cleaners",
    "wof:placetype":"venue"
},
  "geometry": {"coordinates":[-123.060434,44.890098],"type":"Point"}
}