{
  "type": "Feature",
  "properties": {
    "addr:full":"11326 SW 84th Ave Portland OR 97223",
    "addr:housenumber":"11326",
    "addr:postcode":"97223",
    "addr:street":"Sw 84Th Ave",
    "iso:country":"US",
    "sg:address":"11326 SW 84th Ave",
    "sg:city":"Portland",
    "sg:classifiers":[
        {
            "category":"Professional",
            "type":"Services"
        }
    ],
    "sg:phone":"+1 503 670 7808",
    "sg:postcode":"97223",
    "sg:province":"OR",
    "sg:tags":[
        "publication",
        "editorial"
    ],
    "wof:name":"Grant Central",
    "wof:placetype":"venue"
},
  "geometry": {"coordinates":[-122.76351200000001,45.43833],"type":"Point"}
}