{
  "type": "Feature",
  "properties": {
    "iso:country":"US",
    "sg:address":"1219 SW 18th Ave",
    "sg:city":"Portland",
    "sg:classifiers":[
        {
            "category":"Professional",
            "subcategory":"Secretarial Services",
            "type":"Services"
        }
    ],
    "sg:phone":"+1 503 274 4644",
    "sg:postcode":"97205",
    "sg:province":"OR",
    "sg:tags":[
        "reporting"
    ],
    "wof:name":"Capri and Associates",
    "wof:placetype":"venue"
},
  "geometry": {"coordinates":[-122.692697,45.51826],"type":"Point"}
}