{
  "type": "Feature",
  "properties": {
    "addr:full":"627 NE Halsey St Portland OR 97232",
    "addr:housenumber":"627",
    "addr:postcode":"97232",
    "addr:street":"Ne Halsey St",
    "iso:country":"US",
    "sg:address":"627 NE Halsey St",
    "sg:city":"Portland",
    "sg:classifiers":[
        {
            "category":"Building & Trades",
            "subcategory":"Construction",
            "type":"Services"
        }
    ],
    "sg:phone":"+1 503 284 0575",
    "sg:postcode":"97232",
    "sg:province":"OR",
    "sg:tags":[
        "contractor"
    ],
    "wof:name":"Pacific Quality Construction",
    "wof:placetype":"venue"
},
  "geometry": {"coordinates":[-122.658997,45.533699],"type":"Point"}
}