{
  "type": "Feature",
  "properties": {
    "iso:country":"US",
    "sg:address":"5050 SW Griffith Dr",
    "sg:city":"Beaverton",
    "sg:classifiers":[
        {
            "category":"Banks & Credit Unions",
            "subcategory":"Bank",
            "type":"Services"
        }
    ],
    "sg:phone":"+1 503 671 0229",
    "sg:postcode":"97005",
    "sg:province":"OR",
    "sg:tags":[
        "financing"
    ],
    "wof:name":"Wells Fargo Financial Accptnce",
    "wof:placetype":"venue"
},
  "geometry": {"coordinates":[-122.79463,45.483497],"type":"Point"}
}