{
  "type": "Feature",
  "properties": {
    "addr:full":"3535 SW Multnomah Boulevard Portland OR 97219",
    "addr:housenumber":"3535",
    "addr:postcode":"97219",
    "addr:street":"Sw Multnomah Boulevard",
    "iso:country":"US",
    "sg:address":"3535 SW Multnomah Boulevard",
    "sg:city":"Portland",
    "sg:classifiers":[
        {
            "category":"Food & Beverages",
            "subcategory":"Liquor & Beverages",
            "type":"Retail Goods"
        }
    ],
    "sg:phone":"+1 503 244 6947",
    "sg:postcode":"97219",
    "sg:province":"OR",
    "sg:tags":[
        "beer",
        "spirit",
        "wine"
    ],
    "wof:name":"Market Place Wines",
    "wof:placetype":"venue"
},
  "geometry": {"coordinates":[-122.713156,45.467089],"type":"Point"}
}