{
  "type": "Feature",
  "properties": {
    "addr:full":"455 SE 111th Ave Portland OR 97216",
    "addr:housenumber":"455",
    "addr:postcode":"97216",
    "addr:street":"Se 111Th Ave",
    "iso:country":"US",
    "sg:address":"455 SE 111th Ave",
    "sg:city":"Portland",
    "sg:classifiers":[
        {
            "category":"Building & Trades",
            "subcategory":"Construction",
            "type":"Services"
        }
    ],
    "sg:phone":"+1 503 252 2115",
    "sg:postcode":"97216",
    "sg:province":"OR",
    "sg:tags":[
        "house"
    ],
    "wof:name":"Smalko Construction LLC",
    "wof:placetype":"venue"
},
  "geometry": {"coordinates":[-122.549407,45.519991],"type":"Point"}
}