{
  "type": "Feature",
  "properties": {
    "iso:country":"US",
    "sg:address":"10040 SW McDonald St",
    "sg:city":"Portland",
    "sg:classifiers":[
        {
            "category":"Professional",
            "subcategory":"Business Services",
            "type":"Services"
        }
    ],
    "sg:phone":"+1 503 639 2536",
    "sg:postcode":"97224",
    "sg:province":"OR",
    "wof:name":"Tower Sales and Service",
    "wof:placetype":"venue"
},
  "geometry": {"coordinates":[-122.78165199999999,45.418643],"type":"Point"}
}