{
  "type": "Feature",
  "properties": {
    "iso:country":"US",
    "sg:address":"4797 Parkview Dr",
    "sg:city":"Lake Oswego",
    "sg:classifiers":[
        {
            "category":"Building & Trades",
            "subcategory":"Construction",
            "type":"Services"
        }
    ],
    "sg:phone":"+1 503 675 5250",
    "sg:postcode":"97035",
    "sg:province":"OR",
    "sg:tags":[
        "painter"
    ],
    "wof:name":"Boss Painting",
    "wof:placetype":"venue"
},
  "geometry": {"coordinates":[-122.72213000000001,45.420497],"type":"Point"}
}