{
  "type": "Feature",
  "properties": {
    "addr:full":"134 Saddlebutte Ln Roseburg OR 97470",
    "addr:housenumber":"134",
    "addr:postcode":"97470",
    "addr:street":"Saddlebutte Ln",
    "iso:country":"US",
    "sg:address":"134 Saddlebutte Ln",
    "sg:city":"Roseburg",
    "sg:classifiers":[
        {
            "category":"Building & Trades",
            "subcategory":"Plumbing",
            "type":"Services"
        }
    ],
    "sg:phone":"+1 541 863 7030",
    "sg:postcode":"97470",
    "sg:province":"OR",
    "sg:tags":[
        "septic"
    ],
    "wof:name":"Out Back Septic Svc",
    "wof:placetype":"venue"
},
  "geometry": {"coordinates":[-123.35152100000001,43.272051],"type":"Point"}
}