{
  "type": "Feature",
  "properties": {
    "iso:country":"US",
    "sg:address":"3380 64th Pl NE",
    "sg:city":"Salem",
    "sg:classifiers":[
        {
            "category":"Real Estate",
            "subcategory":"Real Estate Agent",
            "type":"Services"
        }
    ],
    "sg:phone":"+1 503 362 5026",
    "sg:postcode":"97305",
    "sg:province":"OR",
    "wof:name":"Don L Nash RE Appraiser",
    "wof:placetype":"venue"
},
  "geometry": {"coordinates":[-122.928465,44.972193],"type":"Point"}
}