{
  "type": "Feature",
  "properties": {
    "addr:full":"13559 S Redland Rd Oregon City OR 97045",
    "addr:housenumber":"13559",
    "addr:postcode":"97045",
    "addr:street":"S Redland Rd",
    "iso:country":"US",
    "sg:address":"13559 S Redland Rd",
    "sg:city":"Oregon City",
    "sg:classifiers":[
        {
            "category":"Restaurant",
            "type":"Food & Drink"
        }
    ],
    "sg:phone":"+1 503 655 7587",
    "sg:postcode":"97045",
    "sg:province":"OR",
    "sg:tags":[
        "eating"
    ],
    "wof:name":"Pioneer Take-N-Bake Pizza",
    "wof:placetype":"venue"
},
  "geometry": {"coordinates":[-122.586304,45.363759],"type":"Point"}
}