{
  "type": "Feature",
  "properties": {
    "addr:full":"8193 SW Xerus Ave Redmond OR 97756",
    "addr:housenumber":"8193",
    "addr:postcode":"97756",
    "addr:street":"Sw Xerus Ave",
    "iso:country":"US",
    "sg:address":"8193 SW Xerus Ave",
    "sg:city":"Redmond",
    "sg:classifiers":[
        {
            "category":"Manufacturing",
            "subcategory":"Retail Goods",
            "type":"Manufacturing & Wholesale Goods"
        },
        {
            "category":"Professional",
            "subcategory":"Business Services",
            "type":"Services"
        }
    ],
    "sg:phone":"+1 541 389 8600",
    "sg:postcode":"97756",
    "sg:province":"OR",
    "sg:tags":[
        "assembly",
        "fabricating"
    ],
    "wof:name":"Assembly Shop",
    "wof:placetype":"venue"
},
  "geometry": {"coordinates":[-121.27208,44.197973],"type":"Point"}
}