{
  "type": "Feature",
  "properties": {
    "addr:full":"63545 N Hwy 97 Bend OR 97701",
    "addr:housenumber":"63545",
    "addr:postcode":"97701",
    "addr:street":"N Hwy 97",
    "iso:country":"US",
    "sg:address":"63545 N Hwy 97",
    "sg:city":"Bend",
    "sg:classifiers":[
        {
            "category":"Retail",
            "subcategory":"Auto Repair",
            "type":"Services"
        }
    ],
    "sg:phone":"+1 541 382 8339",
    "sg:postcode":"97701",
    "sg:province":"OR",
    "sg:tags":[
        "automotive"
    ],
    "wof:name":"Supertows",
    "wof:placetype":"venue"
},
  "geometry": {"coordinates":[-121.297736,44.104602],"type":"Point"}
}