{
  "type": "Feature",
  "properties": {
    "iso:country":"US",
    "sg:address":"5676 Main St",
    "sg:city":"Springfield",
    "sg:classifiers":[
        {
            "category":"Shopping",
            "subcategory":"Computers & Home Electronics",
            "type":"Retail Goods"
        }
    ],
    "sg:phone":"+1 541 747 0423",
    "sg:postcode":"97478",
    "sg:province":"OR",
    "wof:name":"Radio Shack",
    "wof:placetype":"venue"
},
  "geometry": {"coordinates":[-122.929265,44.045749],"type":"Point"}
}