{
  "type": "Feature",
  "properties": {
    "iso:country":"US",
    "sg:address":"368 SW 3rd Ave",
    "sg:city":"Canby",
    "sg:classifiers":[
        {
            "category":"Manufacturing",
            "subcategory":"Printing",
            "type":"Manufacturing & Wholesale Goods"
        }
    ],
    "sg:phone":"+1 503 266 8569",
    "sg:postcode":"97013",
    "sg:province":"OR",
    "sg:tags":[
        "printer"
    ],
    "wof:name":"Nancy's Typesetting Svc",
    "wof:placetype":"venue"
},
  "geometry": {"coordinates":[-122.694267,45.259468],"type":"Point"}
}