{
  "type": "Feature",
  "properties": {
    "iso:country":"US",
    "sg:address":"510 NE Harney St",
    "sg:city":"Newport",
    "sg:classifiers":[
        {
            "category":"Organizations",
            "subcategory":"Membership Organization",
            "type":"Services"
        }
    ],
    "sg:phone":"+1 541 265 3719",
    "sg:postcode":"97365",
    "sg:province":"OR",
    "sg:tags":[
        "society",
        "humane"
    ],
    "wof:name":"Central Coast Humane Society",
    "wof:placetype":"venue"
},
  "geometry": {"coordinates":[-124.042805,44.639924],"type":"Point"}
}