{
  "type": "Feature",
  "properties": {
    "iso:country":"US",
    "sg:address":"10280 SW Hawthorne Ln",
    "sg:city":"Portland",
    "sg:classifiers":[
        {
            "category":"Banks & Credit Unions",
            "subcategory":"Financial Services",
            "type":"Services"
        }
    ],
    "sg:phone":"+1 503 292 9804",
    "sg:postcode":"97225",
    "sg:province":"OR",
    "sg:tags":[
        "trust",
        "management"
    ],
    "wof:name":"Lindbo Ltd Partnership",
    "wof:placetype":"venue"
},
  "geometry": {"coordinates":[-122.77888299999999,45.500122],"type":"Point"}
}