{
  "type": "Feature",
  "properties": {
    "iso:country":"US",
    "sg:address":"724 S Central Ave Ste 104",
    "sg:city":"Medford",
    "sg:classifiers":[
        {
            "category":"Professional",
            "subcategory":"Computer Services",
            "type":"Services"
        }
    ],
    "sg:phone":"+1 541 770 2048",
    "sg:postcode":"97501",
    "sg:province":"OR",
    "sg:tags":[
        "repair"
    ],
    "wof:name":"Cascade Computer Maintenance",
    "wof:placetype":"venue"
},
  "geometry": {"coordinates":[-122.866997,42.320499],"type":"Point"}
}