{
  "type": "Feature",
  "properties": {
    "iso:country":"US",
    "sg:address":"1834 SW 58th Ave",
    "sg:city":"Portland",
    "sg:classifiers":[
        {
            "category":"Real Estate",
            "subcategory":"Real Estate Agent",
            "type":"Services"
        }
    ],
    "sg:phone":"+1 503 292 6332",
    "sg:postcode":"97221",
    "sg:province":"OR",
    "sg:tags":[
        "investment"
    ],
    "wof:name":"Blaine Whipple Realty",
    "wof:placetype":"venue"
},
  "geometry": {"coordinates":[-122.736437,45.510013],"type":"Point"}
}