{
  "type": "Feature",
  "properties": {
    "iso:country":"US",
    "sg:address":"77052 Westersund Rd",
    "sg:city":"Pendleton",
    "sg:phone":"+1 541 276 1698",
    "sg:postcode":"97801",
    "sg:province":"OR",
    "sg:tags":[
        "farm",
        "wheat"
    ],
    "wof:name":"Kevin Porter",
    "wof:placetype":"venue"
},
  "geometry": {"coordinates":[-118.83886,45.756026],"type":"Point"}
}