{
  "type": "Feature",
  "properties": {
    "iso:country":"US",
    "sg:address":"728 Pond Ln",
    "sg:city":"Eugene",
    "sg:classifiers":[
        {
            "category":"Real Estate",
            "subcategory":"Real Estate Operator",
            "type":"Services"
        }
    ],
    "sg:phone":"+1 541 484 6844",
    "sg:postcode":"97401",
    "sg:province":"OR",
    "sg:tags":[
        "property",
        "lessor"
    ],
    "wof:name":"Garden Isle Estates",
    "wof:placetype":"venue"
},
  "geometry": {"coordinates":[-123.10896700000001,44.08441],"type":"Point"}
}