{
  "type": "Feature",
  "properties": {
    "iso:country":"US",
    "sg:address":"1114 Grandview Ave",
    "sg:city":"Grants Pass",
    "sg:classifiers":[
        {
            "category":"Professional",
            "subcategory":"Detective & Security Services",
            "type":"Services"
        }
    ],
    "sg:phone":"+1 541 779 4235",
    "sg:postcode":"97527",
    "sg:province":"OR",
    "sg:tags":[
        "guard",
        "patrol"
    ],
    "wof:name":"Initial Security",
    "wof:placetype":"venue"
},
  "geometry": {"coordinates":[-123.31753999999999,42.417003],"type":"Point"}
}