{
  "type": "Feature",
  "properties": {
    "iso:country":"US",
    "sg:address":"30855 SE Ely Rd",
    "sg:city":"Estacada",
    "sg:classifiers":[
        {
            "category":"Home & Garden",
            "subcategory":"Garden Supply",
            "type":"Retail Goods"
        }
    ],
    "sg:phone":"+1 503 630 2390",
    "sg:postcode":"97023",
    "sg:province":"OR",
    "wof:name":"Mc Gregor Garden Ctr",
    "wof:placetype":"venue"
},
  "geometry": {"coordinates":[-122.345895,45.318011],"type":"Point"}
}