{
  "type": "Feature",
  "properties": {
    "iso:country":"US",
    "sg:address":"82nd & Burnside",
    "sg:city":"Portland",
    "sg:classifiers":[
        {
            "category":"Food Court",
            "type":"Food & Drink"
        },
        {
            "category":"Restaurant",
            "type":"Food & Drink"
        }
    ],
    "sg:phone":"+1 503 853 5858",
    "sg:postcode":"97215",
    "sg:province":"OR",
    "sg:tags":[
        "mexican",
        "stand"
    ],
    "wof:name":"Su Casa Taqueria Cart",
    "wof:placetype":"venue"
},
  "geometry": {"coordinates":[-122.579021,45.522753],"type":"Point"}
}