{
  "type": "Feature",
  "properties": {
    "iso:country":"US",
    "sg:address":"16833 SW Cynthia St",
    "sg:city":"Beaverton",
    "sg:classifiers":[
        {
            "category":"Education",
            "subcategory":"Vocational School",
            "type":"Public Place"
        }
    ],
    "sg:phone":"+1 503 784 3692",
    "sg:postcode":"97007",
    "sg:province":"OR",
    "wof:name":"Frontline Resources Inc",
    "wof:placetype":"venue"
},
  "geometry": {"coordinates":[-122.85010200000001,45.468248],"type":"Point"}
}