{
  "type": "Feature",
  "properties": {
    "iso:country":"US",
    "sg:address":"6015 SW Arrow Wood Ln",
    "sg:city":"Portland",
    "sg:classifiers":[
        {
            "category":"Wholesale",
            "subcategory":"Wine & Distilled Alcoholic Beverages",
            "type":"Manufacturing & Wholesale Goods"
        }
    ],
    "sg:phone":"+1 503 297 4789",
    "sg:postcode":"97223",
    "sg:province":"OR",
    "wof:name":"North Pacific Wine & Spirits",
    "wof:placetype":"venue"
},
  "geometry": {"coordinates":[-122.770889,45.481784],"type":"Point"}
}