{
  "type": "Feature",
  "properties": {
    "iso:country":"US",
    "sg:address":"1000 River Rd",
    "sg:city":"Eugene",
    "sg:classifiers":[
        {
            "category":"Health Services",
            "subcategory":"Chiropractor",
            "type":"Services"
        }
    ],
    "sg:phone":"+1 541 689 0935",
    "sg:postcode":"97404",
    "sg:province":"OR",
    "sg:tags":[
        "chiropractic"
    ],
    "wof:name":"Gervais Brian DC",
    "wof:placetype":"venue"
},
  "geometry": {"coordinates":[-123.120659,44.077999],"type":"Point"}
}