{
  "type": "Feature",
  "properties": {
    "iso:country":"US",
    "sg:address":"3180 Grey Blvd",
    "sg:city":"Nyssa",
    "sg:classifiers":[
        {
            "category":"Insurance",
            "subcategory":"Insurance Agent",
            "type":"Services"
        }
    ],
    "sg:phone":"+1 541 372 2366",
    "sg:postcode":"97913",
    "sg:province":"OR",
    "wof:name":"Esplin Insurance & Fincl Svc",
    "wof:placetype":"venue"
},
  "geometry": {"coordinates":[-117.06608,43.894432],"type":"Point"}
}