{
  "type": "Feature",
  "properties": {
    "addr:full":"1143 SW Stark Street Portland OR 97205",
    "addr:housenumber":"1143",
    "addr:postcode":"97205",
    "addr:street":"Sw Stark Street",
    "iso:country":"US",
    "sg:address":"1143 SW Stark Street",
    "sg:city":"Portland",
    "sg:classifiers":[
        {
            "category":"Food & Beverages",
            "subcategory":"Groceries & Convenience Stores",
            "type":"Retail Goods"
        }
    ],
    "sg:phone":"+1 503 227 4965",
    "sg:postcode":"97205",
    "sg:province":"OR",
    "wof:name":"Georgia's Grocery Store",
    "wof:placetype":"venue"
},
  "geometry": {"coordinates":[-122.682468,45.522288],"type":"Point"}
}