{
  "type": "Feature",
  "properties": {
    "iso:country":"US",
    "sg:address":"298 Garfield St",
    "sg:city":"Ashland",
    "sg:classifiers":[
        {
            "category":"Communications",
            "subcategory":"Film & Video Production",
            "type":"Services"
        }
    ],
    "sg:phone":"+1 541 482 6988",
    "sg:postcode":"97520",
    "sg:province":"OR",
    "sg:tags":[
        "motion"
    ],
    "wof:name":"Brain Labor Productions",
    "wof:placetype":"venue"
},
  "geometry": {"coordinates":[-122.696209,42.189078],"type":"Point"}
}