{
  "type": "Feature",
  "properties": {
    "iso:country":"US",
    "sg:address":"105 NE Burnside Rd",
    "sg:city":"Gresham",
    "sg:classifiers":[
        {
            "category":"Restaurant",
            "type":"Food & Drink"
        }
    ],
    "sg:phone":"+1 503 465 8565",
    "sg:postcode":"97030",
    "sg:province":"OR",
    "wof:name":"Sizzler",
    "wof:placetype":"venue"
},
  "geometry": {"coordinates":[-122.426489,45.507881],"type":"Point"}
}