{
  "type": "Feature",
  "properties": {
    "iso:country":"US",
    "sg:address":"2400 NE Red Sunset Dr",
    "sg:city":"Gresham",
    "sg:classifiers":[
        {
            "category":"Real Estate",
            "subcategory":"Real Estate Operator",
            "type":"Services"
        }
    ],
    "sg:phone":"+1 503 665 2903",
    "sg:postcode":"97030",
    "sg:province":"OR",
    "sg:tags":[
        "building",
        "apartment"
    ],
    "wof:name":"Red Sunset Apartments",
    "wof:placetype":"venue"
},
  "geometry": {"coordinates":[-122.413715,45.515879],"type":"Point"}
}