{
  "type": "Feature",
  "properties": {
    "iso:country":"US",
    "sg:address":"14270 NW Science Park Drive",
    "sg:city":"Portland",
    "sg:classifiers":[
        {
            "category":"Shopping",
            "subcategory":"Stationery & Office Supplies",
            "type":"Retail Goods"
        }
    ],
    "sg:phone":"+1 503 646 5343",
    "sg:postcode":"97229",
    "sg:province":"OR",
    "sg:tags":[
        "equipment"
    ],
    "wof:name":"Office & Dining Warehouse",
    "wof:placetype":"venue"
},
  "geometry": {"coordinates":[-122.825861,45.528589],"type":"Point"}
}