{
  "type": "Feature",
  "properties": {
    "iso:country":"US",
    "sg:address":"2028 8th Ave",
    "sg:city":"West Linn",
    "sg:classifiers":[
        {
            "category":"Restaurant",
            "type":"Food & Drink"
        }
    ],
    "sg:phone":"+1 503 657 5431",
    "sg:postcode":"97068",
    "sg:province":"OR",
    "sg:tags":[
        "eating"
    ],
    "wof:name":"Ixtapa West Linn Inc",
    "wof:placetype":"venue"
},
  "geometry": {"coordinates":[-122.652964,45.345644],"type":"Point"}
}