{
  "type": "Feature",
  "properties": {
    "iso:country":"US",
    "sg:address":"16865 NW Germantown Rd",
    "sg:city":"Portland",
    "sg:classifiers":[
        {
            "category":"Building & Trades",
            "subcategory":"Construction",
            "type":"Services"
        }
    ],
    "sg:phone":"+1 503 645 8458",
    "sg:postcode":"97231",
    "sg:province":"OR",
    "sg:tags":[
        "nonresidential"
    ],
    "wof:name":"Helvetia Construction",
    "wof:placetype":"venue"
},
  "geometry": {"coordinates":[-122.848465,45.580877],"type":"Point"}
}