{
  "type": "Feature",
  "properties": {
    "iso:country":"US",
    "sg:address":"19500 SW Teton Ave",
    "sg:city":"Tualatin",
    "sg:classifiers":[
        {
            "category":"Professional",
            "subcategory":"Printing & Photocopies",
            "type":"Services"
        }
    ],
    "sg:phone":"+1 503 692 4435",
    "sg:postcode":"97062",
    "sg:province":"OR",
    "sg:tags":[
        "lithographer"
    ],
    "wof:name":"Strategic Printing",
    "wof:placetype":"venue"
},
  "geometry": {"coordinates":[-122.783089,45.379162],"type":"Point"}
}