{
  "type": "Feature",
  "properties": {
    "iso:country":"US",
    "sg:address":"850 Siskiyou Blvd",
    "sg:city":"Ashland",
    "sg:classifiers":[
        {
            "category":"Restaurant",
            "type":"Food & Drink"
        }
    ],
    "sg:phone":"+1 541 482 7056",
    "sg:postcode":"97520",
    "sg:province":"OR",
    "sg:tags":[
        "eating"
    ],
    "wof:name":"Michael M Zanoni Chinese",
    "wof:placetype":"venue"
},
  "geometry": {"coordinates":[-122.700405,42.189447],"type":"Point"}
}