{
  "type": "Feature",
  "properties": {
    "iso:country":"US",
    "sg:address":"14700 SE Division St",
    "sg:city":"Portland",
    "sg:classifiers":[
        {
            "category":"Shopping",
            "subcategory":"Optician",
            "type":"Retail Goods"
        }
    ],
    "sg:phone":"+1 503 761 1975",
    "sg:postcode":"97236",
    "sg:province":"OR",
    "sg:tags":[
        "eyewear"
    ],
    "wof:name":"Vision Clinics In Fred Meyer",
    "wof:placetype":"venue"
},
  "geometry": {"coordinates":[-122.51599899999999,45.473598],"type":"Point"}
}