{
  "type": "Feature",
  "properties": {
    "iso:country":"US",
    "sg:address":"8333 NE Russell St",
    "sg:city":"Portland",
    "sg:classifiers":[
        {
            "category":"Arena",
            "subcategory":"Sports Club",
            "type":"Entertainment"
        }
    ],
    "sg:phone":"+1 503 890 5086",
    "sg:postcode":"97220",
    "sg:province":"OR",
    "sg:tags":[
        "martial art"
    ],
    "sg:website":"www.csaportland.com",
    "wof:name":"Combat Sports Academy Portland",
    "wof:placetype":"venue"
},
  "geometry": {"coordinates":[-122.576809,45.541385],"type":"Point"}
}