{
  "type": "Feature",
  "properties": {
    "iso:country":"US",
    "sg:address":"17350 Smith Ave",
    "sg:city":"Sandy",
    "sg:classifiers":[
        {
            "category":"Retail",
            "subcategory":"Repair Shop",
            "type":"Services"
        }
    ],
    "sg:phone":"+1 503 668 7593",
    "sg:postcode":"97055",
    "sg:province":"OR",
    "sg:tags":[
        "spa",
        "hot",
        "tub"
    ],
    "wof:name":"Adventure Pool & Spa Inc",
    "wof:placetype":"venue"
},
  "geometry": {"coordinates":[-122.260668,45.397623],"type":"Point"}
}