{
  "type": "Feature",
  "properties": {
    "addr:full":"24025 NE Shea Ln Troutdale OR 97060",
    "addr:housenumber":"24025",
    "addr:postcode":"97060",
    "addr:street":"Ne Shea Ln",
    "iso:country":"US",
    "sg:address":"24025 NE Shea Ln",
    "sg:city":"Troutdale",
    "sg:classifiers":[
        {
            "category":"Retail",
            "subcategory":"Repair Shop",
            "type":"Services"
        },
        {
            "category":"Building & Trades",
            "subcategory":"Construction",
            "type":"Services"
        }
    ],
    "sg:phone":"+1 503 665 4211",
    "sg:postcode":"97060",
    "sg:province":"OR",
    "sg:tags":[
        "welding",
        "contractor"
    ],
    "wof:name":"Northwest Casting Service Inc",
    "wof:placetype":"venue"
},
  "geometry": {"coordinates":[-122.41579900000001,45.538858],"type":"Point"}
}