{
  "type": "Feature",
  "properties": {
    "addr:full":"12053 Brick Rd SE Turner OR 97392",
    "addr:housenumber":"12053",
    "addr:postcode":"97392",
    "addr:street":"Brick Rd Se",
    "iso:country":"US",
    "sg:address":"12053 Brick Rd SE",
    "sg:city":"Turner",
    "sg:phone":"+1 503 743 4252",
    "sg:postcode":"97392",
    "sg:province":"OR",
    "sg:tags":[
        "farm",
        "corn",
        "cash",
        "crop",
        "field",
        "grain"
    ],
    "wof:name":"Belden & Sons Inc",
    "wof:placetype":"venue"
},
  "geometry": {"coordinates":[-122.895664,44.783947],"type":"Point"}
}