{
  "type": "Feature",
  "properties": {
    "iso:country":"US",
    "sg:address":"16320 NW Joscelyn St",
    "sg:city":"Beaverton",
    "sg:classifiers":[
        {
            "category":"Professional",
            "type":"Services"
        }
    ],
    "sg:phone":"+1 503 690 3326",
    "sg:postcode":"97006",
    "sg:province":"OR",
    "wof:name":"Stevens Technical Services",
    "wof:placetype":"venue"
},
  "geometry": {"coordinates":[-122.845191,45.542988],"type":"Point"}
}