{
  "type": "Feature",
  "properties": {
    "iso:country":"US",
    "sg:address":"10214 SW 36th Ct",
    "sg:city":"Portland",
    "sg:classifiers":[
        {
            "category":"Professional",
            "subcategory":"Secretarial Services",
            "type":"Services"
        }
    ],
    "sg:phone":"+1 503 244 4460",
    "sg:postcode":"97219",
    "sg:province":"OR",
    "sg:tags":[
        "processing",
        "word"
    ],
    "wof:name":"Print Preview Inc",
    "wof:placetype":"venue"
},
  "geometry": {"coordinates":[-122.713731,45.451387],"type":"Point"}
}