{
  "type": "Feature",
  "properties": {
    "addr:full":"23721 SE Bohna Park Rd Boring OR 97089",
    "addr:postcode":"23721;97089",
    "addr:street":"Se Bohna Park Rd",
    "iso:country":"US",
    "sg:address":"23721 SE Bohna Park Rd",
    "sg:city":"Boring",
    "sg:classifiers":[
        {
            "category":"Building & Trades",
            "subcategory":"Construction",
            "type":"Services"
        }
    ],
    "sg:phone":"+1 503 658 2269",
    "sg:postcode":"97089",
    "sg:province":"OR",
    "sg:tags":[
        "house"
    ],
    "wof:name":"Oxenrider Constrution",
    "wof:placetype":"venue"
},
  "geometry": {"coordinates":[-122.421255,45.432617],"type":"Point"}
}