{
  "type": "Feature",
  "properties": {
    "iso:country":"US",
    "sg:address":"1855 Fescue St SE",
    "sg:city":"Albany",
    "sg:classifiers":[
        {
            "category":"Manufacturing",
            "subcategory":"Tools & Machinery",
            "type":"Manufacturing & Wholesale Goods"
        }
    ],
    "sg:phone":"+1 541 917 3626",
    "sg:postcode":"97322",
    "sg:province":"OR",
    "sg:tags":[
        "machine",
        "shop"
    ],
    "wof:name":"Marler Enterprises Inc",
    "wof:placetype":"venue"
},
  "geometry": {"coordinates":[-123.059987,44.622713],"type":"Point"}
}