{
  "type": "Feature",
  "properties": {
    "addr:full":"7373 Milwaukie Expy Milwaukie OR 97222",
    "addr:housenumber":"7373",
    "addr:postcode":"97222",
    "addr:street":"Expy",
    "iso:country":"US",
    "sg:address":"7373 Milwaukie Expy",
    "sg:city":"Milwaukie",
    "sg:classifiers":[
        {
            "category":"Wholesale",
            "subcategory":"Machinery & Supplies",
            "type":"Manufacturing & Wholesale Goods"
        }
    ],
    "sg:phone":"+1 503 659 5438",
    "sg:postcode":"97222",
    "sg:province":"OR",
    "sg:tags":[
        "truck"
    ],
    "sg:website":"www.norliftor.com",
    "wof:name":"Norlift Of Oregon Inc",
    "wof:placetype":"venue"
},
  "geometry": {"coordinates":[-122.58324399999999,45.422979],"type":"Point"}
}