{
  "type": "Feature",
  "properties": {
    "iso:country":"US",
    "sg:address":"3673 NW Tyler Pl",
    "sg:city":"Corvallis",
    "sg:classifiers":[
        {
            "category":"Professional",
            "subcategory":"Computer Services",
            "type":"Services"
        }
    ],
    "sg:phone":"+1 541 757 3491",
    "sg:postcode":"97330",
    "sg:province":"OR",
    "sg:tags":[
        "datum"
    ],
    "wof:name":"Ken Minoura",
    "wof:placetype":"venue"
},
  "geometry": {"coordinates":[-123.29140099999999,44.572617],"type":"Point"}
}