{
  "type": "Feature",
  "properties": {
    "iso:country":"US",
    "sg:address":"41095 Taylor Ln",
    "sg:city":"Pendleton",
    "sg:classifiers":[
        {
            "category":"Farming",
            "subcategory":"Livestock Farm",
            "type":"Manufacturing & Wholesale Goods"
        }
    ],
    "sg:phone":"+1 541 278 0541",
    "sg:postcode":"97801",
    "sg:province":"OR",
    "sg:tags":[
        "beef",
        "feedlot",
        "cattle"
    ],
    "wof:name":"Torco Ranch",
    "wof:placetype":"venue"
},
  "geometry": {"coordinates":[-118.882302,45.652549],"type":"Point"}
}