{
  "type": "Feature",
  "properties": {
    "addr:full":"1133 Erickson St Lake Oswego OR 97034",
    "addr:housenumber":"1133",
    "addr:postcode":"97034",
    "addr:street":"Erickson St",
    "iso:country":"US",
    "sg:address":"1133 Erickson St",
    "sg:city":"Lake Oswego",
    "sg:classifiers":[
        {
            "category":"Professional",
            "subcategory":"Advertising",
            "type":"Services"
        }
    ],
    "sg:phone":"+1 503 636 2370",
    "sg:postcode":"97034",
    "sg:province":"OR",
    "sg:tags":[
        "consulting",
        "management",
        "agency"
    ],
    "wof:name":"Clarke Donelson Inc",
    "wof:placetype":"venue"
},
  "geometry": {"coordinates":[-122.669077,45.407097],"type":"Point"}
}