{
  "type": "Feature",
  "properties": {
    "iso:country":"US",
    "sg:address":"3454 12th St SE",
    "sg:city":"Salem",
    "sg:classifiers":[
        {
            "category":"Organizations",
            "subcategory":"Community Association",
            "type":"Services"
        }
    ],
    "sg:phone":"+1 503 364 8125",
    "sg:postcode":"97302",
    "sg:province":"OR",
    "wof:name":"Friends of Morningside HI",
    "wof:placetype":"venue"
},
  "geometry": {"coordinates":[-123.03074100000001,44.905586],"type":"Point"}
}