{
  "type": "Feature",
  "properties": {
    "iso:country":"US",
    "sg:address":"1742 Delrose Ave",
    "sg:city":"Springfield",
    "sg:classifiers":[
        {
            "category":"Banks & Credit Unions",
            "subcategory":"Financial Services",
            "type":"Services"
        }
    ],
    "sg:phone":"+1 541 726 1185",
    "sg:postcode":"97477",
    "sg:province":"OR",
    "sg:tags":[
        "investor"
    ],
    "wof:name":"Ventis Investment Properties",
    "wof:placetype":"venue"
},
  "geometry": {"coordinates":[-122.999835,44.073358],"type":"Point"}
}