{
  "type": "Feature",
  "properties": {
    "addr:full":"2051 Bennett Creek Rd Cottage Grove OR 97424",
    "addr:housenumber":"2051",
    "addr:postcode":"97424",
    "addr:street":"Bennett Creek Rd",
    "iso:country":"US",
    "sg:address":"2051 Bennett Creek Rd",
    "sg:city":"Cottage Grove",
    "sg:classifiers":[
        {
            "category":"Professional",
            "subcategory":"Management & Consulting",
            "type":"Services"
        }
    ],
    "sg:phone":"+1 541 942 3870",
    "sg:postcode":"97424",
    "sg:province":"OR",
    "sg:tags":[
        "marketing",
        "program"
    ],
    "wof:name":"Blackstone",
    "wof:placetype":"venue"
},
  "geometry": {"coordinates":[-123.08176899999999,43.824061],"type":"Point"}
}