{
  "type": "Feature",
  "properties": {
    "addr:full":"107 SE 9th St Bend OR 97702",
    "addr:housenumber":"107",
    "addr:postcode":"97702",
    "addr:street":"Se 9Th St",
    "iso:country":"US",
    "sg:address":"107 SE 9th St",
    "sg:city":"Bend",
    "sg:classifiers":[
        {
            "category":"Government",
            "subcategory":"Fire Station",
            "type":"Public Place"
        },
        {
            "category":"Retail",
            "subcategory":"Laundry & Dry Cleaning",
            "type":"Services"
        },
        {
            "category":"Building & Trades",
            "subcategory":"Cleaning & Sanitation",
            "type":"Services"
        }
    ],
    "sg:phone":"+1 541 317 9722",
    "sg:postcode":"97702",
    "sg:province":"OR",
    "sg:tags":[
        "cleaner",
        "disaster",
        "recovery",
        "rug",
        "contractor",
        "cleaning-industrial",
        "relief",
        "carpet"
    ],
    "sg:website":"http://www.servpro.com",
    "wof:name":"Servpro",
    "wof:placetype":"venue"
},
  "geometry": {"coordinates":[-121.29280900000001,44.049174],"type":"Point"}
}