{
  "type": "Feature",
  "properties": {
    "addr:full":"15135 SW Hillsboro Hwy Hillsboro OR 97123",
    "addr:housenumber":"15135",
    "addr:postcode":"97123",
    "addr:street":"Sw Hillsboro Hwy",
    "iso:country":"US",
    "sg:address":"15135 SW Hillsboro Hwy",
    "sg:city":"Hillsboro",
    "sg:classifiers":[
        {
            "category":"Building & Trades",
            "subcategory":"Construction",
            "type":"Services"
        }
    ],
    "sg:phone":"+1 503 848 7756",
    "sg:postcode":"97123",
    "sg:province":"OR",
    "sg:tags":[
        "concrete",
        "contractor"
    ],
    "wof:name":"All Star Concrete Pumping",
    "wof:placetype":"venue"
},
  "geometry": {"coordinates":[-122.95479,45.411336],"type":"Point"}
}