{
  "type": "Feature",
  "properties": {
    "addr:full":"1010 SW 13th St Lincoln City OR 97367",
    "addr:housenumber":"1010",
    "addr:postcode":"97367",
    "addr:street":"Sw 13Th St",
    "iso:country":"US",
    "sg:address":"1010 SW 13th St",
    "sg:city":"Lincoln City",
    "sg:classifiers":[
        {
            "category":"Real Estate",
            "subcategory":"Architect",
            "type":"Services"
        }
    ],
    "sg:phone":"+1 541 994 3898",
    "sg:postcode":"97367",
    "sg:province":"OR",
    "sg:tags":[
        "architectural"
    ],
    "wof:name":"Arnold Bondley Architect",
    "wof:placetype":"venue"
},
  "geometry": {"coordinates":[-124.017257,44.958186],"type":"Point"}
}