{
  "type": "Feature",
  "properties": {
    "addr:full":"7595 SW 84th Ave Portland OR 97223",
    "addr:housenumber":"7595",
    "addr:postcode":"97223",
    "addr:street":"Sw 84Th Ave",
    "iso:country":"US",
    "sg:address":"7595 SW 84th Ave",
    "sg:city":"Portland",
    "sg:classifiers":[
        {
            "category":"Restaurant",
            "type":"Food & Drink"
        }
    ],
    "sg:phone":"+1 503 245 3238",
    "sg:postcode":"97223",
    "sg:province":"OR",
    "sg:tags":[
        "pizza"
    ],
    "wof:name":"S Paoli Pizza Inc",
    "wof:placetype":"venue"
},
  "geometry": {"coordinates":[-122.763772,45.464448],"type":"Point"}
}