{
  "type": "Feature",
  "properties": {
    "addr:full":"13921 SW Tualatin Sherwood Rd Sherwood OR 97140",
    "addr:housenumber":"13921",
    "addr:postcode":"97140",
    "addr:street":"Sw Tualatin Sherwood Rd",
    "iso:country":"US",
    "sg:address":"13921 SW Tualatin Sherwood Rd",
    "sg:city":"Sherwood",
    "sg:classifiers":[
        {
            "category":"Wholesale",
            "subcategory":"Auto Parts",
            "type":"Manufacturing & Wholesale Goods"
        }
    ],
    "sg:phone":"+1 503 625 3800",
    "sg:postcode":"97140",
    "sg:province":"OR",
    "sg:tags":[
        "automobile",
        "rebuilt",
        "used"
    ],
    "wof:name":"John's Import Auto Wrecking",
    "wof:placetype":"venue"
},
  "geometry": {"coordinates":[-122.821215,45.368006],"type":"Point"}
}