{
  "type": "Feature",
  "properties": {
    "iso:country":"US",
    "sg:address":"529 NW 4th St",
    "sg:city":"Corvallis",
    "sg:classifiers":[
        {
            "category":"Retail",
            "subcategory":"Auto Repair",
            "type":"Services"
        }
    ],
    "sg:phone":"+1 541 753 1234",
    "sg:postcode":"97330",
    "sg:province":"OR",
    "sg:tags":[
        "automotive",
        "supply"
    ],
    "wof:name":"Corvallis Auto Electric",
    "wof:placetype":"venue"
},
  "geometry": {"coordinates":[-123.259473,44.569236],"type":"Point"}
}