{
  "type": "Feature",
  "properties": {
    "addr:full":"1444 SE Hawthorne Blvd Portland OR 97214",
    "addr:housenumber":"1444",
    "addr:postcode":"97214",
    "addr:street":"Se Hawthorne Blvd",
    "iso:country":"US",
    "sg:address":"1444 SE Hawthorne Blvd",
    "sg:city":"Portland",
    "sg:classifiers":[
        {
            "category":"Education",
            "subcategory":"Preschool",
            "type":"Public Place"
        }
    ],
    "sg:phone":"+1 503 265 9953",
    "sg:postcode":"97214",
    "sg:province":"OR",
    "sg:website":"www.alexanderpreschool.com",
    "wof:name":"Emily Alexander's Preschool of the Arts",
    "wof:placetype":"venue"
},
  "geometry": {"coordinates":[-122.650864,45.51194],"type":"Point"}
}