{
  "type": "Feature",
  "properties": {
    "iso:country":"US",
    "sg:address":"6637 SE 100th Ave",
    "sg:city":"Portland",
    "sg:classifiers":[
        {
            "category":"Mining & Drilling",
            "type":"Manufacturing & Wholesale Goods"
        }
    ],
    "sg:phone":"+1 503 777 7924",
    "sg:postcode":"97266",
    "sg:province":"OR",
    "sg:tags":[
        "construction"
    ],
    "wof:name":"Pacific Rock Products",
    "wof:placetype":"venue"
},
  "geometry": {"coordinates":[-122.561236,45.474638],"type":"Point"}
}