{
  "type": "Feature",
  "properties": {
    "addr:full":"5289 NE Elam Young Pkwy D100 Hillsboro OR 97124",
    "addr:housenumber":"5289",
    "addr:postcode":"97124",
    "addr:street":"Ne Elam Young Pkwy D100",
    "iso:country":"US",
    "sg:address":"5289 NE Elam Young Pkwy D100",
    "sg:city":"Hillsboro",
    "sg:classifiers":[
        {
            "category":"Arts & Performance",
            "subcategory":"Dance",
            "type":"Entertainment"
        }
    ],
    "sg:phone":"+1 503 693 6166",
    "sg:postcode":"97124",
    "sg:province":"OR",
    "sg:tags":[
        "instruction",
        "dancing"
    ],
    "wof:name":"Mainstreet's New Vision Dance",
    "wof:placetype":"venue"
},
  "geometry": {"coordinates":[-122.929761,45.527072],"type":"Point"}
}