{
  "type": "Feature",
  "properties": {
    "iso:country":"US",
    "sg:address":"539 Medford Ctr",
    "sg:city":"Medford",
    "sg:classifiers":[
        {
            "category":"Shopping",
            "subcategory":"Jewelry",
            "type":"Retail Goods"
        }
    ],
    "sg:phone":"+1 541 245 1585",
    "sg:postcode":"97504",
    "sg:province":"OR",
    "wof:name":"J Michaels Fine Jewelry",
    "wof:placetype":"venue"
},
  "geometry": {"coordinates":[-122.866997,42.331299],"type":"Point"}
}