{
  "type": "Feature",
  "properties": {
    "addr:full":"16259 SE Grand St Clackamas OR 97089",
    "addr:postcode":"16259;97089",
    "addr:street":"Se Grand St",
    "iso:country":"US",
    "sg:address":"16259 SE Grand St",
    "sg:city":"Clackamas",
    "sg:classifiers":[
        {
            "category":"Food & Beverages",
            "subcategory":"Meat & Fish",
            "type":"Retail Goods"
        }
    ],
    "sg:phone":"+1 503 658 1753",
    "sg:postcode":"97089",
    "sg:province":"OR",
    "sg:tags":[
        "cutting"
    ],
    "wof:name":"Sportsmen's Meat Cutting",
    "wof:placetype":"venue"
},
  "geometry": {"coordinates":[-122.496882,45.395667],"type":"Point"}
}