{
  "type": "Feature",
  "properties": {
    "iso:country":"US",
    "sg:address":"1601 Metz Hill Rd",
    "sg:city":"Oakland",
    "sg:classifiers":[
        {
            "category":"Restaurant",
            "type":"Food & Drink"
        }
    ],
    "sg:phone":"+1 541 459 1705",
    "sg:postcode":"97462",
    "sg:province":"OR",
    "sg:tags":[
        "italian"
    ],
    "wof:name":"Pedottis Italian Restaurant",
    "wof:placetype":"venue"
},
  "geometry": {"coordinates":[-123.348167,43.4566],"type":"Point"}
}