{
  "type": "Feature",
  "properties": {
    "addr:full":"2831 NW Front Ave Portland OR 97210",
    "addr:housenumber":"2831",
    "addr:postcode":"97210",
    "addr:street":"Nw Front Ave",
    "iso:country":"US",
    "sg:address":"2831 NW Front Ave",
    "sg:city":"Portland",
    "sg:classifiers":[
        {
            "category":"Food & Beverages",
            "subcategory":"Groceries & Convenience Stores",
            "type":"Retail Goods"
        }
    ],
    "sg:phone":"+1 503 222 2737",
    "sg:postcode":"97210",
    "sg:province":"OR",
    "wof:name":"Hi Neighbor Deli",
    "wof:placetype":"venue"
},
  "geometry": {"coordinates":[-122.696048,45.542182],"type":"Point"}
}