{
  "type": "Feature",
  "properties": {
    "iso:country":"US",
    "sg:address":"4048 Crater Lake Ave",
    "sg:city":"Medford",
    "sg:classifiers":[
        {
            "category":"Personal",
            "type":"Services"
        }
    ],
    "sg:phone":"+1 541 772 4040",
    "sg:postcode":"97504",
    "sg:province":"OR",
    "sg:tags":[
        "towing"
    ],
    "wof:name":"Dick's Wrecker Service",
    "wof:placetype":"venue"
},
  "geometry": {"coordinates":[-122.856003,42.375301],"type":"Point"}
}