{
  "type": "Feature",
  "properties": {
    "addr:full":"1330 McGilchrist St SE Salem OR 97302",
    "addr:housenumber":"1330",
    "addr:postcode":"97302",
    "addr:street":"Mcgilchrist St Se",
    "iso:country":"US",
    "sg:address":"1330 McGilchrist St SE",
    "sg:city":"Salem",
    "sg:classifiers":[
        {
            "category":"Autos & Motor Vehicles",
            "subcategory":"Automobile Sales",
            "type":"Retail Goods"
        }
    ],
    "sg:phone":"+1 503 361 8608",
    "sg:postcode":"97302",
    "sg:province":"OR",
    "sg:tags":[
        "car",
        "dealer"
    ],
    "wof:name":"Capitol's Truckworld",
    "wof:placetype":"venue"
},
  "geometry": {"coordinates":[-123.028148,44.916734],"type":"Point"}
}