{
  "type": "Feature",
  "properties": {
    "iso:country":"US",
    "sg:address":"1815 SW Marlow Ave",
    "sg:city":"Portland",
    "sg:classifiers":[
        {
            "category":"Health Services",
            "subcategory":"Health Practitioner",
            "type":"Services"
        }
    ],
    "sg:phone":"+1 503 297 0513",
    "sg:postcode":"97225",
    "sg:province":"OR",
    "wof:name":"Cheryl Brischetto PHD",
    "wof:placetype":"venue"
},
  "geometry": {"coordinates":[-122.784598,45.507681],"type":"Point"}
}