{
  "type": "Feature",
  "properties": {
    "iso:country":"US",
    "sg:address":"601 N Main St",
    "sg:city":"Joseph",
    "sg:classifiers":[
        {
            "category":"Social Services",
            "type":"Services"
        }
    ],
    "sg:phone":"+1 541 432 1818",
    "sg:postcode":"97846",
    "sg:province":"OR",
    "wof:name":"Judy Wandschneider Msw",
    "wof:placetype":"venue"
},
  "geometry": {"coordinates":[-117.229911,45.359038],"type":"Point"}
}