{
  "type": "Feature",
  "properties": {
    "iso:country":"US",
    "sg:address":"17980 SW Shadypeak Ln",
    "sg:city":"Beaverton",
    "sg:classifiers":[
        {
            "category":"Manufacturing",
            "subcategory":"Electronics",
            "type":"Manufacturing & Wholesale Goods"
        }
    ],
    "sg:phone":"+1 503 649 5085",
    "sg:postcode":"97007",
    "sg:province":"OR",
    "sg:tags":[
        "equipment",
        "mfg",
        "electronic",
        "communications"
    ],
    "wof:name":"Survey Technologies Inc",
    "wof:placetype":"venue"
},
  "geometry": {"coordinates":[-122.857525,45.460102],"type":"Point"}
}