{
  "type": "Feature",
  "properties": {
    "iso:country":"US",
    "sg:address":"1515 SE Water Avenue, Suite 300",
    "sg:city":"Portland",
    "sg:classifiers":[
        {
            "category":"Professional",
            "subcategory":"Computer Services",
            "type":"Services"
        }
    ],
    "sg:phone":"+1 971 255 4800",
    "sg:postcode":"97214",
    "sg:province":"OR",
    "sg:website":"http://www.viewpointcs.com/",
    "wof:name":" Viewpoint Construction Software",
    "wof:placetype":"venue"
},
  "geometry": {"coordinates":[-122.665853,45.511539],"type":"Point"}
}