{
  "type": "Feature",
  "properties": {
    "iso:country":"US",
    "sg:address":"24985 Hwy 140 E",
    "sg:city":"Bonanza",
    "sg:classifiers":[
        {
            "category":"Food & Beverages",
            "subcategory":"Groceries & Convenience Stores",
            "type":"Retail Goods"
        }
    ],
    "sg:phone":"+1 541 545 1304",
    "sg:postcode":"97623",
    "sg:province":"OR",
    "wof:name":"Yonna Valley Store",
    "wof:placetype":"venue"
},
  "geometry": {"coordinates":[-121.49311899999999,42.263965],"type":"Point"}
}