{
  "type": "Feature",
  "properties": {
    "addr:full":"10235 NW Cornelius Pass Rd Portland OR 97231",
    "addr:housenumber":"10235",
    "addr:postcode":"97231",
    "addr:street":"Nw Cornelius Pass Rd",
    "iso:country":"US",
    "sg:address":"10235 NW Cornelius Pass Rd",
    "sg:city":"Portland",
    "sg:classifiers":[
        {
            "category":"Organizations",
            "subcategory":"Religious Organization",
            "type":"Services"
        }
    ],
    "sg:phone":"+1 503 645 8649",
    "sg:postcode":"97231",
    "sg:province":"OR",
    "wof:name":"Atma",
    "wof:placetype":"venue"
},
  "geometry": {"coordinates":[-122.866075,45.59839],"type":"Point"}
}