{
  "type": "Feature",
  "properties": {
    "addr:full":"1312 SW 16th Ave Fl 2 Portland OR 97201",
    "addr:housenumber":"1312;2",
    "addr:postcode":"97201",
    "addr:street":"Sw 16Th Ave Fl",
    "iso:country":"US",
    "sg:address":"1312 SW 16th Ave Fl 2",
    "sg:city":"Portland",
    "sg:classifiers":[
        {
            "category":"Professional",
            "subcategory":"Lawyer & Legal Services",
            "type":"Services"
        }
    ],
    "sg:phone":"+1 503 517 9216",
    "sg:postcode":"97201",
    "sg:province":"OR",
    "wof:name":"Altman Robert J Attorney At Law",
    "wof:placetype":"venue"
},
  "geometry": {"coordinates":[-122.690189,45.517458],"type":"Point"}
}