{
  "type": "Feature",
  "properties": {
    "addr:full":"7005 E Burnside St Portland OR 97215",
    "addr:housenumber":"7005",
    "addr:postcode":"97215",
    "addr:street":"E Burnside St",
    "iso:country":"US",
    "sg:address":"7005 E Burnside St",
    "sg:city":"Portland",
    "sg:classifiers":[
        {
            "category":"Wholesale",
            "subcategory":"Apparel",
            "type":"Manufacturing & Wholesale Goods"
        }
    ],
    "sg:phone":"+1 503 408 7685",
    "sg:postcode":"97215",
    "sg:province":"OR",
    "wof:name":"Total Impact Wear Inc",
    "wof:placetype":"venue"
},
  "geometry": {"coordinates":[-122.58989200000001,45.523181],"type":"Point"}
}