{
  "type": "Feature",
  "properties": {
    "iso:country":"US",
    "sg:address":"907 NW Furnish Ave",
    "sg:city":"Pendleton",
    "sg:classifiers":[
        {
            "category":"Building & Trades",
            "subcategory":"Construction",
            "type":"Services"
        }
    ],
    "sg:phone":"+1 541 276 6352",
    "sg:postcode":"97801",
    "sg:province":"OR",
    "sg:tags":[
        "concrete",
        "contractor"
    ],
    "wof:name":"Ellinger Larri Construction",
    "wof:placetype":"venue"
},
  "geometry": {"coordinates":[-118.797319,45.676555],"type":"Point"}
}