{
  "type": "Feature",
  "properties": {
    "addr:full":"7715 Thurston Rd Springfield OR 97478",
    "addr:housenumber":"7715",
    "addr:postcode":"97478",
    "addr:street":"Thurston Rd",
    "iso:country":"US",
    "sg:address":"7715 Thurston Rd",
    "sg:city":"Springfield",
    "sg:classifiers":[
        {
            "category":"Autos & Motor Vehicles",
            "subcategory":"Boat Sales",
            "type":"Retail Goods"
        },
        {
            "category":"Recreation",
            "type":"Entertainment"
        }
    ],
    "sg:phone":"+1 541 726 6078",
    "sg:postcode":"97478",
    "sg:province":"OR",
    "sg:tags":[
        "rafts"
    ],
    "wof:name":"McKenzie River Rafting Company",
    "wof:placetype":"venue"
},
  "geometry": {"coordinates":[-122.885099,44.052901],"type":"Point"}
}