{
  "type": "Feature",
  "properties": {
    "addr:full":"1428 Eugene St Hood River OR 97031",
    "addr:housenumber":"1428",
    "addr:postcode":"97031",
    "addr:street":"Eugene St",
    "iso:country":"US",
    "sg:address":"1428 Eugene St",
    "sg:city":"Hood River",
    "sg:classifiers":[
        {
            "category":"Home & Garden",
            "subcategory":"Household Appliances",
            "type":"Retail Goods"
        }
    ],
    "sg:phone":"+1 541 386 1202",
    "sg:postcode":"97031",
    "sg:province":"OR",
    "wof:name":"Aerus Electrolux",
    "wof:placetype":"venue"
},
  "geometry": {"coordinates":[-121.52676200000001,45.706528],"type":"Point"}
}