{
  "type": "Feature",
  "properties": {
    "addr:full":"87 NW 9th St Ontario OR 97914",
    "addr:housenumber":"87",
    "addr:postcode":"97914",
    "addr:street":"Nw 9Th St",
    "iso:country":"US",
    "sg:address":"87 NW 9th St",
    "sg:city":"Ontario",
    "sg:classifiers":[
        {
            "category":"Professional",
            "subcategory":"Accounting & Tax Preparation",
            "type":"Services"
        }
    ],
    "sg:phone":"+1 541 889 6757",
    "sg:postcode":"97914",
    "sg:province":"OR",
    "sg:tags":[
        "return"
    ],
    "wof:name":"Dickenson Tax Service",
    "wof:placetype":"venue"
},
  "geometry": {"coordinates":[-116.973949,44.029482],"type":"Point"}
}