{
  "type": "Feature",
  "properties": {
    "iso:country":"US",
    "sg:address":"200 SE Hailey Ave",
    "sg:city":"Pendleton",
    "sg:classifiers":[
        {
            "category":"Professional",
            "subcategory":"Accounting & Tax Preparation",
            "type":"Services"
        }
    ],
    "sg:phone":"+1 541 276 9426",
    "sg:postcode":"97801",
    "sg:province":"OR",
    "sg:tags":[
        "accountant"
    ],
    "wof:name":"William R Mc Clintock LLC",
    "wof:placetype":"venue"
},
  "geometry": {"coordinates":[-118.781472,45.668392],"type":"Point"}
}