{
  "type": "Feature",
  "properties": {
    "iso:country":"US",
    "sg:address":"1805 Silverton Rd NE",
    "sg:city":"Salem",
    "sg:classifiers":[
        {
            "category":"Real Estate",
            "subcategory":"Real Estate Agent",
            "type":"Services"
        }
    ],
    "sg:phone":"+1 503 391 6793",
    "sg:postcode":"97303",
    "sg:province":"OR",
    "wof:name":"A L Gibbs Estate Liquidators",
    "wof:placetype":"venue"
},
  "geometry": {"coordinates":[-123.008995,44.962476],"type":"Point"}
}