{
  "type": "Feature",
  "properties": {
    "iso:country":"US",
    "sg:address":"5530 NE 122nd Ave",
    "sg:city":"Portland",
    "sg:classifiers":[
        {
            "category":"Local Transit",
            "type":"Transportation"
        }
    ],
    "sg:phone":"+1 503 349 8677",
    "sg:postcode":"97230",
    "sg:province":"OR",
    "sg:tags":[
        "airport"
    ],
    "sg:website":"www.teetogreentransportation.com",
    "wof:name":"Tee To Green Transportation",
    "wof:placetype":"venue"
},
  "geometry": {"coordinates":[-122.534711,45.563568],"type":"Point"}
}