{
  "type": "Feature",
  "properties": {
    "iso:country":"US",
    "sg:address":"10765 SW Butner Rd",
    "sg:city":"Portland",
    "sg:classifiers":[
        {
            "category":"Professional",
            "type":"Services"
        }
    ],
    "sg:phone":"+1 503 292 9245",
    "sg:postcode":"97225",
    "sg:province":"OR",
    "wof:name":"Heavens Closet",
    "wof:placetype":"venue"
},
  "geometry": {"coordinates":[-122.79086599999999,45.512394],"type":"Point"}
}