{
  "type": "Feature",
  "properties": {
    "iso:country":"US",
    "sg:address":"3686 Windy Creek Rd",
    "sg:city":"Glendale",
    "sg:classifiers":[
        {
            "category":"Building & Trades",
            "subcategory":"Electrical",
            "type":"Services"
        }
    ],
    "sg:phone":"+1 541 832 2279",
    "sg:postcode":"97442",
    "sg:province":"OR",
    "sg:tags":[
        "electrical",
        "contractor"
    ],
    "wof:name":"Shepard Electric",
    "wof:placetype":"venue"
},
  "geometry": {"coordinates":[-123.371867,42.778729],"type":"Point"}
}