{
  "type": "Feature",
  "properties": {
    "iso:country":"US",
    "sg:address":"735 SW Stark St",
    "sg:city":"Portland",
    "sg:classifiers":[
        {
            "category":"Building & Trades",
            "subcategory":"Pest Control",
            "type":"Services"
        }
    ],
    "sg:phone":"+1 503 635 5801",
    "sg:postcode":"97205",
    "sg:province":"OR",
    "wof:name":"Halt Pest Control Inc",
    "wof:placetype":"venue"
},
  "geometry": {"coordinates":[-122.679239,45.521584],"type":"Point"}
}