{
  "type": "Feature",
  "properties": {
    "iso:country":"US",
    "sg:address":"730 Newmark Ave",
    "sg:city":"Coos Bay",
    "sg:classifiers":[
        {
            "category":"Government",
            "subcategory":"Post Office",
            "type":"Public Place"
        }
    ],
    "sg:phone":"+1 541 888 4021",
    "sg:postcode":"97420",
    "sg:province":"OR",
    "wof:name":"US Post Office",
    "wof:placetype":"venue"
},
  "geometry": {"coordinates":[-124.273713,43.392009],"type":"Point"}
}