{
  "type": "Feature",
  "properties": {
    "iso:country":"US",
    "sg:address":"92854 Floras Lake Rd",
    "sg:city":"Langlois",
    "sg:classifiers":[
        {
            "category":"Travel",
            "subcategory":"Hotels & Motels",
            "type":"Entertainment"
        }
    ],
    "sg:phone":"+1 541 348 2573",
    "sg:postcode":"97450",
    "sg:province":"OR",
    "sg:tags":[
        "breakfast",
        "accommodation",
        "bed"
    ],
    "wof:name":"Floras Lake House By The Sea",
    "wof:placetype":"venue"
},
  "geometry": {"coordinates":[-124.49649,42.897087],"type":"Point"}
}