{
  "type": "Feature",
  "properties": {
    "iso:country":"US",
    "sg:address":"17230 NE Sacramento St",
    "sg:city":"Portland",
    "sg:classifiers":[
        {
            "category":"Manufacturing",
            "subcategory":"Apparel",
            "type":"Manufacturing & Wholesale Goods"
        }
    ],
    "sg:phone":"+1 503 230 9480",
    "sg:postcode":"97230",
    "sg:province":"OR",
    "sg:tags":[
        "mfg"
    ],
    "wof:name":"Forresters Inc",
    "wof:placetype":"venue"
},
  "geometry": {"coordinates":[-122.480132,45.540493],"type":"Point"}
}