{
  "type": "Feature",
  "properties": {
    "iso:country":"US",
    "sg:address":"5175 Foxhaven Ct SE",
    "sg:city":"Salem",
    "sg:classifiers":[
        {
            "category":"Real Estate",
            "subcategory":"Real Estate Agent",
            "type":"Services"
        }
    ],
    "sg:phone":"+1 503 378 0447",
    "sg:postcode":"97306",
    "sg:province":"OR",
    "wof:name":"Vollmar & Assoc RE Appraisers",
    "wof:placetype":"venue"
},
  "geometry": {"coordinates":[-123.006284,44.880569],"type":"Point"}
}