{
  "type": "Feature",
  "properties": {
    "iso:country":"US",
    "sg:address":"4284 W 7th Ave",
    "sg:city":"Eugene",
    "sg:classifiers":[
        {
            "category":"Education",
            "subcategory":"Vocational School",
            "type":"Public Place"
        }
    ],
    "sg:phone":"+1 541 684 9004",
    "sg:postcode":"97402",
    "sg:province":"OR",
    "wof:name":"Cr Business Services",
    "wof:placetype":"venue"
},
  "geometry": {"coordinates":[-123.168182,44.051719],"type":"Point"}
}