{
  "type": "Feature",
  "properties": {
    "iso:country":"US",
    "sg:address":"27424 SE Eagle Creek Rd",
    "sg:city":"Estacada",
    "sg:classifiers":[
        {
            "category":"Professional",
            "subcategory":"Management & Consulting",
            "type":"Services"
        }
    ],
    "sg:phone":"+1 503 630 3111",
    "sg:postcode":"97023",
    "sg:province":"OR",
    "wof:name":"TT CMI",
    "wof:placetype":"venue"
},
  "geometry": {"coordinates":[-122.34335299999999,45.323812],"type":"Point"}
}