{
  "type": "Feature",
  "properties": {
    "addr:full":"7665 SW Florence Ln Portland OR 97223",
    "addr:housenumber":"7665",
    "addr:postcode":"97223",
    "addr:street":"Sw Florence Ln",
    "iso:country":"US",
    "sg:address":"7665 SW Florence Ln",
    "sg:city":"Portland",
    "sg:classifiers":[
        {
            "category":"Building & Trades",
            "subcategory":"Construction",
            "type":"Services"
        }
    ],
    "sg:phone":"+1 503 245 5496",
    "sg:postcode":"97223",
    "sg:province":"OR",
    "sg:tags":[
        "repairing",
        "remodeling",
        "contractor"
    ],
    "wof:name":"Tibor Construction",
    "wof:placetype":"venue"
},
  "geometry": {"coordinates":[-122.75388599999999,45.456802],"type":"Point"}
}