{
  "type": "Feature",
  "properties": {
    "iso:country":"US",
    "sg:address":"2043 SE 50th Ave",
    "sg:city":"Portland",
    "sg:classifiers":[
        {
            "category":"Sports & Exercise",
            "subcategory":"Gym",
            "type":"Entertainment"
        }
    ],
    "sg:phone":"+1 503 235 9642",
    "sg:postcode":"97215",
    "sg:province":"OR",
    "sg:tags":[
        "facility",
        "physical",
        "yoga",
        "fitness"
    ],
    "sg:website":"www.yogaunioncwc.com",
    "wof:name":"Yoga Union",
    "wof:placetype":"venue"
},
  "geometry": {"coordinates":[-122.611295,45.508173],"type":"Point"}
}