{
  "type": "Feature",
  "properties": {
    "iso:country":"US",
    "sg:address":"968 NW Division St",
    "sg:city":"Gresham",
    "sg:classifiers":[
        {
            "category":"Organizations",
            "subcategory":"Non-profit Organization",
            "type":"Services"
        }
    ],
    "sg:phone":"+1 503 666 0541",
    "sg:postcode":"97030",
    "sg:province":"OR",
    "sg:tags":[
        "disability"
    ],
    "sg:website":"www.serpenterprises.com",
    "wof:name":"Serp Enterprises",
    "wof:placetype":"venue"
},
  "geometry": {"coordinates":[-122.442357,45.504439],"type":"Point"}
}