{
  "type": "Feature",
  "properties": {
    "iso:country":"US",
    "sg:address":"2303 E Burnside St",
    "sg:city":"Portland",
    "sg:classifiers":[
        {
            "category":"Social Services",
            "type":"Services"
        }
    ],
    "sg:phone":"+1 503 287 1100",
    "sg:postcode":"97214",
    "sg:province":"OR",
    "wof:name":"Christina Rose MA",
    "wof:placetype":"venue"
},
  "geometry": {"coordinates":[-122.642166,45.522945],"type":"Point"}
}