{
  "type": "Feature",
  "properties": {
    "iso:country":"US",
    "sg:address":"16211 NE Glisan St",
    "sg:city":"Portland",
    "sg:classifiers":[
        {
            "category":"Retail",
            "subcategory":"Auto Repair",
            "type":"Services"
        }
    ],
    "sg:phone":"+1 503 408 8069",
    "sg:postcode":"97230",
    "sg:province":"OR",
    "sg:tags":[
        "repairing",
        "automobile"
    ],
    "wof:name":"Glisan & 162nd Avenue",
    "wof:placetype":"venue"
},
  "geometry": {"coordinates":[-122.493357,45.526492],"type":"Point"}
}