{
  "type": "Feature",
  "properties": {
    "iso:country":"US",
    "sg:address":"40 Workman Dr",
    "sg:city":"Woodburn",
    "sg:classifiers":[
        {
            "category":"Building & Trades",
            "subcategory":"Construction",
            "type":"Services"
        }
    ],
    "sg:phone":"+1 503 981 0489",
    "sg:postcode":"97071",
    "sg:province":"OR",
    "sg:tags":[
        "residential"
    ],
    "wof:name":"Alex Kuzmin Construction",
    "wof:placetype":"venue"
},
  "geometry": {"coordinates":[-122.862881,45.144318],"type":"Point"}
}