{
  "type": "Feature",
  "properties": {
    "addr:full":"14925 Lee Rd Dallas OR 97338",
    "addr:housenumber":"14925",
    "addr:postcode":"97338",
    "addr:street":"Lee Rd",
    "iso:country":"US",
    "sg:address":"14925 Lee Rd",
    "sg:city":"Dallas",
    "sg:classifiers":[
        {
            "category":"Building & Trades",
            "subcategory":"Landscaping Services",
            "type":"Services"
        }
    ],
    "sg:phone":"+1 503 623 1963",
    "sg:postcode":"97338",
    "sg:province":"OR",
    "wof:name":"Burbank Douglas Log & Tree Svc",
    "wof:placetype":"venue"
},
  "geometry": {"coordinates":[-123.336771,44.879861],"type":"Point"}
}