{
  "type": "Feature",
  "properties": {
    "iso:country":"US",
    "sg:address":"1000 Valley River Way",
    "sg:city":"Eugene",
    "sg:classifiers":[
        {
            "category":"Travel",
            "subcategory":"Hotels & Motels",
            "type":"Entertainment"
        }
    ],
    "sg:phone":"+1 541 743 1000",
    "sg:postcode":"97401",
    "sg:province":"OR",
    "sg:website":"www.valleyriverinn.com",
    "wof:name":"Valley River Inn",
    "wof:placetype":"venue"
},
  "geometry": {"coordinates":[-123.102908,44.066863],"type":"Point"}
}