{
  "type": "Feature",
  "properties": {
    "iso:country":"US",
    "sg:address":"1130 Nw 22nd Ave Ste 520",
    "sg:city":"Portland",
    "sg:classifiers":[
        {
            "category":"Health Services",
            "subcategory":"Doctor",
            "type":"Services"
        }
    ],
    "sg:phone":"+1 503 274 4800",
    "sg:postcode":"97210",
    "sg:province":"OR",
    "sg:tags":[
        "obstetrician",
        "gynecologist"
    ],
    "sg:website":"www.bridgeviewwomenshealth.com",
    "wof:name":"Lohr Dafna Md",
    "wof:placetype":"venue"
},
  "geometry": {"coordinates":[-122.696144,45.531072],"type":"Point"}
}