{
  "type": "Feature",
  "properties": {
    "addr:full":"101 Shively Creek Rd Days Creek OR 97417",
    "addr:housenumber":"101",
    "addr:postcode":"97417",
    "addr:street":"Shively Creek Rd",
    "iso:country":"US",
    "sg:address":"101 Shively Creek Rd",
    "sg:city":"Days Creek",
    "sg:classifiers":[
        {
            "category":"Manufacturing",
            "subcategory":"Lumber",
            "type":"Manufacturing & Wholesale Goods"
        }
    ],
    "sg:phone":"+1 541 825 3871",
    "sg:postcode":"97417",
    "sg:province":"OR",
    "sg:tags":[
        "fire",
        "fighting"
    ],
    "wof:name":"Jerry Perkins",
    "wof:placetype":"venue"
},
  "geometry": {"coordinates":[-123.170782,42.970659],"type":"Point"}
}