{
  "type": "Feature",
  "properties": {
    "iso:country":"US",
    "sg:address":"2337 NW York St",
    "sg:city":"Portland",
    "sg:classifiers":[
        {
            "category":"Freight",
            "type":"Transportation"
        }
    ],
    "sg:phone":"+1 503 226 7624",
    "sg:postcode":"97210",
    "sg:province":"OR",
    "sg:tags":[
        "warehouse"
    ],
    "wof:name":"Gg Warehouse",
    "wof:placetype":"venue"
},
  "geometry": {"coordinates":[-122.699439,45.539123],"type":"Point"}
}