{
  "type": "Feature",
  "properties": {
    "addr:full":"45690 NW Strohmayer Rd Forest Grove OR 97116",
    "addr:housenumber":"45690",
    "addr:postcode":"97116",
    "addr:street":"Nw Strohmayer Rd",
    "iso:country":"US",
    "sg:address":"45690 NW Strohmayer Rd",
    "sg:city":"Forest Grove",
    "sg:classifiers":[
        {
            "category":"Retail",
            "subcategory":"Laundry & Dry Cleaning",
            "type":"Services"
        }
    ],
    "sg:phone":"+1 503 359 9618",
    "sg:postcode":"97116",
    "sg:province":"OR",
    "sg:tags":[
        "cleaners",
        "rug",
        "carpet"
    ],
    "wof:name":"Ace Carpet & Upholstery Clng",
    "wof:placetype":"venue"
},
  "geometry": {"coordinates":[-123.147018,45.598644],"type":"Point"}
}