{
  "type": "Feature",
  "properties": {
    "iso:country":"US",
    "sg:address":"1035 Young St",
    "sg:city":"Woodburn",
    "sg:classifiers":[
        {
            "category":"Insurance",
            "subcategory":"Insurance Agent",
            "type":"Services"
        }
    ],
    "sg:phone":"+1 503 981 9444",
    "sg:postcode":"97071",
    "sg:province":"OR",
    "sg:tags":[
        "agency"
    ],
    "wof:name":"State Farm Insurance",
    "wof:placetype":"venue"
},
  "geometry": {"coordinates":[-122.84544,45.13762],"type":"Point"}
}