{
  "type": "Feature",
  "properties": {
    "iso:country":"US",
    "sg:address":"3257 Northgate Ave NE",
    "sg:city":"Salem",
    "sg:classifiers":[
        {
            "category":"Insurance",
            "subcategory":"Insurance Agent",
            "type":"Services"
        }
    ],
    "sg:phone":"+1 503 581 7779",
    "sg:postcode":"97301",
    "sg:province":"OR",
    "wof:name":"Allstate Insurance",
    "wof:placetype":"venue"
},
  "geometry": {"coordinates":[-122.996296,44.973346],"type":"Point"}
}