{
  "type": "Feature",
  "properties": {
    "iso:country":"US",
    "sg:address":"1244 Walnut St",
    "sg:city":"Eugene",
    "sg:classifiers":[
        {
            "category":"Social Services",
            "type":"Services"
        }
    ],
    "sg:phone":"+1 541 484 5694",
    "sg:postcode":"97403",
    "sg:province":"OR",
    "sg:tags":[
        "health"
    ],
    "wof:name":"PHD P Stephen Schweitzer",
    "wof:placetype":"venue"
},
  "geometry": {"coordinates":[-123.061559,44.045128],"type":"Point"}
}