{
  "type": "Feature",
  "properties": {
    "iso:country":"US",
    "sg:address":"57120 Hazen Rd",
    "sg:city":"Warren",
    "sg:classifiers":[
        {
            "category":"Building & Trades",
            "subcategory":"Plumbing",
            "type":"Services"
        }
    ],
    "sg:phone":"+1 503 397 4056",
    "sg:postcode":"97053",
    "sg:province":"OR",
    "sg:tags":[
        "refrigeration",
        "contractor"
    ],
    "wof:name":"Fitzgerald Refrigeration",
    "wof:placetype":"venue"
},
  "geometry": {"coordinates":[-122.877774,45.821747],"type":"Point"}
}