{
  "type": "Feature",
  "properties": {
    "iso:country":"US",
    "sg:address":"1852 NE Yellowstone Ln",
    "sg:city":"Bend",
    "sg:classifiers":[
        {
            "category":"Retail",
            "subcategory":"Laundry & Dry Cleaning",
            "type":"Services"
        }
    ],
    "sg:phone":"+1 541 318 1203",
    "sg:postcode":"97701",
    "sg:province":"OR",
    "sg:tags":[
        "cleaners",
        "rug",
        "carpet"
    ],
    "wof:name":"Extreme Clean",
    "wof:placetype":"venue"
},
  "geometry": {"coordinates":[-121.276793,44.082813],"type":"Point"}
}