{
  "type": "Feature",
  "properties": {
    "iso:country":"US",
    "sg:address":"1813 Columbia Blvd",
    "sg:city":"Saint Helens",
    "sg:classifiers":[
        {
            "category":"Professional",
            "subcategory":"Computer Services",
            "type":"Services"
        }
    ],
    "sg:phone":"+1 503 397 1151",
    "sg:postcode":"97051",
    "sg:province":"OR",
    "sg:tags":[
        "datum",
        "programing",
        "custom"
    ],
    "wof:name":"Ede Solutions",
    "wof:placetype":"venue"
},
  "geometry": {"coordinates":[-122.815882,45.85892],"type":"Point"}
}