{
  "type": "Feature",
  "properties": {
    "iso:country":"US",
    "sg:address":"1015 SW Tangent St",
    "sg:city":"Portland",
    "sg:classifiers":[
        {
            "category":"Professional",
            "subcategory":"Business Services",
            "type":"Services"
        }
    ],
    "sg:phone":"+1 503 227 1730",
    "sg:postcode":"97201",
    "sg:province":"OR",
    "sg:tags":[
        "interior",
        "consultant",
        "design",
        "decorator"
    ],
    "wof:name":"Interiors Of Elegance",
    "wof:placetype":"venue"
},
  "geometry": {"coordinates":[-122.688622,45.505037],"type":"Point"}
}