{
  "type": "Feature",
  "properties": {
    "iso:country":"US",
    "sg:address":"360 NW Vermont St",
    "sg:city":"Bend",
    "sg:classifiers":[
        {
            "category":"Social Services",
            "type":"Services"
        }
    ],
    "sg:phone":"+1 541 389 1269",
    "sg:postcode":"97701",
    "sg:province":"OR",
    "sg:tags":[
        "counselor",
        "marriage",
        "family"
    ],
    "wof:name":"Gary Matlick Counseling Svc",
    "wof:placetype":"venue"
},
  "geometry": {"coordinates":[-121.311594,44.061907],"type":"Point"}
}