{
  "type": "Feature",
  "properties": {
    "iso:country":"US",
    "sg:address":"5307 NE Cesar E Chavez Blvd",
    "sg:city":"Portland",
    "sg:classifiers":[
        {
            "category":"Home & Garden",
            "subcategory":"Home Furnishings",
            "type":"Retail Goods"
        },
        {
            "category":"Manufacturing",
            "subcategory":"Glass & Minerals",
            "type":"Manufacturing & Wholesale Goods"
        }
    ],
    "sg:phone":"+1 503 249 2143",
    "sg:postcode":"97211",
    "sg:province":"OR",
    "sg:tags":[
        "housewares",
        "crystal",
        "glassware",
        "china"
    ],
    "wof:name":"Princess House Incorporated",
    "wof:placetype":"venue"
},
  "geometry": {"coordinates":[-122.623459,45.561355],"type":"Point"}
}