{
  "type": "Feature",
  "properties": {
    "addr:full":"69568 Heritage Ln Cove OR 97824",
    "addr:housenumber":"69568",
    "addr:postcode":"97824",
    "addr:street":"Heritage Ln Cove",
    "iso:country":"US",
    "sg:address":"69568 Heritage Ln",
    "sg:city":"Cove",
    "sg:classifiers":[
        {
            "category":"Building & Trades",
            "subcategory":"Construction",
            "type":"Services"
        }
    ],
    "sg:phone":"+1 541 568 0108",
    "sg:postcode":"97824",
    "sg:province":"OR",
    "sg:tags":[
        "general",
        "contractor"
    ],
    "wof:name":"Metsker Heritage Inc",
    "wof:placetype":"venue"
},
  "geometry": {"coordinates":[-117.801553,45.298891],"type":"Point"}
}