{
  "type": "Feature",
  "properties": {
    "iso:country":"US",
    "sg:address":"5857 SE Yamhill St",
    "sg:city":"Portland",
    "sg:classifiers":[
        {
            "category":"Professional",
            "subcategory":"Business Services",
            "type":"Services"
        }
    ],
    "sg:phone":"+1 503 736 1242",
    "sg:postcode":"97215",
    "sg:province":"OR",
    "wof:name":"Lindemann Design",
    "wof:placetype":"venue"
},
  "geometry": {"coordinates":[-122.602315,45.516196],"type":"Point"}
}