{
  "type": "Feature",
  "properties": {
    "iso:country":"US",
    "sg:address":"59255 NW Cedarbrook Ln",
    "sg:city":"Gales Creek",
    "sg:classifiers":[
        {
            "category":"Manufacturing",
            "subcategory":"Furniture",
            "type":"Manufacturing & Wholesale Goods"
        }
    ],
    "sg:phone":"+1 503 357 5515",
    "sg:postcode":"97117",
    "sg:province":"OR",
    "sg:tags":[
        "household",
        "wood",
        "mfg"
    ],
    "wof:name":"Crowell Woodcraft",
    "wof:placetype":"venue"
},
  "geometry": {"coordinates":[-123.288612,45.650824],"type":"Point"}
}