{
  "type": "Feature",
  "properties": {
    "iso:country":"US",
    "sg:address":"116 SE 4th Ave",
    "sg:city":"Estacada",
    "sg:classifiers":[
        {
            "category":"Restaurant",
            "type":"Food & Drink"
        }
    ],
    "sg:phone":"+1 503 630 3208",
    "sg:postcode":"97023",
    "sg:province":"OR",
    "sg:tags":[
        "eating"
    ],
    "wof:name":"Jen Jen Safari Rest Lounge",
    "wof:placetype":"venue"
},
  "geometry": {"coordinates":[-122.335071,45.286649],"type":"Point"}
}