{
  "type": "Feature",
  "properties": {
    "iso:country":"US",
    "sg:address":"3203 Vandenberg Rd",
    "sg:city":"Klamath Falls",
    "sg:classifiers":[
        {
            "category":"Organizations",
            "subcategory":"Non-profit Organization",
            "type":"Services"
        }
    ],
    "sg:phone":"+1 541 885 8131",
    "sg:postcode":"97603",
    "sg:province":"OR",
    "sg:tags":[
        "info",
        "addiction",
        "abuse",
        "treatment",
        "drug"
    ],
    "wof:name":"Consortium",
    "wof:placetype":"venue"
},
  "geometry": {"coordinates":[-121.750564,42.223186],"type":"Point"}
}