{
  "type": "Feature",
  "properties": {
    "iso:country":"US",
    "sg:address":"8578 N Tioga Ave",
    "sg:city":"Portland",
    "sg:classifiers":[
        {
            "category":"Shopping",
            "subcategory":"Gifts & Souvenirs",
            "type":"Retail Goods"
        }
    ],
    "sg:phone":"+1 503 285 2149",
    "sg:postcode":"97203",
    "sg:province":"OR",
    "wof:name":"Passion Parties By Madeline",
    "wof:placetype":"venue"
},
  "geometry": {"coordinates":[-122.74321999999999,45.590687],"type":"Point"}
}