{
  "type": "Feature",
  "properties": {
    "iso:country":"US",
    "sg:address":"5500 SW Dosch Rd",
    "sg:city":"Portland",
    "sg:classifiers":[
        {
            "category":"Place Of Worship",
            "subcategory":"Church",
            "type":"Public Place"
        },
        {
            "category":"Place Of Worship",
            "type":"Public Place"
        }
    ],
    "sg:phone":"+1 503 246 9482",
    "sg:postcode":"97239",
    "sg:province":"OR",
    "sg:tags":[
        "churches-evangelical",
        "churches-covenant",
        "lutheran",
        "covenant",
        "churches-lutheran-evangelical",
        "america",
        "churches-lutheran"
    ],
    "wof:name":"Latvian Lutheran Church",
    "wof:placetype":"venue"
},
  "geometry": {"coordinates":[-122.708237,45.483669],"type":"Point"}
}