{
  "type": "Feature",
  "properties": {
    "addr:full":"15155 SW Opal Dr Beaverton OR 97007",
    "addr:housenumber":"15155",
    "addr:postcode":"97007",
    "addr:street":"Sw Opal Dr",
    "iso:country":"US",
    "sg:address":"15155 SW Opal Dr",
    "sg:city":"Beaverton",
    "sg:classifiers":[
        {
            "category":"Wholesale",
            "subcategory":"Groceries",
            "type":"Manufacturing & Wholesale Goods"
        }
    ],
    "sg:phone":"+1 503 888 0302",
    "sg:postcode":"97007",
    "sg:province":"OR",
    "sg:tags":[
        "snack"
    ],
    "wof:name":"Golden Snacks",
    "wof:placetype":"venue"
},
  "geometry": {"coordinates":[-122.83241700000001,45.451312],"type":"Point"}
}