{
  "type": "Feature",
  "properties": {
    "addr:full":"2009 NE 79th Ave Portland OR 97213",
    "addr:housenumber":"2009",
    "addr:postcode":"97213",
    "addr:street":"Ne 79Th Ave",
    "iso:country":"US",
    "sg:address":"2009 NE 79th Ave",
    "sg:city":"Portland",
    "sg:classifiers":[
        {
            "category":"Insurance",
            "subcategory":"Insurance Agent",
            "type":"Services"
        }
    ],
    "sg:phone":"+1 503 253 5035",
    "sg:postcode":"97213",
    "sg:province":"OR",
    "wof:name":"Allied Insurance",
    "wof:placetype":"venue"
},
  "geometry": {"coordinates":[-122.58216400000001,45.536144],"type":"Point"}
}