{
  "type": "Feature",
  "properties": {
    "iso:country":"US",
    "sg:address":"2009 NE 79th Ave",
    "sg:city":"Portland",
    "sg:classifiers":[
        {
            "category":"Insurance",
            "subcategory":"Insurance Agent",
            "type":"Services"
        }
    ],
    "sg:phone":"+1 503 253 5035",
    "sg:postcode":"97213",
    "sg:province":"OR",
    "wof:name":"Allied Insurance",
    "wof:placetype":"venue"
},
  "geometry": {"coordinates":[-122.582164,45.536144],"type":"Point"}
}