{
  "type": "Feature",
  "properties": {
    "iso:country":"US",
    "sg:address":"40264 SE Trubel Rd",
    "sg:city":"Sandy",
    "sg:classifiers":[
        {
            "category":"Personal",
            "subcategory":"Beauty Salon",
            "type":"Services"
        }
    ],
    "sg:phone":"+1 503 826 0304",
    "sg:postcode":"97055",
    "sg:province":"OR",
    "sg:tags":[
        "shop"
    ],
    "wof:name":"A & G Style Inc",
    "wof:placetype":"venue"
},
  "geometry": {"coordinates":[-122.249392,45.374927],"type":"Point"}
}