{
  "type": "Feature",
  "properties": {
    "iso:country":"US",
    "sg:address":"327 NW Greenwood Ave",
    "sg:city":"Bend",
    "sg:classifiers":[
        {
            "category":"Professional",
            "subcategory":"Lawyer & Legal Services",
            "type":"Services"
        }
    ],
    "sg:phone":"+1 541 382 7900",
    "sg:postcode":"97701",
    "sg:province":"OR",
    "wof:name":"Dwyer Shlsnger Dvilleuve Attys",
    "wof:placetype":"venue"
},
  "geometry": {"coordinates":[-121.312253,44.060238],"type":"Point"}
}