{
  "type": "Feature",
  "properties": {
    "iso:country":"US",
    "sg:address":"17900 NW Fieldstone Dr",
    "sg:city":"Beaverton",
    "sg:phone":"+1 503 629 7290",
    "sg:postcode":"97006",
    "sg:province":"OR",
    "wof:name":"Paul Ramona",
    "wof:placetype":"venue"
},
  "geometry": {"coordinates":[-122.86140399999999,45.528999],"type":"Point"}
}