{
  "type": "Feature",
  "properties": {
    "iso:country":"US",
    "sg:address":"102 NE 128th Ave",
    "sg:city":"Portland",
    "sg:classifiers":[
        {
            "category":"Retail",
            "subcategory":"Repair Shop",
            "type":"Services"
        }
    ],
    "sg:phone":"+1 503 254 7917",
    "sg:postcode":"97230",
    "sg:province":"OR",
    "sg:tags":[
        "electrical"
    ],
    "wof:name":"Schimpf Enterprises",
    "wof:placetype":"venue"
},
  "geometry": {"coordinates":[-122.53159100000001,45.525593],"type":"Point"}
}