{
  "type": "Feature",
  "properties": {
    "iso:country":"US",
    "sg:address":"20076 S Molalla Ave",
    "sg:city":"Oregon City",
    "sg:classifiers":[
        {
            "category":"Building & Trades",
            "subcategory":"Construction",
            "type":"Services"
        }
    ],
    "sg:phone":"+1 503 657 7794",
    "sg:postcode":"97045",
    "sg:province":"OR",
    "sg:tags":[
        "company",
        "landscape"
    ],
    "wof:name":"A Finsihing Touch Landscape",
    "wof:placetype":"venue"
},
  "geometry": {"coordinates":[-122.573852,45.31605],"type":"Point"}
}