{
  "type": "Feature",
  "properties": {
    "iso:country":"US",
    "sg:address":"141 Ivy Dr",
    "sg:city":"Cave Junction",
    "sg:classifiers":[
        {
            "category":"Building & Trades",
            "subcategory":"Construction",
            "type":"Services"
        }
    ],
    "sg:phone":"+1 541 596 2197",
    "sg:postcode":"97523",
    "sg:province":"OR",
    "sg:tags":[
        "excavation",
        "contractor"
    ],
    "wof:name":"M & M Backhoe Service",
    "wof:placetype":"venue"
},
  "geometry": {"coordinates":[-123.654318,42.114686],"type":"Point"}
}