{
  "type": "Feature",
  "properties": {
    "iso:country":"US",
    "sg:address":"1790 NW Hughwood Ave",
    "sg:city":"Roseburg",
    "sg:classifiers":[
        {
            "category":"Insurance",
            "subcategory":"Insurance Agent",
            "type":"Services"
        }
    ],
    "sg:phone":"+1 541 673 7405",
    "sg:postcode":"97470",
    "sg:province":"OR",
    "wof:name":"Kelley Janzen State Farm Insur",
    "wof:placetype":"venue"
},
  "geometry": {"coordinates":[-123.38168899999999,43.2362],"type":"Point"}
}