{
  "type": "Feature",
  "properties": {
    "addr:full":"127 Broadalbin St NW Albany OR 97321",
    "addr:housenumber":"127",
    "addr:postcode":"97321",
    "addr:street":"Broadalbin St Nw",
    "iso:country":"US",
    "sg:address":"127 Broadalbin St NW",
    "sg:city":"Albany",
    "sg:classifiers":[
        {
            "category":"Organizations",
            "subcategory":"Community Association",
            "type":"Services"
        }
    ],
    "sg:phone":"+1 541 926 6622",
    "sg:postcode":"97321",
    "sg:province":"OR",
    "sg:tags":[
        "fraternal"
    ],
    "wof:name":"Fraternal Order Of Eagles",
    "wof:placetype":"venue"
},
  "geometry": {"coordinates":[-123.10751500000001,44.637714],"type":"Point"}
}