{
  "type": "Feature",
  "properties": {
    "addr:full":"13836 NE Sandy Blvd Portland OR 97230",
    "addr:housenumber":"13836",
    "addr:postcode":"97230",
    "addr:street":"Ne Sandy Blvd",
    "iso:country":"US",
    "sg:address":"13836 NE Sandy Blvd",
    "sg:city":"Portland",
    "sg:classifiers":[
        {
            "category":"Professional",
            "subcategory":"Accounting & Tax Preparation",
            "type":"Services"
        }
    ],
    "sg:phone":"+1 503 262 8192",
    "sg:postcode":"97230",
    "sg:province":"OR",
    "sg:tags":[
        "return",
        "filing"
    ],
    "wof:name":"H & R Block Tax Svc",
    "wof:placetype":"venue"
},
  "geometry": {"coordinates":[-122.52143599999999,45.554498],"type":"Point"}
}