{
  "type": "Feature",
  "properties": {
    "addr:full":"6107 SE 82nd Ave Portland OR 97266",
    "addr:housenumber":"6107",
    "addr:postcode":"97266",
    "addr:street":"Se 82Nd Ave",
    "iso:country":"US",
    "sg:address":"6107 SE 82nd Ave",
    "sg:city":"Portland",
    "sg:classifiers":[
        {
            "category":"Retail",
            "subcategory":"Auto Rental",
            "type":"Services"
        }
    ],
    "sg:phone":"+1 503 772 4750",
    "sg:postcode":"97266",
    "sg:province":"OR",
    "sg:tags":[
        "renting",
        "automobile"
    ],
    "wof:name":"Hertz Rent A Car",
    "wof:placetype":"venue"
},
  "geometry": {"coordinates":[-122.579106,45.478279],"type":"Point"}
}