{
  "type": "Feature",
  "properties": {
    "addr:full":"10900 SE 21st Ave Portland OR 97222",
    "addr:postcode":"10900;97222",
    "addr:street":"Se 21St Ave",
    "iso:country":"US",
    "sg:address":"10900 SE 21st Ave",
    "sg:city":"Portland",
    "sg:phone":"+1 503 238 3255",
    "sg:postcode":"97222",
    "sg:province":"OR",
    "sg:website":"https://www.chase.com/",
    "wof:name":"CHASE Bank",
    "wof:placetype":"venue"
},
  "geometry": {"coordinates":[-122.640182,45.444149],"type":"Point"}
}