{
  "type": "Feature",
  "properties": {
    "iso:country":"US",
    "sg:address":"30684 Peterson Rd",
    "sg:city":"Corvallis",
    "sg:classifiers":[
        {
            "category":"Professional",
            "subcategory":"Secretarial Services",
            "type":"Services"
        }
    ],
    "sg:phone":"+1 541 929 6708",
    "sg:postcode":"97333",
    "sg:province":"OR",
    "sg:tags":[
        "court"
    ],
    "wof:name":"Certified Court Reporting",
    "wof:placetype":"venue"
},
  "geometry": {"coordinates":[-123.37629800000001,44.469734],"type":"Point"}
}