{
  "type": "Feature",
  "properties": {
    "addr:full":"4200 Sunnyview Rd NE Salem OR 97305",
    "addr:housenumber":"4200",
    "addr:postcode":"97305",
    "addr:street":"Sunnyview Rd Ne",
    "iso:country":"US",
    "sg:address":"4200 Sunnyview Rd NE",
    "sg:city":"Salem",
    "sg:classifiers":[
        {
            "category":"Real Estate",
            "subcategory":"Real Estate Agent",
            "type":"Services"
        }
    ],
    "sg:phone":"+1 503 362 0525",
    "sg:postcode":"97305",
    "sg:province":"OR",
    "wof:name":"Sunnyview Village Apartments",
    "wof:placetype":"venue"
},
  "geometry": {"coordinates":[-122.978506,44.953942],"type":"Point"}
}