{
  "type": "Feature",
  "properties": {
    "addr:full":"3432 SW 126th Ave Beaverton OR 97005",
    "addr:housenumber":"3432",
    "addr:postcode":"97005",
    "addr:street":"Sw 126Th Ave",
    "iso:country":"US",
    "sg:address":"3432 SW 126th Ave",
    "sg:city":"Beaverton",
    "sg:classifiers":[
        {
            "category":"Building & Trades",
            "subcategory":"Locksmith",
            "type":"Services"
        }
    ],
    "sg:phone":"+1 503 715 3884",
    "sg:postcode":"97005",
    "sg:province":"OR",
    "sg:tags":[
        "key"
    ],
    "wof:name":"A-1 Locksmith",
    "wof:placetype":"venue"
},
  "geometry": {"coordinates":[-122.80646400000001,45.495074],"type":"Point"}
}