{
  "type": "Feature",
  "properties": {
    "iso:country":"US",
    "sg:address":"3550 Indiana Ave",
    "sg:city":"Baker City",
    "sg:classifiers":[
        {
            "category":"Building & Trades",
            "subcategory":"Construction",
            "type":"Services"
        }
    ],
    "sg:phone":"+1 541 523 6058",
    "sg:postcode":"97814",
    "sg:province":"OR",
    "sg:tags":[
        "downspouts",
        "gutter"
    ],
    "wof:name":"Four Seasons Insulation",
    "wof:placetype":"venue"
},
  "geometry": {"coordinates":[-117.85011900000001,44.767288],"type":"Point"}
}