{
  "type": "Feature",
  "properties": {
    "addr:full":"939 SE Alder St Portland OR 97214",
    "addr:housenumber":"939",
    "addr:postcode":"97214",
    "addr:street":"Se Alder St",
    "iso:country":"US",
    "sg:address":"939 SE Alder St",
    "sg:city":"Portland",
    "sg:classifiers":[
        {
            "category":"Professional",
            "type":"Services"
        }
    ],
    "sg:phone":"+1 503 417 8615",
    "sg:postcode":"97214",
    "sg:province":"OR",
    "sg:tags":[
        "establishment"
    ],
    "wof:name":"Pod 22",
    "wof:placetype":"venue"
},
  "geometry": {"coordinates":[-122.655942,45.517999],"type":"Point"}
}