{
  "type": "Feature",
  "properties": {
    "addr:full":"3141 SW 176th Ave Beaverton OR 97006",
    "addr:housenumber":"3141",
    "addr:postcode":"97006",
    "addr:street":"Sw 176Th Ave",
    "iso:country":"US",
    "sg:address":"3141 SW 176th Ave",
    "sg:city":"Beaverton",
    "sg:classifiers":[
        {
            "category":"Manufacturing",
            "subcategory":"Furniture",
            "type":"Manufacturing & Wholesale Goods"
        }
    ],
    "sg:phone":"+1 503 259 0513",
    "sg:postcode":"97006",
    "sg:province":"OR",
    "sg:tags":[
        "manufacture",
        "case",
        "outdoor",
        "plastic",
        "literature",
        "display"
    ],
    "wof:name":"Display Box Inc",
    "wof:placetype":"venue"
},
  "geometry": {"coordinates":[-122.859133,45.497128],"type":"Point"}
}