{
  "type": "Feature",
  "properties": {
    "addr:full":"16555 SE Sunridge Ln Portland OR 97267",
    "addr:postcode":"16555;97267",
    "addr:street":"Se Sunridge Ln",
    "iso:country":"US",
    "sg:address":"16555 SE Sunridge Ln",
    "sg:city":"Portland",
    "sg:classifiers":[
        {
            "category":"Building & Trades",
            "subcategory":"Cleaning & Sanitation",
            "type":"Services"
        }
    ],
    "sg:phone":"+1 503 654 6340",
    "sg:postcode":"97267",
    "sg:province":"OR",
    "sg:tags":[
        "maintenance"
    ],
    "wof:name":"Sterling Janitorial Maintenanc",
    "wof:placetype":"venue"
},
  "geometry": {"coordinates":[-122.58918300000001,45.402925],"type":"Point"}
}