{
  "type": "Feature",
  "properties": {
    "iso:country":"US",
    "sg:address":"1097 Cayuse Cir SE",
    "sg:city":"Salem",
    "sg:classifiers":[
        {
            "category":"Professional",
            "subcategory":"Lawyer & Legal Services",
            "type":"Services"
        }
    ],
    "sg:phone":"+1 503 559 1985",
    "sg:postcode":"97306",
    "sg:province":"OR",
    "sg:tags":[
        "attorney"
    ],
    "wof:name":"Eldon James (Jim) Harms, P.C.",
    "wof:placetype":"venue"
},
  "geometry": {"coordinates":[-123.03260899999999,44.864975],"type":"Point"}
}