{
  "type": "Feature",
  "properties": {
    "addr:full":"3633 NE 90th Ave Portland OR 97220",
    "addr:housenumber":"3633",
    "addr:postcode":"97220",
    "addr:street":"Ne 90Th Ave",
    "iso:country":"US",
    "sg:address":"3633 NE 90th Ave",
    "sg:city":"Portland",
    "sg:classifiers":[
        {
            "category":"Wholesale",
            "subcategory":"Meat",
            "type":"Manufacturing & Wholesale Goods"
        }
    ],
    "sg:phone":"+1 503 254 9855",
    "sg:postcode":"97220",
    "sg:province":"OR",
    "wof:name":"Don Lau Meat Service",
    "wof:placetype":"venue"
},
  "geometry": {"coordinates":[-122.570088,45.548188],"type":"Point"}
}