{
  "type": "Feature",
  "properties": {
    "addr:full":"970 SW Tara Ln Waldport OR 97394",
    "addr:housenumber":"970",
    "addr:postcode":"97394",
    "addr:street":"Sw Tara Ln",
    "iso:country":"US",
    "sg:address":"970 SW Tara Ln",
    "sg:city":"Waldport",
    "sg:classifiers":[
        {
            "category":"Manufacturing",
            "subcategory":"Buildings",
            "type":"Manufacturing & Wholesale Goods"
        },
        {
            "category":"Building & Trades",
            "subcategory":"Construction",
            "type":"Services"
        }
    ],
    "sg:phone":"+1 541 563 6762",
    "sg:postcode":"97394",
    "sg:province":"OR",
    "sg:tags":[
        "industrial",
        "altering",
        "builder",
        "system",
        "specialty",
        "heating",
        "contractor",
        "contractors-commercial",
        "home",
        "remodeling",
        "air conditioning"
    ],
    "wof:name":"Rudolph Construction",
    "wof:placetype":"venue"
},
  "geometry": {"coordinates":[-124.080755,44.41546],"type":"Point"}
}