{
  "type": "Feature",
  "properties": {
    "iso:country":"US",
    "sg:address":"15578 NW Overton Dr",
    "sg:city":"Beaverton",
    "sg:classifiers":[
        {
            "category":"Building & Trades",
            "subcategory":"Construction",
            "type":"Services"
        }
    ],
    "sg:phone":"+1 503 439 0627",
    "sg:postcode":"97006",
    "sg:province":"OR",
    "sg:tags":[
        "painter"
    ],
    "wof:name":"Adams Paint Design",
    "wof:placetype":"venue"
},
  "geometry": {"coordinates":[-122.838123,45.533722],"type":"Point"}
}