{
  "type": "Feature",
  "properties": {
    "iso:country":"US",
    "sg:address":"612 NE Savannah Dr",
    "sg:city":"Bend",
    "sg:classifiers":[
        {
            "category":"Real Estate",
            "subcategory":"Real Estate Agent",
            "type":"Services"
        }
    ],
    "sg:phone":"+1 541 318 1831",
    "sg:postcode":"97701",
    "sg:province":"OR",
    "wof:name":"Pacwest Realty Inc",
    "wof:placetype":"venue"
},
  "geometry": {"coordinates":[-121.274193,44.055873],"type":"Point"}
}