{
  "type": "Feature",
  "properties": {
    "iso:country":"US",
    "sg:address":"7736 SW Wimbledon Cir S",
    "sg:city":"Wilsonville",
    "sg:classifiers":[
        {
            "category":"Real Estate",
            "subcategory":"Real Estate Operator",
            "type":"Services"
        }
    ],
    "sg:phone":"+1 503 682 0401",
    "sg:postcode":"97070",
    "sg:province":"OR",
    "sg:tags":[
        "building",
        "apartment"
    ],
    "wof:name":"Birchwood Apts",
    "wof:placetype":"venue"
},
  "geometry": {"coordinates":[-122.756376,45.307258],"type":"Point"}
}