{
  "type": "Feature",
  "properties": {
    "iso:country":"US",
    "sg:address":"1212 Alder St",
    "sg:city":"La Grande",
    "sg:classifiers":[
        {
            "category":"Real Estate",
            "subcategory":"Architect",
            "type":"Services"
        }
    ],
    "sg:phone":"+1 541 962 6207",
    "sg:postcode":"97850",
    "sg:province":"OR",
    "sg:tags":[
        "home",
        "planning",
        "design"
    ],
    "wof:name":"Alpine Computer Drafting Svc",
    "wof:placetype":"venue"
},
  "geometry": {"coordinates":[-118.105367,45.322894],"type":"Point"}
}