{
  "type": "Feature",
  "properties": {
    "iso:country":"US",
    "sg:address":"2320 Lloyd Center",
    "sg:city":"Portland",
    "sg:classifiers":[
        {
            "category":"Cinema",
            "subcategory":"Movie Theater",
            "type":"Entertainment"
        }
    ],
    "sg:phone":"+1 503 335 3760",
    "sg:postcode":"97232",
    "sg:province":"OR",
    "wof:name":"Lloyd Mall 8",
    "wof:placetype":"venue"
},
  "geometry": {"coordinates":[-122.654488,45.531613],"type":"Point"}
}