{
  "type": "Feature",
  "properties": {
    "addr:full":"91909 Prairie Rd Junction City OR 97448",
    "addr:housenumber":"91909",
    "addr:postcode":"97448",
    "addr:street":"Prairie Rd",
    "iso:country":"US",
    "sg:address":"91909 Prairie Rd",
    "sg:city":"Junction City",
    "sg:classifiers":[
        {
            "category":"Building & Trades",
            "subcategory":"Plumbing",
            "type":"Services"
        }
    ],
    "sg:phone":"+1 541 607 9236",
    "sg:postcode":"97448",
    "sg:province":"OR",
    "sg:tags":[
        "repair",
        "contractor"
    ],
    "wof:name":"Bill Bailey Plumbing Inc",
    "wof:placetype":"venue"
},
  "geometry": {"coordinates":[-123.18727199999999,44.16358],"type":"Point"}
}