{
  "type": "Feature",
  "properties": {
    "addr:full":"11080 SW Tonquin Loop Sherwood OR 97140",
    "addr:housenumber":"11080",
    "addr:postcode":"97140",
    "addr:street":"Sw Tonquin Loop",
    "iso:country":"US",
    "sg:address":"11080 SW Tonquin Loop",
    "sg:city":"Sherwood",
    "sg:classifiers":[
        {
            "category":"Communications",
            "subcategory":"Film & Video Production",
            "type":"Services"
        }
    ],
    "sg:phone":"+1 503 691 2797",
    "sg:postcode":"97140",
    "sg:province":"OR",
    "sg:tags":[
        "motion"
    ],
    "wof:name":"Photographic Design",
    "wof:placetype":"venue"
},
  "geometry": {"coordinates":[-122.791878,45.351718],"type":"Point"}
}