{
  "type": "Feature",
  "properties": {
    "iso:country":"US",
    "sg:address":"4011 SE Ankeny St",
    "sg:city":"Portland",
    "sg:classifiers":[
        {
            "category":"Wholesale",
            "subcategory":"Wine & Distilled Alcoholic Beverages",
            "type":"Manufacturing & Wholesale Goods"
        }
    ],
    "sg:phone":"+1 503 236 5424",
    "sg:postcode":"97214",
    "sg:province":"OR",
    "wof:name":"Zancanella Importing Co",
    "wof:placetype":"venue"
},
  "geometry": {"coordinates":[-122.621566,45.522706],"type":"Point"}
}