{
  "type": "Feature",
  "properties": {
    "iso:country":"US",
    "sg:address":"844 NW Ogden Ave",
    "sg:city":"Bend",
    "sg:classifiers":[
        {
            "category":"Building & Trades",
            "subcategory":"Landscaping Services",
            "type":"Services"
        }
    ],
    "sg:phone":"+1 541 330 9577",
    "sg:postcode":"97701",
    "sg:province":"OR",
    "sg:tags":[
        "landscape",
        "contractor"
    ],
    "wof:name":"Aspen Landscape Development",
    "wof:placetype":"venue"
},
  "geometry": {"coordinates":[-121.324267,44.063337],"type":"Point"}
}