{
  "type": "Feature",
  "properties": {
    "addr:full":"1021 SE Caruthers St Portland OR 97214",
    "addr:housenumber":"1021",
    "addr:postcode":"97214",
    "addr:street":"Se Caruthers St",
    "iso:country":"US",
    "sg:address":"1021 SE Caruthers St",
    "sg:city":"Portland",
    "sg:classifiers":[
        {
            "category":"Professional",
            "type":"Services"
        }
    ],
    "sg:phone":"+1 503 224 5925",
    "sg:postcode":"97214",
    "sg:province":"OR",
    "sg:tags":[
        "processing",
        "data"
    ],
    "wof:name":"Pushdot Studio",
    "wof:placetype":"venue"
},
  "geometry": {"coordinates":[-122.655559,45.505798],"type":"Point"}
}