{
  "type": "Feature",
  "properties": {
    "iso:country":"US",
    "sg:address":"8890 SW Pacer Dr",
    "sg:city":"Beaverton",
    "sg:classifiers":[
        {
            "category":"Building & Trades",
            "subcategory":"Construction",
            "type":"Services"
        }
    ],
    "sg:phone":"+1 503 579 9447",
    "sg:postcode":"97008",
    "sg:province":"OR",
    "sg:tags":[
        "contractor"
    ],
    "wof:name":"Ceramic Tile By Fred",
    "wof:placetype":"venue"
},
  "geometry": {"coordinates":[-122.806129,45.457354],"type":"Point"}
}