{
  "type": "Feature",
  "properties": {
    "addr:full":"22463 SW Park St Sherwood OR 97140",
    "addr:housenumber":"22463",
    "addr:postcode":"97140",
    "addr:street":"Sw Park St",
    "iso:country":"US",
    "sg:address":"22463 SW Park St",
    "sg:city":"Sherwood",
    "sg:classifiers":[
        {
            "category":"Banks & Credit Unions",
            "subcategory":"Investment Brokerage",
            "type":"Services"
        }
    ],
    "sg:phone":"+1 503 625 4813",
    "sg:postcode":"97140",
    "sg:province":"OR",
    "sg:tags":[
        "trust"
    ],
    "wof:name":"Sherwood Foundation For The Arts",
    "wof:placetype":"venue"
},
  "geometry": {"coordinates":[-122.843763,45.355861],"type":"Point"}
}