{
  "type": "Feature",
  "properties": {
    "addr:full":"15663 S Graves Rd Mulino OR 97042",
    "addr:housenumber":"15663",
    "addr:postcode":"97042",
    "addr:street":"S Graves Rd",
    "iso:country":"US",
    "sg:address":"15663 S Graves Rd",
    "sg:city":"Mulino",
    "sg:classifiers":[
        {
            "category":"Professional",
            "type":"Services"
        }
    ],
    "sg:phone":"+1 503 759 3822",
    "sg:postcode":"97042",
    "sg:province":"OR",
    "sg:tags":[
        "establishment"
    ],
    "wof:name":"Freedom Products",
    "wof:placetype":"venue"
},
  "geometry": {"coordinates":[-122.548275,45.224591],"type":"Point"}
}