{
  "type": "Feature",
  "properties": {
    "iso:country":"US",
    "sg:address":"9321 SE Stark St",
    "sg:city":"Portland",
    "sg:classifiers":[
        {
            "category":"Retail",
            "subcategory":"Auto Repair",
            "type":"Services"
        }
    ],
    "sg:phone":"+1 503 232 4060",
    "sg:postcode":"97216",
    "sg:province":"OR",
    "sg:tags":[
        "automobile",
        "brake",
        "equipment-service",
        "air conditioning"
    ],
    "sg:website":"http://www.uhaul.com/Locations/Rentals-near-Portland-OR-97216/016251",
    "wof:name":"Affordable Car Care",
    "wof:placetype":"venue"
},
  "geometry": {"coordinates":[-122.56725,45.519301],"type":"Point"}
}