{
  "type": "Feature",
  "properties": {
    "addr:full":"10420 SW Allen Blvd Beaverton OR 97005",
    "addr:housenumber":"10420",
    "addr:postcode":"97005",
    "addr:street":"Sw Allen Blvd",
    "iso:country":"US",
    "sg:address":"10420 SW Allen Blvd",
    "sg:city":"Beaverton",
    "sg:classifiers":[
        {
            "category":"Education",
            "subcategory":"School",
            "type":"Public Place"
        }
    ],
    "sg:phone":"+1 503 672 3721",
    "sg:postcode":"97005",
    "sg:province":"OR",
    "wof:name":"Beaverton School District 48",
    "wof:placetype":"venue"
},
  "geometry": {"coordinates":[-122.78307100000001,45.476461],"type":"Point"}
}