{
  "type": "Feature",
  "properties": {
    "iso:country":"US",
    "sg:address":"2600 SW Hillsboro Hwy",
    "sg:city":"Hillsboro",
    "sg:classifiers":[
        {
            "category":"Government",
            "subcategory":"Office",
            "type":"Public Place"
        }
    ],
    "sg:phone":"+1 503 681 6206",
    "sg:postcode":"97123",
    "sg:province":"OR",
    "sg:tags":[
        "village"
    ],
    "wof:name":"Jackson Bottom Wetlands Prsrv",
    "wof:placetype":"venue"
},
  "geometry": {"coordinates":[-122.991296,45.500185],"type":"Point"}
}