{
  "type": "Feature",
  "properties": {
    "addr:full":"300 E Powell Blvd Gresham OR 97030",
    "addr:housenumber":"300",
    "addr:postcode":"97030",
    "addr:street":"E Powell Blvd",
    "iso:country":"US",
    "sg:address":"300 E Powell Blvd",
    "sg:city":"Gresham",
    "sg:classifiers":[
        {
            "category":"Banks & Credit Unions",
            "subcategory":"Bank",
            "type":"Services"
        }
    ],
    "sg:phone":"+1 503 661 4500",
    "sg:postcode":"97030",
    "sg:province":"OR",
    "sg:tags":[
        "commercial",
        "saving"
    ],
    "sg:website":"http://usbank.com",
    "wof:name":"Us Bank",
    "wof:placetype":"venue"
},
  "geometry": {"coordinates":[-122.427696,45.498001],"type":"Point"}
}