{
  "type": "Feature",
  "properties": {
    "addr:full":"1701 SE 1st St Redmond OR 97756",
    "addr:housenumber":"1701",
    "addr:postcode":"97756",
    "addr:street":"Se 1St St",
    "iso:country":"US",
    "sg:address":"1701 SE 1st St",
    "sg:city":"Redmond",
    "sg:classifiers":[
        {
            "category":"Freight",
            "type":"Transportation"
        }
    ],
    "sg:phone":"+1 541 548 3593",
    "sg:postcode":"97756",
    "sg:province":"OR",
    "sg:tags":[
        "operator",
        "trucking"
    ],
    "wof:name":"USFreightways",
    "wof:placetype":"venue"
},
  "geometry": {"coordinates":[-121.168871,44.261409],"type":"Point"}
}