{
  "type": "Feature",
  "properties": {
    "iso:country":"US",
    "sg:address":"6350 NW Front Ave",
    "sg:city":"Portland",
    "sg:classifiers":[
        {
            "category":"Manufacturing",
            "subcategory":"Building Materials",
            "type":"Manufacturing & Wholesale Goods"
        }
    ],
    "sg:phone":"+1 503 222 1307",
    "sg:postcode":"97210",
    "sg:province":"OR",
    "sg:tags":[
        "equipment",
        "supply",
        "roofing"
    ],
    "sg:website":"http://www.certainteed.net",
    "wof:name":"Certain Teed Corp",
    "wof:placetype":"venue"
},
  "geometry": {"coordinates":[-122.74454900000001,45.568181],"type":"Point"}
}