{
  "type": "Feature",
  "properties": {
    "iso:country":"US",
    "sg:address":"3835 Kirkway Dr",
    "sg:city":"Baker City",
    "sg:classifiers":[
        {
            "category":"Building & Trades",
            "subcategory":"Construction",
            "type":"Services"
        }
    ],
    "sg:phone":"+1 541 523 5909",
    "sg:postcode":"97814",
    "sg:province":"OR",
    "sg:tags":[
        "concrete",
        "work"
    ],
    "wof:name":"Martin Larry Concrete & Cnstr",
    "wof:placetype":"venue"
},
  "geometry": {"coordinates":[-117.830218,44.789703],"type":"Point"}
}