{
  "type": "Feature",
  "properties": {
    "iso:country":"US",
    "sg:address":"1235 State St",
    "sg:city":"Hood River",
    "sg:classifiers":[
        {
            "category":"Restaurant",
            "type":"Food & Drink"
        }
    ],
    "sg:phone":"+1 541 387 2273",
    "sg:postcode":"97031",
    "sg:province":"OR",
    "sg:tags":[
        "shop",
        "coffee"
    ],
    "wof:name":"Acre Organic Coffeehouse",
    "wof:placetype":"venue"
},
  "geometry": {"coordinates":[-121.52357600000001,45.70784],"type":"Point"}
}