{
  "type": "Feature",
  "properties": {
    "addr:full":"6235 N Basin Ave Portland OR 97217",
    "addr:housenumber":"6235",
    "addr:postcode":"97217",
    "addr:street":"N Basin Ave",
    "iso:country":"US",
    "sg:address":"6235 N Basin Ave",
    "sg:city":"Portland",
    "sg:classifiers":[
        {
            "category":"Banks & Credit Unions",
            "subcategory":"Bank",
            "type":"Services"
        }
    ],
    "sg:phone":"+1 503 240 3000",
    "sg:postcode":"97217",
    "sg:province":"OR",
    "wof:name":"Union Bank Of California",
    "wof:placetype":"venue"
},
  "geometry": {"coordinates":[-122.709878,45.566652],"type":"Point"}
}