{
  "type": "Feature",
  "properties": {
    "addr:full":"550 NE E St Grants Pass OR 97526",
    "addr:housenumber":"550",
    "addr:postcode":"97526",
    "addr:street":"Ne E St",
    "iso:country":"US",
    "sg:address":"550 NE E St",
    "sg:city":"Grants Pass",
    "sg:classifiers":[
        {
            "category":"Professional",
            "type":"Services"
        }
    ],
    "sg:phone":"+1 541 476 5855",
    "sg:postcode":"97526",
    "sg:province":"OR",
    "sg:tags":[
        "establishment"
    ],
    "sg:website":"www.cbdt-sold.com",
    "wof:name":"Colonial Square Enterprises",
    "wof:placetype":"venue"
},
  "geometry": {"coordinates":[-123.318515,42.439429],"type":"Point"}
}