{
  "type": "Feature",
  "properties": {
    "addr:full":"411 W 4th Ave Eugene OR 97401",
    "addr:housenumber":"411",
    "addr:postcode":"97401",
    "addr:street":"W 4Th Ave",
    "iso:country":"US",
    "sg:address":"411 W 4th Ave",
    "sg:city":"Eugene",
    "sg:classifiers":[
        {
            "category":"Wholesale",
            "subcategory":"Electrical",
            "type":"Manufacturing & Wholesale Goods"
        }
    ],
    "sg:phone":"+1 541 683 2474",
    "sg:postcode":"97401",
    "sg:province":"OR",
    "sg:tags":[
        "equipment",
        "electric",
        "supply"
    ],
    "wof:name":"Consolidated Electrical Distr",
    "wof:placetype":"venue"
},
  "geometry": {"coordinates":[-123.100233,44.054966],"type":"Point"}
}