{
  "type": "Feature",
  "properties": {
    "iso:country":"US",
    "sg:address":"836 E Main St Ste 2",
    "sg:city":"Medford",
    "sg:classifiers":[
        {
            "category":"Personal",
            "subcategory":"Beauty Salon",
            "type":"Services"
        },
        {
            "category":"Personal",
            "subcategory":"Tattoo Parlor",
            "type":"Services"
        },
        {
            "category":"Personal",
            "subcategory":"Nail Salon",
            "type":"Services"
        }
    ],
    "sg:phone":"+1 541 779 6800",
    "sg:postcode":"97504",
    "sg:province":"OR",
    "sg:website":"www.completebeautytouch.com",
    "wof:name":"Complete Beauty Touch",
    "wof:placetype":"venue"
},
  "geometry": {"coordinates":[-122.86427999999999,42.327733],"type":"Point"}
}