{
  "type": "Feature",
  "properties": {
    "addr:full":"1450 NW North Albany Rd Albany OR 97321",
    "addr:housenumber":"1450",
    "addr:postcode":"97321",
    "addr:street":"Nw North Albany Rd",
    "iso:country":"US",
    "sg:address":"1450 NW North Albany Rd",
    "sg:city":"Albany",
    "sg:classifiers":[
        {
            "category":"Building & Trades",
            "subcategory":"Construction",
            "type":"Services"
        }
    ],
    "sg:phone":"+1 541 928 3157",
    "sg:postcode":"97321",
    "sg:province":"OR",
    "sg:tags":[
        "new",
        "general",
        "ho",
        "family",
        "contractor"
    ],
    "wof:name":"Sierra Construction",
    "wof:placetype":"venue"
},
  "geometry": {"coordinates":[-123.116968,44.655048],"type":"Point"}
}