{
  "type": "Feature",
  "properties": {
    "iso:country":"US",
    "sg:address":"16071 SE McLoughlin Boulevard",
    "sg:city":"Portland",
    "sg:classifiers":[
        {
            "category":"Professional",
            "subcategory":"Employment Agencies",
            "type":"Services"
        }
    ],
    "sg:phone":"+1 503 786 3883",
    "sg:postcode":"97267",
    "sg:province":"OR",
    "sg:tags":[
        "contractor"
    ],
    "sg:website":"www.laborready.com",
    "wof:name":"Labor Ready",
    "wof:placetype":"venue"
},
  "geometry": {"coordinates":[-122.624948,45.407183],"type":"Point"}
}