{
  "type": "Feature",
  "properties": {
    "addr:full":"62929 N Hwy 97 Bend OR 97701",
    "addr:housenumber":"62929",
    "addr:postcode":"97701",
    "addr:street":"N Hwy 97",
    "iso:country":"US",
    "sg:address":"62929 N Hwy 97",
    "sg:city":"Bend",
    "sg:classifiers":[
        {
            "category":"Restaurant",
            "type":"Food & Drink"
        }
    ],
    "sg:phone":"+1 541 389 0701",
    "sg:postcode":"97701",
    "sg:province":"OR",
    "wof:name":"Shoji's",
    "wof:placetype":"venue"
},
  "geometry": {"coordinates":[-121.306262,44.087494],"type":"Point"}
}