{
  "type": "Feature",
  "properties": {
    "addr:full":"4701 Highway 101 Florence OR 97439",
    "addr:housenumber":"4701",
    "addr:postcode":"97439",
    "addr:street":"Highway 101",
    "iso:country":"US",
    "sg:address":"4701 Highway 101",
    "sg:city":"Florence",
    "sg:classifiers":[
        {
            "category":"Shopping",
            "subcategory":"Department Store",
            "type":"Retail Goods"
        },
        {
            "category":"Food & Beverages",
            "subcategory":"Supermarket",
            "type":"Retail Goods"
        },
        {
            "category":"Shopping",
            "subcategory":"Pharmacy",
            "type":"Retail Goods"
        },
        {
            "category":"Shopping",
            "subcategory":"Discount & Variety Stores",
            "type":"Retail Goods"
        }
    ],
    "sg:phone":"+1 541 902 7300",
    "sg:postcode":"97439",
    "sg:province":"OR",
    "sg:tags":[
        "super"
    ],
    "sg:website":"http://www.fredmeyer.com",
    "wof:name":"Fred Meyer",
    "wof:placetype":"venue"
},
  "geometry": {"coordinates":[-124.10157,44.006508],"type":"Point"}
}