{
  "type": "Feature",
  "properties": {
    "iso:country":"US",
    "sg:address":"14375 NW Science Park Dr",
    "sg:city":"Portland",
    "sg:classifiers":[
        {
            "category":"Sports & Exercise",
            "subcategory":"Bicycle Rental",
            "type":"Entertainment"
        }
    ],
    "sg:phone":"+1 503 985 4000",
    "sg:postcode":"97229",
    "sg:province":"OR",
    "sg:tags":[
        "wear"
    ],
    "sg:website":"www.columbia.com/",
    "wof:name":"Columbia Sportswear Company",
    "wof:placetype":"venue"
},
  "geometry": {"coordinates":[-122.826004,45.529448],"type":"Point"}
}