{
  "type": "Feature",
  "properties": {
    "iso:country":"US",
    "sg:address":"662 NE Garden Valley Blvd",
    "sg:city":"Roseburg",
    "sg:classifiers":[
        {
            "category":"Shopping",
            "subcategory":"Bicycles & Sporting Goods",
            "type":"Retail Goods"
        }
    ],
    "sg:phone":"+1 541 672 3721",
    "sg:postcode":"97470",
    "sg:province":"OR",
    "sg:tags":[
        "parts"
    ],
    "wof:name":"Garden Vly Schwinn & Cyclery",
    "wof:placetype":"venue"
},
  "geometry": {"coordinates":[-123.34902599999999,43.226721],"type":"Point"}
}