{
  "type": "Feature",
  "properties": {
    "iso:country":"US",
    "sg:address":"10858 Arndt Rd NE",
    "sg:city":"Aurora",
    "sg:classifiers":[
        {
            "category":"Organizations",
            "subcategory":"Religious Organization",
            "type":"Services"
        }
    ],
    "sg:phone":"+1 503 678 1188",
    "sg:postcode":"97002",
    "sg:province":"OR",
    "wof:name":"Butteville Community Church",
    "wof:placetype":"venue"
},
  "geometry": {"coordinates":[-122.838764,45.26125],"type":"Point"}
}