{
  "type": "Feature",
  "properties": {
    "iso:country":"US",
    "sg:address":"72 Constantine Pl",
    "sg:city":"Eugene",
    "sg:classifiers":[
        {
            "category":"Professional",
            "subcategory":"Employment Agencies",
            "type":"Services"
        }
    ],
    "sg:phone":"+1 541 302 1226",
    "sg:postcode":"97405",
    "sg:province":"OR",
    "wof:name":"Integrity Staffing of Oregon",
    "wof:placetype":"venue"
},
  "geometry": {"coordinates":[-123.099846,43.99799],"type":"Point"}
}