{
  "type": "Feature",
  "properties": {
    "iso:country":"US",
    "sg:address":"13322 SE Taggart St",
    "sg:city":"Portland",
    "sg:classifiers":[
        {
            "category":"Retail",
            "subcategory":"Repair Shop",
            "type":"Services"
        }
    ],
    "sg:phone":"+1 503 762 4346",
    "sg:postcode":"97236",
    "sg:province":"OR",
    "sg:tags":[
        "equipment",
        "electronic",
        "supply"
    ],
    "wof:name":"Dan's Audio",
    "wof:placetype":"venue"
},
  "geometry": {"coordinates":[-122.525232,45.501122],"type":"Point"}
}