{
  "type": "Feature",
  "properties": {
    "addr:full":"9900 SW Greenburg Rd Portland OR 97223",
    "addr:housenumber":"9900",
    "addr:postcode":"97223",
    "addr:street":"Sw Greenburg Rd",
    "iso:country":"US",
    "sg:address":"9900 SW Greenburg Rd",
    "sg:city":"Portland",
    "sg:classifiers":[
        {
            "category":"Insurance",
            "subcategory":"Insurance Agent",
            "type":"Services"
        },
        {
            "category":"Insurance",
            "subcategory":"Hazard Insurance",
            "type":"Services"
        },
        {
            "category":"Insurance",
            "subcategory":"Title Insurance",
            "type":"Services"
        },
        {
            "category":"Insurance",
            "subcategory":"Life Insurance",
            "type":"Services"
        }
    ],
    "sg:phone":"+1 503 670 0580",
    "sg:postcode":"97223",
    "sg:province":"OR",
    "sg:tags":[
        "auto",
        "commercial",
        "business",
        "homeowner"
    ],
    "sg:website":"http://www.farmersagent.com/ghunter/",
    "wof:name":"George Hunter - Farmers Insurance",
    "wof:placetype":"venue"
},
  "geometry": {"coordinates":[-122.775389,45.448616],"type":"Point"}
}