{
  "type": "Feature",
  "properties": {
    "iso:country":"US",
    "sg:address":"2848 S 6th St",
    "sg:city":"Klamath Falls",
    "sg:classifiers":[
        {
            "category":"Shopping",
            "subcategory":"Jewelry",
            "type":"Retail Goods"
        }
    ],
    "sg:phone":"+1 541 884 9033",
    "sg:postcode":"97603",
    "sg:province":"OR",
    "sg:tags":[
        "jeweler"
    ],
    "sg:website":"www.hollidayjewelry.com",
    "wof:name":"Holliday Jewelry",
    "wof:placetype":"venue"
},
  "geometry": {"coordinates":[-121.75441600000001,42.209924],"type":"Point"}
}