{
  "type": "Feature",
  "properties": {
    "addr:full":"4807 Granite Hill Rd Grants Pass OR 97526",
    "addr:housenumber":"4807",
    "addr:postcode":"97526",
    "addr:street":"Granite Hill Rd",
    "iso:country":"US",
    "sg:address":"4807 Granite Hill Rd",
    "sg:city":"Grants Pass",
    "sg:classifiers":[
        {
            "category":"Building & Trades",
            "subcategory":"Construction",
            "type":"Services"
        }
    ],
    "sg:phone":"+1 541 955 9654",
    "sg:postcode":"97526",
    "sg:province":"OR",
    "sg:tags":[
        "boring",
        "drilling",
        "contractor"
    ],
    "wof:name":"Clear Water Well Drilling",
    "wof:placetype":"venue"
},
  "geometry": {"coordinates":[-123.28515899999999,42.502558],"type":"Point"}
}