{
  "type": "Feature",
  "properties": {
    "addr:full":"23939 SW Gage Rd Wilsonville OR 97070",
    "addr:housenumber":"23939",
    "addr:postcode":"97070",
    "addr:street":"Sw Gage Rd",
    "iso:country":"US",
    "sg:address":"23939 SW Gage Rd",
    "sg:city":"Wilsonville",
    "sg:classifiers":[
        {
            "category":"Education",
            "subcategory":"College",
            "type":"Public Place"
        }
    ],
    "sg:phone":"+1 503 638 9008",
    "sg:postcode":"97070",
    "sg:province":"OR",
    "wof:name":"Daiva Banaitis",
    "wof:placetype":"venue"
},
  "geometry": {"coordinates":[-122.730172,45.347364],"type":"Point"}
}