{
  "type": "Feature",
  "properties": {
    "iso:country":"US",
    "sg:address":"3151 Shield Crest Dr",
    "sg:city":"Klamath Falls",
    "sg:classifiers":[
        {
            "category":"Sports & Exercise",
            "subcategory":"Golf",
            "type":"Entertainment"
        }
    ],
    "sg:phone":"+1 541 884 5305",
    "sg:postcode":"97603",
    "sg:province":"OR",
    "sg:tags":[
        "course"
    ],
    "wof:name":"Shield Crest Golf Shop",
    "wof:placetype":"venue"
},
  "geometry": {"coordinates":[-121.672012,42.196518],"type":"Point"}
}