{
  "type": "Feature",
  "properties": {
    "iso:country":"US",
    "sg:address":"739 NW 8th St",
    "sg:city":"Ontario",
    "sg:classifiers":[
        {
            "category":"Real Estate",
            "subcategory":"Developer",
            "type":"Services"
        }
    ],
    "sg:phone":"+1 541 889 3244",
    "sg:postcode":"97914",
    "sg:province":"OR",
    "sg:tags":[
        "mobile",
        "home"
    ],
    "wof:name":"Cooper Country Mobile Home Prk",
    "wof:placetype":"venue"
},
  "geometry": {"coordinates":[-116.971902,44.034268],"type":"Point"}
}