{
  "type": "Feature",
  "properties": {
    "iso:country":"US",
    "sg:address":"330 Adams St",
    "sg:city":"Eugene",
    "sg:classifiers":[
        {
            "category":"Professional",
            "subcategory":"Computer Services",
            "type":"Services"
        }
    ],
    "sg:phone":"+1 541 342 3764",
    "sg:postcode":"97402",
    "sg:province":"OR",
    "sg:tags":[
        "prepackaged",
        "software"
    ],
    "wof:name":"Craftsman Software Development",
    "wof:placetype":"venue"
},
  "geometry": {"coordinates":[-123.1065,44.056336],"type":"Point"}
}