{
  "type": "Feature",
  "properties": {
    "iso:country":"US",
    "sg:address":"2121 14th Ave SE",
    "sg:city":"Albany",
    "sg:classifiers":[
        {
            "category":"Shopping",
            "type":"Retail Goods"
        }
    ],
    "sg:phone":"+1 541 967 0564",
    "sg:postcode":"97322",
    "sg:province":"OR",
    "sg:tags":[
        "art",
        "gallery",
        "dealer"
    ],
    "wof:name":"Camerons Gallery & Gifts",
    "wof:placetype":"venue"
},
  "geometry": {"coordinates":[-123.080564,44.628846],"type":"Point"}
}