{
  "type": "Feature",
  "properties": {
    "addr:full":"3906 SE 98th Ave Portland OR 97266",
    "addr:housenumber":"3906",
    "addr:postcode":"97266",
    "addr:street":"Se 98Th Ave",
    "iso:country":"US",
    "sg:address":"3906 SE 98th Ave",
    "sg:city":"Portland",
    "sg:classifiers":[
        {
            "category":"Building & Trades",
            "subcategory":"Construction",
            "type":"Services"
        }
    ],
    "sg:phone":"+1 503 761 7012",
    "sg:postcode":"97266",
    "sg:province":"OR",
    "sg:tags":[
        "carpet",
        "floor",
        "installation",
        "install",
        "contractor"
    ],
    "wof:name":"Cochran Floor Covering",
    "wof:placetype":"venue"
},
  "geometry": {"coordinates":[-122.562843,45.493765],"type":"Point"}
}