{
  "type": "Feature",
  "properties": {
    "iso:country":"US",
    "sg:address":"45280 SE Coalman Rd",
    "sg:city":"Sandy",
    "sg:classifiers":[
        {
            "category":"Social Services",
            "subcategory":"Child Care",
            "type":"Services"
        }
    ],
    "sg:phone":"+1 503 668 5826",
    "sg:postcode":"97055",
    "sg:province":"OR",
    "sg:tags":[
        "day"
    ],
    "wof:name":"Canyon Haven Nursery",
    "wof:placetype":"venue"
},
  "geometry": {"coordinates":[-122.19823599999999,45.386398],"type":"Point"}
}