{
  "type": "Feature",
  "properties": {
    "iso:country":"US",
    "sg:address":"21800 SW Murphy Ln",
    "sg:city":"Beaverton",
    "sg:classifiers":[
        {
            "category":"Building & Trades",
            "subcategory":"Landscaping Services",
            "type":"Services"
        }
    ],
    "sg:phone":"+1 503 649 8024",
    "sg:postcode":"97007",
    "sg:province":"OR",
    "sg:tags":[
        "landscape",
        "contractor"
    ],
    "wof:name":"Rigert Homes",
    "wof:placetype":"venue"
},
  "geometry": {"coordinates":[-122.906775,45.475093],"type":"Point"}
}