{
  "type": "Feature",
  "properties": {
    "addr:full":"199 Smith Dr Woodburn OR 97071",
    "addr:housenumber":"199",
    "addr:postcode":"97071",
    "addr:street":"Smith Dr",
    "iso:country":"US",
    "sg:address":"199 Smith Dr",
    "sg:city":"Woodburn",
    "sg:classifiers":[
        {
            "category":"Building & Trades",
            "subcategory":"Plumbing",
            "type":"Services"
        }
    ],
    "sg:phone":"+1 503 982 4069",
    "sg:postcode":"97071",
    "sg:province":"OR",
    "sg:tags":[
        "plumbing",
        "contractor"
    ],
    "wof:name":"Meridian Plumbing",
    "wof:placetype":"venue"
},
  "geometry": {"coordinates":[-122.86366599999999,45.142448],"type":"Point"}
}