{
  "type": "Feature",
  "properties": {
    "addr:full":"16004 SW Tualatin Sherwood Rd Sherwood OR 97140",
    "addr:housenumber":"16004",
    "addr:postcode":"97140",
    "addr:street":"Sw Tualatin Sherwood Rd",
    "iso:country":"US",
    "sg:address":"16004 SW Tualatin Sherwood Rd",
    "sg:city":"Sherwood",
    "sg:classifiers":[
        {
            "category":"Fast Food",
            "type":"Food & Drink"
        },
        {
            "category":"Restaurant",
            "type":"Food & Drink"
        }
    ],
    "sg:phone":"+1 503 625 3577",
    "sg:postcode":"97140",
    "sg:province":"OR",
    "sg:tags":[
        "mexican",
        "take"
    ],
    "sg:website":"http://www.bajafresh.com",
    "wof:name":"Baja Fresh Mexican Grill",
    "wof:placetype":"venue"
},
  "geometry": {"coordinates":[-122.841902,45.369056],"type":"Point"}
}