{
  "type": "Feature",
  "properties": {
    "addr:full":"3830 Vine Maple St Eugene OR 97405",
    "addr:housenumber":"3830",
    "addr:postcode":"97405",
    "addr:street":"Vine Maple St",
    "iso:country":"US",
    "sg:address":"3830 Vine Maple St",
    "sg:city":"Eugene",
    "sg:classifiers":[
        {
            "category":"Organizations",
            "subcategory":"Professional Association",
            "type":"Services"
        }
    ],
    "sg:phone":"+1 541 345 1132",
    "sg:postcode":"97405",
    "sg:province":"OR",
    "sg:tags":[
        "business"
    ],
    "wof:name":"Oregon Gasoline Dealers Assoc",
    "wof:placetype":"venue"
},
  "geometry": {"coordinates":[-123.06407799999999,44.013228],"type":"Point"}
}