{
  "type": "Feature",
  "properties": {
    "addr:full":"3806 SE Grant Ct Portland OR 97214",
    "addr:housenumber":"3806",
    "addr:postcode":"97214",
    "addr:street":"Se Grant Ct",
    "iso:country":"US",
    "sg:address":"3806 SE Grant Ct",
    "sg:city":"Portland",
    "sg:classifiers":[
        {
            "category":"Food & Beverages",
            "subcategory":"Liquor & Beverages",
            "type":"Retail Goods"
        }
    ],
    "sg:phone":"+1 503 234 1517",
    "sg:postcode":"97214",
    "sg:province":"OR",
    "sg:tags":[
        "wine"
    ],
    "wof:name":"Portland Wine Merchants",
    "wof:placetype":"venue"
},
  "geometry": {"coordinates":[-122.622733,45.506782],"type":"Point"}
}