{
  "type": "Feature",
  "properties": {
    "iso:country":"US",
    "sg:address":"10095 Rickreall Rd",
    "sg:city":"Rickreall",
    "sg:classifiers":[
        {
            "category":"Building & Trades",
            "subcategory":"Construction",
            "type":"Services"
        }
    ],
    "sg:phone":"+1 503 623 9084",
    "sg:postcode":"97371",
    "sg:province":"OR",
    "sg:tags":[
        "retaining",
        "wall",
        "paving",
        "mfg"
    ],
    "wof:name":"Western Interlock Inc",
    "wof:placetype":"venue"
},
  "geometry": {"coordinates":[-123.236671,44.930399],"type":"Point"}
}