{
  "type": "Feature",
  "properties": {
    "iso:country":"US",
    "sg:address":"605 NW 12th St",
    "sg:city":"Gresham",
    "sg:classifiers":[
        {
            "category":"Shopping",
            "subcategory":"Clothing, Apparel, & Fashions",
            "type":"Retail Goods"
        }
    ],
    "sg:phone":"+1 503 618 8020",
    "sg:postcode":"97030",
    "sg:province":"OR",
    "sg:tags":[
        "apparel",
        "clothing",
        "store",
        "women's"
    ],
    "sg:website":"http://www.chicosfas.com",
    "wof:name":"Chico's",
    "wof:placetype":"venue"
},
  "geometry": {"coordinates":[-122.438018,45.505878],"type":"Point"}
}