{
  "type": "Feature",
  "properties": {
    "iso:country":"US",
    "sg:address":"4565 NW Kahneeta Dr",
    "sg:city":"Portland",
    "sg:classifiers":[
        {
            "category":"Professional",
            "subcategory":"Business Services",
            "type":"Services"
        }
    ],
    "sg:phone":"+1 503 645 4186",
    "sg:postcode":"97229",
    "sg:province":"OR",
    "wof:name":"Bill Simmons & Associates",
    "wof:placetype":"venue"
},
  "geometry": {"coordinates":[-122.866872,45.554165],"type":"Point"}
}