{
  "type": "Feature",
  "properties": {
    "iso:country":"US",
    "sg:address":"115 NW Morgan Ln",
    "sg:city":"Grants Pass",
    "sg:classifiers":[
        {
            "category":"Real Estate",
            "subcategory":"Developer",
            "type":"Services"
        },
        {
            "category":"Real Estate",
            "subcategory":"Real Estate Operator",
            "type":"Services"
        }
    ],
    "sg:phone":"+1 541 479 5191",
    "sg:postcode":"97526",
    "sg:province":"OR",
    "sg:tags":[
        "mobile",
        "home",
        "site"
    ],
    "wof:name":"Mountain View Mobile Home Park",
    "wof:placetype":"venue"
},
  "geometry": {"coordinates":[-123.324023,42.462188],"type":"Point"}
}