{
  "type": "Feature",
  "properties": {
    "iso:country":"US",
    "sg:address":"233 Rogue River Hwy",
    "sg:city":"Grants Pass",
    "sg:classifiers":[
        {
            "category":"Professional",
            "subcategory":"Business Services",
            "type":"Services"
        }
    ],
    "sg:phone":"+1 541 474 1748",
    "sg:postcode":"97527",
    "sg:province":"OR",
    "sg:tags":[
        "box",
        "mail"
    ],
    "wof:name":"Mail Call-Mailboxes & Mail",
    "wof:placetype":"venue"
},
  "geometry": {"coordinates":[-123.331007,42.426456],"type":"Point"}
}