{
  "type": "Feature",
  "properties": {
    "iso:country":"US",
    "sg:address":"520 SW Powerhouse Dr",
    "sg:city":"Bend",
    "sg:classifiers":[
        {
            "category":"Shopping",
            "subcategory":"Clothing, Apparel, & Fashions",
            "type":"Retail Goods"
        }
    ],
    "sg:phone":"+1 541 617 8849",
    "sg:postcode":"97702",
    "sg:province":"OR",
    "sg:tags":[
        "apparel",
        "women's"
    ],
    "sg:website":"http://www.jjill.com",
    "wof:name":"J. Jill Petites Stores",
    "wof:placetype":"venue"
},
  "geometry": {"coordinates":[-121.31548600000001,44.045057],"type":"Point"}
}