{
  "type": "Feature",
  "properties": {
    "iso:country":"US",
    "sg:address":"17435 NW West Union Rd",
    "sg:city":"Portland",
    "sg:classifiers":[
        {
            "category":"Organizations",
            "subcategory":"Religious Organization",
            "type":"Services"
        }
    ],
    "sg:phone":"+1 503 645 0744",
    "sg:postcode":"97229",
    "sg:province":"OR",
    "sg:tags":[
        "church"
    ],
    "wof:name":"St Gabriel's Episcopal Church",
    "wof:placetype":"venue"
},
  "geometry": {"coordinates":[-122.859385,45.555816],"type":"Point"}
}