{
  "type": "Feature",
  "properties": {
    "addr:full":"11667 NE Glisan St Portland OR 97220",
    "addr:housenumber":"11667",
    "addr:postcode":"97220",
    "addr:street":"Ne Glisan St",
    "iso:country":"US",
    "sg:address":"11667 NE Glisan St",
    "sg:city":"Portland",
    "sg:classifiers":[
        {
            "category":"Education",
            "subcategory":"School",
            "type":"Public Place"
        }
    ],
    "sg:phone":"+1 503 253 5721",
    "sg:postcode":"97220",
    "sg:province":"OR",
    "wof:name":"Pacific School-Investigation",
    "wof:placetype":"venue"
},
  "geometry": {"coordinates":[-122.542788,45.526361],"type":"Point"}
}