{
  "type": "Feature",
  "properties": {
    "addr:full":"4915 Garnet St Eugene OR 97405",
    "addr:housenumber":"4915",
    "addr:postcode":"97405",
    "addr:street":"Garnet St",
    "iso:country":"US",
    "sg:address":"4915 Garnet St",
    "sg:city":"Eugene",
    "sg:classifiers":[
        {
            "category":"Social Services",
            "type":"Services"
        }
    ],
    "sg:phone":"+1 541 343 2339",
    "sg:postcode":"97405",
    "sg:province":"OR",
    "sg:tags":[
        "counselor",
        "marriage",
        "family"
    ],
    "wof:name":"Anita N Browning",
    "wof:placetype":"venue"
},
  "geometry": {"coordinates":[-123.07299500000001,44.000837],"type":"Point"}
}