{
  "type": "Feature",
  "properties": {
    "addr:full":"1530 N Pacific Hwy Woodburn OR 97071",
    "addr:housenumber":"1530",
    "addr:postcode":"97071",
    "addr:street":"N Pacific Hwy",
    "iso:country":"US",
    "sg:address":"1530 N Pacific Hwy",
    "sg:city":"Woodburn",
    "sg:classifiers":[
        {
            "category":"Personal",
            "subcategory":"Beauty Salon",
            "type":"Services"
        }
    ],
    "sg:phone":"+1 503 982 5175",
    "sg:postcode":"97071",
    "sg:province":"OR",
    "wof:name":"Supercuts",
    "wof:placetype":"venue"
},
  "geometry": {"coordinates":[-122.831434,45.150893],"type":"Point"}
}