{
  "type": "Feature",
  "properties": {
    "iso:country":"US",
    "sg:address":"33132 Coleman Rd",
    "sg:city":"Eugene",
    "sg:classifiers":[
        {
            "category":"Manufacturing",
            "subcategory":"Tools & Machinery",
            "type":"Manufacturing & Wholesale Goods"
        },
        {
            "category":"Utilities",
            "subcategory":"Water",
            "type":"Services"
        },
        {
            "category":"Wholesale",
            "subcategory":"Machinery & Supplies",
            "type":"Manufacturing & Wholesale Goods"
        }
    ],
    "sg:phone":"+1 541 344 6177",
    "sg:postcode":"97408",
    "sg:province":"OR",
    "sg:tags":[
        "control",
        "equipment",
        "well",
        "contractor",
        "flood",
        "pump",
        "drilling"
    ],
    "sg:website":"http://www.cwdrilling.com",
    "wof:name":"Advanced Well Tek",
    "wof:placetype":"venue"
},
  "geometry": {"coordinates":[-123.047247,44.197757],"type":"Point"}
}