{
  "type": "Feature",
  "properties": {
    "iso:country":"US",
    "sg:address":"530 Chetco Ln",
    "sg:city":"Brookings",
    "sg:classifiers":[
        {
            "category":"Autos & Motor Vehicles",
            "subcategory":"Automobile Sales",
            "type":"Retail Goods"
        }
    ],
    "sg:phone":"+1 541 469 5321",
    "sg:postcode":"97415",
    "sg:province":"OR",
    "sg:tags":[
        "car",
        "dealer"
    ],
    "sg:website":"www.coastautocenter.com",
    "wof:name":"Coast Auto Ctr Inc",
    "wof:placetype":"venue"
},
  "geometry": {"coordinates":[-124.290733,42.055965],"type":"Point"}
}