{
  "type": "Feature",
  "properties": {
    "iso:country":"US",
    "sg:address":"2820 SE Glenn St",
    "sg:city":"Corvallis",
    "sg:classifiers":[
        {
            "category":"Real Estate",
            "subcategory":"Real Estate Agent",
            "type":"Services"
        }
    ],
    "sg:phone":"+1 541 752 4939",
    "sg:postcode":"97333",
    "sg:province":"OR",
    "sg:tags":[
        "inspection"
    ],
    "wof:name":"Lighthouse Home & Garden LLC",
    "wof:placetype":"venue"
},
  "geometry": {"coordinates":[-123.264889,44.537219],"type":"Point"}
}