{
  "type": "Feature",
  "properties": {
    "iso:country":"US",
    "sg:address":"784 Shively Creek Rd",
    "sg:city":"Days Creek",
    "sg:classifiers":[
        {
            "category":"Retail",
            "subcategory":"Repair Shop",
            "type":"Services"
        }
    ],
    "sg:phone":"+1 541 825 3690",
    "sg:postcode":"97417",
    "sg:province":"OR",
    "sg:tags":[
        "equipment",
        "hydraulic"
    ],
    "wof:name":"Hydraulic Problems Inc",
    "wof:placetype":"venue"
},
  "geometry": {"coordinates":[-123.17102,42.961394],"type":"Point"}
}