{
  "type": "Feature",
  "properties": {
    "iso:country":"US",
    "sg:address":"21730 SW Bennette Rd",
    "sg:city":"Mcminnville",
    "sg:classifiers":[
        {
            "category":"Professional",
            "type":"Services"
        }
    ],
    "sg:phone":"+1 503 434 5784",
    "sg:postcode":"97128",
    "sg:province":"OR",
    "wof:name":"Han D Man Service Co Inc",
    "wof:placetype":"venue"
},
  "geometry": {"coordinates":[-123.337896,45.219356],"type":"Point"}
}