{
  "type": "Feature",
  "properties": {
    "iso:country":"US",
    "sg:address":"2144 NE 23rd Ave",
    "sg:city":"Portland",
    "sg:classifiers":[
        {
            "category":"Professional",
            "subcategory":"Management & Consulting",
            "type":"Services"
        }
    ],
    "sg:phone":"+1 503 287 6012",
    "sg:postcode":"97212",
    "sg:province":"OR",
    "wof:name":"Turner Maralyn E & Assoc",
    "wof:placetype":"venue"
},
  "geometry": {"coordinates":[-122.64210799999999,45.538614],"type":"Point"}
}