{
  "type": "Feature",
  "properties": {
    "iso:country":"US",
    "sg:address":"651 NW 6th St Ste C",
    "sg:city":"Redmond",
    "sg:classifiers":[
        {
            "category":"Wholesale",
            "subcategory":"Medical Equipment & Supplies",
            "type":"Manufacturing & Wholesale Goods"
        },
        {
            "category":"Health Services",
            "subcategory":"Health Practitioner",
            "type":"Services"
        }
    ],
    "sg:phone":"+1 541 548 4245",
    "sg:postcode":"97756",
    "sg:province":"OR",
    "sg:tags":[
        "assistive",
        "device",
        "audiologists",
        "aid",
        "hearing"
    ],
    "wof:name":"Central Oregon Audiology",
    "wof:placetype":"venue"
},
  "geometry": {"coordinates":[-121.174305,44.281521],"type":"Point"}
}