{
  "type": "Feature",
  "properties": {
    "iso:country":"US",
    "sg:address":"445 E Main St",
    "sg:city":"Hillsboro",
    "sg:classifiers":[
        {
            "category":"Health Services",
            "subcategory":"Health Practitioner",
            "type":"Services"
        }
    ],
    "sg:phone":"+1 503 640 3147",
    "sg:postcode":"97123",
    "sg:province":"OR",
    "sg:tags":[
        "pathologist",
        "speech"
    ],
    "wof:name":"Kathy Kohama",
    "wof:placetype":"venue"
},
  "geometry": {"coordinates":[-122.983214,45.522661],"type":"Point"}
}