{
  "type": "Feature",
  "properties": {
    "iso:country":"US",
    "sg:address":"37367 Kgal Dr",
    "sg:city":"Lebanon",
    "sg:phone":"+1 541 258 3982",
    "sg:postcode":"97355",
    "sg:province":"OR",
    "sg:tags":[
        "farm"
    ],
    "wof:name":"Meyer Farms",
    "wof:placetype":"venue"
},
  "geometry": {"coordinates":[-122.905486,44.572918],"type":"Point"}
}