{
  "type": "Feature",
  "properties": {
    "iso:country":"US",
    "sg:address":"1960 SW G St",
    "sg:city":"Grants Pass",
    "sg:classifiers":[
        {
            "category":"Sports & Exercise",
            "subcategory":"Gym",
            "type":"Entertainment"
        }
    ],
    "sg:phone":"+1 541 474 9412",
    "sg:postcode":"97526",
    "sg:province":"OR",
    "sg:tags":[
        "club",
        "health",
        "studio",
        "gymnasium"
    ],
    "wof:name":"G Street Health Club",
    "wof:placetype":"venue"
},
  "geometry": {"coordinates":[-123.34999000000001,42.44067],"type":"Point"}
}