{
  "type": "Feature",
  "properties": {
    "addr:full":"1964 Summers Ln Klamath Falls OR 97603",
    "addr:housenumber":"1964",
    "addr:postcode":"97603",
    "addr:street":"Summers Ln",
    "iso:country":"US",
    "sg:address":"1964 Summers Ln",
    "sg:city":"Klamath Falls",
    "sg:classifiers":[
        {
            "category":"Organizations",
            "subcategory":"Religious Organization",
            "type":"Services"
        }
    ],
    "sg:phone":"+1 541 884 5584",
    "sg:postcode":"97603",
    "sg:province":"OR",
    "sg:tags":[
        "church"
    ],
    "wof:name":"Weaver Mem Wesleyan Church",
    "wof:placetype":"venue"
},
  "geometry": {"coordinates":[-121.737365,42.208826],"type":"Point"}
}