{
  "type": "Feature",
  "properties": {
    "iso:country":"US",
    "sg:address":"236 N Front St",
    "sg:city":"Medford",
    "sg:classifiers":[
        {
            "category":"Restaurant",
            "type":"Food & Drink"
        }
    ],
    "sg:phone":"+1 541 776 3388",
    "sg:postcode":"97501",
    "sg:province":"OR",
    "sg:tags":[
        "chinese"
    ],
    "sg:website":"www.newfareastrestaurant.com/",
    "wof:name":"New Far East",
    "wof:placetype":"venue"
},
  "geometry": {"coordinates":[-122.875,42.327999],"type":"Point"}
}