{
  "type": "Feature",
  "properties": {
    "iso:country":"US",
    "sg:address":"3615 NW Samaritan Dr",
    "sg:city":"Corvallis",
    "sg:classifiers":[
        {
            "category":"Health Services",
            "subcategory":"Hospital",
            "type":"Services"
        }
    ],
    "sg:phone":"+1 541 768 5187",
    "sg:postcode":"97330",
    "sg:province":"OR",
    "wof:name":"Valley Mobile Imaging Dept",
    "wof:placetype":"venue"
},
  "geometry": {"coordinates":[-123.254577,44.6028],"type":"Point"}
}