{
  "type": "Feature",
  "properties": {
    "addr:full":"10010 SW Hall Blvd Tigard OR 97223",
    "addr:housenumber":"10010",
    "addr:postcode":"97223",
    "addr:street":"Sw Hall Blvd",
    "iso:country":"US",
    "sg:address":"10010 SW Hall Blvd",
    "sg:city":"Tigard",
    "sg:classifiers":[
        {
            "category":"Taxi",
            "type":"Transportation"
        }
    ],
    "sg:phone":"+1 503 888 2829",
    "sg:postcode":"97223",
    "sg:province":"OR",
    "wof:name":"economy shuttle",
    "wof:placetype":"venue"
},
  "geometry": {"coordinates":[-122.765452,45.447834],"type":"Point"}
}