{
  "type": "Feature",
  "properties": {
    "addr:full":"2800 N Vancouver Avenue Suite 230 Portland OR 97227",
    "addr:housenumber":"2800",
    "addr:postcode":"97227",
    "addr:street":"N Vancouver Avenue Suite 230",
    "iso:country":"US",
    "sg:address":"2800 N Vancouver Avenue Suite 230",
    "sg:city":"Portland",
    "sg:classifiers":[
        {
            "category":"Health Services",
            "subcategory":"Doctor",
            "type":"Services"
        }
    ],
    "sg:phone":"+1 503 413 4340",
    "sg:postcode":"97227",
    "sg:province":"OR",
    "wof:name":"Bensching Katherine MD",
    "wof:placetype":"venue"
},
  "geometry": {"coordinates":[-122.668108,45.542825],"type":"Point"}
}