{
  "type": "Feature",
  "properties": {
    "iso:country":"US",
    "sg:address":"645 W 6th Ave",
    "sg:city":"Sutherlin",
    "sg:classifiers":[
        {
            "category":"Professional",
            "subcategory":"Management & Consulting",
            "type":"Services"
        }
    ],
    "sg:phone":"+1 541 459 1136",
    "sg:postcode":"97479",
    "sg:province":"OR",
    "wof:name":"Fieldflex",
    "wof:placetype":"venue"
},
  "geometry": {"coordinates":[-123.322639,43.390644],"type":"Point"}
}