{
  "type": "Feature",
  "properties": {
    "addr:full":"2007 Adams Ave La Grande OR 97850",
    "addr:housenumber":"2007",
    "addr:postcode":"97850",
    "addr:street":"Adams Ave",
    "iso:country":"US",
    "sg:address":"2007 Adams Ave",
    "sg:city":"La Grande",
    "sg:classifiers":[
        {
            "category":"Building & Trades",
            "subcategory":"Equipment Rental",
            "type":"Services"
        }
    ],
    "sg:phone":"+1 541 963 8300",
    "sg:postcode":"97850",
    "sg:province":"OR",
    "sg:tags":[
        "retailer",
        "construction",
        "yard",
        "e",
        "party"
    ],
    "wof:name":"Eastern Oregon Rental & Sales",
    "wof:placetype":"venue"
},
  "geometry": {"coordinates":[-118.084283,45.322327],"type":"Point"}
}