{
  "type": "Feature",
  "properties": {
    "iso:country":"US",
    "sg:address":"18880 N W Lone Pine Ln",
    "sg:city":"Terrebonne",
    "sg:phone":"+1 541 548 5747",
    "sg:postcode":"97760",
    "sg:province":"OR",
    "sg:tags":[
        "c",
        "beef",
        "farm",
        "field",
        "cattle",
        "feedlot"
    ],
    "wof:name":"Tc Ranch",
    "wof:placetype":"venue"
},
  "geometry": {"coordinates":[-121.082053,44.377889],"type":"Point"}
}