{
  "type": "Feature",
  "properties": {
    "addr:full":"1680 Oak St Eugene OR 97401",
    "addr:housenumber":"1680",
    "addr:postcode":"97401",
    "addr:street":"Oak St",
    "iso:country":"US",
    "sg:address":"1680 Oak St",
    "sg:city":"Eugene",
    "sg:classifiers":[
        {
            "category":"Banks & Credit Unions",
            "subcategory":"Bank",
            "type":"Services"
        }
    ],
    "sg:phone":"+1 541 484 3132",
    "sg:postcode":"97401",
    "sg:province":"OR",
    "sg:tags":[
        "broker",
        "mortgage"
    ],
    "wof:name":"Oregon Mortgage Group Inc",
    "wof:placetype":"venue"
},
  "geometry": {"coordinates":[-123.09128699999999,44.041335],"type":"Point"}
}