{
  "type": "Feature",
  "properties": {
    "addr:full":"10903 SE Oak St Portland OR 97222",
    "addr:housenumber":"10903",
    "addr:postcode":"97222",
    "addr:street":"Se Oak St",
    "iso:country":"US",
    "sg:address":"10903 SE Oak St",
    "sg:city":"Portland",
    "sg:classifiers":[
        {
            "category":"Building & Trades",
            "subcategory":"Locksmith",
            "type":"Services"
        }
    ],
    "sg:phone":"+1 971 220 9362",
    "sg:postcode":"97222",
    "sg:province":"OR",
    "sg:tags":[
        "key"
    ],
    "wof:name":"24 Hour 7 Day Emergency Locksmith",
    "wof:placetype":"venue"
},
  "geometry": {"coordinates":[-122.62909500000001,45.44429],"type":"Point"}
}