{
  "type": "Feature",
  "properties": {
    "addr:full":"2310 Santiam Hwy SE Albany OR 97322",
    "addr:housenumber":"2310",
    "addr:postcode":"97322",
    "addr:street":"Santiam Hwy Se",
    "iso:country":"US",
    "sg:address":"2310 Santiam Hwy SE",
    "sg:city":"Albany",
    "sg:classifiers":[
        {
            "category":"Restaurant",
            "type":"Food & Drink"
        }
    ],
    "sg:menulink":"http://www.allmenus.com/or/albany/217228-burgerville/menu/",
    "sg:phone":"+1 541 926 0669",
    "sg:postcode":"97322",
    "sg:province":"OR",
    "sg:tags":[
        "burger",
        "american"
    ],
    "wof:name":"Burgerville",
    "wof:placetype":"venue"
},
  "geometry": {"coordinates":[-123.077124,44.632723],"type":"Point"}
}