{
  "type": "Feature",
  "properties": {
    "iso:country":"US",
    "sg:address":"197 E Van Buren St",
    "sg:city":"Cannon Beach",
    "sg:classifiers":[
        {
            "category":"Professional",
            "subcategory":"Computer Services",
            "type":"Services"
        }
    ],
    "sg:phone":"+1 503 436 0211",
    "sg:postcode":"97110",
    "sg:province":"OR",
    "sg:tags":[
        "consultant",
        "designer"
    ],
    "sg:website":"www.northoregoncoast.com",
    "wof:name":"Cheth Rowe Consulting",
    "wof:placetype":"venue"
},
  "geometry": {"coordinates":[-123.95961,45.891252],"type":"Point"}
}