{
  "type": "Feature",
  "properties": {
    "iso:country":"US",
    "sg:address":"319 SW Washington Street Suite 520",
    "sg:city":"Portland",
    "sg:classifiers":[
        {
            "category":"Banks & Credit Unions",
            "subcategory":"Atm",
            "type":"Services"
        }
    ],
    "sg:phone":"+1 503 224 7225",
    "sg:postcode":"97204",
    "sg:province":"OR",
    "sg:tags":[
        "bankruptcy"
    ],
    "wof:name":"Bankruptcy With Dignity",
    "wof:placetype":"venue"
},
  "geometry": {"coordinates":[-122.67499599999999,45.519661],"type":"Point"}
}