{
  "type": "Feature",
  "properties": {
    "iso:country":"US",
    "sg:address":"10921 NE Simpson St",
    "sg:city":"Portland",
    "sg:classifiers":[
        {
            "category":"Retail",
            "subcategory":"Auto Repair",
            "type":"Services"
        }
    ],
    "sg:phone":"+1 503 256 1457",
    "sg:postcode":"97220",
    "sg:province":"OR",
    "sg:tags":[
        "body",
        "automobile",
        "painting"
    ],
    "wof:name":"Magic Auto Body",
    "wof:placetype":"venue"
},
  "geometry": {"coordinates":[-122.54758,45.565911],"type":"Point"}
}