{
  "type": "Feature",
  "properties": {
    "iso:country":"US",
    "sg:address":"1075 W Historic Columbia River Hwy",
    "sg:city":"Troutdale",
    "sg:classifiers":[
        {
            "category":"Retail",
            "subcategory":"Repair Shop",
            "type":"Services"
        }
    ],
    "sg:phone":"+1 503 235 8784",
    "sg:postcode":"97060",
    "sg:province":"OR",
    "sg:tags":[
        "plumbing",
        "drain",
        "cleaning",
        "sewer"
    ],
    "sg:website":"www.jackhowk.com",
    "wof:name":"Jack Howk Plumbing & Drain",
    "wof:placetype":"venue"
},
  "geometry": {"coordinates":[-122.37264399999999,45.536463],"type":"Point"}
}