{
  "type": "Feature",
  "properties": {
    "addr:full":"1404 NW Naito Pkwy Portland OR 97209",
    "addr:housenumber":"1404",
    "addr:postcode":"97209",
    "addr:street":"Nw Naito Pkwy",
    "iso:country":"US",
    "sg:address":"1404 NW Naito Pkwy",
    "sg:city":"Portland",
    "sg:classifiers":[
        {
            "category":"Government",
            "subcategory":"Police Station",
            "type":"Public Place"
        }
    ],
    "sg:phone":"+1 503 823 2100",
    "sg:postcode":"97209",
    "sg:province":"OR",
    "sg:tags":[
        "department"
    ],
    "sg:website":"www.portlandonline.com/police/in...",
    "wof:name":"Portland Police Bureau - Mounted Patrol Unit",
    "wof:placetype":"venue"
},
  "geometry": {"coordinates":[-122.67985299999999,45.532918],"type":"Point"}
}