{
  "type": "Feature",
  "properties": {
    "addr:full":"532 Ferry St SW Albany OR 97321",
    "addr:housenumber":"532",
    "addr:postcode":"97321",
    "addr:street":"Ferry St Sw",
    "iso:country":"US",
    "sg:address":"532 Ferry St SW",
    "sg:city":"Albany",
    "sg:classifiers":[
        {
            "category":"Professional",
            "type":"Services"
        }
    ],
    "sg:phone":"+1 541 926 5811",
    "sg:postcode":"97321",
    "sg:province":"OR",
    "wof:name":"Eleanor Johnson",
    "wof:placetype":"venue"
},
  "geometry": {"coordinates":[-123.108057,44.633578],"type":"Point"}
}