{
  "type": "Feature",
  "properties": {
    "iso:country":"US",
    "sg:address":"898 Pearl St",
    "sg:city":"Eugene",
    "sg:classifiers":[
        {
            "category":"Restaurant",
            "type":"Food & Drink"
        }
    ],
    "sg:phone":"+1 541 343 3005",
    "sg:postcode":"97401",
    "sg:province":"OR",
    "wof:name":"Zenon Cafe",
    "wof:placetype":"venue"
},
  "geometry": {"coordinates":[-123.089681,44.050467],"type":"Point"}
}