{
  "type": "Feature",
  "properties": {
    "iso:country":"US",
    "sg:address":"17951 SW Corral Creek Dr",
    "sg:city":"Sherwood",
    "sg:classifiers":[
        {
            "category":"Shopping",
            "subcategory":"Computers & Home Electronics",
            "type":"Retail Goods"
        }
    ],
    "sg:phone":"+1 503 625 6497",
    "sg:postcode":"97132",
    "sg:province":"OR",
    "sg:tags":[
        "equipment",
        "metal",
        "locating"
    ],
    "wof:name":"Bear-Ied Treasures",
    "wof:placetype":"venue"
},
  "geometry": {"coordinates":[-122.85971499999999,45.292577],"type":"Point"}
}