{
  "type": "Feature",
  "properties": {
    "iso:country":"US",
    "sg:address":"10121 SE Sunnyside Rd Ste 320",
    "sg:city":"Clackamas",
    "sg:classifiers":[
        {
            "category":"Health Services",
            "subcategory":"Doctor",
            "type":"Services"
        },
        {
            "category":"Health Services",
            "subcategory":"Dentist",
            "type":"Services"
        }
    ],
    "sg:phone":"+1 503 786 5080",
    "sg:postcode":"97015",
    "sg:province":"OR",
    "sg:tags":[
        "surgeon",
        "oral",
        "pediatric"
    ],
    "sg:website":"www.sherwooddentistryforchildren...",
    "wof:name":"Doyle David E DDS",
    "wof:placetype":"venue"
},
  "geometry": {"coordinates":[-122.55999799999999,45.433399],"type":"Point"}
}