{
  "type": "Feature",
  "properties": {
    "iso:country":"US",
    "sg:address":"2165 SW Warwick Ave",
    "sg:city":"Portland",
    "sg:classifiers":[
        {
            "category":"Wholesale",
            "subcategory":"Non-durable Goods",
            "type":"Manufacturing & Wholesale Goods"
        }
    ],
    "sg:phone":"+1 503 284 2381",
    "sg:postcode":"97225",
    "sg:province":"OR",
    "wof:name":"Dotpop Distribution Inc",
    "wof:placetype":"venue"
},
  "geometry": {"coordinates":[-122.788002,45.504613],"type":"Point"}
}