{
  "type": "Feature",
  "properties": {
    "iso:country":"US",
    "sg:address":"21025 SW Pacific Hwy",
    "sg:city":"Sherwood",
    "sg:classifiers":[
        {
            "category":"Shopping",
            "type":"Retail Goods"
        }
    ],
    "sg:phone":"+1 503 625 6428",
    "sg:postcode":"97140",
    "sg:province":"OR",
    "sg:tags":[
        "feed",
        "auto",
        "supply"
    ],
    "wof:name":"Sherwood Feed & Garden Store",
    "wof:placetype":"venue"
},
  "geometry": {"coordinates":[-122.846682,45.367665],"type":"Point"}
}