{
  "type": "Feature",
  "properties": {
    "iso:country":"US",
    "sg:address":"1840 5th St",
    "sg:city":"Springfield",
    "sg:classifiers":[
        {
            "category":"Banks & Credit Unions",
            "subcategory":"Bank",
            "type":"Services"
        }
    ],
    "sg:phone":"+1 541 747 6555",
    "sg:postcode":"97477",
    "sg:province":"OR",
    "sg:tags":[
        "loan",
        "real estate"
    ],
    "wof:name":"New Life Mortgage",
    "wof:placetype":"venue"
},
  "geometry": {"coordinates":[-123.019411,44.064663],"type":"Point"}
}