{
  "type": "Feature",
  "properties": {
    "addr:full":"29890 SW Town Center Loop W Wilsonville OR 97070",
    "addr:housenumber":"29890",
    "addr:postcode":"97070",
    "addr:street":"Sw Town Center Loop W",
    "iso:country":"US",
    "sg:address":"29890 SW Town Center Loop W",
    "sg:city":"Wilsonville",
    "sg:classifiers":[
        {
            "category":"Restaurant",
            "type":"Food & Drink"
        }
    ],
    "sg:phone":"+1 503 682 0773",
    "sg:postcode":"97070",
    "sg:province":"OR",
    "sg:tags":[
        "eating"
    ],
    "wof:name":"Boston's Pub & Grill",
    "wof:placetype":"venue"
},
  "geometry": {"coordinates":[-122.765697,45.304026],"type":"Point"}
}