{
  "type": "Feature",
  "properties": {
    "iso:country":"US",
    "sg:address":"807 Main St",
    "sg:city":"Oregon City",
    "sg:classifiers":[
        {
            "category":"Government",
            "subcategory":"Office",
            "type":"Public Place"
        }
    ],
    "sg:phone":"+1 503 655 8233",
    "sg:postcode":"97045",
    "sg:province":"OR",
    "wof:name":"Honorable Robert R Selander",
    "wof:placetype":"venue"
},
  "geometry": {"coordinates":[-122.606954,45.358634],"type":"Point"}
}