{
  "type": "Feature",
  "properties": {
    "addr:full":"8455 SW Schiller Rd Portland OR 97225",
    "addr:housenumber":"8455",
    "addr:postcode":"97225",
    "addr:street":"Sw Schiller Rd",
    "iso:country":"US",
    "sg:address":"8455 SW Schiller Rd",
    "sg:city":"Portland",
    "sg:classifiers":[
        {
            "category":"Professional",
            "subcategory":"Business Services",
            "type":"Services"
        }
    ],
    "sg:phone":"+1 503 297 5138",
    "sg:postcode":"97225",
    "sg:province":"OR",
    "wof:name":"Lxk Associates",
    "wof:placetype":"venue"
},
  "geometry": {"coordinates":[-122.76365199999999,45.501037],"type":"Point"}
}