{
  "type": "Feature",
  "properties": {
    "iso:country":"US",
    "sg:address":"2928 NE Riverside Way",
    "sg:city":"Portland",
    "sg:classifiers":[
        {
            "category":"Home & Garden",
            "subcategory":"Household Appliances",
            "type":"Retail Goods"
        }
    ],
    "sg:phone":"+1 503 249 2985",
    "sg:postcode":"97211",
    "sg:province":"OR",
    "sg:tags":[
        "cleaning",
        "vacuum"
    ],
    "wof:name":"High Purity Vacuum",
    "wof:placetype":"venue"
},
  "geometry": {"coordinates":[-122.639379,45.580981],"type":"Point"}
}