{
  "type": "Feature",
  "properties": {
    "iso:country":"US",
    "sg:address":"981 Medford Center",
    "sg:city":"Medford",
    "sg:classifiers":[
        {
            "category":"Shopping",
            "subcategory":"Pharmacy",
            "type":"Retail Goods"
        }
    ],
    "sg:phone":"+1 541 773 3456",
    "sg:postcode":"97504",
    "sg:province":"OR",
    "wof:name":"Payless Drug Store",
    "wof:placetype":"venue"
},
  "geometry": {"coordinates":[-122.86682399999999,42.33177],"type":"Point"}
}