{
  "type": "Feature",
  "properties": {
    "addr:full":"19750 SE Damascus Ln Boring OR 97089",
    "addr:housenumber":"19750",
    "addr:postcode":"97089",
    "addr:street":"Se Damascus Ln",
    "iso:country":"US",
    "sg:address":"19750 SE Damascus Ln",
    "sg:city":"Boring",
    "sg:classifiers":[
        {
            "category":"Government",
            "subcategory":"Office",
            "type":"Public Place"
        }
    ],
    "sg:phone":"+1 503 658 8545",
    "sg:postcode":"97089",
    "sg:province":"OR",
    "sg:tags":[
        "village"
    ],
    "wof:name":"City Of Damascus",
    "wof:placetype":"venue"
},
  "geometry": {"coordinates":[-122.459053,45.421004],"type":"Point"}
}