{
  "type": "Feature",
  "properties": {
    "addr:full":"13878 S Carus Rd Oregon City OR 97045",
    "addr:housenumber":"13878",
    "addr:postcode":"97045",
    "addr:street":"S Carus Rd",
    "iso:country":"US",
    "sg:address":"13878 S Carus Rd",
    "sg:city":"Oregon City",
    "sg:classifiers":[
        {
            "category":"Building & Trades",
            "subcategory":"Landscaping Services",
            "type":"Services"
        }
    ],
    "sg:phone":"+1 503 632 5125",
    "sg:postcode":"97045",
    "sg:province":"OR",
    "sg:tags":[
        "landscape"
    ],
    "wof:name":"Lakeside Landscape",
    "wof:placetype":"venue"
},
  "geometry": {"coordinates":[-122.583354,45.271382],"type":"Point"}
}