{
  "type": "Feature",
  "properties": {
    "iso:country":"US",
    "sg:address":"5448 Sturdivant Ave",
    "sg:city":"Klamath Falls",
    "sg:classifiers":[
        {
            "category":"Professional",
            "subcategory":"Business Services",
            "type":"Services"
        }
    ],
    "sg:phone":"+1 541 882 6531",
    "sg:postcode":"97603",
    "sg:province":"OR",
    "wof:name":"James K Bryant",
    "wof:placetype":"venue"
},
  "geometry": {"coordinates":[-121.72055,42.185041],"type":"Point"}
}