{
  "type": "Feature",
  "properties": {
    "addr:full":"2701 NW Vaughn St Portland OR 97210",
    "addr:housenumber":"2701",
    "addr:postcode":"97210",
    "addr:street":"Nw Vaughn St",
    "iso:country":"US",
    "sg:address":"2701 NW Vaughn St",
    "sg:city":"Portland",
    "sg:classifiers":[
        {
            "category":"Professional",
            "subcategory":"Management & Consulting",
            "type":"Services"
        }
    ],
    "sg:phone":"+1 503 525 0253",
    "sg:postcode":"97210",
    "sg:province":"OR",
    "sg:tags":[
        "public",
        "relations"
    ],
    "wof:name":"Paxson & Associates",
    "wof:placetype":"venue"
},
  "geometry": {"coordinates":[-122.708676,45.536929],"type":"Point"}
}