{
  "type": "Feature",
  "properties": {
    "iso:country":"US",
    "sg:address":"470 NE Highway 99W",
    "sg:city":"McMinnville",
    "sg:classifiers":[
        {
            "category":"Restaurant",
            "type":"Food & Drink"
        }
    ],
    "sg:phone":"+1 503 472 2536",
    "sg:postcode":"97128",
    "sg:province":"OR",
    "sg:tags":[
        "pizza"
    ],
    "sg:website":"www.papamurphys.com",
    "wof:name":"Papa Murphy's Take'n'bake Pizza",
    "wof:placetype":"venue"
},
  "geometry": {"coordinates":[-123.194,45.223301],"type":"Point"}
}