{
  "type": "Feature",
  "properties": {
    "iso:country":"US",
    "sg:address":"600 NW 158th Ave",
    "sg:city":"Beaverton",
    "sg:classifiers":[
        {
            "category":"Real Estate",
            "subcategory":"Real Estate Operator",
            "type":"Services"
        }
    ],
    "sg:phone":"+1 503 645 7293",
    "sg:postcode":"97005",
    "sg:province":"OR",
    "sg:tags":[
        "apartment"
    ],
    "sg:website":"guardianmanagementllc.com",
    "wof:name":"Guardian Management Llc",
    "wof:placetype":"venue"
},
  "geometry": {"coordinates":[-122.839304,45.52454],"type":"Point"}
}