{
  "type": "Feature",
  "properties": {
    "addr:full":"4090 Main St Springfield OR 97478",
    "addr:housenumber":"4090",
    "addr:postcode":"97478",
    "addr:street":"Main St",
    "iso:country":"US",
    "sg:address":"4090 Main St",
    "sg:city":"Springfield",
    "sg:classifiers":[
        {
            "category":"Restaurant",
            "type":"Food & Drink"
        }
    ],
    "sg:phone":"+1 541 741 3467",
    "sg:postcode":"97478",
    "sg:province":"OR",
    "sg:tags":[
        "eating"
    ],
    "wof:name":"Fins Drive In",
    "wof:placetype":"venue"
},
  "geometry": {"coordinates":[-122.968374,44.045868],"type":"Point"}
}