{
  "type": "Feature",
  "properties": {
    "iso:country":"US",
    "sg:address":"811 W Main St",
    "sg:city":"Carlton",
    "sg:classifiers":[
        {
            "category":"Restaurant",
            "type":"Food & Drink"
        }
    ],
    "sg:phone":"+1 503 852 7400",
    "sg:postcode":"97111",
    "sg:province":"OR",
    "sg:tags":[
        "barbecue",
        "eating"
    ],
    "wof:name":"Haagenson's Mobile Bbq",
    "wof:placetype":"venue"
},
  "geometry": {"coordinates":[-123.18262900000001,45.294319],"type":"Point"}
}