{
  "type": "Feature",
  "properties": {
    "addr:full":"12000 SE 82nd Ave Ste 2084 Portland OR 97086",
    "addr:postcode":"12000;97086",
    "addr:street":"Se 82Nd Ave Ste 2084",
    "iso:country":"US",
    "sg:address":"12000 SE 82nd Ave Ste 2084",
    "sg:city":"Portland",
    "sg:classifiers":[
        {
            "category":"Shopping",
            "subcategory":"Jewelry",
            "type":"Retail Goods"
        }
    ],
    "sg:phone":"+1 503 654 9548",
    "sg:postcode":"97086",
    "sg:province":"OR",
    "sg:website":"www.kay.com",
    "wof:name":"Kay Jewelers",
    "wof:placetype":"venue"
},
  "geometry": {"coordinates":[-122.57651,45.436899],"type":"Point"}
}