{
  "type": "Feature",
  "properties": {
    "addr:full":"4643 NE Sandy Boulevard Portland OR 97213",
    "addr:housenumber":"4643",
    "addr:postcode":"97213",
    "addr:street":"Ne Sandy Boulevard",
    "iso:country":"US",
    "sg:address":"4643 NE Sandy Boulevard",
    "sg:city":"Portland",
    "sg:classifiers":[
        {
            "category":"Food & Beverages",
            "subcategory":"Groceries & Convenience Stores",
            "type":"Retail Goods"
        }
    ],
    "sg:phone":"+1 503 284 5490",
    "sg:postcode":"97213",
    "sg:province":"OR",
    "wof:name":"Seven-Eleven Food Stores",
    "wof:placetype":"venue"
},
  "geometry": {"coordinates":[-122.615388,45.538294],"type":"Point"}
}