{
  "type": "Feature",
  "properties": {
    "addr:full":"9965 SW Tualatin Sherwood Rd Tualatin OR 97062",
    "addr:housenumber":"9965",
    "addr:postcode":"97062",
    "addr:street":"Sw Tualatin Sherwood Rd",
    "iso:country":"US",
    "sg:address":"9965 SW Tualatin Sherwood Rd",
    "sg:city":"Tualatin",
    "sg:classifiers":[
        {
            "category":"Retail",
            "subcategory":"Auto Repair",
            "type":"Services"
        }
    ],
    "sg:phone":"+1 503 692 4000",
    "sg:postcode":"97062",
    "sg:province":"OR",
    "sg:tags":[
        "repairing",
        "automobile"
    ],
    "wof:name":"Sherwood Auto Repair",
    "wof:placetype":"venue"
},
  "geometry": {"coordinates":[-122.781006,45.378158],"type":"Point"}
}