{
  "type": "Feature",
  "properties": {
    "iso:country":"US",
    "sg:address":"1738 Oak Dr",
    "sg:city":"Eugene",
    "sg:classifiers":[
        {
            "category":"Food & Beverages",
            "subcategory":"Fruits & Vegetables",
            "type":"Retail Goods"
        }
    ],
    "sg:phone":"+1 541 689 7546",
    "sg:postcode":"97404",
    "sg:province":"OR",
    "wof:name":"Steve W Haworth",
    "wof:placetype":"venue"
},
  "geometry": {"coordinates":[-123.136385,44.090852],"type":"Point"}
}