{
  "type": "Feature",
  "properties": {
    "iso:country":"US",
    "sg:address":"406 N G St",
    "sg:city":"Lakeview",
    "sg:classifiers":[
        {
            "category":"Restaurant",
            "type":"Food & Drink"
        }
    ],
    "sg:phone":"+1 541 947 5655",
    "sg:postcode":"97630",
    "sg:province":"OR",
    "sg:tags":[
        "agent",
        "real estate"
    ],
    "wof:name":"El Aguila Real",
    "wof:placetype":"venue"
},
  "geometry": {"coordinates":[-120.34704000000001,42.193415],"type":"Point"}
}