{
  "type": "Feature",
  "properties": {
    "addr:full":"806 SW Broadway Ste 500 Portland OR 97205",
    "addr:housenumber":"806",
    "addr:postcode":"97205",
    "addr:street":"Sw Broadway Ste 500",
    "iso:country":"US",
    "sg:address":"806 SW Broadway Ste 500",
    "sg:city":"Portland",
    "sg:classifiers":[
        {
            "category":"Wholesale",
            "subcategory":"Groceries",
            "type":"Manufacturing & Wholesale Goods"
        }
    ],
    "sg:phone":"+1 503 227 5933",
    "sg:postcode":"97205",
    "sg:province":"OR",
    "sg:tags":[
        "grocers-wholesale"
    ],
    "wof:name":"Foodservice Economic Summit",
    "wof:placetype":"venue"
},
  "geometry": {"coordinates":[-122.679991,45.518629],"type":"Point"}
}