{
  "type": "Feature",
  "properties": {
    "iso:country":"US",
    "sg:address":"4229 3rd St",
    "sg:city":"Hubbard",
    "sg:classifiers":[
        {
            "category":"Restaurant",
            "type":"Food & Drink"
        }
    ],
    "sg:phone":"+1 503 982 0389",
    "sg:postcode":"97032",
    "sg:province":"OR",
    "wof:name":"Taqueria Lopez",
    "wof:placetype":"venue"
},
  "geometry": {"coordinates":[-122.802699,45.186203],"type":"Point"}
}