{
  "type": "Feature",
  "properties": {
    "iso:country":"US",
    "sg:address":"1312 Redwood Ave",
    "sg:city":"Grants Pass",
    "sg:classifiers":[
        {
            "category":"Home & Garden",
            "subcategory":"Hardware",
            "type":"Retail Goods"
        }
    ],
    "sg:phone":"+1 541 479 5990",
    "sg:postcode":"97527",
    "sg:province":"OR",
    "wof:name":"Oregon California Supply Inc",
    "wof:placetype":"venue"
},
  "geometry": {"coordinates":[-123.35826900000001,42.422543],"type":"Point"}
}