{
  "type": "Feature",
  "properties": {
    "addr:full":"621 SW Morrison St Ste 521 Portland OR 97205",
    "addr:housenumber":"621",
    "addr:postcode":"97205",
    "addr:street":"Sw Morrison St Ste 521",
    "iso:country":"US",
    "sg:address":"621 SW Morrison St Ste 521",
    "sg:city":"Portland",
    "sg:classifiers":[
        {
            "category":"Professional",
            "subcategory":"Lawyer & Legal Services",
            "type":"Services"
        }
    ],
    "sg:phone":"+1 503 248 0504",
    "sg:postcode":"97205",
    "sg:province":"OR",
    "sg:tags":[
        "plan"
    ],
    "wof:name":"Hunt Scott N",
    "wof:placetype":"venue"
},
  "geometry": {"coordinates":[-122.67882299999999,45.519123],"type":"Point"}
}