{
  "type": "Feature",
  "properties": {
    "addr:full":"1750 SW Allen St Corvallis OR 97333",
    "addr:housenumber":"1750",
    "addr:postcode":"97333",
    "addr:street":"Sw Allen St",
    "iso:country":"US",
    "sg:address":"1750 SW Allen St",
    "sg:city":"Corvallis",
    "sg:classifiers":[
        {
            "category":"Retail",
            "subcategory":"Auto Repair",
            "type":"Services"
        }
    ],
    "sg:phone":"+1 541 754 9390",
    "sg:postcode":"97333",
    "sg:province":"OR",
    "sg:tags":[
        "body"
    ],
    "wof:name":"South Side Repair & Paint Inc",
    "wof:placetype":"venue"
},
  "geometry": {"coordinates":[-123.270285,44.547953],"type":"Point"}
}