{
  "type": "Feature",
  "properties": {
    "addr:full":"5300 N Channel Ave Portland OR 97217",
    "addr:housenumber":"5300",
    "addr:postcode":"97217",
    "addr:street":"N Channel Ave",
    "iso:country":"US",
    "sg:address":"5300 N Channel Ave",
    "sg:city":"Portland",
    "sg:classifiers":[
        {
            "category":"Freight",
            "type":"Transportation"
        }
    ],
    "sg:phone":"+1 503 286 1897",
    "sg:postcode":"97217",
    "sg:province":"OR",
    "sg:tags":[
        "warehouse",
        "public"
    ],
    "wof:name":"Richards Homewares Inc",
    "wof:placetype":"venue"
},
  "geometry": {"coordinates":[-122.71623599999999,45.562663],"type":"Point"}
}