{
  "type": "Feature",
  "properties": {
    "iso:country":"US",
    "sg:address":"20256 Grim Rd NE",
    "sg:city":"Aurora",
    "sg:classifiers":[
        {
            "category":"Education",
            "subcategory":"School",
            "type":"Public Place"
        }
    ],
    "sg:phone":"+1 503 678 8500",
    "sg:postcode":"97002",
    "sg:province":"OR",
    "sg:tags":[
        "management",
        "sch"
    ],
    "wof:name":"North Marion School Dist 015",
    "wof:placetype":"venue"
},
  "geometry": {"coordinates":[-122.795879,45.212315],"type":"Point"}
}