{
  "type": "Feature",
  "properties": {
    "addr:full":"17300 Lake Haven Dr Lake Oswego OR 97035",
    "addr:housenumber":"17300",
    "addr:postcode":"97035",
    "addr:street":"Lake Haven Dr",
    "iso:country":"US",
    "sg:address":"17300 Lake Haven Dr",
    "sg:city":"Lake Oswego",
    "sg:classifiers":[
        {
            "category":"Professional",
            "type":"Services"
        }
    ],
    "sg:phone":"+1 503 635 4058",
    "sg:postcode":"97035",
    "sg:province":"OR",
    "wof:name":"Mertz & Company",
    "wof:placetype":"venue"
},
  "geometry": {"coordinates":[-122.71754900000001,45.401104],"type":"Point"}
}