{
  "type": "Feature",
  "properties": {
    "iso:country":"US",
    "sg:address":"12076 SE 104th Ct",
    "sg:city":"Portland",
    "sg:classifiers":[
        {
            "category":"Professional",
            "type":"Services"
        }
    ],
    "sg:phone":"+1 503 698 8607",
    "sg:postcode":"97266",
    "sg:province":"OR",
    "wof:name":"Randy E Dagel",
    "wof:placetype":"venue"
},
  "geometry": {"coordinates":[-122.55679000000001,45.443314],"type":"Point"}
}