{
  "type": "Feature",
  "properties": {
    "iso:country":"US",
    "sg:address":"6000 Hangar Rd",
    "sg:city":"Tillamook",
    "sg:classifiers":[
        {
            "category":"Professional",
            "type":"Services"
        }
    ],
    "sg:phone":"+1 503 842 1990",
    "sg:postcode":"97141",
    "sg:province":"OR",
    "sg:tags":[
        "establishment"
    ],
    "wof:name":"GSSL Inc",
    "wof:placetype":"venue"
},
  "geometry": {"coordinates":[-123.804139,45.420026],"type":"Point"}
}