{
  "type": "Feature",
  "properties": {
    "addr:full":"405 Court St NE Salem OR 97301",
    "addr:housenumber":"405",
    "addr:postcode":"97301",
    "addr:street":"Court St Ne",
    "iso:country":"US",
    "sg:address":"405 Court St NE",
    "sg:city":"Salem",
    "sg:classifiers":[
        {
            "category":"Shopping",
            "subcategory":"Jewelry",
            "type":"Retail Goods"
        }
    ],
    "sg:phone":"+1 503 581 3205",
    "sg:postcode":"97301",
    "sg:province":"OR",
    "sg:tags":[
        "jeweler"
    ],
    "wof:name":"Vernon Jewelers",
    "wof:placetype":"venue"
},
  "geometry": {"coordinates":[-123.03667299999999,44.940738],"type":"Point"}
}