{
  "type": "Feature",
  "properties": {
    "iso:country":"US",
    "sg:address":"41871 Fish Hatchery Dr",
    "sg:city":"Scio",
    "sg:classifiers":[
        {
            "category":"Professional",
            "subcategory":"Business Services",
            "type":"Services"
        }
    ],
    "sg:phone":"+1 503 394 2868",
    "sg:postcode":"97374",
    "sg:province":"OR",
    "wof:name":"Sumac Enterprises Inc",
    "wof:placetype":"venue"
},
  "geometry": {"coordinates":[-122.738814,44.630399],"type":"Point"}
}