{
  "type": "Feature",
  "properties": {
    "addr:full":"120 E California St Jacksonville OR 97530",
    "addr:housenumber":"120",
    "addr:postcode":"97530",
    "addr:street":"E California St",
    "iso:country":"US",
    "sg:address":"120 E California St",
    "sg:city":"Jacksonville",
    "sg:classifiers":[
        {
            "category":"Food & Beverages",
            "subcategory":"Specialty",
            "type":"Retail Goods"
        },
        {
            "category":"Food & Beverages",
            "subcategory":"Liquor & Beverages",
            "type":"Retail Goods"
        }
    ],
    "sg:phone":"+1 541 899 1047",
    "sg:postcode":"97530",
    "sg:province":"OR",
    "sg:tags":[
        "beer",
        "spirit",
        "wine"
    ],
    "sg:website":"www.jacksonvillemercantile.com",
    "wof:name":"Jacksonville Mercantile",
    "wof:placetype":"venue"
},
  "geometry": {"coordinates":[-122.967203,42.314035],"type":"Point"}
}