{
  "type": "Feature",
  "properties": {
    "addr:full":"520 SW Yamhill St Ste 600 Portland OR 97204",
    "addr:housenumber":"520",
    "addr:postcode":"97204",
    "addr:street":"Sw Yamhill St Ste 600",
    "iso:country":"US",
    "sg:address":"520 SW Yamhill St Ste 600",
    "sg:city":"Portland",
    "sg:classifiers":[
        {
            "category":"Health Services",
            "subcategory":"Doctor",
            "type":"Services"
        }
    ],
    "sg:phone":"+1 503 222 3531",
    "sg:postcode":"97204",
    "sg:province":"OR",
    "sg:tags":[
        "physician",
        "surgeon"
    ],
    "wof:name":"Sogge Eric",
    "wof:placetype":"venue"
},
  "geometry": {"coordinates":[-122.678173,45.51819],"type":"Point"}
}