{
  "type": "Feature",
  "properties": {
    "iso:country":"US",
    "sg:address":"9230 SW Coral St",
    "sg:city":"Portland",
    "sg:classifiers":[
        {
            "category":"Professional",
            "subcategory":"Advertising",
            "type":"Services"
        }
    ],
    "sg:phone":"+1 503 245 1952",
    "sg:postcode":"97223",
    "sg:province":"OR",
    "sg:tags":[
        "advertising-telephone",
        "fax",
        "telemarketing"
    ],
    "wof:name":"Talkbiz Telemarketing Services",
    "wof:placetype":"venue"
},
  "geometry": {"coordinates":[-122.772068,45.448007],"type":"Point"}
}