{
  "type": "Feature",
  "properties": {
    "addr:full":"10224 SW Park Way Portland OR 97225",
    "addr:housenumber":"10224",
    "addr:postcode":"97225",
    "addr:street":"Sw Park Way",
    "iso:country":"US",
    "sg:address":"10224 SW Park Way",
    "sg:city":"Portland",
    "sg:classifiers":[
        {
            "category":"Health Services",
            "subcategory":"Chiropractor",
            "type":"Services"
        }
    ],
    "sg:phone":"+1 503 297 1174",
    "sg:postcode":"97225",
    "sg:province":"OR",
    "wof:name":"Total Health Wellness Center",
    "wof:placetype":"venue"
},
  "geometry": {"coordinates":[-122.782078,45.508141],"type":"Point"}
}