{
  "type": "Feature",
  "properties": {
    "addr:full":"115 W Stewart Ave Medford OR 97501",
    "addr:housenumber":"115",
    "addr:postcode":"97501",
    "addr:street":"W Stewart Ave",
    "iso:country":"US",
    "sg:address":"115 W Stewart Ave",
    "sg:city":"Medford",
    "sg:classifiers":[
        {
            "category":"Banks & Credit Unions",
            "subcategory":"Investment Brokerage",
            "type":"Services"
        }
    ],
    "sg:phone":"+1 541 772 1600",
    "sg:postcode":"97501",
    "sg:province":"OR",
    "sg:tags":[
        "security"
    ],
    "wof:name":"Breeze James K Fincl Planner",
    "wof:placetype":"venue"
},
  "geometry": {"coordinates":[-122.86593999999999,42.312804],"type":"Point"}
}