{
  "type": "Feature",
  "properties": {
    "addr:full":"19240 SE Stark St Portland OR 97233",
    "addr:postcode":"19240;97233",
    "addr:street":"Se Stark St",
    "iso:country":"US",
    "sg:address":"19240 SE Stark St",
    "sg:city":"Portland",
    "sg:classifiers":[
        {
            "category":"Home & Garden",
            "subcategory":"Furniture",
            "type":"Retail Goods"
        }
    ],
    "sg:phone":"+1 503 489 1818",
    "sg:postcode":"97233",
    "sg:province":"OR",
    "sg:tags":[
        "store"
    ],
    "wof:name":"Yes Furniture",
    "wof:placetype":"venue"
},
  "geometry": {"coordinates":[-122.46496999999999,45.518993],"type":"Point"}
}