{
  "type": "Feature",
  "properties": {
    "addr:full":"1288 Mayanna Dr Woodburn OR 97071",
    "addr:housenumber":"1288",
    "addr:postcode":"97071",
    "addr:street":"Mayanna Dr",
    "iso:country":"US",
    "sg:address":"1288 Mayanna Dr",
    "sg:city":"Woodburn",
    "sg:classifiers":[
        {
            "category":"Professional",
            "subcategory":"Management & Consulting",
            "type":"Services"
        }
    ],
    "sg:phone":"+1 503 982 5274",
    "sg:postcode":"97071",
    "sg:province":"OR",
    "sg:tags":[
        "public",
        "relations"
    ],
    "wof:name":"Gj Promotions Inc",
    "wof:placetype":"venue"
},
  "geometry": {"coordinates":[-122.862632,45.152649],"type":"Point"}
}