{
  "type": "Feature",
  "properties": {
    "iso:country":"US",
    "sg:address":"20190 Glen Vista Rd",
    "sg:city":"Bend",
    "sg:classifiers":[
        {
            "category":"Building & Trades",
            "subcategory":"Construction",
            "type":"Services"
        }
    ],
    "sg:phone":"+1 541 383 3392",
    "sg:postcode":"97701",
    "sg:province":"OR",
    "sg:tags":[
        "floor",
        "laying",
        "contractor"
    ],
    "wof:name":"Greg W Klein Tile",
    "wof:placetype":"venue"
},
  "geometry": {"coordinates":[-121.315717,44.100539],"type":"Point"}
}