{
  "type": "Feature",
  "properties": {
    "iso:country":"US",
    "sg:address":"147 SE 1st St",
    "sg:city":"Pendleton",
    "sg:classifiers":[
        {
            "category":"Personal",
            "subcategory":"Beauty Salon",
            "type":"Services"
        }
    ],
    "sg:phone":"+1 541 276 4344",
    "sg:postcode":"97801",
    "sg:province":"OR",
    "wof:name":"Headquarters",
    "wof:placetype":"venue"
},
  "geometry": {"coordinates":[-118.78695500000001,45.673419],"type":"Point"}
}