{
  "type": "Feature",
  "properties": {
    "iso:country":"US",
    "sg:address":"1320 NE 7th St",
    "sg:city":"Grants Pass",
    "sg:classifiers":[
        {
            "category":"Manufacturing",
            "subcategory":"Tools & Machinery",
            "type":"Manufacturing & Wholesale Goods"
        }
    ],
    "sg:phone":"+1 541 472 9118",
    "sg:postcode":"97526",
    "sg:province":"OR",
    "sg:tags":[
        "electrical",
        "mfg"
    ],
    "wof:name":"Action Door & Opening Devices",
    "wof:placetype":"venue"
},
  "geometry": {"coordinates":[-123.32081599999999,42.451736],"type":"Point"}
}