{
  "type": "Feature",
  "properties": {
    "iso:country":"US",
    "sg:address":"3155 NE 76th Ave",
    "sg:city":"Portland",
    "sg:classifiers":[
        {
            "category":"Professional",
            "subcategory":"Advertising",
            "type":"Services"
        }
    ],
    "sg:phone":"+1 503 640 2011",
    "sg:postcode":"97213",
    "sg:province":"OR",
    "sg:tags":[
        "publisher"
    ],
    "wof:name":"Roy Mc Donald Assoc Inc",
    "wof:placetype":"venue"
},
  "geometry": {"coordinates":[-122.584952,45.54588],"type":"Point"}
}