{
  "type": "Feature",
  "properties": {
    "iso:country":"US",
    "sg:address":"642 Windemere St",
    "sg:city":"Aumsville",
    "sg:classifiers":[
        {
            "category":"Shopping",
            "subcategory":"Hobbies, Toys, & Games",
            "type":"Retail Goods"
        }
    ],
    "sg:phone":"+1 503 749 3248",
    "sg:postcode":"97325",
    "sg:province":"OR",
    "sg:tags":[
        "craft",
        "supply"
    ],
    "wof:name":"Shade Tree Things",
    "wof:placetype":"venue"
},
  "geometry": {"coordinates":[-122.863697,44.843557],"type":"Point"}
}