{
  "type": "Feature",
  "properties": {
    "iso:country":"US",
    "sg:address":"5970 SW Hall Blvd",
    "sg:city":"Beaverton",
    "sg:classifiers":[
        {
            "category":"Restaurant",
            "type":"Food & Drink"
        }
    ],
    "sg:phone":"+1 503 730 8059",
    "sg:postcode":"97005",
    "sg:province":"OR",
    "wof:name":"La Morenita Ricos Tacos",
    "wof:placetype":"venue"
},
  "geometry": {"coordinates":[-122.805181,45.476734],"type":"Point"}
}