{
  "type": "Feature",
  "properties": {
    "iso:country":"US",
    "sg:address":"2062 NW Jackpine Pl",
    "sg:city":"Redmond",
    "sg:classifiers":[
        {
            "category":"Building & Trades",
            "subcategory":"Construction",
            "type":"Services"
        }
    ],
    "sg:phone":"+1 541 548 3258",
    "sg:postcode":"97756",
    "sg:province":"OR",
    "sg:tags":[
        "floor",
        "laying",
        "contractor"
    ],
    "wof:name":"Flooring Guys",
    "wof:placetype":"venue"
},
  "geometry": {"coordinates":[-121.190108,44.285997],"type":"Point"}
}