{
  "type": "Feature",
  "properties": {
    "iso:country":"US",
    "sg:address":"3051 Upper River Rd",
    "sg:city":"Grants Pass",
    "sg:classifiers":[
        {
            "category":"Manufacturing",
            "subcategory":"Food",
            "type":"Manufacturing & Wholesale Goods"
        }
    ],
    "sg:phone":"+1 541 476 2020",
    "sg:postcode":"97526",
    "sg:province":"OR",
    "sg:tags":[
        "fluid",
        "milk"
    ],
    "wof:name":"Valley Of The Rogue Dairy",
    "wof:placetype":"venue"
},
  "geometry": {"coordinates":[-123.372176,42.444365],"type":"Point"}
}