{
  "type": "Feature",
  "properties": {
    "addr:full":"2035 12th St Hood River OR 97031",
    "addr:housenumber":"2035",
    "addr:postcode":"97031",
    "addr:street":"12Th St",
    "iso:country":"US",
    "sg:address":"2035 12th St",
    "sg:city":"Hood River",
    "sg:classifiers":[
        {
            "category":"Personal",
            "subcategory":"Beauty Salon",
            "type":"Services"
        }
    ],
    "sg:phone":"+1 541 386 2860",
    "sg:postcode":"97031",
    "sg:province":"OR",
    "wof:name":"United Hair Lines",
    "wof:placetype":"venue"
},
  "geometry": {"coordinates":[-121.523554,45.693562],"type":"Point"}
}