{
  "type": "Feature",
  "properties": {
    "addr:full":"737 E Harbor St Warrenton OR 97146",
    "addr:housenumber":"737 e",
    "addr:postcode":"97146",
    "addr:street":"Harbor St",
    "iso:country":"US",
    "sg:address":"737 E Harbor St",
    "sg:city":"Warrenton",
    "sg:classifiers":[
        {
            "category":"Home & Garden",
            "subcategory":"Carpets & Floor Coverings",
            "type":"Retail Goods"
        }
    ],
    "sg:phone":"+1 503 861 2251",
    "sg:postcode":"97146",
    "sg:province":"OR",
    "sg:tags":[
        "material",
        "con"
    ],
    "wof:name":"Floor Store",
    "wof:placetype":"venue"
},
  "geometry": {"coordinates":[-123.91625500000001,46.164499],"type":"Point"}
}