{
  "type": "Feature",
  "properties": {
    "iso:country":"US",
    "sg:address":"3640 NW Samaritan Dr",
    "sg:city":"Corvallis",
    "sg:classifiers":[
        {
            "category":"Health Services",
            "subcategory":"Doctor",
            "type":"Services"
        }
    ],
    "sg:phone":"+1 541 757 7463",
    "sg:postcode":"97330",
    "sg:province":"OR",
    "sg:tags":[
        "physician",
        "surgeon"
    ],
    "wof:name":"Spine Center Northwest",
    "wof:placetype":"venue"
},
  "geometry": {"coordinates":[-123.25259,44.604334],"type":"Point"}
}