{
  "type": "Feature",
  "properties": {
    "iso:country":"US",
    "sg:address":"4786 US Hwy 101",
    "sg:city":"Lincoln City",
    "sg:classifiers":[
        {
            "category":"Home & Garden",
            "subcategory":"Home Furnishings",
            "type":"Retail Goods"
        }
    ],
    "sg:phone":"+1 541 996 3825",
    "sg:postcode":"97367",
    "sg:province":"OR",
    "sg:tags":[
        "curtain",
        "made",
        "drapery"
    ],
    "wof:name":"Custom Craft Interiors",
    "wof:placetype":"venue"
},
  "geometry": {"coordinates":[-124.016993,44.929776],"type":"Point"}
}