{
  "type": "Feature",
  "properties": {
    "iso:country":"US",
    "sg:address":"1516 Westin Heights Ln",
    "sg:city":"Medford",
    "sg:classifiers":[
        {
            "category":"Professional",
            "subcategory":"Business Services",
            "type":"Services"
        }
    ],
    "sg:phone":"+1 541 608 0139",
    "sg:postcode":"97504",
    "sg:province":"OR",
    "wof:name":"New Heights Design LLC",
    "wof:placetype":"venue"
},
  "geometry": {"coordinates":[-122.864177,42.350141],"type":"Point"}
}