{
  "type": "Feature",
  "properties": {
    "iso:country":"US",
    "sg:address":"10101 SE Main St Ste 2004",
    "sg:city":"Portland",
    "sg:classifiers":[
        {
            "category":"Health Services",
            "subcategory":"Doctor",
            "type":"Services"
        }
    ],
    "sg:phone":"+1 503 257 3204",
    "sg:postcode":"97216",
    "sg:province":"OR",
    "sg:tags":[
        "throat",
        "ear",
        "nose"
    ],
    "wof:name":"Dew Leigh Ann MD",
    "wof:placetype":"venue"
},
  "geometry": {"coordinates":[-122.558998,45.514099],"type":"Point"}
}