{
  "type": "Feature",
  "properties": {
    "iso:country":"US",
    "sg:address":"3028 NE Tennesse Ln",
    "sg:city":"Prineville",
    "sg:classifiers":[
        {
            "category":"Professional",
            "subcategory":"Management & Consulting",
            "type":"Services"
        }
    ],
    "sg:phone":"+1 541 447 1514",
    "sg:postcode":"97754",
    "sg:province":"OR",
    "sg:tags":[
        "business"
    ],
    "wof:name":"James L Hancock",
    "wof:placetype":"venue"
},
  "geometry": {"coordinates":[-120.84256499999999,44.326753],"type":"Point"}
}