{
  "type": "Feature",
  "properties": {
    "iso:country":"US",
    "sg:address":"19101 SE Clinton St",
    "sg:city":"Gresham",
    "sg:classifiers":[
        {
            "category":"Taxi",
            "type":"Transportation"
        }
    ],
    "sg:phone":"+1 503 666 1284",
    "sg:postcode":"97030",
    "sg:province":"OR",
    "wof:name":"SIR Richard's Towncar Service",
    "wof:placetype":"venue"
},
  "geometry": {"coordinates":[-122.466026,45.503528],"type":"Point"}
}