{
  "type": "Feature",
  "properties": {
    "iso:country":"US",
    "sg:address":"2410 NE 23rd St",
    "sg:city":"Gresham",
    "sg:classifiers":[
        {
            "category":"Organizations",
            "subcategory":"Non-profit Organization",
            "type":"Services"
        }
    ],
    "sg:phone":"+1 503 667 4457",
    "sg:postcode":"97030",
    "sg:province":"OR",
    "sg:tags":[
        "social"
    ],
    "wof:name":"Antonio Afch",
    "wof:placetype":"venue"
},
  "geometry": {"coordinates":[-122.405421,45.512984],"type":"Point"}
}