{
  "type": "Feature",
  "properties": {
    "iso:country":"US",
    "sg:address":"467 Laneda Ave",
    "sg:city":"Manzanita",
    "sg:classifiers":[
        {
            "category":"Real Estate",
            "subcategory":"Real Estate Agent",
            "type":"Services"
        }
    ],
    "sg:phone":"+1 503 368 6609",
    "sg:postcode":"97130",
    "sg:province":"OR",
    "wof:name":"Windermere Manzanita",
    "wof:placetype":"venue"
},
  "geometry": {"coordinates":[-123.934112,45.718869],"type":"Point"}
}