{
  "type": "Feature",
  "properties": {
    "iso:country":"US",
    "sg:address":"2626 Fir St",
    "sg:city":"North Bend",
    "sg:classifiers":[
        {
            "category":"Real Estate",
            "subcategory":"Surveying",
            "type":"Services"
        }
    ],
    "sg:phone":"+1 541 756 6806",
    "sg:postcode":"97459",
    "sg:province":"OR",
    "wof:name":"Baldwin Marine Services",
    "wof:placetype":"venue"
},
  "geometry": {"coordinates":[-124.248749,43.39853],"type":"Point"}
}