{
  "type": "Feature",
  "properties": {
    "iso:country":"US",
    "sg:address":"480 River Rd",
    "sg:city":"Eugene",
    "sg:classifiers":[
        {
            "category":"Shopping",
            "subcategory":"Computers & Home Electronics",
            "type":"Retail Goods"
        }
    ],
    "sg:phone":"+1 541 461 0512",
    "sg:postcode":"97404",
    "sg:province":"OR",
    "sg:tags":[
        "accessory"
    ],
    "wof:name":"Hide A Cord",
    "wof:placetype":"venue"
},
  "geometry": {"coordinates":[-123.117797,44.068139],"type":"Point"}
}