{
  "type": "Feature",
  "properties": {
    "iso:country":"US",
    "sg:address":"24000 SW Scholls Ferry Rd",
    "sg:city":"Hillsboro",
    "sg:classifiers":[
        {
            "category":"Farming",
            "subcategory":"Farm",
            "type":"Manufacturing & Wholesale Goods"
        }
    ],
    "sg:phone":"+1 503 628 0431",
    "sg:postcode":"97123",
    "sg:province":"OR",
    "sg:tags":[
        "crop",
        "general"
    ],
    "wof:name":"Rowell Brothers Inc",
    "wof:placetype":"venue"
},
  "geometry": {"coordinates":[-122.92344300000001,45.405623],"type":"Point"}
}