{
  "type": "Feature",
  "properties": {
    "addr:full":"6442 SE 91st Ave Portland OR 97266",
    "addr:housenumber":"6442",
    "addr:postcode":"97266",
    "addr:street":"Se 91St Ave",
    "iso:country":"US",
    "sg:address":"6442 SE 91st Ave",
    "sg:city":"Portland",
    "sg:classifiers":[
        {
            "category":"Professional",
            "subcategory":"Lawyer & Legal Services",
            "type":"Services"
        }
    ],
    "sg:phone":"+1 503 772 5295",
    "sg:postcode":"97266",
    "sg:province":"OR",
    "sg:tags":[
        "divorce",
        "attorney",
        "law",
        "paralegal",
        "family"
    ],
    "wof:name":"Paralegal Alternatives",
    "wof:placetype":"venue"
},
  "geometry": {"coordinates":[-122.56965599999999,45.476123],"type":"Point"}
}