{
  "type": "Feature",
  "properties": {
    "iso:country":"US",
    "sg:address":"1248 SE Main St",
    "sg:city":"Roseburg",
    "sg:classifiers":[
        {
            "category":"Building & Trades",
            "subcategory":"Construction",
            "type":"Services"
        }
    ],
    "sg:phone":"+1 541 672 0721",
    "sg:postcode":"97470",
    "sg:province":"OR",
    "sg:tags":[
        "painter"
    ],
    "wof:name":"Terry Meyer Painting",
    "wof:placetype":"venue"
},
  "geometry": {"coordinates":[-123.346853,43.202708],"type":"Point"}
}