{
  "type": "Feature",
  "properties": {
    "addr:full":"570 Redwood Hwy Grants Pass OR 97527",
    "addr:housenumber":"570",
    "addr:postcode":"97527",
    "addr:street":"Redwood Hwy",
    "iso:country":"US",
    "sg:address":"570 Redwood Hwy",
    "sg:city":"Grants Pass",
    "sg:classifiers":[
        {
            "category":"Wholesale",
            "subcategory":"Machinery & Supplies",
            "type":"Manufacturing & Wholesale Goods"
        }
    ],
    "sg:phone":"+1 541 471 7833",
    "sg:postcode":"97527",
    "sg:province":"OR",
    "sg:tags":[
        "equipment",
        "industrial"
    ],
    "wof:name":"Cash Equipment",
    "wof:placetype":"venue"
},
  "geometry": {"coordinates":[-123.337986,42.424039],"type":"Point"}
}