{
  "type": "Feature",
  "properties": {
    "addr:full":"8391 Ashdown Ct SE Salem OR 97317",
    "addr:housenumber":"8391",
    "addr:postcode":"97317",
    "addr:street":"Ashdown Ct Se",
    "iso:country":"US",
    "sg:address":"8391 Ashdown Ct SE",
    "sg:city":"Salem",
    "sg:classifiers":[
        {
            "category":"Manufacturing",
            "subcategory":"Lumber",
            "type":"Manufacturing & Wholesale Goods"
        }
    ],
    "sg:phone":"+1 503 363 6461",
    "sg:postcode":"97317",
    "sg:province":"OR",
    "sg:tags":[
        "farm",
        "retail",
        "tree",
        "christmas"
    ],
    "wof:name":"Pronzini Christmas Tree Farms",
    "wof:placetype":"venue"
},
  "geometry": {"coordinates":[-122.887224,44.926284],"type":"Point"}
}