{
  "type": "Feature",
  "properties": {
    "addr:full":"11177 SE Mather Rd Clackamas OR 97015",
    "addr:housenumber":"11177",
    "addr:postcode":"97015",
    "addr:street":"Se Mather Rd",
    "iso:country":"US",
    "sg:address":"11177 SE Mather Rd",
    "sg:city":"Clackamas",
    "sg:classifiers":[
        {
            "category":"Personal",
            "subcategory":"Skin Care",
            "type":"Services"
        }
    ],
    "sg:phone":"+1 503 320 1712",
    "sg:postcode":"97015",
    "sg:province":"OR",
    "wof:name":"Bliss Aesthetics",
    "wof:placetype":"venue"
},
  "geometry": {"coordinates":[-122.54891000000001,45.420595],"type":"Point"}
}