{
  "type": "Feature",
  "properties": {
    "iso:country":"US",
    "sg:address":"1414 SE 82nd Ave",
    "sg:city":"Portland",
    "sg:classifiers":[
        {
            "category":"Wholesale",
            "subcategory":"Painting Supplies",
            "type":"Manufacturing & Wholesale Goods"
        }
    ],
    "sg:phone":"+1 503 255 6050",
    "sg:postcode":"97216",
    "sg:province":"OR",
    "sg:tags":[
        "paint"
    ],
    "wof:name":"Kelly-Moore Paint Company",
    "wof:placetype":"venue"
},
  "geometry": {"coordinates":[-122.578631,45.512342],"type":"Point"}
}