{
  "type": "Feature",
  "properties": {
    "addr:full":"4440 State St Salem OR 97301",
    "addr:housenumber":"4440",
    "addr:postcode":"97301",
    "addr:street":"State St",
    "iso:country":"US",
    "sg:address":"4440 State St",
    "sg:city":"Salem",
    "sg:classifiers":[
        {
            "category":"Organizations",
            "subcategory":"Religious Organization",
            "type":"Services"
        }
    ],
    "sg:phone":"+1 503 363 3726",
    "sg:postcode":"97301",
    "sg:province":"OR",
    "sg:tags":[
        "church"
    ],
    "wof:name":"Christ The Good Shepherd Chr",
    "wof:placetype":"venue"
},
  "geometry": {"coordinates":[-122.97381,44.927994],"type":"Point"}
}