{
  "type": "Feature",
  "properties": {
    "iso:country":"US",
    "sg:address":"10373 NE Hancock St Ste 131",
    "sg:city":"Portland",
    "sg:classifiers":[
        {
            "category":"Health Services",
            "subcategory":"Doctor",
            "type":"Services"
        }
    ],
    "sg:phone":"+1 503 254 1102",
    "sg:postcode":"97220",
    "sg:province":"OR",
    "wof:name":"Todd Woods, MD",
    "wof:placetype":"venue"
},
  "geometry": {"coordinates":[-122.555483,45.536583],"type":"Point"}
}