{
  "type": "Feature",
  "properties": {
    "iso:country":"US",
    "sg:address":"243 4th St",
    "sg:city":"Ashland",
    "sg:classifiers":[
        {
            "category":"Travel",
            "subcategory":"Hotels & Motels",
            "type":"Entertainment"
        }
    ],
    "sg:phone":"+1 541 488 1082",
    "sg:postcode":"97520",
    "sg:province":"OR",
    "sg:website":"www.peerlesshotel.com",
    "wof:name":"Peerless Restaurant",
    "wof:placetype":"venue"
},
  "geometry": {"coordinates":[-122.707384,42.197682],"type":"Point"}
}