{
  "type": "Feature",
  "properties": {
    "addr:full":"3195 Talbot Rd S Jefferson OR 97352",
    "addr:housenumber":"3195",
    "addr:postcode":"97352",
    "addr:street":"Talbot Rd S",
    "iso:country":"US",
    "sg:address":"3195 Talbot Rd S",
    "sg:city":"Jefferson",
    "sg:classifiers":[
        {
            "category":"Organizations",
            "subcategory":"Religious Organization",
            "type":"Services"
        }
    ],
    "sg:phone":"+1 541 327 2020",
    "sg:postcode":"97352",
    "sg:province":"OR",
    "wof:name":"Talbot Community Church",
    "wof:placetype":"venue"
},
  "geometry": {"coordinates":[-123.09596500000001,44.760888],"type":"Point"}
}