{
  "type": "Feature",
  "properties": {
    "iso:country":"US",
    "sg:address":"8073 SE 17th Avenue",
    "sg:city":"Portland",
    "sg:classifiers":[
        {
            "category":"Retail",
            "subcategory":"Auto Repair",
            "type":"Services"
        }
    ],
    "sg:phone":"+1 503 239 6699",
    "sg:postcode":"97202",
    "sg:province":"OR",
    "wof:name":"Northwest Car Care Centers",
    "wof:placetype":"venue"
},
  "geometry": {"coordinates":[-122.646885,45.464466],"type":"Point"}
}