{
  "type": "Feature",
  "properties": {
    "iso:country":"US",
    "sg:address":"915 NE Davis Street",
    "sg:city":"Portland",
    "sg:classifiers":[
        {
            "category":"Building & Trades",
            "subcategory":"Plumbing",
            "type":"Services"
        }
    ],
    "sg:phone":"+1 503 546 6686",
    "sg:postcode":"97232",
    "sg:province":"OR",
    "wof:name":"Motoczysz",
    "wof:placetype":"venue"
},
  "geometry": {"coordinates":[-122.65596499999999,45.524457],"type":"Point"}
}