{
  "type": "Feature",
  "properties": {
    "iso:country":"US",
    "sg:address":"17020 SW Upper Boones Ferry Rd",
    "sg:city":"Portland",
    "sg:classifiers":[
        {
            "category":"Real Estate",
            "subcategory":"Real Estate Agent",
            "type":"Services"
        }
    ],
    "sg:phone":"+1 503 620 0881",
    "sg:postcode":"97224",
    "sg:province":"OR",
    "sg:tags":[
        "appraiser"
    ],
    "wof:name":"Mueller & Co",
    "wof:placetype":"venue"
},
  "geometry": {"coordinates":[-122.755139,45.39566],"type":"Point"}
}