{
  "type": "Feature",
  "properties": {
    "iso:country":"US",
    "sg:address":"17252 SE McLoughlin Blvd",
    "sg:city":"Milwaukie",
    "sg:classifiers":[
        {
            "category":"Food & Beverages",
            "subcategory":"Bakery",
            "type":"Retail Goods"
        }
    ],
    "sg:phone":"+1 503 594 0303",
    "sg:postcode":"97267",
    "sg:province":"OR",
    "sg:tags":[
        "sandwich"
    ],
    "wof:name":"Original Philly's",
    "wof:placetype":"venue"
},
  "geometry": {"coordinates":[-122.634305,45.428086],"type":"Point"}
}