{
  "type": "Feature",
  "properties": {
    "iso:country":"US",
    "sg:address":"1015 Webber St",
    "sg:city":"The Dalles",
    "sg:classifiers":[
        {
            "category":"Health Services",
            "subcategory":"Nursing And Care Facility",
            "type":"Services"
        }
    ],
    "sg:phone":"+1 541 296 2156",
    "sg:postcode":"97058",
    "sg:province":"OR",
    "sg:tags":[
        "skilled"
    ],
    "wof:name":"Columbia Basin Nursing Home",
    "wof:placetype":"venue"
},
  "geometry": {"coordinates":[-121.205247,45.607718],"type":"Point"}
}