{
  "type": "Feature",
  "properties": {
    "iso:country":"US",
    "sg:address":"4004 Kruse Way",
    "sg:city":"Lake Oswego",
    "sg:classifiers":[
        {
            "category":"Banks & Credit Unions",
            "subcategory":"Bank",
            "type":"Services"
        }
    ],
    "sg:phone":"+1 503 968 3115",
    "sg:postcode":"97035",
    "sg:province":"OR",
    "sg:tags":[
        "loan",
        "real estate"
    ],
    "wof:name":"Mortgage Market Inc",
    "wof:placetype":"venue"
},
  "geometry": {"coordinates":[-122.716734,45.415983],"type":"Point"}
}