{
  "type": "Feature",
  "properties": {
    "addr:full":"13787 SW Farmington Rd # 163 Beaverton OR 97005",
    "addr:housenumber":"13787",
    "addr:postcode":"97005",
    "addr:street":"Sw Farmington Rd # 163",
    "iso:country":"US",
    "sg:address":"13787 SW Farmington Rd # 163",
    "sg:city":"Beaverton",
    "sg:classifiers":[
        {
            "category":"Building & Trades",
            "subcategory":"Landscaping Services",
            "type":"Services"
        }
    ],
    "sg:phone":"+1 503 645 2862",
    "sg:postcode":"97005",
    "sg:province":"OR",
    "sg:tags":[
        "tree"
    ],
    "wof:name":"Woodruffs Tree Service",
    "wof:placetype":"venue"
},
  "geometry": {"coordinates":[-122.818932,45.486832],"type":"Point"}
}