{
  "type": "Feature",
  "properties": {
    "iso:country":"US",
    "sg:address":"1052 NW Newport Ave",
    "sg:city":"Bend",
    "sg:classifiers":[
        {
            "category":"Shopping",
            "subcategory":"Clothing, Apparel, & Fashions",
            "type":"Retail Goods"
        }
    ],
    "sg:phone":"+1 541 385 1806",
    "sg:postcode":"97701",
    "sg:province":"OR",
    "sg:tags":[
        "infant",
        "wear"
    ],
    "wof:name":"Bambini Of Bend",
    "wof:placetype":"venue"
},
  "geometry": {"coordinates":[-121.32706399999999,44.062459],"type":"Point"}
}