{
  "type": "Feature",
  "properties": {
    "iso:country":"US",
    "sg:address":"3621 NW Marcotte Rd",
    "sg:city":"Portland",
    "sg:classifiers":[
        {
            "category":"Manufacturing",
            "subcategory":"Motor Vehicles & Parts",
            "type":"Manufacturing & Wholesale Goods"
        }
    ],
    "sg:phone":"+1 503 296 1060",
    "sg:postcode":"97229",
    "sg:province":"OR",
    "sg:tags":[
        "mfg"
    ],
    "wof:name":"Dash To Elegance",
    "wof:placetype":"venue"
},
  "geometry": {"coordinates":[-122.794616,45.549131],"type":"Point"}
}