{
  "type": "Feature",
  "properties": {
    "iso:country":"US",
    "sg:address":"2454 Lindley Way",
    "sg:city":"Klamath Falls",
    "sg:classifiers":[
        {
            "category":"Manufacturing",
            "subcategory":"Watercraft",
            "type":"Manufacturing & Wholesale Goods"
        }
    ],
    "sg:phone":"+1 541 884 6259",
    "sg:postcode":"97601",
    "sg:province":"OR",
    "wof:name":"Mallard River Boat Co",
    "wof:placetype":"venue"
},
  "geometry": {"coordinates":[-121.794462,42.209043],"type":"Point"}
}