{
  "type": "Feature",
  "properties": {
    "addr:full":"27850 Lady Slipper Loop Eugene OR 97405",
    "addr:housenumber":"27850",
    "addr:postcode":"97405",
    "addr:street":"Lady Slipper Loop",
    "iso:country":"US",
    "sg:address":"27850 Lady Slipper Loop",
    "sg:city":"Eugene",
    "sg:classifiers":[
        {
            "category":"Professional",
            "subcategory":"Business Services",
            "type":"Services"
        }
    ],
    "sg:phone":"+1 541 343 4730",
    "sg:postcode":"97405",
    "sg:province":"OR",
    "wof:name":"Sheppard West Inc",
    "wof:placetype":"venue"
},
  "geometry": {"coordinates":[-123.240697,43.972381],"type":"Point"}
}