{
  "type": "Feature",
  "properties": {
    "iso:country":"US",
    "sg:address":"541 NE 20th Ave Ste 210",
    "sg:city":"Portland",
    "sg:classifiers":[
        {
            "category":"Health Services",
            "subcategory":"Doctor",
            "type":"Services"
        }
    ],
    "sg:phone":"+1 503 233 6940",
    "sg:postcode":"97232",
    "sg:province":"OR",
    "sg:tags":[
        "physician",
        "family",
        "practice",
        "surgeons",
        "medicine"
    ],
    "sg:website":"http://www.portlandfp.com",
    "wof:name":"Moran-Yandle, Molly Md",
    "wof:placetype":"venue"
},
  "geometry": {"coordinates":[-122.64547399999999,45.526834],"type":"Point"}
}