{
  "type": "Feature",
  "properties": {
    "iso:country":"US",
    "sg:address":"1200 Cherry St Unit 34A",
    "sg:city":"Central Point",
    "sg:classifiers":[
        {
            "category":"Real Estate",
            "subcategory":"Real Estate Operator",
            "type":"Services"
        }
    ],
    "sg:phone":"+1 541 664 9307",
    "sg:postcode":"97502",
    "sg:province":"OR",
    "sg:tags":[
        "apartment"
    ],
    "wof:name":"Willow Glen Apts",
    "wof:placetype":"venue"
},
  "geometry": {"coordinates":[-122.912003,42.3825],"type":"Point"}
}