{
  "type": "Feature",
  "properties": {
    "iso:country":"US",
    "sg:address":"623 29th St",
    "sg:city":"Astoria",
    "sg:classifiers":[
        {
            "category":"Shopping",
            "subcategory":"Books",
            "type":"Retail Goods"
        }
    ],
    "sg:phone":"+1 503 325 2905",
    "sg:postcode":"97103",
    "sg:province":"OR",
    "wof:name":"Mohr Realities",
    "wof:placetype":"venue"
},
  "geometry": {"coordinates":[-123.81162,46.189646],"type":"Point"}
}