{
  "type": "Feature",
  "properties": {
    "addr:full":"2670 Webster Rd Hood River OR 97031",
    "addr:housenumber":"2670",
    "addr:postcode":"97031",
    "addr:street":"Webster Rd",
    "iso:country":"US",
    "sg:address":"2670 Webster Rd",
    "sg:city":"Hood River",
    "sg:classifiers":[
        {
            "category":"Shopping",
            "subcategory":"Gifts & Souvenirs",
            "type":"Retail Goods"
        }
    ],
    "sg:phone":"+1 541 387 3100",
    "sg:postcode":"97031",
    "sg:province":"OR",
    "sg:tags":[
        "basket",
        "parcel"
    ],
    "wof:name":"Fruit Co",
    "wof:placetype":"venue"
},
  "geometry": {"coordinates":[-121.524038,45.641657],"type":"Point"}
}