{
  "type": "Feature",
  "properties": {
    "iso:country":"US",
    "sg:address":"87939 Woodlands Dr",
    "sg:city":"Florence",
    "sg:classifiers":[
        {
            "category":"Building & Trades",
            "subcategory":"Construction",
            "type":"Services"
        }
    ],
    "sg:phone":"+1 541 902 7938",
    "sg:postcode":"97439",
    "sg:province":"OR",
    "sg:tags":[
        "painting",
        "contractor"
    ],
    "wof:name":"Doug J Castle",
    "wof:placetype":"venue"
},
  "geometry": {"coordinates":[-124.122526,44.023948],"type":"Point"}
}