{
  "type": "Feature",
  "properties": {
    "iso:country":"US",
    "sg:address":"19570 NE Ribbon Ridge Rd",
    "sg:city":"Newberg",
    "sg:classifiers":[
        {
            "category":"Professional",
            "type":"Services"
        }
    ],
    "sg:phone":"+1 503 538 1875",
    "sg:postcode":"97132",
    "sg:province":"OR",
    "wof:name":"Foster Shela",
    "wof:placetype":"venue"
},
  "geometry": {"coordinates":[-123.07445300000001,45.355233],"type":"Point"}
}