{
  "type": "Feature",
  "properties": {
    "iso:country":"US",
    "sg:address":"143 N Main St",
    "sg:city":"Phoenix",
    "sg:classifiers":[
        {
            "category":"Health Services",
            "subcategory":"Medical Lab",
            "type":"Services"
        }
    ],
    "sg:phone":"+1 541 535 6390",
    "sg:postcode":"97535",
    "sg:province":"OR",
    "sg:tags":[
        "laboratory"
    ],
    "wof:name":"Bear Creek Prosthetics",
    "wof:placetype":"venue"
},
  "geometry": {"coordinates":[-122.816667,42.275195],"type":"Point"}
}