{
  "type": "Feature",
  "properties": {
    "addr:full":"1211 NW 23rd Ave Portland OR 97210",
    "addr:housenumber":"1211",
    "addr:postcode":"97210",
    "addr:street":"Nw 23Rd Ave",
    "iso:country":"US",
    "sg:address":"1211 NW 23rd Ave",
    "sg:city":"Portland",
    "sg:classifiers":[
        {
            "category":"Personal",
            "subcategory":"Beauty Salon",
            "type":"Services"
        }
    ],
    "sg:phone":"+1 503 228 8363",
    "sg:postcode":"97210",
    "sg:province":"OR",
    "sg:tags":[
        "hair"
    ],
    "sg:website":"www.ausalon.com",
    "wof:name":"Au Salon",
    "wof:placetype":"venue"
},
  "geometry": {"coordinates":[-122.698666,45.531298],"type":"Point"}
}