{
  "type": "Feature",
  "properties": {
    "addr:full":"20225 Kerber Rd Monmouth OR 97361",
    "addr:postcode":"20225;97361",
    "addr:street":"Kerber Rd",
    "iso:country":"US",
    "sg:address":"20225 Kerber Rd",
    "sg:city":"Monmouth",
    "sg:classifiers":[
        {
            "category":"Professional",
            "subcategory":"Management & Consulting",
            "type":"Services"
        }
    ],
    "sg:phone":"+1 503 838 5031",
    "sg:postcode":"97361",
    "sg:province":"OR",
    "sg:tags":[
        "business"
    ],
    "wof:name":"Mat Pro Consulting Services",
    "wof:placetype":"venue"
},
  "geometry": {"coordinates":[-123.459694,44.729054],"type":"Point"}
}