{
  "type": "Feature",
  "properties": {
    "addr:full":"18750 Willamette Dr West Linn OR 97068",
    "addr:housenumber":"18750",
    "addr:postcode":"97068",
    "addr:street":"Willamette Dr",
    "iso:country":"US",
    "sg:address":"18750 Willamette Dr",
    "sg:city":"West Linn",
    "sg:classifiers":[
        {
            "category":"Restaurant",
            "type":"Food & Drink"
        }
    ],
    "sg:menulink":"http://www.allmenus.com/or/northwest-clackamas/77923-papa-murphys/menu/",
    "sg:phone":"+1 503 635 8224",
    "sg:postcode":"97068",
    "sg:province":"OR",
    "sg:tags":[
        "american",
        "pizza"
    ],
    "wof:name":"Papa Murphy's",
    "wof:placetype":"venue"
},
  "geometry": {"coordinates":[-122.643945,45.390359],"type":"Point"}
}