{
  "type": "Feature",
  "properties": {
    "iso:country":"US",
    "sg:address":"920 Leavitt Ln",
    "sg:city":"Grants Pass",
    "sg:classifiers":[
        {
            "category":"Manufacturing",
            "subcategory":"Motor Vehicles & Parts",
            "type":"Manufacturing & Wholesale Goods"
        }
    ],
    "sg:phone":"+1 541 471 9568",
    "sg:postcode":"97527",
    "sg:province":"OR",
    "sg:tags":[
        "mfg"
    ],
    "wof:name":"Safety 1 Motorsports Safety Co",
    "wof:placetype":"venue"
},
  "geometry": {"coordinates":[-123.418678,42.353693],"type":"Point"}
}