{
  "type": "Feature",
  "properties": {
    "iso:country":"US",
    "sg:address":"65675 E Birch Creek Rd",
    "sg:city":"Pilot Rock",
    "sg:classifiers":[
        {
            "category":"Shopping",
            "type":"Retail Goods"
        }
    ],
    "sg:phone":"+1 541 443 8631",
    "sg:postcode":"97868",
    "sg:province":"OR",
    "sg:tags":[
        "trophy",
        "medal",
        "award"
    ],
    "wof:name":"Birch Creek Trophies & Awards",
    "wof:placetype":"venue"
},
  "geometry": {"coordinates":[-118.819862,45.428008],"type":"Point"}
}