{
  "type": "Feature",
  "properties": {
    "addr:full":"2820 Upper Breckenridge Loop NW Salem OR 97304",
    "addr:housenumber":"2820",
    "addr:postcode":"97304",
    "addr:street":"Upper Breckenridge Loop Nw",
    "iso:country":"US",
    "sg:address":"2820 Upper Breckenridge Loop NW",
    "sg:city":"Salem",
    "sg:classifiers":[
        {
            "category":"Restaurant",
            "type":"Food & Drink"
        }
    ],
    "sg:phone":"+1 503 364 8755",
    "sg:postcode":"97304",
    "sg:province":"OR",
    "sg:tags":[
        "eating"
    ],
    "wof:name":"Bud Elgin Concessions",
    "wof:placetype":"venue"
},
  "geometry": {"coordinates":[-123.08854700000001,44.948756],"type":"Point"}
}