{
  "type": "Feature",
  "properties": {
    "iso:country":"US",
    "sg:address":"2820 Upper Breckenridge Loop NW",
    "sg:city":"Salem",
    "sg:classifiers":[
        {
            "category":"Restaurant",
            "type":"Food & Drink"
        }
    ],
    "sg:phone":"+1 503 364 8755",
    "sg:postcode":"97304",
    "sg:province":"OR",
    "sg:tags":[
        "eating"
    ],
    "wof:name":"Bud Elgin Concessions",
    "wof:placetype":"venue"
},
  "geometry": {"coordinates":[-123.088547,44.948756],"type":"Point"}
}