{
  "type": "Feature",
  "properties": {
    "iso:country":"US",
    "sg:address":"16145 SE Stark St",
    "sg:city":"Portland",
    "sg:classifiers":[
        {
            "category":"Professional",
            "subcategory":"Computer Services",
            "type":"Services"
        }
    ],
    "sg:phone":"+1 503 256 5707",
    "sg:postcode":"97233",
    "sg:province":"OR",
    "sg:tags":[
        "repair"
    ],
    "wof:name":"Allied Electronics Svc Ctr",
    "wof:placetype":"venue"
},
  "geometry": {"coordinates":[-122.496447,45.519155],"type":"Point"}
}