{
  "type": "Feature",
  "properties": {
    "iso:country":"US",
    "sg:address":"764 NW 4th St",
    "sg:city":"Grants Pass",
    "sg:classifiers":[
        {
            "category":"Travel",
            "subcategory":"Hotels & Motels",
            "type":"Entertainment"
        }
    ],
    "sg:phone":"+1 541 474 0426",
    "sg:postcode":"97526",
    "sg:province":"OR",
    "sg:tags":[
        "operation"
    ],
    "wof:name":"Wisteria House",
    "wof:placetype":"venue"
},
  "geometry": {"coordinates":[-123.326183,42.44544],"type":"Point"}
}