{
  "type": "Feature",
  "properties": {
    "iso:country":"US",
    "sg:address":"1158 Lorella Ave",
    "sg:city":"Eugene",
    "sg:classifiers":[
        {
            "category":"Building & Trades",
            "subcategory":"Landscaping Services",
            "type":"Services"
        }
    ],
    "sg:phone":"+1 541 302 9434",
    "sg:postcode":"97401",
    "sg:province":"OR",
    "sg:tags":[
        "landscape",
        "contractor"
    ],
    "wof:name":"Artistic Landscapes",
    "wof:placetype":"venue"
},
  "geometry": {"coordinates":[-123.097089,44.074989],"type":"Point"}
}