{
  "type": "Feature",
  "properties": {
    "iso:country":"US",
    "sg:address":"3328 Columbine St",
    "sg:city":"Lebanon",
    "sg:classifiers":[
        {
            "category":"Retail",
            "subcategory":"Repair Shop",
            "type":"Services"
        }
    ],
    "sg:phone":"+1 541 451 5951",
    "sg:postcode":"97355",
    "sg:province":"OR",
    "sg:tags":[
        "welding"
    ],
    "wof:name":"Clm Welding",
    "wof:placetype":"venue"
},
  "geometry": {"coordinates":[-122.910471,44.512988],"type":"Point"}
}