{
  "type": "Feature",
  "properties": {
    "iso:country":"US",
    "sg:address":"2141 E 15th Ave",
    "sg:city":"Eugene",
    "sg:classifiers":[
        {
            "category":"Government",
            "subcategory":"Office",
            "type":"Public Place"
        }
    ],
    "sg:phone":"+1 541 687 7492",
    "sg:postcode":"97403",
    "sg:province":"OR",
    "sg:tags":[
        "transportation"
    ],
    "wof:name":"District 5",
    "wof:placetype":"venue"
},
  "geometry": {"coordinates":[-123.060378,44.043354],"type":"Point"}
}