{
  "type": "Feature",
  "properties": {
    "iso:country":"US",
    "sg:address":"19290 S Badger Dr",
    "sg:city":"Oregon City",
    "sg:classifiers":[
        {
            "category":"Manufacturing",
            "subcategory":"Tools & Machinery",
            "type":"Manufacturing & Wholesale Goods"
        }
    ],
    "sg:phone":"+1 503 631 8047",
    "sg:postcode":"97045",
    "sg:province":"OR",
    "sg:tags":[
        "woodworking",
        "mfg"
    ],
    "wof:name":"Johnston Serena",
    "wof:placetype":"venue"
},
  "geometry": {"coordinates":[-122.470457,45.307507],"type":"Point"}
}