{
  "type": "Feature",
  "properties": {
    "iso:country":"US",
    "sg:address":"107 SE Washington Street",
    "sg:city":"Portland",
    "sg:classifiers":[
        {
            "category":"Bakery",
            "type":"Food & Drink"
        }
    ],
    "sg:phone":"+1 503 239 1932",
    "sg:postcode":"97214",
    "sg:province":"OR",
    "wof:name":"Pie In the Sky Baking Company",
    "wof:placetype":"venue"
},
  "geometry": {"coordinates":[-122.66471,45.518699],"type":"Point"}
}