{
  "type": "Feature",
  "properties": {
    "iso:country":"US",
    "sg:address":"3815 Emerald St",
    "sg:city":"Klamath Falls",
    "sg:classifiers":[
        {
            "category":"Freight",
            "type":"Transportation"
        }
    ],
    "sg:phone":"+1 541 884 0023",
    "sg:postcode":"97601",
    "sg:province":"OR",
    "sg:tags":[
        "operator",
        "local",
        "trucking"
    ],
    "wof:name":"Darrell W Jacobs",
    "wof:placetype":"venue"
},
  "geometry": {"coordinates":[-121.81116900000001,42.188569],"type":"Point"}
}