{
  "type": "Feature",
  "properties": {
    "iso:country":"US",
    "sg:address":"433 W 10th Ave",
    "sg:city":"Eugene",
    "sg:classifiers":[
        {
            "category":"Social Services",
            "type":"Services"
        }
    ],
    "sg:phone":"+1 541 345 4868",
    "sg:postcode":"97401",
    "sg:province":"OR",
    "sg:tags":[
        "counselor",
        "marriage",
        "family"
    ],
    "wof:name":"Kathy Sullivan",
    "wof:placetype":"venue"
},
  "geometry": {"coordinates":[-123.099909,44.048893],"type":"Point"}
}