{
  "type": "Feature",
  "properties": {
    "addr:full":"8636 SW Fair Ridge Way Portland OR 97223",
    "addr:housenumber":"8636",
    "addr:postcode":"97223",
    "addr:street":"Sw Fair Ridge Way",
    "iso:country":"US",
    "sg:address":"8636 SW Fair Ridge Way",
    "sg:city":"Portland",
    "sg:classifiers":[
        {
            "category":"Building & Trades",
            "subcategory":"Locksmith",
            "type":"Services"
        }
    ],
    "sg:phone":"+1 503 715 3734",
    "sg:postcode":"97223",
    "sg:province":"OR",
    "sg:tags":[
        "key"
    ],
    "wof:name":"24 7 Locksmith",
    "wof:placetype":"venue"
},
  "geometry": {"coordinates":[-122.76521099999999,45.475226],"type":"Point"}
}