{
  "type": "Feature",
  "properties": {
    "iso:country":"US",
    "sg:address":"3225 Santiam Hwy SE",
    "sg:city":"Albany",
    "sg:classifiers":[
        {
            "category":"Autos & Motor Vehicles",
            "subcategory":"Automobile Sales",
            "type":"Retail Goods"
        }
    ],
    "sg:phone":"+1 541 924 1439",
    "sg:postcode":"97322",
    "sg:province":"OR",
    "sg:tags":[
        "used"
    ],
    "wof:name":"Prestige Auto Investment",
    "wof:placetype":"venue"
},
  "geometry": {"coordinates":[-123.065224,44.630487],"type":"Point"}
}