{
  "type": "Feature",
  "properties": {
    "addr:full":"2405 Eastside Rd Hood River OR 97031",
    "addr:housenumber":"2405",
    "addr:postcode":"97031",
    "addr:street":"Eastside Rd",
    "iso:country":"US",
    "sg:address":"2405 Eastside Rd",
    "sg:city":"Hood River",
    "sg:classifiers":[
        {
            "category":"Education",
            "subcategory":"School",
            "type":"Public Place"
        }
    ],
    "sg:phone":"+1 541 386 4919",
    "sg:postcode":"97031",
    "sg:province":"OR",
    "wof:name":"Pine Grove Elementary School",
    "wof:placetype":"venue"
},
  "geometry": {"coordinates":[-121.497423,45.653875],"type":"Point"}
}