{
  "type": "Feature",
  "properties": {
    "iso:country":"US",
    "sg:address":"12355 NE Honey Ln",
    "sg:city":"Newberg",
    "sg:classifiers":[
        {
            "category":"Mining & Drilling",
            "type":"Manufacturing & Wholesale Goods"
        }
    ],
    "sg:phone":"+1 503 538 4708",
    "sg:postcode":"97132",
    "sg:province":"OR",
    "sg:tags":[
        "construction"
    ],
    "wof:name":"Nitty Gritty Process Inc",
    "wof:placetype":"venue"
},
  "geometry": {"coordinates":[-122.988214,45.304809],"type":"Point"}
}