{
  "type": "Feature",
  "properties": {
    "iso:country":"US",
    "sg:address":"385 SW 1st Ave",
    "sg:city":"Canby",
    "sg:classifiers":[
        {
            "category":"Travel",
            "subcategory":"Travel Agent",
            "type":"Entertainment"
        }
    ],
    "sg:phone":"+1 503 263 2996",
    "sg:postcode":"97013",
    "sg:province":"OR",
    "sg:tags":[
        "agency"
    ],
    "wof:name":"Amigo Express",
    "wof:placetype":"venue"
},
  "geometry": {"coordinates":[-122.69511,45.261123],"type":"Point"}
}