{
  "type": "Feature",
  "properties": {
    "iso:country":"US",
    "sg:address":"6550 Childs Rd",
    "sg:city":"Lake Oswego",
    "sg:classifiers":[
        {
            "category":"Wholesale",
            "subcategory":"Home Furnishings",
            "type":"Manufacturing & Wholesale Goods"
        }
    ],
    "sg:phone":"+1 503 624 1314",
    "sg:postcode":"97035",
    "sg:province":"OR",
    "sg:tags":[
        "hardwood"
    ],
    "wof:name":"Lake Forest Products",
    "wof:placetype":"venue"
},
  "geometry": {"coordinates":[-122.749757,45.388096],"type":"Point"}
}