{
  "type": "Feature",
  "properties": {
    "addr:full":"243 E Main St Ashland OR 97520",
    "addr:housenumber":"243",
    "addr:postcode":"97520",
    "addr:street":"E Main St",
    "iso:country":"US",
    "sg:address":"243 E Main St",
    "sg:city":"Ashland",
    "sg:classifiers":[
        {
            "category":"Banks & Credit Unions",
            "subcategory":"Bank",
            "type":"Services"
        }
    ],
    "sg:phone":"+1 541 482 4321",
    "sg:postcode":"97520",
    "sg:province":"OR",
    "sg:website":"www.wamu.com",
    "wof:name":"Washington Mutual",
    "wof:placetype":"venue"
},
  "geometry": {"coordinates":[-122.711973,42.195696],"type":"Point"}
}