{
  "type": "Feature",
  "properties": {
    "addr:full":"35251 SE Crescent Rd Boring OR 97009",
    "addr:housenumber":"35251",
    "addr:postcode":"97009",
    "addr:street":"Se Crescent Rd",
    "iso:country":"US",
    "sg:address":"35251 SE Crescent Rd",
    "sg:city":"Boring",
    "sg:classifiers":[
        {
            "category":"Building & Trades",
            "subcategory":"Construction",
            "type":"Services"
        }
    ],
    "sg:phone":"+1 503 668 7551",
    "sg:postcode":"97009",
    "sg:province":"OR",
    "sg:tags":[
        "general",
        "contractor"
    ],
    "wof:name":"Cannon Construction",
    "wof:placetype":"venue"
},
  "geometry": {"coordinates":[-122.298608,45.411709],"type":"Point"}
}