{
  "type": "Feature",
  "properties": {
    "iso:country":"US",
    "sg:address":"1175 Sequoia Ave",
    "sg:city":"Springfield",
    "sg:classifiers":[
        {
            "category":"Building & Trades",
            "subcategory":"Construction",
            "type":"Services"
        }
    ],
    "sg:phone":"+1 541 747 7602",
    "sg:postcode":"97477",
    "sg:province":"OR",
    "sg:tags":[
        "flooring",
        "contractor"
    ],
    "wof:name":"Sidney R Marks",
    "wof:placetype":"venue"
},
  "geometry": {"coordinates":[-123.041141,44.05665],"type":"Point"}
}