{
  "type": "Feature",
  "properties": {
    "iso:country":"US",
    "sg:address":"1825 SE 181st Ave",
    "sg:city":"Portland",
    "sg:classifiers":[
        {
            "category":"Health Services",
            "subcategory":"Nursing And Care Facility",
            "type":"Services"
        }
    ],
    "sg:phone":"+1 503 762 0952",
    "sg:postcode":"97233",
    "sg:province":"OR",
    "wof:name":"Bell Thomas Adult Care Home",
    "wof:placetype":"venue"
},
  "geometry": {"coordinates":[-122.47690799999999,45.509269],"type":"Point"}
}