{
  "type": "Feature",
  "properties": {
    "addr:full":"4512 Jones Rd SE Salem OR 97302",
    "addr:housenumber":"4512",
    "addr:postcode":"97302",
    "addr:street":"Jones Rd Se",
    "iso:country":"US",
    "sg:address":"4512 Jones Rd SE",
    "sg:city":"Salem",
    "sg:classifiers":[
        {
            "category":"Education",
            "subcategory":"School",
            "type":"Public Place"
        }
    ],
    "sg:phone":"+1 503 399 3201",
    "sg:postcode":"97302",
    "sg:province":"OR",
    "wof:name":"Judson Middle School",
    "wof:placetype":"venue"
},
  "geometry": {"coordinates":[-123.04584699999999,44.888617],"type":"Point"}
}