{
  "type": "Feature",
  "properties": {
    "iso:country":"US",
    "sg:address":"4512 Jones Rd SE",
    "sg:city":"Salem",
    "sg:classifiers":[
        {
            "category":"Education",
            "subcategory":"School",
            "type":"Public Place"
        }
    ],
    "sg:phone":"+1 503 399 3201",
    "sg:postcode":"97302",
    "sg:province":"OR",
    "wof:name":"Judson Middle School",
    "wof:placetype":"venue"
},
  "geometry": {"coordinates":[-123.045847,44.888617],"type":"Point"}
}