{
  "type": "Feature",
  "properties": {
    "addr:full":"703 S Main St Milton Freewater OR 97862",
    "addr:housenumber":"703",
    "addr:postcode":"97862",
    "addr:street":"S Main St;Freewater",
    "iso:country":"US",
    "sg:address":"703 S Main St",
    "sg:city":"Milton Freewater",
    "sg:classifiers":[
        {
            "category":"Organizations",
            "subcategory":"Religious Organization",
            "type":"Services"
        }
    ],
    "sg:phone":"+1 541 938 3842",
    "sg:postcode":"97862",
    "sg:province":"OR",
    "wof:name":"Grace Presbyterian Church",
    "wof:placetype":"venue"
},
  "geometry": {"coordinates":[-118.385375,45.929023],"type":"Point"}
}