{
  "type": "Feature",
  "properties": {
    "iso:country":"US",
    "sg:address":"4449 Homedale Rd",
    "sg:city":"Klamath Falls",
    "sg:classifiers":[
        {
            "category":"Food & Beverages",
            "subcategory":"Groceries & Convenience Stores",
            "type":"Retail Goods"
        }
    ],
    "sg:phone":"+1 541 882 3726",
    "sg:postcode":"97603",
    "sg:province":"OR",
    "wof:name":"Ultramart",
    "wof:placetype":"venue"
},
  "geometry": {"coordinates":[-121.72263,42.185564],"type":"Point"}
}