{
  "type": "Feature",
  "properties": {
    "addr:full":"95165 Aldrich Point Rd Astoria OR 97103",
    "addr:housenumber":"95165",
    "addr:postcode":"97103",
    "addr:street":"Aldrich Point Rd",
    "iso:country":"US",
    "sg:address":"95165 Aldrich Point Rd",
    "sg:city":"Astoria",
    "sg:classifiers":[
        {
            "category":"Farming",
            "subcategory":"Dairy Farm",
            "type":"Manufacturing & Wholesale Goods"
        }
    ],
    "sg:phone":"+1 503 458 6442",
    "sg:postcode":"97103",
    "sg:province":"OR",
    "wof:name":"Aldrich Point Dairy",
    "wof:placetype":"venue"
},
  "geometry": {"coordinates":[-123.51447899999999,46.224719],"type":"Point"}
}