{
  "type": "Feature",
  "properties": {
    "iso:country":"US",
    "sg:address":"205 N Pacific Hwy",
    "sg:city":"Talent",
    "sg:classifiers":[
        {
            "category":"Shopping",
            "subcategory":"Pharmacy",
            "type":"Retail Goods"
        }
    ],
    "sg:phone":"+1 541 535 5843",
    "sg:postcode":"97540",
    "sg:province":"OR",
    "sg:website":"http://www.medicap.com/8178.aspx",
    "wof:name":"Medicap Pharmacy",
    "wof:placetype":"venue"
},
  "geometry": {"coordinates":[-122.79586999999999,42.255011],"type":"Point"}
}