{
  "type": "Feature",
  "properties": {
    "iso:country":"US",
    "sg:address":"98 Shady Loop",
    "sg:city":"Springfield",
    "sg:classifiers":[
        {
            "category":"Building & Trades",
            "subcategory":"Construction",
            "type":"Services"
        }
    ],
    "sg:phone":"+1 541 988 0316",
    "sg:postcode":"97477",
    "sg:province":"OR",
    "sg:tags":[
        "contractor"
    ],
    "wof:name":"Handy Dandy Contracting Svc",
    "wof:placetype":"venue"
},
  "geometry": {"coordinates":[-123.026243,44.066356],"type":"Point"}
}