{
  "type": "Feature",
  "properties": {
    "iso:country":"US",
    "sg:address":"736 SW 7th St",
    "sg:city":"Redmond",
    "sg:classifiers":[
        {
            "category":"Health Services",
            "subcategory":"Health Practitioner",
            "type":"Services"
        }
    ],
    "sg:phone":"+1 541 617 8398",
    "sg:postcode":"97756",
    "sg:province":"OR",
    "wof:name":"Rachel Lmt Esmt Smith",
    "wof:placetype":"venue"
},
  "geometry": {"coordinates":[-121.175262,44.271552],"type":"Point"}
}