{
  "type": "Feature",
  "properties": {
    "iso:country":"US",
    "sg:address":"14020 SW Teal Blvd",
    "sg:city":"Beaverton",
    "sg:classifiers":[
        {
            "category":"Professional",
            "subcategory":"Management & Consulting",
            "type":"Services"
        }
    ],
    "sg:phone":"+1 503 293 0704",
    "sg:postcode":"97008",
    "sg:province":"OR",
    "wof:name":"Regal Marketing",
    "wof:placetype":"venue"
},
  "geometry": {"coordinates":[-122.82098000000001,45.441338],"type":"Point"}
}