{
  "type": "Feature",
  "properties": {
    "addr:full":"13610 Barclay Hills Dr Oregon City OR 97045",
    "addr:housenumber":"13610",
    "addr:postcode":"97045",
    "addr:street":"Barclay Hills Dr",
    "iso:country":"US",
    "sg:address":"13610 Barclay Hills Dr",
    "sg:city":"Oregon City",
    "sg:classifiers":[
        {
            "category":"Recreation",
            "type":"Entertainment"
        }
    ],
    "sg:phone":"+1 503 650 8280",
    "sg:postcode":"97045",
    "sg:province":"OR",
    "sg:tags":[
        "party",
        "fishing"
    ],
    "wof:name":"Wildlife Fishing Adventures",
    "wof:placetype":"venue"
},
  "geometry": {"coordinates":[-122.590453,45.343819],"type":"Point"}
}