{
  "type": "Feature",
  "properties": {
    "iso:country":"US",
    "sg:address":"91 Darrell Ave",
    "sg:city":"Winston",
    "sg:classifiers":[
        {
            "category":"Professional",
            "type":"Services"
        }
    ],
    "sg:phone":"+1 541 679 4594",
    "sg:postcode":"97496",
    "sg:province":"OR",
    "wof:name":"Bryce McSperitt",
    "wof:placetype":"venue"
},
  "geometry": {"coordinates":[-123.408776,43.121281],"type":"Point"}
}