{
  "type": "Feature",
  "properties": {
    "iso:country":"US",
    "sg:address":"2947 SE Maple Pl",
    "sg:city":"Gresham",
    "sg:classifiers":[
        {
            "category":"Building & Trades",
            "subcategory":"Construction",
            "type":"Services"
        }
    ],
    "sg:phone":"+1 503 665 9700",
    "sg:postcode":"97080",
    "sg:province":"OR",
    "sg:tags":[
        "house"
    ],
    "wof:name":"Matt Stotts Construction Inc",
    "wof:placetype":"venue"
},
  "geometry": {"coordinates":[-122.417601,45.476578],"type":"Point"}
}