{
  "type": "Feature",
  "properties": {
    "iso:country":"US",
    "sg:address":"923 NE Broadway St",
    "sg:city":"Portland",
    "sg:classifiers":[
        {
            "category":"Food & Beverages",
            "subcategory":"Specialty",
            "type":"Retail Goods"
        }
    ],
    "sg:phone":"+1 503 284 3055",
    "sg:postcode":"97232",
    "sg:province":"OR",
    "sg:tags":[
        "health",
        "diet"
    ],
    "wof:name":"Pearl Fitness Nutrition",
    "wof:placetype":"venue"
},
  "geometry": {"coordinates":[-122.655716,45.535131],"type":"Point"}
}