{
  "type": "Feature",
  "properties": {
    "addr:full":"761 NW 12th St Gresham OR 97030",
    "addr:housenumber":"761",
    "addr:postcode":"97030",
    "addr:street":"Nw 12Th St",
    "iso:country":"US",
    "sg:address":"761 NW 12th St",
    "sg:city":"Gresham",
    "sg:classifiers":[
        {
            "category":"Shopping",
            "subcategory":"Clothing, Apparel, & Fashions",
            "type":"Retail Goods"
        }
    ],
    "sg:phone":"+1 503 667 1158",
    "sg:postcode":"97030",
    "sg:province":"OR",
    "sg:tags":[
        "ready",
        "sportswear"
    ],
    "sg:website":"www.lanebryant.com",
    "wof:name":"Lane Bryant",
    "wof:placetype":"venue"
},
  "geometry": {"coordinates":[-122.44042399999999,45.50592],"type":"Point"}
}