{
  "type": "Feature",
  "properties": {
    "iso:country":"US",
    "sg:address":"1100 6th St",
    "sg:city":"Woodburn",
    "sg:classifiers":[
        {
            "category":"Organizations",
            "subcategory":"Religious Organization",
            "type":"Services"
        }
    ],
    "sg:phone":"+1 503 981 6216",
    "sg:postcode":"97071",
    "sg:province":"OR",
    "sg:tags":[
        "place",
        "worship",
        "church"
    ],
    "sg:website":"http://www.adventist.org",
    "wof:name":"Seventh -Day Adventist Church",
    "wof:placetype":"venue"
},
  "geometry": {"coordinates":[-122.85632,45.149163],"type":"Point"}
}