{
  "type": "Feature",
  "properties": {
    "addr:full":"8518 SW Charlotte Dr Beaverton OR 97007",
    "addr:housenumber":"8518",
    "addr:postcode":"97007",
    "addr:street":"Sw Charlotte Dr",
    "iso:country":"US",
    "sg:address":"8518 SW Charlotte Dr",
    "sg:city":"Beaverton",
    "sg:classifiers":[
        {
            "category":"Professional",
            "subcategory":"Computer Services",
            "type":"Services"
        }
    ],
    "sg:phone":"+1 503 356 1581",
    "sg:postcode":"97007",
    "sg:province":"OR",
    "sg:tags":[
        "engineering",
        "consulting",
        "software"
    ],
    "wof:name":"Softstar Research Inc",
    "wof:placetype":"venue"
},
  "geometry": {"coordinates":[-122.853331,45.45957],"type":"Point"}
}