{
  "type": "Feature",
  "properties": {
    "addr:full":"235 N Front St Woodburn OR 97071",
    "addr:housenumber":"235",
    "addr:postcode":"97071",
    "addr:street":"N Front St",
    "iso:country":"US",
    "sg:address":"235 N Front St",
    "sg:city":"Woodburn",
    "sg:classifiers":[
        {
            "category":"Home & Garden",
            "subcategory":"Household Appliances",
            "type":"Retail Goods"
        }
    ],
    "sg:phone":"+1 503 982 1171",
    "sg:postcode":"97071",
    "sg:province":"OR",
    "sg:tags":[
        "appliances-small"
    ],
    "wof:name":"May's Furniture Co",
    "wof:placetype":"venue"
},
  "geometry": {"coordinates":[-122.857186,45.141915],"type":"Point"}
}