{
  "type": "Feature",
  "properties": {
    "addr:full":"248 Commercial St NE Salem OR 97301",
    "addr:housenumber":"248",
    "addr:postcode":"97301",
    "addr:street":"Commercial St Ne",
    "iso:country":"US",
    "sg:address":"248 Commercial St NE",
    "sg:city":"Salem",
    "sg:classifiers":[
        {
            "category":"Professional",
            "subcategory":"Art Services",
            "type":"Services"
        }
    ],
    "sg:phone":"+1 503 588 7121",
    "sg:postcode":"97301",
    "sg:province":"OR",
    "sg:tags":[
        "photography",
        "commercial"
    ],
    "wof:name":"Kelly James Photography",
    "wof:placetype":"venue"
},
  "geometry": {"coordinates":[-123.039525,44.94204],"type":"Point"}
}