{
  "type": "Feature",
  "properties": {
    "iso:country":"US",
    "sg:address":"46411 Oliver Rd",
    "sg:city":"Halfway",
    "sg:classifiers":[
        {
            "category":"Professional",
            "subcategory":"Management & Consulting",
            "type":"Services"
        }
    ],
    "sg:phone":"+1 541 742 6111",
    "sg:postcode":"97834",
    "sg:province":"OR",
    "sg:tags":[
        "ranching"
    ],
    "wof:name":"Barry R Delcurto",
    "wof:placetype":"venue"
},
  "geometry": {"coordinates":[-117.073336,44.898096],"type":"Point"}
}