{
  "type": "Feature",
  "properties": {
    "addr:full":"1154 Commercial St Astoria OR 97103",
    "addr:housenumber":"1154",
    "addr:postcode":"97103",
    "addr:street":"Commercial St",
    "iso:country":"US",
    "sg:address":"1154 Commercial St",
    "sg:city":"Astoria",
    "sg:classifiers":[
        {
            "category":"Sports & Exercise",
            "subcategory":"Gym",
            "type":"Entertainment"
        }
    ],
    "sg:phone":"+1 503 338 1294",
    "sg:postcode":"97103",
    "sg:province":"OR",
    "sg:tags":[
        "club",
        "health",
        "studio",
        "gymnasium"
    ],
    "wof:name":"Curves For Women",
    "wof:placetype":"venue"
},
  "geometry": {"coordinates":[-123.83114,46.189095],"type":"Point"}
}