{
  "type": "Feature",
  "properties": {
    "iso:country":"US",
    "sg:address":"1240 Lone Mountain Rd",
    "sg:city":"O Brien",
    "sg:classifiers":[
        {
            "category":"Building & Trades",
            "subcategory":"Construction",
            "type":"Services"
        }
    ],
    "sg:phone":"+1 541 596 2527",
    "sg:postcode":"97534",
    "sg:province":"OR",
    "wof:name":"Hopkins",
    "wof:placetype":"venue"
},
  "geometry": {"coordinates":[-123.720412,42.066802],"type":"Point"}
}