{
  "type": "Feature",
  "properties": {
    "iso:country":"US",
    "sg:address":"4440 SW Corbett Ave",
    "sg:city":"Portland",
    "sg:classifiers":[
        {
            "category":"Manufacturing",
            "subcategory":"Printing",
            "type":"Manufacturing & Wholesale Goods"
        }
    ],
    "sg:phone":"+1 503 228 4257",
    "sg:postcode":"97239",
    "sg:province":"OR",
    "sg:tags":[
        "typesetting"
    ],
    "wof:name":"Typemasters",
    "wof:placetype":"venue"
},
  "geometry": {"coordinates":[-122.67616099999999,45.491921],"type":"Point"}
}