{
  "type": "Feature",
  "properties": {
    "addr:full":"1130 SW Morrison St Portland OR 97205",
    "addr:housenumber":"1130",
    "addr:postcode":"97205",
    "addr:street":"Sw Morrison St",
    "iso:country":"US",
    "sg:address":"1130 SW Morrison St",
    "sg:city":"Portland",
    "sg:classifiers":[
        {
            "category":"Manufacturing",
            "subcategory":"Printing",
            "type":"Manufacturing & Wholesale Goods"
        }
    ],
    "sg:phone":"+1 503 244 9045",
    "sg:postcode":"97205",
    "sg:province":"OR",
    "sg:tags":[
        "book"
    ],
    "wof:name":"Facts For Fiction",
    "wof:placetype":"venue"
},
  "geometry": {"coordinates":[-122.68395099999999,45.520402],"type":"Point"}
}