{
  "type": "Feature",
  "properties": {
    "iso:country":"US",
    "sg:address":"421 W 10th St",
    "sg:city":"Medford",
    "sg:classifiers":[
        {
            "category":"Health Services",
            "subcategory":"Clinic",
            "type":"Services"
        }
    ],
    "sg:phone":"+1 541 857 9195",
    "sg:postcode":"97501",
    "sg:province":"OR",
    "sg:tags":[
        "home"
    ],
    "wof:name":"All Care In Home Support Svc",
    "wof:placetype":"venue"
},
  "geometry": {"coordinates":[-122.87515999999999,42.321365],"type":"Point"}
}