{
  "type": "Feature",
  "properties": {
    "addr:full":"745 Willamette St Eugene OR 97401",
    "addr:housenumber":"745",
    "addr:postcode":"97401",
    "addr:street":"Willamette St",
    "iso:country":"US",
    "sg:address":"745 Willamette St",
    "sg:city":"Eugene",
    "sg:classifiers":[
        {
            "category":"Personal",
            "subcategory":"Barber",
            "type":"Services"
        }
    ],
    "sg:phone":"+1 541 345 4644",
    "sg:postcode":"97401",
    "sg:province":"OR",
    "sg:tags":[
        "shop"
    ],
    "wof:name":"Anderson's Barber Shop",
    "wof:placetype":"venue"
},
  "geometry": {"coordinates":[-123.092662,44.051528],"type":"Point"}
}