{
  "type": "Feature",
  "properties": {
    "addr:full":"501 N Graham St Portland OR 97227",
    "addr:housenumber":"501",
    "addr:postcode":"97227",
    "addr:street":"N Graham St",
    "iso:country":"US",
    "sg:address":"501 N Graham St",
    "sg:city":"Portland",
    "sg:classifiers":[
        {
            "category":"Health Services",
            "subcategory":"Doctor",
            "type":"Services"
        }
    ],
    "sg:phone":"+1 503 528 0704",
    "sg:postcode":"97227",
    "sg:province":"OR",
    "wof:name":"Zeklo John MD",
    "wof:placetype":"venue"
},
  "geometry": {"coordinates":[-122.67044,45.542967],"type":"Point"}
}