{
  "type": "Feature",
  "properties": {
    "iso:country":"US",
    "sg:address":"2611 SW 3rd Ave",
    "sg:city":"Portland",
    "sg:classifiers":[
        {
            "category":"Professional",
            "type":"Services"
        }
    ],
    "sg:phone":"+1 503 478 9876",
    "sg:postcode":"97201",
    "sg:province":"OR",
    "wof:name":"Columbia Biotechnologies Corp",
    "wof:placetype":"venue"
},
  "geometry": {"coordinates":[-122.68091800000001,45.505019],"type":"Point"}
}