{
  "type": "Feature",
  "properties": {
    "iso:country":"US",
    "sg:address":"712 NW 3rd Dr",
    "sg:city":"Pendleton",
    "sg:classifiers":[
        {
            "category":"Bars & Pubs",
            "type":"Food & Drink"
        }
    ],
    "sg:phone":"+1 541 278 9397",
    "sg:postcode":"97801",
    "sg:province":"OR",
    "sg:tags":[
        "drinking"
    ],
    "wof:name":"Home Based Business",
    "wof:placetype":"venue"
},
  "geometry": {"coordinates":[-118.790433,45.679384],"type":"Point"}
}