{
  "type": "Feature",
  "properties": {
    "iso:country":"US",
    "sg:address":"1225 SW Alder St",
    "sg:city":"Portland",
    "sg:classifiers":[
        {
            "category":"Shopping",
            "subcategory":"Luggage & Leather Goods",
            "type":"Retail Goods"
        }
    ],
    "sg:phone":"+1 503 274 0316",
    "sg:postcode":"97205",
    "sg:province":"OR",
    "wof:name":"Mexican Leather",
    "wof:placetype":"venue"
},
  "geometry": {"coordinates":[-122.684642,45.521505],"type":"Point"}
}