{
  "type": "Feature",
  "properties": {
    "addr:full":"1800 Valley River Dr Eugene OR 97401",
    "addr:housenumber":"1800",
    "addr:postcode":"97401",
    "addr:street":"Valley River Dr",
    "iso:country":"US",
    "sg:address":"1800 Valley River Dr",
    "sg:city":"Eugene",
    "sg:classifiers":[
        {
            "category":"Health Services",
            "subcategory":"Doctor",
            "type":"Services"
        }
    ],
    "sg:phone":"+1 541 344 6058",
    "sg:postcode":"97401",
    "sg:province":"OR",
    "sg:tags":[
        "dentist"
    ],
    "wof:name":"Cascade Dental",
    "wof:placetype":"venue"
},
  "geometry": {"coordinates":[-123.108628,44.071113],"type":"Point"}
}