{
  "type": "Feature",
  "properties": {
    "iso:country":"US",
    "sg:address":"2530 Pacific Blvd SE",
    "sg:city":"Albany",
    "sg:classifiers":[
        {
            "category":"Building & Trades",
            "subcategory":"Construction",
            "type":"Services"
        }
    ],
    "sg:phone":"+1 541 926 3869",
    "sg:postcode":"97321",
    "sg:province":"OR",
    "sg:tags":[
        "contractor"
    ],
    "wof:name":"Gen Baldwin Contracting Inc",
    "wof:placetype":"venue"
},
  "geometry": {"coordinates":[-123.07499,44.636886],"type":"Point"}
}