{
  "type": "Feature",
  "properties": {
    "iso:country":"US",
    "sg:address":"6560 SW Oleson Rd",
    "sg:city":"Portland",
    "sg:classifiers":[
        {
            "category":"Home & Garden",
            "subcategory":"Home Furnishings",
            "type":"Retail Goods"
        }
    ],
    "sg:phone":"+1 503 244 4665",
    "sg:postcode":"97223",
    "sg:province":"OR",
    "wof:name":"Home Front",
    "wof:placetype":"venue"
},
  "geometry": {"coordinates":[-122.748383,45.47263],"type":"Point"}
}