{
  "type": "Feature",
  "properties": {
    "iso:country":"US",
    "sg:address":"2065 NW Buchanan Ave",
    "sg:city":"Corvallis",
    "sg:classifiers":[
        {
            "category":"Banks & Credit Unions",
            "subcategory":"Bank",
            "type":"Services"
        }
    ],
    "sg:phone":"+1 541 758 6000",
    "sg:postcode":"97330",
    "sg:province":"OR",
    "sg:tags":[
        "depository",
        "banking"
    ],
    "wof:name":"Cash Store",
    "wof:placetype":"venue"
},
  "geometry": {"coordinates":[-123.27355799999999,44.576125],"type":"Point"}
}