{
  "type": "Feature",
  "properties": {
    "iso:country":"US",
    "sg:address":"1683 NE Northview Dr",
    "sg:city":"Bend",
    "sg:classifiers":[
        {
            "category":"Building & Trades",
            "subcategory":"Construction",
            "type":"Services"
        }
    ],
    "sg:phone":"+1 541 382 0088",
    "sg:postcode":"97701",
    "sg:province":"OR",
    "sg:tags":[
        "painter"
    ],
    "wof:name":"Deschutes Painting",
    "wof:placetype":"venue"
},
  "geometry": {"coordinates":[-121.280766,44.068864],"type":"Point"}
}