{
  "type": "Feature",
  "properties": {
    "iso:country":"US",
    "sg:address":"1761 Washburn Way",
    "sg:city":"Klamath Falls",
    "sg:classifiers":[
        {
            "category":"Insurance",
            "subcategory":"Insurance Agent",
            "type":"Services"
        }
    ],
    "sg:phone":"+1 541 883 3227",
    "sg:postcode":"97603",
    "sg:province":"OR",
    "wof:name":"Sharleen Hutchinson Insurance",
    "wof:placetype":"venue"
},
  "geometry": {"coordinates":[-121.75707,42.212778],"type":"Point"}
}