{
  "type": "Feature",
  "properties": {
    "iso:country":"US",
    "sg:address":"1436 NW Everett Street",
    "sg:city":"Portland",
    "sg:classifiers":[
        {
            "category":"Retail",
            "subcategory":"Auto Repair",
            "type":"Services"
        }
    ],
    "sg:phone":"+1 503 241 2697",
    "sg:postcode":"97209",
    "sg:province":"OR",
    "wof:name":"Maddog Garage",
    "wof:placetype":"venue"
},
  "geometry": {"coordinates":[-122.68592,45.525141],"type":"Point"}
}