{
  "type": "Feature",
  "properties": {
    "iso:country":"US",
    "sg:address":"4875 SW Angel Ave",
    "sg:city":"Beaverton",
    "sg:classifiers":[
        {
            "category":"Professional",
            "subcategory":"Business Services",
            "type":"Services"
        },
        {
            "category":"Home & Garden",
            "subcategory":"Furniture",
            "type":"Retail Goods"
        }
    ],
    "sg:phone":"+1 503 646 8191",
    "sg:postcode":"97005",
    "sg:province":"OR",
    "sg:tags":[
        "interior",
        "design"
    ],
    "wof:name":"En Vogue Interiors",
    "wof:placetype":"venue"
},
  "geometry": {"coordinates":[-122.806999,45.485199],"type":"Point"}
}