{
  "type": "Feature",
  "properties": {
    "iso:country":"US",
    "sg:address":"2976 Edison Rd NE",
    "sg:city":"Silverton",
    "sg:classifiers":[
        {
            "category":"Building & Trades",
            "subcategory":"Construction",
            "type":"Services"
        }
    ],
    "sg:phone":"+1 503 873 6967",
    "sg:postcode":"97381",
    "sg:province":"OR",
    "sg:tags":[
        "residential"
    ],
    "wof:name":"Lynn Richman Construction LLC",
    "wof:placetype":"venue"
},
  "geometry": {"coordinates":[-122.77892799999999,44.972099],"type":"Point"}
}