{
  "type": "Feature",
  "properties": {
    "addr:full":"1300 SW 5th Ave Portland OR 97201",
    "addr:housenumber":"1300",
    "addr:postcode":"97201",
    "addr:street":"Sw 5Th Ave",
    "iso:country":"US",
    "sg:address":"1300 SW 5th Ave",
    "sg:city":"Portland",
    "sg:classifiers":[
        {
            "category":"Professional",
            "subcategory":"Lawyer & Legal Services",
            "type":"Services"
        }
    ],
    "sg:phone":"+1 503 241 2300",
    "sg:postcode":"97201",
    "sg:province":"OR",
    "sg:tags":[
        "attorney",
        "estate",
        "business",
        "tax",
        "governmental",
        "planning",
        "law",
        "administrative"
    ],
    "wof:name":"Cameron Jr., John A. - Davis Wright Trem",
    "wof:placetype":"venue"
},
  "geometry": {"coordinates":[-122.67971799999999,45.514809],"type":"Point"}
}