{
  "type": "Feature",
  "properties": {
    "addr:full":"104 SW 3rd St Corvallis OR 97333",
    "addr:housenumber":"104",
    "addr:postcode":"97333",
    "addr:street":"Sw 3Rd St",
    "iso:country":"US",
    "sg:address":"104 SW 3rd St",
    "sg:city":"Corvallis",
    "sg:classifiers":[
        {
            "category":"Personal",
            "subcategory":"Barber",
            "type":"Services"
        }
    ],
    "sg:phone":"+1 541 752 7056",
    "sg:postcode":"97333",
    "sg:province":"OR",
    "sg:tags":[
        "shop"
    ],
    "wof:name":"City Barber Shop",
    "wof:placetype":"venue"
},
  "geometry": {"coordinates":[-123.260999,44.564359],"type":"Point"}
}