{
  "type": "Feature",
  "properties": {
    "addr:full":"7075 Fifteen Mile Rd The Dalles OR 97058",
    "addr:postcode":"7075;97058",
    "addr:street":"Fifteen Mile Rd",
    "iso:country":"US",
    "sg:address":"7075 Fifteen Mile Rd",
    "sg:city":"The Dalles",
    "sg:phone":"+1 541 296 9897",
    "sg:postcode":"97058",
    "sg:province":"OR",
    "sg:tags":[
        "farm",
        "field",
        "camp",
        "crop"
    ],
    "wof:name":"William E Hammel",
    "wof:placetype":"venue"
},
  "geometry": {"coordinates":[-120.954801,45.565719],"type":"Point"}
}