{
  "type": "Feature",
  "properties": {
    "addr:full":"9467 SW Washington Dr Portland OR 97223",
    "addr:housenumber":"9467",
    "addr:postcode":"97223",
    "addr:street":"Sw Washington Dr",
    "iso:country":"US",
    "sg:address":"9467 SW Washington Dr",
    "sg:city":"Portland",
    "sg:classifiers":[
        {
            "category":"Restaurant",
            "type":"Food & Drink"
        }
    ],
    "sg:phone":"+1 503 620 3761",
    "sg:postcode":"97223",
    "sg:province":"OR",
    "sg:tags":[
        "shop",
        "coffee",
        "specialty"
    ],
    "wof:name":"Starbucks",
    "wof:placetype":"venue"
},
  "geometry": {"coordinates":[-122.766048,45.452674],"type":"Point"}
}