{
  "type": "Feature",
  "properties": {
    "iso:country":"US",
    "sg:address":"0309 SW Montgomery St",
    "sg:city":"Portland",
    "sg:classifiers":[
        {
            "category":"Parking",
            "type":"Transportation"
        }
    ],
    "sg:phone":"+1 503 294 3299",
    "sg:postcode":"97201",
    "sg:province":"OR",
    "wof:name":"City Center Parking",
    "wof:placetype":"venue"
},
  "geometry": {"coordinates":[-122.674013,45.509603],"type":"Point"}
}