{
  "type": "Feature",
  "properties": {
    "iso:country":"US",
    "sg:address":"715 SW Morrison Street Suite 504",
    "sg:city":"Portland",
    "sg:classifiers":[
        {
            "category":"Professional",
            "subcategory":"Lawyer & Legal Services",
            "type":"Services"
        }
    ],
    "sg:phone":"+1 503 220 1810",
    "sg:postcode":"97205",
    "sg:province":"OR",
    "wof:name":"Landis Tim Attorney At Law",
    "wof:placetype":"venue"
},
  "geometry": {"coordinates":[-122.679759,45.519388],"type":"Point"}
}