{
  "type": "Feature",
  "properties": {
    "iso:country":"US",
    "sg:address":"190 Oak St",
    "sg:city":"Ashland",
    "sg:classifiers":[
        {
            "category":"Real Estate",
            "subcategory":"Real Estate Agent",
            "type":"Services"
        }
    ],
    "sg:phone":"+1 541 482 5590",
    "sg:postcode":"97520",
    "sg:province":"OR",
    "wof:name":"Coldwell Banker Pro West",
    "wof:placetype":"venue"
},
  "geometry": {"coordinates":[-122.713936,42.197755],"type":"Point"}
}