{
  "type": "Feature",
  "properties": {
    "addr:full":"423 Nugget Dr Rogue River OR 97537",
    "addr:housenumber":"423",
    "addr:postcode":"97537",
    "addr:street":"Nugget Dr",
    "iso:country":"US",
    "sg:address":"423 Nugget Dr",
    "sg:city":"Rogue River",
    "sg:classifiers":[
        {
            "category":"Professional",
            "subcategory":"Accounting & Tax Preparation",
            "type":"Services"
        }
    ],
    "sg:phone":"+1 541 582 1567",
    "sg:postcode":"97537",
    "sg:province":"OR",
    "wof:name":"Suzs Bookkeeping & Word Proc",
    "wof:placetype":"venue"
},
  "geometry": {"coordinates":[-123.158599,42.439305],"type":"Point"}
}