{
  "type": "Feature",
  "properties": {
    "addr:full":"36940 Deming Rd Sandy OR 97055",
    "addr:housenumber":"36940",
    "addr:postcode":"97055",
    "addr:street":"Deming Rd",
    "iso:country":"US",
    "sg:address":"36940 Deming Rd",
    "sg:city":"Sandy",
    "sg:classifiers":[
        {
            "category":"Farming",
            "subcategory":"Berry Farm",
            "type":"Manufacturing & Wholesale Goods"
        }
    ],
    "sg:phone":"+1 503 668 6177",
    "sg:postcode":"97055",
    "sg:province":"OR",
    "sg:tags":[
        "crop"
    ],
    "wof:name":"Pullen Farms",
    "wof:placetype":"venue"
},
  "geometry": {"coordinates":[-122.28399899999999,45.387614],"type":"Point"}
}