{
  "type": "Feature",
  "properties": {
    "addr:full":"2240 W Irwin Way Eugene OR 97402",
    "addr:housenumber":"2240",
    "addr:postcode":"97402",
    "addr:street":"W Irwin Way",
    "iso:country":"US",
    "sg:address":"2240 W Irwin Way",
    "sg:city":"Eugene",
    "sg:classifiers":[
        {
            "category":"Retail",
            "subcategory":"Repair Shop",
            "type":"Services"
        }
    ],
    "sg:phone":"+1 541 461 8974",
    "sg:postcode":"97402",
    "sg:province":"OR",
    "wof:name":"Bakery Equipment Service Corp",
    "wof:placetype":"venue"
},
  "geometry": {"coordinates":[-123.185289,44.090723],"type":"Point"}
}