{
  "type": "Feature",
  "properties": {
    "addr:full":"775 NW 57th St Redmond OR 97756",
    "addr:housenumber":"775",
    "addr:postcode":"97756",
    "addr:street":"Nw 57Th St",
    "iso:country":"US",
    "sg:address":"775 NW 57th St",
    "sg:city":"Redmond",
    "sg:classifiers":[
        {
            "category":"Building & Trades",
            "subcategory":"Construction",
            "type":"Services"
        }
    ],
    "sg:phone":"+1 541 504 0797",
    "sg:postcode":"97756",
    "sg:province":"OR",
    "sg:tags":[
        "contractor"
    ],
    "wof:name":"Veenker Contracting",
    "wof:placetype":"venue"
},
  "geometry": {"coordinates":[-121.237072,44.282486],"type":"Point"}
}