{
  "type": "Feature",
  "properties": {
    "addr:full":"120 SE Clay St Portland OR 97214",
    "addr:housenumber":"120",
    "addr:postcode":"97214",
    "addr:street":"Se Clay St",
    "iso:country":"US",
    "sg:address":"120 SE Clay St",
    "sg:city":"Portland",
    "sg:classifiers":[
        {
            "category":"Wholesale",
            "subcategory":"Auto Parts",
            "type":"Manufacturing & Wholesale Goods"
        }
    ],
    "sg:phone":"+1 503 789 2071",
    "sg:postcode":"97214",
    "sg:province":"OR",
    "sg:tags":[
        "supply",
        "automobile",
        "equipment",
        "parts",
        "towing",
        "accessories-wholesale",
        "manufacturer"
    ],
    "sg:website":"www.fleetsaleswest.com",
    "wof:name":"Fleet Sales West",
    "wof:placetype":"venue"
},
  "geometry": {"coordinates":[-122.664641,45.511533],"type":"Point"}
}