{
  "type": "Feature",
  "properties": {
    "iso:country":"US",
    "sg:address":"1120 NW Couch St Ste 730",
    "sg:city":"Portland",
    "sg:classifiers":[
        {
            "category":"Social Services",
            "subcategory":"Retirement Home",
            "type":"Services"
        }
    ],
    "sg:phone":"+1 503 227 4000",
    "sg:postcode":"97209",
    "sg:province":"OR",
    "sg:tags":[
        "apartment",
        "hotel",
        "community"
    ],
    "wof:name":"Waterford Grand Senior Living",
    "wof:placetype":"venue"
},
  "geometry": {"coordinates":[-122.68235,45.523683],"type":"Point"}
}