{
  "type": "Feature",
  "properties": {
    "iso:country":"US",
    "sg:address":"5835 SW Knightsbridge Dr",
    "sg:city":"Portland",
    "sg:classifiers":[
        {
            "category":"Wholesale",
            "subcategory":"Durable Goods & Equipment",
            "type":"Manufacturing & Wholesale Goods"
        }
    ],
    "sg:phone":"+1 503 246 1103",
    "sg:postcode":"97219",
    "sg:province":"OR",
    "wof:name":"Wholesale Daves LLC Uncle",
    "wof:placetype":"venue"
},
  "geometry": {"coordinates":[-122.736355,45.458987],"type":"Point"}
}