{
  "type": "Feature",
  "properties": {
    "addr:full":"90579 Highway 99 N Eugene OR 97402",
    "addr:housenumber":"90579",
    "addr:postcode":"97402",
    "addr:street":"Highway 99 N",
    "iso:country":"US",
    "sg:address":"90579 Highway 99 N",
    "sg:city":"Eugene",
    "sg:classifiers":[
        {
            "category":"Autos & Motor Vehicles",
            "subcategory":"Automobile Sales",
            "type":"Retail Goods"
        },
        {
            "category":"Autos & Motor Vehicles",
            "subcategory":"Auto Supplies",
            "type":"Retail Goods"
        }
    ],
    "sg:phone":"+1 541 393 8934",
    "sg:postcode":"97402",
    "sg:province":"OR",
    "sg:tags":[
        "part",
        "salvage"
    ],
    "sg:website":"http://gandrautowreckers.com",
    "wof:name":"Pick-A-Part",
    "wof:placetype":"venue"
},
  "geometry": {"coordinates":[-123.20031,44.145378],"type":"Point"}
}