{
  "type": "Feature",
  "properties": {
    "addr:full":"2012 SE Hemlock Ave Portland OR 97214",
    "addr:housenumber":"2012",
    "addr:postcode":"97214",
    "addr:street":"Se Hemlock Ave",
    "iso:country":"US",
    "sg:address":"2012 SE Hemlock Ave",
    "sg:city":"Portland",
    "sg:classifiers":[
        {
            "category":"Professional",
            "subcategory":"Management & Consulting",
            "type":"Services"
        }
    ],
    "sg:phone":"+1 503 231 5336",
    "sg:postcode":"97214",
    "sg:province":"OR",
    "wof:name":"Design Con Structs",
    "wof:placetype":"venue"
},
  "geometry": {"coordinates":[-122.64631799999999,45.507397],"type":"Point"}
}