{
  "type": "Feature",
  "properties": {
    "addr:full":"12414 SE Oatfield Rd Portland OR 97222",
    "addr:housenumber":"12414",
    "addr:postcode":"97222",
    "addr:street":"Se Oatfield Rd",
    "iso:country":"US",
    "sg:address":"12414 SE Oatfield Rd",
    "sg:city":"Portland",
    "sg:classifiers":[
        {
            "category":"Wholesale",
            "subcategory":"Toys & Hobbies",
            "type":"Manufacturing & Wholesale Goods"
        }
    ],
    "sg:phone":"+1 503 786 9227",
    "sg:postcode":"97222",
    "sg:province":"OR",
    "sg:tags":[
        "wholesaler"
    ],
    "wof:name":"Rick Jones Motor Co",
    "wof:placetype":"venue"
},
  "geometry": {"coordinates":[-122.631316,45.433087],"type":"Point"}
}