{
  "type": "Feature",
  "properties": {
    "addr:full":"433 NE Rifle Range Rd Roseburg OR 97470",
    "addr:housenumber":"433",
    "addr:postcode":"97470",
    "addr:street":"Ne Rifle Range Rd",
    "iso:country":"US",
    "sg:address":"433 NE Rifle Range Rd",
    "sg:city":"Roseburg",
    "sg:classifiers":[
        {
            "category":"Government",
            "subcategory":"Office",
            "type":"Public Place"
        }
    ],
    "sg:phone":"+1 541 440 4268",
    "sg:postcode":"97470",
    "sg:province":"OR",
    "sg:website":"www.co.douglas.or.us",
    "wof:name":"Douglas Operations & Mntnc Div",
    "wof:placetype":"venue"
},
  "geometry": {"coordinates":[-123.32181300000001,43.214012],"type":"Point"}
}