{
  "type": "Feature",
  "properties": {
    "iso:country":"US",
    "sg:address":"271 NE Beech St",
    "sg:city":"Toledo",
    "sg:classifiers":[
        {
            "category":"Personal",
            "subcategory":"Barber",
            "type":"Services"
        }
    ],
    "sg:phone":"+1 541 336 4220",
    "sg:postcode":"97391",
    "sg:province":"OR",
    "sg:tags":[
        "shop"
    ],
    "wof:name":"Kristis Barber Shop",
    "wof:placetype":"venue"
},
  "geometry": {"coordinates":[-123.934361,44.621438],"type":"Point"}
}