{
  "type": "Feature",
  "properties": {
    "iso:country":"US",
    "sg:address":"2381 SW 4th Ave",
    "sg:city":"Ontario",
    "sg:classifiers":[
        {
            "category":"Autos & Motor Vehicles",
            "subcategory":"Automobile Sales",
            "type":"Retail Goods"
        }
    ],
    "sg:phone":"+1 541 889 3228",
    "sg:postcode":"97914",
    "sg:province":"OR",
    "sg:tags":[
        "car",
        "dealer"
    ],
    "wof:name":"Westside Motors",
    "wof:placetype":"venue"
},
  "geometry": {"coordinates":[-116.997593,44.024866],"type":"Point"}
}