{
  "type": "Feature",
  "properties": {
    "iso:country":"US",
    "sg:address":"2901 SE Steele Street",
    "sg:city":"Portland",
    "sg:classifiers":[
        {
            "category":"Place Of Worship",
            "subcategory":"Church",
            "type":"Public Place"
        }
    ],
    "sg:phone":"+1 503 234 5017",
    "sg:postcode":"97202",
    "sg:province":"OR",
    "sg:website":"www.reedwood.org",
    "wof:name":"Reedwood Friends Church",
    "wof:placetype":"venue"
},
  "geometry": {"coordinates":[-122.635631,45.484807],"type":"Point"}
}