{
  "type": "Feature",
  "properties": {
    "iso:country":"US",
    "sg:address":"18335 NW West Union Rd Ste I",
    "sg:city":"Portland",
    "sg:classifiers":[
        {
            "category":"Education",
            "subcategory":"Special Training",
            "type":"Public Place"
        }
    ],
    "sg:phone":"+1 503 614 0114",
    "sg:postcode":"97229",
    "sg:province":"OR",
    "sg:tags":[
        "school",
        "language"
    ],
    "sg:website":"www.tutoringclub.com",
    "wof:name":"Tutoring Club of Beaverton",
    "wof:placetype":"venue"
},
  "geometry": {"coordinates":[-122.865674,45.557873],"type":"Point"}
}