{
  "type": "Feature",
  "properties": {
    "iso:country":"US",
    "sg:address":"1130 N Jantzen Ave",
    "sg:city":"Portland",
    "sg:classifiers":[
        {
            "category":"Autos & Motor Vehicles",
            "subcategory":"Boat Sales",
            "type":"Retail Goods"
        }
    ],
    "sg:phone":"+1 503 283 1799",
    "sg:postcode":"97217",
    "sg:province":"OR",
    "sg:tags":[
        "yacht",
        "broker"
    ],
    "wof:name":"Yacht Spot Inc",
    "wof:placetype":"venue"
},
  "geometry": {"coordinates":[-122.68257800000001,45.60968],"type":"Point"}
}