{
  "type": "Feature",
  "properties": {
    "addr:full":"9904 SW Tigard St Portland OR 97223",
    "addr:housenumber":"9904",
    "addr:postcode":"97223",
    "addr:street":"Sw Tigard St",
    "iso:country":"US",
    "sg:address":"9904 SW Tigard St",
    "sg:city":"Portland",
    "sg:classifiers":[
        {
            "category":"Manufacturing",
            "subcategory":"Tools & Machinery",
            "type":"Manufacturing & Wholesale Goods"
        }
    ],
    "sg:phone":"+1 503 620 5422",
    "sg:postcode":"97223",
    "sg:province":"OR",
    "sg:tags":[
        "equipment",
        "mfg",
        "laboratory"
    ],
    "wof:name":"Rolling Components",
    "wof:placetype":"venue"
},
  "geometry": {"coordinates":[-122.777727,45.432965],"type":"Point"}
}