{
  "type": "Feature",
  "properties": {
    "iso:country":"US",
    "sg:address":"5488 Havencrest Dr",
    "sg:city":"Klamath Falls",
    "sg:classifiers":[
        {
            "category":"Professional",
            "type":"Services"
        }
    ],
    "sg:phone":"+1 541 883 2675",
    "sg:postcode":"97603",
    "sg:province":"OR",
    "wof:name":"Bafa Services Corporation",
    "wof:placetype":"venue"
},
  "geometry": {"coordinates":[-121.717434,42.225986],"type":"Point"}
}