{
  "type": "Feature",
  "properties": {
    "iso:country":"US",
    "sg:address":"12 S M St",
    "sg:city":"Lakeview",
    "sg:classifiers":[
        {
            "category":"Professional",
            "type":"Services"
        }
    ],
    "sg:phone":"+1 541 947 3412",
    "sg:postcode":"97630",
    "sg:province":"OR",
    "wof:name":"Bantons Retals",
    "wof:placetype":"venue"
},
  "geometry": {"coordinates":[-120.354412,42.189199],"type":"Point"}
}