{
  "type": "Feature",
  "properties": {
    "iso:country":"US",
    "sg:address":"923 Mistletoe Loop N",
    "sg:city":"Salem",
    "sg:classifiers":[
        {
            "category":"Professional",
            "subcategory":"Accounting & Tax Preparation",
            "type":"Services"
        }
    ],
    "sg:phone":"+1 503 390 3245",
    "sg:postcode":"97303",
    "sg:province":"OR",
    "sg:tags":[
        "return"
    ],
    "wof:name":"Joel E Leming",
    "wof:placetype":"venue"
},
  "geometry": {"coordinates":[-123.022796,45.013044],"type":"Point"}
}