{
  "type": "Feature",
  "properties": {
    "addr:full":"3333 Anderson Ave Klamath Falls OR 97603",
    "addr:housenumber":"3333",
    "addr:postcode":"97603",
    "addr:street":"Anderson Ave",
    "iso:country":"US",
    "sg:address":"3333 Anderson Ave",
    "sg:city":"Klamath Falls",
    "sg:classifiers":[
        {
            "category":"Building & Trades",
            "subcategory":"Construction",
            "type":"Services"
        }
    ],
    "sg:phone":"+1 541 883 3837",
    "sg:postcode":"97603",
    "sg:province":"OR",
    "sg:tags":[
        "general",
        "contractor"
    ],
    "wof:name":"William Hickels Construction",
    "wof:placetype":"venue"
},
  "geometry": {"coordinates":[-121.749015,42.181292],"type":"Point"}
}