{
  "type": "Feature",
  "properties": {
    "addr:full":"216 NE 28th Ave Portland OR 97232",
    "addr:housenumber":"216",
    "addr:postcode":"97232",
    "addr:street":"Ne 28Th Ave",
    "iso:country":"US",
    "sg:address":"216 NE 28th Ave",
    "sg:city":"Portland",
    "sg:classifiers":[
        {
            "category":"Manufacturing",
            "subcategory":"Apparel",
            "type":"Manufacturing & Wholesale Goods"
        }
    ],
    "sg:phone":"+1 503 235 8770",
    "sg:postcode":"97232",
    "sg:province":"OR",
    "sg:tags":[
        "board",
        "sportswear-wholesale",
        "snow",
        "manufacturer",
        "mfg"
    ],
    "sg:website":"http://www.bettyrides.com",
    "wof:name":"Betty Rides",
    "wof:placetype":"venue"
},
  "geometry": {"coordinates":[-122.637249,45.524448],"type":"Point"}
}