{
  "type": "Feature",
  "properties": {
    "addr:full":"251 NW 4th St Redmond OR 97756",
    "addr:housenumber":"251",
    "addr:postcode":"97756",
    "addr:street":"Nw 4Th St",
    "iso:country":"US",
    "sg:address":"251 NW 4th St",
    "sg:city":"Redmond",
    "sg:classifiers":[
        {
            "category":"Insurance",
            "subcategory":"Insurance Agent",
            "type":"Services"
        }
    ],
    "sg:phone":"+1 541 389 3171",
    "sg:postcode":"97756",
    "sg:province":"OR",
    "sg:tags":[
        "system",
        "contractor",
        "air conditioning"
    ],
    "sg:website":"http://www.centraloregonlandwatch.org",
    "wof:name":"Central Oregon Claims",
    "wof:placetype":"venue"
},
  "geometry": {"coordinates":[-121.172119,44.277883],"type":"Point"}
}