{
  "type": "Feature",
  "properties": {
    "addr:full":"760 SW Vista Ave Portland OR 97205",
    "addr:housenumber":"760",
    "addr:postcode":"97205",
    "addr:street":"Sw Vista Ave",
    "iso:country":"US",
    "sg:address":"760 SW Vista Ave",
    "sg:city":"Portland",
    "sg:classifiers":[
        {
            "category":"Banks & Credit Unions",
            "subcategory":"Investment Brokerage",
            "type":"Services"
        }
    ],
    "sg:phone":"+1 503 228 2920",
    "sg:postcode":"97205",
    "sg:province":"OR",
    "wof:name":"B & B Investments",
    "wof:placetype":"venue"
},
  "geometry": {"coordinates":[-122.69811900000001,45.523278],"type":"Point"}
}