{
  "type": "Feature",
  "properties": {
    "iso:country":"US",
    "sg:address":"1307 NE 111th Ave",
    "sg:city":"Portland",
    "sg:classifiers":[
        {
            "category":"Professional",
            "type":"Services"
        }
    ],
    "sg:phone":"+1 503 253 5568",
    "sg:postcode":"97220",
    "sg:province":"OR",
    "sg:tags":[
        "processing",
        "data"
    ],
    "wof:name":"Data Services For Schools",
    "wof:placetype":"venue"
},
  "geometry": {"coordinates":[-122.548314,45.532375],"type":"Point"}
}