{
  "type": "Feature",
  "properties": {
    "iso:country":"US",
    "sg:address":"46616 Tuckwila",
    "sg:city":"Lyons",
    "sg:classifiers":[
        {
            "category":"Building & Trades",
            "subcategory":"Construction",
            "type":"Services"
        }
    ],
    "sg:phone":"+1 503 859 3117",
    "sg:postcode":"97358",
    "sg:province":"OR",
    "sg:tags":[
        "general",
        "contractor"
    ],
    "wof:name":"Lindemann Construction",
    "wof:placetype":"venue"
},
  "geometry": {"coordinates":[-122.55650300000001,44.766986],"type":"Point"}
}