{
  "type": "Feature",
  "properties": {
    "iso:country":"US",
    "sg:address":"574 Quail Ln",
    "sg:city":"Roseburg",
    "sg:classifiers":[
        {
            "category":"Building & Trades",
            "subcategory":"Plumbing",
            "type":"Services"
        }
    ],
    "sg:phone":"+1 541 440 6941",
    "sg:postcode":"97470",
    "sg:province":"OR",
    "sg:tags":[
        "contractor"
    ],
    "wof:name":"All Temp Mechanical",
    "wof:placetype":"venue"
},
  "geometry": {"coordinates":[-123.418001,43.266037],"type":"Point"}
}