{
  "type": "Feature",
  "properties": {
    "iso:country":"US",
    "sg:address":"2200 Centennial Blvd",
    "sg:city":"Eugene",
    "sg:classifiers":[
        {
            "category":"Autos & Motor Vehicles",
            "subcategory":"Automobile Sales",
            "type":"Retail Goods"
        }
    ],
    "sg:phone":"+1 541 687 8888",
    "sg:postcode":"97401",
    "sg:province":"OR",
    "sg:tags":[
        "repair",
        "general"
    ],
    "sg:website":"www.mbeugene.com",
    "wof:name":"Mercedes-Benz Of Eugene",
    "wof:placetype":"venue"
},
  "geometry": {"coordinates":[-123.07674400000001,44.059658],"type":"Point"}
}