{
  "type": "Feature",
  "properties": {
    "addr:full":"5012 NE 28th Avenue Portland OR 97211",
    "addr:housenumber":"5012",
    "addr:postcode":"97211",
    "addr:street":"Ne 28Th Avenue",
    "iso:country":"US",
    "sg:address":"5012 NE 28th Avenue",
    "sg:city":"Portland",
    "sg:classifiers":[
        {
            "category":"Personal",
            "subcategory":"Tattoo Parlor",
            "type":"Services"
        }
    ],
    "sg:phone":"+1 503 493 4445",
    "sg:postcode":"97211",
    "sg:province":"OR",
    "wof:name":"Temple Tattoo",
    "wof:placetype":"venue"
},
  "geometry": {"coordinates":[-122.636713,45.55917],"type":"Point"}
}