{
  "type": "Feature",
  "properties": {
    "addr:full":"640 Brian Way Medford OR 97501",
    "addr:housenumber":"640",
    "addr:postcode":"97501",
    "addr:street":"Brian Way",
    "iso:country":"US",
    "sg:address":"640 Brian Way",
    "sg:city":"Medford",
    "sg:classifiers":[
        {
            "category":"Wholesale",
            "subcategory":"Electrical",
            "type":"Manufacturing & Wholesale Goods"
        }
    ],
    "sg:phone":"+1 541 779 0394",
    "sg:postcode":"97501",
    "sg:province":"OR",
    "sg:tags":[
        "fire",
        "equipment",
        "protection"
    ],
    "sg:website":"www.cascadefire.com",
    "wof:name":"Cascade Fire Equipment Co",
    "wof:placetype":"venue"
},
  "geometry": {"coordinates":[-122.89479300000001,42.34339],"type":"Point"}
}