{
  "type": "Feature",
  "properties": {
    "iso:country":"US",
    "sg:address":"106 NW Minnesota Ave",
    "sg:city":"Bend",
    "sg:classifiers":[
        {
            "category":"Shopping",
            "subcategory":"Used Merchandise",
            "type":"Retail Goods"
        }
    ],
    "sg:phone":"+1 541 389 4166",
    "sg:postcode":"97701",
    "sg:province":"OR",
    "sg:tags":[
        "antique"
    ],
    "wof:name":"Antique Appraisals By Trivia",
    "wof:placetype":"venue"
},
  "geometry": {"coordinates":[-121.313377,44.058275],"type":"Point"}
}