{
  "type": "Feature",
  "properties": {
    "iso:country":"US",
    "sg:address":"10121 SE Sunnyside Rd",
    "sg:city":"Clackamas",
    "sg:classifiers":[
        {
            "category":"Health Services",
            "subcategory":"Health Practitioner",
            "type":"Services"
        }
    ],
    "sg:phone":"+1 503 513 5511",
    "sg:postcode":"97015",
    "sg:province":"OR",
    "sg:tags":[
        "therapist",
        "physical"
    ],
    "wof:name":"Mechanical Diagnosis & Thrpy",
    "wof:placetype":"venue"
},
  "geometry": {"coordinates":[-122.560619,45.433502],"type":"Point"}
}