{
  "type": "Feature",
  "properties": {
    "iso:country":"US",
    "sg:address":"2507 SE Clinton St",
    "sg:city":"Portland",
    "sg:classifiers":[
        {
            "category":"Arts & Performance",
            "subcategory":"Art Gallery",
            "type":"Entertainment"
        }
    ],
    "sg:phone":"+1 503 957 6800",
    "sg:postcode":"97202",
    "sg:province":"OR",
    "sg:website":"www.studio2507.com",
    "wof:name":"Studio 2507/ Annie Meyer Artwork",
    "wof:placetype":"venue"
},
  "geometry": {"coordinates":[-122.639976,45.503533],"type":"Point"}
}