{
  "type": "Feature",
  "properties": {
    "iso:country":"US",
    "sg:address":"13503 SE Division St",
    "sg:city":"Portland",
    "sg:classifiers":[
        {
            "category":"Insurance",
            "subcategory":"Hazard Insurance",
            "type":"Services"
        }
    ],
    "sg:phone":"+1 503 618 7079",
    "sg:postcode":"97236",
    "sg:province":"OR",
    "sg:website":"http://www.metlifeautoandhome.com",
    "wof:name":"Metlife",
    "wof:placetype":"venue"
},
  "geometry": {"coordinates":[-122.52467799999999,45.504052],"type":"Point"}
}