{
  "type": "Feature",
  "properties": {
    "iso:country":"US",
    "sg:address":"3950 N Mississippi Ave",
    "sg:city":"Portland",
    "sg:classifiers":[
        {
            "category":"Restaurant",
            "type":"Food & Drink"
        }
    ],
    "sg:phone":"+1 503 287 7629",
    "sg:postcode":"97227",
    "sg:province":"OR",
    "sg:tags":[
        "southern"
    ],
    "sg:website":"missdeltapdx.net/home.html",
    "wof:name":"Miss Delta",
    "wof:placetype":"venue"
},
  "geometry": {"coordinates":[-122.675535,45.55149],"type":"Point"}
}