{
  "type": "Feature",
  "properties": {
    "iso:country":"US",
    "sg:address":"1200 SE Harvey Dr",
    "sg:city":"Grants Pass",
    "sg:classifiers":[
        {
            "category":"Education",
            "subcategory":"School",
            "type":"Public Place"
        }
    ],
    "sg:phone":"+1 541 474 5780",
    "sg:postcode":"97526",
    "sg:province":"OR",
    "wof:name":"Riverside Elementary School",
    "wof:placetype":"venue"
},
  "geometry": {"coordinates":[-123.298501,42.426868],"type":"Point"}
}