{
  "type": "Feature",
  "properties": {
    "iso:country":"US",
    "sg:address":"15835 SE String Town Rd",
    "sg:city":"Dayton",
    "sg:classifiers":[
        {
            "category":"Professional",
            "subcategory":"Management & Consulting",
            "type":"Services"
        },
        {
            "category":"Farming",
            "subcategory":"Farm",
            "type":"Manufacturing & Wholesale Goods"
        }
    ],
    "sg:phone":"+1 503 864 2448",
    "sg:postcode":"97114",
    "sg:province":"OR",
    "wof:name":"Harold Morgan",
    "wof:placetype":"venue"
},
  "geometry": {"coordinates":[-123.07541000000001,45.198326],"type":"Point"}
}