{
  "type": "Feature",
  "properties": {
    "iso:country":"US",
    "sg:address":"5061 Liberty Rd S",
    "sg:city":"Salem",
    "sg:classifiers":[
        {
            "category":"Banks & Credit Unions",
            "subcategory":"Investment Brokerage",
            "type":"Services"
        },
        {
            "category":"Insurance",
            "subcategory":"Hazard Insurance",
            "type":"Services"
        },
        {
            "category":"Banks & Credit Unions",
            "subcategory":"Financial Services",
            "type":"Services"
        },
        {
            "category":"Insurance",
            "subcategory":"Life Insurance",
            "type":"Services"
        }
    ],
    "sg:phone":"+1 541 889 6414",
    "sg:postcode":"97306",
    "sg:province":"OR",
    "sg:website":"http://www.countryfinancial.com",
    "wof:name":"COUNTRY Financial - Mark Haueter",
    "wof:placetype":"venue"
},
  "geometry": {"coordinates":[-123.061218,44.882851],"type":"Point"}
}