{
  "type": "Feature",
  "properties": {
    "iso:country":"US",
    "sg:address":"5510 N Lombard Street",
    "sg:city":"Portland",
    "sg:classifiers":[
        {
            "category":"Autos & Motor Vehicles",
            "subcategory":"Auto Supplies",
            "type":"Retail Goods"
        }
    ],
    "sg:phone":"+1 503 289 1956",
    "sg:postcode":"97203",
    "sg:province":"OR",
    "sg:tags":[
        "tire"
    ],
    "wof:name":"Les Schwab Tire Centers",
    "wof:placetype":"venue"
},
  "geometry": {"coordinates":[-122.725847,45.583252],"type":"Point"}
}