{
  "type": "Feature",
  "properties": {
    "iso:country":"US",
    "sg:address":"11053 SE Division St",
    "sg:city":"Portland",
    "sg:classifiers":[
        {
            "category":"Manufacturing",
            "subcategory":"Printing",
            "type":"Manufacturing & Wholesale Goods"
        }
    ],
    "sg:phone":"+1 971 230 4016",
    "sg:postcode":"97266",
    "sg:province":"OR",
    "sg:tags":[
        "publisher"
    ],
    "wof:name":"New Ideas By Carmen",
    "wof:placetype":"venue"
},
  "geometry": {"coordinates":[-122.549657,45.504286],"type":"Point"}
}