{
  "type": "Feature",
  "properties": {
    "iso:country":"US",
    "sg:address":"1901 NW Upshur St",
    "sg:city":"Portland",
    "sg:classifiers":[
        {
            "category":"Real Estate",
            "subcategory":"Architect",
            "type":"Services"
        }
    ],
    "sg:phone":"+1 503 222 3232",
    "sg:postcode":"97209",
    "sg:province":"OR",
    "wof:name":"John Vosmek Architects",
    "wof:placetype":"venue"
},
  "geometry": {"coordinates":[-122.69277,45.53632],"type":"Point"}
}