{
  "type": "Feature",
  "properties": {
    "iso:country":"US",
    "sg:address":"7632 SW Durham Rd",
    "sg:city":"Portland",
    "sg:classifiers":[
        {
            "category":"Insurance",
            "subcategory":"Insurance Agent",
            "type":"Services"
        }
    ],
    "sg:phone":"+1 503 603 5902",
    "sg:postcode":"97224",
    "sg:province":"OR",
    "wof:name":"Allstate",
    "wof:placetype":"venue"
},
  "geometry": {"coordinates":[-122.755465,45.403459],"type":"Point"}
}