{
  "type": "Feature",
  "properties": {
    "iso:country":"US",
    "sg:address":"1088 Newmark Ave",
    "sg:city":"Coos Bay",
    "sg:classifiers":[
        {
            "category":"Restaurant",
            "type":"Food & Drink"
        }
    ],
    "sg:phone":"+1 541 888 4353",
    "sg:postcode":"97420",
    "sg:province":"OR",
    "wof:name":"Gussie's Restaurant & Lounge",
    "wof:placetype":"venue"
},
  "geometry": {"coordinates":[-124.269434,43.391829],"type":"Point"}
}