{
  "type": "Feature",
  "properties": {
    "iso:country":"US",
    "sg:address":"1408 Mohawk Blvd",
    "sg:city":"Springfield",
    "sg:classifiers":[
        {
            "category":"Food & Beverages",
            "subcategory":"Liquor & Beverages",
            "type":"Retail Goods"
        }
    ],
    "sg:phone":"+1 541 746 4611",
    "sg:postcode":"97477",
    "sg:province":"OR",
    "sg:tags":[
        "store"
    ],
    "sg:website":"http://www.northgateliquor.com",
    "wof:name":"Northgate Liquor Store",
    "wof:placetype":"venue"
},
  "geometry": {"coordinates":[-123.00110599999999,44.057641],"type":"Point"}
}