{
  "type": "Feature",
  "properties": {
    "iso:country":"US",
    "sg:address":"2222 Broadway St",
    "sg:city":"North Bend",
    "sg:classifiers":[
        {
            "category":"Shopping",
            "type":"Retail Goods"
        }
    ],
    "sg:phone":"+1 541 756 8944",
    "sg:postcode":"97459",
    "sg:province":"OR",
    "sg:tags":[
        "hearing",
        "equipment",
        "supply",
        "merchandise",
        "impaired"
    ],
    "wof:name":"Willoughby Hearing Aid Centers",
    "wof:placetype":"venue"
},
  "geometry": {"coordinates":[-124.239356,43.403566],"type":"Point"}
}