{
  "type": "Feature",
  "properties": {
    "iso:country":"US",
    "sg:address":"936 SE Powell Blvd",
    "sg:city":"Portland",
    "sg:classifiers":[
        {
            "category":"Retail",
            "subcategory":"Auto Repair",
            "type":"Services"
        }
    ],
    "sg:phone":"+1 503 232 5545",
    "sg:postcode":"97202",
    "sg:province":"OR",
    "sg:tags":[
        "repairing",
        "automobile"
    ],
    "sg:website":"www.pacificmotorsportsonline.com",
    "wof:name":"Pacific Motorsports",
    "wof:placetype":"venue"
},
  "geometry": {"coordinates":[-122.6564,45.50148],"type":"Point"}
}