{
  "type": "Feature",
  "properties": {
    "iso:country":"US",
    "sg:address":"405 SW 8th St",
    "sg:city":"Redmond",
    "sg:classifiers":[
        {
            "category":"Real Estate",
            "subcategory":"Developer",
            "type":"Services"
        }
    ],
    "sg:phone":"+1 541 504 7000",
    "sg:postcode":"97756",
    "sg:province":"OR",
    "wof:name":"MHI",
    "wof:placetype":"venue"
},
  "geometry": {"coordinates":[-121.176489,44.273506],"type":"Point"}
}