{
  "type": "Feature",
  "properties": {
    "addr:full":"190 East Ln Ontario OR 97914",
    "addr:housenumber":"190",
    "addr:postcode":"97914",
    "addr:street":"East Ln",
    "iso:country":"US",
    "sg:address":"190 East Ln",
    "sg:city":"Ontario",
    "sg:classifiers":[
        {
            "category":"Social Services",
            "subcategory":"Job Training",
            "type":"Services"
        }
    ],
    "sg:phone":"+1 541 889 7864",
    "sg:postcode":"97914",
    "sg:province":"OR",
    "sg:tags":[
        "employment"
    ],
    "sg:website":"www.trainingemployment.org",
    "wof:name":"Training Employment Consortium",
    "wof:placetype":"venue"
},
  "geometry": {"coordinates":[-116.940361,44.023253],"type":"Point"}
}