{
  "type": "Feature",
  "properties": {
    "iso:country":"US",
    "sg:address":"3492 Marcola Rd",
    "sg:city":"Springfield",
    "sg:classifiers":[
        {
            "category":"Home & Garden",
            "subcategory":"Building Materials",
            "type":"Retail Goods"
        }
    ],
    "sg:phone":"+1 541 726 6507",
    "sg:postcode":"97478",
    "sg:province":"OR",
    "sg:tags":[
        "repair",
        "glass"
    ],
    "wof:name":"I-5 Glass",
    "wof:placetype":"venue"
},
  "geometry": {"coordinates":[-122.974158,44.065192],"type":"Point"}
}