{
  "type": "Feature",
  "properties": {
    "iso:country":"US",
    "sg:address":"36823 Honey Sign Dr",
    "sg:city":"Lebanon",
    "sg:classifiers":[
        {
            "category":"Farming",
            "subcategory":"Farm",
            "type":"Manufacturing & Wholesale Goods"
        }
    ],
    "sg:phone":"+1 541 258 5631",
    "sg:postcode":"97355",
    "sg:province":"OR",
    "sg:tags":[
        "crop",
        "general"
    ],
    "wof:name":"Red Oak Farm",
    "wof:placetype":"venue"
},
  "geometry": {"coordinates":[-122.92436,44.604191],"type":"Point"}
}