{
  "type": "Feature",
  "properties": {
    "iso:country":"US",
    "sg:address":"2310 NW Everett St",
    "sg:city":"Portland",
    "sg:classifiers":[
        {
            "category":"Organizations",
            "subcategory":"Community Association",
            "type":"Services"
        }
    ],
    "sg:phone":"+1 503 223 4204",
    "sg:postcode":"97210",
    "sg:province":"OR",
    "sg:tags":[
        "support",
        "business"
    ],
    "wof:name":"Passport Unlimited",
    "wof:placetype":"venue"
},
  "geometry": {"coordinates":[-122.699584,45.524697],"type":"Point"}
}