{
  "type": "Feature",
  "properties": {
    "iso:country":"US",
    "sg:address":"3333 Anderson Ave",
    "sg:city":"Klamath Falls",
    "sg:classifiers":[
        {
            "category":"Professional",
            "subcategory":"Computer Services",
            "type":"Services"
        }
    ],
    "sg:phone":"+1 541 885 2932",
    "sg:postcode":"97603",
    "sg:province":"OR",
    "sg:tags":[
        "related"
    ],
    "wof:name":"Theeric Computer Consulting",
    "wof:placetype":"venue"
},
  "geometry": {"coordinates":[-121.749015,42.181292],"type":"Point"}
}