{
  "type": "Feature",
  "properties": {
    "iso:country":"US",
    "sg:address":"628 W 19th St",
    "sg:city":"Mcminnville",
    "sg:classifiers":[
        {
            "category":"Shopping",
            "type":"Retail Goods"
        }
    ],
    "sg:phone":"+1 503 472 9792",
    "sg:postcode":"97128",
    "sg:province":"OR",
    "sg:tags":[
        "merchandise"
    ],
    "wof:name":"Jti LLC",
    "wof:placetype":"venue"
},
  "geometry": {"coordinates":[-123.205116,45.221783],"type":"Point"}
}