{
  "type": "Feature",
  "properties": {
    "iso:country":"US",
    "sg:address":"645 E 3rd St",
    "sg:city":"Mcminnville",
    "sg:classifiers":[
        {
            "category":"Home & Garden",
            "subcategory":"Building Materials",
            "type":"Retail Goods"
        },
        {
            "category":"Retail",
            "subcategory":"Auto Repair",
            "type":"Services"
        }
    ],
    "sg:phone":"+1 503 472 7800",
    "sg:postcode":"97128",
    "sg:province":"OR",
    "sg:tags":[
        "plate",
        "window",
        "replacement",
        "glass",
        "contractor"
    ],
    "wof:name":"McMinnville Glass Shop Inc",
    "wof:placetype":"venue"
},
  "geometry": {"coordinates":[-123.192871,45.210096],"type":"Point"}
}