{
  "type": "Feature",
  "properties": {
    "iso:country":"US",
    "sg:address":"415 NE 80th Ave",
    "sg:city":"Portland",
    "sg:classifiers":[
        {
            "category":"Building & Trades",
            "subcategory":"Construction",
            "type":"Services"
        }
    ],
    "sg:phone":"+1 503 546 7304",
    "sg:postcode":"97213",
    "sg:province":"OR",
    "sg:tags":[
        "roofing",
        "contractor"
    ],
    "wof:name":"Roof It Yourself",
    "wof:placetype":"venue"
},
  "geometry": {"coordinates":[-122.58153299999999,45.525867],"type":"Point"}
}