{
  "type": "Feature",
  "properties": {
    "iso:country":"US",
    "sg:address":"11360 SW Beaverton-Hillsdale Hwy",
    "sg:city":"Beaverton",
    "sg:classifiers":[
        {
            "category":"Home & Garden",
            "subcategory":"Furniture",
            "type":"Retail Goods"
        }
    ],
    "sg:phone":"+1 503 646 4219",
    "sg:postcode":"97005",
    "sg:province":"OR",
    "sg:tags":[
        "mattress"
    ],
    "wof:name":"Sleep Country USA",
    "wof:placetype":"venue"
},
  "geometry": {"coordinates":[-122.79341599999999,45.486468],"type":"Point"}
}