{
  "type": "Feature",
  "properties": {
    "iso:country":"US",
    "sg:address":"124 NW Midland Ave",
    "sg:city":"Grants Pass",
    "sg:classifiers":[
        {
            "category":"Health Services",
            "subcategory":"Doctor",
            "type":"Services"
        }
    ],
    "sg:phone":"+1 541 474 2944",
    "sg:postcode":"97526",
    "sg:province":"OR",
    "sg:tags":[
        "physician",
        "surgeon",
        "medical"
    ],
    "wof:name":"Steven R Foutz MD",
    "wof:placetype":"venue"
},
  "geometry": {"coordinates":[-123.32312,42.45506],"type":"Point"}
}