{
  "type": "Feature",
  "properties": {
    "iso:country":"US",
    "sg:address":"135 Silver Ln Ste 200",
    "sg:city":"Eugene",
    "sg:classifiers":[
        {
            "category":"Banks & Credit Unions",
            "subcategory":"Financial Services",
            "type":"Services"
        },
        {
            "category":"Professional",
            "subcategory":"Credit Reporting & Collection",
            "type":"Services"
        }
    ],
    "sg:phone":"+1 541 688 9445",
    "sg:postcode":"97404",
    "sg:province":"OR",
    "sg:tags":[
        "debt",
        "adjuster",
        "agency"
    ],
    "sg:website":"http://www.pacificcoastcredit.com",
    "wof:name":"Pacific Coast Credit",
    "wof:placetype":"venue"
},
  "geometry": {"coordinates":[-123.13061999999999,44.095596],"type":"Point"}
}