{
  "type": "Feature",
  "properties": {
    "addr:full":"720 Shelokum Dr Silverton OR 97381",
    "addr:housenumber":"720",
    "addr:postcode":"97381",
    "addr:street":"Shelokum Dr",
    "iso:country":"US",
    "sg:address":"720 Shelokum Dr",
    "sg:city":"Silverton",
    "sg:classifiers":[
        {
            "category":"Manufacturing",
            "subcategory":"Buildings",
            "type":"Manufacturing & Wholesale Goods"
        },
        {
            "category":"Building & Trades",
            "subcategory":"Construction",
            "type":"Services"
        }
    ],
    "sg:phone":"+1 503 874 8822",
    "sg:postcode":"97381",
    "sg:province":"OR",
    "sg:tags":[
        "home",
        "builder",
        "contractor"
    ],
    "sg:website":"http://www.a-wardwinninghomes.com",
    "wof:name":"Award Winning Homes",
    "wof:placetype":"venue"
},
  "geometry": {"coordinates":[-122.772308,45.001678],"type":"Point"}
}