{
  "type": "Feature",
  "properties": {
    "iso:country":"US",
    "sg:address":"5291 Chinook Ct",
    "sg:city":"Lake Oswego",
    "sg:classifiers":[
        {
            "category":"Social Services",
            "type":"Services"
        }
    ],
    "sg:phone":"+1 503 620 8689",
    "sg:postcode":"97035",
    "sg:province":"OR",
    "sg:tags":[
        "home",
        "referral",
        "nursing",
        "information"
    ],
    "wof:name":"Abby's Referral For Adult Care",
    "wof:placetype":"venue"
},
  "geometry": {"coordinates":[-122.73170399999999,45.391173],"type":"Point"}
}