{
  "type": "Feature",
  "properties": {
    "iso:country":"US",
    "sg:address":"2445 SW Roxbury Ave",
    "sg:city":"Portland",
    "sg:classifiers":[
        {
            "category":"Professional",
            "type":"Services"
        }
    ],
    "sg:phone":"+1 503 641 2283",
    "sg:postcode":"97225",
    "sg:province":"OR",
    "wof:name":"Allison King Vocal Studio",
    "wof:placetype":"venue"
},
  "geometry": {"coordinates":[-122.78842,45.5025],"type":"Point"}
}