{
  "type": "Feature",
  "properties": {
    "addr:full":"7378 Lookingglass Rd Roseburg OR 97470",
    "addr:housenumber":"7378",
    "addr:postcode":"97470",
    "addr:street":"Lookingglass Rd",
    "iso:country":"US",
    "sg:address":"7378 Lookingglass Rd",
    "sg:city":"Roseburg",
    "sg:classifiers":[
        {
            "category":"Food & Beverages",
            "subcategory":"Groceries & Convenience Stores",
            "type":"Retail Goods"
        }
    ],
    "sg:phone":"+1 541 679 5651",
    "sg:postcode":"97470",
    "sg:province":"OR",
    "sg:tags":[
        "independent",
        "grocer"
    ],
    "wof:name":"Lookingglass Store",
    "wof:placetype":"venue"
},
  "geometry": {"coordinates":[-123.485832,43.177854],"type":"Point"}
}