{
  "type": "Feature",
  "properties": {
    "iso:country":"US",
    "sg:address":"216 Redwood Hwy",
    "sg:city":"Grants Pass",
    "sg:classifiers":[
        {
            "category":"Home & Garden",
            "subcategory":"Household Appliances",
            "type":"Retail Goods"
        }
    ],
    "sg:phone":"+1 541 476 2183",
    "sg:postcode":"97527",
    "sg:province":"OR",
    "sg:tags":[
        "machine",
        "repair",
        "vacuum",
        "sewing",
        "cleaners"
    ],
    "wof:name":"Bernina Sewing & Vacuum Center",
    "wof:placetype":"venue"
},
  "geometry": {"coordinates":[-123.332832,42.425032],"type":"Point"}
}