{
  "type": "Feature",
  "properties": {
    "iso:country":"US",
    "sg:address":"35696 SE Squaw Mountain Rd",
    "sg:city":"Estacada",
    "sg:classifiers":[
        {
            "category":"Wholesale",
            "subcategory":"Painting Supplies",
            "type":"Manufacturing & Wholesale Goods"
        }
    ],
    "sg:phone":"+1 503 630 7664",
    "sg:postcode":"97023",
    "sg:province":"OR",
    "sg:tags":[
        "paint-wholesale",
        "manufacturer"
    ],
    "wof:name":"Estes William Auto Body",
    "wof:placetype":"venue"
},
  "geometry": {"coordinates":[-122.298852,45.280886],"type":"Point"}
}