{
  "type": "Feature",
  "properties": {
    "iso:country":"US",
    "sg:address":"17420 SE Division St",
    "sg:city":"Portland",
    "sg:classifiers":[
        {
            "category":"Professional",
            "subcategory":"Business Services",
            "type":"Services"
        }
    ],
    "sg:phone":"+1 503 762 5840",
    "sg:postcode":"97236",
    "sg:province":"OR",
    "sg:tags":[
        "liquidator"
    ],
    "wof:name":"Six Day Liquidators",
    "wof:placetype":"venue"
},
  "geometry": {"coordinates":[-122.483902,45.504508],"type":"Point"}
}