{
  "type": "Feature",
  "properties": {
    "addr:full":"2170 NW Wilson St Portland OR 97210",
    "addr:housenumber":"2170",
    "addr:postcode":"97210",
    "addr:street":"Nw Wilson St",
    "iso:country":"US",
    "sg:address":"2170 NW Wilson St",
    "sg:city":"Portland",
    "sg:classifiers":[
        {
            "category":"Autos & Motor Vehicles",
            "subcategory":"Automobile Sales",
            "type":"Retail Goods"
        },
        {
            "category":"Autos & Motor Vehicles",
            "subcategory":"Auto Supplies",
            "type":"Retail Goods"
        },
        {
            "category":"Autos & Motor Vehicles",
            "subcategory":"Motorcycle Sales",
            "type":"Retail Goods"
        },
        {
            "category":"Retail",
            "subcategory":"Auto Repair",
            "type":"Services"
        }
    ],
    "sg:phone":"+1 503 292 7488",
    "sg:postcode":"97210",
    "sg:province":"OR",
    "sg:tags":[
        "used",
        "car",
        "accessory",
        "dealers-used",
        "part",
        "new",
        "cars-wholesale"
    ],
    "sg:website":"www.motocorsa.com",
    "wof:name":"MotoCorsa",
    "wof:placetype":"venue"
},
  "geometry": {"coordinates":[-122.69628,45.537671],"type":"Point"}
}