{
  "type": "Feature",
  "properties": {
    "iso:country":"US",
    "sg:address":"10706 SW Capitol Hwy",
    "sg:city":"Portland",
    "sg:classifiers":[
        {
            "category":"Building & Trades",
            "subcategory":"Construction",
            "type":"Services"
        }
    ],
    "sg:phone":"+1 503 246 9931",
    "sg:postcode":"97219",
    "sg:province":"OR",
    "sg:tags":[
        "roofing",
        "contractor"
    ],
    "wof:name":"ARM Roofing",
    "wof:placetype":"venue"
},
  "geometry": {"coordinates":[-122.72475900000001,45.448448],"type":"Point"}
}