{
  "type": "Feature",
  "properties": {
    "addr:full":"5285 SW Philomath Blvd Corvallis OR 97333",
    "addr:housenumber":"5285",
    "addr:postcode":"97333",
    "addr:street":"Sw Philomath Blvd",
    "iso:country":"US",
    "sg:address":"5285 SW Philomath Blvd",
    "sg:city":"Corvallis",
    "sg:classifiers":[
        {
            "category":"Personal",
            "subcategory":"Beauty Salon",
            "type":"Services"
        }
    ],
    "sg:phone":"+1 541 754 9348",
    "sg:postcode":"97333",
    "sg:province":"OR",
    "sg:tags":[
        "shop"
    ],
    "wof:name":"Barbs Little Salon",
    "wof:placetype":"venue"
},
  "geometry": {"coordinates":[-123.311769,44.550983],"type":"Point"}
}