{
  "type": "Feature",
  "properties": {
    "iso:country":"US",
    "sg:address":"1539 NW 19th Ave.",
    "sg:city":"Portland",
    "sg:classifiers":[
        {
            "category":"Real Estate",
            "subcategory":"Real Estate Services",
            "type":"Services"
        }
    ],
    "sg:phone":"+1 503 287 4346",
    "sg:postcode":"97212",
    "sg:province":"OR",
    "sg:website":"www.capmng.com/",
    "wof:name":"Capital Property Management",
    "wof:placetype":"venue"
},
  "geometry": {"coordinates":[-122.69080599999999,45.53404],"type":"Point"}
}