{
  "type": "Feature",
  "properties": {
    "addr:full":"10202 SE 32nd Ave Milwaukie OR 97222",
    "addr:housenumber":"10202",
    "addr:postcode":"97222",
    "addr:street":"Se 32Nd Ave",
    "iso:country":"US",
    "sg:address":"10202 SE 32nd Ave",
    "sg:city":"Milwaukie",
    "sg:classifiers":[
        {
            "category":"Health Services",
            "subcategory":"Health Practitioner",
            "type":"Services"
        }
    ],
    "sg:phone":"+1 503 513 8701",
    "sg:postcode":"97222",
    "sg:province":"OR",
    "sg:tags":[
        "midwife"
    ],
    "wof:name":"Milwaukie Women's Clinic",
    "wof:placetype":"venue"
},
  "geometry": {"coordinates":[-122.62965199999999,45.447839],"type":"Point"}
}