{
  "type": "Feature",
  "properties": {
    "iso:country":"US",
    "sg:address":"3506 SE 66th Ave",
    "sg:city":"Portland",
    "sg:classifiers":[
        {
            "category":"Building & Trades",
            "subcategory":"Electrical",
            "type":"Services"
        }
    ],
    "sg:phone":"+1 503 777 5090",
    "sg:postcode":"97206",
    "sg:province":"OR",
    "sg:tags":[
        "electric",
        "contractor"
    ],
    "wof:name":"Rl Electrical Construction",
    "wof:placetype":"venue"
},
  "geometry": {"coordinates":[-122.595213,45.495737],"type":"Point"}
}