{
  "type": "Feature",
  "properties": {
    "iso:country":"US",
    "sg:address":"2595 Broadway St",
    "sg:city":"Baker City",
    "sg:classifiers":[
        {
            "category":"Building & Trades",
            "subcategory":"Plumbing",
            "type":"Services"
        }
    ],
    "sg:phone":"+1 541 523 3402",
    "sg:postcode":"97814",
    "sg:province":"OR",
    "sg:tags":[
        "heating",
        "contractor"
    ],
    "wof:name":"Valley Metal & Heating",
    "wof:placetype":"venue"
},
  "geometry": {"coordinates":[-117.837369,44.778032],"type":"Point"}
}