{
  "type": "Feature",
  "properties": {
    "addr:full":"403 NE 11th St Grants Pass OR 97526",
    "addr:housenumber":"403",
    "addr:postcode":"97526",
    "addr:street":"Ne 11Th St",
    "iso:country":"US",
    "sg:address":"403 NE 11th St",
    "sg:city":"Grants Pass",
    "sg:classifiers":[
        {
            "category":"Restaurant",
            "type":"Food & Drink"
        }
    ],
    "sg:phone":"+1 541 474 2561",
    "sg:postcode":"97526",
    "sg:province":"OR",
    "wof:name":"Dotties Diner",
    "wof:placetype":"venue"
},
  "geometry": {"coordinates":[-123.310603,42.4402],"type":"Point"}
}