{
  "type": "Feature",
  "properties": {
    "addr:full":"880 E Elm Ave Hermiston OR 97838",
    "addr:housenumber":"880",
    "addr:postcode":"97838",
    "addr:street":"E Elm Ave",
    "iso:country":"US",
    "sg:address":"880 E Elm Ave",
    "sg:city":"Hermiston",
    "sg:classifiers":[
        {
            "category":"Building & Trades",
            "subcategory":"Construction",
            "type":"Services"
        }
    ],
    "sg:phone":"+1 541 567 6106",
    "sg:postcode":"97838",
    "sg:province":"OR",
    "sg:tags":[
        "excavating",
        "contractor"
    ],
    "wof:name":"Kalal Construction Inc",
    "wof:placetype":"venue"
},
  "geometry": {"coordinates":[-119.276375,45.849314],"type":"Point"}
}