{
  "type": "Feature",
  "properties": {
    "iso:country":"US",
    "sg:address":"12805 SW 22nd St",
    "sg:city":"Beaverton",
    "sg:classifiers":[
        {
            "category":"Manufacturing",
            "subcategory":"Printing",
            "type":"Manufacturing & Wholesale Goods"
        }
    ],
    "sg:phone":"+1 503 626 3837",
    "sg:postcode":"97008",
    "sg:province":"OR",
    "sg:tags":[
        "printer",
        "form",
        "system",
        "business"
    ],
    "wof:name":"Janco Business Forms Supply",
    "wof:placetype":"venue"
},
  "geometry": {"coordinates":[-122.807619,45.47195],"type":"Point"}
}