{
  "type": "Feature",
  "properties": {
    "addr:full":"113 S 10th St Philomath OR 97370",
    "addr:housenumber":"113",
    "addr:postcode":"97370",
    "addr:street":"S 10Th St",
    "iso:country":"US",
    "sg:address":"113 S 10th St",
    "sg:city":"Philomath",
    "sg:classifiers":[
        {
            "category":"Professional",
            "subcategory":"Computer Services",
            "type":"Services"
        }
    ],
    "sg:phone":"+1 541 929 3203",
    "sg:postcode":"97370",
    "sg:province":"OR",
    "sg:tags":[
        "information",
        "geographic",
        "system"
    ],
    "wof:name":"Aimee Lesieutre",
    "wof:placetype":"venue"
},
  "geometry": {"coordinates":[-123.37227300000001,44.53993],"type":"Point"}
}