{
  "type": "Feature",
  "properties": {
    "iso:country":"US",
    "sg:address":"2705 E Burnside St # 108",
    "sg:city":"Portland",
    "sg:classifiers":[
        {
            "category":"Social Services",
            "type":"Services"
        },
        {
            "category":"Professional",
            "subcategory":"Employment Agencies",
            "type":"Services"
        }
    ],
    "sg:phone":"+1 503 233 0190",
    "sg:postcode":"97214",
    "sg:province":"OR",
    "sg:tags":[
        "workers'",
        "placement",
        "volunteer"
    ],
    "sg:website":"http://www.oregonaeyc.org",
    "wof:name":"Oregon A.E.Y.C.",
    "wof:placetype":"venue"
},
  "geometry": {"coordinates":[-122.63784099999999,45.522878],"type":"Point"}
}