{
  "type": "Feature",
  "properties": {
    "addr:full":"3491 Wildwood Ct NW Salem OR 97304",
    "addr:housenumber":"3491",
    "addr:postcode":"97304",
    "addr:street":"Wildwood Ct Nw",
    "iso:country":"US",
    "sg:address":"3491 Wildwood Ct NW",
    "sg:city":"Salem",
    "sg:classifiers":[
        {
            "category":"Wholesale",
            "subcategory":"Machinery & Supplies",
            "type":"Manufacturing & Wholesale Goods"
        }
    ],
    "sg:phone":"+1 503 588 7857",
    "sg:postcode":"97304",
    "sg:province":"OR",
    "sg:tags":[
        "carpet",
        "cleaning",
        "rug"
    ],
    "wof:name":"Mold Technologies",
    "wof:placetype":"venue"
},
  "geometry": {"coordinates":[-123.099069,44.94882],"type":"Point"}
}