{
  "type": "Feature",
  "properties": {
    "iso:country":"US",
    "sg:address":"37201 SE Boitano Rd",
    "sg:city":"Sandy",
    "sg:classifiers":[
        {
            "category":"Farming",
            "subcategory":"Livestock Farm",
            "type":"Manufacturing & Wholesale Goods"
        }
    ],
    "sg:phone":"+1 503 668 4559",
    "sg:postcode":"97055",
    "sg:province":"OR",
    "sg:tags":[
        "ranch"
    ],
    "wof:name":"Mario And Dolores Boitano",
    "wof:placetype":"venue"
},
  "geometry": {"coordinates":[-122.28430400000001,45.367783],"type":"Point"}
}