{
  "type": "Feature",
  "properties": {
    "iso:country":"US",
    "sg:address":"330 SE 6th Ave",
    "sg:city":"Portland",
    "sg:classifiers":[
        {
            "category":"Retail",
            "subcategory":"Repair Shop",
            "type":"Services"
        }
    ],
    "sg:phone":"+1 503 233 5225",
    "sg:postcode":"97214",
    "sg:province":"OR",
    "sg:tags":[
        "armature",
        "electrical",
        "rewinding"
    ],
    "wof:name":"Superior Electric Motor Svc",
    "wof:placetype":"venue"
},
  "geometry": {"coordinates":[-122.65963499999999,45.520293],"type":"Point"}
}