{
  "type": "Feature",
  "properties": {
    "addr:full":"720 SE Sandy Blvd Portland OR 97214",
    "addr:housenumber":"720",
    "addr:postcode":"97214",
    "addr:street":"Se Sandy Blvd",
    "iso:country":"US",
    "sg:address":"720 SE Sandy Blvd",
    "sg:city":"Portland",
    "sg:classifiers":[
        {
            "category":"Professional",
            "subcategory":"Management & Consulting",
            "type":"Services"
        }
    ],
    "sg:phone":"+1 503 233 7791",
    "sg:postcode":"97214",
    "sg:province":"OR",
    "sg:tags":[
        "material",
        "handling",
        "furniture"
    ],
    "wof:name":"Kruegers Liquidators",
    "wof:placetype":"venue"
},
  "geometry": {"coordinates":[-122.657804,45.519156],"type":"Point"}
}