{
  "type": "Feature",
  "properties": {
    "addr:full":"1220 Montello Ave Hood River OR 97031",
    "addr:housenumber":"1220",
    "addr:postcode":"97031",
    "addr:street":"Montello Ave",
    "iso:country":"US",
    "sg:address":"1220 Montello Ave",
    "sg:city":"Hood River",
    "sg:classifiers":[
        {
            "category":"Professional",
            "subcategory":"Business Services",
            "type":"Services"
        }
    ],
    "sg:phone":"+1 541 386 1094",
    "sg:postcode":"97031",
    "sg:province":"OR",
    "wof:name":"Valerie Dosch Int Design",
    "wof:placetype":"venue"
},
  "geometry": {"coordinates":[-121.524232,45.705574],"type":"Point"}
}