{
  "type": "Feature",
  "properties": {
    "iso:country":"US",
    "sg:address":"618 Holly St",
    "sg:city":"Junction City",
    "sg:classifiers":[
        {
            "category":"Retail",
            "subcategory":"Auto Repair",
            "type":"Services"
        }
    ],
    "sg:phone":"+1 541 998 6035",
    "sg:postcode":"97448",
    "sg:province":"OR",
    "sg:tags":[
        "wrecker"
    ],
    "wof:name":"Jim's Towing",
    "wof:placetype":"venue"
},
  "geometry": {"coordinates":[-123.203586,44.219891],"type":"Point"}
}