{
  "type": "Feature",
  "properties": {
    "iso:country":"US",
    "sg:address":"8775 SW Cascade Ave",
    "sg:city":"Beaverton",
    "sg:classifiers":[
        {
            "category":"Home & Garden",
            "subcategory":"Furniture",
            "type":"Retail Goods"
        }
    ],
    "sg:phone":"+1 503 626 9340",
    "sg:postcode":"97008",
    "sg:province":"OR",
    "sg:tags":[
        "mattress"
    ],
    "wof:name":"Mattress World",
    "wof:placetype":"venue"
},
  "geometry": {"coordinates":[-122.786118,45.449657],"type":"Point"}
}