{
  "type": "Feature",
  "properties": {
    "addr:full":"4033 NW Yeon Ave Portland OR 97210",
    "addr:housenumber":"4033",
    "addr:postcode":"97210",
    "addr:street":"Nw Yeon Ave",
    "iso:country":"US",
    "sg:address":"4033 NW Yeon Ave",
    "sg:city":"Portland",
    "sg:classifiers":[
        {
            "category":"Manufacturing",
            "subcategory":"Metals",
            "type":"Manufacturing & Wholesale Goods"
        },
        {
            "category":"Wholesale",
            "subcategory":"Metals & Minerals",
            "type":"Manufacturing & Wholesale Goods"
        }
    ],
    "sg:phone":"+1 503 226 1511",
    "sg:postcode":"97210",
    "sg:province":"OR",
    "sg:tags":[
        "steel",
        "fabricated",
        "center",
        "structural"
    ],
    "wof:name":"American Steel L L C",
    "wof:placetype":"venue"
},
  "geometry": {"coordinates":[-122.731247,45.554016],"type":"Point"}
}