{
  "type": "Feature",
  "properties": {
    "iso:country":"US",
    "sg:address":"1205 N Pacific Hwy",
    "sg:city":"Cottage Grove",
    "sg:classifiers":[
        {
            "category":"Personal",
            "subcategory":"Beauty Salon",
            "type":"Services"
        }
    ],
    "sg:phone":"+1 541 942 1688",
    "sg:postcode":"97424",
    "sg:province":"OR",
    "wof:name":"New Creations Hair Design",
    "wof:placetype":"venue"
},
  "geometry": {"coordinates":[-123.05664,43.804529],"type":"Point"}
}