{
  "type": "Feature",
  "properties": {
    "iso:country":"US",
    "sg:address":"5253 SE 82nd Ave",
    "sg:city":"Portland",
    "sg:classifiers":[
        {
            "category":"Shopping",
            "subcategory":"Department Store",
            "type":"Retail Goods"
        }
    ],
    "sg:phone":"+1 503 788 2867",
    "sg:postcode":"97266",
    "sg:province":"OR",
    "sg:tags":[
        "grocery"
    ],
    "sg:website":"www.fredmeyer.com",
    "wof:name":"Fred Meyer",
    "wof:placetype":"venue"
},
  "geometry": {"coordinates":[-122.578959,45.484209],"type":"Point"}
}