{
  "type": "Feature",
  "properties": {
    "iso:country":"US",
    "sg:address":"548 SW 11th St",
    "sg:city":"Newport",
    "sg:classifiers":[
        {
            "category":"Communications",
            "subcategory":"Film & Video Production",
            "type":"Services"
        }
    ],
    "sg:phone":"+1 541 265 8258",
    "sg:postcode":"97365",
    "sg:province":"OR",
    "sg:tags":[
        "motion",
        "picture",
        "taping"
    ],
    "wof:name":"Pacific Media Productions",
    "wof:placetype":"venue"
},
  "geometry": {"coordinates":[-124.056667,44.630725],"type":"Point"}
}