{
  "type": "Feature",
  "properties": {
    "iso:country":"US",
    "sg:address":"195 SW Meadow Dr",
    "sg:city":"Beaverton",
    "sg:classifiers":[
        {
            "category":"Building & Trades",
            "subcategory":"Construction",
            "type":"Services"
        }
    ],
    "sg:phone":"+1 503 674 7959",
    "sg:postcode":"97006",
    "sg:province":"OR",
    "sg:tags":[
        "residential"
    ],
    "wof:name":"N Brothers Construction",
    "wof:placetype":"venue"
},
  "geometry": {"coordinates":[-122.827145,45.516574],"type":"Point"}
}