{
  "type": "Feature",
  "properties": {
    "iso:country":"US",
    "sg:address":"5600 Mill Creek Rd",
    "sg:city":"Prineville",
    "sg:classifiers":[
        {
            "category":"Farming",
            "subcategory":"Livestock Farm",
            "type":"Manufacturing & Wholesale Goods"
        }
    ],
    "sg:phone":"+1 541 447 4131",
    "sg:postcode":"97754",
    "sg:province":"OR",
    "sg:tags":[
        "beef",
        "feedlot",
        "cattle"
    ],
    "wof:name":"Bill Coffer",
    "wof:placetype":"venue"
},
  "geometry": {"coordinates":[-120.670338,44.344863],"type":"Point"}
}