{
  "type": "Feature",
  "properties": {
    "iso:country":"US",
    "sg:address":"87563 Oberman Rd",
    "sg:city":"Bandon",
    "sg:classifiers":[
        {
            "category":"Home & Garden",
            "subcategory":"Mobile Homes",
            "type":"Retail Goods"
        }
    ],
    "sg:phone":"+1 541 347 2030",
    "sg:postcode":"97411",
    "sg:province":"OR",
    "sg:tags":[
        "dealer"
    ],
    "wof:name":"By The Sea Homes Inc",
    "wof:placetype":"venue"
},
  "geometry": {"coordinates":[-124.417615,43.088304],"type":"Point"}
}