{
  "type": "Feature",
  "properties": {
    "addr:full":"10400 NE Halsey St Portland OR 97220",
    "addr:housenumber":"10400",
    "addr:postcode":"97220",
    "addr:street":"Ne Halsey St",
    "iso:country":"US",
    "sg:address":"10400 NE Halsey St",
    "sg:city":"Portland",
    "sg:classifiers":[
        {
            "category":"Autos & Motor Vehicles",
            "subcategory":"Auto Supplies",
            "type":"Retail Goods"
        },
        {
            "category":"Wholesale",
            "subcategory":"Auto Parts",
            "type":"Manufacturing & Wholesale Goods"
        },
        {
            "category":"Retail",
            "subcategory":"Auto Repair",
            "type":"Services"
        }
    ],
    "sg:phone":"+1 503 252 1493",
    "sg:postcode":"97220",
    "sg:province":"OR",
    "sg:tags":[
        "wheel",
        "shop",
        "automobile",
        "vehicles-supplies",
        "drive",
        "accessory",
        "four",
        "equipment",
        "machine",
        "truck"
    ],
    "wof:name":"Scs Auto Parts, Inc",
    "wof:placetype":"venue"
},
  "geometry": {"coordinates":[-122.555481,45.533531],"type":"Point"}
}