{
  "type": "Feature",
  "properties": {
    "iso:country":"US",
    "sg:address":"1859 Riverside Dr",
    "sg:city":"Klamath Falls",
    "sg:classifiers":[
        {
            "category":"Retail",
            "subcategory":"Auto Repair",
            "type":"Services"
        }
    ],
    "sg:phone":"+1 541 273 0291",
    "sg:postcode":"97601",
    "sg:province":"OR",
    "sg:tags":[
        "general"
    ],
    "wof:name":"Jbs Great Basin Truck Repair",
    "wof:placetype":"venue"
},
  "geometry": {"coordinates":[-121.788366,42.202944],"type":"Point"}
}