{
  "type": "Feature",
  "properties": {
    "iso:country":"US",
    "sg:address":"19300 SW 65th Ave",
    "sg:city":"Tualatin",
    "sg:classifiers":[
        {
            "category":"Health Services",
            "subcategory":"Doctor",
            "type":"Services"
        }
    ],
    "sg:phone":"+1 503 692 7447",
    "sg:postcode":"97062",
    "sg:province":"OR",
    "wof:name":"Legacy Imaging & Radiology Services",
    "wof:placetype":"venue"
},
  "geometry": {"coordinates":[-122.74400300000001,45.380699],"type":"Point"}
}