{
  "type": "Feature",
  "properties": {
    "iso:country":"US",
    "sg:address":"549 Hansen Ave S",
    "sg:city":"Salem",
    "sg:classifiers":[
        {
            "category":"Professional",
            "type":"Services"
        }
    ],
    "sg:phone":"+1 503 364 0146",
    "sg:postcode":"97302",
    "sg:province":"OR",
    "wof:name":"Kyle Kelso Foundation Inc",
    "wof:placetype":"venue"
},
  "geometry": {"coordinates":[-123.052741,44.912244],"type":"Point"}
}