{
  "type": "Feature",
  "properties": {
    "iso:country":"US",
    "sg:address":"128 W Antler Ave",
    "sg:city":"Redmond",
    "sg:classifiers":[
        {
            "category":"Insurance",
            "subcategory":"Insurance Agent",
            "type":"Services"
        }
    ],
    "sg:phone":"+1 541 923 5190",
    "sg:postcode":"97756",
    "sg:province":"OR",
    "wof:name":"Country Mutual Insurance Co",
    "wof:placetype":"venue"
},
  "geometry": {"coordinates":[-121.169791,44.276445],"type":"Point"}
}