{
  "type": "Feature",
  "properties": {
    "iso:country":"US",
    "sg:address":"1654 NW Crest Pl",
    "sg:city":"Corvallis",
    "sg:classifiers":[
        {
            "category":"Professional",
            "type":"Services"
        }
    ],
    "sg:phone":"+1 541 754 0622",
    "sg:postcode":"97330",
    "sg:province":"OR",
    "sg:tags":[
        "consulting",
        "geologist"
    ],
    "wof:name":"Robert S Yeats Dr",
    "wof:placetype":"venue"
},
  "geometry": {"coordinates":[-123.285731,44.584388],"type":"Point"}
}