{
  "type": "Feature",
  "properties": {
    "addr:full":"2487 Pheasant Blvd Apt 39 Springfield OR 97477",
    "addr:housenumber":"2487;39",
    "addr:postcode":"97477",
    "addr:street":"Pheasant Blvd Apt",
    "iso:country":"US",
    "sg:address":"2487 Pheasant Blvd Apt 39",
    "sg:city":"Springfield",
    "sg:classifiers":[
        {
            "category":"Real Estate",
            "subcategory":"Real Estate Services",
            "type":"Services"
        },
        {
            "category":"Real Estate",
            "subcategory":"Real Estate Operator",
            "type":"Services"
        }
    ],
    "sg:phone":"+1 541 746 3311",
    "sg:postcode":"97477",
    "sg:province":"OR",
    "sg:tags":[
        "apartment",
        "vacancy",
        "listing",
        "rental",
        "finder"
    ],
    "wof:name":"Pheasant Court Apts",
    "wof:placetype":"venue"
},
  "geometry": {"coordinates":[-123.03334,44.070186],"type":"Point"}
}