{
  "type": "Feature",
  "properties": {
    "iso:country":"US",
    "sg:address":"15780 Wilson River Hwy",
    "sg:city":"Tillamook",
    "sg:classifiers":[
        {
            "category":"Animal Shelter",
            "type":"Public Place"
        },
        {
            "category":"Retail",
            "subcategory":"Pet Boarding",
            "type":"Services"
        }
    ],
    "sg:phone":"+1 503 842 6930",
    "sg:postcode":"97141",
    "sg:province":"OR",
    "sg:tags":[
        "kennel"
    ],
    "wof:name":"Wilson River K9 Lodge",
    "wof:placetype":"venue"
},
  "geometry": {"coordinates":[-123.687117,45.491453],"type":"Point"}
}