{
  "type": "Feature",
  "properties": {
    "addr:full":"2900 SE 122nd Ave Portland OR 97236",
    "addr:housenumber":"2900",
    "addr:postcode":"97236",
    "addr:street":"Se 122Nd Ave",
    "iso:country":"US",
    "sg:address":"2900 SE 122nd Ave",
    "sg:city":"Portland",
    "sg:classifiers":[
        {
            "category":"Government",
            "subcategory":"Office",
            "type":"Public Place"
        }
    ],
    "sg:phone":"+1 503 988 5480",
    "sg:postcode":"97236",
    "sg:province":"OR",
    "sg:tags":[
        "county",
        "resource"
    ],
    "wof:name":"Multnomah County Aging Svc",
    "wof:placetype":"venue"
},
  "geometry": {"coordinates":[-122.537588,45.502033],"type":"Point"}
}