{
  "type": "Feature",
  "properties": {
    "iso:country":"US",
    "sg:address":"103 SW 1st Ave",
    "sg:city":"John Day",
    "sg:classifiers":[
        {
            "category":"Professional",
            "subcategory":"Computer Services",
            "type":"Services"
        }
    ],
    "sg:phone":"+1 541 575 2000",
    "sg:postcode":"97845",
    "sg:province":"OR",
    "wof:name":"High Desert Net Inc",
    "wof:placetype":"venue"
},
  "geometry": {"coordinates":[-118.95365099999999,44.415089],"type":"Point"}
}