{
  "type": "Feature",
  "properties": {
    "iso:country":"US",
    "sg:address":"8956 NE Killingsworth St",
    "sg:city":"Portland",
    "sg:classifiers":[
        {
            "category":"Retail",
            "subcategory":"Auto Repair",
            "type":"Services"
        }
    ],
    "sg:phone":"+1 503 255 2499",
    "sg:postcode":"97220",
    "sg:province":"OR",
    "sg:tags":[
        "repairing",
        "automobile"
    ],
    "wof:name":"A & M Pro Auto Care Inc",
    "wof:placetype":"venue"
},
  "geometry": {"coordinates":[-122.56965700000001,45.562571],"type":"Point"}
}