{
  "type": "Feature",
  "properties": {
    "iso:country":"US",
    "sg:address":"6655 SW Hampton St",
    "sg:city":"Tigard",
    "sg:classifiers":[
        {
            "category":"Health Services",
            "subcategory":"Health Practitioner",
            "type":"Services"
        }
    ],
    "sg:phone":"+1 503 293 1151",
    "sg:postcode":"97223",
    "sg:province":"OR",
    "sg:tags":[
        "nutritionist"
    ],
    "wof:name":"Inner View/Nutritional Evltn",
    "wof:placetype":"venue"
},
  "geometry": {"coordinates":[-122.745359,45.427562],"type":"Point"}
}