{
  "type": "Feature",
  "properties": {
    "iso:country":"US",
    "sg:address":"30701 Camas Swale Rd",
    "sg:city":"Creswell",
    "sg:classifiers":[
        {
            "category":"Home & Garden",
            "subcategory":"Household Appliances",
            "type":"Retail Goods"
        }
    ],
    "sg:phone":"+1 541 895 2355",
    "sg:postcode":"97426",
    "sg:province":"OR",
    "sg:tags":[
        "cleaners",
        "vacuum"
    ],
    "wof:name":"Centra-Flo Built In Vacuum",
    "wof:placetype":"venue"
},
  "geometry": {"coordinates":[-123.133432,43.920346],"type":"Point"}
}