{
  "type": "Feature",
  "properties": {
    "iso:country":"US",
    "sg:address":"206 SE Court Ave",
    "sg:city":"Pendleton",
    "sg:classifiers":[
        {
            "category":"Manufacturing",
            "subcategory":"Printing",
            "type":"Manufacturing & Wholesale Goods"
        }
    ],
    "sg:phone":"+1 541 276 7845",
    "sg:postcode":"97801",
    "sg:province":"OR",
    "sg:tags":[
        "printer"
    ],
    "wof:name":"Master Printers Northwest",
    "wof:placetype":"venue"
},
  "geometry": {"coordinates":[-118.784681,45.673449],"type":"Point"}
}