{
  "type": "Feature",
  "properties": {
    "addr:full":"2147 NE 81st Ave Portland OR 97213",
    "addr:housenumber":"2147",
    "addr:postcode":"97213",
    "addr:street":"Ne 81St Ave",
    "iso:country":"US",
    "sg:address":"2147 NE 81st Ave",
    "sg:city":"Portland",
    "sg:classifiers":[
        {
            "category":"Communications",
            "type":"Services"
        }
    ],
    "sg:phone":"+1 503 261 0433",
    "sg:postcode":"97213",
    "sg:province":"OR",
    "sg:tags":[
        "equipment",
        "data",
        "system"
    ],
    "wof:name":"Deschutes Communications",
    "wof:placetype":"venue"
},
  "geometry": {"coordinates":[-122.579909,45.537669],"type":"Point"}
}