{
  "type": "Feature",
  "properties": {
    "iso:country":"US",
    "sg:address":"1200 SW 211th Pl",
    "sg:city":"Beaverton",
    "sg:classifiers":[
        {
            "category":"Professional",
            "subcategory":"Engineering",
            "type":"Services"
        }
    ],
    "sg:phone":"+1 503 591 7044",
    "sg:postcode":"97006",
    "sg:province":"OR",
    "wof:name":"Transamp Inc",
    "wof:placetype":"venue"
},
  "geometry": {"coordinates":[-122.89398799999999,45.510473],"type":"Point"}
}