{
  "type": "Feature",
  "properties": {
    "iso:country":"US",
    "sg:address":"1938 NW 1st St",
    "sg:city":"Bend",
    "sg:classifiers":[
        {
            "category":"Building & Trades",
            "subcategory":"Construction",
            "type":"Services"
        }
    ],
    "sg:phone":"+1 541 382 7718",
    "sg:postcode":"97701",
    "sg:province":"OR",
    "sg:tags":[
        "house",
        "general",
        "contractor"
    ],
    "wof:name":"R E Tadevic Construction Inc",
    "wof:placetype":"venue"
},
  "geometry": {"coordinates":[-121.313518,44.06743],"type":"Point"}
}