{
  "type": "Feature",
  "properties": {
    "addr:full":"10324 NE Halsey St Ste 1 Portland OR 97220",
    "addr:housenumber":"10324",
    "addr:postcode":"97220",
    "addr:street":"Ne Halsey St Ste 1",
    "iso:country":"US",
    "sg:address":"10324 NE Halsey St Ste 1",
    "sg:city":"Portland",
    "sg:classifiers":[
        {
            "category":"Insurance",
            "subcategory":"Hazard Insurance",
            "type":"Services"
        }
    ],
    "sg:phone":"+1 503 253 7283",
    "sg:postcode":"97220",
    "sg:province":"OR",
    "wof:name":"Allen & Assoc Ins, Inc- Nationwide Insurance",
    "wof:placetype":"venue"
},
  "geometry": {"coordinates":[-122.55632799999999,45.533537],"type":"Point"}
}