{
  "type": "Feature",
  "properties": {
    "addr:full":"11626 SW Pacific Hwy Portland OR 97223",
    "addr:housenumber":"11626",
    "addr:postcode":"97223",
    "addr:street":"Sw Pacific Hwy",
    "iso:country":"US",
    "sg:address":"11626 SW Pacific Hwy",
    "sg:city":"Portland",
    "sg:phone":"+1 800 326 3264",
    "sg:postcode":"97223",
    "sg:province":"OR",
    "sg:website":"http://www.REGmovies.com",
    "wof:name":"Regal Tigard 11 Cinemas",
    "wof:placetype":"venue"
},
  "geometry": {"coordinates":[-122.753612,45.438693],"type":"Point"}
}