{
  "type": "Feature",
  "properties": {
    "iso:country":"US",
    "sg:address":"2790 SE 73rd Ave",
    "sg:city":"Hillsboro",
    "sg:classifiers":[
        {
            "category":"Building & Trades",
            "subcategory":"Construction",
            "type":"Services"
        }
    ],
    "sg:phone":"+1 503 848 8819",
    "sg:postcode":"97123",
    "sg:province":"OR",
    "sg:tags":[
        "excavation",
        "demolition",
        "contractor"
    ],
    "sg:website":"http://www.rychartexcavation.com",
    "wof:name":"Rychart Excavation Inc",
    "wof:placetype":"venue"
},
  "geometry": {"coordinates":[-122.90728,45.499515],"type":"Point"}
}