{
  "type": "Feature",
  "properties": {
    "addr:full":"7215 N Macrum Ave Portland OR 97203",
    "addr:housenumber":"7215",
    "addr:postcode":"97203",
    "addr:street":"N Macrum Ave",
    "iso:country":"US",
    "sg:address":"7215 N Macrum Ave",
    "sg:city":"Portland",
    "sg:classifiers":[
        {
            "category":"Professional",
            "type":"Services"
        }
    ],
    "sg:phone":"+1 503 285 8644",
    "sg:postcode":"97203",
    "sg:province":"OR",
    "wof:name":"Larrys Shuttle Service",
    "wof:placetype":"venue"
},
  "geometry": {"coordinates":[-122.73520600000001,45.584402],"type":"Point"}
}