{
  "type": "Feature",
  "properties": {
    "iso:country":"US",
    "sg:address":"2011 Cove Ave",
    "sg:city":"La Grande",
    "sg:classifiers":[
        {
            "category":"Shopping",
            "subcategory":"Used Merchandise",
            "type":"Retail Goods"
        }
    ],
    "sg:phone":"+1 541 663 8397",
    "sg:postcode":"97850",
    "sg:province":"OR",
    "sg:tags":[
        "book",
        "rare",
        "dealer"
    ],
    "wof:name":"Leonardo's Book Shelf",
    "wof:placetype":"venue"
},
  "geometry": {"coordinates":[-118.081188,45.32595],"type":"Point"}
}