{
  "type": "Feature",
  "properties": {
    "iso:country":"US",
    "sg:address":"565 S Main St",
    "sg:city":"Lebanon",
    "sg:classifiers":[
        {
            "category":"Professional",
            "type":"Services"
        }
    ],
    "sg:phone":"+1 541 259 2478",
    "sg:postcode":"97355",
    "sg:province":"OR",
    "sg:tags":[
        "establishment"
    ],
    "wof:name":"Pacific States Management",
    "wof:placetype":"venue"
},
  "geometry": {"coordinates":[-122.906992,44.540345],"type":"Point"}
}