{
  "type": "Feature",
  "properties": {
    "iso:country":"US",
    "sg:address":"408 SE Baker St",
    "sg:city":"Mcminnville",
    "sg:classifiers":[
        {
            "category":"Real Estate",
            "subcategory":"Surveying",
            "type":"Services"
        }
    ],
    "sg:phone":"+1 541 318 5447",
    "sg:postcode":"97128",
    "sg:province":"OR",
    "sg:tags":[
        "planning",
        "land"
    ],
    "wof:name":"Aurora Development Inc",
    "wof:placetype":"venue"
},
  "geometry": {"coordinates":[-123.19795999999999,45.206655],"type":"Point"}
}