{
  "type": "Feature",
  "properties": {
    "addr:full":"384 Oak St Ashland OR 97520",
    "addr:housenumber":"384",
    "addr:postcode":"97520",
    "addr:street":"Oak St",
    "iso:country":"US",
    "sg:address":"384 Oak St",
    "sg:city":"Ashland",
    "sg:classifiers":[
        {
            "category":"Home & Garden",
            "subcategory":"Building Materials",
            "type":"Retail Goods"
        }
    ],
    "sg:phone":"+1 541 482 1621",
    "sg:postcode":"97520",
    "sg:province":"OR",
    "sg:tags":[
        "lumber"
    ],
    "wof:name":"Ashland Lumber Co Inc",
    "wof:placetype":"venue"
},
  "geometry": {"coordinates":[-122.711484,42.200923],"type":"Point"}
}