{
  "type": "Feature",
  "properties": {
    "iso:country":"US",
    "sg:address":"949 SW Oak St",
    "sg:city":"Portland",
    "sg:classifiers":[
        {
            "category":"Restaurant",
            "type":"Food & Drink"
        }
    ],
    "sg:menulink":"http://www.allmenus.com/or/portland/26514-roccos-pizza/menu/",
    "sg:phone":"+1 503 223 9835",
    "sg:postcode":"97205",
    "sg:province":"OR",
    "sg:tags":[
        "american",
        "pizza"
    ],
    "wof:name":"Rocco's Pizza",
    "wof:placetype":"venue"
},
  "geometry": {"coordinates":[-122.68057,45.522642],"type":"Point"}
}