{
  "type": "Feature",
  "properties": {
    "addr:full":"1440 NW Overton St Portland OR 97209",
    "addr:housenumber":"1440",
    "addr:postcode":"97209",
    "addr:street":"Nw Overton St",
    "iso:country":"US",
    "sg:address":"1440 NW Overton St",
    "sg:city":"Portland",
    "sg:classifiers":[
        {
            "category":"Retail",
            "subcategory":"Event Space",
            "type":"Services"
        }
    ],
    "sg:postcode":"97209",
    "sg:province":"OR",
    "sg:tags":[
        "venue"
    ],
    "wof:name":"The Village Theater",
    "wof:placetype":"venue"
},
  "geometry": {"coordinates":[-122.68620900000001,45.531677],"type":"Point"}
}