{
  "type": "Feature",
  "properties": {
    "addr:full":"9660 S Macksburg Rd Canby OR 97013",
    "addr:housenumber":"9660",
    "addr:postcode":"97013",
    "addr:street":"S Macksburg Rd",
    "iso:country":"US",
    "sg:address":"9660 S Macksburg Rd",
    "sg:city":"Canby",
    "sg:classifiers":[
        {
            "category":"Retail",
            "subcategory":"Animal Services",
            "type":"Services"
        }
    ],
    "sg:phone":"+1 503 263 2020",
    "sg:postcode":"97013",
    "sg:province":"OR",
    "wof:name":"Special T Hackneys",
    "wof:placetype":"venue"
},
  "geometry": {"coordinates":[-122.668993,45.215821],"type":"Point"}
}