{
  "type": "Feature",
  "properties": {
    "iso:country":"US",
    "sg:address":"2013 S 6th St",
    "sg:city":"Klamath Falls",
    "sg:classifiers":[
        {
            "category":"Wholesale",
            "subcategory":"Machinery & Supplies",
            "type":"Manufacturing & Wholesale Goods"
        }
    ],
    "sg:phone":"+1 541 882 5031",
    "sg:postcode":"97601",
    "sg:province":"OR",
    "sg:tags":[
        "equipment",
        "industrial"
    ],
    "wof:name":"Bradlleys Kflls Dsl Injctn Sr",
    "wof:placetype":"venue"
},
  "geometry": {"coordinates":[-121.766645,42.216226],"type":"Point"}
}