{
  "type": "Feature",
  "properties": {
    "iso:country":"US",
    "sg:address":"237 SE Miller Ave",
    "sg:city":"Roseburg",
    "sg:classifiers":[
        {
            "category":"Home & Garden",
            "subcategory":"Building Materials",
            "type":"Retail Goods"
        }
    ],
    "sg:phone":"+1 541 672 2685",
    "sg:postcode":"97470",
    "sg:province":"OR",
    "sg:tags":[
        "glass"
    ],
    "wof:name":"Roseburg Glass Co",
    "wof:placetype":"venue"
},
  "geometry": {"coordinates":[-123.353306,43.20713],"type":"Point"}
}