{
  "type": "Feature",
  "properties": {
    "iso:country":"US",
    "sg:address":"32965 Tucker Ln",
    "sg:city":"Lebanon",
    "sg:classifiers":[
        {
            "category":"Manufacturing",
            "subcategory":"Lumber",
            "type":"Manufacturing & Wholesale Goods"
        }
    ],
    "sg:phone":"+1 541 451 5960",
    "sg:postcode":"97355",
    "sg:province":"OR",
    "sg:tags":[
        "mill"
    ],
    "wof:name":"Two-Mac Enterprises",
    "wof:placetype":"venue"
},
  "geometry": {"coordinates":[-122.928282,44.543393],"type":"Point"}
}