{
  "type": "Feature",
  "properties": {
    "iso:country":"US",
    "sg:address":"1222 Redwood Ave",
    "sg:city":"Grants Pass",
    "sg:classifiers":[
        {
            "category":"Professional",
            "subcategory":"Management & Consulting",
            "type":"Services"
        }
    ],
    "sg:phone":"+1 541 476 1568",
    "sg:postcode":"97527",
    "sg:province":"OR",
    "sg:tags":[
        "business"
    ],
    "wof:name":"Bear Distributors",
    "wof:placetype":"venue"
},
  "geometry": {"coordinates":[-123.352211,42.422518],"type":"Point"}
}