{
  "type": "Feature",
  "properties": {
    "iso:country":"US",
    "sg:address":"3419 NE 35th Pl",
    "sg:city":"Portland",
    "sg:classifiers":[
        {
            "category":"Shopping",
            "type":"Retail Goods"
        }
    ],
    "sg:phone":"+1 503 281 2542",
    "sg:postcode":"97212",
    "sg:province":"OR",
    "sg:tags":[
        "merchandise"
    ],
    "wof:name":"Hall L J Ron Reverend",
    "wof:placetype":"venue"
},
  "geometry": {"coordinates":[-122.627173,45.548095],"type":"Point"}
}