{
  "type": "Feature",
  "properties": {
    "iso:country":"US",
    "sg:address":"916 SE 20th Ave",
    "sg:city":"Portland",
    "sg:classifiers":[
        {
            "category":"Retail",
            "subcategory":"Repair Shop",
            "type":"Services"
        }
    ],
    "sg:phone":"+1 503 234 9378",
    "sg:postcode":"97214",
    "sg:province":"OR",
    "sg:tags":[
        "antique",
        "used",
        "merchandise"
    ],
    "sg:website":"www.greenfurniturehospital.com/",
    "wof:name":"Green Furniture Hospital",
    "wof:placetype":"venue"
},
  "geometry": {"coordinates":[-122.645304,45.516162],"type":"Point"}
}