{
  "type": "Feature",
  "properties": {
    "iso:country":"US",
    "sg:address":"8229 Wilsonville Rd",
    "sg:city":"Wilsonville",
    "sg:classifiers":[
        {
            "category":"Shopping",
            "subcategory":"Shoes",
            "type":"Retail Goods"
        }
    ],
    "sg:phone":"+1 503 682 0539",
    "sg:postcode":"97070",
    "sg:province":"OR",
    "wof:name":"Pace Setter Athletic",
    "wof:placetype":"venue"
},
  "geometry": {"coordinates":[-122.76102400000001,45.303078],"type":"Point"}
}