{
  "type": "Feature",
  "properties": {
    "iso:country":"US",
    "sg:address":"2620 SW Georgian Pl",
    "sg:city":"Portland",
    "sg:classifiers":[
        {
            "category":"Manufacturing",
            "subcategory":"Printing",
            "type":"Manufacturing & Wholesale Goods"
        }
    ],
    "sg:phone":"+1 503 223 9899",
    "sg:postcode":"97201",
    "sg:province":"OR",
    "sg:tags":[
        "book"
    ],
    "wof:name":"Georgian Press Co",
    "wof:placetype":"venue"
},
  "geometry": {"coordinates":[-122.703666,45.505482],"type":"Point"}
}