{
  "type": "Feature",
  "properties": {
    "iso:country":"US",
    "sg:address":"36480 Hwy 101 N",
    "sg:city":"Nehalem",
    "sg:classifiers":[
        {
            "category":"Real Estate",
            "subcategory":"Real Estate Agent",
            "type":"Services"
        }
    ],
    "sg:phone":"+1 503 368 3865",
    "sg:postcode":"97131",
    "sg:province":"OR",
    "sg:tags":[
        "rental",
        "vacation"
    ],
    "wof:name":"Beach Break Vac Rentals LLC",
    "wof:placetype":"venue"
},
  "geometry": {"coordinates":[-123.916859,45.717852],"type":"Point"}
}