{
  "type": "Feature",
  "properties": {
    "iso:country":"US",
    "sg:address":"548 S 4th St",
    "sg:city":"Springfield",
    "sg:classifiers":[
        {
            "category":"Professional",
            "subcategory":"Computer Services",
            "type":"Services"
        }
    ],
    "sg:phone":"+1 541 744 0276",
    "sg:postcode":"97477",
    "sg:province":"OR",
    "sg:tags":[
        "related"
    ],
    "wof:name":"Engstrom Consulting",
    "wof:placetype":"venue"
},
  "geometry": {"coordinates":[-123.020818,44.041214],"type":"Point"}
}