{
  "type": "Feature",
  "properties": {
    "addr:full":"5933 NE Win Sivers Dr Portland OR 97220",
    "addr:housenumber":"5933",
    "addr:postcode":"97220",
    "addr:street":"Ne Win Sivers Dr",
    "iso:country":"US",
    "sg:address":"5933 NE Win Sivers Dr",
    "sg:city":"Portland",
    "sg:classifiers":[
        {
            "category":"Organizations",
            "subcategory":"Non-profit Organization",
            "type":"Services"
        },
        {
            "category":"Professional",
            "subcategory":"Management & Consulting",
            "type":"Services"
        }
    ],
    "sg:phone":"+1 503 262 9421",
    "sg:postcode":"97220",
    "sg:province":"OR",
    "sg:tags":[
        "business"
    ],
    "wof:name":"Rto West",
    "wof:placetype":"venue"
},
  "geometry": {"coordinates":[-122.53804700000001,45.56546],"type":"Point"}
}