{
  "type": "Feature",
  "properties": {
    "addr:full":"95 SE 8th Ave Ontario OR 97914",
    "addr:housenumber":"95",
    "addr:postcode":"97914",
    "addr:street":"Se 8Th Ave",
    "iso:country":"US",
    "sg:address":"95 SE 8th Ave",
    "sg:city":"Ontario",
    "sg:classifiers":[
        {
            "category":"Wholesale",
            "subcategory":"Farm Supplies",
            "type":"Manufacturing & Wholesale Goods"
        }
    ],
    "sg:phone":"+1 541 889 5329",
    "sg:postcode":"97914",
    "sg:province":"OR",
    "sg:tags":[
        "fertilizer"
    ],
    "wof:name":"Farmers Supply Co-Op",
    "wof:placetype":"venue"
},
  "geometry": {"coordinates":[-116.965157,44.019614],"type":"Point"}
}