{
  "type": "Feature",
  "properties": {
    "addr:full":"9450 SW Commerce Cir Wilsonville OR 97070",
    "addr:housenumber":"9450",
    "addr:postcode":"97070",
    "addr:street":"Sw Commerce Cir",
    "iso:country":"US",
    "sg:address":"9450 SW Commerce Cir",
    "sg:city":"Wilsonville",
    "sg:classifiers":[
        {
            "category":"Insurance",
            "subcategory":"Insurance Agent",
            "type":"Services"
        }
    ],
    "sg:phone":"+1 503 570 8736",
    "sg:postcode":"97070",
    "sg:province":"OR",
    "wof:name":"Allstate Insurance",
    "wof:placetype":"venue"
},
  "geometry": {"coordinates":[-122.77217400000001,45.334908],"type":"Point"}
}