{
  "type": "Feature",
  "properties": {
    "addr:full":"4744 NW Bethany Blvd Portland OR 97229",
    "addr:housenumber":"4744",
    "addr:postcode":"97229",
    "addr:street":"Nw Bethany Blvd",
    "iso:country":"US",
    "sg:address":"4744 NW Bethany Blvd",
    "sg:city":"Portland",
    "sg:classifiers":[
        {
            "category":"Banks & Credit Unions",
            "subcategory":"Investment Brokerage",
            "type":"Services"
        },
        {
            "category":"Banks & Credit Unions",
            "subcategory":"Bank",
            "type":"Services"
        },
        {
            "category":"Banks & Credit Unions",
            "subcategory":"Financial Services",
            "type":"Services"
        }
    ],
    "sg:phone":"+1 503 533 5554",
    "sg:postcode":"97229",
    "sg:province":"OR",
    "sg:tags":[
        "mutual",
        "retirement",
        "broker",
        "fund",
        "planning",
        "security",
        "bond",
        "stock"
    ],
    "sg:website":"http://www.edwardjones.com/en_US/fa/index.html&CIRN=491818",
    "wof:name":"Edward Jones - Financial Advisor: DAVID W GARTON",
    "wof:placetype":"venue"
},
  "geometry": {"coordinates":[-122.83681799999999,45.553577],"type":"Point"}
}