{
  "type": "Feature",
  "properties": {
    "addr:full":"2315 NE Alberta St Portland OR 97211",
    "addr:housenumber":"2315",
    "addr:postcode":"97211",
    "addr:street":"Ne Alberta St",
    "iso:country":"US",
    "sg:address":"2315 NE Alberta St",
    "sg:city":"Portland",
    "sg:classifiers":[
        {
            "category":"Restaurant",
            "type":"Food & Drink"
        }
    ],
    "sg:phone":"+1 503 288 8191",
    "sg:postcode":"97211",
    "sg:province":"OR",
    "sg:tags":[
        "peruvian",
        "american",
        "latin"
    ],
    "sg:website":"www.delinti.com",
    "wof:name":"Del Inti",
    "wof:placetype":"venue"
},
  "geometry": {"coordinates":[-122.641548,45.559216],"type":"Point"}
}