{
  "type": "Feature",
  "properties": {
    "iso:country":"US",
    "sg:address":"3015 NE West Devils Lake Rd",
    "sg:city":"Lincoln City",
    "sg:classifiers":[
        {
            "category":"Health Services",
            "subcategory":"Health Practitioner",
            "type":"Services"
        }
    ],
    "sg:phone":"+1 541 994 9916",
    "sg:postcode":"97367",
    "sg:province":"OR",
    "wof:name":"Cheung Wai Tak",
    "wof:placetype":"venue"
},
  "geometry": {"coordinates":[-123.996989,44.988262],"type":"Point"}
}