{
  "type": "Feature",
  "properties": {
    "iso:country":"US",
    "sg:address":"15421 SW Mazama Pl",
    "sg:city":"Portland",
    "sg:classifiers":[
        {
            "category":"Retail",
            "subcategory":"Self-service Laundry",
            "type":"Services"
        }
    ],
    "sg:phone":"+1 503 639 4750",
    "sg:postcode":"97224",
    "sg:province":"OR",
    "sg:tags":[
        "coin"
    ],
    "wof:name":"Rainier Rainwash Laundromat LL",
    "wof:placetype":"venue"
},
  "geometry": {"coordinates":[-122.787013,45.408309],"type":"Point"}
}