{
  "type": "Feature",
  "properties": {
    "addr:full":"13896 S Meyers Rd Oregon City OR 97045",
    "addr:housenumber":"13896",
    "addr:postcode":"97045",
    "addr:street":"S Meyers Rd",
    "iso:country":"US",
    "sg:address":"13896 S Meyers Rd",
    "sg:city":"Oregon City",
    "sg:classifiers":[
        {
            "category":"Social Services",
            "type":"Services"
        }
    ],
    "sg:phone":"+1 503 742 9939",
    "sg:postcode":"97045",
    "sg:province":"OR",
    "wof:name":"Healthy Start Clackamas County",
    "wof:placetype":"venue"
},
  "geometry": {"coordinates":[-122.58376699999999,45.319413],"type":"Point"}
}