{
  "type": "Feature",
  "properties": {
    "iso:country":"US",
    "sg:address":"13620 SW Beef Bend Rd",
    "sg:city":"Portland",
    "sg:classifiers":[
        {
            "category":"Home & Garden",
            "subcategory":"Building Materials",
            "type":"Retail Goods"
        },
        {
            "category":"Building & Trades",
            "subcategory":"Construction",
            "type":"Services"
        }
    ],
    "sg:phone":"+1 503 442 0724",
    "sg:postcode":"97224",
    "sg:province":"OR",
    "sg:tags":[
        "refinishing",
        "top",
        "counter",
        "tile-contractors",
        "sealing",
        "tile-cleaning"
    ],
    "wof:name":"OPE",
    "wof:placetype":"venue"
},
  "geometry": {"coordinates":[-122.817656,45.403531],"type":"Point"}
}