{
  "type": "Feature",
  "properties": {
    "addr:full":"381 W Idaho Ave Ontario OR 97914",
    "addr:housenumber":"381",
    "addr:postcode":"97914",
    "addr:street":"W Idaho Ave",
    "iso:country":"US",
    "sg:address":"381 W Idaho Ave",
    "sg:city":"Ontario",
    "sg:classifiers":[
        {
            "category":"Professional",
            "subcategory":"Lawyer & Legal Services",
            "type":"Services"
        }
    ],
    "sg:phone":"+1 541 881 1776",
    "sg:postcode":"97914",
    "sg:province":"OR",
    "wof:name":"Goicochea Law Offs Ontariovale",
    "wof:placetype":"venue"
},
  "geometry": {"coordinates":[-116.966914,44.027364],"type":"Point"}
}