{
  "type": "Feature",
  "properties": {
    "iso:country":"US",
    "sg:address":"2136 NE 12th Ave",
    "sg:city":"Portland",
    "sg:classifiers":[
        {
            "category":"Professional",
            "type":"Services"
        },
        {
            "category":"Restaurant",
            "type":"Food & Drink"
        }
    ],
    "sg:phone":"+1 503 281 1073",
    "sg:postcode":"97212",
    "sg:province":"OR",
    "sg:tags":[
        "seafood",
        "caterer"
    ],
    "wof:name":"Suttenberg Gary",
    "wof:placetype":"venue"
},
  "geometry": {"coordinates":[-122.65300000000001,45.537998],"type":"Point"}
}