{
  "type": "Feature",
  "properties": {
    "addr:full":"57537 S Morse Rd Warren OR 97053",
    "addr:housenumber":"57537",
    "addr:postcode":"97053",
    "addr:street":"S Morse Rd",
    "iso:country":"US",
    "sg:address":"57537 S Morse Rd",
    "sg:city":"Warren",
    "sg:classifiers":[
        {
            "category":"Professional",
            "type":"Services"
        }
    ],
    "sg:phone":"+1 503 366 1205",
    "sg:postcode":"97053",
    "sg:province":"OR",
    "wof:name":"Kirk R Giggers",
    "wof:placetype":"venue"
},
  "geometry": {"coordinates":[-122.848933,45.83036],"type":"Point"}
}