{
  "type": "Feature",
  "properties": {
    "iso:country":"US",
    "sg:address":"1619 Main St",
    "sg:city":"Philomath",
    "sg:classifiers":[
        {
            "category":"Manufacturing",
            "subcategory":"Lumber",
            "type":"Manufacturing & Wholesale Goods"
        }
    ],
    "sg:phone":"+1 541 929 3408",
    "sg:postcode":"97370",
    "sg:province":"OR",
    "sg:tags":[
        "forester"
    ],
    "wof:name":"Integrated Resource Management",
    "wof:placetype":"venue"
},
  "geometry": {"coordinates":[-123.36314900000001,44.5401],"type":"Point"}
}