{
  "type": "Feature",
  "properties": {
    "iso:country":"US",
    "sg:address":"3220 NW 185th Ave",
    "sg:city":"Portland",
    "sg:classifiers":[
        {
            "category":"Health Services",
            "subcategory":"Dentist",
            "type":"Services"
        }
    ],
    "sg:phone":"+1 503 645 3521",
    "sg:postcode":"97229",
    "sg:province":"OR",
    "wof:name":"Family Dentistry",
    "wof:placetype":"venue"
},
  "geometry": {"coordinates":[-122.867244,45.543449],"type":"Point"}
}