{
  "type": "Feature",
  "properties": {
    "iso:country":"US",
    "sg:address":"5243 Silverton Rd NE",
    "sg:city":"Salem",
    "sg:classifiers":[
        {
            "category":"Wholesale",
            "subcategory":"Farm Supplies",
            "type":"Manufacturing & Wholesale Goods"
        }
    ],
    "sg:phone":"+1 503 586 2426",
    "sg:postcode":"97305",
    "sg:province":"OR",
    "sg:tags":[
        "equipment"
    ],
    "wof:name":"Halton Co",
    "wof:placetype":"venue"
},
  "geometry": {"coordinates":[-122.95387100000001,44.974395],"type":"Point"}
}