{
  "type": "Feature",
  "properties": {
    "addr:full":"15 N 4th St Central Point OR 97502",
    "addr:housenumber":"15",
    "addr:postcode":"97502",
    "addr:street":"N 4Th St",
    "iso:country":"US",
    "sg:address":"15 N 4th St",
    "sg:city":"Central Point",
    "sg:classifiers":[
        {
            "category":"Personal",
            "subcategory":"Shoe Repair & Shine",
            "type":"Services"
        }
    ],
    "sg:phone":"+1 541 664 2479",
    "sg:postcode":"97502",
    "sg:province":"OR",
    "sg:tags":[
        "repairing",
        "parlor",
        "boot"
    ],
    "wof:name":"Bostwick's Shoe Repair",
    "wof:placetype":"venue"
},
  "geometry": {"coordinates":[-122.91529800000001,42.376296],"type":"Point"}
}