{
  "type": "Feature",
  "properties": {
    "iso:country":"US",
    "sg:address":"15 N 4th St",
    "sg:city":"Central Point",
    "sg:classifiers":[
        {
            "category":"Personal",
            "subcategory":"Shoe Repair & Shine",
            "type":"Services"
        }
    ],
    "sg:phone":"+1 541 664 2479",
    "sg:postcode":"97502",
    "sg:province":"OR",
    "sg:tags":[
        "repairing",
        "parlor",
        "boot"
    ],
    "wof:name":"Bostwick's Shoe Repair",
    "wof:placetype":"venue"
},
  "geometry": {"coordinates":[-122.915298,42.376296],"type":"Point"}
}