{
  "type": "Feature",
  "properties": {
    "addr:full":"7154 SW la View Dr Portland OR 97219",
    "addr:housenumber":"7154",
    "addr:postcode":"97219",
    "addr:street":"Sw La View Dr",
    "iso:country":"US",
    "sg:address":"7154 SW la View Dr",
    "sg:city":"Portland",
    "sg:classifiers":[
        {
            "category":"Manufacturing",
            "subcategory":"Food",
            "type":"Manufacturing & Wholesale Goods"
        },
        {
            "category":"Food & Beverages",
            "subcategory":"Groceries & Convenience Stores",
            "type":"Retail Goods"
        }
    ],
    "sg:phone":"+1 503 754 7777",
    "sg:postcode":"97219",
    "sg:province":"OR",
    "sg:tags":[
        "product"
    ],
    "wof:name":"Lushious",
    "wof:placetype":"venue"
},
  "geometry": {"coordinates":[-122.675285,45.472197],"type":"Point"}
}