{
  "type": "Feature",
  "properties": {
    "iso:country":"US",
    "sg:address":"32837 NW Ridge Dr",
    "sg:city":"Scappoose",
    "sg:classifiers":[
        {
            "category":"Building & Trades",
            "subcategory":"Equipment Rental",
            "type":"Services"
        }
    ],
    "sg:phone":"+1 503 543 2161",
    "sg:postcode":"97056",
    "sg:province":"OR",
    "wof:name":"Pg Enterprises",
    "wof:placetype":"venue"
},
  "geometry": {"coordinates":[-122.89143300000001,45.764267],"type":"Point"}
}