{
  "type": "Feature",
  "properties": {
    "iso:country":"US",
    "sg:address":"10330 SE 32nd Ave",
    "sg:city":"Portland",
    "sg:classifiers":[
        {
            "category":"Health Services",
            "subcategory":"Doctor",
            "type":"Services"
        }
    ],
    "sg:phone":"+1 503 652 5260",
    "sg:postcode":"97222",
    "sg:province":"OR",
    "sg:tags":[
        "medicine",
        "internal"
    ],
    "wof:name":"Vajdos Margaret MD",
    "wof:placetype":"venue"
},
  "geometry": {"coordinates":[-122.629997,45.4482],"type":"Point"}
}