{
  "type": "Feature",
  "properties": {
    "iso:country":"US",
    "sg:address":"42508 Moody Rd",
    "sg:city":"Richland",
    "sg:classifiers":[
        {
            "category":"Food & Beverages",
            "subcategory":"Dairy",
            "type":"Retail Goods"
        }
    ],
    "sg:phone":"+1 541 893 6740",
    "sg:postcode":"97870",
    "sg:province":"OR",
    "sg:tags":[
        "product"
    ],
    "wof:name":"Eagle Valley Egg Inc",
    "wof:placetype":"venue"
},
  "geometry": {"coordinates":[-117.165721,44.786441],"type":"Point"}
}