{
  "type": "Feature",
  "properties": {
    "addr:full":"525 Rogue Air Dr Shady Cove OR 97539",
    "addr:housenumber":"525",
    "addr:postcode":"97539",
    "addr:street":"Rogue Air Dr Shady Cove",
    "iso:country":"US",
    "sg:address":"525 Rogue Air Dr",
    "sg:city":"Shady Cove",
    "sg:classifiers":[
        {
            "category":"Retail",
            "subcategory":"Portrait Studio",
            "type":"Services"
        }
    ],
    "sg:phone":"+1 541 878 2766",
    "sg:postcode":"97539",
    "sg:province":"OR",
    "sg:tags":[
        "photographer"
    ],
    "wof:name":"Virginia's Photography & Photo",
    "wof:placetype":"venue"
},
  "geometry": {"coordinates":[-122.831079,42.605801],"type":"Point"}
}