{
  "type": "Feature",
  "properties": {
    "iso:country":"US",
    "sg:address":"321 SE 3rd St",
    "sg:city":"Toledo",
    "sg:classifiers":[
        {
            "category":"Education",
            "subcategory":"School",
            "type":"Public Place"
        }
    ],
    "sg:phone":"+1 541 336 2541",
    "sg:postcode":"97391",
    "sg:province":"OR",
    "wof:name":"Harrison Mary Elementary Schl",
    "wof:placetype":"venue"
},
  "geometry": {"coordinates":[-123.933388,44.618271],"type":"Point"}
}