{
  "type": "Feature",
  "properties": {
    "addr:full":"321 SE 3rd St Toledo OR 97391",
    "addr:housenumber":"321",
    "addr:postcode":"97391",
    "addr:street":"Se 3Rd St",
    "iso:country":"US",
    "sg:address":"321 SE 3rd St",
    "sg:city":"Toledo",
    "sg:classifiers":[
        {
            "category":"Education",
            "subcategory":"School",
            "type":"Public Place"
        }
    ],
    "sg:phone":"+1 541 336 2541",
    "sg:postcode":"97391",
    "sg:province":"OR",
    "wof:name":"Harrison Mary Elementary Schl",
    "wof:placetype":"venue"
},
  "geometry": {"coordinates":[-123.93338799999999,44.618271],"type":"Point"}
}