{
  "type": "Feature",
  "properties": {
    "iso:country":"US",
    "sg:address":"10506 NE Halsey St",
    "sg:city":"Portland",
    "sg:classifiers":[
        {
            "category":"Autos & Motor Vehicles",
            "subcategory":"Auto Supplies",
            "type":"Retail Goods"
        }
    ],
    "sg:phone":"+1 503 239 3500",
    "sg:postcode":"97220",
    "sg:province":"OR",
    "sg:tags":[
        "filter",
        "gas"
    ],
    "wof:name":"Premium Filter Co Inc",
    "wof:placetype":"venue"
},
  "geometry": {"coordinates":[-122.554266,45.533448],"type":"Point"}
}