{
  "type": "Feature",
  "properties": {
    "iso:country":"US",
    "sg:address":"1480 SW Hilldale Ave",
    "sg:city":"Portland",
    "sg:classifiers":[
        {
            "category":"Arts & Performance",
            "subcategory":"Theater",
            "type":"Entertainment"
        }
    ],
    "sg:phone":"+1 503 574 2692",
    "sg:postcode":"97225",
    "sg:province":"OR",
    "sg:tags":[
        "group"
    ],
    "wof:name":"Rose City Comedy Show",
    "wof:placetype":"venue"
},
  "geometry": {"coordinates":[-122.802314,45.509685],"type":"Point"}
}