{
  "type": "Feature",
  "properties": {
    "addr:full":"511 SW 10th Ave Portland OR 97205",
    "addr:housenumber":"511",
    "addr:postcode":"97205",
    "addr:street":"Sw 10Th Ave",
    "iso:country":"US",
    "sg:address":"511 SW 10th Ave",
    "sg:city":"Portland",
    "sg:classifiers":[
        {
            "category":"Travel",
            "subcategory":"Travel Agent",
            "type":"Entertainment"
        }
    ],
    "sg:phone":"+1 503 226 4018",
    "sg:postcode":"97205",
    "sg:province":"OR",
    "sg:tags":[
        "agency",
        "steamship"
    ],
    "sg:website":"www.cascademarine.net",
    "wof:name":"Cascade Marine Agencies",
    "wof:placetype":"venue"
},
  "geometry": {"coordinates":[-122.681783,45.52077],"type":"Point"}
}