{
  "type": "Feature",
  "properties": {
    "addr:full":"61354 Blakely Rd Bend OR 97702",
    "addr:housenumber":"61354",
    "addr:postcode":"97702",
    "addr:street":"Blakely Rd",
    "iso:country":"US",
    "sg:address":"61354 Blakely Rd",
    "sg:city":"Bend",
    "sg:classifiers":[
        {
            "category":"Real Estate",
            "subcategory":"Real Estate Operator",
            "type":"Services"
        }
    ],
    "sg:phone":"+1 541 389 3279",
    "sg:postcode":"97702",
    "sg:province":"OR",
    "sg:tags":[
        "building",
        "apartment"
    ],
    "wof:name":"Executive House Apartments",
    "wof:placetype":"venue"
},
  "geometry": {"coordinates":[-121.31926300000001,44.026861],"type":"Point"}
}