{
  "type": "Feature",
  "properties": {
    "iso:country":"US",
    "sg:address":"4040 Highland Ave",
    "sg:city":"Grants Pass",
    "sg:classifiers":[
        {
            "category":"Retail",
            "subcategory":"Auto Repair",
            "type":"Services"
        }
    ],
    "sg:phone":"+1 541 474 3333",
    "sg:postcode":"97526",
    "sg:province":"OR",
    "sg:tags":[
        "general"
    ],
    "wof:name":"Allstate Drive Shaft Inc",
    "wof:placetype":"venue"
},
  "geometry": {"coordinates":[-123.35985100000001,42.486977],"type":"Point"}
}