{
  "type": "Feature",
  "properties": {
    "addr:full":"2400 SE Ankeny Portland OR 97214",
    "addr:housenumber":"2400",
    "addr:postcode":"97214",
    "addr:street":"Se Ankeny",
    "iso:country":"US",
    "sg:address":"2400 SE Ankeny",
    "sg:city":"Portland",
    "sg:classifiers":[
        {
            "category":"Professional",
            "subcategory":"Art Services",
            "type":"Services"
        }
    ],
    "sg:phone":"+1 503 238 5957",
    "sg:postcode":"97214",
    "sg:province":"OR",
    "sg:tags":[
        "photographer",
        "photographers-portrait"
    ],
    "sg:website":"www.hollandstudios.com",
    "wof:name":"Holland Studios",
    "wof:placetype":"venue"
},
  "geometry": {"coordinates":[-122.641144,45.521968],"type":"Point"}
}