{
  "type": "Feature",
  "properties": {
    "addr:full":"155 S 2nd St Central Point OR 97502",
    "addr:housenumber":"155",
    "addr:postcode":"97502",
    "addr:street":"S 2Nd St",
    "iso:country":"US",
    "sg:address":"155 S 2nd St",
    "sg:city":"Central Point",
    "sg:classifiers":[
        {
            "category":"Government",
            "subcategory":"Office",
            "type":"Public Place"
        }
    ],
    "sg:phone":"+1 541 664 3324",
    "sg:postcode":"97502",
    "sg:province":"OR",
    "sg:tags":[
        "city",
        "planning",
        "dev"
    ],
    "wof:name":"City Zoning",
    "wof:placetype":"venue"
},
  "geometry": {"coordinates":[-122.914849,42.373533],"type":"Point"}
}