{
  "type": "Feature",
  "properties": {
    "iso:country":"US",
    "sg:address":"2633 Crosby Ave",
    "sg:city":"Klamath Falls",
    "sg:classifiers":[
        {
            "category":"Insurance",
            "subcategory":"Insurance Agent",
            "type":"Services"
        }
    ],
    "sg:phone":"+1 541 885 2666",
    "sg:postcode":"97603",
    "sg:province":"OR",
    "sg:tags":[
        "medical"
    ],
    "wof:name":"West Occupational Care Clinic",
    "wof:placetype":"venue"
},
  "geometry": {"coordinates":[-121.75626099999999,42.205483],"type":"Point"}
}