{
  "type": "Feature",
  "properties": {
    "iso:country":"US",
    "sg:address":"435 Tillicum Dr",
    "sg:city":"Silverton",
    "sg:classifiers":[
        {
            "category":"Building & Trades",
            "subcategory":"Construction",
            "type":"Services"
        }
    ],
    "sg:phone":"+1 503 873 7561",
    "sg:postcode":"97381",
    "sg:province":"OR",
    "sg:tags":[
        "wallcoverings-installation",
        "wallpaper"
    ],
    "wof:name":"Shannon Russell Paperhanging Inc",
    "wof:placetype":"venue"
},
  "geometry": {"coordinates":[-122.77000200000001,45.001232],"type":"Point"}
}