{
  "type": "Feature",
  "properties": {
    "iso:country":"US",
    "sg:address":"11745 SW Beaverton Hillsdale Hwy",
    "sg:city":"Beaverton",
    "sg:classifiers":[
        {
            "category":"Personal",
            "subcategory":"Tanning Parlor",
            "type":"Services"
        }
    ],
    "sg:phone":"+1 503 646 9653",
    "sg:postcode":"97005",
    "sg:province":"OR",
    "sg:website":"www.sunsetwesttanning.com",
    "wof:name":"Sunset West Tanning",
    "wof:placetype":"venue"
},
  "geometry": {"coordinates":[-122.79701799999999,45.486669],"type":"Point"}
}