{
  "type": "Feature",
  "properties": {
    "addr:full":"610 5th St Brookings OR 97415",
    "addr:housenumber":"610",
    "addr:postcode":"97415",
    "addr:street":"5Th St",
    "iso:country":"US",
    "sg:address":"610 5th St",
    "sg:city":"Brookings",
    "sg:classifiers":[
        {
            "category":"Professional",
            "subcategory":"Accounting & Tax Preparation",
            "type":"Services"
        }
    ],
    "sg:phone":"+1 541 469 7741",
    "sg:postcode":"97415",
    "sg:province":"OR",
    "sg:tags":[
        "return",
        "filing"
    ],
    "wof:name":"Clar T Byers",
    "wof:placetype":"venue"
},
  "geometry": {"coordinates":[-124.287924,42.055067],"type":"Point"}
}