{
  "type": "Feature",
  "properties": {
    "addr:full":"16070 NE Halsey St Portland OR 97230",
    "addr:housenumber":"16070",
    "addr:postcode":"97230",
    "addr:street":"Ne Halsey St",
    "iso:country":"US",
    "sg:address":"16070 NE Halsey St",
    "sg:city":"Portland",
    "sg:classifiers":[
        {
            "category":"Organizations",
            "subcategory":"Religious Organization",
            "type":"Services"
        }
    ],
    "sg:phone":"+1 503 256 0873",
    "sg:postcode":"97230",
    "sg:province":"OR",
    "wof:name":"House of Prayer For All People",
    "wof:placetype":"venue"
},
  "geometry": {"coordinates":[-122.496774,45.533537],"type":"Point"}
}