{
  "type": "Feature",
  "properties": {
    "iso:country":"US",
    "sg:address":"9838 SE 17th Ave",
    "sg:city":"Milwaukie",
    "sg:classifiers":[
        {
            "category":"Food & Beverages",
            "subcategory":"Specialty",
            "type":"Retail Goods"
        }
    ],
    "sg:phone":"+1 503 786 8202",
    "sg:postcode":"97222",
    "sg:province":"OR",
    "sg:tags":[
        "gourmet",
        "shop"
    ],
    "wof:name":"Gourmet Solutions",
    "wof:placetype":"venue"
},
  "geometry": {"coordinates":[-122.645814,45.452611],"type":"Point"}
}