{
  "type": "Feature",
  "properties": {
    "addr:full":"17501 SE McLoughlin Blvd Portland OR 97267",
    "addr:postcode":"17501;97267",
    "addr:street":"Se Mcloughlin Blvd",
    "iso:country":"US",
    "sg:address":"17501 SE McLoughlin Blvd",
    "sg:city":"Portland",
    "sg:classifiers":[
        {
            "category":"Autos & Motor Vehicles",
            "subcategory":"Automobile Sales",
            "type":"Retail Goods"
        }
    ],
    "sg:phone":"+1 503 659 5475",
    "sg:postcode":"97267",
    "sg:province":"OR",
    "sg:tags":[
        "automotive"
    ],
    "wof:name":"Penske Truck Rental",
    "wof:placetype":"venue"
},
  "geometry": {"coordinates":[-122.61599699999999,45.396099],"type":"Point"}
}