{
  "type": "Feature",
  "properties": {
    "addr:full":"2285 Elysium Ave Eugene OR 97401",
    "addr:housenumber":"2285",
    "addr:postcode":"97401",
    "addr:street":"Elysium Ave",
    "iso:country":"US",
    "sg:address":"2285 Elysium Ave",
    "sg:city":"Eugene",
    "sg:classifiers":[
        {
            "category":"Social Services",
            "type":"Services"
        }
    ],
    "sg:phone":"+1 541 338 7501",
    "sg:postcode":"97401",
    "sg:province":"OR",
    "wof:name":"Assessment - Intervention Rslt",
    "wof:placetype":"venue"
},
  "geometry": {"coordinates":[-123.07620199999999,44.086596],"type":"Point"}
}