{
  "type": "Feature",
  "properties": {
    "addr:full":"1366 N Gould St Coquille OR 97423",
    "addr:housenumber":"1366",
    "addr:postcode":"97423",
    "addr:street":"N Gould St",
    "iso:country":"US",
    "sg:address":"1366 N Gould St",
    "sg:city":"Coquille",
    "sg:classifiers":[
        {
            "category":"Education",
            "subcategory":"School",
            "type":"Public Place"
        }
    ],
    "sg:phone":"+1 541 396 2811",
    "sg:postcode":"97423",
    "sg:province":"OR",
    "sg:tags":[
        "elementary"
    ],
    "wof:name":"Lincoln Elementary School",
    "wof:placetype":"venue"
},
  "geometry": {"coordinates":[-124.182225,43.186846],"type":"Point"}
}