{
  "type": "Feature",
  "properties": {
    "iso:country":"US",
    "sg:address":"4925 SW Griffith Dr",
    "sg:city":"Beaverton",
    "sg:classifiers":[
        {
            "category":"Sports & Exercise",
            "subcategory":"Gym",
            "type":"Entertainment"
        }
    ],
    "sg:phone":"+1 503 644 3900",
    "sg:postcode":"97005",
    "sg:province":"OR",
    "sg:tags":[
        "trainer"
    ],
    "sg:website":"www.ymca-beaverton.org/beaverton...",
    "wof:name":"YMCA of Columbia-Willamette",
    "wof:placetype":"venue"
},
  "geometry": {"coordinates":[-122.795419,45.484029],"type":"Point"}
}