{
  "type": "Feature",
  "properties": {
    "iso:country":"US",
    "sg:address":"2095 Terrel Dr",
    "sg:city":"Medford",
    "sg:classifiers":[
        {
            "category":"Building & Trades",
            "subcategory":"Cleaning & Sanitation",
            "type":"Services"
        }
    ],
    "sg:phone":"+1 541 779 9248",
    "sg:postcode":"97501",
    "sg:province":"OR",
    "sg:tags":[
        "maintenance",
        "landscape"
    ],
    "wof:name":"Dan Wootons Landscape Maint",
    "wof:placetype":"venue"
},
  "geometry": {"coordinates":[-122.890613,42.299645],"type":"Point"}
}