{
  "type": "Feature",
  "properties": {
    "iso:country":"US",
    "sg:address":"2065 SW Palos Verdes Dr",
    "sg:city":"Roseburg",
    "sg:classifiers":[
        {
            "category":"Education",
            "subcategory":"Special Training",
            "type":"Public Place"
        }
    ],
    "sg:phone":"+1 541 440 5474",
    "sg:postcode":"97470",
    "sg:province":"OR",
    "sg:tags":[
        "equipment"
    ],
    "wof:name":"Adventure Aviation Institute",
    "wof:placetype":"venue"
},
  "geometry": {"coordinates":[-123.386358,43.154699],"type":"Point"}
}