{
  "type": "Feature",
  "properties": {
    "iso:country":"US",
    "sg:address":"4850 SW Scholls Ferry Rd",
    "sg:city":"Portland",
    "sg:classifiers":[
        {
            "category":"Insurance",
            "subcategory":"Insurance Agent",
            "type":"Services"
        },
        {
            "category":"Insurance",
            "subcategory":"Hazard Insurance",
            "type":"Services"
        },
        {
            "category":"Insurance",
            "subcategory":"Title Insurance",
            "type":"Services"
        },
        {
            "category":"Insurance",
            "subcategory":"Life Insurance",
            "type":"Services"
        }
    ],
    "sg:phone":"+1 503 292 2528",
    "sg:postcode":"97225",
    "sg:province":"OR",
    "sg:tags":[
        "business",
        "auto",
        "commercial",
        "homeowner",
        "motorcycle",
        "renter"
    ],
    "wof:name":"Allstate Insurance Company - Ramon Guevara",
    "wof:placetype":"venue"
},
  "geometry": {"coordinates":[-122.75097700000001,45.485199],"type":"Point"}
}