{
  "type": "Feature",
  "properties": {
    "addr:full":"19250 SW 65th Ave Tualatin OR 97062",
    "addr:housenumber":"19250",
    "addr:postcode":"97062",
    "addr:street":"Sw 65Th Ave",
    "iso:country":"US",
    "sg:address":"19250 SW 65th Ave",
    "sg:city":"Tualatin",
    "sg:classifiers":[
        {
            "category":"Health Services",
            "subcategory":"Doctor",
            "type":"Services"
        }
    ],
    "sg:phone":"+1 503 352 0770",
    "sg:postcode":"97062",
    "sg:province":"OR",
    "sg:tags":[
        "medicine",
        "internal"
    ],
    "wof:name":"Delaney Jaymee MD",
    "wof:placetype":"venue"
},
  "geometry": {"coordinates":[-122.743731,45.38149],"type":"Point"}
}