{
  "type": "Feature",
  "properties": {
    "addr:full":"765 NE Darnielle Dr Hillsboro OR 97124",
    "addr:housenumber":"765",
    "addr:postcode":"97124",
    "addr:street":"Ne Darnielle Dr",
    "iso:country":"US",
    "sg:address":"765 NE Darnielle Dr",
    "sg:city":"Hillsboro",
    "sg:classifiers":[
        {
            "category":"Organizations",
            "subcategory":"Religious Organization",
            "type":"Services"
        }
    ],
    "sg:phone":"+1 503 681 0127",
    "sg:postcode":"97124",
    "sg:province":"OR",
    "wof:name":"Iglesia Del Pueblo",
    "wof:placetype":"venue"
},
  "geometry": {"coordinates":[-122.977474,45.530223],"type":"Point"}
}