{
  "type": "Feature",
  "properties": {
    "addr:full":"1235 SW Highway 97 Madras OR 97741",
    "addr:housenumber":"1235",
    "addr:postcode":"97741",
    "addr:street":"Sw Highway 97",
    "iso:country":"US",
    "sg:address":"1235 SW Highway 97",
    "sg:city":"Madras",
    "sg:classifiers":[
        {
            "category":"Restaurant",
            "type":"Food & Drink"
        }
    ],
    "sg:menulink":"http://www.allmenus.com/or/madras/88140-abbys-legendary-pizza/menu/",
    "sg:phone":"+1 541 475 6363",
    "sg:postcode":"97741",
    "sg:province":"OR",
    "sg:tags":[
        "american",
        "pizza"
    ],
    "wof:name":"Abby's Legendary Pizza",
    "wof:placetype":"venue"
},
  "geometry": {"coordinates":[-121.132836,44.618972],"type":"Point"}
}