{
  "type": "Feature",
  "properties": {
    "iso:country":"US",
    "sg:address":"4007 SE Kelly St",
    "sg:city":"Portland",
    "sg:classifiers":[
        {
            "category":"Restaurant",
            "type":"Food & Drink"
        }
    ],
    "sg:phone":"+1 503 238 3920",
    "sg:postcode":"97202",
    "sg:province":"OR",
    "sg:tags":[
        "eating"
    ],
    "wof:name":"Mitaris Inc",
    "wof:placetype":"venue"
},
  "geometry": {"coordinates":[-122.620925,45.499871],"type":"Point"}
}