{
  "type": "Feature",
  "properties": {
    "iso:country":"US",
    "sg:address":"59 Coburg Rd",
    "sg:city":"Eugene",
    "sg:classifiers":[
        {
            "category":"Restaurant",
            "type":"Food & Drink"
        }
    ],
    "sg:phone":"+1 541 485 5336",
    "sg:postcode":"97401",
    "sg:province":"OR",
    "wof:name":"Cascade Hospitality Inc",
    "wof:placetype":"venue"
},
  "geometry": {"coordinates":[-123.08000800000001,44.062227],"type":"Point"}
}