{
  "type": "Feature",
  "properties": {
    "iso:country":"US",
    "sg:address":"415 NW 3rd St",
    "sg:city":"Prineville",
    "sg:classifiers":[
        {
            "category":"Personal",
            "subcategory":"Tanning Parlor",
            "type":"Services"
        }
    ],
    "sg:phone":"+1 541 447 2785",
    "sg:postcode":"97754",
    "sg:province":"OR",
    "sg:tags":[
        "salon"
    ],
    "wof:name":"Electric Beach Tanning Salon",
    "wof:placetype":"venue"
},
  "geometry": {"coordinates":[-120.852999,44.303014],"type":"Point"}
}