{
  "type": "Feature",
  "properties": {
    "addr:full":"14 SW Nye St Newport OR 97365",
    "addr:housenumber":"14",
    "addr:postcode":"97365",
    "addr:street":"Sw Nye St",
    "iso:country":"US",
    "sg:address":"14 SW Nye St",
    "sg:city":"Newport",
    "sg:classifiers":[
        {
            "category":"Health Services",
            "subcategory":"Optometrist",
            "type":"Services"
        }
    ],
    "sg:phone":"+1 541 265 8828",
    "sg:postcode":"97365",
    "sg:province":"OR",
    "wof:name":"Eye Care Ctr",
    "wof:placetype":"venue"
},
  "geometry": {"coordinates":[-124.05572600000001,44.636441],"type":"Point"}
}