{
  "type": "Feature",
  "properties": {
    "iso:country":"US",
    "sg:address":"1162 Marine Dr",
    "sg:city":"Astoria",
    "sg:classifiers":[
        {
            "category":"Shopping",
            "subcategory":"Stationery & Office Supplies",
            "type":"Retail Goods"
        },
        {
            "category":"Home & Garden",
            "subcategory":"Furniture",
            "type":"Retail Goods"
        }
    ],
    "sg:phone":"+1 503 468 3685",
    "sg:postcode":"97103",
    "sg:province":"OR",
    "sg:tags":[
        "store"
    ],
    "wof:name":"Bargain's Galore!",
    "wof:placetype":"venue"
},
  "geometry": {"coordinates":[-123.830713,46.189717],"type":"Point"}
}