{
  "type": "Feature",
  "properties": {
    "iso:country":"US",
    "sg:address":"20 N 5th St",
    "sg:city":"Cottage Grove",
    "sg:classifiers":[
        {
            "category":"Professional",
            "subcategory":"Accounting & Tax Preparation",
            "type":"Services"
        }
    ],
    "sg:phone":"+1 541 942 3379",
    "sg:postcode":"97424",
    "sg:province":"OR",
    "wof:name":"Zeller & Co Llp Cpas",
    "wof:placetype":"venue"
},
  "geometry": {"coordinates":[-123.062774,43.797854],"type":"Point"}
}