{
  "type": "Feature",
  "properties": {
    "iso:country":"US",
    "sg:address":"4400 SW Advance Rd",
    "sg:city":"Wilsonville",
    "sg:classifiers":[
        {
            "category":"Building & Trades",
            "subcategory":"Landscaping Services",
            "type":"Services"
        }
    ],
    "sg:phone":"+1 503 682 0705",
    "sg:postcode":"97070",
    "sg:province":"OR",
    "sg:tags":[
        "gardener",
        "lawn",
        "landscape",
        "maintenance",
        "contractor"
    ],
    "wof:name":"Becks Botanical",
    "wof:placetype":"venue"
},
  "geometry": {"coordinates":[-122.72175799999999,45.317452],"type":"Point"}
}