{
  "type": "Feature",
  "properties": {
    "iso:country":"US",
    "sg:address":"582 22nd St",
    "sg:city":"Astoria",
    "sg:classifiers":[
        {
            "category":"Health Services",
            "subcategory":"Doctor",
            "type":"Services"
        }
    ],
    "sg:phone":"+1 503 325 0045",
    "sg:postcode":"97103",
    "sg:province":"OR",
    "sg:tags":[
        "physician",
        "surgeon"
    ],
    "wof:name":"Charles R Star MD PC",
    "wof:placetype":"venue"
},
  "geometry": {"coordinates":[-123.817137,46.187655],"type":"Point"}
}