{
  "type": "Feature",
  "properties": {
    "iso:country":"US",
    "sg:address":"2029 NW Lovejoy St",
    "sg:city":"Portland",
    "sg:classifiers":[
        {
            "category":"Manufacturing",
            "subcategory":"Metals",
            "type":"Manufacturing & Wholesale Goods"
        }
    ],
    "sg:phone":"+1 503 226 0185",
    "sg:postcode":"97209",
    "sg:province":"OR",
    "sg:tags":[
        "metal-wholesale",
        "manufacturer"
    ],
    "wof:name":"Wolf Sales Company, Inc",
    "wof:placetype":"venue"
},
  "geometry": {"coordinates":[-122.693119,45.529889],"type":"Point"}
}