{
  "type": "Feature",
  "properties": {
    "iso:country":"US",
    "sg:address":"1001 SE Tualatin Valley Hwy Ste A1",
    "sg:city":"Hillsboro",
    "sg:classifiers":[
        {
            "category":"Restaurant",
            "type":"Food & Drink"
        }
    ],
    "sg:phone":"+1 503 693 7011",
    "sg:postcode":"97123",
    "sg:province":"OR",
    "sg:tags":[
        "mexican"
    ],
    "wof:name":"Juan Colorado Mexican Rstrnt",
    "wof:placetype":"venue"
},
  "geometry": {"coordinates":[-122.972628,45.511562],"type":"Point"}
}