{
  "type": "Feature",
  "properties": {
    "addr:full":"450 NW 257th Ave Ste 506 Troutdale OR 97060",
    "addr:housenumber":"450",
    "addr:postcode":"97060",
    "addr:street":"Nw 257Th Ave Ste 506",
    "iso:country":"US",
    "sg:address":"450 NW 257th Ave Ste 506",
    "sg:city":"Troutdale",
    "sg:classifiers":[
        {
            "category":"Food & Beverages",
            "subcategory":"Specialty",
            "type":"Retail Goods"
        },
        {
            "category":"Shopping",
            "subcategory":"Gifts & Souvenirs",
            "type":"Retail Goods"
        }
    ],
    "sg:phone":"+1 503 666 6550",
    "sg:postcode":"97060",
    "sg:province":"OR",
    "sg:tags":[
        "shop",
        "gourmet",
        "basket"
    ],
    "sg:website":"http://www.harryanddavid.com",
    "wof:name":"Harry and David",
    "wof:placetype":"venue"
},
  "geometry": {"coordinates":[-122.389381,45.544392],"type":"Point"}
}