{
  "type": "Feature",
  "properties": {
    "iso:country":"US",
    "sg:address":"317 E Main St",
    "sg:city":"Medford",
    "sg:classifiers":[
        {
            "category":"Restaurant",
            "type":"Food & Drink"
        }
    ],
    "sg:phone":"+1 541 773 7427",
    "sg:postcode":"97501",
    "sg:province":"OR",
    "wof:name":"Porkys Pride Real Pit BBQ",
    "wof:placetype":"venue"
},
  "geometry": {"coordinates":[-122.87074,42.327395],"type":"Point"}
}