{
  "type": "Feature",
  "properties": {
    "addr:full":"645 NW Park Blvd Ontario OR 97914",
    "addr:housenumber":"645",
    "addr:postcode":"97914",
    "addr:street":"Nw Park Blvd",
    "iso:country":"US",
    "sg:address":"645 NW Park Blvd",
    "sg:city":"Ontario",
    "sg:classifiers":[
        {
            "category":"Building & Trades",
            "subcategory":"Construction",
            "type":"Services"
        }
    ],
    "sg:phone":"+1 541 889 8284",
    "sg:postcode":"97914",
    "sg:province":"OR",
    "sg:tags":[
        "house",
        "general",
        "contractor"
    ],
    "wof:name":"Erlebach Bruce D Construction",
    "wof:placetype":"venue"
},
  "geometry": {"coordinates":[-116.975526,44.033645],"type":"Point"}
}