{
  "type": "Feature",
  "properties": {
    "iso:country":"US",
    "sg:address":"2873 22nd St SE",
    "sg:city":"Salem",
    "sg:classifiers":[
        {
            "category":"Professional",
            "subcategory":"Research",
            "type":"Services"
        }
    ],
    "sg:phone":"+1 503 391 4412",
    "sg:postcode":"97302",
    "sg:province":"OR",
    "sg:tags":[
        "development",
        "lab"
    ],
    "wof:name":"Composite Materials R D",
    "wof:placetype":"venue"
},
  "geometry": {"coordinates":[-123.017328,44.915732],"type":"Point"}
}