{
  "type": "Feature",
  "properties": {
    "iso:country":"US",
    "sg:address":"5371 70th Ave SE",
    "sg:city":"Salem",
    "sg:classifiers":[
        {
            "category":"Shopping",
            "subcategory":"Florist",
            "type":"Retail Goods"
        }
    ],
    "sg:phone":"+1 503 362 8633",
    "sg:postcode":"97317",
    "sg:province":"OR",
    "wof:name":"Pats Flower Shop",
    "wof:placetype":"venue"
},
  "geometry": {"coordinates":[-122.916923,44.874763],"type":"Point"}
}