{
  "type": "Feature",
  "properties": {
    "iso:country":"US",
    "sg:address":"27001 SE Kelso Rd",
    "sg:city":"Boring",
    "sg:classifiers":[
        {
            "category":"Building & Trades",
            "subcategory":"Construction",
            "type":"Services"
        }
    ],
    "sg:phone":"+1 503 668 8154",
    "sg:postcode":"97009",
    "sg:province":"OR",
    "sg:tags":[
        "carpentry",
        "contractor"
    ],
    "wof:name":"Sheridan Woodworking",
    "wof:placetype":"venue"
},
  "geometry": {"coordinates":[-122.383786,45.418128],"type":"Point"}
}