{
  "type": "Feature",
  "properties": {
    "addr:full":"32133 Viewcrest Dr Warren OR 97053",
    "addr:postcode":"32133;97053",
    "addr:street":"Viewcrest Dr",
    "iso:country":"US",
    "sg:address":"32133 Viewcrest Dr",
    "sg:city":"Warren",
    "sg:classifiers":[
        {
            "category":"Real Estate",
            "subcategory":"Real Estate Operator",
            "type":"Services"
        }
    ],
    "sg:phone":"+1 503 543 5079",
    "sg:postcode":"97053",
    "sg:province":"OR",
    "sg:tags":[
        "mobile",
        "home",
        "site"
    ],
    "wof:name":"Rudds Mobile Court",
    "wof:placetype":"venue"
},
  "geometry": {"coordinates":[-122.89460699999999,45.802744],"type":"Point"}
}