{
  "type": "Feature",
  "properties": {
    "addr:full":"51506 Riverland Ave La Pine OR 97739",
    "addr:housenumber":"51506",
    "addr:postcode":"97739",
    "addr:street":"Riverland Ave",
    "iso:country":"US",
    "sg:address":"51506 Riverland Ave",
    "sg:city":"La Pine",
    "sg:classifiers":[
        {
            "category":"Shopping",
            "subcategory":"Bicycles & Sporting Goods",
            "type":"Retail Goods"
        }
    ],
    "sg:phone":"+1 541 536 3188",
    "sg:postcode":"97739",
    "sg:province":"OR",
    "sg:tags":[
        "gun",
        "gunsmith"
    ],
    "wof:name":"High Desert Gunsmithing",
    "wof:placetype":"venue"
},
  "geometry": {"coordinates":[-121.541191,43.671748],"type":"Point"}
}