{
  "type": "Feature",
  "properties": {
    "iso:country":"US",
    "sg:address":"1231 NW Hoyt St Ste 204",
    "sg:city":"Portland",
    "sg:classifiers":[
        {
            "category":"Professional",
            "subcategory":"Art Services",
            "type":"Services"
        }
    ],
    "sg:phone":"+1 503 295 1979",
    "sg:postcode":"97209",
    "sg:province":"OR",
    "sg:tags":[
        "commercial",
        "artist"
    ],
    "sg:website":"http://www.ansteyhealy.com",
    "wof:name":"Flint Design Co.",
    "wof:placetype":"venue"
},
  "geometry": {"coordinates":[-122.68362399999999,45.527218],"type":"Point"}
}