{
  "type": "Feature",
  "properties": {
    "addr:full":"6613 NE Pettibone Dr Corvallis OR 97330",
    "addr:housenumber":"6613",
    "addr:postcode":"97330",
    "addr:street":"Ne Pettibone Dr",
    "iso:country":"US",
    "sg:address":"6613 NE Pettibone Dr",
    "sg:city":"Corvallis",
    "sg:classifiers":[
        {
            "category":"Farming",
            "subcategory":"Nursery",
            "type":"Manufacturing & Wholesale Goods"
        }
    ],
    "sg:phone":"+1 541 745 5188",
    "sg:postcode":"97330",
    "sg:province":"OR",
    "sg:tags":[
        "ornamental",
        "supply"
    ],
    "wof:name":"Oregon Rhododendrons",
    "wof:placetype":"venue"
},
  "geometry": {"coordinates":[-123.214918,44.638886],"type":"Point"}
}