{
  "type": "Feature",
  "properties": {
    "addr:full":"16250 Pacific Hwy Lake Oswego OR 97034",
    "addr:housenumber":"16250",
    "addr:postcode":"97034",
    "addr:street":"Pacific Hwy",
    "iso:country":"US",
    "sg:address":"16250 Pacific Hwy",
    "sg:city":"Lake Oswego",
    "sg:classifiers":[
        {
            "category":"Building & Trades",
            "subcategory":"Plumbing",
            "type":"Services"
        }
    ],
    "sg:phone":"+1 503 895 1213",
    "sg:postcode":"97034",
    "sg:province":"OR",
    "sg:website":"lakeoswegoserviceplumber.weebly.com",
    "wof:name":"Lake Oswego Service Plumber",
    "wof:placetype":"venue"
},
  "geometry": {"coordinates":[-122.659459,45.408194],"type":"Point"}
}