{
  "type": "Feature",
  "properties": {
    "iso:country":"US",
    "sg:address":"2625 NE 20th Ave",
    "sg:city":"Portland",
    "sg:classifiers":[
        {
            "category":"Professional",
            "subcategory":"Accounting & Tax Preparation",
            "type":"Services"
        }
    ],
    "sg:phone":"+1 503 284 1633",
    "sg:postcode":"97212",
    "sg:province":"OR",
    "wof:name":"Pilgrim Accounting Service",
    "wof:placetype":"venue"
},
  "geometry": {"coordinates":[-122.645364,45.541086],"type":"Point"}
}