{
  "type": "Feature",
  "properties": {
    "addr:full":"63010 Plateau Dr Bend OR 97701",
    "addr:housenumber":"63010",
    "addr:postcode":"97701",
    "addr:street":"Plateau Dr",
    "iso:country":"US",
    "sg:address":"63010 Plateau Dr",
    "sg:city":"Bend",
    "sg:classifiers":[
        {
            "category":"Home & Garden",
            "subcategory":"Carpets & Floor Coverings",
            "type":"Retail Goods"
        }
    ],
    "sg:phone":"+1 541 388 9208",
    "sg:postcode":"97701",
    "sg:province":"OR",
    "sg:tags":[
        "material"
    ],
    "wof:name":"Central Oregon Whl Flrg Co",
    "wof:placetype":"venue"
},
  "geometry": {"coordinates":[-121.29306200000001,44.087914],"type":"Point"}
}