{
  "type": "Feature",
  "properties": {
    "addr:full":"3463 SW Binford Way Gresham OR 97080",
    "addr:housenumber":"3463",
    "addr:postcode":"97080",
    "addr:street":"Sw Binford Way",
    "iso:country":"US",
    "sg:address":"3463 SW Binford Way",
    "sg:city":"Gresham",
    "sg:classifiers":[
        {
            "category":"Professional",
            "subcategory":"Detective & Security Services",
            "type":"Services"
        }
    ],
    "sg:phone":"+1 503 618 8871",
    "sg:postcode":"97080",
    "sg:province":"OR",
    "sg:tags":[
        "equipment",
        "system",
        "consultant"
    ],
    "wof:name":"Cicp",
    "wof:placetype":"venue"
},
  "geometry": {"coordinates":[-122.45971,45.472072],"type":"Point"}
}