{
  "type": "Feature",
  "properties": {
    "iso:country":"US",
    "sg:address":"3175 College St",
    "sg:city":"Baker City",
    "sg:classifiers":[
        {
            "category":"Professional",
            "subcategory":"Computer Services",
            "type":"Services"
        }
    ],
    "sg:phone":"+1 541 523 3566",
    "sg:postcode":"97814",
    "sg:province":"OR",
    "sg:tags":[
        "consultant",
        "designer"
    ],
    "wof:name":"Mark Payne Consulting",
    "wof:placetype":"venue"
},
  "geometry": {"coordinates":[-117.834738,44.787892],"type":"Point"}
}