{
  "type": "Feature",
  "properties": {
    "iso:country":"US",
    "sg:address":"1675 E Gregory Rd",
    "sg:city":"Central Point",
    "sg:classifiers":[
        {
            "category":"Retail",
            "subcategory":"Auto Repair",
            "type":"Services"
        }
    ],
    "sg:phone":"+1 541 826 2200",
    "sg:postcode":"97502",
    "sg:province":"OR",
    "wof:name":"Small Engine Specialties",
    "wof:placetype":"venue"
},
  "geometry": {"coordinates":[-122.864558,42.41709],"type":"Point"}
}