{
  "type": "Feature",
  "properties": {
    "iso:country":"US",
    "sg:address":"13345 SW Allen Blvd",
    "sg:city":"Beaverton",
    "sg:classifiers":[
        {
            "category":"Building & Trades",
            "subcategory":"Locksmith",
            "type":"Services"
        }
    ],
    "sg:phone":"+1 503 715 3887",
    "sg:postcode":"97005",
    "sg:province":"OR",
    "sg:tags":[
        "key"
    ],
    "wof:name":"0 Locksmith",
    "wof:placetype":"venue"
},
  "geometry": {"coordinates":[-122.814179,45.476611],"type":"Point"}
}