{
  "type": "Feature",
  "properties": {
    "iso:country":"US",
    "sg:address":"10275 SW Park Way",
    "sg:city":"Portland",
    "sg:classifiers":[
        {
            "category":"Autos & Motor Vehicles",
            "subcategory":"Fuel & Gas Station",
            "type":"Retail Goods"
        },
        {
            "category":"Retail",
            "subcategory":"Auto Repair",
            "type":"Services"
        }
    ],
    "sg:phone":"+1 503 292 7929",
    "sg:postcode":"97225",
    "sg:province":"OR",
    "sg:website":"www.kevorksautocare.com",
    "wof:name":"Kevork's Auto Care",
    "wof:placetype":"venue"
},
  "geometry": {"coordinates":[-122.78299699999999,45.508499],"type":"Point"}
}