{
  "type": "Feature",
  "properties": {
    "addr:full":"2313 NE Alameda St Portland OR 97212",
    "addr:housenumber":"2313",
    "addr:postcode":"97212",
    "addr:street":"Ne Alameda St",
    "iso:country":"US",
    "sg:address":"2313 NE Alameda St",
    "sg:city":"Portland",
    "sg:classifiers":[
        {
            "category":"Professional",
            "subcategory":"Engineering",
            "type":"Services"
        }
    ],
    "sg:phone":"+1 503 287 0511",
    "sg:postcode":"97212",
    "sg:province":"OR",
    "sg:tags":[
        "engineer"
    ],
    "wof:name":"Geo Lavielle Technical Pc",
    "wof:placetype":"venue"
},
  "geometry": {"coordinates":[-122.641835,45.551842],"type":"Point"}
}