{
  "type": "Feature",
  "properties": {
    "addr:full":"2927 NE Everett St Portland OR 97232",
    "addr:housenumber":"2927",
    "addr:postcode":"97232",
    "addr:street":"Ne Everett St",
    "iso:country":"US",
    "sg:address":"2927 NE Everett St",
    "sg:city":"Portland",
    "sg:classifiers":[
        {
            "category":"Personal",
            "type":"Services"
        }
    ],
    "sg:phone":"+1 503 239 7906",
    "sg:postcode":"97232",
    "sg:province":"OR",
    "wof:name":"A Touch of Energy",
    "wof:placetype":"venue"
},
  "geometry": {"coordinates":[-122.63475800000001,45.525113],"type":"Point"}
}