{
  "type": "Feature",
  "properties": {
    "iso:country":"US",
    "sg:address":"16250 SW Palermo Ln",
    "sg:city":"Portland",
    "sg:classifiers":[
        {
            "category":"Shopping",
            "subcategory":"Hobbies, Toys, & Games",
            "type":"Retail Goods"
        },
        {
            "category":"Shopping",
            "subcategory":"Crafts & Fabrics",
            "type":"Retail Goods"
        }
    ],
    "sg:phone":"+1 503 590 0279",
    "sg:postcode":"97223",
    "sg:province":"OR",
    "sg:tags":[
        "shop",
        "hobby",
        "model",
        "supply"
    ],
    "wof:name":"The Holy Land Crafts",
    "wof:placetype":"venue"
},
  "geometry": {"coordinates":[-122.844356,45.418849],"type":"Point"}
}