{
  "type": "Feature",
  "properties": {
    "iso:country":"US",
    "sg:address":"13770 NW Orchard View Rd",
    "sg:city":"Mcminnville",
    "sg:classifiers":[
        {
            "category":"Social Services",
            "subcategory":"Adult Care",
            "type":"Services"
        }
    ],
    "sg:phone":"+1 503 434 6518",
    "sg:postcode":"97128",
    "sg:province":"OR",
    "sg:tags":[
        "foster"
    ],
    "wof:name":"Rhodes Foster Care Home",
    "wof:placetype":"venue"
},
  "geometry": {"coordinates":[-123.262905,45.234802],"type":"Point"}
}