{
  "type": "Feature",
  "properties": {
    "iso:country":"US",
    "sg:address":"1040 Madison St",
    "sg:city":"Baker City",
    "sg:classifiers":[
        {
            "category":"Organizations",
            "subcategory":"Community Association",
            "type":"Services"
        }
    ],
    "sg:phone":"+1 541 523 3577",
    "sg:postcode":"97814",
    "sg:province":"OR",
    "wof:name":"Delta Kappa Gamma Society",
    "wof:placetype":"venue"
},
  "geometry": {"coordinates":[-117.817741,44.780467],"type":"Point"}
}