{
  "type": "Feature",
  "properties": {
    "addr:full":"1919 SE 82nd Ave Portland OR 97216",
    "addr:housenumber":"1919",
    "addr:postcode":"97216",
    "addr:street":"Se 82Nd Ave",
    "iso:country":"US",
    "sg:address":"1919 SE 82nd Ave",
    "sg:city":"Portland",
    "sg:classifiers":[
        {
            "category":"Restaurant",
            "type":"Food & Drink"
        }
    ],
    "sg:phone":"+1 503 788 5244",
    "sg:postcode":"97216",
    "sg:province":"OR",
    "sg:tags":[
        "vietnamese"
    ],
    "sg:website":"www.phovanrestaurant.com",
    "wof:name":"Pho Van Restaurant",
    "wof:placetype":"venue"
},
  "geometry": {"coordinates":[-122.578003,45.509201],"type":"Point"}
}