{
  "type": "Feature",
  "properties": {
    "iso:country":"US",
    "sg:address":"13665 NW Pali St",
    "sg:city":"Seal Rock",
    "sg:classifiers":[
        {
            "category":"Museum",
            "type":"Entertainment"
        }
    ],
    "sg:phone":"+1 541 563 5614",
    "sg:postcode":"97376",
    "sg:province":"OR",
    "sg:tags":[
        "gallery"
    ],
    "wof:name":"Seacliff Studio Gallery",
    "wof:placetype":"venue"
},
  "geometry": {"coordinates":[-124.065308,44.525847],"type":"Point"}
}