{
  "type": "Feature",
  "properties": {
    "iso:country":"US",
    "sg:address":"6960 SW Varns St",
    "sg:city":"Tigard",
    "sg:classifiers":[
        {
            "category":"Health Services",
            "subcategory":"Doctor",
            "type":"Services"
        }
    ],
    "sg:phone":"+1 503 443 3800",
    "sg:postcode":"97223",
    "sg:province":"OR",
    "sg:tags":[
        "clinic"
    ],
    "wof:name":"Hazelden Springbrook",
    "wof:placetype":"venue"
},
  "geometry": {"coordinates":[-122.751188,45.42418],"type":"Point"}
}