{
  "type": "Feature",
  "properties": {
    "iso:country":"US",
    "sg:address":"16131 US Hwy 101",
    "sg:city":"Brookings",
    "sg:classifiers":[
        {
            "category":"Home & Garden",
            "subcategory":"Carpets & Floor Coverings",
            "type":"Retail Goods"
        }
    ],
    "sg:phone":"+1 541 469 0104",
    "sg:postcode":"97415",
    "sg:province":"OR",
    "sg:tags":[
        "dealer",
        "rug"
    ],
    "wof:name":"Trinity Carpet Brokers Inc",
    "wof:placetype":"venue"
},
  "geometry": {"coordinates":[-124.2548,42.046314],"type":"Point"}
}