{
  "type": "Feature",
  "properties": {
    "iso:country":"US",
    "sg:address":"5768 Main St",
    "sg:city":"Springfield",
    "sg:classifiers":[
        {
            "category":"Food & Beverages",
            "subcategory":"Bakery",
            "type":"Retail Goods"
        }
    ],
    "sg:phone":"+1 541 868 1072",
    "sg:postcode":"97478",
    "sg:province":"OR",
    "wof:name":"Bagel Sphere",
    "wof:placetype":"venue"
},
  "geometry": {"coordinates":[-122.92764099999999,44.045757],"type":"Point"}
}