{
  "type": "Feature",
  "properties": {
    "iso:country":"US",
    "sg:address":"1949 SE Stephens St",
    "sg:city":"Roseburg",
    "sg:classifiers":[
        {
            "category":"Organizations",
            "subcategory":"Religious Organization",
            "type":"Services"
        }
    ],
    "sg:phone":"+1 541 229 5000",
    "sg:postcode":"97470",
    "sg:province":"OR",
    "sg:tags":[
        "church"
    ],
    "wof:name":"New Religious Sci Chr",
    "wof:placetype":"venue"
},
  "geometry": {"coordinates":[-123.35297300000001,43.196034],"type":"Point"}
}