{
  "type": "Feature",
  "properties": {
    "addr:full":"15383 Bangy Rd Lake Oswego OR 97035",
    "addr:housenumber":"15383",
    "addr:postcode":"97035",
    "addr:street":"Bangy Rd",
    "iso:country":"US",
    "sg:address":"15383 Bangy Rd",
    "sg:city":"Lake Oswego",
    "sg:classifiers":[
        {
            "category":"Building & Trades",
            "subcategory":"Construction",
            "type":"Services"
        },
        {
            "category":"Home & Garden",
            "subcategory":"Furniture",
            "type":"Retail Goods"
        }
    ],
    "sg:phone":"+1 503 639 9676",
    "sg:postcode":"97035",
    "sg:province":"OR",
    "sg:tags":[
        "interior",
        "design",
        "store"
    ],
    "wof:name":"Georgetown Manor",
    "wof:placetype":"venue"
},
  "geometry": {"coordinates":[-122.74299600000001,45.414001],"type":"Point"}
}