{
  "type": "Feature",
  "properties": {
    "iso:country":"US",
    "sg:address":"82981 Joseph Hwy",
    "sg:city":"Joseph",
    "sg:classifiers":[
        {
            "category":"Home & Garden",
            "subcategory":"Building Materials",
            "type":"Retail Goods"
        }
    ],
    "sg:phone":"+1 541 426 4744",
    "sg:postcode":"97846",
    "sg:province":"OR",
    "sg:tags":[
        "glass",
        "window",
        "plate"
    ],
    "wof:name":"Wallowa Valley Glass",
    "wof:placetype":"venue"
},
  "geometry": {"coordinates":[-117.229956,45.380981],"type":"Point"}
}