{
  "type": "Feature",
  "properties": {
    "addr:full":"215 W Estella St Glide OR 97443",
    "addr:housenumber":"215",
    "addr:postcode":"97443",
    "addr:street":"W Estella St",
    "iso:country":"US",
    "sg:address":"215 W Estella St",
    "sg:city":"Glide",
    "sg:classifiers":[
        {
            "category":"Organizations",
            "subcategory":"Religious Organization",
            "type":"Services"
        }
    ],
    "sg:phone":"+1 541 496 3767",
    "sg:postcode":"97443",
    "sg:province":"OR",
    "sg:tags":[
        "church"
    ],
    "wof:name":"Calvary Chapel Of Glide",
    "wof:placetype":"venue"
},
  "geometry": {"coordinates":[-123.090361,43.300146],"type":"Point"}
}