{
  "type": "Feature",
  "properties": {
    "iso:country":"US",
    "sg:address":"33954 McFarland Rd",
    "sg:city":"Tangent",
    "sg:classifiers":[
        {
            "category":"Professional",
            "subcategory":"Business Services",
            "type":"Services"
        }
    ],
    "sg:phone":"+1 541 924 9546",
    "sg:postcode":"97389",
    "sg:province":"OR",
    "sg:tags":[
        "interior",
        "consultant",
        "design",
        "decorator"
    ],
    "wof:name":"Bobbi J Heagy Interiors",
    "wof:placetype":"venue"
},
  "geometry": {"coordinates":[-123.112695,44.569545],"type":"Point"}
}