{
  "type": "Feature",
  "properties": {
    "addr:full":"14235 SE Steele St Portland OR 97236",
    "addr:housenumber":"14235",
    "addr:postcode":"97236",
    "addr:street":"Se Steele St",
    "iso:country":"US",
    "sg:address":"14235 SE Steele St",
    "sg:city":"Portland",
    "sg:classifiers":[
        {
            "category":"Home & Garden",
            "subcategory":"Garden Supply",
            "type":"Retail Goods"
        },
        {
            "category":"Building & Trades",
            "subcategory":"Construction",
            "type":"Services"
        },
        {
            "category":"Sports & Exercise",
            "subcategory":"Swimming Pool",
            "type":"Entertainment"
        }
    ],
    "sg:phone":"+1 503 760 4554",
    "sg:postcode":"97236",
    "sg:province":"OR",
    "sg:tags":[
        "consulting",
        "designing"
    ],
    "sg:website":"http://www.bluemountainpools.com/",
    "wof:name":"Blue Mountain Pools",
    "wof:placetype":"venue"
},
  "geometry": {"coordinates":[-122.51543100000001,45.484349],"type":"Point"}
}