{
  "type": "Feature",
  "properties": {
    "addr:full":"305 NE 6th St Grants Pass OR 97526",
    "addr:housenumber":"305",
    "addr:postcode":"97526",
    "addr:street":"Ne 6Th St",
    "iso:country":"US",
    "sg:address":"305 NE 6th St",
    "sg:city":"Grants Pass",
    "sg:classifiers":[
        {
            "category":"Home & Garden",
            "subcategory":"Home Furnishings",
            "type":"Retail Goods"
        }
    ],
    "sg:phone":"+1 541 476 7032",
    "sg:postcode":"97526",
    "sg:province":"OR",
    "wof:name":"Imartstores Pampered Gourmet",
    "wof:placetype":"venue"
},
  "geometry": {"coordinates":[-123.32599399999999,42.440754],"type":"Point"}
}