{
  "type": "Feature",
  "properties": {
    "iso:country":"US",
    "sg:address":"17105 NE Everett St",
    "sg:city":"Portland",
    "sg:classifiers":[
        {
            "category":"Personal",
            "subcategory":"Massage",
            "type":"Services"
        },
        {
            "category":"Health Services",
            "subcategory":"Clinic",
            "type":"Services"
        },
        {
            "category":"Health Services",
            "subcategory":"Health Practitioner",
            "type":"Services"
        }
    ],
    "sg:phone":"+1 503 997 8608",
    "sg:postcode":"97230",
    "sg:province":"OR",
    "sg:tags":[
        "medicine",
        "alternative",
        "therapist",
        "therapy",
        "physical"
    ],
    "wof:name":"A Compassionate Touch Massage and Bodywork",
    "wof:placetype":"venue"
},
  "geometry": {"coordinates":[-122.48722600000001,45.524868],"type":"Point"}
}