{
  "type": "Feature",
  "properties": {
    "addr:full":"7100 SW Hampton St Portland OR 97223",
    "addr:housenumber":"7100",
    "addr:postcode":"97223",
    "addr:street":"Sw Hampton St",
    "iso:country":"US",
    "sg:address":"7100 SW Hampton St",
    "sg:city":"Portland",
    "sg:classifiers":[
        {
            "category":"Professional",
            "subcategory":"Employment Agencies",
            "type":"Services"
        }
    ],
    "sg:phone":"+1 503 639 1266",
    "sg:postcode":"97223",
    "sg:province":"OR",
    "wof:name":"Car People Agency",
    "wof:placetype":"venue"
},
  "geometry": {"coordinates":[-122.750445,45.42755],"type":"Point"}
}