{
  "type": "Feature",
  "properties": {
    "iso:country":"US",
    "sg:address":"1915 SE Stone St",
    "sg:city":"Corvallis",
    "sg:classifiers":[
        {
            "category":"Real Estate",
            "subcategory":"Surveying",
            "type":"Services"
        }
    ],
    "sg:phone":"+1 541 752 7515",
    "sg:postcode":"97333",
    "sg:province":"OR",
    "sg:website":"www.parsons-surveying.com",
    "wof:name":"Parsons Surveying",
    "wof:placetype":"venue"
},
  "geometry": {"coordinates":[-123.26085399999999,44.546381],"type":"Point"}
}