{
  "type": "Feature",
  "properties": {
    "addr:full":"1991 W 2nd Ave Eugene OR 97402",
    "addr:housenumber":"1991",
    "addr:postcode":"97402",
    "addr:street":"W 2Nd Ave",
    "iso:country":"US",
    "sg:address":"1991 W 2nd Ave",
    "sg:city":"Eugene",
    "sg:classifiers":[
        {
            "category":"Wholesale",
            "subcategory":"Construction Materials",
            "type":"Manufacturing & Wholesale Goods"
        }
    ],
    "sg:phone":"+1 541 345 2301",
    "sg:postcode":"97402",
    "sg:province":"OR",
    "sg:tags":[
        "timberland",
        "company",
        "timber"
    ],
    "wof:name":"Giustina Land & Timber Co",
    "wof:placetype":"venue"
},
  "geometry": {"coordinates":[-123.12104100000001,44.057623],"type":"Point"}
}