{
  "type": "Feature",
  "properties": {
    "addr:full":"3037 SW Flower Ter Portland OR 97239",
    "addr:housenumber":"3037",
    "addr:postcode":"97239",
    "addr:street":"Sw Flower Ter",
    "iso:country":"US",
    "sg:address":"3037 SW Flower Ter",
    "sg:city":"Portland",
    "sg:classifiers":[
        {
            "category":"Professional",
            "subcategory":"Detective & Security Services",
            "type":"Services"
        }
    ],
    "sg:phone":"+1 503 892 2961",
    "sg:postcode":"97239",
    "sg:province":"OR",
    "sg:tags":[
        "car"
    ],
    "wof:name":"Michael J Mc Gee",
    "wof:placetype":"venue"
},
  "geometry": {"coordinates":[-122.709253,45.482209],"type":"Point"}
}