{
  "type": "Feature",
  "properties": {
    "iso:country":"US",
    "sg:address":"8152 SW Hall Blvd 514",
    "sg:city":"Beaverton",
    "sg:classifiers":[
        {
            "category":"Shopping",
            "subcategory":"Stationery & Office Supplies",
            "type":"Retail Goods"
        },
        {
            "category":"Professional",
            "subcategory":"Computer Services",
            "type":"Services"
        }
    ],
    "sg:phone":"+1 503 762 9989",
    "sg:postcode":"97008",
    "sg:province":"OR",
    "sg:tags":[
        "machine",
        "repair",
        "copy",
        "equipment-service"
    ],
    "sg:website":"http://www.inkjetswest.com",
    "wof:name":"Ink Jets West",
    "wof:placetype":"venue"
},
  "geometry": {"coordinates":[-122.793961,45.460643],"type":"Point"}
}