{
  "type": "Feature",
  "properties": {
    "iso:country":"US",
    "sg:address":"36678 Allstead Ln",
    "sg:city":"Halfway",
    "sg:classifiers":[
        {
            "category":"Farming",
            "subcategory":"Livestock Farm",
            "type":"Manufacturing & Wholesale Goods"
        }
    ],
    "sg:phone":"+1 541 742 4930",
    "sg:postcode":"97834",
    "sg:province":"OR",
    "sg:tags":[
        "llama"
    ],
    "wof:name":"Wallowa Llamas",
    "wof:placetype":"venue"
},
  "geometry": {"coordinates":[-117.150086,44.937504],"type":"Point"}
}