{
  "type": "Feature",
  "properties": {
    "addr:full":"4815 NE 42nd Avenue Portland OR 97218",
    "addr:housenumber":"4815",
    "addr:postcode":"97218",
    "addr:street":"Ne 42Nd Avenue",
    "iso:country":"US",
    "sg:address":"4815 NE 42nd Avenue",
    "sg:city":"Portland",
    "sg:classifiers":[
        {
            "category":"Real Estate",
            "subcategory":"Architect",
            "type":"Services"
        }
    ],
    "sg:phone":"+1 503 288 4073",
    "sg:postcode":"97218",
    "sg:province":"OR",
    "wof:name":"Knight's Building Design",
    "wof:placetype":"venue"
},
  "geometry": {"coordinates":[-122.620561,45.557999],"type":"Point"}
}