{
  "type": "Feature",
  "properties": {
    "iso:country":"US",
    "sg:address":"432 W Umpqua St",
    "sg:city":"Roseburg",
    "sg:classifiers":[
        {
            "category":"Real Estate",
            "subcategory":"Real Estate Operator",
            "type":"Services"
        }
    ],
    "sg:phone":"+1 541 673 4032",
    "sg:postcode":"97470",
    "sg:province":"OR",
    "sg:tags":[
        "building",
        "apartment"
    ],
    "wof:name":"Pratt Jacqueline Baker Trust",
    "wof:placetype":"venue"
},
  "geometry": {"coordinates":[-123.359143,43.216959],"type":"Point"}
}