{
  "type": "Feature",
  "properties": {
    "addr:full":"4443 NE 82nd Avenue Portland OR 97220",
    "addr:housenumber":"4443",
    "addr:postcode":"97220",
    "addr:street":"Ne 82Nd Avenue",
    "iso:country":"US",
    "sg:address":"4443 NE 82nd Avenue",
    "sg:city":"Portland",
    "sg:classifiers":[
        {
            "category":"Retail",
            "subcategory":"Emissions Testing",
            "type":"Services"
        },
        {
            "category":"Autos & Motor Vehicles",
            "subcategory":"Automobile Sales",
            "type":"Retail Goods"
        },
        {
            "category":"Autos & Motor Vehicles",
            "subcategory":"Auto Supplies",
            "type":"Retail Goods"
        },
        {
            "category":"Retail",
            "subcategory":"Auto Repair",
            "type":"Services"
        }
    ],
    "sg:phone":"+1 503 288 8634",
    "sg:postcode":"97220",
    "sg:province":"OR",
    "sg:tags":[
        "body",
        "used",
        "transmission",
        "car",
        "accessory",
        "inspection",
        "lube",
        "oil",
        "brake",
        "part",
        "painting",
        "repairing"
    ],
    "sg:website":"http://portland.citysearch.com/profile/external/41108605/portland_or/superior_import_repair.html?publisher=yellowpages&reference_id=1&placement=ypwebsitemip",
    "wof:name":"Superior Import Repair",
    "wof:placetype":"venue"
},
  "geometry": {"coordinates":[-122.578631,45.554623],"type":"Point"}
}