{
  "type": "Feature",
  "properties": {
    "iso:country":"US",
    "sg:address":"6635 N. Baltimore St. Unit #104",
    "sg:city":"Portland",
    "sg:classifiers":[
        {
            "category":"Professional",
            "subcategory":"Art Services",
            "type":"Services"
        }
    ],
    "sg:phone":"+1 503 231 8988",
    "sg:postcode":"97203",
    "sg:province":"OR",
    "sg:tags":[
        "graphic",
        "design"
    ],
    "sg:website":"www.dieselfuelprints.com/store/i...",
    "wof:name":"Diesel Fuel Prints",
    "wof:placetype":"venue"
},
  "geometry": {"coordinates":[-122.761145,45.588618],"type":"Point"}
}