{
  "type": "Feature",
  "properties": {
    "addr:full":"5930 Sunset Ridge Rd Klamath Falls OR 97601",
    "addr:housenumber":"5930",
    "addr:postcode":"97601",
    "addr:street":"Sunset Ridge Rd",
    "iso:country":"US",
    "sg:address":"5930 Sunset Ridge Rd",
    "sg:city":"Klamath Falls",
    "sg:classifiers":[
        {
            "category":"Banks & Credit Unions",
            "subcategory":"Financial Services",
            "type":"Services"
        }
    ],
    "sg:phone":"+1 541 884 4824",
    "sg:postcode":"97601",
    "sg:province":"OR",
    "sg:tags":[
        "investment",
        "closed"
    ],
    "wof:name":"Kapsure Investments LLC",
    "wof:placetype":"venue"
},
  "geometry": {"coordinates":[-121.821495,42.270268],"type":"Point"}
}