{
  "type": "Feature",
  "properties": {
    "addr:full":"90465 Sheffler Rd Elmira OR 97437",
    "addr:postcode":"90465;97437",
    "addr:street":"Sheffler Rd",
    "iso:country":"US",
    "sg:address":"90465 Sheffler Rd",
    "sg:city":"Elmira",
    "sg:classifiers":[
        {
            "category":"Building & Trades",
            "subcategory":"Plumbing",
            "type":"Services"
        }
    ],
    "sg:phone":"+1 541 935 2156",
    "sg:postcode":"97437",
    "sg:province":"OR",
    "sg:tags":[
        "plumber",
        "industrial",
        "contractors-commercial"
    ],
    "wof:name":"S C I Plumbing & Heating",
    "wof:placetype":"venue"
},
  "geometry": {"coordinates":[-123.412166,44.1125],"type":"Point"}
}