{
  "type": "Feature",
  "properties": {
    "addr:full":"2182 SW Yamhill St Portland OR 97205",
    "addr:housenumber":"2182",
    "addr:postcode":"97205",
    "addr:street":"Sw Yamhill St",
    "iso:country":"US",
    "sg:address":"2182 SW Yamhill St",
    "sg:city":"Portland",
    "sg:classifiers":[
        {
            "category":"Real Estate",
            "subcategory":"Real Estate Agent",
            "type":"Services"
        }
    ],
    "sg:phone":"+1 503 223 6881",
    "sg:postcode":"97205",
    "sg:province":"OR",
    "sg:tags":[
        "investment"
    ],
    "wof:name":"Ron Rubin",
    "wof:placetype":"venue"
},
  "geometry": {"coordinates":[-122.696106,45.52248],"type":"Point"}
}