{
  "type": "Feature",
  "properties": {
    "addr:full":"1801 12th St Hood River OR 97031",
    "addr:housenumber":"1801",
    "addr:postcode":"97031",
    "addr:street":"12Th St",
    "iso:country":"US",
    "sg:address":"1801 12th St",
    "sg:city":"Hood River",
    "sg:classifiers":[
        {
            "category":"Shopping",
            "subcategory":"Used Merchandise",
            "type":"Retail Goods"
        }
    ],
    "sg:phone":"+1 541 308 0837",
    "sg:postcode":"97031",
    "sg:province":"OR",
    "sg:tags":[
        "shop",
        "thrift"
    ],
    "wof:name":"Value-Mart",
    "wof:placetype":"venue"
},
  "geometry": {"coordinates":[-121.523534,45.695675],"type":"Point"}
}