{
  "type": "Feature",
  "properties": {
    "iso:country":"US",
    "sg:address":"11135 SW Capitol Hwy",
    "sg:city":"Portland",
    "sg:classifiers":[
        {
            "category":"Education",
            "subcategory":"Special Training",
            "type":"Public Place"
        }
    ],
    "sg:phone":"+1 503 244 0754",
    "sg:postcode":"97219",
    "sg:province":"OR",
    "sg:tags":[
        "center"
    ],
    "wof:name":"Early Opk",
    "wof:placetype":"venue"
},
  "geometry": {"coordinates":[-122.72702099999999,45.444934],"type":"Point"}
}