{
  "type": "Feature",
  "properties": {
    "iso:country":"US",
    "sg:address":"10184 SW Park Way",
    "sg:city":"Portland",
    "sg:classifiers":[
        {
            "category":"Building & Trades",
            "subcategory":"Construction",
            "type":"Services"
        }
    ],
    "sg:phone":"+1 503 526 3887",
    "sg:postcode":"97225",
    "sg:province":"OR",
    "sg:tags":[
        "roofing"
    ],
    "sg:website":"www.raindropnw.com",
    "wof:name":"Raindrop Roofing NW LLC",
    "wof:placetype":"venue"
},
  "geometry": {"coordinates":[-122.78346500000001,45.508991],"type":"Point"}
}