{
  "type": "Feature",
  "properties": {
    "iso:country":"US",
    "sg:address":"3313 Dick George Rd",
    "sg:city":"Cave Junction",
    "sg:classifiers":[
        {
            "category":"Farming",
            "subcategory":"Nursery",
            "type":"Manufacturing & Wholesale Goods"
        }
    ],
    "sg:phone":"+1 541 592 4130",
    "sg:postcode":"97523",
    "sg:province":"OR",
    "sg:tags":[
        "potted",
        "plant",
        "grower"
    ],
    "wof:name":"Siskiyou Greenhouses Inc",
    "wof:placetype":"venue"
},
  "geometry": {"coordinates":[-123.594965,42.093997],"type":"Point"}
}