{
  "type": "Feature",
  "properties": {
    "iso:country":"US",
    "sg:address":"77 NE Morgan St",
    "sg:city":"Portland",
    "sg:classifiers":[
        {
            "category":"Recreation",
            "type":"Entertainment"
        }
    ],
    "sg:phone":"+1 503 240 0631",
    "sg:postcode":"97211",
    "sg:province":"OR",
    "sg:tags":[
        "guide"
    ],
    "sg:website":"www.sturgeonfrank.com",
    "wof:name":"Frank's Guide Svc",
    "wof:placetype":"venue"
},
  "geometry": {"coordinates":[-122.665316,45.574506],"type":"Point"}
}