{
  "type": "Feature",
  "properties": {
    "addr:full":"133 NE 192nd Ave Portland OR 97230",
    "addr:housenumber":"133",
    "addr:postcode":"97230",
    "addr:street":"Ne 192Nd Ave",
    "iso:country":"US",
    "sg:address":"133 NE 192nd Ave",
    "sg:city":"Portland",
    "sg:classifiers":[
        {
            "category":"Place Of Worship",
            "subcategory":"Church",
            "type":"Public Place"
        },
        {
            "category":"Place Of Worship",
            "type":"Public Place"
        },
        {
            "category":"Organizations",
            "subcategory":"Religious Organization",
            "type":"Services"
        }
    ],
    "sg:phone":"+1 503 666 2450",
    "sg:postcode":"97230",
    "sg:province":"OR",
    "sg:tags":[
        "god",
        "churches-church",
        "churches-pentecostal"
    ],
    "wof:name":"Rockwood Church Of God",
    "wof:placetype":"venue"
},
  "geometry": {"coordinates":[-122.465431,45.523713],"type":"Point"}
}