{
  "type": "Feature",
  "properties": {
    "iso:country":"US",
    "sg:address":"19333 SE Division St",
    "sg:city":"Gresham",
    "sg:classifiers":[
        {
            "category":"Manufacturing",
            "subcategory":"Jewelry",
            "type":"Manufacturing & Wholesale Goods"
        },
        {
            "category":"Home & Garden",
            "subcategory":"Building Materials",
            "type":"Retail Goods"
        },
        {
            "category":"Utilities",
            "subcategory":"Natural Gas",
            "type":"Services"
        }
    ],
    "sg:phone":"+1 503 928 4895",
    "sg:postcode":"97030",
    "sg:province":"OR",
    "sg:tags":[
        "stone",
        "product",
        "natural-wholesale",
        "manufacturer"
    ],
    "sg:website":"http://www.stonenw.com",
    "wof:name":"Stone NW, Inc.",
    "wof:placetype":"venue"
},
  "geometry": {"coordinates":[-122.463841,45.504475],"type":"Point"}
}