{
  "type": "Feature",
  "properties": {
    "iso:country":"US",
    "sg:address":"82289 Rattlesnake Rd",
    "sg:city":"Dexter",
    "sg:classifiers":[
        {
            "category":"Social Services",
            "type":"Services"
        }
    ],
    "sg:phone":"+1 541 937 3365",
    "sg:postcode":"97431",
    "sg:province":"OR",
    "sg:tags":[
        "disabled",
        "need",
        "product",
        "special",
        "developmentally"
    ],
    "wof:name":"Newcomer Home",
    "wof:placetype":"venue"
},
  "geometry": {"coordinates":[-122.83088499999999,43.901669],"type":"Point"}
}