{
  "type": "Feature",
  "properties": {
    "iso:country":"US",
    "sg:address":"1017 NE 2nd St",
    "sg:city":"Bend",
    "sg:classifiers":[
        {
            "category":"Building & Trades",
            "subcategory":"Construction",
            "type":"Services"
        }
    ],
    "sg:phone":"+1 541 389 1616",
    "sg:postcode":"97701",
    "sg:province":"OR",
    "sg:tags":[
        "windows"
    ],
    "wof:name":"Advanced Windshield Repair",
    "wof:placetype":"venue"
},
  "geometry": {"coordinates":[-121.30398700000001,44.060796],"type":"Point"}
}