{
  "type": "Feature",
  "properties": {
    "iso:country":"US",
    "sg:address":"4841 NE Mallory Ave",
    "sg:city":"Portland",
    "sg:classifiers":[
        {
            "category":"Building & Trades",
            "subcategory":"Construction",
            "type":"Services"
        }
    ],
    "sg:phone":"+1 503 421 8580",
    "sg:postcode":"97211",
    "sg:province":"OR",
    "sg:tags":[
        "wallcoverings-installation",
        "wallpaper",
        "painting",
        "contractor"
    ],
    "wof:name":"Crew Painting",
    "wof:placetype":"venue"
},
  "geometry": {"coordinates":[-122.663588,45.557957],"type":"Point"}
}