{
  "type": "Feature",
  "properties": {
    "iso:country":"US",
    "sg:address":"17440 SW Cheyenne Way",
    "sg:city":"Tualatin",
    "sg:classifiers":[
        {
            "category":"Wholesale",
            "subcategory":"Medical Equipment & Supplies",
            "type":"Manufacturing & Wholesale Goods"
        }
    ],
    "sg:phone":"+1 503 885 0199",
    "sg:postcode":"97062",
    "sg:province":"OR",
    "wof:name":"Epic Industries",
    "wof:placetype":"venue"
},
  "geometry": {"coordinates":[-122.779065,45.394017],"type":"Point"}
}