{
  "type": "Feature",
  "properties": {
    "iso:country":"US",
    "sg:address":"33145 Gilmore Rd",
    "sg:city":"Scappoose",
    "sg:classifiers":[
        {
            "category":"Building & Trades",
            "subcategory":"Construction",
            "type":"Services"
        }
    ],
    "sg:phone":"+1 503 543 2914",
    "sg:postcode":"97056",
    "sg:province":"OR",
    "sg:tags":[
        "excavating",
        "contractor"
    ],
    "wof:name":"Kessi Construction",
    "wof:placetype":"venue"
},
  "geometry": {"coordinates":[-122.88649700000001,45.771478],"type":"Point"}
}