{
  "type": "Feature",
  "properties": {
    "iso:country":"US",
    "sg:address":"7009 SW Nyberg St",
    "sg:city":"Tualatin",
    "sg:classifiers":[
        {
            "category":"Food & Beverages",
            "subcategory":"Liquor & Beverages",
            "type":"Retail Goods"
        }
    ],
    "sg:phone":"+1 503 691 7777",
    "sg:postcode":"97062",
    "sg:province":"OR",
    "sg:tags":[
        "beer",
        "spirit",
        "wine"
    ],
    "sg:website":"www.winestylesstore.com",
    "wof:name":"Winestyles",
    "wof:placetype":"venue"
},
  "geometry": {"coordinates":[-122.74761599999999,45.382907],"type":"Point"}
}