{
  "type": "Feature",
  "properties": {
    "iso:country":"US",
    "sg:address":"525 Berntzen Rd",
    "sg:city":"Eugene",
    "sg:classifiers":[
        {
            "category":"Wholesale",
            "subcategory":"Vending Machines",
            "type":"Manufacturing & Wholesale Goods"
        }
    ],
    "sg:phone":"+1 541 689 1578",
    "sg:postcode":"97402",
    "sg:province":"OR",
    "sg:tags":[
        "operator"
    ],
    "wof:name":"Ace Family Connection",
    "wof:placetype":"venue"
},
  "geometry": {"coordinates":[-123.157997,44.066503],"type":"Point"}
}