{
  "type": "Feature",
  "properties": {
    "iso:country":"US",
    "sg:address":"990 NW Angeline Ave",
    "sg:city":"Gresham",
    "sg:classifiers":[
        {
            "category":"Building & Trades",
            "subcategory":"Cleaning & Sanitation",
            "type":"Services"
        }
    ],
    "sg:phone":"+1 503 674 7662",
    "sg:postcode":"97030",
    "sg:province":"OR",
    "sg:tags":[
        "maintenance"
    ],
    "wof:name":"All About Clean",
    "wof:placetype":"venue"
},
  "geometry": {"coordinates":[-122.449079,45.501181],"type":"Point"}
}