{
  "type": "Feature",
  "properties": {
    "iso:country":"US",
    "sg:address":"500 NW 6th St",
    "sg:city":"Grants Pass",
    "sg:classifiers":[
        {
            "category":"Government",
            "subcategory":"Office",
            "type":"Public Place"
        }
    ],
    "sg:phone":"+1 541 474 5243",
    "sg:postcode":"97526",
    "sg:province":"OR",
    "sg:tags":[
        "county"
    ],
    "wof:name":"Josephine County Clerk's Ofc",
    "wof:placetype":"venue"
},
  "geometry": {"coordinates":[-123.325257,42.442154],"type":"Point"}
}