{
  "type": "Feature",
  "properties": {
    "iso:country":"US",
    "sg:address":"3637 NE 122nd Avenue",
    "sg:city":"Portland",
    "sg:classifiers":[
        {
            "category":"Real Estate",
            "subcategory":"Real Estate Operator",
            "type":"Services"
        }
    ],
    "sg:phone":"+1 503 256 0993",
    "sg:postcode":"97230",
    "sg:province":"OR",
    "sg:tags":[
        "apartment"
    ],
    "wof:name":"Garden Crest Apts",
    "wof:placetype":"venue"
},
  "geometry": {"coordinates":[-122.53747300000001,45.549065],"type":"Point"}
}