{
  "type": "Feature",
  "properties": {
    "addr:full":"1532 NE Barnes Ln Gresham OR 97030",
    "addr:housenumber":"1532",
    "addr:postcode":"97030",
    "addr:street":"Ne Barnes Ln",
    "iso:country":"US",
    "sg:address":"1532 NE Barnes Ln",
    "sg:city":"Gresham",
    "sg:classifiers":[
        {
            "category":"Building & Trades",
            "subcategory":"Plumbing",
            "type":"Services"
        }
    ],
    "sg:phone":"+1 503 669 6585",
    "sg:postcode":"97030",
    "sg:province":"OR",
    "sg:tags":[
        "contractor"
    ],
    "wof:name":"Home Town Heating & Cooling",
    "wof:placetype":"venue"
},
  "geometry": {"coordinates":[-122.392988,45.509406],"type":"Point"}
}