{
  "type": "Feature",
  "properties": {
    "addr:full":"18385 S Springwater Rd Estacada OR 97023",
    "addr:housenumber":"18385",
    "addr:postcode":"97023",
    "addr:street":"S Springwater Rd",
    "iso:country":"US",
    "sg:address":"18385 S Springwater Rd",
    "sg:city":"Estacada",
    "sg:classifiers":[
        {
            "category":"Wholesale",
            "subcategory":"Auto Parts",
            "type":"Manufacturing & Wholesale Goods"
        }
    ],
    "sg:phone":"+1 503 631 2401",
    "sg:postcode":"97023",
    "sg:province":"OR",
    "wof:name":"Jimbos Nifty Fifties",
    "wof:placetype":"venue"
},
  "geometry": {"coordinates":[-122.411005,45.338267],"type":"Point"}
}