{
  "type": "Feature",
  "properties": {
    "iso:country":"US",
    "sg:address":"17417 SE McLoughlin Boulevard",
    "sg:city":"Portland",
    "sg:classifiers":[
        {
            "category":"Sports & Exercise",
            "subcategory":"Gym",
            "type":"Entertainment"
        }
    ],
    "sg:phone":"+1 503 653 2500",
    "sg:postcode":"97267",
    "sg:province":"OR",
    "sg:website":"www.curves.com",
    "wof:name":"Curves McLoughlin",
    "wof:placetype":"venue"
},
  "geometry": {"coordinates":[-122.616873,45.396646],"type":"Point"}
}