{
  "type": "Feature",
  "properties": {
    "iso:country":"US",
    "sg:address":"16933 65th Ave",
    "sg:city":"Lake Oswego",
    "sg:classifiers":[
        {
            "category":"Food & Beverages",
            "subcategory":"Bakery",
            "type":"Retail Goods"
        }
    ],
    "sg:phone":"+1 503 670 1515",
    "sg:postcode":"97035",
    "sg:province":"OR",
    "sg:tags":[
        "sandwich"
    ],
    "wof:name":"Italiano Subs",
    "wof:placetype":"venue"
},
  "geometry": {"coordinates":[-122.74400300000001,45.390301],"type":"Point"}
}