{
  "type": "Feature",
  "properties": {
    "iso:country":"US",
    "sg:address":"1875 SE Belmont St",
    "sg:city":"Portland",
    "sg:classifiers":[
        {
            "category":"Professional",
            "subcategory":"Art Services",
            "type":"Services"
        }
    ],
    "sg:phone":"+1 503 872 9631",
    "sg:postcode":"97214",
    "sg:province":"OR",
    "sg:tags":[
        "graphic",
        "designer"
    ],
    "sg:website":"www.nemodesign.com",
    "wof:name":"Nemo Design",
    "wof:placetype":"venue"
},
  "geometry": {"coordinates":[-122.64706,45.516544],"type":"Point"}
}