{
  "type": "Feature",
  "properties": {
    "iso:country":"US",
    "sg:address":"6310 SW 176th Pl",
    "sg:city":"Beaverton",
    "sg:classifiers":[
        {
            "category":"Building & Trades",
            "subcategory":"Construction",
            "type":"Services"
        }
    ],
    "sg:phone":"+1 503 642 9454",
    "sg:postcode":"97007",
    "sg:province":"OR",
    "sg:tags":[
        "contractor"
    ],
    "wof:name":"Wagner Verlin",
    "wof:placetype":"venue"
},
  "geometry": {"coordinates":[-122.858164,45.474012],"type":"Point"}
}