{
  "type": "Feature",
  "properties": {
    "addr:full":"6234 N Greeley Ave Portland OR 97217",
    "addr:housenumber":"6234",
    "addr:postcode":"97217",
    "addr:street":"N Greeley Ave",
    "iso:country":"US",
    "sg:address":"6234 N Greeley Ave",
    "sg:city":"Portland",
    "sg:classifiers":[
        {
            "category":"Banks & Credit Unions",
            "subcategory":"Bank",
            "type":"Services"
        }
    ],
    "sg:phone":"+1 503 289 5626",
    "sg:postcode":"97217",
    "sg:province":"OR",
    "sg:tags":[
        "mortgage"
    ],
    "wof:name":"Discover Mortage",
    "wof:placetype":"venue"
},
  "geometry": {"coordinates":[-122.695498,45.566761],"type":"Point"}
}