{
  "type": "Feature",
  "properties": {
    "iso:country":"US",
    "sg:address":"25156 Kyle Rd",
    "sg:city":"Monroe",
    "sg:classifiers":[
        {
            "category":"Farming",
            "subcategory":"Vineyard",
            "type":"Manufacturing & Wholesale Goods"
        }
    ],
    "sg:phone":"+1 541 847 5795",
    "sg:postcode":"97456",
    "sg:province":"OR",
    "sg:tags":[
        "grape"
    ],
    "wof:name":"Lush Vineyards",
    "wof:placetype":"venue"
},
  "geometry": {"coordinates":[-123.325157,44.311071],"type":"Point"}
}