{
  "type": "Feature",
  "properties": {
    "addr:full":"4545 NE 125th Pl Portland OR 97230",
    "addr:housenumber":"4545",
    "addr:postcode":"97230",
    "addr:street":"Ne 125Th Pl",
    "iso:country":"US",
    "sg:address":"4545 NE 125th Pl",
    "sg:city":"Portland",
    "sg:classifiers":[
        {
            "category":"Real Estate",
            "subcategory":"Real Estate Operator",
            "type":"Services"
        }
    ],
    "sg:phone":"+1 503 253 1097",
    "sg:postcode":"97230",
    "sg:province":"OR",
    "sg:tags":[
        "apartment"
    ],
    "wof:name":"Willow Springs Apts",
    "wof:placetype":"venue"
},
  "geometry": {"coordinates":[-122.53371799999999,45.553586],"type":"Point"}
}