{
  "type": "Feature",
  "properties": {
    "addr:full":"690 N 5th Street Jacksonville OR 97530",
    "addr:housenumber":"690",
    "addr:postcode":"97530",
    "addr:street":"N 5Th Street",
    "iso:country":"US",
    "sg:address":"690 N 5th Street",
    "sg:city":"Jacksonville",
    "sg:classifiers":[
        {
            "category":"Food & Beverages",
            "subcategory":"Liquor & Beverages",
            "type":"Retail Goods"
        },
        {
            "category":"Food & Beverages",
            "subcategory":"Meat & Fish",
            "type":"Retail Goods"
        }
    ],
    "sg:phone":"+1 541 899 1829",
    "sg:postcode":"97530",
    "sg:province":"OR",
    "sg:tags":[
        "shop",
        "beer",
        "spirit",
        "wine"
    ],
    "sg:website":"www.garywest.com/",
    "wof:name":"Gary West Meats",
    "wof:placetype":"venue"
},
  "geometry": {"coordinates":[-122.96119400000001,42.31794],"type":"Point"}
}