{
  "type": "Feature",
  "properties": {
    "iso:country":"US",
    "sg:address":"2707 Broadway St",
    "sg:city":"North Bend",
    "sg:classifiers":[
        {
            "category":"Freight",
            "type":"Transportation"
        },
        {
            "category":"Real Estate",
            "subcategory":"Real Estate Agent",
            "type":"Services"
        }
    ],
    "sg:phone":"+1 541 756 0347",
    "sg:postcode":"97459",
    "sg:province":"OR",
    "sg:tags":[
        "management",
        "special"
    ],
    "wof:name":"E L Edwards Realty Inc",
    "wof:placetype":"venue"
},
  "geometry": {"coordinates":[-124.239187,43.396953],"type":"Point"}
}