{
  "type": "Feature",
  "properties": {
    "iso:country":"US",
    "sg:address":"1050 SW 3rd Ave",
    "sg:city":"Ontario",
    "sg:classifiers":[
        {
            "category":"Health Services",
            "subcategory":"Podiatrist",
            "type":"Services"
        }
    ],
    "sg:phone":"+1 541 881 1319",
    "sg:postcode":"97914",
    "sg:province":"OR",
    "wof:name":"Foot & Ankle Clinic",
    "wof:placetype":"venue"
},
  "geometry": {"coordinates":[-116.976745,44.02575],"type":"Point"}
}