{
  "type": "Feature",
  "properties": {
    "iso:country":"US",
    "sg:address":"4910 SE 62nd Ave",
    "sg:city":"Portland",
    "sg:classifiers":[
        {
            "category":"Museum",
            "type":"Entertainment"
        }
    ],
    "sg:phone":"+1 503 927 1240",
    "sg:postcode":"97206",
    "sg:province":"OR",
    "wof:name":"Planes Of Reference Corp",
    "wof:placetype":"venue"
},
  "geometry": {"coordinates":[-122.59901499999999,45.487163],"type":"Point"}
}