{
  "type": "Feature",
  "properties": {
    "iso:country":"US",
    "sg:address":"1100 NW Glisan St",
    "sg:city":"Portland",
    "sg:classifiers":[
        {
            "category":"Shopping",
            "subcategory":"Clothing, Apparel, & Fashions",
            "type":"Retail Goods"
        }
    ],
    "sg:phone":"+1 503 228 7313",
    "sg:postcode":"97209",
    "sg:province":"OR",
    "wof:name":"Aubergine",
    "wof:placetype":"venue"
},
  "geometry": {"coordinates":[-122.683229,45.526505],"type":"Point"}
}