{
  "type": "Feature",
  "properties": {
    "iso:country":"US",
    "sg:address":"2344 NE 23rd Ave",
    "sg:city":"Portland",
    "sg:classifiers":[
        {
            "category":"Professional",
            "subcategory":"Business Services",
            "type":"Services"
        },
        {
            "category":"Wholesale",
            "subcategory":"Books, Periodicals, & Newspapers",
            "type":"Manufacturing & Wholesale Goods"
        }
    ],
    "sg:phone":"+1 503 249 0842",
    "sg:postcode":"97212",
    "sg:province":"OR",
    "sg:tags":[
        "consultant",
        "publishing",
        "representative",
        "publisher"
    ],
    "wof:name":"Enigma Services",
    "wof:placetype":"venue"
},
  "geometry": {"coordinates":[-122.642189,45.539302],"type":"Point"}
}