{
  "type": "Feature",
  "properties": {
    "iso:country":"US",
    "sg:address":"1005 NW Locust Ave",
    "sg:city":"Prineville",
    "sg:classifiers":[
        {
            "category":"Manufacturing",
            "subcategory":"Wood Products",
            "type":"Manufacturing & Wholesale Goods"
        }
    ],
    "sg:phone":"+1 541 447 8196",
    "sg:postcode":"97754",
    "sg:province":"OR",
    "sg:tags":[
        "tree"
    ],
    "wof:name":"Accurate Contracting",
    "wof:placetype":"venue"
},
  "geometry": {"coordinates":[-120.85712100000001,44.308518],"type":"Point"}
}