{
  "type": "Feature",
  "properties": {
    "iso:country":"US",
    "sg:address":"2976 Little Valley Rd",
    "sg:city":"Harper",
    "sg:classifiers":[
        {
            "category":"Retail",
            "subcategory":"Animal Services",
            "type":"Services"
        }
    ],
    "sg:phone":"+1 541 358 2250",
    "sg:postcode":"97906",
    "sg:province":"OR",
    "sg:website":"www.bobbyusher.com",
    "wof:name":"Usher Training Stables",
    "wof:placetype":"venue"
},
  "geometry": {"coordinates":[-117.506647,43.898098],"type":"Point"}
}