{
  "type": "Feature",
  "properties": {
    "iso:country":"US",
    "sg:address":"33225 Craig Loop",
    "sg:city":"Cottage Grove",
    "sg:classifiers":[
        {
            "category":"Professional",
            "type":"Services"
        }
    ],
    "sg:phone":"+1 541 726 5671",
    "sg:postcode":"97424",
    "sg:province":"OR",
    "wof:name":"Cedarvall Foundation",
    "wof:placetype":"venue"
},
  "geometry": {"coordinates":[-123.021076,43.813224],"type":"Point"}
}