{
  "type": "Feature",
  "properties": {
    "addr:full":"5306 N Maryland Ave Portland OR 97217",
    "addr:housenumber":"5306",
    "addr:postcode":"97217",
    "addr:street":"N Maryland Ave",
    "iso:country":"US",
    "sg:address":"5306 N Maryland Ave",
    "sg:city":"Portland",
    "sg:classifiers":[
        {
            "category":"Retail",
            "subcategory":"Animal Services",
            "type":"Services"
        }
    ],
    "sg:phone":"+1 503 465 6819",
    "sg:postcode":"97217",
    "sg:province":"OR",
    "wof:name":"Country Kanine Daykare",
    "wof:placetype":"venue"
},
  "geometry": {"coordinates":[-122.681048,45.562659],"type":"Point"}
}