{
  "type": "Feature",
  "properties": {
    "addr:full":"15405 SW 116th Ave Portland OR 97224",
    "addr:housenumber":"15405",
    "addr:postcode":"97224",
    "addr:street":"Sw 116Th Ave",
    "iso:country":"US",
    "sg:address":"15405 SW 116th Ave",
    "sg:city":"Portland",
    "sg:classifiers":[
        {
            "category":"Banks & Credit Unions",
            "subcategory":"Investment Brokerage",
            "type":"Services"
        },
        {
            "category":"Professional",
            "subcategory":"Management & Consulting",
            "type":"Services"
        }
    ],
    "sg:phone":"+1 503 620 3531",
    "sg:postcode":"97224",
    "sg:province":"OR",
    "sg:tags":[
        "advisory",
        "financial"
    ],
    "wof:name":"Garry F Liday Corporation",
    "wof:placetype":"venue"
},
  "geometry": {"coordinates":[-122.797369,45.405699],"type":"Point"}
}