{
  "type": "Feature",
  "properties": {
    "iso:country":"US",
    "sg:address":"51636 Huntington Rd",
    "sg:city":"La Pine",
    "sg:classifiers":[
        {
            "category":"Insurance",
            "subcategory":"Insurance Agent",
            "type":"Services"
        }
    ],
    "sg:phone":"+1 541 536 3655",
    "sg:postcode":"97739",
    "sg:province":"OR",
    "wof:name":"Farmers Insurance Group",
    "wof:placetype":"venue"
},
  "geometry": {"coordinates":[-121.50402800000001,43.67539],"type":"Point"}
}