{
  "type": "Feature",
  "properties": {
    "iso:country":"US",
    "sg:address":"17175 SW Tualatin Valley Hwy",
    "sg:city":"Beaverton",
    "sg:classifiers":[
        {
            "category":"Health Services",
            "subcategory":"Doctor",
            "type":"Services"
        }
    ],
    "sg:phone":"+1 503 356 5646",
    "sg:postcode":"97006",
    "sg:province":"OR",
    "sg:tags":[
        "physician",
        "surgeon"
    ],
    "wof:name":"Medical Clinic At Tanasbourne",
    "wof:placetype":"venue"
},
  "geometry": {"coordinates":[-122.855147,45.49266],"type":"Point"}
}