{
  "type": "Feature",
  "properties": {
    "addr:full":"6196 Sunnyside Rd SE Salem OR 97306",
    "addr:housenumber":"6196",
    "addr:postcode":"97306",
    "addr:street":"Sunnyside Rd Se",
    "iso:country":"US",
    "sg:address":"6196 Sunnyside Rd SE",
    "sg:city":"Salem",
    "sg:classifiers":[
        {
            "category":"Organizations",
            "subcategory":"Religious Organization",
            "type":"Services"
        }
    ],
    "sg:phone":"+1 503 364 7877",
    "sg:postcode":"97306",
    "sg:province":"OR",
    "wof:name":"Rolling Hills",
    "wof:placetype":"venue"
},
  "geometry": {"coordinates":[-123.033811,44.865033],"type":"Point"}
}