{
  "type": "Feature",
  "properties": {
    "iso:country":"US",
    "sg:address":"5833 SW Macadam Ave",
    "sg:city":"Portland",
    "sg:classifiers":[
        {
            "category":"Restaurant",
            "type":"Food & Drink"
        }
    ],
    "sg:phone":"+1 503 246 6227",
    "sg:postcode":"97239",
    "sg:province":"OR",
    "sg:tags":[
        "traditional",
        "american"
    ],
    "sg:website":"www.macadamsbarandgrill.com",
    "wof:name":"Macadam's Bar and Grill",
    "wof:placetype":"venue"
},
  "geometry": {"coordinates":[-122.673619,45.481568],"type":"Point"}
}