{
  "type": "Feature",
  "properties": {
    "addr:full":"4547 SW 96th Ave Ste B Beaverton OR 97005",
    "addr:housenumber":"4547",
    "addr:postcode":"97005",
    "addr:street":"Sw 96Th Ave Ste B",
    "iso:country":"US",
    "sg:address":"4547 SW 96th Ave Ste B",
    "sg:city":"Beaverton",
    "sg:classifiers":[
        {
            "category":"Professional",
            "subcategory":"Lawyer & Legal Services",
            "type":"Services"
        }
    ],
    "sg:phone":"+1 503 644 8686",
    "sg:postcode":"97005",
    "sg:province":"OR",
    "sg:tags":[
        "attorney",
        "accident",
        "personal",
        "worker",
        "damage",
        "labor",
        "benefit",
        "employee",
        "injury",
        "property",
        "employment",
        "compensation",
        "law"
    ],
    "sg:website":"www.hootonwoldokrent.com",
    "wof:name":"Hooton Wold & Okrent Llp",
    "wof:placetype":"venue"
},
  "geometry": {"coordinates":[-122.77600099999999,45.487202],"type":"Point"}
}