{
  "type": "Feature",
  "properties": {
    "iso:country":"US",
    "sg:address":"975 Oak St",
    "sg:city":"Eugene",
    "sg:classifiers":[
        {
            "category":"Insurance",
            "subcategory":"Insurance Agent",
            "type":"Services"
        }
    ],
    "sg:phone":"+1 541 687 2222",
    "sg:postcode":"97401",
    "sg:province":"OR",
    "wof:name":"Willis Of Oregon Inc",
    "wof:placetype":"venue"
},
  "geometry": {"coordinates":[-123.091137,44.04909],"type":"Point"}
}