{
  "type": "Feature",
  "properties": {
    "addr:full":"2022 SE 42nd Ave Portland OR 97215",
    "addr:housenumber":"2022",
    "addr:postcode":"97215",
    "addr:street":"Se 42Nd Ave",
    "iso:country":"US",
    "sg:address":"2022 SE 42nd Ave",
    "sg:city":"Portland",
    "sg:classifiers":[
        {
            "category":"Shopping",
            "subcategory":"Clothing, Apparel, & Fashions",
            "type":"Retail Goods"
        }
    ],
    "sg:phone":"+1 503 233 6562",
    "sg:postcode":"97215",
    "sg:province":"OR",
    "wof:name":"Jasmine Patten",
    "wof:placetype":"venue"
},
  "geometry": {"coordinates":[-122.61900300000001,45.508192],"type":"Point"}
}