{
  "type": "Feature",
  "properties": {
    "addr:full":"2650 Chuckanut St Eugene OR 97408",
    "addr:housenumber":"2650",
    "addr:postcode":"97408",
    "addr:street":"Chuckanut St",
    "iso:country":"US",
    "sg:address":"2650 Chuckanut St",
    "sg:city":"Eugene",
    "sg:classifiers":[
        {
            "category":"Shopping",
            "subcategory":"Stationery & Office Supplies",
            "type":"Retail Goods"
        }
    ],
    "sg:phone":"+1 541 345 4226",
    "sg:postcode":"97408",
    "sg:province":"OR",
    "sg:tags":[
        "rubber",
        "stamp",
        "plastic"
    ],
    "sg:website":"www.craftsmanstamps.com",
    "wof:name":"Craftsman Rubber Stamps",
    "wof:placetype":"venue"
},
  "geometry": {"coordinates":[-123.07314599999999,44.092077],"type":"Point"}
}