{
  "type": "Feature",
  "properties": {
    "iso:country":"US",
    "sg:address":"815 Dorris St",
    "sg:city":"Eugene",
    "sg:classifiers":[
        {
            "category":"Building & Trades",
            "subcategory":"Construction",
            "type":"Services"
        }
    ],
    "sg:phone":"+1 541 689 5189",
    "sg:postcode":"97404",
    "sg:province":"OR",
    "sg:tags":[
        "painting",
        "contractor"
    ],
    "wof:name":"Siegel Painting",
    "wof:placetype":"venue"
},
  "geometry": {"coordinates":[-123.120752,44.074095],"type":"Point"}
}