{
  "type": "Feature",
  "properties": {
    "iso:country":"US",
    "sg:address":"19929 SW Stokesay Ln",
    "sg:city":"Beaverton",
    "sg:classifiers":[
        {
            "category":"Travel",
            "subcategory":"Travel Agent",
            "type":"Entertainment"
        }
    ],
    "sg:phone":"+1 503 848 2870",
    "sg:postcode":"97007",
    "sg:province":"OR",
    "sg:tags":[
        "agency",
        "bureau"
    ],
    "wof:name":"Gordon Tour & Travel",
    "wof:placetype":"venue"
},
  "geometry": {"coordinates":[-122.882255,45.487973],"type":"Point"}
}