{
  "type": "Feature",
  "properties": {
    "iso:country":"US",
    "sg:address":"2105 Auburn St",
    "sg:city":"Klamath Falls",
    "sg:classifiers":[
        {
            "category":"Professional",
            "subcategory":"Computer Services",
            "type":"Services"
        }
    ],
    "sg:phone":"+1 541 884 1980",
    "sg:postcode":"97601",
    "sg:province":"OR",
    "sg:tags":[
        "training"
    ],
    "wof:name":"Technomethods",
    "wof:placetype":"venue"
},
  "geometry": {"coordinates":[-121.76816100000001,42.233277],"type":"Point"}
}