{
  "type": "Feature",
  "properties": {
    "addr:full":"345 NE Greenwood Ave Bend OR 97701",
    "addr:housenumber":"345",
    "addr:postcode":"97701",
    "addr:street":"Ne Greenwood Ave",
    "iso:country":"US",
    "sg:address":"345 NE Greenwood Ave",
    "sg:city":"Bend",
    "sg:classifiers":[
        {
            "category":"Real Estate",
            "subcategory":"Real Estate Agent",
            "type":"Services"
        }
    ],
    "sg:phone":"+1 541 383 3227",
    "sg:postcode":"97701",
    "sg:province":"OR",
    "wof:name":"Keith Clinton PC",
    "wof:placetype":"venue"
},
  "geometry": {"coordinates":[-121.30182000000001,44.059865],"type":"Point"}
}