{
  "type": "Feature",
  "properties": {
    "addr:full":"1075 Market St NE Salem OR 97301",
    "addr:housenumber":"1075",
    "addr:postcode":"97301",
    "addr:street":"Market St Ne",
    "iso:country":"US",
    "sg:address":"1075 Market St NE",
    "sg:city":"Salem",
    "sg:classifiers":[
        {
            "category":"Professional",
            "type":"Services"
        }
    ],
    "sg:phone":"+1 503 587 9699",
    "sg:postcode":"97301",
    "sg:province":"OR",
    "wof:name":"Missing Pieces",
    "wof:placetype":"venue"
},
  "geometry": {"coordinates":[-123.022673,44.949122],"type":"Point"}
}