{
  "type": "Feature",
  "properties": {
    "iso:country":"US",
    "sg:address":"9918 Yank Gulch Rd",
    "sg:city":"Talent",
    "sg:classifiers":[
        {
            "category":"Shopping",
            "subcategory":"Books",
            "type":"Retail Goods"
        }
    ],
    "sg:phone":"+1 541 512 9000",
    "sg:postcode":"97540",
    "sg:province":"OR",
    "sg:tags":[
        "dealer"
    ],
    "wof:name":"Robert Gavora Fine & Rare Book",
    "wof:placetype":"venue"
},
  "geometry": {"coordinates":[-122.812628,42.19936],"type":"Point"}
}