{
  "type": "Feature",
  "properties": {
    "iso:country":"US",
    "sg:address":"15810 SE Main St",
    "sg:city":"Portland",
    "sg:classifiers":[
        {
            "category":"Manufacturing",
            "subcategory":"Toys & Sporting Goods",
            "type":"Manufacturing & Wholesale Goods"
        }
    ],
    "sg:phone":"+1 503 252 9036",
    "sg:postcode":"97233",
    "sg:province":"OR",
    "sg:tags":[
        "mfg"
    ],
    "wof:name":"Holladay & Son Wire Produ",
    "wof:placetype":"venue"
},
  "geometry": {"coordinates":[-122.499698,45.51373],"type":"Point"}
}