{
  "type": "Feature",
  "properties": {
    "iso:country":"US",
    "sg:address":"253 Scravel Hill Rd SE",
    "sg:city":"Albany",
    "sg:classifiers":[
        {
            "category":"Recreation",
            "type":"Entertainment"
        }
    ],
    "sg:phone":"+1 541 926 8289",
    "sg:postcode":"97322",
    "sg:province":"OR",
    "sg:tags":[
        "club",
        "membership"
    ],
    "wof:name":"Propst Air Service",
    "wof:placetype":"venue"
},
  "geometry": {"coordinates":[-123.029042,44.638153],"type":"Point"}
}