{
  "type": "Feature",
  "properties": {
    "iso:country":"US",
    "sg:address":"1417 12th St",
    "sg:city":"Oregon City",
    "sg:classifiers":[
        {
            "category":"Education",
            "subcategory":"School",
            "type":"Public Place"
        }
    ],
    "sg:phone":"+1 503 656 4283",
    "sg:postcode":"97045",
    "sg:province":"OR",
    "wof:name":"Oregon City School District 62",
    "wof:placetype":"venue"
},
  "geometry": {"coordinates":[-122.59377499999999,45.356181],"type":"Point"}
}