{
  "type": "Feature",
  "properties": {
    "iso:country":"US",
    "sg:address":"961 Terrace Dr",
    "sg:city":"Lake Oswego",
    "sg:classifiers":[
        {
            "category":"Professional",
            "subcategory":"Management & Consulting",
            "type":"Services"
        }
    ],
    "sg:phone":"+1 503 691 8900",
    "sg:postcode":"97034",
    "sg:province":"OR",
    "sg:tags":[
        "consultant"
    ],
    "wof:name":"G H Goldstick and Co Inc",
    "wof:placetype":"venue"
},
  "geometry": {"coordinates":[-122.688712,45.40881],"type":"Point"}
}