{
  "type": "Feature",
  "properties": {
    "iso:country":"US",
    "sg:address":"534 SW 3rd Ave Ste 612",
    "sg:city":"Portland",
    "sg:classifiers":[
        {
            "category":"Shopping",
            "subcategory":"Jewelry",
            "type":"Retail Goods"
        },
        {
            "category":"Shopping",
            "subcategory":"Discount & Variety Stores",
            "type":"Retail Goods"
        }
    ],
    "sg:phone":"+1 503 248 9118",
    "sg:postcode":"97204",
    "sg:province":"OR",
    "sg:tags":[
        "wholesale"
    ],
    "sg:website":"telavivdiamond.com",
    "wof:name":"Tel Aviv Diamond & Jewelry Company",
    "wof:placetype":"venue"
},
  "geometry": {"coordinates":[-122.674772,45.518979],"type":"Point"}
}