{
  "type": "Feature",
  "properties": {
    "addr:full":"13211 SE Briggs St Portland OR 97222",
    "addr:housenumber":"13211",
    "addr:postcode":"97222",
    "addr:street":"Se Briggs St",
    "iso:country":"US",
    "sg:address":"13211 SE Briggs St",
    "sg:city":"Portland",
    "sg:classifiers":[
        {
            "category":"Utilities",
            "subcategory":"Water",
            "type":"Services"
        }
    ],
    "sg:phone":"+1 503 659 1127",
    "sg:postcode":"97222",
    "sg:province":"OR",
    "sg:tags":[
        "bulk",
        "companies-bottled"
    ],
    "wof:name":"Cup Of Water Ijn",
    "wof:placetype":"venue"
},
  "geometry": {"coordinates":[-122.628287,45.427296],"type":"Point"}
}