{
  "type": "Feature",
  "properties": {
    "addr:full":"550 SE Clay St Dallas OR 97338",
    "addr:housenumber":"550",
    "addr:postcode":"97338",
    "addr:street":"Se Clay St",
    "iso:country":"US",
    "sg:address":"550 SE Clay St",
    "sg:city":"Dallas",
    "sg:classifiers":[
        {
            "category":"Health Services",
            "subcategory":"Doctor",
            "type":"Services"
        }
    ],
    "sg:phone":"+1 503 623 7344",
    "sg:postcode":"97338",
    "sg:province":"OR",
    "sg:tags":[
        "physician",
        "surgeon"
    ],
    "wof:name":"Gina P Remington MD",
    "wof:placetype":"venue"
},
  "geometry": {"coordinates":[-123.31031400000001,44.918468],"type":"Point"}
}