{
  "type": "Feature",
  "properties": {
    "iso:country":"US",
    "sg:address":"19555 Tumalo Reservoir Rd",
    "sg:city":"Bend",
    "sg:classifiers":[
        {
            "category":"Building & Trades",
            "subcategory":"Electrical",
            "type":"Services"
        }
    ],
    "sg:phone":"+1 541 385 0603",
    "sg:postcode":"97701",
    "sg:province":"OR",
    "sg:tags":[
        "electrical",
        "electric",
        "contractor"
    ],
    "wof:name":"Cascade Electric Svc Inc",
    "wof:placetype":"venue"
},
  "geometry": {"coordinates":[-121.350812,44.138157],"type":"Point"}
}