{
  "type": "Feature",
  "properties": {
    "iso:country":"US",
    "sg:address":"555 Foss Rd",
    "sg:city":"Talent",
    "sg:classifiers":[
        {
            "category":"Building & Trades",
            "subcategory":"Construction",
            "type":"Services"
        }
    ],
    "sg:phone":"+1 541 535 6565",
    "sg:postcode":"97540",
    "sg:province":"OR",
    "sg:tags":[
        "backhoe",
        "operator",
        "excavation"
    ],
    "wof:name":"Light Touch Excavation",
    "wof:placetype":"venue"
},
  "geometry": {"coordinates":[-122.79576400000001,42.240954],"type":"Point"}
}