{
  "type": "Feature",
  "properties": {
    "iso:country":"US",
    "sg:address":"14855 S Leland Rd",
    "sg:city":"Beavercreek",
    "sg:classifiers":[
        {
            "category":"Organizations",
            "subcategory":"Religious Organization",
            "type":"Services"
        }
    ],
    "sg:phone":"+1 503 632 8100",
    "sg:postcode":"97004",
    "sg:province":"OR",
    "sg:tags":[
        "church"
    ],
    "sg:website":"www.gvbc.com",
    "wof:name":"Grand View Baptist Church",
    "wof:placetype":"venue"
},
  "geometry": {"coordinates":[-122.560641,45.289607],"type":"Point"}
}