{
  "type": "Feature",
  "properties": {
    "iso:country":"US",
    "sg:address":"1844 W Harvard Ave",
    "sg:city":"Roseburg",
    "sg:classifiers":[
        {
            "category":"Health Services",
            "subcategory":"Chiropractor",
            "type":"Services"
        }
    ],
    "sg:phone":"+1 541 672 8831",
    "sg:postcode":"97470",
    "sg:province":"OR",
    "wof:name":"Kaul Family Chiropractic",
    "wof:placetype":"venue"
},
  "geometry": {"coordinates":[-123.370333,43.213697],"type":"Point"}
}