{
  "type": "Feature",
  "properties": {
    "iso:country":"US",
    "sg:address":"17627 SE McLoughlin Boulevard",
    "sg:city":"Portland",
    "sg:classifiers":[
        {
            "category":"Autos & Motor Vehicles",
            "subcategory":"Auto Supplies",
            "type":"Retail Goods"
        },
        {
            "category":"Retail",
            "subcategory":"Auto Repair",
            "type":"Services"
        }
    ],
    "sg:phone":"+1 503 655 9392",
    "sg:postcode":"97267",
    "sg:province":"OR",
    "sg:tags":[
        "transmission",
        "transmissions-other"
    ],
    "wof:name":"Oc Transmission",
    "wof:placetype":"venue"
},
  "geometry": {"coordinates":[-122.616159,45.395474],"type":"Point"}
}