{
  "type": "Feature",
  "properties": {
    "addr:full":"16205 SW Dove Rd Terrebonne OR 97760",
    "addr:housenumber":"16205",
    "addr:postcode":"97760",
    "addr:street":"Sw Dove Rd",
    "iso:country":"US",
    "sg:address":"16205 SW Dove Rd",
    "sg:city":"Terrebonne",
    "sg:classifiers":[
        {
            "category":"Wholesale",
            "subcategory":"Durable Goods & Equipment",
            "type":"Manufacturing & Wholesale Goods"
        }
    ],
    "sg:phone":"+1 541 923 2324",
    "sg:postcode":"97760",
    "sg:province":"OR",
    "sg:tags":[
        "representative",
        "manufacturer"
    ],
    "wof:name":"Indoff Inc",
    "wof:placetype":"venue"
},
  "geometry": {"coordinates":[-121.28232300000001,44.404405],"type":"Point"}
}