{
  "type": "Feature",
  "properties": {
    "iso:country":"US",
    "sg:address":"20040 NW Nestucca Dr",
    "sg:city":"Portland",
    "sg:classifiers":[
        {
            "category":"Professional",
            "type":"Services"
        }
    ],
    "sg:phone":"+1 503 645 7395",
    "sg:postcode":"97229",
    "sg:province":"OR",
    "wof:name":"Kenbe LLC",
    "wof:placetype":"venue"
},
  "geometry": {"coordinates":[-122.882915,45.554525],"type":"Point"}
}