{
  "type": "Feature",
  "properties": {
    "iso:country":"US",
    "sg:address":"6945 Wheatland Rd N",
    "sg:city":"Salem",
    "sg:classifiers":[
        {
            "category":"Social Services",
            "subcategory":"Child Care",
            "type":"Services"
        }
    ],
    "sg:phone":"+1 503 393 6843",
    "sg:postcode":"97303",
    "sg:province":"OR",
    "sg:tags":[
        "day"
    ],
    "wof:name":"Keizer Christian Church",
    "wof:placetype":"venue"
},
  "geometry": {"coordinates":[-123.02491999999999,45.01982],"type":"Point"}
}