{
  "type": "Feature",
  "properties": {
    "iso:country":"US",
    "sg:address":"550 Capitol St NE",
    "sg:city":"Salem",
    "sg:classifiers":[
        {
            "category":"Government",
            "subcategory":"Office",
            "type":"Public Place"
        }
    ],
    "sg:phone":"+1 503 378 5849",
    "sg:postcode":"97301",
    "sg:province":"OR",
    "sg:tags":[
        "government-state",
        "government-united",
        "state"
    ],
    "wof:name":"State of Oregon Motor Carrier Transportation Division",
    "wof:placetype":"venue"
},
  "geometry": {"coordinates":[-123.026574,44.942464],"type":"Point"}
}