{
  "type": "Feature",
  "properties": {
    "addr:full":"32578 Scappoose Vernonia Hwy Scappoose OR 97056",
    "addr:postcode":"32578;97056",
    "addr:street":"Vernonia Hwy",
    "iso:country":"US",
    "sg:address":"32578 Scappoose Vernonia Hwy",
    "sg:city":"Scappoose",
    "sg:classifiers":[
        {
            "category":"Real Estate",
            "subcategory":"Real Estate Agent",
            "type":"Services"
        }
    ],
    "sg:phone":"+1 503 543 5997",
    "sg:postcode":"97056",
    "sg:province":"OR",
    "wof:name":"New Dimensions RE Netwrk",
    "wof:placetype":"venue"
},
  "geometry": {"coordinates":[-122.897046,45.776729],"type":"Point"}
}