{
  "type": "Feature",
  "properties": {
    "iso:country":"US",
    "sg:address":"3593 Silverton Rd NE",
    "sg:city":"Salem",
    "sg:classifiers":[
        {
            "category":"Shopping",
            "type":"Retail Goods"
        }
    ],
    "sg:phone":"+1 503 385 8111",
    "sg:postcode":"97305",
    "sg:province":"OR",
    "sg:tags":[
        "item",
        "boutique"
    ],
    "wof:name":"Eve's Boutique",
    "wof:placetype":"venue"
},
  "geometry": {"coordinates":[-122.98863900000001,44.968514],"type":"Point"}
}