{
  "type": "Feature",
  "properties": {
    "addr:full":"2367 NW 141st Pl Portland OR 97229",
    "addr:housenumber":"2367",
    "addr:postcode":"97229",
    "addr:street":"Nw 141St Pl",
    "iso:country":"US",
    "sg:address":"2367 NW 141st Pl",
    "sg:city":"Portland",
    "sg:classifiers":[
        {
            "category":"Building & Trades",
            "subcategory":"Construction",
            "type":"Services"
        }
    ],
    "sg:phone":"+1 503 629 0473",
    "sg:postcode":"97229",
    "sg:province":"OR",
    "sg:tags":[
        "home",
        "builder"
    ],
    "wof:name":"Executive Specialty Homes",
    "wof:placetype":"venue"
},
  "geometry": {"coordinates":[-122.82267400000001,45.536816],"type":"Point"}
}