{
  "type": "Feature",
  "properties": {
    "iso:country":"US",
    "sg:address":"38755 Reed Rd",
    "sg:city":"Nehalem",
    "sg:classifiers":[
        {
            "category":"Real Estate",
            "subcategory":"Architect",
            "type":"Services"
        }
    ],
    "sg:phone":"+1 503 368 6294",
    "sg:postcode":"97131",
    "sg:province":"OR",
    "sg:tags":[
        "architectural"
    ],
    "wof:name":"Tom Bender",
    "wof:placetype":"venue"
},
  "geometry": {"coordinates":[-123.950607,45.738735],"type":"Point"}
}