{
  "type": "Feature",
  "properties": {
    "addr:full":"7812 SE Reedway St Portland OR 97206",
    "addr:housenumber":"7812",
    "addr:postcode":"97206",
    "addr:street":"Se Reedway St",
    "iso:country":"US",
    "sg:address":"7812 SE Reedway St",
    "sg:city":"Portland",
    "sg:classifiers":[
        {
            "category":"Building & Trades",
            "subcategory":"Locksmith",
            "type":"Services"
        }
    ],
    "sg:phone":"+1 503 821 0898",
    "sg:postcode":"97206",
    "sg:province":"OR",
    "sg:tags":[
        "key"
    ],
    "wof:name":"Abbe Locks 24 Locksmith",
    "wof:placetype":"venue"
},
  "geometry": {"coordinates":[-122.58314799999999,45.481543],"type":"Point"}
}