{
  "type": "Feature",
  "properties": {
    "iso:country":"US",
    "sg:address":"740 E Scenic Dr",
    "sg:city":"The Dalles",
    "sg:classifiers":[
        {
            "category":"Personal",
            "subcategory":"Beauty Salon",
            "type":"Services"
        }
    ],
    "sg:phone":"+1 541 298 4374",
    "sg:postcode":"97058",
    "sg:province":"OR",
    "sg:tags":[
        "shop"
    ],
    "wof:name":"Margies Hair Change",
    "wof:placetype":"venue"
},
  "geometry": {"coordinates":[-121.181009,45.589393],"type":"Point"}
}