{
  "type": "Feature",
  "properties": {
    "iso:country":"US",
    "sg:address":"1296 SW Cedar Dr",
    "sg:city":"Warrenton",
    "sg:classifiers":[
        {
            "category":"Restaurant",
            "type":"Food & Drink"
        }
    ],
    "sg:phone":"+1 503 861 9723",
    "sg:postcode":"97146",
    "sg:province":"OR",
    "sg:tags":[
        "eating"
    ],
    "wof:name":"Harbor Galley",
    "wof:placetype":"venue"
},
  "geometry": {"coordinates":[-123.93050100000001,46.153629],"type":"Point"}
}