{
  "type": "Feature",
  "properties": {
    "addr:full":"2615 SE 39th Loop Hillsboro OR 97123",
    "addr:housenumber":"2615",
    "addr:postcode":"97123",
    "addr:street":"Se 39Th Loop",
    "iso:country":"US",
    "sg:address":"2615 SE 39th Loop",
    "sg:city":"Hillsboro",
    "sg:classifiers":[
        {
            "category":"Wholesale",
            "subcategory":"Auto Parts",
            "type":"Manufacturing & Wholesale Goods"
        }
    ],
    "sg:phone":"+1 503 640 7465",
    "sg:postcode":"97123",
    "sg:province":"OR",
    "sg:tags":[
        "automobile",
        "supply"
    ],
    "wof:name":"Unichip Of North America",
    "wof:placetype":"venue"
},
  "geometry": {"coordinates":[-122.943995,45.499092],"type":"Point"}
}