{
  "type": "Feature",
  "properties": {
    "iso:country":"US",
    "sg:address":"15998 SW Hampshire Ter",
    "sg:city":"Portland",
    "sg:classifiers":[
        {
            "category":"Professional",
            "subcategory":"Business Services",
            "type":"Services"
        }
    ],
    "sg:phone":"+1 503 579 3475",
    "sg:postcode":"97224",
    "sg:province":"OR",
    "sg:tags":[
        "flo",
        "supply"
    ],
    "sg:website":"www.tropicalinteriors.com",
    "wof:name":"Tropical Interiors Inc",
    "wof:placetype":"venue"
},
  "geometry": {"coordinates":[-122.82231,45.404401],"type":"Point"}
}