{
  "type": "Feature",
  "properties": {
    "iso:country":"US",
    "sg:address":"19720 NW Tanasbourne Dr Ste 200",
    "sg:city":"Hillsboro",
    "sg:classifiers":[
        {
            "category":"Professional",
            "subcategory":"Lawyer & Legal Services",
            "type":"Services"
        }
    ],
    "sg:phone":"+1 503 352 9360",
    "sg:postcode":"97124",
    "sg:province":"OR",
    "sg:tags":[
        "attorney",
        "criminal",
        "law"
    ],
    "sg:website":"http://corbridgeshortlaw.com",
    "wof:name":"Corbridge & Short Law Group",
    "wof:placetype":"venue"
},
  "geometry": {"coordinates":[-122.87947800000001,45.544],"type":"Point"}
}