{
  "type": "Feature",
  "properties": {
    "addr:full":"1255 Plummer Ave Grants Pass OR 97527",
    "addr:housenumber":"1255",
    "addr:postcode":"97527",
    "addr:street":"Plummer Ave",
    "iso:country":"US",
    "sg:address":"1255 Plummer Ave",
    "sg:city":"Grants Pass",
    "sg:classifiers":[
        {
            "category":"Professional",
            "subcategory":"Business Services",
            "type":"Services"
        }
    ],
    "sg:phone":"+1 541 476 1439",
    "sg:postcode":"97527",
    "sg:province":"OR",
    "wof:name":"David Pylant Signs",
    "wof:placetype":"venue"
},
  "geometry": {"coordinates":[-123.33813499999999,42.427035],"type":"Point"}
}