{
  "type": "Feature",
  "properties": {
    "addr:full":"17440 SE Stark Street Portland OR 97233",
    "addr:postcode":"17440;97233",
    "addr:street":"Se Stark Street",
    "iso:country":"US",
    "sg:address":"17440 SE Stark Street",
    "sg:city":"Portland",
    "sg:classifiers":[
        {
            "category":"Restaurant",
            "type":"Food & Drink"
        }
    ],
    "sg:phone":"+1 503 252 6760",
    "sg:postcode":"97233",
    "sg:province":"OR",
    "wof:name":"Annie's Restaurant",
    "wof:placetype":"venue"
},
  "geometry": {"coordinates":[-122.48341499999999,45.519025],"type":"Point"}
}