{
  "type": "Feature",
  "properties": {
    "addr:full":"19059 SE Division St Gresham OR 97030",
    "addr:postcode":"19059;97030",
    "addr:street":"Se Division St",
    "iso:country":"US",
    "sg:address":"19059 SE Division St",
    "sg:city":"Gresham",
    "sg:classifiers":[
        {
            "category":"Building & Trades",
            "subcategory":"Equipment Rental",
            "type":"Services"
        }
    ],
    "sg:phone":"+1 503 666 3411",
    "sg:postcode":"97030",
    "sg:province":"OR",
    "wof:name":"Four Seasons Hot Tubbing",
    "wof:placetype":"venue"
},
  "geometry": {"coordinates":[-122.46316899999999,45.504569],"type":"Point"}
}