{
  "type": "Feature",
  "properties": {
    "iso:country":"US",
    "sg:address":"1211 Darley Dr",
    "sg:city":"Roseburg",
    "sg:classifiers":[
        {
            "category":"Building & Trades",
            "subcategory":"Construction",
            "type":"Services"
        }
    ],
    "sg:phone":"+1 541 672 3343",
    "sg:postcode":"97471",
    "sg:province":"OR",
    "sg:tags":[
        "road",
        "contractor"
    ],
    "wof:name":"C. Weavers' Construction Inc",
    "wof:placetype":"venue"
},
  "geometry": {"coordinates":[-123.38256800000001,43.248711],"type":"Point"}
}