{
  "type": "Feature",
  "properties": {
    "iso:country":"US",
    "sg:address":"21975 S Woodland Way",
    "sg:city":"Estacada",
    "sg:classifiers":[
        {
            "category":"Professional",
            "subcategory":"Lawyer & Legal Services",
            "type":"Services"
        }
    ],
    "sg:phone":"+1 503 630 7736",
    "sg:postcode":"97023",
    "sg:province":"OR",
    "sg:tags":[
        "attorney"
    ],
    "wof:name":"Terrance L Mc Cauley",
    "wof:placetype":"venue"
},
  "geometry": {"coordinates":[-122.369281,45.289141],"type":"Point"}
}