{
  "type": "Feature",
  "properties": {
    "addr:full":"1720 NW Lovejoy #337 Portland OR 97209",
    "addr:housenumber":"1720",
    "addr:postcode":"97209",
    "addr:street":"Nw Lovejoy # 337",
    "iso:country":"US",
    "sg:address":"1720 NW Lovejoy #337",
    "sg:city":"Portland",
    "sg:classifiers":[
        {
            "category":"Personal",
            "subcategory":"Beauty Salon",
            "type":"Services"
        },
        {
            "category":"Personal",
            "subcategory":"Skin Care",
            "type":"Services"
        },
        {
            "category":"Personal",
            "subcategory":"Day Spa",
            "type":"Services"
        }
    ],
    "sg:phone":"+1 503 888 1573",
    "sg:postcode":"97209",
    "sg:province":"OR",
    "sg:tags":[
        "eyelash"
    ],
    "sg:website":"www.servellobody.com/",
    "wof:name":"Servello Spa Room",
    "wof:placetype":"venue"
},
  "geometry": {"coordinates":[-122.689052,45.529711],"type":"Point"}
}