{
  "type": "Feature",
  "properties": {
    "iso:country":"US",
    "sg:address":"9865 State Hwy 212",
    "sg:city":"Clackamas",
    "sg:classifiers":[
        {
            "category":"Autos & Motor Vehicles",
            "subcategory":"Recreational Vehicle Sales",
            "type":"Retail Goods"
        }
    ],
    "sg:phone":"+1 503 656 6805",
    "sg:postcode":"97015",
    "sg:province":"OR",
    "sg:tags":[
        "home"
    ],
    "wof:name":"Motor Sales Co",
    "wof:placetype":"venue"
},
  "geometry": {"coordinates":[-122.56265,45.407541],"type":"Point"}
}