{
  "type": "Feature",
  "properties": {
    "iso:country":"US",
    "sg:address":"3615 NW Saint Helens Rd",
    "sg:city":"Portland",
    "sg:classifiers":[
        {
            "category":"Wholesale",
            "subcategory":"Machinery & Supplies",
            "type":"Manufacturing & Wholesale Goods"
        }
    ],
    "sg:phone":"+1 503 223 2202",
    "sg:postcode":"97210",
    "sg:province":"OR",
    "sg:tags":[
        "fitting",
        "industrial",
        "valve"
    ],
    "sg:website":"www.portlandwindustrial.com",
    "wof:name":"Portland Windustrial Inc",
    "wof:placetype":"venue"
},
  "geometry": {"coordinates":[-122.722031,45.544428],"type":"Point"}
}