{
  "type": "Feature",
  "properties": {
    "addr:full":"2735 N Lombard St Portland OR 97217",
    "addr:housenumber":"2735",
    "addr:postcode":"97217",
    "addr:street":"N Lombard St",
    "iso:country":"US",
    "sg:address":"2735 N Lombard St",
    "sg:city":"Portland",
    "sg:classifiers":[
        {
            "category":"Shopping",
            "subcategory":"Baby Store",
            "type":"Retail Goods"
        }
    ],
    "sg:phone":"+1 503 285 0690",
    "sg:postcode":"97217",
    "sg:province":"OR",
    "sg:tags":[
        "gear",
        "furniture"
    ],
    "sg:website":"www.zoombabygear.com",
    "wof:name":"Zoom Baby Gear",
    "wof:placetype":"venue"
},
  "geometry": {"coordinates":[-122.695286,45.577132],"type":"Point"}
}