{
  "type": "Feature",
  "properties": {
    "addr:full":"1040 Green Acres Rd Eugene OR 97408",
    "addr:housenumber":"1040",
    "addr:postcode":"97408",
    "addr:street":"Green Acres Rd",
    "iso:country":"US",
    "sg:address":"1040 Green Acres Rd",
    "sg:city":"Eugene",
    "sg:classifiers":[
        {
            "category":"Shopping",
            "type":"Retail Goods"
        }
    ],
    "sg:phone":"+1 541 344 9668",
    "sg:postcode":"97408",
    "sg:province":"OR",
    "sg:tags":[
        "telephone",
        "cellular"
    ],
    "wof:name":"D C Wireless",
    "wof:placetype":"venue"
},
  "geometry": {"coordinates":[-123.094236,44.093241],"type":"Point"}
}