{
  "type": "Feature",
  "properties": {
    "iso:country":"US",
    "sg:address":"857 St Andrews Way",
    "sg:city":"Eagle Point",
    "sg:classifiers":[
        {
            "category":"Building & Trades",
            "subcategory":"Construction",
            "type":"Services"
        }
    ],
    "sg:phone":"+1 541 826 2015",
    "sg:postcode":"97524",
    "sg:province":"OR",
    "sg:tags":[
        "house"
    ],
    "wof:name":"Thurmond Construction Inc",
    "wof:placetype":"venue"
},
  "geometry": {"coordinates":[-122.798568,42.462329],"type":"Point"}
}