{
  "type": "Feature",
  "properties": {
    "iso:country":"US",
    "sg:address":"65245 Cline Falls Rd",
    "sg:city":"Bend",
    "sg:classifiers":[
        {
            "category":"Home & Garden",
            "subcategory":"Garden Supply",
            "type":"Retail Goods"
        }
    ],
    "sg:phone":"+1 541 318 1600",
    "sg:postcode":"97701",
    "sg:province":"OR",
    "sg:tags":[
        "nurseryman"
    ],
    "wof:name":"Ten Peaks Nursery",
    "wof:placetype":"venue"
},
  "geometry": {"coordinates":[-121.324013,44.167732],"type":"Point"}
}