{
  "type": "Feature",
  "properties": {
    "addr:full":"4329 NE Killingsworth St Portland OR 97218",
    "addr:housenumber":"4329",
    "addr:postcode":"97218",
    "addr:street":"Ne Killingsworth St",
    "iso:country":"US",
    "sg:address":"4329 NE Killingsworth St",
    "sg:city":"Portland",
    "sg:classifiers":[
        {
            "category":"Retail",
            "subcategory":"Repair Shop",
            "type":"Services"
        }
    ],
    "sg:phone":"+1 503 287 9690",
    "sg:postcode":"97218",
    "sg:province":"OR",
    "sg:tags":[
        "vinyl"
    ],
    "wof:name":"Trim-Flex Vinyl Co",
    "wof:placetype":"venue"
},
  "geometry": {"coordinates":[-122.618396,45.562871],"type":"Point"}
}