{
  "type": "Feature",
  "properties": {
    "iso:country":"US",
    "sg:address":"20570 Whitehaven Ln",
    "sg:city":"Bend",
    "sg:classifiers":[
        {
            "category":"Building & Trades",
            "subcategory":"Construction",
            "type":"Services"
        }
    ],
    "sg:phone":"+1 541 617 1063",
    "sg:postcode":"97702",
    "sg:province":"OR",
    "sg:tags":[
        "painting",
        "contractor"
    ],
    "wof:name":"Accucolor Painting",
    "wof:placetype":"venue"
},
  "geometry": {"coordinates":[-121.295884,44.005711],"type":"Point"}
}