{
  "type": "Feature",
  "properties": {
    "iso:country":"US",
    "sg:address":"120 N Roosevelt Dr",
    "sg:city":"Seaside",
    "sg:classifiers":[
        {
            "category":"Communications",
            "subcategory":"Radio Station",
            "type":"Services"
        }
    ],
    "sg:phone":"+1 503 738 8668",
    "sg:postcode":"97138",
    "sg:province":"OR",
    "sg:tags":[
        "broadcast"
    ],
    "wof:name":"KCBZ",
    "wof:placetype":"venue"
},
  "geometry": {"coordinates":[-123.91964,45.995044],"type":"Point"}
}