{
  "type": "Feature",
  "properties": {
    "iso:country":"US",
    "sg:address":"23035 Zlabek Rd",
    "sg:city":"Tulelake",
    "sg:phone":"+1 530 667 5375",
    "sg:postcode":"96134",
    "sg:province":"OR",
    "sg:tags":[
        "farm",
        "grain",
        "cash"
    ],
    "wof:name":"Richard L Vaughn",
    "wof:placetype":"venue"
},
  "geometry": {"coordinates":[-121.45980400000001,41.988184],"type":"Point"}
}