{
  "type": "Feature",
  "properties": {
    "addr:full":"555 Liberty St SE Salem OR 97301",
    "addr:housenumber":"555",
    "addr:postcode":"97301",
    "addr:street":"Liberty St Se",
    "iso:country":"US",
    "sg:address":"555 Liberty St SE",
    "sg:city":"Salem",
    "sg:classifiers":[
        {
            "category":"Government",
            "subcategory":"Office",
            "type":"Public Place"
        }
    ],
    "sg:phone":"+1 503 588 6242",
    "sg:postcode":"97301",
    "sg:province":"OR",
    "sg:tags":[
        "village"
    ],
    "wof:name":"Salem Housing Safety Inspctn",
    "wof:placetype":"venue"
},
  "geometry": {"coordinates":[-123.040848,44.936304],"type":"Point"}
}