{
  "type": "Feature",
  "properties": {
    "iso:country":"US",
    "sg:address":"1540 Monterey Ave",
    "sg:city":"Eugene",
    "sg:classifiers":[
        {
            "category":"Manufacturing",
            "subcategory":"Building Materials",
            "type":"Manufacturing & Wholesale Goods"
        }
    ],
    "sg:phone":"+1 541 484 2665",
    "sg:postcode":"97401",
    "sg:province":"OR",
    "sg:tags":[
        "mfg"
    ],
    "wof:name":"Marvic Enterprises Inc",
    "wof:placetype":"venue"
},
  "geometry": {"coordinates":[-123.09026,44.080546],"type":"Point"}
}