{
  "type": "Feature",
  "properties": {
    "addr:full":"342 Fairview St Silverton OR 97381",
    "addr:housenumber":"342",
    "addr:postcode":"97381",
    "addr:street":"Fairview St",
    "iso:country":"US",
    "sg:address":"342 Fairview St",
    "sg:city":"Silverton",
    "sg:classifiers":[
        {
            "category":"Health Services",
            "subcategory":"Clinic",
            "type":"Services"
        }
    ],
    "sg:phone":"+1 503 982 8108",
    "sg:postcode":"97381",
    "sg:province":"OR",
    "sg:tags":[
        "medical"
    ],
    "wof:name":"Woodburn Medical Clinic Billin",
    "wof:placetype":"venue"
},
  "geometry": {"coordinates":[-122.79074900000001,45.004559],"type":"Point"}
}