{
  "type": "Feature",
  "properties": {
    "addr:full":"14843 Bluegrass Loop Sisters OR 97759",
    "addr:housenumber":"14843",
    "addr:postcode":"97759",
    "addr:street":"Bluegrass Loop",
    "iso:country":"US",
    "sg:address":"14843 Bluegrass Loop",
    "sg:city":"Sisters",
    "sg:classifiers":[
        {
            "category":"Building & Trades",
            "subcategory":"Construction",
            "type":"Services"
        }
    ],
    "sg:phone":"+1 541 549 6466",
    "sg:postcode":"97759",
    "sg:province":"OR",
    "sg:tags":[
        "system",
        "contractor",
        "air conditioning"
    ],
    "wof:name":"Balance Hydronics And Air",
    "wof:placetype":"venue"
},
  "geometry": {"coordinates":[-121.598331,44.29396],"type":"Point"}
}