{
  "type": "Feature",
  "properties": {
    "iso:country":"US",
    "sg:address":"635 N Killingsworth Ct",
    "sg:city":"Portland",
    "sg:classifiers":[
        {
            "category":"Professional",
            "subcategory":"Business Services",
            "type":"Services"
        }
    ],
    "sg:phone":"+1 503 240 6088",
    "sg:postcode":"97217",
    "sg:province":"OR",
    "sg:tags":[
        "venue",
        "event",
        "space"
    ],
    "sg:website":"www.northstarballroom.com/",
    "wof:name":"North Star Ballroom",
    "wof:placetype":"venue"
},
  "geometry": {"coordinates":[-122.673745,45.562091],"type":"Point"}
}