{
  "type": "Feature",
  "properties": {
    "iso:country":"US",
    "sg:address":"1108 SW Chamberlain St",
    "sg:city":"Bend",
    "sg:classifiers":[
        {
            "category":"Wholesale",
            "subcategory":"Jewelry",
            "type":"Manufacturing & Wholesale Goods"
        }
    ],
    "sg:phone":"+1 541 389 5855",
    "sg:postcode":"97702",
    "sg:province":"OR",
    "sg:tags":[
        "platinum",
        "silver",
        "gold"
    ],
    "wof:name":"Bill Fleming Coin & Jewelry",
    "wof:placetype":"venue"
},
  "geometry": {"coordinates":[-121.313491,44.040201],"type":"Point"}
}