{
  "type": "Feature",
  "properties": {
    "iso:country":"US",
    "sg:address":"25721 S Highway 170",
    "sg:city":"Canby",
    "sg:classifiers":[
        {
            "category":"Personal",
            "subcategory":"Beauty Salon",
            "type":"Services"
        }
    ],
    "sg:phone":"+1 503 266 5521",
    "sg:postcode":"97013",
    "sg:province":"OR",
    "wof:name":"Country Cut & Curl",
    "wof:placetype":"venue"
},
  "geometry": {"coordinates":[-122.684144,45.236089],"type":"Point"}
}