{
  "type": "Feature",
  "properties": {
    "iso:country":"US",
    "sg:address":"16815 SE River Rd",
    "sg:city":"Portland",
    "sg:classifiers":[
        {
            "category":"Shopping",
            "subcategory":"Jewelry",
            "type":"Retail Goods"
        }
    ],
    "sg:phone":"+1 503 654 4390",
    "sg:postcode":"97267",
    "sg:province":"OR",
    "sg:tags":[
        "pearl"
    ],
    "wof:name":"Pearl Teigland",
    "wof:placetype":"venue"
},
  "geometry": {"coordinates":[-122.633726,45.401369],"type":"Point"}
}