{
  "type": "Feature",
  "properties": {
    "iso:country":"US",
    "sg:address":"42382 Hwy 226",
    "sg:city":"Scio",
    "sg:classifiers":[
        {
            "category":"Retail",
            "subcategory":"Portrait Studio",
            "type":"Services"
        }
    ],
    "sg:phone":"+1 503 394 7070",
    "sg:postcode":"97374",
    "sg:province":"OR",
    "sg:tags":[
        "photo"
    ],
    "wof:name":"Miller Photography",
    "wof:placetype":"venue"
},
  "geometry": {"coordinates":[-122.712112,44.718453],"type":"Point"}
}