{
  "type": "Feature",
  "properties": {
    "iso:country":"US",
    "sg:address":"3225 Oakcrest Dr",
    "sg:city":"Forest Grove",
    "sg:phone":"+1 503 357 6382",
    "sg:postcode":"97116",
    "sg:province":"OR",
    "sg:tags":[
        "farm",
        "corn"
    ],
    "wof:name":"Terry Peters",
    "wof:placetype":"venue"
},
  "geometry": {"coordinates":[-123.129282,45.534325],"type":"Point"}
}