{
  "type": "Feature",
  "properties": {
    "iso:country":"US",
    "sg:address":"8515 Lone Oak Rd N",
    "sg:city":"McMinnville",
    "sg:classifiers":[
        {
            "category":"Autos & Motor Vehicles",
            "subcategory":"Automobile Sales",
            "type":"Retail Goods"
        },
        {
            "category":"Retail",
            "subcategory":"Auto Repair",
            "type":"Services"
        }
    ],
    "sg:phone":"+1 503 472 0465",
    "sg:postcode":"97128",
    "sg:province":"OR",
    "sg:tags":[
        "car"
    ],
    "wof:name":"Capitol Honda",
    "wof:placetype":"venue"
},
  "geometry": {"coordinates":[-123.152,45.2383],"type":"Point"}
}