{
  "type": "Feature",
  "properties": {
    "addr:full":"5625 NE 62nd Ave Portland OR 97218",
    "addr:housenumber":"5625",
    "addr:postcode":"97218",
    "addr:street":"Ne 62Nd Ave",
    "iso:country":"US",
    "sg:address":"5625 NE 62nd Ave",
    "sg:city":"Portland",
    "sg:classifiers":[
        {
            "category":"Building & Trades",
            "subcategory":"Construction",
            "type":"Services"
        }
    ],
    "sg:phone":"+1 503 287 3331",
    "sg:postcode":"97218",
    "sg:province":"OR",
    "sg:tags":[
        "concrete",
        "contractor"
    ],
    "wof:name":"Gilbert Weltsch",
    "wof:placetype":"venue"
},
  "geometry": {"coordinates":[-122.599351,45.563592],"type":"Point"}
}