{
  "type": "Feature",
  "properties": {
    "iso:country":"US",
    "sg:address":"1585 SW Marlow Ave Ste 120",
    "sg:city":"Portland",
    "sg:classifiers":[
        {
            "category":"Health Services",
            "subcategory":"Doctor",
            "type":"Services"
        }
    ],
    "sg:phone":"+1 503 297 1687",
    "sg:postcode":"97225",
    "sg:province":"OR",
    "sg:tags":[
        "surgeon",
        "oral"
    ],
    "wof:name":"Gable Harold DDS Gentle Dental Cedar Hills",
    "wof:placetype":"venue"
},
  "geometry": {"coordinates":[-122.783997,45.5079],"type":"Point"}
}