{
  "type": "Feature",
  "properties": {
    "iso:country":"US",
    "sg:address":"688 S Fern Way",
    "sg:city":"Springfield",
    "sg:classifiers":[
        {
            "category":"Restaurant",
            "type":"Food & Drink"
        }
    ],
    "sg:phone":"+1 541 746 7273",
    "sg:postcode":"97478",
    "sg:province":"OR",
    "sg:tags":[
        "eating"
    ],
    "wof:name":"Blimpie",
    "wof:placetype":"venue"
},
  "geometry": {"coordinates":[-122.953721,44.040584],"type":"Point"}
}