{
  "type": "Feature",
  "properties": {
    "addr:full":"69826 Summerville Rd Summerville OR 97876",
    "addr:postcode":"69826;97876",
    "addr:street":"Summerville Rd",
    "iso:country":"US",
    "sg:address":"69826 Summerville Rd",
    "sg:city":"Summerville",
    "sg:classifiers":[
        {
            "category":"Freight",
            "type":"Transportation"
        }
    ],
    "sg:phone":"+1 541 534 6970",
    "sg:postcode":"97876",
    "sg:province":"OR",
    "sg:tags":[
        "operator",
        "local",
        "trucking"
    ],
    "wof:name":"Way Corporation",
    "wof:placetype":"venue"
},
  "geometry": {"coordinates":[-118.026544,45.522255],"type":"Point"}
}