{
  "type": "Feature",
  "properties": {
    "iso:country":"US",
    "sg:address":"1711 SE Hawthorne Blvd",
    "sg:city":"Portland",
    "sg:classifiers":[
        {
            "category":"Shopping",
            "subcategory":"Pets & Pet Supplies",
            "type":"Retail Goods"
        }
    ],
    "sg:phone":"+1 503 235 4677",
    "sg:postcode":"97214",
    "sg:province":"OR",
    "sg:tags":[
        "store"
    ],
    "wof:name":"Maranatha Pet Supply",
    "wof:placetype":"venue"
},
  "geometry": {"coordinates":[-122.648252,45.512215],"type":"Point"}
}