{
  "type": "Feature",
  "properties": {
    "addr:full":"115 E Main St Molalla OR 97038",
    "addr:housenumber":"115",
    "addr:postcode":"97038",
    "addr:street":"E Main St",
    "iso:country":"US",
    "sg:address":"115 E Main St",
    "sg:city":"Molalla",
    "sg:classifiers":[
        {
            "category":"Real Estate",
            "subcategory":"Real Estate Agent",
            "type":"Services"
        }
    ],
    "sg:phone":"+1 503 829 7310",
    "sg:postcode":"97038",
    "sg:province":"OR",
    "wof:name":"Heritage Homes Realty Inc",
    "wof:placetype":"venue"
},
  "geometry": {"coordinates":[-122.576972,45.147589],"type":"Point"}
}