{
  "type": "Feature",
  "properties": {
    "iso:country":"US",
    "sg:address":"14000 SE Rhine St",
    "sg:city":"Portland",
    "sg:classifiers":[
        {
            "category":"Ice Cream",
            "type":"Food & Drink"
        }
    ],
    "sg:phone":"+1 503 760 3098",
    "sg:postcode":"97236",
    "sg:province":"OR",
    "wof:name":"All Star Ice Cream",
    "wof:placetype":"venue"
},
  "geometry": {"coordinates":[-122.519379,45.497352],"type":"Point"}
}