{
  "type": "Feature",
  "properties": {
    "iso:country":"US",
    "sg:address":"17108 Boones Ferry Rd NE",
    "sg:city":"Woodburn",
    "sg:classifiers":[
        {
            "category":"Wholesale",
            "subcategory":"Machinery & Supplies",
            "type":"Manufacturing & Wholesale Goods"
        }
    ],
    "sg:phone":"+1 503 982 2941",
    "sg:postcode":"97071",
    "sg:province":"OR",
    "sg:tags":[
        "equipment",
        "industrial"
    ],
    "wof:name":"Kd Automation LLC",
    "wof:placetype":"venue"
},
  "geometry": {"coordinates":[-122.84889699999999,45.167107],"type":"Point"}
}