{
  "type": "Feature",
  "properties": {
    "addr:full":"2019 Aero Way Medford OR 97504",
    "addr:housenumber":"2019",
    "addr:postcode":"97504",
    "addr:street":"Aero Way",
    "iso:country":"US",
    "sg:address":"2019 Aero Way",
    "sg:city":"Medford",
    "sg:classifiers":[
        {
            "category":"Insurance",
            "subcategory":"Insurance Agent",
            "type":"Services"
        }
    ],
    "sg:phone":"+1 541 773 1404",
    "sg:postcode":"97504",
    "sg:province":"OR",
    "wof:name":"State Farm Insurance",
    "wof:placetype":"venue"
},
  "geometry": {"coordinates":[-122.86072900000001,42.366147],"type":"Point"}
}