{
  "type": "Feature",
  "properties": {
    "addr:full":"60 Collin Ct Eugene OR 97404",
    "addr:housenumber":"60",
    "addr:postcode":"97404",
    "addr:street":"Collin Ct",
    "iso:country":"US",
    "sg:address":"60 Collin Ct",
    "sg:city":"Eugene",
    "sg:classifiers":[
        {
            "category":"Building & Trades",
            "subcategory":"Plumbing",
            "type":"Services"
        }
    ],
    "sg:phone":"+1 541 689 4235",
    "sg:postcode":"97404",
    "sg:province":"OR",
    "sg:tags":[
        "contractor"
    ],
    "wof:name":"Reliable Plumbing & Mechanical",
    "wof:placetype":"venue"
},
  "geometry": {"coordinates":[-123.139555,44.119404],"type":"Point"}
}