{
  "type": "Feature",
  "properties": {
    "iso:country":"US",
    "sg:address":"1207 W Central Ave",
    "sg:city":"Sutherlin",
    "sg:classifiers":[
        {
            "category":"Bars & Pubs",
            "type":"Food & Drink"
        }
    ],
    "sg:phone":"+1 541 459 2069",
    "sg:postcode":"97479",
    "sg:province":"OR",
    "wof:name":"Cozy Corner",
    "wof:placetype":"venue"
},
  "geometry": {"coordinates":[-123.330691,43.387197],"type":"Point"}
}