{
  "type": "Feature",
  "properties": {
    "iso:country":"US",
    "sg:address":"1504 W 2nd Ave",
    "sg:city":"Eugene",
    "sg:classifiers":[
        {
            "category":"Wholesale",
            "subcategory":"Electrical",
            "type":"Manufacturing & Wholesale Goods"
        }
    ],
    "sg:phone":"+1 541 345 1579",
    "sg:postcode":"97402",
    "sg:province":"OR",
    "sg:tags":[
        "electric",
        "motor"
    ],
    "sg:website":"www.kalenelectric.com",
    "wof:name":"Kalen Electric Co",
    "wof:placetype":"venue"
},
  "geometry": {"coordinates":[-123.11423000000001,44.05742],"type":"Point"}
}