{
  "type": "Feature",
  "properties": {
    "addr:full":"5242 NE Columbia Blvd Portland OR 97218",
    "addr:housenumber":"5242",
    "addr:postcode":"97218",
    "addr:street":"Ne Columbia Blvd",
    "iso:country":"US",
    "sg:address":"5242 NE Columbia Blvd",
    "sg:city":"Portland",
    "sg:classifiers":[
        {
            "category":"Building & Trades",
            "subcategory":"Construction",
            "type":"Services"
        }
    ],
    "sg:phone":"+1 503 280 8872",
    "sg:postcode":"97218",
    "sg:province":"OR",
    "sg:tags":[
        "contractor"
    ],
    "wof:name":"H & H Welding",
    "wof:placetype":"venue"
},
  "geometry": {"coordinates":[-122.606278,45.56956],"type":"Point"}
}