{
  "type": "Feature",
  "properties": {
    "iso:country":"US",
    "sg:address":"386 NW Macleay Blvd",
    "sg:city":"Portland",
    "sg:classifiers":[
        {
            "category":"Wholesale",
            "subcategory":"Auto Parts",
            "type":"Manufacturing & Wholesale Goods"
        }
    ],
    "sg:phone":"+1 503 226 8280",
    "sg:postcode":"97210",
    "sg:province":"OR",
    "sg:tags":[
        "truck"
    ],
    "wof:name":"Northwest Fleet Products Inc",
    "wof:placetype":"venue"
},
  "geometry": {"coordinates":[-122.70964499999999,45.526243],"type":"Point"}
}