{
  "type": "Feature",
  "properties": {
    "iso:country":"US",
    "sg:address":"4940 SE Woodstock Boulevard",
    "sg:city":"Portland",
    "sg:classifiers":[
        {
            "category":"Building & Trades",
            "subcategory":"Construction",
            "type":"Services"
        }
    ],
    "sg:phone":"+1 503 772 4663",
    "sg:postcode":"97206",
    "sg:province":"OR",
    "sg:tags":[
        "contractor"
    ],
    "wof:name":"Oregon Home Services",
    "wof:placetype":"venue"
},
  "geometry": {"coordinates":[-122.611503,45.479062],"type":"Point"}
}