{
  "type": "Feature",
  "properties": {
    "addr:full":"29559 Santiam Terrace Rd Lebanon OR 97355",
    "addr:postcode":"29559;97355",
    "addr:street":"Santiam Terrace Rd",
    "iso:country":"US",
    "sg:address":"29559 Santiam Terrace Rd",
    "sg:city":"Lebanon",
    "sg:classifiers":[
        {
            "category":"Health Services",
            "subcategory":"Health Practitioner",
            "type":"Services"
        }
    ],
    "sg:phone":"+1 541 367 2872",
    "sg:postcode":"97355",
    "sg:province":"OR",
    "wof:name":"Debra Cowart Midwife",
    "wof:placetype":"venue"
},
  "geometry": {"coordinates":[-122.80513999999999,44.456917],"type":"Point"}
}