{
  "type": "Feature",
  "properties": {
    "iso:country":"US",
    "sg:address":"29545 Ellensburg Ave",
    "sg:city":"Gold Beach",
    "sg:classifiers":[
        {
            "category":"Shopping",
            "subcategory":"Pharmacy",
            "type":"Retail Goods"
        }
    ],
    "sg:phone":"+1 541 247 4544",
    "sg:postcode":"97444",
    "sg:province":"OR",
    "sg:tags":[
        "drug",
        "store"
    ],
    "wof:name":"Corner Drug Inc",
    "wof:placetype":"venue"
},
  "geometry": {"coordinates":[-124.420593,42.409291],"type":"Point"}
}