{
  "type": "Feature",
  "properties": {
    "addr:full":"1231 NE M. L. King Jr Blvd, Ste #528 Portland OR 97232",
    "addr:housenumber":"1231",
    "addr:postcode":"97232",
    "addr:street":"Ne M. L. King Jr Blvd Ste # 528",
    "iso:country":"US",
    "sg:address":"1231 NE M. L. King Jr Blvd, Ste #528",
    "sg:city":"Portland",
    "sg:classifiers":[
        {
            "category":"Professional",
            "subcategory":"Art Services",
            "type":"Services"
        }
    ],
    "sg:phone":"+1 503 889 6071",
    "sg:postcode":"97232",
    "sg:province":"OR",
    "sg:tags":[
        "graphic",
        "design"
    ],
    "wof:name":"SwitchEnergy Films + Interactive",
    "wof:placetype":"venue"
},
  "geometry": {"coordinates":[-122.661796,45.531887],"type":"Point"}
}