{
  "type": "Feature",
  "properties": {
    "iso:country":"US",
    "sg:address":"2207 NE Columbia Blvd",
    "sg:city":"Portland",
    "sg:classifiers":[
        {
            "category":"Freight",
            "type":"Transportation"
        }
    ],
    "sg:phone":"+1 503 275 4248",
    "sg:postcode":"97211",
    "sg:province":"OR",
    "sg:tags":[
        "general"
    ],
    "wof:name":"US Bancorp",
    "wof:placetype":"venue"
},
  "geometry": {"coordinates":[-122.64197,45.576255],"type":"Point"}
}