{
  "type": "Feature",
  "properties": {
    "iso:country":"US",
    "sg:address":"3603 Crater Lake Hwy",
    "sg:city":"Medford",
    "sg:classifiers":[
        {
            "category":"Restaurant",
            "type":"Food & Drink"
        }
    ],
    "sg:phone":"+1 541 779 8146",
    "sg:postcode":"97504",
    "sg:province":"OR",
    "wof:name":"Spicers Restaurant and Dessertery",
    "wof:placetype":"venue"
},
  "geometry": {"coordinates":[-122.85700199999999,42.362202],"type":"Point"}
}