{
  "type": "Feature",
  "properties": {
    "iso:country":"US",
    "sg:address":"2165 W 11th Ave",
    "sg:city":"Eugene",
    "sg:classifiers":[
        {
            "category":"Bars & Pubs",
            "type":"Food & Drink"
        }
    ],
    "sg:phone":"+1 541 683 6021",
    "sg:postcode":"97402",
    "sg:province":"OR",
    "sg:tags":[
        "drinking"
    ],
    "wof:name":"Divas Gentlemens Club",
    "wof:placetype":"venue"
},
  "geometry": {"coordinates":[-123.12714699999999,44.047898],"type":"Point"}
}