{
  "type": "Feature",
  "properties": {
    "iso:country":"US",
    "sg:address":"15770 Upper Boones Ferry Rd",
    "sg:city":"Lake Oswego",
    "sg:classifiers":[
        {
            "category":"Shopping",
            "subcategory":"Computers & Home Electronics",
            "type":"Retail Goods"
        }
    ],
    "sg:phone":"+1 503 598 8968",
    "sg:postcode":"97035",
    "sg:province":"OR",
    "sg:website":"www.projectus.com",
    "wof:name":"Projectus",
    "wof:placetype":"venue"
},
  "geometry": {"coordinates":[-122.745412,45.394848],"type":"Point"}
}