{
  "type": "Feature",
  "properties": {
    "iso:country":"US",
    "sg:address":"12420 NE Siskiyou St",
    "sg:city":"Portland",
    "sg:classifiers":[
        {
            "category":"Place Of Worship",
            "subcategory":"Church",
            "type":"Public Place"
        }
    ],
    "sg:postcode":"97230",
    "sg:province":"OR",
    "wof:name":"Tree of Life Church",
    "wof:placetype":"venue"
},
  "geometry": {"coordinates":[-122.535186,45.544221],"type":"Point"}
}