{
  "type": "Feature",
  "properties": {
    "addr:full":"140 Daisey Ln Jacksonville OR 97530",
    "addr:housenumber":"140",
    "addr:postcode":"97530",
    "addr:street":"Daisey Ln",
    "iso:country":"US",
    "sg:address":"140 Daisey Ln",
    "sg:city":"Jacksonville",
    "sg:classifiers":[
        {
            "category":"Social Services",
            "subcategory":"Child Care",
            "type":"Services"
        }
    ],
    "sg:phone":"+1 541 890 1319",
    "sg:postcode":"97530",
    "sg:province":"OR",
    "sg:tags":[
        "kindergarten",
        "academic",
        "school"
    ],
    "wof:name":"Star Of The Morning Childrens",
    "wof:placetype":"venue"
},
  "geometry": {"coordinates":[-122.970809,42.306245],"type":"Point"}
}