{
  "type": "Feature",
  "properties": {
    "addr:full":"1635 N Alvord Ln Otis OR 97368",
    "addr:housenumber":"1635",
    "addr:postcode":"97368",
    "addr:street":"N Alvord Ln",
    "iso:country":"US",
    "sg:address":"1635 N Alvord Ln",
    "sg:city":"Otis",
    "sg:classifiers":[
        {
            "category":"Shopping",
            "subcategory":"Computers & Home Electronics",
            "type":"Retail Goods"
        }
    ],
    "sg:phone":"+1 541 994 4911",
    "sg:postcode":"97368",
    "sg:province":"OR",
    "wof:name":"Freshjive Sound",
    "wof:placetype":"venue"
},
  "geometry": {"coordinates":[-123.886616,44.993063],"type":"Point"}
}