{
  "type": "Feature",
  "properties": {
    "iso:country":"US",
    "sg:address":"84376 Hwy 11",
    "sg:city":"Milton Freewater",
    "sg:classifiers":[
        {
            "category":"Shopping",
            "subcategory":"Used Merchandise",
            "type":"Retail Goods"
        }
    ],
    "sg:phone":"+1 541 938 5240",
    "sg:postcode":"97862",
    "sg:province":"OR",
    "sg:tags":[
        "furniture"
    ],
    "wof:name":"Country Trader",
    "wof:placetype":"venue"
},
  "geometry": {"coordinates":[-118.387146,45.970197],"type":"Point"}
}