{
  "type": "Feature",
  "properties": {
    "iso:country":"US",
    "sg:address":"2120 NE 166th Dr",
    "sg:city":"Portland",
    "sg:classifiers":[
        {
            "category":"Building & Trades",
            "subcategory":"Construction",
            "type":"Services"
        }
    ],
    "sg:phone":"+1 503 257 1450",
    "sg:postcode":"97230",
    "sg:province":"OR",
    "sg:tags":[
        "house"
    ],
    "wof:name":"Carlys",
    "wof:placetype":"venue"
},
  "geometry": {"coordinates":[-122.49093000000001,45.538217],"type":"Point"}
}