{
  "type": "Feature",
  "properties": {
    "iso:country":"US",
    "sg:address":"7840 SW Matheny Dr",
    "sg:city":"Beaverton",
    "sg:classifiers":[
        {
            "category":"Insurance",
            "subcategory":"Health Insurance",
            "type":"Services"
        }
    ],
    "sg:phone":"+1 503 646 7092",
    "sg:postcode":"97008",
    "sg:province":"OR",
    "sg:tags":[
        "carrier"
    ],
    "wof:name":"Long-Term Care Assure",
    "wof:placetype":"venue"
},
  "geometry": {"coordinates":[-122.803992,45.462896],"type":"Point"}
}