{
  "type": "Feature",
  "properties": {
    "iso:country":"US",
    "sg:address":"17500 S Hallbacka Ln",
    "sg:city":"Mulino",
    "sg:classifiers":[
        {
            "category":"Health Services",
            "subcategory":"Doctor",
            "type":"Services"
        }
    ],
    "sg:phone":"+1 503 860 4534",
    "sg:postcode":"97042",
    "sg:province":"OR",
    "sg:tags":[
        "medical"
    ],
    "wof:name":"Bill Nichols Dr",
    "wof:placetype":"venue"
},
  "geometry": {"coordinates":[-122.511347,45.173291],"type":"Point"}
}