{
  "type": "Feature",
  "properties": {
    "iso:country":"US",
    "sg:address":"710 NE Cleveland Ave",
    "sg:city":"Gresham",
    "sg:classifiers":[
        {
            "category":"Shopping",
            "type":"Retail Goods"
        }
    ],
    "sg:phone":"+1 503 663 6909",
    "sg:postcode":"97030",
    "sg:province":"OR",
    "sg:tags":[
        "equipment",
        "telephone",
        "supply"
    ],
    "wof:name":"Associated Communications Grp",
    "wof:placetype":"venue"
},
  "geometry": {"coordinates":[-122.421027,45.5027],"type":"Point"}
}