{
  "type": "Feature",
  "properties": {
    "addr:full":"2715 SE Ash St Portland OR 97214",
    "addr:housenumber":"2715",
    "addr:postcode":"97214",
    "addr:street":"Se Ash St",
    "iso:country":"US",
    "sg:address":"2715 SE Ash St",
    "sg:city":"Portland",
    "sg:classifiers":[
        {
            "category":"Organizations",
            "subcategory":"Non-profit Organization",
            "type":"Services"
        }
    ],
    "sg:phone":"+1 503 233 9365",
    "sg:postcode":"97214",
    "sg:province":"OR",
    "sg:tags":[
        "disability"
    ],
    "wof:name":"Developmental Systems Inc",
    "wof:placetype":"venue"
},
  "geometry": {"coordinates":[-122.637418,45.521535],"type":"Point"}
}