{
  "type": "Feature",
  "properties": {
    "iso:country":"US",
    "sg:address":"1353 Hoyt St SE",
    "sg:city":"Salem",
    "sg:classifiers":[
        {
            "category":"Manufacturing",
            "subcategory":"Tools & Machinery",
            "type":"Manufacturing & Wholesale Goods"
        }
    ],
    "sg:phone":"+1 503 370 9062",
    "sg:postcode":"97302",
    "sg:province":"OR",
    "sg:tags":[
        "interlock",
        "ignition",
        "devices"
    ],
    "wof:name":"Guardian Interlock Systems",
    "wof:placetype":"venue"
},
  "geometry": {"coordinates":[-123.028479,44.918944],"type":"Point"}
}