{
  "type": "Feature",
  "properties": {
    "addr:full":"3617 S Pacific Hwy Medford OR 97501",
    "addr:housenumber":"3617",
    "addr:postcode":"97501",
    "addr:street":"S Pacific Hwy",
    "iso:country":"US",
    "sg:address":"3617 S Pacific Hwy",
    "sg:city":"Medford",
    "sg:classifiers":[
        {
            "category":"Health Services",
            "subcategory":"Doctor",
            "type":"Services"
        }
    ],
    "sg:phone":"+1 541 535 6239",
    "sg:postcode":"97501",
    "sg:province":"OR",
    "sg:tags":[
        "physician",
        "family",
        "gynecology",
        "practice",
        "surgeons",
        "obstetrics",
        "medicine",
        "surgeon"
    ],
    "sg:website":"http://www.laclinicahealth.org",
    "wof:name":"La Clinica",
    "wof:placetype":"venue"
},
  "geometry": {"coordinates":[-122.83128000000001,42.286154],"type":"Point"}
}