{
  "type": "Feature",
  "properties": {
    "iso:country":"US",
    "sg:address":"1230 W Harvard Ave",
    "sg:city":"Roseburg",
    "sg:classifiers":[
        {
            "category":"Autos & Motor Vehicles",
            "subcategory":"Fuel & Gas Station",
            "type":"Retail Goods"
        }
    ],
    "sg:phone":"+1 541 673 4555",
    "sg:postcode":"97471",
    "sg:province":"OR",
    "wof:name":"B J's Towing",
    "wof:placetype":"venue"
},
  "geometry": {"coordinates":[-123.363186,43.214205],"type":"Point"}
}