{
  "type": "Feature",
  "properties": {
    "iso:country":"US",
    "sg:address":"8338 N Lombard St",
    "sg:city":"Portland",
    "sg:classifiers":[
        {
            "category":"Restaurant",
            "type":"Food & Drink"
        }
    ],
    "sg:phone":"+1 503 247 1066",
    "sg:postcode":"97203",
    "sg:province":"OR",
    "sg:tags":[
        "traditional",
        "american"
    ],
    "wof:name":"John Street Caf?",
    "wof:placetype":"venue"
},
  "geometry": {"coordinates":[-122.75299800000001,45.589699],"type":"Point"}
}