{
  "type": "Feature",
  "properties": {
    "iso:country":"US",
    "sg:address":"34 NW Broadway",
    "sg:city":"Portland",
    "sg:classifiers":[
        {
            "category":"Professional",
            "type":"Services"
        }
    ],
    "sg:phone":"+1 503 222 6999",
    "sg:postcode":"97209",
    "sg:province":"OR",
    "wof:name":"Braketeam",
    "wof:placetype":"venue"
},
  "geometry": {"coordinates":[-122.677376,45.523522],"type":"Point"}
}