{
  "type": "Feature",
  "properties": {
    "addr:full":"10302 S A St La Grande OR 97850",
    "addr:housenumber":"10302",
    "addr:postcode":"97850",
    "addr:street":"S A St;Grande",
    "iso:country":"US",
    "sg:address":"10302 S A St",
    "sg:city":"La Grande",
    "sg:classifiers":[
        {
            "category":"Retail",
            "subcategory":"Repair Shop",
            "type":"Services"
        }
    ],
    "sg:phone":"+1 541 963 6228",
    "sg:postcode":"97850",
    "sg:province":"OR",
    "sg:tags":[
        "upholsterer"
    ],
    "wof:name":"Custom Trim Shop",
    "wof:placetype":"venue"
},
  "geometry": {"coordinates":[-118.044217,45.339206],"type":"Point"}
}