{
  "type": "Feature",
  "properties": {
    "addr:full":"67337 Parsons Ln Elgin OR 97827",
    "addr:housenumber":"67337",
    "addr:postcode":"97827",
    "addr:street":"Parsons Ln",
    "iso:country":"US",
    "sg:address":"67337 Parsons Ln",
    "sg:city":"Elgin",
    "sg:classifiers":[
        {
            "category":"Freight",
            "type":"Transportation"
        }
    ],
    "sg:phone":"+1 541 437 2455",
    "sg:postcode":"97827",
    "sg:province":"OR",
    "sg:tags":[
        "commercial",
        "storage"
    ],
    "wof:name":"D & S Storage",
    "wof:placetype":"venue"
},
  "geometry": {"coordinates":[-117.885925,45.592793],"type":"Point"}
}