{
  "type": "Feature",
  "properties": {
    "iso:country":"US",
    "sg:address":"4101 Kruse Way",
    "sg:city":"Lake Oswego",
    "sg:classifiers":[
        {
            "category":"Retail",
            "subcategory":"Auto Rental",
            "type":"Services"
        }
    ],
    "sg:phone":"+1 503 675 1102",
    "sg:postcode":"97035",
    "sg:province":"OR",
    "sg:tags":[
        "renting",
        "automobile"
    ],
    "wof:name":"Enterprise Rent-A-Car",
    "wof:placetype":"venue"
},
  "geometry": {"coordinates":[-122.72200599999999,45.417731],"type":"Point"}
}