{
  "type": "Feature",
  "properties": {
    "iso:country":"US",
    "sg:address":"16310 SE Katie Ct",
    "sg:city":"Portland",
    "sg:classifiers":[
        {
            "category":"Autos & Motor Vehicles",
            "subcategory":"Auto Supplies",
            "type":"Retail Goods"
        },
        {
            "category":"Wholesale",
            "subcategory":"Auto Parts",
            "type":"Manufacturing & Wholesale Goods"
        },
        {
            "category":"Retail",
            "subcategory":"Auto Repair",
            "type":"Services"
        }
    ],
    "sg:phone":"+1 503 659 3416",
    "sg:postcode":"97267",
    "sg:province":"OR",
    "sg:tags":[
        "automobile",
        "rebuilt-wholesale",
        "supplies-used",
        "rebuilt",
        "manufacturer"
    ],
    "sg:website":"http://www.economygarages.com",
    "wof:name":"John Fox Company",
    "wof:placetype":"venue"
},
  "geometry": {"coordinates":[-122.602419,45.404723],"type":"Point"}
}