{
  "type": "Feature",
  "properties": {
    "iso:country":"US",
    "sg:address":"93610 Grassy Knob Rd",
    "sg:city":"Sixes",
    "sg:classifiers":[
        {
            "category":"Building & Trades",
            "subcategory":"Construction",
            "type":"Services"
        }
    ],
    "sg:phone":"+1 541 332 2585",
    "sg:postcode":"97465",
    "sg:province":"OR",
    "sg:tags":[
        "carpenter"
    ],
    "wof:name":"C W Home Building",
    "wof:placetype":"venue"
},
  "geometry": {"coordinates":[-124.483428,42.803209],"type":"Point"}
}