{
  "type": "Feature",
  "properties": {
    "iso:country":"US",
    "sg:address":"1281 N Meyers Butte Rd",
    "sg:city":"Powell Butte",
    "sg:classifiers":[
        {
            "category":"Building & Trades",
            "subcategory":"Construction",
            "type":"Services"
        }
    ],
    "sg:phone":"+1 541 447 2853",
    "sg:postcode":"97753",
    "sg:province":"OR",
    "sg:tags":[
        "house",
        "general",
        "contractor"
    ],
    "wof:name":"Waibel Construction Inc",
    "wof:placetype":"venue"
},
  "geometry": {"coordinates":[-120.963812,44.298757],"type":"Point"}
}