{
  "type": "Feature",
  "properties": {
    "iso:country":"US",
    "sg:address":"1033 Young St",
    "sg:city":"Woodburn",
    "sg:classifiers":[
        {
            "category":"Personal",
            "subcategory":"Barber",
            "type":"Services"
        }
    ],
    "sg:phone":"+1 503 981 5154",
    "sg:postcode":"97071",
    "sg:province":"OR",
    "sg:tags":[
        "shop"
    ],
    "wof:name":"Leonard's Barber & Style",
    "wof:placetype":"venue"
},
  "geometry": {"coordinates":[-122.845527,45.137713],"type":"Point"}
}