{
  "type": "Feature",
  "properties": {
    "iso:country":"US",
    "sg:address":"513 SW 4th Avenue",
    "sg:city":"Portland",
    "sg:classifiers":[
        {
            "category":"Communications",
            "subcategory":"Newspaper",
            "type":"Services"
        },
        {
            "category":"Food & Beverages",
            "subcategory":"Groceries & Convenience Stores",
            "type":"Retail Goods"
        }
    ],
    "sg:phone":"+1 503 227 7060",
    "sg:postcode":"97204",
    "sg:province":"OR",
    "sg:tags":[
        "magazine"
    ],
    "wof:name":"Peterson's Fourth Avenue",
    "wof:placetype":"venue"
},
  "geometry": {"coordinates":[-122.675765,45.519687],"type":"Point"}
}