{
  "type": "Feature",
  "properties": {
    "addr:full":"3718 SW Marigold St Portland OR 97219",
    "addr:housenumber":"3718",
    "addr:postcode":"97219",
    "addr:street":"Sw Marigold St",
    "iso:country":"US",
    "sg:address":"3718 SW Marigold St",
    "sg:city":"Portland",
    "sg:classifiers":[
        {
            "category":"Sports & Exercise",
            "subcategory":"Golf",
            "type":"Entertainment"
        }
    ],
    "sg:phone":"+1 503 829 9763",
    "sg:postcode":"97219",
    "sg:province":"OR",
    "sg:tags":[
        "course",
        "public"
    ],
    "sg:website":"http://www.ranchgolfcourse.com",
    "wof:name":"Ranch Hill Golf Club",
    "wof:placetype":"venue"
},
  "geometry": {"coordinates":[-122.715509,45.460251],"type":"Point"}
}