{
  "type": "Feature",
  "properties": {
    "iso:country":"US",
    "sg:address":"31919 Oakville Rd",
    "sg:city":"Shedd",
    "sg:classifiers":[
        {
            "category":"Education",
            "subcategory":"Special Training",
            "type":"Public Place"
        }
    ],
    "sg:phone":"+1 541 752 7450",
    "sg:postcode":"97377",
    "sg:province":"OR",
    "wof:name":"Lighthouse Mennonite School",
    "wof:placetype":"venue"
},
  "geometry": {"coordinates":[-123.18900600000001,44.5058],"type":"Point"}
}