{
  "type": "Feature",
  "properties": {
    "iso:country":"US",
    "sg:address":"1004 S Main St",
    "sg:city":"Milton Freewater",
    "sg:classifiers":[
        {
            "category":"Restaurant",
            "type":"Food & Drink"
        }
    ],
    "sg:phone":"+1 541 938 6576",
    "sg:postcode":"97862",
    "sg:province":"OR",
    "sg:tags":[
        "eating"
    ],
    "wof:name":"M F Supper Club Restaurant",
    "wof:placetype":"venue"
},
  "geometry": {"coordinates":[-118.383702,45.926196],"type":"Point"}
}