{
  "type": "Feature",
  "properties": {
    "iso:country":"US",
    "sg:address":"2755 E Lone Oak Loop B",
    "sg:city":"Eugene",
    "sg:classifiers":[
        {
            "category":"Real Estate",
            "subcategory":"Real Estate Services",
            "type":"Services"
        },
        {
            "category":"Real Estate",
            "subcategory":"Real Estate Operator",
            "type":"Services"
        }
    ],
    "sg:phone":"+1 541 461 3060",
    "sg:postcode":"97404",
    "sg:province":"OR",
    "sg:tags":[
        "vacancy",
        "apartment",
        "rental",
        "finder",
        "listing"
    ],
    "wof:name":"Green Leaf Village",
    "wof:placetype":"venue"
},
  "geometry": {"coordinates":[-123.12496,44.101227],"type":"Point"}
}