{
  "type": "Feature",
  "properties": {
    "addr:full":"8125 W Hwy 126 Redmond OR 97756",
    "addr:housenumber":"8125",
    "addr:postcode":"97756",
    "addr:street":"W Hwy 126",
    "iso:country":"US",
    "sg:address":"8125 W Hwy 126",
    "sg:city":"Redmond",
    "sg:classifiers":[
        {
            "category":"Building & Trades",
            "subcategory":"Construction",
            "type":"Services"
        }
    ],
    "sg:phone":"+1 541 923 1079",
    "sg:postcode":"97756",
    "sg:province":"OR",
    "sg:tags":[
        "hanging",
        "contractor"
    ],
    "wof:name":"Van Blaricum Chris",
    "wof:placetype":"venue"
},
  "geometry": {"coordinates":[-121.268344,44.279032],"type":"Point"}
}