{
  "type": "Feature",
  "properties": {
    "addr:full":"2451 SW Cherry Park Rd Troutdale OR 97060",
    "addr:housenumber":"2451",
    "addr:postcode":"97060",
    "addr:street":"Sw Cherry Park Rd",
    "iso:country":"US",
    "sg:address":"2451 SW Cherry Park Rd",
    "sg:city":"Troutdale",
    "sg:classifiers":[
        {
            "category":"Food & Beverages",
            "subcategory":"Specialty",
            "type":"Retail Goods"
        }
    ],
    "sg:phone":"+1 503 674 8633",
    "sg:postcode":"97060",
    "sg:province":"OR",
    "wof:name":"AB Health Nutrition",
    "wof:placetype":"venue"
},
  "geometry": {"coordinates":[-122.412648,45.527783],"type":"Point"}
}