{
  "type": "Feature",
  "properties": {
    "iso:country":"US",
    "sg:address":"15020 SE Cedar Ave",
    "sg:city":"Portland",
    "sg:classifiers":[
        {
            "category":"Freight",
            "type":"Transportation"
        }
    ],
    "sg:phone":"+1 503 659 2966",
    "sg:postcode":"97267",
    "sg:province":"OR",
    "sg:tags":[
        "log",
        "trucker"
    ],
    "wof:name":"Richard Reed Trucking",
    "wof:placetype":"venue"
},
  "geometry": {"coordinates":[-122.64408400000001,45.416644],"type":"Point"}
}