{
  "type": "Feature",
  "properties": {
    "iso:country":"US",
    "sg:address":"2377 Oakmont Way",
    "sg:city":"Eugene",
    "sg:classifiers":[
        {
            "category":"Health Services",
            "subcategory":"Dentist",
            "type":"Services"
        }
    ],
    "sg:phone":"+1 541 225 5648",
    "sg:postcode":"97401",
    "sg:province":"OR",
    "sg:website":"http://crisdental.com",
    "wof:name":"crisdental",
    "wof:placetype":"venue"
},
  "geometry": {"coordinates":[-123.074258,44.066492],"type":"Point"}
}