{
  "type": "Feature",
  "properties": {
    "iso:country":"US",
    "sg:address":"4805 NE Glisan St",
    "sg:city":"Portland",
    "sg:classifiers":[
        {
            "category":"Health Services",
            "subcategory":"Doctor",
            "type":"Services"
        }
    ],
    "sg:phone":"+1 503 215 6029",
    "sg:postcode":"97213",
    "sg:province":"OR",
    "sg:tags":[
        "physician",
        "oncology",
        "surgeons",
        "surgeon",
        "surgery-general",
        "gynecologic"
    ],
    "sg:website":"http://www.oregonclinic.com",
    "wof:name":"Oregon Clinic The Radiation Oncology",
    "wof:placetype":"venue"
},
  "geometry": {"coordinates":[-122.614434,45.52652],"type":"Point"}
}