{
  "type": "Feature",
  "properties": {
    "iso:country":"US",
    "sg:address":"5713 NE Fremont Street",
    "sg:city":"Portland",
    "sg:classifiers":[
        {
            "category":"Coffee & Tea",
            "type":"Food & Drink"
        }
    ],
    "sg:phone":"+1 503 284 6097",
    "sg:postcode":"97213",
    "sg:province":"OR",
    "sg:website":"www.morningfixcoffee.com",
    "wof:name":"Morning Fix",
    "wof:placetype":"venue"
},
  "geometry": {"coordinates":[-122.60400199999999,45.548244],"type":"Point"}
}