{
  "type": "Feature",
  "properties": {
    "addr:full":"4440 Main St Springfield OR 97478",
    "addr:housenumber":"4440",
    "addr:postcode":"97478",
    "addr:street":"Main St",
    "iso:country":"US",
    "sg:address":"4440 Main St",
    "sg:city":"Springfield",
    "sg:classifiers":[
        {
            "category":"Retail",
            "subcategory":"Auto Repair",
            "type":"Services"
        }
    ],
    "sg:phone":"+1 541 744 6206",
    "sg:postcode":"97478",
    "sg:province":"OR",
    "sg:tags":[
        "machine",
        "automobile",
        "shop"
    ],
    "wof:name":"Engine Research & Development",
    "wof:placetype":"venue"
},
  "geometry": {"coordinates":[-122.95594199999999,44.045834],"type":"Point"}
}