{
  "type": "Feature",
  "properties": {
    "iso:country":"US",
    "sg:address":"4965 NW Skycrest Pkwy",
    "sg:city":"Portland",
    "sg:classifiers":[
        {
            "category":"Professional",
            "subcategory":"Business Services",
            "type":"Services"
        }
    ],
    "sg:phone":"+1 503 645 4076",
    "sg:postcode":"97229",
    "sg:province":"OR",
    "wof:name":"Skycrest Partnership",
    "wof:placetype":"venue"
},
  "geometry": {"coordinates":[-122.82548800000001,45.555527],"type":"Point"}
}