{
  "type": "Feature",
  "properties": {
    "addr:full":"24900 SE Stark St Ste 201 Gresham OR 97030",
    "addr:postcode":"24900;97030",
    "addr:street":"Se Stark St Ste 201",
    "iso:country":"US",
    "sg:address":"24900 SE Stark St Ste 201",
    "sg:city":"Gresham",
    "sg:classifiers":[
        {
            "category":"Health Services",
            "subcategory":"Doctor",
            "type":"Services"
        }
    ],
    "sg:phone":"+1 503 667 9000",
    "sg:postcode":"97030",
    "sg:province":"OR",
    "sg:tags":[
        "dermatologist"
    ],
    "wof:name":"Kazmierowski John A Phy",
    "wof:placetype":"venue"
},
  "geometry": {"coordinates":[-122.40799699999999,45.518902],"type":"Point"}
}