{
  "type": "Feature",
  "properties": {
    "addr:full":"145 NE 2nd Ave Hillsboro OR 97124",
    "addr:housenumber":"145",
    "addr:postcode":"97124",
    "addr:street":"Ne 2Nd Ave",
    "iso:country":"US",
    "sg:address":"145 NE 2nd Ave",
    "sg:city":"Hillsboro",
    "sg:classifiers":[
        {
            "category":"Government",
            "subcategory":"Office",
            "type":"Public Place"
        }
    ],
    "sg:phone":"+1 503 846 3443",
    "sg:postcode":"97124",
    "sg:province":"OR",
    "wof:name":"Honorable Nancy W Campbell",
    "wof:placetype":"venue"
},
  "geometry": {"coordinates":[-122.988039,45.523346],"type":"Point"}
}