{
  "type": "Feature",
  "properties": {
    "addr:full":"9833 N Portsmouth Ave Portland OR 97203",
    "addr:housenumber":"9833",
    "addr:postcode":"97203",
    "addr:street":"N Portsmouth Ave",
    "iso:country":"US",
    "sg:address":"9833 N Portsmouth Ave",
    "sg:city":"Portland",
    "sg:classifiers":[
        {
            "category":"Social Services",
            "type":"Services"
        }
    ],
    "sg:phone":"+1 503 286 1015",
    "sg:postcode":"97203",
    "sg:province":"OR",
    "sg:tags":[
        "organization",
        "welfare"
    ],
    "sg:website":"www.jyp.org",
    "wof:name":"Imani House Program",
    "wof:placetype":"venue"
},
  "geometry": {"coordinates":[-122.721154,45.592807],"type":"Point"}
}