{
  "type": "Feature",
  "properties": {
    "iso:country":"US",
    "sg:address":"22791 S Reid Rd",
    "sg:city":"Estacada",
    "sg:classifiers":[
        {
            "category":"Manufacturing",
            "subcategory":"Tools & Machinery",
            "type":"Manufacturing & Wholesale Goods"
        }
    ],
    "sg:phone":"+1 503 630 3994",
    "sg:postcode":"97023",
    "sg:province":"OR",
    "sg:tags":[
        "designed",
        "built"
    ],
    "wof:name":"Soll & Soll",
    "wof:placetype":"venue"
},
  "geometry": {"coordinates":[-122.348651,45.275112],"type":"Point"}
}