{
  "type": "Feature",
  "properties": {
    "iso:country":"US",
    "sg:address":"1208 NE Montgomery Pl",
    "sg:city":"Albany",
    "sg:classifiers":[
        {
            "category":"Professional",
            "subcategory":"Detective & Security Services",
            "type":"Services"
        }
    ],
    "sg:phone":"+1 541 917 8819",
    "sg:postcode":"97321",
    "sg:province":"OR",
    "sg:tags":[
        "information",
        "bureau"
    ],
    "wof:name":"Mikes Pool And Spa Service",
    "wof:placetype":"venue"
},
  "geometry": {"coordinates":[-123.10148,44.652419],"type":"Point"}
}