{
  "type": "Feature",
  "properties": {
    "addr:full":"2580 Willakenzie Rd Eugene OR 97401",
    "addr:postcode":"2580;97401",
    "addr:street":"Willakenzie Rd",
    "iso:country":"US",
    "sg:address":"2580 Willakenzie Rd",
    "sg:city":"Eugene",
    "sg:classifiers":[
        {
            "category":"Building & Trades",
            "subcategory":"Construction",
            "type":"Services"
        }
    ],
    "sg:phone":"+1 541 338 8495",
    "sg:postcode":"97401",
    "sg:province":"OR",
    "sg:tags":[
        "general",
        "contractor"
    ],
    "wof:name":"VIK Construction",
    "wof:placetype":"venue"
},
  "geometry": {"coordinates":[-123.074117,44.079313],"type":"Point"}
}