{
  "type": "Feature",
  "properties": {
    "addr:full":"5125 Auburn Rd NE Salem OR 97317",
    "addr:housenumber":"5125",
    "addr:postcode":"97317",
    "addr:street":"Auburn Rd Ne",
    "iso:country":"US",
    "sg:address":"5125 Auburn Rd NE",
    "sg:city":"Salem",
    "sg:classifiers":[
        {
            "category":"Manufacturing",
            "subcategory":"Buildings",
            "type":"Manufacturing & Wholesale Goods"
        },
        {
            "category":"Building & Trades",
            "subcategory":"Construction",
            "type":"Services"
        }
    ],
    "sg:phone":"+1 503 363 9775",
    "sg:postcode":"97317",
    "sg:province":"OR",
    "sg:tags":[
        "home",
        "builder",
        "contractor"
    ],
    "wof:name":"Pudding River Builders",
    "wof:placetype":"venue"
},
  "geometry": {"coordinates":[-122.956293,44.936291],"type":"Point"}
}