{
  "type": "Feature",
  "properties": {
    "iso:country":"US",
    "sg:address":"1351 Poplar St",
    "sg:city":"Sweet Home",
    "sg:classifiers":[
        {
            "category":"Building & Trades",
            "subcategory":"Construction",
            "type":"Services"
        }
    ],
    "sg:phone":"+1 541 367 2757",
    "sg:postcode":"97386",
    "sg:province":"OR",
    "sg:tags":[
        "contractor"
    ],
    "wof:name":"Aronson & Son",
    "wof:placetype":"venue"
},
  "geometry": {"coordinates":[-122.72783800000001,44.40068],"type":"Point"}
}