{
  "type": "Feature",
  "properties": {
    "addr:full":"2808 NE M L King Blvd Portland OR 97212",
    "addr:housenumber":"2808",
    "addr:postcode":"97212",
    "addr:street":"Ne M L King Blvd",
    "iso:country":"US",
    "sg:address":"2808 NE M L King Blvd",
    "sg:city":"Portland",
    "sg:classifiers":[
        {
            "category":"Insurance",
            "subcategory":"Insurance Agent",
            "type":"Services"
        },
        {
            "category":"Insurance",
            "subcategory":"Hazard Insurance",
            "type":"Services"
        },
        {
            "category":"Insurance",
            "subcategory":"Title Insurance",
            "type":"Services"
        },
        {
            "category":"Insurance",
            "subcategory":"Life Insurance",
            "type":"Services"
        }
    ],
    "sg:phone":"+1 503 284 4228",
    "sg:postcode":"97212",
    "sg:province":"OR",
    "sg:tags":[
        "business",
        "auto",
        "commercial",
        "homeowner",
        "motorcycle",
        "renter"
    ],
    "wof:name":"Allstate Insurance Company - Anthony Armstrong",
    "wof:placetype":"venue"
},
  "geometry": {"coordinates":[-122.66153,45.543042],"type":"Point"}
}