{
  "type": "Feature",
  "properties": {
    "iso:country":"US",
    "sg:address":"4880 State Hwy 66",
    "sg:city":"Ashland",
    "sg:classifiers":[
        {
            "category":"Farming",
            "subcategory":"Livestock Farm",
            "type":"Manufacturing & Wholesale Goods"
        }
    ],
    "sg:phone":"+1 541 488 1779",
    "sg:postcode":"97520",
    "sg:province":"OR",
    "sg:tags":[
        "animal",
        "general"
    ],
    "wof:name":"Oak Creek Ranch",
    "wof:placetype":"venue"
},
  "geometry": {"coordinates":[-122.63456600000001,42.159744],"type":"Point"}
}