{
  "type": "Feature",
  "properties": {
    "iso:country":"US",
    "sg:address":"1813 W Harvard Ave",
    "sg:city":"Roseburg",
    "sg:classifiers":[
        {
            "category":"Health Services",
            "subcategory":"Doctor",
            "type":"Services"
        }
    ],
    "sg:phone":"+1 541 673 3447",
    "sg:postcode":"97470",
    "sg:province":"OR",
    "sg:tags":[
        "medical"
    ],
    "wof:name":"Gerald Engstrom MD",
    "wof:placetype":"venue"
},
  "geometry": {"coordinates":[-123.369861,43.2135],"type":"Point"}
}