{
  "type": "Feature",
  "properties": {
    "iso:country":"US",
    "sg:address":"2636 NE Belvue St",
    "sg:city":"Corvallis",
    "sg:classifiers":[
        {
            "category":"Professional",
            "subcategory":"Management & Consulting",
            "type":"Services"
        }
    ],
    "sg:phone":"+1 541 758 1212",
    "sg:postcode":"97330",
    "sg:province":"OR",
    "sg:tags":[
        "retail",
        "direct",
        "sales"
    ],
    "wof:name":"Earth 2 O",
    "wof:placetype":"venue"
},
  "geometry": {"coordinates":[-123.248819,44.593854],"type":"Point"}
}