{
  "type": "Feature",
  "properties": {
    "iso:country":"US",
    "sg:address":"1363 Edgewater St NW",
    "sg:city":"Salem",
    "sg:classifiers":[
        {
            "category":"Retail",
            "subcategory":"Auto Repair",
            "type":"Services"
        }
    ],
    "sg:phone":"+1 503 588 7066",
    "sg:postcode":"97304",
    "sg:province":"OR",
    "sg:tags":[
        "general"
    ],
    "wof:name":"Woody & Sons",
    "wof:placetype":"venue"
},
  "geometry": {"coordinates":[-123.06029700000001,44.939764],"type":"Point"}
}