{
  "type": "Feature",
  "properties": {
    "iso:country":"US",
    "sg:address":"3970 High St",
    "sg:city":"Eugene",
    "sg:classifiers":[
        {
            "category":"Building & Trades",
            "subcategory":"Landscaping Services",
            "type":"Services"
        }
    ],
    "sg:phone":"+1 541 349 0882",
    "sg:postcode":"97405",
    "sg:province":"OR",
    "sg:tags":[
        "landscape"
    ],
    "wof:name":"Triditional Gardens",
    "wof:placetype":"venue"
},
  "geometry": {"coordinates":[-123.089382,44.013035],"type":"Point"}
}