{
  "type": "Feature",
  "properties": {
    "iso:country":"US",
    "sg:address":"203 Hwy 20",
    "sg:city":"Hines",
    "sg:classifiers":[
        {
            "category":"Food & Beverages",
            "subcategory":"Groceries & Convenience Stores",
            "type":"Retail Goods"
        }
    ],
    "sg:phone":"+1 541 573 6341",
    "sg:postcode":"97738",
    "sg:province":"OR",
    "sg:tags":[
        "market"
    ],
    "wof:name":"Hines Market",
    "wof:placetype":"venue"
},
  "geometry": {"coordinates":[-119.084611,43.558866],"type":"Point"}
}