{
  "type": "Feature",
  "properties": {
    "iso:country":"US",
    "sg:address":"1010 1st St SE",
    "sg:city":"Bandon",
    "sg:classifiers":[
        {
            "category":"Professional",
            "subcategory":"Lawyer & Legal Services",
            "type":"Services"
        }
    ],
    "sg:phone":"+1 541 347 3757",
    "sg:postcode":"97411",
    "sg:province":"OR",
    "sg:tags":[
        "employee",
        "benefit",
        "worker",
        "attorney",
        "compensation"
    ],
    "sg:website":"http://www.blackchapman.com",
    "wof:name":"Black Chapman Webber & Stevens",
    "wof:placetype":"venue"
},
  "geometry": {"coordinates":[-124.399984,43.119801],"type":"Point"}
}