{
  "type": "Feature",
  "properties": {
    "iso:country":"US",
    "sg:address":"5512 SW Kelly Ave",
    "sg:city":"Portland",
    "sg:classifiers":[
        {
            "category":"Personal",
            "subcategory":"Beauty Salon",
            "type":"Services"
        }
    ],
    "sg:phone":"+1 503 294 1948",
    "sg:postcode":"97239",
    "sg:province":"OR",
    "wof:name":"David R Prouty Hair Design",
    "wof:placetype":"venue"
},
  "geometry": {"coordinates":[-122.675753,45.483719],"type":"Point"}
}