{
  "type": "Feature",
  "properties": {
    "addr:full":"2791 Victoria Ct Medford OR 97504",
    "addr:housenumber":"2791",
    "addr:postcode":"97504",
    "addr:street":"Victoria Ct",
    "iso:country":"US",
    "sg:address":"2791 Victoria Ct",
    "sg:city":"Medford",
    "sg:classifiers":[
        {
            "category":"Professional",
            "subcategory":"Engineering",
            "type":"Services"
        }
    ],
    "sg:phone":"+1 541 773 6417",
    "sg:postcode":"97504",
    "sg:province":"OR",
    "wof:name":"J JS Cad & Design",
    "wof:placetype":"venue"
},
  "geometry": {"coordinates":[-122.84041000000001,42.346318],"type":"Point"}
}