{
  "type": "Feature",
  "properties": {
    "iso:country":"US",
    "sg:address":"2324 NE 82nd Ave",
    "sg:city":"Portland",
    "sg:classifiers":[
        {
            "category":"Manufacturing",
            "subcategory":"Metals",
            "type":"Manufacturing & Wholesale Goods"
        }
    ],
    "sg:phone":"+1 503 252 4322",
    "sg:postcode":"97220",
    "sg:province":"OR",
    "sg:tags":[
        "foundry"
    ],
    "wof:name":"Hanset Sheet Metal",
    "wof:placetype":"venue"
},
  "geometry": {"coordinates":[-122.578853,45.538893],"type":"Point"}
}