{
  "type": "Feature",
  "properties": {
    "iso:country":"US",
    "sg:address":"1405 US Hwy 101",
    "sg:city":"Lincoln City",
    "sg:classifiers":[
        {
            "category":"Utilities",
            "subcategory":"Natural Gas",
            "type":"Services"
        }
    ],
    "sg:phone":"+1 541 994 2111",
    "sg:postcode":"97367",
    "sg:province":"OR",
    "sg:tags":[
        "company"
    ],
    "wof:name":"Northwest Natural Gas Company",
    "wof:placetype":"venue"
},
  "geometry": {"coordinates":[-124.013659,44.957622],"type":"Point"}
}