{
  "type": "Feature",
  "properties": {
    "addr:full":"1507 SE 122nd Ave Portland OR 97233",
    "addr:housenumber":"1507",
    "addr:postcode":"97233",
    "addr:street":"Se 122Nd Ave",
    "iso:country":"US",
    "sg:address":"1507 SE 122nd Ave",
    "sg:city":"Portland",
    "sg:classifiers":[
        {
            "category":"Communications",
            "subcategory":"Newspaper",
            "type":"Services"
        }
    ],
    "sg:phone":"+1 503 954 1001",
    "sg:postcode":"97233",
    "sg:province":"OR",
    "sg:tags":[
        "print",
        "medium"
    ],
    "wof:name":"Latina Style Magazine",
    "wof:placetype":"venue"
},
  "geometry": {"coordinates":[-122.537845,45.512848],"type":"Point"}
}