{
  "type": "Feature",
  "properties": {
    "addr:full":"8638 N Lombard St Portland OR 97203",
    "addr:housenumber":"8638",
    "addr:postcode":"97203",
    "addr:street":"N Lombard St",
    "iso:country":"US",
    "sg:address":"8638 N Lombard St",
    "sg:city":"Portland",
    "sg:classifiers":[
        {
            "category":"Cinema",
            "subcategory":"Movie Theater",
            "type":"Entertainment"
        }
    ],
    "sg:phone":"+1 503 735 1946",
    "sg:postcode":"97203",
    "sg:province":"OR",
    "wof:name":"Raindog Playwrights Project",
    "wof:placetype":"venue"
},
  "geometry": {"coordinates":[-122.755505,45.589994],"type":"Point"}
}