{
  "type": "Feature",
  "properties": {
    "iso:country":"US",
    "sg:address":"11537 SE Flavel St",
    "sg:city":"Portland",
    "sg:classifiers":[
        {
            "category":"Health Services",
            "subcategory":"Podiatrist",
            "type":"Services"
        }
    ],
    "sg:phone":"+1 503 761 8125",
    "sg:postcode":"97266",
    "sg:province":"OR",
    "sg:tags":[
        "equipment",
        "supply"
    ],
    "wof:name":"About Magnetic Health",
    "wof:placetype":"venue"
},
  "geometry": {"coordinates":[-122.54445699999999,45.4684],"type":"Point"}
}