{
  "type": "Feature",
  "properties": {
    "addr:full":"17980 Wilson River Hwy Tillamook OR 97141",
    "addr:housenumber":"17980",
    "addr:postcode":"97141",
    "addr:street":"Wilson River Hwy",
    "iso:country":"US",
    "sg:address":"17980 Wilson River Hwy",
    "sg:city":"Tillamook",
    "sg:classifiers":[
        {
            "category":"Professional",
            "subcategory":"Computer Services",
            "type":"Services"
        }
    ],
    "sg:phone":"+1 503 842 8309",
    "sg:postcode":"97141",
    "sg:province":"OR",
    "sg:tags":[
        "consulting",
        "retail"
    ],
    "wof:name":"Wood John",
    "wof:placetype":"venue"
},
  "geometry": {"coordinates":[-123.689762,45.486332],"type":"Point"}
}