{
  "type": "Feature",
  "properties": {
    "addr:full":"2440 SE 89th Ave Portland OR 97216",
    "addr:housenumber":"2440",
    "addr:postcode":"97216",
    "addr:street":"Se 89Th Ave",
    "iso:country":"US",
    "sg:address":"2440 SE 89th Ave",
    "sg:city":"Portland",
    "sg:classifiers":[
        {
            "category":"Wholesale",
            "subcategory":"Machinery & Supplies",
            "type":"Manufacturing & Wholesale Goods"
        }
    ],
    "sg:phone":"+1 503 777 3800",
    "sg:postcode":"97216",
    "sg:province":"OR",
    "sg:tags":[
        "equipment",
        "establishment"
    ],
    "wof:name":"Ceragem Portland Corp",
    "wof:placetype":"venue"
},
  "geometry": {"coordinates":[-122.57217900000001,45.507557],"type":"Point"}
}