{
  "type": "Feature",
  "properties": {
    "iso:country":"US",
    "sg:address":"1119 W 2nd St",
    "sg:city":"The Dalles",
    "sg:classifiers":[
        {
            "category":"Autos & Motor Vehicles",
            "subcategory":"Recreational Vehicle Sales",
            "type":"Retail Goods"
        }
    ],
    "sg:phone":"+1 541 296 3761",
    "sg:postcode":"97058",
    "sg:province":"OR",
    "wof:name":"Brace Brothers",
    "wof:placetype":"venue"
},
  "geometry": {"coordinates":[-121.19480799999999,45.607023],"type":"Point"}
}