{
  "type": "Feature",
  "properties": {
    "addr:full":"1410 SW Broadway Portland OR 97201",
    "addr:housenumber":"1410",
    "addr:postcode":"97201",
    "addr:street":"Sw Broadway",
    "iso:country":"US",
    "sg:address":"1410 SW Broadway",
    "sg:city":"Portland",
    "sg:classifiers":[
        {
            "category":"Real Estate",
            "subcategory":"Real Estate Operator",
            "type":"Services"
        }
    ],
    "sg:phone":"+1 503 224 2308",
    "sg:postcode":"97201",
    "sg:province":"OR",
    "sg:tags":[
        "apartment"
    ],
    "wof:name":"Regency Apartments",
    "wof:placetype":"venue"
},
  "geometry": {"coordinates":[-122.682168,45.514605],"type":"Point"}
}