{
  "type": "Feature",
  "properties": {
    "addr:full":"111 S Miller St Rockaway Beach OR 97136",
    "addr:housenumber":"111",
    "addr:postcode":"97136",
    "addr:street":"S Miller St",
    "iso:country":"US",
    "sg:address":"111 S Miller St",
    "sg:city":"Rockaway Beach",
    "sg:classifiers":[
        {
            "category":"Health Services",
            "subcategory":"Doctor",
            "type":"Services"
        }
    ],
    "sg:phone":"+1 503 355 2700",
    "sg:postcode":"97136",
    "sg:province":"OR",
    "sg:tags":[
        "physician",
        "surgeon"
    ],
    "wof:name":"Tillamook County Health Dept",
    "wof:placetype":"venue"
},
  "geometry": {"coordinates":[-123.94430699999999,45.612525],"type":"Point"}
}