{
  "type": "Feature",
  "properties": {
    "iso:country":"US",
    "sg:address":"2175 US Hwy 101",
    "sg:city":"Florence",
    "sg:classifiers":[
        {
            "category":"Restaurant",
            "type":"Food & Drink"
        }
    ],
    "sg:phone":"+1 541 997 2931",
    "sg:postcode":"97439",
    "sg:province":"OR",
    "sg:tags":[
        "eating"
    ],
    "wof:name":"Lazy Lady Coffee & Espresso",
    "wof:placetype":"venue"
},
  "geometry": {"coordinates":[-124.101384,43.985245],"type":"Point"}
}