{
  "type": "Feature",
  "properties": {
    "iso:country":"US",
    "sg:address":"1916 NE 129th Pl",
    "sg:city":"Portland",
    "sg:classifiers":[
        {
            "category":"Professional",
            "subcategory":"Business Services",
            "type":"Services"
        }
    ],
    "sg:phone":"+1 503 261 1570",
    "sg:postcode":"97230",
    "sg:province":"OR",
    "sg:tags":[
        "sewing",
        "contractor"
    ],
    "wof:name":"Golden Manufacturing Company",
    "wof:placetype":"venue"
},
  "geometry": {"coordinates":[-122.530452,45.537092],"type":"Point"}
}