{
  "type": "Feature",
  "properties": {
    "iso:country":"US",
    "sg:address":"8235 NE Beech St",
    "sg:city":"Portland",
    "sg:classifiers":[
        {
            "category":"Professional",
            "subcategory":"Business Services",
            "type":"Services"
        }
    ],
    "sg:phone":"+1 503 287 1842",
    "sg:postcode":"97220",
    "sg:province":"OR",
    "wof:name":"Action Accessories LLC",
    "wof:placetype":"venue"
},
  "geometry": {"coordinates":[-122.576374,45.549645],"type":"Point"}
}