{
  "type": "Feature",
  "properties": {
    "iso:country":"US",
    "sg:address":"22075 SW Lebeau Rd",
    "sg:city":"Sherwood",
    "sg:classifiers":[
        {
            "category":"Farming",
            "subcategory":"Vineyard",
            "type":"Manufacturing & Wholesale Goods"
        }
    ],
    "sg:phone":"+1 503 625 1978",
    "sg:postcode":"97140",
    "sg:province":"OR",
    "wof:name":"Alloro Vineyard",
    "wof:placetype":"venue"
},
  "geometry": {"coordinates":[-122.909066,45.369672],"type":"Point"}
}