{
  "type": "Feature",
  "properties": {
    "addr:full":"8800 Doughty Rd Bay City OR 97107",
    "addr:postcode":"8800;97107",
    "addr:street":"Doughty Rd",
    "iso:country":"US",
    "sg:address":"8800 Doughty Rd",
    "sg:city":"Bay City",
    "sg:classifiers":[
        {
            "category":"Building & Trades",
            "subcategory":"Construction",
            "type":"Services"
        }
    ],
    "sg:phone":"+1 503 377 2391",
    "sg:postcode":"97107",
    "sg:province":"OR",
    "sg:tags":[
        "general",
        "commercial",
        "family",
        "contractor"
    ],
    "wof:name":"Tim Hall Builders",
    "wof:placetype":"venue"
},
  "geometry": {"coordinates":[-123.869404,45.518116],"type":"Point"}
}