{
  "type": "Feature",
  "properties": {
    "iso:country":"US",
    "sg:address":"10184 SW Park Way",
    "sg:city":"Portland",
    "sg:phone":"+1 503 291 5082",
    "sg:postcode":"97225",
    "sg:province":"OR",
    "wof:name":"Cascade Enforcement Agency",
    "wof:placetype":"venue"
},
  "geometry": {"coordinates":[-122.780779,45.507646],"type":"Point"}
}