{
  "type": "Feature",
  "properties": {
    "iso:country":"US",
    "sg:address":"9901 N Hurst Ave",
    "sg:city":"Portland",
    "sg:classifiers":[
        {
            "category":"Manufacturing",
            "subcategory":"Food",
            "type":"Manufacturing & Wholesale Goods"
        }
    ],
    "sg:phone":"+1 503 289 1221",
    "sg:postcode":"97203",
    "sg:province":"OR",
    "sg:tags":[
        "mfg"
    ],
    "wof:name":"Pacific Greece",
    "wof:placetype":"venue"
},
  "geometry": {"coordinates":[-122.70958,45.592922],"type":"Point"}
}