{
  "type": "Feature",
  "properties": {
    "iso:country":"US",
    "sg:address":"1005 Green Acres Rd",
    "sg:city":"Eugene",
    "sg:classifiers":[
        {
            "category":"Shopping",
            "type":"Retail Goods"
        }
    ],
    "sg:phone":"+1 541 342 1098",
    "sg:postcode":"97408",
    "sg:province":"OR",
    "sg:tags":[
        "merchandise"
    ],
    "wof:name":"Nextel Store",
    "wof:placetype":"venue"
},
  "geometry": {"coordinates":[-123.097047,44.093914],"type":"Point"}
}