{
  "type": "Feature",
  "properties": {
    "addr:full":"2780 SW Rutland Ter Portland OR 97205",
    "addr:housenumber":"2780",
    "addr:postcode":"97205",
    "addr:street":"Sw Rutland Ter",
    "iso:country":"US",
    "sg:address":"2780 SW Rutland Ter",
    "sg:city":"Portland",
    "sg:classifiers":[
        {
            "category":"Shopping",
            "subcategory":"Pets & Pet Supplies",
            "type":"Retail Goods"
        }
    ],
    "sg:phone":"+1 503 224 5077",
    "sg:postcode":"97205",
    "sg:province":"OR",
    "sg:tags":[
        "furnishing",
        "dog",
        "store",
        "cat"
    ],
    "wof:name":"Portlandpetcommunity.Com",
    "wof:placetype":"venue"
},
  "geometry": {"coordinates":[-122.707688,45.522642],"type":"Point"}
}