{
  "type": "Feature",
  "properties": {
    "iso:country":"US",
    "sg:address":"1603 Sherman Ave",
    "sg:city":"North Bend",
    "sg:classifiers":[
        {
            "category":"Restaurant",
            "type":"Food & Drink"
        }
    ],
    "sg:phone":"+1 541 756 2710",
    "sg:postcode":"97459",
    "sg:province":"OR",
    "sg:tags":[
        "eating"
    ],
    "wof:name":"Mom's Kitchen",
    "wof:placetype":"venue"
},
  "geometry": {"coordinates":[-124.223967,43.411832],"type":"Point"}
}