{
  "type": "Feature",
  "properties": {
    "iso:country":"US",
    "sg:address":"4411 N Kerby Ave",
    "sg:city":"Portland",
    "sg:classifiers":[
        {
            "category":"Education",
            "subcategory":"Special Training",
            "type":"Public Place"
        },
        {
            "category":"Communications",
            "type":"Services"
        }
    ],
    "sg:phone":"+1 503 331 6989",
    "sg:postcode":"97217",
    "sg:province":"OR",
    "sg:tags":[
        "translator",
        "school",
        "language",
        "interpreter"
    ],
    "wof:name":"Kelley & Sons Inc",
    "wof:placetype":"venue"
},
  "geometry": {"coordinates":[-122.672275,45.555101],"type":"Point"}
}