{
  "type": "Feature",
  "properties": {
    "addr:full":"3015 NW Grant Pl Corvallis OR 97330",
    "addr:housenumber":"3015",
    "addr:postcode":"97330",
    "addr:street":"Nw Grant Pl",
    "iso:country":"US",
    "sg:address":"3015 NW Grant Pl",
    "sg:city":"Corvallis",
    "sg:classifiers":[
        {
            "category":"Building & Trades",
            "subcategory":"Landscaping Services",
            "type":"Services"
        }
    ],
    "sg:phone":"+1 541 758 5193",
    "sg:postcode":"97330",
    "sg:province":"OR",
    "sg:tags":[
        "landscape"
    ],
    "wof:name":"Trillium Landscaping Inc",
    "wof:placetype":"venue"
},
  "geometry": {"coordinates":[-123.28516500000001,44.578903],"type":"Point"}
}