{
  "type": "Feature",
  "properties": {
    "addr:full":"73965 London Rd Cottage Grove OR 97424",
    "addr:housenumber":"73965",
    "addr:postcode":"97424",
    "addr:street":"London Rd",
    "iso:country":"US",
    "sg:address":"73965 London Rd",
    "sg:city":"Cottage Grove",
    "sg:classifiers":[
        {
            "category":"Recreation",
            "type":"Entertainment"
        }
    ],
    "sg:phone":"+1 541 942 3771",
    "sg:postcode":"97424",
    "sg:province":"OR",
    "sg:tags":[
        "house",
        "mail"
    ],
    "wof:name":"Al Kidwell Designs Al Kid",
    "wof:placetype":"venue"
},
  "geometry": {"coordinates":[-123.076505,43.666761],"type":"Point"}
}