{
  "type": "Feature",
  "properties": {
    "addr:full":"4509 S 6th St Klamath Falls OR 97603",
    "addr:housenumber":"4509",
    "addr:postcode":"97603",
    "addr:street":"S 6Th St",
    "iso:country":"US",
    "sg:address":"4509 S 6th St",
    "sg:city":"Klamath Falls",
    "sg:classifiers":[
        {
            "category":"Professional",
            "subcategory":"Computer Services",
            "type":"Services"
        }
    ],
    "sg:phone":"+1 541 884 6492",
    "sg:postcode":"97603",
    "sg:province":"OR",
    "sg:tags":[
        "repair"
    ],
    "wof:name":"Advanced Business Systems",
    "wof:placetype":"venue"
},
  "geometry": {"coordinates":[-121.73363000000001,42.206575],"type":"Point"}
}