{
  "type": "Feature",
  "properties": {
    "iso:country":"US",
    "sg:address":"404 N Main St",
    "sg:city":"Phoenix",
    "sg:classifiers":[
        {
            "category":"Wholesale",
            "subcategory":"Medical Equipment & Supplies",
            "type":"Manufacturing & Wholesale Goods"
        },
        {
            "category":"Manufacturing",
            "subcategory":"Chemicals & Compounds",
            "type":"Manufacturing & Wholesale Goods"
        },
        {
            "category":"Shopping",
            "subcategory":"Pharmacy",
            "type":"Retail Goods"
        }
    ],
    "sg:phone":"+1 541 535 1561",
    "sg:postcode":"97535",
    "sg:province":"OR",
    "sg:tags":[
        "pharmaceutical",
        "product",
        "health",
        "home",
        "care"
    ],
    "wof:name":"Phoenix Pharmacy",
    "wof:placetype":"venue"
},
  "geometry": {"coordinates":[-122.817577,42.276008],"type":"Point"}
}