{
  "type": "Feature",
  "properties": {
    "iso:country":"US",
    "sg:address":"463 Hollyhock Pl N",
    "sg:city":"Salem",
    "sg:classifiers":[
        {
            "category":"Professional",
            "type":"Services"
        }
    ],
    "sg:phone":"+1 503 390 0533",
    "sg:postcode":"97303",
    "sg:province":"OR",
    "wof:name":"Darrell Huskey",
    "wof:placetype":"venue"
},
  "geometry": {"coordinates":[-123.031437,44.980271],"type":"Point"}
}