{
  "type": "Feature",
  "properties": {
    "addr:full":"153 SW 5th St Redmond OR 97756",
    "addr:housenumber":"153",
    "addr:postcode":"97756",
    "addr:street":"Sw 5Th St",
    "iso:country":"US",
    "sg:address":"153 SW 5th St",
    "sg:city":"Redmond",
    "sg:classifiers":[
        {
            "category":"Insurance",
            "subcategory":"Insurance Agent",
            "type":"Services"
        },
        {
            "category":"Banks & Credit Unions",
            "subcategory":"Bank",
            "type":"Services"
        }
    ],
    "sg:phone":"+1 541 548 2911",
    "sg:postcode":"97756",
    "sg:province":"OR",
    "sg:tags":[
        "title",
        "escrow"
    ],
    "wof:name":"Western Title & Escrow Inc",
    "wof:placetype":"venue"
},
  "geometry": {"coordinates":[-121.173281,44.275992],"type":"Point"}
}