{
  "type": "Feature",
  "properties": {
    "addr:full":"12840 SW Canyon Rd Beaverton OR 97005",
    "addr:housenumber":"12840",
    "addr:postcode":"97005",
    "addr:street":"Sw Canyon Rd",
    "iso:country":"US",
    "sg:address":"12840 SW Canyon Rd",
    "sg:city":"Beaverton",
    "sg:classifiers":[
        {
            "category":"Banks & Credit Unions",
            "subcategory":"Bank",
            "type":"Services"
        }
    ],
    "sg:phone":"+1 503 643 4622",
    "sg:postcode":"97005",
    "sg:province":"OR",
    "sg:tags":[
        "mortgage",
        "loan",
        "broker",
        "real estate"
    ],
    "wof:name":"Columbia Funding Group Inc",
    "wof:placetype":"venue"
},
  "geometry": {"coordinates":[-122.80686900000001,45.488272],"type":"Point"}
}