{
  "type": "Feature",
  "properties": {
    "iso:country":"US",
    "sg:address":"11770 SW Tiedeman Ave",
    "sg:city":"Portland",
    "sg:classifiers":[
        {
            "category":"Building & Trades",
            "subcategory":"Landscaping Services",
            "type":"Services"
        }
    ],
    "sg:phone":"+1 503 684 3915",
    "sg:postcode":"97223",
    "sg:province":"OR",
    "wof:name":"Oriental Pruning",
    "wof:placetype":"venue"
},
  "geometry": {"coordinates":[-122.782918,45.436131],"type":"Point"}
}