{
  "type": "Feature",
  "properties": {
    "addr:full":"6205 NE Prescott St Portland OR 97218",
    "addr:housenumber":"6205",
    "addr:postcode":"97218",
    "addr:street":"Ne Prescott St",
    "iso:country":"US",
    "sg:address":"6205 NE Prescott St",
    "sg:city":"Portland",
    "sg:classifiers":[
        {
            "category":"Restaurant",
            "type":"Food & Drink"
        }
    ],
    "sg:phone":"+1 503 287 8495",
    "sg:postcode":"97218",
    "sg:province":"OR",
    "sg:tags":[
        "breakfast",
        "eating",
        "brunch"
    ],
    "wof:name":"Prescott Cafe",
    "wof:placetype":"venue"
},
  "geometry": {"coordinates":[-122.59899900000001,45.555599],"type":"Point"}
}