{
  "type": "Feature",
  "properties": {
    "addr:full":"1445 Acacia Dr S Salem OR 97302",
    "addr:housenumber":"1445",
    "addr:postcode":"97302",
    "addr:street":"Acacia Dr S",
    "iso:country":"US",
    "sg:address":"1445 Acacia Dr S",
    "sg:city":"Salem",
    "sg:classifiers":[
        {
            "category":"Personal",
            "type":"Services"
        }
    ],
    "sg:phone":"+1 503 364 8518",
    "sg:postcode":"97302",
    "sg:province":"OR",
    "sg:tags":[
        "miscellaneous",
        "errand"
    ],
    "wof:name":"Let's Create",
    "wof:placetype":"venue"
},
  "geometry": {"coordinates":[-123.06677500000001,44.910505],"type":"Point"}
}