{
  "type": "Feature",
  "properties": {
    "addr:full":"8307 SE Monterey Ave Clackamas OR 97086",
    "addr:housenumber":"8307",
    "addr:postcode":"97086",
    "addr:street":"Se Monterey Ave",
    "iso:country":"US",
    "sg:address":"8307 SE Monterey Ave",
    "sg:city":"Clackamas",
    "sg:classifiers":[
        {
            "category":"Personal",
            "subcategory":"Beauty Salon",
            "type":"Services"
        },
        {
            "category":"Education",
            "subcategory":"Vocational School",
            "type":"Public Place"
        }
    ],
    "sg:phone":"+1 503 659 2834",
    "sg:postcode":"97086",
    "sg:province":"OR",
    "sg:tags":[
        "spa",
        "cosmetology"
    ],
    "sg:website":"www.nwcollege.edu/",
    "wof:name":"Northwest College of Hair Design",
    "wof:placetype":"venue"
},
  "geometry": {"coordinates":[-122.576947,45.438305],"type":"Point"}
}