{
  "type": "Feature",
  "properties": {
    "iso:country":"US",
    "sg:address":"888 SW 5th Avenue Suite 300",
    "sg:city":"Portland",
    "sg:classifiers":[
        {
            "category":"Professional",
            "subcategory":"Lawyer & Legal Services",
            "type":"Services"
        }
    ],
    "sg:phone":"+1 503 228 6351",
    "sg:postcode":"97204",
    "sg:province":"OR",
    "sg:website":"www.bullivant.com",
    "wof:name":"Pettit Holly",
    "wof:placetype":"venue"
},
  "geometry": {"coordinates":[-122.678342,45.517444],"type":"Point"}
}