{
  "type": "Feature",
  "properties": {
    "iso:country":"US",
    "sg:address":"555 NW Saltzman Road",
    "sg:city":"Portland",
    "sg:classifiers":[
        {
            "category":"Food & Beverages",
            "subcategory":"Candy",
            "type":"Retail Goods"
        },
        {
            "category":"Fast Food",
            "type":"Food & Drink"
        }
    ],
    "sg:phone":"+1 503 626 7572",
    "sg:postcode":"97229",
    "sg:province":"OR",
    "sg:tags":[
        "dessert"
    ],
    "sg:website":"www.dairyqueen.com",
    "wof:name":"Dairy Queen",
    "wof:placetype":"venue"
},
  "geometry": {"coordinates":[-122.806302,45.524485],"type":"Point"}
}