{
  "type": "Feature",
  "properties": {
    "iso:country":"US",
    "sg:address":"83125 Siltcoos Station Rd",
    "sg:city":"Westlake",
    "sg:classifiers":[
        {
            "category":"Building & Trades",
            "subcategory":"Electrical",
            "type":"Services"
        }
    ],
    "sg:phone":"+1 541 997 4977",
    "sg:postcode":"97493",
    "sg:province":"OR",
    "sg:tags":[
        "electrical",
        "contractor"
    ],
    "wof:name":"J E Reynolds Electric Inc",
    "wof:placetype":"venue"
},
  "geometry": {"coordinates":[-124.057159,43.894325],"type":"Point"}
}