{
  "type": "Feature",
  "properties": {
    "iso:country":"US",
    "sg:address":"4609 SE 35th Ave",
    "sg:city":"Portland",
    "sg:classifiers":[
        {
            "category":"Shopping",
            "subcategory":"Clothing, Apparel, & Fashions",
            "type":"Retail Goods"
        }
    ],
    "sg:phone":"+1 503 788 5280",
    "sg:postcode":"97202",
    "sg:province":"OR",
    "sg:tags":[
        "bridal",
        "veil",
        "custom"
    ],
    "wof:name":"August Veils",
    "wof:placetype":"venue"
},
  "geometry": {"coordinates":[-122.628398,45.48979],"type":"Point"}
}