{
  "type": "Feature",
  "properties": {
    "iso:country":"US",
    "sg:address":"762 SW 231st Ave",
    "sg:city":"Hillsboro",
    "sg:classifiers":[
        {
            "category":"Utilities",
            "subcategory":"Telephone",
            "type":"Services"
        }
    ],
    "sg:phone":"+1 503 591 9409",
    "sg:postcode":"97123",
    "sg:province":"OR",
    "sg:tags":[
        "communications"
    ],
    "wof:name":"Mondoodle Inc",
    "wof:placetype":"venue"
},
  "geometry": {"coordinates":[-122.914464,45.512761],"type":"Point"}
}