{
  "type": "Feature",
  "properties": {
    "iso:country":"US",
    "sg:address":"7235 SE Milwaukie Ave",
    "sg:city":"Portland",
    "sg:classifiers":[
        {
            "category":"Retail",
            "subcategory":"Repair Shop",
            "type":"Services"
        },
        {
            "category":"Professional",
            "subcategory":"Business Services",
            "type":"Services"
        }
    ],
    "sg:phone":"+1 503 233 8059",
    "sg:postcode":"97202",
    "sg:province":"OR",
    "sg:tags":[
        "power",
        "mfg",
        "transmission",
        "equipment",
        "hot",
        "spa",
        "tub"
    ],
    "wof:name":"Rose City Pool & Spa Service",
    "wof:placetype":"venue"
},
  "geometry": {"coordinates":[-122.64854,45.471949],"type":"Point"}
}