{
  "type": "Feature",
  "properties": {
    "iso:country":"US",
    "sg:address":"12140 SW Merestone Ct",
    "sg:city":"Tigard",
    "sg:classifiers":[
        {
            "category":"Professional",
            "type":"Services"
        }
    ],
    "sg:phone":"+1 503 590 6661",
    "sg:postcode":"97223",
    "sg:province":"OR",
    "sg:tags":[
        "information",
        "bureau"
    ],
    "wof:name":"Motorcycle Tour Information",
    "wof:placetype":"venue"
},
  "geometry": {"coordinates":[-122.801097,45.435472],"type":"Point"}
}