{
  "type": "Feature",
  "properties": {
    "iso:country":"US",
    "sg:address":"317 Marian Ave",
    "sg:city":"Central Point",
    "sg:classifiers":[
        {
            "category":"Real Estate",
            "subcategory":"Real Estate Operator",
            "type":"Services"
        }
    ],
    "sg:phone":"+1 541 664 4663",
    "sg:postcode":"97502",
    "sg:province":"OR",
    "sg:tags":[
        "mobile",
        "home",
        "site"
    ],
    "wof:name":"Miller Estates",
    "wof:placetype":"venue"
},
  "geometry": {"coordinates":[-122.928596,42.385799],"type":"Point"}
}