{
  "type": "Feature",
  "properties": {
    "iso:country":"US",
    "sg:address":"11165 SW Hall Blvd",
    "sg:city":"Portland",
    "sg:classifiers":[
        {
            "category":"Social Services",
            "subcategory":"Child Care",
            "type":"Services"
        }
    ],
    "sg:phone":"+1 503 452 7095",
    "sg:postcode":"97223",
    "sg:province":"OR",
    "sg:tags":[
        "day"
    ],
    "wof:name":"Bumble Babies",
    "wof:placetype":"venue"
},
  "geometry": {"coordinates":[-122.765435,45.438933],"type":"Point"}
}