{
  "type": "Feature",
  "properties": {
    "iso:country":"US",
    "sg:address":"285 Liberty St NE",
    "sg:city":"Salem",
    "sg:classifiers":[
        {
            "category":"Shopping",
            "subcategory":"Clothing, Apparel, & Fashions",
            "type":"Retail Goods"
        }
    ],
    "sg:phone":"+1 503 363 6693",
    "sg:postcode":"97301",
    "sg:province":"OR",
    "sg:tags":[
        "dancing",
        "supply"
    ],
    "wof:name":"DGC Pro",
    "wof:placetype":"venue"
},
  "geometry": {"coordinates":[-123.038281,44.941254],"type":"Point"}
}