{
  "type": "Feature",
  "properties": {
    "iso:country":"US",
    "sg:address":"195 E 17th Ave",
    "sg:city":"Eugene",
    "sg:classifiers":[
        {
            "category":"Restaurant",
            "type":"Food & Drink"
        }
    ],
    "sg:phone":"+1 541 344 5881",
    "sg:postcode":"97401",
    "sg:province":"OR",
    "wof:name":"Nana's Kitchen",
    "wof:placetype":"venue"
},
  "geometry": {"coordinates":[-123.090708,44.041207],"type":"Point"}
}