{
  "type": "Feature",
  "properties": {
    "iso:country":"US",
    "sg:address":"60 Division Ave",
    "sg:city":"Eugene",
    "sg:classifiers":[
        {
            "category":"Food & Beverages",
            "subcategory":"Groceries & Convenience Stores",
            "type":"Retail Goods"
        }
    ],
    "sg:phone":"+1 541 461 1400",
    "sg:postcode":"97404",
    "sg:province":"OR",
    "sg:tags":[
        "supermarket"
    ],
    "wof:name":"Fred Meyer",
    "wof:placetype":"venue"
},
  "geometry": {"coordinates":[-123.126238,44.098946],"type":"Point"}
}