{
  "type": "Feature",
  "properties": {
    "iso:country":"US",
    "sg:address":"1711 SE Hawthorne Blvd",
    "sg:city":"Portland",
    "sg:classifiers":[
        {
            "category":"Organizations",
            "subcategory":"Religious Organization",
            "type":"Services"
        }
    ],
    "sg:phone":"+1 503 230 8908",
    "sg:postcode":"97214",
    "sg:province":"OR",
    "wof:name":"Portland Chapter",
    "wof:placetype":"venue"
},
  "geometry": {"coordinates":[-122.64766400000001,45.512265],"type":"Point"}
}