{
  "type": "Feature",
  "properties": {
    "addr:full":"3525 SE Milwaukie Ave Portland OR 97202",
    "addr:housenumber":"3525",
    "addr:postcode":"97202",
    "addr:street":"Se Milwaukie Ave",
    "iso:country":"US",
    "sg:address":"3525 SE Milwaukie Ave",
    "sg:city":"Portland",
    "sg:classifiers":[
        {
            "category":"Social Services",
            "subcategory":"Job Training",
            "type":"Services"
        }
    ],
    "sg:phone":"+1 503 234 1729",
    "sg:postcode":"97202",
    "sg:province":"OR",
    "sg:tags":[
        "rehabilitation"
    ],
    "wof:name":"Alternative Rehabilitation",
    "wof:placetype":"venue"
},
  "geometry": {"coordinates":[-122.653749,45.49695],"type":"Point"}
}