{
  "type": "Feature",
  "properties": {
    "iso:country":"US",
    "sg:address":"217 SW Frenwood Way",
    "sg:city":"Beaverton",
    "sg:classifiers":[
        {
            "category":"Building & Trades",
            "subcategory":"Construction",
            "type":"Services"
        }
    ],
    "sg:phone":"+1 503 646 5465",
    "sg:postcode":"97005",
    "sg:province":"OR",
    "sg:tags":[
        "contractor"
    ],
    "wof:name":"Urban Rock Masonry LLC",
    "wof:placetype":"venue"
},
  "geometry": {"coordinates":[-122.808008,45.51851],"type":"Point"}
}