{
  "type": "Feature",
  "properties": {
    "addr:full":"11010 SE Mill Ct Portland OR 97216",
    "addr:housenumber":"11010",
    "addr:postcode":"97216",
    "addr:street":"Se Mill Ct",
    "iso:country":"US",
    "sg:address":"11010 SE Mill Ct",
    "sg:city":"Portland",
    "sg:classifiers":[
        {
            "category":"Recreation",
            "type":"Entertainment"
        }
    ],
    "sg:phone":"+1 503 254 0847",
    "sg:postcode":"97216",
    "sg:province":"OR",
    "sg:tags":[
        "instruction",
        "ski",
        "skiing"
    ],
    "sg:website":"www.mogulbusters.com",
    "wof:name":"Mogul Buster Ski School",
    "wof:placetype":"venue"
},
  "geometry": {"coordinates":[-122.550511,45.510792],"type":"Point"}
}