{
  "type": "Feature",
  "properties": {
    "iso:country":"US",
    "sg:address":"551 SE Keel Ave",
    "sg:city":"Lincoln City",
    "sg:classifiers":[
        {
            "category":"Building & Trades",
            "subcategory":"Construction",
            "type":"Services"
        }
    ],
    "sg:phone":"+1 541 996 5555",
    "sg:postcode":"97367",
    "sg:province":"OR",
    "sg:tags":[
        "contractor"
    ],
    "wof:name":"Sundance Construction",
    "wof:placetype":"venue"
},
  "geometry": {"coordinates":[-124.012451,44.963234],"type":"Point"}
}