{
  "type": "Feature",
  "properties": {
    "addr:full":"700 F Ave La Grande OR 97850",
    "addr:housenumber":"700",
    "addr:postcode":"97850",
    "addr:street":"F Ave",
    "iso:country":"US",
    "sg:address":"700 F Ave",
    "sg:city":"La Grande",
    "sg:classifiers":[
        {
            "category":"Health Services",
            "subcategory":"Doctor",
            "type":"Services"
        }
    ],
    "sg:phone":"+1 541 963 8578",
    "sg:postcode":"97850",
    "sg:province":"OR",
    "sg:tags":[
        "medical"
    ],
    "wof:name":"Donald Warren MD",
    "wof:placetype":"venue"
},
  "geometry": {"coordinates":[-118.100465,45.316835],"type":"Point"}
}