{
  "type": "Feature",
  "properties": {
    "iso:country":"US",
    "sg:address":"2720 SW 89th Ave",
    "sg:city":"Portland",
    "sg:classifiers":[
        {
            "category":"Shopping",
            "subcategory":"Clothing, Apparel, & Fashions",
            "type":"Retail Goods"
        }
    ],
    "sg:phone":"+1 503 292 0268",
    "sg:postcode":"97225",
    "sg:province":"OR",
    "sg:tags":[
        "brassiere"
    ],
    "wof:name":"Sculptress Pennyrich Bras",
    "wof:placetype":"venue"
},
  "geometry": {"coordinates":[-122.7692,45.498149],"type":"Point"}
}