{
  "type": "Feature",
  "properties": {
    "iso:country":"US",
    "sg:address":"14964 NW Farmstead Ct",
    "sg:city":"Beaverton",
    "sg:classifiers":[
        {
            "category":"Manufacturing",
            "subcategory":"Buildings",
            "type":"Manufacturing & Wholesale Goods"
        },
        {
            "category":"Home & Garden",
            "subcategory":"Building Materials",
            "type":"Retail Goods"
        },
        {
            "category":"Building & Trades",
            "subcategory":"Construction",
            "type":"Services"
        }
    ],
    "sg:phone":"+1 503 626 2489",
    "sg:postcode":"97006",
    "sg:province":"OR",
    "sg:tags":[
        "builder",
        "gazebo",
        "patio",
        "contractor"
    ],
    "wof:name":"John Breiling And Associates",
    "wof:placetype":"venue"
},
  "geometry": {"coordinates":[-122.830427,45.522232],"type":"Point"}
}