{
  "type": "Feature",
  "properties": {
    "iso:country":"US",
    "sg:address":"265 Strand St",
    "sg:city":"St Helens",
    "sg:classifiers":[
        {
            "category":"Government",
            "subcategory":"Office",
            "type":"Public Place"
        }
    ],
    "sg:phone":"+1 503 397 6272",
    "sg:postcode":"97051",
    "sg:province":"OR",
    "sg:tags":[
        "city"
    ],
    "sg:website":"www.ci.st-helens.or.us",
    "wof:name":"St Helens City Hall",
    "wof:placetype":"venue"
},
  "geometry": {"coordinates":[-122.797344,45.863708],"type":"Point"}
}