{
  "type": "Feature",
  "properties": {
    "iso:country":"US",
    "sg:address":"8675 N Crawford St",
    "sg:city":"Portland",
    "sg:classifiers":[
        {
            "category":"Recreation",
            "subcategory":"Boat Charter",
            "type":"Entertainment"
        }
    ],
    "sg:phone":"+1 503 286 3552",
    "sg:postcode":"97203",
    "sg:province":"OR",
    "sg:tags":[
        "boating"
    ],
    "sg:website":"www.independentmarinepropeller.com",
    "wof:name":"Independent Marine Propeller Shop",
    "wof:placetype":"venue"
},
  "geometry": {"coordinates":[-122.759855,45.588083],"type":"Point"}
}