{
  "type": "Feature",
  "properties": {
    "addr:full":"6155 SW Murray Blvd Beaverton OR 97008",
    "addr:housenumber":"6155",
    "addr:postcode":"97008",
    "addr:street":"Sw Murray Blvd",
    "iso:country":"US",
    "sg:address":"6155 SW Murray Blvd",
    "sg:city":"Beaverton",
    "sg:classifiers":[
        {
            "category":"Food & Beverages",
            "subcategory":"Groceries & Convenience Stores",
            "type":"Retail Goods"
        }
    ],
    "sg:phone":"+1 503 643 3414",
    "sg:postcode":"97008",
    "sg:province":"OR",
    "wof:name":"Enchanted Florist Inc",
    "wof:placetype":"venue"
},
  "geometry": {"coordinates":[-122.826159,45.475283],"type":"Point"}
}