{
  "type": "Feature",
  "properties": {
    "iso:country":"US",
    "sg:address":"1600 Sky Park Dr",
    "sg:city":"Medford",
    "sg:classifiers":[
        {
            "category":"Real Estate",
            "subcategory":"Real Estate Agent",
            "type":"Services"
        }
    ],
    "sg:phone":"+1 541 858 4650",
    "sg:postcode":"97504",
    "sg:province":"OR",
    "wof:name":"Cam Properties",
    "wof:placetype":"venue"
},
  "geometry": {"coordinates":[-122.862859,42.356405],"type":"Point"}
}