{
  "type": "Feature",
  "properties": {
    "iso:country":"US",
    "sg:address":"2900 SW Peaceful Lane",
    "sg:city":"Portland",
    "sg:classifiers":[
        {
            "category":"Place Of Worship",
            "subcategory":"Synagogue",
            "type":"Public Place"
        }
    ],
    "sg:phone":"+1 503 246 8077",
    "sg:postcode":"97239",
    "sg:province":"OR",
    "wof:name":"United Synagogue-Regional Office",
    "wof:placetype":"venue"
},
  "geometry": {"coordinates":[-122.707705,45.483163],"type":"Point"}
}