{
  "type": "Feature",
  "properties": {
    "iso:country":"US",
    "sg:address":"16225 NE Glisan St",
    "sg:city":"Portland",
    "sg:classifiers":[
        {
            "category":"Restaurant",
            "type":"Food & Drink"
        },
        {
            "category":"Food & Beverages",
            "subcategory":"Groceries & Convenience Stores",
            "type":"Retail Goods"
        }
    ],
    "sg:phone":"+1 503 255 4356",
    "sg:postcode":"97230",
    "sg:province":"OR",
    "sg:tags":[
        "mexican"
    ],
    "wof:name":"Tortilleria Y Tienda De Leon's",
    "wof:placetype":"venue"
},
  "geometry": {"coordinates":[-122.49612,45.526428],"type":"Point"}
}