{
  "type": "Feature",
  "properties": {
    "iso:country":"US",
    "sg:address":"221 Brown St",
    "sg:city":"Silverton",
    "sg:classifiers":[
        {
            "category":"Building & Trades",
            "subcategory":"Cleaning & Sanitation",
            "type":"Services"
        }
    ],
    "sg:phone":"+1 503 873 0526",
    "sg:postcode":"97381",
    "sg:province":"OR",
    "sg:tags":[
        "maintenance"
    ],
    "wof:name":"Professional Spaces",
    "wof:placetype":"venue"
},
  "geometry": {"coordinates":[-122.787893,45.010769],"type":"Point"}
}