{
  "type": "Feature",
  "properties": {
    "addr:full":"59639 Halfway Rd Coos Bay OR 97420",
    "addr:postcode":"59639;97420",
    "addr:street":"Halfway Rd",
    "iso:country":"US",
    "sg:address":"59639 Halfway Rd",
    "sg:city":"Coos Bay",
    "sg:classifiers":[
        {
            "category":"Manufacturing",
            "subcategory":"Retail Goods",
            "type":"Manufacturing & Wholesale Goods"
        }
    ],
    "sg:phone":"+1 541 269 9678",
    "sg:postcode":"97420",
    "sg:province":"OR",
    "sg:tags":[
        "product",
        "mfg"
    ],
    "wof:name":"Seiger Industries",
    "wof:placetype":"venue"
},
  "geometry": {"coordinates":[-124.22771,43.241578],"type":"Point"}
}