{
  "type": "Feature",
  "properties": {
    "iso:country":"US",
    "sg:address":"17007 SE Division St",
    "sg:city":"Portland",
    "sg:classifiers":[
        {
            "category":"Restaurant",
            "type":"Food & Drink"
        }
    ],
    "sg:phone":"+1 503 762 2334",
    "sg:postcode":"97236",
    "sg:province":"OR",
    "wof:name":"Kettle Inn",
    "wof:placetype":"venue"
},
  "geometry": {"coordinates":[-122.48772700000001,45.504714],"type":"Point"}
}