{
  "type": "Feature",
  "properties": {
    "iso:country":"US",
    "sg:address":"1484 S B St",
    "sg:city":"Springfield",
    "sg:classifiers":[
        {
            "category":"Building & Trades",
            "subcategory":"Equipment Rental",
            "type":"Services"
        }
    ],
    "sg:phone":"+1 541 746 6800",
    "sg:postcode":"97477",
    "sg:province":"OR",
    "sg:tags":[
        "scaffolding"
    ],
    "wof:name":"Mc Kenzie Scaffolding LLC",
    "wof:placetype":"venue"
},
  "geometry": {"coordinates":[-123.005184,44.043789],"type":"Point"}
}