{
  "type": "Feature",
  "properties": {
    "addr:full":"1315 3rd St Tillamook OR 97141",
    "addr:housenumber":"1315",
    "addr:postcode":"97141",
    "addr:street":"3Rd St",
    "iso:country":"US",
    "sg:address":"1315 3rd St",
    "sg:city":"Tillamook",
    "sg:classifiers":[
        {
            "category":"Home & Garden",
            "subcategory":"Hardware",
            "type":"Retail Goods"
        }
    ],
    "sg:phone":"+1 503 842 2313",
    "sg:postcode":"97141",
    "sg:province":"OR",
    "wof:name":"Fosmark Paint and Floor Cvg",
    "wof:placetype":"venue"
},
  "geometry": {"coordinates":[-123.85123400000001,45.456237],"type":"Point"}
}