{
  "type": "Feature",
  "properties": {
    "iso:country":"US",
    "sg:address":"1824 Main St",
    "sg:city":"Baker City",
    "sg:classifiers":[
        {
            "category":"Building & Trades",
            "subcategory":"Construction",
            "type":"Services"
        }
    ],
    "sg:phone":"+1 541 523 3383",
    "sg:postcode":"97814",
    "sg:province":"OR",
    "sg:tags":[
        "tile",
        "dealer"
    ],
    "wof:name":"Howard Marble Works",
    "wof:placetype":"venue"
},
  "geometry": {"coordinates":[-117.82975399999999,44.776022],"type":"Point"}
}