{
  "type": "Feature",
  "properties": {
    "iso:country":"US",
    "sg:address":"982 Moorea Dr",
    "sg:city":"Roseburg",
    "sg:classifiers":[
        {
            "category":"Real Estate",
            "subcategory":"Real Estate Agent",
            "type":"Services"
        }
    ],
    "sg:phone":"+1 541 673 6796",
    "sg:postcode":"97471",
    "sg:province":"OR",
    "wof:name":"Rosefelt",
    "wof:placetype":"venue"
},
  "geometry": {"coordinates":[-123.372573,43.249295],"type":"Point"}
}