{
  "type": "Feature",
  "properties": {
    "addr:full":"2618 10th St Baker City OR 97814",
    "addr:housenumber":"2618",
    "addr:postcode":"97814",
    "addr:street":"10Th St",
    "iso:country":"US",
    "sg:address":"2618 10th St",
    "sg:city":"Baker City",
    "sg:classifiers":[
        {
            "category":"Insurance",
            "subcategory":"Insurance Agent",
            "type":"Services"
        }
    ],
    "sg:phone":"+1 541 523 4267",
    "sg:postcode":"97814",
    "sg:province":"OR",
    "wof:name":"Bisnett & Assoc Insurance Inc",
    "wof:placetype":"venue"
},
  "geometry": {"coordinates":[-117.841106,44.78333],"type":"Point"}
}