{
  "type": "Feature",
  "properties": {
    "iso:country":"US",
    "sg:address":"945 Dahlia Ter",
    "sg:city":"Eagle Point",
    "sg:classifiers":[
        {
            "category":"Building & Trades",
            "subcategory":"Landscaping Services",
            "type":"Services"
        }
    ],
    "sg:phone":"+1 541 830 8481",
    "sg:postcode":"97524",
    "sg:province":"OR",
    "sg:tags":[
        "landscape",
        "contractor"
    ],
    "wof:name":"Dan Skomerza's Pro Landscape",
    "wof:placetype":"venue"
},
  "geometry": {"coordinates":[-122.82195299999999,42.485476],"type":"Point"}
}