{
  "type": "Feature",
  "properties": {
    "iso:country":"US",
    "sg:address":"1400 Elm Ave",
    "sg:city":"Klamath Falls",
    "sg:classifiers":[
        {
            "category":"Home & Garden",
            "subcategory":"Hardware",
            "type":"Retail Goods"
        }
    ],
    "sg:phone":"+1 541 273 8463",
    "sg:postcode":"97601",
    "sg:province":"OR",
    "wof:name":"Bell Hardware",
    "wof:placetype":"venue"
},
  "geometry": {"coordinates":[-121.775615,42.22245],"type":"Point"}
}