{
  "type": "Feature",
  "properties": {
    "addr:full":"3660 SE 122nd Ave Portland OR 97236",
    "addr:housenumber":"3660",
    "addr:postcode":"97236",
    "addr:street":"Se 122Nd Ave",
    "iso:country":"US",
    "sg:address":"3660 SE 122nd Ave",
    "sg:city":"Portland",
    "sg:classifiers":[
        {
            "category":"Home & Garden",
            "subcategory":"Hardware",
            "type":"Retail Goods"
        }
    ],
    "sg:phone":"+1 503 761 2640",
    "sg:postcode":"97236",
    "sg:province":"OR",
    "sg:tags":[
        "store"
    ],
    "wof:name":"Coast-To-Coast Stores",
    "wof:placetype":"venue"
},
  "geometry": {"coordinates":[-122.53800200000001,45.495701],"type":"Point"}
}