{
  "type": "Feature",
  "properties": {
    "addr:full":"115 NE Collins St Depoe Bay OR 97341",
    "addr:housenumber":"115",
    "addr:postcode":"97341",
    "addr:street":"Ne Collins St",
    "iso:country":"US",
    "sg:address":"115 NE Collins St",
    "sg:city":"Depoe Bay",
    "sg:classifiers":[
        {
            "category":"Travel",
            "subcategory":"Campground",
            "type":"Entertainment"
        }
    ],
    "sg:phone":"+1 541 765 2601",
    "sg:postcode":"97341",
    "sg:province":"OR",
    "wof:name":"Martin's Trailer Harbor",
    "wof:placetype":"venue"
},
  "geometry": {"coordinates":[-124.05997000000001,44.811765],"type":"Point"}
}