{
  "type": "Feature",
  "properties": {
    "addr:full":"1776 Avalon St Klamath Falls OR 97603",
    "addr:housenumber":"1776",
    "addr:postcode":"97603",
    "addr:street":"Avalon St",
    "iso:country":"US",
    "sg:address":"1776 Avalon St",
    "sg:city":"Klamath Falls",
    "sg:classifiers":[
        {
            "category":"Shopping",
            "subcategory":"Shoes",
            "type":"Retail Goods"
        }
    ],
    "sg:phone":"+1 541 884 1705",
    "sg:postcode":"97603",
    "sg:province":"OR",
    "sg:tags":[
        "consulting",
        "management"
    ],
    "wof:name":"Meldisco 1776 Avalon St",
    "wof:placetype":"venue"
},
  "geometry": {"coordinates":[-121.753023,42.212677],"type":"Point"}
}