{
  "type": "Feature",
  "properties": {
    "iso:country":"US",
    "sg:address":"74889 Palmer Junction Rd",
    "sg:city":"Elgin",
    "sg:classifiers":[
        {
            "category":"Farming",
            "subcategory":"Livestock Farm",
            "type":"Manufacturing & Wholesale Goods"
        }
    ],
    "sg:phone":"+1 541 437 3602",
    "sg:postcode":"97827",
    "sg:province":"OR",
    "sg:tags":[
        "beef",
        "feedlot",
        "cattle"
    ],
    "wof:name":"Ashburn Ranch",
    "wof:placetype":"venue"
},
  "geometry": {"coordinates":[-117.89664999999999,45.696512],"type":"Point"}
}