{
  "type": "Feature",
  "properties": {
    "iso:country":"US",
    "sg:address":"2163 Salem Dallas Hwy NW",
    "sg:city":"Salem",
    "sg:classifiers":[
        {
            "category":"Shopping",
            "subcategory":"Bicycles & Sporting Goods",
            "type":"Retail Goods"
        }
    ],
    "sg:phone":"+1 503 585 9409",
    "sg:postcode":"97304",
    "sg:province":"OR",
    "sg:tags":[
        "gun",
        "gunsmith"
    ],
    "wof:name":"Robert D Harms Gunsmith & Tool",
    "wof:placetype":"venue"
},
  "geometry": {"coordinates":[-123.074984,44.932865],"type":"Point"}
}