{
  "type": "Feature",
  "properties": {
    "iso:country":"US",
    "sg:address":"93910 Pitney Ln",
    "sg:city":"Junction City",
    "sg:classifiers":[
        {
            "category":"Banks & Credit Unions",
            "subcategory":"Financial Services",
            "type":"Services"
        }
    ],
    "sg:phone":"+1 541 998 1640",
    "sg:postcode":"97448",
    "sg:province":"OR",
    "sg:tags":[
        "investment",
        "closed"
    ],
    "wof:name":"American Dream Funding",
    "wof:placetype":"venue"
},
  "geometry": {"coordinates":[-123.219055,44.212362],"type":"Point"}
}