{
  "type": "Feature",
  "properties": {
    "iso:country":"US",
    "sg:address":"400 Antelope Rd",
    "sg:city":"White City",
    "sg:classifiers":[
        {
            "category":"Recreation",
            "type":"Entertainment"
        }
    ],
    "sg:phone":"+1 541 774 8183",
    "sg:postcode":"97503",
    "sg:province":"OR",
    "sg:tags":[
        "parks"
    ],
    "sg:website":"www.jacksoncountyparks.com",
    "wof:name":"Jackson County Parks",
    "wof:placetype":"venue"
},
  "geometry": {"coordinates":[-122.879473,42.427301],"type":"Point"}
}