{
  "type": "Feature",
  "properties": {
    "addr:full":"6501 SE King Rd Portland OR 97222",
    "addr:housenumber":"6501",
    "addr:postcode":"97222",
    "addr:street":"Se King Rd",
    "iso:country":"US",
    "sg:address":"6501 SE King Rd",
    "sg:city":"Portland",
    "sg:classifiers":[
        {
            "category":"Health Services",
            "subcategory":"Chiropractor",
            "type":"Services"
        }
    ],
    "sg:phone":"+1 503 252 9576",
    "sg:postcode":"97222",
    "sg:province":"OR",
    "sg:tags":[
        "chiropractic"
    ],
    "wof:name":"Heuchert Rudolph DC",
    "wof:placetype":"venue"
},
  "geometry": {"coordinates":[-122.595696,45.447941],"type":"Point"}
}