{
  "type": "Feature",
  "properties": {
    "iso:country":"US",
    "sg:address":"1220 NW Lovejoy Ste 130",
    "sg:city":"Portland",
    "sg:classifiers":[
        {
            "category":"Real Estate",
            "subcategory":"Real Estate Agent",
            "type":"Services"
        }
    ],
    "sg:phone":"+1 503 888 6181",
    "sg:postcode":"97209",
    "sg:province":"OR",
    "sg:website":"www.realtytrust.com/drewmcculloch",
    "wof:name":"Drew McCulloch - Realty Trust Group",
    "wof:placetype":"venue"
},
  "geometry": {"coordinates":[-122.68364099999999,45.530001],"type":"Point"}
}