{
  "type": "Feature",
  "properties": {
    "iso:country":"US",
    "sg:address":"1773 NE 3rd St",
    "sg:city":"Prineville",
    "sg:classifiers":[
        {
            "category":"Travel",
            "subcategory":"Hotels & Motels",
            "type":"Entertainment"
        }
    ],
    "sg:phone":"+1 541 447 7100",
    "sg:postcode":"97754",
    "sg:province":"OR",
    "sg:tags":[
        "lodging"
    ],
    "sg:website":"http://www.staffordinn.com",
    "wof:name":"Stafford Inn",
    "wof:placetype":"venue"
},
  "geometry": {"coordinates":[-120.825951,44.302919],"type":"Point"}
}