{
  "type": "Feature",
  "properties": {
    "iso:country":"US",
    "sg:address":"836 SW 12th St",
    "sg:city":"Redmond",
    "sg:classifiers":[
        {
            "category":"Professional",
            "subcategory":"Lawyer & Legal Services",
            "type":"Services"
        }
    ],
    "sg:phone":"+1 541 504 8250",
    "sg:postcode":"97756",
    "sg:province":"OR",
    "sg:tags":[
        "attorney"
    ],
    "wof:name":"Oliver & Duncan",
    "wof:placetype":"venue"
},
  "geometry": {"coordinates":[-121.18068599999999,44.269228],"type":"Point"}
}