{
  "type": "Feature",
  "properties": {
    "iso:country":"US",
    "sg:address":"4728 S Killins Loop",
    "sg:city":"Woodburn",
    "sg:classifiers":[
        {
            "category":"Professional",
            "type":"Services"
        }
    ],
    "sg:phone":"+1 503 634 2298",
    "sg:postcode":"97071",
    "sg:province":"OR",
    "wof:name":"Grs Errection Inc",
    "wof:placetype":"venue"
},
  "geometry": {"coordinates":[-122.770448,45.145],"type":"Point"}
}