{
  "type": "Feature",
  "properties": {
    "iso:country":"US",
    "sg:address":"5657 SW Harvest Ave",
    "sg:city":"Redmond",
    "sg:classifiers":[
        {
            "category":"Manufacturing",
            "subcategory":"Tools & Machinery",
            "type":"Manufacturing & Wholesale Goods"
        }
    ],
    "sg:phone":"+1 541 923 4702",
    "sg:postcode":"97756",
    "sg:province":"OR",
    "sg:tags":[
        "industrial",
        "general"
    ],
    "wof:name":"Alvin L Gitchell",
    "wof:placetype":"venue"
},
  "geometry": {"coordinates":[-121.232789,44.22776],"type":"Point"}
}