{
  "type": "Feature",
  "properties": {
    "iso:country":"US",
    "sg:address":"61111 27th St",
    "sg:city":"Bend",
    "sg:classifiers":[
        {
            "category":"Education",
            "subcategory":"School",
            "type":"Public Place"
        }
    ],
    "sg:phone":"+1 541 383 6480",
    "sg:postcode":"97702",
    "sg:province":"OR",
    "sg:website":"www.bend.k12.or.us",
    "wof:name":"High Desert Middle School",
    "wof:placetype":"venue"
},
  "geometry": {"coordinates":[-121.263902,44.028273],"type":"Point"}
}