{
  "type": "Feature",
  "properties": {
    "iso:country":"US",
    "sg:address":"12451 Duckflat Rd SE",
    "sg:city":"Turner",
    "sg:classifiers":[
        {
            "category":"Freight",
            "type":"Transportation"
        }
    ],
    "sg:phone":"+1 503 743 2704",
    "sg:postcode":"97392",
    "sg:province":"OR",
    "sg:tags":[
        "operator",
        "local",
        "trucking"
    ],
    "wof:name":"William A Kosareff Trucking",
    "wof:placetype":"venue"
},
  "geometry": {"coordinates":[-122.938236,44.774281],"type":"Point"}
}