{
  "type": "Feature",
  "properties": {
    "addr:full":"1655 Decker Point Rd Reedsport OR 97467",
    "addr:housenumber":"1655",
    "addr:postcode":"97467",
    "addr:street":"Decker Point Rd",
    "iso:country":"US",
    "sg:address":"1655 Decker Point Rd",
    "sg:city":"Reedsport",
    "sg:classifiers":[
        {
            "category":"Manufacturing",
            "subcategory":"Toys & Sporting Goods",
            "type":"Manufacturing & Wholesale Goods"
        }
    ],
    "sg:phone":"+1 541 271 2585",
    "sg:postcode":"97467",
    "sg:province":"OR",
    "sg:tags":[
        "mfg"
    ],
    "wof:name":"Black Tail Bows",
    "wof:placetype":"venue"
},
  "geometry": {"coordinates":[-124.113294,43.694582],"type":"Point"}
}