{
  "type": "Feature",
  "properties": {
    "addr:full":"34424 State Hwy 58 Eugene OR 97405",
    "addr:housenumber":"34424",
    "addr:postcode":"97405",
    "addr:street":"State Hwy 58",
    "iso:country":"US",
    "sg:address":"34424 State Hwy 58",
    "sg:city":"Eugene",
    "sg:classifiers":[
        {
            "category":"Wholesale",
            "subcategory":"Toys & Hobbies",
            "type":"Manufacturing & Wholesale Goods"
        }
    ],
    "sg:phone":"+1 541 746 0657",
    "sg:postcode":"97405",
    "sg:province":"OR",
    "sg:tags":[
        "wholesaler"
    ],
    "wof:name":"Birdog Auto Wholesaler",
    "wof:placetype":"venue"
},
  "geometry": {"coordinates":[-122.997334,43.993441],"type":"Point"}
}