{
  "type": "Feature",
  "properties": {
    "iso:country":"US",
    "sg:address":"951 Galls Creek Rd",
    "sg:city":"Gold Hill",
    "sg:classifiers":[
        {
            "category":"Professional",
            "subcategory":"Management & Consulting",
            "type":"Services"
        }
    ],
    "sg:phone":"+1 541 855 7148",
    "sg:postcode":"97525",
    "sg:province":"OR",
    "sg:tags":[
        "construction",
        "framing",
        "contractor"
    ],
    "wof:name":"Ottis Roberts Construction",
    "wof:placetype":"venue"
},
  "geometry": {"coordinates":[-123.066648,42.416571],"type":"Point"}
}