{
  "type": "Feature",
  "properties": {
    "addr:full":"727 SE Cass Ave Roseburg OR 97470",
    "addr:housenumber":"727",
    "addr:postcode":"97470",
    "addr:street":"Se Cass Ave",
    "iso:country":"US",
    "sg:address":"727 SE Cass Ave",
    "sg:city":"Roseburg",
    "sg:classifiers":[
        {
            "category":"Health Services",
            "subcategory":"Doctor",
            "type":"Services"
        }
    ],
    "sg:phone":"+1 541 957 5762",
    "sg:postcode":"97470",
    "sg:province":"OR",
    "sg:tags":[
        "medical"
    ],
    "wof:name":"Bill Salbador MD",
    "wof:placetype":"venue"
},
  "geometry": {"coordinates":[-123.346417,43.208494],"type":"Point"}
}