{
  "type": "Feature",
  "properties": {
    "addr:full":"3320 SW River Rd Hillsboro OR 97123",
    "addr:housenumber":"3320",
    "addr:postcode":"97123",
    "addr:street":"Sw River Rd",
    "iso:country":"US",
    "sg:address":"3320 SW River Rd",
    "sg:city":"Hillsboro",
    "sg:classifiers":[
        {
            "category":"Home & Garden",
            "subcategory":"Building Materials",
            "type":"Retail Goods"
        }
    ],
    "sg:phone":"+1 503 640 1889",
    "sg:postcode":"97123",
    "sg:province":"OR",
    "sg:tags":[
        "windows"
    ],
    "wof:name":"Sundance Windows",
    "wof:placetype":"venue"
},
  "geometry": {"coordinates":[-122.941226,45.49565],"type":"Point"}
}