{
  "type": "Feature",
  "properties": {
    "iso:country":"US",
    "sg:address":"3913 Halliday Rd",
    "sg:city":"Vale",
    "sg:classifiers":[
        {
            "category":"Farming",
            "subcategory":"Livestock Farm",
            "type":"Manufacturing & Wholesale Goods"
        }
    ],
    "sg:phone":"+1 541 889 6093",
    "sg:postcode":"97918",
    "sg:province":"OR",
    "sg:tags":[
        "cattle",
        "crop",
        "row"
    ],
    "wof:name":"Burkhardt Farms Inc",
    "wof:placetype":"venue"
},
  "geometry": {"coordinates":[-117.145693,43.995996],"type":"Point"}
}