{
  "type": "Feature",
  "properties": {
    "iso:country":"US",
    "sg:address":"4235 NE 15th Ave",
    "sg:city":"Portland",
    "sg:classifiers":[
        {
            "category":"Building & Trades",
            "subcategory":"Locksmith",
            "type":"Services"
        }
    ],
    "sg:phone":"+1 503 205 0639",
    "sg:postcode":"97211",
    "sg:province":"OR",
    "sg:tags":[
        "key"
    ],
    "wof:name":"Any Place 24 Locksmith",
    "wof:placetype":"venue"
},
  "geometry": {"coordinates":[-122.65053899999999,45.553974],"type":"Point"}
}