{
  "type": "Feature",
  "properties": {
    "iso:country":"US",
    "sg:address":"14670 SW Davis Rd",
    "sg:city":"Beaverton",
    "sg:classifiers":[
        {
            "category":"Professional",
            "type":"Services"
        }
    ],
    "sg:phone":"+1 503 643 3005",
    "sg:postcode":"97007",
    "sg:province":"OR",
    "wof:name":"Imperial Artchina",
    "wof:placetype":"venue"
},
  "geometry": {"coordinates":[-122.82571,45.473138],"type":"Point"}
}