{
  "type": "Feature",
  "properties": {
    "addr:full":"1425 N Roosevelt Dr Seaside OR 97138",
    "addr:housenumber":"1425",
    "addr:postcode":"97138",
    "addr:street":"N Roosevelt Dr",
    "iso:country":"US",
    "sg:address":"1425 N Roosevelt Dr",
    "sg:city":"Seaside",
    "sg:classifiers":[
        {
            "category":"Building & Trades",
            "subcategory":"Plumbing",
            "type":"Services"
        }
    ],
    "sg:phone":"+1 503 717 1667",
    "sg:postcode":"97138",
    "sg:province":"OR",
    "sg:tags":[
        "heating",
        "contractor"
    ],
    "wof:name":"Diamond Heating",
    "wof:placetype":"venue"
},
  "geometry": {"coordinates":[-123.916346,46.003515],"type":"Point"}
}