{
  "type": "Feature",
  "properties": {
    "iso:country":"US",
    "sg:address":"421 SW 7th St",
    "sg:city":"Pendleton",
    "sg:classifiers":[
        {
            "category":"Home & Garden",
            "subcategory":"Building Materials",
            "type":"Retail Goods"
        }
    ],
    "sg:phone":"+1 541 276 8135",
    "sg:postcode":"97801",
    "sg:province":"OR",
    "sg:tags":[
        "glass",
        "window",
        "plate"
    ],
    "wof:name":"Northwest Windshields",
    "wof:placetype":"venue"
},
  "geometry": {"coordinates":[-118.792739,45.668355],"type":"Point"}
}