{
  "type": "Feature",
  "properties": {
    "iso:country":"US",
    "sg:address":"115 W Broadway",
    "sg:city":"Eugene",
    "sg:classifiers":[
        {
            "category":"Food & Beverages",
            "subcategory":"Specialty",
            "type":"Retail Goods"
        }
    ],
    "sg:phone":"+1 541 484 9933",
    "sg:postcode":"97401",
    "sg:province":"OR",
    "wof:name":"Cafe Paradiso",
    "wof:placetype":"venue"
},
  "geometry": {"coordinates":[-123.094554,44.049993],"type":"Point"}
}