{
  "type": "Feature",
  "properties": {
    "iso:country":"US",
    "sg:address":"29050 S Needy Rd",
    "sg:city":"Canby",
    "sg:classifiers":[
        {
            "category":"Shopping",
            "subcategory":"Hobbies, Toys, & Games",
            "type":"Retail Goods"
        }
    ],
    "sg:phone":"+1 503 651 3280",
    "sg:postcode":"97013",
    "sg:province":"OR",
    "wof:name":"Handmade By Sharon",
    "wof:placetype":"venue"
},
  "geometry": {"coordinates":[-122.70244099999999,45.190045],"type":"Point"}
}