{
  "type": "Feature",
  "properties": {
    "iso:country":"US",
    "sg:address":"20004 NW Tanasbourne Dr",
    "sg:city":"Hillsboro",
    "sg:classifiers":[
        {
            "category":"Wholesale",
            "subcategory":"Electrical",
            "type":"Manufacturing & Wholesale Goods"
        }
    ],
    "sg:phone":"+1 503 617 7800",
    "sg:postcode":"97124",
    "sg:province":"OR",
    "sg:tags":[
        "semiconductor"
    ],
    "sg:website":"www.tel.com",
    "wof:name":"Tokyo Electron America Inc",
    "wof:placetype":"venue"
},
  "geometry": {"coordinates":[-122.881349,45.544776],"type":"Point"}
}