{
  "type": "Feature",
  "properties": {
    "addr:full":"2201 Lloyd Ctr Spc T18 Portland OR 97232",
    "addr:housenumber":"2201",
    "addr:postcode":"97232",
    "addr:street":"Lloyd Ctr;T18",
    "iso:country":"US",
    "sg:address":"2201 Lloyd Ctr Spc T18",
    "sg:city":"Portland",
    "sg:classifiers":[
        {
            "category":"Utilities",
            "subcategory":"Mobile Phone",
            "type":"Services"
        },
        {
            "category":"Shopping",
            "subcategory":"Mobile Phones",
            "type":"Retail Goods"
        },
        {
            "category":"Utilities",
            "subcategory":"Telephone",
            "type":"Services"
        },
        {
            "category":"Professional",
            "subcategory":"Computer Services",
            "type":"Services"
        }
    ],
    "sg:phone":"+1 503 284 6806",
    "sg:postcode":"97232",
    "sg:province":"OR",
    "sg:tags":[
        "telecommunication",
        "supply",
        "communication",
        "system",
        "wireless",
        "equipment",
        "cellular"
    ],
    "sg:website":"http://clickserve.dartsearch.net/link/click?lid=43000000308049899",
    "wof:name":"T-Mobile",
    "wof:placetype":"venue"
},
  "geometry": {"coordinates":[-122.653571,45.531895],"type":"Point"}
}