{
  "type": "Feature",
  "properties": {
    "addr:full":"4148 NE Sandy Boulevard Portland OR 97212",
    "addr:housenumber":"4148",
    "addr:postcode":"97212",
    "addr:street":"Ne Sandy Boulevard",
    "iso:country":"US",
    "sg:address":"4148 NE Sandy Boulevard",
    "sg:city":"Portland",
    "sg:classifiers":[
        {
            "category":"Arts & Performance",
            "subcategory":"Art Gallery",
            "type":"Entertainment"
        }
    ],
    "sg:phone":"+1 503 493 0403",
    "sg:postcode":"97212",
    "sg:province":"OR",
    "wof:name":"So Be It Art & Events",
    "wof:placetype":"venue"
},
  "geometry": {"coordinates":[-122.619944,45.535968],"type":"Point"}
}