{
  "type": "Feature",
  "properties": {
    "iso:country":"US",
    "sg:address":"7125 NE Emerson St",
    "sg:city":"Portland",
    "sg:classifiers":[
        {
            "category":"Manufacturing",
            "subcategory":"Wood Products",
            "type":"Manufacturing & Wholesale Goods"
        },
        {
            "category":"Building & Trades",
            "subcategory":"Construction",
            "type":"Services"
        }
    ],
    "sg:phone":"+1 503 252 2339",
    "sg:postcode":"97218",
    "sg:province":"OR",
    "sg:tags":[
        "supply-manufacturers",
        "equipment",
        "woodworking",
        "supply"
    ],
    "wof:name":"Woodtech Equipment",
    "wof:placetype":"venue"
},
  "geometry": {"coordinates":[-122.589687,45.561315],"type":"Point"}
}