{
  "type": "Feature",
  "properties": {
    "iso:country":"US",
    "sg:address":"203 SW Emigrant Ave",
    "sg:city":"Pendleton",
    "sg:classifiers":[
        {
            "category":"Professional",
            "subcategory":"Accounting & Tax Preparation",
            "type":"Services"
        }
    ],
    "sg:phone":"+1 541 276 0659",
    "sg:postcode":"97801",
    "sg:province":"OR",
    "sg:tags":[
        "return",
        "filing"
    ],
    "wof:name":"H & R Block Tax Svc",
    "wof:placetype":"venue"
},
  "geometry": {"coordinates":[-118.788179,45.670095],"type":"Point"}
}