{
  "type": "Feature",
  "properties": {
    "iso:country":"US",
    "sg:address":"14147 SE 268th Ct",
    "sg:city":"Boring",
    "sg:classifiers":[
        {
            "category":"Professional",
            "subcategory":"Accounting & Tax Preparation",
            "type":"Services"
        }
    ],
    "sg:phone":"+1 503 663 1281",
    "sg:postcode":"97009",
    "sg:province":"OR",
    "sg:tags":[
        "bookkeeping"
    ],
    "wof:name":"A+ Bookkeeping Solutions LLC",
    "wof:placetype":"venue"
},
  "geometry": {"coordinates":[-122.386679,45.41976],"type":"Point"}
}