{
  "type": "Feature",
  "properties": {
    "iso:country":"US",
    "sg:address":"1840 E Barnett Rd",
    "sg:city":"Medford",
    "sg:classifiers":[
        {
            "category":"Shopping",
            "type":"Retail Goods"
        }
    ],
    "sg:phone":"+1 541 779 8199",
    "sg:postcode":"97504",
    "sg:province":"OR",
    "sg:tags":[
        "orthopedic",
        "appliance"
    ],
    "wof:name":"Hanger Prosthetics & Ortho",
    "wof:placetype":"venue"
},
  "geometry": {"coordinates":[-122.842159,42.316223],"type":"Point"}
}