{
  "type": "Feature",
  "properties": {
    "addr:full":"1911 SW Vista Pl Pendleton OR 97801",
    "addr:housenumber":"1911",
    "addr:postcode":"97801",
    "addr:street":"Sw Vista Pl",
    "iso:country":"US",
    "sg:address":"1911 SW Vista Pl",
    "sg:city":"Pendleton",
    "sg:classifiers":[
        {
            "category":"Travel",
            "subcategory":"Campground",
            "type":"Entertainment"
        }
    ],
    "sg:phone":"+1 541 966 8690",
    "sg:postcode":"97801",
    "sg:province":"OR",
    "sg:tags":[
        "trailer"
    ],
    "wof:name":"Catalpa Tree Rv Park",
    "wof:placetype":"venue"
},
  "geometry": {"coordinates":[-118.823397,45.642258],"type":"Point"}
}