{
  "type": "Feature",
  "properties": {
    "addr:full":"425 SE 3rd Ave Portland OR 97214",
    "addr:housenumber":"425",
    "addr:postcode":"97214",
    "addr:street":"Se 3Rd Ave",
    "iso:country":"US",
    "sg:address":"425 SE 3rd Ave",
    "sg:city":"Portland",
    "sg:classifiers":[
        {
            "category":"Education",
            "subcategory":"Dance Studio",
            "type":"Public Place"
        }
    ],
    "sg:phone":"+1 503 453 6083",
    "sg:postcode":"97214",
    "sg:province":"OR",
    "sg:tags":[
        "company"
    ],
    "wof:name":"Polaris Dance Co",
    "wof:placetype":"venue"
},
  "geometry": {"coordinates":[-122.66283300000001,45.519547],"type":"Point"}
}