{
  "type": "Feature",
  "properties": {
    "addr:full":"2101 Ave F White City OR 97503",
    "addr:housenumber":"2101",
    "addr:postcode":"97503",
    "addr:street":"Ave F",
    "iso:country":"US",
    "sg:address":"2101 Ave F",
    "sg:city":"White City",
    "sg:classifiers":[
        {
            "category":"Freight",
            "type":"Transportation"
        }
    ],
    "sg:phone":"+1 541 826 8288",
    "sg:postcode":"97503",
    "sg:province":"OR",
    "sg:tags":[
        "hauling",
        "trucking"
    ],
    "wof:name":"Whipple Transport Inc",
    "wof:placetype":"venue"
},
  "geometry": {"coordinates":[-122.853425,42.43422],"type":"Point"}
}