{
  "type": "Feature",
  "properties": {
    "iso:country":"US",
    "sg:address":"61966 SE 27th St",
    "sg:city":"Bend",
    "sg:classifiers":[
        {
            "category":"Place Of Worship",
            "subcategory":"Church",
            "type":"Public Place"
        },
        {
            "category":"Place Of Worship",
            "type":"Public Place"
        },
        {
            "category":"Organizations",
            "subcategory":"Religious Organization",
            "type":"Services"
        }
    ],
    "sg:phone":"+1 541 389 8002",
    "sg:postcode":"97702",
    "sg:province":"OR",
    "sg:tags":[
        "churches-jehovah's",
        "witness"
    ],
    "sg:website":"http://www.watchtower.org",
    "wof:name":"Jehovah's Witnesses Inc",
    "wof:placetype":"venue"
},
  "geometry": {"coordinates":[-121.26357299999999,44.050079],"type":"Point"}
}