{
  "type": "Feature",
  "properties": {
    "iso:country":"US",
    "sg:address":"626 SE 27th Ave",
    "sg:city":"Portland",
    "sg:classifiers":[
        {
            "category":"Professional",
            "subcategory":"Accounting & Tax Preparation",
            "type":"Services"
        }
    ],
    "sg:phone":"+1 503 235 8058",
    "sg:postcode":"97214",
    "sg:province":"OR",
    "sg:tags":[
        "bookkeeping",
        "general"
    ],
    "wof:name":"Trissell's Bookkeeping Svc",
    "wof:placetype":"venue"
},
  "geometry": {"coordinates":[-122.63802800000001,45.518052],"type":"Point"}
}