{
  "type": "Feature",
  "properties": {
    "addr:full":"1600 NW Garden Valley Blvd 1 Roseburg OR 97471",
    "addr:housenumber":"1600;1",
    "addr:postcode":"97471",
    "addr:street":"Nw Garden Valley Blvd",
    "iso:country":"US",
    "sg:address":"1600 NW Garden Valley Blvd 1",
    "sg:city":"Roseburg",
    "sg:classifiers":[
        {
            "category":"Insurance",
            "subcategory":"Hazard Insurance",
            "type":"Services"
        }
    ],
    "sg:phone":"+1 541 673 0242",
    "sg:postcode":"97471",
    "sg:province":"OR",
    "sg:tags":[
        "commercial",
        "business"
    ],
    "wof:name":"Tammy Logan Insurance",
    "wof:placetype":"venue"
},
  "geometry": {"coordinates":[-123.377961,43.23476],"type":"Point"}
}