{
  "type": "Feature",
  "properties": {
    "addr:full":"255 Pacific Blvd SW Albany OR 97321",
    "addr:housenumber":"255",
    "addr:postcode":"97321",
    "addr:street":"Pacific Blvd Sw",
    "iso:country":"US",
    "sg:address":"255 Pacific Blvd SW",
    "sg:city":"Albany",
    "sg:classifiers":[
        {
            "category":"Shopping",
            "subcategory":"Pets & Pet Supplies",
            "type":"Retail Goods"
        },
        {
            "category":"Retail",
            "subcategory":"Animal Services",
            "type":"Services"
        }
    ],
    "sg:phone":"+1 541 926 0698",
    "sg:postcode":"97321",
    "sg:province":"OR",
    "sg:tags":[
        "grooming",
        "furnishing",
        "dog",
        "cat"
    ],
    "sg:website":"http://www.agroomingplace.com",
    "wof:name":"A Grooming Place & Oregon Pet Grooming Academy",
    "wof:placetype":"venue"
},
  "geometry": {"coordinates":[-123.10503199999999,44.629125],"type":"Point"}
}