{
  "type": "Feature",
  "properties": {
    "iso:country":"US",
    "sg:address":"11695 SW Timberline Ct",
    "sg:city":"Beaverton",
    "sg:classifiers":[
        {
            "category":"Shopping",
            "subcategory":"Bicycles & Sporting Goods",
            "type":"Retail Goods"
        }
    ],
    "sg:phone":"+1 503 626 2363",
    "sg:postcode":"97008",
    "sg:province":"OR",
    "wof:name":"Don Norris Gunsmithing",
    "wof:placetype":"venue"
},
  "geometry": {"coordinates":[-122.79748499999999,45.464161],"type":"Point"}
}