{
  "type": "Feature",
  "properties": {
    "iso:country":"US",
    "sg:address":"5802 NW Columbia Dr",
    "sg:city":"Madras",
    "sg:classifiers":[
        {
            "category":"Retail",
            "subcategory":"Repair Shop",
            "type":"Services"
        },
        {
            "category":"Building & Trades",
            "subcategory":"Construction",
            "type":"Services"
        },
        {
            "category":"Building & Trades",
            "subcategory":"Electrical",
            "type":"Services"
        },
        {
            "category":"Home & Garden",
            "subcategory":"Household Appliances",
            "type":"Retail Goods"
        },
        {
            "category":"Wholesale",
            "subcategory":"Machinery & Supplies",
            "type":"Manufacturing & Wholesale Goods"
        },
        {
            "category":"Restaurant",
            "type":"Food & Drink"
        }
    ],
    "sg:phone":"+1 541 475 3975",
    "sg:postcode":"97741",
    "sg:province":"OR",
    "sg:tags":[
        "heating",
        "major",
        "industrial",
        "refinishing",
        "specialty",
        "pump",
        "system",
        "appliances-small",
        "contractor",
        "equipment",
        "furnaces-heating",
        "equipment-commercial",
        "refrigeration",
        "air conditioning",
        "heat",
        "supplies-refrigeration"
    ],
    "wof:name":"Towler Heating & Cooling",
    "wof:placetype":"venue"
},
  "geometry": {"coordinates":[-121.173711,44.719402],"type":"Point"}
}