{
  "type": "Feature",
  "properties": {
    "iso:country":"US",
    "sg:address":"2510 State Hwy 66",
    "sg:city":"Ashland",
    "sg:classifiers":[
        {
            "category":"Bars & Pubs",
            "type":"Food & Drink"
        }
    ],
    "sg:phone":"+1 541 488 1434",
    "sg:postcode":"97520",
    "sg:province":"OR",
    "sg:tags":[
        "drinking"
    ],
    "wof:name":"Oak Tree Northwest Bar & Grill",
    "wof:placetype":"venue"
},
  "geometry": {"coordinates":[-122.662111,42.186],"type":"Point"}
}