{
  "type": "Feature",
  "properties": {
    "iso:country":"US",
    "sg:address":"13634 SW Pleasant Valley Rd",
    "sg:city":"Beaverton",
    "sg:classifiers":[
        {
            "category":"Building & Trades",
            "subcategory":"Construction",
            "type":"Services"
        }
    ],
    "sg:phone":"+1 503 245 2004",
    "sg:postcode":"97007",
    "sg:province":"OR",
    "sg:tags":[
        "contractor"
    ],
    "wof:name":"Petersen Brothers Contracting",
    "wof:placetype":"venue"
},
  "geometry": {"coordinates":[-122.877855,45.420972],"type":"Point"}
}