{
  "type": "Feature",
  "properties": {
    "iso:country":"US",
    "sg:address":"1125 SE Madison St # 210",
    "sg:city":"Portland",
    "sg:classifiers":[
        {
            "category":"Social Services",
            "type":"Services"
        },
        {
            "category":"Professional",
            "subcategory":"Employment Agencies",
            "type":"Services"
        }
    ],
    "sg:phone":"+1 503 231 7480",
    "sg:postcode":"97214",
    "sg:province":"OR",
    "sg:tags":[
        "human",
        "employer"
    ],
    "wof:name":"African Women's Coalition",
    "wof:placetype":"venue"
},
  "geometry": {"coordinates":[-122.65445099999999,45.512948],"type":"Point"}
}