{
  "type": "Feature",
  "properties": {
    "addr:full":"15750 S Pierce Rd Molalla OR 97038",
    "addr:housenumber":"15750",
    "addr:postcode":"97038",
    "addr:street":"S Pierce Rd",
    "iso:country":"US",
    "sg:address":"15750 S Pierce Rd",
    "sg:city":"Molalla",
    "sg:classifiers":[
        {
            "category":"Manufacturing",
            "subcategory":"Lumber",
            "type":"Manufacturing & Wholesale Goods"
        }
    ],
    "sg:phone":"+1 503 759 8060",
    "sg:postcode":"97038",
    "sg:province":"OR",
    "sg:tags":[
        "company",
        "logging"
    ],
    "wof:name":"King Fisher Logging & Tree Frm",
    "wof:placetype":"venue"
},
  "geometry": {"coordinates":[-122.544749,45.085322],"type":"Point"}
}