{
  "type": "Feature",
  "properties": {
    "addr:full":"5497 SE International Way Portland OR 97222",
    "addr:housenumber":"5497",
    "addr:postcode":"97222",
    "addr:street":"Se International Way",
    "iso:country":"US",
    "sg:address":"5497 SE International Way",
    "sg:city":"Portland",
    "sg:classifiers":[
        {
            "category":"Education",
            "subcategory":"School",
            "type":"Public Place"
        }
    ],
    "sg:phone":"+1 503 656 5433",
    "sg:postcode":"97222",
    "sg:province":"OR",
    "sg:tags":[
        "church"
    ],
    "wof:name":"Life Christian Center",
    "wof:placetype":"venue"
},
  "geometry": {"coordinates":[-122.606224,45.432412],"type":"Point"}
}