{
  "type": "Feature",
  "properties": {
    "iso:country":"US",
    "sg:address":"1865 NE Davis Street",
    "sg:city":"Portland",
    "sg:classifiers":[
        {
            "category":"Real Estate",
            "subcategory":"Real Estate Operator",
            "type":"Services"
        }
    ],
    "sg:phone":"+1 503 236 2320",
    "sg:postcode":"97232",
    "sg:province":"OR",
    "sg:tags":[
        "apartment"
    ],
    "wof:name":"Silvercrest Apartments",
    "wof:placetype":"venue"
},
  "geometry": {"coordinates":[-122.646812,45.524313],"type":"Point"}
}