{
  "type": "Feature",
  "properties": {
    "addr:full":"54952 Huntington Rd Bend OR 97707",
    "addr:housenumber":"54952",
    "addr:postcode":"97707",
    "addr:street":"Huntington Rd",
    "iso:country":"US",
    "sg:address":"54952 Huntington Rd",
    "sg:city":"Bend",
    "sg:classifiers":[
        {
            "category":"Manufacturing",
            "subcategory":"Food",
            "type":"Manufacturing & Wholesale Goods"
        }
    ],
    "sg:phone":"+1 541 593 6005",
    "sg:postcode":"97707",
    "sg:province":"OR",
    "sg:tags":[
        "canned",
        "mfg"
    ],
    "wof:name":"Robbins & Assoc",
    "wof:placetype":"venue"
},
  "geometry": {"coordinates":[-121.449403,43.805419],"type":"Point"}
}