{
  "type": "Feature",
  "properties": {
    "addr:full":"5390 SW Dominie Ct Beaverton OR 97007",
    "addr:housenumber":"5390",
    "addr:postcode":"97007",
    "addr:street":"Sw Dominie Ct",
    "iso:country":"US",
    "sg:address":"5390 SW Dominie Ct",
    "sg:city":"Beaverton",
    "sg:classifiers":[
        {
            "category":"Professional",
            "type":"Services"
        }
    ],
    "sg:phone":"+1 503 259 9417",
    "sg:postcode":"97007",
    "sg:province":"OR",
    "wof:name":"La Bella Luna Baskets",
    "wof:placetype":"venue"
},
  "geometry": {"coordinates":[-122.883095,45.481423],"type":"Point"}
}