{
  "type": "Feature",
  "properties": {
    "addr:full":"7930 Ajax St White City OR 97503",
    "addr:housenumber":"7930",
    "addr:postcode":"97503",
    "addr:street":"Ajax St",
    "iso:country":"US",
    "sg:address":"7930 Ajax St",
    "sg:city":"White City",
    "sg:classifiers":[
        {
            "category":"Building & Trades",
            "subcategory":"Cleaning & Sanitation",
            "type":"Services"
        }
    ],
    "sg:phone":"+1 541 826 7994",
    "sg:postcode":"97503",
    "sg:province":"OR",
    "sg:tags":[
        "maintenance"
    ],
    "wof:name":"Pioneer Maintenance",
    "wof:placetype":"venue"
},
  "geometry": {"coordinates":[-122.843976,42.430892],"type":"Point"}
}