{
  "type": "Feature",
  "properties": {
    "iso:country":"US",
    "sg:address":"101 Acorn St",
    "sg:city":"Merlin",
    "sg:classifiers":[
        {
            "category":"Place Of Worship",
            "subcategory":"Church",
            "type":"Public Place"
        },
        {
            "category":"Place Of Worship",
            "type":"Public Place"
        }
    ],
    "sg:phone":"+1 541 471 0153",
    "sg:postcode":"97532",
    "sg:province":"OR",
    "sg:tags":[
        "churches-seventh-day",
        "adventist",
        "christian",
        "churches-advent"
    ],
    "sg:website":"http://www.adventist.org",
    "wof:name":"North Valley Seventh-Day Adventist Chrch",
    "wof:placetype":"venue"
},
  "geometry": {"coordinates":[-123.417458,42.513329],"type":"Point"}
}