{
  "type": "Feature",
  "properties": {
    "iso:country":"US",
    "sg:address":"26477 Gunners Lake Mainline",
    "sg:city":"Scappoose",
    "sg:classifiers":[
        {
            "category":"Wholesale",
            "subcategory":"Home Furnishings",
            "type":"Manufacturing & Wholesale Goods"
        }
    ],
    "sg:phone":"+1 503 543 3661",
    "sg:postcode":"97056",
    "sg:province":"OR",
    "wof:name":"Nancy Shepherd",
    "wof:placetype":"venue"
},
  "geometry": {"coordinates":[-123.03031,45.821838],"type":"Point"}
}