{
  "type": "Feature",
  "properties": {
    "iso:country":"US",
    "sg:address":"4845 NE 87th Ave",
    "sg:city":"Portland",
    "sg:classifiers":[
        {
            "category":"Manufacturing",
            "subcategory":"Lumber",
            "type":"Manufacturing & Wholesale Goods"
        }
    ],
    "sg:phone":"+1 503 253 3381",
    "sg:postcode":"97220",
    "sg:province":"OR",
    "sg:tags":[
        "operation",
        "timber",
        "tract"
    ],
    "wof:name":"Oregon Trees LLC",
    "wof:placetype":"venue"
},
  "geometry": {"coordinates":[-122.573455,45.558335],"type":"Point"}
}