{
  "type": "Feature",
  "properties": {
    "addr:full":"60 E 10th Ave Eugene OR 97401",
    "addr:housenumber":"60",
    "addr:postcode":"97401",
    "addr:street":"E 10Th Ave",
    "iso:country":"US",
    "sg:address":"60 E 10th Ave",
    "sg:city":"Eugene",
    "sg:classifiers":[
        {
            "category":"Education",
            "subcategory":"Dance Studio",
            "type":"Public Place"
        }
    ],
    "sg:phone":"+1 541 342 4611",
    "sg:postcode":"97401",
    "sg:province":"OR",
    "wof:name":"Ballet Fantastique",
    "wof:placetype":"venue"
},
  "geometry": {"coordinates":[-123.091359,44.048737],"type":"Point"}
}