{
  "type": "Feature",
  "properties": {
    "addr:full":"22050 SW Rosedale Rd Beaverton OR 97007",
    "addr:housenumber":"22050",
    "addr:postcode":"97007",
    "addr:street":"Sw Rosedale Rd",
    "iso:country":"US",
    "sg:address":"22050 SW Rosedale Rd",
    "sg:city":"Beaverton",
    "sg:classifiers":[
        {
            "category":"Farming",
            "subcategory":"Livestock Farm",
            "type":"Manufacturing & Wholesale Goods"
        }
    ],
    "sg:phone":"+1 503 649 6611",
    "sg:postcode":"97007",
    "sg:province":"OR",
    "sg:tags":[
        "feedlot",
        "field",
        "crop",
        "beef",
        "cattle"
    ],
    "wof:name":"Joe Santoro",
    "wof:placetype":"venue"
},
  "geometry": {"coordinates":[-122.90471100000001,45.470156],"type":"Point"}
}