{
  "type": "Feature",
  "properties": {
    "iso:country":"US",
    "sg:address":"11180 SW Hall Blvd",
    "sg:city":"Portland",
    "sg:classifiers":[
        {
            "category":"Professional",
            "subcategory":"Art Services",
            "type":"Services"
        }
    ],
    "sg:phone":"+1 503 481 5012",
    "sg:postcode":"97223",
    "sg:province":"OR",
    "sg:tags":[
        "graphic",
        "designer"
    ],
    "wof:name":"BGB Design",
    "wof:placetype":"venue"
},
  "geometry": {"coordinates":[-122.765287,45.438628],"type":"Point"}
}