{
  "type": "Feature",
  "properties": {
    "iso:country":"US",
    "sg:address":"2211 NW Front Ave",
    "sg:city":"Portland",
    "sg:classifiers":[
        {
            "category":"Building & Trades",
            "subcategory":"Construction",
            "type":"Services"
        }
    ],
    "sg:phone":"+1 503 224 5454",
    "sg:postcode":"97209",
    "sg:province":"OR",
    "sg:tags":[
        "designer"
    ],
    "wof:name":"Lori Mason Design",
    "wof:placetype":"venue"
},
  "geometry": {"coordinates":[-122.689998,45.538658],"type":"Point"}
}