{
  "type": "Feature",
  "properties": {
    "iso:country":"US",
    "sg:address":"219 NW Cliff St",
    "sg:city":"Newport",
    "sg:classifiers":[
        {
            "category":"Travel",
            "subcategory":"Hotels & Motels",
            "type":"Entertainment"
        }
    ],
    "sg:phone":"+1 541 265 3334",
    "sg:postcode":"97365",
    "sg:province":"OR",
    "sg:tags":[
        "operation",
        "eating"
    ],
    "sg:website":"www.nyebeach.com",
    "wof:name":"Nye Beach Hotel & Cafe",
    "wof:placetype":"venue"
},
  "geometry": {"coordinates":[-124.061983,44.637992],"type":"Point"}
}