{
  "type": "Feature",
  "properties": {
    "iso:country":"US",
    "sg:address":"14554 E Marquam Rd NE",
    "sg:city":"Mount Angel",
    "sg:classifiers":[
        {
            "category":"Restaurant",
            "type":"Food & Drink"
        }
    ],
    "sg:phone":"+1 503 845 2523",
    "sg:postcode":"97362",
    "sg:province":"OR",
    "sg:tags":[
        "eating"
    ],
    "wof:name":"Caroline S Catering",
    "wof:placetype":"venue"
},
  "geometry": {"coordinates":[-122.76312799999999,45.071212],"type":"Point"}
}