{
  "type": "Feature",
  "properties": {
    "addr:full":"565 12th St Astoria OR 97103",
    "addr:housenumber":"565",
    "addr:postcode":"97103",
    "addr:street":"12Th St",
    "iso:country":"US",
    "sg:address":"565 12th St",
    "sg:city":"Astoria",
    "sg:classifiers":[
        {
            "category":"Place Of Worship",
            "subcategory":"Church",
            "type":"Public Place"
        },
        {
            "category":"Place Of Worship",
            "type":"Public Place"
        }
    ],
    "sg:phone":"+1 503 325 3871",
    "sg:postcode":"97103",
    "sg:province":"OR",
    "sg:tags":[
        "churches-lutheran"
    ],
    "wof:name":"Peace Lutheran Church",
    "wof:placetype":"venue"
},
  "geometry": {"coordinates":[-123.830251,46.187185],"type":"Point"}
}