{
  "type": "Feature",
  "properties": {
    "iso:country":"US",
    "sg:address":"3230 SW 185th Ave",
    "sg:city":"Beaverton",
    "sg:classifiers":[
        {
            "category":"Manufacturing",
            "subcategory":"Paper Products",
            "type":"Manufacturing & Wholesale Goods"
        }
    ],
    "sg:phone":"+1 503 319 5458",
    "sg:postcode":"97006",
    "sg:province":"OR",
    "sg:tags":[
        "mill"
    ],
    "wof:name":"Rincon Aguilar Abel",
    "wof:placetype":"venue"
},
  "geometry": {"coordinates":[-122.867131,45.497139],"type":"Point"}
}