{
  "type": "Feature",
  "properties": {
    "iso:country":"US",
    "sg:address":"7195 Lawnridge St NE",
    "sg:city":"Keizer",
    "sg:classifiers":[
        {
            "category":"Building & Trades",
            "subcategory":"Construction",
            "type":"Services"
        }
    ],
    "sg:phone":"+1 503 390 2841",
    "sg:postcode":"97303",
    "sg:province":"OR",
    "sg:tags":[
        "water",
        "well",
        "drilling"
    ],
    "wof:name":"Sippel Well Drilling Inc",
    "wof:placetype":"venue"
},
  "geometry": {"coordinates":[-123.020855,45.02225],"type":"Point"}
}