{
  "type": "Feature",
  "properties": {
    "iso:country":"US",
    "sg:address":"2908 NE Baroness Pl",
    "sg:city":"Bend",
    "sg:classifiers":[
        {
            "category":"Wholesale",
            "subcategory":"Electrical",
            "type":"Manufacturing & Wholesale Goods"
        }
    ],
    "sg:phone":"+1 415 723 7853",
    "sg:postcode":"97701",
    "sg:province":"OR",
    "sg:tags":[
        "equipment",
        "car",
        "audio",
        "accessory"
    ],
    "wof:name":"World Piece Commerce Co",
    "wof:placetype":"venue"
},
  "geometry": {"coordinates":[-121.26917,44.078734],"type":"Point"}
}