{
  "type": "Feature",
  "properties": {
    "addr:full":"30503 SW Firdale Rd Cornelius OR 97113",
    "addr:housenumber":"30503",
    "addr:postcode":"97113",
    "addr:street":"Sw Firdale Rd",
    "iso:country":"US",
    "sg:address":"30503 SW Firdale Rd",
    "sg:city":"Cornelius",
    "sg:classifiers":[
        {
            "category":"Professional",
            "subcategory":"Business Services",
            "type":"Services"
        }
    ],
    "sg:phone":"+1 503 628 1939",
    "sg:postcode":"97113",
    "sg:province":"OR",
    "wof:name":"JV Associates",
    "wof:placetype":"venue"
},
  "geometry": {"coordinates":[-122.988542,45.446209],"type":"Point"}
}