{
  "type": "Feature",
  "properties": {
    "iso:country":"US",
    "sg:address":"14240 SW Pacific Hwy",
    "sg:city":"Portland",
    "sg:classifiers":[
        {
            "category":"Home & Garden",
            "subcategory":"Garden Supply",
            "type":"Retail Goods"
        }
    ],
    "sg:phone":"+1 503 684 2727",
    "sg:postcode":"97224",
    "sg:province":"OR",
    "sg:tags":[
        "nursery",
        "gardening"
    ],
    "wof:name":"The Gardener's Choice",
    "wof:placetype":"venue"
},
  "geometry": {"coordinates":[-122.788591,45.417401],"type":"Point"}
}