{
  "type": "Feature",
  "properties": {
    "iso:country":"US",
    "sg:address":"843 NE Rogahn St",
    "sg:city":"Hillsboro",
    "sg:classifiers":[
        {
            "category":"Restaurant",
            "type":"Food & Drink"
        }
    ],
    "sg:phone":"+1 503 640 2481",
    "sg:postcode":"97124",
    "sg:province":"OR",
    "sg:tags":[
        "eating"
    ],
    "wof:name":"Fapp Enterprises Inc",
    "wof:placetype":"venue"
},
  "geometry": {"coordinates":[-122.977235,45.54434],"type":"Point"}
}