{
  "type": "Feature",
  "properties": {
    "addr:full":"444 SW 6th St Redmond OR 97756",
    "addr:housenumber":"444",
    "addr:postcode":"97756",
    "addr:street":"Sw 6Th St",
    "iso:country":"US",
    "sg:address":"444 SW 6th St",
    "sg:city":"Redmond",
    "sg:classifiers":[
        {
            "category":"Shopping",
            "subcategory":"Florist",
            "type":"Retail Goods"
        }
    ],
    "sg:phone":"+1 541 548 6089",
    "sg:postcode":"97756",
    "sg:province":"OR",
    "wof:name":"Flower Boutique",
    "wof:placetype":"venue"
},
  "geometry": {"coordinates":[-121.17421299999999,44.273105],"type":"Point"}
}