{
  "type": "Feature",
  "properties": {
    "iso:country":"US",
    "sg:address":"42828 SE Pagh Rd",
    "sg:city":"Sandy",
    "sg:classifiers":[
        {
            "category":"Building & Trades",
            "subcategory":"Construction",
            "type":"Services"
        }
    ],
    "sg:phone":"+1 503 810 0177",
    "sg:postcode":"97055",
    "sg:province":"OR",
    "sg:tags":[
        "altering",
        "remodeling",
        "contractor"
    ],
    "wof:name":"John Duff Patrick",
    "wof:placetype":"venue"
},
  "geometry": {"coordinates":[-122.21893,45.346019],"type":"Point"}
}