{
  "type": "Feature",
  "properties": {
    "iso:country":"US",
    "sg:address":"401 SW Fairgrounds Rd",
    "sg:city":"Madras",
    "sg:classifiers":[
        {
            "category":"Retail",
            "subcategory":"Veterinary Services",
            "type":"Services"
        }
    ],
    "sg:phone":"+1 541 475 2283",
    "sg:postcode":"97741",
    "sg:province":"OR",
    "wof:name":"Madras Animal Hospital",
    "wof:placetype":"venue"
},
  "geometry": {"coordinates":[-121.13748,44.617861],"type":"Point"}
}