{
  "type": "Feature",
  "properties": {
    "iso:country":"US",
    "sg:address":"2600 SE 71st Ave",
    "sg:city":"Portland",
    "sg:classifiers":[
        {
            "category":"Professional",
            "type":"Services"
        }
    ],
    "sg:phone":"+1 503 774 5651",
    "sg:postcode":"97206",
    "sg:province":"OR",
    "sg:tags":[
        "establishment"
    ],
    "wof:name":"Multnomah Esd",
    "wof:placetype":"venue"
},
  "geometry": {"coordinates":[-122.589736,45.504198],"type":"Point"}
}