{
  "type": "Feature",
  "properties": {
    "addr:full":"30240 SW Parkway Ave Wilsonville OR 97070",
    "addr:housenumber":"30240",
    "addr:postcode":"97070",
    "addr:street":"Sw Parkway Ave",
    "iso:country":"US",
    "sg:address":"30240 SW Parkway Ave",
    "sg:city":"Wilsonville",
    "sg:classifiers":[
        {
            "category":"Banks & Credit Unions",
            "subcategory":"Investment Brokerage",
            "type":"Services"
        }
    ],
    "sg:phone":"+1 503 682 9675",
    "sg:postcode":"97070",
    "sg:province":"OR",
    "sg:tags":[
        "advisory"
    ],
    "wof:name":"WOW",
    "wof:placetype":"venue"
},
  "geometry": {"coordinates":[-122.76872,45.297854],"type":"Point"}
}