{
  "type": "Feature",
  "properties": {
    "addr:full":"2114 Avalon Way Hood River OR 97031",
    "addr:housenumber":"2114",
    "addr:postcode":"97031",
    "addr:street":"Avalon Way",
    "iso:country":"US",
    "sg:address":"2114 Avalon Way",
    "sg:city":"Hood River",
    "sg:classifiers":[
        {
            "category":"Real Estate",
            "subcategory":"Real Estate Agent",
            "type":"Services"
        }
    ],
    "sg:phone":"+1 541 490 6006",
    "sg:postcode":"97031",
    "sg:province":"OR",
    "sg:tags":[
        "company",
        "investment"
    ],
    "wof:name":"Windcove LLC",
    "wof:placetype":"venue"
},
  "geometry": {"coordinates":[-121.530186,45.695194],"type":"Point"}
}