{
  "type": "Feature",
  "properties": {
    "addr:full":"7327 N Charleston Ave Portland OR 97203",
    "addr:housenumber":"7327",
    "addr:postcode":"97203",
    "addr:street":"N Charleston Ave",
    "iso:country":"US",
    "sg:address":"7327 N Charleston Ave",
    "sg:city":"Portland",
    "sg:classifiers":[
        {
            "category":"Personal",
            "subcategory":"Beauty Salon",
            "type":"Services"
        },
        {
            "category":"Personal",
            "subcategory":"Tattoo Parlor",
            "type":"Services"
        }
    ],
    "sg:phone":"+1 503 289 0830",
    "sg:postcode":"97203",
    "sg:province":"OR",
    "sg:tags":[
        "hair"
    ],
    "sg:website":"www.theparlourstjohns.com",
    "wof:name":"The Parlour - St. Johns",
    "wof:placetype":"venue"
},
  "geometry": {"coordinates":[-122.752304,45.589045],"type":"Point"}
}