{
  "type": "Feature",
  "properties": {
    "iso:country":"US",
    "sg:address":"425 SW Frenwood Way",
    "sg:city":"Beaverton",
    "sg:classifiers":[
        {
            "category":"Organizations",
            "subcategory":"Religious Organization",
            "type":"Services"
        }
    ],
    "sg:phone":"+1 503 643 2037",
    "sg:postcode":"97005",
    "sg:province":"OR",
    "wof:name":"Faith Expressions",
    "wof:placetype":"venue"
},
  "geometry": {"coordinates":[-122.806191,45.516453],"type":"Point"}
}