{
  "type": "Feature",
  "properties": {
    "addr:full":"931 SW King Ave Portland OR 97205",
    "addr:housenumber":"931",
    "addr:postcode":"97205",
    "addr:street":"Sw King Ave",
    "iso:country":"US",
    "sg:address":"931 SW King Ave",
    "sg:city":"Portland",
    "sg:classifiers":[
        {
            "category":"Professional",
            "subcategory":"Lawyer & Legal Services",
            "type":"Services"
        }
    ],
    "sg:phone":"+1 503 222 1162",
    "sg:postcode":"97205",
    "sg:province":"OR",
    "wof:name":"Zackheim Ivan S Atty",
    "wof:placetype":"venue"
},
  "geometry": {"coordinates":[-122.69499999999999,45.521702],"type":"Point"}
}