{
  "type": "Feature",
  "properties": {
    "iso:country":"US",
    "sg:address":"3298 Lakemont Dr",
    "sg:city":"Eugene",
    "sg:classifiers":[
        {
            "category":"Banks & Credit Unions",
            "subcategory":"Financial Services",
            "type":"Services"
        }
    ],
    "sg:phone":"+1 541 344 6060",
    "sg:postcode":"97408",
    "sg:province":"OR",
    "sg:tags":[
        "investor"
    ],
    "wof:name":"Cochran Investments",
    "wof:placetype":"venue"
},
  "geometry": {"coordinates":[-123.084909,44.099614],"type":"Point"}
}