{
  "type": "Feature",
  "properties": {
    "iso:country":"US",
    "sg:address":"15205 SW 74th Ave",
    "sg:city":"Portland",
    "sg:classifiers":[
        {
            "category":"Manufacturing",
            "subcategory":"Signs",
            "type":"Manufacturing & Wholesale Goods"
        },
        {
            "category":"Building & Trades",
            "subcategory":"Construction",
            "type":"Services"
        }
    ],
    "sg:phone":"+1 503 620 8200",
    "sg:postcode":"97224",
    "sg:province":"OR",
    "sg:tags":[
        "installs",
        "maintains",
        "mfg"
    ],
    "wof:name":"Meyer Sign Co Of Oregon Inc",
    "wof:placetype":"venue"
},
  "geometry": {"coordinates":[-122.75205800000001,45.406002],"type":"Point"}
}