{
  "type": "Feature",
  "properties": {
    "iso:country":"US",
    "sg:address":"425 2nd Ave SW",
    "sg:city":"Albany",
    "sg:classifiers":[
        {
            "category":"Professional",
            "type":"Services"
        }
    ],
    "sg:phone":"+1 541 791 9488",
    "sg:postcode":"97321",
    "sg:province":"OR",
    "wof:name":"Down River LLC",
    "wof:placetype":"venue"
},
  "geometry": {"coordinates":[-123.108861,44.63625],"type":"Point"}
}