{
  "type": "Feature",
  "properties": {
    "iso:country":"US",
    "sg:address":"888 SW 5th Ave Ste 900",
    "sg:city":"Portland",
    "sg:classifiers":[
        {
            "category":"Manufacturing",
            "subcategory":"Buildings",
            "type":"Manufacturing & Wholesale Goods"
        },
        {
            "category":"Building & Trades",
            "subcategory":"Construction",
            "type":"Services"
        }
    ],
    "sg:phone":"+1 503 228 8446",
    "sg:postcode":"97204",
    "sg:province":"OR",
    "sg:tags":[
        "home",
        "builder",
        "contractor"
    ],
    "wof:name":"Neighborhood Homes Inc",
    "wof:placetype":"venue"
},
  "geometry": {"coordinates":[-122.678252,45.517529],"type":"Point"}
}