{
  "type": "Feature",
  "properties": {
    "addr:full":"7506 SW 17th Dr Portland OR 97219",
    "addr:housenumber":"7506",
    "addr:postcode":"97219",
    "addr:street":"Sw 17Th Dr",
    "iso:country":"US",
    "sg:address":"7506 SW 17th Dr",
    "sg:city":"Portland",
    "sg:classifiers":[
        {
            "category":"Wholesale",
            "subcategory":"Groceries",
            "type":"Manufacturing & Wholesale Goods"
        }
    ],
    "sg:phone":"+1 503 246 7909",
    "sg:postcode":"97219",
    "sg:province":"OR",
    "sg:tags":[
        "food",
        "products-wholesale"
    ],
    "wof:name":"Northcoast Food Marketing",
    "wof:placetype":"venue"
},
  "geometry": {"coordinates":[-122.694469,45.469909],"type":"Point"}
}