{
  "type": "Feature",
  "properties": {
    "addr:full":"831 Lancaster Dr NE Salem OR 97301",
    "addr:housenumber":"831",
    "addr:postcode":"97301",
    "addr:street":"Lancaster Dr Ne",
    "iso:country":"US",
    "sg:address":"831 Lancaster Dr NE",
    "sg:city":"Salem",
    "sg:classifiers":[
        {
            "category":"Coffee & Tea",
            "type":"Food & Drink"
        }
    ],
    "sg:menulink":"http://www.allmenus.com/or/salem/119461-starbucks-coffee/menu/",
    "sg:phone":"+1 503 763 2807",
    "sg:postcode":"97301",
    "sg:province":"OR",
    "sg:tags":[
        "american"
    ],
    "wof:name":"Starbucks Coffee",
    "wof:placetype":"venue"
},
  "geometry": {"coordinates":[-122.983172,44.94147],"type":"Point"}
}