{
  "type": "Feature",
  "properties": {
    "iso:country":"US",
    "sg:address":"2035 Camellia Way",
    "sg:city":"Woodburn",
    "sg:classifiers":[
        {
            "category":"Arts & Performance",
            "subcategory":"Music",
            "type":"Entertainment"
        }
    ],
    "sg:phone":"+1 503 984 2360",
    "sg:postcode":"97071",
    "sg:province":"OR",
    "sg:tags":[
        "band",
        "musician",
        "orchestra"
    ],
    "wof:name":"Dance Tonight Band",
    "wof:placetype":"venue"
},
  "geometry": {"coordinates":[-122.863749,45.159784],"type":"Point"}
}