{
  "type": "Feature",
  "properties": {
    "addr:full":"314 SW 4th Ave Portland OR 97204",
    "addr:housenumber":"314",
    "addr:postcode":"97204",
    "addr:street":"Sw 4Th Ave",
    "iso:country":"US",
    "sg:address":"314 SW 4th Ave",
    "sg:city":"Portland",
    "sg:classifiers":[
        {
            "category":"Professional",
            "subcategory":"Lawyer & Legal Services",
            "type":"Services"
        }
    ],
    "sg:phone":"+1 503 727 3100",
    "sg:postcode":"97204",
    "sg:province":"OR",
    "sg:website":"www.abclegal.com",
    "wof:name":"ABC Legal Services",
    "wof:placetype":"venue"
},
  "geometry": {"coordinates":[-122.674982,45.521038],"type":"Point"}
}