{
  "type": "Feature",
  "properties": {
    "iso:country":"US",
    "sg:address":"3582 SE Powell Boulevard",
    "sg:city":"Portland",
    "sg:classifiers":[
        {
            "category":"Restaurant",
            "type":"Food & Drink"
        }
    ],
    "sg:phone":"+1 503 233 5363",
    "sg:postcode":"97202",
    "sg:province":"OR",
    "sg:tags":[
        "chinese"
    ],
    "wof:name":"Gold Bowl Chinese Restaurant",
    "wof:placetype":"venue"
},
  "geometry": {"coordinates":[-122.626515,45.496885],"type":"Point"}
}