{
  "type": "Feature",
  "properties": {
    "iso:country":"US",
    "sg:address":"3425 Strathmore Pl",
    "sg:city":"Eugene",
    "sg:classifiers":[
        {
            "category":"Organizations",
            "subcategory":"Professional Association",
            "type":"Services"
        }
    ],
    "sg:phone":"+1 541 344 6615",
    "sg:postcode":"97405",
    "sg:province":"OR",
    "wof:name":"Next Level Training",
    "wof:placetype":"venue"
},
  "geometry": {"coordinates":[-123.144685,44.036899],"type":"Point"}
}