{
  "type": "Feature",
  "properties": {
    "addr:full":"11899 S Mount Hope Rd Molalla OR 97038",
    "addr:housenumber":"11899",
    "addr:postcode":"97038",
    "addr:street":"S Mount Hope Rd",
    "iso:country":"US",
    "sg:address":"11899 S Mount Hope Rd",
    "sg:city":"Molalla",
    "sg:phone":"+1 503 829 8680",
    "sg:postcode":"97038",
    "sg:province":"OR",
    "sg:tags":[
        "farm",
        "wheat"
    ],
    "wof:name":"Mauer Farm",
    "wof:placetype":"venue"
},
  "geometry": {"coordinates":[-122.620983,45.12899],"type":"Point"}
}