{
  "type": "Feature",
  "properties": {
    "iso:country":"US",
    "sg:address":"3030 SW Advance Rd",
    "sg:city":"Wilsonville",
    "sg:classifiers":[
        {
            "category":"Sports & Exercise",
            "subcategory":"Golf",
            "type":"Entertainment"
        }
    ],
    "sg:phone":"+1 503 682 2022",
    "sg:postcode":"97070",
    "sg:province":"OR",
    "sg:tags":[
        "course",
        "public"
    ],
    "wof:name":"Sandelie Golf Course",
    "wof:placetype":"venue"
},
  "geometry": {"coordinates":[-122.712199,45.317403],"type":"Point"}
}