{
  "type": "Feature",
  "properties": {
    "iso:country":"US",
    "sg:address":"14480 NE Rex Hill Ct",
    "sg:city":"Newberg",
    "sg:classifiers":[
        {
            "category":"Wholesale",
            "subcategory":"Non-durable Goods",
            "type":"Manufacturing & Wholesale Goods"
        }
    ],
    "sg:phone":"+1 503 537 7065",
    "sg:postcode":"97132",
    "sg:province":"OR",
    "sg:tags":[
        "dry",
        "goods-wholesale"
    ],
    "wof:name":"Nw Implement Supply",
    "wof:placetype":"venue"
},
  "geometry": {"coordinates":[-122.93167699999999,45.321924],"type":"Point"}
}