{
  "type": "Feature",
  "properties": {
    "addr:full":"1320 W 2nd Ave Eugene OR 97402",
    "addr:housenumber":"1320",
    "addr:postcode":"97402",
    "addr:street":"W 2Nd Ave",
    "iso:country":"US",
    "sg:address":"1320 W 2nd Ave",
    "sg:city":"Eugene",
    "sg:classifiers":[
        {
            "category":"Professional",
            "subcategory":"Computer Services",
            "type":"Services"
        }
    ],
    "sg:phone":"+1 541 684 9798",
    "sg:postcode":"97402",
    "sg:province":"OR",
    "sg:tags":[
        "web",
        "graphic",
        "design",
        "site"
    ],
    "wof:name":"Giant Network Productions",
    "wof:placetype":"venue"
},
  "geometry": {"coordinates":[-123.112804,44.057493],"type":"Point"}
}