{
  "type": "Feature",
  "properties": {
    "addr:full":"9218 SW Beaverton-Hillsdale Hwy Beaverton OR 97005",
    "addr:housenumber":"9218",
    "addr:postcode":"97005",
    "addr:street":"Sw Beaverton-Hillsdale Hwy",
    "iso:country":"US",
    "sg:address":"9218 SW Beaverton-Hillsdale Hwy",
    "sg:city":"Beaverton",
    "sg:classifiers":[
        {
            "category":"Personal",
            "subcategory":"Beauty Salon",
            "type":"Services"
        }
    ],
    "sg:phone":"+1 503 292 0196",
    "sg:postcode":"97005",
    "sg:province":"OR",
    "sg:tags":[
        "shop"
    ],
    "wof:name":"Valley Hair Design",
    "wof:placetype":"venue"
},
  "geometry": {"coordinates":[-122.77443,45.486417],"type":"Point"}
}