{
  "type": "Feature",
  "properties": {
    "iso:country":"US",
    "sg:address":"826 9th Ave SW",
    "sg:city":"Albany",
    "sg:classifiers":[
        {
            "category":"Personal",
            "type":"Services"
        }
    ],
    "sg:phone":"+1 541 928 5377",
    "sg:postcode":"97321",
    "sg:province":"OR",
    "wof:name":"Church Ladies Quilting",
    "wof:placetype":"venue"
},
  "geometry": {"coordinates":[-123.112455,44.630079],"type":"Point"}
}