{
  "type": "Feature",
  "properties": {
    "iso:country":"US",
    "sg:address":"22221 SW Antioch Downs Ct",
    "sg:city":"Tualatin",
    "sg:classifiers":[
        {
            "category":"Professional",
            "subcategory":"Management & Consulting",
            "type":"Services"
        }
    ],
    "sg:phone":"+1 503 638 9077",
    "sg:postcode":"97062",
    "sg:province":"OR",
    "wof:name":"M D C Associates Co",
    "wof:placetype":"venue"
},
  "geometry": {"coordinates":[-122.728196,45.361068],"type":"Point"}
}