{
  "type": "Feature",
  "properties": {
    "iso:country":"US",
    "sg:address":"3807 NE 8th Ave",
    "sg:city":"Portland",
    "sg:classifiers":[
        {
            "category":"Utilities",
            "subcategory":"Refuse",
            "type":"Services"
        }
    ],
    "sg:phone":"+1 503 460 9084",
    "sg:postcode":"97212",
    "sg:province":"OR",
    "sg:tags":[
        "truck",
        "dump"
    ],
    "wof:name":"United Trucking Co Llc",
    "wof:placetype":"venue"
},
  "geometry": {"coordinates":[-122.657646,45.55019],"type":"Point"}
}