{
  "type": "Feature",
  "properties": {
    "addr:full":"2242 NE Columbia Blvd Portland OR 97211",
    "addr:housenumber":"2242",
    "addr:postcode":"97211",
    "addr:street":"Ne Columbia Blvd",
    "iso:country":"US",
    "sg:address":"2242 NE Columbia Blvd",
    "sg:city":"Portland",
    "sg:classifiers":[
        {
            "category":"Wholesale",
            "subcategory":"Hardware",
            "type":"Manufacturing & Wholesale Goods"
        }
    ],
    "sg:phone":"+1 503 281 2411",
    "sg:postcode":"97211",
    "sg:province":"OR",
    "sg:tags":[
        "hardware-wholesale",
        "manufacturer"
    ],
    "wof:name":"Rigpro",
    "wof:placetype":"venue"
},
  "geometry": {"coordinates":[-122.642537,45.576241],"type":"Point"}
}