{
  "type": "Feature",
  "properties": {
    "addr:full":"19435 SW 129th Ave Tualatin OR 97062",
    "addr:housenumber":"19435",
    "addr:postcode":"97062",
    "addr:street":"Sw 129Th Ave",
    "iso:country":"US",
    "sg:address":"19435 SW 129th Ave",
    "sg:city":"Tualatin",
    "sg:classifiers":[
        {
            "category":"Home & Garden",
            "subcategory":"Hardware",
            "type":"Retail Goods"
        }
    ],
    "sg:phone":"+1 503 692 9284",
    "sg:postcode":"97062",
    "sg:province":"OR",
    "sg:tags":[
        "industrial",
        "fire",
        "commercial",
        "sprinklers-residential",
        "automatic"
    ],
    "sg:website":"http://www.afpsys.com",
    "wof:name":"Afp Systems",
    "wof:placetype":"venue"
},
  "geometry": {"coordinates":[-122.809681,45.376704],"type":"Point"}
}