{
  "type": "Feature",
  "properties": {
    "addr:full":"10760 SW Beavertn Hllsdle Hwy Beaverton OR 97005",
    "addr:housenumber":"10760",
    "addr:postcode":"97005",
    "addr:street":"Sw Beavertn Hllsdle Hwy",
    "iso:country":"US",
    "sg:address":"10760 SW Beavertn Hllsdle Hwy",
    "sg:city":"Beaverton",
    "sg:classifiers":[
        {
            "category":"Shopping",
            "subcategory":"Stationery & Office Supplies",
            "type":"Retail Goods"
        },
        {
            "category":"Building & Trades",
            "subcategory":"Construction",
            "type":"Services"
        },
        {
            "category":"Home & Garden",
            "subcategory":"Furniture",
            "type":"Retail Goods"
        }
    ],
    "sg:phone":"+1 503 644 4040",
    "sg:postcode":"97005",
    "sg:province":"OR",
    "sg:tags":[
        "interior",
        "equipment",
        "design",
        "store"
    ],
    "wof:name":"Scan/Design Furniture",
    "wof:placetype":"venue"
},
  "geometry": {"coordinates":[-122.78800200000001,45.486599],"type":"Point"}
}