{
  "type": "Feature",
  "properties": {
    "iso:country":"US",
    "sg:address":"1001 SE Water Ave",
    "sg:city":"Portland",
    "sg:classifiers":[
        {
            "category":"Recreation",
            "type":"Entertainment"
        }
    ],
    "sg:phone":"+1 503 223 1736",
    "sg:postcode":"97214",
    "sg:province":"OR",
    "sg:tags":[
        "entertainers-family",
        "business"
    ],
    "wof:name":"Complete Music",
    "wof:placetype":"venue"
},
  "geometry": {"coordinates":[-122.66580999999999,45.515808],"type":"Point"}
}