{
  "type": "Feature",
  "properties": {
    "addr:full":"152 NE 11th St Newport OR 97365",
    "addr:housenumber":"152",
    "addr:postcode":"97365",
    "addr:street":"Ne 11Th St",
    "iso:country":"US",
    "sg:address":"152 NE 11th St",
    "sg:city":"Newport",
    "sg:classifiers":[
        {
            "category":"Home & Garden",
            "subcategory":"Building Materials",
            "type":"Retail Goods"
        }
    ],
    "sg:phone":"+1 541 265 2226",
    "sg:postcode":"97365",
    "sg:province":"OR",
    "sg:tags":[
        "shop",
        "glass"
    ],
    "wof:name":"Port-A-Cover",
    "wof:placetype":"venue"
},
  "geometry": {"coordinates":[-124.052368,44.644637],"type":"Point"}
}