{
  "type": "Feature",
  "properties": {
    "iso:country":"US",
    "sg:address":"4846 S 6th St",
    "sg:city":"Klamath Falls",
    "sg:classifiers":[
        {
            "category":"Shopping",
            "subcategory":"Used Merchandise",
            "type":"Retail Goods"
        }
    ],
    "sg:phone":"+1 541 884 0197",
    "sg:postcode":"97603",
    "sg:province":"OR",
    "wof:name":"Basin Book Trader",
    "wof:placetype":"venue"
},
  "geometry": {"coordinates":[-121.728342,42.206438],"type":"Point"}
}