{
  "type": "Feature",
  "properties": {
    "addr:full":"390 9th St Florence OR 97439",
    "addr:housenumber":"390",
    "addr:postcode":"97439",
    "addr:street":"9Th St",
    "iso:country":"US",
    "sg:address":"390 9th St",
    "sg:city":"Florence",
    "sg:classifiers":[
        {
            "category":"Health Services",
            "subcategory":"Doctor",
            "type":"Services"
        },
        {
            "category":"Health Services",
            "subcategory":"Clinic",
            "type":"Services"
        }
    ],
    "sg:phone":"+1 541 902 6126",
    "sg:postcode":"97439",
    "sg:province":"OR",
    "sg:tags":[
        "physician",
        "surgeon",
        "osteopathic"
    ],
    "wof:name":"Anthony L Dodson Md",
    "wof:placetype":"venue"
},
  "geometry": {"coordinates":[-124.11752,43.974591],"type":"Point"}
}