{
  "type": "Feature",
  "properties": {
    "iso:country":"US",
    "sg:address":"11415 SE Highland Loop",
    "sg:city":"Clackamas",
    "sg:classifiers":[
        {
            "category":"Shopping",
            "subcategory":"Clothing, Apparel, & Fashions",
            "type":"Retail Goods"
        }
    ],
    "sg:phone":"+1 503 698 7095",
    "sg:postcode":"97015",
    "sg:province":"OR",
    "sg:tags":[
        "m",
        "mfg"
    ],
    "wof:name":"Hugs & Kisses",
    "wof:placetype":"venue"
},
  "geometry": {"coordinates":[-122.551839,45.417908],"type":"Point"}
}