{
  "type": "Feature",
  "properties": {
    "iso:country":"US",
    "sg:address":"32897 Fern Rd",
    "sg:city":"Philomath",
    "sg:classifiers":[
        {
            "category":"Farming",
            "subcategory":"Poultry Farm",
            "type":"Manufacturing & Wholesale Goods"
        }
    ],
    "sg:phone":"+1 541 929 5605",
    "sg:postcode":"97370",
    "sg:province":"OR",
    "sg:tags":[
        "hatchery"
    ],
    "wof:name":"Lonsway Farms",
    "wof:placetype":"venue"
},
  "geometry": {"coordinates":[-123.366905,44.517647],"type":"Point"}
}