{
  "type": "Feature",
  "properties": {
    "addr:full":"3815 Marion St SE Albany OR 97322",
    "addr:housenumber":"3815",
    "addr:postcode":"97322",
    "addr:street":"Marion St Se",
    "iso:country":"US",
    "sg:address":"3815 Marion St SE",
    "sg:city":"Albany",
    "sg:classifiers":[
        {
            "category":"Freight",
            "type":"Transportation"
        }
    ],
    "sg:phone":"+1 541 928 5755",
    "sg:postcode":"97322",
    "sg:province":"OR",
    "sg:tags":[
        "refrigeration"
    ],
    "wof:name":"Sno Temp Cold Storage",
    "wof:placetype":"venue"
},
  "geometry": {"coordinates":[-123.097934,44.606339],"type":"Point"}
}