{
  "type": "Feature",
  "properties": {
    "iso:country":"US",
    "sg:address":"319 SW Washington St",
    "sg:city":"Portland",
    "sg:classifiers":[
        {
            "category":"Professional",
            "subcategory":"Engineering",
            "type":"Services"
        }
    ],
    "sg:phone":"+1 503 220 5992",
    "sg:postcode":"97204",
    "sg:province":"OR",
    "sg:tags":[
        "management",
        "design",
        "architectural"
    ],
    "sg:website":"www.heery.com",
    "wof:name":"Heery International Inc",
    "wof:placetype":"venue"
},
  "geometry": {"coordinates":[-122.675678,45.51988],"type":"Point"}
}