{
  "type": "Feature",
  "properties": {
    "addr:full":"1625 NW Sundial Rd Troutdale OR 97060",
    "addr:housenumber":"1625",
    "addr:postcode":"97060",
    "addr:street":"Nw Sundial Rd",
    "iso:country":"US",
    "sg:address":"1625 NW Sundial Rd",
    "sg:city":"Troutdale",
    "sg:classifiers":[
        {
            "category":"Manufacturing",
            "subcategory":"Chemicals & Compounds",
            "type":"Manufacturing & Wholesale Goods"
        }
    ],
    "sg:phone":"+1 503 666 8398",
    "sg:postcode":"97060",
    "sg:province":"OR",
    "sg:tags":[
        "diagnostic"
    ],
    "sg:website":"www.mmldiagnostics.com",
    "wof:name":"MML Diagnostics Packaging",
    "wof:placetype":"venue"
},
  "geometry": {"coordinates":[-122.408843,45.552251],"type":"Point"}
}