{
  "type": "Feature",
  "properties": {
    "addr:full":"900 NW Mawrcrest Dr Gresham OR 97030",
    "addr:housenumber":"900",
    "addr:postcode":"97030",
    "addr:street":"Nw Mawrcrest Dr",
    "iso:country":"US",
    "sg:address":"900 NW Mawrcrest Dr",
    "sg:city":"Gresham",
    "sg:classifiers":[
        {
            "category":"Real Estate",
            "subcategory":"Real Estate Operator",
            "type":"Services"
        }
    ],
    "sg:phone":"+1 503 666 3512",
    "sg:postcode":"97030",
    "sg:province":"OR",
    "sg:tags":[
        "apartment"
    ],
    "wof:name":"Bryn Mawr Apartments",
    "wof:placetype":"venue"
},
  "geometry": {"coordinates":[-122.456791,45.502802],"type":"Point"}
}