{
  "type": "Feature",
  "properties": {
    "addr:full":"88870 Stock Still Rd Bandon OR 97411",
    "addr:postcode":"88870;97411",
    "addr:street":"Stock Still Rd",
    "iso:country":"US",
    "sg:address":"88870 Stock Still Rd",
    "sg:city":"Bandon",
    "sg:classifiers":[
        {
            "category":"Wholesale",
            "subcategory":"Motor Vehicles",
            "type":"Manufacturing & Wholesale Goods"
        }
    ],
    "sg:phone":"+1 541 347 8062",
    "sg:postcode":"97411",
    "sg:province":"OR",
    "sg:tags":[
        "truck",
        "driver"
    ],
    "wof:name":"Alan Menje",
    "wof:placetype":"venue"
},
  "geometry": {"coordinates":[-124.370785,43.208272],"type":"Point"}
}