{
  "type": "Feature",
  "properties": {
    "iso:country":"US",
    "sg:address":"959 Hardcastle Ave",
    "sg:city":"Woodburn",
    "sg:classifiers":[
        {
            "category":"Building & Trades",
            "subcategory":"Construction",
            "type":"Services"
        }
    ],
    "sg:phone":"+1 503 981 6224",
    "sg:postcode":"97071",
    "sg:province":"OR",
    "sg:tags":[
        "contractor"
    ],
    "wof:name":"Scheratski Dami",
    "wof:placetype":"venue"
},
  "geometry": {"coordinates":[-122.845666,45.145726],"type":"Point"}
}