{
  "type": "Feature",
  "properties": {
    "addr:full":"850 Conger St Eugene OR 97402",
    "addr:housenumber":"850",
    "addr:postcode":"97402",
    "addr:street":"Conger St",
    "iso:country":"US",
    "sg:address":"850 Conger St",
    "sg:city":"Eugene",
    "sg:classifiers":[
        {
            "category":"Wholesale",
            "subcategory":"Machinery & Supplies",
            "type":"Manufacturing & Wholesale Goods"
        }
    ],
    "sg:phone":"+1 541 683 9333",
    "sg:postcode":"97402",
    "sg:province":"OR",
    "sg:tags":[
        "equipment",
        "safety",
        "clothing"
    ],
    "wof:name":"Sanderson Safety Supply Co",
    "wof:placetype":"venue"
},
  "geometry": {"coordinates":[-123.134139,44.050481],"type":"Point"}
}