{
  "type": "Feature",
  "properties": {
    "addr:full":"712 N Central St Coquille OR 97423",
    "addr:housenumber":"712",
    "addr:postcode":"97423",
    "addr:street":"N Central St",
    "iso:country":"US",
    "sg:address":"712 N Central St",
    "sg:city":"Coquille",
    "sg:classifiers":[
        {
            "category":"Professional",
            "type":"Services"
        }
    ],
    "sg:phone":"+1 541 396 7357",
    "sg:postcode":"97423",
    "sg:province":"OR",
    "wof:name":"Goodeworks",
    "wof:placetype":"venue"
},
  "geometry": {"coordinates":[-124.188858,43.181861],"type":"Point"}
}