{
  "type": "Feature",
  "properties": {
    "iso:country":"US",
    "sg:address":"7500 W Baseline",
    "sg:city":"Beaverton",
    "sg:classifiers":[
        {
            "category":"Shopping",
            "subcategory":"Pharmacy",
            "type":"Retail Goods"
        }
    ],
    "sg:phone":"+1 503 591 0997",
    "sg:postcode":"97005",
    "sg:province":"OR",
    "sg:tags":[
        "drugstore"
    ],
    "sg:website":"www.albertsons.com",
    "wof:name":"Albertson's Food & Drug",
    "wof:placetype":"venue"
},
  "geometry": {"coordinates":[-122.806,45.4953],"type":"Point"}
}