{
  "type": "Feature",
  "properties": {
    "addr:full":"2260 Oakmont Way Eugene OR 97401",
    "addr:housenumber":"2260",
    "addr:postcode":"97401",
    "addr:street":"Oakmont Way",
    "iso:country":"US",
    "sg:address":"2260 Oakmont Way",
    "sg:city":"Eugene",
    "sg:classifiers":[
        {
            "category":"Manufacturing",
            "subcategory":"Paper Products",
            "type":"Manufacturing & Wholesale Goods"
        }
    ],
    "sg:phone":"+1 541 341 3992",
    "sg:postcode":"97401",
    "sg:province":"OR",
    "sg:tags":[
        "label"
    ],
    "wof:name":"Label & Bar Code Inc",
    "wof:placetype":"venue"
},
  "geometry": {"coordinates":[-123.074913,44.067245],"type":"Point"}
}