{
  "type": "Feature",
  "properties": {
    "iso:country":"US",
    "sg:address":"222 4th Ave SW",
    "sg:city":"Albany",
    "sg:classifiers":[
        {
            "category":"Professional",
            "subcategory":"Management & Consulting",
            "type":"Services"
        }
    ],
    "sg:phone":"+1 541 928 0700",
    "sg:postcode":"97321",
    "sg:province":"OR",
    "sg:tags":[
        "consultant",
        "automation"
    ],
    "wof:name":"Oregon Automation Inc",
    "wof:placetype":"venue"
},
  "geometry": {"coordinates":[-123.105931,44.634801],"type":"Point"}
}