{
  "type": "Feature",
  "properties": {
    "iso:country":"US",
    "sg:address":"700 NE Multnomah St",
    "sg:city":"Portland",
    "sg:classifiers":[
        {
            "category":"Travel",
            "subcategory":"Travel Agent",
            "type":"Entertainment"
        }
    ],
    "sg:phone":"+1 503 231 1600",
    "sg:postcode":"97232",
    "sg:province":"OR",
    "sg:tags":[
        "agency",
        "bureau"
    ],
    "sg:website":"www.wtpdx.com",
    "wof:name":"World Travel Inc",
    "wof:placetype":"venue"
},
  "geometry": {"coordinates":[-122.656587,45.531493],"type":"Point"}
}