{
  "type": "Feature",
  "properties": {
    "iso:country":"US",
    "sg:address":"16800 SW Siler Ridge Ln",
    "sg:city":"Beaverton",
    "sg:classifiers":[
        {
            "category":"Arts & Performance",
            "subcategory":"Theater",
            "type":"Entertainment"
        }
    ],
    "sg:phone":"+1 503 579 6987",
    "sg:postcode":"97007",
    "sg:province":"OR",
    "sg:tags":[
        "group"
    ],
    "wof:name":"Rose City Flute Choir",
    "wof:placetype":"venue"
},
  "geometry": {"coordinates":[-122.850502,45.440892],"type":"Point"}
}