{
  "type": "Feature",
  "properties": {
    "iso:country":"US",
    "sg:address":"425 del Rio Rd",
    "sg:city":"Roseburg",
    "sg:classifiers":[
        {
            "category":"Manufacturing",
            "subcategory":"Lumber",
            "type":"Manufacturing & Wholesale Goods"
        }
    ],
    "sg:phone":"+1 541 440 0180",
    "sg:postcode":"97470",
    "sg:province":"OR",
    "sg:tags":[
        "mill"
    ],
    "wof:name":"Do Able Products Inc",
    "wof:placetype":"venue"
},
  "geometry": {"coordinates":[-123.360483,43.287106],"type":"Point"}
}