{
  "type": "Feature",
  "properties": {
    "iso:country":"US",
    "sg:address":"55 SW Yamhill St",
    "sg:city":"Portland",
    "sg:classifiers":[
        {
            "category":"Professional",
            "subcategory":"Lawyer & Legal Services",
            "type":"Services"
        }
    ],
    "sg:phone":"+1 503 224 2165",
    "sg:postcode":"97204",
    "sg:province":"OR",
    "wof:name":"MacMillan Roderic S",
    "wof:placetype":"venue"
},
  "geometry": {"coordinates":[-122.672997,45.516899],"type":"Point"}
}