{
  "type": "Feature",
  "properties": {
    "addr:full":"6290 SW Arctic Dr Beaverton OR 97005",
    "addr:housenumber":"6290",
    "addr:postcode":"97005",
    "addr:street":"Sw Arctic Dr",
    "iso:country":"US",
    "sg:address":"6290 SW Arctic Dr",
    "sg:city":"Beaverton",
    "sg:classifiers":[
        {
            "category":"Insurance",
            "subcategory":"Insurance Agent",
            "type":"Services"
        }
    ],
    "sg:phone":"+1 503 644 9945",
    "sg:postcode":"97005",
    "sg:province":"OR",
    "wof:name":"W B Adams Co",
    "wof:placetype":"venue"
},
  "geometry": {"coordinates":[-122.77860800000001,45.475838],"type":"Point"}
}