{
  "type": "Feature",
  "properties": {
    "addr:full":"16545 Ellendale Rd Dallas OR 97338",
    "addr:housenumber":"16545",
    "addr:postcode":"97338",
    "addr:street":"Ellendale Rd",
    "iso:country":"US",
    "sg:address":"16545 Ellendale Rd",
    "sg:city":"Dallas",
    "sg:classifiers":[
        {
            "category":"Social Services",
            "subcategory":"Child Care",
            "type":"Services"
        },
        {
            "category":"Retail",
            "subcategory":"Animal Services",
            "type":"Services"
        }
    ],
    "sg:phone":"+1 503 831 1811",
    "sg:postcode":"97338",
    "sg:province":"OR",
    "sg:tags":[
        "cat",
        "dog",
        "day",
        "kennel"
    ],
    "wof:name":"Dallas Doggie Daycare Inc",
    "wof:placetype":"venue"
},
  "geometry": {"coordinates":[-123.369224,44.921329],"type":"Point"}
}