{
  "type": "Feature",
  "properties": {
    "addr:full":"61400 S Hwy 97 Bend OR 97702",
    "addr:housenumber":"61400",
    "addr:postcode":"97702",
    "addr:street":"S Hwy 97",
    "iso:country":"US",
    "sg:address":"61400 S Hwy 97",
    "sg:city":"Bend",
    "sg:classifiers":[
        {
            "category":"Food & Beverages",
            "subcategory":"Bakery",
            "type":"Retail Goods"
        }
    ],
    "sg:phone":"+1 541 330 1729",
    "sg:postcode":"97702",
    "sg:province":"OR",
    "wof:name":"Wonder Bread",
    "wof:placetype":"venue"
},
  "geometry": {"coordinates":[-121.31214,44.028914],"type":"Point"}
}