{
  "type": "Feature",
  "properties": {
    "addr:full":"10713 SE 82nd Ave Portland OR 97086",
    "addr:postcode":"10713;97086",
    "addr:street":"Se 82Nd Ave",
    "iso:country":"US",
    "sg:address":"10713 SE 82nd Ave",
    "sg:city":"Portland",
    "sg:classifiers":[
        {
            "category":"Building & Trades",
            "subcategory":"Locksmith",
            "type":"Services"
        }
    ],
    "sg:phone":"+1 503 303 6800",
    "sg:postcode":"97086",
    "sg:province":"OR",
    "sg:tags":[
        "key"
    ],
    "wof:name":"1 & 1 Anytime Locksmith",
    "wof:placetype":"venue"
},
  "geometry": {"coordinates":[-122.579052,45.445183],"type":"Point"}
}