{
  "type": "Feature",
  "properties": {
    "iso:country":"US",
    "sg:address":"603 S 10th St",
    "sg:city":"Coos Bay",
    "sg:classifiers":[
        {
            "category":"Professional",
            "subcategory":"Computer Services",
            "type":"Services"
        }
    ],
    "sg:phone":"+1 541 266 7344",
    "sg:postcode":"97420",
    "sg:province":"OR",
    "sg:tags":[
        "robotics",
        "software"
    ],
    "wof:name":"Distinct Knowledge",
    "wof:placetype":"venue"
},
  "geometry": {"coordinates":[-124.22211900000001,43.363586],"type":"Point"}
}