{
  "type": "Feature",
  "properties": {
    "addr:full":"15055 SW Sequoia Pkwy Portland OR 97224",
    "addr:housenumber":"15055",
    "addr:postcode":"97224",
    "addr:street":"Sw Sequoia Pkwy",
    "iso:country":"US",
    "sg:address":"15055 SW Sequoia Pkwy",
    "sg:city":"Portland",
    "sg:classifiers":[
        {
            "category":"Communications",
            "type":"Services"
        }
    ],
    "sg:phone":"+1 503 403 4200",
    "sg:postcode":"97224",
    "sg:province":"OR",
    "sg:tags":[
        "equipment",
        "data",
        "system"
    ],
    "sg:website":"http://www.asiapt.com",
    "wof:name":"Asia Pacific Telecom",
    "wof:placetype":"venue"
},
  "geometry": {"coordinates":[-122.746843,45.411265],"type":"Point"}
}