{
  "type": "Feature",
  "properties": {
    "iso:country":"US",
    "sg:address":"3155 SW 234th Ave",
    "sg:city":"Hillsboro",
    "sg:classifiers":[
        {
            "category":"Building & Trades",
            "subcategory":"Construction",
            "type":"Services"
        }
    ],
    "sg:phone":"+1 503 649 6422",
    "sg:postcode":"97123",
    "sg:province":"OR",
    "sg:tags":[
        "painting",
        "painter",
        "contractor"
    ],
    "wof:name":"Kevin Fitzpatrick Painting Co",
    "wof:placetype":"venue"
},
  "geometry": {"coordinates":[-122.917388,45.498899],"type":"Point"}
}