{
  "type": "Feature",
  "properties": {
    "iso:country":"US",
    "sg:address":"1111 SW 10th Ave",
    "sg:city":"Portland",
    "sg:classifiers":[
        {
            "category":"Social Services",
            "type":"Services"
        }
    ],
    "sg:phone":"+1 503 223 5069",
    "sg:postcode":"97205",
    "sg:province":"OR",
    "sg:tags":[
        "organization",
        "membership"
    ],
    "wof:name":"Northwest Loaves & Fshes Inc",
    "wof:placetype":"venue"
},
  "geometry": {"coordinates":[-122.68431200000001,45.516106],"type":"Point"}
}