{
  "type": "Feature",
  "properties": {
    "addr:full":"12917 S W Lark Meadow Ln Powell Butte OR 97753",
    "addr:housenumber":"12917",
    "addr:postcode":"97753",
    "addr:street":"S W Lark Meadow Ln",
    "iso:country":"US",
    "sg:address":"12917 S W Lark Meadow Ln",
    "sg:city":"Powell Butte",
    "sg:classifiers":[
        {
            "category":"Building & Trades",
            "subcategory":"Construction",
            "type":"Services"
        }
    ],
    "sg:phone":"+1 541 416 9758",
    "sg:postcode":"97753",
    "sg:province":"OR",
    "sg:tags":[
        "house",
        "nonresidential"
    ],
    "wof:name":"Fisher Construction",
    "wof:placetype":"venue"
},
  "geometry": {"coordinates":[-121.01339299999999,44.305452],"type":"Point"}
}