{
  "type": "Feature",
  "properties": {
    "addr:full":"1346 NE Emerson St Portland OR 97211",
    "addr:housenumber":"1346",
    "addr:postcode":"97211",
    "addr:street":"Ne Emerson St",
    "iso:country":"US",
    "sg:address":"1346 NE Emerson St",
    "sg:city":"Portland",
    "sg:classifiers":[
        {
            "category":"Professional",
            "type":"Services"
        }
    ],
    "sg:phone":"+1 503 287 8748",
    "sg:postcode":"97211",
    "sg:province":"OR",
    "wof:name":"Florence M Fleskes",
    "wof:placetype":"venue"
},
  "geometry": {"coordinates":[-122.652372,45.561731],"type":"Point"}
}