{
  "type": "Feature",
  "properties": {
    "iso:country":"US",
    "sg:address":"1905 Agate St",
    "sg:city":"Eugene",
    "sg:classifiers":[
        {
            "category":"Retail",
            "subcategory":"Auto Repair",
            "type":"Services"
        }
    ],
    "sg:phone":"+1 541 344 0869",
    "sg:postcode":"97403",
    "sg:province":"OR",
    "sg:tags":[
        "repairing",
        "automobile"
    ],
    "wof:name":"Sun Automotive",
    "wof:placetype":"venue"
},
  "geometry": {"coordinates":[-123.06961800000001,44.038413],"type":"Point"}
}