{
  "type": "Feature",
  "properties": {
    "addr:full":"20337 S Leland Rd Oregon City OR 97045",
    "addr:housenumber":"20337",
    "addr:postcode":"97045",
    "addr:street":"S Leland Rd",
    "iso:country":"US",
    "sg:address":"20337 S Leland Rd",
    "sg:city":"Oregon City",
    "sg:classifiers":[
        {
            "category":"Autos & Motor Vehicles",
            "subcategory":"Automobile Sales",
            "type":"Retail Goods"
        }
    ],
    "sg:phone":"+1 503 657 0405",
    "sg:postcode":"97045",
    "sg:province":"OR",
    "wof:name":"Trail Pals",
    "wof:placetype":"venue"
},
  "geometry": {"coordinates":[-122.60239,45.310751],"type":"Point"}
}