{
  "type": "Feature",
  "properties": {
    "iso:country":"US",
    "sg:address":"1336 N 1st St",
    "sg:city":"Stayton",
    "sg:classifiers":[
        {
            "category":"Professional",
            "subcategory":"Accounting & Tax Preparation",
            "type":"Services"
        }
    ],
    "sg:phone":"+1 503 769 6813",
    "sg:postcode":"97383",
    "sg:province":"OR",
    "sg:tags":[
        "bookkeeping"
    ],
    "wof:name":"Hansen, Edward A Pc",
    "wof:placetype":"venue"
},
  "geometry": {"coordinates":[-122.794319,44.804608],"type":"Point"}
}