{
  "type": "Feature",
  "properties": {
    "iso:country":"US",
    "sg:address":"120 SW Ankeny St",
    "sg:city":"Portland",
    "sg:classifiers":[
        {
            "category":"Shopping",
            "subcategory":"Gifts & Souvenirs",
            "type":"Retail Goods"
        }
    ],
    "sg:phone":"+1 503 294 7132",
    "sg:postcode":"97204",
    "sg:province":"OR",
    "sg:tags":[
        "shop"
    ],
    "wof:name":"Gifts With Attitude By Icbm",
    "wof:placetype":"venue"
},
  "geometry": {"coordinates":[-122.672137,45.522456],"type":"Point"}
}