{
  "type": "Feature",
  "properties": {
    "addr:full":"10710 NE Morris St Portland OR 97220",
    "addr:housenumber":"10710",
    "addr:postcode":"97220",
    "addr:street":"Ne Morris St",
    "iso:country":"US",
    "sg:address":"10710 NE Morris St",
    "sg:city":"Portland",
    "sg:classifiers":[
        {
            "category":"Real Estate",
            "subcategory":"Surveying",
            "type":"Services"
        }
    ],
    "sg:phone":"+1 503 254 8779",
    "sg:postcode":"97220",
    "sg:province":"OR",
    "wof:name":"Agape Land Survey Co",
    "wof:placetype":"venue"
},
  "geometry": {"coordinates":[-122.555671,45.543488],"type":"Point"}
}