{
  "type": "Feature",
  "properties": {
    "iso:country":"US",
    "sg:address":"27501 SE Nelson Rd",
    "sg:city":"Sandy",
    "sg:classifiers":[
        {
            "category":"Building & Trades",
            "subcategory":"Construction",
            "type":"Services"
        }
    ],
    "sg:phone":"+1 503 637 3639",
    "sg:postcode":"97055",
    "sg:province":"OR",
    "sg:tags":[
        "house"
    ],
    "wof:name":"Jhc Construction",
    "wof:placetype":"venue"
},
  "geometry": {"coordinates":[-122.21868000000001,45.327119],"type":"Point"}
}