{
  "type": "Feature",
  "properties": {
    "iso:country":"US",
    "sg:address":"2322 NW Irving St",
    "sg:city":"Portland",
    "sg:classifiers":[
        {
            "category":"Professional",
            "type":"Services"
        }
    ],
    "sg:phone":"+1 503 243 5300",
    "sg:postcode":"97210",
    "sg:province":"OR",
    "sg:tags":[
        "establishment"
    ],
    "wof:name":"Irving'Son Irving St",
    "wof:placetype":"venue"
},
  "geometry": {"coordinates":[-122.700236,45.527546],"type":"Point"}
}