{
  "type": "Feature",
  "properties": {
    "iso:country":"US",
    "sg:address":"309 SE 21st Pl",
    "sg:city":"Hillsboro",
    "sg:classifiers":[
        {
            "category":"Building & Trades",
            "subcategory":"Construction",
            "type":"Services"
        }
    ],
    "sg:phone":"+1 503 648 7730",
    "sg:postcode":"97123",
    "sg:province":"OR",
    "sg:tags":[
        "masonry",
        "contractor"
    ],
    "wof:name":"Dave Clooten Masonry",
    "wof:placetype":"venue"
},
  "geometry": {"coordinates":[-122.96135599999999,45.519258],"type":"Point"}
}