{
  "type": "Feature",
  "properties": {
    "iso:country":"US",
    "sg:address":"36 S Riverside Ave",
    "sg:city":"Medford",
    "sg:classifiers":[
        {
            "category":"Shopping",
            "subcategory":"Clothing, Apparel, & Fashions",
            "type":"Retail Goods"
        }
    ],
    "sg:phone":"+1 541 773 5165",
    "sg:postcode":"97501",
    "sg:province":"OR",
    "sg:tags":[
        "ready",
        "bathing",
        "lingerie",
        "suit"
    ],
    "wof:name":"Cellar Downtown",
    "wof:placetype":"venue"
},
  "geometry": {"coordinates":[-122.870187,42.326772],"type":"Point"}
}