{
  "type": "Feature",
  "properties": {
    "iso:country":"US",
    "sg:address":"34535 S Ellis Rd",
    "sg:city":"Molalla",
    "sg:classifiers":[
        {
            "category":"Professional",
            "type":"Services"
        }
    ],
    "sg:phone":"+1 503 829 4691",
    "sg:postcode":"97038",
    "sg:province":"OR",
    "wof:name":"Moms Attic",
    "wof:placetype":"venue"
},
  "geometry": {"coordinates":[-122.543932,45.105951],"type":"Point"}
}