{
  "type": "Feature",
  "properties": {
    "iso:country":"US",
    "sg:address":"83528 N Harvey Rd",
    "sg:city":"Creswell",
    "sg:classifiers":[
        {
            "category":"Building & Trades",
            "subcategory":"Landscaping Services",
            "type":"Services"
        }
    ],
    "sg:phone":"+1 541 895 4201",
    "sg:postcode":"97426",
    "sg:province":"OR",
    "wof:name":"Earth Services Landscaping",
    "wof:placetype":"venue"
},
  "geometry": {"coordinates":[-123.024351,43.93102],"type":"Point"}
}