{
  "type": "Feature",
  "properties": {
    "addr:full":"927 Molalla Ave Oregon City OR 97045",
    "addr:housenumber":"927",
    "addr:postcode":"97045",
    "addr:street":"Molalla Ave",
    "iso:country":"US",
    "sg:address":"927 Molalla Ave",
    "sg:city":"Oregon City",
    "sg:classifiers":[
        {
            "category":"Retail",
            "subcategory":"Self-service Laundry",
            "type":"Services"
        }
    ],
    "sg:phone":"+1 503 656 9704",
    "sg:postcode":"97045",
    "sg:province":"OR",
    "sg:tags":[
        "coin"
    ],
    "wof:name":"Carousel Cleaners & Laundry",
    "wof:placetype":"venue"
},
  "geometry": {"coordinates":[-122.594323,45.341658],"type":"Point"}
}