{
  "type": "Feature",
  "properties": {
    "iso:country":"US",
    "sg:address":"315 SW 9th St",
    "sg:city":"Newport",
    "sg:classifiers":[
        {
            "category":"Professional",
            "type":"Services"
        }
    ],
    "sg:phone":"+1 541 265 8812",
    "sg:postcode":"97365",
    "sg:province":"OR",
    "sg:tags":[
        "establishment"
    ],
    "wof:name":"LA Maison",
    "wof:placetype":"venue"
},
  "geometry": {"coordinates":[-124.054992,44.6331],"type":"Point"}
}