{
  "type": "Feature",
  "properties": {
    "iso:country":"US",
    "sg:address":"2642 NW Nordic Ave",
    "sg:city":"Bend",
    "sg:classifiers":[
        {
            "category":"Shopping",
            "type":"Retail Goods"
        }
    ],
    "sg:phone":"+1 541 382 3911",
    "sg:postcode":"97701",
    "sg:province":"OR",
    "sg:tags":[
        "merchandise"
    ],
    "wof:name":"Haynes, Danna",
    "wof:placetype":"venue"
},
  "geometry": {"coordinates":[-121.35590999999999,44.073457],"type":"Point"}
}