{
  "type": "Feature",
  "properties": {
    "addr:full":"2233 NW 22nd Ave Portland OR 97210",
    "addr:housenumber":"2233",
    "addr:postcode":"97210",
    "addr:street":"Nw 22Nd Ave",
    "iso:country":"US",
    "sg:address":"2233 NW 22nd Ave",
    "sg:city":"Portland",
    "sg:classifiers":[
        {
            "category":"Personal",
            "type":"Services"
        }
    ],
    "sg:phone":"+1 360 693 1213",
    "sg:postcode":"97210",
    "sg:province":"OR",
    "sg:tags":[
        "mover"
    ],
    "wof:name":"Allied Van Lines Agents",
    "wof:placetype":"venue"
},
  "geometry": {"coordinates":[-122.697408,45.538738],"type":"Point"}
}