{
  "type": "Feature",
  "properties": {
    "addr:full":"120 NW 13th Ave Portland OR 97209",
    "addr:housenumber":"120",
    "addr:postcode":"97209",
    "addr:street":"Nw 13Th Ave",
    "iso:country":"US",
    "sg:address":"120 NW 13th Ave",
    "sg:city":"Portland",
    "sg:classifiers":[
        {
            "category":"Shopping",
            "subcategory":"Beauty & Cosmetics",
            "type":"Retail Goods"
        },
        {
            "category":"Personal",
            "subcategory":"Hair Removal",
            "type":"Services"
        },
        {
            "category":"Personal",
            "subcategory":"Skin Care",
            "type":"Services"
        }
    ],
    "sg:phone":"+1 503 360 1178",
    "sg:postcode":"97209",
    "sg:province":"OR",
    "sg:tags":[
        "supply"
    ],
    "sg:website":"www.be-smooth.net",
    "wof:name":"Be Smooth Wax & Beauty Boutique",
    "wof:placetype":"venue"
},
  "geometry": {"coordinates":[-122.684172,45.523775],"type":"Point"}
}