{
  "type": "Feature",
  "properties": {
    "iso:country":"US",
    "sg:address":"1230 Sonora Ave",
    "sg:city":"Astoria",
    "sg:classifiers":[
        {
            "category":"Manufacturing",
            "subcategory":"Food",
            "type":"Manufacturing & Wholesale Goods"
        }
    ],
    "sg:phone":"+1 503 325 9138",
    "sg:postcode":"97103",
    "sg:province":"OR",
    "sg:tags":[
        "malt",
        "beverage",
        "mfg"
    ],
    "wof:name":"Astoria Brewing Co",
    "wof:placetype":"venue"
},
  "geometry": {"coordinates":[-123.845536,46.182281],"type":"Point"}
}