{
  "type": "Feature",
  "properties": {
    "addr:full":"2495 Fairgrounds Rd NE Salem OR 97301",
    "addr:housenumber":"2495",
    "addr:postcode":"97301",
    "addr:street":"Fairgrounds Rd Ne",
    "iso:country":"US",
    "sg:address":"2495 Fairgrounds Rd NE",
    "sg:city":"Salem",
    "sg:classifiers":[
        {
            "category":"Food & Beverages",
            "subcategory":"Groceries & Convenience Stores",
            "type":"Retail Goods"
        }
    ],
    "sg:phone":"+1 503 362 3424",
    "sg:postcode":"97301",
    "sg:province":"OR",
    "sg:website":"http://www.circlek.com",
    "wof:name":"Circle K",
    "wof:placetype":"venue"
},
  "geometry": {"coordinates":[-123.021828,44.955639],"type":"Point"}
}