{
  "type": "Feature",
  "properties": {
    "iso:country":"US",
    "sg:address":"1585 Bond Ln",
    "sg:city":"Eugene",
    "sg:classifiers":[
        {
            "category":"Professional",
            "subcategory":"Management & Consulting",
            "type":"Services"
        }
    ],
    "sg:phone":"+1 541 344 8766",
    "sg:postcode":"97401",
    "sg:province":"OR",
    "sg:tags":[
        "business"
    ],
    "wof:name":"Abacus Consulting LLC",
    "wof:placetype":"venue"
},
  "geometry": {"coordinates":[-123.08957,44.079999],"type":"Point"}
}