{
  "type": "Feature",
  "properties": {
    "addr:full":"332 SE 82nd Ave Portland OR 97216",
    "addr:housenumber":"332",
    "addr:postcode":"97216",
    "addr:street":"Se 82Nd Ave",
    "iso:country":"US",
    "sg:address":"332 SE 82nd Ave",
    "sg:city":"Portland",
    "sg:classifiers":[
        {
            "category":"Shopping",
            "type":"Retail Goods"
        }
    ],
    "sg:phone":"+1 503 261 9309",
    "sg:postcode":"97216",
    "sg:province":"OR",
    "sg:tags":[
        "hearing",
        "equipment",
        "supply",
        "impaired"
    ],
    "wof:name":"Hearing Care Ctr Of America",
    "wof:placetype":"venue"
},
  "geometry": {"coordinates":[-122.578986,45.520016],"type":"Point"}
}