{
  "type": "Feature",
  "properties": {
    "addr:full":"8220 SE Harrison St Portland OR 97216",
    "addr:housenumber":"8220",
    "addr:postcode":"97216",
    "addr:street":"Se Harrison St",
    "iso:country":"US",
    "sg:address":"8220 SE Harrison St",
    "sg:city":"Portland",
    "sg:classifiers":[
        {
            "category":"Professional",
            "type":"Services"
        }
    ],
    "sg:phone":"+1 503 774 8899",
    "sg:postcode":"97216",
    "sg:province":"OR",
    "sg:tags":[
        "chinese"
    ],
    "wof:name":"Jin Jin Deli",
    "wof:placetype":"venue"
},
  "geometry": {"coordinates":[-122.578413,45.508326],"type":"Point"}
}