{
  "type": "Feature",
  "properties": {
    "iso:country":"US",
    "sg:address":"5773 New Hope Rd",
    "sg:city":"Grants Pass",
    "sg:classifiers":[
        {
            "category":"Professional",
            "subcategory":"Computer Services",
            "type":"Services"
        }
    ],
    "sg:phone":"+1 541 956 1568",
    "sg:postcode":"97527",
    "sg:province":"OR",
    "sg:tags":[
        "programing",
        "custom"
    ],
    "wof:name":"Bowdoin Consulting",
    "wof:placetype":"venue"
},
  "geometry": {"coordinates":[-123.367054,42.358643],"type":"Point"}
}