{
  "type": "Feature",
  "properties": {
    "addr:full":"21515 NW Evergreen Pkwy Hillsboro OR 97124",
    "addr:housenumber":"21515",
    "addr:postcode":"97124",
    "addr:street":"Nw Evergreen Pkwy",
    "iso:country":"US",
    "sg:address":"21515 NW Evergreen Pkwy",
    "sg:city":"Hillsboro",
    "sg:classifiers":[
        {
            "category":"Wholesale",
            "subcategory":"Electrical",
            "type":"Manufacturing & Wholesale Goods"
        }
    ],
    "sg:phone":"+1 503 439 4000",
    "sg:postcode":"97124",
    "sg:province":"OR",
    "sg:tags":[
        "electronic"
    ],
    "wof:name":"Etec",
    "wof:placetype":"venue"
},
  "geometry": {"coordinates":[-122.897806,45.546424],"type":"Point"}
}