{
  "type": "Feature",
  "properties": {
    "iso:country":"US",
    "sg:address":"22889 SE Naomi Dr",
    "sg:city":"Boring",
    "sg:classifiers":[
        {
            "category":"Organizations",
            "subcategory":"Community Association",
            "type":"Services"
        }
    ],
    "sg:phone":"+1 503 658 2375",
    "sg:postcode":"97089",
    "sg:province":"OR",
    "wof:name":"Rancho Ondo Homeowners Assn",
    "wof:placetype":"venue"
},
  "geometry": {"coordinates":[-122.431671,45.411851],"type":"Point"}
}