{
  "type": "Feature",
  "properties": {
    "iso:country":"US",
    "sg:address":"10995 SE 25th Ave",
    "sg:city":"Portland",
    "sg:classifiers":[
        {
            "category":"Organizations",
            "subcategory":"Religious Organization",
            "type":"Services"
        }
    ],
    "sg:phone":"+1 503 654 5449",
    "sg:postcode":"97222",
    "sg:province":"OR",
    "sg:tags":[
        "church"
    ],
    "wof:name":"St John's The Baptist Catholic",
    "wof:placetype":"venue"
},
  "geometry": {"coordinates":[-122.636706,45.44377],"type":"Point"}
}