{
  "type": "Feature",
  "properties": {
    "iso:country":"US",
    "sg:address":"1931 SE 50th Ave",
    "sg:city":"Portland",
    "sg:classifiers":[
        {
            "category":"Professional",
            "subcategory":"Art Services",
            "type":"Services"
        }
    ],
    "sg:phone":"+1 503 236 6390",
    "sg:postcode":"97215",
    "sg:province":"OR",
    "sg:tags":[
        "graphic",
        "designer"
    ],
    "wof:name":"Petrograf",
    "wof:placetype":"venue"
},
  "geometry": {"coordinates":[-122.611385,45.509196],"type":"Point"}
}