{
  "type": "Feature",
  "properties": {
    "iso:country":"US",
    "sg:address":"1084 Colony Pond Dr",
    "sg:city":"Eugene",
    "sg:classifiers":[
        {
            "category":"Retail",
            "subcategory":"Auto Repair",
            "type":"Services"
        }
    ],
    "sg:phone":"+1 541 685 9791",
    "sg:postcode":"97401",
    "sg:province":"OR",
    "sg:tags":[
        "automotive",
        "tune"
    ],
    "wof:name":"Transhelp Inc",
    "wof:placetype":"venue"
},
  "geometry": {"coordinates":[-123.108852,44.084163],"type":"Point"}
}