{
  "type": "Feature",
  "properties": {
    "addr:full":"13125 NE Failing St Portland OR 97230",
    "addr:housenumber":"13125",
    "addr:postcode":"97230",
    "addr:street":"Ne Failing St",
    "iso:country":"US",
    "sg:address":"13125 NE Failing St",
    "sg:city":"Portland",
    "sg:classifiers":[
        {
            "category":"Utilities",
            "subcategory":"Water",
            "type":"Services"
        }
    ],
    "sg:phone":"+1 503 253 1553",
    "sg:postcode":"97230",
    "sg:province":"OR",
    "sg:tags":[
        "equipment",
        "conditioning",
        "softening"
    ],
    "sg:website":"http://www.wmciprime.com",
    "wof:name":"Wmci",
    "wof:placetype":"venue"
},
  "geometry": {"coordinates":[-122.528228,45.550433],"type":"Point"}
}