{
  "type": "Feature",
  "properties": {
    "addr:full":"16863 SE Carmel Ct Portland OR 97267",
    "addr:postcode":"16863;97267",
    "addr:street":"Se Carmel Ct",
    "iso:country":"US",
    "sg:address":"16863 SE Carmel Ct",
    "sg:city":"Portland",
    "sg:classifiers":[
        {
            "category":"Professional",
            "type":"Services"
        }
    ],
    "sg:phone":"+1 503 659 5788",
    "sg:postcode":"97267",
    "sg:province":"OR",
    "wof:name":"Egger Art Studio",
    "wof:placetype":"venue"
},
  "geometry": {"coordinates":[-122.631339,45.400724],"type":"Point"}
}