{
  "type": "Feature",
  "properties": {
    "iso:country":"US",
    "sg:address":"318 S 28th Ave",
    "sg:city":"Cornelius",
    "sg:classifiers":[
        {
            "category":"Manufacturing",
            "subcategory":"Tools & Machinery",
            "type":"Manufacturing & Wholesale Goods"
        }
    ],
    "sg:phone":"+1 503 681 2489",
    "sg:postcode":"97113",
    "sg:province":"OR",
    "sg:tags":[
        "electronic"
    ],
    "wof:name":"Miratron",
    "wof:placetype":"venue"
},
  "geometry": {"coordinates":[-123.036969,45.5173],"type":"Point"}
}