{
  "type": "Feature",
  "properties": {
    "addr:full":"23875 SW Farmington Rd Beaverton OR 97007",
    "addr:housenumber":"23875",
    "addr:postcode":"97007",
    "addr:street":"Sw Farmington Rd",
    "iso:country":"US",
    "sg:address":"23875 SW Farmington Rd",
    "sg:city":"Beaverton",
    "sg:classifiers":[
        {
            "category":"Farming",
            "subcategory":"Livestock Farm",
            "type":"Manufacturing & Wholesale Goods"
        }
    ],
    "sg:phone":"+1 503 628 1320",
    "sg:postcode":"97007",
    "sg:province":"OR",
    "sg:tags":[
        "equine"
    ],
    "wof:name":"Shenandoah Valley Ranch",
    "wof:placetype":"venue"
},
  "geometry": {"coordinates":[-122.92266100000001,45.448333],"type":"Point"}
}