{
  "type": "Feature",
  "properties": {
    "iso:country":"US",
    "sg:address":"1655 SW Highland Ave Ste 3",
    "sg:city":"Redmond",
    "sg:classifiers":[
        {
            "category":"Professional",
            "subcategory":"Accounting & Tax Preparation",
            "type":"Services"
        }
    ],
    "sg:phone":"+1 541 548 1011",
    "sg:postcode":"97756",
    "sg:province":"OR",
    "sg:tags":[
        "public",
        "accountants-certified"
    ],
    "wof:name":"Dasenko Joel C CPA PC",
    "wof:placetype":"venue"
},
  "geometry": {"coordinates":[-121.18608,44.269512],"type":"Point"}
}