{
  "type": "Feature",
  "properties": {
    "addr:full":"12435 SE Raymond St Portland OR 97236",
    "addr:postcode":"12435;97236",
    "addr:street":"Se Raymond St",
    "iso:country":"US",
    "sg:address":"12435 SE Raymond St",
    "sg:city":"Portland",
    "sg:classifiers":[
        {
            "category":"Building & Trades",
            "subcategory":"Construction",
            "type":"Services"
        }
    ],
    "sg:phone":"+1 503 760 2429",
    "sg:postcode":"97236",
    "sg:province":"OR",
    "sg:tags":[
        "contractor"
    ],
    "wof:name":"Professional Appliance Instlln",
    "wof:placetype":"venue"
},
  "geometry": {"coordinates":[-122.534497,45.485947],"type":"Point"}
}