{
  "type": "Feature",
  "properties": {
    "iso:country":"US",
    "sg:address":"710 SE 16th Ave",
    "sg:city":"Hillsboro",
    "sg:classifiers":[
        {
            "category":"Social Services",
            "subcategory":"Adult Care",
            "type":"Services"
        }
    ],
    "sg:phone":"+1 503 640 2793",
    "sg:postcode":"97123",
    "sg:province":"OR",
    "sg:tags":[
        "residential"
    ],
    "wof:name":"Dollys Guest House",
    "wof:placetype":"venue"
},
  "geometry": {"coordinates":[-122.96642,45.513617],"type":"Point"}
}