{
  "type": "Feature",
  "properties": {
    "iso:country":"US",
    "sg:address":"65160 Hwy 20",
    "sg:city":"Bend",
    "sg:classifiers":[
        {
            "category":"Building & Trades",
            "subcategory":"Construction",
            "type":"Services"
        }
    ],
    "sg:phone":"+1 541 382 7581",
    "sg:postcode":"97701",
    "sg:province":"OR",
    "sg:tags":[
        "contractor"
    ],
    "wof:name":"ARR Contracting Co",
    "wof:placetype":"venue"
},
  "geometry": {"coordinates":[-121.36480400000001,44.164346],"type":"Point"}
}