{
  "type": "Feature",
  "properties": {
    "iso:country":"US",
    "sg:address":"9800 SE Fuller Rd",
    "sg:city":"Portland",
    "sg:classifiers":[
        {
            "category":"Real Estate",
            "subcategory":"Real Estate Agent",
            "type":"Services"
        }
    ],
    "sg:phone":"+1 503 657 7341",
    "sg:postcode":"97086",
    "sg:province":"OR",
    "sg:website":"www.realestatebook.com",
    "wof:name":"Real Estate Book",
    "wof:placetype":"venue"
},
  "geometry": {"coordinates":[-122.576133,45.453248],"type":"Point"}
}