{
  "type": "Feature",
  "properties": {
    "iso:country":"US",
    "sg:address":"20133 Archie Briggs Rd",
    "sg:city":"Bend",
    "sg:classifiers":[
        {
            "category":"Building & Trades",
            "subcategory":"Construction",
            "type":"Services"
        }
    ],
    "sg:phone":"+1 541 330 6558",
    "sg:postcode":"97701",
    "sg:province":"OR",
    "sg:tags":[
        "general",
        "contractor"
    ],
    "wof:name":"Sun Forest Construction",
    "wof:placetype":"venue"
},
  "geometry": {"coordinates":[-121.31651100000001,44.091279],"type":"Point"}
}