{
  "type": "Feature",
  "properties": {
    "iso:country":"US",
    "sg:address":"57232 Cedar Creek Rd",
    "sg:city":"Scappoose",
    "sg:classifiers":[
        {
            "category":"Wholesale",
            "subcategory":"Machinery & Supplies",
            "type":"Manufacturing & Wholesale Goods"
        }
    ],
    "sg:phone":"+1 503 543 3986",
    "sg:postcode":"97056",
    "sg:province":"OR",
    "sg:tags":[
        "equipment",
        "transportation"
    ],
    "wof:name":"Aviacomp",
    "wof:placetype":"venue"
},
  "geometry": {"coordinates":[-122.974675,45.826551],"type":"Point"}
}