{
  "type": "Feature",
  "properties": {
    "iso:country":"US",
    "sg:address":"5420 NW Irwin Ln",
    "sg:city":"Redmond",
    "sg:classifiers":[
        {
            "category":"Building & Trades",
            "subcategory":"Electrical",
            "type":"Services"
        }
    ],
    "sg:phone":"+1 541 548 2914",
    "sg:postcode":"97756",
    "sg:province":"OR",
    "sg:tags":[
        "communication",
        "specialization"
    ],
    "wof:name":"High Desert Telecommunications",
    "wof:placetype":"venue"
},
  "geometry": {"coordinates":[-121.230886,44.331002],"type":"Point"}
}