{
  "type": "Feature",
  "properties": {
    "addr:full":"7875 SW Alden St Portland OR 97223",
    "addr:housenumber":"7875",
    "addr:postcode":"97223",
    "addr:street":"Sw Alden St",
    "iso:country":"US",
    "sg:address":"7875 SW Alden St",
    "sg:city":"Portland",
    "sg:phone":"+1 503 608 8155",
    "sg:postcode":"97223",
    "sg:province":"OR",
    "wof:name":"Dr. Marilyn Walkey, MD- Acupuncture",
    "wof:placetype":"venue"
},
  "geometry": {"coordinates":[-122.757862,45.460331],"type":"Point"}
}