{
  "type": "Feature",
  "properties": {
    "iso:country":"US",
    "sg:address":"712 SE Hawthorne Blvd",
    "sg:city":"Portland",
    "sg:classifiers":[
        {
            "category":"Health Services",
            "subcategory":"Clinic",
            "type":"Services"
        },
        {
            "category":"Organizations",
            "subcategory":"Non-profit Organization",
            "type":"Services"
        }
    ],
    "sg:phone":"+1 503 595 5501",
    "sg:postcode":"97214",
    "sg:province":"OR",
    "sg:tags":[
        "foundations-educational",
        "philanthropic",
        "research",
        "welfare",
        "charity"
    ],
    "wof:name":"Partners For A Hunger-Free Oregon",
    "wof:placetype":"venue"
},
  "geometry": {"coordinates":[-122.65857800000001,45.512241],"type":"Point"}
}