{
  "type": "Feature",
  "properties": {
    "iso:country":"US",
    "sg:address":"622 NW Cedar Ave",
    "sg:city":"Redmond",
    "sg:classifiers":[
        {
            "category":"Shopping",
            "type":"Retail Goods"
        }
    ],
    "sg:phone":"+1 541 548 4131",
    "sg:postcode":"97756",
    "sg:province":"OR",
    "sg:tags":[
        "art",
        "gallery",
        "dealer"
    ],
    "wof:name":"L S Metalworks",
    "wof:placetype":"venue"
},
  "geometry": {"coordinates":[-121.175128,44.278243],"type":"Point"}
}