{
  "type": "Feature",
  "properties": {
    "iso:country":"US",
    "sg:address":"13668 S Mueller Rd",
    "sg:city":"Oregon City",
    "sg:classifiers":[
        {
            "category":"Communications",
            "subcategory":"Film & Video Production",
            "type":"Services"
        }
    ],
    "sg:phone":"+1 503 226 2159",
    "sg:postcode":"97045",
    "sg:province":"OR",
    "sg:tags":[
        "motion"
    ],
    "wof:name":"Botz Productions",
    "wof:placetype":"venue"
},
  "geometry": {"coordinates":[-122.582971,45.278578],"type":"Point"}
}