{
  "type": "Feature",
  "properties": {
    "iso:country":"US",
    "sg:address":"937 NW 12th St",
    "sg:city":"Gresham",
    "sg:classifiers":[
        {
            "category":"Shopping",
            "subcategory":"Clothing, Apparel, & Fashions",
            "type":"Retail Goods"
        }
    ],
    "sg:phone":"+1 503 669 8992",
    "sg:postcode":"97030",
    "sg:province":"OR",
    "sg:tags":[
        "infant",
        "wear"
    ],
    "sg:website":"www.childrensplace.com",
    "wof:name":"Children's Place",
    "wof:placetype":"venue"
},
  "geometry": {"coordinates":[-122.442094,45.505914],"type":"Point"}
}