{
  "type": "Feature",
  "properties": {
    "iso:country":"US",
    "sg:address":"850 SW 5th Ave",
    "sg:city":"Portland",
    "sg:classifiers":[
        {
            "category":"Shopping",
            "subcategory":"Department Store",
            "type":"Retail Goods"
        }
    ],
    "sg:phone":"+1 503 226 3200",
    "sg:postcode":"97204",
    "sg:province":"OR",
    "sg:website":"www.saksfifthavenue.com",
    "wof:name":"Saks Fifth Avenue",
    "wof:placetype":"venue"
},
  "geometry": {"coordinates":[-122.67757,45.517742],"type":"Point"}
}