{
  "type": "Feature",
  "properties": {
    "iso:country":"US",
    "sg:address":"4085 W 11th Ave",
    "sg:city":"Eugene",
    "sg:classifiers":[
        {
            "category":"Wholesale",
            "subcategory":"Electrical",
            "type":"Manufacturing & Wholesale Goods"
        }
    ],
    "sg:phone":"+1 541 686 9676",
    "sg:postcode":"97402",
    "sg:province":"OR",
    "sg:tags":[
        "equipment"
    ],
    "wof:name":"Graybar Electric Company Inc",
    "wof:placetype":"venue"
},
  "geometry": {"coordinates":[-123.162111,44.048117],"type":"Point"}
}