{
  "type": "Feature",
  "properties": {
    "iso:country":"US",
    "sg:address":"4865 State Hwy 234",
    "sg:city":"White City",
    "sg:classifiers":[
        {
            "category":"Retail",
            "subcategory":"Auto Repair",
            "type":"Services"
        }
    ],
    "sg:phone":"+1 541 830 0777",
    "sg:postcode":"97503",
    "sg:province":"OR",
    "sg:tags":[
        "repairing",
        "automobile",
        "general"
    ],
    "wof:name":"Certified Auto Repair Services",
    "wof:placetype":"venue"
},
  "geometry": {"coordinates":[-122.899934,42.504844],"type":"Point"}
}