{
  "type": "Feature",
  "properties": {
    "addr:full":"2730 NW 31st Ave Portland OR 97210",
    "addr:housenumber":"2730",
    "addr:postcode":"97210",
    "addr:street":"Nw 31St Ave",
    "iso:country":"US",
    "sg:address":"2730 NW 31st Ave",
    "sg:city":"Portland",
    "sg:classifiers":[
        {
            "category":"Brewery",
            "type":"Food & Drink"
        }
    ],
    "sg:phone":"+1 503 226 0224",
    "sg:postcode":"97210",
    "sg:province":"OR",
    "wof:name":"Portland Brewing Company",
    "wof:placetype":"venue"
},
  "geometry": {"coordinates":[-122.71302799999999,45.541501],"type":"Point"}
}