{
  "type": "Feature",
  "properties": {
    "iso:country":"US",
    "sg:address":"6641 SE Johnson Creek Blvd",
    "sg:city":"Portland",
    "sg:classifiers":[
        {
            "category":"Structure",
            "subcategory":"Warehouse",
            "type":"Public Place"
        },
        {
            "category":"Industrial Area",
            "type":"Public Place"
        }
    ],
    "sg:phone":"+1 503 777 3813",
    "sg:postcode":"97206",
    "sg:province":"OR",
    "sg:tags":[
        "consultant",
        "warehouses-public-commercial"
    ],
    "wof:name":"Crosswhite Industrial Park",
    "wof:placetype":"venue"
},
  "geometry": {"coordinates":[-122.59430500000001,45.455978],"type":"Point"}
}