{
  "type": "Feature",
  "properties": {
    "addr:full":"859 Sundance St Eugene OR 97405",
    "addr:housenumber":"859",
    "addr:postcode":"97405",
    "addr:street":"Sundance St",
    "iso:country":"US",
    "sg:address":"859 Sundance St",
    "sg:city":"Eugene",
    "sg:classifiers":[
        {
            "category":"Professional",
            "subcategory":"Business Services",
            "type":"Services"
        }
    ],
    "sg:phone":"+1 541 345 8380",
    "sg:postcode":"97405",
    "sg:province":"OR",
    "wof:name":"Nancy Winiarski",
    "wof:placetype":"venue"
},
  "geometry": {"coordinates":[-123.105869,44.012746],"type":"Point"}
}