{
  "type": "Feature",
  "properties": {
    "addr:full":"294 Union Ave Grants Pass OR 97527",
    "addr:housenumber":"294",
    "addr:postcode":"97527",
    "addr:street":"Union Ave",
    "iso:country":"US",
    "sg:address":"294 Union Ave",
    "sg:city":"Grants Pass",
    "sg:classifiers":[
        {
            "category":"Restaurant",
            "type":"Food & Drink"
        }
    ],
    "sg:phone":"+1 541 479 2422",
    "sg:postcode":"97527",
    "sg:province":"OR",
    "sg:tags":[
        "shop",
        "coffee"
    ],
    "wof:name":"Copperbarrel Coffee & Beverage",
    "wof:placetype":"venue"
},
  "geometry": {"coordinates":[-123.339153,42.422479],"type":"Point"}
}