{
  "type": "Feature",
  "properties": {
    "addr:full":"5625 Lost Lake Rd Hood River OR 97031",
    "addr:housenumber":"5625",
    "addr:postcode":"97031",
    "addr:street":"Lost Lake Rd",
    "iso:country":"US",
    "sg:address":"5625 Lost Lake Rd",
    "sg:city":"Hood River",
    "sg:classifiers":[
        {
            "category":"Manufacturing",
            "subcategory":"Retail Goods",
            "type":"Manufacturing & Wholesale Goods"
        }
    ],
    "sg:phone":"+1 541 354 2610",
    "sg:postcode":"97031",
    "sg:province":"OR",
    "sg:tags":[
        "product",
        "mfg"
    ],
    "wof:name":"Rocky Pisto",
    "wof:placetype":"venue"
},
  "geometry": {"coordinates":[-121.66535399999999,45.563175],"type":"Point"}
}