{
  "type": "Feature",
  "properties": {
    "iso:country":"US",
    "sg:address":"61850 27th St",
    "sg:city":"Bend",
    "sg:classifiers":[
        {
            "category":"Autos & Motor Vehicles",
            "subcategory":"Automobile Sales",
            "type":"Retail Goods"
        }
    ],
    "sg:phone":"+1 541 382 6752",
    "sg:postcode":"97702",
    "sg:province":"OR",
    "sg:tags":[
        "used"
    ],
    "wof:name":"Cascade Street Rod Specialties",
    "wof:placetype":"venue"
},
  "geometry": {"coordinates":[-121.263496,44.045954],"type":"Point"}
}