{
  "type": "Feature",
  "properties": {
    "iso:country":"US",
    "sg:address":"1560 Commercial St SE",
    "sg:city":"Salem",
    "sg:classifiers":[
        {
            "category":"Professional",
            "subcategory":"Management & Consulting",
            "type":"Services"
        }
    ],
    "sg:phone":"+1 503 391 9911",
    "sg:postcode":"97302",
    "sg:province":"OR",
    "sg:tags":[
        "business"
    ],
    "wof:name":"Sunrise Medical Consultants",
    "wof:placetype":"venue"
},
  "geometry": {"coordinates":[-123.044321,44.925824],"type":"Point"}
}