{
  "type": "Feature",
  "properties": {
    "addr:full":"6224 13th Ave SE Salem OR 97306",
    "addr:housenumber":"6224",
    "addr:postcode":"97306",
    "addr:street":"13Th Ave Se",
    "iso:country":"US",
    "sg:address":"6224 13th Ave SE",
    "sg:city":"Salem",
    "sg:classifiers":[
        {
            "category":"Freight",
            "type":"Transportation"
        }
    ],
    "sg:phone":"+1 503 363 6964",
    "sg:postcode":"97306",
    "sg:province":"OR",
    "sg:tags":[
        "operator",
        "local",
        "trucking"
    ],
    "wof:name":"Dvs Delivery Svc",
    "wof:placetype":"venue"
},
  "geometry": {"coordinates":[-123.029155,44.864519],"type":"Point"}
}