{
  "type": "Feature",
  "properties": {
    "iso:country":"US",
    "sg:address":"2143 Davcor St SE",
    "sg:city":"Salem",
    "sg:classifiers":[
        {
            "category":"Wholesale",
            "subcategory":"Medical Equipment & Supplies",
            "type":"Manufacturing & Wholesale Goods"
        }
    ],
    "sg:phone":"+1 503 399 1765",
    "sg:postcode":"97302",
    "sg:province":"OR",
    "sg:tags":[
        "dental"
    ],
    "wof:name":"Bio-Medical Dental Corporation",
    "wof:placetype":"venue"
},
  "geometry": {"coordinates":[-123.020652,44.915059],"type":"Point"}
}