{
  "type": "Feature",
  "properties": {
    "addr:full":"44743 McKay Creek Rd Pilot Rock OR 97868",
    "addr:housenumber":"44743",
    "addr:postcode":"97868",
    "addr:street":"Mckay Creek Rd",
    "iso:country":"US",
    "sg:address":"44743 McKay Creek Rd",
    "sg:city":"Pilot Rock",
    "sg:classifiers":[
        {
            "category":"Building & Trades",
            "subcategory":"Construction",
            "type":"Services"
        }
    ],
    "sg:phone":"+1 541 443 6301",
    "sg:postcode":"97868",
    "sg:province":"OR",
    "sg:tags":[
        "general",
        "contractor"
    ],
    "wof:name":"Inskobuilt",
    "wof:placetype":"venue"
},
  "geometry": {"coordinates":[-118.74994100000001,45.502525],"type":"Point"}
}