{
  "type": "Feature",
  "properties": {
    "iso:country":"US",
    "sg:address":"2 N Central Ave",
    "sg:city":"Medford",
    "sg:classifiers":[
        {
            "category":"Shopping",
            "subcategory":"Jewelry",
            "type":"Retail Goods"
        }
    ],
    "sg:phone":"+1 541 857 8898",
    "sg:postcode":"97501",
    "sg:province":"OR",
    "wof:name":"Commonwealth Advertising",
    "wof:placetype":"venue"
},
  "geometry": {"coordinates":[-122.872041,42.326638],"type":"Point"}
}