{
  "type": "Feature",
  "properties": {
    "addr:full":"5767 NE Columbia Blvd Portland OR 97218",
    "addr:housenumber":"5767",
    "addr:postcode":"97218",
    "addr:street":"Ne Columbia Blvd",
    "iso:country":"US",
    "sg:address":"5767 NE Columbia Blvd",
    "sg:city":"Portland",
    "sg:classifiers":[
        {
            "category":"Building & Trades",
            "subcategory":"Construction",
            "type":"Services"
        }
    ],
    "sg:phone":"+1 503 473 8838",
    "sg:postcode":"97218",
    "sg:province":"OR",
    "sg:tags":[
        "interior",
        "design"
    ],
    "sg:website":"www.onstage-online.com",
    "wof:name":"On Stage",
    "wof:placetype":"venue"
},
  "geometry": {"coordinates":[-122.604366,45.569475],"type":"Point"}
}