{
  "type": "Feature",
  "properties": {
    "iso:country":"US",
    "sg:address":"8222 N Highway 97 Ste C",
    "sg:city":"Terrebonne",
    "sg:classifiers":[
        {
            "category":"Professional",
            "subcategory":"Accounting & Tax Preparation",
            "type":"Services"
        }
    ],
    "sg:phone":"+1 541 548 3030",
    "sg:postcode":"97760",
    "sg:province":"OR",
    "sg:tags":[
        "public",
        "accountants-certified"
    ],
    "wof:name":"Bassett Jesen, Gayle",
    "wof:placetype":"venue"
},
  "geometry": {"coordinates":[-121.178788,44.350732],"type":"Point"}
}