{
  "type": "Feature",
  "properties": {
    "iso:country":"US",
    "sg:address":"12520 SW Gem Ln",
    "sg:city":"Beaverton",
    "sg:classifiers":[
        {
            "category":"Manufacturing",
            "subcategory":"Printing",
            "type":"Manufacturing & Wholesale Goods"
        }
    ],
    "sg:phone":"+1 503 526 1350",
    "sg:postcode":"97005",
    "sg:province":"OR",
    "sg:tags":[
        "publisher"
    ],
    "wof:name":"False Idol Studios",
    "wof:placetype":"venue"
},
  "geometry": {"coordinates":[-122.806461,45.499041],"type":"Point"}
}