{
  "type": "Feature",
  "properties": {
    "iso:country":"US",
    "sg:address":"5437 Rosalia Way",
    "sg:city":"Lake Oswego",
    "sg:classifiers":[
        {
            "category":"Real Estate",
            "subcategory":"Developer",
            "type":"Services"
        }
    ],
    "sg:phone":"+1 503 620 4373",
    "sg:postcode":"97035",
    "sg:province":"OR",
    "wof:name":"Ossey Development",
    "wof:placetype":"venue"
},
  "geometry": {"coordinates":[-122.732384,45.430086],"type":"Point"}
}