{
  "type": "Feature",
  "properties": {
    "iso:country":"US",
    "sg:address":"370 Liberty St SE",
    "sg:city":"Salem",
    "sg:classifiers":[
        {
            "category":"Shopping",
            "subcategory":"Jewelry",
            "type":"Retail Goods"
        }
    ],
    "sg:phone":"+1 503 585 8400",
    "sg:postcode":"97301",
    "sg:province":"OR",
    "wof:name":"Northwest Jewelry Designs",
    "wof:placetype":"venue"
},
  "geometry": {"coordinates":[-123.040071,44.937378],"type":"Point"}
}