{
  "type": "Feature",
  "properties": {
    "addr:full":"8457 Darley Rd SE Aumsville OR 97325",
    "addr:housenumber":"8457",
    "addr:postcode":"97325",
    "addr:street":"Darley Rd Se",
    "iso:country":"US",
    "sg:address":"8457 Darley Rd SE",
    "sg:city":"Aumsville",
    "sg:classifiers":[
        {
            "category":"Manufacturing",
            "subcategory":"Lumber",
            "type":"Manufacturing & Wholesale Goods"
        }
    ],
    "sg:phone":"+1 503 749 2288",
    "sg:postcode":"97325",
    "sg:province":"OR",
    "sg:tags":[
        "forestry"
    ],
    "wof:name":"Mq Franco Reforest Station Inc",
    "wof:placetype":"venue"
},
  "geometry": {"coordinates":[-122.890265,44.785449],"type":"Point"}
}