{
  "type": "Feature",
  "properties": {
    "iso:country":"US",
    "sg:address":"1211 SE 82nd Ave",
    "sg:city":"Portland",
    "sg:classifiers":[
        {
            "category":"Shopping",
            "subcategory":"Shoes",
            "type":"Retail Goods"
        }
    ],
    "sg:phone":"+1 503 652 1935",
    "sg:postcode":"97216",
    "sg:province":"OR",
    "sg:tags":[
        "shoe",
        "store"
    ],
    "wof:name":"Payless Shoesource",
    "wof:placetype":"venue"
},
  "geometry": {"coordinates":[-122.57882499999999,45.513576],"type":"Point"}
}