{
  "type": "Feature",
  "properties": {
    "addr:full":"18407 SW Scholls Ferry Road Beaverton OR 97007",
    "addr:housenumber":"18407",
    "addr:postcode":"97007",
    "addr:street":"Sw Scholls Ferry Road",
    "iso:country":"US",
    "sg:address":"18407 SW Scholls Ferry Road",
    "sg:city":"Beaverton",
    "sg:classifiers":[
        {
            "category":"Retail",
            "subcategory":"Event Space",
            "type":"Services"
        },
        {
            "category":"Wholesale",
            "subcategory":"Fruits & Vegetables",
            "type":"Manufacturing & Wholesale Goods"
        }
    ],
    "sg:phone":"+1 503 352 4448",
    "sg:postcode":"97007",
    "sg:province":"OR",
    "sg:tags":[
        "venue",
        "veggie"
    ],
    "sg:website":"www.lolichsfamilyfarm.com",
    "wof:name":"Lolich's Family Farm",
    "wof:placetype":"venue"
},
  "geometry": {"coordinates":[-122.86621,45.427099],"type":"Point"}
}