{
  "type": "Feature",
  "properties": {
    "iso:country":"US",
    "sg:address":"51590 Huntington Rd",
    "sg:city":"La Pine",
    "sg:classifiers":[
        {
            "category":"Organizations",
            "subcategory":"Non-profit Organization",
            "type":"Services"
        }
    ],
    "sg:phone":"+1 541 536 7808",
    "sg:postcode":"97739",
    "sg:province":"OR",
    "sg:tags":[
        "information",
        "alcoholism",
        "treatment"
    ],
    "wof:name":"Rimrock Trails Adolescent",
    "wof:placetype":"venue"
},
  "geometry": {"coordinates":[-121.504683,43.673483],"type":"Point"}
}