{
  "type": "Feature",
  "properties": {
    "addr:full":"405 NW 95th Ave Portland OR 97229",
    "addr:housenumber":"405",
    "addr:postcode":"97229",
    "addr:street":"Nw 95Th Ave",
    "iso:country":"US",
    "sg:address":"405 NW 95th Ave",
    "sg:city":"Portland",
    "sg:classifiers":[
        {
            "category":"Shopping",
            "type":"Retail Goods"
        }
    ],
    "sg:phone":"+1 503 297 6757",
    "sg:postcode":"97229",
    "sg:province":"OR",
    "sg:tags":[
        "product",
        "wood"
    ],
    "wof:name":"Cone International LLC",
    "wof:placetype":"venue"
},
  "geometry": {"coordinates":[-122.775344,45.522626],"type":"Point"}
}