{
  "type": "Feature",
  "properties": {
    "addr:full":"21440 NW Nicholas Ct Hillsboro OR 97124",
    "addr:housenumber":"21440",
    "addr:postcode":"97124",
    "addr:street":"Nw Nicholas Ct",
    "iso:country":"US",
    "sg:address":"21440 NW Nicholas Ct",
    "sg:city":"Hillsboro",
    "sg:classifiers":[
        {
            "category":"Retail",
            "subcategory":"Auto Repair",
            "type":"Services"
        }
    ],
    "sg:phone":"+1 503 617 0904",
    "sg:postcode":"97124",
    "sg:province":"OR",
    "sg:tags":[
        "repairing",
        "automobile",
        "general"
    ],
    "wof:name":"Rock Creek Japanese Auto Repr",
    "wof:placetype":"venue"
},
  "geometry": {"coordinates":[-122.89792,45.531843],"type":"Point"}
}