{
  "type": "Feature",
  "properties": {
    "iso:country":"US",
    "sg:address":"640 SW Bay Blvd",
    "sg:city":"Newport",
    "sg:classifiers":[
        {
            "category":"Shopping",
            "type":"Retail Goods"
        }
    ],
    "sg:phone":"+1 541 265 5430",
    "sg:postcode":"97365",
    "sg:province":"OR",
    "sg:tags":[
        "art",
        "gallery",
        "dealer"
    ],
    "wof:name":"Rickert Gallery",
    "wof:placetype":"venue"
},
  "geometry": {"coordinates":[-124.054847,44.629026],"type":"Point"}
}