{
  "type": "Feature",
  "properties": {
    "addr:full":"10625 SW 35th Ave Portland OR 97219",
    "addr:housenumber":"10625",
    "addr:postcode":"97219",
    "addr:street":"Sw 35Th Ave",
    "iso:country":"US",
    "sg:address":"10625 SW 35th Ave",
    "sg:city":"Portland",
    "sg:classifiers":[
        {
            "category":"Education",
            "subcategory":"School",
            "type":"Public Place"
        }
    ],
    "sg:phone":"+1 503 916 5680",
    "sg:postcode":"97219",
    "sg:province":"OR",
    "sg:tags":[
        "middle",
        "care",
        "day",
        "child"
    ],
    "sg:website":"http://jackson.pps.k12.or.us",
    "wof:name":"Jackson Middle School",
    "wof:placetype":"venue"
},
  "geometry": {"coordinates":[-122.712818,45.448972],"type":"Point"}
}