{
  "type": "Feature",
  "properties": {
    "addr:full":"19887 Case Rd NE Aurora OR 97002",
    "addr:housenumber":"19887",
    "addr:postcode":"97002",
    "addr:street":"Case Rd Ne",
    "iso:country":"US",
    "sg:address":"19887 Case Rd NE",
    "sg:city":"Aurora",
    "sg:classifiers":[
        {
            "category":"Building & Trades",
            "subcategory":"Construction",
            "type":"Services"
        }
    ],
    "sg:phone":"+1 503 789 7430",
    "sg:postcode":"97002",
    "sg:province":"OR",
    "sg:tags":[
        "concrete",
        "contractor"
    ],
    "wof:name":"Burden Concrete",
    "wof:placetype":"venue"
},
  "geometry": {"coordinates":[-122.877892,45.204467],"type":"Point"}
}