{
  "type": "Feature",
  "properties": {
    "addr:full":"1717 Lenora Dr Medford OR 97504",
    "addr:housenumber":"1717",
    "addr:postcode":"97504",
    "addr:street":"Lenora Dr",
    "iso:country":"US",
    "sg:address":"1717 Lenora Dr",
    "sg:city":"Medford",
    "sg:classifiers":[
        {
            "category":"Professional",
            "subcategory":"Management & Consulting",
            "type":"Services"
        }
    ],
    "sg:phone":"+1 541 734 2091",
    "sg:postcode":"97504",
    "sg:province":"OR",
    "sg:tags":[
        "consultant",
        "business"
    ],
    "wof:name":"Logical Solutions",
    "wof:placetype":"venue"
},
  "geometry": {"coordinates":[-122.85156000000001,42.334372],"type":"Point"}
}