{
  "type": "Feature",
  "properties": {
    "addr:full":"1048 Lancaster Dr NE Salem OR 97301",
    "addr:housenumber":"1048",
    "addr:postcode":"97301",
    "addr:street":"Lancaster Dr Ne",
    "iso:country":"US",
    "sg:address":"1048 Lancaster Dr NE",
    "sg:city":"Salem",
    "sg:classifiers":[
        {
            "category":"Food & Beverages",
            "subcategory":"Groceries & Convenience Stores",
            "type":"Retail Goods"
        }
    ],
    "sg:phone":"+1 503 364 9866",
    "sg:postcode":"97301",
    "sg:province":"OR",
    "sg:tags":[
        "grocer"
    ],
    "wof:name":"Great Start Food Stores",
    "wof:placetype":"venue"
},
  "geometry": {"coordinates":[-122.98336,44.943835],"type":"Point"}
}