{
  "type": "Feature",
  "properties": {
    "iso:country":"US",
    "sg:address":"3445 NE 36th Ave",
    "sg:city":"Portland",
    "sg:classifiers":[
        {
            "category":"Professional",
            "subcategory":"Art Services",
            "type":"Services"
        }
    ],
    "sg:phone":"+1 503 274 1267",
    "sg:postcode":"97212",
    "sg:province":"OR",
    "sg:tags":[
        "commercial",
        "design"
    ],
    "wof:name":"Paul Clark Design",
    "wof:placetype":"venue"
},
  "geometry": {"coordinates":[-122.62615599999999,45.547839],"type":"Point"}
}