{
  "type": "Feature",
  "properties": {
    "addr:full":"2853 SE Stark St Portland OR 97214",
    "addr:housenumber":"2853",
    "addr:postcode":"97214",
    "addr:street":"Se Stark St",
    "iso:country":"US",
    "sg:address":"2853 SE Stark St",
    "sg:city":"Portland",
    "sg:classifiers":[
        {
            "category":"Professional",
            "subcategory":"Business Services",
            "type":"Services"
        }
    ],
    "sg:phone":"+1 503 233 9148",
    "sg:postcode":"97214",
    "sg:province":"OR",
    "wof:name":"Stark Images",
    "wof:placetype":"venue"
},
  "geometry": {"coordinates":[-122.636396,45.519387],"type":"Point"}
}