{
  "type": "Feature",
  "properties": {
    "addr:full":"32126 S Wright Rd Molalla OR 97038",
    "addr:housenumber":"32126",
    "addr:postcode":"97038",
    "addr:street":"S Wright Rd",
    "iso:country":"US",
    "sg:address":"32126 S Wright Rd",
    "sg:city":"Molalla",
    "sg:classifiers":[
        {
            "category":"Wholesale",
            "subcategory":"Farm Supplies",
            "type":"Manufacturing & Wholesale Goods"
        }
    ],
    "sg:phone":"+1 503 829 2694",
    "sg:postcode":"97038",
    "sg:province":"OR",
    "sg:tags":[
        "raw",
        "product",
        "material"
    ],
    "wof:name":"Molalla Saddle Club Inc",
    "wof:placetype":"venue"
},
  "geometry": {"coordinates":[-122.52516,45.140402],"type":"Point"}
}