{
  "type": "Feature",
  "properties": {
    "iso:country":"US",
    "sg:address":"1525 NE Weidler St",
    "sg:city":"Portland",
    "sg:classifiers":[
        {
            "category":"Social Services",
            "type":"Services"
        }
    ],
    "sg:phone":"+1 503 525 1151",
    "sg:postcode":"97232",
    "sg:province":"OR",
    "sg:tags":[
        "counselor",
        "marriage",
        "family"
    ],
    "wof:name":"Wendy Talbot",
    "wof:placetype":"venue"
},
  "geometry": {"coordinates":[-122.649645,45.534385],"type":"Point"}
}