{
  "type": "Feature",
  "properties": {
    "iso:country":"US",
    "sg:address":"12741 NE Halsey St",
    "sg:city":"Portland",
    "sg:classifiers":[
        {
            "category":"Insurance",
            "subcategory":"Insurance Agent",
            "type":"Services"
        }
    ],
    "sg:phone":"+1 503 256 5677",
    "sg:postcode":"97230",
    "sg:province":"OR",
    "wof:name":"Ben Phegley Insurance",
    "wof:placetype":"venue"
},
  "geometry": {"coordinates":[-122.531728,45.533618],"type":"Point"}
}