{
  "type": "Feature",
  "properties": {
    "iso:country":"US",
    "sg:address":"811 E 2nd St",
    "sg:city":"The Dalles",
    "sg:classifiers":[
        {
            "category":"Home & Garden",
            "subcategory":"Building Materials",
            "type":"Retail Goods"
        }
    ],
    "sg:phone":"+1 541 296 5414",
    "sg:postcode":"97058",
    "sg:province":"OR",
    "sg:tags":[
        "lumber"
    ],
    "wof:name":"Tum-A-Lum Lumber Co",
    "wof:placetype":"venue"
},
  "geometry": {"coordinates":[-121.175701,45.598419],"type":"Point"}
}