{
  "type": "Feature",
  "properties": {
    "iso:country":"US",
    "sg:address":"701 E Burnside",
    "sg:city":"Portland",
    "sg:classifiers":[
        {
            "category":"Brewery",
            "type":"Food & Drink"
        }
    ],
    "sg:postcode":"97214",
    "sg:province":"OR",
    "sg:website":"www.burnsidebrewingco.com",
    "wof:name":"Burnside Brewing Co",
    "wof:placetype":"venue"
},
  "geometry": {"coordinates":[-122.658494,45.52327],"type":"Point"}
}