{
  "type": "Feature",
  "properties": {
    "iso:country":"US",
    "sg:address":"331 State St",
    "sg:city":"Salem",
    "sg:classifiers":[
        {
            "category":"Professional",
            "subcategory":"Lawyer & Legal Services",
            "type":"Services"
        }
    ],
    "sg:phone":"+1 503 753 3130",
    "sg:postcode":"97301",
    "sg:province":"OR",
    "sg:tags":[
        "attorney"
    ],
    "wof:name":"Dennis Sarriugarte",
    "wof:placetype":"venue"
},
  "geometry": {"coordinates":[-123.039286,44.940163],"type":"Point"}
}