{
  "type": "Feature",
  "properties": {
    "addr:full":"155 Elizabeth Dr Stanfield OR 97875",
    "addr:housenumber":"155",
    "addr:postcode":"97875",
    "addr:street":"Elizabeth Dr",
    "iso:country":"US",
    "sg:address":"155 Elizabeth Dr",
    "sg:city":"Stanfield",
    "sg:classifiers":[
        {
            "category":"Freight",
            "type":"Transportation"
        }
    ],
    "sg:phone":"+1 541 449 3629",
    "sg:postcode":"97875",
    "sg:province":"OR",
    "sg:tags":[
        "operator",
        "local",
        "trucking"
    ],
    "wof:name":"Garcia Trucking",
    "wof:placetype":"venue"
},
  "geometry": {"coordinates":[-119.228103,45.792004],"type":"Point"}
}