{
  "type": "Feature",
  "properties": {
    "iso:country":"US",
    "sg:address":"33 NW Davis Street",
    "sg:city":"Portland",
    "sg:classifiers":[
        {
            "category":"Parking",
            "type":"Transportation"
        }
    ],
    "sg:phone":"+1 503 823 2898",
    "sg:postcode":"97209",
    "sg:province":"OR",
    "wof:name":"Smart Park Garages",
    "wof:placetype":"venue"
},
  "geometry": {"coordinates":[-122.67062900000001,45.524476],"type":"Point"}
}