{
  "type": "Feature",
  "properties": {
    "iso:country":"US",
    "sg:address":"3601 NE 162nd Avenue Apt 47",
    "sg:city":"Portland",
    "sg:classifiers":[
        {
            "category":"Real Estate",
            "subcategory":"Real Estate Operator",
            "type":"Services"
        }
    ],
    "sg:phone":"+1 503 258 1100",
    "sg:postcode":"97230",
    "sg:province":"OR",
    "sg:tags":[
        "apartment"
    ],
    "wof:name":"Zachary Park Apts",
    "wof:placetype":"venue"
},
  "geometry": {"coordinates":[-122.495952,45.548857],"type":"Point"}
}