{
  "type": "Feature",
  "properties": {
    "iso:country":"US",
    "sg:address":"7403 SW Mapleleaf St",
    "sg:city":"Portland",
    "sg:classifiers":[
        {
            "category":"Building & Trades",
            "subcategory":"Landscaping Services",
            "type":"Services"
        }
    ],
    "sg:phone":"+1 503 246 8140",
    "sg:postcode":"97223",
    "sg:province":"OR",
    "sg:tags":[
        "landscape",
        "contractor"
    ],
    "wof:name":"Jeff Carver Landscape",
    "wof:placetype":"venue"
},
  "geometry": {"coordinates":[-122.752941,45.445548],"type":"Point"}
}