{
  "type": "Feature",
  "properties": {
    "iso:country":"US",
    "sg:address":"115 Brooks Ln",
    "sg:city":"Ashland",
    "sg:classifiers":[
        {
            "category":"Communications",
            "subcategory":"Film & Video Production",
            "type":"Services"
        }
    ],
    "sg:phone":"+1 541 482 7704",
    "sg:postcode":"97520",
    "sg:province":"OR",
    "sg:tags":[
        "motion"
    ],
    "wof:name":"Jbj Productions Inc",
    "wof:placetype":"venue"
},
  "geometry": {"coordinates":[-122.673665,42.191513],"type":"Point"}
}