{
  "type": "Feature",
  "properties": {
    "iso:country":"US",
    "sg:address":"40958 S Sawtell Rd",
    "sg:city":"Molalla",
    "sg:classifiers":[
        {
            "category":"Manufacturing",
            "subcategory":"Metals",
            "type":"Manufacturing & Wholesale Goods"
        }
    ],
    "sg:phone":"+1 503 829 6002",
    "sg:postcode":"97038",
    "sg:province":"OR",
    "sg:tags":[
        "rolling",
        "forming"
    ],
    "wof:name":"The Water Boy Idea",
    "wof:placetype":"venue"
},
  "geometry": {"coordinates":[-122.521837,45.015018],"type":"Point"}
}