{
  "type": "Feature",
  "properties": {
    "iso:country":"US",
    "sg:address":"14180 SW Pacific Hwy",
    "sg:city":"Portland",
    "sg:classifiers":[
        {
            "category":"Building & Trades",
            "subcategory":"Locksmith",
            "type":"Services"
        }
    ],
    "sg:phone":"+1 503 452 5357",
    "sg:postcode":"97224",
    "sg:province":"OR",
    "sg:tags":[
        "key"
    ],
    "wof:name":"24 7 Complete Locksmith",
    "wof:placetype":"venue"
},
  "geometry": {"coordinates":[-122.788054,45.417469],"type":"Point"}
}