{
  "type": "Feature",
  "properties": {
    "iso:country":"US",
    "sg:address":"1120 NW Couch Street",
    "sg:city":"Portland",
    "sg:classifiers":[
        {
            "category":"Professional",
            "subcategory":"Lawyer & Legal Services",
            "type":"Services"
        }
    ],
    "sg:phone":"+1 503 727 2259",
    "sg:postcode":"97209",
    "sg:province":"OR",
    "wof:name":"Markley Julia E Atty",
    "wof:placetype":"venue"
},
  "geometry": {"coordinates":[-122.682345,45.523649],"type":"Point"}
}