{
  "type": "Feature",
  "properties": {
    "iso:country":"US",
    "sg:address":"470 S Walnut St",
    "sg:city":"Canby",
    "sg:classifiers":[
        {
            "category":"Building & Trades",
            "subcategory":"Plumbing",
            "type":"Services"
        }
    ],
    "sg:phone":"+1 503 632 6138",
    "sg:postcode":"97013",
    "sg:province":"OR",
    "sg:tags":[
        "septic"
    ],
    "wof:name":"Griff's Septic Svc Inc",
    "wof:placetype":"venue"
},
  "geometry": {"coordinates":[-122.666282,45.26036],"type":"Point"}
}