{
  "type": "Feature",
  "properties": {
    "addr:full":"14585 Wilco Hwy NE Woodburn OR 97071",
    "addr:postcode":"14585;97071",
    "addr:street":"Wilco Hwy Ne",
    "iso:country":"US",
    "sg:address":"14585 Wilco Hwy NE",
    "sg:city":"Woodburn",
    "sg:classifiers":[
        {
            "category":"Manufacturing",
            "subcategory":"Tools & Machinery",
            "type":"Manufacturing & Wholesale Goods"
        }
    ],
    "sg:phone":"+1 503 349 5468",
    "sg:postcode":"97071",
    "sg:province":"OR",
    "sg:tags":[
        "manufacture",
        "marine"
    ],
    "wof:name":"Next Level Designs Inc",
    "wof:placetype":"venue"
},
  "geometry": {"coordinates":[-122.824631,45.127568],"type":"Point"}
}