{
  "type": "Feature",
  "properties": {
    "addr:full":"6815 SE 114th Ave Portland OR 97266",
    "addr:housenumber":"6815",
    "addr:postcode":"97266",
    "addr:street":"Se 114Th Ave",
    "iso:country":"US",
    "sg:address":"6815 SE 114th Ave",
    "sg:city":"Portland",
    "sg:classifiers":[
        {
            "category":"Communications",
            "subcategory":"Film & Video Production",
            "type":"Services"
        }
    ],
    "sg:phone":"+1 503 760 0973",
    "sg:postcode":"97266",
    "sg:province":"OR",
    "sg:tags":[
        "motion"
    ],
    "wof:name":"Davis Productions",
    "wof:placetype":"venue"
},
  "geometry": {"coordinates":[-122.545346,45.473133],"type":"Point"}
}