{
  "type": "Feature",
  "properties": {
    "addr:full":"180 E Virginia St Stayton OR 97383",
    "addr:housenumber":"180",
    "addr:postcode":"97383",
    "addr:street":"E Virginia St",
    "iso:country":"US",
    "sg:address":"180 E Virginia St",
    "sg:city":"Stayton",
    "sg:classifiers":[
        {
            "category":"Building & Trades",
            "subcategory":"Construction",
            "type":"Services"
        }
    ],
    "sg:phone":"+1 503 769 1807",
    "sg:postcode":"97383",
    "sg:province":"OR",
    "sg:tags":[
        "residential",
        "remodeling",
        "painting",
        "repair"
    ],
    "wof:name":"Kenneth D Lindsey",
    "wof:placetype":"venue"
},
  "geometry": {"coordinates":[-122.79349000000001,44.799984],"type":"Point"}
}