{
  "type": "Feature",
  "properties": {
    "iso:country":"US",
    "sg:address":"16444 SE Sunnyside Rd",
    "sg:city":"Clackamas",
    "sg:classifiers":[
        {
            "category":"Sports & Exercise",
            "subcategory":"Gym",
            "type":"Entertainment"
        }
    ],
    "sg:phone":"+1 503 658 1778",
    "sg:postcode":"97015",
    "sg:province":"OR",
    "sg:website":"www.curves.com",
    "wof:name":"Curves",
    "wof:placetype":"venue"
},
  "geometry": {"coordinates":[-122.49453699999999,45.427021],"type":"Point"}
}