{
  "type": "Feature",
  "properties": {
    "addr:full":"9735 SW Sunshine Ct Beaverton OR 97005",
    "addr:housenumber":"9735",
    "addr:postcode":"97005",
    "addr:street":"Sw Sunshine Ct",
    "iso:country":"US",
    "sg:address":"9735 SW Sunshine Ct",
    "sg:city":"Beaverton",
    "sg:classifiers":[
        {
            "category":"Building & Trades",
            "subcategory":"Construction",
            "type":"Services"
        }
    ],
    "sg:phone":"+1 503 643 6700",
    "sg:postcode":"97005",
    "sg:province":"OR",
    "sg:tags":[
        "general",
        "contractor"
    ],
    "wof:name":"Mc Carthy Construction",
    "wof:placetype":"venue"
},
  "geometry": {"coordinates":[-122.77760000000001,45.476023],"type":"Point"}
}