{
  "type": "Feature",
  "properties": {
    "iso:country":"US",
    "sg:address":"220 Heather Dr",
    "sg:city":"Stanfield",
    "sg:classifiers":[
        {
            "category":"Local Transit",
            "type":"Transportation"
        }
    ],
    "sg:phone":"+1 541 449 3289",
    "sg:postcode":"97875",
    "sg:province":"OR",
    "sg:tags":[
        "limousine"
    ],
    "wof:name":"Luxury In Motion",
    "wof:placetype":"venue"
},
  "geometry": {"coordinates":[-119.224289,45.789252],"type":"Point"}
}