{
  "type": "Feature",
  "properties": {
    "iso:country":"US",
    "sg:address":"2222 SE Foxglove Ct",
    "sg:city":"Hillsboro",
    "sg:classifiers":[
        {
            "category":"Utilities",
            "subcategory":"Telephone",
            "type":"Services"
        }
    ],
    "sg:phone":"+1 503 640 6700",
    "sg:postcode":"97123",
    "sg:province":"OR",
    "sg:tags":[
        "communications"
    ],
    "wof:name":"Teleplan",
    "wof:placetype":"venue"
},
  "geometry": {"coordinates":[-122.959669,45.500387],"type":"Point"}
}