{
  "type": "Feature",
  "properties": {
    "iso:country":"US",
    "sg:address":"944 SW 14th St",
    "sg:city":"Redmond",
    "sg:classifiers":[
        {
            "category":"Retail",
            "subcategory":"Repair Shop",
            "type":"Services"
        }
    ],
    "sg:phone":"+1 541 548 3492",
    "sg:postcode":"97756",
    "sg:province":"OR",
    "wof:name":"Walts Horseshoeing",
    "wof:placetype":"venue"
},
  "geometry": {"coordinates":[-121.182925,44.268153],"type":"Point"}
}