{
  "type": "Feature",
  "properties": {
    "addr:full":"885 22nd Ave SW Albany OR 97321",
    "addr:housenumber":"885",
    "addr:postcode":"97321",
    "addr:street":"22Nd Ave Sw",
    "iso:country":"US",
    "sg:address":"885 22nd Ave SW",
    "sg:city":"Albany",
    "sg:classifiers":[
        {
            "category":"Home & Garden",
            "subcategory":"Home Furnishings",
            "type":"Retail Goods"
        }
    ],
    "sg:phone":"+1 541 928 8488",
    "sg:postcode":"97321",
    "sg:province":"OR",
    "sg:tags":[
        "lamp",
        "shades"
    ],
    "wof:name":"J & J Electric Inc",
    "wof:placetype":"venue"
},
  "geometry": {"coordinates":[-123.113274,44.62056],"type":"Point"}
}