{
  "type": "Feature",
  "properties": {
    "addr:full":"2009 Olympic St Springfield OR 97477",
    "addr:housenumber":"2009",
    "addr:postcode":"97477",
    "addr:street":"Olympic St",
    "iso:country":"US",
    "sg:address":"2009 Olympic St",
    "sg:city":"Springfield",
    "sg:classifiers":[
        {
            "category":"Government",
            "subcategory":"Office",
            "type":"Public Place"
        }
    ],
    "sg:phone":"+1 541 726 3761",
    "sg:postcode":"97477",
    "sg:province":"OR",
    "wof:name":"Springfield Traffic Signals",
    "wof:placetype":"venue"
},
  "geometry": {"coordinates":[-122.996008,44.059669],"type":"Point"}
}