{
  "type": "Feature",
  "properties": {
    "iso:country":"US",
    "sg:address":"921 Country Club Rd",
    "sg:city":"Eugene",
    "sg:classifiers":[
        {
            "category":"Social Services",
            "type":"Services"
        }
    ],
    "sg:phone":"+1 541 686 6000",
    "sg:postcode":"97401",
    "sg:province":"OR",
    "sg:tags":[
        "counselor",
        "marriage",
        "family"
    ],
    "wof:name":"Christians Addressing Family",
    "wof:placetype":"venue"
},
  "geometry": {"coordinates":[-123.098719,44.065452],"type":"Point"}
}