{
  "type": "Feature",
  "properties": {
    "iso:country":"US",
    "sg:address":"539 NW Buddy Ln",
    "sg:city":"Grants Pass",
    "sg:classifiers":[
        {
            "category":"Social Services",
            "subcategory":"Child Care",
            "type":"Services"
        }
    ],
    "sg:phone":"+1 541 479 0281",
    "sg:postcode":"97526",
    "sg:province":"OR",
    "sg:tags":[
        "day"
    ],
    "wof:name":"Lynn Morgan",
    "wof:placetype":"venue"
},
  "geometry": {"coordinates":[-123.328214,42.462682],"type":"Point"}
}