{
  "type": "Feature",
  "properties": {
    "iso:country":"US",
    "sg:address":"96568 Hwy 99 W",
    "sg:city":"Junction City",
    "sg:classifiers":[
        {
            "category":"Personal",
            "subcategory":"Shoe Repair & Shine",
            "type":"Services"
        }
    ],
    "sg:phone":"+1 541 998 6723",
    "sg:postcode":"97448",
    "sg:province":"OR",
    "sg:tags":[
        "parlor"
    ],
    "wof:name":"Junction City Shoe Repair",
    "wof:placetype":"venue"
},
  "geometry": {"coordinates":[-123.244055,44.280596],"type":"Point"}
}