{
  "type": "Feature",
  "properties": {
    "iso:country":"US",
    "sg:address":"93560 Hwy 99 S",
    "sg:city":"Junction City",
    "sg:classifiers":[
        {
            "category":"Home & Garden",
            "subcategory":"Home Furnishings",
            "type":"Retail Goods"
        }
    ],
    "sg:phone":"+1 541 998 2272",
    "sg:postcode":"97448",
    "sg:province":"OR",
    "sg:tags":[
        "curtain",
        "made",
        "drapery"
    ],
    "wof:name":"Commercial Drapery & Blind",
    "wof:placetype":"venue"
},
  "geometry": {"coordinates":[-123.203526,44.202951],"type":"Point"}
}