{
  "type": "Feature",
  "properties": {
    "iso:country":"US",
    "sg:address":"123 E Pine St",
    "sg:city":"Central Point",
    "sg:classifiers":[
        {
            "category":"Professional",
            "type":"Services"
        }
    ],
    "sg:phone":"+1 541 664 1981",
    "sg:postcode":"97502",
    "sg:province":"OR",
    "wof:name":"Lulus Chic",
    "wof:placetype":"venue"
},
  "geometry": {"coordinates":[-122.91638399999999,42.374685],"type":"Point"}
}