{
  "type": "Feature",
  "properties": {
    "iso:country":"US",
    "sg:address":"2095 Centennial Blvd",
    "sg:city":"Eugene",
    "sg:classifiers":[
        {
            "category":"Autos & Motor Vehicles",
            "subcategory":"Automobile Sales",
            "type":"Retail Goods"
        }
    ],
    "sg:phone":"+1 541 485 5880",
    "sg:postcode":"97401",
    "sg:province":"OR",
    "sg:tags":[
        "new",
        "car"
    ],
    "wof:name":"Saturn",
    "wof:placetype":"venue"
},
  "geometry": {"coordinates":[-123.081237,44.059659],"type":"Point"}
}