{
  "type": "Feature",
  "properties": {
    "iso:country":"US",
    "sg:address":"15015 SE 362nd Ave",
    "sg:city":"Boring",
    "sg:classifiers":[
        {
            "category":"Wholesale",
            "subcategory":"Plants",
            "type":"Manufacturing & Wholesale Goods"
        }
    ],
    "sg:phone":"+1 503 668 6842",
    "sg:postcode":"97009",
    "sg:province":"OR",
    "sg:tags":[
        "nursery"
    ],
    "wof:name":"Boyko Nursery",
    "wof:placetype":"venue"
},
  "geometry": {"coordinates":[-122.290998,45.414463],"type":"Point"}
}