{
  "type": "Feature",
  "properties": {
    "iso:country":"US",
    "sg:address":"915 SE 12th Avenue",
    "sg:city":"Portland",
    "sg:classifiers":[
        {
            "category":"Autos & Motor Vehicles",
            "subcategory":"Auto Supplies",
            "type":"Retail Goods"
        },
        {
            "category":"Retail",
            "subcategory":"Auto Repair",
            "type":"Services"
        }
    ],
    "sg:phone":"+1 503 963 8468",
    "sg:postcode":"97214",
    "sg:province":"OR",
    "sg:tags":[
        "glass",
        "detailing"
    ],
    "wof:name":"Tommy's Window Tinting",
    "wof:placetype":"venue"
},
  "geometry": {"coordinates":[-122.653497,45.516333],"type":"Point"}
}