{
  "type": "Feature",
  "properties": {
    "iso:country":"US",
    "sg:address":"5050 NE Hoyt Street Suite 514",
    "sg:city":"Portland",
    "sg:classifiers":[
        {
            "category":"Health Services",
            "subcategory":"Doctor",
            "type":"Services"
        }
    ],
    "sg:phone":"+1 503 215 2399",
    "sg:postcode":"97213",
    "sg:province":"OR",
    "sg:website":"www.oregonclinic.com",
    "wof:name":"Young Don A MD",
    "wof:placetype":"venue"
},
  "geometry": {"coordinates":[-122.610775,45.527203],"type":"Point"}
}