{
  "type": "Feature",
  "properties": {
    "iso:country":"US",
    "sg:address":"2466 Ave A",
    "sg:city":"White City",
    "sg:classifiers":[
        {
            "category":"Professional",
            "type":"Services"
        }
    ],
    "sg:phone":"+1 541 826 5169",
    "sg:postcode":"97503",
    "sg:province":"OR",
    "sg:tags":[
        "establishment"
    ],
    "wof:name":"Jaime Calvillo",
    "wof:placetype":"venue"
},
  "geometry": {"coordinates":[-122.848975,42.425456],"type":"Point"}
}