{
  "type": "Feature",
  "properties": {
    "addr:full":"2355 Crescent Ave Eugene OR 97408",
    "addr:housenumber":"2355",
    "addr:postcode":"97408",
    "addr:street":"Crescent Ave",
    "iso:country":"US",
    "sg:address":"2355 Crescent Ave",
    "sg:city":"Eugene",
    "sg:classifiers":[
        {
            "category":"Retail",
            "subcategory":"Repair Shop",
            "type":"Services"
        }
    ],
    "sg:phone":"+1 541 683 0611",
    "sg:postcode":"97408",
    "sg:province":"OR",
    "sg:tags":[
        "lock",
        "locksmith"
    ],
    "wof:name":"J'n S Locksmithing",
    "wof:placetype":"venue"
},
  "geometry": {"coordinates":[-123.075124,44.092993],"type":"Point"}
}