{
  "type": "Feature",
  "properties": {
    "iso:country":"US",
    "sg:address":"6357 SW Lombard Ave",
    "sg:city":"Beaverton",
    "sg:classifiers":[
        {
            "category":"Restaurant",
            "type":"Food & Drink"
        }
    ],
    "sg:phone":"+1 503 643 7207",
    "sg:postcode":"97008",
    "sg:province":"OR",
    "sg:tags":[
        "eating"
    ],
    "wof:name":"Dinos Catering",
    "wof:placetype":"venue"
},
  "geometry": {"coordinates":[-122.80037299999999,45.47375],"type":"Point"}
}