{
  "type": "Feature",
  "properties": {
    "iso:country":"US",
    "sg:address":"745 S E St",
    "sg:city":"Lakeview",
    "sg:classifiers":[
        {
            "category":"Building & Trades",
            "subcategory":"Construction",
            "type":"Services"
        }
    ],
    "sg:phone":"+1 541 947 5922",
    "sg:postcode":"97630",
    "sg:province":"OR",
    "sg:tags":[
        "contractor"
    ],
    "wof:name":"Cates Construction",
    "wof:placetype":"venue"
},
  "geometry": {"coordinates":[-120.344488,42.179292],"type":"Point"}
}