{
  "type": "Feature",
  "properties": {
    "iso:country":"US",
    "sg:address":"3924 NW Walnut Pl",
    "sg:city":"Corvallis",
    "sg:classifiers":[
        {
            "category":"Professional",
            "subcategory":"Engineering",
            "type":"Services"
        },
        {
            "category":"Manufacturing",
            "subcategory":"Tools & Machinery",
            "type":"Manufacturing & Wholesale Goods"
        }
    ],
    "sg:phone":"+1 541 754 2819",
    "sg:postcode":"97330",
    "sg:province":"OR",
    "sg:tags":[
        "farm",
        "consulting",
        "mfg",
        "business",
        "engineer"
    ],
    "wof:name":"Trimmer Engineering Inc",
    "wof:placetype":"venue"
},
  "geometry": {"coordinates":[-123.297809,44.593021],"type":"Point"}
}