{
  "type": "Feature",
  "properties": {
    "iso:country":"US",
    "sg:address":"52290 SE 1st St",
    "sg:city":"Scappoose",
    "sg:classifiers":[
        {
            "category":"Shopping",
            "subcategory":"Computers & Home Electronics",
            "type":"Retail Goods"
        }
    ],
    "sg:phone":"+1 503 740 7743",
    "sg:postcode":"97056",
    "sg:province":"OR",
    "sg:tags":[
        "consumer",
        "sales"
    ],
    "wof:name":"Compcoach",
    "wof:placetype":"venue"
},
  "geometry": {"coordinates":[-122.877075,45.753809],"type":"Point"}
}