{
  "type": "Feature",
  "properties": {
    "iso:country":"US",
    "sg:address":"865 Grant St",
    "sg:city":"Eugene",
    "sg:classifiers":[
        {
            "category":"Manufacturing",
            "subcategory":"Food",
            "type":"Manufacturing & Wholesale Goods"
        }
    ],
    "sg:phone":"+1 541 484 9123",
    "sg:postcode":"97402",
    "sg:province":"OR",
    "sg:tags":[
        "frozen",
        "fruit"
    ],
    "wof:name":"Cascade Dispensing Systems",
    "wof:placetype":"venue"
},
  "geometry": {"coordinates":[-123.120053,44.050586],"type":"Point"}
}