{
  "type": "Feature",
  "properties": {
    "addr:full":"204 W Oregon Ave Creswell OR 97426",
    "addr:housenumber":"204",
    "addr:postcode":"97426",
    "addr:street":"W Oregon Ave",
    "iso:country":"US",
    "sg:address":"204 W Oregon Ave",
    "sg:city":"Creswell",
    "sg:classifiers":[
        {
            "category":"Restaurant",
            "type":"Food & Drink"
        },
        {
            "category":"Ice Cream",
            "type":"Food & Drink"
        }
    ],
    "sg:phone":"+1 541 895 4100",
    "sg:postcode":"97426",
    "sg:province":"OR",
    "sg:tags":[
        "frozen",
        "dessert"
    ],
    "wof:name":"Old Time Scoop",
    "wof:placetype":"venue"
},
  "geometry": {"coordinates":[-123.021084,43.917851],"type":"Point"}
}