{
  "type": "Feature",
  "properties": {
    "iso:country":"US",
    "sg:address":"1500 NE Irving St",
    "sg:city":"Portland",
    "sg:classifiers":[
        {
            "category":"Professional",
            "subcategory":"Lawyer & Legal Services",
            "type":"Services"
        }
    ],
    "sg:phone":"+1 503 229 0400",
    "sg:postcode":"97232",
    "sg:province":"OR",
    "wof:name":"Smith Gameson Diamond Olney",
    "wof:placetype":"venue"
},
  "geometry": {"coordinates":[-122.649503,45.527924],"type":"Point"}
}