{
  "type": "Feature",
  "properties": {
    "iso:country":"US",
    "sg:address":"807 NW Quarry Rd",
    "sg:city":"Albany",
    "sg:classifiers":[
        {
            "category":"Retail",
            "subcategory":"Laundry & Dry Cleaning",
            "type":"Services"
        }
    ],
    "sg:phone":"+1 541 812 1434",
    "sg:postcode":"97321",
    "sg:province":"OR",
    "wof:name":"Crystal Clean Carpet Care",
    "wof:placetype":"venue"
},
  "geometry": {"coordinates":[-123.11500700000001,44.654422],"type":"Point"}
}