{
  "type": "Feature",
  "properties": {
    "iso:country":"US",
    "sg:address":"1010 8th St",
    "sg:city":"Springfield",
    "sg:classifiers":[
        {
            "category":"Shopping",
            "type":"Retail Goods"
        },
        {
            "category":"Professional",
            "subcategory":"Art Services",
            "type":"Services"
        }
    ],
    "sg:phone":"+1 541 744 0909",
    "sg:postcode":"97477",
    "sg:province":"OR",
    "sg:tags":[
        "commercial",
        "design",
        "gallery",
        "dealer"
    ],
    "wof:name":"Dena Brown Creative Services",
    "wof:placetype":"venue"
},
  "geometry": {"coordinates":[-123.01533499999999,44.054767],"type":"Point"}
}