{
  "type": "Feature",
  "properties": {
    "addr:full":"1359 N Coast Hwy Newport OR 97365",
    "addr:housenumber":"1359",
    "addr:postcode":"97365",
    "addr:street":"N Coast Hwy",
    "iso:country":"US",
    "sg:address":"1359 N Coast Hwy",
    "sg:city":"Newport",
    "sg:classifiers":[
        {
            "category":"Autos & Motor Vehicles",
            "subcategory":"Automobile Sales",
            "type":"Retail Goods"
        }
    ],
    "sg:phone":"+1 541 265 3309",
    "sg:postcode":"97365",
    "sg:province":"OR",
    "sg:tags":[
        "car",
        "dealer"
    ],
    "wof:name":"Central Coast Auto Inc",
    "wof:placetype":"venue"
},
  "geometry": {"coordinates":[-124.053116,44.646913],"type":"Point"}
}