{
  "type": "Feature",
  "properties": {
    "addr:full":"325 Holly St Junction City OR 97448",
    "addr:housenumber":"325",
    "addr:postcode":"97448",
    "addr:street":"Holly St",
    "iso:country":"US",
    "sg:address":"325 Holly St",
    "sg:city":"Junction City",
    "sg:classifiers":[
        {
            "category":"Professional",
            "subcategory":"Business Services",
            "type":"Services"
        }
    ],
    "sg:phone":"+1 541 607 4000",
    "sg:postcode":"97448",
    "sg:province":"OR",
    "sg:tags":[
        "paging",
        "answering"
    ],
    "wof:name":"MTM Communications",
    "wof:placetype":"venue"
},
  "geometry": {"coordinates":[-123.203594,44.217239],"type":"Point"}
}