{
  "type": "Feature",
  "properties": {
    "addr:full":"4850 SW Scholls Ferry Rd Portland OR 97225",
    "addr:housenumber":"4850",
    "addr:postcode":"97225",
    "addr:street":"Sw Scholls Ferry Rd",
    "iso:country":"US",
    "sg:address":"4850 SW Scholls Ferry Rd",
    "sg:city":"Portland",
    "sg:classifiers":[
        {
            "category":"Professional",
            "subcategory":"Business Services",
            "type":"Services"
        }
    ],
    "sg:phone":"+1 503 297 3156",
    "sg:postcode":"97225",
    "sg:province":"OR",
    "sg:tags":[
        "mail",
        "voice",
        "messaging"
    ],
    "wof:name":"Page One",
    "wof:placetype":"venue"
},
  "geometry": {"coordinates":[-122.754946,45.483377],"type":"Point"}
}