{
  "type": "Feature",
  "properties": {
    "addr:full":"85132 Larson Rd Eugene OR 97405",
    "addr:postcode":"85132;97405",
    "addr:street":"Larson Rd",
    "iso:country":"US",
    "sg:address":"85132 Larson Rd",
    "sg:city":"Eugene",
    "sg:classifiers":[
        {
            "category":"Real Estate",
            "subcategory":"Real Estate Agent",
            "type":"Services"
        }
    ],
    "sg:phone":"+1 541 334 6484",
    "sg:postcode":"97405",
    "sg:province":"OR",
    "wof:name":"Brock & Assoc Real Estate",
    "wof:placetype":"venue"
},
  "geometry": {"coordinates":[-123.18396799999999,43.97113],"type":"Point"}
}