{
  "type": "Feature",
  "properties": {
    "addr:full":"2323 NE 181st Ave Portland OR 97230",
    "addr:housenumber":"2323",
    "addr:postcode":"97230",
    "addr:street":"Ne 181St Ave",
    "iso:country":"US",
    "sg:address":"2323 NE 181st Ave",
    "sg:city":"Portland",
    "sg:classifiers":[
        {
            "category":"Travel",
            "subcategory":"Hotels & Motels",
            "type":"Entertainment"
        }
    ],
    "sg:phone":"+1 503 492 4000",
    "sg:postcode":"97230",
    "sg:province":"OR",
    "wof:name":"Hawthorn Inn & Suites",
    "wof:placetype":"venue"
},
  "geometry": {"coordinates":[-122.476997,45.540401],"type":"Point"}
}