{
  "type": "Feature",
  "properties": {
    "addr:full":"1383 Cal Young Rd Eugene OR 97401",
    "addr:housenumber":"1383",
    "addr:postcode":"97401",
    "addr:street":"Cal Young Rd",
    "iso:country":"US",
    "sg:address":"1383 Cal Young Rd",
    "sg:city":"Eugene",
    "sg:classifiers":[
        {
            "category":"Professional",
            "subcategory":"Accounting & Tax Preparation",
            "type":"Services"
        }
    ],
    "sg:phone":"+1 541 344 4729",
    "sg:postcode":"97401",
    "sg:province":"OR",
    "sg:tags":[
        "return",
        "filing"
    ],
    "wof:name":"Jeff Taylor Tax Svc",
    "wof:placetype":"venue"
},
  "geometry": {"coordinates":[-123.09332000000001,44.077722],"type":"Point"}
}