{
  "type": "Feature",
  "properties": {
    "iso:country":"US",
    "sg:address":"406 NE 3rd St",
    "sg:city":"Mcminnville",
    "sg:classifiers":[
        {
            "category":"Shopping",
            "subcategory":"Gifts & Souvenirs",
            "type":"Retail Goods"
        }
    ],
    "sg:phone":"+1 503 434 5152",
    "sg:postcode":"97128",
    "sg:province":"OR",
    "sg:tags":[
        "shop"
    ],
    "wof:name":"Granderson's",
    "wof:placetype":"venue"
},
  "geometry": {"coordinates":[-123.19558600000001,45.209943],"type":"Point"}
}