{
  "type": "Feature",
  "properties": {
    "iso:country":"US",
    "sg:address":"31740 Fox Hollow Rd",
    "sg:city":"Eugene",
    "sg:classifiers":[
        {
            "category":"Professional",
            "subcategory":"Research",
            "type":"Services"
        }
    ],
    "sg:phone":"+1 541 744 7072",
    "sg:postcode":"97405",
    "sg:province":"OR",
    "sg:tags":[
        "environmental",
        "ecological"
    ],
    "wof:name":"Center For Watershed & Health",
    "wof:placetype":"venue"
},
  "geometry": {"coordinates":[-123.094928,43.974184],"type":"Point"}
}