{
  "type": "Feature",
  "properties": {
    "addr:full":"5814 N Bowdoin St Portland OR 97203",
    "addr:housenumber":"5814",
    "addr:postcode":"97203",
    "addr:street":"N Bowdoin St",
    "iso:country":"US",
    "sg:address":"5814 N Bowdoin St",
    "sg:city":"Portland",
    "sg:classifiers":[
        {
            "category":"Manufacturing",
            "subcategory":"Textiles",
            "type":"Manufacturing & Wholesale Goods"
        }
    ],
    "sg:phone":"+1 503 289 2541",
    "sg:postcode":"97203",
    "sg:province":"OR",
    "sg:tags":[
        "mill",
        "fabric",
        "cotton"
    ],
    "wof:name":"Sew Blessed",
    "wof:placetype":"venue"
},
  "geometry": {"coordinates":[-122.728342,45.582933],"type":"Point"}
}