{
  "type": "Feature",
  "properties": {
    "iso:country":"US",
    "sg:address":"348 US Hwy 101",
    "sg:city":"Yachats",
    "sg:classifiers":[
        {
            "category":"Real Estate",
            "subcategory":"Real Estate Agent",
            "type":"Services"
        }
    ],
    "sg:phone":"+1 541 547 5000",
    "sg:postcode":"97498",
    "sg:province":"OR",
    "wof:name":"All Coast Properties",
    "wof:placetype":"venue"
},
  "geometry": {"coordinates":[-124.099347,44.308697],"type":"Point"}
}