{
  "type": "Feature",
  "properties": {
    "iso:country":"US",
    "sg:address":"7471 SW Bridgeport Rd, Building G",
    "sg:city":"Portland",
    "sg:classifiers":[
        {
            "category":"Coffee & Tea",
            "type":"Food & Drink"
        }
    ],
    "sg:phone":"+1 503 684 2726",
    "sg:postcode":"97224",
    "sg:province":"OR",
    "sg:website":"www.peets.com",
    "wof:name":"Peet's Coffee and Tea",
    "wof:placetype":"venue"
},
  "geometry": {"coordinates":[-122.75271100000001,45.394338],"type":"Point"}
}