{
  "type": "Feature",
  "properties": {
    "addr:full":"34500 State Hwy 58 Eugene OR 97405",
    "addr:housenumber":"34500",
    "addr:postcode":"97405",
    "addr:street":"State Hwy 58",
    "iso:country":"US",
    "sg:address":"34500 State Hwy 58",
    "sg:city":"Eugene",
    "sg:classifiers":[
        {
            "category":"Food & Beverages",
            "subcategory":"Groceries & Convenience Stores",
            "type":"Retail Goods"
        }
    ],
    "sg:phone":"+1 541 741 6098",
    "sg:postcode":"97405",
    "sg:province":"OR",
    "sg:tags":[
        "grocer"
    ],
    "wof:name":"Highway 58 Market",
    "wof:placetype":"venue"
},
  "geometry": {"coordinates":[-122.99721,43.993375],"type":"Point"}
}