{
  "type": "Feature",
  "properties": {
    "iso:country":"US",
    "sg:address":"2515 E Powell Blvd",
    "sg:city":"Gresham",
    "sg:classifiers":[
        {
            "category":"Autos & Motor Vehicles",
            "subcategory":"Fuel & Gas Station",
            "type":"Retail Goods"
        }
    ],
    "sg:phone":"+1 503 661 2968",
    "sg:postcode":"97080",
    "sg:province":"OR",
    "sg:tags":[
        "station",
        "gasoline"
    ],
    "wof:name":"Fadis Quick Mart",
    "wof:placetype":"venue"
},
  "geometry": {"coordinates":[-122.40560499999999,45.493783],"type":"Point"}
}