{
  "type": "Feature",
  "properties": {
    "iso:country":"US",
    "sg:address":"1700 SE Tempest Dr",
    "sg:city":"Bend",
    "sg:classifiers":[
        {
            "category":"Real Estate",
            "subcategory":"Real Estate Operator",
            "type":"Services"
        }
    ],
    "sg:phone":"+1 541 383 2556",
    "sg:postcode":"97702",
    "sg:province":"OR",
    "sg:tags":[
        "building",
        "apartment"
    ],
    "wof:name":"Ariel Glen Apts",
    "wof:placetype":"venue"
},
  "geometry": {"coordinates":[-121.27828599999999,44.04602],"type":"Point"}
}