{
  "type": "Feature",
  "properties": {
    "iso:country":"US",
    "sg:address":"283 Kensington Ave",
    "sg:city":"Astoria",
    "sg:classifiers":[
        {
            "category":"Real Estate",
            "subcategory":"Real Estate Agent",
            "type":"Services"
        }
    ],
    "sg:phone":"+1 503 325 5130",
    "sg:postcode":"97103",
    "sg:province":"OR",
    "sg:tags":[
        "inspection"
    ],
    "wof:name":"Professional Home Inspection",
    "wof:placetype":"venue"
},
  "geometry": {"coordinates":[-123.840338,46.183477],"type":"Point"}
}