{
  "type": "Feature",
  "properties": {
    "addr:full":"31348 State Hwy 170 Canby OR 97013",
    "addr:housenumber":"31348",
    "addr:postcode":"97013",
    "addr:street":"State Hwy 170",
    "iso:country":"US",
    "sg:address":"31348 State Hwy 170",
    "sg:city":"Canby",
    "sg:classifiers":[
        {
            "category":"Wholesale",
            "subcategory":"Poultry",
            "type":"Manufacturing & Wholesale Goods"
        }
    ],
    "sg:phone":"+1 503 651 2152",
    "sg:postcode":"97013",
    "sg:province":"OR",
    "sg:tags":[
        "eggs"
    ],
    "sg:website":"www.willamette-egg.com",
    "wof:name":"Willamette Egg Farms LLC",
    "wof:placetype":"venue"
},
  "geometry": {"coordinates":[-122.681331,45.153667],"type":"Point"}
}