{
  "type": "Feature",
  "properties": {
    "iso:country":"US",
    "sg:address":"401 Freeman Rd",
    "sg:city":"Central Point",
    "sg:classifiers":[
        {
            "category":"Building & Trades",
            "subcategory":"Construction",
            "type":"Services"
        }
    ],
    "sg:phone":"+1 541 664 6839",
    "sg:postcode":"97502",
    "sg:province":"OR",
    "sg:tags":[
        "contractor"
    ],
    "wof:name":"Chad Grimm Tile Setter",
    "wof:placetype":"venue"
},
  "geometry": {"coordinates":[-122.907256,42.373008],"type":"Point"}
}