{
  "type": "Feature",
  "properties": {
    "addr:full":"3420 NW Elmwood Dr Corvallis OR 97330",
    "addr:housenumber":"3420",
    "addr:postcode":"97330",
    "addr:street":"Nw Elmwood Dr",
    "iso:country":"US",
    "sg:address":"3420 NW Elmwood Dr",
    "sg:city":"Corvallis",
    "sg:classifiers":[
        {
            "category":"Organizations",
            "subcategory":"Membership Organization",
            "type":"Services"
        }
    ],
    "sg:phone":"+1 541 757 0040",
    "sg:postcode":"97330",
    "sg:province":"OR",
    "wof:name":"National Space Society",
    "wof:placetype":"venue"
},
  "geometry": {"coordinates":[-123.289518,44.587745],"type":"Point"}
}