{
  "type": "Feature",
  "properties": {
    "iso:country":"US",
    "sg:address":"2455 NE Diamond Lake Blvd",
    "sg:city":"Roseburg",
    "sg:classifiers":[
        {
            "category":"Bars & Pubs",
            "type":"Food & Drink"
        }
    ],
    "sg:phone":"+1 541 673 1296",
    "sg:postcode":"97470",
    "sg:province":"OR",
    "sg:tags":[
        "drinking"
    ],
    "wof:name":"Cowgirls Inc",
    "wof:placetype":"venue"
},
  "geometry": {"coordinates":[-123.325658,43.2129],"type":"Point"}
}