{
  "type": "Feature",
  "properties": {
    "iso:country":"US",
    "sg:address":"3181 SW Sam Jackson Park Rd",
    "sg:city":"Portland",
    "sg:classifiers":[
        {
            "category":"Professional",
            "subcategory":"Research",
            "type":"Services"
        },
        {
            "category":"Health Services",
            "subcategory":"Doctor",
            "type":"Services"
        }
    ],
    "sg:phone":"+1 503 494 4493",
    "sg:postcode":"97239",
    "sg:province":"OR",
    "sg:tags":[
        "development",
        "laboratory",
        "medical"
    ],
    "wof:name":"Lung Research Laboratory",
    "wof:placetype":"venue"
},
  "geometry": {"coordinates":[-122.689259,45.499088],"type":"Point"}
}