{
  "type": "Feature",
  "properties": {
    "iso:country":"US",
    "sg:address":"89201 Sherwood Island Rd",
    "sg:city":"Florence",
    "sg:classifiers":[
        {
            "category":"Building & Trades",
            "subcategory":"Construction",
            "type":"Services"
        }
    ],
    "sg:phone":"+1 541 997 9492",
    "sg:postcode":"97439",
    "sg:province":"OR",
    "sg:tags":[
        "general",
        "contractor"
    ],
    "wof:name":"Ronald G Mann Building",
    "wof:placetype":"venue"
},
  "geometry": {"coordinates":[-124.092923,44.059096],"type":"Point"}
}