{
  "type": "Feature",
  "properties": {
    "iso:country":"US",
    "sg:address":"1221 SW Maple St",
    "sg:city":"Dallas",
    "sg:classifiers":[
        {
            "category":"Building & Trades",
            "subcategory":"Construction",
            "type":"Services"
        }
    ],
    "sg:phone":"+1 503 623 5297",
    "sg:postcode":"97338",
    "sg:province":"OR",
    "sg:tags":[
        "house"
    ],
    "wof:name":"Nash Craft Construction",
    "wof:placetype":"venue"
},
  "geometry": {"coordinates":[-123.33463999999999,44.91631],"type":"Point"}
}