{
  "type": "Feature",
  "properties": {
    "addr:full":"1750 SW Skyline Blvd #19 Portland OR 97221",
    "addr:housenumber":"1750;19",
    "addr:postcode":"97221",
    "addr:street":"Sw Skyline Blvd #",
    "iso:country":"US",
    "sg:address":"1750 SW Skyline Blvd #19",
    "sg:city":"Portland",
    "sg:classifiers":[
        {
            "category":"Professional",
            "type":"Services"
        }
    ],
    "sg:phone":"+1 503 345 9176",
    "sg:postcode":"97221",
    "sg:province":"OR",
    "sg:website":"www.gatewaysolutionsinc.com",
    "wof:name":"Gateway Solutions Inc",
    "wof:placetype":"venue"
},
  "geometry": {"coordinates":[-122.73455199999999,45.509994],"type":"Point"}
}