{
  "type": "Feature",
  "properties": {
    "addr:full":"15975 NW Orchard View Rd Mcminnville OR 97128",
    "addr:housenumber":"15975",
    "addr:postcode":"97128",
    "addr:street":"Nw Orchard View Rd",
    "iso:country":"US",
    "sg:address":"15975 NW Orchard View Rd",
    "sg:city":"Mcminnville",
    "sg:classifiers":[
        {
            "category":"Retail",
            "subcategory":"Repair Shop",
            "type":"Services"
        }
    ],
    "sg:phone":"+1 503 472 2056",
    "sg:postcode":"97128",
    "sg:province":"OR",
    "wof:name":"Pratt Kathleen A Housecleaning",
    "wof:placetype":"venue"
},
  "geometry": {"coordinates":[-123.280265,45.244664],"type":"Point"}
}