{
  "type": "Feature",
  "properties": {
    "iso:country":"US",
    "sg:address":"62968 N Rolla Rd",
    "sg:city":"Bend",
    "sg:classifiers":[
        {
            "category":"Health Services",
            "subcategory":"Doctor",
            "type":"Services"
        }
    ],
    "sg:phone":"+1 541 389 8714",
    "sg:postcode":"97754",
    "sg:province":"OR",
    "sg:tags":[
        "medical"
    ],
    "wof:name":"Susan Hart Fnp",
    "wof:placetype":"venue"
},
  "geometry": {"coordinates":[-120.84777699999999,44.321362],"type":"Point"}
}