{
  "type": "Feature",
  "properties": {
    "iso:country":"US",
    "sg:address":"5570 SE Drake Rd",
    "sg:city":"Hillsboro",
    "sg:classifiers":[
        {
            "category":"Retail",
            "subcategory":"Repair Shop",
            "type":"Services"
        },
        {
            "category":"Professional",
            "subcategory":"Computer Services",
            "type":"Services"
        }
    ],
    "sg:phone":"+1 503 516 7469",
    "sg:postcode":"97123",
    "sg:province":"OR",
    "sg:tags":[
        "technical",
        "repair-business",
        "assistance",
        "equipment-service",
        "support"
    ],
    "sg:website":"http://www.paulcomputerguy.com",
    "wof:name":"Paul Computer Guy",
    "wof:placetype":"venue"
},
  "geometry": {"coordinates":[-122.925117,45.502831],"type":"Point"}
}