{
  "type": "Feature",
  "properties": {
    "addr:full":"19210 SW Martinazzi Ave Tualatin OR 97062",
    "addr:housenumber":"19210",
    "addr:postcode":"97062",
    "addr:street":"Sw Martinazzi Ave",
    "iso:country":"US",
    "sg:address":"19210 SW Martinazzi Ave",
    "sg:city":"Tualatin",
    "sg:classifiers":[
        {
            "category":"Travel",
            "subcategory":"Campground",
            "type":"Entertainment"
        }
    ],
    "sg:phone":"+1 503 885 2820",
    "sg:postcode":"97062",
    "sg:province":"OR",
    "sg:tags":[
        "camp"
    ],
    "wof:name":"Cedar Ridge",
    "wof:placetype":"venue"
},
  "geometry": {"coordinates":[-122.759,45.379639],"type":"Point"}
}