{
  "type": "Feature",
  "properties": {
    "iso:country":"US",
    "sg:address":"1046 26th Ct",
    "sg:city":"Sweet Home",
    "sg:classifiers":[
        {
            "category":"Building & Trades",
            "subcategory":"Construction",
            "type":"Services"
        }
    ],
    "sg:phone":"+1 541 367 8125",
    "sg:postcode":"97386",
    "sg:province":"OR",
    "sg:tags":[
        "installation",
        "flooring",
        "contractor"
    ],
    "wof:name":"Gene Penrod Floors",
    "wof:placetype":"venue"
},
  "geometry": {"coordinates":[-122.712063,44.396731],"type":"Point"}
}