{
  "type": "Feature",
  "properties": {
    "addr:full":"1160 Grant St Eugene OR 97402",
    "addr:housenumber":"1160",
    "addr:postcode":"97402",
    "addr:street":"Grant St",
    "iso:country":"US",
    "sg:address":"1160 Grant St",
    "sg:city":"Eugene",
    "sg:classifiers":[
        {
            "category":"Manufacturing",
            "subcategory":"Wood Products",
            "type":"Manufacturing & Wholesale Goods"
        }
    ],
    "sg:phone":"+1 541 683 3527",
    "sg:postcode":"97402",
    "sg:province":"OR",
    "sg:tags":[
        "millwork"
    ],
    "wof:name":"Jones Jm Sons Millwork",
    "wof:placetype":"venue"
},
  "geometry": {"coordinates":[-123.12014000000001,44.047076],"type":"Point"}
}