{
  "type": "Feature",
  "properties": {
    "iso:country":"US",
    "sg:address":"2746 SE 84th Ave",
    "sg:city":"Portland",
    "sg:classifiers":[
        {
            "category":"Restaurant",
            "type":"Food & Drink"
        }
    ],
    "sg:phone":"+1 503 706 7250",
    "sg:postcode":"97266",
    "sg:province":"OR",
    "sg:tags":[
        "pasta"
    ],
    "wof:name":"Carbo Nater",
    "wof:placetype":"venue"
},
  "geometry": {"coordinates":[-122.576791,45.503065],"type":"Point"}
}