{
  "type": "Feature",
  "properties": {
    "iso:country":"US",
    "sg:address":"635 S Hwy 395",
    "sg:city":"Hermiston",
    "sg:classifiers":[
        {
            "category":"Travel",
            "subcategory":"Hotels & Motels",
            "type":"Entertainment"
        }
    ],
    "sg:phone":"+1 541 567 5561",
    "sg:postcode":"97838",
    "sg:province":"OR",
    "sg:tags":[
        "operation",
        "business"
    ],
    "wof:name":"Way Inn Motel The",
    "wof:placetype":"venue"
},
  "geometry": {"coordinates":[-119.287858,45.836058],"type":"Point"}
}