{
  "type": "Feature",
  "properties": {
    "addr:full":"121 SW Salmon St Portland OR 97204",
    "addr:housenumber":"121",
    "addr:postcode":"97204",
    "addr:street":"Sw Salmon St",
    "iso:country":"US",
    "sg:address":"121 SW Salmon St",
    "sg:city":"Portland",
    "sg:classifiers":[
        {
            "category":"Real Estate",
            "subcategory":"Real Estate Agent",
            "type":"Services"
        }
    ],
    "sg:phone":"+1 503 221 0090",
    "sg:postcode":"97204",
    "sg:province":"OR",
    "sg:tags":[
        "business"
    ],
    "wof:name":"Bpn Enterprise LLC",
    "wof:placetype":"venue"
},
  "geometry": {"coordinates":[-122.67547,45.516009],"type":"Point"}
}