{
  "type": "Feature",
  "properties": {
    "iso:country":"US",
    "sg:address":"1464 Rhododendron Dr",
    "sg:city":"Florence",
    "sg:classifiers":[
        {
            "category":"Shopping",
            "subcategory":"Clothing, Apparel, & Fashions",
            "type":"Retail Goods"
        }
    ],
    "sg:phone":"+1 541 902 7609",
    "sg:postcode":"97439",
    "sg:province":"OR",
    "sg:tags":[
        "shop",
        "bridal"
    ],
    "wof:name":"Rose Waters Wedding & Flower",
    "wof:placetype":"venue"
},
  "geometry": {"coordinates":[-124.105611,43.970837],"type":"Point"}
}