{
  "type": "Feature",
  "properties": {
    "addr:full":"11919 N Jantzen Dr Portland OR 97217",
    "addr:housenumber":"11919",
    "addr:postcode":"97217",
    "addr:street":"N Jantzen Dr",
    "iso:country":"US",
    "sg:address":"11919 N Jantzen Dr",
    "sg:city":"Portland",
    "sg:classifiers":[
        {
            "category":"Insurance",
            "subcategory":"Insurance Agent",
            "type":"Services"
        }
    ],
    "sg:phone":"+1 503 285 6030",
    "sg:postcode":"97217",
    "sg:province":"OR",
    "sg:tags":[
        "adjuster"
    ],
    "wof:name":"William C Pritchett Co",
    "wof:placetype":"venue"
},
  "geometry": {"coordinates":[-122.67859,45.609533],"type":"Point"}
}