{
  "type": "Feature",
  "properties": {
    "iso:country":"US",
    "sg:address":"215 S 24th St",
    "sg:city":"Philomath",
    "sg:classifiers":[
        {
            "category":"Building & Trades",
            "subcategory":"Plumbing",
            "type":"Services"
        }
    ],
    "sg:phone":"+1 541 929 2982",
    "sg:postcode":"97370",
    "sg:province":"OR",
    "sg:tags":[
        "contractor"
    ],
    "wof:name":"Aztec AC Rfrgn & Htg",
    "wof:placetype":"venue"
},
  "geometry": {"coordinates":[-123.350477,44.540552],"type":"Point"}
}