{
  "type": "Feature",
  "properties": {
    "addr:full":"25383 State Hwy 99 Monroe OR 97456",
    "addr:housenumber":"25383",
    "addr:postcode":"97456",
    "addr:street":"State Hwy 99",
    "iso:country":"US",
    "sg:address":"25383 State Hwy 99",
    "sg:city":"Monroe",
    "sg:classifiers":[
        {
            "category":"Professional",
            "subcategory":"Business Services",
            "type":"Services"
        }
    ],
    "sg:phone":"+1 541 847 5711",
    "sg:postcode":"97456",
    "sg:province":"OR",
    "wof:name":"Fields Enterprises",
    "wof:placetype":"venue"
},
  "geometry": {"coordinates":[-123.29925,44.327134],"type":"Point"}
}