{
  "type": "Feature",
  "properties": {
    "iso:country":"US",
    "sg:address":"160 10th St",
    "sg:city":"Astoria",
    "sg:classifiers":[
        {
            "category":"Shopping",
            "type":"Retail Goods"
        }
    ],
    "sg:phone":"+1 503 325 4589",
    "sg:postcode":"97103",
    "sg:province":"OR",
    "sg:tags":[
        "merchandise"
    ],
    "wof:name":"Astoriavisual Arts",
    "wof:placetype":"venue"
},
  "geometry": {"coordinates":[-123.832618,46.190002],"type":"Point"}
}