{
  "type": "Feature",
  "properties": {
    "addr:full":"1615 NW 14th Pl Corvallis OR 97330",
    "addr:housenumber":"1615",
    "addr:postcode":"97330",
    "addr:street":"Nw 14Th Pl",
    "iso:country":"US",
    "sg:address":"1615 NW 14th Pl",
    "sg:city":"Corvallis",
    "sg:classifiers":[
        {
            "category":"Professional",
            "subcategory":"Computer Services",
            "type":"Services"
        }
    ],
    "sg:phone":"+1 541 754 9524",
    "sg:postcode":"97330",
    "sg:province":"OR",
    "sg:tags":[
        "prepackaged",
        "software"
    ],
    "wof:name":"Celestial Software Inc",
    "wof:placetype":"venue"
},
  "geometry": {"coordinates":[-123.268429,44.582222],"type":"Point"}
}