{
  "type": "Feature",
  "properties": {
    "iso:country":"US",
    "sg:address":"4474 SW Bear Dr",
    "sg:city":"Madras",
    "sg:classifiers":[
        {
            "category":"Professional",
            "type":"Services"
        }
    ],
    "sg:phone":"+1 541 546 5003",
    "sg:postcode":"97741",
    "sg:province":"OR",
    "wof:name":"Elizabeth A Bauer",
    "wof:placetype":"venue"
},
  "geometry": {"coordinates":[-121.159874,44.568208],"type":"Point"}
}