{
  "type": "Feature",
  "properties": {
    "iso:country":"US",
    "sg:address":"729 SW 15th Ave",
    "sg:city":"Portland",
    "sg:phone":"+1 503 222 2171",
    "sg:postcode":"97205",
    "sg:province":"OR",
    "wof:name":"Gracies Restaurant",
    "wof:placetype":"venue"
},
  "geometry": {"coordinates":[-122.687281,45.521178],"type":"Point"}
}