{
  "type": "Feature",
  "properties": {
    "iso:country":"US",
    "sg:address":"20872 NW Lapine Way",
    "sg:city":"Portland",
    "sg:classifiers":[
        {
            "category":"Building & Trades",
            "subcategory":"Construction",
            "type":"Services"
        }
    ],
    "sg:phone":"+1 503 590 7141",
    "sg:postcode":"97229",
    "sg:province":"OR",
    "sg:tags":[
        "house"
    ],
    "wof:name":"Denham Brothers Construction",
    "wof:placetype":"venue"
},
  "geometry": {"coordinates":[-122.889861,45.555885],"type":"Point"}
}