{
  "type": "Feature",
  "properties": {
    "iso:country":"US",
    "sg:address":"17825 SE River Rd",
    "sg:city":"Portland",
    "sg:classifiers":[
        {
            "category":"Manufacturing",
            "subcategory":"Tools & Machinery",
            "type":"Manufacturing & Wholesale Goods"
        }
    ],
    "sg:phone":"+1 503 786 3098",
    "sg:postcode":"97267",
    "sg:province":"OR",
    "sg:tags":[
        "mfg"
    ],
    "wof:name":"Hayes Innovations Inc",
    "wof:placetype":"venue"
},
  "geometry": {"coordinates":[-122.622822,45.394048],"type":"Point"}
}