{
  "type": "Feature",
  "properties": {
    "iso:country":"US",
    "sg:address":"900 SE Wilson Ave",
    "sg:city":"Bend",
    "sg:classifiers":[
        {
            "category":"Recreation",
            "type":"Entertainment"
        }
    ],
    "sg:phone":"+1 541 388 0002",
    "sg:postcode":"97702",
    "sg:province":"OR",
    "sg:tags":[
        "organization",
        "skiing"
    ],
    "sg:website":"www.mbsef.org",
    "wof:name":"Mt Bachelor Ski Education",
    "wof:placetype":"venue"
},
  "geometry": {"coordinates":[-121.29055700000001,44.044299],"type":"Point"}
}