{
  "type": "Feature",
  "properties": {
    "iso:country":"US",
    "sg:address":"5124 N.E. 42nd Street",
    "sg:city":"Portland",
    "sg:classifiers":[
        {
            "category":"Restaurant",
            "type":"Food & Drink"
        }
    ],
    "sg:phone":"+1 503 473 8484",
    "sg:postcode":"97218",
    "sg:province":"OR",
    "wof:name":"Steaming Pot Gumbolaya",
    "wof:placetype":"venue"
},
  "geometry": {"coordinates":[-122.620227,45.559929],"type":"Point"}
}