{
  "type": "Feature",
  "properties": {
    "iso:country":"US",
    "sg:address":"1414 SW 6th Ave",
    "sg:city":"Portland",
    "sg:classifiers":[
        {
            "category":"Travel",
            "subcategory":"Hotels & Motels",
            "type":"Entertainment"
        }
    ],
    "sg:phone":"+1 503 221 1611",
    "sg:postcode":"97201",
    "sg:province":"OR",
    "wof:name":"Portland Inn City Center",
    "wof:placetype":"venue"
},
  "geometry": {"coordinates":[-122.681184,45.514314],"type":"Point"}
}