{
  "type": "Feature",
  "properties": {
    "iso:country":"US",
    "sg:address":"1701 SE Hawthorne Blvd",
    "sg:city":"Portland",
    "sg:classifiers":[
        {
            "category":"Personal",
            "subcategory":"Beauty Salon",
            "type":"Services"
        },
        {
            "category":"Personal",
            "subcategory":"Barber",
            "type":"Services"
        },
        {
            "category":"Personal",
            "subcategory":"Nail Salon",
            "type":"Services"
        }
    ],
    "sg:phone":"+1 503 239 7529",
    "sg:postcode":"97214",
    "sg:province":"OR",
    "sg:tags":[
        "hair",
        "stylist"
    ],
    "wof:name":"Boston Cutters Salon For Color",
    "wof:placetype":"venue"
},
  "geometry": {"coordinates":[-122.64859,45.512192],"type":"Point"}
}