{
  "type": "Feature",
  "properties": {
    "addr:full":"7615 Booth Rd Klamath Falls OR 97603",
    "addr:housenumber":"7615",
    "addr:postcode":"97603",
    "addr:street":"Booth Rd",
    "iso:country":"US",
    "sg:address":"7615 Booth Rd",
    "sg:city":"Klamath Falls",
    "sg:classifiers":[
        {
            "category":"Professional",
            "subcategory":"Business Services",
            "type":"Services"
        }
    ],
    "sg:phone":"+1 541 273 1025",
    "sg:postcode":"97603",
    "sg:province":"OR",
    "sg:tags":[
        "underground",
        "fuel",
        "testing",
        "tank"
    ],
    "wof:name":"Precision Testing",
    "wof:placetype":"venue"
},
  "geometry": {"coordinates":[-121.696347,42.192092],"type":"Point"}
}