{
  "type": "Feature",
  "properties": {
    "iso:country":"US",
    "sg:address":"203 SE H St",
    "sg:city":"Grants Pass",
    "sg:classifiers":[
        {
            "category":"Banks & Credit Unions",
            "subcategory":"Bank",
            "type":"Services"
        }
    ],
    "sg:phone":"+1 541 955 5106",
    "sg:postcode":"97526",
    "sg:province":"OR",
    "sg:tags":[
        "loan",
        "broker"
    ],
    "wof:name":"All Real Estate Ln Investments",
    "wof:placetype":"venue"
},
  "geometry": {"coordinates":[-123.325126,42.437348],"type":"Point"}
}