{
  "type": "Feature",
  "properties": {
    "iso:country":"US",
    "sg:address":"510 SW 3rd Ave Ste 422",
    "sg:city":"Portland",
    "sg:classifiers":[
        {
            "category":"Professional",
            "subcategory":"Management & Consulting",
            "type":"Services"
        }
    ],
    "sg:phone":"+1 503 227 0212",
    "sg:postcode":"97204",
    "sg:province":"OR",
    "sg:tags":[
        "consultant"
    ],
    "wof:name":"D W Banks Company Inc",
    "wof:placetype":"venue"
},
  "geometry": {"coordinates":[-122.67485000000001,45.519513],"type":"Point"}
}