{
  "type": "Feature",
  "properties": {
    "iso:country":"US",
    "sg:address":"550 SW Industrial Way",
    "sg:city":"Bend",
    "sg:classifiers":[
        {
            "category":"Shopping",
            "subcategory":"Crafts & Fabrics",
            "type":"Retail Goods"
        }
    ],
    "sg:phone":"+1 541 617 8854",
    "sg:postcode":"97702",
    "sg:province":"OR",
    "sg:tags":[
        "art",
        "supply"
    ],
    "sg:website":"http://www.azillionbeadsbend.com",
    "wof:name":"Azillion Beads",
    "wof:placetype":"venue"
},
  "geometry": {"coordinates":[-121.31412899999999,44.050243],"type":"Point"}
}