{
  "type": "Feature",
  "properties": {
    "addr:full":"57 Spyglass Ln Florence OR 97439",
    "addr:housenumber":"57",
    "addr:postcode":"97439",
    "addr:street":"Spyglass Ln",
    "iso:country":"US",
    "sg:address":"57 Spyglass Ln",
    "sg:city":"Florence",
    "sg:classifiers":[
        {
            "category":"Manufacturing",
            "subcategory":"Tools & Machinery",
            "type":"Manufacturing & Wholesale Goods"
        }
    ],
    "sg:phone":"+1 541 997 1951",
    "sg:postcode":"97439",
    "sg:province":"OR",
    "sg:tags":[
        "representative",
        "mfg"
    ],
    "wof:name":"Tooling Kreieations",
    "wof:placetype":"venue"
},
  "geometry": {"coordinates":[-124.12155,44.004737],"type":"Point"}
}