{
  "type": "Feature",
  "properties": {
    "addr:full":"10495 NW Flotoma Dr Portland OR 97229",
    "addr:housenumber":"10495",
    "addr:postcode":"97229",
    "addr:street":"Nw Flotoma Dr",
    "iso:country":"US",
    "sg:address":"10495 NW Flotoma Dr",
    "sg:city":"Portland",
    "sg:classifiers":[
        {
            "category":"Real Estate",
            "subcategory":"Real Estate Services",
            "type":"Services"
        }
    ],
    "sg:phone":"+1 503 292 9843",
    "sg:postcode":"97229",
    "sg:province":"OR",
    "sg:tags":[
        "exchange"
    ],
    "wof:name":"Central Oregon Time Share",
    "wof:placetype":"venue"
},
  "geometry": {"coordinates":[-122.784814,45.521561],"type":"Point"}
}