{
  "type": "Feature",
  "properties": {
    "addr:full":"250 Broadalbin St SW Albany OR 97321",
    "addr:housenumber":"250",
    "addr:postcode":"97321",
    "addr:street":"Broadalbin St Sw",
    "iso:country":"US",
    "sg:address":"250 Broadalbin St SW",
    "sg:city":"Albany",
    "sg:classifiers":[
        {
            "category":"Social Services",
            "subcategory":"Job Training",
            "type":"Services"
        }
    ],
    "sg:phone":"+1 541 928 6335",
    "sg:postcode":"97321",
    "sg:province":"OR",
    "sg:tags":[
        "employment"
    ],
    "sg:website":"www.csc.gen.or.us",
    "wof:name":"Community Services Consortium",
    "wof:placetype":"venue"
},
  "geometry": {"coordinates":[-123.107286,44.635937],"type":"Point"}
}