{
  "type": "Feature",
  "properties": {
    "iso:country":"US",
    "sg:address":"859 Wills Ct",
    "sg:city":"Eugene",
    "sg:classifiers":[
        {
            "category":"Food & Beverages",
            "subcategory":"Specialty",
            "type":"Retail Goods"
        }
    ],
    "sg:phone":"+1 541 484 9933",
    "sg:postcode":"97405",
    "sg:province":"OR",
    "sg:tags":[
        "tea",
        "coffee"
    ],
    "wof:name":"Cafe Paradiso",
    "wof:placetype":"venue"
},
  "geometry": {"coordinates":[-123.104984,44.018778],"type":"Point"}
}