{
  "type": "Feature",
  "properties": {
    "iso:country":"US",
    "sg:address":"1210 W Main St",
    "sg:city":"Sheridan",
    "sg:classifiers":[
        {
            "category":"Manufacturing",
            "subcategory":"Tools & Machinery",
            "type":"Manufacturing & Wholesale Goods"
        }
    ],
    "sg:phone":"+1 503 843 3663",
    "sg:postcode":"97378",
    "sg:province":"OR",
    "wof:name":"Industrial Manufacturing Co",
    "wof:placetype":"venue"
},
  "geometry": {"coordinates":[-123.416782,45.098087],"type":"Point"}
}