{
  "type": "Feature",
  "properties": {
    "iso:country":"US",
    "sg:address":"1203 State St",
    "sg:city":"Hood River",
    "sg:classifiers":[
        {
            "category":"Wholesale",
            "subcategory":"Computers",
            "type":"Manufacturing & Wholesale Goods"
        }
    ],
    "sg:phone":"+1 541 387 3088",
    "sg:postcode":"97031",
    "sg:province":"OR",
    "wof:name":"Thomson Jan & Scott",
    "wof:placetype":"venue"
},
  "geometry": {"coordinates":[-121.524066,45.707846],"type":"Point"}
}