{
  "type": "Feature",
  "properties": {
    "iso:country":"US",
    "sg:address":"421 W Central Ave",
    "sg:city":"Sutherlin",
    "sg:classifiers":[
        {
            "category":"Retail",
            "subcategory":"Auto Repair",
            "type":"Services"
        }
    ],
    "sg:phone":"+1 541 459 1623",
    "sg:postcode":"97479",
    "sg:province":"OR",
    "sg:tags":[
        "repairing",
        "automobile"
    ],
    "wof:name":"M & P Auto Svc",
    "wof:placetype":"venue"
},
  "geometry": {"coordinates":[-123.318361,43.389312],"type":"Point"}
}