{
  "type": "Feature",
  "properties": {
    "iso:country":"US",
    "sg:address":"11460 SE Eola Hills Rd",
    "sg:city":"Amity",
    "sg:classifiers":[
        {
            "category":"Farming",
            "subcategory":"Farm",
            "type":"Manufacturing & Wholesale Goods"
        }
    ],
    "sg:phone":"+1 503 835 3008",
    "sg:postcode":"97101",
    "sg:province":"OR",
    "sg:tags":[
        "crop",
        "general"
    ],
    "wof:name":"Janzen Farms",
    "wof:placetype":"venue"
},
  "geometry": {"coordinates":[-123.120672,45.110082],"type":"Point"}
}