{
  "type": "Feature",
  "properties": {
    "addr:full":"20180 NE Sunnycrest Rd Newberg OR 97132",
    "addr:housenumber":"20180",
    "addr:postcode":"97132",
    "addr:street":"Ne Sunnycrest Rd",
    "iso:country":"US",
    "sg:address":"20180 NE Sunnycrest Rd",
    "sg:city":"Newberg",
    "sg:classifiers":[
        {
            "category":"Professional",
            "type":"Services"
        }
    ],
    "sg:phone":"+1 503 538 4547",
    "sg:postcode":"97132",
    "sg:province":"OR",
    "wof:name":"Emerson Walton",
    "wof:placetype":"venue"
},
  "geometry": {"coordinates":[-123.019328,45.301864],"type":"Point"}
}