{
  "type": "Feature",
  "properties": {
    "iso:country":"US",
    "sg:address":"1345 Poplar Dr",
    "sg:city":"Medford",
    "sg:classifiers":[
        {
            "category":"Banks & Credit Unions",
            "subcategory":"Bank",
            "type":"Services"
        }
    ],
    "sg:phone":"+1 541 779 3545",
    "sg:postcode":"97504",
    "sg:province":"OR",
    "wof:name":"Dorris Bill Insurance",
    "wof:placetype":"venue"
},
  "geometry": {"coordinates":[-122.86900300000001,42.342499],"type":"Point"}
}