{
  "type": "Feature",
  "properties": {
    "iso:country":"US",
    "sg:address":"4540 SW Hall Blvd",
    "sg:city":"Beaverton",
    "sg:classifiers":[
        {
            "category":"Insurance",
            "subcategory":"Insurance Agent",
            "type":"Services"
        },
        {
            "category":"Insurance",
            "subcategory":"Hazard Insurance",
            "type":"Services"
        },
        {
            "category":"Insurance",
            "subcategory":"Title Insurance",
            "type":"Services"
        },
        {
            "category":"Insurance",
            "subcategory":"Health Insurance",
            "type":"Services"
        },
        {
            "category":"Insurance",
            "subcategory":"Life Insurance",
            "type":"Services"
        }
    ],
    "sg:phone":"+1 503 646 4101",
    "sg:postcode":"97005",
    "sg:province":"OR",
    "sg:tags":[
        "auto",
        "commercial",
        "business",
        "homeowner"
    ],
    "sg:website":"http://www.farmersagent.com/dfilippi",
    "wof:name":"Don Filippi - Farmers Insurance",
    "wof:placetype":"venue"
},
  "geometry": {"coordinates":[-122.804069,45.48663],"type":"Point"}
}