{
  "type": "Feature",
  "properties": {
    "iso:country":"US",
    "sg:address":"12048 SE 36th Ave",
    "sg:city":"Milwaukie",
    "sg:classifiers":[
        {
            "category":"Real Estate",
            "subcategory":"Real Estate Agent",
            "type":"Services"
        }
    ],
    "sg:phone":"+1 503 659 2093",
    "sg:postcode":"97222",
    "sg:province":"OR",
    "sg:tags":[
        "appraiser"
    ],
    "wof:name":"Jess Johnson",
    "wof:placetype":"venue"
},
  "geometry": {"coordinates":[-122.62562,45.437268],"type":"Point"}
}