{
  "type": "Feature",
  "properties": {
    "iso:country":"US",
    "sg:address":"16 N Front St",
    "sg:city":"Central Point",
    "sg:classifiers":[
        {
            "category":"Autos & Motor Vehicles",
            "subcategory":"Fuel & Gas Station",
            "type":"Retail Goods"
        }
    ],
    "sg:phone":"+1 541 664 4495",
    "sg:postcode":"97502",
    "sg:province":"OR",
    "sg:tags":[
        "oil"
    ],
    "wof:name":"Bi-Mor Stations Inc",
    "wof:placetype":"venue"
},
  "geometry": {"coordinates":[-122.91799899999999,42.3741],"type":"Point"}
}