{
  "type": "Feature",
  "properties": {
    "iso:country":"US",
    "sg:address":"1001 Vista Dr",
    "sg:city":"Grants Pass",
    "sg:classifiers":[
        {
            "category":"Professional",
            "subcategory":"Computer Services",
            "type":"Services"
        }
    ],
    "sg:phone":"+1 541 474 6964",
    "sg:postcode":"97527",
    "sg:province":"OR",
    "wof:name":"Streamlined Computer Tech",
    "wof:placetype":"venue"
},
  "geometry": {"coordinates":[-123.32485,42.429916],"type":"Point"}
}