{
  "type": "Feature",
  "properties": {
    "iso:country":"US",
    "sg:address":"15105 S Hattan Rd",
    "sg:city":"Oregon City",
    "sg:classifiers":[
        {
            "category":"Freight",
            "type":"Transportation"
        }
    ],
    "sg:phone":"+1 503 631 3608",
    "sg:postcode":"97045",
    "sg:province":"OR",
    "sg:tags":[
        "operator",
        "local",
        "trucking"
    ],
    "wof:name":"G & G Trucking",
    "wof:placetype":"venue"
},
  "geometry": {"coordinates":[-122.49545000000001,45.387478],"type":"Point"}
}