{
  "type": "Feature",
  "properties": {
    "iso:country":"US",
    "sg:address":"1925 Barons Ave",
    "sg:city":"Medford",
    "sg:classifiers":[
        {
            "category":"Manufacturing",
            "subcategory":"Lumber",
            "type":"Manufacturing & Wholesale Goods"
        }
    ],
    "sg:phone":"+1 541 779 3883",
    "sg:postcode":"97501",
    "sg:province":"OR",
    "sg:tags":[
        "forestry"
    ],
    "wof:name":"Jrs Forestry",
    "wof:placetype":"venue"
},
  "geometry": {"coordinates":[-122.87575,42.300952],"type":"Point"}
}