{
  "type": "Feature",
  "properties": {
    "iso:country":"US",
    "sg:address":"3623 SE Hawthorne Blvd",
    "sg:city":"Portland",
    "sg:classifiers":[
        {
            "category":"Shopping",
            "subcategory":"Music",
            "type":"Retail Goods"
        }
    ],
    "sg:phone":"+1 503 736 9110",
    "sg:postcode":"97214",
    "sg:province":"OR",
    "wof:name":"Reverb",
    "wof:placetype":"venue"
},
  "geometry": {"coordinates":[-122.62581,45.512054],"type":"Point"}
}