{
  "type": "Feature",
  "properties": {
    "iso:country":"US",
    "sg:address":"2575 SE Tualatin Valley Hwy",
    "sg:city":"Hillsboro",
    "sg:classifiers":[
        {
            "category":"Personal",
            "type":"Services"
        }
    ],
    "sg:phone":"+1 503 640 8957",
    "sg:postcode":"97123",
    "sg:province":"OR",
    "sg:tags":[
        "consulting",
        "management"
    ],
    "wof:name":"Jenny Craig",
    "wof:placetype":"venue"
},
  "geometry": {"coordinates":[-122.9575,45.505755],"type":"Point"}
}