{
  "type": "Feature",
  "properties": {
    "iso:country":"US",
    "sg:address":"47676 McKenzie Hwy",
    "sg:city":"Vida",
    "sg:classifiers":[
        {
            "category":"Professional",
            "type":"Services"
        }
    ],
    "sg:phone":"+1 541 896 0877",
    "sg:postcode":"97488",
    "sg:province":"OR",
    "wof:name":"Hookin Dreams",
    "wof:placetype":"venue"
},
  "geometry": {"coordinates":[-122.493442,44.132646],"type":"Point"}
}