{
  "type": "Feature",
  "properties": {
    "iso:country":"US",
    "sg:address":"3095 NW 366th Pl",
    "sg:city":"Cornelius",
    "sg:classifiers":[
        {
            "category":"Building & Trades",
            "subcategory":"Plumbing",
            "type":"Services"
        }
    ],
    "sg:phone":"+1 503 693 3161",
    "sg:postcode":"97113",
    "sg:province":"OR",
    "sg:tags":[
        "conditioning",
        "air",
        "system",
        "contractor"
    ],
    "wof:name":"Rite-Way Heating & Air",
    "wof:placetype":"venue"
},
  "geometry": {"coordinates":[-123.053506,45.541565],"type":"Point"}
}