{
  "type": "Feature",
  "properties": {
    "iso:country":"US",
    "sg:address":"4716 Poinsettia St NE",
    "sg:city":"Salem",
    "sg:classifiers":[
        {
            "category":"Health Services",
            "subcategory":"Nursing And Care Facility",
            "type":"Services"
        }
    ],
    "sg:phone":"+1 503 393 2762",
    "sg:postcode":"97305",
    "sg:province":"OR",
    "wof:name":"Palmers Tree Farm",
    "wof:placetype":"venue"
},
  "geometry": {"coordinates":[-122.964825,45.034153],"type":"Point"}
}