{
  "type": "Feature",
  "properties": {
    "iso:country":"US",
    "sg:address":"2102 Pacific Ave",
    "sg:city":"Forest Grove",
    "sg:classifiers":[
        {
            "category":"Government",
            "subcategory":"Police Station",
            "type":"Public Place"
        }
    ],
    "sg:phone":"+1 503 992 3260",
    "sg:postcode":"97116",
    "sg:province":"OR",
    "sg:tags":[
        "department"
    ],
    "sg:website":"www.ci.forest-grove.or.us",
    "wof:name":"Forest Grove Police Dept",
    "wof:placetype":"venue"
},
  "geometry": {"coordinates":[-123.108454,45.51956],"type":"Point"}
}