{
  "type": "Feature",
  "properties": {
    "iso:country":"US",
    "sg:address":"9500 SW Barbur Blvd # 300",
    "sg:city":"Portland",
    "sg:classifiers":[
        {
            "category":"Travel",
            "subcategory":"Hotels & Motels",
            "type":"Entertainment"
        }
    ],
    "sg:phone":"+1 503 245 1131",
    "sg:postcode":"97219",
    "sg:province":"OR",
    "sg:tags":[
        "hotels-apartment"
    ],
    "wof:name":"Rf Investment Co",
    "wof:placetype":"venue"
},
  "geometry": {"coordinates":[-122.713808,45.456489],"type":"Point"}
}