{
  "type": "Feature",
  "properties": {
    "iso:country":"US",
    "sg:address":"9515 NW Columbia Dr",
    "sg:city":"Madras",
    "sg:classifiers":[
        {
            "category":"Farming",
            "subcategory":"Farm",
            "type":"Manufacturing & Wholesale Goods"
        }
    ],
    "sg:phone":"+1 541 475 3029",
    "sg:postcode":"97741",
    "sg:province":"OR",
    "sg:tags":[
        "crop",
        "general"
    ],
    "wof:name":"Mecca Rim Rances",
    "wof:placetype":"venue"
},
  "geometry": {"coordinates":[-121.17329599999999,44.767528],"type":"Point"}
}