{
  "type": "Feature",
  "properties": {
    "iso:country":"US",
    "sg:address":"5387 Pearson Rd SE",
    "sg:city":"Turner",
    "sg:classifiers":[
        {
            "category":"Building & Trades",
            "subcategory":"Construction",
            "type":"Services"
        }
    ],
    "sg:phone":"+1 503 585 5518",
    "sg:postcode":"97392",
    "sg:province":"OR",
    "sg:tags":[
        "contractor"
    ],
    "wof:name":"Mikes Roof Care",
    "wof:placetype":"venue"
},
  "geometry": {"coordinates":[-122.951791,44.770323],"type":"Point"}
}