{
  "type": "Feature",
  "properties": {
    "addr:full":"218 SW 2nd Ave Canby OR 97013",
    "addr:housenumber":"218",
    "addr:postcode":"97013",
    "addr:street":"Sw 2Nd Ave",
    "iso:country":"US",
    "sg:address":"218 SW 2nd Ave",
    "sg:city":"Canby",
    "sg:classifiers":[
        {
            "category":"Insurance",
            "subcategory":"Insurance Agent",
            "type":"Services"
        }
    ],
    "sg:phone":"+1 503 266 9190",
    "sg:postcode":"97013",
    "sg:province":"OR",
    "wof:name":"Metlife-Robert Armstrong",
    "wof:placetype":"venue"
},
  "geometry": {"coordinates":[-122.692543,45.260748],"type":"Point"}
}