{
  "type": "Feature",
  "properties": {
    "iso:country":"US",
    "sg:address":"1100 SW 6th Ave",
    "sg:city":"Portland",
    "sg:classifiers":[
        {
            "category":"Banks & Credit Unions",
            "subcategory":"Investment Brokerage",
            "type":"Services"
        }
    ],
    "sg:phone":"+1 503 321 8901",
    "sg:postcode":"97204",
    "sg:province":"OR",
    "sg:tags":[
        "stock",
        "bond"
    ],
    "wof:name":"Sentra Securities",
    "wof:placetype":"venue"
},
  "geometry": {"coordinates":[-122.68041,45.515737],"type":"Point"}
}