{
  "type": "Feature",
  "properties": {
    "iso:country":"US",
    "sg:address":"1118 12th St SE",
    "sg:city":"Salem",
    "sg:classifiers":[
        {
            "category":"Health Services",
            "subcategory":"Clinic",
            "type":"Services"
        }
    ],
    "sg:phone":"+1 503 371 4567",
    "sg:postcode":"97302",
    "sg:province":"OR",
    "sg:tags":[
        "home"
    ],
    "sg:website":"www.firstcallhomehealth.com",
    "wof:name":"First Call Home Health Agency",
    "wof:placetype":"venue"
},
  "geometry": {"coordinates":[-123.030565,44.926484],"type":"Point"}
}