{
  "type": "Feature",
  "properties": {
    "addr:full":"527 NE Royal Ct Portland OR 97232",
    "addr:housenumber":"527",
    "addr:postcode":"97232",
    "addr:street":"Ne Royal Ct",
    "iso:country":"US",
    "sg:address":"527 NE Royal Ct",
    "sg:city":"Portland",
    "sg:classifiers":[
        {
            "category":"Shopping",
            "subcategory":"Catalog Store",
            "type":"Retail Goods"
        }
    ],
    "sg:phone":"+1 503 234 3700",
    "sg:postcode":"97232",
    "sg:province":"OR",
    "sg:tags":[
        "music"
    ],
    "wof:name":"Import Cdscom",
    "wof:placetype":"venue"
},
  "geometry": {"coordinates":[-122.62590299999999,45.527295],"type":"Point"}
}