{
  "type": "Feature",
  "properties": {
    "iso:country":"US",
    "sg:address":"900 SE 5th St",
    "sg:city":"Gresham",
    "sg:classifiers":[
        {
            "category":"Education",
            "subcategory":"School",
            "type":"Public Place"
        }
    ],
    "sg:phone":"+1 503 661 6050",
    "sg:postcode":"97080",
    "sg:province":"OR",
    "wof:name":"East Gresham Grade School",
    "wof:placetype":"venue"
},
  "geometry": {"coordinates":[-122.42221000000001,45.493834],"type":"Point"}
}