{
  "type": "Feature",
  "properties": {
    "addr:full":"8101 SE Flavel Street Portland OR 97206",
    "addr:housenumber":"8101",
    "addr:postcode":"97206",
    "addr:street":"Se Flavel Street",
    "iso:country":"US",
    "sg:address":"8101 SE Flavel Street",
    "sg:city":"Portland",
    "sg:classifiers":[
        {
            "category":"Building & Trades",
            "subcategory":"Construction",
            "type":"Services"
        }
    ],
    "sg:phone":"+1 503 788 2274",
    "sg:postcode":"97206",
    "sg:province":"OR",
    "sg:tags":[
        "contractor"
    ],
    "sg:website":"www.oregonremodelers.com",
    "wof:name":"Oregon Remodelers Association",
    "wof:placetype":"venue"
},
  "geometry": {"coordinates":[-122.57990700000001,45.468776],"type":"Point"}
}