{
  "type": "Feature",
  "properties": {
    "addr:full":"6868 Crater Lake Hwy White City OR 97503",
    "addr:housenumber":"6868",
    "addr:postcode":"97503",
    "addr:street":"Crater Lake Hwy",
    "iso:country":"US",
    "sg:address":"6868 Crater Lake Hwy",
    "sg:city":"White City",
    "sg:classifiers":[
        {
            "category":"Building & Trades",
            "subcategory":"Construction",
            "type":"Services"
        }
    ],
    "sg:phone":"+1 541 779 1515",
    "sg:postcode":"97503",
    "sg:province":"OR",
    "sg:tags":[
        "air",
        "heating",
        "conditioning/hvac"
    ],
    "wof:name":"Kennedy Fuel",
    "wof:placetype":"venue"
},
  "geometry": {"coordinates":[-122.853996,42.4175],"type":"Point"}
}