{
  "type": "Feature",
  "properties": {
    "addr:full":"315 SE 102nd Ave Portland OR 97216",
    "addr:housenumber":"315",
    "addr:postcode":"97216",
    "addr:street":"Se 102Nd Ave",
    "iso:country":"US",
    "sg:address":"315 SE 102nd Ave",
    "sg:city":"Portland",
    "sg:classifiers":[
        {
            "category":"Shopping",
            "subcategory":"Clothing, Apparel, & Fashions",
            "type":"Retail Goods"
        }
    ],
    "sg:phone":"+1 503 253 5680",
    "sg:postcode":"97216",
    "sg:province":"OR",
    "sg:tags":[
        "wig",
        "toupee",
        "hairpiece"
    ],
    "wof:name":"Sandi's Wig Shop",
    "wof:placetype":"venue"
},
  "geometry": {"coordinates":[-122.558475,45.519612],"type":"Point"}
}