{
  "type": "Feature",
  "properties": {
    "iso:country":"US",
    "sg:address":"2701 NW Vaughn Street Suite 202",
    "sg:city":"Portland",
    "sg:classifiers":[
        {
            "category":"Deli",
            "type":"Food & Drink"
        },
        {
            "category":"Food & Beverages",
            "subcategory":"Bakery",
            "type":"Retail Goods"
        }
    ],
    "sg:phone":"+1 503 225 1154",
    "sg:postcode":"97210",
    "sg:province":"OR",
    "sg:tags":[
        "sandwich"
    ],
    "wof:name":"Suns",
    "wof:placetype":"venue"
},
  "geometry": {"coordinates":[-122.706873,45.536795],"type":"Point"}
}