{
  "type": "Feature",
  "properties": {
    "addr:full":"10115 SW Nimbus Ave Tigard OR 97223",
    "addr:housenumber":"10115",
    "addr:postcode":"97223",
    "addr:street":"Sw Nimbus Ave",
    "iso:country":"US",
    "sg:address":"10115 SW Nimbus Ave",
    "sg:city":"Tigard",
    "sg:classifiers":[
        {
            "category":"Coffee & Tea",
            "type":"Food & Drink"
        }
    ],
    "sg:phone":"+1 503 968 1892",
    "sg:postcode":"97223",
    "sg:province":"OR",
    "sg:website":"www.javamamacoffee.com/",
    "wof:name":"Java Mama",
    "wof:placetype":"venue"
},
  "geometry": {"coordinates":[-122.78990899999999,45.446637],"type":"Point"}
}