{
  "type": "Feature",
  "properties": {
    "iso:country":"US",
    "sg:address":"3426 NE 53rd Ave",
    "sg:city":"Portland",
    "sg:classifiers":[
        {
            "category":"Professional",
            "subcategory":"Business Services",
            "type":"Services"
        }
    ],
    "sg:phone":"+1 503 249 2021",
    "sg:postcode":"97213",
    "sg:province":"OR",
    "wof:name":"Cooper Design",
    "wof:placetype":"venue"
},
  "geometry": {"coordinates":[-122.608538,45.547413],"type":"Point"}
}