{
  "type": "Feature",
  "properties": {
    "iso:country":"US",
    "sg:address":"15 NE Hammond Ave",
    "sg:city":"Cascade Locks",
    "sg:classifiers":[
        {
            "category":"Professional",
            "type":"Services"
        }
    ],
    "sg:phone":"+1 541 374 8814",
    "sg:postcode":"97014",
    "sg:province":"OR",
    "wof:name":"Gorge Lift Truck Service",
    "wof:placetype":"venue"
},
  "geometry": {"coordinates":[-121.88139,45.674317],"type":"Point"}
}