{
  "type": "Feature",
  "properties": {
    "iso:country":"US",
    "sg:address":"1658 Long St",
    "sg:city":"Sweet Home",
    "sg:classifiers":[
        {
            "category":"Organizations",
            "subcategory":"Religious Organization",
            "type":"Services"
        }
    ],
    "sg:phone":"+1 541 367 6855",
    "sg:postcode":"97386",
    "sg:province":"OR",
    "sg:tags":[
        "church"
    ],
    "wof:name":"River Of Life Fellowship",
    "wof:placetype":"venue"
},
  "geometry": {"coordinates":[-122.72478099999999,44.397722],"type":"Point"}
}