{
  "type": "Feature",
  "properties": {
    "iso:country":"US",
    "sg:address":"885 N 1st Pl",
    "sg:city":"Hermiston",
    "sg:classifiers":[
        {
            "category":"Retail",
            "subcategory":"Auto Repair",
            "type":"Services"
        }
    ],
    "sg:phone":"+1 541 567 8806",
    "sg:postcode":"97838",
    "sg:province":"OR",
    "sg:tags":[
        "body",
        "automobile",
        "painting",
        "automotive"
    ],
    "wof:name":"Ware's Auto Body Inc",
    "wof:placetype":"venue"
},
  "geometry": {"coordinates":[-119.294899,45.84602],"type":"Point"}
}