{
  "type": "Feature",
  "properties": {
    "iso:country":"US",
    "sg:address":"418 SW 4th Ave",
    "sg:city":"Portland",
    "sg:classifiers":[
        {
            "category":"Professional",
            "type":"Services"
        }
    ],
    "sg:phone":"+1 503 222 3992",
    "sg:postcode":"97204",
    "sg:province":"OR",
    "sg:tags":[
        "establishment"
    ],
    "wof:name":"B S LTD",
    "wof:placetype":"venue"
},
  "geometry": {"coordinates":[-122.675719,45.519956],"type":"Point"}
}