{
  "type": "Feature",
  "properties": {
    "iso:country":"US",
    "sg:address":"1288 SW Simpson Ave. Suite I - 124",
    "sg:city":"Bend",
    "sg:classifiers":[
        {
            "category":"Professional",
            "subcategory":"Computer Services",
            "type":"Services"
        }
    ],
    "sg:phone":"+1 541 617 1909",
    "sg:postcode":"97702",
    "sg:province":"OR",
    "sg:website":"http://www.atlasguides.com/",
    "wof:name":"Atlas Guides",
    "wof:placetype":"venue"
},
  "geometry": {"coordinates":[-121.331903,44.047833],"type":"Point"}
}