{
  "type": "Feature",
  "properties": {
    "addr:full":"27534 State Hwy 213 Mulino OR 97042",
    "addr:housenumber":"27534",
    "addr:postcode":"97042",
    "addr:street":"State Hwy 213",
    "iso:country":"US",
    "sg:address":"27534 State Hwy 213",
    "sg:city":"Mulino",
    "sg:classifiers":[
        {
            "category":"Bars & Pubs",
            "type":"Food & Drink"
        }
    ],
    "sg:phone":"+1 503 829 3151",
    "sg:postcode":"97042",
    "sg:province":"OR",
    "sg:tags":[
        "grill",
        "bar"
    ],
    "wof:name":"Horseshoe Bar & Grill",
    "wof:placetype":"venue"
},
  "geometry": {"coordinates":[-122.581216,45.208275],"type":"Point"}
}