{
  "type": "Feature",
  "properties": {
    "iso:country":"US",
    "sg:address":"10845 NE Red Hills Rd",
    "sg:city":"Dundee",
    "sg:classifiers":[
        {
            "category":"Professional",
            "subcategory":"Business Services",
            "type":"Services"
        }
    ],
    "sg:phone":"+1 503 359 9590",
    "sg:postcode":"97115",
    "sg:province":"OR",
    "wof:name":"Harter Construction",
    "wof:placetype":"venue"
},
  "geometry": {"coordinates":[-123.020979,45.293424],"type":"Point"}
}