{
  "type": "Feature",
  "properties": {
    "iso:country":"US",
    "sg:address":"1105 N Riverside Ave",
    "sg:city":"Medford",
    "sg:classifiers":[
        {
            "category":"Wholesale",
            "subcategory":"Computers",
            "type":"Manufacturing & Wholesale Goods"
        }
    ],
    "sg:phone":"+1 541 858 4659",
    "sg:postcode":"97501",
    "sg:province":"OR",
    "wof:name":"Seatek Computer Services",
    "wof:placetype":"venue"
},
  "geometry": {"coordinates":[-122.875887,42.337901],"type":"Point"}
}