{
  "type": "Feature",
  "properties": {
    "iso:country":"US",
    "sg:address":"2342 Kingman Rd",
    "sg:city":"Nyssa",
    "sg:classifiers":[
        {
            "category":"Farming",
            "subcategory":"Livestock Farm",
            "type":"Manufacturing & Wholesale Goods"
        }
    ],
    "sg:phone":"+1 541 372 2681",
    "sg:postcode":"97913",
    "sg:province":"OR",
    "sg:tags":[
        "beef",
        "cash",
        "crop",
        "field",
        "grain",
        "cattle",
        "feedlot"
    ],
    "wof:name":"Patrick C Conant",
    "wof:placetype":"venue"
},
  "geometry": {"coordinates":[-117.051993,43.779929],"type":"Point"}
}