{
  "type": "Feature",
  "properties": {
    "iso:country":"US",
    "sg:address":"114 NW 15th St",
    "sg:city":"Corvallis",
    "sg:classifiers":[
        {
            "category":"Personal",
            "subcategory":"Beauty Salon",
            "type":"Services"
        }
    ],
    "sg:phone":"+1 541 752 7050",
    "sg:postcode":"97330",
    "sg:province":"OR",
    "sg:tags":[
        "shop"
    ],
    "wof:name":"Red House",
    "wof:placetype":"venue"
},
  "geometry": {"coordinates":[-123.272773,44.568389],"type":"Point"}
}