{
  "type": "Feature",
  "properties": {
    "iso:country":"US",
    "sg:address":"2900 Pringle Rd SE",
    "sg:city":"Salem",
    "sg:classifiers":[
        {
            "category":"Freight",
            "type":"Transportation"
        }
    ],
    "sg:phone":"+1 503 362 2212",
    "sg:postcode":"97302",
    "sg:province":"OR",
    "sg:tags":[
        "storage",
        "wine"
    ],
    "wof:name":"Northwest Distribution & Stge",
    "wof:placetype":"venue"
},
  "geometry": {"coordinates":[-123.02679999999999,44.911419],"type":"Point"}
}