{
  "type": "Feature",
  "properties": {
    "addr:full":"9650 SE 82nd Ave Portland OR 97266",
    "addr:housenumber":"9650",
    "addr:postcode":"97266",
    "addr:street":"Se 82Nd Ave",
    "iso:country":"US",
    "sg:address":"9650 SE 82nd Ave",
    "sg:city":"Portland",
    "sg:classifiers":[
        {
            "category":"Shopping",
            "subcategory":"Baby Store",
            "type":"Retail Goods"
        }
    ],
    "sg:phone":"+1 503 777 3006",
    "sg:postcode":"97266",
    "sg:province":"OR",
    "sg:tags":[
        "gear",
        "furniture"
    ],
    "wof:name":"Babies R US the Baby Super Store",
    "wof:placetype":"venue"
},
  "geometry": {"coordinates":[-122.579002,45.4524],"type":"Point"}
}