{
  "type": "Feature",
  "properties": {
    "iso:country":"US",
    "sg:address":"1100 Grand Ave",
    "sg:city":"Nyssa",
    "sg:classifiers":[
        {
            "category":"Real Estate",
            "subcategory":"Real Estate Operator",
            "type":"Services"
        }
    ],
    "sg:phone":"+1 541 372 2418",
    "sg:postcode":"97913",
    "sg:province":"OR",
    "sg:tags":[
        "property",
        "lessor"
    ],
    "wof:name":"Ray Schulthies",
    "wof:placetype":"venue"
},
  "geometry": {"coordinates":[-117.134895,43.838131],"type":"Point"}
}