{
  "type": "Feature",
  "properties": {
    "iso:country":"US",
    "sg:address":"1149 S Water St",
    "sg:city":"Silverton",
    "sg:classifiers":[
        {
            "category":"Building & Trades",
            "subcategory":"Landscaping Services",
            "type":"Services"
        }
    ],
    "sg:phone":"+1 503 873 8885",
    "sg:postcode":"97381",
    "sg:province":"OR",
    "sg:tags":[
        "landscape"
    ],
    "wof:name":"Dave Rose Services",
    "wof:placetype":"venue"
},
  "geometry": {"coordinates":[-122.772221,44.993692],"type":"Point"}
}