{
  "type": "Feature",
  "properties": {
    "iso:country":"US",
    "sg:address":"11010 SE Foster Rd",
    "sg:city":"Portland",
    "sg:classifiers":[
        {
            "category":"Food & Beverages",
            "subcategory":"Groceries & Convenience Stores",
            "type":"Retail Goods"
        }
    ],
    "sg:phone":"+1 503 760 8494",
    "sg:postcode":"97266",
    "sg:province":"OR",
    "wof:name":"Foster Mini Mart",
    "wof:placetype":"venue"
},
  "geometry": {"coordinates":[-122.55031,45.47583],"type":"Point"}
}