{
  "type": "Feature",
  "properties": {
    "addr:full":"11010 SE Foster Rd Portland OR 97266",
    "addr:housenumber":"11010",
    "addr:postcode":"97266",
    "addr:street":"Se Foster Rd",
    "iso:country":"US",
    "sg:address":"11010 SE Foster Rd",
    "sg:city":"Portland",
    "sg:classifiers":[
        {
            "category":"Food & Beverages",
            "subcategory":"Groceries & Convenience Stores",
            "type":"Retail Goods"
        }
    ],
    "sg:phone":"+1 503 760 8494",
    "sg:postcode":"97266",
    "sg:province":"OR",
    "wof:name":"Foster Mini Mart",
    "wof:placetype":"venue"
},
  "geometry": {"coordinates":[-122.55031,45.47583],"type":"Point"}
}