{
  "type": "Feature",
  "properties": {
    "addr:full":"7126 SE Milwaukie Avenue Portland OR 97202",
    "addr:housenumber":"7126",
    "addr:postcode":"97202",
    "addr:street":"Se Milwaukie Avenue",
    "iso:country":"US",
    "sg:address":"7126 SE Milwaukie Avenue",
    "sg:city":"Portland",
    "sg:classifiers":[
        {
            "category":"Arts & Performance",
            "subcategory":"Art Gallery",
            "type":"Entertainment"
        }
    ],
    "sg:phone":"+1 503 238 7126",
    "sg:postcode":"97202",
    "sg:province":"OR",
    "sg:website":"www.gallery7126.com/",
    "wof:name":"Gallery 7126 Limited",
    "wof:placetype":"venue"
},
  "geometry": {"coordinates":[-122.648746,45.472525],"type":"Point"}
}