{
  "type": "Feature",
  "properties": {
    "iso:country":"US",
    "sg:address":"3375 SW Terwilliger Blvd",
    "sg:city":"Portland",
    "sg:classifiers":[
        {
            "category":"Health Services",
            "subcategory":"Doctor",
            "type":"Services"
        }
    ],
    "sg:phone":"+1 503 494 2435",
    "sg:postcode":"97239",
    "sg:province":"OR",
    "sg:tags":[
        "physician",
        "surgeon"
    ],
    "wof:name":"Stout J Timothy M D Ph.D.",
    "wof:placetype":"venue"
},
  "geometry": {"coordinates":[-122.68265100000001,45.499297],"type":"Point"}
}