{
  "type": "Feature",
  "properties": {
    "addr:full":"987 Hillview Dr Ashland OR 97520",
    "addr:housenumber":"987",
    "addr:postcode":"97520",
    "addr:street":"Hillview Dr",
    "iso:country":"US",
    "sg:address":"987 Hillview Dr",
    "sg:city":"Ashland",
    "sg:classifiers":[
        {
            "category":"Organizations",
            "subcategory":"Religious Organization",
            "type":"Services"
        }
    ],
    "sg:phone":"+1 541 482 1146",
    "sg:postcode":"97520",
    "sg:province":"OR",
    "sg:tags":[
        "catholic",
        "roman",
        "place",
        "worship",
        "church"
    ],
    "sg:website":"http://www.stannechurch.com",
    "wof:name":"Our Lady Of Mtn Cathlic Ch",
    "wof:placetype":"venue"
},
  "geometry": {"coordinates":[-122.683708,42.177921],"type":"Point"}
}