{
  "type": "Feature",
  "properties": {
    "iso:country":"US",
    "sg:address":"2165 NW Watters St",
    "sg:city":"Roseburg",
    "sg:classifiers":[
        {
            "category":"Organizations",
            "subcategory":"Religious Organization",
            "type":"Services"
        }
    ],
    "sg:phone":"+1 541 672 2250",
    "sg:postcode":"97470",
    "sg:province":"OR",
    "sg:tags":[
        "church"
    ],
    "wof:name":"Umpqua Unitarian Universalist",
    "wof:placetype":"venue"
},
  "geometry": {"coordinates":[-123.383796,43.234169],"type":"Point"}
}