{
  "type": "Feature",
  "properties": {
    "addr:full":"134 W Burnside Street Portland OR 97209",
    "addr:housenumber":"134",
    "addr:postcode":"97209",
    "addr:street":"W Burnside Street",
    "iso:country":"US",
    "sg:address":"134 W Burnside Street",
    "sg:city":"Portland",
    "sg:classifiers":[
        {
            "category":"Health Services",
            "subcategory":"Chiropractor",
            "type":"Services"
        }
    ],
    "sg:phone":"+1 503 223 2213",
    "sg:postcode":"97209",
    "sg:province":"OR",
    "wof:name":"West Burnside Chiropractic Clinic",
    "wof:placetype":"venue"
},
  "geometry": {"coordinates":[-122.67156799999999,45.523209],"type":"Point"}
}