{
  "type": "Feature",
  "properties": {
    "addr:full":"5801 N Fessenden Street Portland OR 97203",
    "addr:housenumber":"5801",
    "addr:postcode":"97203",
    "addr:street":"N Fessenden Street",
    "iso:country":"US",
    "sg:address":"5801 N Fessenden Street",
    "sg:city":"Portland",
    "sg:classifiers":[
        {
            "category":"Real Estate",
            "subcategory":"Real Estate Operator",
            "type":"Services"
        }
    ],
    "sg:phone":"+1 503 289 9124",
    "sg:postcode":"97203",
    "sg:province":"OR",
    "sg:tags":[
        "apartment"
    ],
    "wof:name":"Parkview Apartments",
    "wof:placetype":"venue"
},
  "geometry": {"coordinates":[-122.725356,45.591125],"type":"Point"}
}