{
  "type": "Feature",
  "properties": {
    "addr:full":"1365 Clearview Ave NE Salem OR 97303",
    "addr:housenumber":"1365",
    "addr:postcode":"97303",
    "addr:street":"Clearview Ave Ne",
    "iso:country":"US",
    "sg:address":"1365 Clearview Ave NE",
    "sg:city":"Salem",
    "sg:classifiers":[
        {
            "category":"Building & Trades",
            "subcategory":"Construction",
            "type":"Services"
        }
    ],
    "sg:phone":"+1 503 209 9910",
    "sg:postcode":"97303",
    "sg:province":"OR",
    "sg:tags":[
        "house"
    ],
    "wof:name":"John Blake Construction",
    "wof:placetype":"venue"
},
  "geometry": {"coordinates":[-123.01679799999999,44.981715],"type":"Point"}
}