{
  "type": "Feature",
  "properties": {
    "iso:country":"US",
    "sg:address":"1704 63rd Ave NE",
    "sg:city":"Salem",
    "sg:classifiers":[
        {
            "category":"Farming",
            "subcategory":"Farm",
            "type":"Manufacturing & Wholesale Goods"
        }
    ],
    "sg:phone":"+1 503 581 3182",
    "sg:postcode":"97305",
    "sg:province":"OR",
    "sg:tags":[
        "crop",
        "general"
    ],
    "wof:name":"Forest Meadow Farm",
    "wof:placetype":"venue"
},
  "geometry": {"coordinates":[-122.931004,44.946742],"type":"Point"}
}