{
  "type": "Feature",
  "properties": {
    "iso:country":"US",
    "sg:address":"92165 Applegate Trl",
    "sg:city":"Junction City",
    "sg:classifiers":[
        {
            "category":"Building & Trades",
            "subcategory":"Construction",
            "type":"Services"
        }
    ],
    "sg:phone":"+1 541 998 3229",
    "sg:postcode":"97448",
    "sg:province":"OR",
    "sg:tags":[
        "house"
    ],
    "wof:name":"Scott Swancutt Builder",
    "wof:placetype":"venue"
},
  "geometry": {"coordinates":[-123.30613700000001,44.159694],"type":"Point"}
}