{
  "type": "Feature",
  "properties": {
    "iso:country":"US",
    "sg:address":"1007 SW 1st Ave",
    "sg:city":"Canby",
    "sg:classifiers":[
        {
            "category":"Personal",
            "subcategory":"Tanning Parlor",
            "type":"Services"
        }
    ],
    "sg:phone":"+1 503 263 3030",
    "sg:postcode":"97013",
    "sg:province":"OR",
    "sg:tags":[
        "salon"
    ],
    "wof:name":"Coco Tans",
    "wof:placetype":"venue"
},
  "geometry": {"coordinates":[-122.702551,45.257023],"type":"Point"}
}