{
  "type": "Feature",
  "properties": {
    "addr:full":"197 Metolius Ln Roseburg OR 97470",
    "addr:housenumber":"197",
    "addr:postcode":"97470",
    "addr:street":"Metolius Ln",
    "iso:country":"US",
    "sg:address":"197 Metolius Ln",
    "sg:city":"Roseburg",
    "sg:classifiers":[
        {
            "category":"Building & Trades",
            "subcategory":"Plumbing",
            "type":"Services"
        }
    ],
    "sg:phone":"+1 541 679 5121",
    "sg:postcode":"97470",
    "sg:province":"OR",
    "sg:tags":[
        "plumbing",
        "contractor"
    ],
    "wof:name":"Roto-Rooter Plumbing & Drain",
    "wof:placetype":"venue"
},
  "geometry": {"coordinates":[-123.37984299999999,43.164486],"type":"Point"}
}