{
  "type": "Feature",
  "properties": {
    "addr:full":"4105 SE Malden St Portland OR 97202",
    "addr:housenumber":"4105",
    "addr:postcode":"97202",
    "addr:street":"Se Malden St",
    "iso:country":"US",
    "sg:address":"4105 SE Malden St",
    "sg:city":"Portland",
    "sg:classifiers":[
        {
            "category":"Building & Trades",
            "subcategory":"Construction",
            "type":"Services"
        }
    ],
    "sg:phone":"+1 503 774 0887",
    "sg:postcode":"97202",
    "sg:province":"OR",
    "sg:tags":[
        "house"
    ],
    "wof:name":"Ron Agner Construction Inc",
    "wof:placetype":"venue"
},
  "geometry": {"coordinates":[-122.620929,45.467828],"type":"Point"}
}