{
  "type": "Feature",
  "properties": {
    "addr:full":"340 SW Morrison St Portland OR 97204",
    "addr:housenumber":"340",
    "addr:postcode":"97204",
    "addr:street":"Sw Morrison St",
    "iso:country":"US",
    "sg:address":"340 SW Morrison St",
    "sg:city":"Portland",
    "sg:classifiers":[
        {
            "category":"Shopping",
            "subcategory":"Clothing, Apparel, & Fashions",
            "type":"Retail Goods"
        }
    ],
    "sg:phone":"+1 503 224 5473",
    "sg:postcode":"97204",
    "sg:province":"OR",
    "sg:tags":[
        "men's",
        "clothing"
    ],
    "wof:name":"Collier",
    "wof:placetype":"venue"
},
  "geometry": {"coordinates":[-122.676194,45.518063],"type":"Point"}
}