{
  "type": "Feature",
  "properties": {
    "iso:country":"US",
    "sg:address":"147 SE Court St",
    "sg:city":"Dallas",
    "sg:classifiers":[
        {
            "category":"Manufacturing",
            "subcategory":"Printing",
            "type":"Manufacturing & Wholesale Goods"
        }
    ],
    "sg:phone":"+1 503 838 3467",
    "sg:postcode":"97338",
    "sg:province":"OR",
    "sg:tags":[
        "newspaper"
    ],
    "sg:website":"www.itemizerobserver.com",
    "wof:name":"Itemizer Observer",
    "wof:placetype":"venue"
},
  "geometry": {"coordinates":[-123.316207,44.920407],"type":"Point"}
}