{
  "type": "Feature",
  "properties": {
    "iso:country":"US",
    "sg:address":"3625 Belle Vista Ct S",
    "sg:city":"Salem",
    "sg:classifiers":[
        {
            "category":"Professional",
            "subcategory":"Computer Services",
            "type":"Services"
        }
    ],
    "sg:phone":"+1 503 316 0971",
    "sg:postcode":"97302",
    "sg:province":"OR",
    "sg:tags":[
        "repair",
        "maintenance"
    ],
    "wof:name":"Kvd Supply",
    "wof:placetype":"venue"
},
  "geometry": {"coordinates":[-123.052905,44.904349],"type":"Point"}
}