{
  "type": "Feature",
  "properties": {
    "addr:full":"15 SE 20th Ave Portland OR 97214",
    "addr:housenumber":"15",
    "addr:postcode":"97214",
    "addr:street":"Se 20Th Ave",
    "iso:country":"US",
    "sg:address":"15 SE 20th Ave",
    "sg:city":"Portland",
    "sg:classifiers":[
        {
            "category":"Cinema",
            "subcategory":"Movie Rental",
            "type":"Entertainment"
        }
    ],
    "sg:phone":"+1 503 231 0714",
    "sg:postcode":"97214",
    "sg:province":"OR",
    "sg:tags":[
        "video",
        "tape"
    ],
    "wof:name":"American Family Video",
    "wof:placetype":"venue"
},
  "geometry": {"coordinates":[-122.645572,45.52227],"type":"Point"}
}