{
  "type": "Feature",
  "properties": {
    "addr:full":"207 Kings Way Central Point OR 97502",
    "addr:housenumber":"207",
    "addr:postcode":"97502",
    "addr:street":"Kings Way",
    "iso:country":"US",
    "sg:address":"207 Kings Way",
    "sg:city":"Central Point",
    "sg:classifiers":[
        {
            "category":"Manufacturing",
            "subcategory":"Tools & Machinery",
            "type":"Manufacturing & Wholesale Goods"
        }
    ],
    "sg:phone":"+1 541 664 6658",
    "sg:postcode":"97502",
    "sg:province":"OR",
    "sg:tags":[
        "industrial",
        "mfg"
    ],
    "wof:name":"Bryant Stump Grinding Ser",
    "wof:placetype":"venue"
},
  "geometry": {"coordinates":[-122.923937,42.382497],"type":"Point"}
}