{
  "type": "Feature",
  "properties": {
    "addr:full":"188 NW Garden Valley Blvd Roseburg OR 97470",
    "addr:housenumber":"188",
    "addr:postcode":"97470",
    "addr:street":"Nw Garden Valley Blvd",
    "iso:country":"US",
    "sg:address":"188 NW Garden Valley Blvd",
    "sg:city":"Roseburg",
    "sg:classifiers":[
        {
            "category":"Real Estate",
            "subcategory":"Real Estate Agent",
            "type":"Services"
        }
    ],
    "sg:phone":"+1 541 673 8015",
    "sg:postcode":"97470",
    "sg:province":"OR",
    "wof:name":"Rental Owner Assoc of Dou",
    "wof:placetype":"venue"
},
  "geometry": {"coordinates":[-123.355304,43.226782],"type":"Point"}
}