{
  "type": "Feature",
  "properties": {
    "iso:country":"US",
    "sg:address":"9101 Shaw Sq SE",
    "sg:city":"Aumsville",
    "sg:classifiers":[
        {
            "category":"Cinema",
            "subcategory":"Movie Rental",
            "type":"Entertainment"
        }
    ],
    "sg:phone":"+1 503 931 8424",
    "sg:postcode":"97325",
    "sg:province":"OR",
    "sg:tags":[
        "motion",
        "picture",
        "distributor",
        "film",
        "exchange"
    ],
    "wof:name":"Donkey Worx Productions",
    "wof:placetype":"venue"
},
  "geometry": {"coordinates":[-122.871742,44.867069],"type":"Point"}
}