{
  "type": "Feature",
  "properties": {
    "iso:country":"US",
    "sg:address":"616 NW Arizona Ave",
    "sg:city":"Bend",
    "sg:classifiers":[
        {
            "category":"Shopping",
            "subcategory":"Jewelry",
            "type":"Retail Goods"
        }
    ],
    "sg:phone":"+1 541 617 8845",
    "sg:postcode":"97701",
    "sg:province":"OR",
    "sg:tags":[
        "jeweler"
    ],
    "wof:name":"Nomad Piercing Studio LLC",
    "wof:placetype":"venue"
},
  "geometry": {"coordinates":[-121.315714,44.05156],"type":"Point"}
}