{
  "type": "Feature",
  "properties": {
    "iso:country":"US",
    "sg:address":"1720 Washington St SW",
    "sg:city":"Albany",
    "sg:classifiers":[
        {
            "category":"Personal",
            "subcategory":"Barber",
            "type":"Services"
        }
    ],
    "sg:phone":"+1 541 926 9544",
    "sg:postcode":"97322",
    "sg:province":"OR",
    "sg:tags":[
        "shop"
    ],
    "wof:name":"Westside Barbershop PC",
    "wof:placetype":"venue"
},
  "geometry": {"coordinates":[-123.107209,44.623841],"type":"Point"}
}