{
  "type": "Feature",
  "properties": {
    "iso:country":"US",
    "sg:address":"1309 Ashland Mine Rd",
    "sg:city":"Ashland",
    "sg:classifiers":[
        {
            "category":"Organizations",
            "subcategory":"Religious Organization",
            "type":"Services"
        }
    ],
    "sg:phone":"+1 541 488 9699",
    "sg:postcode":"97520",
    "sg:province":"OR",
    "wof:name":"Immanuel Investments LLC",
    "wof:placetype":"venue"
},
  "geometry": {"coordinates":[-122.734799,42.212814],"type":"Point"}
}