{
  "type": "Feature",
  "properties": {
    "iso:country":"US",
    "sg:address":"2875 Myrtle St",
    "sg:city":"Baker City",
    "sg:classifiers":[
        {
            "category":"Retail",
            "subcategory":"Auto Repair",
            "type":"Services"
        }
    ],
    "sg:phone":"+1 541 523 9409",
    "sg:postcode":"97814",
    "sg:province":"OR",
    "sg:tags":[
        "automotive",
        "towing",
        "logging"
    ],
    "wof:name":"Ricks Auto Body",
    "wof:placetype":"venue"
},
  "geometry": {"coordinates":[-117.840756,44.770083],"type":"Point"}
}