{
  "type": "Feature",
  "properties": {
    "addr:full":"3220 Hillcrest Rd Medford OR 97501",
    "addr:housenumber":"3220",
    "addr:postcode":"97501",
    "addr:street":"Hillcrest Rd",
    "iso:country":"US",
    "sg:address":"3220 Hillcrest Rd",
    "sg:city":"Medford",
    "sg:classifiers":[
        {
            "category":"Banks & Credit Unions",
            "subcategory":"Bank",
            "type":"Services"
        }
    ],
    "sg:phone":"+1 541 779 0007",
    "sg:postcode":"97501",
    "sg:province":"OR",
    "wof:name":"South Valley Bank",
    "wof:placetype":"venue"
},
  "geometry": {"coordinates":[-122.821674,42.330816],"type":"Point"}
}