{
  "type": "Feature",
  "properties": {
    "iso:country":"US",
    "sg:address":"1790 W 11th Ave",
    "sg:city":"Eugene",
    "sg:classifiers":[
        {
            "category":"Shopping",
            "subcategory":"Computers & Home Electronics",
            "type":"Retail Goods"
        }
    ],
    "sg:phone":"+1 541 343 2646",
    "sg:postcode":"97402",
    "sg:province":"OR",
    "wof:name":"Personal Computer Associates",
    "wof:placetype":"venue"
},
  "geometry": {"coordinates":[-123.119145,44.04767],"type":"Point"}
}