{
  "type": "Feature",
  "properties": {
    "addr:full":"15358 US Hwy 101 Brookings OR 97415",
    "addr:postcode":"15358;97415",
    "addr:street":"Us Hwy 101",
    "iso:country":"US",
    "sg:address":"15358 US Hwy 101",
    "sg:city":"Brookings",
    "sg:classifiers":[
        {
            "category":"Home & Garden",
            "subcategory":"Building Materials",
            "type":"Retail Goods"
        }
    ],
    "sg:phone":"+1 541 469 4768",
    "sg:postcode":"97415",
    "sg:province":"OR",
    "sg:tags":[
        "glass",
        "window",
        "plate"
    ],
    "wof:name":"Discount Auto Glass & Glass",
    "wof:placetype":"venue"
},
  "geometry": {"coordinates":[-124.230985,42.026291],"type":"Point"}
}