{
  "type": "Feature",
  "properties": {
    "iso:country":"US",
    "sg:address":"541 NE 20th Ave Ste 101",
    "sg:city":"Portland",
    "sg:classifiers":[
        {
            "category":"Professional",
            "subcategory":"Computer Services",
            "type":"Services"
        }
    ],
    "sg:phone":"+1 503 445 4997",
    "sg:postcode":"97232",
    "sg:province":"OR",
    "sg:tags":[
        "designer",
        "network",
        "technical",
        "consultant",
        "assistance",
        "system",
        "design",
        "support",
        "software"
    ],
    "sg:website":"http://www.teamlogicit.com/nepdxor",
    "wof:name":"TeamLogic IT",
    "wof:placetype":"venue"
},
  "geometry": {"coordinates":[-122.64547399999999,45.526834],"type":"Point"}
}