{
  "type": "Feature",
  "properties": {
    "addr:full":"6735 SE 82nd Ave Portland OR 97266",
    "addr:housenumber":"6735",
    "addr:postcode":"97266",
    "addr:street":"Se 82Nd Ave",
    "iso:country":"US",
    "sg:address":"6735 SE 82nd Ave",
    "sg:city":"Portland",
    "sg:classifiers":[
        {
            "category":"Retail",
            "subcategory":"Auto Repair",
            "type":"Services"
        }
    ],
    "sg:phone":"+1 503 771 0364",
    "sg:postcode":"97266",
    "sg:province":"OR",
    "sg:tags":[
        "alternator",
        "generator"
    ],
    "wof:name":"Startmart",
    "wof:placetype":"venue"
},
  "geometry": {"coordinates":[-122.579134,45.473599],"type":"Point"}
}