{
  "type": "Feature",
  "properties": {
    "addr:full":"522 Liles Ln Umpqua OR 97486",
    "addr:housenumber":"522",
    "addr:postcode":"97486",
    "addr:street":"Liles Ln",
    "iso:country":"US",
    "sg:address":"522 Liles Ln",
    "sg:city":"Umpqua",
    "sg:classifiers":[
        {
            "category":"Farming",
            "subcategory":"Livestock Farm",
            "type":"Manufacturing & Wholesale Goods"
        }
    ],
    "sg:phone":"+1 541 459 3964",
    "sg:postcode":"97486",
    "sg:province":"OR",
    "sg:tags":[
        "beef",
        "feedlot",
        "cattle"
    ],
    "wof:name":"Jamie L Hopkins",
    "wof:placetype":"venue"
},
  "geometry": {"coordinates":[-123.503326,43.361436],"type":"Point"}
}