{
  "type": "Feature",
  "properties": {
    "iso:country":"US",
    "sg:address":"14330 White Ln SE",
    "sg:city":"Jefferson",
    "sg:classifiers":[
        {
            "category":"Wholesale",
            "subcategory":"Stationery",
            "type":"Manufacturing & Wholesale Goods"
        }
    ],
    "sg:phone":"+1 541 327 1126",
    "sg:postcode":"97352",
    "sg:province":"OR",
    "sg:tags":[
        "supply"
    ],
    "wof:name":"Best Friends Creations",
    "wof:placetype":"venue"
},
  "geometry": {"coordinates":[-123.025521,44.746448],"type":"Point"}
}