{
  "type": "Feature",
  "properties": {
    "addr:full":"27350 SW Ladd Hill Rd Sherwood OR 97140",
    "addr:housenumber":"27350",
    "addr:postcode":"97140",
    "addr:street":"Sw Ladd Hill Rd",
    "iso:country":"US",
    "sg:address":"27350 SW Ladd Hill Rd",
    "sg:city":"Sherwood",
    "sg:classifiers":[
        {
            "category":"Professional",
            "subcategory":"Management & Consulting",
            "type":"Services"
        }
    ],
    "sg:phone":"+1 503 925 9229",
    "sg:postcode":"97140",
    "sg:province":"OR",
    "sg:tags":[
        "communication",
        "business",
        "consultant"
    ],
    "wof:name":"G Robert Stewart",
    "wof:placetype":"venue"
},
  "geometry": {"coordinates":[-122.84571,45.321547],"type":"Point"}
}