{
  "type": "Feature",
  "properties": {
    "iso:country":"US",
    "sg:address":"17872 Old Wood Rd",
    "sg:city":"Bend",
    "sg:classifiers":[
        {
            "category":"Manufacturing",
            "subcategory":"Building Materials",
            "type":"Manufacturing & Wholesale Goods"
        }
    ],
    "sg:phone":"+1 541 317 0556",
    "sg:postcode":"97707",
    "sg:province":"OR",
    "sg:tags":[
        "flagstone",
        "paving"
    ],
    "wof:name":"Old World Cobblestone Inc",
    "wof:placetype":"venue"
},
  "geometry": {"coordinates":[-121.433392,43.824648],"type":"Point"}
}