{
  "type": "Feature",
  "properties": {
    "iso:country":"US",
    "sg:address":"199 Port Dock Rd",
    "sg:city":"Reedsport",
    "sg:classifiers":[
        {
            "category":"Retail",
            "subcategory":"Veterinary Services",
            "type":"Services"
        }
    ],
    "sg:phone":"+1 541 271 4696",
    "sg:postcode":"97467",
    "sg:province":"OR",
    "wof:name":"Lower Umpqua Veterinary Clinic",
    "wof:placetype":"venue"
},
  "geometry": {"coordinates":[-124.09783299999999,43.706428],"type":"Point"}
}