{
  "type": "Feature",
  "properties": {
    "addr:full":"501 Main St Klamath Falls OR 97601",
    "addr:housenumber":"501",
    "addr:postcode":"97601",
    "addr:street":"Main St",
    "iso:country":"US",
    "sg:address":"501 Main St",
    "sg:city":"Klamath Falls",
    "sg:classifiers":[
        {
            "category":"Banks & Credit Unions",
            "subcategory":"Bank",
            "type":"Services"
        }
    ],
    "sg:phone":"+1 541 882 7242",
    "sg:postcode":"97601",
    "sg:province":"OR",
    "sg:tags":[
        "loan",
        "real estate"
    ],
    "wof:name":"RBC Mortgage Co",
    "wof:placetype":"venue"
},
  "geometry": {"coordinates":[-121.78256399999999,42.224748],"type":"Point"}
}