{
  "type": "Feature",
  "properties": {
    "addr:full":"401 E Powell Blvd Gresham OR 97030",
    "addr:housenumber":"401",
    "addr:postcode":"97030",
    "addr:street":"E Powell Blvd",
    "iso:country":"US",
    "sg:address":"401 E Powell Blvd",
    "sg:city":"Gresham",
    "sg:classifiers":[
        {
            "category":"Cinema",
            "subcategory":"Movie Theater",
            "type":"Entertainment"
        }
    ],
    "sg:phone":"+1 503 665 0604",
    "sg:postcode":"97030",
    "sg:province":"OR",
    "wof:name":"Mt Hood Theatre",
    "wof:placetype":"venue"
},
  "geometry": {"coordinates":[-122.42601999999999,45.498105],"type":"Point"}
}