{
  "type": "Feature",
  "properties": {
    "iso:country":"US",
    "sg:address":"11640 Howell Prairie Rd NE",
    "sg:city":"Gervais",
    "sg:classifiers":[
        {
            "category":"Farming",
            "subcategory":"Livestock Farm",
            "type":"Manufacturing & Wholesale Goods"
        }
    ],
    "sg:phone":"+1 503 792 3191",
    "sg:postcode":"97026",
    "sg:province":"OR",
    "sg:tags":[
        "equine"
    ],
    "wof:name":"Heritage Valley Minatures",
    "wof:placetype":"venue"
},
  "geometry": {"coordinates":[-122.866444,45.088196],"type":"Point"}
}