{
  "type": "Feature",
  "properties": {
    "addr:full":"1050 Tierra Lynn Dr Woodburn OR 97071",
    "addr:housenumber":"1050",
    "addr:postcode":"97071",
    "addr:street":"Tierra Lynn Dr",
    "iso:country":"US",
    "sg:address":"1050 Tierra Lynn Dr",
    "sg:city":"Woodburn",
    "sg:classifiers":[
        {
            "category":"Building & Trades",
            "subcategory":"Construction",
            "type":"Services"
        }
    ],
    "sg:phone":"+1 503 982 5910",
    "sg:postcode":"97071",
    "sg:province":"OR",
    "sg:tags":[
        "hanging",
        "contractor"
    ],
    "wof:name":"Alpha Enterprises",
    "wof:placetype":"venue"
},
  "geometry": {"coordinates":[-122.840237,45.145919],"type":"Point"}
}