{
  "type": "Feature",
  "properties": {
    "addr:full":"1653 Jerome Ave Astoria OR 97103",
    "addr:housenumber":"1653",
    "addr:postcode":"97103",
    "addr:street":"Jerome Ave",
    "iso:country":"US",
    "sg:address":"1653 Jerome Ave",
    "sg:city":"Astoria",
    "sg:classifiers":[
        {
            "category":"Education",
            "subcategory":"Special Training",
            "type":"Public Place"
        }
    ],
    "sg:phone":"+1 503 338 7660",
    "sg:postcode":"97103",
    "sg:province":"OR",
    "wof:name":"Merts Inc",
    "wof:placetype":"venue"
},
  "geometry": {"coordinates":[-123.824389,46.184151],"type":"Point"}
}