{
  "type": "Feature",
  "properties": {
    "iso:country":"US",
    "sg:address":"1855 S A St",
    "sg:city":"Springfield",
    "sg:classifiers":[
        {
            "category":"Autos & Motor Vehicles",
            "subcategory":"Automobile Sales",
            "type":"Retail Goods"
        }
    ],
    "sg:phone":"+1 541 747 5714",
    "sg:postcode":"97477",
    "sg:province":"OR",
    "sg:tags":[
        "used"
    ],
    "wof:name":"T L Morgan Motors",
    "wof:placetype":"venue"
},
  "geometry": {"coordinates":[-122.997666,44.045222],"type":"Point"}
}