{
  "type": "Feature",
  "properties": {
    "iso:country":"US",
    "sg:address":"796 Winter St NE",
    "sg:city":"Salem",
    "sg:classifiers":[
        {
            "category":"Government",
            "subcategory":"Office",
            "type":"Public Place"
        }
    ],
    "sg:phone":"+1 503 378 5499",
    "sg:postcode":"97301",
    "sg:province":"OR",
    "wof:name":"Counselors & Therapists Board",
    "wof:placetype":"venue"
},
  "geometry": {"coordinates":[-123.02796499999999,44.94682],"type":"Point"}
}