{
  "type": "Feature",
  "properties": {
    "addr:full":"8152 SW Hall Blvd # 512 Beaverton OR 97008",
    "addr:housenumber":"8152",
    "addr:postcode":"97008",
    "addr:street":"Sw Hall Blvd # 512",
    "iso:country":"US",
    "sg:address":"8152 SW Hall Blvd # 512",
    "sg:city":"Beaverton",
    "sg:classifiers":[
        {
            "category":"Wholesale",
            "subcategory":"Medical Equipment & Supplies",
            "type":"Manufacturing & Wholesale Goods"
        },
        {
            "category":"Shopping",
            "subcategory":"Beauty & Cosmetics",
            "type":"Retail Goods"
        },
        {
            "category":"Personal",
            "subcategory":"Beauty Salon",
            "type":"Services"
        }
    ],
    "sg:phone":"+1 503 524 4223",
    "sg:postcode":"97008",
    "sg:province":"OR",
    "sg:tags":[
        "manufacturer",
        "cosmetics-wholesale",
        "perfume"
    ],
    "sg:website":"http://www.mrdata2000.com",
    "wof:name":"Justmed Inc",
    "wof:placetype":"venue"
},
  "geometry": {"coordinates":[-122.793961,45.460643],"type":"Point"}
}