{
  "type": "Feature",
  "properties": {
    "addr:full":"1540 Ash St Lake Oswego OR 97034",
    "addr:housenumber":"1540",
    "addr:postcode":"97034",
    "addr:street":"Ash St",
    "iso:country":"US",
    "sg:address":"1540 Ash St",
    "sg:city":"Lake Oswego",
    "sg:classifiers":[
        {
            "category":"Professional",
            "subcategory":"Management & Consulting",
            "type":"Services"
        }
    ],
    "sg:phone":"+1 503 803 5461",
    "sg:postcode":"97034",
    "sg:province":"OR",
    "sg:tags":[
        "consultant",
        "business"
    ],
    "wof:name":"Chadco LLC",
    "wof:placetype":"venue"
},
  "geometry": {"coordinates":[-122.676282,45.408858],"type":"Point"}
}