{
  "type": "Feature",
  "properties": {
    "iso:country":"US",
    "sg:address":"10 Crater Lake Ave",
    "sg:city":"Medford",
    "sg:classifiers":[
        {
            "category":"Real Estate",
            "subcategory":"Real Estate Services",
            "type":"Services"
        }
    ],
    "sg:phone":"+1 541 779 5420",
    "sg:postcode":"97504",
    "sg:province":"OR",
    "wof:name":"Redd McCarty Realtors",
    "wof:placetype":"venue"
},
  "geometry": {"coordinates":[-122.86212500000001,42.328016],"type":"Point"}
}