{
  "type": "Feature",
  "properties": {
    "iso:country":"US",
    "sg:address":"1680 S Crestline Dr",
    "sg:city":"Waldport",
    "sg:classifiers":[
        {
            "category":"Sports & Exercise",
            "subcategory":"Golf",
            "type":"Entertainment"
        }
    ],
    "sg:phone":"+1 541 563 3020",
    "sg:postcode":"97394",
    "sg:province":"OR",
    "sg:tags":[
        "shop",
        "course",
        "pro",
        "cafe"
    ],
    "sg:website":"www.crestviewhillsgolf.com",
    "wof:name":"Crestview Hills Golf Course",
    "wof:placetype":"venue"
},
  "geometry": {"coordinates":[-124.065174,44.414809],"type":"Point"}
}