{
  "type": "Feature",
  "properties": {
    "iso:country":"US",
    "sg:address":"11250 Deep Creek Rd",
    "sg:city":"Clatskanie",
    "sg:classifiers":[
        {
            "category":"Wholesale",
            "subcategory":"Farm Supplies",
            "type":"Manufacturing & Wholesale Goods"
        }
    ],
    "sg:phone":"+1 503 755 2375",
    "sg:postcode":"97016",
    "sg:province":"OR",
    "wof:name":"Deep Creek Ranch",
    "wof:placetype":"venue"
},
  "geometry": {"coordinates":[-123.335422,45.975727],"type":"Point"}
}