{
  "type": "Feature",
  "properties": {
    "iso:country":"US",
    "sg:address":"1050 Englewood Dr",
    "sg:city":"Lake Oswego",
    "sg:classifiers":[
        {
            "category":"Food & Beverages",
            "subcategory":"Specialty",
            "type":"Retail Goods"
        }
    ],
    "sg:phone":"+1 503 246 1798",
    "sg:postcode":"97034",
    "sg:province":"OR",
    "sg:tags":[
        "florist"
    ],
    "wof:name":"Puddle Duck Farm Herbs",
    "wof:placetype":"venue"
},
  "geometry": {"coordinates":[-122.691316,45.43414],"type":"Point"}
}