{
  "type": "Feature",
  "properties": {
    "iso:country":"US",
    "sg:address":"13250 State Hwy 211",
    "sg:city":"Molalla",
    "sg:classifiers":[
        {
            "category":"Recreation",
            "type":"Entertainment"
        }
    ],
    "sg:phone":"+1 503 829 2532",
    "sg:postcode":"97038",
    "sg:province":"OR",
    "sg:tags":[
        "historical"
    ],
    "wof:name":"Family History Ctr",
    "wof:placetype":"venue"
},
  "geometry": {"coordinates":[-122.592364,45.149091],"type":"Point"}
}