{
  "type": "Feature",
  "properties": {
    "addr:full":"6950 SW 105th Ave Beaverton OR 97008",
    "addr:housenumber":"6950",
    "addr:postcode":"97008",
    "addr:street":"Sw 105Th Ave",
    "iso:country":"US",
    "sg:address":"6950 SW 105th Ave",
    "sg:city":"Beaverton",
    "sg:classifiers":[
        {
            "category":"Health Services",
            "subcategory":"Clinic",
            "type":"Services"
        }
    ],
    "sg:phone":"+1 503 641 6393",
    "sg:postcode":"97008",
    "sg:province":"OR",
    "sg:tags":[
        "medical"
    ],
    "wof:name":"A Animal Health Services Spay And Neuter Clinic",
    "wof:placetype":"venue"
},
  "geometry": {"coordinates":[-122.784418,45.469572],"type":"Point"}
}