{
  "type": "Feature",
  "properties": {
    "iso:country":"US",
    "sg:address":"2808 SE 18th Cir",
    "sg:city":"Gresham",
    "sg:classifiers":[
        {
            "category":"Manufacturing",
            "subcategory":"Printing",
            "type":"Manufacturing & Wholesale Goods"
        }
    ],
    "sg:phone":"+1 541 504 9113",
    "sg:postcode":"97080",
    "sg:province":"OR",
    "sg:tags":[
        "periodical"
    ],
    "wof:name":"Save Nation Publications",
    "wof:placetype":"venue"
},
  "geometry": {"coordinates":[-122.40383199999999,45.483949],"type":"Point"}
}