{
  "type": "Feature",
  "properties": {
    "iso:country":"US",
    "sg:address":"6464 SW Borland Rd Ste A3",
    "sg:city":"Tualatin",
    "sg:classifiers":[
        {
            "category":"Health Services",
            "subcategory":"Hospital",
            "type":"Services"
        }
    ],
    "sg:phone":"+1 971 404 3366",
    "sg:postcode":"97062",
    "sg:province":"OR",
    "sg:tags":[
        "surgery"
    ],
    "wof:name":"Cascade Spine Center",
    "wof:placetype":"venue"
},
  "geometry": {"coordinates":[-122.743509,45.376735],"type":"Point"}
}