{
  "type": "Feature",
  "properties": {
    "iso:country":"US",
    "sg:address":"3766 Rivers Edge Dr",
    "sg:city":"Lake Oswego",
    "sg:classifiers":[
        {
            "category":"Real Estate",
            "subcategory":"Real Estate Operator",
            "type":"Services"
        }
    ],
    "sg:phone":"+1 503 638 3814",
    "sg:postcode":"97034",
    "sg:province":"OR",
    "wof:name":"Maclean Corporation",
    "wof:placetype":"venue"
},
  "geometry": {"coordinates":[-122.715026,45.38511],"type":"Point"}
}