{
  "type": "Feature",
  "properties": {
    "addr:full":"2607 SE Hawthorne Blvd Portland OR 97214",
    "addr:housenumber":"2607",
    "addr:postcode":"97214",
    "addr:street":"Se Hawthorne Blvd",
    "iso:country":"US",
    "sg:address":"2607 SE Hawthorne Blvd",
    "sg:city":"Portland",
    "sg:classifiers":[
        {
            "category":"Shopping",
            "type":"Retail Goods"
        }
    ],
    "sg:phone":"+1 503 517 8880",
    "sg:postcode":"97214",
    "sg:province":"OR",
    "sg:tags":[
        "assistive",
        "aid",
        "device",
        "merchandise",
        "hearing"
    ],
    "wof:name":"Deaf & Hearing Out Reach",
    "wof:placetype":"venue"
},
  "geometry": {"coordinates":[-122.63907399999999,45.51207],"type":"Point"}
}