{
  "type": "Feature",
  "properties": {
    "iso:country":"US",
    "sg:address":"1903 Sherman Ave",
    "sg:city":"North Bend",
    "sg:classifiers":[
        {
            "category":"Restaurant",
            "type":"Food & Drink"
        }
    ],
    "sg:phone":"+1 541 756 1322",
    "sg:postcode":"97459",
    "sg:province":"OR",
    "sg:tags":[
        "eating"
    ],
    "wof:name":"Tai's Dynasty",
    "wof:placetype":"venue"
},
  "geometry": {"coordinates":[-124.223951,43.407907],"type":"Point"}
}