{
  "type": "Feature",
  "properties": {
    "iso:country":"US",
    "sg:address":"11140 SW Barnes Rd",
    "sg:city":"Portland",
    "sg:classifiers":[
        {
            "category":"Fast Food",
            "type":"Food & Drink"
        },
        {
            "category":"Restaurant",
            "type":"Food & Drink"
        },
        {
            "category":"Professional",
            "type":"Services"
        }
    ],
    "sg:phone":"+1 503 646 1100",
    "sg:postcode":"97225",
    "sg:province":"OR",
    "sg:tags":[
        "delivery",
        "take",
        "pizza"
    ],
    "sg:website":"http://www.godfatherspizza.com",
    "wof:name":"Godfather's Pizza",
    "wof:placetype":"venue"
},
  "geometry": {"coordinates":[-122.789001,45.515099],"type":"Point"}
}