{
  "type": "Feature",
  "properties": {
    "addr:full":"201 Munsel Creek Loop Florence OR 97439",
    "addr:housenumber":"201",
    "addr:postcode":"97439",
    "addr:street":"Munsel Creek Loop",
    "iso:country":"US",
    "sg:address":"201 Munsel Creek Loop",
    "sg:city":"Florence",
    "sg:classifiers":[
        {
            "category":"Real Estate",
            "subcategory":"Real Estate Agent",
            "type":"Services"
        }
    ],
    "sg:phone":"+1 541 997 5333",
    "sg:postcode":"97439",
    "sg:province":"OR",
    "wof:name":"Florentine Estates",
    "wof:placetype":"venue"
},
  "geometry": {"coordinates":[-124.09553699999999,44.004975],"type":"Point"}
}