{
  "type": "Feature",
  "properties": {
    "iso:country":"US",
    "sg:address":"8253 SW Wilsonville Rd",
    "sg:city":"Wilsonville",
    "sg:classifiers":[
        {
            "category":"Restaurant",
            "type":"Food & Drink"
        }
    ],
    "sg:menulink":"http://www.allmenus.com/or/wilsonville/164468-wendys/menu/",
    "sg:phone":"+1 503 682 7920",
    "sg:postcode":"97070",
    "sg:province":"OR",
    "sg:tags":[
        "burger",
        "american",
        "soup"
    ],
    "wof:name":"Wendy's",
    "wof:placetype":"venue"
},
  "geometry": {"coordinates":[-122.763417,45.304526],"type":"Point"}
}