{
  "type": "Feature",
  "properties": {
    "addr:full":"13631 SE Johnson Rd Milwaukie OR 97222",
    "addr:housenumber":"13631",
    "addr:postcode":"97222",
    "addr:street":"Se Johnson Rd",
    "iso:country":"US",
    "sg:address":"13631 SE Johnson Rd",
    "sg:city":"Milwaukie",
    "sg:classifiers":[
        {
            "category":"Home & Garden",
            "subcategory":"Hardware",
            "type":"Retail Goods"
        }
    ],
    "sg:phone":"+1 503 794 2500",
    "sg:postcode":"97222",
    "sg:province":"OR",
    "sg:tags":[
        "store"
    ],
    "sg:website":"www.lowes.com",
    "wof:name":"Lowe's",
    "wof:placetype":"venue"
},
  "geometry": {"coordinates":[-122.584773,45.424511],"type":"Point"}
}