{
  "type": "Feature",
  "properties": {
    "iso:country":"US",
    "sg:address":"3550 SE Powell Blvd",
    "sg:city":"Portland",
    "sg:classifiers":[
        {
            "category":"Restaurant",
            "type":"Food & Drink"
        }
    ],
    "sg:phone":"+1 503 234 6401",
    "sg:postcode":"97202",
    "sg:province":"OR",
    "sg:tags":[
        "mexican"
    ],
    "wof:name":"Taco House Original",
    "wof:placetype":"venue"
},
  "geometry": {"coordinates":[-122.626999,45.496799],"type":"Point"}
}