{
  "type": "Feature",
  "properties": {
    "addr:full":"9886 S Heinz Rd Canby OR 97013",
    "addr:housenumber":"9886",
    "addr:postcode":"97013",
    "addr:street":"S Heinz Rd",
    "iso:country":"US",
    "sg:address":"9886 S Heinz Rd",
    "sg:city":"Canby",
    "sg:classifiers":[
        {
            "category":"Building & Trades",
            "subcategory":"Construction",
            "type":"Services"
        }
    ],
    "sg:phone":"+1 503 651 2938",
    "sg:postcode":"97013",
    "sg:province":"OR",
    "sg:tags":[
        "commercial"
    ],
    "wof:name":"R D M Construction",
    "wof:placetype":"venue"
},
  "geometry": {"coordinates":[-122.663763,45.192174],"type":"Point"}
}