{
  "type": "Feature",
  "properties": {
    "iso:country":"US",
    "sg:address":"29975 1st St",
    "sg:city":"Shedd",
    "sg:classifiers":[
        {
            "category":"Home & Garden",
            "subcategory":"Garden Supply",
            "type":"Retail Goods"
        }
    ],
    "sg:phone":"+1 541 491 3641",
    "sg:postcode":"97377",
    "sg:province":"OR",
    "sg:tags":[
        "bulb",
        "seed"
    ],
    "wof:name":"Mountain View Seeds LTD",
    "wof:placetype":"venue"
},
  "geometry": {"coordinates":[-123.108968,44.457077],"type":"Point"}
}