{
  "type": "Feature",
  "properties": {
    "iso:country":"US",
    "sg:address":"2233 Willamette St",
    "sg:city":"Eugene",
    "sg:classifiers":[
        {
            "category":"Health Services",
            "subcategory":"Doctor",
            "type":"Services"
        }
    ],
    "sg:phone":"+1 541 484 2136",
    "sg:postcode":"97405",
    "sg:province":"OR",
    "sg:tags":[
        "dentist"
    ],
    "wof:name":"John E Villano DDS",
    "wof:placetype":"venue"
},
  "geometry": {"coordinates":[-123.09138299999999,44.035197],"type":"Point"}
}