{
  "type": "Feature",
  "properties": {
    "iso:country":"US",
    "sg:address":"11370 Elkins Rd",
    "sg:city":"Monmouth",
    "sg:classifiers":[
        {
            "category":"Professional",
            "type":"Services"
        }
    ],
    "sg:phone":"+1 503 838 6552",
    "sg:postcode":"97361",
    "sg:province":"OR",
    "sg:tags":[
        "publication",
        "writing"
    ],
    "wof:name":"Gail Wells Communications",
    "wof:placetype":"venue"
},
  "geometry": {"coordinates":[-123.265218,44.800585],"type":"Point"}
}