{
  "type": "Feature",
  "properties": {
    "addr:full":"1600 SE Court Pl Pendleton OR 97801",
    "addr:housenumber":"1600",
    "addr:postcode":"97801",
    "addr:street":"Se Court Pl",
    "iso:country":"US",
    "sg:address":"1600 SE Court Pl",
    "sg:city":"Pendleton",
    "sg:classifiers":[
        {
            "category":"Health Services",
            "subcategory":"Doctor",
            "type":"Services"
        }
    ],
    "sg:phone":"+1 541 276 3213",
    "sg:postcode":"97801",
    "sg:province":"OR",
    "sg:tags":[
        "physician",
        "surgeon"
    ],
    "wof:name":"Inland Eye Institute",
    "wof:placetype":"venue"
},
  "geometry": {"coordinates":[-118.769445,45.674482],"type":"Point"}
}