{
  "type": "Feature",
  "properties": {
    "iso:country":"US",
    "sg:address":"5065 Fir Dell Ct SE",
    "sg:city":"Salem",
    "sg:classifiers":[
        {
            "category":"Shopping",
            "subcategory":"Gifts & Souvenirs",
            "type":"Retail Goods"
        }
    ],
    "sg:phone":"+1 503 931 6408",
    "sg:postcode":"97306",
    "sg:province":"OR",
    "wof:name":"Country Orchid",
    "wof:placetype":"venue"
},
  "geometry": {"coordinates":[-123.052517,44.883386],"type":"Point"}
}