{
  "type": "Feature",
  "properties": {
    "iso:country":"US",
    "sg:address":"20239 NW Pihl Rd",
    "sg:city":"Banks",
    "sg:classifiers":[
        {
            "category":"Building & Trades",
            "subcategory":"Construction",
            "type":"Services"
        }
    ],
    "sg:phone":"+1 503 648 3225",
    "sg:postcode":"97106",
    "sg:province":"OR",
    "sg:tags":[
        "fence",
        "contractor"
    ],
    "wof:name":"Dan Williams Construction Inc",
    "wof:placetype":"venue"
},
  "geometry": {"coordinates":[-123.161394,45.66681],"type":"Point"}
}