{
  "type": "Feature",
  "properties": {
    "addr:full":"1560 NE 1st St Bend OR 97701",
    "addr:housenumber":"1560",
    "addr:postcode":"97701",
    "addr:street":"Ne 1St St",
    "iso:country":"US",
    "sg:address":"1560 NE 1st St",
    "sg:city":"Bend",
    "sg:classifiers":[
        {
            "category":"Professional",
            "type":"Services"
        }
    ],
    "sg:phone":"+1 541 388 9252",
    "sg:postcode":"97701",
    "sg:province":"OR",
    "wof:name":"Northwest Surf Co",
    "wof:placetype":"venue"
},
  "geometry": {"coordinates":[-121.305508,44.065012],"type":"Point"}
}