{
  "type": "Feature",
  "properties": {
    "iso:country":"US",
    "sg:address":"242 NW F St",
    "sg:city":"Grants Pass",
    "sg:classifiers":[
        {
            "category":"Retail",
            "subcategory":"Auto Repair",
            "type":"Services"
        }
    ],
    "sg:phone":"+1 541 476 4144",
    "sg:postcode":"97526",
    "sg:province":"OR",
    "sg:tags":[
        "general"
    ],
    "wof:name":"Toms Auto Service",
    "wof:placetype":"venue"
},
  "geometry": {"coordinates":[-123.328526,42.440738],"type":"Point"}
}