{
  "type": "Feature",
  "properties": {
    "iso:country":"US",
    "sg:address":"3127 SW Anchor Ave",
    "sg:city":"Lincoln City",
    "sg:classifiers":[
        {
            "category":"Travel",
            "subcategory":"Hotels & Motels",
            "type":"Entertainment"
        }
    ],
    "sg:phone":"+1 541 996 2001",
    "sg:postcode":"97367",
    "sg:province":"OR",
    "sg:tags":[
        "binoculars",
        "operation",
        "telescope"
    ],
    "wof:name":"Westshore Oceanfront Motel",
    "wof:placetype":"venue"
},
  "geometry": {"coordinates":[-124.022936,44.944604],"type":"Point"}
}