{
  "type": "Feature",
  "properties": {
    "addr:full":"21243 S Ridge Rd Oregon City OR 97045",
    "addr:housenumber":"21243",
    "addr:postcode":"97045",
    "addr:street":"S Ridge Rd",
    "iso:country":"US",
    "sg:address":"21243 S Ridge Rd",
    "sg:city":"Oregon City",
    "sg:classifiers":[
        {
            "category":"Professional",
            "type":"Services"
        }
    ],
    "sg:phone":"+1 503 631 2201",
    "sg:postcode":"97045",
    "sg:province":"OR",
    "wof:name":"Douglas Rambo & Girli H R",
    "wof:placetype":"venue"
},
  "geometry": {"coordinates":[-122.439791,45.302478],"type":"Point"}
}