{
  "type": "Feature",
  "properties": {
    "iso:country":"US",
    "sg:address":"1010 Brownsboro-Eagle Point Hwy",
    "sg:city":"Eagle Point",
    "sg:classifiers":[
        {
            "category":"Building & Trades",
            "subcategory":"Construction",
            "type":"Services"
        }
    ],
    "sg:phone":"+1 541 830 0857",
    "sg:postcode":"97524",
    "sg:province":"OR",
    "sg:tags":[
        "home",
        "builder"
    ],
    "wof:name":"A Touch Of Home",
    "wof:placetype":"venue"
},
  "geometry": {"coordinates":[-122.786536,42.478988],"type":"Point"}
}