{
  "type": "Feature",
  "properties": {
    "iso:country":"US",
    "sg:address":"11703 NE Glenn Widing Dr",
    "sg:city":"Portland",
    "sg:classifiers":[
        {
            "category":"Shopping",
            "subcategory":"Computers & Home Electronics",
            "type":"Retail Goods"
        }
    ],
    "sg:phone":"+1 503 253 1177",
    "sg:postcode":"97220",
    "sg:province":"OR",
    "sg:tags":[
        "equipment",
        "electronic",
        "supply"
    ],
    "wof:name":"Best Buy",
    "wof:placetype":"venue"
},
  "geometry": {"coordinates":[-122.543215,45.570089],"type":"Point"}
}