{
  "type": "Feature",
  "properties": {
    "addr:full":"88706 Territorial Rd Elmira OR 97437",
    "addr:postcode":"88706;97437",
    "addr:street":"Territorial Rd",
    "iso:country":"US",
    "sg:address":"88706 Territorial Rd",
    "sg:city":"Elmira",
    "sg:classifiers":[
        {
            "category":"Food & Beverages",
            "subcategory":"Groceries & Convenience Stores",
            "type":"Retail Goods"
        }
    ],
    "sg:phone":"+1 541 935 2771",
    "sg:postcode":"97437",
    "sg:province":"OR",
    "sg:tags":[
        "grocer",
        "grocers-specialty"
    ],
    "wof:name":"Lee's Hilltop Market",
    "wof:placetype":"venue"
},
  "geometry": {"coordinates":[-123.35556800000001,44.06524],"type":"Point"}
}