{
  "type": "Feature",
  "properties": {
    "iso:country":"US",
    "sg:address":"7234 N Oatman Ave",
    "sg:city":"Portland",
    "sg:classifiers":[
        {
            "category":"Building & Trades",
            "subcategory":"Locksmith",
            "type":"Services"
        }
    ],
    "sg:phone":"+1 503 715 3776",
    "sg:postcode":"97217",
    "sg:province":"OR",
    "sg:tags":[
        "key"
    ],
    "wof:name":"Lock and Locksmith",
    "wof:placetype":"venue"
},
  "geometry": {"coordinates":[-122.700247,45.575468],"type":"Point"}
}