{
  "type": "Feature",
  "properties": {
    "iso:country":"US",
    "sg:address":"1650 W 11th Ave",
    "sg:city":"Eugene",
    "sg:classifiers":[
        {
            "category":"Home & Garden",
            "subcategory":"Home Furnishings",
            "type":"Retail Goods"
        }
    ],
    "sg:phone":"+1 541 484 6467",
    "sg:postcode":"97402",
    "sg:province":"OR",
    "sg:tags":[
        "curtain",
        "made",
        "drapery"
    ],
    "wof:name":"De-French Draperies",
    "wof:placetype":"venue"
},
  "geometry": {"coordinates":[-123.11752300000001,44.047657],"type":"Point"}
}