{
  "type": "Feature",
  "properties": {
    "iso:country":"US",
    "sg:address":"21620 SE Ash St",
    "sg:city":"Gresham",
    "sg:classifiers":[
        {
            "category":"Building & Trades",
            "subcategory":"Landscaping Services",
            "type":"Services"
        },
        {
            "category":"Wholesale",
            "subcategory":"Machinery & Supplies",
            "type":"Manufacturing & Wholesale Goods"
        },
        {
            "category":"Professional",
            "subcategory":"Business Services",
            "type":"Services"
        }
    ],
    "sg:phone":"+1 503 666 8354",
    "sg:postcode":"97030",
    "sg:province":"OR",
    "sg:tags":[
        "lawn",
        "designer",
        "consultant",
        "irrigation",
        "system",
        "equipment",
        "contractor",
        "landscape"
    ],
    "sg:website":"http://royalgreenlandscaping.com",
    "wof:name":"Royal Green Landscaping",
    "wof:placetype":"venue"
},
  "geometry": {"coordinates":[-122.440355,45.521018],"type":"Point"}
}