{
  "type": "Feature",
  "properties": {
    "iso:country":"US",
    "sg:address":"914 SW 12th St",
    "sg:city":"Newport",
    "sg:classifiers":[
        {
            "category":"Manufacturing",
            "subcategory":"Signs",
            "type":"Manufacturing & Wholesale Goods"
        }
    ],
    "sg:phone":"+1 541 265 8440",
    "sg:postcode":"97365",
    "sg:province":"OR",
    "sg:tags":[
        "specialty",
        "mfg"
    ],
    "wof:name":"Jerry White & Associates",
    "wof:placetype":"venue"
},
  "geometry": {"coordinates":[-124.058545,44.626586],"type":"Point"}
}