{
  "type": "Feature",
  "properties": {
    "addr:full":"1022 NW Marshall St Unit S-360 Portland OR 97209",
    "addr:housenumber":"1022",
    "addr:postcode":"97209",
    "addr:street":"Nw Marshall St Unit S-360",
    "iso:country":"US",
    "sg:address":"1022 NW Marshall St Unit S-360",
    "sg:city":"Portland",
    "sg:classifiers":[
        {
            "category":"Professional",
            "subcategory":"Business Services",
            "type":"Services"
        }
    ],
    "sg:phone":"+1 503 796 9822",
    "sg:postcode":"97209",
    "sg:province":"OR",
    "sg:tags":[
        "relation",
        "public"
    ],
    "sg:website":"www.liaisonpr.com",
    "wof:name":"Liaison Public Relations",
    "wof:placetype":"venue"
},
  "geometry": {"coordinates":[-122.681629,45.530804],"type":"Point"}
}