{
  "type": "Feature",
  "properties": {
    "iso:country":"US",
    "sg:address":"7134 NE Halsey St",
    "sg:city":"Portland",
    "sg:classifiers":[
        {
            "category":"Retail",
            "subcategory":"Auto Repair",
            "type":"Services"
        }
    ],
    "sg:phone":"+1 503 257 3307",
    "sg:postcode":"97213",
    "sg:province":"OR",
    "sg:tags":[
        "repairing",
        "automobile"
    ],
    "wof:name":"Armando's Auto Repair",
    "wof:placetype":"venue"
},
  "geometry": {"coordinates":[-122.589578,45.533519],"type":"Point"}
}