{
  "type": "Feature",
  "properties": {
    "iso:country":"US",
    "sg:address":"16552 SE Mcloughlin Blvd",
    "sg:city":"Portland",
    "sg:classifiers":[
        {
            "category":"Education",
            "subcategory":"School",
            "type":"Public Place"
        }
    ],
    "sg:phone":"+1 503 653 3640",
    "sg:postcode":"97267",
    "sg:province":"OR",
    "wof:name":"Academy Altrntive Schl Program",
    "wof:placetype":"venue"
},
  "geometry": {"coordinates":[-122.62235800000001,45.403551],"type":"Point"}
}