{
  "type": "Feature",
  "properties": {
    "iso:country":"US",
    "sg:address":"242 NE 12th St",
    "sg:city":"Newport",
    "sg:classifiers":[
        {
            "category":"Wholesale",
            "subcategory":"Non-durable Goods",
            "type":"Manufacturing & Wholesale Goods"
        }
    ],
    "sg:phone":"+1 541 265 4241",
    "sg:postcode":"97365",
    "sg:province":"OR",
    "wof:name":"Gizmosforall",
    "wof:placetype":"venue"
},
  "geometry": {"coordinates":[-124.050445,44.645338],"type":"Point"}
}