{
  "type": "Feature",
  "properties": {
    "iso:country":"US",
    "sg:address":"4206 NE 52nd Ave",
    "sg:city":"Portland",
    "sg:classifiers":[
        {
            "category":"Shopping",
            "subcategory":"Jewelry",
            "type":"Retail Goods"
        }
    ],
    "sg:phone":"+1 503 413 9203",
    "sg:postcode":"97218",
    "sg:province":"OR",
    "sg:tags":[
        "precious",
        "semi-precious",
        "stone"
    ],
    "wof:name":"Gem Tech Services",
    "wof:placetype":"venue"
},
  "geometry": {"coordinates":[-122.60968200000001,45.553277],"type":"Point"}
}