{
  "type": "Feature",
  "properties": {
    "addr:full":"3676 40th Ave SE Albany OR 97322",
    "addr:housenumber":"3676",
    "addr:postcode":"97322",
    "addr:street":"40Th Ave Se",
    "iso:country":"US",
    "sg:address":"3676 40th Ave SE",
    "sg:city":"Albany",
    "sg:classifiers":[
        {
            "category":"Sports & Exercise",
            "subcategory":"Race Track",
            "type":"Entertainment"
        }
    ],
    "sg:phone":"+1 541 967 5091",
    "sg:postcode":"97322",
    "sg:province":"OR",
    "sg:tags":[
        "operation",
        "racing",
        "or"
    ],
    "wof:name":"Charlie James Racing",
    "wof:placetype":"venue"
},
  "geometry": {"coordinates":[-123.0557,44.605068],"type":"Point"}
}