{
  "type": "Feature",
  "properties": {
    "iso:country":"US",
    "sg:address":"22007 S Beavercreek Rd",
    "sg:city":"Beavercreek",
    "sg:classifiers":[
        {
            "category":"Restaurant",
            "type":"Food & Drink"
        }
    ],
    "sg:phone":"+1 503 632 7412",
    "sg:postcode":"97004",
    "sg:province":"OR",
    "sg:tags":[
        "eating"
    ],
    "wof:name":"Simplicity Coffee Company",
    "wof:placetype":"venue"
},
  "geometry": {"coordinates":[-122.535168,45.287987],"type":"Point"}
}