{
  "type": "Feature",
  "properties": {
    "iso:country":"US",
    "sg:address":"1899 Larson Rd",
    "sg:city":"Roseburg",
    "sg:classifiers":[
        {
            "category":"Manufacturing",
            "subcategory":"Lumber",
            "type":"Manufacturing & Wholesale Goods"
        }
    ],
    "sg:phone":"+1 541 679 6526",
    "sg:postcode":"97470",
    "sg:province":"OR",
    "sg:tags":[
        "logging"
    ],
    "wof:name":"Bill Smith & John Woodric",
    "wof:placetype":"venue"
},
  "geometry": {"coordinates":[-123.53724,43.151342],"type":"Point"}
}