{
  "type": "Feature",
  "properties": {
    "iso:country":"US",
    "sg:address":"231 S Main St",
    "sg:city":"Myrtle Creek",
    "sg:classifiers":[
        {
            "category":"Food & Beverages",
            "subcategory":"Groceries & Convenience Stores",
            "type":"Retail Goods"
        }
    ],
    "sg:phone":"+1 541 863 5287",
    "sg:postcode":"97457",
    "sg:province":"OR",
    "sg:tags":[
        "grocer"
    ],
    "wof:name":"South County Market",
    "wof:placetype":"venue"
},
  "geometry": {"coordinates":[-123.288361,43.023715],"type":"Point"}
}