{
  "type": "Feature",
  "properties": {
    "iso:country":"US",
    "sg:address":"508 E Whiteaker Ave",
    "sg:city":"Cottage Grove",
    "sg:classifiers":[
        {
            "category":"Real Estate",
            "subcategory":"Real Estate Agent",
            "type":"Services"
        }
    ],
    "sg:phone":"+1 541 302 3760",
    "sg:postcode":"97424",
    "sg:province":"OR",
    "sg:tags":[
        "appraiser"
    ],
    "wof:name":"Oregon Value Rl Est Apprsl",
    "wof:placetype":"venue"
},
  "geometry": {"coordinates":[-123.061955,43.798068],"type":"Point"}
}