{
  "type": "Feature",
  "properties": {
    "iso:country":"US",
    "sg:address":"1001 SE Water Ave",
    "sg:city":"Portland",
    "sg:classifiers":[
        {
            "category":"Banks & Credit Unions",
            "subcategory":"Bank",
            "type":"Services"
        }
    ],
    "sg:phone":"+1 503 234 1905",
    "sg:postcode":"97214",
    "sg:province":"OR",
    "sg:tags":[
        "loan",
        "real estate"
    ],
    "wof:name":"Mortgages Direct",
    "wof:placetype":"venue"
},
  "geometry": {"coordinates":[-122.66583,45.515104],"type":"Point"}
}