{
  "type": "Feature",
  "properties": {
    "addr:full":"11 NE Hancock St Portland OR 97212",
    "addr:housenumber":"11",
    "addr:postcode":"97212",
    "addr:street":"Ne Hancock St",
    "iso:country":"US",
    "sg:address":"11 NE Hancock St",
    "sg:city":"Portland",
    "sg:classifiers":[
        {
            "category":"Shopping",
            "subcategory":"Bicycles & Sporting Goods",
            "type":"Retail Goods"
        }
    ],
    "sg:phone":"+1 503 233 1237",
    "sg:postcode":"97212",
    "sg:province":"OR",
    "sg:website":"www.calspharmacy.com",
    "wof:name":"Cal's Pharmacy",
    "wof:placetype":"venue"
},
  "geometry": {"coordinates":[-122.666246,45.53653],"type":"Point"}
}