{
  "type": "Feature",
  "properties": {
    "addr:full":"29490 S Meridian Rd Hubbard OR 97032",
    "addr:housenumber":"29490",
    "addr:postcode":"97032",
    "addr:street":"S Meridian Rd",
    "iso:country":"US",
    "sg:address":"29490 S Meridian Rd",
    "sg:city":"Hubbard",
    "sg:classifiers":[
        {
            "category":"Building & Trades",
            "subcategory":"Construction",
            "type":"Services"
        }
    ],
    "sg:phone":"+1 503 263 4647",
    "sg:postcode":"97032",
    "sg:province":"OR",
    "wof:name":"Hangar Construction Unlimited",
    "wof:placetype":"venue"
},
  "geometry": {"coordinates":[-122.74739099999999,45.178883],"type":"Point"}
}