{
  "type": "Feature",
  "properties": {
    "iso:country":"US",
    "sg:address":"29490 S Meridian Rd",
    "sg:city":"Hubbard",
    "sg:classifiers":[
        {
            "category":"Building & Trades",
            "subcategory":"Construction",
            "type":"Services"
        }
    ],
    "sg:phone":"+1 503 263 4647",
    "sg:postcode":"97032",
    "sg:province":"OR",
    "wof:name":"Hangar Construction Unlimited",
    "wof:placetype":"venue"
},
  "geometry": {"coordinates":[-122.747391,45.178883],"type":"Point"}
}