{
  "type": "Feature",
  "properties": {
    "iso:country":"US",
    "sg:address":"1250 82nd Dr",
    "sg:city":"Gladstone",
    "sg:classifiers":[
        {
            "category":"Sports & Exercise",
            "subcategory":"Gym",
            "type":"Entertainment"
        }
    ],
    "sg:phone":"+1 503 656 4663",
    "sg:postcode":"97027",
    "sg:province":"OR",
    "sg:tags":[
        "spa",
        "health"
    ],
    "wof:name":"Spa & Stoves For Less",
    "wof:placetype":"venue"
},
  "geometry": {"coordinates":[-122.57540299999999,45.391369],"type":"Point"}
}