{
  "type": "Feature",
  "properties": {
    "iso:country":"US",
    "sg:address":"2490 McMillan St",
    "sg:city":"Eugene",
    "sg:classifiers":[
        {
            "category":"Personal",
            "type":"Services"
        }
    ],
    "sg:phone":"+1 541 338 8519",
    "sg:postcode":"97405",
    "sg:province":"OR",
    "wof:name":"Ebridalfaircom LLC",
    "wof:placetype":"venue"
},
  "geometry": {"coordinates":[-123.093571,44.032383],"type":"Point"}
}