{
  "type": "Feature",
  "properties": {
    "iso:country":"US",
    "sg:address":"9755 SW Barnes Road",
    "sg:city":"Portland",
    "sg:classifiers":[
        {
            "category":"Professional",
            "subcategory":"Lawyer & Legal Services",
            "type":"Services"
        }
    ],
    "sg:phone":"+1 503 295 2924",
    "sg:postcode":"97225",
    "sg:province":"OR",
    "wof:name":"Williams Michael L",
    "wof:placetype":"venue"
},
  "geometry": {"coordinates":[-122.778327,45.511557],"type":"Point"}
}