{
  "type": "Feature",
  "properties": {
    "iso:country":"US",
    "sg:address":"4412 SW Corbett Avenue",
    "sg:city":"Portland",
    "sg:classifiers":[
        {
            "category":"Real Estate",
            "subcategory":"Architect",
            "type":"Services"
        }
    ],
    "sg:phone":"+1 503 248 9170",
    "sg:postcode":"97239",
    "sg:province":"OR",
    "wof:name":"Peck Smiley Ettlin Architects",
    "wof:placetype":"venue"
},
  "geometry": {"coordinates":[-122.676396,45.491433],"type":"Point"}
}