{
  "type": "Feature",
  "properties": {
    "addr:full":"17030 SW Baseline Rd Beaverton OR 97006",
    "addr:housenumber":"17030",
    "addr:postcode":"97006",
    "addr:street":"Sw Baseline Rd",
    "iso:country":"US",
    "sg:address":"17030 SW Baseline Rd",
    "sg:city":"Beaverton",
    "sg:classifiers":[
        {
            "category":"Retail",
            "subcategory":"Auto Repair",
            "type":"Services"
        }
    ],
    "sg:phone":"+1 503 645 0833",
    "sg:postcode":"97006",
    "sg:province":"OR",
    "wof:name":"Setniker Elmer's Auto Repair",
    "wof:placetype":"venue"
},
  "geometry": {"coordinates":[-122.851997,45.5126],"type":"Point"}
}