{
  "type": "Feature",
  "properties": {
    "iso:country":"US",
    "sg:address":"13063 SE 139th Ave",
    "sg:city":"Clackamas",
    "sg:classifiers":[
        {
            "category":"Health Services",
            "subcategory":"Doctor",
            "type":"Services"
        }
    ],
    "sg:phone":"+1 503 819 5706",
    "sg:postcode":"97086",
    "sg:province":"OR",
    "sg:tags":[
        "medical"
    ],
    "wof:name":"Northwest Center For Change",
    "wof:placetype":"venue"
},
  "geometry": {"coordinates":[-122.522175,45.427878],"type":"Point"}
}