{
  "type": "Feature",
  "properties": {
    "iso:country":"US",
    "sg:address":"8050 SE Stark St",
    "sg:city":"Portland",
    "sg:classifiers":[
        {
            "category":"Shopping",
            "type":"Retail Goods"
        }
    ],
    "sg:phone":"+1 503 292 9695",
    "sg:postcode":"97215",
    "sg:province":"OR",
    "sg:tags":[
        "hearing",
        "equipment",
        "supply",
        "impaired"
    ],
    "wof:name":"Hearing Care Ctr Of America",
    "wof:placetype":"venue"
},
  "geometry": {"coordinates":[-122.58085199999999,45.519073],"type":"Point"}
}