{
  "type": "Feature",
  "properties": {
    "addr:full":"1492 Duane St Astoria OR 97103",
    "addr:housenumber":"1492",
    "addr:postcode":"97103",
    "addr:street":"Duane St",
    "iso:country":"US",
    "sg:address":"1492 Duane St",
    "sg:city":"Astoria",
    "sg:classifiers":[
        {
            "category":"Retail",
            "subcategory":"Auto Rental",
            "type":"Services"
        }
    ],
    "sg:phone":"+1 503 325 7700",
    "sg:postcode":"97103",
    "sg:province":"OR",
    "sg:tags":[
        "passenger",
        "car"
    ],
    "wof:name":"Hertz",
    "wof:placetype":"venue"
},
  "geometry": {"coordinates":[-123.828097,46.188557],"type":"Point"}
}