{
  "type": "Feature",
  "properties": {
    "iso:country":"US",
    "sg:address":"11018 SE Malden St",
    "sg:city":"Portland",
    "sg:classifiers":[
        {
            "category":"Professional",
            "subcategory":"Management & Consulting",
            "type":"Services"
        }
    ],
    "sg:phone":"+1 503 761 8964",
    "sg:postcode":"97266",
    "sg:province":"OR",
    "sg:tags":[
        "business"
    ],
    "wof:name":"Channel Consulting Inc",
    "wof:placetype":"venue"
},
  "geometry": {"coordinates":[-122.54943,45.46677],"type":"Point"}
}