{
  "type": "Feature",
  "properties": {
    "addr:full":"1106 Sherman St SE Albany OR 97322",
    "addr:housenumber":"1106",
    "addr:postcode":"97322",
    "addr:street":"Sherman St Se",
    "iso:country":"US",
    "sg:address":"1106 Sherman St SE",
    "sg:city":"Albany",
    "sg:classifiers":[
        {
            "category":"Building & Trades",
            "subcategory":"Equipment Rental",
            "type":"Services"
        }
    ],
    "sg:phone":"+1 541 812 1353",
    "sg:postcode":"97322",
    "sg:province":"OR",
    "sg:tags":[
        "medical"
    ],
    "wof:name":"American Eye Instruments Inc",
    "wof:placetype":"venue"
},
  "geometry": {"coordinates":[-123.089265,44.63053],"type":"Point"}
}