{
  "type": "Feature",
  "properties": {
    "iso:country":"US",
    "sg:address":"937 NE D St",
    "sg:city":"Grants Pass",
    "sg:classifiers":[
        {
            "category":"Personal",
            "subcategory":"Beauty Salon",
            "type":"Services"
        }
    ],
    "sg:phone":"+1 541 479 6113",
    "sg:postcode":"97526",
    "sg:province":"OR",
    "sg:tags":[
        "shop"
    ],
    "wof:name":"Action Hair Designs",
    "wof:placetype":"venue"
},
  "geometry": {"coordinates":[-123.312771,42.440057],"type":"Point"}
}