{
  "type": "Feature",
  "properties": {
    "iso:country":"US",
    "sg:address":"2829 Lancaster Dr NE",
    "sg:city":"Salem",
    "sg:classifiers":[
        {
            "category":"Banks & Credit Unions",
            "subcategory":"Bank",
            "type":"Services"
        }
    ],
    "sg:phone":"+1 503 585 7084",
    "sg:postcode":"97305",
    "sg:province":"OR",
    "wof:name":"First Tech Credit Union",
    "wof:placetype":"venue"
},
  "geometry": {"coordinates":[-122.98361300000001,44.963085],"type":"Point"}
}