{
  "type": "Feature",
  "properties": {
    "iso:country":"US",
    "sg:address":"10700 SW Beaverton-Hillsdale Hwy",
    "sg:city":"Beaverton",
    "sg:classifiers":[
        {
            "category":"Professional",
            "subcategory":"Accounting & Tax Preparation",
            "type":"Services"
        }
    ],
    "sg:phone":"+1 503 646 2868",
    "sg:postcode":"97005",
    "sg:province":"OR",
    "sg:tags":[
        "accountant"
    ],
    "wof:name":"Sang-Soon Kim CPA",
    "wof:placetype":"venue"
},
  "geometry": {"coordinates":[-122.788115,45.486523],"type":"Point"}
}