{
  "type": "Feature",
  "properties": {
    "addr:full":"625 SW 13th St Redmond OR 97756",
    "addr:housenumber":"625",
    "addr:postcode":"97756",
    "addr:street":"Sw 13Th St",
    "iso:country":"US",
    "sg:address":"625 SW 13th St",
    "sg:city":"Redmond",
    "sg:classifiers":[
        {
            "category":"Professional",
            "type":"Services"
        }
    ],
    "sg:phone":"+1 541 548 6312",
    "sg:postcode":"97756",
    "sg:province":"OR",
    "wof:name":"Buckhorn Outfitters",
    "wof:placetype":"venue"
},
  "geometry": {"coordinates":[-121.18182299999999,44.271322],"type":"Point"}
}