{
  "type": "Feature",
  "properties": {
    "iso:country":"US",
    "sg:address":"1335 Ravenwood Dr",
    "sg:city":"Eugene",
    "sg:classifiers":[
        {
            "category":"Farming",
            "subcategory":"Farm & Veterinary Services",
            "type":"Manufacturing & Wholesale Goods"
        }
    ],
    "sg:phone":"+1 541 342 8006",
    "sg:postcode":"97401",
    "sg:province":"OR",
    "sg:tags":[
        "breeder",
        "livestock"
    ],
    "wof:name":"Cloud Nine Walkers",
    "wof:placetype":"venue"
},
  "geometry": {"coordinates":[-123.093987,44.078381],"type":"Point"}
}