{
  "type": "Feature",
  "properties": {
    "iso:country":"US",
    "sg:address":"1 Coburg Rd",
    "sg:city":"Eugene",
    "sg:classifiers":[
        {
            "category":"Retail",
            "subcategory":"Laundry & Dry Cleaning",
            "type":"Services"
        }
    ],
    "sg:phone":"+1 541 343 7424",
    "sg:postcode":"97401",
    "sg:province":"OR",
    "sg:tags":[
        "garment",
        "plant",
        "agent",
        "drycleaning"
    ],
    "wof:name":"Marjorie Mc Ayeal",
    "wof:placetype":"venue"
},
  "geometry": {"coordinates":[-123.081751,44.060501],"type":"Point"}
}