{
  "type": "Feature",
  "properties": {
    "iso:country":"US",
    "sg:address":"7417 SW Beaverton Hillsdale Suite 100",
    "sg:city":"Portland",
    "sg:classifiers":[
        {
            "category":"Professional",
            "subcategory":"Accounting & Tax Preparation",
            "type":"Services"
        }
    ],
    "sg:phone":"+1 503 297 8572",
    "sg:postcode":"97225",
    "sg:province":"OR",
    "sg:tags":[
        "accountant"
    ],
    "wof:name":"Sievertsen John A CPA",
    "wof:placetype":"venue"
},
  "geometry": {"coordinates":[-122.75367300000001,45.486104],"type":"Point"}
}