{
  "type": "Feature",
  "properties": {
    "iso:country":"US",
    "sg:address":"5279 N Lombard Street",
    "sg:city":"Portland",
    "sg:classifiers":[
        {
            "category":"Health Services",
            "subcategory":"Doctor",
            "type":"Services"
        }
    ],
    "sg:phone":"+1 503 215 3300",
    "sg:postcode":"97203",
    "sg:province":"OR",
    "sg:tags":[
        "practice",
        "family"
    ],
    "wof:name":"Mizushima Aoi MD",
    "wof:placetype":"venue"
},
  "geometry": {"coordinates":[-122.723896,45.582289],"type":"Point"}
}