{
  "type": "Feature",
  "properties": {
    "addr:full":"11314 SE 82nd Ave Portland OR 97255",
    "addr:housenumber":"11314",
    "addr:postcode":"97255",
    "addr:street":"Se 82Nd Ave",
    "iso:country":"US",
    "sg:address":"11314 SE 82nd Ave",
    "sg:city":"Portland",
    "sg:classifiers":[
        {
            "category":"Restaurant",
            "type":"Food & Drink"
        }
    ],
    "sg:phone":"+1 503 513 4845",
    "sg:postcode":"97255",
    "sg:province":"OR",
    "sg:tags":[
        "mexican"
    ],
    "wof:name":"Andale Andale",
    "wof:placetype":"venue"
},
  "geometry": {"coordinates":[-122.579052,45.461159],"type":"Point"}
}