{
  "type": "Feature",
  "properties": {
    "iso:country":"US",
    "sg:address":"15230 SW Sequoia Pkwy",
    "sg:city":"Portland",
    "sg:classifiers":[
        {
            "category":"Wholesale",
            "subcategory":"Chemicals & Plastics",
            "type":"Manufacturing & Wholesale Goods"
        },
        {
            "category":"Shopping",
            "type":"Retail Goods"
        }
    ],
    "sg:phone":"+1 503 620 4960",
    "sg:postcode":"97224",
    "sg:province":"OR",
    "sg:tags":[
        "home",
        "garden"
    ],
    "sg:website":"www.tapplastics.com",
    "wof:name":"TAP Plastics",
    "wof:placetype":"venue"
},
  "geometry": {"coordinates":[-122.74602899999999,45.410071],"type":"Point"}
}