{
  "type": "Feature",
  "properties": {
    "iso:country":"US",
    "sg:address":"9125 SW Gemini Dr",
    "sg:city":"Beaverton",
    "sg:classifiers":[
        {
            "category":"Shopping",
            "subcategory":"Computers & Home Electronics",
            "type":"Retail Goods"
        }
    ],
    "sg:phone":"+1 503 626 6622",
    "sg:postcode":"97008",
    "sg:province":"OR",
    "wof:name":"Sales Office",
    "wof:placetype":"venue"
},
  "geometry": {"coordinates":[-122.791338,45.45425],"type":"Point"}
}