{
  "type": "Feature",
  "properties": {
    "iso:country":"US",
    "sg:address":"15015 NW West Union Rd",
    "sg:city":"Portland",
    "sg:classifiers":[
        {
            "category":"Building & Trades",
            "subcategory":"Construction",
            "type":"Services"
        }
    ],
    "sg:phone":"+1 503 645 5253",
    "sg:postcode":"97229",
    "sg:province":"OR",
    "sg:tags":[
        "house"
    ],
    "wof:name":"J L M & Sons Inc",
    "wof:placetype":"venue"
},
  "geometry": {"coordinates":[-122.83149,45.542849],"type":"Point"}
}