{
  "type": "Feature",
  "properties": {
    "iso:country":"US",
    "sg:address":"1047 Buxton Ave",
    "sg:city":"Troutdale",
    "sg:classifiers":[
        {
            "category":"Freight",
            "type":"Transportation"
        }
    ],
    "sg:phone":"+1 503 699 8555",
    "sg:postcode":"97060",
    "sg:province":"OR",
    "sg:tags":[
        "local",
        "without",
        "storage",
        "trucking"
    ],
    "wof:name":"B C Transfer",
    "wof:placetype":"venue"
},
  "geometry": {"coordinates":[-122.388445,45.535409],"type":"Point"}
}