{
  "type": "Feature",
  "properties": {
    "iso:country":"US",
    "sg:address":"91 SW 212th Ave",
    "sg:city":"Beaverton",
    "sg:classifiers":[
        {
            "category":"Professional",
            "subcategory":"Engineering",
            "type":"Services"
        }
    ],
    "sg:phone":"+1 503 706 6913",
    "sg:postcode":"97006",
    "sg:province":"OR",
    "sg:website":"www.endeavoreng.com",
    "wof:name":"Endeavor Engineering",
    "wof:placetype":"venue"
},
  "geometry": {"coordinates":[-122.89572200000001,45.518973],"type":"Point"}
}