{
  "type": "Feature",
  "properties": {
    "addr:full":"1118 12th St SE Salem OR 97302",
    "addr:housenumber":"1118",
    "addr:postcode":"97302",
    "addr:street":"12Th St Se",
    "iso:country":"US",
    "sg:address":"1118 12th St SE",
    "sg:city":"Salem",
    "sg:classifiers":[
        {
            "category":"Social Services",
            "type":"Services"
        }
    ],
    "sg:phone":"+1 503 371 7393",
    "sg:postcode":"97302",
    "sg:province":"OR",
    "sg:tags":[
        "counselor",
        "marriage",
        "family"
    ],
    "wof:name":"In Focus Counseling",
    "wof:placetype":"venue"
},
  "geometry": {"coordinates":[-123.030565,44.926484],"type":"Point"}
}