{
  "type": "Feature",
  "properties": {
    "iso:country":"US",
    "sg:address":"2748 Anderson Creek Rd",
    "sg:city":"Talent",
    "sg:classifiers":[
        {
            "category":"Building & Trades",
            "subcategory":"Construction",
            "type":"Services"
        },
        {
            "category":"Manufacturing",
            "subcategory":"Lumber",
            "type":"Manufacturing & Wholesale Goods"
        }
    ],
    "sg:phone":"+1 541 535 7295",
    "sg:postcode":"97540",
    "sg:province":"OR",
    "sg:tags":[
        "excavation",
        "logging",
        "contractor"
    ],
    "wof:name":"Henry Blank Excavation & Logging",
    "wof:placetype":"venue"
},
  "geometry": {"coordinates":[-122.843903,42.213539],"type":"Point"}
}