{
  "type": "Feature",
  "properties": {
    "addr:full":"209 Portland Ave Medford OR 97504",
    "addr:housenumber":"209",
    "addr:postcode":"97504",
    "addr:street":"Portland Ave",
    "iso:country":"US",
    "sg:address":"209 Portland Ave",
    "sg:city":"Medford",
    "sg:classifiers":[
        {
            "category":"Real Estate",
            "subcategory":"Real Estate Agent",
            "type":"Services"
        }
    ],
    "sg:phone":"+1 541 770 1699",
    "sg:postcode":"97504",
    "sg:province":"OR",
    "wof:name":"Frey Real Estate Services",
    "wof:placetype":"venue"
},
  "geometry": {"coordinates":[-122.861643,42.324075],"type":"Point"}
}