{
  "type": "Feature",
  "properties": {
    "addr:full":"280 Stonehedge Pl Woodburn OR 97071",
    "addr:housenumber":"280",
    "addr:postcode":"97071",
    "addr:street":"Stonehedge Pl",
    "iso:country":"US",
    "sg:address":"280 Stonehedge Pl",
    "sg:city":"Woodburn",
    "sg:classifiers":[
        {
            "category":"Real Estate",
            "subcategory":"Real Estate Operator",
            "type":"Services"
        }
    ],
    "sg:phone":"+1 503 981 0054",
    "sg:postcode":"97071",
    "sg:province":"OR",
    "sg:tags":[
        "building",
        "apartment"
    ],
    "wof:name":"Stonehedge Court",
    "wof:placetype":"venue"
},
  "geometry": {"coordinates":[-122.848004,45.150037],"type":"Point"}
}