{
  "type": "Feature",
  "properties": {
    "iso:country":"US",
    "sg:address":"50 S Dean St",
    "sg:city":"Coquille",
    "sg:classifiers":[
        {
            "category":"Organizations",
            "subcategory":"Religious Organization",
            "type":"Services"
        }
    ],
    "sg:phone":"+1 541 396 3849",
    "sg:postcode":"97423",
    "sg:province":"OR",
    "sg:tags":[
        "church"
    ],
    "wof:name":"Holy Name Catholic Church",
    "wof:placetype":"venue"
},
  "geometry": {"coordinates":[-124.184726,43.173705],"type":"Point"}
}