{
  "type": "Feature",
  "properties": {
    "addr:full":"9715 SW Barbur Blvd Portland OR 97219",
    "addr:housenumber":"9715",
    "addr:postcode":"97219",
    "addr:street":"Sw Barbur Blvd",
    "iso:country":"US",
    "sg:address":"9715 SW Barbur Blvd",
    "sg:city":"Portland",
    "sg:classifiers":[
        {
            "category":"Retail",
            "subcategory":"Veterinary Services",
            "type":"Services"
        }
    ],
    "sg:phone":"+1 503 246 3373",
    "sg:postcode":"97219",
    "sg:province":"OR",
    "sg:tags":[
        "veterinarian"
    ],
    "wof:name":"Pierce Paige DVM",
    "wof:placetype":"venue"
},
  "geometry": {"coordinates":[-122.717539,45.454852],"type":"Point"}
}