{
  "type": "Feature",
  "properties": {
    "addr:full":"1191 Coos Bay Wagon Rd Roseburg OR 97470",
    "addr:housenumber":"1191",
    "addr:postcode":"97470",
    "addr:street":"Coos;Wagon Rd",
    "iso:country":"US",
    "sg:address":"1191 Coos Bay Wagon Rd",
    "sg:city":"Roseburg",
    "sg:classifiers":[
        {
            "category":"Travel",
            "subcategory":"Hotels & Motels",
            "type":"Entertainment"
        }
    ],
    "sg:phone":"+1 541 679 1369",
    "sg:postcode":"97470",
    "sg:province":"OR",
    "sg:tags":[
        "operation"
    ],
    "wof:name":"Morning Glory Inn",
    "wof:placetype":"venue"
},
  "geometry": {"coordinates":[-123.506139,43.178115],"type":"Point"}
}