{
  "type": "Feature",
  "properties": {
    "iso:country":"US",
    "sg:address":"5060 Fir Dell Ct SE",
    "sg:city":"Salem",
    "sg:classifiers":[
        {
            "category":"Professional",
            "subcategory":"Business Services",
            "type":"Services"
        }
    ],
    "sg:phone":"+1 503 362 2273",
    "sg:postcode":"97306",
    "sg:province":"OR",
    "wof:name":"Sipe Internet Sales",
    "wof:placetype":"venue"
},
  "geometry": {"coordinates":[-123.052367,44.883355],"type":"Point"}
}