{
  "type": "Feature",
  "properties": {
    "iso:country":"US",
    "sg:address":"87481 Rhodowood Dr",
    "sg:city":"Florence",
    "sg:classifiers":[
        {
            "category":"Manufacturing",
            "subcategory":"Retail Goods",
            "type":"Manufacturing & Wholesale Goods"
        }
    ],
    "sg:phone":"+1 541 902 2867",
    "sg:postcode":"97439",
    "sg:province":"OR",
    "sg:tags":[
        "product",
        "mfg"
    ],
    "wof:name":"Coastal Currier LLC",
    "wof:placetype":"venue"
},
  "geometry": {"coordinates":[-124.12035,44.013118],"type":"Point"}
}