{
  "type": "Feature",
  "properties": {
    "iso:country":"US",
    "sg:address":"21810 Gooseneck Creek Rd",
    "sg:city":"Sheridan",
    "sg:classifiers":[
        {
            "category":"Wholesale",
            "subcategory":"Groceries",
            "type":"Manufacturing & Wholesale Goods"
        }
    ],
    "sg:phone":"+1 503 843 2758",
    "sg:postcode":"97378",
    "sg:province":"OR",
    "wof:name":"Glen Castle Foods",
    "wof:placetype":"venue"
},
  "geometry": {"coordinates":[-123.473189,45.006255],"type":"Point"}
}