{
  "type": "Feature",
  "properties": {
    "iso:country":"US",
    "sg:address":"605 E 2nd St",
    "sg:city":"The Dalles",
    "sg:classifiers":[
        {
            "category":"Professional",
            "subcategory":"Business Services",
            "type":"Services"
        },
        {
            "category":"Autos & Motor Vehicles",
            "subcategory":"Motorcycle Sales",
            "type":"Retail Goods"
        }
    ],
    "sg:phone":"+1 541 298 6900",
    "sg:postcode":"97058",
    "sg:province":"OR",
    "sg:tags":[
        "scooter"
    ],
    "wof:name":"Adrenaline Motor Sport Racing",
    "wof:placetype":"venue"
},
  "geometry": {"coordinates":[-121.178208,45.599627],"type":"Point"}
}