{
  "type": "Feature",
  "properties": {
    "iso:country":"US",
    "sg:address":"5507 Fernbrook Ct S",
    "sg:city":"Salem",
    "sg:classifiers":[
        {
            "category":"Building & Trades",
            "subcategory":"Construction",
            "type":"Services"
        }
    ],
    "sg:phone":"+1 503 371 4598",
    "sg:postcode":"97306",
    "sg:province":"OR",
    "sg:tags":[
        "contractor"
    ],
    "wof:name":"Pacific West Sawing & Dem Inc",
    "wof:placetype":"venue"
},
  "geometry": {"coordinates":[-123.074904,44.874381],"type":"Point"}
}