{
  "type": "Feature",
  "properties": {
    "addr:full":"3023 E 2nd St The Dalles OR 97058",
    "addr:housenumber":"3023",
    "addr:postcode":"97058",
    "addr:street":"E 2Nd St",
    "iso:country":"US",
    "sg:address":"3023 E 2nd St",
    "sg:city":"The Dalles",
    "sg:classifiers":[
        {
            "category":"Retail",
            "subcategory":"Laundry & Dry Cleaning",
            "type":"Services"
        }
    ],
    "sg:phone":"+1 541 296 2291",
    "sg:postcode":"97058",
    "sg:province":"OR",
    "wof:name":"Aramark Uniform Svc",
    "wof:placetype":"venue"
},
  "geometry": {"coordinates":[-121.137108,45.601204],"type":"Point"}
}