{
  "type": "Feature",
  "properties": {
    "addr:full":"6640 SW Redwood Ln Portland OR 97224",
    "addr:housenumber":"6640",
    "addr:postcode":"97224",
    "addr:street":"Sw Redwood Ln",
    "iso:country":"US",
    "sg:address":"6640 SW Redwood Ln",
    "sg:city":"Portland",
    "sg:classifiers":[
        {
            "category":"Health Services",
            "subcategory":"Doctor",
            "type":"Services"
        }
    ],
    "sg:phone":"+1 503 620 7358",
    "sg:postcode":"97224",
    "sg:province":"OR",
    "sg:tags":[
        "clinic",
        "practice",
        "family"
    ],
    "sg:website":"www.theportlandclinic.com",
    "wof:name":"Portland Clinic Llp the",
    "wof:placetype":"venue"
},
  "geometry": {"coordinates":[-122.746002,45.4095],"type":"Point"}
}