{
  "type": "Feature",
  "properties": {
    "iso:country":"US",
    "sg:address":"15499 NW Norwich St",
    "sg:city":"Beaverton",
    "sg:classifiers":[
        {
            "category":"Building & Trades",
            "subcategory":"Locksmith",
            "type":"Services"
        }
    ],
    "sg:phone":"+1 503 764 2455",
    "sg:postcode":"97006",
    "sg:province":"OR",
    "sg:tags":[
        "lock"
    ],
    "wof:name":"Any Presentations",
    "wof:placetype":"venue"
},
  "geometry": {"coordinates":[-122.83718500000001,45.537815],"type":"Point"}
}