{
  "type": "Feature",
  "properties": {
    "iso:country":"US",
    "sg:address":"12600 SW 72nd Ave",
    "sg:city":"Portland",
    "sg:classifiers":[
        {
            "category":"Real Estate",
            "subcategory":"Developer",
            "type":"Services"
        }
    ],
    "sg:phone":"+1 503 620 0189",
    "sg:postcode":"97223",
    "sg:province":"OR",
    "wof:name":"Governors Oregon Corp",
    "wof:placetype":"venue"
},
  "geometry": {"coordinates":[-122.751508,45.429114],"type":"Point"}
}