{
  "type": "Feature",
  "properties": {
    "addr:full":"1336 Jay Ct West Linn OR 97068",
    "addr:housenumber":"1336",
    "addr:postcode":"97068",
    "addr:street":"Jay Ct",
    "iso:country":"US",
    "sg:address":"1336 Jay Ct",
    "sg:city":"West Linn",
    "sg:classifiers":[
        {
            "category":"Real Estate",
            "subcategory":"Real Estate Agent",
            "type":"Services"
        }
    ],
    "sg:phone":"+1 503 650 2974",
    "sg:postcode":"97068",
    "sg:province":"OR",
    "sg:tags":[
        "leasing",
        "rental"
    ],
    "wof:name":"In Palm Spring LLC",
    "wof:placetype":"venue"
},
  "geometry": {"coordinates":[-122.66046,45.34107],"type":"Point"}
}