{
  "type": "Feature",
  "properties": {
    "iso:country":"US",
    "sg:address":"4675 Goodpasture Loop",
    "sg:city":"Eugene",
    "sg:classifiers":[
        {
            "category":"Professional",
            "type":"Services"
        }
    ],
    "sg:phone":"+1 541 343 5452",
    "sg:postcode":"97401",
    "sg:province":"OR",
    "wof:name":"Kgn Overhead Door",
    "wof:placetype":"venue"
},
  "geometry": {"coordinates":[-123.105913,44.088345],"type":"Point"}
}