{
  "type": "Feature",
  "properties": {
    "addr:full":"1318 NW Abernethy Rd Portland OR 97229",
    "addr:housenumber":"1318",
    "addr:postcode":"97229",
    "addr:street":"Nw Abernethy Rd",
    "iso:country":"US",
    "sg:address":"1318 NW Abernethy Rd",
    "sg:city":"Portland",
    "sg:classifiers":[
        {
            "category":"Restaurant",
            "type":"Food & Drink"
        }
    ],
    "sg:phone":"+1 503 288 5149",
    "sg:postcode":"97229",
    "sg:province":"OR",
    "sg:tags":[
        "eating"
    ],
    "wof:name":"Wok N Roll",
    "wof:placetype":"venue"
},
  "geometry": {"coordinates":[-122.762236,45.532709],"type":"Point"}
}