{
  "type": "Feature",
  "properties": {
    "addr:full":"1 Park Ave Brookings OR 97415",
    "addr:housenumber":"1",
    "addr:postcode":"97415",
    "addr:street":"Park Ave",
    "iso:country":"US",
    "sg:address":"1 Park Ave",
    "sg:city":"Brookings",
    "sg:classifiers":[
        {
            "category":"Health Services",
            "subcategory":"Nursing And Care Facility",
            "type":"Services"
        }
    ],
    "sg:phone":"+1 541 469 3111",
    "sg:postcode":"97415",
    "sg:province":"OR",
    "sg:tags":[
        "home",
        "convalescent"
    ],
    "wof:name":"Curry Good Samaritan Ctr",
    "wof:placetype":"venue"
},
  "geometry": {"coordinates":[-124.28267,42.05396],"type":"Point"}
}