{
  "type": "Feature",
  "properties": {
    "iso:country":"US",
    "sg:address":"8506 SW Salish Ln",
    "sg:city":"Wilsonville",
    "sg:classifiers":[
        {
            "category":"Freight",
            "type":"Transportation"
        }
    ],
    "sg:phone":"+1 503 829 9179",
    "sg:postcode":"97070",
    "sg:province":"OR",
    "sg:tags":[
        "broker",
        "trucking"
    ],
    "wof:name":"US Post Office",
    "wof:placetype":"venue"
},
  "geometry": {"coordinates":[-122.764548,45.338188],"type":"Point"}
}