{
  "type": "Feature",
  "properties": {
    "iso:country":"US",
    "sg:address":"33522 Oakville Rd SW",
    "sg:city":"Albany",
    "sg:classifiers":[
        {
            "category":"Farming",
            "subcategory":"Farm",
            "type":"Manufacturing & Wholesale Goods"
        }
    ],
    "sg:phone":"+1 541 928 9761",
    "sg:postcode":"97321",
    "sg:province":"OR",
    "sg:tags":[
        "crop",
        "general"
    ],
    "wof:name":"Ohling Farm",
    "wof:placetype":"venue"
},
  "geometry": {"coordinates":[-123.17080799999999,44.535797],"type":"Point"}
}