{
  "type": "Feature",
  "properties": {
    "addr:full":"3001 SE Hawthorne Blvd Portland OR 97214",
    "addr:housenumber":"3001",
    "addr:postcode":"97214",
    "addr:street":"Se Hawthorne Blvd",
    "iso:country":"US",
    "sg:address":"3001 SE Hawthorne Blvd",
    "sg:city":"Portland",
    "sg:classifiers":[
        {
            "category":"Restaurant",
            "type":"Food & Drink"
        }
    ],
    "sg:phone":"+1 503 238 6293",
    "sg:postcode":"97214",
    "sg:province":"OR",
    "wof:name":"At the Hop",
    "wof:placetype":"venue"
},
  "geometry": {"coordinates":[-122.63400300000001,45.512199],"type":"Point"}
}