{
  "type": "Feature",
  "properties": {
    "addr:full":"1223 Lloyd Center Portland OR 97232",
    "addr:housenumber":"1223",
    "addr:postcode":"97232",
    "addr:street":"Lloyd",
    "iso:country":"US",
    "sg:address":"1223 Lloyd Center",
    "sg:city":"Portland",
    "sg:classifiers":[
        {
            "category":"Shopping",
            "subcategory":"Clothing, Apparel, & Fashions",
            "type":"Retail Goods"
        }
    ],
    "sg:phone":"+1 503 282 1863",
    "sg:postcode":"97232",
    "sg:province":"OR",
    "sg:tags":[
        "accessory",
        "clothing",
        "women's"
    ],
    "wof:name":"Torrid",
    "wof:placetype":"venue"
},
  "geometry": {"coordinates":[-122.654437,45.531996],"type":"Point"}
}