{
  "type": "Feature",
  "properties": {
    "iso:country":"US",
    "sg:address":"422 SW Broadway",
    "sg:city":"Portland",
    "sg:classifiers":[
        {
            "category":"Communications",
            "subcategory":"Television Station",
            "type":"Services"
        }
    ],
    "sg:phone":"+1 503 228 1410",
    "sg:postcode":"97205",
    "sg:province":"OR",
    "sg:tags":[
        "satellite",
        "cable"
    ],
    "wof:name":"Lodgenet Entertainment Corp",
    "wof:placetype":"venue"
},
  "geometry": {"coordinates":[-122.678636,45.5212],"type":"Point"}
}