{
  "type": "Feature",
  "properties": {
    "addr:full":"17829 S Wesley Ct Oregon City OR 97045",
    "addr:housenumber":"17829",
    "addr:postcode":"97045",
    "addr:street":"S Wesley Ct",
    "iso:country":"US",
    "sg:address":"17829 S Wesley Ct",
    "sg:city":"Oregon City",
    "sg:classifiers":[
        {
            "category":"Building & Trades",
            "subcategory":"Construction",
            "type":"Services"
        }
    ],
    "sg:phone":"+1 503 631 8924",
    "sg:postcode":"97045",
    "sg:province":"OR",
    "sg:tags":[
        "sheet",
        "contractor"
    ],
    "wof:name":"Alan Smith Construction",
    "wof:placetype":"venue"
},
  "geometry": {"coordinates":[-122.50005400000001,45.344451],"type":"Point"}
}