{
  "type": "Feature",
  "properties": {
    "addr:full":"12725 SW Millikan Way Ste 300 Beaverton OR 97005",
    "addr:housenumber":"12725",
    "addr:postcode":"97005",
    "addr:street":"Sw Millikan Way Ste 300",
    "iso:country":"US",
    "sg:address":"12725 SW Millikan Way Ste 300",
    "sg:city":"Beaverton",
    "sg:classifiers":[
        {
            "category":"Wholesale",
            "subcategory":"Computers",
            "type":"Manufacturing & Wholesale Goods"
        }
    ],
    "sg:phone":"+1 503 906 7910",
    "sg:postcode":"97005",
    "sg:province":"OR",
    "wof:name":"Milestone Systems USA",
    "wof:placetype":"venue"
},
  "geometry": {"coordinates":[-122.807945,45.489843],"type":"Point"}
}