{
  "type": "Feature",
  "properties": {
    "iso:country":"US",
    "sg:address":"9570 SW Barbur Blvd",
    "sg:city":"Portland",
    "sg:classifiers":[
        {
            "category":"Banks & Credit Unions",
            "subcategory":"Investment Brokerage",
            "type":"Services"
        }
    ],
    "sg:phone":"+1 503 293 6344",
    "sg:postcode":"97219",
    "sg:province":"OR",
    "sg:tags":[
        "security",
        "management",
        "consulting"
    ],
    "wof:name":"Securities America Inc",
    "wof:placetype":"venue"
},
  "geometry": {"coordinates":[-122.71418,45.456286],"type":"Point"}
}