{
  "type": "Feature",
  "properties": {
    "iso:country":"US",
    "sg:address":"2241 NW Hoyt St",
    "sg:city":"Portland",
    "sg:classifiers":[
        {
            "category":"Travel",
            "subcategory":"Hotels & Motels",
            "type":"Entertainment"
        }
    ],
    "sg:phone":"+1 503 228 5925",
    "sg:postcode":"97210",
    "sg:province":"OR",
    "sg:tags":[
        "operation"
    ],
    "wof:name":"Room & Board",
    "wof:placetype":"venue"
},
  "geometry": {"coordinates":[-122.697923,45.527028],"type":"Point"}
}