{
  "type": "Feature",
  "properties": {
    "iso:country":"US",
    "sg:address":"2550 SW Hillsboro Hwy",
    "sg:city":"Hillsboro",
    "sg:classifiers":[
        {
            "category":"Utilities",
            "subcategory":"Sewage",
            "type":"Services"
        }
    ],
    "sg:phone":"+1 503 681 3600",
    "sg:postcode":"97123",
    "sg:province":"OR",
    "sg:tags":[
        "system",
        "sewerage"
    ],
    "wof:name":"Clean Water Services",
    "wof:placetype":"venue"
},
  "geometry": {"coordinates":[-122.990874,45.502374],"type":"Point"}
}