{
  "type": "Feature",
  "properties": {
    "iso:country":"US",
    "sg:address":"18515 Webster Rd",
    "sg:city":"Gladstone",
    "sg:classifiers":[
        {
            "category":"Restaurant",
            "type":"Food & Drink"
        }
    ],
    "sg:phone":"+1 503 723 6082",
    "sg:postcode":"97027",
    "sg:province":"OR",
    "sg:tags":[
        "delicatessen"
    ],
    "wof:name":"Happyrock Deli",
    "wof:placetype":"venue"
},
  "geometry": {"coordinates":[-122.584575,45.389403],"type":"Point"}
}