{
  "type": "Feature",
  "properties": {
    "iso:country":"US",
    "sg:address":"107 SW 1st St",
    "sg:city":"Enterprise",
    "sg:classifiers":[
        {
            "category":"Professional",
            "type":"Services"
        }
    ],
    "sg:phone":"+1 541 426 4109",
    "sg:postcode":"97828",
    "sg:province":"OR",
    "sg:tags":[
        "establishment"
    ],
    "wof:name":"Blue Mountain Community",
    "wof:placetype":"venue"
},
  "geometry": {"coordinates":[-117.278865,45.425139],"type":"Point"}
}