{
  "type": "Feature",
  "properties": {
    "iso:country":"US",
    "sg:address":"12675 NW Cornell Rd Ste B",
    "sg:city":"Portland",
    "sg:classifiers":[
        {
            "category":"Professional",
            "subcategory":"Business Services",
            "type":"Services"
        },
        {
            "category":"Government",
            "subcategory":"Post Office",
            "type":"Public Place"
        }
    ],
    "sg:phone":"+1 800 275 8777",
    "sg:postcode":"97229",
    "sg:province":"OR",
    "sg:tags":[
        "mail",
        "shipping"
    ],
    "sg:website":"http://www.usps.com",
    "wof:name":"USPS - United States Post Office - CPU Cedar Mill Cont Branch",
    "wof:placetype":"venue"
},
  "geometry": {"coordinates":[-122.808167,45.52499],"type":"Point"}
}