{
  "type": "Feature",
  "properties": {
    "iso:country":"US",
    "sg:address":"227 SW Pine St Ste 320",
    "sg:city":"Portland",
    "sg:classifiers":[
        {
            "category":"Structure",
            "subcategory":"Office Building",
            "type":"Public Place"
        }
    ],
    "sg:phone":"+1 503 464 4050",
    "sg:postcode":"97204",
    "sg:province":"OR",
    "sg:tags":[
        "park"
    ],
    "wof:name":"Montara",
    "wof:placetype":"venue"
},
  "geometry": {"coordinates":[-122.673029,45.521392],"type":"Point"}
}