{
  "type": "Feature",
  "properties": {
    "iso:country":"US",
    "sg:address":"16581 SE Catlyn Woods Dr",
    "sg:city":"Portland",
    "sg:classifiers":[
        {
            "category":"Travel",
            "subcategory":"Hotels & Motels",
            "type":"Entertainment"
        }
    ],
    "sg:phone":"+1 503 652 7041",
    "sg:postcode":"97267",
    "sg:province":"OR",
    "sg:tags":[
        "membership",
        "lodging"
    ],
    "wof:name":"Friendship Hmes Fmly Cncorcium",
    "wof:placetype":"venue"
},
  "geometry": {"coordinates":[-122.594007,45.402575],"type":"Point"}
}