{
  "type": "Feature",
  "properties": {
    "iso:country":"US",
    "sg:address":"15005 Highway 47",
    "sg:city":"Yamhill",
    "sg:classifiers":[
        {
            "category":"Utilities",
            "subcategory":"Water",
            "type":"Services"
        }
    ],
    "sg:phone":"+1 503 662 3777",
    "sg:postcode":"97148",
    "sg:province":"OR",
    "sg:tags":[
        "company-utility",
        "system",
        "supply"
    ],
    "wof:name":"South Yamhill Water Co",
    "wof:placetype":"venue"
},
  "geometry": {"coordinates":[-123.182906,45.329427],"type":"Point"}
}