{
  "type": "Feature",
  "properties": {
    "iso:country":"US",
    "sg:address":"2154 NE Broadway St # 200",
    "sg:city":"Portland",
    "sg:classifiers":[
        {
            "category":"Industrial Area",
            "type":"Public Place"
        }
    ],
    "sg:phone":"+1 503 284 2147",
    "sg:postcode":"97232",
    "sg:province":"OR",
    "sg:tags":[
        "development"
    ],
    "wof:name":"Wenston-Scherzer Co",
    "wof:placetype":"venue"
},
  "geometry": {"coordinates":[-122.64380800000001,45.535011],"type":"Point"}
}