{
  "type": "Feature",
  "properties": {
    "iso:country":"US",
    "sg:address":"1239 Silver Falls Dr NE",
    "sg:city":"Silverton",
    "sg:classifiers":[
        {
            "category":"Manufacturing",
            "subcategory":"Lumber",
            "type":"Manufacturing & Wholesale Goods"
        }
    ],
    "sg:phone":"+1 503 873 4926",
    "sg:postcode":"97381",
    "sg:province":"OR",
    "sg:tags":[
        "farm",
        "crop",
        "field",
        "tract",
        "operation",
        "timber"
    ],
    "wof:name":"Donald Reinhart",
    "wof:placetype":"venue"
},
  "geometry": {"coordinates":[-122.692437,44.945257],"type":"Point"}
}