{
  "type": "Feature",
  "properties": {
    "iso:country":"US",
    "sg:address":"14149 NE Airport Way",
    "sg:city":"Portland",
    "sg:classifiers":[
        {
            "category":"Farming",
            "subcategory":"Fish & Marine Products",
            "type":"Manufacturing & Wholesale Goods"
        },
        {
            "category":"Manufacturing",
            "subcategory":"Glass & Minerals",
            "type":"Manufacturing & Wholesale Goods"
        }
    ],
    "sg:phone":"+1 503 408 8242",
    "sg:postcode":"97230",
    "sg:province":"OR",
    "sg:tags":[
        "fiberglass",
        "material"
    ],
    "wof:name":"North American Composites",
    "wof:placetype":"venue"
},
  "geometry": {"coordinates":[-122.518461,45.561733],"type":"Point"}
}