{
  "type": "Feature",
  "properties": {
    "addr:full":"3026 NE 33rd Ave Portland OR 97212",
    "addr:housenumber":"3026",
    "addr:postcode":"97212",
    "addr:street":"Ne 33Rd Ave",
    "iso:country":"US",
    "sg:address":"3026 NE 33rd Ave",
    "sg:city":"Portland",
    "sg:classifiers":[
        {
            "category":"Professional",
            "subcategory":"Management & Consulting",
            "type":"Services"
        }
    ],
    "sg:phone":"+1 925 939 3390",
    "sg:postcode":"97212",
    "sg:province":"OR",
    "wof:name":"Risk Control Consulting Svcs",
    "wof:placetype":"venue"
},
  "geometry": {"coordinates":[-122.630612,45.545125],"type":"Point"}
}