{
  "type": "Feature",
  "properties": {
    "iso:country":"US",
    "sg:address":"15108 S Thayer Rd",
    "sg:city":"Oregon City",
    "sg:classifiers":[
        {
            "category":"Professional",
            "subcategory":"Business Services",
            "type":"Services"
        }
    ],
    "sg:phone":"+1 503 655 1307",
    "sg:postcode":"97045",
    "sg:province":"OR",
    "wof:name":"Grand Tree Ltd Partnership",
    "wof:placetype":"venue"
},
  "geometry": {"coordinates":[-122.555604,45.331324],"type":"Point"}
}