{
  "type": "Feature",
  "properties": {
    "addr:full":"2349 NW 22nd Ave Portland OR 97210",
    "addr:housenumber":"2349",
    "addr:postcode":"97210",
    "addr:street":"Nw 22Nd Ave",
    "iso:country":"US",
    "sg:address":"2349 NW 22nd Ave",
    "sg:city":"Portland",
    "sg:classifiers":[
        {
            "category":"Retail",
            "subcategory":"Car Wash",
            "type":"Services"
        }
    ],
    "sg:phone":"+1 503 525 2273",
    "sg:postcode":"97210",
    "sg:province":"OR",
    "sg:tags":[
        "carwash"
    ],
    "wof:name":"Care Wash International",
    "wof:placetype":"venue"
},
  "geometry": {"coordinates":[-122.697002,45.539125],"type":"Point"}
}