{
  "type": "Feature",
  "properties": {
    "iso:country":"US",
    "sg:address":"25 NW 23rd Pl",
    "sg:city":"Portland",
    "sg:classifiers":[
        {
            "category":"Professional",
            "subcategory":"Accounting & Tax Preparation",
            "type":"Services"
        }
    ],
    "sg:phone":"+1 503 221 7955",
    "sg:postcode":"97210",
    "sg:province":"OR",
    "sg:tags":[
        "bookkeeping",
        "general"
    ],
    "wof:name":"Portland Bookkeeping Svc",
    "wof:placetype":"venue"
},
  "geometry": {"coordinates":[-122.699971,45.523851],"type":"Point"}
}