{
  "type": "Feature",
  "properties": {
    "addr:full":"888 SW 5th Ave Ste 1440 Portland OR 97204",
    "addr:housenumber":"888",
    "addr:postcode":"97204",
    "addr:street":"Sw 5Th Ave Ste 1440",
    "iso:country":"US",
    "sg:address":"888 SW 5th Ave Ste 1440",
    "sg:city":"Portland",
    "sg:classifiers":[
        {
            "category":"Professional",
            "subcategory":"Employment Agencies",
            "type":"Services"
        }
    ],
    "sg:phone":"+1 503 227 1440",
    "sg:postcode":"97204",
    "sg:province":"OR",
    "sg:tags":[
        "opportunity"
    ],
    "wof:name":"Sfn Professional Services",
    "wof:placetype":"venue"
},
  "geometry": {"coordinates":[-122.678252,45.517529],"type":"Point"}
}