{
  "type": "Feature",
  "properties": {
    "addr:full":"1415 NW Murphy Ct Prineville OR 97754",
    "addr:housenumber":"1415",
    "addr:postcode":"97754",
    "addr:street":"Nw Murphy Ct",
    "iso:country":"US",
    "sg:address":"1415 NW Murphy Ct",
    "sg:city":"Prineville",
    "sg:classifiers":[
        {
            "category":"Building & Trades",
            "subcategory":"Construction",
            "type":"Services"
        }
    ],
    "sg:phone":"+1 541 279 0386",
    "sg:postcode":"97754",
    "sg:province":"OR",
    "sg:tags":[
        "paving",
        "road",
        "contractor"
    ],
    "wof:name":"Northwest Sign Recycling",
    "wof:placetype":"venue"
},
  "geometry": {"coordinates":[-120.86668,44.315932],"type":"Point"}
}