{
  "type": "Feature",
  "properties": {
    "addr:full":"4570 Commercial St SE Salem OR 97302",
    "addr:housenumber":"4570",
    "addr:postcode":"97302",
    "addr:street":"Commercial St Se",
    "iso:country":"US",
    "sg:address":"4570 Commercial St SE",
    "sg:city":"Salem",
    "sg:classifiers":[
        {
            "category":"Utilities",
            "subcategory":"Telephone",
            "type":"Services"
        },
        {
            "category":"Shopping",
            "subcategory":"Mobile Phones",
            "type":"Retail Goods"
        },
        {
            "category":"Manufacturing",
            "subcategory":"Electronics",
            "type":"Manufacturing & Wholesale Goods"
        },
        {
            "category":"Shopping",
            "subcategory":"Computers & Home Electronics",
            "type":"Retail Goods"
        },
        {
            "category":"Communications",
            "type":"Services"
        }
    ],
    "sg:phone":"+1 503 363 1079",
    "sg:postcode":"97302",
    "sg:province":"OR",
    "sg:tags":[
        "sound",
        "television",
        "theater",
        "supply",
        "system",
        "equipment",
        "radio",
        "cellular",
        "telecommunications-equipment",
        "consumer",
        "store"
    ],
    "sg:website":"http://www.radioshack.com",
    "wof:name":"RadioShack",
    "wof:placetype":"venue"
},
  "geometry": {"coordinates":[-123.033316,44.887614],"type":"Point"}
}