{
  "type": "Feature",
  "properties": {
    "addr:full":"18221 SE Pine St Portland OR 97233",
    "addr:postcode":"18221;97233",
    "addr:street":"Se Pine St",
    "iso:country":"US",
    "sg:address":"18221 SE Pine St",
    "sg:city":"Portland",
    "sg:classifiers":[
        {
            "category":"Manufacturing",
            "subcategory":"Tools & Machinery",
            "type":"Manufacturing & Wholesale Goods"
        }
    ],
    "sg:phone":"+1 503 666 2982",
    "sg:postcode":"97233",
    "sg:province":"OR",
    "sg:tags":[
        "measuring",
        "instrument",
        "electrical",
        "mfg"
    ],
    "wof:name":"Foton Precision",
    "wof:placetype":"venue"
},
  "geometry": {"coordinates":[-122.47309,45.520615],"type":"Point"}
}