{
  "type": "Feature",
  "properties": {
    "iso:country":"US",
    "sg:address":"171 W Main St",
    "sg:city":"Long Creek",
    "sg:classifiers":[
        {
            "category":"Travel",
            "subcategory":"Hotels & Motels",
            "type":"Entertainment"
        }
    ],
    "sg:phone":"+1 541 421 9212",
    "sg:postcode":"97856",
    "sg:province":"OR",
    "wof:name":"Long Creek Lodge",
    "wof:placetype":"venue"
},
  "geometry": {"coordinates":[-119.10473,44.713678],"type":"Point"}
}