{
  "type": "Feature",
  "properties": {
    "iso:country":"US",
    "sg:address":"24146 Old Peak Rd",
    "sg:city":"Philomath",
    "sg:classifiers":[
        {
            "category":"Professional",
            "subcategory":"Management & Consulting",
            "type":"Services"
        }
    ],
    "sg:phone":"+1 541 929 4240",
    "sg:postcode":"97370",
    "sg:province":"OR",
    "sg:tags":[
        "business"
    ],
    "wof:name":"Jesse Ford",
    "wof:placetype":"venue"
},
  "geometry": {"coordinates":[-123.419578,44.544861],"type":"Point"}
}