{
  "type": "Feature",
  "properties": {
    "iso:country":"US",
    "sg:address":"1020 Wasco Ave",
    "sg:city":"Hood River",
    "sg:classifiers":[
        {
            "category":"Professional",
            "subcategory":"Research",
            "type":"Services"
        },
        {
            "category":"Professional",
            "subcategory":"Management & Consulting",
            "type":"Services"
        }
    ],
    "sg:phone":"+1 541 386 9003",
    "sg:postcode":"97031",
    "sg:province":"OR",
    "sg:tags":[
        "environmental",
        "ecological",
        "business"
    ],
    "wof:name":"Inter-Fluve Inc",
    "wof:placetype":"venue"
},
  "geometry": {"coordinates":[-121.520832,45.711515],"type":"Point"}
}