{
  "type": "Feature",
  "properties": {
    "iso:country":"US",
    "sg:address":"13851 SE Tiara Dr",
    "sg:city":"Portland",
    "sg:classifiers":[
        {
            "category":"Professional",
            "subcategory":"Secretarial Services",
            "type":"Services"
        }
    ],
    "sg:phone":"+1 503 786 4972",
    "sg:postcode":"97267",
    "sg:province":"OR",
    "sg:tags":[
        "reporting"
    ],
    "wof:name":"Nancy Stewart",
    "wof:placetype":"venue"
},
  "geometry": {"coordinates":[-122.586978,45.422991],"type":"Point"}
}