{
  "type": "Feature",
  "properties": {
    "iso:country":"US",
    "sg:address":"1709 W Island Rd",
    "sg:city":"Ontario",
    "sg:classifiers":[
        {
            "category":"Farming",
            "subcategory":"Farm",
            "type":"Manufacturing & Wholesale Goods"
        }
    ],
    "sg:phone":"+1 541 889 8278",
    "sg:postcode":"97914",
    "sg:province":"OR",
    "sg:tags":[
        "crop",
        "general"
    ],
    "wof:name":"William J Duyn",
    "wof:placetype":"venue"
},
  "geometry": {"coordinates":[-116.989554,44.003168],"type":"Point"}
}