{
  "type": "Feature",
  "properties": {
    "addr:full":"51813 Columbia River Hwy Scappoose OR 97056",
    "addr:housenumber":"51813",
    "addr:postcode":"97056",
    "addr:street":"Columbia River Hwy",
    "iso:country":"US",
    "sg:address":"51813 Columbia River Hwy",
    "sg:city":"Scappoose",
    "sg:classifiers":[
        {
            "category":"Autos & Motor Vehicles",
            "subcategory":"Auto Supplies",
            "type":"Retail Goods"
        }
    ],
    "sg:phone":"+1 503 543 6318",
    "sg:postcode":"97056",
    "sg:province":"OR",
    "sg:tags":[
        "automobile",
        "part"
    ],
    "sg:website":"http://www.napaonline.com",
    "wof:name":"Napa Auto Parts",
    "wof:placetype":"venue"
},
  "geometry": {"coordinates":[-122.87724,45.748158],"type":"Point"}
}