{
  "type": "Feature",
  "properties": {
    "iso:country":"US",
    "sg:address":"70887 Fern Hill Rd",
    "sg:city":"Rainier",
    "sg:classifiers":[
        {
            "category":"Retail",
            "subcategory":"Animal Services",
            "type":"Services"
        }
    ],
    "sg:phone":"+1 503 556 2946",
    "sg:postcode":"97048",
    "sg:province":"OR",
    "sg:tags":[
        "operator",
        "trucking"
    ],
    "wof:name":"Colorspot",
    "wof:placetype":"venue"
},
  "geometry": {"coordinates":[-123.013009,46.022766],"type":"Point"}
}