{
  "type": "Feature",
  "properties": {
    "iso:country":"US",
    "sg:address":"1854 NE Hwy 99W",
    "sg:city":"Mcminnville",
    "sg:classifiers":[
        {
            "category":"Retail",
            "subcategory":"Auto Repair",
            "type":"Services"
        }
    ],
    "sg:phone":"+1 503 435 0379",
    "sg:postcode":"97128",
    "sg:province":"OR",
    "sg:tags":[
        "automobile",
        "lubrication",
        "automotive"
    ],
    "wof:name":"Jiffy Lube",
    "wof:placetype":"venue"
},
  "geometry": {"coordinates":[-123.17706099999999,45.22759],"type":"Point"}
}