{
  "type": "Feature",
  "properties": {
    "iso:country":"US",
    "sg:address":"2809 NE 58th Ave",
    "sg:city":"Portland",
    "sg:classifiers":[
        {
            "category":"Building & Trades",
            "subcategory":"Construction",
            "type":"Services"
        }
    ],
    "sg:phone":"+1 503 778 5158",
    "sg:postcode":"97213",
    "sg:province":"OR",
    "sg:tags":[
        "house"
    ],
    "wof:name":"Tzur Enterprises",
    "wof:placetype":"venue"
},
  "geometry": {"coordinates":[-122.603605,45.543609],"type":"Point"}
}