{
  "type": "Feature",
  "properties": {
    "iso:country":"US",
    "sg:address":"7900 NE 82nd Ave",
    "sg:city":"Portland",
    "sg:phone":"+1 503 460 3000",
    "sg:postcode":"97220",
    "sg:province":"OR",
    "wof:name":"Embassy Suites-Downtown",
    "wof:placetype":"venue"
},
  "geometry": {"coordinates":[-122.573328,45.580006],"type":"Point"}
}