{
  "type": "Feature",
  "properties": {
    "iso:country":"US",
    "sg:address":"1712 E Mcandrews Rd",
    "sg:city":"Medford",
    "sg:classifiers":[
        {
            "category":"Health Services",
            "subcategory":"Nursing And Care Facility",
            "type":"Services"
        },
        {
            "category":"Health Services",
            "subcategory":"Health Practitioner",
            "type":"Services"
        },
        {
            "category":"Health Services",
            "subcategory":"Chiropractor",
            "type":"Services"
        }
    ],
    "sg:phone":"+1 541 772 5000",
    "sg:postcode":"97504",
    "sg:province":"OR",
    "sg:tags":[
        "therapist",
        "management",
        "pain",
        "physical",
        "chiropractic"
    ],
    "sg:website":"http://www.drmarkmarfarland.com",
    "wof:name":"McFarland Chiropractic",
    "wof:placetype":"venue"
},
  "geometry": {"coordinates":[-122.860668,42.341053],"type":"Point"}
}