{
  "type": "Feature",
  "properties": {
    "iso:country":"US",
    "sg:address":"19450 NW Cornell Rd",
    "sg:city":"Hillsboro",
    "sg:classifiers":[
        {
            "category":"Shopping",
            "subcategory":"Musical Instruments",
            "type":"Retail Goods"
        }
    ],
    "sg:phone":"+1 503 439 9500",
    "sg:postcode":"97124",
    "sg:province":"OR",
    "sg:website":"www.fivestarguitars.com",
    "wof:name":"Five Star Guitars",
    "wof:placetype":"venue"
},
  "geometry": {"coordinates":[-122.87769,45.534564],"type":"Point"}
}