{
  "type": "Feature",
  "properties": {
    "iso:country":"US",
    "sg:address":"3116 S Hemlock St",
    "sg:city":"Cannon Beach",
    "sg:classifiers":[
        {
            "category":"Coffee & Tea",
            "type":"Food & Drink"
        },
        {
            "category":"Restaurant",
            "type":"Food & Drink"
        },
        {
            "category":"Bakery",
            "type":"Food & Drink"
        }
    ],
    "sg:phone":"+1 503 436 9600",
    "sg:postcode":"97145",
    "sg:province":"OR",
    "sg:tags":[
        "brunch",
        "breakfast"
    ],
    "sg:website":"www.wavesofgrainbakery.com/",
    "wof:name":"Waves of Grain Bakery",
    "wof:placetype":"venue"
},
  "geometry": {"coordinates":[-123.95991100000001,45.873137],"type":"Point"}
}