{
  "type": "Feature",
  "properties": {
    "iso:country":"US",
    "sg:address":"2010 W Burnside St",
    "sg:city":"Portland",
    "sg:classifiers":[
        {
            "category":"Autos & Motor Vehicles",
            "subcategory":"Automobile Sales",
            "type":"Retail Goods"
        }
    ],
    "sg:phone":"+1 503 230 8000",
    "sg:postcode":"97209",
    "sg:province":"OR",
    "wof:name":"Rose City Auto & Truck Broker",
    "wof:placetype":"venue"
},
  "geometry": {"coordinates":[-122.693136,45.523076],"type":"Point"}
}