{
  "type": "Feature",
  "properties": {
    "iso:country":"US",
    "sg:address":"5141 SW Beaverton Hillsdale Hwy",
    "sg:city":"Portland",
    "sg:classifiers":[
        {
            "category":"Professional",
            "subcategory":"Employment Agencies",
            "type":"Services"
        }
    ],
    "sg:phone":"+1 503 244 5252",
    "sg:postcode":"97221",
    "sg:province":"OR",
    "sg:tags":[
        "resume"
    ],
    "wof:name":"Career Resume Svc",
    "wof:placetype":"venue"
},
  "geometry": {"coordinates":[-122.728667,45.487061],"type":"Point"}
}