{
  "type": "Feature",
  "properties": {
    "addr:full":"12005 N Burgard Way Portland OR 97203",
    "addr:housenumber":"12005",
    "addr:postcode":"97203",
    "addr:street":"N Burgard Way",
    "iso:country":"US",
    "sg:address":"12005 N Burgard Way",
    "sg:city":"Portland",
    "sg:classifiers":[
        {
            "category":"Building & Trades",
            "subcategory":"Construction",
            "type":"Services"
        }
    ],
    "sg:phone":"+1 503 285 0100",
    "sg:postcode":"97203",
    "sg:province":"OR",
    "sg:tags":[
        "wallcoverings-installation",
        "wallpaper",
        "painting",
        "contractor"
    ],
    "wof:name":"Dunkin & Bush, Inc.",
    "wof:placetype":"venue"
},
  "geometry": {"coordinates":[-122.767464,45.608391],"type":"Point"}
}