{
  "type": "Feature",
  "properties": {
    "iso:country":"US",
    "sg:address":"4109 S Hwy 97",
    "sg:city":"Redmond",
    "sg:classifiers":[
        {
            "category":"Professional",
            "type":"Services"
        }
    ],
    "sg:phone":"+1 541 923 7661",
    "sg:postcode":"97756",
    "sg:province":"OR",
    "sg:tags":[
        "establishment"
    ],
    "wof:name":"Greens At Redmond",
    "wof:placetype":"venue"
},
  "geometry": {"coordinates":[-121.196048,44.239421],"type":"Point"}
}