{
  "type": "Feature",
  "properties": {
    "iso:country":"US",
    "sg:address":"126 W Main St",
    "sg:city":"Medford",
    "sg:classifiers":[
        {
            "category":"Shopping",
            "subcategory":"Used Merchandise",
            "type":"Retail Goods"
        }
    ],
    "sg:phone":"+1 541 772 3228",
    "sg:postcode":"97501",
    "sg:province":"OR",
    "sg:tags":[
        "antique"
    ],
    "wof:name":"Memories Antiques",
    "wof:placetype":"venue"
},
  "geometry": {"coordinates":[-122.87499200000001,42.325243],"type":"Point"}
}