{
  "type": "Feature",
  "properties": {
    "iso:country":"US",
    "sg:address":"5063 SW Helmholtz Way",
    "sg:city":"Redmond",
    "sg:classifiers":[
        {
            "category":"Building & Trades",
            "subcategory":"Landscaping Services",
            "type":"Services"
        }
    ],
    "sg:phone":"+1 541 548 7512",
    "sg:postcode":"97756",
    "sg:province":"OR",
    "sg:tags":[
        "tree"
    ],
    "wof:name":"Ml Sheets Construction",
    "wof:placetype":"venue"
},
  "geometry": {"coordinates":[-121.22966,44.22978],"type":"Point"}
}