{
  "type": "Feature",
  "properties": {
    "addr:full":"333 SW 5th Ave Portland OR 97204",
    "addr:housenumber":"333",
    "addr:postcode":"97204",
    "addr:street":"Sw 5Th Ave",
    "iso:country":"US",
    "sg:address":"333 SW 5th Ave",
    "sg:city":"Portland",
    "sg:classifiers":[
        {
            "category":"Professional",
            "subcategory":"Research",
            "type":"Services"
        }
    ],
    "sg:phone":"+1 503 226 9004",
    "sg:postcode":"97204",
    "sg:province":"OR",
    "sg:tags":[
        "market"
    ],
    "wof:name":"ABC",
    "wof:placetype":"venue"
},
  "geometry": {"coordinates":[-122.676483,45.521046],"type":"Point"}
}