{
  "type": "Feature",
  "properties": {
    "addr:full":"3639 Arabian Dr Ontario OR 97914",
    "addr:housenumber":"3639",
    "addr:postcode":"97914",
    "addr:street":"Arabian Dr",
    "iso:country":"US",
    "sg:address":"3639 Arabian Dr",
    "sg:city":"Ontario",
    "sg:classifiers":[
        {
            "category":"Farming",
            "subcategory":"Livestock Farm",
            "type":"Manufacturing & Wholesale Goods"
        }
    ],
    "sg:phone":"+1 541 889 6073",
    "sg:postcode":"97914",
    "sg:province":"OR",
    "sg:tags":[
        "beef",
        "feedlot",
        "cattle"
    ],
    "wof:name":"Lawrence Winebarger",
    "wof:placetype":"venue"
},
  "geometry": {"coordinates":[-117.10587,43.957533],"type":"Point"}
}