{
  "type": "Feature",
  "properties": {
    "addr:full":"5074 Skyline Village Loop S Salem OR 97306",
    "addr:housenumber":"5074",
    "addr:postcode":"97306",
    "addr:street":"Skyline Village Loop",
    "iso:country":"US",
    "sg:address":"5074 Skyline Village Loop S",
    "sg:city":"Salem",
    "sg:classifiers":[
        {
            "category":"Professional",
            "type":"Services"
        }
    ],
    "sg:phone":"+1 503 362 0604",
    "sg:postcode":"97306",
    "sg:province":"OR",
    "wof:name":"Oregon Crohns & Colitis Suppo",
    "wof:placetype":"venue"
},
  "geometry": {"coordinates":[-123.07015199999999,44.881429],"type":"Point"}
}