{
  "type": "Feature",
  "properties": {
    "addr:full":"2240 S Church St Dallas OR 97338",
    "addr:housenumber":"2240",
    "addr:postcode":"97338",
    "addr:street":"S Church St",
    "iso:country":"US",
    "sg:address":"2240 S Church St",
    "sg:city":"Dallas",
    "sg:classifiers":[
        {
            "category":"Manufacturing",
            "subcategory":"Building Materials",
            "type":"Manufacturing & Wholesale Goods"
        }
    ],
    "sg:phone":"+1 503 623 5907",
    "sg:postcode":"97338",
    "sg:province":"OR",
    "sg:tags":[
        "mfg",
        "wood",
        "kitchen",
        "cabinet"
    ],
    "wof:name":"Mark Hall Cabinets",
    "wof:placetype":"venue"
},
  "geometry": {"coordinates":[-123.318681,44.903075],"type":"Point"}
}