{
  "type": "Feature",
  "properties": {
    "iso:country":"US",
    "sg:address":"729 NE 14th St",
    "sg:city":"Mcminnville",
    "sg:classifiers":[
        {
            "category":"Professional",
            "subcategory":"Business Services",
            "type":"Services"
        }
    ],
    "sg:phone":"+1 503 560 7700",
    "sg:postcode":"97128",
    "sg:province":"OR",
    "sg:tags":[
        "consultant",
        "coach"
    ],
    "wof:name":"Jeff Mcmurtry Technical Consulting",
    "wof:placetype":"venue"
},
  "geometry": {"coordinates":[-123.19142600000001,45.217878],"type":"Point"}
}