{
  "type": "Feature",
  "properties": {
    "iso:country":"US",
    "sg:address":"118 NW Greenwood Ave",
    "sg:city":"Bend",
    "sg:classifiers":[
        {
            "category":"Personal",
            "subcategory":"Beauty Salon",
            "type":"Services"
        },
        {
            "category":"Personal",
            "subcategory":"Barber",
            "type":"Services"
        }
    ],
    "sg:phone":"+1 541 388 4090",
    "sg:postcode":"97701",
    "sg:province":"OR",
    "sg:tags":[
        "hair",
        "stylist"
    ],
    "wof:name":"Planet Hair",
    "wof:placetype":"venue"
},
  "geometry": {"coordinates":[-121.30907500000001,44.059952],"type":"Point"}
}