{
  "type": "Feature",
  "properties": {
    "addr:full":"27322 Rowell Hill Rd Sweet Home OR 97386",
    "addr:postcode":"27322;97386",
    "addr:street":"Rowell Hill Rd",
    "iso:country":"US",
    "sg:address":"27322 Rowell Hill Rd",
    "sg:city":"Sweet Home",
    "sg:classifiers":[
        {
            "category":"Wholesale",
            "subcategory":"Machinery & Supplies",
            "type":"Manufacturing & Wholesale Goods"
        }
    ],
    "sg:phone":"+1 541 367 4307",
    "sg:postcode":"97386",
    "sg:province":"OR",
    "sg:tags":[
        "construction",
        "general"
    ],
    "wof:name":"Keith Wooley General Cnstr",
    "wof:placetype":"venue"
},
  "geometry": {"coordinates":[-122.751681,44.393878],"type":"Point"}
}