{
  "type": "Feature",
  "properties": {
    "iso:country":"US",
    "sg:address":"2127 Linnell Ave",
    "sg:city":"Roseburg",
    "sg:classifiers":[
        {
            "category":"Building & Trades",
            "subcategory":"Construction",
            "type":"Services"
        }
    ],
    "sg:phone":"+1 541 784 3696",
    "sg:postcode":"97470",
    "sg:province":"OR",
    "sg:tags":[
        "residential",
        "commercial"
    ],
    "wof:name":"Lane Builders",
    "wof:placetype":"venue"
},
  "geometry": {"coordinates":[-123.387806,43.148038],"type":"Point"}
}