{
  "type": "Feature",
  "properties": {
    "addr:full":"13939 N Rivergate Blvd Portland OR 97203",
    "addr:housenumber":"13939",
    "addr:postcode":"97203",
    "addr:street":"N Rivergate Blvd",
    "iso:country":"US",
    "sg:address":"13939 N Rivergate Blvd",
    "sg:city":"Portland",
    "sg:classifiers":[
        {
            "category":"Home & Garden",
            "subcategory":"Building Materials",
            "type":"Retail Goods"
        },
        {
            "category":"Manufacturing",
            "subcategory":"Building Materials",
            "type":"Manufacturing & Wholesale Goods"
        }
    ],
    "sg:phone":"+1 503 286 1677",
    "sg:postcode":"97203",
    "sg:province":"OR",
    "sg:tags":[
        "cement",
        "concrete",
        "shape",
        "cement-wholesale",
        "block",
        "manufacturer"
    ],
    "sg:website":"http://www.ashgrove.com",
    "wof:name":"Ash Grove Cement Company",
    "wof:placetype":"venue"
},
  "geometry": {"coordinates":[-122.780123,45.622731],"type":"Point"}
}