{
  "type": "Feature",
  "properties": {
    "iso:country":"US",
    "sg:address":"2769 SW Reindeer Ct",
    "sg:city":"Redmond",
    "sg:classifiers":[
        {
            "category":"Building & Trades",
            "subcategory":"Construction",
            "type":"Services"
        }
    ],
    "sg:phone":"+1 541 504 8952",
    "sg:postcode":"97756",
    "sg:province":"OR",
    "sg:tags":[
        "house"
    ],
    "wof:name":"Sibila Construction",
    "wof:placetype":"venue"
},
  "geometry": {"coordinates":[-121.200791,44.255707],"type":"Point"}
}