{
  "type": "Feature",
  "properties": {
    "addr:full":"63098 Riverstone Dr Bend OR 97701",
    "addr:housenumber":"63098",
    "addr:postcode":"97701",
    "addr:street":"Riverstone Dr",
    "iso:country":"US",
    "sg:address":"63098 Riverstone Dr",
    "sg:city":"Bend",
    "sg:classifiers":[
        {
            "category":"Professional",
            "subcategory":"Business Services",
            "type":"Services"
        }
    ],
    "sg:phone":"+1 541 385 7203",
    "sg:postcode":"97701",
    "sg:province":"OR",
    "sg:tags":[
        "consultant",
        "coach"
    ],
    "wof:name":"Steven B. Consulting",
    "wof:placetype":"venue"
},
  "geometry": {"coordinates":[-121.314339,44.091244],"type":"Point"}
}