{
  "type": "Feature",
  "properties": {
    "addr:full":"2235 NE 26th Ave Portland OR 97212",
    "addr:housenumber":"2235",
    "addr:postcode":"97212",
    "addr:street":"Ne 26Th Ave",
    "iso:country":"US",
    "sg:address":"2235 NE 26th Ave",
    "sg:city":"Portland",
    "sg:classifiers":[
        {
            "category":"Shopping",
            "subcategory":"Florist",
            "type":"Retail Goods"
        }
    ],
    "sg:phone":"+1 503 284 2683",
    "sg:postcode":"97212",
    "sg:province":"OR",
    "wof:name":"Flowers By Garden Angels",
    "wof:placetype":"venue"
},
  "geometry": {"coordinates":[-122.63919,45.537913],"type":"Point"}
}