{
  "type": "Feature",
  "properties": {
    "addr:full":"248 SW Wood St Hillsboro OR 97123",
    "addr:housenumber":"248",
    "addr:postcode":"97123",
    "addr:street":"Sw Wood St",
    "iso:country":"US",
    "sg:address":"248 SW Wood St",
    "sg:city":"Hillsboro",
    "sg:classifiers":[
        {
            "category":"Retail",
            "subcategory":"Auto Repair",
            "type":"Services"
        }
    ],
    "sg:phone":"+1 503 648 9346",
    "sg:postcode":"97123",
    "sg:province":"OR",
    "sg:tags":[
        "shop",
        "automotive",
        "general"
    ],
    "wof:name":"European Werks",
    "wof:placetype":"venue"
},
  "geometry": {"coordinates":[-122.991908,45.512736],"type":"Point"}
}