{
  "type": "Feature",
  "properties": {
    "addr:full":"5093 Leif Erickson Dr Astoria OR 97103",
    "addr:housenumber":"5093",
    "addr:postcode":"97103",
    "addr:street":"Leif Erickson Dr",
    "iso:country":"US",
    "sg:address":"5093 Leif Erickson Dr",
    "sg:city":"Astoria",
    "sg:classifiers":[
        {
            "category":"Building & Trades",
            "subcategory":"Construction",
            "type":"Services"
        }
    ],
    "sg:phone":"+1 503 325 5888",
    "sg:postcode":"97103",
    "sg:province":"OR",
    "sg:tags":[
        "residential",
        "remodel",
        "contractor"
    ],
    "wof:name":"Cecil Dundas Construction",
    "wof:placetype":"venue"
},
  "geometry": {"coordinates":[-123.77693499999999,46.194742],"type":"Point"}
}