{
  "type": "Feature",
  "properties": {
    "addr:full":"2717 Stark St Eugene OR 97404",
    "addr:housenumber":"2717",
    "addr:postcode":"97404",
    "addr:street":"Stark St",
    "iso:country":"US",
    "sg:address":"2717 Stark St",
    "sg:city":"Eugene",
    "sg:classifiers":[
        {
            "category":"Professional",
            "subcategory":"Management & Consulting",
            "type":"Services"
        }
    ],
    "sg:phone":"+1 541 461 1278",
    "sg:postcode":"97404",
    "sg:province":"OR",
    "sg:tags":[
        "sales",
        "retail",
        "direct",
        "contractor"
    ],
    "wof:name":"True Light Metalworks",
    "wof:placetype":"venue"
},
  "geometry": {"coordinates":[-123.146697,44.104151],"type":"Point"}
}