{
  "type": "Feature",
  "properties": {
    "iso:country":"US",
    "sg:address":"24900 SE Stark St Ste 208",
    "sg:city":"Gresham",
    "sg:classifiers":[
        {
            "category":"Health Services",
            "subcategory":"Doctor",
            "type":"Services"
        }
    ],
    "sg:phone":"+1 503 661 4526",
    "sg:postcode":"97030",
    "sg:province":"OR",
    "sg:tags":[
        "physician",
        "surgeon"
    ],
    "wof:name":"Mt Hood General & Vascular Surgeons",
    "wof:placetype":"venue"
},
  "geometry": {"coordinates":[-122.40799699999999,45.518902],"type":"Point"}
}