{
  "type": "Feature",
  "properties": {
    "addr:full":"375 Portland Ave Gladstone OR 97027",
    "addr:housenumber":"375",
    "addr:postcode":"97027",
    "addr:street":"Portland Ave",
    "iso:country":"US",
    "sg:address":"375 Portland Ave",
    "sg:city":"Gladstone",
    "sg:classifiers":[
        {
            "category":"Real Estate",
            "subcategory":"Surveying",
            "type":"Services"
        }
    ],
    "sg:phone":"+1 503 656 9440",
    "sg:postcode":"97027",
    "sg:province":"OR",
    "sg:tags":[
        "surveyor"
    ],
    "wof:name":"Associated Land Surveyors",
    "wof:placetype":"venue"
},
  "geometry": {"coordinates":[-122.593842,45.379171],"type":"Point"}
}