{
  "type": "Feature",
  "properties": {
    "iso:country":"US",
    "sg:address":"501 Lancaster Dr NE",
    "sg:city":"Salem",
    "sg:classifiers":[
        {
            "category":"Bars & Pubs",
            "type":"Food & Drink"
        }
    ],
    "sg:phone":"+1 503 363 2395",
    "sg:postcode":"97301",
    "sg:province":"OR",
    "sg:tags":[
        "drinking"
    ],
    "wof:name":"Free-Loader",
    "wof:placetype":"venue"
},
  "geometry": {"coordinates":[-122.98300999999999,44.938676],"type":"Point"}
}