{
  "type": "Feature",
  "properties": {
    "addr:full":"1040 SW Westwood Ct Portland OR 97239",
    "addr:housenumber":"1040",
    "addr:postcode":"97239",
    "addr:street":"Sw Westwood Ct",
    "iso:country":"US",
    "sg:address":"1040 SW Westwood Ct",
    "sg:city":"Portland",
    "sg:classifiers":[
        {
            "category":"Real Estate",
            "subcategory":"Real Estate Agent",
            "type":"Services"
        }
    ],
    "sg:phone":"+1 503 246 5066",
    "sg:postcode":"97239",
    "sg:province":"OR",
    "wof:name":"Homarketing USA-21/2 Percent",
    "wof:placetype":"venue"
},
  "geometry": {"coordinates":[-122.691418,45.483312],"type":"Point"}
}