{
  "type": "Feature",
  "properties": {
    "addr:full":"17225 NW Corridor Ct Beaverton OR 97006",
    "addr:housenumber":"17225",
    "addr:postcode":"97006",
    "addr:street":"Nw Corridor Ct",
    "iso:country":"US",
    "sg:address":"17225 NW Corridor Ct",
    "sg:city":"Beaverton",
    "sg:classifiers":[
        {
            "category":"Social Services",
            "subcategory":"Child Care",
            "type":"Services"
        }
    ],
    "sg:phone":"+1 503 629 9726",
    "sg:postcode":"97006",
    "sg:province":"OR",
    "sg:tags":[
        "elementary",
        "school"
    ],
    "wof:name":"Children's World Learning Centers",
    "wof:placetype":"venue"
},
  "geometry": {"coordinates":[-122.853996,45.5354],"type":"Point"}
}