{
  "type": "Feature",
  "properties": {
    "iso:country":"US",
    "sg:address":"320 Market St",
    "sg:city":"Lebanon",
    "sg:classifiers":[
        {
            "category":"Education",
            "subcategory":"College",
            "type":"Public Place"
        }
    ],
    "sg:phone":"+1 541 258 2003",
    "sg:postcode":"97355",
    "sg:province":"OR",
    "sg:tags":[
        "academic",
        "school"
    ],
    "wof:name":"Lebanon Jobs Program",
    "wof:placetype":"venue"
},
  "geometry": {"coordinates":[-122.907106,44.51825],"type":"Point"}
}