{
  "type": "Feature",
  "properties": {
    "addr:full":"1252 Alameda Dr Ontario OR 97914",
    "addr:housenumber":"1252",
    "addr:postcode":"97914",
    "addr:street":"Alameda Dr",
    "iso:country":"US",
    "sg:address":"1252 Alameda Dr",
    "sg:city":"Ontario",
    "sg:classifiers":[
        {
            "category":"Education",
            "subcategory":"School",
            "type":"Public Place"
        }
    ],
    "sg:phone":"+1 541 889 5497",
    "sg:postcode":"97914",
    "sg:province":"OR",
    "wof:name":"Alameda Elementary School",
    "wof:placetype":"venue"
},
  "geometry": {"coordinates":[-116.983064,44.017571],"type":"Point"}
}