{
  "type": "Feature",
  "properties": {
    "addr:full":"915 NE 7th St Bend OR 97701",
    "addr:housenumber":"915",
    "addr:postcode":"97701",
    "addr:street":"Ne 7Th St",
    "iso:country":"US",
    "sg:address":"915 NE 7th St",
    "sg:city":"Bend",
    "sg:classifiers":[
        {
            "category":"Building & Trades",
            "subcategory":"Construction",
            "type":"Services"
        }
    ],
    "sg:phone":"+1 541 312 3710",
    "sg:postcode":"97701",
    "sg:province":"OR",
    "sg:tags":[
        "carpentry",
        "contractor"
    ],
    "wof:name":"North Pacific Supply",
    "wof:placetype":"venue"
},
  "geometry": {"coordinates":[-121.29549799999999,44.059814],"type":"Point"}
}