{
  "type": "Feature",
  "properties": {
    "addr:full":"1055 N 5th St Jacksonville OR 97530",
    "addr:housenumber":"1055",
    "addr:postcode":"97530",
    "addr:street":"N 5Th St",
    "iso:country":"US",
    "sg:address":"1055 N 5th St",
    "sg:city":"Jacksonville",
    "sg:classifiers":[
        {
            "category":"Building & Trades",
            "subcategory":"Construction",
            "type":"Services"
        }
    ],
    "sg:phone":"+1 541 899 7195",
    "sg:postcode":"97530",
    "sg:province":"OR",
    "sg:tags":[
        "heavy"
    ],
    "wof:name":"Tri Mir LLC",
    "wof:placetype":"venue"
},
  "geometry": {"coordinates":[-122.958372,42.320575],"type":"Point"}
}