{
  "type": "Feature",
  "properties": {
    "iso:country":"US",
    "sg:address":"10015 SW Terwilliger Blvd",
    "sg:city":"Portland",
    "sg:classifiers":[
        {
            "category":"Education",
            "subcategory":"Special Training",
            "type":"Public Place"
        }
    ],
    "sg:phone":"+1 503 768 6749",
    "sg:postcode":"97219",
    "sg:province":"OR",
    "sg:tags":[
        "educational"
    ],
    "wof:name":"Ncvli",
    "wof:placetype":"venue"
},
  "geometry": {"coordinates":[-122.677851,45.45306],"type":"Point"}
}