{
  "type": "Feature",
  "properties": {
    "addr:full":"222 SE Salmon Ave Redmond OR 97756",
    "addr:housenumber":"222",
    "addr:postcode":"97756",
    "addr:street":"Se Salmon Ave",
    "iso:country":"US",
    "sg:address":"222 SE Salmon Ave",
    "sg:city":"Redmond",
    "sg:classifiers":[
        {
            "category":"Building & Trades",
            "subcategory":"Equipment Rental",
            "type":"Services"
        }
    ],
    "sg:phone":"+1 541 923 0900",
    "sg:postcode":"97756",
    "sg:province":"OR",
    "sg:tags":[
        "contractor"
    ],
    "wof:name":"RSA Co",
    "wof:placetype":"venue"
},
  "geometry": {"coordinates":[-121.165288,44.253474],"type":"Point"}
}