{
  "type": "Feature",
  "properties": {
    "iso:country":"US",
    "sg:address":"1074 Moneda Ave N",
    "sg:city":"Salem",
    "sg:classifiers":[
        {
            "category":"Home & Garden",
            "subcategory":"Carpets & Floor Coverings",
            "type":"Retail Goods"
        }
    ],
    "sg:phone":"+1 503 390 5323",
    "sg:postcode":"97303",
    "sg:province":"OR",
    "wof:name":"Magic Wizzard Carpet Cleaning",
    "wof:placetype":"venue"
},
  "geometry": {"coordinates":[-123.046061,44.993111],"type":"Point"}
}