{
  "type": "Feature",
  "properties": {
    "iso:country":"US",
    "sg:address":"720 NE Flanders Street Suite 204",
    "sg:city":"Portland",
    "sg:classifiers":[
        {
            "category":"Professional",
            "subcategory":"Lawyer & Legal Services",
            "type":"Services"
        }
    ],
    "sg:phone":"+1 503 231 4669",
    "sg:postcode":"97232",
    "sg:province":"OR",
    "sg:tags":[
        "personal",
        "injury"
    ],
    "wof:name":"Cedric R Brown",
    "wof:placetype":"venue"
},
  "geometry": {"coordinates":[-122.658449,45.525762],"type":"Point"}
}