{
  "type": "Feature",
  "properties": {
    "iso:country":"US",
    "sg:address":"1400 W 8th St",
    "sg:city":"The Dalles",
    "sg:classifiers":[
        {
            "category":"Government",
            "subcategory":"Fire Station",
            "type":"Public Place"
        }
    ],
    "sg:phone":"+1 541 296 9445",
    "sg:postcode":"97058",
    "sg:province":"OR",
    "sg:tags":[
        "department"
    ],
    "sg:website":"www.mcfr.org",
    "wof:name":"Mid-Columbia Fire & Rescue",
    "wof:placetype":"venue"
},
  "geometry": {"coordinates":[-121.203619,45.606464],"type":"Point"}
}