{
  "type": "Feature",
  "properties": {
    "iso:country":"US",
    "sg:address":"123 NW 2nd Ave",
    "sg:city":"Portland",
    "sg:classifiers":[
        {
            "category":"Manufacturing",
            "subcategory":"Printing",
            "type":"Manufacturing & Wholesale Goods"
        }
    ],
    "sg:phone":"+1 503 248 1190",
    "sg:postcode":"97209",
    "sg:province":"OR",
    "sg:tags":[
        "publisher"
    ],
    "wof:name":"Zuri Media",
    "wof:placetype":"venue"
},
  "geometry": {"coordinates":[-122.672489,45.524399],"type":"Point"}
}