{
  "type": "Feature",
  "properties": {
    "addr:full":"41 E Stewart Ave Medford OR 97501",
    "addr:housenumber":"41",
    "addr:postcode":"97501",
    "addr:street":"E Stewart Ave",
    "iso:country":"US",
    "sg:address":"41 E Stewart Ave",
    "sg:city":"Medford",
    "sg:classifiers":[
        {
            "category":"Fast Food",
            "type":"Food & Drink"
        },
        {
            "category":"Restaurant",
            "type":"Food & Drink"
        },
        {
            "category":"Food & Beverages",
            "subcategory":"Groceries & Convenience Stores",
            "type":"Retail Goods"
        }
    ],
    "sg:phone":"+1 541 779 4294",
    "sg:postcode":"97501",
    "sg:province":"OR",
    "sg:tags":[
        "shop",
        "american",
        "sandwich"
    ],
    "sg:website":"http://www.arbys.com",
    "wof:name":"Arby's",
    "wof:placetype":"venue"
},
  "geometry": {"coordinates":[-122.860041,42.312956],"type":"Point"}
}