{
  "type": "Feature",
  "properties": {
    "addr:full":"1301 SE Stark St Portland OR 97214",
    "addr:housenumber":"1301",
    "addr:postcode":"97214",
    "addr:street":"Se Stark St",
    "iso:country":"US",
    "sg:address":"1301 SE Stark St",
    "sg:city":"Portland",
    "sg:classifiers":[
        {
            "category":"Retail",
            "subcategory":"Repair Shop",
            "type":"Services"
        },
        {
            "category":"Shopping",
            "type":"Retail Goods"
        }
    ],
    "sg:phone":"+1 503 234 2370",
    "sg:postcode":"97214",
    "sg:province":"OR",
    "sg:tags":[
        "picture",
        "frame",
        "framing",
        "custom"
    ],
    "sg:website":"www.framingresource.net",
    "wof:name":"Framing Resource",
    "wof:placetype":"venue"
},
  "geometry": {"coordinates":[-122.65242000000001,45.519563],"type":"Point"}
}