{
  "type": "Feature",
  "properties": {
    "iso:country":"US",
    "sg:address":"5335 Daisy St Spc 122",
    "sg:city":"Springfield",
    "sg:classifiers":[
        {
            "category":"Social Services",
            "subcategory":"Adult Care",
            "type":"Services"
        }
    ],
    "sg:phone":"+1 541 988 5984",
    "sg:postcode":"97478",
    "sg:province":"OR",
    "sg:tags":[
        "nurses-home"
    ],
    "wof:name":"Rising Sun Family Care",
    "wof:placetype":"venue"
},
  "geometry": {"coordinates":[-122.93798099999999,44.041679],"type":"Point"}
}