{
  "type": "Feature",
  "properties": {
    "addr:full":"19291 SE 502nd Ave Sandy OR 97055",
    "addr:postcode":"19291;97055",
    "addr:street":"Se 502Nd Ave",
    "iso:country":"US",
    "sg:address":"19291 SE 502nd Ave",
    "sg:city":"Sandy",
    "sg:classifiers":[
        {
            "category":"Health Services",
            "subcategory":"Doctor",
            "type":"Services"
        }
    ],
    "sg:phone":"+1 503 668 7956",
    "sg:postcode":"97055",
    "sg:province":"OR",
    "sg:tags":[
        "medical"
    ],
    "wof:name":"Courser Darel MD",
    "wof:placetype":"venue"
},
  "geometry": {"coordinates":[-122.147502,45.384303],"type":"Point"}
}