{
  "type": "Feature",
  "properties": {
    "iso:country":"US",
    "sg:address":"1867 SW 14th Ave",
    "sg:city":"Portland",
    "sg:classifiers":[
        {
            "category":"Wholesale",
            "subcategory":"Medical Equipment & Supplies",
            "type":"Manufacturing & Wholesale Goods"
        }
    ],
    "sg:phone":"+1 503 546 0600",
    "sg:postcode":"97201",
    "sg:province":"OR",
    "sg:tags":[
        "physician",
        "surgeon"
    ],
    "wof:name":"Xtract Solutions LLC",
    "wof:placetype":"venue"
},
  "geometry": {"coordinates":[-122.690862,45.512689],"type":"Point"}
}