{
  "type": "Feature",
  "properties": {
    "addr:full":"711 NE 61st Ct Hillsboro OR 97124",
    "addr:housenumber":"711",
    "addr:postcode":"97124",
    "addr:street":"Ne 61St Ct",
    "iso:country":"US",
    "sg:address":"711 NE 61st Ct",
    "sg:city":"Hillsboro",
    "sg:classifiers":[
        {
            "category":"Retail",
            "subcategory":"Auto Repair",
            "type":"Services"
        }
    ],
    "sg:phone":"+1 503 648 4898",
    "sg:postcode":"97124",
    "sg:province":"OR",
    "sg:tags":[
        "body",
        "automobile",
        "painting",
        "repairing"
    ],
    "wof:name":"My Nourished Body And Mind",
    "wof:placetype":"venue"
},
  "geometry": {"coordinates":[-122.917686,45.528125],"type":"Point"}
}