{
  "type": "Feature",
  "properties": {
    "iso:country":"US",
    "sg:address":"3205 SW Cedar Hills Blvd",
    "sg:city":"Beaverton",
    "sg:classifiers":[
        {
            "category":"Restaurant",
            "type":"Food & Drink"
        }
    ],
    "sg:phone":"+1 503 643 6739",
    "sg:postcode":"97005",
    "sg:province":"OR",
    "sg:tags":[
        "japanese"
    ],
    "wof:name":"Samurai Sams",
    "wof:placetype":"venue"
},
  "geometry": {"coordinates":[-122.80866899999999,45.49671],"type":"Point"}
}