{
  "type": "Feature",
  "properties": {
    "iso:country":"US",
    "sg:address":"9805 SW Whitford Ln",
    "sg:city":"Beaverton",
    "sg:classifiers":[
        {
            "category":"Building & Trades",
            "subcategory":"Construction",
            "type":"Services"
        }
    ],
    "sg:phone":"+1 503 574 4092",
    "sg:postcode":"97008",
    "sg:province":"OR",
    "sg:tags":[
        "hanging",
        "contractor"
    ],
    "wof:name":"Mark Stilwell Painting",
    "wof:placetype":"venue"
},
  "geometry": {"coordinates":[-122.77591,45.464246],"type":"Point"}
}