{
  "type": "Feature",
  "properties": {
    "iso:country":"US",
    "sg:address":"9045 Pueblo Ave NE",
    "sg:city":"Salem",
    "sg:classifiers":[
        {
            "category":"Real Estate",
            "subcategory":"Real Estate Agent",
            "type":"Services"
        },
        {
            "category":"Home & Garden",
            "subcategory":"Mobile Homes",
            "type":"Retail Goods"
        }
    ],
    "sg:phone":"+1 503 463 8588",
    "sg:postcode":"97305",
    "sg:province":"OR",
    "sg:tags":[
        "broker"
    ],
    "wof:name":"Mobile Home Marketing Inc",
    "wof:placetype":"venue"
},
  "geometry": {"coordinates":[-122.95851,45.048891],"type":"Point"}
}