{
  "type": "Feature",
  "properties": {
    "iso:country":"US",
    "sg:address":"2135 NE Territorial Pl",
    "sg:city":"Canby",
    "sg:classifiers":[
        {
            "category":"Home & Garden",
            "subcategory":"Hardware",
            "type":"Retail Goods"
        }
    ],
    "sg:phone":"+1 503 266 5377",
    "sg:postcode":"97013",
    "sg:province":"OR",
    "sg:tags":[
        "store"
    ],
    "wof:name":"True North Films",
    "wof:placetype":"venue"
},
  "geometry": {"coordinates":[-122.67031299999999,45.281301],"type":"Point"}
}