{
  "type": "Feature",
  "properties": {
    "iso:country":"US",
    "sg:address":"309 SW 6th Ave",
    "sg:city":"Portland",
    "sg:classifiers":[
        {
            "category":"Professional",
            "subcategory":"Business Services",
            "type":"Services"
        }
    ],
    "sg:phone":"+1 503 790 2500",
    "sg:postcode":"97204",
    "sg:province":"OR",
    "sg:tags":[
        "center",
        "value",
        "stored",
        "call",
        "providing",
        "payment"
    ],
    "wof:name":"Vesta Corporation",
    "wof:placetype":"venue"
},
  "geometry": {"coordinates":[-122.677566,45.521155],"type":"Point"}
}