{
  "type": "Feature",
  "properties": {
    "addr:full":"1008 NE 122nd Ave Portland OR 97230",
    "addr:housenumber":"1008",
    "addr:postcode":"97230",
    "addr:street":"Ne 122Nd Ave",
    "iso:country":"US",
    "sg:address":"1008 NE 122nd Ave",
    "sg:city":"Portland",
    "sg:classifiers":[
        {
            "category":"Professional",
            "subcategory":"Accounting & Tax Preparation",
            "type":"Services"
        }
    ],
    "sg:phone":"+1 503 252 9197",
    "sg:postcode":"97230",
    "sg:province":"OR",
    "sg:tags":[
        "bookkeeping",
        "general"
    ],
    "wof:name":"Bookkeeping Co",
    "wof:placetype":"venue"
},
  "geometry": {"coordinates":[-122.537621,45.530045],"type":"Point"}
}