{
  "type": "Feature",
  "properties": {
    "addr:full":"6410 SE Milwaukie Ave Portland OR 97202",
    "addr:housenumber":"6410",
    "addr:postcode":"97202",
    "addr:street":"Se Milwaukie Ave",
    "iso:country":"US",
    "sg:address":"6410 SE Milwaukie Ave",
    "sg:city":"Portland",
    "sg:classifiers":[
        {
            "category":"Restaurant",
            "type":"Food & Drink"
        }
    ],
    "sg:phone":"+1 503 239 8544",
    "sg:postcode":"97202",
    "sg:province":"OR",
    "sg:tags":[
        "sandwich"
    ],
    "sg:website":"www.phillypdx.com/",
    "wof:name":"Philadelphia's Steaks & Hoagies",
    "wof:placetype":"venue"
},
  "geometry": {"coordinates":[-122.649002,45.4762],"type":"Point"}
}