{
  "type": "Feature",
  "properties": {
    "iso:country":"US",
    "sg:address":"10 Crater Lake Ave",
    "sg:city":"Medford",
    "sg:classifiers":[
        {
            "category":"Banks & Credit Unions",
            "subcategory":"Financial Services",
            "type":"Services"
        }
    ],
    "sg:phone":"+1 541 608 8850",
    "sg:postcode":"97504",
    "sg:province":"OR",
    "sg:tags":[
        "broker",
        "mortgage"
    ],
    "wof:name":"American Mortgage Network",
    "wof:placetype":"venue"
},
  "geometry": {"coordinates":[-122.86199999999999,42.327999],"type":"Point"}
}