{
  "type": "Feature",
  "properties": {
    "iso:country":"US",
    "sg:address":"12389 NW Kearney St",
    "sg:city":"Portland",
    "sg:classifiers":[
        {
            "category":"Travel",
            "subcategory":"Travel Agent",
            "type":"Entertainment"
        }
    ],
    "sg:phone":"+1 503 646 8628",
    "sg:postcode":"97229",
    "sg:province":"OR",
    "sg:tags":[
        "agency"
    ],
    "wof:name":"Paul J Willoughby",
    "wof:placetype":"venue"
},
  "geometry": {"coordinates":[-122.80426900000001,45.529599],"type":"Point"}
}