{
  "type": "Feature",
  "properties": {
    "addr:full":"1120 NW Couch St Fl 10 Portland OR 97209",
    "addr:housenumber":"1120;10",
    "addr:postcode":"97209",
    "addr:street":"Nw Couch St Fl",
    "iso:country":"US",
    "sg:address":"1120 NW Couch St Fl 10",
    "sg:city":"Portland",
    "sg:classifiers":[
        {
            "category":"Building & Trades",
            "subcategory":"Equipment Rental",
            "type":"Services"
        }
    ],
    "sg:phone":"+1 503 727 2046",
    "sg:postcode":"97209",
    "sg:province":"OR",
    "sg:tags":[
        "leasing",
        "equipment-renting",
        "furniture"
    ],
    "sg:website":"http://www.pb.com",
    "wof:name":"Pitney Bowes",
    "wof:placetype":"venue"
},
  "geometry": {"coordinates":[-122.68235,45.523683],"type":"Point"}
}