{
  "type": "Feature",
  "properties": {
    "iso:country":"US",
    "sg:address":"1175 G St",
    "sg:city":"Springfield",
    "sg:classifiers":[
        {
            "category":"Organizations",
            "subcategory":"Religious Organization",
            "type":"Services"
        }
    ],
    "sg:phone":"+1 541 746 6031",
    "sg:postcode":"97477",
    "sg:province":"OR",
    "sg:tags":[
        "american",
        "baptist",
        "church"
    ],
    "wof:name":"First Bptst Church-Springfield",
    "wof:placetype":"venue"
},
  "geometry": {"coordinates":[-123.012041,44.052383],"type":"Point"}
}