{
  "type": "Feature",
  "properties": {
    "addr:full":"1721 SW Odem Medo Rd Redmond OR 97756",
    "addr:housenumber":"1721",
    "addr:postcode":"97756",
    "addr:street":"Sw;Medo Rd",
    "iso:country":"US",
    "sg:address":"1721 SW Odem Medo Rd",
    "sg:city":"Redmond",
    "sg:classifiers":[
        {
            "category":"Personal",
            "type":"Services"
        },
        {
            "category":"Sports & Exercise",
            "subcategory":"Gym",
            "type":"Entertainment"
        }
    ],
    "sg:phone":"+1 541 526 0046",
    "sg:postcode":"97756",
    "sg:province":"OR",
    "sg:tags":[
        "trainer",
        "consultant",
        "program",
        "physical",
        "fitness"
    ],
    "sg:website":"http://www.jazzercise.com",
    "wof:name":"Jazzercise Redmond Fitness Center",
    "wof:placetype":"venue"
},
  "geometry": {"coordinates":[-121.186091,44.252649],"type":"Point"}
}