{
  "type": "Feature",
  "properties": {
    "iso:country":"US",
    "sg:address":"24533 Alsea Hwy",
    "sg:city":"Philomath",
    "sg:classifiers":[
        {
            "category":"Manufacturing",
            "subcategory":"Lumber",
            "type":"Manufacturing & Wholesale Goods"
        }
    ],
    "sg:phone":"+1 541 929 3266",
    "sg:postcode":"97370",
    "sg:province":"OR",
    "sg:tags":[
        "government"
    ],
    "wof:name":"Forestry Dept",
    "wof:placetype":"venue"
},
  "geometry": {"coordinates":[-123.398567,44.531556],"type":"Point"}
}