{
  "type": "Feature",
  "properties": {
    "iso:country":"US",
    "sg:address":"4115 SE Clinton St Ste 1",
    "sg:city":"Portland",
    "sg:classifiers":[
        {
            "category":"Building & Trades",
            "subcategory":"Electrical",
            "type":"Services"
        }
    ],
    "sg:phone":"+1 503 288 2211",
    "sg:postcode":"97202",
    "sg:province":"OR",
    "sg:tags":[
        "electrician"
    ],
    "sg:website":"www.dekorteelectric.com",
    "wof:name":"Dekorte Electric",
    "wof:placetype":"venue"
},
  "geometry": {"coordinates":[-122.620135,45.503586],"type":"Point"}
}