{
  "type": "Feature",
  "properties": {
    "iso:country":"US",
    "sg:address":"54 A Ave",
    "sg:city":"Lake Oswego",
    "sg:classifiers":[
        {
            "category":"Banks & Credit Unions",
            "subcategory":"Bank",
            "type":"Services"
        }
    ],
    "sg:phone":"+1 503 635 4321",
    "sg:postcode":"97034",
    "sg:province":"OR",
    "sg:website":"www.usbank.com",
    "wof:name":"US Bancorp",
    "wof:placetype":"venue"
},
  "geometry": {"coordinates":[-122.663697,45.419134],"type":"Point"}
}