{
  "type": "Feature",
  "properties": {
    "iso:country":"US",
    "sg:address":"5885 SE McNary Rd",
    "sg:city":"Portland",
    "sg:classifiers":[
        {
            "category":"Home & Garden",
            "subcategory":"Mobile Homes",
            "type":"Retail Goods"
        }
    ],
    "sg:phone":"+1 503 513 0509",
    "sg:postcode":"97267",
    "sg:province":"OR",
    "wof:name":"Century Mobile Homes Inc",
    "wof:placetype":"venue"
},
  "geometry": {"coordinates":[-122.603147,45.403327],"type":"Point"}
}