{
  "type": "Feature",
  "properties": {
    "iso:country":"US",
    "sg:address":"19395 S Pease Rd",
    "sg:city":"Oregon City",
    "sg:classifiers":[
        {
            "category":"Manufacturing",
            "subcategory":"Tools & Machinery",
            "type":"Manufacturing & Wholesale Goods"
        }
    ],
    "sg:phone":"+1 503 582 0555",
    "sg:postcode":"97045",
    "sg:province":"OR",
    "sg:tags":[
        "pump"
    ],
    "wof:name":"Vogelsang USA",
    "wof:placetype":"venue"
},
  "geometry": {"coordinates":[-122.611641,45.326507],"type":"Point"}
}