{
  "type": "Feature",
  "properties": {
    "iso:country":"US",
    "sg:address":"525 SE 11th Ave",
    "sg:city":"Portland",
    "sg:classifiers":[
        {
            "category":"Manufacturing",
            "subcategory":"Apparel",
            "type":"Manufacturing & Wholesale Goods"
        }
    ],
    "sg:phone":"+1 503 236 3473",
    "sg:postcode":"97214",
    "sg:province":"OR",
    "sg:tags":[
        "snowboard",
        "mfg"
    ],
    "sg:website":"www.bonfiresnowboarding.com",
    "wof:name":"Bonfire Snowboarding Inc",
    "wof:placetype":"venue"
},
  "geometry": {"coordinates":[-122.654723,45.518808],"type":"Point"}
}