{
  "type": "Feature",
  "properties": {
    "iso:country":"US",
    "sg:address":"1241 Duane St",
    "sg:city":"Astoria",
    "sg:classifiers":[
        {
            "category":"Utilities",
            "subcategory":"Cable",
            "type":"Services"
        }
    ],
    "sg:phone":"+1 503 325 6114",
    "sg:postcode":"97103",
    "sg:province":"OR",
    "sg:tags":[
        "television"
    ],
    "wof:name":"Charter Cmmnctons Holdings LLC",
    "wof:placetype":"venue"
},
  "geometry": {"coordinates":[-123.829657,46.18824],"type":"Point"}
}