{
  "type": "Feature",
  "properties": {
    "iso:country":"US",
    "sg:address":"2348 NW Lovejoy St",
    "sg:city":"Portland",
    "sg:classifiers":[
        {
            "category":"Health Services",
            "subcategory":"Health Practitioner",
            "type":"Services"
        }
    ],
    "sg:phone":"+1 503 224 7224",
    "sg:postcode":"97210",
    "sg:province":"OR",
    "sg:tags":[
        "acupuncture"
    ],
    "wof:name":"An Hao Clinic",
    "wof:placetype":"venue"
},
  "geometry": {"coordinates":[-122.699939,45.529695],"type":"Point"}
}