{
  "type": "Feature",
  "properties": {
    "iso:country":"US",
    "sg:address":"1201 NE Steenson Rd",
    "sg:city":"Salem",
    "sg:classifiers":[
        {
            "category":"Professional",
            "subcategory":"Management & Consulting",
            "type":"Services"
        }
    ],
    "sg:phone":"+1 503 399 9912",
    "sg:postcode":"97365",
    "sg:province":"OR",
    "sg:tags":[
        "organization",
        "public",
        "relations"
    ],
    "wof:name":"Oregon Community College Assn",
    "wof:placetype":"venue"
},
  "geometry": {"coordinates":[-124.018369,44.639477],"type":"Point"}
}