{
  "type": "Feature",
  "properties": {
    "addr:full":"1201 NE Steenson Rd Salem OR 97365",
    "addr:housenumber":"1201",
    "addr:postcode":"97365",
    "addr:street":"Ne Steenson Rd",
    "iso:country":"US",
    "sg:address":"1201 NE Steenson Rd",
    "sg:city":"Salem",
    "sg:classifiers":[
        {
            "category":"Professional",
            "subcategory":"Management & Consulting",
            "type":"Services"
        }
    ],
    "sg:phone":"+1 503 399 9912",
    "sg:postcode":"97365",
    "sg:province":"OR",
    "sg:tags":[
        "organization",
        "public",
        "relations"
    ],
    "wof:name":"Oregon Community College Assn",
    "wof:placetype":"venue"
},
  "geometry": {"coordinates":[-124.01836900000001,44.639477],"type":"Point"}
}