{
  "type": "Feature",
  "properties": {
    "iso:country":"US",
    "sg:address":"24035 SW Mountain Creek Rd",
    "sg:city":"Sherwood",
    "sg:classifiers":[
        {
            "category":"Wholesale",
            "subcategory":"Groceries",
            "type":"Manufacturing & Wholesale Goods"
        }
    ],
    "sg:phone":"+1 503 628 1196",
    "sg:postcode":"97140",
    "sg:province":"OR",
    "wof:name":"Oregon Lavender Company",
    "wof:placetype":"venue"
},
  "geometry": {"coordinates":[-122.925707,45.385297],"type":"Point"}
}