{
  "type": "Feature",
  "properties": {
    "addr:full":"571 E St Lebanon OR 97355",
    "addr:housenumber":"571",
    "addr:postcode":"97355",
    "addr:street":"E St",
    "iso:country":"US",
    "sg:address":"571 E St",
    "sg:city":"Lebanon",
    "sg:classifiers":[
        {
            "category":"Personal",
            "type":"Services"
        },
        {
            "category":"Professional",
            "subcategory":"Accounting & Tax Preparation",
            "type":"Services"
        }
    ],
    "sg:phone":"+1 541 451 1158",
    "sg:postcode":"97355",
    "sg:province":"OR",
    "sg:tags":[
        "return",
        "filing"
    ],
    "wof:name":"Thrifty Income Tax Service",
    "wof:placetype":"venue"
},
  "geometry": {"coordinates":[-122.915091,44.532074],"type":"Point"}
}