{
  "type": "Feature",
  "properties": {
    "addr:full":"132 E 13th Ave Eugene OR 97401",
    "addr:housenumber":"132",
    "addr:postcode":"97401",
    "addr:street":"E 13Th Ave",
    "iso:country":"US",
    "sg:address":"132 E 13th Ave",
    "sg:city":"Eugene",
    "sg:classifiers":[
        {
            "category":"Shopping",
            "subcategory":"Used Merchandise",
            "type":"Retail Goods"
        }
    ],
    "sg:phone":"+1 541 338 4395",
    "sg:postcode":"97401",
    "sg:province":"OR",
    "wof:name":"Eugene Jeans Vintage Outlet",
    "wof:placetype":"venue"
},
  "geometry": {"coordinates":[-123.090947,44.045443],"type":"Point"}
}