{
  "type": "Feature",
  "properties": {
    "iso:country":"US",
    "sg:address":"1640 NW 19th Ave",
    "sg:city":"Portland",
    "sg:classifiers":[
        {
            "category":"Education",
            "subcategory":"School",
            "type":"Public Place"
        }
    ],
    "sg:phone":"+1 503 423 2726",
    "sg:postcode":"97209",
    "sg:province":"OR",
    "sg:tags":[
        "k-",
        "private"
    ],
    "wof:name":"Phame Academy",
    "wof:placetype":"venue"
},
  "geometry": {"coordinates":[-122.69064299999999,45.534508],"type":"Point"}
}