{
  "type": "Feature",
  "properties": {
    "addr:full":"12909 SW 68th Pkwy Ste 410 Portland OR 97223",
    "addr:housenumber":"12909",
    "addr:postcode":"97223",
    "addr:street":"Sw 68Th Pkwy Ste 410",
    "iso:country":"US",
    "sg:address":"12909 SW 68th Pkwy Ste 410",
    "sg:city":"Portland",
    "sg:classifiers":[
        {
            "category":"Shopping",
            "subcategory":"Jewelry",
            "type":"Retail Goods"
        }
    ],
    "sg:phone":"+1 503 221 2442",
    "sg:postcode":"97223",
    "sg:province":"OR",
    "sg:website":"www.cameronjewelers.com",
    "wof:name":"Cameron Jewelers",
    "wof:placetype":"venue"
},
  "geometry": {"coordinates":[-122.74742999999999,45.426716],"type":"Point"}
}