{
  "type": "Feature",
  "properties": {
    "iso:country":"US",
    "sg:address":"201 Dixon Ave",
    "sg:city":"Molalla",
    "sg:classifiers":[
        {
            "category":"Shopping",
            "subcategory":"Computers & Home Electronics",
            "type":"Retail Goods"
        }
    ],
    "sg:phone":"+1 503 829 9888",
    "sg:postcode":"97038",
    "sg:province":"OR",
    "sg:tags":[
        "equipment",
        "electronic",
        "supply"
    ],
    "sg:website":"www.excesscomponents.com",
    "wof:name":"Excess Components",
    "wof:placetype":"venue"
},
  "geometry": {"coordinates":[-122.583895,45.149224],"type":"Point"}
}