{
  "type": "Feature",
  "properties": {
    "addr:full":"2344 NW Grimes Rd Prineville OR 97754",
    "addr:housenumber":"2344",
    "addr:postcode":"97754",
    "addr:street":"Nw Grimes Rd",
    "iso:country":"US",
    "sg:address":"2344 NW Grimes Rd",
    "sg:city":"Prineville",
    "sg:classifiers":[
        {
            "category":"Retail",
            "subcategory":"Repair Shop",
            "type":"Services"
        }
    ],
    "sg:phone":"+1 541 447 6784",
    "sg:postcode":"97754",
    "sg:province":"OR",
    "sg:tags":[
        "contractor"
    ],
    "wof:name":"Black's Equipment Savers",
    "wof:placetype":"venue"
},
  "geometry": {"coordinates":[-120.869924,44.362933],"type":"Point"}
}