{
  "type": "Feature",
  "properties": {
    "iso:country":"US",
    "sg:address":"4732 SW Wickiup Ave",
    "sg:city":"Redmond",
    "sg:classifiers":[
        {
            "category":"Retail",
            "subcategory":"Repair Shop",
            "type":"Services"
        }
    ],
    "sg:phone":"+1 541 923 2665",
    "sg:postcode":"97756",
    "sg:province":"OR",
    "sg:tags":[
        "welding"
    ],
    "wof:name":"Double D Welding",
    "wof:placetype":"venue"
},
  "geometry": {"coordinates":[-121.22475300000001,44.247451],"type":"Point"}
}