{
  "type": "Feature",
  "properties": {
    "iso:country":"US",
    "sg:address":"5380 SE Byron Dr",
    "sg:city":"Portland",
    "sg:classifiers":[
        {
            "category":"Building & Trades",
            "subcategory":"Construction",
            "type":"Services"
        }
    ],
    "sg:phone":"+1 503 775 2997",
    "sg:postcode":"97267",
    "sg:province":"OR",
    "sg:tags":[
        "roofing",
        "contractor"
    ],
    "wof:name":"Hessel Roofing",
    "wof:placetype":"venue"
},
  "geometry": {"coordinates":[-122.60674,45.406687],"type":"Point"}
}