{
  "type": "Feature",
  "properties": {
    "iso:country":"US",
    "sg:address":"1800 SE M L King Blvd",
    "sg:city":"Portland",
    "sg:classifiers":[
        {
            "category":"Retail",
            "subcategory":"Auto Repair",
            "type":"Services"
        }
    ],
    "sg:phone":"+1 503 231 4947",
    "sg:postcode":"97214",
    "sg:province":"OR",
    "sg:website":"www.rebornautomotive.com",
    "wof:name":"Re-Born Automotive",
    "wof:placetype":"venue"
},
  "geometry": {"coordinates":[-122.661879,45.509746],"type":"Point"}
}