{
  "type": "Feature",
  "properties": {
    "addr:full":"7000 SW Hampton St Portland OR 97223",
    "addr:housenumber":"7000",
    "addr:postcode":"97223",
    "addr:street":"Sw Hampton St",
    "iso:country":"US",
    "sg:address":"7000 SW Hampton St",
    "sg:city":"Portland",
    "sg:classifiers":[
        {
            "category":"Banks & Credit Unions",
            "subcategory":"Bank",
            "type":"Services"
        }
    ],
    "sg:phone":"+1 503 977 0810",
    "sg:postcode":"97223",
    "sg:province":"OR",
    "sg:tags":[
        "loan",
        "real estate"
    ],
    "wof:name":"Executive Financial Solutions",
    "wof:placetype":"venue"
},
  "geometry": {"coordinates":[-122.751566,45.427602],"type":"Point"}
}