{
  "type": "Feature",
  "properties": {
    "addr:full":"767 Willamette St Eugene OR 97401",
    "addr:housenumber":"767",
    "addr:postcode":"97401",
    "addr:street":"Willamette St",
    "iso:country":"US",
    "sg:address":"767 Willamette St",
    "sg:city":"Eugene",
    "sg:classifiers":[
        {
            "category":"Professional",
            "subcategory":"Lawyer & Legal Services",
            "type":"Services"
        }
    ],
    "sg:phone":"+1 541 465 9095",
    "sg:postcode":"97401",
    "sg:province":"OR",
    "sg:tags":[
        "attorney"
    ],
    "wof:name":"James P Caher",
    "wof:placetype":"venue"
},
  "geometry": {"coordinates":[-123.09266100000001,44.051783],"type":"Point"}
}