{
  "type": "Feature",
  "properties": {
    "iso:country":"US",
    "sg:address":"12909 SW 68th Pkwy",
    "sg:city":"Portland",
    "sg:classifiers":[
        {
            "category":"Real Estate",
            "subcategory":"Real Estate Services",
            "type":"Services"
        },
        {
            "category":"Banks & Credit Unions",
            "subcategory":"Investment Brokerage",
            "type":"Services"
        }
    ],
    "sg:phone":"+1 503 598 7508",
    "sg:postcode":"97223",
    "sg:province":"OR",
    "sg:tags":[
        "trust",
        "management"
    ],
    "wof:name":"Pac Trust",
    "wof:placetype":"venue"
},
  "geometry": {"coordinates":[-122.74691799999999,45.425133],"type":"Point"}
}