{
  "type": "Feature",
  "properties": {
    "addr:full":"815 NE Davis St Portland OR 97232",
    "addr:housenumber":"815",
    "addr:postcode":"97232",
    "addr:street":"Ne Davis St",
    "iso:country":"US",
    "sg:address":"815 NE Davis St",
    "sg:city":"Portland",
    "sg:classifiers":[
        {
            "category":"Wholesale",
            "subcategory":"Construction Materials",
            "type":"Manufacturing & Wholesale Goods"
        }
    ],
    "sg:phone":"+1 503 231 1166",
    "sg:postcode":"97232",
    "sg:province":"OR",
    "sg:tags":[
        "lumber",
        "plywood"
    ],
    "sg:website":"www.north-pacific.com",
    "wof:name":"North Pacific Group Inc",
    "wof:placetype":"venue"
},
  "geometry": {"coordinates":[-122.65674199999999,45.524419],"type":"Point"}
}