{
  "type": "Feature",
  "properties": {
    "iso:country":"US",
    "sg:address":"5613 SE 82nd Avenue",
    "sg:city":"Portland",
    "sg:classifiers":[
        {
            "category":"Restaurant",
            "type":"Food & Drink"
        }
    ],
    "sg:phone":"+1 503 777 9007",
    "sg:postcode":"97266",
    "sg:province":"OR",
    "wof:name":"McDonald's Corporation",
    "wof:placetype":"venue"
},
  "geometry": {"coordinates":[-122.57895000000001,45.482361],"type":"Point"}
}