{
  "type": "Feature",
  "properties": {
    "addr:full":"3750 Ave H White City OR 97503",
    "addr:postcode":"97503",
    "addr:street":"3750 Ave H",
    "iso:country":"US",
    "sg:address":"3750 Ave H",
    "sg:city":"White City",
    "sg:classifiers":[
        {
            "category":"Organizations",
            "subcategory":"Religious Organization",
            "type":"Services"
        }
    ],
    "sg:phone":"+1 541 282 0142",
    "sg:postcode":"97503",
    "sg:province":"OR",
    "sg:tags":[
        "church"
    ],
    "wof:name":"Masjid L Tawheed",
    "wof:placetype":"venue"
},
  "geometry": {"coordinates":[-122.821963,42.438483],"type":"Point"}
}