{
  "type": "Feature",
  "properties": {
    "iso:country":"US",
    "sg:address":"680 Alameda Ave",
    "sg:city":"Astoria",
    "sg:classifiers":[
        {
            "category":"Communications",
            "subcategory":"Film & Video Production",
            "type":"Services"
        }
    ],
    "sg:phone":"+1 503 325 8397",
    "sg:postcode":"97103",
    "sg:province":"OR",
    "sg:tags":[
        "tv",
        "tape"
    ],
    "wof:name":"C P Productions Inc",
    "wof:placetype":"venue"
},
  "geometry": {"coordinates":[-123.855364,46.181989],"type":"Point"}
}