{
  "type": "Feature",
  "properties": {
    "iso:country":"US",
    "sg:address":"4375 Logsden Rd",
    "sg:city":"Logsden",
    "sg:classifiers":[
        {
            "category":"Building & Trades",
            "subcategory":"Plumbing",
            "type":"Services"
        }
    ],
    "sg:phone":"+1 541 265 7576",
    "sg:postcode":"97380",
    "sg:province":"OR",
    "sg:tags":[
        "plumbing",
        "contractor"
    ],
    "wof:name":"Lincoln Plumbing LLC",
    "wof:placetype":"venue"
},
  "geometry": {"coordinates":[-123.84503599999999,44.734457],"type":"Point"}
}