{
  "type": "Feature",
  "properties": {
    "addr:full":"29595 Bellfountain Rd Corvallis OR 97333",
    "addr:postcode":"29595;97333",
    "addr:street":"Bellfountain Rd",
    "iso:country":"US",
    "sg:address":"29595 Bellfountain Rd",
    "sg:city":"Corvallis",
    "sg:classifiers":[
        {
            "category":"Manufacturing",
            "subcategory":"Buildings",
            "type":"Manufacturing & Wholesale Goods"
        },
        {
            "category":"Building & Trades",
            "subcategory":"Construction",
            "type":"Services"
        }
    ],
    "sg:phone":"+1 541 753 2871",
    "sg:postcode":"97333",
    "sg:province":"OR",
    "sg:tags":[
        "industrial",
        "specialty",
        "builder",
        "heating",
        "system",
        "contractors-commercial",
        "home",
        "contractor",
        "air conditioning"
    ],
    "wof:name":"R M Sutherland Construction",
    "wof:placetype":"venue"
},
  "geometry": {"coordinates":[-123.336133,44.438063],"type":"Point"}
}