{
  "type": "Feature",
  "properties": {
    "iso:country":"US",
    "sg:address":"3514 SW Dakota St",
    "sg:city":"Portland",
    "sg:classifiers":[
        {
            "category":"Building & Trades",
            "subcategory":"Construction",
            "type":"Services"
        }
    ],
    "sg:phone":"+1 503 998 6046",
    "sg:postcode":"97221",
    "sg:province":"OR",
    "sg:tags":[
        "contractor",
        "painting",
        "painter",
        "hanging"
    ],
    "wof:name":"Columbia Painting Inc",
    "wof:placetype":"venue"
},
  "geometry": {"coordinates":[-122.71302,45.477983],"type":"Point"}
}