{
  "type": "Feature",
  "properties": {
    "addr:full":"15450 SE for More Ct Clackamas OR 97015",
    "addr:postcode":"15450;97015",
    "addr:street":"Se For More Ct",
    "iso:country":"US",
    "sg:address":"15450 SE for More Ct",
    "sg:city":"Clackamas",
    "sg:classifiers":[
        {
            "category":"Manufacturing",
            "subcategory":"Tools & Machinery",
            "type":"Manufacturing & Wholesale Goods"
        }
    ],
    "sg:phone":"+1 503 655 6117",
    "sg:postcode":"97015",
    "sg:province":"OR",
    "sg:tags":[
        "food",
        "product"
    ],
    "wof:name":"Tech-Mark Inc",
    "wof:placetype":"venue"
},
  "geometry": {"coordinates":[-122.53132600000001,45.410407],"type":"Point"}
}