{
  "type": "Feature",
  "properties": {
    "addr:full":"421 E 2nd St The Dalles OR 97058",
    "addr:housenumber":"421",
    "addr:postcode":"97058",
    "addr:street":"E 2Nd St",
    "iso:country":"US",
    "sg:address":"421 E 2nd St",
    "sg:city":"The Dalles",
    "sg:classifiers":[
        {
            "category":"Wholesale",
            "subcategory":"Machinery & Supplies",
            "type":"Manufacturing & Wholesale Goods"
        }
    ],
    "sg:phone":"+1 541 298 4822",
    "sg:postcode":"97058",
    "sg:province":"OR",
    "sg:tags":[
        "janitor"
    ],
    "wof:name":"Onriver Supply Inc",
    "wof:placetype":"venue"
},
  "geometry": {"coordinates":[-121.180418,45.600676],"type":"Point"}
}