{
  "type": "Feature",
  "properties": {
    "iso:country":"US",
    "sg:address":"202 S River St",
    "sg:city":"Enterprise",
    "sg:classifiers":[
        {
            "category":"Building & Trades",
            "subcategory":"Construction",
            "type":"Services"
        }
    ],
    "sg:phone":"+1 541 426 4744",
    "sg:postcode":"97828",
    "sg:province":"OR",
    "sg:tags":[
        "equipment",
        "light",
        "rental",
        "installation",
        "glass"
    ],
    "wof:name":"Wallowa Valley Glass",
    "wof:placetype":"venue"
},
  "geometry": {"coordinates":[-117.27763899999999,45.424587],"type":"Point"}
}