{
  "type": "Feature",
  "properties": {
    "addr:full":"2505 Hwy 101 N Tillamook OR 97141",
    "addr:housenumber":"2505",
    "addr:postcode":"97141",
    "addr:street":"Hwy 101 N",
    "iso:country":"US",
    "sg:address":"2505 Hwy 101 N",
    "sg:city":"Tillamook",
    "sg:classifiers":[
        {
            "category":"Personal",
            "subcategory":"Beauty Salon",
            "type":"Services"
        }
    ],
    "sg:phone":"+1 503 842 4247",
    "sg:postcode":"97141",
    "sg:province":"OR",
    "sg:tags":[
        "shop"
    ],
    "wof:name":"Avenues of Hair Design",
    "wof:placetype":"venue"
},
  "geometry": {"coordinates":[-123.84412399999999,45.475767],"type":"Point"}
}