{
  "type": "Feature",
  "properties": {
    "addr:full":"1130 NW 22nd Ave Portland OR 97210",
    "addr:housenumber":"1130",
    "addr:postcode":"97210",
    "addr:street":"Nw 22Nd Ave",
    "iso:country":"US",
    "sg:address":"1130 NW 22nd Ave",
    "sg:city":"Portland",
    "sg:classifiers":[
        {
            "category":"Health Services",
            "subcategory":"Doctor",
            "type":"Services"
        }
    ],
    "sg:phone":"+1 503 299 6500",
    "sg:postcode":"97210",
    "sg:province":"OR",
    "sg:tags":[
        "medical"
    ],
    "wof:name":"Keith S Lanier MD",
    "wof:placetype":"venue"
},
  "geometry": {"coordinates":[-122.69655299999999,45.531035],"type":"Point"}
}