{
  "type": "Feature",
  "properties": {
    "addr:full":"781 Eastridge Dr Medford OR 97504",
    "addr:housenumber":"781",
    "addr:postcode":"97504",
    "addr:street":"Eastridge Dr",
    "iso:country":"US",
    "sg:address":"781 Eastridge Dr",
    "sg:city":"Medford",
    "sg:classifiers":[
        {
            "category":"Farming",
            "subcategory":"Livestock Farm",
            "type":"Manufacturing & Wholesale Goods"
        }
    ],
    "sg:phone":"+1 541 608 2845",
    "sg:postcode":"97504",
    "sg:province":"OR",
    "sg:tags":[
        "animal",
        "general"
    ],
    "wof:name":"Billings Ranch Homes",
    "wof:placetype":"venue"
},
  "geometry": {"coordinates":[-122.817939,42.31449],"type":"Point"}
}