{
  "type": "Feature",
  "properties": {
    "iso:country":"US",
    "sg:address":"18032 Carlson Ave",
    "sg:city":"Sandy",
    "sg:classifiers":[
        {
            "category":"Shopping",
            "subcategory":"Pets & Pet Supplies",
            "type":"Retail Goods"
        },
        {
            "category":"Retail",
            "subcategory":"Animal Services",
            "type":"Services"
        }
    ],
    "sg:phone":"+1 503 762 2703",
    "sg:postcode":"97055",
    "sg:province":"OR",
    "sg:tags":[
        "grooming",
        "dog",
        "cat"
    ],
    "wof:name":"Tlc Grooming By Wendy",
    "wof:placetype":"venue"
},
  "geometry": {"coordinates":[-122.27287200000001,45.392214],"type":"Point"}
}