{
  "type": "Feature",
  "properties": {
    "addr:full":"14075 SW Chickadee Rd Terrebonne OR 97760",
    "addr:housenumber":"14075",
    "addr:postcode":"97760",
    "addr:street":"Sw Chickadee Rd",
    "iso:country":"US",
    "sg:address":"14075 SW Chickadee Rd",
    "sg:city":"Terrebonne",
    "sg:classifiers":[
        {
            "category":"Real Estate",
            "subcategory":"Real Estate Services",
            "type":"Services"
        },
        {
            "category":"Building & Trades",
            "subcategory":"Cleaning & Sanitation",
            "type":"Services"
        }
    ],
    "sg:phone":"+1 541 977 3169",
    "sg:postcode":"97760",
    "sg:province":"OR",
    "sg:tags":[
        "maintenance",
        "cleaners-interior"
    ],
    "wof:name":"Growing Pains Landscaping Main",
    "wof:placetype":"venue"
},
  "geometry": {"coordinates":[-121.27817,44.43616],"type":"Point"}
}