{
  "type": "Feature",
  "properties": {
    "iso:country":"US",
    "sg:address":"129 E Front St Ste 11",
    "sg:city":"Merrill",
    "sg:classifiers":[
        {
            "category":"Manufacturing",
            "subcategory":"Pet Food",
            "type":"Manufacturing & Wholesale Goods"
        },
        {
            "category":"Shopping",
            "subcategory":"Pets & Pet Supplies",
            "type":"Retail Goods"
        },
        {
            "category":"Farming",
            "subcategory":"Farm",
            "type":"Manufacturing & Wholesale Goods"
        }
    ],
    "sg:phone":"+1 541 798 5373",
    "sg:postcode":"97633",
    "sg:province":"OR",
    "sg:tags":[
        "feed",
        "hay"
    ],
    "wof:name":"Parks Hickey Hay Sales",
    "wof:placetype":"venue"
},
  "geometry": {"coordinates":[-121.59982599999999,42.02401],"type":"Point"}
}