{
  "type": "Feature",
  "properties": {
    "iso:country":"US",
    "sg:address":"1158 NW Knoxville Blvd",
    "sg:city":"Bend",
    "sg:classifiers":[
        {
            "category":"Professional",
            "subcategory":"Management & Consulting",
            "type":"Services"
        }
    ],
    "sg:phone":"+1 541 318 4736",
    "sg:postcode":"97701",
    "sg:province":"OR",
    "sg:tags":[
        "consultant",
        "business"
    ],
    "wof:name":"Sbb Consulting",
    "wof:placetype":"venue"
},
  "geometry": {"coordinates":[-121.337163,44.060209],"type":"Point"}
}