{
  "type": "Feature",
  "properties": {
    "iso:country":"US",
    "sg:address":"104 Locke Ln",
    "sg:city":"Phoenix",
    "sg:classifiers":[
        {
            "category":"Home & Garden",
            "subcategory":"Furniture",
            "type":"Retail Goods"
        }
    ],
    "sg:phone":"+1 541 535 3645",
    "sg:postcode":"97535",
    "sg:province":"OR",
    "wof:name":"R Furniture Corp",
    "wof:placetype":"venue"
},
  "geometry": {"coordinates":[-122.823343,42.272351],"type":"Point"}
}