{
  "type": "Feature",
  "properties": {
    "iso:country":"US",
    "sg:address":"34840 SE Bell Maple Dr",
    "sg:city":"Boring",
    "sg:classifiers":[
        {
            "category":"Building & Trades",
            "subcategory":"Landscaping Services",
            "type":"Services"
        }
    ],
    "sg:phone":"+1 503 663 7570",
    "sg:postcode":"97009",
    "sg:province":"OR",
    "wof:name":"David Leek Stump Grinding",
    "wof:placetype":"venue"
},
  "geometry": {"coordinates":[-122.301139,45.437189],"type":"Point"}
}