{
  "type": "Feature",
  "properties": {
    "iso:country":"US",
    "sg:address":"101 SW Main Street",
    "sg:city":"Portland",
    "sg:classifiers":[
        {
            "category":"Professional",
            "subcategory":"Lawyer & Legal Services",
            "type":"Services"
        }
    ],
    "sg:phone":"+1 503 226 0062",
    "sg:postcode":"97204",
    "sg:province":"OR",
    "wof:name":"Thompson and Ritchey",
    "wof:placetype":"venue"
},
  "geometry": {"coordinates":[-122.67548600000001,45.515122],"type":"Point"}
}