{
  "type": "Feature",
  "properties": {
    "addr:full":"710 NE Cleveland Ave Gresham OR 97030",
    "addr:housenumber":"710",
    "addr:postcode":"97030",
    "addr:street":"Ne Cleveland Ave",
    "iso:country":"US",
    "sg:address":"710 NE Cleveland Ave",
    "sg:city":"Gresham",
    "sg:classifiers":[
        {
            "category":"Shopping",
            "subcategory":"Clothing, Apparel, & Fashions",
            "type":"Retail Goods"
        }
    ],
    "sg:phone":"+1 503 661 1566",
    "sg:postcode":"97030",
    "sg:province":"OR",
    "sg:tags":[
        "t"
    ],
    "wof:name":"Cy Graphics",
    "wof:placetype":"venue"
},
  "geometry": {"coordinates":[-122.421027,45.5027],"type":"Point"}
}