{
  "type": "Feature",
  "properties": {
    "iso:country":"US",
    "sg:address":"6650 SW Redwood Ln",
    "sg:city":"Portland",
    "sg:classifiers":[
        {
            "category":"Professional",
            "subcategory":"Lawyer & Legal Services",
            "type":"Services"
        }
    ],
    "sg:phone":"+1 503 352 6985",
    "sg:postcode":"97224",
    "sg:province":"OR",
    "wof:name":"Hertsel Shadian Attorney At Law Llc",
    "wof:placetype":"venue"
},
  "geometry": {"coordinates":[-122.746394,45.409466],"type":"Point"}
}