{
  "type": "Feature",
  "properties": {
    "addr:full":"18641 SE Clinton St Gresham OR 97030",
    "addr:postcode":"18641;97030",
    "addr:street":"Se Clinton St",
    "iso:country":"US",
    "sg:address":"18641 SE Clinton St",
    "sg:city":"Gresham",
    "sg:classifiers":[
        {
            "category":"Social Services",
            "type":"Services"
        }
    ],
    "sg:phone":"+1 503 491 1982",
    "sg:postcode":"97030",
    "sg:province":"OR",
    "wof:name":"Ldsr",
    "wof:placetype":"venue"
},
  "geometry": {"coordinates":[-122.470416,45.50279],"type":"Point"}
}