{
  "type": "Feature",
  "properties": {
    "iso:country":"US",
    "sg:address":"2622 W 8th St",
    "sg:city":"The Dalles",
    "sg:classifiers":[
        {
            "category":"Professional",
            "subcategory":"Accounting & Tax Preparation",
            "type":"Services"
        }
    ],
    "sg:phone":"+1 541 296 5858",
    "sg:postcode":"97058",
    "sg:province":"OR",
    "wof:name":"Superior Service",
    "wof:placetype":"venue"
},
  "geometry": {"coordinates":[-121.216459,45.615063],"type":"Point"}
}