{
  "type": "Feature",
  "properties": {
    "iso:country":"US",
    "sg:address":"6966 Setness Ln NE",
    "sg:city":"Silverton",
    "sg:phone":"+1 503 873 3614",
    "sg:postcode":"97381",
    "sg:province":"OR",
    "sg:tags":[
        "farm"
    ],
    "wof:name":"Pumpkins & Gourds",
    "wof:placetype":"venue"
},
  "geometry": {"coordinates":[-122.7787,45.023283],"type":"Point"}
}