{
  "type": "Feature",
  "properties": {
    "iso:country":"US",
    "sg:address":"999 Lloyd Center",
    "sg:city":"Portland",
    "sg:classifiers":[
        {
            "category":"Shopping",
            "subcategory":"Beauty & Cosmetics",
            "type":"Retail Goods"
        }
    ],
    "sg:phone":"+1 503 288 6026",
    "sg:postcode":"97232",
    "sg:province":"OR",
    "sg:tags":[
        "jewelry",
        "gift"
    ],
    "wof:name":"Merle Norman Cosmetics",
    "wof:placetype":"venue"
},
  "geometry": {"coordinates":[-122.652027,45.531977],"type":"Point"}
}