{
  "type": "Feature",
  "properties": {
    "iso:country":"US",
    "sg:address":"94678 Toftdahl Rd",
    "sg:city":"Junction City",
    "sg:classifiers":[
        {
            "category":"Building & Trades",
            "subcategory":"Construction",
            "type":"Services"
        }
    ],
    "sg:phone":"+1 541 998 2892",
    "sg:postcode":"97448",
    "sg:province":"OR",
    "sg:tags":[
        "contractor"
    ],
    "wof:name":"Lynn H Wheeler Builder",
    "wof:placetype":"venue"
},
  "geometry": {"coordinates":[-123.209204,44.232814],"type":"Point"}
}