{
  "type": "Feature",
  "properties": {
    "iso:country":"US",
    "sg:address":"21285 SE Idlewine Rd",
    "sg:city":"Eagle Creek",
    "sg:classifiers":[
        {
            "category":"Farming",
            "subcategory":"Livestock Farm",
            "type":"Manufacturing & Wholesale Goods"
        }
    ],
    "sg:phone":"+1 503 637 3591",
    "sg:postcode":"97022",
    "sg:province":"OR",
    "sg:tags":[
        "equine"
    ],
    "wof:name":"Elysian Farms",
    "wof:placetype":"venue"
},
  "geometry": {"coordinates":[-122.33859,45.370514],"type":"Point"}
}