{
  "type": "Feature",
  "properties": {
    "iso:country":"US",
    "sg:address":"28895 US Hwy 730",
    "sg:city":"Umatilla",
    "sg:classifiers":[
        {
            "category":"Retail",
            "subcategory":"Auto Repair",
            "type":"Services"
        }
    ],
    "sg:phone":"+1 541 922 5265",
    "sg:postcode":"97882",
    "sg:province":"OR",
    "sg:tags":[
        "body",
        "automobile",
        "painting",
        "general"
    ],
    "wof:name":"Against The Flow",
    "wof:placetype":"venue"
},
  "geometry": {"coordinates":[-119.354318,45.915485],"type":"Point"}
}