{
  "type": "Feature",
  "properties": {
    "iso:country":"US",
    "sg:address":"12777 NE Whitaker Way",
    "sg:city":"Portland",
    "sg:classifiers":[
        {
            "category":"Manufacturing",
            "subcategory":"Printing",
            "type":"Manufacturing & Wholesale Goods"
        }
    ],
    "sg:phone":"+1 503 257 3229",
    "sg:postcode":"97230",
    "sg:province":"OR",
    "sg:tags":[
        "printer"
    ],
    "wof:name":"Copy Express",
    "wof:placetype":"venue"
},
  "geometry": {"coordinates":[-122.533664,45.561633],"type":"Point"}
}