{
  "type": "Feature",
  "properties": {
    "addr:full":"30404 S Partridge Rd Colton OR 97017",
    "addr:housenumber":"30404",
    "addr:postcode":"97017",
    "addr:street":"S Partridge Rd",
    "iso:country":"US",
    "sg:address":"30404 S Partridge Rd",
    "sg:city":"Colton",
    "sg:classifiers":[
        {
            "category":"Building & Trades",
            "subcategory":"Construction",
            "type":"Services"
        }
    ],
    "sg:phone":"+1 503 824 4202",
    "sg:postcode":"97017",
    "sg:province":"OR",
    "sg:tags":[
        "contractor"
    ],
    "wof:name":"Foster Dj Construction",
    "wof:placetype":"venue"
},
  "geometry": {"coordinates":[-122.388631,45.167212],"type":"Point"}
}