{
  "type": "Feature",
  "properties": {
    "addr:full":"5375 Oakridge Rd Lake Oswego OR 97035",
    "addr:housenumber":"5375",
    "addr:postcode":"97035",
    "addr:street":"Oakridge Rd",
    "iso:country":"US",
    "sg:address":"5375 Oakridge Rd",
    "sg:city":"Lake Oswego",
    "sg:classifiers":[
        {
            "category":"Building & Trades",
            "subcategory":"Locksmith",
            "type":"Services"
        }
    ],
    "sg:phone":"+1 503 715 3833",
    "sg:postcode":"97035",
    "sg:province":"OR",
    "sg:tags":[
        "key"
    ],
    "wof:name":"111 Locksmith",
    "wof:placetype":"venue"
},
  "geometry": {"coordinates":[-122.73194100000001,45.409986],"type":"Point"}
}