{
  "type": "Feature",
  "properties": {
    "addr:full":"2870 Willamette St Eugene OR 97405",
    "addr:housenumber":"2870",
    "addr:postcode":"97405",
    "addr:street":"Willamette St",
    "iso:country":"US",
    "sg:address":"2870 Willamette St",
    "sg:city":"Eugene",
    "sg:classifiers":[
        {
            "category":"Restaurant",
            "type":"Food & Drink"
        }
    ],
    "sg:menulink":"http://www.allmenus.com/or/eugene-springfield/78809-pizza-hut/menu/",
    "sg:phone":"+1 541 686 1600",
    "sg:postcode":"97405",
    "sg:province":"OR",
    "sg:tags":[
        "american",
        "pizza"
    ],
    "wof:name":"Pizza Hut",
    "wof:placetype":"venue"
},
  "geometry": {"coordinates":[-123.090716,44.026778],"type":"Point"}
}