{
  "type": "Feature",
  "properties": {
    "addr:full":"1260 7th Ave SW Albany OR 97321",
    "addr:housenumber":"1260",
    "addr:postcode":"97321",
    "addr:street":"7Th Ave Sw",
    "iso:country":"US",
    "sg:address":"1260 7th Ave SW",
    "sg:city":"Albany",
    "sg:classifiers":[
        {
            "category":"Manufacturing",
            "subcategory":"Petroleum Products",
            "type":"Manufacturing & Wholesale Goods"
        }
    ],
    "sg:phone":"+1 541 619 7275",
    "sg:postcode":"97321",
    "sg:province":"OR",
    "sg:tags":[
        "contract"
    ],
    "wof:name":"Manske Industries",
    "wof:placetype":"venue"
},
  "geometry": {"coordinates":[-123.11794,44.631122],"type":"Point"}
}