{
  "type": "Feature",
  "properties": {
    "iso:country":"US",
    "sg:address":"1647 Englewood Dr",
    "sg:city":"Lake Oswego",
    "sg:classifiers":[
        {
            "category":"Professional",
            "subcategory":"Business Services",
            "type":"Services"
        }
    ],
    "sg:phone":"+1 503 245 1026",
    "sg:postcode":"97034",
    "sg:province":"OR",
    "wof:name":"Marge Creary Interiors",
    "wof:placetype":"venue"
},
  "geometry": {"coordinates":[-122.685924,45.434555],"type":"Point"}
}