{
  "type": "Feature",
  "properties": {
    "addr:full":"3604 Hwy 140 W Klamath Falls OR 97601",
    "addr:housenumber":"3604",
    "addr:postcode":"97601",
    "addr:street":"Hwy 140 W",
    "iso:country":"US",
    "sg:address":"3604 Hwy 140 W",
    "sg:city":"Klamath Falls",
    "sg:classifiers":[
        {
            "category":"Retail",
            "subcategory":"Repair Shop",
            "type":"Services"
        }
    ],
    "sg:phone":"+1 541 850 9853",
    "sg:postcode":"97601",
    "sg:province":"OR",
    "sg:tags":[
        "welding"
    ],
    "wof:name":"Hughs Frontier Welding Earth M",
    "wof:placetype":"venue"
},
  "geometry": {"coordinates":[-121.806237,42.195232],"type":"Point"}
}