{
  "type": "Feature",
  "properties": {
    "iso:country":"US",
    "sg:address":"4230 NE 122nd Ave",
    "sg:city":"Portland",
    "sg:classifiers":[
        {
            "category":"Personal",
            "subcategory":"Beauty Salon",
            "type":"Services"
        }
    ],
    "sg:phone":"+1 503 253 1206",
    "sg:postcode":"97230",
    "sg:province":"OR",
    "sg:tags":[
        "shop"
    ],
    "wof:name":"Tiffany Beauty Salon Inc",
    "wof:placetype":"venue"
},
  "geometry": {"coordinates":[-122.537254,45.552615],"type":"Point"}
}