{
  "type": "Feature",
  "properties": {
    "addr:full":"19565 NE Hwy 240 Newberg OR 97132",
    "addr:housenumber":"19565",
    "addr:postcode":"97132",
    "addr:street":"Ne Hwy 240",
    "iso:country":"US",
    "sg:address":"19565 NE Hwy 240",
    "sg:city":"Newberg",
    "sg:classifiers":[
        {
            "category":"Retail",
            "subcategory":"Auto Repair",
            "type":"Services"
        }
    ],
    "sg:phone":"+1 503 538 2495",
    "sg:postcode":"97132",
    "sg:province":"OR",
    "sg:tags":[
        "automobile",
        "restoration",
        "classic"
    ],
    "wof:name":"Brandt's Automotive Restor",
    "wof:placetype":"venue"
},
  "geometry": {"coordinates":[-123.032383,45.316773],"type":"Point"}
}