{
  "type": "Feature",
  "properties": {
    "iso:country":"US",
    "sg:address":"408 SW 5th Ave",
    "sg:city":"Portland",
    "sg:classifiers":[
        {
            "category":"Manufacturing",
            "subcategory":"Signs",
            "type":"Manufacturing & Wholesale Goods"
        }
    ],
    "sg:phone":"+1 503 222 4229",
    "sg:postcode":"97204",
    "sg:province":"OR",
    "sg:website":"www.tisgrafx.com",
    "wof:name":"Tis Technical Imaging Svc",
    "wof:placetype":"venue"
},
  "geometry": {"coordinates":[-122.676518,45.520735],"type":"Point"}
}