{
  "type": "Feature",
  "properties": {
    "iso:country":"US",
    "sg:address":"1440 Justice Rd",
    "sg:city":"Central Point",
    "sg:classifiers":[
        {
            "category":"Manufacturing",
            "subcategory":"Watercraft",
            "type":"Manufacturing & Wholesale Goods"
        }
    ],
    "sg:phone":"+1 541 779 4141",
    "sg:postcode":"97502",
    "sg:province":"OR",
    "sg:tags":[
        "metalwork",
        "sheet",
        "boat",
        "mfg"
    ],
    "sg:website":"www.willieboats.com",
    "wof:name":"Willie Boats Inc",
    "wof:placetype":"venue"
},
  "geometry": {"coordinates":[-122.856899,42.394571],"type":"Point"}
}