{
  "type": "Feature",
  "properties": {
    "iso:country":"US",
    "sg:address":"11935 SW Burnett Ln",
    "sg:city":"Beaverton",
    "sg:classifiers":[
        {
            "category":"Building & Trades",
            "subcategory":"Construction",
            "type":"Services"
        }
    ],
    "sg:phone":"+1 503 524 9236",
    "sg:postcode":"97008",
    "sg:province":"OR",
    "sg:tags":[
        "general",
        "contractor"
    ],
    "wof:name":"TYGR Construction Co",
    "wof:placetype":"venue"
},
  "geometry": {"coordinates":[-122.800042,45.45186],"type":"Point"}
}