{
  "type": "Feature",
  "properties": {
    "addr:full":"930 N Killingsworth St Portland OR 97217",
    "addr:housenumber":"930",
    "addr:postcode":"97217",
    "addr:street":"N Killingsworth St",
    "iso:country":"US",
    "sg:address":"930 N Killingsworth St",
    "sg:city":"Portland",
    "sg:classifiers":[
        {
            "category":"Retail",
            "subcategory":"Auto Repair",
            "type":"Services"
        }
    ],
    "sg:phone":"+1 503 289 6650",
    "sg:postcode":"97217",
    "sg:province":"OR",
    "sg:tags":[
        "automotive",
        "general"
    ],
    "wof:name":"Standard Auto Repair",
    "wof:placetype":"venue"
},
  "geometry": {"coordinates":[-122.676771,45.562599],"type":"Point"}
}