{
  "type": "Feature",
  "properties": {
    "iso:country":"US",
    "sg:address":"11015 Portland Rd NE",
    "sg:city":"Brooks",
    "sg:classifiers":[
        {
            "category":"Farming",
            "subcategory":"Farm & Veterinary Services",
            "type":"Manufacturing & Wholesale Goods"
        }
    ],
    "sg:phone":"+1 503 393 7401",
    "sg:postcode":"97305",
    "sg:province":"OR",
    "sg:tags":[
        "chemical",
        "application",
        "aerial",
        "applicator"
    ],
    "wof:name":"Industrial Aviation Services",
    "wof:placetype":"venue"
},
  "geometry": {"coordinates":[-122.922309,45.078592],"type":"Point"}
}