{
  "type": "Feature",
  "properties": {
    "iso:country":"US",
    "sg:address":"3541 Royal Crest Dr",
    "sg:city":"The Dalles",
    "sg:classifiers":[
        {
            "category":"Shopping",
            "subcategory":"Clothing, Apparel, & Fashions",
            "type":"Retail Goods"
        }
    ],
    "sg:phone":"+1 541 296 9849",
    "sg:postcode":"97058",
    "sg:province":"OR",
    "sg:tags":[
        "family"
    ],
    "wof:name":"Doncaster Clothing",
    "wof:placetype":"venue"
},
  "geometry": {"coordinates":[-121.130189,45.598625],"type":"Point"}
}