{
  "type": "Feature",
  "properties": {
    "iso:country":"US",
    "sg:address":"546 Bus Park Dr",
    "sg:city":"Medford",
    "sg:classifiers":[
        {
            "category":"Wholesale",
            "subcategory":"Electrical",
            "type":"Manufacturing & Wholesale Goods"
        }
    ],
    "sg:phone":"+1 541 779 5611",
    "sg:postcode":"97504",
    "sg:province":"OR",
    "sg:tags":[
        "alarm",
        "burglar",
        "system"
    ],
    "sg:website":"www.sonitrol.cc",
    "wof:name":"Sonitrol",
    "wof:placetype":"venue"
},
  "geometry": {"coordinates":[-122.882118,42.37242],"type":"Point"}
}