{
  "type": "Feature",
  "properties": {
    "iso:country":"US",
    "sg:address":"204 S 12th St",
    "sg:city":"La Grande",
    "sg:classifiers":[
        {
            "category":"Building & Trades",
            "subcategory":"Construction",
            "type":"Services"
        }
    ],
    "sg:phone":"+1 541 963 5853",
    "sg:postcode":"97850",
    "sg:province":"OR",
    "sg:tags":[
        "general",
        "contractor"
    ],
    "wof:name":"Dallas Lee Miller Contracting",
    "wof:placetype":"venue"
},
  "geometry": {"coordinates":[-118.08649,45.310211],"type":"Point"}
}