{
  "type": "Feature",
  "properties": {
    "iso:country":"US",
    "sg:address":"319 SW Washington St",
    "sg:city":"Portland",
    "sg:phone":"+1 503 274 4332",
    "sg:postcode":"97204",
    "sg:province":"OR",
    "wof:name":"Engert Mary Lou",
    "wof:placetype":"venue"
},
  "geometry": {"coordinates":[-122.67500099999999,45.519632],"type":"Point"}
}