{
  "type": "Feature",
  "properties": {
    "iso:country":"US",
    "sg:address":"4120 River Rd N",
    "sg:city":"Keizer",
    "sg:classifiers":[
        {
            "category":"Social Services",
            "type":"Services"
        }
    ],
    "sg:phone":"+1 503 316 3950",
    "sg:postcode":"97303",
    "sg:province":"OR",
    "sg:tags":[
        "senior",
        "citizen"
    ],
    "wof:name":"Day Break Adult Day Svc",
    "wof:placetype":"venue"
},
  "geometry": {"coordinates":[-123.02652999999999,44.986347],"type":"Point"}
}