{
  "type": "Feature",
  "properties": {
    "iso:country":"US",
    "sg:address":"346 Victor Point Rd NE",
    "sg:city":"Silverton",
    "sg:classifiers":[
        {
            "category":"Manufacturing",
            "subcategory":"Glass & Minerals",
            "type":"Manufacturing & Wholesale Goods"
        }
    ],
    "sg:phone":"+1 503 873 5706",
    "sg:postcode":"97381",
    "sg:province":"OR",
    "sg:tags":[
        "treated",
        "or"
    ],
    "wof:name":"Silverton Sand & Gravel",
    "wof:placetype":"venue"
},
  "geometry": {"coordinates":[-122.75869299999999,44.930082],"type":"Point"}
}