{
  "type": "Feature",
  "properties": {
    "iso:country":"US",
    "sg:address":"810 SE Belmont Ste 1",
    "sg:city":"Portland",
    "sg:classifiers":[
        {
            "category":"Communications",
            "subcategory":"Newspaper",
            "type":"Services"
        },
        {
            "category":"Professional",
            "subcategory":"Art Services",
            "type":"Services"
        }
    ],
    "sg:phone":"+1 503 272 1899",
    "sg:postcode":"97214",
    "sg:province":"OR",
    "sg:tags":[
        "photographer",
        "advertising"
    ],
    "wof:name":"Aaron Rogosin Photography",
    "wof:placetype":"venue"
},
  "geometry": {"coordinates":[-122.657483,45.516346],"type":"Point"}
}