{
  "type": "Feature",
  "properties": {
    "addr:full":"4142 SE 42nd Ave Portland OR 97206",
    "addr:housenumber":"4142",
    "addr:postcode":"97206",
    "addr:street":"Se 42Nd Ave",
    "iso:country":"US",
    "sg:address":"4142 SE 42nd Ave",
    "sg:city":"Portland",
    "sg:classifiers":[
        {
            "category":"Home & Garden",
            "subcategory":"Building Materials",
            "type":"Retail Goods"
        }
    ],
    "sg:phone":"+1 503 595 9036",
    "sg:postcode":"97206",
    "sg:province":"OR",
    "wof:name":"Pacific Supply Company",
    "wof:placetype":"venue"
},
  "geometry": {"coordinates":[-122.61895800000001,45.492748],"type":"Point"}
}