{
  "type": "Feature",
  "properties": {
    "addr:full":"4315 Wendover St Eugene OR 97404",
    "addr:housenumber":"4315",
    "addr:postcode":"97404",
    "addr:street":"Wendover St",
    "iso:country":"US",
    "sg:address":"4315 Wendover St",
    "sg:city":"Eugene",
    "sg:classifiers":[
        {
            "category":"Building & Trades",
            "subcategory":"Construction",
            "type":"Services"
        }
    ],
    "sg:phone":"+1 541 688 8265",
    "sg:postcode":"97404",
    "sg:province":"OR",
    "sg:tags":[
        "house"
    ],
    "wof:name":"Level Construction & Remo",
    "wof:placetype":"venue"
},
  "geometry": {"coordinates":[-123.12925799999999,44.128697],"type":"Point"}
}