{
  "type": "Feature",
  "properties": {
    "iso:country":"US",
    "sg:address":"18205 SW Boones Ferry Rd",
    "sg:city":"Portland",
    "sg:classifiers":[
        {
            "category":"Manufacturing",
            "subcategory":"Metals",
            "type":"Manufacturing & Wholesale Goods"
        }
    ],
    "sg:phone":"+1 503 829 9227",
    "sg:postcode":"97062",
    "sg:province":"OR",
    "sg:tags":[
        "steel"
    ],
    "wof:name":"R B Steel Fab",
    "wof:placetype":"venue"
},
  "geometry": {"coordinates":[-122.756692,45.388303],"type":"Point"}
}