{
  "type": "Feature",
  "properties": {
    "iso:country":"US",
    "sg:address":"2820 Osborn Cutoff Rd",
    "sg:city":"Mosier",
    "sg:classifiers":[
        {
            "category":"Utilities",
            "subcategory":"Water",
            "type":"Services"
        }
    ],
    "sg:phone":"+1 541 296 8544",
    "sg:postcode":"97040",
    "sg:province":"OR",
    "sg:tags":[
        "fire",
        "company-utility",
        "tender",
        "resource",
        "suppression"
    ],
    "wof:name":"Columbia River Tenders",
    "wof:placetype":"venue"
},
  "geometry": {"coordinates":[-121.327692,45.642094],"type":"Point"}
}