{
  "type": "Feature",
  "properties": {
    "addr:full":"850 Main St Dallas OR 97338",
    "addr:housenumber":"850",
    "addr:postcode":"97338",
    "addr:street":"Main St",
    "iso:country":"US",
    "sg:address":"850 Main St",
    "sg:city":"Dallas",
    "sg:classifiers":[
        {
            "category":"Government",
            "subcategory":"Police Station",
            "type":"Public Place"
        }
    ],
    "sg:phone":"+1 503 623 9251",
    "sg:postcode":"97338",
    "sg:province":"OR",
    "sg:tags":[
        "protection",
        "sheriff"
    ],
    "wof:name":"Polk County Sheriff Office",
    "wof:placetype":"venue"
},
  "geometry": {"coordinates":[-123.316665,44.920999],"type":"Point"}
}