{
  "type": "Feature",
  "properties": {
    "iso:country":"US",
    "sg:address":"5712 SW Nebraska St",
    "sg:city":"Portland",
    "sg:classifiers":[
        {
            "category":"Building & Trades",
            "subcategory":"Locksmith",
            "type":"Services"
        }
    ],
    "sg:phone":"+1 503 715 3792",
    "sg:postcode":"97221",
    "sg:province":"OR",
    "sg:tags":[
        "key"
    ],
    "wof:name":"Available Locksmith",
    "wof:placetype":"venue"
},
  "geometry": {"coordinates":[-122.735422,45.478233],"type":"Point"}
}