{
  "type": "Feature",
  "properties": {
    "iso:country":"US",
    "sg:address":"86616 Pine Grove Rd",
    "sg:city":"Eugene",
    "sg:classifiers":[
        {
            "category":"Farming",
            "subcategory":"Livestock Farm",
            "type":"Manufacturing & Wholesale Goods"
        }
    ],
    "sg:phone":"+1 541 686 8386",
    "sg:postcode":"97402",
    "sg:province":"OR",
    "sg:tags":[
        "beef",
        "feedlot",
        "cattle"
    ],
    "wof:name":"Hansen & Son Unlimited",
    "wof:placetype":"venue"
},
  "geometry": {"coordinates":[-123.241192,44.012274],"type":"Point"}
}