{
  "type": "Feature",
  "properties": {
    "iso:country":"US",
    "sg:address":"4647 Averill Dr",
    "sg:city":"Grants Pass",
    "sg:classifiers":[
        {
            "category":"Real Estate",
            "subcategory":"Real Estate Operator",
            "type":"Services"
        }
    ],
    "sg:phone":"+1 541 476 9488",
    "sg:postcode":"97526",
    "sg:province":"OR",
    "sg:tags":[
        "commercial"
    ],
    "wof:name":"Nations Olen",
    "wof:placetype":"venue"
},
  "geometry": {"coordinates":[-123.246213,42.425948],"type":"Point"}
}