{
  "type": "Feature",
  "properties": {
    "addr:full":"1240 Bay St Florence OR 97439",
    "addr:housenumber":"1240",
    "addr:postcode":"97439",
    "addr:street":"Bay St",
    "iso:country":"US",
    "sg:address":"1240 Bay St",
    "sg:city":"Florence",
    "sg:classifiers":[
        {
            "category":"Food & Beverages",
            "subcategory":"Specialty",
            "type":"Retail Goods"
        }
    ],
    "sg:phone":"+1 541 997 3443",
    "sg:postcode":"97439",
    "sg:province":"OR",
    "sg:tags":[
        "tea",
        "coffee"
    ],
    "wof:name":"Siuslaw River Coffee Roasters",
    "wof:placetype":"venue"
},
  "geometry": {"coordinates":[-124.10760999999999,43.966279],"type":"Point"}
}