{
  "type": "Feature",
  "properties": {
    "addr:full":"830 NW Everett St Portland OR 97209",
    "addr:housenumber":"830",
    "addr:postcode":"97209",
    "addr:street":"Nw Everett St",
    "iso:country":"US",
    "sg:address":"830 NW Everett St",
    "sg:city":"Portland",
    "sg:classifiers":[
        {
            "category":"Shopping",
            "subcategory":"Used Merchandise",
            "type":"Retail Goods"
        }
    ],
    "sg:phone":"+1 503 226 4595",
    "sg:postcode":"97209",
    "sg:province":"OR",
    "sg:tags":[
        "furniture"
    ],
    "sg:website":"www.officesinc.com",
    "wof:name":"Offices Inc",
    "wof:placetype":"venue"
},
  "geometry": {"coordinates":[-122.67994899999999,45.525065],"type":"Point"}
}