{
  "type": "Feature",
  "properties": {
    "iso:country":"US",
    "sg:address":"155 S Hwy",
    "sg:city":"Saint Helens",
    "sg:classifiers":[
        {
            "category":"Shopping",
            "subcategory":"Pharmacy",
            "type":"Retail Goods"
        }
    ],
    "sg:phone":"+1 503 397 1435",
    "sg:postcode":"97051",
    "sg:province":"OR",
    "wof:name":"HI-School Pharmacy of Oregon",
    "wof:placetype":"venue"
},
  "geometry": {"coordinates":[-122.822692,45.857551],"type":"Point"}
}