{
  "type": "Feature",
  "properties": {
    "iso:country":"US",
    "sg:address":"6600 SW 92nd Ave Ste 190",
    "sg:city":"Portland",
    "sg:classifiers":[
        {
            "category":"Professional",
            "subcategory":"Accounting & Tax Preparation",
            "type":"Services"
        }
    ],
    "sg:phone":"+1 503 626 4077",
    "sg:postcode":"97223",
    "sg:province":"OR",
    "sg:tags":[
        "accountant"
    ],
    "wof:name":"Towle Janet C CPA",
    "wof:placetype":"venue"
},
  "geometry": {"coordinates":[-122.771294,45.471902],"type":"Point"}
}