{
  "type": "Feature",
  "properties": {
    "iso:country":"US",
    "sg:address":"1800 NW Garden Valley Blvd",
    "sg:city":"Roseburg",
    "sg:classifiers":[
        {
            "category":"Food & Beverages",
            "subcategory":"Groceries & Convenience Stores",
            "type":"Retail Goods"
        }
    ],
    "sg:phone":"+1 541 673 1157",
    "sg:postcode":"97470",
    "sg:province":"OR",
    "sg:tags":[
        "grocer"
    ],
    "wof:name":"Ridgeway Market",
    "wof:placetype":"venue"
},
  "geometry": {"coordinates":[-123.380653,43.235117],"type":"Point"}
}