{
  "type": "Feature",
  "properties": {
    "iso:country":"US",
    "sg:address":"5634 Hazelgreen Rd NE",
    "sg:city":"Salem",
    "sg:classifiers":[
        {
            "category":"Fast Food",
            "type":"Food & Drink"
        },
        {
            "category":"Restaurant",
            "type":"Food & Drink"
        }
    ],
    "sg:phone":"+1 503 393 8521",
    "sg:postcode":"97305",
    "sg:province":"OR",
    "wof:name":"Great Snack Escape",
    "wof:placetype":"venue"
},
  "geometry": {"coordinates":[-122.94681799999999,45.005537],"type":"Point"}
}