{
  "type": "Feature",
  "properties": {
    "iso:country":"US",
    "sg:address":"11062 Takilma Rd",
    "sg:city":"Cave Junction",
    "sg:classifiers":[
        {
            "category":"Building & Trades",
            "subcategory":"Construction",
            "type":"Services"
        }
    ],
    "sg:phone":"+1 541 592 4485",
    "sg:postcode":"97523",
    "sg:province":"OR",
    "sg:tags":[
        "concrete",
        "contractor"
    ],
    "wof:name":"Meidinger Concrete Constr",
    "wof:placetype":"venue"
},
  "geometry": {"coordinates":[-123.618239,42.054286],"type":"Point"}
}