{
  "type": "Feature",
  "properties": {
    "addr:full":"10721 NE Sandy Blvd Portland OR 97220",
    "addr:housenumber":"10721",
    "addr:postcode":"97220",
    "addr:street":"Ne Sandy Blvd",
    "iso:country":"US",
    "sg:address":"10721 NE Sandy Blvd",
    "sg:city":"Portland",
    "sg:classifiers":[
        {
            "category":"Retail",
            "subcategory":"Auto Rental",
            "type":"Services"
        },
        {
            "category":"Building & Trades",
            "subcategory":"Equipment Rental",
            "type":"Services"
        },
        {
            "category":"Retail",
            "subcategory":"Storage",
            "type":"Services"
        }
    ],
    "sg:phone":"+1 503 252 3368",
    "sg:postcode":"97220",
    "sg:province":"OR",
    "sg:tags":[
        "renting",
        "moving-self",
        "leasing",
        "truck",
        "van",
        "moving",
        "trailer"
    ],
    "sg:website":"http://www.budgettruck.com",
    "wof:name":"Budget Truck Rental",
    "wof:placetype":"venue"
},
  "geometry": {"coordinates":[-122.552483,45.55869],"type":"Point"}
}