{
  "type": "Feature",
  "properties": {
    "addr:full":"1180 SW McGinnis Ct Troutdale OR 97060",
    "addr:housenumber":"1180",
    "addr:postcode":"97060",
    "addr:street":"Sw Mcginnis Ct",
    "iso:country":"US",
    "sg:address":"1180 SW McGinnis Ct",
    "sg:city":"Troutdale",
    "sg:classifiers":[
        {
            "category":"Professional",
            "subcategory":"Advertising",
            "type":"Services"
        }
    ],
    "sg:phone":"+1 503 618 7488",
    "sg:postcode":"97060",
    "sg:province":"OR",
    "sg:tags":[
        "counselor"
    ],
    "wof:name":"Ad Tactics",
    "wof:placetype":"venue"
},
  "geometry": {"coordinates":[-122.403018,45.532916],"type":"Point"}
}