{
  "type": "Feature",
  "properties": {
    "addr:full":"1665 High St Eugene OR 97401",
    "addr:housenumber":"1665",
    "addr:postcode":"97401",
    "addr:street":"High St",
    "iso:country":"US",
    "sg:address":"1665 High St",
    "sg:city":"Eugene",
    "sg:classifiers":[
        {
            "category":"Professional",
            "subcategory":"Research",
            "type":"Services"
        }
    ],
    "sg:phone":"+1 541 683 2800",
    "sg:postcode":"97401",
    "sg:province":"OR",
    "wof:name":"Oregon Women's Research Ctr",
    "wof:placetype":"venue"
},
  "geometry": {"coordinates":[-123.088128,44.041844],"type":"Point"}
}