{
  "type": "Feature",
  "properties": {
    "iso:country":"US",
    "sg:address":"317 E 3rd St",
    "sg:city":"The Dalles",
    "sg:classifiers":[
        {
            "category":"Home & Garden",
            "subcategory":"Hardware",
            "type":"Retail Goods"
        }
    ],
    "sg:phone":"+1 541 296 8670",
    "sg:postcode":"97058",
    "sg:province":"OR",
    "wof:name":"Truserv Corporation",
    "wof:placetype":"venue"
},
  "geometry": {"coordinates":[-121.182369,45.600629],"type":"Point"}
}