{
  "type": "Feature",
  "properties": {
    "addr:full":"8900 SW Burnham St Portland OR 97223",
    "addr:housenumber":"8900",
    "addr:postcode":"97223",
    "addr:street":"Sw Burnham St",
    "iso:country":"US",
    "sg:address":"8900 SW Burnham St",
    "sg:city":"Portland",
    "sg:classifiers":[
        {
            "category":"Building & Trades",
            "subcategory":"Plumbing",
            "type":"Services"
        }
    ],
    "sg:phone":"+1 503 628 6841",
    "sg:postcode":"97223",
    "sg:province":"OR",
    "sg:tags":[
        "heating",
        "contractor"
    ],
    "wof:name":"Willamette Hvac",
    "wof:placetype":"venue"
},
  "geometry": {"coordinates":[-122.767714,45.42666],"type":"Point"}
}