{
  "type": "Feature",
  "properties": {
    "iso:country":"US",
    "sg:address":"12949 SW Walnut St",
    "sg:city":"Portland",
    "sg:classifiers":[
        {
            "category":"Personal",
            "subcategory":"Beauty Salon",
            "type":"Services"
        }
    ],
    "sg:phone":"+1 503 844 6907",
    "sg:postcode":"97223",
    "sg:province":"OR",
    "sg:tags":[
        "shop"
    ],
    "wof:name":"Laurianas Salon",
    "wof:placetype":"venue"
},
  "geometry": {"coordinates":[-122.810103,45.427798],"type":"Point"}
}