{
  "type": "Feature",
  "properties": {
    "iso:country":"US",
    "sg:address":"7516 SW MacAdam Ave",
    "sg:city":"Portland",
    "sg:classifiers":[
        {
            "category":"Retail",
            "subcategory":"Auto Repair",
            "type":"Services"
        }
    ],
    "sg:phone":"+1 503 246 2200",
    "sg:postcode":"97219",
    "sg:province":"OR",
    "sg:website":"www.autowerksnw.com/",
    "wof:name":"Autowerks NW",
    "wof:placetype":"venue"
},
  "geometry": {"coordinates":[-122.671469,45.470116],"type":"Point"}
}