{
  "type": "Feature",
  "properties": {
    "iso:country":"US",
    "sg:address":"34012 S Ellis Rd",
    "sg:city":"Molalla",
    "sg:classifiers":[
        {
            "category":"Farming",
            "subcategory":"Farm",
            "type":"Manufacturing & Wholesale Goods"
        }
    ],
    "sg:phone":"+1 503 829 9159",
    "sg:postcode":"97038",
    "sg:province":"OR",
    "sg:tags":[
        "crop",
        "general"
    ],
    "wof:name":"Power Line Farms",
    "wof:placetype":"venue"
},
  "geometry": {"coordinates":[-122.543695,45.114227],"type":"Point"}
}