{
  "type": "Feature",
  "properties": {
    "addr:full":"935 NW Southwater Dr Roseburg OR 97471",
    "addr:housenumber":"935",
    "addr:postcode":"97471",
    "addr:street":"Nw Southwater Dr",
    "iso:country":"US",
    "sg:address":"935 NW Southwater Dr",
    "sg:city":"Roseburg",
    "sg:classifiers":[
        {
            "category":"Building & Trades",
            "subcategory":"Landscaping Services",
            "type":"Services"
        }
    ],
    "sg:phone":"+1 541 672 6058",
    "sg:postcode":"97471",
    "sg:province":"OR",
    "sg:tags":[
        "tree"
    ],
    "wof:name":"Beals Mountain Tree Farm",
    "wof:placetype":"venue"
},
  "geometry": {"coordinates":[-123.37779999999999,43.219341],"type":"Point"}
}