{
  "type": "Feature",
  "properties": {
    "addr:full":"1206 N Hayden Meadows Drive Portland OR 97217",
    "addr:housenumber":"1206",
    "addr:postcode":"97217",
    "addr:street":"N Hayden Meadows Drive",
    "iso:country":"US",
    "sg:address":"1206 N Hayden Meadows Drive",
    "sg:city":"Portland",
    "sg:classifiers":[
        {
            "category":"Shopping",
            "subcategory":"Bicycles & Sporting Goods",
            "type":"Retail Goods"
        }
    ],
    "sg:phone":"+1 503 286 1292",
    "sg:postcode":"97217",
    "sg:province":"OR",
    "wof:name":"Exercise Equipment Northwest",
    "wof:placetype":"venue"
},
  "geometry": {"coordinates":[-122.680183,45.593],"type":"Point"}
}