{
  "type": "Feature",
  "properties": {
    "iso:country":"US",
    "sg:address":"61131 S Hwy 97",
    "sg:city":"Bend",
    "sg:classifiers":[
        {
            "category":"Bars & Pubs",
            "type":"Food & Drink"
        }
    ],
    "sg:phone":"+1 541 388 8178",
    "sg:postcode":"97702",
    "sg:province":"OR",
    "sg:tags":[
        "drinking"
    ],
    "wof:name":"Timbers South",
    "wof:placetype":"venue"
},
  "geometry": {"coordinates":[-121.317847,44.017448],"type":"Point"}
}