{
  "type": "Feature",
  "properties": {
    "iso:country":"US",
    "sg:address":"7114 SE 18th Ave",
    "sg:city":"Portland",
    "sg:classifiers":[
        {
            "category":"Real Estate",
            "subcategory":"Architect",
            "type":"Services"
        }
    ],
    "sg:phone":"+1 503 236 5995",
    "sg:postcode":"97202",
    "sg:province":"OR",
    "sg:tags":[
        "architectural"
    ],
    "wof:name":"James E Hagerman Architect",
    "wof:placetype":"venue"
},
  "geometry": {"coordinates":[-122.646502,45.472734],"type":"Point"}
}