{
  "type": "Feature",
  "properties": {
    "iso:country":"US",
    "sg:address":"13123 SW Clearview Way",
    "sg:city":"Portland",
    "sg:classifiers":[
        {
            "category":"Professional",
            "subcategory":"Management & Consulting",
            "type":"Services"
        },
        {
            "category":"Professional",
            "subcategory":"Employment Agencies",
            "type":"Services"
        }
    ],
    "sg:phone":"+1 503 524 8565",
    "sg:postcode":"97223",
    "sg:province":"OR",
    "sg:tags":[
        "consultant",
        "resource",
        "human"
    ],
    "wof:name":"Outsrc Inc",
    "wof:placetype":"venue"
},
  "geometry": {"coordinates":[-122.812355,45.421847],"type":"Point"}
}