{
  "type": "Feature",
  "properties": {
    "iso:country":"US",
    "sg:address":"1520 Balboa St",
    "sg:city":"Eugene",
    "sg:classifiers":[
        {
            "category":"Education",
            "subcategory":"Special Training",
            "type":"Public Place"
        }
    ],
    "sg:phone":"+1 541 687 8353",
    "sg:postcode":"97408",
    "sg:province":"OR",
    "sg:tags":[
        "small",
        "educational",
        "business"
    ],
    "wof:name":"Oregon Counsel For Bus Educatn",
    "wof:placetype":"venue"
},
  "geometry": {"coordinates":[-123.089083,44.093399],"type":"Point"}
}