{
  "type": "Feature",
  "properties": {
    "iso:country":"US",
    "sg:address":"43957 US Hwy 26",
    "sg:city":"Seaside",
    "sg:classifiers":[
        {
            "category":"Building & Trades",
            "subcategory":"Construction",
            "type":"Services"
        }
    ],
    "sg:phone":"+1 503 755 2764",
    "sg:postcode":"97138",
    "sg:province":"OR",
    "sg:tags":[
        "rough",
        "framing",
        "contractor"
    ],
    "wof:name":"Pendergrass Construction",
    "wof:placetype":"venue"
},
  "geometry": {"coordinates":[-123.60816199999999,45.884177],"type":"Point"}
}