{
  "type": "Feature",
  "properties": {
    "iso:country":"US",
    "sg:address":"4335 Memorie Ln",
    "sg:city":"Klamath Falls",
    "sg:classifiers":[
        {
            "category":"Professional",
            "subcategory":"Management & Consulting",
            "type":"Services"
        }
    ],
    "sg:phone":"+1 541 883 6422",
    "sg:postcode":"97603",
    "sg:province":"OR",
    "wof:name":"Nursing Knowledge",
    "wof:placetype":"venue"
},
  "geometry": {"coordinates":[-121.735648,42.188412],"type":"Point"}
}