{
  "type": "Feature",
  "properties": {
    "iso:country":"US",
    "sg:address":"230 E Main St",
    "sg:city":"Lexington",
    "sg:classifiers":[
        {
            "category":"Shopping",
            "subcategory":"Clothing, Apparel, & Fashions",
            "type":"Retail Goods"
        }
    ],
    "sg:phone":"+1 541 377 4245",
    "sg:postcode":"97839",
    "sg:province":"OR",
    "sg:tags":[
        "accessory",
        "women's"
    ],
    "wof:name":"Waterfall Of Stitches",
    "wof:placetype":"venue"
},
  "geometry": {"coordinates":[-119.683899,45.444371],"type":"Point"}
}