{
  "type": "Feature",
  "properties": {
    "addr:full":"17025 SE McLoughlin Blvd Milwaukie OR 97267",
    "addr:postcode":"17025;97267",
    "addr:street":"Se Mcloughlin Blvd",
    "iso:country":"US",
    "sg:address":"17025 SE McLoughlin Blvd",
    "sg:city":"Milwaukie",
    "sg:classifiers":[
        {
            "category":"Personal",
            "type":"Services"
        }
    ],
    "sg:phone":"+1 503 786 1930",
    "sg:postcode":"97267",
    "sg:province":"OR",
    "sg:tags":[
        "electrolysis"
    ],
    "wof:name":"Electrolysis Plus By Carla",
    "wof:placetype":"venue"
},
  "geometry": {"coordinates":[-122.619709,45.400528],"type":"Point"}
}