{
  "type": "Feature",
  "properties": {
    "iso:country":"US",
    "sg:address":"310 NW Flanders St",
    "sg:city":"Portland",
    "sg:classifiers":[
        {
            "category":"Shopping",
            "subcategory":"Pharmacy",
            "type":"Retail Goods"
        }
    ],
    "sg:phone":"+1 503 827 3949",
    "sg:postcode":"97209",
    "sg:province":"OR",
    "wof:name":"Cascadia",
    "wof:placetype":"venue"
},
  "geometry": {"coordinates":[-122.674426,45.525878],"type":"Point"}
}