{
  "type": "Feature",
  "properties": {
    "iso:country":"US",
    "sg:address":"30424 SE Church Rd",
    "sg:city":"Boring",
    "sg:classifiers":[
        {
            "category":"Farming",
            "subcategory":"Nursery",
            "type":"Manufacturing & Wholesale Goods"
        }
    ],
    "sg:phone":"+1 503 663 5330",
    "sg:postcode":"97009",
    "sg:province":"OR",
    "sg:tags":[
        "ornamental"
    ],
    "wof:name":"K & J Nursery",
    "wof:placetype":"venue"
},
  "geometry": {"coordinates":[-122.354156,45.425231],"type":"Point"}
}