{
  "type": "Feature",
  "properties": {
    "addr:full":"222 Ollis Rd Cave Junction OR 97523",
    "addr:housenumber":"222",
    "addr:postcode":"97523",
    "addr:street":"Ollis Rd",
    "iso:country":"US",
    "sg:address":"222 Ollis Rd",
    "sg:city":"Cave Junction",
    "sg:classifiers":[
        {
            "category":"Real Estate",
            "subcategory":"Real Estate Operator",
            "type":"Services"
        }
    ],
    "sg:phone":"+1 541 592 2346",
    "sg:postcode":"97523",
    "sg:province":"OR",
    "sg:tags":[
        "mobile",
        "home",
        "community"
    ],
    "wof:name":"River Valley Village",
    "wof:placetype":"venue"
},
  "geometry": {"coordinates":[-123.65468799999999,42.172868],"type":"Point"}
}