{
  "type": "Feature",
  "properties": {
    "iso:country":"US",
    "sg:address":"7211 SE 62nd Ave",
    "sg:city":"Portland",
    "sg:classifiers":[
        {
            "category":"Social Services",
            "type":"Services"
        },
        {
            "category":"Government",
            "subcategory":"Office",
            "type":"Public Place"
        }
    ],
    "sg:phone":"+1 503 988 5961",
    "sg:postcode":"97206",
    "sg:province":"OR",
    "sg:tags":[
        "recreation",
        "executive",
        "center",
        "welfare"
    ],
    "sg:website":"http://impactnw.org",
    "wof:name":"Brentwood Darlington Comm Ctr",
    "wof:placetype":"venue"
},
  "geometry": {"coordinates":[-122.599582,45.470827],"type":"Point"}
}