{
  "type": "Feature",
  "properties": {
    "iso:country":"US",
    "sg:address":"690 Black Oak Dr",
    "sg:city":"Medford",
    "sg:classifiers":[
        {
            "category":"Professional",
            "subcategory":"Computer Services",
            "type":"Services"
        }
    ],
    "sg:phone":"+1 541 779 2440",
    "sg:postcode":"97504",
    "sg:province":"OR",
    "sg:tags":[
        "related"
    ],
    "wof:name":"z Tutor",
    "wof:placetype":"venue"
},
  "geometry": {"coordinates":[-122.835744,42.318862],"type":"Point"}
}