{
  "type": "Feature",
  "properties": {
    "addr:full":"61543 American Loop Bend OR 97702",
    "addr:housenumber":"61543",
    "addr:postcode":"97702",
    "addr:street":"American Loop",
    "iso:country":"US",
    "sg:address":"61543 American Loop",
    "sg:city":"Bend",
    "sg:classifiers":[
        {
            "category":"Manufacturing",
            "subcategory":"Tools & Machinery",
            "type":"Manufacturing & Wholesale Goods"
        }
    ],
    "sg:phone":"+1 541 388 2015",
    "sg:postcode":"97702",
    "sg:province":"OR",
    "sg:tags":[
        "woodworking",
        "industrial",
        "mfg"
    ],
    "wof:name":"Complete Millwright Services",
    "wof:placetype":"venue"
},
  "geometry": {"coordinates":[-121.29212800000001,44.036459],"type":"Point"}
}