{
  "type": "Feature",
  "properties": {
    "addr:full":"5371 Wocus Rd Klamath Falls OR 97601",
    "addr:housenumber":"5371",
    "addr:postcode":"97601",
    "addr:street":"Wocus Rd",
    "iso:country":"US",
    "sg:address":"5371 Wocus Rd",
    "sg:city":"Klamath Falls",
    "sg:classifiers":[
        {
            "category":"Building & Trades",
            "subcategory":"Construction",
            "type":"Services"
        }
    ],
    "sg:phone":"+1 541 883 8747",
    "sg:postcode":"97601",
    "sg:province":"OR",
    "sg:tags":[
        "contractor"
    ],
    "wof:name":"Tri R Contracting LLC",
    "wof:placetype":"venue"
},
  "geometry": {"coordinates":[-121.807759,42.279435],"type":"Point"}
}