{
  "type": "Feature",
  "properties": {
    "addr:full":"691 Murphy Rd Medford OR 97504",
    "addr:housenumber":"691",
    "addr:postcode":"97504",
    "addr:street":"Murphy Rd",
    "iso:country":"US",
    "sg:address":"691 Murphy Rd",
    "sg:city":"Medford",
    "sg:classifiers":[
        {
            "category":"Health Services",
            "subcategory":"Doctor",
            "type":"Services"
        }
    ],
    "sg:phone":"+1 541 608 7511",
    "sg:postcode":"97504",
    "sg:province":"OR",
    "sg:tags":[
        "physician",
        "surgeon",
        "osteopathic"
    ],
    "wof:name":"Osteoporosis Center",
    "wof:placetype":"venue"
},
  "geometry": {"coordinates":[-122.82876,42.318249],"type":"Point"}
}