{
  "type": "Feature",
  "properties": {
    "iso:country":"US",
    "sg:address":"1001 SE Water Ave",
    "sg:city":"Portland",
    "sg:classifiers":[
        {
            "category":"Communications",
            "subcategory":"Film & Video Production",
            "type":"Services"
        }
    ],
    "sg:phone":"+1 503 239 1956",
    "sg:postcode":"97214",
    "sg:province":"OR",
    "sg:tags":[
        "services-commercial"
    ],
    "wof:name":"Shaka Brah Video Prod",
    "wof:placetype":"venue"
},
  "geometry": {"coordinates":[-122.66580999999999,45.515808],"type":"Point"}
}