{
  "type": "Feature",
  "properties": {
    "iso:country":"US",
    "sg:address":"175 NW Gilbert Way",
    "sg:city":"Newport",
    "sg:classifiers":[
        {
            "category":"Professional",
            "subcategory":"Business Services",
            "type":"Services"
        }
    ],
    "sg:phone":"+1 541 265 8746",
    "sg:postcode":"97365",
    "sg:province":"OR",
    "sg:tags":[
        "reservation",
        "motel",
        "hotel"
    ],
    "wof:name":"Agate Beach Motel",
    "wof:placetype":"venue"
},
  "geometry": {"coordinates":[-124.060714,44.673787],"type":"Point"}
}