{
  "type": "Feature",
  "properties": {
    "addr:full":"6623 NE 78th Ct Portland OR 97218",
    "addr:housenumber":"6623",
    "addr:postcode":"97218",
    "addr:street":"Ne 78Th Ct",
    "iso:country":"US",
    "sg:address":"6623 NE 78th Ct",
    "sg:city":"Portland",
    "sg:classifiers":[
        {
            "category":"Transit Center",
            "subcategory":"Freight",
            "type":"Transportation"
        }
    ],
    "sg:phone":"+1 503 255 2822",
    "sg:postcode":"97218",
    "sg:province":"OR",
    "sg:tags":[
        "forwarding",
        "container",
        "broker"
    ],
    "sg:website":"http://www.usnw.com",
    "wof:name":"Us Northwest Express",
    "wof:placetype":"venue"
},
  "geometry": {"coordinates":[-122.58143699999999,45.56954],"type":"Point"}
}