{
  "type": "Feature",
  "properties": {
    "iso:country":"US",
    "sg:address":"40 S Gun Club Rd",
    "sg:city":"Independence",
    "sg:classifiers":[
        {
            "category":"Professional",
            "subcategory":"Art Services",
            "type":"Services"
        }
    ],
    "sg:phone":"+1 503 838 2118",
    "sg:postcode":"97351",
    "sg:province":"OR",
    "sg:tags":[
        "commercial",
        "design"
    ],
    "wof:name":"West Coast Photo Graphics",
    "wof:placetype":"venue"
},
  "geometry": {"coordinates":[-123.20618399999999,44.853911],"type":"Point"}
}