{
  "type": "Feature",
  "properties": {
    "iso:country":"US",
    "sg:address":"3760 SE Hawthorne Blvd",
    "sg:city":"Portland",
    "sg:classifiers":[
        {
            "category":"Shopping",
            "subcategory":"Computers & Home Electronics",
            "type":"Retail Goods"
        }
    ],
    "sg:phone":"+1 503 234 5341",
    "sg:postcode":"97214",
    "sg:province":"OR",
    "sg:tags":[
        "equipment",
        "electronic",
        "supply"
    ],
    "sg:website":"fredsoundofmusic.com",
    "wof:name":"Fred's Sound of Music Audio Video",
    "wof:placetype":"venue"
},
  "geometry": {"coordinates":[-122.624753,45.51163],"type":"Point"}
}