{
  "type": "Feature",
  "properties": {
    "iso:country":"US",
    "sg:address":"1575 SW Cypress Ln",
    "sg:city":"Mcminnville",
    "sg:classifiers":[
        {
            "category":"Retail",
            "subcategory":"Auto Repair",
            "type":"Services"
        }
    ],
    "sg:phone":"+1 503 472 2342",
    "sg:postcode":"97128",
    "sg:province":"OR",
    "sg:tags":[
        "general"
    ],
    "wof:name":"Roys Mobile Rv Repair",
    "wof:placetype":"venue"
},
  "geometry": {"coordinates":[-123.2197,45.194857],"type":"Point"}
}