{
  "type": "Feature",
  "properties": {
    "addr:full":"2155 Etna St Klamath Falls OR 97603",
    "addr:housenumber":"2155",
    "addr:postcode":"97603",
    "addr:street":"Etna St",
    "iso:country":"US",
    "sg:address":"2155 Etna St",
    "sg:city":"Klamath Falls",
    "sg:classifiers":[
        {
            "category":"Building & Trades",
            "subcategory":"Landscaping Services",
            "type":"Services"
        }
    ],
    "sg:phone":"+1 541 884 1177",
    "sg:postcode":"97603",
    "sg:province":"OR",
    "sg:tags":[
        "landscape",
        "contractor"
    ],
    "wof:name":"Horizon Garden & Landscape",
    "wof:placetype":"venue"
},
  "geometry": {"coordinates":[-121.73642599999999,42.207607],"type":"Point"}
}