{
  "type": "Feature",
  "properties": {
    "addr:full":"3121 SW Iowa St Portland OR 97239",
    "addr:housenumber":"3121",
    "addr:postcode":"97239",
    "addr:street":"Sw Iowa St",
    "iso:country":"US",
    "sg:address":"3121 SW Iowa St",
    "sg:city":"Portland",
    "sg:classifiers":[
        {
            "category":"Professional",
            "type":"Services"
        }
    ],
    "sg:phone":"+1 503 245 3009",
    "sg:postcode":"97239",
    "sg:province":"OR",
    "sg:website":"www.songbirdindex.com",
    "wof:name":"Songbird Indexing Svc Ioi",
    "wof:placetype":"venue"
},
  "geometry": {"coordinates":[-122.70772700000001,45.479659],"type":"Point"}
}