{
  "type": "Feature",
  "properties": {
    "addr:full":"710 W Hermiston Ave Hermiston OR 97838",
    "addr:housenumber":"710",
    "addr:postcode":"97838",
    "addr:street":"W Hermiston Ave",
    "iso:country":"US",
    "sg:address":"710 W Hermiston Ave",
    "sg:city":"Hermiston",
    "sg:classifiers":[
        {
            "category":"Autos & Motor Vehicles",
            "subcategory":"Fuel & Gas Station",
            "type":"Retail Goods"
        }
    ],
    "sg:phone":"+1 541 567 0202",
    "sg:postcode":"97838",
    "sg:province":"OR",
    "sg:tags":[
        "oil"
    ],
    "wof:name":"Westside 76 & Food Mart",
    "wof:placetype":"venue"
},
  "geometry": {"coordinates":[-119.300867,45.840604],"type":"Point"}
}