{
  "type": "Feature",
  "properties": {
    "addr:full":"709 S Riverside Ave Medford OR 97501",
    "addr:housenumber":"709",
    "addr:postcode":"97501",
    "addr:street":"S Riverside Ave",
    "iso:country":"US",
    "sg:address":"709 S Riverside Ave",
    "sg:city":"Medford",
    "sg:classifiers":[
        {
            "category":"Shopping",
            "subcategory":"Optical Goods",
            "type":"Retail Goods"
        },
        {
            "category":"Health Services",
            "subcategory":"Optometrist",
            "type":"Services"
        },
        {
            "category":"Personal",
            "subcategory":"Shoe Repair & Shine",
            "type":"Services"
        }
    ],
    "sg:phone":"+1 541 776 3718",
    "sg:postcode":"97501",
    "sg:province":"OR",
    "sg:tags":[
        "lens",
        "eyeglass",
        "contact",
        "sunglass"
    ],
    "sg:website":"http://www.riversidevisioncare.com",
    "wof:name":"Riverside Vision Care",
    "wof:placetype":"venue"
},
  "geometry": {"coordinates":[-122.86597399999999,42.320712],"type":"Point"}
}