{
  "type": "Feature",
  "properties": {
    "iso:country":"US",
    "sg:address":"141 N Broadway",
    "sg:city":"Coos Bay",
    "sg:classifiers":[
        {
            "category":"Real Estate",
            "subcategory":"Real Estate Agent",
            "type":"Services"
        }
    ],
    "sg:phone":"+1 541 269 4650",
    "sg:postcode":"97420",
    "sg:province":"OR",
    "wof:name":"Evergreen Pacific Mortgage Inc",
    "wof:placetype":"venue"
},
  "geometry": {"coordinates":[-124.213246,43.368374],"type":"Point"}
}