{
  "type": "Feature",
  "properties": {
    "iso:country":"US",
    "sg:address":"9300 SW Beaverton Hillsdale Hwy",
    "sg:city":"Beaverton",
    "sg:classifiers":[
        {
            "category":"Personal",
            "type":"Services"
        },
        {
            "category":"Sports & Exercise",
            "subcategory":"Bowling",
            "type":"Entertainment"
        }
    ],
    "sg:phone":"+1 503 292 3523",
    "sg:postcode":"97005",
    "sg:province":"OR",
    "sg:tags":[
        "party",
        "planning",
        "event"
    ],
    "sg:website":"www.valleylanes.com/",
    "wof:name":"Valley Lanes",
    "wof:placetype":"venue"
},
  "geometry": {"coordinates":[-122.772313,45.48504],"type":"Point"}
}