{
  "type": "Feature",
  "properties": {
    "iso:country":"US",
    "sg:address":"25304 Oak Ln",
    "sg:city":"Philomath",
    "sg:classifiers":[
        {
            "category":"Building & Trades",
            "subcategory":"Construction",
            "type":"Services"
        }
    ],
    "sg:phone":"+1 541 929 5238",
    "sg:postcode":"97370",
    "sg:province":"OR",
    "sg:tags":[
        "contractor"
    ],
    "wof:name":"Mc Ginty Building",
    "wof:placetype":"venue"
},
  "geometry": {"coordinates":[-123.366478,44.510887],"type":"Point"}
}