{
  "type": "Feature",
  "properties": {
    "iso:country":"US",
    "sg:address":"5061 NW Hemlock Ave",
    "sg:city":"Redmond",
    "sg:classifiers":[
        {
            "category":"Health Services",
            "subcategory":"Health Practitioner",
            "type":"Services"
        }
    ],
    "sg:phone":"+1 541 923 9708",
    "sg:postcode":"97756",
    "sg:province":"OR",
    "sg:tags":[
        "acupuncture",
        "medicine",
        "alternative"
    ],
    "wof:name":"Barbara Baldwin",
    "wof:placetype":"venue"
},
  "geometry": {"coordinates":[-121.228808,44.283852],"type":"Point"}
}