{
  "type": "Feature",
  "properties": {
    "iso:country":"US",
    "sg:address":"455 N Columbia St",
    "sg:city":"Milton Freewater",
    "sg:classifiers":[
        {
            "category":"Food & Beverages",
            "subcategory":"Groceries & Convenience Stores",
            "type":"Retail Goods"
        }
    ],
    "sg:phone":"+1 541 938 5341",
    "sg:postcode":"97862",
    "sg:province":"OR",
    "wof:name":"Safeway",
    "wof:placetype":"venue"
},
  "geometry": {"coordinates":[-118.38767900000001,45.940686],"type":"Point"}
}