{
  "type": "Feature",
  "properties": {
    "iso:country":"US",
    "sg:address":"30827 Beaver Homes Rd",
    "sg:city":"Rainier",
    "sg:classifiers":[
        {
            "category":"Building & Trades",
            "subcategory":"Electrical",
            "type":"Services"
        }
    ],
    "sg:phone":"+1 503 556 2548",
    "sg:postcode":"97048",
    "sg:province":"OR",
    "sg:tags":[
        "electrical",
        "electric",
        "contractor"
    ],
    "wof:name":"Allen's Electric",
    "wof:placetype":"venue"
},
  "geometry": {"coordinates":[-122.928658,46.004133],"type":"Point"}
}