{
  "type": "Feature",
  "properties": {
    "addr:full":"3615 Highway 101 N Seaside OR 97138",
    "addr:housenumber":"3615",
    "addr:postcode":"97138",
    "addr:street":"Highway 101 N",
    "iso:country":"US",
    "sg:address":"3615 Highway 101 N",
    "sg:city":"Seaside",
    "sg:classifiers":[
        {
            "category":"Restaurant",
            "type":"Food & Drink"
        }
    ],
    "sg:phone":"+1 503 717 9123",
    "sg:postcode":"97138",
    "sg:province":"OR",
    "sg:tags":[
        "mexican"
    ],
    "wof:name":"El Mariachi Mexican Restaurant",
    "wof:placetype":"venue"
},
  "geometry": {"coordinates":[-123.912537,46.03013],"type":"Point"}
}