{
  "type": "Feature",
  "properties": {
    "iso:country":"US",
    "sg:address":"4545 SE Aldercrest Rd",
    "sg:city":"Portland",
    "sg:classifiers":[
        {
            "category":"Real Estate",
            "subcategory":"Developer",
            "type":"Services"
        }
    ],
    "sg:phone":"+1 503 201 4663",
    "sg:postcode":"97222",
    "sg:province":"OR",
    "wof:name":"Tucker Construction",
    "wof:placetype":"venue"
},
  "geometry": {"coordinates":[-122.619539,45.426062],"type":"Point"}
}