{
  "type": "Feature",
  "properties": {
    "iso:country":"US",
    "sg:address":"120 NW 10th Ave",
    "sg:city":"Portland",
    "sg:classifiers":[
        {
            "category":"Food & Beverages",
            "subcategory":"Specialty",
            "type":"Retail Goods"
        },
        {
            "category":"Food & Beverages",
            "subcategory":"Groceries & Convenience Stores",
            "type":"Retail Goods"
        }
    ],
    "sg:phone":"+1 503 227 6777",
    "sg:postcode":"97209",
    "sg:province":"OR",
    "sg:website":"www.penzys.com",
    "wof:name":"Penzeys Spices",
    "wof:placetype":"venue"
},
  "geometry": {"coordinates":[-122.680837,45.524195],"type":"Point"}
}