{
  "type": "Feature",
  "properties": {
    "iso:country":"US",
    "sg:address":"1180 S Park St",
    "sg:city":"Lebanon",
    "sg:classifiers":[
        {
            "category":"Health Services",
            "subcategory":"Doctor",
            "type":"Services"
        }
    ],
    "sg:phone":"+1 541 451 1991",
    "sg:postcode":"97355",
    "sg:province":"OR",
    "sg:tags":[
        "dentist"
    ],
    "wof:name":"Mid-Valley Dental",
    "wof:placetype":"venue"
},
  "geometry": {"coordinates":[-122.906746,44.534563],"type":"Point"}
}