{
  "type": "Feature",
  "properties": {
    "addr:full":"917 SW Oak St Portland OR 97205",
    "addr:housenumber":"917",
    "addr:postcode":"97205",
    "addr:street":"Sw Oak St",
    "iso:country":"US",
    "sg:address":"917 SW Oak St",
    "sg:city":"Portland",
    "sg:classifiers":[
        {
            "category":"Professional",
            "subcategory":"Art Services",
            "type":"Services"
        }
    ],
    "sg:phone":"+1 971 322 3907",
    "sg:postcode":"97205",
    "sg:province":"OR",
    "sg:tags":[
        "designer",
        "display",
        "producer"
    ],
    "wof:name":"Psilo Design Group",
    "wof:placetype":"venue"
},
  "geometry": {"coordinates":[-122.680232,45.522554],"type":"Point"}
}