{
  "type": "Feature",
  "properties": {
    "addr:full":"27037 S Shibley Rd Colton OR 97017",
    "addr:housenumber":"27037",
    "addr:postcode":"97017",
    "addr:street":"S Shibley Rd",
    "iso:country":"US",
    "sg:address":"27037 S Shibley Rd",
    "sg:city":"Colton",
    "sg:classifiers":[
        {
            "category":"Building & Trades",
            "subcategory":"Construction",
            "type":"Services"
        }
    ],
    "sg:phone":"+1 503 558 8180",
    "sg:postcode":"97017",
    "sg:province":"OR",
    "sg:tags":[
        "general",
        "contractor"
    ],
    "wof:name":"Scott Bever Construction",
    "wof:placetype":"venue"
},
  "geometry": {"coordinates":[-122.352779,45.214472],"type":"Point"}
}