{
  "type": "Feature",
  "properties": {
    "addr:full":"1240 SE Gideon St Portland OR 97202",
    "addr:housenumber":"1240",
    "addr:postcode":"97202",
    "addr:street":"Se Gideon St",
    "iso:country":"US",
    "sg:address":"1240 SE Gideon St",
    "sg:city":"Portland",
    "sg:classifiers":[
        {
            "category":"Industrial Area",
            "type":"Public Place"
        }
    ],
    "sg:phone":"+1 503 234 8617",
    "sg:postcode":"97202",
    "sg:province":"OR",
    "sg:tags":[
        "development"
    ],
    "wof:name":"Freeway Industries Inc",
    "wof:placetype":"venue"
},
  "geometry": {"coordinates":[-122.65368100000001,45.502791],"type":"Point"}
}