{
  "type": "Feature",
  "properties": {
    "addr:full":"515 NE Roberts Ave Gresham OR 97030",
    "addr:housenumber":"515",
    "addr:postcode":"97030",
    "addr:street":"Ne Roberts Ave",
    "iso:country":"US",
    "sg:address":"515 NE Roberts Ave",
    "sg:city":"Gresham",
    "sg:classifiers":[
        {
            "category":"Health Services",
            "subcategory":"Clinic",
            "type":"Services"
        }
    ],
    "sg:phone":"+1 503 674 7059",
    "sg:postcode":"97030",
    "sg:province":"OR",
    "sg:tags":[
        "holistic",
        "practitioner"
    ],
    "wof:name":"K I Ctr For Holistic Healing",
    "wof:placetype":"venue"
},
  "geometry": {"coordinates":[-122.429726,45.50298],"type":"Point"}
}