{
  "type": "Feature",
  "properties": {
    "addr:full":"11540 SE Foster Rd Portland OR 97266",
    "addr:housenumber":"11540",
    "addr:postcode":"97266",
    "addr:street":"Se Foster Rd",
    "iso:country":"US",
    "sg:address":"11540 SE Foster Rd",
    "sg:city":"Portland",
    "sg:classifiers":[
        {
            "category":"Restaurant",
            "type":"Food & Drink"
        }
    ],
    "sg:phone":"+1 503 762 9190",
    "sg:postcode":"97266",
    "sg:province":"OR",
    "sg:tags":[
        "shop",
        "coffee"
    ],
    "wof:name":"B's Coffee Cabana",
    "wof:placetype":"venue"
},
  "geometry": {"coordinates":[-122.54516700000001,45.476348],"type":"Point"}
}