{
  "type": "Feature",
  "properties": {
    "iso:country":"US",
    "sg:address":"8123 SE 17th Ave",
    "sg:city":"Portland",
    "sg:classifiers":[
        {
            "category":"Manufacturing",
            "subcategory":"Printing",
            "type":"Manufacturing & Wholesale Goods"
        }
    ],
    "sg:phone":"+1 503 234 4540",
    "sg:postcode":"97202",
    "sg:province":"OR",
    "sg:tags":[
        "printer",
        "commercial",
        "form"
    ],
    "wof:name":"Willamette Valley Printing",
    "wof:placetype":"venue"
},
  "geometry": {"coordinates":[-122.647114,45.463766],"type":"Point"}
}