{
  "type": "Feature",
  "properties": {
    "addr:full":"12751 SW 2nd St Beaverton OR 97005",
    "addr:housenumber":"12751",
    "addr:postcode":"97005",
    "addr:street":"Sw 2Nd St",
    "iso:country":"US",
    "sg:address":"12751 SW 2nd St",
    "sg:city":"Beaverton",
    "sg:classifiers":[
        {
            "category":"Health Services",
            "subcategory":"Dentist",
            "type":"Services"
        }
    ],
    "sg:phone":"+1 503 644 3312",
    "sg:postcode":"97005",
    "sg:province":"OR",
    "wof:name":"Nguyen Thao",
    "wof:placetype":"venue"
},
  "geometry": {"coordinates":[-122.807999,45.485802],"type":"Point"}
}