{
  "type": "Feature",
  "properties": {
    "addr:full":"304 1st St Rufus OR 97050",
    "addr:housenumber":"304",
    "addr:postcode":"97050",
    "addr:street":"1St St",
    "iso:country":"US",
    "sg:address":"304 1st St",
    "sg:city":"Rufus",
    "sg:classifiers":[
        {
            "category":"Travel",
            "subcategory":"Hotels & Motels",
            "type":"Entertainment"
        }
    ],
    "sg:phone":"+1 541 739 2310",
    "sg:postcode":"97050",
    "sg:province":"OR",
    "wof:name":"Tyee Motel",
    "wof:placetype":"venue"
},
  "geometry": {"coordinates":[-120.731116,45.696723],"type":"Point"}
}