{
  "type": "Feature",
  "properties": {
    "iso:country":"US",
    "sg:address":"14500 Old Mehama Rd SE",
    "sg:city":"Stayton",
    "sg:classifiers":[
        {
            "category":"Food & Beverages",
            "subcategory":"Fruits & Vegetables",
            "type":"Retail Goods"
        }
    ],
    "sg:phone":"+1 503 769 7260",
    "sg:postcode":"97383",
    "sg:province":"OR",
    "sg:tags":[
        "produce"
    ],
    "wof:name":"East Santiam Produce",
    "wof:placetype":"venue"
},
  "geometry": {"coordinates":[-122.75637399999999,44.800636],"type":"Point"}
}