{
  "type": "Feature",
  "properties": {
    "addr:full":"131 NW Hawthorne Ave Bend OR 97701",
    "addr:housenumber":"131",
    "addr:postcode":"97701",
    "addr:street":"Nw Hawthorne Ave",
    "iso:country":"US",
    "sg:address":"131 NW Hawthorne Ave",
    "sg:city":"Bend",
    "sg:classifiers":[
        {
            "category":"Health Services",
            "subcategory":"Health Practitioner",
            "type":"Services"
        }
    ],
    "sg:phone":"+1 541 388 3592",
    "sg:postcode":"97701",
    "sg:province":"OR",
    "wof:name":"Barram R Andrew Psy D",
    "wof:placetype":"venue"
},
  "geometry": {"coordinates":[-121.30923300000001,44.057877],"type":"Point"}
}