{
  "type": "Feature",
  "properties": {
    "iso:country":"US",
    "sg:address":"190 S Main St",
    "sg:city":"Winston",
    "sg:classifiers":[
        {
            "category":"Cinema",
            "subcategory":"Movie Rental",
            "type":"Entertainment"
        }
    ],
    "sg:phone":"+1 541 679 9355",
    "sg:postcode":"97496",
    "sg:province":"OR",
    "sg:tags":[
        "leasing",
        "video",
        "disc",
        "tape"
    ],
    "wof:name":"All That Video",
    "wof:placetype":"venue"
},
  "geometry": {"coordinates":[-123.413314,43.120655],"type":"Point"}
}