{
  "type": "Feature",
  "properties": {
    "iso:country":"US",
    "sg:address":"6650 SW Redwood Lane",
    "sg:city":"Portland",
    "sg:classifiers":[
        {
            "category":"Building & Trades",
            "subcategory":"Construction",
            "type":"Services"
        }
    ],
    "sg:phone":"+1 503 274 4442",
    "sg:postcode":"97224",
    "sg:province":"OR",
    "sg:tags":[
        "contractor"
    ],
    "wof:name":"Panattoni Companies",
    "wof:placetype":"venue"
},
  "geometry": {"coordinates":[-122.74635000000001,45.4096],"type":"Point"}
}