{
  "type": "Feature",
  "properties": {
    "iso:country":"US",
    "sg:address":"711 Medford Center",
    "sg:city":"Medford",
    "sg:classifiers":[
        {
            "category":"Organizations",
            "subcategory":"Non-profit Organization",
            "type":"Services"
        }
    ],
    "sg:phone":"+1 541 282 5540",
    "sg:postcode":"97504",
    "sg:province":"OR",
    "sg:tags":[
        "charitable",
        "institution"
    ],
    "wof:name":"Open Hands Open Hearts",
    "wof:placetype":"venue"
},
  "geometry": {"coordinates":[-122.867294,42.331131],"type":"Point"}
}