{
  "type": "Feature",
  "properties": {
    "addr:full":"12790 SE Stark St # 206 Portland OR 97233",
    "addr:postcode":"12790;97233",
    "addr:street":"Se Stark St # 206",
    "iso:country":"US",
    "sg:address":"12790 SE Stark St # 206",
    "sg:city":"Portland",
    "sg:phone":"+1 503 771 1166",
    "sg:postcode":"97233",
    "sg:province":"OR",
    "wof:name":"Northwest Technical Institute",
    "wof:placetype":"venue"
},
  "geometry": {"coordinates":[-122.53179299999999,45.51907],"type":"Point"}
}