{
  "type": "Feature",
  "properties": {
    "iso:country":"US",
    "sg:address":"1972 NE 3rd St",
    "sg:city":"Bend",
    "sg:classifiers":[
        {
            "category":"Recreation",
            "type":"Entertainment"
        }
    ],
    "sg:phone":"+1 541 389 5640",
    "sg:postcode":"97701",
    "sg:province":"OR",
    "sg:tags":[
        "equipment",
        "rental"
    ],
    "wof:name":"Fantastic Recreation Rentals",
    "wof:placetype":"venue"
},
  "geometry": {"coordinates":[-121.302445,44.068895],"type":"Point"}
}