{
  "type": "Feature",
  "properties": {
    "iso:country":"US",
    "sg:address":"136 SW Valentine Ave",
    "sg:city":"Sutherlin",
    "sg:classifiers":[
        {
            "category":"Retail",
            "subcategory":"Auto Repair",
            "type":"Services"
        }
    ],
    "sg:phone":"+1 541 459 5502",
    "sg:postcode":"97479",
    "sg:province":"OR",
    "sg:tags":[
        "general"
    ],
    "wof:name":"KB Automotive",
    "wof:placetype":"venue"
},
  "geometry": {"coordinates":[-123.314758,43.38688],"type":"Point"}
}