{
  "type": "Feature",
  "properties": {
    "iso:country":"US",
    "sg:address":"54850 McKenzie River Dr",
    "sg:city":"Blue River",
    "sg:classifiers":[
        {
            "category":"Professional",
            "subcategory":"Business Services",
            "type":"Services"
        }
    ],
    "sg:phone":"+1 541 822 1039",
    "sg:postcode":"97413",
    "sg:province":"OR",
    "wof:name":"Management Solutions Inc",
    "wof:placetype":"venue"
},
  "geometry": {"coordinates":[-122.22836,44.168291],"type":"Point"}
}