{
  "type": "Feature",
  "properties": {
    "addr:full":"45 SW 3rd St Warrenton OR 97146",
    "addr:housenumber":"45",
    "addr:postcode":"97146",
    "addr:street":"Sw 3Rd St",
    "iso:country":"US",
    "sg:address":"45 SW 3rd St",
    "sg:city":"Warrenton",
    "sg:classifiers":[
        {
            "category":"Retail",
            "subcategory":"Auto Repair",
            "type":"Services"
        }
    ],
    "sg:phone":"+1 503 861 1284",
    "sg:postcode":"97146",
    "sg:province":"OR",
    "sg:tags":[
        "body",
        "automobile",
        "painting"
    ],
    "wof:name":"Williamson Body Repair",
    "wof:placetype":"venue"
},
  "geometry": {"coordinates":[-123.926355,46.16255],"type":"Point"}
}