{
  "type": "Feature",
  "properties": {
    "iso:country":"US",
    "sg:address":"1191 E Grove St",
    "sg:city":"Vernonia",
    "sg:classifiers":[
        {
            "category":"Building & Trades",
            "subcategory":"Construction",
            "type":"Services"
        }
    ],
    "sg:phone":"+1 503 429 0162",
    "sg:postcode":"97064",
    "sg:province":"OR",
    "sg:tags":[
        "contractor"
    ],
    "wof:name":"Precision Building Maintenance",
    "wof:placetype":"venue"
},
  "geometry": {"coordinates":[-123.171645,45.861814],"type":"Point"}
}