{
  "type": "Feature",
  "properties": {
    "iso:country":"US",
    "sg:address":"155 13th St",
    "sg:city":"Lakeside",
    "sg:classifiers":[
        {
            "category":"Wholesale",
            "subcategory":"Electrical",
            "type":"Manufacturing & Wholesale Goods"
        }
    ],
    "sg:phone":"+1 541 759 2470",
    "sg:postcode":"97449",
    "sg:province":"OR",
    "sg:tags":[
        "control",
        "security",
        "system"
    ],
    "wof:name":"Walker Security",
    "wof:placetype":"venue"
},
  "geometry": {"coordinates":[-124.170267,43.577642],"type":"Point"}
}