{
  "type": "Feature",
  "properties": {
    "iso:country":"US",
    "sg:address":"6130 SW Alice Ln",
    "sg:city":"Beaverton",
    "sg:classifiers":[
        {
            "category":"Professional",
            "subcategory":"Management & Consulting",
            "type":"Services"
        }
    ],
    "sg:phone":"+1 503 626 3430",
    "sg:postcode":"97008",
    "sg:province":"OR",
    "sg:tags":[
        "retail",
        "direct",
        "sales"
    ],
    "wof:name":"Seasonal Fruit Juice Inc Wate",
    "wof:placetype":"venue"
},
  "geometry": {"coordinates":[-122.795149,45.476102],"type":"Point"}
}