{
  "type": "Feature",
  "properties": {
    "iso:country":"US",
    "sg:address":"244 NE Franklin Ave",
    "sg:city":"Bend",
    "sg:classifiers":[
        {
            "category":"Real Estate",
            "subcategory":"Real Estate Agent",
            "type":"Services"
        }
    ],
    "sg:phone":"+1 541 312 9449",
    "sg:postcode":"97701",
    "sg:province":"OR",
    "wof:name":"Pru-One Inc",
    "wof:placetype":"venue"
},
  "geometry": {"coordinates":[-121.30328299999999,44.056023],"type":"Point"}
}