{
  "type": "Feature",
  "properties": {
    "iso:country":"US",
    "sg:address":"3196 Sorrel Way",
    "sg:city":"Eugene",
    "sg:classifiers":[
        {
            "category":"Professional",
            "subcategory":"Business Services",
            "type":"Services"
        }
    ],
    "sg:phone":"+1 541 338 8265",
    "sg:postcode":"97401",
    "sg:province":"OR",
    "wof:name":"Home Team Enterprises LLC",
    "wof:placetype":"venue"
},
  "geometry": {"coordinates":[-123.061564,44.063662],"type":"Point"}
}