{
  "type": "Feature",
  "properties": {
    "addr:full":"5603 SW Hood Ave Portland OR 97239",
    "addr:housenumber":"5603",
    "addr:postcode":"97239",
    "addr:street":"Sw Hood Ave",
    "iso:country":"US",
    "sg:address":"5603 SW Hood Ave",
    "sg:city":"Portland",
    "sg:classifiers":[
        {
            "category":"Recreation",
            "type":"Entertainment"
        }
    ],
    "sg:phone":"+1 503 227 2681",
    "sg:postcode":"97239",
    "sg:province":"OR",
    "sg:tags":[
        "carnival"
    ],
    "sg:website":"www.rosefestival.org",
    "wof:name":"Portland Rose Festival Assn",
    "wof:placetype":"venue"
},
  "geometry": {"coordinates":[-122.674864,45.483137],"type":"Point"}
}