{
  "type": "Feature",
  "properties": {
    "iso:country":"US",
    "sg:address":"5340 Linn Ln",
    "sg:city":"West Linn",
    "sg:classifiers":[
        {
            "category":"Wholesale",
            "subcategory":"Toys & Hobbies",
            "type":"Manufacturing & Wholesale Goods"
        }
    ],
    "sg:phone":"+1 503 657 9333",
    "sg:postcode":"97068",
    "sg:province":"OR",
    "sg:tags":[
        "wholesaler"
    ],
    "wof:name":"M S Wholesale Co",
    "wof:placetype":"venue"
},
  "geometry": {"coordinates":[-122.632922,45.367163],"type":"Point"}
}