{
  "type": "Feature",
  "properties": {
    "addr:full":"1067 Lookingglass Rd Roseburg OR 97470",
    "addr:housenumber":"1067",
    "addr:postcode":"97470",
    "addr:street":"Lookingglass Rd",
    "iso:country":"US",
    "sg:address":"1067 Lookingglass Rd",
    "sg:city":"Roseburg",
    "sg:classifiers":[
        {
            "category":"Real Estate",
            "subcategory":"Real Estate Operator",
            "type":"Services"
        }
    ],
    "sg:phone":"+1 541 440 3777",
    "sg:postcode":"97470",
    "sg:province":"OR",
    "sg:tags":[
        "building",
        "apartment"
    ],
    "wof:name":"Westview Commons",
    "wof:placetype":"venue"
},
  "geometry": {"coordinates":[-123.38881000000001,43.210689],"type":"Point"}
}