{
  "type": "Feature",
  "properties": {
    "addr:full":"1327 SE Grand Ave Portland OR 97214",
    "addr:housenumber":"1327",
    "addr:postcode":"97214",
    "addr:street":"Se Grand Ave",
    "iso:country":"US",
    "sg:address":"1327 SE Grand Ave",
    "sg:city":"Portland",
    "sg:classifiers":[
        {
            "category":"Shopping",
            "subcategory":"Stationery & Office Supplies",
            "type":"Retail Goods"
        }
    ],
    "sg:phone":"+1 503 235 2800",
    "sg:postcode":"97214",
    "sg:province":"OR",
    "sg:tags":[
        "equipment"
    ],
    "sg:website":"www.portlandofficefurniture.com/",
    "wof:name":"Portland Office Furniture",
    "wof:placetype":"venue"
},
  "geometry": {"coordinates":[-122.660948,45.51329],"type":"Point"}
}