{
  "type": "Feature",
  "properties": {
    "iso:country":"US",
    "sg:address":"131 SW 19th St",
    "sg:city":"Bend",
    "sg:classifiers":[
        {
            "category":"Building & Trades",
            "subcategory":"Construction",
            "type":"Services"
        }
    ],
    "sg:phone":"+1 541 382 6258",
    "sg:postcode":"97702",
    "sg:province":"OR",
    "sg:tags":[
        "house"
    ],
    "wof:name":"Eiel S Eielson Construction",
    "wof:placetype":"venue"
},
  "geometry": {"coordinates":[-121.342082,44.049546],"type":"Point"}
}