{
  "type": "Feature",
  "properties": {
    "addr:full":"56835 Venture Ln Sunriver OR 97707",
    "addr:housenumber":"56835",
    "addr:postcode":"97707",
    "addr:street":"Venture Ln",
    "iso:country":"US",
    "sg:address":"56835 Venture Ln",
    "sg:city":"Sunriver",
    "sg:classifiers":[
        {
            "category":"Professional",
            "subcategory":"Accounting & Tax Preparation",
            "type":"Services"
        }
    ],
    "sg:phone":"+1 541 593 1114",
    "sg:postcode":"97707",
    "sg:province":"OR",
    "sg:tags":[
        "return",
        "filing"
    ],
    "wof:name":"Accountable Tax & Bookkeeping",
    "wof:placetype":"venue"
},
  "geometry": {"coordinates":[-121.435031,43.864623],"type":"Point"}
}