{
  "type": "Feature",
  "properties": {
    "iso:country":"US",
    "sg:address":"12 S Main St",
    "sg:city":"Joseph",
    "sg:classifiers":[
        {
            "category":"Home & Garden",
            "subcategory":"Home Furnishings",
            "type":"Retail Goods"
        }
    ],
    "sg:phone":"+1 541 432 2690",
    "sg:postcode":"97846",
    "sg:province":"OR",
    "sg:tags":[
        "fireplace"
    ],
    "wof:name":"Anton's Home & Hearth",
    "wof:placetype":"venue"
},
  "geometry": {"coordinates":[-117.229786,45.352301],"type":"Point"}
}