{
  "type": "Feature",
  "properties": {
    "iso:country":"US",
    "sg:address":"5933 NE Win Sivers Drive",
    "sg:city":"Portland",
    "sg:classifiers":[
        {
            "category":"Professional",
            "subcategory":"Employment Agencies",
            "type":"Services"
        }
    ],
    "sg:phone":"+1 503 262 8700",
    "sg:postcode":"97220",
    "sg:province":"OR",
    "sg:tags":[
        "opportunity"
    ],
    "sg:website":"http://www.optistaffing.com",
    "wof:name":"Opti Staffing Group",
    "wof:placetype":"venue"
},
  "geometry": {"coordinates":[-122.53795100000001,45.565362],"type":"Point"}
}