{
  "type": "Feature",
  "properties": {
    "iso:country":"US",
    "sg:address":"24023 NE Shea Ln",
    "sg:city":"Troutdale",
    "sg:classifiers":[
        {
            "category":"Shopping",
            "subcategory":"Computers & Home Electronics",
            "type":"Retail Goods"
        }
    ],
    "sg:phone":"+1 503 669 2600",
    "sg:postcode":"97060",
    "sg:province":"OR",
    "wof:name":"Dishworks Satellite Co Inc",
    "wof:placetype":"venue"
},
  "geometry": {"coordinates":[-122.415806,45.538857],"type":"Point"}
}