{
  "type": "Feature",
  "properties": {
    "iso:country":"US",
    "sg:address":"32071 Birdfoot Dr",
    "sg:city":"Tangent",
    "sg:classifiers":[
        {
            "category":"Manufacturing",
            "subcategory":"Chemicals & Compounds",
            "type":"Manufacturing & Wholesale Goods"
        }
    ],
    "sg:phone":"+1 541 928 8892",
    "sg:postcode":"97389",
    "sg:province":"OR",
    "sg:tags":[
        "product",
        "mfg"
    ],
    "wof:name":"K&H Supply Put",
    "wof:placetype":"venue"
},
  "geometry": {"coordinates":[-123.10722199999999,44.541317],"type":"Point"}
}