{
  "type": "Feature",
  "properties": {
    "iso:country":"US",
    "sg:address":"2214 NE Division St",
    "sg:city":"Bend",
    "sg:classifiers":[
        {
            "category":"Professional",
            "type":"Services"
        }
    ],
    "sg:phone":"+1 541 617 9120",
    "sg:postcode":"97701",
    "sg:province":"OR",
    "wof:name":"Hire Call",
    "wof:placetype":"venue"
},
  "geometry": {"coordinates":[-121.30595,44.071939],"type":"Point"}
}