{
  "type": "Feature",
  "properties": {
    "iso:country":"US",
    "sg:address":"213 S Pine St",
    "sg:city":"Carlton",
    "sg:classifiers":[
        {
            "category":"Winery",
            "type":"Food & Drink"
        }
    ],
    "sg:phone":"+1 503 852 0082",
    "sg:postcode":"97111",
    "sg:province":"OR",
    "sg:website":"thegrandcruestates.com/",
    "wof:name":"Sol?na Carlton Tasting Room",
    "wof:placetype":"venue"
},
  "geometry": {"coordinates":[-123.22199999999999,45.290798],"type":"Point"}
}