{
  "type": "Feature",
  "properties": {
    "addr:full":"6181 SW Erickson Ave Beaverton OR 97008",
    "addr:housenumber":"6181",
    "addr:postcode":"97008",
    "addr:street":"Sw Erickson Ave",
    "iso:country":"US",
    "sg:address":"6181 SW Erickson Ave",
    "sg:city":"Beaverton",
    "sg:classifiers":[
        {
            "category":"Manufacturing",
            "subcategory":"Printing",
            "type":"Manufacturing & Wholesale Goods"
        }
    ],
    "sg:phone":"+1 503 641 1672",
    "sg:postcode":"97008",
    "sg:province":"OR",
    "sg:tags":[
        "publisher"
    ],
    "wof:name":"Stuhmer Publications",
    "wof:placetype":"venue"
},
  "geometry": {"coordinates":[-122.812191,45.475216],"type":"Point"}
}