{
  "type": "Feature",
  "properties": {
    "addr:full":"6149 SW Murray Blvd Beaverton OR 97008",
    "addr:housenumber":"6149",
    "addr:postcode":"97008",
    "addr:street":"Sw Murray Blvd",
    "iso:country":"US",
    "sg:address":"6149 SW Murray Blvd",
    "sg:city":"Beaverton",
    "sg:classifiers":[
        {
            "category":"Insurance",
            "subcategory":"Hazard Insurance",
            "type":"Services"
        },
        {
            "category":"Insurance",
            "subcategory":"Insurance Agent",
            "type":"Services"
        },
        {
            "category":"Insurance",
            "subcategory":"Life Insurance",
            "type":"Services"
        },
        {
            "category":"Insurance",
            "subcategory":"Title Insurance",
            "type":"Services"
        }
    ],
    "sg:phone":"+1 503 641 5400",
    "sg:postcode":"97008",
    "sg:province":"OR",
    "sg:tags":[
        "auto",
        "homeowner"
    ],
    "sg:website":"http://www.nationwide.com/agent/Beaverton-OREGON-insurance-agent/john-dehlin-1/office.html",
    "wof:name":"Dehlin & Associates Inc - Nationwide Insurance",
    "wof:placetype":"venue"
},
  "geometry": {"coordinates":[-122.826116,45.47534],"type":"Point"}
}