{
  "type": "Feature",
  "properties": {
    "addr:full":"4319 NW Yeon Avenue Portland OR 97210",
    "addr:housenumber":"4319",
    "addr:postcode":"97210",
    "addr:street":"Nw Yeon Avenue",
    "iso:country":"US",
    "sg:address":"4319 NW Yeon Avenue",
    "sg:city":"Portland",
    "sg:classifiers":[
        {
            "category":"Travel",
            "subcategory":"Hotels & Motels",
            "type":"Entertainment"
        }
    ],
    "sg:phone":"+1 503 497 9044",
    "sg:postcode":"97210",
    "sg:province":"OR",
    "wof:name":"La Quinta Inn & Suites",
    "wof:placetype":"venue"
},
  "geometry": {"coordinates":[-122.72989099999999,45.553445],"type":"Point"}
}