{
  "type": "Feature",
  "properties": {
    "iso:country":"US",
    "sg:address":"85168 N Hideaway Hills Rd",
    "sg:city":"Eugene",
    "sg:classifiers":[
        {
            "category":"Professional",
            "type":"Services"
        }
    ],
    "sg:phone":"+1 541 485 8691",
    "sg:postcode":"97405",
    "sg:province":"OR",
    "wof:name":"Hideaway Hills Editing Service",
    "wof:placetype":"venue"
},
  "geometry": {"coordinates":[-123.039944,43.975123],"type":"Point"}
}