{
  "type": "Feature",
  "properties": {
    "iso:country":"US",
    "sg:address":"3220 SW Sherwood Pl",
    "sg:city":"Portland",
    "sg:classifiers":[
        {
            "category":"Professional",
            "subcategory":"Art Services",
            "type":"Services"
        }
    ],
    "sg:phone":"+1 503 799 8975",
    "sg:postcode":"97201",
    "sg:province":"OR",
    "sg:tags":[
        "designer",
        "display",
        "producer"
    ],
    "wof:name":"Foy Michael Designs",
    "wof:placetype":"venue"
},
  "geometry": {"coordinates":[-122.69955899999999,45.499872],"type":"Point"}
}