{
  "type": "Feature",
  "properties": {
    "addr:full":"918 Lloyd Center Portland OR 97232",
    "addr:housenumber":"918",
    "addr:postcode":"97232",
    "addr:street":"Lloyd",
    "iso:country":"US",
    "sg:address":"918 Lloyd Center",
    "sg:city":"Portland",
    "sg:classifiers":[
        {
            "category":"Shopping",
            "subcategory":"Clothing, Apparel, & Fashions",
            "type":"Retail Goods"
        }
    ],
    "sg:phone":"+1 503 282 9147",
    "sg:postcode":"97232",
    "sg:province":"OR",
    "sg:tags":[
        "furnishing"
    ],
    "sg:website":"www.zumiez.com",
    "wof:name":"Zumiez Inc",
    "wof:placetype":"venue"
},
  "geometry": {"coordinates":[-122.651904,45.531829],"type":"Point"}
}