{
  "type": "Feature",
  "properties": {
    "addr:full":"5340 SE Lincoln St Portland OR 97215",
    "addr:housenumber":"5340",
    "addr:postcode":"97215",
    "addr:street":"Se Lincoln St",
    "iso:country":"US",
    "sg:address":"5340 SE Lincoln St",
    "sg:city":"Portland",
    "sg:classifiers":[
        {
            "category":"Personal",
            "subcategory":"Beauty Salon",
            "type":"Services"
        }
    ],
    "sg:phone":"+1 503 233 9019",
    "sg:postcode":"97215",
    "sg:province":"OR",
    "sg:tags":[
        "shop"
    ],
    "wof:name":"Hair Fashions By Susan",
    "wof:placetype":"venue"
},
  "geometry": {"coordinates":[-122.607187,45.50797],"type":"Point"}
}