{
  "type": "Feature",
  "properties": {
    "addr:full":"4440 NE Fremont St Portland OR 97213",
    "addr:housenumber":"4440",
    "addr:postcode":"97213",
    "addr:street":"Ne Fremont St",
    "iso:country":"US",
    "sg:address":"4440 NE Fremont St",
    "sg:city":"Portland",
    "sg:classifiers":[
        {
            "category":"Restaurant",
            "type":"Food & Drink"
        }
    ],
    "sg:phone":"+1 971 222 3433",
    "sg:postcode":"97213",
    "sg:province":"OR",
    "sg:tags":[
        "grill",
        "style",
        "bar",
        "family",
        "lunch",
        "american",
        "new",
        "brunch",
        "breakfast"
    ],
    "sg:website":"www.solunagrill.com",
    "wof:name":"Soluna Grill",
    "wof:placetype":"venue"
},
  "geometry": {"coordinates":[-122.61704400000001,45.548112],"type":"Point"}
}