{
  "type": "Feature",
  "properties": {
    "addr:full":"8200 SW Piute Ct Tualatin OR 97062",
    "addr:housenumber":"8200",
    "addr:postcode":"97062",
    "addr:street":"Sw Piute Ct",
    "iso:country":"US",
    "sg:address":"8200 SW Piute Ct",
    "sg:city":"Tualatin",
    "sg:classifiers":[
        {
            "category":"Professional",
            "subcategory":"Computer Services",
            "type":"Services"
        }
    ],
    "sg:phone":"+1 503 691 1069",
    "sg:postcode":"97062",
    "sg:province":"OR",
    "sg:tags":[
        "related"
    ],
    "wof:name":"L Hadley & Associates",
    "wof:placetype":"venue"
},
  "geometry": {"coordinates":[-122.76119,45.368161],"type":"Point"}
}