{
  "type": "Feature",
  "properties": {
    "iso:country":"US",
    "sg:address":"435 E Newport Ave",
    "sg:city":"Hermiston",
    "sg:classifiers":[
        {
            "category":"Health Services",
            "subcategory":"Hospital",
            "type":"Services"
        }
    ],
    "sg:phone":"+1 541 567 2367",
    "sg:postcode":"97838",
    "sg:province":"OR",
    "sg:tags":[
        "mental"
    ],
    "wof:name":"Umatilla County Mental Health",
    "wof:placetype":"venue"
},
  "geometry": {"coordinates":[-119.284572,45.838734],"type":"Point"}
}