{
  "type": "Feature",
  "properties": {
    "iso:country":"US",
    "sg:address":"3925 NW Redwood Ln",
    "sg:city":"Redmond",
    "sg:classifiers":[
        {
            "category":"Social Services",
            "type":"Services"
        }
    ],
    "sg:phone":"+1 541 447 9409",
    "sg:postcode":"97756",
    "sg:province":"OR",
    "sg:tags":[
        "counselor",
        "marriage",
        "family"
    ],
    "wof:name":"Good Samaritan Ministries",
    "wof:placetype":"venue"
},
  "geometry": {"coordinates":[-121.214729,44.29944],"type":"Point"}
}