{
  "type": "Feature",
  "properties": {
    "iso:country":"US",
    "sg:address":"85500 Dillard Access Rd",
    "sg:city":"Eugene",
    "sg:classifiers":[
        {
            "category":"Building & Trades",
            "subcategory":"Construction",
            "type":"Services"
        }
    ],
    "sg:phone":"+1 541 988 9121",
    "sg:postcode":"97405",
    "sg:province":"OR",
    "sg:tags":[
        "contractor"
    ],
    "wof:name":"N M Cameron Construction Co",
    "wof:placetype":"venue"
},
  "geometry": {"coordinates":[-123.004704,43.986029],"type":"Point"}
}