{
  "type": "Feature",
  "properties": {
    "addr:full":"6016 N Greeley Ave Portland OR 97217",
    "addr:housenumber":"6016",
    "addr:postcode":"97217",
    "addr:street":"N Greeley Ave",
    "iso:country":"US",
    "sg:address":"6016 N Greeley Ave",
    "sg:city":"Portland",
    "sg:classifiers":[
        {
            "category":"Manufacturing",
            "subcategory":"Soap",
            "type":"Manufacturing & Wholesale Goods"
        }
    ],
    "sg:phone":"+1 503 285 0809",
    "sg:postcode":"97217",
    "sg:province":"OR",
    "sg:tags":[
        "detergents-wholesale",
        "manufacturer"
    ],
    "wof:name":"Kar Products Co Div",
    "wof:placetype":"venue"
},
  "geometry": {"coordinates":[-122.695601,45.566477],"type":"Point"}
}