{
  "type": "Feature",
  "properties": {
    "iso:country":"US",
    "sg:address":"1590 NE Williamson Blvd",
    "sg:city":"Bend",
    "sg:classifiers":[
        {
            "category":"Health Services",
            "subcategory":"Doctor",
            "type":"Services"
        },
        {
            "category":"Health Services",
            "subcategory":"Dentist",
            "type":"Services"
        }
    ],
    "sg:phone":"+1 541 388 1500",
    "sg:postcode":"97701",
    "sg:province":"OR",
    "sg:tags":[
        "dentists-oral",
        "physician",
        "maxillofacial",
        "surgeons",
        "surgery",
        "oral"
    ],
    "wof:name":"Loxley Emine C DMD",
    "wof:placetype":"venue"
},
  "geometry": {"coordinates":[-121.27018,44.065675],"type":"Point"}
}