{
  "type": "Feature",
  "properties": {
    "iso:country":"US",
    "sg:address":"15745 SW 116th Ave",
    "sg:city":"Portland",
    "sg:classifiers":[
        {
            "category":"Food & Beverages",
            "subcategory":"Liquor & Beverages",
            "type":"Retail Goods"
        }
    ],
    "sg:phone":"+1 503 620 5115",
    "sg:postcode":"97224",
    "sg:province":"OR",
    "sg:tags":[
        "beer",
        "spirit",
        "store",
        "wine"
    ],
    "wof:name":"King City Liquor Store 189",
    "wof:placetype":"venue"
},
  "geometry": {"coordinates":[-122.796997,45.405701],"type":"Point"}
}