{
  "type": "Feature",
  "properties": {
    "iso:country":"US",
    "sg:address":"700 N Hayden Island Dr",
    "sg:city":"Portland",
    "sg:classifiers":[
        {
            "category":"Banks & Credit Unions",
            "subcategory":"Bank",
            "type":"Services"
        }
    ],
    "sg:phone":"+1 503 283 8777",
    "sg:postcode":"97217",
    "sg:province":"OR",
    "sg:tags":[
        "loan",
        "real estate"
    ],
    "wof:name":"Mountaintop Mortgage",
    "wof:placetype":"venue"
},
  "geometry": {"coordinates":[-122.675212,45.611367],"type":"Point"}
}