{
  "type": "Feature",
  "properties": {
    "iso:country":"US",
    "sg:address":"2400 Hartman Ln Ste 500",
    "sg:city":"Springfield",
    "sg:classifiers":[
        {
            "category":"Health Services",
            "subcategory":"Clinic",
            "type":"Services"
        },
        {
            "category":"Health Services",
            "subcategory":"Medical Lab",
            "type":"Services"
        },
        {
            "category":"Personal",
            "type":"Services"
        }
    ],
    "sg:phone":"+1 866 867 0393",
    "sg:postcode":"97477",
    "sg:province":"OR",
    "sg:tags":[
        "laboratory",
        "testing",
        "paternity",
        "drug"
    ],
    "sg:website":"http://national.citysearch.com/profile/external/604046672/springfield_or/rapid_std_dna_drug_testing_springfield.html?publisher=yellowpages&reference_id=1&placement=ypwebsitemip",
    "wof:name":"Rapid STD DNA Drug Testing SPRINGFIELD",
    "wof:placetype":"venue"
},
  "geometry": {"coordinates":[-123.03993199999999,44.06876],"type":"Point"}
}