{
  "type": "Feature",
  "properties": {
    "iso:country":"US",
    "sg:address":"826 SE 166th Pl",
    "sg:city":"Portland",
    "sg:classifiers":[
        {
            "category":"Manufacturing",
            "subcategory":"Toys & Sporting Goods",
            "type":"Manufacturing & Wholesale Goods"
        }
    ],
    "sg:phone":"+1 503 254 8505",
    "sg:postcode":"97233",
    "sg:province":"OR",
    "sg:tags":[
        "mfg"
    ],
    "wof:name":"Jakes Products",
    "wof:placetype":"venue"
},
  "geometry": {"coordinates":[-122.49175200000001,45.515959],"type":"Point"}
}