{
  "type": "Feature",
  "properties": {
    "iso:country":"US",
    "sg:address":"6076 Washburn Way",
    "sg:city":"Klamath Falls",
    "sg:classifiers":[
        {
            "category":"Home & Garden",
            "subcategory":"Furniture",
            "type":"Retail Goods"
        }
    ],
    "sg:phone":"+1 541 850 8677",
    "sg:postcode":"97603",
    "sg:province":"OR",
    "sg:tags":[
        "top",
        "counter"
    ],
    "wof:name":"Countertops By Topsecret",
    "wof:placetype":"venue"
},
  "geometry": {"coordinates":[-121.757174,42.17217],"type":"Point"}
}