{
  "type": "Feature",
  "properties": {
    "addr:full":"520 SW Yamhill St Portland OR 97204",
    "addr:housenumber":"520",
    "addr:postcode":"97204",
    "addr:street":"Sw Yamhill St",
    "iso:country":"US",
    "sg:address":"520 SW Yamhill St",
    "sg:city":"Portland",
    "sg:classifiers":[
        {
            "category":"Professional",
            "subcategory":"Lawyer & Legal Services",
            "type":"Services"
        }
    ],
    "sg:phone":"+1 503 224 1110",
    "sg:postcode":"97204",
    "sg:province":"OR",
    "sg:tags":[
        "attorney"
    ],
    "wof:name":"Silver Geoffrey Squier",
    "wof:placetype":"venue"
},
  "geometry": {"coordinates":[-122.678836,45.518274],"type":"Point"}
}