{
  "type": "Feature",
  "properties": {
    "addr:full":"1042 SE 151st Ave Portland OR 97233",
    "addr:housenumber":"1042",
    "addr:postcode":"97233",
    "addr:street":"Se 151St Ave",
    "iso:country":"US",
    "sg:address":"1042 SE 151st Ave",
    "sg:city":"Portland",
    "sg:classifiers":[
        {
            "category":"Building & Trades",
            "subcategory":"Locksmith",
            "type":"Services"
        }
    ],
    "sg:phone":"+1 503 616 9452",
    "sg:postcode":"97233",
    "sg:province":"OR",
    "sg:tags":[
        "key"
    ],
    "wof:name":"A To Z 24 Hour Locksmith",
    "wof:placetype":"venue"
},
  "geometry": {"coordinates":[-122.50789399999999,45.515151],"type":"Point"}
}