{
  "type": "Feature",
  "properties": {
    "iso:country":"US",
    "sg:address":"109 E 2nd St",
    "sg:city":"The Dalles",
    "sg:classifiers":[
        {
            "category":"Professional",
            "subcategory":"Computer Services",
            "type":"Services"
        }
    ],
    "sg:phone":"+1 541 296 9918",
    "sg:postcode":"97058",
    "sg:province":"OR",
    "sg:tags":[
        "repair"
    ],
    "sg:website":"www.windy-river.com",
    "wof:name":"Windy River Computers Inc",
    "wof:placetype":"venue"
},
  "geometry": {"coordinates":[-121.184113,45.602401],"type":"Point"}
}