{
  "type": "Feature",
  "properties": {
    "addr:full":"4814 US Hwy 101 Lincoln City OR 97367",
    "addr:housenumber":"4814",
    "addr:postcode":"97367",
    "addr:street":"Us Hwy 101",
    "iso:country":"US",
    "sg:address":"4814 US Hwy 101",
    "sg:city":"Lincoln City",
    "sg:classifiers":[
        {
            "category":"Restaurant",
            "type":"Food & Drink"
        },
        {
            "category":"Bars & Pubs",
            "type":"Food & Drink"
        }
    ],
    "sg:phone":"+1 541 996 9800",
    "sg:postcode":"97367",
    "sg:province":"OR",
    "sg:tags":[
        "lounge",
        "eating",
        "cocktail"
    ],
    "wof:name":"Shucker's Oyster Bar",
    "wof:placetype":"venue"
},
  "geometry": {"coordinates":[-124.016831,44.929676],"type":"Point"}
}