{
  "type": "Feature",
  "properties": {
    "addr:full":"1193 Royvonne Ave SE Salem OR 97302",
    "addr:housenumber":"1193",
    "addr:postcode":"97302",
    "addr:street":"Royvonne Ave Se",
    "iso:country":"US",
    "sg:address":"1193 Royvonne Ave SE",
    "sg:city":"Salem",
    "sg:classifiers":[
        {
            "category":"Real Estate",
            "subcategory":"Real Estate Agent",
            "type":"Services"
        }
    ],
    "sg:phone":"+1 503 362 9431",
    "sg:postcode":"97302",
    "sg:province":"OR",
    "wof:name":"Riverwood Properties",
    "wof:placetype":"venue"
},
  "geometry": {"coordinates":[-123.030826,44.886042],"type":"Point"}
}