{
  "type": "Feature",
  "properties": {
    "iso:country":"US",
    "sg:address":"725 River Ave",
    "sg:city":"Eugene",
    "sg:classifiers":[
        {
            "category":"Recreation",
            "subcategory":"Arcade",
            "type":"Entertainment"
        },
        {
            "category":"Building & Trades",
            "subcategory":"Equipment Rental",
            "type":"Services"
        }
    ],
    "sg:phone":"+1 541 688 1888",
    "sg:postcode":"97404",
    "sg:province":"OR",
    "sg:tags":[
        "owner",
        "operator",
        "machine",
        "amusement",
        "devices"
    ],
    "sg:website":"www.amusementunlimited.com",
    "wof:name":"Amusement Unlimited Inc",
    "wof:placetype":"venue"
},
  "geometry": {"coordinates":[-123.112207,44.096719],"type":"Point"}
}