{
  "type": "Feature",
  "properties": {
    "iso:country":"US",
    "sg:address":"1624 N Coast Hwy",
    "sg:city":"Newport",
    "sg:classifiers":[
        {
            "category":"Health Services",
            "subcategory":"Clinic",
            "type":"Services"
        }
    ],
    "sg:phone":"+1 541 574 6597",
    "sg:postcode":"97365",
    "sg:province":"OR",
    "sg:tags":[
        "specialty",
        "outpatient"
    ],
    "wof:name":"Good Samaritan Hosp Corvallis",
    "wof:placetype":"venue"
},
  "geometry": {"coordinates":[-124.053505,44.650529],"type":"Point"}
}