{
  "type": "Feature",
  "properties": {
    "iso:country":"US",
    "sg:address":"7007 SE Lake Rd",
    "sg:city":"Portland",
    "sg:classifiers":[
        {
            "category":"Real Estate",
            "subcategory":"Real Estate Services",
            "type":"Services"
        },
        {
            "category":"Real Estate",
            "subcategory":"Real Estate Agent",
            "type":"Services"
        }
    ],
    "sg:phone":"+1 503 786 3005",
    "sg:postcode":"97267",
    "sg:province":"OR",
    "sg:tags":[
        "buyer",
        "broker"
    ],
    "wof:name":"Cj Realty Leasing",
    "wof:placetype":"venue"
},
  "geometry": {"coordinates":[-122.58929000000001,45.423114],"type":"Point"}
}