{
  "type": "Feature",
  "properties": {
    "iso:country":"US",
    "sg:address":"201 SE Fairview St",
    "sg:city":"Prineville",
    "sg:classifiers":[
        {
            "category":"Freight",
            "type":"Transportation"
        }
    ],
    "sg:phone":"+1 541 447 5120",
    "sg:postcode":"97754",
    "sg:province":"OR",
    "sg:tags":[
        "operator",
        "local",
        "storage",
        "trucking"
    ],
    "wof:name":"Anderson L Trucking",
    "wof:placetype":"venue"
},
  "geometry": {"coordinates":[-120.840984,44.30029],"type":"Point"}
}