{
  "type": "Feature",
  "properties": {
    "addr:full":"27801 SE Dee St Boring OR 97009",
    "addr:postcode":"27801;97009",
    "addr:street":"Se Dee St",
    "iso:country":"US",
    "sg:address":"27801 SE Dee St",
    "sg:city":"Boring",
    "sg:classifiers":[
        {
            "category":"Education",
            "subcategory":"School",
            "type":"Public Place"
        }
    ],
    "sg:phone":"+1 503 668 9393",
    "sg:postcode":"97009",
    "sg:province":"OR",
    "wof:name":"Sandy School District 046",
    "wof:placetype":"venue"
},
  "geometry": {"coordinates":[-122.377764,45.431835],"type":"Point"}
}