{
  "type": "Feature",
  "properties": {
    "iso:country":"US",
    "sg:address":"694 S Ponderosa Ct",
    "sg:city":"Canby",
    "sg:classifiers":[
        {
            "category":"Home & Garden",
            "subcategory":"Carpets & Floor Coverings",
            "type":"Retail Goods"
        }
    ],
    "sg:phone":"+1 503 651 1818",
    "sg:postcode":"97013",
    "sg:province":"OR",
    "sg:tags":[
        "material"
    ],
    "wof:name":"Impact Fitness Products",
    "wof:placetype":"venue"
},
  "geometry": {"coordinates":[-122.678459,45.25842],"type":"Point"}
}