{
  "type": "Feature",
  "properties": {
    "addr:full":"11462 SW Pacific Hwy Portland OR 97223",
    "addr:housenumber":"11462",
    "addr:postcode":"97223",
    "addr:street":"Sw Pacific Hwy",
    "iso:country":"US",
    "sg:address":"11462 SW Pacific Hwy",
    "sg:city":"Portland",
    "sg:phone":"+1 503 620 8880",
    "sg:postcode":"97223",
    "sg:province":"OR",
    "sg:website":"http://www.americastire.com/dtcs/home.do?utm_source=YellowPages&utm_medium=iyp&utm_campaign=YellowPagesIYPOrg",
    "wof:name":"America's Tire",
    "wof:placetype":"venue"
},
  "geometry": {"coordinates":[-122.74574200000001,45.442512],"type":"Point"}
}