{
  "type": "Feature",
  "properties": {
    "iso:country":"US",
    "sg:address":"12 Black Oak Dr",
    "sg:city":"Medford",
    "sg:classifiers":[
        {
            "category":"Organizations",
            "subcategory":"Membership Organization",
            "type":"Services"
        }
    ],
    "sg:phone":"+1 541 773 5040",
    "sg:postcode":"97504",
    "sg:province":"OR",
    "wof:name":"Magdalene Home",
    "wof:placetype":"venue"
},
  "geometry": {"coordinates":[-122.836795,42.329692],"type":"Point"}
}