{
  "type": "Feature",
  "properties": {
    "iso:country":"US",
    "sg:address":"3209 SE Knapp St",
    "sg:city":"Portland",
    "sg:classifiers":[
        {
            "category":"Professional",
            "subcategory":"Secretarial Services",
            "type":"Services"
        }
    ],
    "sg:phone":"+1 503 222 3222",
    "sg:postcode":"97202",
    "sg:province":"OR",
    "sg:tags":[
        "reporting"
    ],
    "wof:name":"Lord Cheryl",
    "wof:placetype":"venue"
},
  "geometry": {"coordinates":[-122.629459,45.471099],"type":"Point"}
}