{
  "type": "Feature",
  "properties": {
    "addr:full":"4977 W 11th Ave Eugene OR 97402",
    "addr:housenumber":"4977",
    "addr:postcode":"97402",
    "addr:street":"W 11Th Ave",
    "iso:country":"US",
    "sg:address":"4977 W 11th Ave",
    "sg:city":"Eugene",
    "sg:classifiers":[
        {
            "category":"Home & Garden",
            "subcategory":"Building Materials",
            "type":"Retail Goods"
        }
    ],
    "sg:phone":"+1 541 434 2166",
    "sg:postcode":"97402",
    "sg:province":"OR",
    "wof:name":"Redwood Northwest",
    "wof:placetype":"venue"
},
  "geometry": {"coordinates":[-123.18399700000001,44.048342],"type":"Point"}
}