{
  "type": "Feature",
  "properties": {
    "addr:full":"4436 NE Wygant St Portland OR 97218",
    "addr:housenumber":"4436",
    "addr:postcode":"97218",
    "addr:street":"Ne Wygant St",
    "iso:country":"US",
    "sg:address":"4436 NE Wygant St",
    "sg:city":"Portland",
    "sg:classifiers":[
        {
            "category":"Wholesale",
            "subcategory":"Wine & Distilled Alcoholic Beverages",
            "type":"Manufacturing & Wholesale Goods"
        }
    ],
    "sg:phone":"+1 503 231 7688",
    "sg:postcode":"97218",
    "sg:province":"OR",
    "sg:tags":[
        "liquors-wholesale"
    ],
    "wof:name":"Deco Distilling",
    "wof:placetype":"venue"
},
  "geometry": {"coordinates":[-122.61624,45.557345],"type":"Point"}
}