{
  "type": "Feature",
  "properties": {
    "iso:country":"US",
    "sg:address":"1009 SW Rivington Dr",
    "sg:city":"Portland",
    "sg:classifiers":[
        {
            "category":"Banks & Credit Unions",
            "subcategory":"Investment Brokerage",
            "type":"Services"
        }
    ],
    "sg:phone":"+1 503 243 6748",
    "sg:postcode":"97201",
    "sg:province":"OR",
    "sg:tags":[
        "security"
    ],
    "wof:name":"Allocation Plus LLC",
    "wof:placetype":"venue"
},
  "geometry": {"coordinates":[-122.691012,45.508474],"type":"Point"}
}