{
  "type": "Feature",
  "properties": {
    "iso:country":"US",
    "sg:address":"4729 S 6th St",
    "sg:city":"Klamath Falls",
    "sg:classifiers":[
        {
            "category":"Professional",
            "type":"Services"
        },
        {
            "category":"Shopping",
            "subcategory":"Hobbies, Toys, & Games",
            "type":"Retail Goods"
        }
    ],
    "sg:phone":"+1 541 273 6125",
    "sg:postcode":"97603",
    "sg:province":"OR",
    "sg:tags":[
        "craft"
    ],
    "wof:name":"Scrappers Corner",
    "wof:placetype":"venue"
},
  "geometry": {"coordinates":[-121.72916499999999,42.206583],"type":"Point"}
}