{
  "type": "Feature",
  "properties": {
    "addr:full":"1250 State Rd Mosier OR 97040",
    "addr:housenumber":"1250",
    "addr:postcode":"97040",
    "addr:street":"State Rd",
    "iso:country":"US",
    "sg:address":"1250 State Rd",
    "sg:city":"Mosier",
    "sg:classifiers":[
        {
            "category":"Government",
            "subcategory":"Fire Station",
            "type":"Public Place"
        }
    ],
    "sg:phone":"+1 541 478 3765",
    "sg:postcode":"97040",
    "sg:province":"OR",
    "sg:tags":[
        "protection"
    ],
    "wof:name":"Mosier Rural Fire",
    "wof:placetype":"venue"
},
  "geometry": {"coordinates":[-121.362235,45.682716],"type":"Point"}
}