{
  "type": "Feature",
  "properties": {
    "iso:country":"US",
    "sg:address":"1500 SW 1st Ave #270",
    "sg:city":"Portland",
    "sg:classifiers":[
        {
            "category":"Social Services",
            "subcategory":"Child Care",
            "type":"Services"
        }
    ],
    "sg:phone":"+1 503 345 4820",
    "sg:postcode":"97201",
    "sg:province":"OR",
    "sg:tags":[
        "educational",
        "referral",
        "support",
        "cancer"
    ],
    "wof:name":"Susan G. Komen For The Cure",
    "wof:placetype":"venue"
},
  "geometry": {"coordinates":[-122.676483,45.512402],"type":"Point"}
}