{
  "type": "Feature",
  "properties": {
    "iso:country":"US",
    "sg:address":"2201 Lloyd Center",
    "sg:city":"Portland",
    "sg:classifiers":[
        {
            "category":"Building & Trades",
            "subcategory":"Construction",
            "type":"Services"
        }
    ],
    "sg:phone":"+1 503 284 0312",
    "sg:postcode":"97232",
    "sg:province":"OR",
    "sg:tags":[
        "general",
        "contractor"
    ],
    "wof:name":"James Barb Construction",
    "wof:placetype":"venue"
},
  "geometry": {"coordinates":[-122.654635,45.531796],"type":"Point"}
}