{
  "type": "Feature",
  "properties": {
    "iso:country":"US",
    "sg:address":"298 Laneda Ave",
    "sg:city":"Manzanita",
    "sg:classifiers":[
        {
            "category":"Professional",
            "subcategory":"Lawyer & Legal Services",
            "type":"Services"
        }
    ],
    "sg:phone":"+1 503 368 4800",
    "sg:postcode":"97130",
    "sg:province":"OR",
    "sg:tags":[
        "attorney"
    ],
    "wof:name":"Mari Trevino",
    "wof:placetype":"venue"
},
  "geometry": {"coordinates":[-123.936053,45.71854],"type":"Point"}
}