{
  "type": "Feature",
  "properties": {
    "iso:country":"US",
    "sg:address":"806 SW Broadway Ste 400",
    "sg:city":"Portland",
    "sg:classifiers":[
        {
            "category":"Banks & Credit Unions",
            "subcategory":"Bank",
            "type":"Services"
        },
        {
            "category":"Banks & Credit Unions",
            "subcategory":"Financial Services",
            "type":"Services"
        }
    ],
    "sg:phone":"+1 503 525 2222",
    "sg:postcode":"97205",
    "sg:province":"OR",
    "sg:tags":[
        "investment",
        "management",
        "stock",
        "broker",
        "bond"
    ],
    "sg:website":"http://www.hoeferarnett.com",
    "wof:name":"Hoefer & Arnett Inc",
    "wof:placetype":"venue"
},
  "geometry": {"coordinates":[-122.679991,45.518629],"type":"Point"}
}