{
  "type": "Feature",
  "properties": {
    "addr:full":"6200 NE 19th Ave Portland OR 97211",
    "addr:housenumber":"6200",
    "addr:postcode":"97211",
    "addr:street":"Ne 19Th Ave",
    "iso:country":"US",
    "sg:address":"6200 NE 19th Ave",
    "sg:city":"Portland",
    "sg:classifiers":[
        {
            "category":"Personal",
            "type":"Services"
        }
    ],
    "sg:phone":"+1 503 282 6261",
    "sg:postcode":"97211",
    "sg:province":"OR",
    "sg:tags":[
        "clergy"
    ],
    "wof:name":"David More Maynard Rev",
    "wof:placetype":"venue"
},
  "geometry": {"coordinates":[-122.64601500000001,45.567758],"type":"Point"}
}