{
  "type": "Feature",
  "properties": {
    "addr:full":"105 W Valley View Rd Talent OR 97540",
    "addr:housenumber":"105",
    "addr:postcode":"97540",
    "addr:street":"W Valley View Rd",
    "iso:country":"US",
    "sg:address":"105 W Valley View Rd",
    "sg:city":"Talent",
    "sg:classifiers":[
        {
            "category":"Restaurant",
            "type":"Food & Drink"
        }
    ],
    "sg:menulink":"http://www.allmenus.com/or/ashland/89009-figaros-pizza/menu/",
    "sg:phone":"+1 541 535 7949",
    "sg:postcode":"97540",
    "sg:province":"OR",
    "sg:tags":[
        "american",
        "italian",
        "pizza"
    ],
    "wof:name":"Figaro's Pizza",
    "wof:placetype":"venue"
},
  "geometry": {"coordinates":[-122.784021,42.245427],"type":"Point"}
}