{
  "type": "Feature",
  "properties": {
    "addr:full":"2079 NW Aloclek Dr Hillsboro OR 97124",
    "addr:housenumber":"2079",
    "addr:postcode":"97124",
    "addr:street":"Nw Aloclek Dr",
    "iso:country":"US",
    "sg:address":"2079 NW Aloclek Dr",
    "sg:city":"Hillsboro",
    "sg:classifiers":[
        {
            "category":"Professional",
            "subcategory":"Printing & Photocopies",
            "type":"Services"
        }
    ],
    "sg:phone":"+1 503 533 7859",
    "sg:postcode":"97124",
    "sg:province":"OR",
    "sg:tags":[
        "consultant"
    ],
    "wof:name":"The Oregonian",
    "wof:placetype":"venue"
},
  "geometry": {"coordinates":[-122.895769,45.534764],"type":"Point"}
}