{
  "type": "Feature",
  "properties": {
    "iso:country":"US",
    "sg:address":"1744 NE 42nd Ave",
    "sg:city":"Portland",
    "sg:classifiers":[
        {
            "category":"Travel",
            "subcategory":"Travel Agent",
            "type":"Entertainment"
        }
    ],
    "sg:phone":"+1 503 288 7842",
    "sg:postcode":"97213",
    "sg:province":"OR",
    "sg:tags":[
        "agency",
        "bureau"
    ],
    "wof:name":"Pat & Mike Travel",
    "wof:placetype":"venue"
},
  "geometry": {"coordinates":[-122.61983600000001,45.535679],"type":"Point"}
}