{
  "type": "Feature",
  "properties": {
    "iso:country":"US",
    "sg:address":"101 Thunderegg Blvd",
    "sg:city":"Nyssa",
    "sg:classifiers":[
        {
            "category":"Food & Beverages",
            "subcategory":"Groceries & Convenience Stores",
            "type":"Retail Goods"
        }
    ],
    "sg:phone":"+1 541 372 8079",
    "sg:postcode":"97913",
    "sg:province":"OR",
    "wof:name":"Logan's Express",
    "wof:placetype":"venue"
},
  "geometry": {"coordinates":[-117.002044,43.878603],"type":"Point"}
}