{
  "type": "Feature",
  "properties": {
    "addr:full":"2373 Kuebler Rd S Salem OR 97302",
    "addr:housenumber":"2373",
    "addr:postcode":"97302",
    "addr:street":"Kuebler Rd",
    "iso:country":"US",
    "sg:address":"2373 Kuebler Rd S",
    "sg:city":"Salem",
    "sg:classifiers":[
        {
            "category":"Education",
            "subcategory":"School",
            "type":"Public Place"
        }
    ],
    "sg:phone":"+1 503 399 3261",
    "sg:postcode":"97302",
    "sg:province":"OR",
    "wof:name":"Sprague High School",
    "wof:placetype":"venue"
},
  "geometry": {"coordinates":[-123.080562,44.883384],"type":"Point"}
}