{
  "type": "Feature",
  "properties": {
    "iso:country":"US",
    "sg:address":"7970 SW Cirrus Dr",
    "sg:city":"Beaverton",
    "sg:classifiers":[
        {
            "category":"Home & Garden",
            "subcategory":"Household Appliances",
            "type":"Retail Goods"
        },
        {
            "category":"Wholesale",
            "subcategory":"Construction Materials",
            "type":"Manufacturing & Wholesale Goods"
        },
        {
            "category":"Home & Garden",
            "subcategory":"Building Materials",
            "type":"Retail Goods"
        },
        {
            "category":"Building & Trades",
            "subcategory":"Construction",
            "type":"Services"
        },
        {
            "category":"Building & Trades",
            "subcategory":"Electrical",
            "type":"Services"
        }
    ],
    "sg:phone":"+1 503 641 6808",
    "sg:postcode":"97008",
    "sg:province":"OR",
    "sg:tags":[
        "systems-wholesale",
        "dishwashing",
        "radiators-heating",
        "supply",
        "equipment-wholesale",
        "system",
        "heating",
        "machine",
        "equipment",
        "furnaces-heating",
        "sales",
        "manufacturer",
        "electric"
    ],
    "wof:name":"Pacific Hydronics",
    "wof:placetype":"venue"
},
  "geometry": {"coordinates":[-122.790511,45.462233],"type":"Point"}
}