{
  "type": "Feature",
  "properties": {
    "iso:country":"US",
    "sg:address":"100 US Hwy 101",
    "sg:city":"Florence",
    "sg:classifiers":[
        {
            "category":"Real Estate",
            "subcategory":"Real Estate Agent",
            "type":"Services"
        }
    ],
    "sg:phone":"+1 541 997 7777",
    "sg:postcode":"97439",
    "sg:province":"OR",
    "sg:website":"www.cbcoast.com",
    "wof:name":"Coldwell Banker Coast Real Est",
    "wof:placetype":"venue"
},
  "geometry": {"coordinates":[-124.108081,43.967673],"type":"Point"}
}