{
  "type": "Feature",
  "properties": {
    "addr:full":"6538 SE Scott Dr Portland OR 97215",
    "addr:housenumber":"6538",
    "addr:postcode":"97215",
    "addr:street":"Se Scott Dr",
    "iso:country":"US",
    "sg:address":"6538 SE Scott Dr",
    "sg:city":"Portland",
    "sg:classifiers":[
        {
            "category":"Building & Trades",
            "subcategory":"Electrical",
            "type":"Services"
        }
    ],
    "sg:phone":"+1 503 238 6693",
    "sg:postcode":"97215",
    "sg:province":"OR",
    "sg:tags":[
        "electrician"
    ],
    "wof:name":"Smith Electric Inc",
    "wof:placetype":"venue"
},
  "geometry": {"coordinates":[-122.596439,45.518026],"type":"Point"}
}