{
  "type": "Feature",
  "properties": {
    "iso:country":"US",
    "sg:address":"13 SW Byers Ave",
    "sg:city":"Pendleton",
    "sg:classifiers":[
        {
            "category":"Restaurant",
            "type":"Food & Drink"
        }
    ],
    "sg:phone":"+1 541 278 4200",
    "sg:postcode":"97801",
    "sg:province":"OR",
    "wof:name":"Waterstreet Italian Restaurant",
    "wof:placetype":"venue"
},
  "geometry": {"coordinates":[-118.78818,45.673616],"type":"Point"}
}