{
  "type": "Feature",
  "properties": {
    "iso:country":"US",
    "sg:address":"403 NW 5th Ave",
    "sg:city":"Portland",
    "sg:classifiers":[
        {
            "category":"Building & Trades",
            "subcategory":"Locksmith",
            "type":"Services"
        }
    ],
    "sg:phone":"+1 503 715 3787",
    "sg:postcode":"97209",
    "sg:province":"OR",
    "sg:tags":[
        "key"
    ],
    "wof:name":"Rain or Shine Locksmith",
    "wof:placetype":"venue"
},
  "geometry": {"coordinates":[-122.675696,45.525949],"type":"Point"}
}