{
  "type": "Feature",
  "properties": {
    "addr:full":"33671 S Dickey Prairie Rd Molalla OR 97038",
    "addr:housenumber":"33671",
    "addr:postcode":"97038",
    "addr:street":"S Dickey Prairie Rd",
    "iso:country":"US",
    "sg:address":"33671 S Dickey Prairie Rd",
    "sg:city":"Molalla",
    "sg:classifiers":[
        {
            "category":"Wholesale",
            "subcategory":"Machinery & Supplies",
            "type":"Manufacturing & Wholesale Goods"
        }
    ],
    "sg:phone":"+1 503 829 2063",
    "sg:postcode":"97038",
    "sg:province":"OR",
    "sg:tags":[
        "industrial",
        "equipment",
        "used",
        "machinery-new",
        "supplies-wholesale"
    ],
    "sg:website":"http://www.cpowerind.com",
    "wof:name":"C Power Industries, Inc",
    "wof:placetype":"venue"
},
  "geometry": {"coordinates":[-122.530646,45.117978],"type":"Point"}
}