{
  "type": "Feature",
  "properties": {
    "iso:country":"US",
    "sg:address":"235 NE Rice St",
    "sg:city":"Myrtle Creek",
    "sg:classifiers":[
        {
            "category":"Social Services",
            "subcategory":"Child Care",
            "type":"Services"
        }
    ],
    "sg:phone":"+1 541 863 5814",
    "sg:postcode":"97457",
    "sg:province":"OR",
    "sg:tags":[
        "kindergarten",
        "academic",
        "school"
    ],
    "wof:name":"Little Folks Christian School",
    "wof:placetype":"venue"
},
  "geometry": {"coordinates":[-123.283964,43.029116],"type":"Point"}
}