{
  "type": "Feature",
  "properties": {
    "iso:country":"US",
    "sg:address":"13500 SW Highway 99W",
    "sg:city":"Mcminnville",
    "sg:classifiers":[
        {
            "category":"Professional",
            "type":"Services"
        },
        {
            "category":"Personal",
            "type":"Services"
        }
    ],
    "sg:phone":"+1 877 776 0467",
    "sg:postcode":"97128",
    "sg:province":"OR",
    "sg:tags":[
        "industrial",
        "material",
        "storage",
        "movers-commercial",
        "full",
        "moving",
        "services-labor",
        "mover"
    ],
    "sg:website":"http://www.arpin.com",
    "wof:name":"Team Pomeroy Moving & Storage - Agent for Arpin Van Lines",
    "wof:placetype":"venue"
},
  "geometry": {"coordinates":[-123.20487300000001,45.163806],"type":"Point"}
}