{
  "type": "Feature",
  "properties": {
    "iso:country":"US",
    "sg:address":"543 Cherry St",
    "sg:city":"Central Point",
    "sg:classifiers":[
        {
            "category":"Building & Trades",
            "subcategory":"Cleaning & Sanitation",
            "type":"Services"
        }
    ],
    "sg:phone":"+1 541 664 3954",
    "sg:postcode":"97502",
    "sg:province":"OR",
    "sg:tags":[
        "janitorial"
    ],
    "wof:name":"G & W Janitorial Services",
    "wof:placetype":"venue"
},
  "geometry": {"coordinates":[-122.916371,42.379793],"type":"Point"}
}