{
  "type": "Feature",
  "properties": {
    "addr:full":"705 N Killingsworth St Portland OR 97217",
    "addr:housenumber":"705",
    "addr:postcode":"97217",
    "addr:street":"N Killingsworth St",
    "iso:country":"US",
    "sg:address":"705 N Killingsworth St",
    "sg:city":"Portland",
    "sg:classifiers":[
        {
            "category":"Education",
            "subcategory":"Junior College",
            "type":"Public Place"
        }
    ],
    "sg:phone":"+1 503 244 6111",
    "sg:postcode":"97217",
    "sg:province":"OR",
    "sg:tags":[
        "technical",
        "institute"
    ],
    "wof:name":"Portland Community College",
    "wof:placetype":"venue"
},
  "geometry": {"coordinates":[-122.674937,45.562756],"type":"Point"}
}