{
  "type": "Feature",
  "properties": {
    "addr:full":"317 W Broadway Eugene OR 97401",
    "addr:housenumber":"317",
    "addr:postcode":"97401",
    "addr:street":"W Broadway",
    "iso:country":"US",
    "sg:address":"317 W Broadway",
    "sg:city":"Eugene",
    "sg:classifiers":[
        {
            "category":"Manufacturing",
            "subcategory":"Printing",
            "type":"Manufacturing & Wholesale Goods"
        }
    ],
    "sg:phone":"+1 541 687 0082",
    "sg:postcode":"97401",
    "sg:province":"OR",
    "sg:tags":[
        "publisher"
    ],
    "wof:name":"Elizabeth Lewis Publishers",
    "wof:placetype":"venue"
},
  "geometry": {"coordinates":[-123.098653,44.049997],"type":"Point"}
}