{
  "type": "Feature",
  "properties": {
    "iso:country":"US",
    "sg:address":"2377 W Hayes St",
    "sg:city":"Woodburn",
    "sg:classifiers":[
        {
            "category":"Real Estate",
            "subcategory":"Real Estate Services",
            "type":"Services"
        },
        {
            "category":"Real Estate",
            "subcategory":"Real Estate Operator",
            "type":"Services"
        }
    ],
    "sg:phone":"+1 503 981 0919",
    "sg:postcode":"97071",
    "sg:province":"OR",
    "sg:tags":[
        "vacancy",
        "apartment",
        "rental",
        "finder",
        "listing"
    ],
    "wof:name":"Barclay Square Apartment",
    "wof:placetype":"venue"
},
  "geometry": {"coordinates":[-122.878193,45.147419],"type":"Point"}
}