{
  "type": "Feature",
  "properties": {
    "iso:country":"US",
    "sg:address":"16074 Lake Forest Blvd",
    "sg:city":"Lake Oswego",
    "sg:classifiers":[
        {
            "category":"Manufacturing",
            "subcategory":"Tools & Machinery",
            "type":"Manufacturing & Wholesale Goods"
        }
    ],
    "sg:phone":"+1 503 675 3528",
    "sg:postcode":"97035",
    "sg:province":"OR",
    "sg:tags":[
        "mfg"
    ],
    "wof:name":"Mold Masters LLC",
    "wof:placetype":"venue"
},
  "geometry": {"coordinates":[-122.74278099999999,45.411052],"type":"Point"}
}