{
  "type": "Feature",
  "properties": {
    "addr:full":"9155 SW Barnes Road Suite 314 Portland OR 97225",
    "addr:housenumber":"9155",
    "addr:postcode":"97225",
    "addr:street":"Sw Barnes Road Suite 314",
    "iso:country":"US",
    "sg:address":"9155 SW Barnes Road Suite 314",
    "sg:city":"Portland",
    "sg:classifiers":[
        {
            "category":"Health Services",
            "subcategory":"Doctor",
            "type":"Services"
        }
    ],
    "sg:phone":"+1 503 297 3384",
    "sg:postcode":"97225",
    "sg:province":"OR",
    "wof:name":"Anita A. Goel, MD",
    "wof:placetype":"venue"
},
  "geometry": {"coordinates":[-122.77114400000001,45.508886],"type":"Point"}
}