{
  "type": "Feature",
  "properties": {
    "iso:country":"US",
    "sg:address":"725 NW Broadway St",
    "sg:city":"Bend",
    "sg:classifiers":[
        {
            "category":"Professional",
            "subcategory":"Lawyer & Legal Services",
            "type":"Services"
        }
    ],
    "sg:phone":"+1 541 383 2764",
    "sg:postcode":"97701",
    "sg:province":"OR",
    "sg:tags":[
        "information",
        "attorney",
        "referral"
    ],
    "wof:name":"Mark G Reinecke",
    "wof:placetype":"venue"
},
  "geometry": {"coordinates":[-121.31686500000001,44.058077],"type":"Point"}
}