{
  "type": "Feature",
  "properties": {
    "addr:full":"4368 Snowbrush Ct Lake Oswego OR 97035",
    "addr:housenumber":"4368",
    "addr:postcode":"97035",
    "addr:street":"Snowbrush Ct",
    "iso:country":"US",
    "sg:address":"4368 Snowbrush Ct",
    "sg:city":"Lake Oswego",
    "sg:classifiers":[
        {
            "category":"Professional",
            "subcategory":"Art Services",
            "type":"Services"
        }
    ],
    "sg:phone":"+1 503 636 0044",
    "sg:postcode":"97035",
    "sg:province":"OR",
    "sg:tags":[
        "commercial",
        "design"
    ],
    "sg:website":"www.heirloomartists.com",
    "wof:name":"Heirloom Artists-Calligraphers",
    "wof:placetype":"venue"
},
  "geometry": {"coordinates":[-122.720405,45.422046],"type":"Point"}
}