{
  "type": "Feature",
  "properties": {
    "iso:country":"US",
    "sg:address":"4921 SW Hewett Blvd",
    "sg:city":"Portland",
    "sg:classifiers":[
        {
            "category":"Banks & Credit Unions",
            "subcategory":"Investment Brokerage",
            "type":"Services"
        }
    ],
    "sg:phone":"+1 503 222 4860",
    "sg:postcode":"97221",
    "sg:province":"OR",
    "sg:tags":[
        "advisory"
    ],
    "wof:name":"Bruce H Russell & Associates",
    "wof:placetype":"venue"
},
  "geometry": {"coordinates":[-122.72721,45.502718],"type":"Point"}
}