{
  "type": "Feature",
  "properties": {
    "addr:full":"2300 Frontage Rd Reedsport OR 97467",
    "addr:housenumber":"2300",
    "addr:postcode":"97467",
    "addr:street":"Frontage Rd",
    "iso:country":"US",
    "sg:address":"2300 Frontage Rd",
    "sg:city":"Reedsport",
    "sg:classifiers":[
        {
            "category":"Shopping",
            "type":"Retail Goods"
        }
    ],
    "sg:phone":"+1 541 271 2822",
    "sg:postcode":"97467",
    "sg:province":"OR",
    "sg:tags":[
        "monument"
    ],
    "wof:name":"Dunes Memorial Chapel",
    "wof:placetype":"venue"
},
  "geometry": {"coordinates":[-124.123864,43.695623],"type":"Point"}
}