{
  "type": "Feature",
  "properties": {
    "iso:country":"US",
    "sg:address":"524 N Berkeley Way",
    "sg:city":"Medford",
    "sg:classifiers":[
        {
            "category":"Building & Trades",
            "subcategory":"Landscaping Services",
            "type":"Services"
        }
    ],
    "sg:phone":"+1 541 734 0574",
    "sg:postcode":"97504",
    "sg:province":"OR",
    "sg:tags":[
        "landscape"
    ],
    "wof:name":"Halleys Landscape",
    "wof:placetype":"venue"
},
  "geometry": {"coordinates":[-122.850431,42.334711],"type":"Point"}
}