{
  "type": "Feature",
  "properties": {
    "iso:country":"US",
    "sg:address":"983 Willagillespie Rd",
    "sg:city":"Eugene",
    "sg:classifiers":[
        {
            "category":"Organizations",
            "subcategory":"Membership Organization",
            "type":"Services"
        }
    ],
    "sg:phone":"+1 541 484 0661",
    "sg:postcode":"97401",
    "sg:province":"OR",
    "sg:tags":[
        "automobile"
    ],
    "sg:website":"www.aaa.com",
    "wof:name":"AAA Travel Agency",
    "wof:placetype":"venue"
},
  "geometry": {"coordinates":[-123.100262,44.069106],"type":"Point"}
}