{
  "type": "Feature",
  "properties": {
    "iso:country":"US",
    "sg:address":"245 W 5th Ave",
    "sg:city":"Eugene",
    "sg:classifiers":[
        {
            "category":"Shopping",
            "subcategory":"Florist",
            "type":"Retail Goods"
        }
    ],
    "sg:phone":"+1 541 342 2400",
    "sg:postcode":"97401",
    "sg:province":"OR",
    "wof:name":"Ken Gillespie Florist",
    "wof:placetype":"venue"
},
  "geometry": {"coordinates":[-123.096721,44.054415],"type":"Point"}
}