{
  "type": "Feature",
  "properties": {
    "addr:full":"1689 NW Martin Ave Roseburg OR 97470",
    "addr:housenumber":"1689",
    "addr:postcode":"97470",
    "addr:street":"Nw Martin Ave",
    "iso:country":"US",
    "sg:address":"1689 NW Martin Ave",
    "sg:city":"Roseburg",
    "sg:classifiers":[
        {
            "category":"Professional",
            "subcategory":"Accounting & Tax Preparation",
            "type":"Services"
        }
    ],
    "sg:phone":"+1 541 673 6214",
    "sg:postcode":"97470",
    "sg:province":"OR",
    "wof:name":"Hardie Bookkeeping & Tax Svc",
    "wof:placetype":"venue"
},
  "geometry": {"coordinates":[-123.379514,43.22576],"type":"Point"}
}