{
  "type": "Feature",
  "properties": {
    "addr:full":"925 NW 2nd St Portland OR 97255",
    "addr:housenumber":"925",
    "addr:postcode":"97255",
    "addr:street":"Nw 2Nd St",
    "iso:country":"US",
    "sg:address":"925 NW 2nd St",
    "sg:city":"Portland",
    "sg:classifiers":[
        {
            "category":"Restaurant",
            "type":"Food & Drink"
        },
        {
            "category":"Recreation",
            "subcategory":"Dance Hall",
            "type":"Entertainment"
        }
    ],
    "sg:postcode":"97255",
    "sg:province":"OR",
    "sg:tags":[
        "club",
        "basque",
        "spanish"
    ],
    "wof:name":"Ibiza",
    "wof:placetype":"venue"
},
  "geometry": {"coordinates":[-122.675473,45.516296],"type":"Point"}
}