{
  "type": "Feature",
  "properties": {
    "iso:country":"US",
    "sg:address":"1818 SW Stringtown Rd",
    "sg:city":"Forest Grove",
    "sg:classifiers":[
        {
            "category":"Farming",
            "subcategory":"Nursery",
            "type":"Manufacturing & Wholesale Goods"
        }
    ],
    "sg:phone":"+1 503 359 5305",
    "sg:postcode":"97116",
    "sg:province":"OR",
    "sg:tags":[
        "ornamental"
    ],
    "wof:name":"West Wind Gardens",
    "wof:placetype":"venue"
},
  "geometry": {"coordinates":[-123.119626,45.504774],"type":"Point"}
}