{
  "type": "Feature",
  "properties": {
    "iso:country":"US",
    "sg:address":"314 Hilltop Dr",
    "sg:city":"Newberg",
    "sg:classifiers":[
        {
            "category":"Building & Trades",
            "subcategory":"Landscaping Services",
            "type":"Services"
        },
        {
            "category":"Utilities",
            "subcategory":"Water",
            "type":"Services"
        },
        {
            "category":"Utilities",
            "subcategory":"Electric",
            "type":"Services"
        },
        {
            "category":"Professional",
            "subcategory":"Engineering",
            "type":"Services"
        },
        {
            "category":"Utilities",
            "type":"Services"
        }
    ],
    "sg:phone":"+1 503 360 3045",
    "sg:postcode":"97132",
    "sg:province":"OR",
    "sg:tags":[
        "leak",
        "energy",
        "conservation",
        "consultant",
        "detecting",
        "public"
    ],
    "wof:name":"Power Quality & Maintenance",
    "wof:placetype":"venue"
},
  "geometry": {"coordinates":[-122.977183,45.326036],"type":"Point"}
}