{
  "type": "Feature",
  "properties": {
    "iso:country":"US",
    "sg:address":"13765 SE Old Station Rd",
    "sg:city":"Mcminnville",
    "sg:classifiers":[
        {
            "category":"Building & Trades",
            "subcategory":"Construction",
            "type":"Services"
        }
    ],
    "sg:phone":"+1 503 835 3023",
    "sg:postcode":"97128",
    "sg:province":"OR",
    "sg:tags":[
        "carpentry",
        "contractor"
    ],
    "wof:name":"Larry Weirich",
    "wof:placetype":"venue"
},
  "geometry": {"coordinates":[-123.20064,45.159893],"type":"Point"}
}