{
  "type": "Feature",
  "properties": {
    "iso:country":"US",
    "sg:address":"65 W 36th Ave",
    "sg:city":"Eugene",
    "sg:classifiers":[
        {
            "category":"Building & Trades",
            "subcategory":"Equipment Rental",
            "type":"Services"
        }
    ],
    "sg:phone":"+1 541 344 8410",
    "sg:postcode":"97405",
    "sg:province":"OR",
    "sg:tags":[
        "leasing"
    ],
    "wof:name":"Evergreen Funding Inc",
    "wof:placetype":"venue"
},
  "geometry": {"coordinates":[-123.096434,44.015866],"type":"Point"}
}