{
  "type": "Feature",
  "properties": {
    "iso:country":"US",
    "sg:address":"20 SE 2nd St",
    "sg:city":"Newport",
    "sg:classifiers":[
        {
            "category":"Social Services",
            "type":"Services"
        }
    ],
    "sg:phone":"+1 541 574 0669",
    "sg:postcode":"97365",
    "sg:province":"OR",
    "sg:tags":[
        "senior",
        "citizen"
    ],
    "wof:name":"Senior Meal Sites",
    "wof:placetype":"venue"
},
  "geometry": {"coordinates":[-124.05301900000001,44.634863],"type":"Point"}
}