{
  "type": "Feature",
  "properties": {
    "iso:country":"US",
    "sg:address":"91035 Poodle Creek Rd",
    "sg:city":"Noti",
    "sg:classifiers":[
        {
            "category":"Farming",
            "subcategory":"Livestock Farm",
            "type":"Manufacturing & Wholesale Goods"
        }
    ],
    "sg:phone":"+1 541 935 2602",
    "sg:postcode":"97461",
    "sg:province":"OR",
    "sg:tags":[
        "beef",
        "feedlot",
        "cattle"
    ],
    "wof:name":"Baker Farm",
    "wof:placetype":"venue"
},
  "geometry": {"coordinates":[-123.45895400000001,44.126086],"type":"Point"}
}