{
  "type": "Feature",
  "properties": {
    "iso:country":"US",
    "sg:address":"16251 SE McLoughlin Blvd",
    "sg:city":"Portland",
    "sg:classifiers":[
        {
            "category":"Restaurant",
            "type":"Food & Drink"
        }
    ],
    "sg:phone":"+1 503 653 2477",
    "sg:postcode":"97267",
    "sg:province":"OR",
    "sg:tags":[
        "eating"
    ],
    "wof:name":"Apple Peddler Restaurant",
    "wof:placetype":"venue"
},
  "geometry": {"coordinates":[-122.62329800000001,45.404714],"type":"Point"}
}