{
  "type": "Feature",
  "properties": {
    "iso:country":"US",
    "sg:address":"1522 Revere Ct S",
    "sg:city":"Salem",
    "sg:classifiers":[
        {
            "category":"Health Services",
            "subcategory":"Optometrist",
            "type":"Services"
        }
    ],
    "sg:phone":"+1 503 763 6916",
    "sg:postcode":"97302",
    "sg:province":"OR",
    "wof:name":"Johns Herb Od PC",
    "wof:placetype":"venue"
},
  "geometry": {"coordinates":[-123.067332,44.890796],"type":"Point"}
}