{
  "type": "Feature",
  "properties": {
    "addr:full":"19594 S Falcon Dr Oregon City OR 97045",
    "addr:housenumber":"19594",
    "addr:postcode":"97045",
    "addr:street":"S Falcon Dr",
    "iso:country":"US",
    "sg:address":"19594 S Falcon Dr",
    "sg:city":"Oregon City",
    "sg:classifiers":[
        {
            "category":"Building & Trades",
            "subcategory":"Construction",
            "type":"Services"
        }
    ],
    "sg:phone":"+1 503 657 1740",
    "sg:postcode":"97045",
    "sg:province":"OR",
    "sg:tags":[
        "paving",
        "contractor"
    ],
    "wof:name":"Willamette Excavation Inc",
    "wof:placetype":"venue"
},
  "geometry": {"coordinates":[-122.587351,45.324377],"type":"Point"}
}