{
  "type": "Feature",
  "properties": {
    "iso:country":"US",
    "sg:address":"724 NW Federal St",
    "sg:city":"Bend",
    "sg:classifiers":[
        {
            "category":"Real Estate",
            "subcategory":"Architect",
            "type":"Services"
        }
    ],
    "sg:phone":"+1 541 383 9015",
    "sg:postcode":"97701",
    "sg:province":"OR",
    "sg:tags":[
        "building",
        "designer"
    ],
    "wof:name":"Tozer Design Studio",
    "wof:placetype":"venue"
},
  "geometry": {"coordinates":[-121.327701,44.057251],"type":"Point"}
}