{
  "type": "Feature",
  "properties": {
    "iso:country":"US",
    "sg:address":"8810 SW Scoffins St",
    "sg:city":"Tigard",
    "sg:classifiers":[
        {
            "category":"Professional",
            "subcategory":"Accounting & Tax Preparation",
            "type":"Services"
        }
    ],
    "sg:phone":"+1 503 639 2200",
    "sg:postcode":"97223",
    "sg:province":"OR",
    "sg:tags":[
        "return",
        "filing"
    ],
    "sg:website":"www.tigardtax.com",
    "wof:name":"Tigard Tax",
    "wof:placetype":"venue"
},
  "geometry": {"coordinates":[-122.767099,45.431246],"type":"Point"}
}