{
  "type": "Feature",
  "properties": {
    "iso:country":"US",
    "sg:address":"245 Wilson St S",
    "sg:city":"Salem",
    "sg:classifiers":[
        {
            "category":"Education",
            "subcategory":"Special Training",
            "type":"Public Place"
        }
    ],
    "sg:phone":"+1 503 315 7168",
    "sg:postcode":"97302",
    "sg:province":"OR",
    "sg:tags":[
        "school",
        "instruction",
        "music"
    ],
    "wof:name":"Music Guy",
    "wof:placetype":"venue"
},
  "geometry": {"coordinates":[-123.04632599999999,44.928268],"type":"Point"}
}