{
  "type": "Feature",
  "properties": {
    "addr:full":"7348 Clear Creek Rd Mt Hood Parkdale OR 97041",
    "addr:housenumber":"7348",
    "addr:postcode":"97041",
    "addr:street":"Clear Creek Rd",
    "iso:country":"US",
    "sg:address":"7348 Clear Creek Rd",
    "sg:city":"Mt Hood Parkdale",
    "sg:classifiers":[
        {
            "category":"Personal",
            "subcategory":"Beauty Salon",
            "type":"Services"
        }
    ],
    "sg:phone":"+1 541 352 7438",
    "sg:postcode":"97041",
    "sg:province":"OR",
    "sg:tags":[
        "shop"
    ],
    "wof:name":"Shear Shoppe",
    "wof:placetype":"venue"
},
  "geometry": {"coordinates":[-121.596846,45.515336],"type":"Point"}
}