{
  "type": "Feature",
  "properties": {
    "addr:full":"19365 SW 65th Ave Tualatin OR 97062",
    "addr:housenumber":"19365",
    "addr:postcode":"97062",
    "addr:street":"Sw 65Th Ave",
    "iso:country":"US",
    "sg:address":"19365 SW 65th Ave",
    "sg:city":"Tualatin",
    "sg:classifiers":[
        {
            "category":"Health Services",
            "subcategory":"Clinic",
            "type":"Services"
        }
    ],
    "sg:phone":"+1 503 486 5672",
    "sg:postcode":"97062",
    "sg:province":"OR",
    "sg:tags":[
        "welfare"
    ],
    "wof:name":"Oregon Men's Clinic",
    "wof:placetype":"venue"
},
  "geometry": {"coordinates":[-122.74395800000001,45.380128],"type":"Point"}
}