{
  "type": "Feature",
  "properties": {
    "iso:country":"US",
    "sg:address":"15865 SE 114th Ave",
    "sg:city":"Clackamas",
    "sg:classifiers":[
        {
            "category":"Wholesale",
            "subcategory":"Construction Materials",
            "type":"Manufacturing & Wholesale Goods"
        }
    ],
    "sg:phone":"+1 503 557 7079",
    "sg:postcode":"97015",
    "sg:province":"OR",
    "sg:tags":[
        "equipment",
        "maker",
        "cabinet"
    ],
    "wof:name":"Richelieu Of America",
    "wof:placetype":"venue"
},
  "geometry": {"coordinates":[-122.552054,45.407877],"type":"Point"}
}