{
  "type": "Feature",
  "properties": {
    "addr:full":"294 W 37th Ave Eugene OR 97405",
    "addr:housenumber":"294",
    "addr:postcode":"97405",
    "addr:street":"W 37Th Ave",
    "iso:country":"US",
    "sg:address":"294 W 37th Ave",
    "sg:city":"Eugene",
    "sg:classifiers":[
        {
            "category":"Professional",
            "type":"Services"
        }
    ],
    "sg:phone":"+1 541 484 4949",
    "sg:postcode":"97405",
    "sg:province":"OR",
    "wof:name":"Skyhawk Inc",
    "wof:placetype":"venue"
},
  "geometry": {"coordinates":[-123.09915700000001,44.015704],"type":"Point"}
}