{
  "type": "Feature",
  "properties": {
    "addr:full":"38706 Pioneer Blvd Sandy OR 97055",
    "addr:housenumber":"38706",
    "addr:postcode":"97055",
    "addr:street":"Pioneer Blvd",
    "iso:country":"US",
    "sg:address":"38706 Pioneer Blvd",
    "sg:city":"Sandy",
    "sg:classifiers":[
        {
            "category":"Health Services",
            "subcategory":"Health Practitioner",
            "type":"Services"
        }
    ],
    "sg:phone":"+1 503 668 1181",
    "sg:postcode":"97055",
    "sg:province":"OR",
    "sg:tags":[
        "physician"
    ],
    "wof:name":"Schoolhouse Natural Medicine",
    "wof:placetype":"venue"
},
  "geometry": {"coordinates":[-122.265387,45.396373],"type":"Point"}
}