{
  "type": "Feature",
  "properties": {
    "iso:country":"US",
    "sg:address":"2950 SE Stark St",
    "sg:city":"Portland",
    "sg:classifiers":[
        {
            "category":"Wholesale",
            "subcategory":"Durable Goods & Equipment",
            "type":"Manufacturing & Wholesale Goods"
        }
    ],
    "sg:phone":"+1 503 231 8881",
    "sg:postcode":"97214",
    "sg:province":"OR",
    "sg:tags":[
        "exporter"
    ],
    "sg:website":"www.concannonlbr.com",
    "wof:name":"Concannon Lumber Co",
    "wof:placetype":"venue"
},
  "geometry": {"coordinates":[-122.635243,45.519236],"type":"Point"}
}