{
  "type": "Feature",
  "properties": {
    "addr:full":"3105 NE O B Riley Rd Bend OR 97701",
    "addr:housenumber":"3105",
    "addr:postcode":"97701",
    "addr:street":"Ne O B Riley Rd",
    "iso:country":"US",
    "sg:address":"3105 NE O B Riley Rd",
    "sg:city":"Bend",
    "sg:classifiers":[
        {
            "category":"Travel",
            "subcategory":"Hotels & Motels",
            "type":"Entertainment"
        },
        {
            "category":"Restaurant",
            "type":"Food & Drink"
        },
        {
            "category":"Travel",
            "subcategory":"Bed & Breakfast",
            "type":"Entertainment"
        },
        {
            "category":"Professional",
            "subcategory":"Management & Consulting",
            "type":"Services"
        }
    ],
    "sg:phone":"+1 541 389 9600",
    "sg:postcode":"97701",
    "sg:province":"OR",
    "sg:tags":[
        "consultant",
        "inn",
        "lodging"
    ],
    "sg:website":"http://www.shiloinns.com",
    "wof:name":"Shilo Inn Suites Hotel - Bend",
    "wof:placetype":"venue"
},
  "geometry": {"coordinates":[-121.305694,44.081737],"type":"Point"}
}