{
  "type": "Feature",
  "properties": {
    "addr:full":"15700 NW Blueridge Dr Beaverton OR 97006",
    "addr:housenumber":"15700",
    "addr:postcode":"97006",
    "addr:street":"Nw Blueridge Dr",
    "iso:country":"US",
    "sg:address":"15700 NW Blueridge Dr",
    "sg:city":"Beaverton",
    "sg:classifiers":[
        {
            "category":"Restaurant",
            "type":"Food & Drink"
        }
    ],
    "sg:phone":"+1 503 531 7220",
    "sg:postcode":"97006",
    "sg:province":"OR",
    "sg:tags":[
        "pizza"
    ],
    "sg:website":"www.papaspizza.net",
    "wof:name":"Papa's Pizza",
    "wof:placetype":"venue"
},
  "geometry": {"coordinates":[-122.83799399999999,45.524487],"type":"Point"}
}