{
  "type": "Feature",
  "properties": {
    "iso:country":"US",
    "sg:address":"565 Union St NE",
    "sg:city":"Salem",
    "sg:classifiers":[
        {
            "category":"Professional",
            "subcategory":"Engineering",
            "type":"Services"
        }
    ],
    "sg:phone":"+1 503 362 1208",
    "sg:postcode":"97301",
    "sg:province":"OR",
    "sg:tags":[
        "engineer"
    ],
    "wof:name":"Athalye Consulting Engineers",
    "wof:placetype":"venue"
},
  "geometry": {"coordinates":[-123.03292999999999,44.944849],"type":"Point"}
}