{
  "type": "Feature",
  "properties": {
    "iso:country":"US",
    "sg:address":"18130 NW Dixie Mountain Rd",
    "sg:city":"North Plains",
    "sg:classifiers":[
        {
            "category":"Professional",
            "type":"Services"
        }
    ],
    "sg:phone":"+1 503 647 2708",
    "sg:postcode":"97133",
    "sg:province":"OR",
    "wof:name":"James E Shaw & Norma J Sh",
    "wof:placetype":"venue"
},
  "geometry": {"coordinates":[-122.986542,45.650898],"type":"Point"}
}