{
  "type": "Feature",
  "properties": {
    "addr:full":"108 NW 4th St Madras OR 97741",
    "addr:housenumber":"108",
    "addr:postcode":"97741",
    "addr:street":"Nw 4Th St",
    "iso:country":"US",
    "sg:address":"108 NW 4th St",
    "sg:city":"Madras",
    "sg:classifiers":[
        {
            "category":"Retail",
            "subcategory":"Repair Shop",
            "type":"Services"
        }
    ],
    "sg:phone":"+1 541 475 2519",
    "sg:postcode":"97741",
    "sg:province":"OR",
    "sg:tags":[
        "welding"
    ],
    "wof:name":"Green Spot Welders",
    "wof:placetype":"venue"
},
  "geometry": {"coordinates":[-121.13053600000001,44.637869],"type":"Point"}
}