{
  "type": "Feature",
  "properties": {
    "iso:country":"US",
    "sg:address":"428 NE Newton Creek Rd",
    "sg:city":"Roseburg",
    "sg:classifiers":[
        {
            "category":"Retail",
            "subcategory":"Repair Shop",
            "type":"Services"
        }
    ],
    "sg:phone":"+1 541 672 5617",
    "sg:postcode":"97470",
    "sg:province":"OR",
    "sg:tags":[
        "outboard",
        "motor",
        "boat"
    ],
    "wof:name":"Independent Marine Sales & Svc",
    "wof:placetype":"venue"
},
  "geometry": {"coordinates":[-123.352425,43.244196],"type":"Point"}
}