{
  "type": "Feature",
  "properties": {
    "iso:country":"US",
    "sg:address":"3620 NE 122nd Ave",
    "sg:city":"Portland",
    "sg:classifiers":[
        {
            "category":"Health Services",
            "subcategory":"Doctor",
            "type":"Services"
        }
    ],
    "sg:phone":"+1 503 256 9880",
    "sg:postcode":"97230",
    "sg:province":"OR",
    "sg:tags":[
        "medical"
    ],
    "wof:name":"Gledwoyn Inc Punja & Banne",
    "wof:placetype":"venue"
},
  "geometry": {"coordinates":[-122.537245,45.548616],"type":"Point"}
}