{
  "type": "Feature",
  "properties": {
    "iso:country":"US",
    "sg:address":"17609 NE Tykeson Rd",
    "sg:city":"Newberg",
    "sg:classifiers":[
        {
            "category":"Professional",
            "type":"Services"
        }
    ],
    "sg:phone":"+1 503 537 2533",
    "sg:postcode":"97132",
    "sg:province":"OR",
    "wof:name":"James Thompson",
    "wof:placetype":"venue"
},
  "geometry": {"coordinates":[-123.06486,45.375259],"type":"Point"}
}