{
  "type": "Feature",
  "properties": {
    "addr:full":"6054 Commercial St SE Salem OR 97306",
    "addr:housenumber":"6054",
    "addr:postcode":"97306",
    "addr:street":"Commercial St Se",
    "iso:country":"US",
    "sg:address":"6054 Commercial St SE",
    "sg:city":"Salem",
    "sg:classifiers":[
        {
            "category":"Communications",
            "subcategory":"Film & Video Production",
            "type":"Services"
        }
    ],
    "sg:phone":"+1 503 588 0778",
    "sg:postcode":"97306",
    "sg:province":"OR",
    "sg:tags":[
        "motion",
        "picture",
        "rental",
        "equipment"
    ],
    "wof:name":"Camera Cars Ltd",
    "wof:placetype":"venue"
},
  "geometry": {"coordinates":[-123.02177,44.868674],"type":"Point"}
}