{
  "type": "Feature",
  "properties": {
    "addr:full":"871 Medford Center Medford OR 97504",
    "addr:housenumber":"871",
    "addr:postcode":"97504",
    "addr:street":"Medford Center",
    "iso:country":"US",
    "sg:address":"871 Medford Center",
    "sg:city":"Medford",
    "sg:classifiers":[
        {
            "category":"Real Estate",
            "subcategory":"Real Estate Services",
            "type":"Services"
        }
    ],
    "sg:phone":"+1 541 941 4287",
    "sg:postcode":"97504",
    "sg:province":"OR",
    "sg:website":"www.eastmedford.com",
    "wof:name":"Geoff O'Neill - Broker @ John L. Scott Medford",
    "wof:placetype":"venue"
},
  "geometry": {"coordinates":[-122.86606,42.334134],"type":"Point"}
}