{
  "type": "Feature",
  "properties": {
    "iso:country":"US",
    "sg:address":"1200 Oak St",
    "sg:city":"Eugene",
    "sg:phone":"+1 541 343 1230",
    "sg:postcode":"97401",
    "sg:province":"OR",
    "sg:website":"http://www.tararinthai.com",
    "wof:name":"Ta Ra Rin Thai Cuisine",
    "wof:placetype":"venue"
},
  "geometry": {"coordinates":[-123.091217,44.046619],"type":"Point"}
}