{
  "type": "Feature",
  "properties": {
    "iso:country":"US",
    "sg:address":"427 Front St",
    "sg:city":"Junction City",
    "sg:classifiers":[
        {
            "category":"Organizations",
            "subcategory":"Community Association",
            "type":"Services"
        }
    ],
    "sg:phone":"+1 541 998 1164",
    "sg:postcode":"97448",
    "sg:province":"OR",
    "sg:tags":[
        "fraternal"
    ],
    "wof:name":"Loyal Order Of Moose",
    "wof:placetype":"venue"
},
  "geometry": {"coordinates":[-123.201463,44.217735],"type":"Point"}
}