{
  "type": "Feature",
  "properties": {
    "iso:country":"US",
    "sg:address":"37380 Highway 226",
    "sg:city":"Lebanon",
    "sg:classifiers":[
        {
            "category":"Professional",
            "subcategory":"Management & Consulting",
            "type":"Services"
        }
    ],
    "sg:phone":"+1 541 258 3937",
    "sg:postcode":"97355",
    "sg:province":"OR",
    "sg:tags":[
        "farm"
    ],
    "wof:name":"A Wendling",
    "wof:placetype":"venue"
},
  "geometry": {"coordinates":[-122.87559400000001,44.63186],"type":"Point"}
}