{
  "type": "Feature",
  "properties": {
    "iso:country":"US",
    "sg:address":"14665 SW 81st Ave",
    "sg:city":"Portland",
    "sg:classifiers":[
        {
            "category":"Organizations",
            "subcategory":"Religious Organization",
            "type":"Services"
        }
    ],
    "sg:phone":"+1 503 639 3435",
    "sg:postcode":"97224",
    "sg:province":"OR",
    "wof:name":"Bonita Community Church",
    "wof:placetype":"venue"
},
  "geometry": {"coordinates":[-122.760755,45.414538],"type":"Point"}
}