{
  "type": "Feature",
  "properties": {
    "iso:country":"US",
    "sg:address":"8075 SW Cirrus Dr",
    "sg:city":"Beaverton",
    "sg:classifiers":[
        {
            "category":"Retail",
            "subcategory":"Portrait Studio",
            "type":"Services"
        }
    ],
    "sg:phone":"+1 503 684 5600",
    "sg:postcode":"97008",
    "sg:province":"OR",
    "sg:tags":[
        "photographer"
    ],
    "sg:website":"www.fstopstudios.net",
    "wof:name":"F Stop Studios",
    "wof:placetype":"venue"
},
  "geometry": {"coordinates":[-122.79085600000001,45.460774],"type":"Point"}
}