{
  "type": "Feature",
  "properties": {
    "addr:full":"21800 NE North Valley Rd Newberg OR 97132",
    "addr:housenumber":"21800",
    "addr:postcode":"97132",
    "addr:street":"Ne North Valley Rd",
    "iso:country":"US",
    "sg:address":"21800 NE North Valley Rd",
    "sg:city":"Newberg",
    "sg:classifiers":[
        {
            "category":"Farming",
            "subcategory":"Farm & Veterinary Services",
            "type":"Manufacturing & Wholesale Goods"
        }
    ],
    "sg:phone":"+1 503 538 2401",
    "sg:postcode":"97132",
    "sg:province":"OR",
    "sg:tags":[
        "nut"
    ],
    "wof:name":"Willamette Filbert Growers",
    "wof:placetype":"venue"
},
  "geometry": {"coordinates":[-123.0176,45.328988],"type":"Point"}
}