{
  "type": "Feature",
  "properties": {
    "iso:country":"US",
    "sg:address":"61308 Robin Hood Ln",
    "sg:city":"Bend",
    "sg:classifiers":[
        {
            "category":"Building & Trades",
            "subcategory":"Construction",
            "type":"Services"
        }
    ],
    "sg:phone":"+1 541 318 9081",
    "sg:postcode":"97702",
    "sg:province":"OR",
    "sg:tags":[
        "general",
        "contractor"
    ],
    "wof:name":"RB Construction",
    "wof:placetype":"venue"
},
  "geometry": {"coordinates":[-121.285276,44.025656],"type":"Point"}
}