{
  "type": "Feature",
  "properties": {
    "addr:full":"1200 SE 82nd Ave Portland OR 97216",
    "addr:housenumber":"1200",
    "addr:postcode":"97216",
    "addr:street":"Se 82Nd Ave",
    "iso:country":"US",
    "sg:address":"1200 SE 82nd Ave",
    "sg:city":"Portland",
    "sg:classifiers":[
        {
            "category":"Home & Garden",
            "subcategory":"Home Furnishings",
            "type":"Retail Goods"
        }
    ],
    "sg:phone":"+1 503 654 9495",
    "sg:postcode":"97216",
    "sg:province":"OR",
    "sg:tags":[
        "furniture"
    ],
    "wof:name":"Bombay Company 810",
    "wof:placetype":"venue"
},
  "geometry": {"coordinates":[-122.57873499999999,45.514711],"type":"Point"}
}