{
  "type": "Feature",
  "properties": {
    "addr:full":"2209 Madison St Klamath Falls OR 97603",
    "addr:housenumber":"2209",
    "addr:postcode":"97603",
    "addr:street":"Madison St",
    "iso:country":"US",
    "sg:address":"2209 Madison St",
    "sg:city":"Klamath Falls",
    "sg:classifiers":[
        {
            "category":"Shopping",
            "subcategory":"Tobacco",
            "type":"Retail Goods"
        }
    ],
    "sg:phone":"+1 541 884 0719",
    "sg:postcode":"97603",
    "sg:province":"OR",
    "sg:tags":[
        "cigarette",
        "cigar",
        "dealer"
    ],
    "wof:name":"Rick's Smoke Shop",
    "wof:placetype":"venue"
},
  "geometry": {"coordinates":[-121.71771699999999,42.207473],"type":"Point"}
}