{
  "type": "Feature",
  "properties": {
    "iso:country":"US",
    "sg:address":"33950 SW Ladd Hill Rd",
    "sg:city":"Wilsonville",
    "sg:classifiers":[
        {
            "category":"Organizations",
            "subcategory":"Religious Organization",
            "type":"Services"
        }
    ],
    "sg:phone":"+1 503 570 2885",
    "sg:postcode":"97070",
    "sg:province":"OR",
    "sg:tags":[
        "church"
    ],
    "wof:name":"Hope Fellowship",
    "wof:placetype":"venue"
},
  "geometry": {"coordinates":[-122.85669799999999,45.282408],"type":"Point"}
}