{
  "type": "Feature",
  "properties": {
    "iso:country":"US",
    "sg:address":"2350 SW Multnomah Blvd",
    "sg:city":"Portland",
    "sg:classifiers":[
        {
            "category":"Health Services",
            "subcategory":"Dentist",
            "type":"Services"
        }
    ],
    "sg:phone":"+1 503 245 0180",
    "sg:postcode":"97219",
    "sg:province":"OR",
    "wof:name":"David A. Goldwyn, DDS PC",
    "wof:placetype":"venue"
},
  "geometry": {"coordinates":[-122.70159099999999,45.465085],"type":"Point"}
}