{
  "type": "Feature",
  "properties": {
    "iso:country":"US",
    "sg:address":"0509 SW Texas St",
    "sg:city":"Portland",
    "sg:classifiers":[
        {
            "category":"Health Services",
            "subcategory":"Medical Lab",
            "type":"Services"
        },
        {
            "category":"Insurance",
            "subcategory":"Health Insurance",
            "type":"Services"
        }
    ],
    "sg:phone":"+1 503 452 1444",
    "sg:postcode":"97219",
    "sg:province":"OR",
    "sg:tags":[
        "maintenance"
    ],
    "wof:name":"Health Bridges International",
    "wof:placetype":"venue"
},
  "geometry": {"coordinates":[-122.67382499999999,45.473701],"type":"Point"}
}