{
  "type": "Feature",
  "properties": {
    "iso:country":"US",
    "sg:address":"3000 Westgate",
    "sg:city":"Portland",
    "sg:classifiers":[
        {
            "category":"Autos & Motor Vehicles",
            "subcategory":"Automobile Sales",
            "type":"Retail Goods"
        }
    ],
    "sg:phone":"+1 541 276 6075",
    "sg:postcode":"97239",
    "sg:province":"OR",
    "sg:tags":[
        "car"
    ],
    "sg:website":"www.keystonerv.com",
    "wof:name":"Keystone RV Co.",
    "wof:placetype":"venue"
},
  "geometry": {"coordinates":[-122.755876,45.479845],"type":"Point"}
}