{
  "type": "Feature",
  "properties": {
    "iso:country":"US",
    "sg:address":"1470 SW Knoll Ave",
    "sg:city":"Bend",
    "sg:classifiers":[
        {
            "category":"Professional",
            "subcategory":"Engineering",
            "type":"Services"
        }
    ],
    "sg:phone":"+1 541 389 9659",
    "sg:postcode":"97702",
    "sg:province":"OR",
    "sg:tags":[
        "engineer"
    ],
    "wof:name":"Eclipse Engineering",
    "wof:placetype":"venue"
},
  "geometry": {"coordinates":[-121.332858,44.050438],"type":"Point"}
}