{
  "type": "Feature",
  "properties": {
    "iso:country":"US",
    "sg:address":"7160 SW Fir Loop",
    "sg:city":"Portland",
    "sg:classifiers":[
        {
            "category":"Wholesale",
            "subcategory":"Non-durable Goods",
            "type":"Manufacturing & Wholesale Goods"
        }
    ],
    "sg:phone":"+1 503 620 0770",
    "sg:postcode":"97223",
    "sg:province":"OR",
    "sg:tags":[
        "advertising",
        "specialty"
    ],
    "wof:name":"Marco-Ideas Unlimited",
    "wof:placetype":"venue"
},
  "geometry": {"coordinates":[-122.751007,45.423217],"type":"Point"}
}