{
  "type": "Feature",
  "properties": {
    "iso:country":"US",
    "sg:address":"1595 NE 6th St",
    "sg:city":"Grants Pass",
    "sg:classifiers":[
        {
            "category":"Banks & Credit Unions",
            "subcategory":"Bank",
            "type":"Services"
        }
    ],
    "sg:phone":"+1 541 474 2100",
    "sg:postcode":"97526",
    "sg:province":"OR",
    "sg:tags":[
        "mortgage",
        "loan",
        "broker",
        "real estate"
    ],
    "wof:name":"Home Loan Store of Grants Pass",
    "wof:placetype":"venue"
},
  "geometry": {"coordinates":[-123.322532,42.456468],"type":"Point"}
}