{
  "type": "Feature",
  "properties": {
    "iso:country":"US",
    "sg:address":"506 NW Connell Ave",
    "sg:city":"Hillsboro",
    "sg:classifiers":[
        {
            "category":"Food & Beverages",
            "subcategory":"Groceries & Convenience Stores",
            "type":"Retail Goods"
        }
    ],
    "sg:phone":"+1 503 648 6449",
    "sg:postcode":"97124",
    "sg:province":"OR",
    "wof:name":"Northside Grocery",
    "wof:placetype":"venue"
},
  "geometry": {"coordinates":[-122.993606,45.528513],"type":"Point"}
}