{
  "type": "Feature",
  "properties": {
    "iso:country":"US",
    "sg:address":"2033 Cardinal Ave",
    "sg:city":"Medford",
    "sg:classifiers":[
        {
            "category":"Food & Beverages",
            "subcategory":"Groceries & Convenience Stores",
            "type":"Retail Goods"
        }
    ],
    "sg:phone":"+1 541 773 9849",
    "sg:postcode":"97504",
    "sg:province":"OR",
    "wof:name":"Cash & Carry",
    "wof:placetype":"venue"
},
  "geometry": {"coordinates":[-122.862999,42.370098],"type":"Point"}
}