{
  "type": "Feature",
  "properties": {
    "iso:country":"US",
    "sg:address":"501 SE Hawthorne Blvd",
    "sg:city":"Portland",
    "sg:classifiers":[
        {
            "category":"Government",
            "subcategory":"Office",
            "type":"Public Place"
        }
    ],
    "sg:phone":"+1 503 988 3326",
    "sg:postcode":"97214",
    "sg:province":"OR",
    "wof:name":"Multnomah County Assessment",
    "wof:placetype":"venue"
},
  "geometry": {"coordinates":[-122.659763,45.512232],"type":"Point"}
}