{
  "type": "Feature",
  "properties": {
    "addr:full":"16575 SE Webster Rd Milwaukie OR 97267",
    "addr:housenumber":"16575",
    "addr:postcode":"97267",
    "addr:street":"Se Webster Rd",
    "iso:country":"US",
    "sg:address":"16575 SE Webster Rd",
    "sg:city":"Milwaukie",
    "sg:classifiers":[
        {
            "category":"Place Of Worship",
            "subcategory":"Church",
            "type":"Public Place"
        }
    ],
    "sg:phone":"+1 503 653 0174",
    "sg:postcode":"97267",
    "sg:province":"OR",
    "sg:website":"www.newlifemilwaukie.org",
    "wof:name":"New Life Christian Center",
    "wof:placetype":"venue"
},
  "geometry": {"coordinates":[-122.58681300000001,45.402995],"type":"Point"}
}