{
  "type": "Feature",
  "properties": {
    "addr:full":"2879 Old Military Rd Central Point OR 97502",
    "addr:housenumber":"2879",
    "addr:postcode":"97502",
    "addr:street":"Old Military Rd",
    "iso:country":"US",
    "sg:address":"2879 Old Military Rd",
    "sg:city":"Central Point",
    "sg:classifiers":[
        {
            "category":"Communications",
            "type":"Services"
        }
    ],
    "sg:phone":"+1 541 664 4826",
    "sg:postcode":"97502",
    "sg:province":"OR",
    "sg:tags":[
        "recording",
        "rehearsal",
        "studio"
    ],
    "wof:name":"Oregon Sound Recording",
    "wof:placetype":"venue"
},
  "geometry": {"coordinates":[-122.959,42.3578],"type":"Point"}
}