{
  "type": "Feature",
  "properties": {
    "iso:country":"US",
    "sg:address":"40 NE 28th Ave",
    "sg:city":"Portland",
    "sg:classifiers":[
        {
            "category":"Restaurant",
            "type":"Food & Drink"
        }
    ],
    "sg:phone":"+1 503 238 1058",
    "sg:postcode":"97255",
    "sg:province":"OR",
    "sg:tags":[
        "italian"
    ],
    "sg:website":"labucaitaliancafe.com/index.html",
    "wof:name":"La Buca",
    "wof:placetype":"venue"
},
  "geometry": {"coordinates":[-122.63725599999999,45.523143],"type":"Point"}
}