{
  "type": "Feature",
  "properties": {
    "iso:country":"US",
    "sg:address":"333 NW 4th Ave",
    "sg:city":"Portland",
    "sg:classifiers":[
        {
            "category":"Building & Trades",
            "subcategory":"Locksmith",
            "type":"Services"
        }
    ],
    "sg:phone":"+1 503 715 3746",
    "sg:postcode":"97209",
    "sg:province":"OR",
    "sg:tags":[
        "key"
    ],
    "wof:name":"111 Locksmith",
    "wof:placetype":"venue"
},
  "geometry": {"coordinates":[-122.674665,45.525469],"type":"Point"}
}