{
  "type": "Feature",
  "properties": {
    "iso:country":"US",
    "sg:address":"450 11th Ave SE",
    "sg:city":"Albany",
    "sg:classifiers":[
        {
            "category":"Manufacturing",
            "subcategory":"Metals",
            "type":"Manufacturing & Wholesale Goods"
        }
    ],
    "sg:phone":"+1 541 926 2525",
    "sg:postcode":"97322",
    "sg:province":"OR",
    "sg:tags":[
        "ornamental",
        "work"
    ],
    "wof:name":"Metal Creations",
    "wof:placetype":"venue"
},
  "geometry": {"coordinates":[-123.099452,44.629683],"type":"Point"}
}