{
  "type": "Feature",
  "properties": {
    "iso:country":"US",
    "sg:address":"6620 SW Beaverton-Hillsdale Hwy",
    "sg:city":"Portland",
    "sg:classifiers":[
        {
            "category":"Restaurant",
            "type":"Food & Drink"
        }
    ],
    "sg:phone":"+1 503 292 8899",
    "sg:postcode":"97225",
    "sg:province":"OR",
    "wof:name":"Sakuoa Bana Restaurant",
    "wof:placetype":"venue"
},
  "geometry": {"coordinates":[-122.744304,45.486994],"type":"Point"}
}