{
  "type": "Feature",
  "properties": {
    "iso:country":"US",
    "sg:address":"1100 E Main St",
    "sg:city":"Medford",
    "sg:classifiers":[
        {
            "category":"Wholesale",
            "subcategory":"Seafood",
            "type":"Manufacturing & Wholesale Goods"
        }
    ],
    "sg:phone":"+1 541 779 4975",
    "sg:postcode":"97504",
    "sg:province":"OR",
    "wof:name":"Ocean Beauty Seafoods Inc",
    "wof:placetype":"venue"
},
  "geometry": {"coordinates":[-122.860001,42.327702],"type":"Point"}
}