{
  "type": "Feature",
  "properties": {
    "iso:country":"US",
    "sg:address":"241 NE 2nd Ave",
    "sg:city":"Canby",
    "sg:classifiers":[
        {
            "category":"Shopping",
            "subcategory":"Computers & Home Electronics",
            "type":"Retail Goods"
        }
    ],
    "sg:phone":"+1 503 266 6646",
    "sg:postcode":"97013",
    "sg:province":"OR",
    "sg:tags":[
        "equipment",
        "satellite",
        "system"
    ],
    "wof:name":"ACME Satellite",
    "wof:placetype":"venue"
},
  "geometry": {"coordinates":[-122.69064,45.264386],"type":"Point"}
}