{
  "type": "Feature",
  "properties": {
    "addr:full":"2281 NW Hoyt St Portland OR 97210",
    "addr:housenumber":"2281",
    "addr:postcode":"97210",
    "addr:street":"Nw Hoyt St",
    "iso:country":"US",
    "sg:address":"2281 NW Hoyt St",
    "sg:city":"Portland",
    "sg:classifiers":[
        {
            "category":"Sports & Exercise",
            "subcategory":"Gym",
            "type":"Entertainment"
        }
    ],
    "sg:phone":"+1 503 221 5030",
    "sg:postcode":"97210",
    "sg:province":"OR",
    "sg:tags":[
        "fitness",
        "physical",
        "facility"
    ],
    "wof:name":"Longevity Wellness Center",
    "wof:placetype":"venue"
},
  "geometry": {"coordinates":[-122.697344,45.527043],"type":"Point"}
}