{
  "type": "Feature",
  "properties": {
    "iso:country":"US",
    "sg:address":"8283 Vireo Ct",
    "sg:city":"Redmond",
    "sg:classifiers":[
        {
            "category":"Building & Trades",
            "subcategory":"Construction",
            "type":"Services"
        }
    ],
    "sg:phone":"+1 541 548 7050",
    "sg:postcode":"97756",
    "sg:province":"OR",
    "sg:tags":[
        "house"
    ],
    "wof:name":"S & S Services",
    "wof:placetype":"venue"
},
  "geometry": {"coordinates":[-121.271387,44.270066],"type":"Point"}
}