{
  "type": "Feature",
  "properties": {
    "iso:country":"US",
    "sg:address":"1201 SE 6th Ave",
    "sg:city":"Coquille",
    "sg:classifiers":[
        {
            "category":"Manufacturing",
            "subcategory":"Buildings",
            "type":"Manufacturing & Wholesale Goods"
        },
        {
            "category":"Building & Trades",
            "subcategory":"Construction",
            "type":"Services"
        }
    ],
    "sg:phone":"+1 541 396 5445",
    "sg:postcode":"97423",
    "sg:province":"OR",
    "sg:tags":[
        "home",
        "builder",
        "contractor"
    ],
    "wof:name":"Country Classic Construction",
    "wof:placetype":"venue"
},
  "geometry": {"coordinates":[-124.177261,43.166691],"type":"Point"}
}