{
  "type": "Feature",
  "properties": {
    "addr:full":"812 Oak St Medford OR 97501",
    "addr:housenumber":"812",
    "addr:postcode":"97501",
    "addr:street":"Oak St",
    "iso:country":"US",
    "sg:address":"812 Oak St",
    "sg:city":"Medford",
    "sg:classifiers":[
        {
            "category":"Restaurant",
            "type":"Food & Drink"
        }
    ],
    "sg:phone":"+1 541 779 0855",
    "sg:postcode":"97501",
    "sg:province":"OR",
    "sg:tags":[
        "eating"
    ],
    "wof:name":"Cafe Bohemia",
    "wof:placetype":"venue"
},
  "geometry": {"coordinates":[-122.88436400000001,42.333462],"type":"Point"}
}