{
  "type": "Feature",
  "properties": {
    "addr:full":"135 SE Main Street Suite 101 Portland OR 97214",
    "addr:housenumber":"135",
    "addr:postcode":"97214",
    "addr:street":"Se Main Street Suite 101",
    "iso:country":"US",
    "sg:address":"135 SE Main Street Suite 101",
    "sg:city":"Portland",
    "sg:classifiers":[
        {
            "category":"Shopping",
            "subcategory":"Bicycles & Sporting Goods",
            "type":"Retail Goods"
        },
        {
            "category":"Professional",
            "subcategory":"Business Services",
            "type":"Services"
        },
        {
            "category":"Parking",
            "subcategory":"Bicycle",
            "type":"Transportation"
        }
    ],
    "sg:phone":"+1 503 226 0696",
    "sg:postcode":"97214",
    "sg:province":"OR",
    "sg:tags":[
        "shop",
        "bicycles-wholesale",
        "system",
        "bike",
        "security",
        "rack",
        "manufacturer"
    ],
    "sg:website":"www.cyclonebicycle.com",
    "wof:name":"Cyclone Bicycle Supply",
    "wof:placetype":"venue"
},
  "geometry": {"coordinates":[-122.66389700000001,45.513596],"type":"Point"}
}