{
  "type": "Feature",
  "properties": {
    "iso:country":"US",
    "sg:address":"60022 Minnetonka Ln",
    "sg:city":"Bend",
    "sg:classifiers":[
        {
            "category":"Retail",
            "subcategory":"Auto Repair",
            "type":"Services"
        }
    ],
    "sg:phone":"+1 541 388 8432",
    "sg:postcode":"97702",
    "sg:province":"OR",
    "sg:tags":[
        "general"
    ],
    "wof:name":"Drw Mobile Automotive Repair",
    "wof:placetype":"venue"
},
  "geometry": {"coordinates":[-121.35812300000001,43.979306],"type":"Point"}
}