{
  "type": "Feature",
  "properties": {
    "addr:full":"4826 N Lombard St Portland OR 97203",
    "addr:housenumber":"4826",
    "addr:postcode":"97203",
    "addr:street":"N Lombard St",
    "iso:country":"US",
    "sg:address":"4826 N Lombard St",
    "sg:city":"Portland",
    "sg:classifiers":[
        {
            "category":"Building & Trades",
            "subcategory":"Locksmith",
            "type":"Services"
        }
    ],
    "sg:phone":"+1 503 820 0020",
    "sg:postcode":"97203",
    "sg:province":"OR",
    "sg:tags":[
        "key"
    ],
    "wof:name":"Emergency 1 Locksmith",
    "wof:placetype":"venue"
},
  "geometry": {"coordinates":[-122.718818,45.580405],"type":"Point"}
}