{
  "type": "Feature",
  "properties": {
    "iso:country":"US",
    "sg:address":"372 W Hood Ave",
    "sg:city":"Sisters",
    "sg:classifiers":[
        {
            "category":"Shopping",
            "subcategory":"Clothing, Apparel, & Fashions",
            "type":"Retail Goods"
        }
    ],
    "sg:phone":"+1 541 549 9910",
    "sg:postcode":"97759",
    "sg:province":"OR",
    "sg:tags":[
        "alteration"
    ],
    "wof:name":"Miss Sew-It-All Costume-Sewing",
    "wof:placetype":"venue"
},
  "geometry": {"coordinates":[-121.553304,44.2904],"type":"Point"}
}