{
  "type": "Feature",
  "properties": {
    "iso:country":"US",
    "sg:address":"2235 Country Club Rd",
    "sg:city":"Woodburn",
    "sg:classifiers":[
        {
            "category":"Banks & Credit Unions",
            "subcategory":"Bank",
            "type":"Services"
        }
    ],
    "sg:phone":"+1 503 982 1626",
    "sg:postcode":"97071",
    "sg:province":"OR",
    "sg:tags":[
        "broker",
        "mortgage"
    ],
    "wof:name":"Columbia Funding Group Inc",
    "wof:placetype":"venue"
},
  "geometry": {"coordinates":[-122.87385,45.152759],"type":"Point"}
}