{
  "type": "Feature",
  "properties": {
    "addr:full":"107 SE Grand Ave Portland OR 97214",
    "addr:housenumber":"107",
    "addr:postcode":"97214",
    "addr:street":"Se Grand Ave",
    "iso:country":"US",
    "sg:address":"107 SE Grand Ave",
    "sg:city":"Portland",
    "sg:classifiers":[
        {
            "category":"Autos & Motor Vehicles",
            "subcategory":"Automobile Sales",
            "type":"Retail Goods"
        }
    ],
    "sg:phone":"+1 877 414 3167",
    "sg:postcode":"97214",
    "sg:province":"OR",
    "sg:tags":[
        "car",
        "used",
        "dealership"
    ],
    "sg:website":"http://local.ingenio.com/Listings/Details.aspx?NUM=a%3a10126525%3a13%3a4859924%3a14%3a0%3a7",
    "wof:name":"Wentworth Chevrolet",
    "wof:placetype":"venue"
},
  "geometry": {"coordinates":[-122.660721,45.522177],"type":"Point"}
}