{
  "type": "Feature",
  "properties": {
    "iso:country":"US",
    "sg:address":"3321 Hidden Spring",
    "sg:city":"Medford",
    "sg:classifiers":[
        {
            "category":"Travel",
            "subcategory":"Travel Agent",
            "type":"Entertainment"
        }
    ],
    "sg:phone":"+1 541 734 2020",
    "sg:postcode":"97504",
    "sg:province":"OR",
    "sg:tags":[
        "agency",
        "bureau"
    ],
    "wof:name":"Trips R Us Travel",
    "wof:placetype":"venue"
},
  "geometry": {"coordinates":[-122.82244,42.312117],"type":"Point"}
}