{
  "type": "Feature",
  "properties": {
    "addr:full":"715 NW 3rd St Prineville OR 97754",
    "addr:housenumber":"715",
    "addr:postcode":"97754",
    "addr:street":"Nw 3Rd St",
    "iso:country":"US",
    "sg:address":"715 NW 3rd St",
    "sg:city":"Prineville",
    "sg:classifiers":[
        {
            "category":"Real Estate",
            "subcategory":"Real Estate Services",
            "type":"Services"
        },
        {
            "category":"Real Estate",
            "subcategory":"Real Estate Agent",
            "type":"Services"
        }
    ],
    "sg:phone":"+1 541 447 3940",
    "sg:postcode":"97754",
    "sg:province":"OR",
    "sg:tags":[
        "buyer",
        "management",
        "broker"
    ],
    "sg:website":"http://www.tare.net",
    "wof:name":"The Associates Real Estate Inc",
    "wof:placetype":"venue"
},
  "geometry": {"coordinates":[-120.855114,44.302939],"type":"Point"}
}