{
  "type": "Feature",
  "properties": {
    "iso:country":"US",
    "sg:address":"360 Elk Dr",
    "sg:city":"Cottage Grove",
    "sg:classifiers":[
        {
            "category":"Shopping",
            "subcategory":"Hobbies, Toys, & Games",
            "type":"Retail Goods"
        }
    ],
    "sg:phone":"+1 541 942 7312",
    "sg:postcode":"97424",
    "sg:province":"OR",
    "wof:name":"Pacific Stamp & Hobby Inc",
    "wof:placetype":"venue"
},
  "geometry": {"coordinates":[-123.062211,43.810319],"type":"Point"}
}