{
  "type": "Feature",
  "properties": {
    "addr:full":"502 S Central Ave Medford OR 97501",
    "addr:housenumber":"502",
    "addr:postcode":"97501",
    "addr:street":"S Central Ave",
    "iso:country":"US",
    "sg:address":"502 S Central Ave",
    "sg:city":"Medford",
    "sg:classifiers":[
        {
            "category":"Professional",
            "subcategory":"Business Services",
            "type":"Services"
        },
        {
            "category":"Real Estate",
            "subcategory":"Surveying",
            "type":"Services"
        },
        {
            "category":"Real Estate",
            "subcategory":"Real Estate Agent",
            "type":"Services"
        },
        {
            "category":"Real Estate",
            "subcategory":"Real Estate Services",
            "type":"Services"
        }
    ],
    "sg:phone":"+1 541 772 7258",
    "sg:postcode":"97501",
    "sg:province":"OR",
    "sg:tags":[
        "appraisers-business",
        "industrial",
        "commercial",
        "appraisers-commercial",
        "broker",
        "buyer",
        "appraiser"
    ],
    "wof:name":"Frohreich Rick V Real Estate Appraiser",
    "wof:placetype":"venue"
},
  "geometry": {"coordinates":[-122.868343,42.322439],"type":"Point"}
}