{
  "type": "Feature",
  "properties": {
    "addr:full":"5057 Brooklake Rd NE Brooks OR 97305",
    "addr:housenumber":"5057",
    "addr:postcode":"97305",
    "addr:street":"Brooklake Rd Ne",
    "iso:country":"US",
    "sg:address":"5057 Brooklake Rd NE",
    "sg:city":"Brooks",
    "sg:classifiers":[
        {
            "category":"Freight",
            "type":"Transportation"
        }
    ],
    "sg:phone":"+1 503 399 1300",
    "sg:postcode":"97305",
    "sg:province":"OR",
    "sg:tags":[
        "trucking"
    ],
    "wof:name":"Cherry City Express",
    "wof:placetype":"venue"
},
  "geometry": {"coordinates":[-122.95867699999999,45.048136],"type":"Point"}
}