{
  "type": "Feature",
  "properties": {
    "iso:country":"US",
    "sg:address":"346 Boyer Rd",
    "sg:city":"Grants Pass",
    "sg:classifiers":[
        {
            "category":"Recreation",
            "type":"Entertainment"
        }
    ],
    "sg:phone":"+1 541 474 7738",
    "sg:postcode":"97526",
    "sg:province":"OR",
    "sg:tags":[
        "club",
        "membership"
    ],
    "wof:name":"Scandanavian Heritage Club",
    "wof:placetype":"venue"
},
  "geometry": {"coordinates":[-123.391916,42.548062],"type":"Point"}
}