{
  "type": "Feature",
  "properties": {
    "addr:full":"346 Boyer Rd Grants Pass OR 97526",
    "addr:housenumber":"346",
    "addr:postcode":"97526",
    "addr:street":"Boyer Rd",
    "iso:country":"US",
    "sg:address":"346 Boyer Rd",
    "sg:city":"Grants Pass",
    "sg:classifiers":[
        {
            "category":"Recreation",
            "type":"Entertainment"
        }
    ],
    "sg:phone":"+1 541 474 7738",
    "sg:postcode":"97526",
    "sg:province":"OR",
    "sg:tags":[
        "club",
        "membership"
    ],
    "wof:name":"Scandanavian Heritage Club",
    "wof:placetype":"venue"
},
  "geometry": {"coordinates":[-123.39191599999999,42.548062],"type":"Point"}
}