{
  "type": "Feature",
  "properties": {
    "iso:country":"US",
    "sg:address":"61307 Robin Hood Ln",
    "sg:city":"Bend",
    "sg:classifiers":[
        {
            "category":"Real Estate",
            "subcategory":"Real Estate Agent",
            "type":"Services"
        }
    ],
    "sg:phone":"+1 541 317 0197",
    "sg:postcode":"97702",
    "sg:province":"OR",
    "sg:tags":[
        "appraiser"
    ],
    "wof:name":"Sam Houston Appraisers",
    "wof:placetype":"venue"
},
  "geometry": {"coordinates":[-121.285397,44.025567],"type":"Point"}
}