{
  "type": "Feature",
  "properties": {
    "iso:country":"US",
    "sg:address":"2645 SW Sandlewood Ave",
    "sg:city":"Gresham",
    "sg:classifiers":[
        {
            "category":"Building & Trades",
            "subcategory":"Construction",
            "type":"Services"
        }
    ],
    "sg:phone":"+1 503 998 2511",
    "sg:postcode":"97080",
    "sg:province":"OR",
    "sg:tags":[
        "remodeling",
        "vinyl"
    ],
    "wof:name":"Bid All Construction LLC",
    "wof:placetype":"venue"
},
  "geometry": {"coordinates":[-122.46677,45.478089],"type":"Point"}
}