{
  "type": "Feature",
  "properties": {
    "iso:country":"US",
    "sg:address":"13500 SW Pacific Hwy",
    "sg:city":"Tigard",
    "sg:classifiers":[
        {
            "category":"Professional",
            "subcategory":"Detective & Security Services",
            "type":"Services"
        }
    ],
    "sg:phone":"+1 503 524 4407",
    "sg:postcode":"97223",
    "sg:province":"OR",
    "sg:tags":[
        "investigator"
    ],
    "wof:name":"WCI Investigative Svc",
    "wof:placetype":"venue"
},
  "geometry": {"coordinates":[-122.783546,45.422717],"type":"Point"}
}