{
  "type": "Feature",
  "properties": {
    "iso:country":"US",
    "sg:address":"120 E Ellendale Ave",
    "sg:city":"Dallas",
    "sg:classifiers":[
        {
            "category":"Autos & Motor Vehicles",
            "subcategory":"Fuel & Gas Station",
            "type":"Retail Goods"
        }
    ],
    "sg:phone":"+1 503 623 3227",
    "sg:postcode":"97338",
    "sg:province":"OR",
    "sg:tags":[
        "oil"
    ],
    "wof:name":"Lee's Auto Svc",
    "wof:placetype":"venue"
},
  "geometry": {"coordinates":[-123.307563,44.930063],"type":"Point"}
}