{
  "type": "Feature",
  "properties": {
    "iso:country":"US",
    "sg:address":"1284 NW Highland St",
    "sg:city":"Roseburg",
    "sg:classifiers":[
        {
            "category":"Wholesale",
            "subcategory":"Machinery & Supplies",
            "type":"Manufacturing & Wholesale Goods"
        },
        {
            "category":"Personal",
            "subcategory":"Beauty Salon",
            "type":"Services"
        }
    ],
    "sg:phone":"+1 541 677 0246",
    "sg:postcode":"97470",
    "sg:province":"OR",
    "sg:tags":[
        "shop",
        "equipment",
        "establishment"
    ],
    "wof:name":"Takin Care Of Beauty",
    "wof:placetype":"venue"
},
  "geometry": {"coordinates":[-123.354986,43.223045],"type":"Point"}
}