{
  "type": "Feature",
  "properties": {
    "iso:country":"US",
    "sg:address":"621 Main St",
    "sg:city":"Oregon City",
    "sg:classifiers":[
        {
            "category":"Professional",
            "subcategory":"Accounting & Tax Preparation",
            "type":"Services"
        }
    ],
    "sg:phone":"+1 503 655 6997",
    "sg:postcode":"97045",
    "sg:province":"OR",
    "wof:name":"Phil H James CPA",
    "wof:placetype":"venue"
},
  "geometry": {"coordinates":[-122.60914699999999,45.357549],"type":"Point"}
}