{
  "type": "Feature",
  "properties": {
    "addr:full":"13175 SE Sunnyside Rd Happy Valley OR 97086",
    "addr:housenumber":"13175",
    "addr:postcode":"97086",
    "addr:street":"Se Sunnyside Rd",
    "iso:country":"US",
    "sg:address":"13175 SE Sunnyside Rd",
    "sg:city":"Happy Valley",
    "sg:classifiers":[
        {
            "category":"Bars & Pubs",
            "type":"Food & Drink"
        },
        {
            "category":"Restaurant",
            "type":"Food & Drink"
        },
        {
            "category":"Bars & Pubs",
            "subcategory":"Lounge",
            "type":"Food & Drink"
        }
    ],
    "sg:phone":"+1 503 698 6018",
    "sg:postcode":"97086",
    "sg:province":"OR",
    "sg:tags":[
        "traditional",
        "american",
        "karaoke"
    ],
    "sg:website":"www.gloriazpubgrill.com",
    "wof:name":"Gloria'z Pub & Grill",
    "wof:placetype":"venue"
},
  "geometry": {"coordinates":[-122.528139,45.426883],"type":"Point"}
}