{
  "type": "Feature",
  "properties": {
    "iso:country":"US",
    "sg:address":"9652 SW Beaverton Hillsdale Hwy",
    "sg:city":"Beaverton",
    "sg:classifiers":[
        {
            "category":"Building & Trades",
            "subcategory":"Construction",
            "type":"Services"
        },
        {
            "category":"Home & Garden",
            "subcategory":"Furniture",
            "type":"Retail Goods"
        }
    ],
    "sg:phone":"+1 503 646 8949",
    "sg:postcode":"97005",
    "sg:province":"OR",
    "sg:tags":[
        "interior",
        "design",
        "store"
    ],
    "wof:name":"Ernesto Garcia Interiors",
    "wof:placetype":"venue"
},
  "geometry": {"coordinates":[-122.776235,45.486501],"type":"Point"}
}