{
  "type": "Feature",
  "properties": {
    "addr:full":"7589 SW Vlahos Dr Wilsonville OR 97070",
    "addr:housenumber":"7589",
    "addr:postcode":"97070",
    "addr:street":"Sw Vlahos Dr",
    "iso:country":"US",
    "sg:address":"7589 SW Vlahos Dr",
    "sg:city":"Wilsonville",
    "sg:classifiers":[
        {
            "category":"Restaurant",
            "type":"Food & Drink"
        }
    ],
    "sg:phone":"+1 503 684 2012",
    "sg:postcode":"97070",
    "sg:province":"OR",
    "sg:tags":[
        "caterer"
    ],
    "wof:name":"Conners Events & Catering",
    "wof:placetype":"venue"
},
  "geometry": {"coordinates":[-122.756204,45.310387],"type":"Point"}
}