{
  "type": "Feature",
  "properties": {
    "iso:country":"US",
    "sg:address":"340 Khyber Ct SE",
    "sg:city":"Salem",
    "sg:classifiers":[
        {
            "category":"Local Transit",
            "type":"Transportation"
        }
    ],
    "sg:phone":"+1 503 587 7395",
    "sg:postcode":"97306",
    "sg:province":"OR",
    "wof:name":"Johanson Transportation",
    "wof:placetype":"venue"
},
  "geometry": {"coordinates":[-123.052651,44.881137],"type":"Point"}
}