{
  "type": "Feature",
  "properties": {
    "addr:full":"1280 SW Oak St Hillsboro OR 97123",
    "addr:housenumber":"1280",
    "addr:postcode":"97123",
    "addr:street":"Sw Oak St",
    "iso:country":"US",
    "sg:address":"1280 SW Oak St",
    "sg:city":"Hillsboro",
    "sg:classifiers":[
        {
            "category":"Restaurant",
            "type":"Food & Drink"
        }
    ],
    "sg:phone":"+1 503 693 0469",
    "sg:postcode":"97123",
    "sg:province":"OR",
    "wof:name":"Sunset Grill Restaurant",
    "wof:placetype":"venue"
},
  "geometry": {"coordinates":[-123.006801,45.519802],"type":"Point"}
}