{
  "type": "Feature",
  "properties": {
    "iso:country":"US",
    "sg:address":"227 NW 5th St",
    "sg:city":"Grants Pass",
    "sg:classifiers":[
        {
            "category":"Utilities",
            "subcategory":"Telephone",
            "type":"Services"
        }
    ],
    "sg:phone":"+1 541 472 9788",
    "sg:postcode":"97526",
    "sg:province":"OR",
    "sg:tags":[
        "internet"
    ],
    "wof:name":"Commerce Guard",
    "wof:placetype":"venue"
},
  "geometry": {"coordinates":[-123.327591,42.440594],"type":"Point"}
}