{
  "type": "Feature",
  "properties": {
    "iso:country":"US",
    "sg:address":"300 SW Columbia St",
    "sg:city":"Bend",
    "sg:classifiers":[
        {
            "category":"Organizations",
            "subcategory":"Professional Association",
            "type":"Services"
        }
    ],
    "sg:phone":"+1 541 318 3431",
    "sg:postcode":"97702",
    "sg:province":"OR",
    "wof:name":"Broken Top Community Assn",
    "wof:placetype":"venue"
},
  "geometry": {"coordinates":[-121.327058,44.046448],"type":"Point"}
}