{
  "type": "Feature",
  "properties": {
    "iso:country":"US",
    "sg:address":"62581 Eagle Rd",
    "sg:city":"Bend",
    "sg:classifiers":[
        {
            "category":"Real Estate",
            "subcategory":"Real Estate Operator",
            "type":"Services"
        }
    ],
    "sg:phone":"+1 541 389 3997",
    "sg:postcode":"97701",
    "sg:province":"OR",
    "sg:tags":[
        "building",
        "nonresidential"
    ],
    "wof:name":"Eagle Investment Associates",
    "wof:placetype":"venue"
},
  "geometry": {"coordinates":[-121.25369499999999,44.073565],"type":"Point"}
}