{
  "type": "Feature",
  "properties": {
    "iso:country":"US",
    "sg:address":"2013 1st St",
    "sg:city":"Baker City",
    "sg:classifiers":[
        {
            "category":"Health Services",
            "subcategory":"Doctor",
            "type":"Services"
        }
    ],
    "sg:phone":"+1 541 524 9283",
    "sg:postcode":"97814",
    "sg:province":"OR",
    "sg:tags":[
        "anesthetist"
    ],
    "wof:name":"Baker City Anesthesia",
    "wof:placetype":"venue"
},
  "geometry": {"coordinates":[-117.831053,44.778],"type":"Point"}
}