{
  "type": "Feature",
  "properties": {
    "iso:country":"US",
    "sg:address":"7525 NE Alameda St",
    "sg:city":"Portland",
    "sg:classifiers":[
        {
            "category":"Building & Trades",
            "subcategory":"Construction",
            "type":"Services"
        }
    ],
    "sg:phone":"+1 503 254 9892",
    "sg:postcode":"97213",
    "sg:province":"OR",
    "sg:tags":[
        "contractor"
    ],
    "wof:name":"Northwest Paint Preparation",
    "wof:placetype":"venue"
},
  "geometry": {"coordinates":[-122.58839,45.542788],"type":"Point"}
}