{
  "type": "Feature",
  "properties": {
    "addr:full":"9069 SW 35th Ave Portland OR 97219",
    "addr:housenumber":"9069",
    "addr:postcode":"97219",
    "addr:street":"Sw 35Th Ave",
    "iso:country":"US",
    "sg:address":"9069 SW 35th Ave",
    "sg:city":"Portland",
    "sg:classifiers":[
        {
            "category":"Real Estate",
            "subcategory":"Real Estate Operator",
            "type":"Services"
        }
    ],
    "sg:phone":"+1 503 246 1737",
    "sg:postcode":"97219",
    "sg:province":"OR",
    "sg:tags":[
        "building",
        "nonresidential"
    ],
    "wof:name":"Elmer L & Edith M Reho Fmly Tr",
    "wof:placetype":"venue"
},
  "geometry": {"coordinates":[-122.713531,45.458874],"type":"Point"}
}