{
  "type": "Feature",
  "properties": {
    "iso:country":"US",
    "sg:address":"9280 SW Palomino Pl",
    "sg:city":"Beaverton",
    "sg:classifiers":[
        {
            "category":"Professional",
            "subcategory":"Lawyer & Legal Services",
            "type":"Services"
        }
    ],
    "sg:phone":"+1 503 887 8796",
    "sg:postcode":"97008",
    "sg:province":"OR",
    "sg:tags":[
        "plan"
    ],
    "wof:name":"Hemmingson Leslie E D",
    "wof:placetype":"venue"
},
  "geometry": {"coordinates":[-122.823047,45.452283],"type":"Point"}
}