{
  "type": "Feature",
  "properties": {
    "iso:country":"US",
    "sg:address":"115 SE Court St",
    "sg:city":"Dallas",
    "sg:classifiers":[
        {
            "category":"Personal",
            "subcategory":"Beauty Salon",
            "type":"Services"
        },
        {
            "category":"Personal",
            "subcategory":"Day Spa",
            "type":"Services"
        },
        {
            "category":"Personal",
            "subcategory":"Tanning Parlor",
            "type":"Services"
        }
    ],
    "sg:phone":"+1 503 623 3606",
    "sg:postcode":"97338",
    "sg:province":"OR",
    "wof:name":"Envy Spa Salon",
    "wof:placetype":"venue"
},
  "geometry": {"coordinates":[-123.316514,44.920471],"type":"Point"}
}