{
  "type": "Feature",
  "properties": {
    "addr:full":"5258 Teresa Way Central Point OR 97502",
    "addr:housenumber":"5258",
    "addr:postcode":"97502",
    "addr:street":"Teresa Way",
    "iso:country":"US",
    "sg:address":"5258 Teresa Way",
    "sg:city":"Central Point",
    "sg:classifiers":[
        {
            "category":"Building & Trades",
            "subcategory":"Cleaning & Sanitation",
            "type":"Services"
        }
    ],
    "sg:phone":"+1 541 772 4657",
    "sg:postcode":"97502",
    "sg:province":"OR",
    "wof:name":"Service Master Co",
    "wof:placetype":"venue"
},
  "geometry": {"coordinates":[-122.91848899999999,42.393102],"type":"Point"}
}