{
  "type": "Feature",
  "properties": {
    "iso:country":"US",
    "sg:address":"2301 NW Thurman Street Suite D",
    "sg:city":"Portland",
    "sg:classifiers":[
        {
            "category":"Professional",
            "subcategory":"Lawyer & Legal Services",
            "type":"Services"
        }
    ],
    "sg:phone":"+1 503 223 2120",
    "sg:postcode":"97210",
    "sg:province":"OR",
    "wof:name":"Lawrence Ryan Atty",
    "wof:placetype":"venue"
},
  "geometry": {"coordinates":[-122.698662,45.535531],"type":"Point"}
}