{
  "type": "Feature",
  "properties": {
    "iso:country":"US",
    "sg:address":"2635 Brookside Dr",
    "sg:city":"Medford",
    "sg:classifiers":[
        {
            "category":"Real Estate",
            "subcategory":"Real Estate Agent",
            "type":"Services"
        }
    ],
    "sg:phone":"+1 541 773 7088",
    "sg:postcode":"97504",
    "sg:province":"OR",
    "sg:tags":[
        "appraiser"
    ],
    "wof:name":"David Fromme Co",
    "wof:placetype":"venue"
},
  "geometry": {"coordinates":[-122.842716,42.349009],"type":"Point"}
}