{
  "type": "Feature",
  "properties": {
    "addr:full":"130 SE Adams Ave Sherwood OR 97140",
    "addr:housenumber":"130",
    "addr:postcode":"97140",
    "addr:street":"Se Adams Ave",
    "iso:country":"US",
    "sg:address":"130 SE Adams Ave",
    "sg:city":"Sherwood",
    "sg:classifiers":[
        {
            "category":"Building & Trades",
            "subcategory":"Construction",
            "type":"Services"
        }
    ],
    "sg:phone":"+1 503 307 5373",
    "sg:postcode":"97140",
    "sg:province":"OR",
    "sg:tags":[
        "steel",
        "erection",
        "structural"
    ],
    "wof:name":"Ronald S Lang",
    "wof:placetype":"venue"
},
  "geometry": {"coordinates":[-122.836187,45.357617],"type":"Point"}
}