{
  "type": "Feature",
  "properties": {
    "iso:country":"US",
    "sg:address":"2351 NW York St",
    "sg:city":"Portland",
    "sg:classifiers":[
        {
            "category":"Building & Trades",
            "subcategory":"Locksmith",
            "type":"Services"
        }
    ],
    "sg:phone":"+1 503 914 1130",
    "sg:postcode":"97210",
    "sg:province":"OR",
    "sg:tags":[
        "key"
    ],
    "wof:name":"Always Portland Locksmith",
    "wof:placetype":"venue"
},
  "geometry": {"coordinates":[-122.69996399999999,45.539177],"type":"Point"}
}