{
  "type": "Feature",
  "properties": {
    "iso:country":"US",
    "sg:address":"19648 Hwy 126",
    "sg:city":"Walton",
    "sg:classifiers":[
        {
            "category":"Retail",
            "subcategory":"Auto Repair",
            "type":"Services"
        }
    ],
    "sg:phone":"+1 541 935 7828",
    "sg:postcode":"97490",
    "sg:province":"OR",
    "sg:tags":[
        "body"
    ],
    "wof:name":"Walton Body Shop The",
    "wof:placetype":"venue"
},
  "geometry": {"coordinates":[-123.55535,44.035681],"type":"Point"}
}