{
  "type": "Feature",
  "properties": {
    "iso:country":"US",
    "sg:address":"1115 SE 3rd St",
    "sg:city":"Corvallis",
    "sg:classifiers":[
        {
            "category":"Professional",
            "type":"Services"
        },
        {
            "category":"Restaurant",
            "type":"Food & Drink"
        }
    ],
    "sg:phone":"+1 541 754 6958",
    "sg:postcode":"97333",
    "sg:province":"OR",
    "sg:tags":[
        "style",
        "family",
        "house",
        "vegetarian",
        "mediterranean",
        "continental",
        "american",
        "caterer",
        "steak",
        "seafood",
        "pizza"
    ],
    "sg:website":"http://www.FireWorksVenue.com",
    "wof:name":"Fireworks Restaurant & Bar",
    "wof:placetype":"venue"
},
  "geometry": {"coordinates":[-123.265,44.553328],"type":"Point"}
}