{
  "type": "Feature",
  "properties": {
    "addr:full":"1045 Baltimore Ave SE Bandon OR 97411",
    "addr:housenumber":"1045",
    "addr:postcode":"bandon or 97411",
    "addr:street":"Baltimore Ave Se",
    "iso:country":"US",
    "sg:address":"1045 Baltimore Ave SE",
    "sg:city":"Bandon",
    "sg:classifiers":[
        {
            "category":"Real Estate",
            "subcategory":"Surveying",
            "type":"Services"
        }
    ],
    "sg:phone":"+1 541 347 9517",
    "sg:postcode":"97411",
    "sg:province":"OR",
    "wof:name":"Prahar Land Plg & Surveying",
    "wof:placetype":"venue"
},
  "geometry": {"coordinates":[-124.412899,43.113808],"type":"Point"}
}