{
  "type": "Feature",
  "properties": {
    "addr:full":"1609 NE 137th Ave Portland OR 97230",
    "addr:housenumber":"1609",
    "addr:postcode":"97230",
    "addr:street":"Ne 137Th Ave",
    "iso:country":"US",
    "sg:address":"1609 NE 137th Ave",
    "sg:city":"Portland",
    "sg:classifiers":[
        {
            "category":"Professional",
            "type":"Services"
        }
    ],
    "sg:phone":"+1 503 257 7573",
    "sg:postcode":"97230",
    "sg:province":"OR",
    "sg:tags":[
        "arranger",
        "music",
        "composer"
    ],
    "wof:name":"Empath Production & Recording",
    "wof:placetype":"venue"
},
  "geometry": {"coordinates":[-122.522088,45.534848],"type":"Point"}
}