{
  "type": "Feature",
  "properties": {
    "addr:full":"5204 NE 36th Ave Portland OR 97211",
    "addr:housenumber":"5204",
    "addr:postcode":"97211",
    "addr:street":"Ne 36Th Ave",
    "iso:country":"US",
    "sg:address":"5204 NE 36th Ave",
    "sg:city":"Portland",
    "sg:classifiers":[
        {
            "category":"Shopping",
            "subcategory":"Computers & Home Electronics",
            "type":"Retail Goods"
        }
    ],
    "sg:phone":"+1 503 287 8952",
    "sg:postcode":"97211",
    "sg:province":"OR",
    "sg:tags":[
        "software"
    ],
    "sg:website":"www.versabet.com",
    "wof:name":"JPM Computer",
    "wof:placetype":"venue"
},
  "geometry": {"coordinates":[-122.626526,45.560532],"type":"Point"}
}