{
  "type": "Feature",
  "properties": {
    "iso:country":"US",
    "sg:address":"380 Churchdale Ave N",
    "sg:city":"Keizer",
    "sg:classifiers":[
        {
            "category":"Organizations",
            "subcategory":"Religious Organization",
            "type":"Services"
        }
    ],
    "sg:phone":"+1 503 393 0222",
    "sg:postcode":"97303",
    "sg:province":"OR",
    "sg:tags":[
        "church"
    ],
    "wof:name":"Keizer Community Church",
    "wof:placetype":"venue"
},
  "geometry": {"coordinates":[-123.02831399999999,44.994626],"type":"Point"}
}