{
  "type": "Feature",
  "properties": {
    "iso:country":"US",
    "sg:address":"4805 SW Oleson Rd",
    "sg:city":"Portland",
    "sg:classifiers":[
        {
            "category":"Real Estate",
            "subcategory":"Real Estate Agent",
            "type":"Services"
        }
    ],
    "sg:phone":"+1 503 297 4731",
    "sg:postcode":"97225",
    "sg:province":"OR",
    "sg:tags":[
        "appraiser"
    ],
    "wof:name":"Donnerberg Appraisal Co",
    "wof:placetype":"venue"
},
  "geometry": {"coordinates":[-122.747754,45.484858],"type":"Point"}
}