{
  "type": "Feature",
  "properties": {
    "iso:country":"US",
    "sg:address":"93976 Ocean Way",
    "sg:city":"Gold Beach",
    "sg:classifiers":[
        {
            "category":"Building & Trades",
            "subcategory":"Plumbing",
            "type":"Services"
        }
    ],
    "sg:phone":"+1 541 247 8100",
    "sg:postcode":"97444",
    "sg:province":"OR",
    "sg:tags":[
        "refrigeration",
        "heating",
        "contractor"
    ],
    "wof:name":"Tion Heating",
    "wof:placetype":"venue"
},
  "geometry": {"coordinates":[-124.428102,42.432455],"type":"Point"}
}