{
  "type": "Feature",
  "properties": {
    "iso:country":"US",
    "sg:address":"2350 Martin Dr",
    "sg:city":"Stayton",
    "sg:classifiers":[
        {
            "category":"Social Services",
            "subcategory":"Child Care",
            "type":"Services"
        },
        {
            "category":"Education",
            "subcategory":"Preschool",
            "type":"Public Place"
        }
    ],
    "sg:phone":"+1 503 767 7473",
    "sg:postcode":"97383",
    "sg:province":"OR",
    "sg:tags":[
        "kindergarten",
        "nursery",
        "day"
    ],
    "wof:name":"Rise & Shine Child Care Center",
    "wof:placetype":"venue"
},
  "geometry": {"coordinates":[-122.793105,44.812502],"type":"Point"}
}