{
  "type": "Feature",
  "properties": {
    "addr:full":"319 SW Washington Street Portland OR 97204",
    "addr:housenumber":"319",
    "addr:postcode":"97204",
    "addr:street":"Sw Washington Street",
    "iso:country":"US",
    "sg:address":"319 SW Washington Street",
    "sg:city":"Portland",
    "sg:classifiers":[
        {
            "category":"Coffee & Tea",
            "type":"Food & Drink"
        }
    ],
    "sg:phone":"+1 503 525 2233",
    "sg:postcode":"97204",
    "sg:province":"OR",
    "wof:name":"Petite Cafe & Deli",
    "wof:placetype":"venue"
},
  "geometry": {"coordinates":[-122.67499599999999,45.519661],"type":"Point"}
}