{
  "type": "Feature",
  "properties": {
    "addr:full":"10435 SE 82nd Ave Portland OR 97086",
    "addr:postcode":"10435;97086",
    "addr:street":"Se 82Nd Ave",
    "iso:country":"US",
    "sg:address":"10435 SE 82nd Ave",
    "sg:city":"Portland",
    "sg:classifiers":[
        {
            "category":"Personal",
            "subcategory":"Nail Salon",
            "type":"Services"
        }
    ],
    "sg:phone":"+1 503 777 8799",
    "sg:postcode":"97086",
    "sg:province":"OR",
    "wof:name":"No 1 Nails",
    "wof:placetype":"venue"
},
  "geometry": {"coordinates":[-122.57908500000001,45.447586],"type":"Point"}
}