{
  "type": "Feature",
  "properties": {
    "addr:full":"544 NE Pine St Sublimity OR 97385",
    "addr:housenumber":"544",
    "addr:postcode":"97385",
    "addr:street":"Ne Pine St",
    "iso:country":"US",
    "sg:address":"544 NE Pine St",
    "sg:city":"Sublimity",
    "sg:classifiers":[
        {
            "category":"Social Services",
            "subcategory":"Child Care",
            "type":"Services"
        }
    ],
    "sg:phone":"+1 503 769 1426",
    "sg:postcode":"97385",
    "sg:province":"OR",
    "wof:name":"Kids Academy",
    "wof:placetype":"venue"
},
  "geometry": {"coordinates":[-122.787935,44.837803],"type":"Point"}
}