{
  "type": "Feature",
  "properties": {
    "iso:country":"US",
    "sg:address":"520 SW 6th Ave Ste 1130",
    "sg:city":"Portland",
    "sg:classifiers":[
        {
            "category":"Professional",
            "subcategory":"Business Services",
            "type":"Services"
        }
    ],
    "sg:phone":"+1 503 241 3506",
    "sg:postcode":"97204",
    "sg:province":"OR",
    "sg:tags":[
        "environmental",
        "product",
        "ecological"
    ],
    "sg:website":"http://www.rivernetwork.org",
    "wof:name":"River Network",
    "wof:placetype":"venue"
},
  "geometry": {"coordinates":[-122.677916,45.520233],"type":"Point"}
}