{
  "type": "Feature",
  "properties": {
    "iso:country":"US",
    "sg:address":"17879 Dixonville Rd",
    "sg:city":"Roseburg",
    "sg:classifiers":[
        {
            "category":"Building & Trades",
            "subcategory":"Construction",
            "type":"Services"
        }
    ],
    "sg:phone":"+1 541 957 0965",
    "sg:postcode":"97470",
    "sg:province":"OR",
    "sg:tags":[
        "paving",
        "road",
        "contractor"
    ],
    "wof:name":"Bruce Standley Construction",
    "wof:placetype":"venue"
},
  "geometry": {"coordinates":[-123.243025,43.195784],"type":"Point"}
}