{
  "type": "Feature",
  "properties": {
    "iso:country":"US",
    "sg:address":"4185 SE Howe St",
    "sg:city":"Portland",
    "sg:classifiers":[
        {
            "category":"Restaurant",
            "type":"Food & Drink"
        }
    ],
    "sg:phone":"+1 503 786 6804",
    "sg:postcode":"97222",
    "sg:province":"OR",
    "sg:tags":[
        "eating"
    ],
    "wof:name":"Freedom Cup LLC",
    "wof:placetype":"venue"
},
  "geometry": {"coordinates":[-122.621505,45.453011],"type":"Point"}
}