{
  "type": "Feature",
  "properties": {
    "addr:full":"1314 NE Foster Way Grants Pass OR 97526",
    "addr:housenumber":"1314",
    "addr:postcode":"97526",
    "addr:street":"Ne Foster Way",
    "iso:country":"US",
    "sg:address":"1314 NE Foster Way",
    "sg:city":"Grants Pass",
    "sg:classifiers":[
        {
            "category":"Real Estate",
            "subcategory":"Real Estate Agent",
            "type":"Services"
        }
    ],
    "sg:phone":"+1 541 476 7218",
    "sg:postcode":"97526",
    "sg:province":"OR",
    "wof:name":"Richard Ward Assoc",
    "wof:placetype":"venue"
},
  "geometry": {"coordinates":[-123.321547,42.451667],"type":"Point"}
}