{
  "type": "Feature",
  "properties": {
    "iso:country":"US",
    "sg:address":"611 NE 3rd St",
    "sg:city":"Mcminnville",
    "sg:classifiers":[
        {
            "category":"Manufacturing",
            "subcategory":"Printing",
            "type":"Manufacturing & Wholesale Goods"
        }
    ],
    "sg:phone":"+1 503 472 5114",
    "sg:postcode":"97128",
    "sg:province":"OR",
    "sg:tags":[
        "dealers-wholesale",
        "news",
        "newspaper"
    ],
    "sg:website":"http://www.oregonlitho.com",
    "wof:name":"News-Register Publishing Co",
    "wof:placetype":"venue"
},
  "geometry": {"coordinates":[-123.193163,45.210018],"type":"Point"}
}