{
  "type": "Feature",
  "properties": {
    "iso:country":"US",
    "sg:address":"415 E Pine St",
    "sg:city":"Central Point",
    "sg:classifiers":[
        {
            "category":"Freight",
            "type":"Transportation"
        }
    ],
    "sg:phone":"+1 541 665 2990",
    "sg:postcode":"97502",
    "sg:province":"OR",
    "sg:tags":[
        "broker",
        "trucking"
    ],
    "wof:name":"All Points Inc",
    "wof:placetype":"venue"
},
  "geometry": {"coordinates":[-122.913799,42.376052],"type":"Point"}
}