{
  "type": "Feature",
  "properties": {
    "iso:country":"US",
    "sg:address":"894 NW Burnside Rd",
    "sg:city":"Gresham",
    "sg:classifiers":[
        {
            "category":"Shopping",
            "subcategory":"Bicycles & Sporting Goods",
            "type":"Retail Goods"
        }
    ],
    "sg:phone":"+1 503 669 4653",
    "sg:postcode":"97030",
    "sg:province":"OR",
    "sg:tags":[
        "equipment",
        "golf",
        "supply"
    ],
    "wof:name":"Smart Golf",
    "wof:placetype":"venue"
},
  "geometry": {"coordinates":[-122.442004,45.511967],"type":"Point"}
}