{
  "type": "Feature",
  "properties": {
    "iso:country":"US",
    "sg:address":"102 W A St",
    "sg:city":"Rainier",
    "sg:classifiers":[
        {
            "category":"Wholesale",
            "subcategory":"Painting Supplies",
            "type":"Manufacturing & Wholesale Goods"
        },
        {
            "category":"Home & Garden",
            "subcategory":"Garden Supply",
            "type":"Retail Goods"
        },
        {
            "category":"Wholesale",
            "subcategory":"Construction Materials",
            "type":"Manufacturing & Wholesale Goods"
        },
        {
            "category":"Home & Garden",
            "subcategory":"Hardware",
            "type":"Retail Goods"
        }
    ],
    "sg:phone":"+1 503 556 3171",
    "sg:postcode":"97048",
    "sg:province":"OR",
    "sg:tags":[
        "lawn",
        "paint",
        "equipment",
        "part",
        "plumbing",
        "fixtures",
        "store"
    ],
    "sg:website":"http://www.truevalue.com/rainierhardware",
    "wof:name":"Rainier True Value",
    "wof:placetype":"venue"
},
  "geometry": {"coordinates":[-122.93565099999999,46.089935],"type":"Point"}
}