{
  "type": "Feature",
  "properties": {
    "iso:country":"US",
    "sg:address":"611 Klamath Ave",
    "sg:city":"Klamath Falls",
    "sg:classifiers":[
        {
            "category":"Banks & Credit Unions",
            "subcategory":"Bank",
            "type":"Services"
        }
    ],
    "sg:phone":"+1 541 273 1046",
    "sg:postcode":"97601",
    "sg:province":"OR",
    "sg:tags":[
        "loan"
    ],
    "wof:name":"Quick Check Cashing Svc",
    "wof:placetype":"venue"
},
  "geometry": {"coordinates":[-121.78105100000001,42.224872],"type":"Point"}
}