{
  "type": "Feature",
  "properties": {
    "iso:country":"US",
    "sg:address":"3005 SW Morris Ave",
    "sg:city":"Corvallis",
    "sg:classifiers":[
        {
            "category":"Shopping",
            "subcategory":"Hobbies, Toys, & Games",
            "type":"Retail Goods"
        }
    ],
    "sg:phone":"+1 541 758 3637",
    "sg:postcode":"97333",
    "sg:province":"OR",
    "wof:name":"Glass By Debra Klang",
    "wof:placetype":"venue"
},
  "geometry": {"coordinates":[-123.284018,44.555806],"type":"Point"}
}