{
  "type": "Feature",
  "properties": {
    "iso:country":"US",
    "sg:address":"5338 N Borthwick Avenue",
    "sg:city":"Portland",
    "sg:classifiers":[
        {
            "category":"Organizations",
            "subcategory":"Religious Organization",
            "type":"Services"
        }
    ],
    "sg:phone":"+1 503 285 2956",
    "sg:postcode":"97217",
    "sg:province":"OR",
    "sg:website":"www.church-of-christ.org",
    "wof:name":"Church of Christ",
    "wof:placetype":"venue"
},
  "geometry": {"coordinates":[-122.673805,45.5617],"type":"Point"}
}