{
  "type": "Feature",
  "properties": {
    "addr:full":"7350 SW 187th Pl Beaverton OR 97007",
    "addr:housenumber":"7350",
    "addr:postcode":"97007",
    "addr:street":"Sw 187Th Pl",
    "iso:country":"US",
    "sg:address":"7350 SW 187th Pl",
    "sg:city":"Beaverton",
    "sg:classifiers":[
        {
            "category":"Banks & Credit Unions",
            "subcategory":"Investment Brokerage",
            "type":"Services"
        }
    ],
    "sg:phone":"+1 503 259 3330",
    "sg:postcode":"97007",
    "sg:province":"OR",
    "sg:tags":[
        "firm",
        "brokerage"
    ],
    "wof:name":"Alpen Securities",
    "wof:placetype":"venue"
},
  "geometry": {"coordinates":[-122.868954,45.466586],"type":"Point"}
}