{
  "type": "Feature",
  "properties": {
    "iso:country":"US",
    "sg:address":"2848 S 6th St",
    "sg:city":"Klamath Falls",
    "sg:classifiers":[
        {
            "category":"Shopping",
            "subcategory":"Clothing, Apparel, & Fashions",
            "type":"Retail Goods"
        }
    ],
    "sg:phone":"+1 541 883 7659",
    "sg:postcode":"97603",
    "sg:province":"OR",
    "sg:tags":[
        "decor",
        "ranch",
        "western",
        "cowboy"
    ],
    "wof:name":"Home On The Range",
    "wof:placetype":"venue"
},
  "geometry": {"coordinates":[-121.75441600000001,42.209924],"type":"Point"}
}