{
  "type": "Feature",
  "properties": {
    "iso:country":"US",
    "sg:address":"8959 SW Barbur Blvd #204",
    "sg:city":"Portland",
    "sg:classifiers":[
        {
            "category":"Professional",
            "subcategory":"Management & Consulting",
            "type":"Services"
        }
    ],
    "sg:phone":"+1 800 344 8725",
    "sg:postcode":"97219",
    "sg:province":"OR",
    "sg:tags":[
        "marketing",
        "consultant"
    ],
    "sg:website":"http://www.mdcresearch.com",
    "wof:name":"Market Decisions Corporation",
    "wof:placetype":"venue"
},
  "geometry": {"coordinates":[-122.707144,45.460239],"type":"Point"}
}