{
  "type": "Feature",
  "properties": {
    "addr:full":"1167 Marine Dr Astoria OR 97103",
    "addr:housenumber":"1167",
    "addr:postcode":"97103",
    "addr:street":"Marine Dr",
    "iso:country":"US",
    "sg:address":"1167 Marine Dr",
    "sg:city":"Astoria",
    "sg:classifiers":[
        {
            "category":"Shopping",
            "subcategory":"Music",
            "type":"Retail Goods"
        }
    ],
    "sg:phone":"+1 503 325 0268",
    "sg:postcode":"97103",
    "sg:province":"OR",
    "sg:tags":[
        "used",
        "musical",
        "merchandise"
    ],
    "wof:name":"Mallternative",
    "wof:placetype":"venue"
},
  "geometry": {"coordinates":[-123.830986,46.189632],"type":"Point"}
}