{
  "type": "Feature",
  "properties": {
    "iso:country":"US",
    "sg:address":"16170 Dyke Rd",
    "sg:city":"La Pine",
    "sg:classifiers":[
        {
            "category":"Building & Trades",
            "subcategory":"Construction",
            "type":"Services"
        }
    ],
    "sg:phone":"+1 541 536 8457",
    "sg:postcode":"97739",
    "sg:province":"OR",
    "sg:tags":[
        "house"
    ],
    "wof:name":"Jack Pine Homebuilding & Remod",
    "wof:placetype":"venue"
},
  "geometry": {"coordinates":[-121.517366,43.720711],"type":"Point"}
}