{
  "type": "Feature",
  "properties": {
    "iso:country":"US",
    "sg:address":"6038 Glenwild Ct SE",
    "sg:city":"Turner",
    "sg:classifiers":[
        {
            "category":"Building & Trades",
            "subcategory":"Construction",
            "type":"Services"
        }
    ],
    "sg:phone":"+1 503 743 2479",
    "sg:postcode":"97392",
    "sg:province":"OR",
    "sg:tags":[
        "carpentry",
        "contractor"
    ],
    "wof:name":"Lundgren Timothy Construction",
    "wof:placetype":"venue"
},
  "geometry": {"coordinates":[-122.935371,44.847018],"type":"Point"}
}