{
  "type": "Feature",
  "properties": {
    "iso:country":"US",
    "sg:address":"5737 Prairie Ln",
    "sg:city":"Grants Pass",
    "sg:phone":"+1 541 476 9501",
    "sg:postcode":"97527",
    "sg:province":"OR",
    "sg:tags":[
        "farm",
        "field",
        "crop"
    ],
    "wof:name":"Brookmead Ranch & Gardens",
    "wof:placetype":"venue"
},
  "geometry": {"coordinates":[-123.441185,42.404031],"type":"Point"}
}