{
  "type": "Feature",
  "properties": {
    "iso:country":"US",
    "sg:address":"26438 Crow Rd",
    "sg:city":"Eugene",
    "sg:classifiers":[
        {
            "category":"Building & Trades",
            "subcategory":"Landscaping Services",
            "type":"Services"
        }
    ],
    "sg:phone":"+1 541 607 5667",
    "sg:postcode":"97402",
    "sg:province":"OR",
    "sg:tags":[
        "consultant",
        "designer",
        "landscape",
        "contractor"
    ],
    "sg:website":"http://www.camaslandscape.com",
    "wof:name":"Camas Landscape Services",
    "wof:placetype":"venue"
},
  "geometry": {"coordinates":[-123.297521,43.988862],"type":"Point"}
}