{
  "type": "Feature",
  "properties": {
    "addr:full":"16015 NE Siskiyou St Portland OR 97230",
    "addr:housenumber":"16015",
    "addr:postcode":"97230",
    "addr:street":"Ne Siskiyou St",
    "iso:country":"US",
    "sg:address":"16015 NE Siskiyou St",
    "sg:city":"Portland",
    "sg:classifiers":[
        {
            "category":"Social Services",
            "subcategory":"Adult Care",
            "type":"Services"
        }
    ],
    "sg:phone":"+1 503 255 6191",
    "sg:postcode":"97230",
    "sg:province":"OR",
    "sg:tags":[
        "residential",
        "aged",
        "homes-institutional"
    ],
    "wof:name":"Epsylon Adult Foster Care",
    "wof:placetype":"venue"
},
  "geometry": {"coordinates":[-122.497299,45.545601],"type":"Point"}
}