{
  "type": "Feature",
  "properties": {
    "iso:country":"US",
    "sg:address":"15220 NW Laidlaw Rd Ste 200",
    "sg:city":"Portland",
    "sg:classifiers":[
        {
            "category":"Real Estate",
            "subcategory":"Real Estate Services",
            "type":"Services"
        },
        {
            "category":"Real Estate",
            "subcategory":"Real Estate Agent",
            "type":"Services"
        }
    ],
    "sg:phone":"+1 503 891 4860",
    "sg:postcode":"97229",
    "sg:province":"OR",
    "sg:website":"www.LeaseOptionGroupHomes.com",
    "wof:name":"Lease Option and Owner Finance Group",
    "wof:placetype":"venue"
},
  "geometry": {"coordinates":[-122.833887,45.555405],"type":"Point"}
}