{
  "type": "Feature",
  "properties": {
    "iso:country":"US",
    "sg:address":"2041 Vine St",
    "sg:city":"Grants Pass",
    "sg:classifiers":[
        {
            "category":"Wholesale",
            "subcategory":"Machinery & Supplies",
            "type":"Manufacturing & Wholesale Goods"
        }
    ],
    "sg:phone":"+1 541 476 6316",
    "sg:postcode":"97526",
    "sg:province":"OR",
    "sg:tags":[
        "equipment",
        "mining"
    ],
    "wof:name":"Armadillo Mining Shop",
    "wof:placetype":"venue"
},
  "geometry": {"coordinates":[-123.3236,42.462915],"type":"Point"}
}