{
  "type": "Feature",
  "properties": {
    "iso:country":"US",
    "sg:address":"131 Ohio St",
    "sg:city":"Ashland",
    "sg:classifiers":[
        {
            "category":"Professional",
            "subcategory":"Business Services",
            "type":"Services"
        }
    ],
    "sg:phone":"+1 541 488 6495",
    "sg:postcode":"97520",
    "sg:province":"OR",
    "wof:name":"Workable Solutions",
    "wof:placetype":"venue"
},
  "geometry": {"coordinates":[-122.71516,42.204123],"type":"Point"}
}