{
  "type": "Feature",
  "properties": {
    "iso:country":"US",
    "sg:address":"1640 NE Irving St",
    "sg:city":"Portland",
    "sg:classifiers":[
        {
            "category":"Professional",
            "type":"Services"
        }
    ],
    "sg:phone":"+1 503 287 7540",
    "sg:postcode":"97232",
    "sg:province":"OR",
    "wof:name":"Susan J Chandler",
    "wof:placetype":"venue"
},
  "geometry": {"coordinates":[-122.64777100000001,45.527849],"type":"Point"}
}