{
  "type": "Feature",
  "properties": {
    "addr:full":"13454 SE 126th Ave Clackamas OR 97015",
    "addr:postcode":"13454;97015",
    "addr:street":"Se 126Th Ave",
    "iso:country":"US",
    "sg:address":"13454 SE 126th Ave",
    "sg:city":"Clackamas",
    "sg:classifiers":[
        {
            "category":"Professional",
            "subcategory":"Engineering",
            "type":"Services"
        }
    ],
    "sg:phone":"+1 503 698 2357",
    "sg:postcode":"97015",
    "sg:province":"OR",
    "sg:tags":[
        "engineer"
    ],
    "wof:name":"Butler Consulting Inc",
    "wof:placetype":"venue"
},
  "geometry": {"coordinates":[-122.534004,45.425141],"type":"Point"}
}