{
  "type": "Feature",
  "properties": {
    "addr:full":"1441 Deborah Rd Newberg OR 97132",
    "addr:housenumber":"1441",
    "addr:postcode":"97132",
    "addr:street":"Deborah Rd",
    "iso:country":"US",
    "sg:address":"1441 Deborah Rd",
    "sg:city":"Newberg",
    "sg:classifiers":[
        {
            "category":"Education",
            "subcategory":"School",
            "type":"Public Place"
        }
    ],
    "sg:phone":"+1 503 554 4450",
    "sg:postcode":"97132",
    "sg:province":"OR",
    "sg:website":"www.newberg.k12.or.us",
    "wof:name":"Mabel Rush Elementary School",
    "wof:placetype":"venue"
},
  "geometry": {"coordinates":[-122.949907,45.311401],"type":"Point"}
}