{
  "type": "Feature",
  "properties": {
    "addr:full":"165 W 11th Ave Eugene OR 97401",
    "addr:housenumber":"165",
    "addr:postcode":"97401",
    "addr:street":"W 11Th Ave",
    "iso:country":"US",
    "sg:address":"165 W 11th Ave",
    "sg:city":"Eugene",
    "sg:classifiers":[
        {
            "category":"Real Estate",
            "subcategory":"Real Estate Agent",
            "type":"Services"
        }
    ],
    "sg:phone":"+1 541 343 3711",
    "sg:postcode":"97401",
    "sg:province":"OR",
    "wof:name":"B & A Inc",
    "wof:placetype":"venue"
},
  "geometry": {"coordinates":[-123.095636,44.047787],"type":"Point"}
}