{
  "type": "Feature",
  "properties": {
    "addr:full":"2039 N Coast Hwy Newport OR 97365",
    "addr:housenumber":"2039",
    "addr:postcode":"97365",
    "addr:street":"N Coast Hwy",
    "iso:country":"US",
    "sg:address":"2039 N Coast Hwy",
    "sg:city":"Newport",
    "sg:classifiers":[
        {
            "category":"Banks & Credit Unions",
            "subcategory":"Bank",
            "type":"Services"
        }
    ],
    "sg:phone":"+1 541 265 9880",
    "sg:postcode":"97365",
    "sg:province":"OR",
    "sg:tags":[
        "mortgage"
    ],
    "wof:name":"Landmark Mortgage Co",
    "wof:placetype":"venue"
},
  "geometry": {"coordinates":[-124.053078,44.651788],"type":"Point"}
}