{
  "type": "Feature",
  "properties": {
    "addr:full":"1120 NE Viking Ct Bend OR 97701",
    "addr:housenumber":"1120",
    "addr:postcode":"97701",
    "addr:street":"Ne Viking Ct",
    "iso:country":"US",
    "sg:address":"1120 NE Viking Ct",
    "sg:city":"Bend",
    "sg:classifiers":[
        {
            "category":"Building & Trades",
            "subcategory":"Cleaning & Sanitation",
            "type":"Services"
        }
    ],
    "sg:phone":"+1 541 617 1938",
    "sg:postcode":"97701",
    "sg:province":"OR",
    "sg:tags":[
        "maintenance"
    ],
    "wof:name":"Clean Rite Jantr & Pressure",
    "wof:placetype":"venue"
},
  "geometry": {"coordinates":[-121.29002800000001,44.071587],"type":"Point"}
}