{
  "type": "Feature",
  "properties": {
    "addr:full":"2475 Commercial St SE Salem OR 97302",
    "addr:housenumber":"2475",
    "addr:postcode":"97302",
    "addr:street":"Commercial St Se",
    "iso:country":"US",
    "sg:address":"2475 Commercial St SE",
    "sg:city":"Salem",
    "sg:classifiers":[
        {
            "category":"Autos & Motor Vehicles",
            "subcategory":"Automobile Sales",
            "type":"Retail Goods"
        }
    ],
    "sg:phone":"+1 503 585 5000",
    "sg:postcode":"97302",
    "sg:province":"OR",
    "sg:tags":[
        "car",
        "dealer"
    ],
    "wof:name":"Acura Of Salem",
    "wof:placetype":"venue"
},
  "geometry": {"coordinates":[-123.04495199999999,44.918067],"type":"Point"}
}