{
  "type": "Feature",
  "properties": {
    "addr:full":"21197 SW Pamela Ct Beaverton OR 97006",
    "addr:housenumber":"21197",
    "addr:postcode":"97006",
    "addr:street":"Sw Pamela Ct",
    "iso:country":"US",
    "sg:address":"21197 SW Pamela Ct",
    "sg:city":"Beaverton",
    "sg:classifiers":[
        {
            "category":"Building & Trades",
            "subcategory":"Construction",
            "type":"Services"
        }
    ],
    "sg:phone":"+1 503 649 9888",
    "sg:postcode":"97006",
    "sg:province":"OR",
    "sg:tags":[
        "installation",
        "carpet"
    ],
    "wof:name":"Better Rug Services",
    "wof:placetype":"venue"
},
  "geometry": {"coordinates":[-122.89553100000001,45.509411],"type":"Point"}
}