{
  "type": "Feature",
  "properties": {
    "iso:country":"US",
    "sg:address":"2007 SE Ash St",
    "sg:city":"Portland",
    "sg:classifiers":[
        {
            "category":"Professional",
            "type":"Services"
        }
    ],
    "sg:phone":"+1 503 234 0548",
    "sg:postcode":"97214",
    "sg:province":"OR",
    "sg:website":"www.mfia-eng.com/",
    "wof:name":"MFIA, Inc. Consulting Engineers",
    "wof:placetype":"venue"
},
  "geometry": {"coordinates":[-122.645188,45.521706],"type":"Point"}
}