{
  "type": "Feature",
  "properties": {
    "addr:full":"25245 Yamhill River Rd Willamina OR 97396",
    "addr:postcode":"25245;97396",
    "addr:street":"Yamhill River Rd",
    "iso:country":"US",
    "sg:address":"25245 Yamhill River Rd",
    "sg:city":"Willamina",
    "sg:classifiers":[
        {
            "category":"Professional",
            "subcategory":"Research",
            "type":"Services"
        }
    ],
    "sg:phone":"+1 503 876 4488",
    "sg:postcode":"97396",
    "sg:province":"OR",
    "sg:tags":[
        "development",
        "marketing",
        "product"
    ],
    "wof:name":"Havel Designs",
    "wof:placetype":"venue"
},
  "geometry": {"coordinates":[-123.544563,45.05427],"type":"Point"}
}