{
  "type": "Feature",
  "properties": {
    "iso:country":"US",
    "sg:address":"214 NW Couch St",
    "sg:city":"Portland",
    "sg:classifiers":[
        {
            "category":"Personal",
            "subcategory":"Tattoo Parlor",
            "type":"Services"
        }
    ],
    "sg:phone":"+1 503 288 1842",
    "sg:postcode":"97209",
    "sg:province":"OR",
    "sg:website":"www.electriccobratattooclub.com",
    "wof:name":"Electric Cobra Tattoo Club",
    "wof:placetype":"venue"
},
  "geometry": {"coordinates":[-122.672532,45.523859],"type":"Point"}
}