{
  "type": "Feature",
  "properties": {
    "iso:country":"US",
    "sg:address":"401 NW 13th Avenue",
    "sg:city":"Portland",
    "sg:classifiers":[
        {
            "category":"Professional",
            "type":"Services"
        }
    ],
    "sg:phone":"+1 503 224 9204",
    "sg:postcode":"97209",
    "sg:province":"OR",
    "sg:website":"www.swellpath.com",
    "wof:name":"SwellPath Interactive",
    "wof:placetype":"venue"
},
  "geometry": {"coordinates":[-122.684252,45.525785],"type":"Point"}
}