{
  "type": "Feature",
  "properties": {
    "iso:country":"US",
    "sg:address":"264 N 3rd Ave",
    "sg:city":"Rockaway Beach",
    "sg:classifiers":[
        {
            "category":"Restaurant",
            "type":"Food & Drink"
        }
    ],
    "sg:phone":"+1 503 436 0285",
    "sg:postcode":"97136",
    "sg:province":"OR",
    "wof:name":"Lumberyard Rotisserie & Grill",
    "wof:placetype":"venue"
},
  "geometry": {"coordinates":[-123.942138,45.614916],"type":"Point"}
}