{
  "type": "Feature",
  "properties": {
    "iso:country":"US",
    "sg:address":"1025 SW Washington St",
    "sg:city":"Portland",
    "sg:classifiers":[
        {
            "category":"Food & Beverages",
            "subcategory":"Liquor & Beverages",
            "type":"Retail Goods"
        }
    ],
    "sg:phone":"+1 503 223 6002",
    "sg:postcode":"97205",
    "sg:province":"OR",
    "sg:tags":[
        "beer",
        "spirit",
        "wine"
    ],
    "sg:website":"www.vinopoliswineshop.com/",
    "wof:name":"Vinopolis",
    "wof:placetype":"venue"
},
  "geometry": {"coordinates":[-122.681866,45.521713],"type":"Point"}
}