{
  "type": "Feature",
  "properties": {
    "iso:country":"US",
    "sg:address":"18005 SW Lower Boones Ferry Rd",
    "sg:city":"Portland",
    "sg:classifiers":[
        {
            "category":"Wholesale",
            "subcategory":"Apparel",
            "type":"Manufacturing & Wholesale Goods"
        },
        {
            "category":"Shopping",
            "subcategory":"Clothing, Apparel, & Fashions",
            "type":"Retail Goods"
        }
    ],
    "sg:phone":"+1 503 620 1777",
    "sg:postcode":"97224",
    "sg:province":"OR",
    "wof:name":"Barbara Johnson's Clothing",
    "wof:placetype":"venue"
},
  "geometry": {"coordinates":[-122.752764,45.390458],"type":"Point"}
}