{
  "type": "Feature",
  "properties": {
    "iso:country":"US",
    "sg:address":"1895 NW 9th St",
    "sg:city":"Corvallis",
    "sg:classifiers":[
        {
            "category":"Restaurant",
            "type":"Food & Drink"
        }
    ],
    "sg:menulink":"http://www.allmenus.com/or/corvallis/5826-ruby-tuesdays/menu/",
    "sg:phone":"+1 541 752 9899",
    "sg:postcode":"97330",
    "sg:province":"OR",
    "sg:tags":[
        "burger",
        "american"
    ],
    "wof:name":"Ruby Tuesdays",
    "wof:placetype":"venue"
},
  "geometry": {"coordinates":[-123.25608699999999,44.586643],"type":"Point"}
}