{
  "type": "Feature",
  "properties": {
    "iso:country":"US",
    "sg:address":"4677 Arizona Ave NE",
    "sg:city":"Salem",
    "sg:classifiers":[
        {
            "category":"Wholesale",
            "subcategory":"Office Equipment",
            "type":"Manufacturing & Wholesale Goods"
        },
        {
            "category":"Retail",
            "subcategory":"Repair Shop",
            "type":"Services"
        }
    ],
    "sg:phone":"+1 503 371 4571",
    "sg:postcode":"97305",
    "sg:province":"OR",
    "sg:tags":[
        "sell",
        "fax",
        "duplicating",
        "machine",
        "copying",
        "copy"
    ],
    "wof:name":"Copi-Tek Northwest Inc",
    "wof:placetype":"venue"
},
  "geometry": {"coordinates":[-122.970377,44.967252],"type":"Point"}
}