{
  "type": "Feature",
  "properties": {
    "iso:country":"US",
    "sg:address":"20581 S Upper Highland Rd",
    "sg:city":"Beavercreek",
    "sg:classifiers":[
        {
            "category":"Building & Trades",
            "subcategory":"Construction",
            "type":"Services"
        }
    ],
    "sg:phone":"+1 503 632 4897",
    "sg:postcode":"97004",
    "sg:province":"OR",
    "sg:tags":[
        "house"
    ],
    "wof:name":"Jl &K General Cont Corp",
    "wof:placetype":"venue"
},
  "geometry": {"coordinates":[-122.444022,45.248043],"type":"Point"}
}