{
  "type": "Feature",
  "properties": {
    "iso:country":"US",
    "sg:address":"7915 Warren St",
    "sg:city":"Bay City",
    "sg:classifiers":[
        {
            "category":"Retail",
            "subcategory":"Auto Repair",
            "type":"Services"
        }
    ],
    "sg:phone":"+1 503 377 2501",
    "sg:postcode":"97107",
    "sg:province":"OR",
    "sg:tags":[
        "repairing",
        "automobile"
    ],
    "wof:name":"Klingelhofer Auto Repair",
    "wof:placetype":"venue"
},
  "geometry": {"coordinates":[-123.881811,45.513396],"type":"Point"}
}