{
  "type": "Feature",
  "properties": {
    "iso:country":"US",
    "sg:address":"9404 SE Cooper St",
    "sg:city":"Portland",
    "sg:classifiers":[
        {
            "category":"Manufacturing",
            "subcategory":"Printing",
            "type":"Manufacturing & Wholesale Goods"
        }
    ],
    "sg:phone":"+1 503 777 6036",
    "sg:postcode":"97266",
    "sg:province":"OR",
    "sg:tags":[
        "periodical"
    ],
    "wof:name":"Teen Praise Newsletter",
    "wof:placetype":"venue"
},
  "geometry": {"coordinates":[-122.566793,45.472901],"type":"Point"}
}