{
  "type": "Feature",
  "properties": {
    "iso:country":"US",
    "sg:address":"725 NE Weidler Street",
    "sg:city":"Portland",
    "sg:classifiers":[
        {
            "category":"Fast Food",
            "type":"Food & Drink"
        },
        {
            "category":"Restaurant",
            "type":"Food & Drink"
        }
    ],
    "sg:phone":"+1 503 281 8351",
    "sg:postcode":"97232",
    "sg:province":"OR",
    "sg:tags":[
        "mexican"
    ],
    "wof:name":"Taco Bell",
    "wof:placetype":"venue"
},
  "geometry": {"coordinates":[-122.657922,45.534465],"type":"Point"}
}