{
  "type": "Feature",
  "properties": {
    "addr:full":"SE 21st St & SE Clatsop St Portland OR 97202",
    "addr:postcode":"97202",
    "addr:street":"Se 21St St & Se Clatsop St",
    "iso:country":"US",
    "sg:address":"SE 21st St & SE Clatsop St",
    "sg:city":"Portland",
    "sg:classifiers":[
        {
            "category":"Park",
            "type":"Public Place"
        }
    ],
    "sg:postcode":"97202",
    "sg:province":"OR",
    "sg:website":"www.portlandonline.com/parks/ind...",
    "wof:name":"Johnson Creek Park",
    "wof:placetype":"venue"
},
  "geometry": {"coordinates":[-122.643074,45.460753],"type":"Point"}
}