{
  "type": "Feature",
  "properties": {
    "addr:full":"4849 SE 30th Ave Portland OR 97202",
    "addr:housenumber":"4849",
    "addr:postcode":"97202",
    "addr:street":"Se 30Th Ave",
    "iso:country":"US",
    "sg:address":"4849 SE 30th Ave",
    "sg:city":"Portland",
    "sg:classifiers":[
        {
            "category":"Real Estate",
            "subcategory":"Real Estate Operator",
            "type":"Services"
        }
    ],
    "sg:phone":"+1 503 238 1808",
    "sg:postcode":"97202",
    "sg:province":"OR",
    "sg:tags":[
        "building",
        "apartment"
    ],
    "wof:name":"Lambert Gardens Apartments",
    "wof:placetype":"venue"
},
  "geometry": {"coordinates":[-122.634416,45.486733],"type":"Point"}
}