{
  "type": "Feature",
  "properties": {
    "iso:country":"US",
    "sg:address":"3975 Mercantile Dr Ste 158",
    "sg:city":"Lake Oswego",
    "sg:classifiers":[
        {
            "category":"Health Services",
            "subcategory":"Doctor",
            "type":"Services"
        }
    ],
    "sg:phone":"+1 503 636 9011",
    "sg:postcode":"97035",
    "sg:province":"OR",
    "sg:tags":[
        "dermatologist"
    ],
    "wof:name":"Allergy Asthma & Dermatology Associates PC",
    "wof:placetype":"venue"
},
  "geometry": {"coordinates":[-122.718002,45.414799],"type":"Point"}
}