{
  "type": "Feature",
  "properties": {
    "iso:country":"US",
    "sg:address":"1037 River Rd",
    "sg:city":"Eugene",
    "sg:classifiers":[
        {
            "category":"Personal",
            "subcategory":"Beauty Salon",
            "type":"Services"
        }
    ],
    "sg:phone":"+1 541 688 7575",
    "sg:postcode":"97404",
    "sg:province":"OR",
    "sg:tags":[
        "manicuring"
    ],
    "wof:name":"Nail Nook",
    "wof:placetype":"venue"
},
  "geometry": {"coordinates":[-123.121442,44.079917],"type":"Point"}
}