{
  "type": "Feature",
  "properties": {
    "iso:country":"US",
    "sg:address":"89975 Prairie Rd",
    "sg:city":"Eugene",
    "sg:classifiers":[
        {
            "category":"Manufacturing",
            "subcategory":"Rubber & Plastics",
            "type":"Manufacturing & Wholesale Goods"
        }
    ],
    "sg:phone":"+1 541 461 9797",
    "sg:postcode":"97402",
    "sg:province":"OR",
    "sg:tags":[
        "product",
        "mfg"
    ],
    "wof:name":"Elkhart Plastics West",
    "wof:placetype":"venue"
},
  "geometry": {"coordinates":[-123.162657,44.103672],"type":"Point"}
}