{
  "type": "Feature",
  "properties": {
    "addr:full":"6305 SE Foster Rd Portland OR 97206",
    "addr:housenumber":"6305",
    "addr:postcode":"97206",
    "addr:street":"Se Foster Rd",
    "iso:country":"US",
    "sg:address":"6305 SE Foster Rd",
    "sg:city":"Portland",
    "sg:classifiers":[
        {
            "category":"Arts & Performance",
            "subcategory":"Dance",
            "type":"Entertainment"
        }
    ],
    "sg:phone":"+1 503 771 7470",
    "sg:postcode":"97206",
    "sg:province":"OR",
    "sg:tags":[
        "school"
    ],
    "sg:website":"www.tangoberretin.com",
    "wof:name":"Tango Berretin",
    "wof:placetype":"venue"
},
  "geometry": {"coordinates":[-122.598327,45.490403],"type":"Point"}
}