{
  "type": "Feature",
  "properties": {
    "addr:full":"250 Hansard Ave Lebanon OR 97355",
    "addr:housenumber":"250",
    "addr:postcode":"97355",
    "addr:street":"Hansard Ave",
    "iso:country":"US",
    "sg:address":"250 Hansard Ave",
    "sg:city":"Lebanon",
    "sg:classifiers":[
        {
            "category":"Structure",
            "subcategory":"Warehouse",
            "type":"Public Place"
        },
        {
            "category":"Retail",
            "subcategory":"Storage",
            "type":"Services"
        }
    ],
    "sg:phone":"+1 541 259 4405",
    "sg:postcode":"97355",
    "sg:province":"OR",
    "sg:tags":[
        "self",
        "warehouses-merchandise"
    ],
    "wof:name":"Western Warehousing",
    "wof:placetype":"venue"
},
  "geometry": {"coordinates":[-122.918831,44.549049],"type":"Point"}
}