{
  "type": "Feature",
  "properties": {
    "iso:country":"US",
    "sg:address":"1146 Elizabeth St",
    "sg:city":"Eugene",
    "sg:classifiers":[
        {
            "category":"Manufacturing",
            "subcategory":"Buildings",
            "type":"Manufacturing & Wholesale Goods"
        },
        {
            "category":"Building & Trades",
            "subcategory":"Construction",
            "type":"Services"
        }
    ],
    "sg:phone":"+1 541 688 3049",
    "sg:postcode":"97402",
    "sg:province":"OR",
    "sg:tags":[
        "home",
        "builder",
        "management",
        "contractor"
    ],
    "wof:name":"Schenfeld Construction Inc",
    "wof:placetype":"venue"
},
  "geometry": {"coordinates":[-123.16991400000001,44.074086],"type":"Point"}
}