{
  "type": "Feature",
  "properties": {
    "iso:country":"US",
    "sg:address":"2595 NE Jack London St",
    "sg:city":"Corvallis",
    "sg:classifiers":[
        {
            "category":"Social Services",
            "subcategory":"Adult Care",
            "type":"Services"
        }
    ],
    "sg:phone":"+1 541 754 5808",
    "sg:postcode":"97330",
    "sg:province":"OR",
    "sg:tags":[
        "residential"
    ],
    "wof:name":"Park Place Assisted Living",
    "wof:placetype":"venue"
},
  "geometry": {"coordinates":[-123.246892,44.593219],"type":"Point"}
}