{
  "type": "Feature",
  "properties": {
    "iso:country":"US",
    "sg:address":"12790 SE Stark Street Suite 205",
    "sg:city":"Portland",
    "sg:classifiers":[
        {
            "category":"Real Estate",
            "subcategory":"Real Estate Services",
            "type":"Services"
        }
    ],
    "sg:phone":"+1 503 777 0788",
    "sg:postcode":"97233",
    "sg:province":"OR",
    "sg:tags":[
        "management",
        "property"
    ],
    "wof:name":"Portland Homes",
    "wof:placetype":"venue"
},
  "geometry": {"coordinates":[-122.53276,45.519026],"type":"Point"}
}