{
  "type": "Feature",
  "properties": {
    "addr:full":"5908 SE Woodstock Blvd Portland OR 97206",
    "addr:housenumber":"5908",
    "addr:postcode":"97206",
    "addr:street":"Se Woodstock Blvd",
    "iso:country":"US",
    "sg:address":"5908 SE Woodstock Blvd",
    "sg:city":"Portland",
    "sg:classifiers":[
        {
            "category":"Building & Trades",
            "subcategory":"Construction",
            "type":"Services"
        }
    ],
    "sg:phone":"+1 503 775 2160",
    "sg:postcode":"97206",
    "sg:province":"OR",
    "sg:tags":[
        "house"
    ],
    "wof:name":"Vaday Constuction Inc",
    "wof:placetype":"venue"
},
  "geometry": {"coordinates":[-122.603449,45.479088],"type":"Point"}
}