{
  "type": "Feature",
  "properties": {
    "iso:country":"US",
    "sg:address":"10555 SW 130th Ave",
    "sg:city":"Beaverton",
    "sg:classifiers":[
        {
            "category":"Professional",
            "type":"Services"
        }
    ],
    "sg:phone":"+1 503 579 0376",
    "sg:postcode":"97008",
    "sg:province":"OR",
    "sg:tags":[
        "establishment"
    ],
    "wof:name":"Faxline",
    "wof:placetype":"venue"
},
  "geometry": {"coordinates":[-122.810537,45.442875],"type":"Point"}
}