{
  "type": "Feature",
  "properties": {
    "iso:country":"US",
    "sg:address":"315 Loughridge Ave",
    "sg:city":"Grants Pass",
    "sg:classifiers":[
        {
            "category":"Building & Trades",
            "subcategory":"Plumbing",
            "type":"Services"
        }
    ],
    "sg:phone":"+1 541 479 2901",
    "sg:postcode":"97526",
    "sg:province":"OR",
    "sg:tags":[
        "plumbing",
        "contractor"
    ],
    "wof:name":"Roto-Rooter Plumbing & Drain",
    "wof:placetype":"venue"
},
  "geometry": {"coordinates":[-123.325356,42.456729],"type":"Point"}
}