{
  "type": "Feature",
  "properties": {
    "addr:full":"6276 SE Reed St Portland OR 97201",
    "addr:housenumber":"6276",
    "addr:postcode":"97201",
    "addr:street":"Se Reed St",
    "iso:country":"US",
    "sg:address":"6276 SE Reed St",
    "sg:city":"Portland",
    "sg:classifiers":[
        {
            "category":"Building & Trades",
            "subcategory":"Locksmith",
            "type":"Services"
        }
    ],
    "sg:phone":"+1 503 405 9231",
    "sg:postcode":"97201",
    "sg:province":"OR",
    "sg:tags":[
        "key"
    ],
    "wof:name":"A Locksmith 1 24 7",
    "wof:placetype":"venue"
},
  "geometry": {"coordinates":[-122.629181,45.477063],"type":"Point"}
}