{
  "type": "Feature",
  "properties": {
    "addr:full":"10445 Rickreall Rd Rickreall OR 97371",
    "addr:housenumber":"10445",
    "addr:postcode":"97371",
    "addr:street":"Rickreall Rd",
    "iso:country":"US",
    "sg:address":"10445 Rickreall Rd",
    "sg:city":"Rickreall",
    "sg:classifiers":[
        {
            "category":"Autos & Motor Vehicles",
            "subcategory":"Recreational Vehicle Sales",
            "type":"Retail Goods"
        }
    ],
    "sg:phone":"+1 503 831 2334",
    "sg:postcode":"97371",
    "sg:province":"OR",
    "wof:name":"On The Way Rv",
    "wof:placetype":"venue"
},
  "geometry": {"coordinates":[-123.24556699999999,44.928939],"type":"Point"}
}