{
  "type": "Feature",
  "properties": {
    "iso:country":"US",
    "sg:address":"840 Holly St",
    "sg:city":"Junction City",
    "sg:classifiers":[
        {
            "category":"Social Services",
            "type":"Services"
        }
    ],
    "sg:phone":"+1 541 998 5367",
    "sg:postcode":"97448",
    "sg:province":"OR",
    "wof:name":"Senior Meals",
    "wof:placetype":"venue"
},
  "geometry": {"coordinates":[-123.203654,44.221407],"type":"Point"}
}