{
  "type": "Feature",
  "properties": {
    "iso:country":"US",
    "sg:address":"1112 Court St",
    "sg:city":"Medford",
    "sg:classifiers":[
        {
            "category":"Autos & Motor Vehicles",
            "subcategory":"Auto Supplies",
            "type":"Retail Goods"
        }
    ],
    "sg:phone":"+1 541 776 6336",
    "sg:postcode":"97501",
    "sg:province":"OR",
    "sg:tags":[
        "tire"
    ],
    "wof:name":"Steve Dehle's Reliable Used",
    "wof:placetype":"venue"
},
  "geometry": {"coordinates":[-122.880382,42.340704],"type":"Point"}
}