{
  "type": "Feature",
  "properties": {
    "iso:country":"US",
    "sg:address":"3933 SW Kelly Ave",
    "sg:city":"Portland",
    "sg:classifiers":[
        {
            "category":"Professional",
            "subcategory":"Engineering",
            "type":"Services"
        }
    ],
    "sg:phone":"+1 503 536 7517",
    "sg:postcode":"97239",
    "sg:province":"OR",
    "sg:tags":[
        "civil",
        "structural",
        "engineer"
    ],
    "sg:website":"http://www.vlmk.com",
    "wof:name":"VLMK Consulting Engineers",
    "wof:placetype":"venue"
},
  "geometry": {"coordinates":[-122.67498500000001,45.493962],"type":"Point"}
}