{
  "type": "Feature",
  "properties": {
    "iso:country":"US",
    "sg:address":"4720 N Amherst St",
    "sg:city":"Portland",
    "sg:classifiers":[
        {
            "category":"Retail",
            "subcategory":"Portrait Studio",
            "type":"Services"
        }
    ],
    "sg:phone":"+1 503 283 1016",
    "sg:postcode":"97203",
    "sg:province":"OR",
    "sg:tags":[
        "photo"
    ],
    "wof:name":"Stickley Photography",
    "wof:placetype":"venue"
},
  "geometry": {"coordinates":[-122.717069,45.575593],"type":"Point"}
}