{
  "type": "Feature",
  "properties": {
    "iso:country":"US",
    "sg:address":"357 Kermanshah St",
    "sg:city":"Roseburg",
    "sg:classifiers":[
        {
            "category":"Building & Trades",
            "subcategory":"Cleaning & Sanitation",
            "type":"Services"
        }
    ],
    "sg:phone":"+1 541 679 8878",
    "sg:postcode":"97470",
    "sg:province":"OR",
    "sg:tags":[
        "maintenance"
    ],
    "wof:name":"Docks Chimney Sweep",
    "wof:placetype":"venue"
},
  "geometry": {"coordinates":[-123.378692,43.141124],"type":"Point"}
}