{
  "type": "Feature",
  "properties": {
    "addr:full":"10000 SE 82nd Ave Portland OR 97266",
    "addr:postcode":"10000;97266",
    "addr:street":"Se 82Nd Ave",
    "iso:country":"US",
    "sg:address":"10000 SE 82nd Ave",
    "sg:city":"Portland",
    "sg:classifiers":[
        {
            "category":"Shopping",
            "subcategory":"Department Store",
            "type":"Retail Goods"
        },
        {
            "category":"Shopping",
            "subcategory":"Mobile Phones",
            "type":"Retail Goods"
        },
        {
            "category":"Food & Beverages",
            "subcategory":"Groceries & Convenience Stores",
            "type":"Retail Goods"
        }
    ],
    "sg:phone":"+1 503 788 4748",
    "sg:postcode":"97266",
    "sg:province":"OR",
    "sg:website":"www.walmart.com",
    "wof:name":"Walmart",
    "wof:placetype":"venue"
},
  "geometry": {"coordinates":[-122.576679,45.450456],"type":"Point"}
}