{
  "type": "Feature",
  "properties": {
    "addr:full":"431 SW Madison St Portland OR 97204",
    "addr:housenumber":"431",
    "addr:postcode":"97204",
    "addr:street":"Sw Madison St",
    "iso:country":"US",
    "sg:address":"431 SW Madison St",
    "sg:city":"Portland",
    "sg:classifiers":[
        {
            "category":"Food & Beverages",
            "subcategory":"Bakery",
            "type":"Retail Goods"
        }
    ],
    "sg:phone":"+1 503 227 0707",
    "sg:postcode":"97204",
    "sg:province":"OR",
    "sg:tags":[
        "cookie",
        "cracker"
    ],
    "wof:name":"Cookie Cabana",
    "wof:placetype":"venue"
},
  "geometry": {"coordinates":[-122.679147,45.515455],"type":"Point"}
}