{
  "type": "Feature",
  "properties": {
    "iso:country":"US",
    "sg:address":"37065 US Hwy 26",
    "sg:city":"Sandy",
    "sg:classifiers":[
        {
            "category":"Shopping",
            "subcategory":"Bicycles & Sporting Goods",
            "type":"Retail Goods"
        }
    ],
    "sg:phone":"+1 503 826 8760",
    "sg:postcode":"97055",
    "sg:province":"OR",
    "sg:tags":[
        "snowboard"
    ],
    "wof:name":"Northern Alliance",
    "wof:placetype":"venue"
},
  "geometry": {"coordinates":[-122.281568,45.401685],"type":"Point"}
}