{
  "type": "Feature",
  "properties": {
    "iso:country":"US",
    "sg:address":"2370 NW Saint Helens Rd",
    "sg:city":"Portland",
    "sg:classifiers":[
        {
            "category":"Manufacturing",
            "subcategory":"Tools & Machinery",
            "type":"Manufacturing & Wholesale Goods"
        },
        {
            "category":"Wholesale",
            "subcategory":"Machinery & Supplies",
            "type":"Manufacturing & Wholesale Goods"
        },
        {
            "category":"Home & Garden",
            "subcategory":"Building Materials",
            "type":"Retail Goods"
        }
    ],
    "sg:phone":"+1 503 295 6946",
    "sg:postcode":"97210",
    "sg:province":"OR",
    "sg:tags":[
        "equipment",
        "fasteners-industrial",
        "industrial"
    ],
    "sg:website":"http://www.fastenal.com",
    "wof:name":"Fastenal Company",
    "wof:placetype":"venue"
},
  "geometry": {"coordinates":[-122.715851,45.538611],"type":"Point"}
}