{
  "type": "Feature",
  "properties": {
    "iso:country":"US",
    "sg:address":"6750 SW Whisper Ct",
    "sg:city":"Beaverton",
    "sg:classifiers":[
        {
            "category":"Building & Trades",
            "subcategory":"Construction",
            "type":"Services"
        }
    ],
    "sg:phone":"+1 503 643 2497",
    "sg:postcode":"97008",
    "sg:province":"OR",
    "sg:tags":[
        "door",
        "window",
        "installation"
    ],
    "wof:name":"Illumintaion W & D",
    "wof:placetype":"venue"
},
  "geometry": {"coordinates":[-122.811543,45.47167],"type":"Point"}
}