{
  "type": "Feature",
  "properties": {
    "iso:country":"US",
    "sg:address":"1508 Coburg Rd",
    "sg:city":"Eugene",
    "sg:classifiers":[
        {
            "category":"Manufacturing",
            "subcategory":"Food",
            "type":"Manufacturing & Wholesale Goods"
        }
    ],
    "sg:phone":"+1 541 686 5783",
    "sg:postcode":"97401",
    "sg:province":"OR",
    "sg:tags":[
        "product",
        "confectionery",
        "candy",
        "mfg"
    ],
    "wof:name":"Larsen's Fine Candies",
    "wof:placetype":"venue"
},
  "geometry": {"coordinates":[-123.068541,44.078752],"type":"Point"}
}