{
  "type": "Feature",
  "properties": {
    "addr:full":"221 W Bishop Way Brownsville OR 97327",
    "addr:housenumber":"221",
    "addr:postcode":"97327",
    "addr:street":"W Bishop Way",
    "iso:country":"US",
    "sg:address":"221 W Bishop Way",
    "sg:city":"Brownsville",
    "sg:classifiers":[
        {
            "category":"Shopping",
            "subcategory":"Music",
            "type":"Retail Goods"
        }
    ],
    "sg:phone":"+1 541 466 5061",
    "sg:postcode":"97327",
    "sg:province":"OR",
    "sg:tags":[
        "video",
        "disc",
        "tape",
        "cassette"
    ],
    "wof:name":"Central Linn Video",
    "wof:placetype":"venue"
},
  "geometry": {"coordinates":[-122.989052,44.387809],"type":"Point"}
}