{
  "type": "Feature",
  "properties": {
    "iso:country":"US",
    "sg:address":"410 S Beavercreek Rd",
    "sg:city":"Oregon City",
    "sg:classifiers":[
        {
            "category":"Real Estate",
            "subcategory":"Real Estate Operator",
            "type":"Services"
        }
    ],
    "sg:phone":"+1 503 657 2931",
    "sg:postcode":"97045",
    "sg:province":"OR",
    "wof:name":"Red Soils Business Park",
    "wof:placetype":"venue"
},
  "geometry": {"coordinates":[-122.591883,45.333643],"type":"Point"}
}