{
  "type": "Feature",
  "properties": {
    "iso:country":"US",
    "sg:address":"3155 River Rd S Ste 100",
    "sg:city":"Salem",
    "sg:classifiers":[
        {
            "category":"Professional",
            "subcategory":"Management & Consulting",
            "type":"Services"
        }
    ],
    "sg:phone":"+1 503 362 5235",
    "sg:postcode":"97302",
    "sg:province":"OR",
    "sg:tags":[
        "consultant"
    ],
    "wof:name":"River Building",
    "wof:placetype":"venue"
},
  "geometry": {"coordinates":[-123.071009,44.910332],"type":"Point"}
}