{
  "type": "Feature",
  "properties": {
    "addr:full":"5600 State Hwy 211 Hubbard OR 97032",
    "addr:housenumber":"5600",
    "addr:postcode":"97032",
    "addr:street":"State Hwy 211",
    "iso:country":"US",
    "sg:address":"5600 State Hwy 211",
    "sg:city":"Hubbard",
    "sg:classifiers":[
        {
            "category":"Wholesale",
            "subcategory":"Plants",
            "type":"Manufacturing & Wholesale Goods"
        }
    ],
    "sg:phone":"+1 503 634 2460",
    "sg:postcode":"97032",
    "sg:province":"OR",
    "sg:tags":[
        "nursery",
        "tree"
    ],
    "wof:name":"B-West Hills Nursery",
    "wof:placetype":"venue"
},
  "geometry": {"coordinates":[-122.753665,45.144238],"type":"Point"}
}