{
  "type": "Feature",
  "properties": {
    "iso:country":"US",
    "sg:address":"6769 SW Mill Rd",
    "sg:city":"Gaston",
    "sg:classifiers":[
        {
            "category":"Retail",
            "subcategory":"Laundry & Dry Cleaning",
            "type":"Services"
        }
    ],
    "sg:phone":"+1 503 359 3554",
    "sg:postcode":"97119",
    "sg:province":"OR",
    "sg:tags":[
        "cleaners",
        "rug",
        "carpet"
    ],
    "wof:name":"On The Spot Carpet",
    "wof:placetype":"venue"
},
  "geometry": {"coordinates":[-123.184697,45.471473],"type":"Point"}
}