{
  "type": "Feature",
  "properties": {
    "iso:country":"US",
    "sg:address":"2728 Edison Ave",
    "sg:city":"Klamath Falls",
    "sg:classifiers":[
        {
            "category":"Freight",
            "type":"Transportation"
        }
    ],
    "sg:phone":"+1 541 273 2031",
    "sg:postcode":"97603",
    "sg:province":"OR",
    "sg:tags":[
        "commercial",
        "storage"
    ],
    "wof:name":"Chase Rentals Storage",
    "wof:placetype":"venue"
},
  "geometry": {"coordinates":[-121.756789,42.193755],"type":"Point"}
}