{
  "type": "Feature",
  "properties": {
    "iso:country":"US",
    "sg:address":"2019 State St",
    "sg:city":"Salem",
    "sg:classifiers":[
        {
            "category":"Health Services",
            "subcategory":"Doctor",
            "type":"Services"
        }
    ],
    "sg:phone":"+1 503 363 9637",
    "sg:postcode":"97301",
    "sg:province":"OR",
    "sg:tags":[
        "dentist"
    ],
    "wof:name":"Steven D Cowgill DDS",
    "wof:placetype":"venue"
},
  "geometry": {"coordinates":[-123.016766,44.934441],"type":"Point"}
}