{
  "type": "Feature",
  "properties": {
    "iso:country":"US",
    "sg:address":"5916 NE Going St",
    "sg:city":"Portland",
    "sg:classifiers":[
        {
            "category":"Organizations",
            "subcategory":"Non-profit Organization",
            "type":"Services"
        }
    ],
    "sg:phone":"+1 503 287 7469",
    "sg:postcode":"97218",
    "sg:province":"OR",
    "sg:tags":[
        "service/non-profit",
        "community"
    ],
    "wof:name":"Portland Toy & Joy",
    "wof:placetype":"venue"
},
  "geometry": {"coordinates":[-122.60184599999999,45.556541],"type":"Point"}
}