{
  "type": "Feature",
  "properties": {
    "iso:country":"US",
    "sg:address":"304 N Main St",
    "sg:city":"Riddle",
    "sg:classifiers":[
        {
            "category":"Restaurant",
            "type":"Food & Drink"
        }
    ],
    "sg:phone":"+1 541 863 6111",
    "sg:postcode":"97469",
    "sg:province":"OR",
    "wof:name":"Bill & Rubys Rock-N-Ore House",
    "wof:placetype":"venue"
},
  "geometry": {"coordinates":[-123.36594599999999,42.950599],"type":"Point"}
}