{
  "type": "Feature",
  "properties": {
    "iso:country":"US",
    "sg:address":"18200 SW Pacific Hwy",
    "sg:city":"Tualatin",
    "sg:classifiers":[
        {
            "category":"Manufacturing",
            "subcategory":"Tools & Machinery",
            "type":"Manufacturing & Wholesale Goods"
        },
        {
            "category":"Industrial Area",
            "type":"Public Place"
        }
    ],
    "sg:phone":"+1 503 691 1199",
    "sg:postcode":"97062",
    "sg:province":"OR",
    "sg:tags":[
        "repair",
        "equipment-repairing",
        "machinery-rebuild"
    ],
    "wof:name":"G. H. Mcculloch, Inc.",
    "wof:placetype":"venue"
},
  "geometry": {"coordinates":[-122.80716700000001,45.388139],"type":"Point"}
}