{
  "type": "Feature",
  "properties": {
    "iso:country":"US",
    "sg:address":"732 SE J St",
    "sg:city":"Grants Pass",
    "sg:classifiers":[
        {
            "category":"Retail",
            "subcategory":"Auto Repair",
            "type":"Services"
        }
    ],
    "sg:phone":"+1 541 479 4523",
    "sg:postcode":"97526",
    "sg:province":"OR",
    "sg:tags":[
        "general"
    ],
    "wof:name":"Combined Diesel Service",
    "wof:placetype":"venue"
},
  "geometry": {"coordinates":[-123.31739899999999,42.434656],"type":"Point"}
}