{
  "type": "Feature",
  "properties": {
    "addr:full":"1561 MOUNT HOOD AVE WOODBURN OR 97071",
    "addr:housenumber":"1561",
    "addr:postcode":"97071",
    "addr:street":"Mount Hood Ave",
    "iso:country":"US",
    "sg:address":"1561 MOUNT HOOD AVE",
    "sg:city":"WOODBURN",
    "sg:classifiers":[
        {
            "category":"Home & Garden",
            "subcategory":"Household Appliances",
            "type":"Retail Goods"
        },
        {
            "category":"Communications",
            "subcategory":"Radio Station",
            "type":"Services"
        },
        {
            "category":"Shopping",
            "subcategory":"Computers & Home Electronics",
            "type":"Retail Goods"
        },
        {
            "category":"Home & Garden",
            "subcategory":"Furniture",
            "type":"Retail Goods"
        }
    ],
    "sg:phone":"+1 503 981 7342",
    "sg:postcode":"97071",
    "sg:province":"OR",
    "sg:tags":[
        "renting",
        "television",
        "leasing",
        "radio-renting",
        "equipment",
        "rental"
    ],
    "sg:website":"http://www.rentacenter.com/",
    "wof:name":"Rent-A-Center",
    "wof:placetype":"venue"
},
  "geometry": {"coordinates":[-122.836405,45.151388],"type":"Point"}
}