{
  "type": "Feature",
  "properties": {
    "iso:country":"US",
    "sg:address":"4410 NE Tillamook St",
    "sg:city":"Portland",
    "sg:classifiers":[
        {
            "category":"Shopping",
            "subcategory":"Used Merchandise",
            "type":"Retail Goods"
        }
    ],
    "sg:phone":"+1 503 284 2908",
    "sg:postcode":"97213",
    "sg:province":"OR",
    "sg:tags":[
        "wear"
    ],
    "wof:name":"Gingerbread Express",
    "wof:placetype":"venue"
},
  "geometry": {"coordinates":[-122.61700399999999,45.5377],"type":"Point"}
}