{
  "type": "Feature",
  "properties": {
    "iso:country":"US",
    "sg:address":"15114 SE McLoughlin Boulevard",
    "sg:city":"Portland",
    "sg:classifiers":[
        {
            "category":"Shopping",
            "subcategory":"Jewelry",
            "type":"Retail Goods"
        },
        {
            "category":"Shopping",
            "subcategory":"Pawn Shop",
            "type":"Retail Goods"
        }
    ],
    "sg:phone":"+1 503 785 1168",
    "sg:postcode":"97267",
    "sg:province":"OR",
    "sg:website":"www.atgjewelry.com",
    "wof:name":"All That Glitters Jewelry & Loans",
    "wof:placetype":"venue"
},
  "geometry": {"coordinates":[-122.630454,45.413905],"type":"Point"}
}