{
  "type": "Feature",
  "properties": {
    "iso:country":"US",
    "sg:address":"811 SW Naito Parkway",
    "sg:city":"Portland",
    "sg:classifiers":[
        {
            "category":"Professional",
            "subcategory":"Lawyer & Legal Services",
            "type":"Services"
        }
    ],
    "sg:phone":"+1 503 224 7392",
    "sg:postcode":"97204",
    "sg:province":"OR",
    "wof:name":"Reynolds Stephen D Atty At Law",
    "wof:placetype":"venue"
},
  "geometry": {"coordinates":[-122.67314500000001,45.516676],"type":"Point"}
}