{
  "type": "Feature",
  "properties": {
    "iso:country":"US",
    "sg:address":"2937 W Jay Ave",
    "sg:city":"Roseburg",
    "sg:classifiers":[
        {
            "category":"Social Services",
            "type":"Services"
        },
        {
            "category":"Manufacturing",
            "subcategory":"Buildings",
            "type":"Manufacturing & Wholesale Goods"
        },
        {
            "category":"Building & Trades",
            "subcategory":"Construction",
            "type":"Services"
        }
    ],
    "sg:phone":"+1 541 673 2179",
    "sg:postcode":"97471",
    "sg:province":"OR",
    "sg:tags":[
        "home",
        "builder",
        "contractor"
    ],
    "wof:name":"Umpqua Homes For The Handicapped, Inc",
    "wof:placetype":"venue"
},
  "geometry": {"coordinates":[-123.38595100000001,43.21302],"type":"Point"}
}