{
  "type": "Feature",
  "properties": {
    "addr:full":"345 S Central Valley Dr Central Point OR 97502",
    "addr:housenumber":"345",
    "addr:postcode":"97502",
    "addr:street":"S Central Valley Dr",
    "iso:country":"US",
    "sg:address":"345 S Central Valley Dr",
    "sg:city":"Central Point",
    "sg:classifiers":[
        {
            "category":"Real Estate",
            "subcategory":"Real Estate Operator",
            "type":"Services"
        }
    ],
    "sg:phone":"+1 541 664 8659",
    "sg:postcode":"97502",
    "sg:province":"OR",
    "sg:tags":[
        "apartment"
    ],
    "wof:name":"West Pine Terrace Apartments",
    "wof:placetype":"venue"
},
  "geometry": {"coordinates":[-122.92255400000001,42.367918],"type":"Point"}
}