{
  "type": "Feature",
  "properties": {
    "addr:full":"45 E Sherman St Lebanon OR 97355",
    "addr:housenumber":"45",
    "addr:postcode":"97355",
    "addr:street":"E Sherman St",
    "iso:country":"US",
    "sg:address":"45 E Sherman St",
    "sg:city":"Lebanon",
    "sg:classifiers":[
        {
            "category":"Manufacturing",
            "subcategory":"Printing",
            "type":"Manufacturing & Wholesale Goods"
        }
    ],
    "sg:phone":"+1 541 258 5558",
    "sg:postcode":"97355",
    "sg:province":"OR",
    "sg:tags":[
        "screen",
        "commercial"
    ],
    "wof:name":"Think It Screen Printing",
    "wof:placetype":"venue"
},
  "geometry": {"coordinates":[-122.906494,44.539219],"type":"Point"}
}