{
  "type": "Feature",
  "properties": {
    "iso:country":"US",
    "sg:address":"512 Crater Lake Ave",
    "sg:city":"Medford",
    "sg:classifiers":[
        {
            "category":"Wholesale",
            "subcategory":"Construction Materials",
            "type":"Manufacturing & Wholesale Goods"
        }
    ],
    "sg:phone":"+1 541 773 3661",
    "sg:postcode":"97504",
    "sg:province":"OR",
    "sg:tags":[
        "lumber"
    ],
    "wof:name":"Forestglen Lumber Co",
    "wof:placetype":"venue"
},
  "geometry": {"coordinates":[-122.862223,42.334523],"type":"Point"}
}