{
  "type": "Feature",
  "properties": {
    "addr:full":"4928 Haskins Rd Bonanza OR 97623",
    "addr:housenumber":"4928",
    "addr:postcode":"97623",
    "addr:street":"Haskins Rd",
    "iso:country":"US",
    "sg:address":"4928 Haskins Rd",
    "sg:city":"Bonanza",
    "sg:classifiers":[
        {
            "category":"Real Estate",
            "subcategory":"Real Estate Operator",
            "type":"Services"
        }
    ],
    "sg:phone":"+1 541 545 6659",
    "sg:postcode":"97623",
    "sg:province":"OR",
    "sg:tags":[
        "property",
        "lessor"
    ],
    "wof:name":"G P Wu & Son I N C",
    "wof:placetype":"venue"
},
  "geometry": {"coordinates":[-121.462204,42.267674],"type":"Point"}
}