{
  "type": "Feature",
  "properties": {
    "iso:country":"US",
    "sg:address":"47772 McKenzie Hwy",
    "sg:city":"Vida",
    "sg:classifiers":[
        {
            "category":"Professional",
            "type":"Services"
        }
    ],
    "sg:phone":"+1 541 896 3321",
    "sg:postcode":"97488",
    "sg:province":"OR",
    "wof:name":"Jack Pratt",
    "wof:placetype":"venue"
},
  "geometry": {"coordinates":[-122.489856,44.1329],"type":"Point"}
}