{
  "type": "Feature",
  "properties": {
    "addr:full":"424 W Linden Way Heppner OR 97836",
    "addr:housenumber":"424",
    "addr:postcode":"97836",
    "addr:street":"W Linden Way",
    "iso:country":"US",
    "sg:address":"424 W Linden Way",
    "sg:city":"Heppner",
    "sg:classifiers":[
        {
            "category":"Home & Garden",
            "subcategory":"Building Materials",
            "type":"Retail Goods"
        }
    ],
    "sg:phone":"+1 541 676 9157",
    "sg:postcode":"97836",
    "sg:province":"OR",
    "wof:name":"Petty John's Farm & Builders",
    "wof:placetype":"venue"
},
  "geometry": {"coordinates":[-119.55985099999999,45.363873],"type":"Point"}
}