{
  "type": "Feature",
  "properties": {
    "iso:country":"US",
    "sg:address":"3505 Hulsey Ave SE",
    "sg:city":"Salem",
    "sg:classifiers":[
        {
            "category":"Shopping",
            "subcategory":"Gifts & Souvenirs",
            "type":"Retail Goods"
        }
    ],
    "sg:phone":"+1 503 362 3403",
    "sg:postcode":"97302",
    "sg:province":"OR",
    "sg:tags":[
        "jewelry"
    ],
    "wof:name":"A Rita Original",
    "wof:placetype":"venue"
},
  "geometry": {"coordinates":[-123.036186,44.904342],"type":"Point"}
}