{
  "type": "Feature",
  "properties": {
    "iso:country":"US",
    "sg:address":"14215 SW Teal Blvd",
    "sg:city":"Beaverton",
    "sg:classifiers":[
        {
            "category":"Health Services",
            "subcategory":"Health Practitioner",
            "type":"Services"
        }
    ],
    "sg:phone":"+1 503 524 5579",
    "sg:postcode":"97008",
    "sg:province":"OR",
    "wof:name":"Pym Lynda Dhs Naturopathic Con",
    "wof:placetype":"venue"
},
  "geometry": {"coordinates":[-122.82277999999999,45.441316],"type":"Point"}
}