{
  "type": "Feature",
  "properties": {
    "addr:full":"5094 Auburn Rd NE Salem OR 97301",
    "addr:housenumber":"5094",
    "addr:postcode":"97301",
    "addr:street":"Auburn Rd Ne",
    "iso:country":"US",
    "sg:address":"5094 Auburn Rd NE",
    "sg:city":"Salem",
    "sg:classifiers":[
        {
            "category":"Building & Trades",
            "subcategory":"Construction",
            "type":"Services"
        }
    ],
    "sg:phone":"+1 503 371 5819",
    "sg:postcode":"97301",
    "sg:province":"OR",
    "sg:tags":[
        "floor",
        "laying",
        "contractor"
    ],
    "wof:name":"Lowry s Instulation Service",
    "wof:placetype":"venue"
},
  "geometry": {"coordinates":[-122.95650500000001,44.936255],"type":"Point"}
}