{
  "type": "Feature",
  "properties": {
    "addr:full":"4506 SE Belmont St # 110 Portland OR 97215",
    "addr:housenumber":"4506",
    "addr:postcode":"97215",
    "addr:street":"Se Belmont St # 110",
    "iso:country":"US",
    "sg:address":"4506 SE Belmont St # 110",
    "sg:city":"Portland",
    "sg:classifiers":[
        {
            "category":"Wholesale",
            "subcategory":"Medical Equipment & Supplies",
            "type":"Manufacturing & Wholesale Goods"
        }
    ],
    "sg:phone":"+1 503 239 1918",
    "sg:postcode":"97215",
    "sg:province":"OR",
    "sg:tags":[
        "device",
        "surgical",
        "appliance",
        "prosthetic"
    ],
    "wof:name":"Moor, Michael Prosthetics Orthotics",
    "wof:placetype":"venue"
},
  "geometry": {"coordinates":[-122.616091,45.516548],"type":"Point"}
}