{
  "type": "Feature",
  "properties": {
    "addr:full":"3026 SE 85th Ave Portland OR 97266",
    "addr:housenumber":"3026",
    "addr:postcode":"97266",
    "addr:street":"Se 85Th Ave",
    "iso:country":"US",
    "sg:address":"3026 SE 85th Ave",
    "sg:city":"Portland",
    "sg:classifiers":[
        {
            "category":"Wholesale",
            "subcategory":"Machinery & Supplies",
            "type":"Manufacturing & Wholesale Goods"
        }
    ],
    "sg:phone":"+1 503 788 9349",
    "sg:postcode":"97266",
    "sg:province":"OR",
    "sg:tags":[
        "pump"
    ],
    "wof:name":"RMS Pump",
    "wof:placetype":"venue"
},
  "geometry": {"coordinates":[-122.574927,45.499311],"type":"Point"}
}