{
  "type": "Feature",
  "properties": {
    "addr:full":"981 SE Dix Ct Troutdale OR 97060",
    "addr:housenumber":"981",
    "addr:postcode":"97060",
    "addr:street":"Se Dix Ct",
    "iso:country":"US",
    "sg:address":"981 SE Dix Ct",
    "sg:city":"Troutdale",
    "sg:classifiers":[
        {
            "category":"Building & Trades",
            "subcategory":"Construction",
            "type":"Services"
        }
    ],
    "sg:phone":"+1 503 666 7982",
    "sg:postcode":"97060",
    "sg:province":"OR",
    "sg:tags":[
        "carpentry",
        "contractor"
    ],
    "wof:name":"Craig Secanti Construction",
    "wof:placetype":"venue"
},
  "geometry": {"coordinates":[-122.383698,45.534845],"type":"Point"}
}