{
  "type": "Feature",
  "properties": {
    "addr:full":"2209 NW Mill Pond Rd Portland OR 97229",
    "addr:housenumber":"2209",
    "addr:postcode":"97229",
    "addr:street":"Nw Mill Pond Rd",
    "iso:country":"US",
    "sg:address":"2209 NW Mill Pond Rd",
    "sg:city":"Portland",
    "sg:classifiers":[
        {
            "category":"Home & Garden",
            "subcategory":"Home Furnishings",
            "type":"Retail Goods"
        },
        {
            "category":"Retail",
            "subcategory":"Repair Shop",
            "type":"Services"
        },
        {
            "category":"Shopping",
            "subcategory":"Jewelry",
            "type":"Retail Goods"
        }
    ],
    "sg:phone":"+1 503 292 2884",
    "sg:postcode":"97229",
    "sg:province":"OR",
    "sg:tags":[
        "watch",
        "clock"
    ],
    "wof:name":"M Radi",
    "wof:placetype":"venue"
},
  "geometry": {"coordinates":[-122.78357,45.537968],"type":"Point"}
}