{
  "type": "Feature",
  "properties": {
    "addr:full":"50 SW 2nd Ave Portland OR 97204",
    "addr:housenumber":"50",
    "addr:postcode":"97204",
    "addr:street":"Sw 2Nd Ave",
    "iso:country":"US",
    "sg:address":"50 SW 2nd Ave",
    "sg:city":"Portland",
    "sg:classifiers":[
        {
            "category":"Real Estate",
            "subcategory":"Architect",
            "type":"Services"
        }
    ],
    "sg:phone":"+1 503 294 0210",
    "sg:postcode":"97204",
    "sg:province":"OR",
    "sg:tags":[
        "architectural"
    ],
    "wof:name":"Nelson Dn/Sscate/Architects PC",
    "wof:placetype":"venue"
},
  "geometry": {"coordinates":[-122.672388,45.522],"type":"Point"}
}