{
  "type": "Feature",
  "properties": {
    "addr:full":"732 SW 6th St Redmond OR 97756",
    "addr:housenumber":"732",
    "addr:postcode":"97756",
    "addr:street":"Sw 6Th St",
    "iso:country":"US",
    "sg:address":"732 SW 6th St",
    "sg:city":"Redmond",
    "sg:classifiers":[
        {
            "category":"Wholesale",
            "subcategory":"Furniture",
            "type":"Manufacturing & Wholesale Goods"
        }
    ],
    "sg:phone":"+1 541 923 4155",
    "sg:postcode":"97756",
    "sg:province":"OR",
    "wof:name":"Great American",
    "wof:placetype":"venue"
},
  "geometry": {"coordinates":[-121.174184,44.270266],"type":"Point"}
}