{
  "type": "Feature",
  "properties": {
    "iso:country":"US",
    "sg:address":"11600 NW Lambert St",
    "sg:city":"Portland",
    "sg:classifiers":[
        {
            "category":"Professional",
            "subcategory":"Management & Consulting",
            "type":"Services"
        }
    ],
    "sg:phone":"+1 503 285 4663",
    "sg:postcode":"97229",
    "sg:province":"OR",
    "wof:name":"Aaro Health Connection",
    "wof:placetype":"venue"
},
  "geometry": {"coordinates":[-122.796268,45.578511],"type":"Point"}
}