{
  "type": "Feature",
  "properties": {
    "iso:country":"US",
    "sg:address":"121 SW Salmon St",
    "sg:city":"Portland",
    "sg:classifiers":[
        {
            "category":"Government",
            "subcategory":"Office",
            "type":"Public Place"
        }
    ],
    "sg:phone":"+1 503 274 7482",
    "sg:postcode":"97204",
    "sg:province":"OR",
    "sg:tags":[
        "educational",
        "program",
        "administrative"
    ],
    "wof:name":"Small Bus Intl Trade Program",
    "wof:placetype":"venue"
},
  "geometry": {"coordinates":[-122.67547,45.516009],"type":"Point"}
}