{
  "type": "Feature",
  "properties": {
    "addr:full":"1200 NW Naito Parkway Portland OR 97209",
    "addr:housenumber":"1200",
    "addr:postcode":"97209",
    "addr:street":"Nw Naito Parkway",
    "iso:country":"US",
    "sg:address":"1200 NW Naito Parkway",
    "sg:city":"Portland",
    "sg:classifiers":[
        {
            "category":"Landmark",
            "subcategory":"Tourist Information",
            "type":"Public Place"
        }
    ],
    "sg:phone":"+1 503 226 8181",
    "sg:postcode":"97209",
    "sg:province":"OR",
    "sg:tags":[
        "tour"
    ],
    "wof:name":"Oregon Rail Holdings",
    "wof:placetype":"venue"
},
  "geometry": {"coordinates":[-122.678331,45.532075],"type":"Point"}
}