{
  "type": "Feature",
  "properties": {
    "iso:country":"US",
    "sg:address":"830 S Canyon Blvd",
    "sg:city":"John Day",
    "sg:classifiers":[
        {
            "category":"Restaurant",
            "type":"Food & Drink"
        }
    ],
    "sg:phone":"+1 541 575 2426",
    "sg:postcode":"97845",
    "sg:province":"OR",
    "sg:tags":[
        "eating"
    ],
    "wof:name":"Snaffle Bit Dinner House",
    "wof:placetype":"venue"
},
  "geometry": {"coordinates":[-118.950788,44.408595],"type":"Point"}
}