{
  "type": "Feature",
  "properties": {
    "addr:full":"19450 NE Deach Rd Yamhill OR 97148",
    "addr:housenumber":"19450",
    "addr:postcode":"97148",
    "addr:street":"Ne Deach Rd",
    "iso:country":"US",
    "sg:address":"19450 NE Deach Rd",
    "sg:city":"Yamhill",
    "sg:classifiers":[
        {
            "category":"Professional",
            "subcategory":"Business Services",
            "type":"Services"
        }
    ],
    "sg:phone":"+1 503 887 4101",
    "sg:postcode":"97148",
    "sg:province":"OR",
    "sg:tags":[
        "consultant",
        "coach"
    ],
    "wof:name":"Brian Culp Consulting",
    "wof:placetype":"venue"
},
  "geometry": {"coordinates":[-123.109863,45.356991],"type":"Point"}
}