{
  "type": "Feature",
  "properties": {
    "iso:country":"US",
    "sg:address":"2612 E Barnett Rd",
    "sg:city":"Medford",
    "sg:classifiers":[
        {
            "category":"Professional",
            "subcategory":"Computer Services",
            "type":"Services"
        }
    ],
    "sg:phone":"+1 541 770 8007",
    "sg:postcode":"97504",
    "sg:province":"OR",
    "sg:tags":[
        "consulting"
    ],
    "wof:name":"C & H Computing",
    "wof:placetype":"venue"
},
  "geometry": {"coordinates":[-122.832902,42.316419],"type":"Point"}
}