{
  "type": "Feature",
  "properties": {
    "addr:full":"113 S Main St Milton Freewater OR 97862",
    "addr:housenumber":"113",
    "addr:postcode":"97862",
    "addr:street":"S Main St;Freewater",
    "iso:country":"US",
    "sg:address":"113 S Main St",
    "sg:city":"Milton Freewater",
    "sg:classifiers":[
        {
            "category":"Health Services",
            "subcategory":"Health Practitioner",
            "type":"Services"
        }
    ],
    "sg:phone":"+1 541 938 5553",
    "sg:postcode":"97862",
    "sg:province":"OR",
    "sg:tags":[
        "therapist",
        "physical"
    ],
    "wof:name":"Blue Mountain Physical Therapy",
    "wof:placetype":"venue"
},
  "geometry": {"coordinates":[-118.39077399999999,45.935686],"type":"Point"}
}