{
  "type": "Feature",
  "properties": {
    "addr:full":"23188 SW Johnson St Hillsboro OR 97123",
    "addr:housenumber":"23188",
    "addr:postcode":"97123",
    "addr:street":"Sw Johnson St",
    "iso:country":"US",
    "sg:address":"23188 SW Johnson St",
    "sg:city":"Hillsboro",
    "sg:classifiers":[
        {
            "category":"Professional",
            "type":"Services"
        }
    ],
    "sg:phone":"+1 503 356 9193",
    "sg:postcode":"97123",
    "sg:province":"OR",
    "wof:name":"Blue Horizons",
    "wof:placetype":"venue"
},
  "geometry": {"coordinates":[-122.91408,45.502376],"type":"Point"}
}