{
  "type": "Feature",
  "properties": {
    "iso:country":"US",
    "sg:address":"2160 Breyman St NE",
    "sg:city":"Salem",
    "sg:classifiers":[
        {
            "category":"Real Estate",
            "subcategory":"Architect",
            "type":"Services"
        }
    ],
    "sg:phone":"+1 503 581 4963",
    "sg:postcode":"97301",
    "sg:province":"OR",
    "wof:name":"Jim K Whitney",
    "wof:placetype":"venue"
},
  "geometry": {"coordinates":[-123.012893,44.93778],"type":"Point"}
}