{
  "type": "Feature",
  "properties": {
    "iso:country":"US",
    "sg:address":"5005 NW Highland Dr",
    "sg:city":"Corvallis",
    "sg:classifiers":[
        {
            "category":"Organizations",
            "subcategory":"Religious Organization",
            "type":"Services"
        }
    ],
    "sg:phone":"+1 541 758 9800",
    "sg:postcode":"97330",
    "sg:province":"OR",
    "wof:name":"Crescent Vly Evang Free Church",
    "wof:placetype":"venue"
},
  "geometry": {"coordinates":[-123.261199,44.621552],"type":"Point"}
}