{
  "type": "Feature",
  "properties": {
    "iso:country":"US",
    "sg:address":"558 SE 9th St",
    "sg:city":"Bend",
    "sg:classifiers":[
        {
            "category":"Retail",
            "subcategory":"Auto Repair",
            "type":"Services"
        }
    ],
    "sg:phone":"+1 541 383 5101",
    "sg:postcode":"97702",
    "sg:province":"OR",
    "sg:tags":[
        "wheel",
        "automotive",
        "axle",
        "alignment"
    ],
    "wof:name":"Alignment Techniques",
    "wof:placetype":"venue"
},
  "geometry": {"coordinates":[-121.292723,44.045969],"type":"Point"}
}