{
  "type": "Feature",
  "properties": {
    "iso:country":"US",
    "sg:address":"2400 SW Court Pl",
    "sg:city":"Pendleton",
    "sg:classifiers":[
        {
            "category":"Travel",
            "subcategory":"Hotels & Motels",
            "type":"Entertainment"
        }
    ],
    "sg:phone":"+1 541 276 6000",
    "sg:postcode":"97801",
    "sg:province":"OR",
    "sg:website":"www.oxfordsuites.com",
    "wof:name":"Oxford Suites",
    "wof:placetype":"venue"
},
  "geometry": {"coordinates":[-118.808784,45.666181],"type":"Point"}
}