{
  "type": "Feature",
  "properties": {
    "iso:country":"US",
    "sg:address":"2544 Howard Ave",
    "sg:city":"Medford",
    "sg:classifiers":[
        {
            "category":"Retail",
            "subcategory":"Repair Shop",
            "type":"Services"
        }
    ],
    "sg:phone":"+1 541 772 1889",
    "sg:postcode":"97501",
    "sg:province":"OR",
    "sg:tags":[
        "armature",
        "rewinding"
    ],
    "wof:name":"Dr JS Scooter Service",
    "wof:placetype":"venue"
},
  "geometry": {"coordinates":[-122.893515,42.3548],"type":"Point"}
}