{
  "type": "Feature",
  "properties": {
    "addr:full":"1371 3rd St Umatilla OR 97882",
    "addr:housenumber":"1371",
    "addr:postcode":"97882",
    "addr:street":"3Rd St",
    "iso:country":"US",
    "sg:address":"1371 3rd St",
    "sg:city":"Umatilla",
    "sg:classifiers":[
        {
            "category":"Government",
            "subcategory":"Office",
            "type":"Public Place"
        }
    ],
    "sg:phone":"+1 541 922 5574",
    "sg:postcode":"97882",
    "sg:province":"OR",
    "sg:tags":[
        "executive"
    ],
    "wof:name":"Head Start of Umatilla Morrow",
    "wof:placetype":"venue"
},
  "geometry": {"coordinates":[-119.33712,45.920978],"type":"Point"}
}