{
  "type": "Feature",
  "properties": {
    "addr:full":"200 E Hancock St Newberg OR 97132",
    "addr:housenumber":"200",
    "addr:postcode":"97132",
    "addr:street":"E Hancock St",
    "iso:country":"US",
    "sg:address":"200 E Hancock St",
    "sg:city":"Newberg",
    "sg:classifiers":[
        {
            "category":"Personal",
            "type":"Services"
        }
    ],
    "sg:phone":"+1 503 538 1114",
    "sg:postcode":"97132",
    "sg:province":"OR",
    "sg:tags":[
        "therapist",
        "massage"
    ],
    "wof:name":"Candi Johnson",
    "wof:placetype":"venue"
},
  "geometry": {"coordinates":[-122.97812399999999,45.301168],"type":"Point"}
}