{
  "type": "Feature",
  "properties": {
    "addr:full":"874 Creekside Dr SE Salem OR 97306",
    "addr:housenumber":"874",
    "addr:postcode":"97306",
    "addr:street":"Creekside Dr Se",
    "iso:country":"US",
    "sg:address":"874 Creekside Dr SE",
    "sg:city":"Salem",
    "sg:classifiers":[
        {
            "category":"Building & Trades",
            "subcategory":"Construction",
            "type":"Services"
        }
    ],
    "sg:phone":"+1 503 362 5945",
    "sg:postcode":"97306",
    "sg:province":"OR",
    "sg:tags":[
        "contractor"
    ],
    "wof:name":"Bresee Homes Inc",
    "wof:placetype":"venue"
},
  "geometry": {"coordinates":[-123.037262,44.866335],"type":"Point"}
}