{
  "type": "Feature",
  "properties": {
    "iso:country":"US",
    "sg:address":"4680 Chamberlain Dr",
    "sg:city":"Hood River",
    "sg:classifiers":[
        {
            "category":"Farming",
            "subcategory":"Orchard",
            "type":"Manufacturing & Wholesale Goods"
        }
    ],
    "sg:phone":"+1 541 354 1470",
    "sg:postcode":"97031",
    "sg:province":"OR",
    "sg:tags":[
        "fruit",
        "tree"
    ],
    "wof:name":"Ronald Gehrig",
    "wof:placetype":"venue"
},
  "geometry": {"coordinates":[-121.57591499999999,45.639783],"type":"Point"}
}