{
  "type": "Feature",
  "properties": {
    "addr:full":"15125 State Hwy 66 Ashland OR 97520",
    "addr:housenumber":"15125",
    "addr:postcode":"97520",
    "addr:street":"State Hwy 66",
    "iso:country":"US",
    "sg:address":"15125 State Hwy 66",
    "sg:city":"Ashland",
    "sg:classifiers":[
        {
            "category":"Organizations",
            "subcategory":"Religious Organization",
            "type":"Services"
        }
    ],
    "sg:phone":"+1 541 482 1258",
    "sg:postcode":"97520",
    "sg:province":"OR",
    "wof:name":"Lincoln Christian Church",
    "wof:placetype":"venue"
},
  "geometry": {"coordinates":[-122.403807,42.108601],"type":"Point"}
}