{
  "type": "Feature",
  "properties": {
    "iso:country":"US",
    "sg:address":"14825 NW Ash St",
    "sg:city":"Portland",
    "sg:classifiers":[
        {
            "category":"Communications",
            "subcategory":"Film & Video Production",
            "type":"Services"
        }
    ],
    "sg:phone":"+1 503 285 8974",
    "sg:postcode":"97231",
    "sg:province":"OR",
    "sg:tags":[
        "picture",
        "companies-film",
        "producer",
        "tv",
        "motion",
        "studio",
        "radio"
    ],
    "sg:website":"http://www.encountervideo.com",
    "wof:name":"Encounter Video, Inc",
    "wof:placetype":"venue"
},
  "geometry": {"coordinates":[-122.83091,45.597291],"type":"Point"}
}