{
  "type": "Feature",
  "properties": {
    "iso:country":"US",
    "sg:address":"424 NE Broadway St",
    "sg:city":"Portland",
    "sg:classifiers":[
        {
            "category":"Shopping",
            "subcategory":"Musical Instruments",
            "type":"Retail Goods"
        }
    ],
    "sg:phone":"+1 503 288 6950",
    "sg:postcode":"97232",
    "sg:province":"OR",
    "sg:website":"www.rhythmtraders.com",
    "wof:name":"Rhythm Traders",
    "wof:placetype":"venue"
},
  "geometry": {"coordinates":[-122.66139200000001,45.535077],"type":"Point"}
}