{
  "type": "Feature",
  "properties": {
    "iso:country":"US",
    "sg:address":"3196 Meadow Ln",
    "sg:city":"Eugene",
    "sg:classifiers":[
        {
            "category":"Building & Trades",
            "subcategory":"Construction",
            "type":"Services"
        }
    ],
    "sg:phone":"+1 541 689 7574",
    "sg:postcode":"97402",
    "sg:province":"OR",
    "sg:tags":[
        "excavating",
        "contractor"
    ],
    "wof:name":"Perrco Storrs Co",
    "wof:placetype":"venue"
},
  "geometry": {"coordinates":[-123.14492300000001,44.063249],"type":"Point"}
}