{
  "type": "Feature",
  "properties": {
    "addr:full":"6740 SW 171st Ave Beaverton OR 97007",
    "addr:housenumber":"6740",
    "addr:postcode":"97007",
    "addr:street":"Sw 171St Ave",
    "iso:country":"US",
    "sg:address":"6740 SW 171st Ave",
    "sg:city":"Beaverton",
    "sg:classifiers":[
        {
            "category":"Shopping",
            "subcategory":"Used Merchandise",
            "type":"Retail Goods"
        }
    ],
    "sg:phone":"+1 503 642 5356",
    "sg:postcode":"97007",
    "sg:province":"OR",
    "wof:name":"Attic Cat Collectibles",
    "wof:placetype":"venue"
},
  "geometry": {"coordinates":[-122.853171,45.470864],"type":"Point"}
}