{
  "type": "Feature",
  "properties": {
    "addr:full":"1662 SW 1st Ct Gresham OR 97080",
    "addr:housenumber":"1662",
    "addr:postcode":"97080",
    "addr:street":"Sw 1St Ct",
    "iso:country":"US",
    "sg:address":"1662 SW 1st Ct",
    "sg:city":"Gresham",
    "sg:classifiers":[
        {
            "category":"Professional",
            "subcategory":"Management & Consulting",
            "type":"Services"
        }
    ],
    "sg:phone":"+1 503 492 9549",
    "sg:postcode":"97080",
    "sg:province":"OR",
    "sg:tags":[
        "consultant"
    ],
    "sg:website":"http://www.corumgroup.com",
    "wof:name":"The Corum Group Ltd",
    "wof:placetype":"venue"
},
  "geometry": {"coordinates":[-122.448835,45.496315],"type":"Point"}
}