{
  "type": "Feature",
  "properties": {
    "iso:country":"US",
    "sg:address":"1915 SW 25th St",
    "sg:city":"Gresham",
    "sg:classifiers":[
        {
            "category":"Building & Trades",
            "subcategory":"Plumbing",
            "type":"Services"
        }
    ],
    "sg:phone":"+1 503 492 5605",
    "sg:postcode":"97080",
    "sg:province":"OR",
    "sg:tags":[
        "heating",
        "contractor"
    ],
    "wof:name":"Performance Mechanical Htg",
    "wof:placetype":"venue"
},
  "geometry": {"coordinates":[-122.453287,45.478545],"type":"Point"}
}