{
  "type": "Feature",
  "properties": {
    "addr:full":"N Bryant St & N Delaware Ave Portland OR 97217",
    "addr:postcode":"97217",
    "addr:street":"N Bryant St & N Delaware Ave",
    "iso:country":"US",
    "sg:address":"N Bryant St & N Delaware Ave",
    "sg:city":"Portland",
    "sg:classifiers":[
        {
            "category":"Recreation",
            "subcategory":"Dog Park",
            "type":"Entertainment"
        },
        {
            "category":"Shopping Center",
            "type":"Public Place"
        }
    ],
    "sg:phone":"+1 503 823 2525",
    "sg:postcode":"97217",
    "sg:province":"OR",
    "sg:tags":[
        "soccer"
    ],
    "sg:website":"www.portlandonline.com/parks/fin...",
    "wof:name":"Arbor Lodge Park",
    "wof:placetype":"venue"
},
  "geometry": {"coordinates":[-122.69248,45.57355],"type":"Point"}
}