{
  "type": "Feature",
  "properties": {
    "addr:full":"9366 SE 32nd Ave Portland OR 97222",
    "addr:housenumber":"9366",
    "addr:postcode":"97222",
    "addr:street":"Se 32Nd Ave",
    "iso:country":"US",
    "sg:address":"9366 SE 32nd Ave",
    "sg:city":"Portland",
    "sg:classifiers":[
        {
            "category":"Building & Trades",
            "subcategory":"Construction",
            "type":"Services"
        }
    ],
    "sg:phone":"+1 503 659 4256",
    "sg:postcode":"97222",
    "sg:province":"OR",
    "sg:tags":[
        "excavation",
        "contractor"
    ],
    "wof:name":"Ronald Mituniewicz Cnstr",
    "wof:placetype":"venue"
},
  "geometry": {"coordinates":[-122.629863,45.455569],"type":"Point"}
}