{
  "type": "Feature",
  "properties": {
    "iso:country":"US",
    "sg:address":"3108 Douglas Cir",
    "sg:city":"Lake Oswego",
    "sg:classifiers":[
        {
            "category":"Professional",
            "type":"Services"
        }
    ],
    "sg:phone":"+1 503 636 5218",
    "sg:postcode":"97035",
    "sg:province":"OR",
    "wof:name":"Columbia Pacific Dev LLC",
    "wof:placetype":"venue"
},
  "geometry": {"coordinates":[-122.709913,45.41358],"type":"Point"}
}