{
  "type": "Feature",
  "properties": {
    "addr:full":"2738 NE 14th Ave Portland OR 97212",
    "addr:housenumber":"2738",
    "addr:postcode":"97212",
    "addr:street":"Ne 14Th Ave",
    "iso:country":"US",
    "sg:address":"2738 NE 14th Ave",
    "sg:city":"Portland",
    "sg:classifiers":[
        {
            "category":"Communications",
            "type":"Services"
        }
    ],
    "sg:phone":"+1 503 281 0534",
    "sg:postcode":"97212",
    "sg:province":"OR",
    "wof:name":"Business Communication & Mktg.",
    "wof:placetype":"venue"
},
  "geometry": {"coordinates":[-122.65145,45.542392],"type":"Point"}
}