{
  "type": "Feature",
  "properties": {
    "iso:country":"US",
    "sg:address":"1225 NW Murray Rd Ste 105",
    "sg:city":"Portland",
    "sg:classifiers":[
        {
            "category":"Professional",
            "type":"Services"
        }
    ],
    "sg:phone":"+1 503 526 1080",
    "sg:postcode":"97229",
    "sg:province":"OR",
    "sg:tags":[
        "shows",
        "exposition",
        "fair",
        "trade"
    ],
    "sg:website":"http://www.hfgf.com",
    "wof:name":"Showcase Production",
    "wof:placetype":"venue"
},
  "geometry": {"coordinates":[-122.812922,45.528268],"type":"Point"}
}