{
  "type": "Feature",
  "properties": {
    "iso:country":"US",
    "sg:address":"1000 S Springbrook Rd",
    "sg:city":"Newberg",
    "sg:classifiers":[
        {
            "category":"Manufacturing",
            "subcategory":"Printing",
            "type":"Manufacturing & Wholesale Goods"
        }
    ],
    "sg:phone":"+1 503 538 5248",
    "sg:postcode":"97132",
    "sg:province":"OR",
    "sg:tags":[
        "mfg"
    ],
    "wof:name":"KCS Creations",
    "wof:placetype":"venue"
},
  "geometry": {"coordinates":[-122.947024,45.292244],"type":"Point"}
}