{
  "type": "Feature",
  "properties": {
    "iso:country":"US",
    "sg:address":"700 SW Taylor St",
    "sg:city":"Portland",
    "sg:classifiers":[
        {
            "category":"Professional",
            "subcategory":"Lawyer & Legal Services",
            "type":"Services"
        }
    ],
    "sg:phone":"+1 503 227 1168",
    "sg:postcode":"97205",
    "sg:province":"OR",
    "sg:tags":[
        "plan"
    ],
    "wof:name":"William Brown C/Broadvie",
    "wof:placetype":"venue"
},
  "geometry": {"coordinates":[-122.68032100000001,45.518009],"type":"Point"}
}