{
  "type": "Feature",
  "properties": {
    "addr:full":"116 NE 160th Ave Portland OR 97230",
    "addr:housenumber":"116",
    "addr:postcode":"97230",
    "addr:street":"Ne 160Th Ave",
    "iso:country":"US",
    "sg:address":"116 NE 160th Ave",
    "sg:city":"Portland",
    "sg:classifiers":[
        {
            "category":"Real Estate",
            "subcategory":"Real Estate Operator",
            "type":"Services"
        }
    ],
    "sg:phone":"+1 503 253 4755",
    "sg:postcode":"97230",
    "sg:province":"OR",
    "sg:tags":[
        "building",
        "nonresidential"
    ],
    "wof:name":"Sandpiper Properties",
    "wof:placetype":"venue"
},
  "geometry": {"coordinates":[-122.498924,45.523791],"type":"Point"}
}