{
  "type": "Feature",
  "properties": {
    "addr:full":"751 Main St Sweet Home OR 97386",
    "addr:housenumber":"751",
    "addr:postcode":"97386",
    "addr:street":"Main St",
    "iso:country":"US",
    "sg:address":"751 Main St",
    "sg:city":"Sweet Home",
    "sg:classifiers":[
        {
            "category":"Shopping",
            "subcategory":"Tobacco",
            "type":"Retail Goods"
        }
    ],
    "sg:phone":"+1 541 367 4951",
    "sg:postcode":"97386",
    "sg:province":"OR",
    "sg:tags":[
        "cigarette",
        "cigar",
        "dealer"
    ],
    "wof:name":"Stogie's Road",
    "wof:placetype":"venue"
},
  "geometry": {"coordinates":[-122.736029,44.397529],"type":"Point"}
}