{
  "type": "Feature",
  "properties": {
    "iso:country":"US",
    "sg:address":"735 NW 21st Avenue",
    "sg:city":"Portland",
    "sg:classifiers":[
        {
            "category":"Restaurant",
            "type":"Food & Drink"
        },
        {
            "category":"Food & Beverages",
            "subcategory":"Meat & Fish",
            "type":"Retail Goods"
        }
    ],
    "sg:phone":"+1 503 227 2700",
    "sg:postcode":"97209",
    "sg:province":"OR",
    "sg:tags":[
        "seafood",
        "market"
    ],
    "sg:website":"www.newmansfish.com/index.html",
    "wof:name":"Newman's Fish Market",
    "wof:placetype":"venue"
},
  "geometry": {"coordinates":[-122.694647,45.528202],"type":"Point"}
}