{
  "type": "Feature",
  "properties": {
    "iso:country":"US",
    "sg:address":"675 12th St SE",
    "sg:city":"Salem",
    "sg:classifiers":[
        {
            "category":"Shopping",
            "type":"Retail Goods"
        }
    ],
    "sg:phone":"+1 503 581 9191",
    "sg:postcode":"97301",
    "sg:province":"OR",
    "sg:tags":[
        "merchandise"
    ],
    "wof:name":"Hanger Prosthetics & Orthotics",
    "wof:placetype":"venue"
},
  "geometry": {"coordinates":[-123.029967,44.931213],"type":"Point"}
}