{
  "type": "Feature",
  "properties": {
    "addr:full":"19445 Provisioner Ct Oregon City OR 97045",
    "addr:housenumber":"19445",
    "addr:postcode":"97045",
    "addr:street":"Provisioner Ct",
    "iso:country":"US",
    "sg:address":"19445 Provisioner Ct",
    "sg:city":"Oregon City",
    "sg:classifiers":[
        {
            "category":"Education",
            "subcategory":"Vocational School",
            "type":"Public Place"
        }
    ],
    "sg:phone":"+1 503 314 3628",
    "sg:postcode":"97045",
    "sg:province":"OR",
    "wof:name":"X Form Media LLC",
    "wof:placetype":"venue"
},
  "geometry": {"coordinates":[-122.60111499999999,45.32333],"type":"Point"}
}