{
  "type": "Feature",
  "properties": {
    "addr:full":"7410 SW Bridgeport Rd Tigard OR 97224",
    "addr:housenumber":"7410",
    "addr:postcode":"97224",
    "addr:street":"Sw Bridgeport Rd",
    "iso:country":"US",
    "sg:address":"7410 SW Bridgeport Rd",
    "sg:city":"Tigard",
    "sg:classifiers":[
        {
            "category":"Shopping",
            "subcategory":"Bicycles & Sporting Goods",
            "type":"Retail Goods"
        },
        {
            "category":"Sports & Exercise",
            "subcategory":"Bicycle Rental",
            "type":"Entertainment"
        }
    ],
    "sg:phone":"+1 503 624 8600",
    "sg:postcode":"97224",
    "sg:province":"OR",
    "sg:tags":[
        "bike",
        "outdoor",
        "gear",
        "wear"
    ],
    "sg:website":"www.REI.com/Tualitin",
    "wof:name":"REI",
    "wof:placetype":"venue"
},
  "geometry": {"coordinates":[-122.752937,45.394005],"type":"Point"}
}