{
  "type": "Feature",
  "properties": {
    "addr:full":"32120 SW Cypress Pt Wilsonville OR 97070",
    "addr:housenumber":"32120",
    "addr:postcode":"97070",
    "addr:street":"Sw Cypress Pt",
    "iso:country":"US",
    "sg:address":"32120 SW Cypress Pt",
    "sg:city":"Wilsonville",
    "sg:classifiers":[
        {
            "category":"Professional",
            "subcategory":"Secretarial Services",
            "type":"Services"
        }
    ],
    "sg:phone":"+1 503 694 6256",
    "sg:postcode":"97070",
    "sg:province":"OR",
    "sg:tags":[
        "reporting"
    ],
    "wof:name":"Southern Ore Reporting Assoc",
    "wof:placetype":"venue"
},
  "geometry": {"coordinates":[-122.76545299999999,45.288372],"type":"Point"}
}