{
  "type": "Feature",
  "properties": {
    "addr:full":"10220 SW Greenburg Road Suite 135 Portland OR 97223",
    "addr:housenumber":"10220",
    "addr:postcode":"97223",
    "addr:street":"Sw Greenburg Road Suite 135",
    "iso:country":"US",
    "sg:address":"10220 SW Greenburg Road Suite 135",
    "sg:city":"Portland",
    "sg:classifiers":[
        {
            "category":"Professional",
            "subcategory":"Employment Agencies",
            "type":"Services"
        }
    ],
    "sg:phone":"+1 503 246 5342",
    "sg:postcode":"97223",
    "sg:province":"OR",
    "wof:name":"Randstad",
    "wof:placetype":"venue"
},
  "geometry": {"coordinates":[-122.77640100000001,45.446208],"type":"Point"}
}