{
  "type": "Feature",
  "properties": {
    "iso:country":"US",
    "sg:address":"15075 SW Koll Pkwy",
    "sg:city":"Beaverton",
    "sg:classifiers":[
        {
            "category":"Manufacturing",
            "subcategory":"Tools & Machinery",
            "type":"Manufacturing & Wholesale Goods"
        }
    ],
    "sg:phone":"+1 503 643 9414",
    "sg:postcode":"97006",
    "sg:province":"OR",
    "sg:tags":[
        "machine"
    ],
    "wof:name":"International Tools & Tech",
    "wof:placetype":"venue"
},
  "geometry": {"coordinates":[-122.833727,45.512703],"type":"Point"}
}