{
  "type": "Feature",
  "properties": {
    "iso:country":"US",
    "sg:address":"6869 65 Ave",
    "sg:city":"Lake Oswego",
    "sg:classifiers":[
        {
            "category":"Building & Trades",
            "subcategory":"Locksmith",
            "type":"Services"
        }
    ],
    "sg:phone":"+1 503 715 3858",
    "sg:postcode":"97034",
    "sg:province":"OR",
    "sg:tags":[
        "key"
    ],
    "wof:name":"Locksmith 24 Hour",
    "wof:placetype":"venue"
},
  "geometry": {"coordinates":[-122.74319800000001,45.436926],"type":"Point"}
}