{
  "type": "Feature",
  "properties": {
    "iso:country":"US",
    "sg:address":"90 N Polk St",
    "sg:city":"Eugene",
    "sg:classifiers":[
        {
            "category":"Manufacturing",
            "subcategory":"Retail Goods",
            "type":"Manufacturing & Wholesale Goods"
        }
    ],
    "sg:phone":"+1 541 343 4708",
    "sg:postcode":"97402",
    "sg:province":"OR",
    "sg:tags":[
        "lead",
        "mfg"
    ],
    "wof:name":"Distribution International",
    "wof:placetype":"venue"
},
  "geometry": {"coordinates":[-123.112504,44.059903],"type":"Point"}
}