{
  "type": "Feature",
  "properties": {
    "iso:country":"US",
    "sg:address":"13244 SE Reedway Pl",
    "sg:city":"Portland",
    "sg:classifiers":[
        {
            "category":"Building & Trades",
            "subcategory":"Construction",
            "type":"Services"
        }
    ],
    "sg:phone":"+1 503 762 1871",
    "sg:postcode":"97236",
    "sg:province":"OR",
    "sg:tags":[
        "hanging",
        "contractor"
    ],
    "wof:name":"Phoenix Painting Inc",
    "wof:placetype":"venue"
},
  "geometry": {"coordinates":[-122.527033,45.480901],"type":"Point"}
}