{
  "type": "Feature",
  "properties": {
    "addr:full":"1810 NW Mulholland Dr Roseburg OR 97470",
    "addr:housenumber":"1810",
    "addr:postcode":"97470",
    "addr:street":"Nw Mulholland Dr",
    "iso:country":"US",
    "sg:address":"1810 NW Mulholland Dr",
    "sg:city":"Roseburg",
    "sg:classifiers":[
        {
            "category":"Wholesale",
            "subcategory":"Chemicals & Plastics",
            "type":"Manufacturing & Wholesale Goods"
        }
    ],
    "sg:phone":"+1 541 957 0907",
    "sg:postcode":"97470",
    "sg:province":"OR",
    "sg:tags":[
        "oxygen"
    ],
    "wof:name":"Lincare",
    "wof:placetype":"venue"
},
  "geometry": {"coordinates":[-123.360141,43.231512],"type":"Point"}
}