{
  "type": "Feature",
  "properties": {
    "iso:country":"US",
    "sg:address":"5919 SE Belmont Street",
    "sg:city":"Portland",
    "sg:classifiers":[
        {
            "category":"Health Services",
            "subcategory":"Doctor",
            "type":"Services"
        }
    ],
    "sg:phone":"+1 503 234 7366",
    "sg:postcode":"97215",
    "sg:province":"OR",
    "sg:tags":[
        "practice",
        "family"
    ],
    "wof:name":"Hamley Michele C-Fnp",
    "wof:placetype":"venue"
},
  "geometry": {"coordinates":[-122.60279300000001,45.516869],"type":"Point"}
}