{
  "type": "Feature",
  "properties": {
    "iso:country":"US",
    "sg:address":"8948 NE Killingsworth Street",
    "sg:city":"Portland",
    "sg:classifiers":[
        {
            "category":"Retail",
            "subcategory":"Auto Repair",
            "type":"Services"
        }
    ],
    "sg:phone":"+1 503 252 5112",
    "sg:postcode":"97220",
    "sg:province":"OR",
    "wof:name":"Paden Drivetrain",
    "wof:placetype":"venue"
},
  "geometry": {"coordinates":[-122.568583,45.562323],"type":"Point"}
}