{
  "type": "Feature",
  "properties": {
    "iso:country":"US",
    "sg:address":"115 N Water St",
    "sg:city":"Weston",
    "sg:classifiers":[
        {
            "category":"Organizations",
            "subcategory":"Religious Organization",
            "type":"Services"
        }
    ],
    "sg:phone":"+1 541 566 3784",
    "sg:postcode":"97886",
    "sg:province":"OR",
    "sg:tags":[
        "church"
    ],
    "wof:name":"Assembly Of God Weston",
    "wof:placetype":"venue"
},
  "geometry": {"coordinates":[-118.425304,45.814498],"type":"Point"}
}