{
  "type": "Feature",
  "properties": {
    "iso:country":"US",
    "sg:address":"677 Laksonen Loop",
    "sg:city":"Springfield",
    "sg:classifiers":[
        {
            "category":"Building & Trades",
            "subcategory":"Landscaping Services",
            "type":"Services"
        }
    ],
    "sg:phone":"+1 541 726 2640",
    "sg:postcode":"97478",
    "sg:province":"OR",
    "sg:tags":[
        "lawn",
        "maintenance",
        "grounds"
    ],
    "wof:name":"New Thumb Lawn & Garden Svc",
    "wof:placetype":"venue"
},
  "geometry": {"coordinates":[-122.90337599999999,44.051627],"type":"Point"}
}