{
  "type": "Feature",
  "properties": {
    "iso:country":"US",
    "sg:address":"1605 NE Lytle St",
    "sg:city":"Bend",
    "sg:classifiers":[
        {
            "category":"Restaurant",
            "type":"Food & Drink"
        }
    ],
    "sg:phone":"+1 541 382 1646",
    "sg:postcode":"97701",
    "sg:province":"OR",
    "sg:tags":[
        "caterer"
    ],
    "wof:name":"TLC Catering",
    "wof:placetype":"venue"
},
  "geometry": {"coordinates":[-121.30457,44.066585],"type":"Point"}
}