{
  "type": "Feature",
  "properties": {
    "iso:country":"US",
    "sg:address":"1055 S Highway 395",
    "sg:city":"Hermiston",
    "sg:classifiers":[
        {
            "category":"Insurance",
            "subcategory":"Hazard Insurance",
            "type":"Services"
        },
        {
            "category":"Banks & Credit Unions",
            "subcategory":"Investment Brokerage",
            "type":"Services"
        },
        {
            "category":"Insurance",
            "subcategory":"Life Insurance",
            "type":"Services"
        },
        {
            "category":"Banks & Credit Unions",
            "subcategory":"Financial Services",
            "type":"Services"
        }
    ],
    "sg:phone":"+1 815 591 2212",
    "sg:postcode":"97838",
    "sg:province":"OR",
    "sg:website":"http://national.citysearch.com/profile/external/42911897/hermiston_or/country_financial_adam_meador.html?publisher=yellowpages&reference_id=1&placement=ypwebsitemip",
    "wof:name":"COUNTRY Financial - Adam Meador",
    "wof:placetype":"venue"
},
  "geometry": {"coordinates":[-119.284477,45.833023],"type":"Point"}
}