{
  "type": "Feature",
  "properties": {
    "addr:full":"60255 Arapaho Ln Bend OR 97702",
    "addr:housenumber":"60255",
    "addr:postcode":"97702",
    "addr:street":"Arapaho Ln",
    "iso:country":"US",
    "sg:address":"60255 Arapaho Ln",
    "sg:city":"Bend",
    "sg:classifiers":[
        {
            "category":"Local Transit",
            "type":"Transportation"
        }
    ],
    "sg:phone":"+1 541 385 9238",
    "sg:postcode":"97702",
    "sg:province":"OR",
    "sg:tags":[
        "handicapped"
    ],
    "wof:name":"High Desert Transport",
    "wof:placetype":"venue"
},
  "geometry": {"coordinates":[-121.354941,43.988995],"type":"Point"}
}