{
  "type": "Feature",
  "properties": {
    "iso:country":"US",
    "sg:address":"2838 E Burnside St",
    "sg:city":"Portland",
    "sg:classifiers":[
        {
            "category":"Organizations",
            "subcategory":"Religious Organization",
            "type":"Services"
        }
    ],
    "sg:phone":"+1 503 233 8358",
    "sg:postcode":"97214",
    "sg:province":"OR",
    "wof:name":"Arch Diocese of Portland",
    "wof:placetype":"venue"
},
  "geometry": {"coordinates":[-122.636276,45.522798],"type":"Point"}
}