{
  "type": "Feature",
  "properties": {
    "addr:full":"9151 SE McBrod Ave Milwaukie OR 97222",
    "addr:housenumber":"9151",
    "addr:postcode":"97222",
    "addr:street":"Se Mcbrod Ave",
    "iso:country":"US",
    "sg:address":"9151 SE McBrod Ave",
    "sg:city":"Milwaukie",
    "sg:classifiers":[
        {
            "category":"Wholesale",
            "subcategory":"Electrical",
            "type":"Manufacturing & Wholesale Goods"
        }
    ],
    "sg:phone":"+1 503 653 8619",
    "sg:postcode":"97222",
    "sg:province":"OR",
    "sg:tags":[
        "equipment",
        "electric",
        "supply"
    ],
    "sg:website":"www.wselectric.com",
    "wof:name":"Western States Electric Inc",
    "wof:placetype":"venue"
},
  "geometry": {"coordinates":[-122.64387600000001,45.454936],"type":"Point"}
}