{
  "type": "Feature",
  "properties": {
    "iso:country":"US",
    "sg:address":"363 State St",
    "sg:city":"Salem",
    "sg:classifiers":[
        {
            "category":"Real Estate",
            "subcategory":"Architect",
            "type":"Services"
        }
    ],
    "sg:phone":"+1 503 581 4114",
    "sg:postcode":"97301",
    "sg:province":"OR",
    "wof:name":"Arbuckle Costic Architects Inc",
    "wof:placetype":"venue"
},
  "geometry": {"coordinates":[-123.039665,44.940294],"type":"Point"}
}