{
  "type": "Feature",
  "properties": {
    "addr:full":"60932 Aspen Dr Bend OR 97702",
    "addr:housenumber":"60932",
    "addr:postcode":"97702",
    "addr:street":"Aspen Dr",
    "iso:country":"US",
    "sg:address":"60932 Aspen Dr",
    "sg:city":"Bend",
    "sg:classifiers":[
        {
            "category":"Building & Trades",
            "subcategory":"Construction",
            "type":"Services"
        }
    ],
    "sg:phone":"+1 541 312 3602",
    "sg:postcode":"97702",
    "sg:province":"OR",
    "sg:tags":[
        "house"
    ],
    "wof:name":"Mike Seidel Construction",
    "wof:placetype":"venue"
},
  "geometry": {"coordinates":[-121.330868,44.012362],"type":"Point"}
}