{
  "type": "Feature",
  "properties": {
    "iso:country":"US",
    "sg:address":"233 Rogue River Hwy",
    "sg:city":"Grants Pass",
    "sg:classifiers":[
        {
            "category":"Professional",
            "subcategory":"Business Services",
            "type":"Services"
        }
    ],
    "sg:phone":"+1 541 955 8480",
    "sg:postcode":"97527",
    "sg:province":"OR",
    "wof:name":"Senior Fin Solutns Southrn or",
    "wof:placetype":"venue"
},
  "geometry": {"coordinates":[-123.331007,42.426456],"type":"Point"}
}