{
  "type": "Feature",
  "properties": {
    "addr:full":"15509 NE Airport Way Portland OR 97230",
    "addr:housenumber":"15509",
    "addr:postcode":"97230",
    "addr:street":"Ne Airport Way",
    "iso:country":"US",
    "sg:address":"15509 NE Airport Way",
    "sg:city":"Portland",
    "sg:classifiers":[
        {
            "category":"Transit Center",
            "subcategory":"Freight",
            "type":"Transportation"
        },
        {
            "category":"Professional",
            "subcategory":"Business Services",
            "type":"Services"
        },
        {
            "category":"Taxi",
            "type":"Transportation"
        },
        {
            "category":"Government",
            "subcategory":"Post Office",
            "type":"Public Place"
        }
    ],
    "sg:phone":"+1 503 256 5204",
    "sg:postcode":"97230",
    "sg:province":"OR",
    "sg:tags":[
        "cargo",
        "courier",
        "package",
        "express",
        "shipping",
        "air",
        "delivery",
        "mail",
        "forwarding"
    ],
    "sg:website":"http://www.dhl.com",
    "wof:name":"Dhl Global Forwarding",
    "wof:placetype":"venue"
},
  "geometry": {"coordinates":[-122.50327299999999,45.558306],"type":"Point"}
}