{
  "type": "Feature",
  "properties": {
    "iso:country":"US",
    "sg:address":"525 1st St",
    "sg:city":"Lake Oswego",
    "sg:classifiers":[
        {
            "category":"Shopping",
            "subcategory":"Computers & Home Electronics",
            "type":"Retail Goods"
        }
    ],
    "sg:phone":"+1 503 635 7200",
    "sg:postcode":"97034",
    "sg:province":"OR",
    "wof:name":"H E C Inc",
    "wof:placetype":"venue"
},
  "geometry": {"coordinates":[-122.663651,45.421601],"type":"Point"}
}