{
  "type": "Feature",
  "properties": {
    "iso:country":"US",
    "sg:address":"3111 Millersburg Dr NE",
    "sg:city":"Albany",
    "sg:classifiers":[
        {
            "category":"Real Estate",
            "subcategory":"Real Estate Agent",
            "type":"Services"
        }
    ],
    "sg:phone":"+1 541 928 1964",
    "sg:postcode":"97321",
    "sg:province":"OR",
    "wof:name":"Oregon Valley Enterprize LLC",
    "wof:placetype":"venue"
},
  "geometry": {"coordinates":[-123.059298,44.698474],"type":"Point"}
}