{
  "type": "Feature",
  "properties": {
    "iso:country":"US",
    "sg:address":"2650 NE Courtney Dr",
    "sg:city":"Bend",
    "sg:classifiers":[
        {
            "category":"Health Services",
            "subcategory":"Clinic",
            "type":"Services"
        }
    ],
    "sg:phone":"+1 541 296 8884",
    "sg:postcode":"97701",
    "sg:province":"OR",
    "sg:tags":[
        "organization",
        "medical",
        "surgical"
    ],
    "wof:name":"Central Oregon IPA Inc",
    "wof:placetype":"venue"
},
  "geometry": {"coordinates":[-121.264762,44.071932],"type":"Point"}
}