{
  "type": "Feature",
  "properties": {
    "iso:country":"US",
    "sg:address":"990 N Phoenix Rd",
    "sg:city":"Medford",
    "sg:classifiers":[
        {
            "category":"Utilities",
            "subcategory":"Mobile Phone",
            "type":"Services"
        }
    ],
    "sg:phone":"+1 541 494 7575",
    "sg:postcode":"97504",
    "sg:province":"OR",
    "sg:tags":[
        "telephone",
        "cellular"
    ],
    "wof:name":"High Tech Center",
    "wof:placetype":"venue"
},
  "geometry": {"coordinates":[-122.814108,42.318166],"type":"Point"}
}