{
  "type": "Feature",
  "properties": {
    "addr:full":"5838 SE Center St Portland OR 97206",
    "addr:housenumber":"5838",
    "addr:postcode":"97206",
    "addr:street":"Se Center St",
    "iso:country":"US",
    "sg:address":"5838 SE Center St",
    "sg:city":"Portland",
    "sg:classifiers":[
        {
            "category":"Professional",
            "subcategory":"Art Services",
            "type":"Services"
        }
    ],
    "sg:phone":"+1 503 236 7600",
    "sg:postcode":"97206",
    "sg:province":"OR",
    "sg:tags":[
        "commercial",
        "design"
    ],
    "wof:name":"Fuze",
    "wof:placetype":"venue"
},
  "geometry": {"coordinates":[-122.60202700000001,45.493824],"type":"Point"}
}