{
  "type": "Feature",
  "properties": {
    "iso:country":"US",
    "sg:address":"8225 SW Fairway Dr",
    "sg:city":"Portland",
    "sg:classifiers":[
        {
            "category":"Professional",
            "subcategory":"Lawyer & Legal Services",
            "type":"Services"
        }
    ],
    "sg:phone":"+1 503 297 4594",
    "sg:postcode":"97225",
    "sg:province":"OR",
    "wof:name":"Law Firm of Karl I Mullen",
    "wof:placetype":"venue"
},
  "geometry": {"coordinates":[-122.762085,45.4933],"type":"Point"}
}