{
  "type": "Feature",
  "properties": {
    "iso:country":"US",
    "sg:address":"432 NW 6th St",
    "sg:city":"Grants Pass",
    "sg:classifiers":[
        {
            "category":"Retail",
            "subcategory":"Portrait Studio",
            "type":"Services"
        }
    ],
    "sg:phone":"+1 541 660 5803",
    "sg:postcode":"97526",
    "sg:province":"OR",
    "sg:tags":[
        "photographer",
        "photo"
    ],
    "wof:name":"Travis Gagnon Photography",
    "wof:placetype":"venue"
},
  "geometry": {"coordinates":[-123.325621,42.441701],"type":"Point"}
}