{
  "type": "Feature",
  "properties": {
    "iso:country":"US",
    "sg:address":"4070 39th Ave SE",
    "sg:city":"Albany",
    "sg:classifiers":[
        {
            "category":"Utilities",
            "subcategory":"Water",
            "type":"Services"
        }
    ],
    "sg:phone":"+1 541 926 4676",
    "sg:postcode":"97322",
    "sg:province":"OR",
    "sg:tags":[
        "supply"
    ],
    "wof:name":"Grand Prairie Water Supply",
    "wof:placetype":"venue"
},
  "geometry": {"coordinates":[-123.05261400000001,44.606883],"type":"Point"}
}