{
  "type": "Feature",
  "properties": {
    "iso:country":"US",
    "sg:address":"17 NW Hawthorne Ave",
    "sg:city":"Bend",
    "sg:classifiers":[
        {
            "category":"Insurance",
            "subcategory":"Insurance Agent",
            "type":"Services"
        }
    ],
    "sg:phone":"+1 541 382 4731",
    "sg:postcode":"97701",
    "sg:province":"OR",
    "wof:name":"Jackson Insurance & Financial",
    "wof:placetype":"venue"
},
  "geometry": {"coordinates":[-121.308589,44.057875],"type":"Point"}
}