{
  "type": "Feature",
  "properties": {
    "iso:country":"US",
    "sg:address":"28590 SE Wally Rd",
    "sg:city":"Boring",
    "sg:classifiers":[
        {
            "category":"Wholesale",
            "subcategory":"Farm Supplies",
            "type":"Manufacturing & Wholesale Goods"
        }
    ],
    "sg:phone":"+1 503 663 9411",
    "sg:postcode":"97009",
    "sg:province":"OR",
    "wof:name":"Decorative Bark Products Inc",
    "wof:placetype":"venue"
},
  "geometry": {"coordinates":[-122.373738,45.430267],"type":"Point"}
}