{
  "type": "Feature",
  "properties": {
    "iso:country":"US",
    "sg:address":"SW 10th and Washington",
    "sg:city":"Portland",
    "sg:classifiers":[
        {
            "category":"Restaurant",
            "type":"Food & Drink"
        },
        {
            "category":"Food Court",
            "type":"Food & Drink"
        }
    ],
    "sg:postcode":"97205",
    "sg:province":"OR",
    "sg:tags":[
        "ethiopian",
        "stand"
    ],
    "wof:name":"Emame's Ethiopian Cuisine",
    "wof:placetype":"venue"
},
  "geometry": {"coordinates":[-122.68139600000001,45.521352],"type":"Point"}
}