{
  "type": "Feature",
  "properties": {
    "iso:country":"US",
    "sg:address":"3291 Pheasant Blvd",
    "sg:city":"Springfield",
    "sg:classifiers":[
        {
            "category":"Shopping",
            "subcategory":"Computers & Home Electronics",
            "type":"Retail Goods"
        }
    ],
    "sg:phone":"+1 541 746 9429",
    "sg:postcode":"97477",
    "sg:province":"OR",
    "wof:name":"Key Success",
    "wof:placetype":"venue"
},
  "geometry": {"coordinates":[-123.035387,44.079338],"type":"Point"}
}