{
  "type": "Feature",
  "properties": {
    "iso:country":"US",
    "sg:address":"2306 Robertson Crst",
    "sg:city":"Grants Pass",
    "sg:classifiers":[
        {
            "category":"Home & Garden",
            "subcategory":"Garden Supply",
            "type":"Retail Goods"
        }
    ],
    "sg:phone":"+1 541 476 6830",
    "sg:postcode":"97527",
    "sg:province":"OR",
    "sg:tags":[
        "landscaping",
        "equipment"
    ],
    "wof:name":"Marble Mountain Limestone",
    "wof:placetype":"venue"
},
  "geometry": {"coordinates":[-123.30807,42.410548],"type":"Point"}
}