{
  "type": "Feature",
  "properties": {
    "iso:country":"US",
    "sg:address":"36585 SE Bluff Rd",
    "sg:city":"Boring",
    "sg:classifiers":[
        {
            "category":"Structure",
            "subcategory":"Office Building",
            "type":"Public Place"
        }
    ],
    "sg:phone":"+1 503 680 8900",
    "sg:postcode":"97009",
    "sg:province":"OR",
    "sg:tags":[
        "park"
    ],
    "wof:name":"K. Bredenkamp Properties",
    "wof:placetype":"venue"
},
  "geometry": {"coordinates":[-122.287048,45.451591],"type":"Point"}
}