{
  "type": "Feature",
  "properties": {
    "iso:country":"US",
    "sg:address":"13950 SW 72nd Ave",
    "sg:city":"Portland",
    "sg:classifiers":[
        {
            "category":"Manufacturing",
            "subcategory":"Furniture",
            "type":"Manufacturing & Wholesale Goods"
        }
    ],
    "sg:phone":"+1 503 598 0851",
    "sg:postcode":"97223",
    "sg:province":"OR",
    "sg:tags":[
        "window",
        "shades"
    ],
    "wof:name":"DSC Fabrics Of Portland",
    "wof:placetype":"venue"
},
  "geometry": {"coordinates":[-122.74998600000001,45.419302],"type":"Point"}
}