{
  "type": "Feature",
  "properties": {
    "iso:country":"US",
    "sg:address":"2339 SE Grand Ave",
    "sg:city":"Portland",
    "sg:classifiers":[
        {
            "category":"Freight",
            "type":"Transportation"
        }
    ],
    "sg:phone":"+1 503 232 9131",
    "sg:postcode":"97214",
    "sg:province":"OR",
    "sg:tags":[
        "cartage",
        "trucking"
    ],
    "wof:name":"Fourier Truck Svc",
    "wof:placetype":"venue"
},
  "geometry": {"coordinates":[-122.660874,45.506135],"type":"Point"}
}