{
  "type": "Feature",
  "properties": {
    "addr:full":"628 SW Mill St Sheridan OR 97378",
    "addr:housenumber":"628",
    "addr:postcode":"97378",
    "addr:street":"Sw Mill St",
    "iso:country":"US",
    "sg:address":"628 SW Mill St",
    "sg:city":"Sheridan",
    "sg:classifiers":[
        {
            "category":"Professional",
            "subcategory":"Computer Services",
            "type":"Services"
        }
    ],
    "sg:phone":"+1 503 843 2716",
    "sg:postcode":"97378",
    "sg:province":"OR",
    "sg:tags":[
        "related"
    ],
    "wof:name":"Nooktech",
    "wof:placetype":"venue"
},
  "geometry": {"coordinates":[-123.405529,45.093894],"type":"Point"}
}