{
  "type": "Feature",
  "properties": {
    "iso:country":"US",
    "sg:address":"Rogue Valley Mall",
    "sg:city":"Medford",
    "sg:classifiers":[
        {
            "category":"Home & Garden",
            "subcategory":"Carpets & Floor Coverings",
            "type":"Retail Goods"
        }
    ],
    "sg:phone":"+1 541 772 0852",
    "sg:postcode":"97501",
    "sg:province":"OR",
    "sg:tags":[
        "mattress"
    ],
    "wof:name":"America the Beautiful Dreamer",
    "wof:placetype":"venue"
},
  "geometry": {"coordinates":[-122.878998,42.317299],"type":"Point"}
}