{
  "type": "Feature",
  "properties": {
    "addr:full":"2118 SE Hogan Rd Gresham OR 97080",
    "addr:housenumber":"2118",
    "addr:postcode":"97080",
    "addr:street":"Se Hogan Rd",
    "iso:country":"US",
    "sg:address":"2118 SE Hogan Rd",
    "sg:city":"Gresham",
    "sg:classifiers":[
        {
            "category":"Retail",
            "subcategory":"Storage",
            "type":"Services"
        }
    ],
    "sg:phone":"+1 503 272 1998",
    "sg:postcode":"97080",
    "sg:province":"OR",
    "sg:tags":[
        "automobile",
        "self",
        "commercial",
        "household"
    ],
    "sg:website":"http://portland.citysearch.com/profile/external/604189382/gresham_or/money_saver_mini_storage.html?publisher=yellowpages&reference_id=1&placement=ypwebsitemip",
    "wof:name":"Money Saver Mini Storage",
    "wof:placetype":"venue"
},
  "geometry": {"coordinates":[-122.413971,45.481603],"type":"Point"}
}