{
  "type": "Feature",
  "properties": {
    "iso:country":"US",
    "sg:address":"16756 SE 82nd Dr",
    "sg:city":"Clackamas",
    "sg:classifiers":[
        {
            "category":"Retail",
            "subcategory":"Veterinary Services",
            "type":"Services"
        }
    ],
    "sg:phone":"+1 503 683 1913",
    "sg:postcode":"97015",
    "sg:province":"OR",
    "sg:tags":[
        "veterinarian"
    ],
    "sg:website":"www.VCANWVS.com",
    "wof:name":"VCA Northwest Veterinary Specialists",
    "wof:placetype":"venue"
},
  "geometry": {"coordinates":[-122.567891,45.400774],"type":"Point"}
}