{
  "type": "Feature",
  "properties": {
    "iso:country":"US",
    "sg:address":"1600 SW Cedar Hills Blvd Ste 107",
    "sg:city":"Beaverton",
    "sg:classifiers":[
        {
            "category":"Health Services",
            "subcategory":"Dentist",
            "type":"Services"
        }
    ],
    "sg:phone":"+1 503 643 7502",
    "sg:postcode":"97225",
    "sg:province":"OR",
    "sg:tags":[
        "dentists-cosmetic",
        "dental",
        "dentists-pediatric",
        "clinic",
        "dentistry"
    ],
    "sg:website":"www.cedarhillsdentalcare.com",
    "wof:name":"Cedar Hills Dental Care PC",
    "wof:placetype":"venue"
},
  "geometry": {"coordinates":[-122.79591600000001,45.508133],"type":"Point"}
}