{
  "type": "Feature",
  "properties": {
    "addr:full":"800 Willamette St Ste 525 Eugene OR 97401",
    "addr:housenumber":"800",
    "addr:postcode":"97401",
    "addr:street":"Willamette St Ste 525",
    "iso:country":"US",
    "sg:address":"800 Willamette St Ste 525",
    "sg:city":"Eugene",
    "sg:classifiers":[
        {
            "category":"Real Estate",
            "subcategory":"Real Estate Services",
            "type":"Services"
        },
        {
            "category":"Banks & Credit Unions",
            "subcategory":"Financial Services",
            "type":"Services"
        }
    ],
    "sg:phone":"+1 541 681 4340",
    "sg:postcode":"97401",
    "sg:province":"OR",
    "sg:tags":[
        "loan",
        "mortgage"
    ],
    "sg:website":"http://www.countrywidehomeloans.com",
    "wof:name":"Countrywide Home Loans",
    "wof:placetype":"venue"
},
  "geometry": {"coordinates":[-123.092743,44.051022],"type":"Point"}
}