{
  "type": "Feature",
  "properties": {
    "iso:country":"US",
    "sg:address":"207 Madison St",
    "sg:city":"Eugene",
    "sg:classifiers":[
        {
            "category":"Shopping",
            "subcategory":"Bicycles & Sporting Goods",
            "type":"Retail Goods"
        }
    ],
    "sg:phone":"+1 541 485 4007",
    "sg:postcode":"97402",
    "sg:province":"OR",
    "wof:name":"Backcountry Gear Limited",
    "wof:placetype":"venue"
},
  "geometry": {"coordinates":[-123.103302,44.056819],"type":"Point"}
}