{
  "type": "Feature",
  "properties": {
    "iso:country":"US",
    "sg:address":"1116 Turbyne Rd",
    "sg:city":"Sweet Home",
    "sg:classifiers":[
        {
            "category":"Professional",
            "subcategory":"Secretarial Services",
            "type":"Services"
        }
    ],
    "sg:phone":"+1 541 367 3548",
    "sg:postcode":"97386",
    "sg:province":"OR",
    "sg:tags":[
        "reporting"
    ],
    "wof:name":"Lloyd Mutinsky",
    "wof:placetype":"venue"
},
  "geometry": {"coordinates":[-122.712951,44.373227],"type":"Point"}
}