{
  "type": "Feature",
  "properties": {
    "iso:country":"US",
    "sg:address":"1389 Pearl St",
    "sg:city":"Eugene",
    "sg:classifiers":[
        {
            "category":"Shopping",
            "subcategory":"Clothing, Apparel, & Fashions",
            "type":"Retail Goods"
        }
    ],
    "sg:phone":"+1 541 343 8821",
    "sg:postcode":"97401",
    "sg:province":"OR",
    "wof:name":"Bon Ton Exchange",
    "wof:placetype":"venue"
},
  "geometry": {"coordinates":[-123.089621,44.044854],"type":"Point"}
}