{
  "type": "Feature",
  "properties": {
    "iso:country":"US",
    "sg:address":"24485 SW Scholls Ferry Rd",
    "sg:city":"Hillsboro",
    "sg:classifiers":[
        {
            "category":"Restaurant",
            "type":"Food & Drink"
        }
    ],
    "sg:phone":"+1 503 628 1904",
    "sg:postcode":"97123",
    "sg:province":"OR",
    "sg:tags":[
        "eating"
    ],
    "wof:name":"Scholls Public House",
    "wof:placetype":"venue"
},
  "geometry": {"coordinates":[-122.92904900000001,45.401201],"type":"Point"}
}