{
  "type": "Feature",
  "properties": {
    "iso:country":"US",
    "sg:address":"1921 Turner Rd SE",
    "sg:city":"Salem",
    "sg:classifiers":[
        {
            "category":"Professional",
            "type":"Services"
        }
    ],
    "sg:phone":"+1 503 945 3993",
    "sg:postcode":"97302",
    "sg:province":"OR",
    "wof:name":"Hq 641st Med Bn",
    "wof:placetype":"venue"
},
  "geometry": {"coordinates":[-122.99863000000001,44.9144],"type":"Point"}
}