{
  "type": "Feature",
  "properties": {
    "addr:full":"3580 NE Simpson Street Portland OR 97211",
    "addr:housenumber":"3580",
    "addr:postcode":"97211",
    "addr:street":"Ne Simpson Street",
    "iso:country":"US",
    "sg:address":"3580 NE Simpson Street",
    "sg:city":"Portland",
    "sg:classifiers":[
        {
            "category":"Food & Beverages",
            "subcategory":"Meat & Fish",
            "type":"Retail Goods"
        }
    ],
    "sg:phone":"+1 503 331 0111",
    "sg:postcode":"97211",
    "sg:province":"OR",
    "sg:tags":[
        "seafood",
        "market"
    ],
    "wof:name":"Gilson Marine Farms",
    "wof:placetype":"venue"
},
  "geometry": {"coordinates":[-122.62693400000001,45.565013],"type":"Point"}
}