{
  "type": "Feature",
  "properties": {
    "iso:country":"US",
    "sg:address":"210 Rolling Hills Rd",
    "sg:city":"Roseburg",
    "sg:classifiers":[
        {
            "category":"Organizations",
            "subcategory":"Religious Organization",
            "type":"Services"
        }
    ],
    "sg:phone":"+1 541 679 0295",
    "sg:postcode":"97470",
    "sg:province":"OR",
    "wof:name":"Nehalem Renewal Ministries",
    "wof:placetype":"venue"
},
  "geometry": {"coordinates":[-123.396126,43.138948],"type":"Point"}
}