{
  "type": "Feature",
  "properties": {
    "iso:country":"US",
    "sg:address":"11645 SW Cloud Ct",
    "sg:city":"Tigard",
    "sg:classifiers":[
        {
            "category":"Building & Trades",
            "subcategory":"Locksmith",
            "type":"Services"
        }
    ],
    "sg:phone":"+1 503 715 2016",
    "sg:postcode":"97224",
    "sg:province":"OR",
    "sg:tags":[
        "key"
    ],
    "wof:name":"0 Locksmith",
    "wof:placetype":"venue"
},
  "geometry": {"coordinates":[-122.79717599999999,45.416349],"type":"Point"}
}