{
  "type": "Feature",
  "properties": {
    "addr:full":"1300 N Elizabeth St Milton Freewater OR 97862",
    "addr:housenumber":"1300",
    "addr:postcode":"97862",
    "addr:street":"N Elizabeth St;Freewater",
    "iso:country":"US",
    "sg:address":"1300 N Elizabeth St",
    "sg:city":"Milton Freewater",
    "sg:classifiers":[
        {
            "category":"Freight",
            "type":"Transportation"
        }
    ],
    "sg:phone":"+1 541 938 6214",
    "sg:postcode":"97862",
    "sg:province":"OR",
    "sg:tags":[
        "commercial",
        "storage"
    ],
    "wof:name":"Jones Mini Storage",
    "wof:placetype":"venue"
},
  "geometry": {"coordinates":[-118.389106,45.948372],"type":"Point"}
}