{
  "type": "Feature",
  "properties": {
    "iso:country":"US",
    "sg:address":"84940 Matlock Ln",
    "sg:city":"Veneta",
    "sg:classifiers":[
        {
            "category":"Recreation",
            "type":"Entertainment"
        }
    ],
    "sg:phone":"+1 541 935 1557",
    "sg:postcode":"97487",
    "sg:province":"OR",
    "sg:tags":[
        "club",
        "membership"
    ],
    "wof:name":"Eugene Figure Skating Club",
    "wof:placetype":"venue"
},
  "geometry": {"coordinates":[-123.387366,43.972415],"type":"Point"}
}