{
  "type": "Feature",
  "properties": {
    "iso:country":"US",
    "sg:address":"6441 SE 82nd Ave",
    "sg:city":"Portland",
    "sg:classifiers":[
        {
            "category":"Retail",
            "subcategory":"Auto Repair",
            "type":"Services"
        }
    ],
    "sg:phone":"+1 503 774 5310",
    "sg:postcode":"97266",
    "sg:province":"OR",
    "sg:tags":[
        "repairing",
        "automobile",
        "general"
    ],
    "wof:name":"Paul's Automotive",
    "wof:placetype":"venue"
},
  "geometry": {"coordinates":[-122.57914,45.476239],"type":"Point"}
}