{
  "type": "Feature",
  "properties": {
    "iso:country":"US",
    "sg:address":"112 NW Greeley Ave",
    "sg:city":"Bend",
    "sg:classifiers":[
        {
            "category":"Organizations",
            "subcategory":"Non-profit Organization",
            "type":"Services"
        }
    ],
    "sg:phone":"+1 541 383 1448",
    "sg:postcode":"97701",
    "sg:province":"OR",
    "sg:tags":[
        "information",
        "alcoholism",
        "treatment"
    ],
    "wof:name":"M E & Assoc",
    "wof:placetype":"venue"
},
  "geometry": {"coordinates":[-121.309846,44.057035],"type":"Point"}
}