{
  "type": "Feature",
  "properties": {
    "addr:full":"1828 22nd Ave Forest Grove OR 97116",
    "addr:housenumber":"1828",
    "addr:postcode":"97116",
    "addr:street":"22Nd Ave",
    "iso:country":"US",
    "sg:address":"1828 22nd Ave",
    "sg:city":"Forest Grove",
    "sg:classifiers":[
        {
            "category":"Manufacturing",
            "subcategory":"Lumber",
            "type":"Manufacturing & Wholesale Goods"
        }
    ],
    "sg:phone":"+1 503 992 7753",
    "sg:postcode":"97116",
    "sg:province":"OR",
    "sg:tags":[
        "logging"
    ],
    "wof:name":"3rd Charm Logging",
    "wof:placetype":"venue"
},
  "geometry": {"coordinates":[-123.114328,45.522166],"type":"Point"}
}