{
  "type": "Feature",
  "properties": {
    "iso:country":"US",
    "sg:address":"215 SE Morrison St",
    "sg:city":"Portland",
    "sg:classifiers":[
        {
            "category":"Retail",
            "subcategory":"Event Space",
            "type":"Services"
        },
        {
            "category":"Shopping",
            "subcategory":"Party Supplies",
            "type":"Retail Goods"
        },
        {
            "category":"Professional",
            "subcategory":"Art Services",
            "type":"Services"
        },
        {
            "category":"Personal",
            "type":"Services"
        }
    ],
    "sg:phone":"+1 503 358 6552",
    "sg:postcode":"97214",
    "sg:province":"OR",
    "sg:tags":[
        "photographer",
        "favors",
        "planning",
        "meeting",
        "rental"
    ],
    "sg:website":"www.pdxphotolounge.com/",
    "wof:name":"PDX Photo Lounge",
    "wof:placetype":"venue"
},
  "geometry": {"coordinates":[-122.66328,45.517597],"type":"Point"}
}