{
  "type": "Feature",
  "properties": {
    "iso:country":"US",
    "sg:address":"2750 Main St",
    "sg:city":"Springfield",
    "sg:classifiers":[
        {
            "category":"Autos & Motor Vehicles",
            "subcategory":"Auto Supplies",
            "type":"Retail Goods"
        }
    ],
    "sg:phone":"+1 541 726 0175",
    "sg:postcode":"97477",
    "sg:province":"OR",
    "wof:name":"Randys Tire Corner Inc",
    "wof:placetype":"venue"
},
  "geometry": {"coordinates":[-122.986814,44.045961],"type":"Point"}
}