{
  "type": "Feature",
  "properties": {
    "addr:full":"4175 E Amazon Dr Eugene OR 97405",
    "addr:housenumber":"4175",
    "addr:postcode":"97405",
    "addr:street":"E Amazon Dr",
    "iso:country":"US",
    "sg:address":"4175 E Amazon Dr",
    "sg:city":"Eugene",
    "sg:classifiers":[
        {
            "category":"Professional",
            "type":"Services"
        }
    ],
    "sg:phone":"+1 541 686 0101",
    "sg:postcode":"97405",
    "sg:province":"OR",
    "sg:tags":[
        "establishment"
    ],
    "wof:name":"Patricia M Kortekaas Pt",
    "wof:placetype":"venue"
},
  "geometry": {"coordinates":[-123.075615,44.00936],"type":"Point"}
}