{
  "type": "Feature",
  "properties": {
    "addr:full":"541 E Arch St Union OR 97883",
    "addr:housenumber":"541",
    "addr:postcode":"97883",
    "addr:street":"E Arch St",
    "iso:country":"US",
    "sg:address":"541 E Arch St",
    "sg:city":"Union",
    "sg:classifiers":[
        {
            "category":"Building & Trades",
            "subcategory":"Construction",
            "type":"Services"
        }
    ],
    "sg:phone":"+1 541 562 5712",
    "sg:postcode":"97883",
    "sg:province":"OR",
    "sg:tags":[
        "general",
        "contractor"
    ],
    "wof:name":"Judy Construction",
    "wof:placetype":"venue"
},
  "geometry": {"coordinates":[-117.857242,45.20921],"type":"Point"}
}