{
  "type": "Feature",
  "properties": {
    "addr:full":"29850 NW Evergreen Rd Hillsboro OR 97124",
    "addr:housenumber":"29850",
    "addr:postcode":"97124",
    "addr:street":"Nw Evergreen Rd",
    "iso:country":"US",
    "sg:address":"29850 NW Evergreen Rd",
    "sg:city":"Hillsboro",
    "sg:classifiers":[
        {
            "category":"Education",
            "subcategory":"Special Training",
            "type":"Public Place"
        },
        {
            "category":"Education",
            "subcategory":"School",
            "type":"Public Place"
        }
    ],
    "sg:phone":"+1 503 844 1400",
    "sg:postcode":"97124",
    "sg:province":"OR",
    "sg:tags":[
        "middle",
        "educational"
    ],
    "wof:name":"Evergreen Middle School",
    "wof:placetype":"venue"
},
  "geometry": {"coordinates":[-122.98515,45.549915],"type":"Point"}
}