{
  "type": "Feature",
  "properties": {
    "iso:country":"US",
    "sg:address":"118 Hogue Dr",
    "sg:city":"Selma",
    "sg:classifiers":[
        {
            "category":"Freight",
            "type":"Transportation"
        }
    ],
    "sg:phone":"+1 541 597 2336",
    "sg:postcode":"97538",
    "sg:province":"OR",
    "sg:tags":[
        "commercial",
        "storage"
    ],
    "wof:name":"Four Acres Mini Storage",
    "wof:placetype":"venue"
},
  "geometry": {"coordinates":[-123.616483,42.278247],"type":"Point"}
}