{
  "type": "Feature",
  "properties": {
    "iso:country":"US",
    "sg:address":"224 NW 1st Ave",
    "sg:city":"Canby",
    "sg:classifiers":[
        {
            "category":"Food & Beverages",
            "subcategory":"Bakery",
            "type":"Retail Goods"
        }
    ],
    "sg:phone":"+1 503 263 7443",
    "sg:postcode":"97013",
    "sg:province":"OR",
    "sg:tags":[
        "doughnut"
    ],
    "wof:name":"Donut Factory",
    "wof:placetype":"venue"
},
  "geometry": {"coordinates":[-122.695083,45.262201],"type":"Point"}
}