{
  "type": "Feature",
  "properties": {
    "addr:full":"7620 NE Killingsworth St Portland OR 97218",
    "addr:housenumber":"7620",
    "addr:postcode":"97218",
    "addr:street":"Ne Killingsworth St",
    "iso:country":"US",
    "sg:address":"7620 NE Killingsworth St",
    "sg:city":"Portland",
    "sg:classifiers":[
        {
            "category":"Retail",
            "subcategory":"Auto Repair",
            "type":"Services"
        }
    ],
    "sg:phone":"+1 503 255 2009",
    "sg:postcode":"97218",
    "sg:province":"OR",
    "sg:tags":[
        "body",
        "automobile",
        "painting"
    ],
    "wof:name":"All In One Auto Body",
    "wof:placetype":"venue"
},
  "geometry": {"coordinates":[-122.57857,45.56259],"type":"Point"}
}