{
  "type": "Feature",
  "properties": {
    "iso:country":"US",
    "sg:address":"8930 SE Stark Street",
    "sg:city":"Portland",
    "sg:classifiers":[
        {
            "category":"Autos & Motor Vehicles",
            "subcategory":"Motorcycle Sales",
            "type":"Retail Goods"
        }
    ],
    "sg:phone":"+1 503 257 7047",
    "sg:postcode":"97216",
    "sg:province":"OR",
    "wof:name":"Rose City Motorcycle Sales & Service",
    "wof:placetype":"venue"
},
  "geometry": {"coordinates":[-122.571564,45.518949],"type":"Point"}
}