{
  "type": "Feature",
  "properties": {
    "addr:full":"277 Greenwood St Junction City OR 97448",
    "addr:housenumber":"277",
    "addr:postcode":"97448",
    "addr:street":"Greenwood St",
    "iso:country":"US",
    "sg:address":"277 Greenwood St",
    "sg:city":"Junction City",
    "sg:classifiers":[
        {
            "category":"Health Services",
            "subcategory":"Doctor",
            "type":"Services"
        }
    ],
    "sg:phone":"+1 541 998 6755",
    "sg:postcode":"97448",
    "sg:province":"OR",
    "sg:tags":[
        "medical"
    ],
    "wof:name":"Junction City Phy Thrp",
    "wof:placetype":"venue"
},
  "geometry": {"coordinates":[-123.202462,44.215968],"type":"Point"}
}