{
  "type": "Feature",
  "properties": {
    "addr:full":"7700 NE Ambassador Place Portland OR 97220",
    "addr:housenumber":"7700",
    "addr:postcode":"97220",
    "addr:street":"Ne Ambassador Place",
    "iso:country":"US",
    "sg:address":"7700 NE Ambassador Place",
    "sg:city":"Portland",
    "sg:classifiers":[
        {
            "category":"Cinema",
            "subcategory":"Movie Rental",
            "type":"Entertainment"
        }
    ],
    "sg:phone":"+1 503 284 7581",
    "sg:postcode":"97220",
    "sg:province":"OR",
    "sg:tags":[
        "picture",
        "exchange",
        "motion",
        "game",
        "video",
        "distributor",
        "film"
    ],
    "sg:website":"www.rentrak.com",
    "wof:name":"Rentrak Corporation",
    "wof:placetype":"venue"
},
  "geometry": {"coordinates":[-122.570954,45.57785],"type":"Point"}
}