{
  "type": "Feature",
  "properties": {
    "iso:country":"US",
    "sg:address":"1175 Kentucky Ave",
    "sg:city":"Coos Bay",
    "sg:classifiers":[
        {
            "category":"Communications",
            "subcategory":"Film & Video Production",
            "type":"Services"
        }
    ],
    "sg:phone":"+1 541 888 2068",
    "sg:postcode":"97420",
    "sg:province":"OR",
    "sg:tags":[
        "motion"
    ],
    "wof:name":"Media Voice Productions",
    "wof:placetype":"venue"
},
  "geometry": {"coordinates":[-124.266616,43.381376],"type":"Point"}
}