{
  "type": "Feature",
  "properties": {
    "addr:full":"55 SW Ash St Portland OR 97204",
    "addr:housenumber":"55",
    "addr:postcode":"97204",
    "addr:street":"Sw Ash St",
    "iso:country":"US",
    "sg:address":"55 SW Ash St",
    "sg:city":"Portland",
    "sg:classifiers":[
        {
            "category":"Building & Trades",
            "subcategory":"Construction",
            "type":"Services"
        }
    ],
    "sg:phone":"+1 503 224 9643",
    "sg:postcode":"97204",
    "sg:province":"OR",
    "sg:tags":[
        "contractor"
    ],
    "wof:name":"Skyward Construction",
    "wof:placetype":"venue"
},
  "geometry": {"coordinates":[-122.670964,45.521764],"type":"Point"}
}