{
  "type": "Feature",
  "properties": {
    "iso:country":"US",
    "sg:address":"2691 8th St",
    "sg:city":"Baker City",
    "sg:classifiers":[
        {
            "category":"Retail",
            "subcategory":"Auto Repair",
            "type":"Services"
        }
    ],
    "sg:phone":"+1 541 523 7505",
    "sg:postcode":"97814",
    "sg:province":"OR",
    "sg:tags":[
        "repairing",
        "automobile",
        "radiator",
        "automotive"
    ],
    "wof:name":"B & S Radiator Works",
    "wof:placetype":"venue"
},
  "geometry": {"coordinates":[-117.838858,44.782704],"type":"Point"}
}