{
  "type": "Feature",
  "properties": {
    "iso:country":"US",
    "sg:address":"22001 S Beavercreek Rd",
    "sg:city":"Beavercreek",
    "sg:classifiers":[
        {
            "category":"Food & Beverages",
            "subcategory":"Groceries & Convenience Stores",
            "type":"Retail Goods"
        }
    ],
    "sg:phone":"+1 503 632 3131",
    "sg:postcode":"97004",
    "sg:province":"OR",
    "sg:tags":[
        "liquor",
        "grocer"
    ],
    "wof:name":"Beavercreek Grocery",
    "wof:placetype":"venue"
},
  "geometry": {"coordinates":[-122.535301,45.28791],"type":"Point"}
}