{
  "type": "Feature",
  "properties": {
    "addr:full":"1703 NE Alberta St Portland OR 97211",
    "addr:housenumber":"1703",
    "addr:postcode":"97211",
    "addr:street":"Ne Alberta St",
    "iso:country":"US",
    "sg:address":"1703 NE Alberta St",
    "sg:city":"Portland",
    "sg:classifiers":[
        {
            "category":"Shopping",
            "subcategory":"Clothing, Apparel, & Fashions",
            "type":"Retail Goods"
        }
    ],
    "sg:phone":"+1 503 282 0228",
    "sg:postcode":"97211",
    "sg:province":"OR",
    "sg:tags":[
        "boutique",
        "shoe",
        "store"
    ],
    "wof:name":"Unique Ly Yours",
    "wof:placetype":"venue"
},
  "geometry": {"coordinates":[-122.646798,45.559154],"type":"Point"}
}