{
  "type": "Feature",
  "properties": {
    "addr:full":"565 W Arlington St Gladstone OR 97027",
    "addr:housenumber":"565",
    "addr:postcode":"97027",
    "addr:street":"W Arlington St",
    "iso:country":"US",
    "sg:address":"565 W Arlington St",
    "sg:city":"Gladstone",
    "sg:classifiers":[
        {
            "category":"Shopping",
            "subcategory":"Used Merchandise",
            "type":"Retail Goods"
        }
    ],
    "sg:phone":"+1 503 723 0029",
    "sg:postcode":"97027",
    "sg:province":"OR",
    "sg:tags":[
        "shop",
        "consignment"
    ],
    "wof:name":"Online Consignments Ctr",
    "wof:placetype":"venue"
},
  "geometry": {"coordinates":[-122.600532,45.376036],"type":"Point"}
}