{
  "type": "Feature",
  "properties": {
    "iso:country":"US",
    "sg:address":"8435 SW 74th Ave",
    "sg:city":"Portland",
    "sg:classifiers":[
        {
            "category":"Manufacturing",
            "subcategory":"Tools & Machinery",
            "type":"Manufacturing & Wholesale Goods"
        }
    ],
    "sg:phone":"+1 503 246 1320",
    "sg:postcode":"97223",
    "sg:province":"OR",
    "sg:tags":[
        "electrical",
        "mfg"
    ],
    "wof:name":"All West Door Wather Stripping",
    "wof:placetype":"venue"
},
  "geometry": {"coordinates":[-122.75284600000001,45.458365],"type":"Point"}
}