{
  "type": "Feature",
  "properties": {
    "iso:country":"US",
    "sg:address":"1703 Jasper St",
    "sg:city":"Cove",
    "sg:classifiers":[
        {
            "category":"Freight",
            "type":"Transportation"
        }
    ],
    "sg:phone":"+1 541 568 4652",
    "sg:postcode":"97824",
    "sg:province":"OR",
    "sg:tags":[
        "operator",
        "trucking"
    ],
    "wof:name":"Johnny K Denning",
    "wof:placetype":"venue"
},
  "geometry": {"coordinates":[-117.808393,45.305004],"type":"Point"}
}