{
  "type": "Feature",
  "properties": {
    "addr:full":"31332 Camas Swale Rd Creswell OR 97426",
    "addr:postcode":"31332;97426",
    "addr:street":"Swale Rd",
    "iso:country":"US",
    "sg:address":"31332 Camas Swale Rd",
    "sg:city":"Creswell",
    "sg:classifiers":[
        {
            "category":"Wholesale",
            "subcategory":"Machinery & Supplies",
            "type":"Manufacturing & Wholesale Goods"
        }
    ],
    "sg:phone":"+1 541 895 5135",
    "sg:postcode":"97426",
    "sg:province":"OR",
    "sg:tags":[
        "rebuilding",
        "aircraft"
    ],
    "wof:name":"Replica Fighters Assn",
    "wof:placetype":"venue"
},
  "geometry": {"coordinates":[-123.110541,43.918961],"type":"Point"}
}