{
  "type": "Feature",
  "properties": {
    "addr:full":"15943 SW Hall Blvd Portland OR 97224",
    "addr:housenumber":"15943",
    "addr:postcode":"97224",
    "addr:street":"Sw Hall Blvd",
    "iso:country":"US",
    "sg:address":"15943 SW Hall Blvd",
    "sg:city":"Portland",
    "sg:classifiers":[
        {
            "category":"Sports & Exercise",
            "subcategory":"Gym",
            "type":"Entertainment"
        }
    ],
    "sg:phone":"+1 503 620 0284",
    "sg:postcode":"97224",
    "sg:province":"OR",
    "sg:tags":[
        "fitness",
        "physical",
        "facility"
    ],
    "wof:name":"Fit 2b Her",
    "wof:placetype":"venue"
},
  "geometry": {"coordinates":[-122.764606,45.40493],"type":"Point"}
}