{
  "type": "Feature",
  "properties": {
    "iso:country":"US",
    "sg:address":"4949 SE 26th Ave",
    "sg:city":"Portland",
    "sg:classifiers":[
        {
            "category":"Organizations",
            "subcategory":"Labor Organization",
            "type":"Services"
        }
    ],
    "sg:phone":"+1 503 295 2828",
    "sg:postcode":"97202",
    "sg:province":"OR",
    "wof:name":"Stagehands Local 28 Iatse",
    "wof:placetype":"venue"
},
  "geometry": {"coordinates":[-122.63952999999999,45.487329],"type":"Point"}
}