{
  "type": "Feature",
  "properties": {
    "addr:full":"40985 State Hwy 62 Prospect OR 97536",
    "addr:housenumber":"40985",
    "addr:postcode":"97536",
    "addr:street":"State Hwy 62",
    "iso:country":"US",
    "sg:address":"40985 State Hwy 62",
    "sg:city":"Prospect",
    "sg:classifiers":[
        {
            "category":"Building & Trades",
            "subcategory":"Equipment Rental",
            "type":"Services"
        }
    ],
    "sg:phone":"+1 541 560 3793",
    "sg:postcode":"97536",
    "sg:province":"OR",
    "sg:tags":[
        "toilet"
    ],
    "wof:name":"Steward's Porta Potties",
    "wof:placetype":"venue"
},
  "geometry": {"coordinates":[-122.57161000000001,42.714185],"type":"Point"}
}