{
  "type": "Feature",
  "properties": {
    "iso:country":"US",
    "sg:address":"1111 Chetco Ave",
    "sg:city":"Brookings",
    "sg:classifiers":[
        {
            "category":"Home & Garden",
            "subcategory":"Hardware",
            "type":"Retail Goods"
        }
    ],
    "sg:phone":"+1 541 412 1145",
    "sg:postcode":"97415",
    "sg:province":"OR",
    "wof:name":"Hennick's Do It Best Hardware",
    "wof:placetype":"venue"
},
  "geometry": {"coordinates":[-124.292362,42.055478],"type":"Point"}
}