{
  "type": "Feature",
  "properties": {
    "iso:country":"US",
    "sg:address":"7755 US Hwy 101 N",
    "sg:city":"Gleneden Beach",
    "sg:classifiers":[
        {
            "category":"Real Estate",
            "subcategory":"Real Estate Agent",
            "type":"Services"
        }
    ],
    "sg:phone":"+1 541 764 3323",
    "sg:postcode":"97376",
    "sg:province":"OR",
    "wof:name":"Windemere Distinctive Coastal",
    "wof:placetype":"venue"
},
  "geometry": {"coordinates":[-124.081036,44.482908],"type":"Point"}
}