{
  "type": "Feature",
  "properties": {
    "addr:full":"5044 Cherry Heights Rd The Dalles OR 97058",
    "addr:housenumber":"5044",
    "addr:postcode":"97058",
    "addr:street":"Cherry Heights Rd",
    "iso:country":"US",
    "sg:address":"5044 Cherry Heights Rd",
    "sg:city":"The Dalles",
    "sg:classifiers":[
        {
            "category":"Building & Trades",
            "subcategory":"Construction",
            "type":"Services"
        }
    ],
    "sg:phone":"+1 541 296 4737",
    "sg:postcode":"97058",
    "sg:province":"OR",
    "sg:tags":[
        "excavation",
        "contractor"
    ],
    "wof:name":"Donald Ellett Excavating",
    "wof:placetype":"venue"
},
  "geometry": {"coordinates":[-121.24334899999999,45.603292],"type":"Point"}
}