{
  "type": "Feature",
  "properties": {
    "addr:full":"22565 Rickard Rd Bend OR 97702",
    "addr:postcode":"22565;97702",
    "addr:street":"Rickard Rd",
    "iso:country":"US",
    "sg:address":"22565 Rickard Rd",
    "sg:city":"Bend",
    "sg:classifiers":[
        {
            "category":"Home & Garden",
            "subcategory":"Garden Supply",
            "type":"Retail Goods"
        },
        {
            "category":"Manufacturing",
            "subcategory":"Paper Products",
            "type":"Manufacturing & Wholesale Goods"
        },
        {
            "category":"Farming",
            "subcategory":"Nursery",
            "type":"Manufacturing & Wholesale Goods"
        }
    ],
    "sg:phone":"+1 541 388 4802",
    "sg:postcode":"97702",
    "sg:province":"OR",
    "sg:tags":[
        "equipment",
        "bamboo",
        "seed",
        "growers'",
        "bulb"
    ],
    "wof:name":"Gary P Grimm",
    "wof:placetype":"venue"
},
  "geometry": {"coordinates":[-121.194756,44.007821],"type":"Point"}
}