{
  "type": "Feature",
  "properties": {
    "addr:full":"756 NE Lombard St Portland OR 97211",
    "addr:housenumber":"756",
    "addr:postcode":"97211",
    "addr:street":"Ne Lombard St",
    "iso:country":"US",
    "sg:address":"756 NE Lombard St",
    "sg:city":"Portland",
    "sg:classifiers":[
        {
            "category":"Shopping",
            "type":"Retail Goods"
        }
    ],
    "sg:phone":"+1 503 574 4506",
    "sg:postcode":"97211",
    "sg:province":"OR",
    "sg:tags":[
        "merchandise"
    ],
    "wof:name":"Tonnesan Investment Group",
    "wof:placetype":"venue"
},
  "geometry": {"coordinates":[-122.65818,45.577139],"type":"Point"}
}