{
  "type": "Feature",
  "properties": {
    "addr:full":"1524 NE Hancock St Portland OR 97212",
    "addr:housenumber":"1524",
    "addr:postcode":"97212",
    "addr:street":"Ne Hancock St",
    "iso:country":"US",
    "sg:address":"1524 NE Hancock St",
    "sg:city":"Portland",
    "sg:classifiers":[
        {
            "category":"Shopping",
            "subcategory":"Clothing, Apparel, & Fashions",
            "type":"Retail Goods"
        }
    ],
    "sg:phone":"+1 503 282 1037",
    "sg:postcode":"97212",
    "sg:province":"OR",
    "wof:name":"Maximum Output",
    "wof:placetype":"venue"
},
  "geometry": {"coordinates":[-122.64963400000001,45.536386],"type":"Point"}
}