{
  "type": "Feature",
  "properties": {
    "iso:country":"US",
    "sg:address":"16883 SE Fragrance Ave",
    "sg:city":"Portland",
    "sg:classifiers":[
        {
            "category":"Organizations",
            "subcategory":"Community Association",
            "type":"Services"
        }
    ],
    "sg:phone":"+1 503 557 1712",
    "sg:postcode":"97267",
    "sg:province":"OR",
    "wof:name":"Rocky Mountain Elk Foundation",
    "wof:placetype":"venue"
},
  "geometry": {"coordinates":[-122.57852,45.400159],"type":"Point"}
}