{
  "type": "Feature",
  "properties": {
    "iso:country":"US",
    "sg:address":"651 S Main St",
    "sg:city":"Lebanon",
    "sg:classifiers":[
        {
            "category":"Shopping",
            "subcategory":"Bicycles & Sporting Goods",
            "type":"Retail Goods"
        }
    ],
    "sg:phone":"+1 541 258 8485",
    "sg:postcode":"97355",
    "sg:province":"OR",
    "sg:tags":[
        "equipment",
        "skateboard"
    ],
    "wof:name":"Main Street Skateboards",
    "wof:placetype":"venue"
},
  "geometry": {"coordinates":[-122.906987,44.539581],"type":"Point"}
}