{
  "type": "Feature",
  "properties": {
    "addr:full":"7915 SW 19th Ave Portland OR 97219",
    "addr:housenumber":"7915",
    "addr:postcode":"97219",
    "addr:street":"Sw 19Th Ave",
    "iso:country":"US",
    "sg:address":"7915 SW 19th Ave",
    "sg:city":"Portland",
    "sg:classifiers":[
        {
            "category":"Organizations",
            "subcategory":"Membership Organization",
            "type":"Services"
        }
    ],
    "sg:phone":"+1 503 245 3328",
    "sg:postcode":"97219",
    "sg:province":"OR",
    "sg:tags":[
        "athletic"
    ],
    "wof:name":"Portland Baseball Umpires Assn",
    "wof:placetype":"venue"
},
  "geometry": {"coordinates":[-122.69749,45.467812],"type":"Point"}
}