{
  "type": "Feature",
  "properties": {
    "iso:country":"US",
    "sg:address":"1245 NW Lovejoy",
    "sg:city":"Portland",
    "sg:classifiers":[
        {
            "category":"Banks & Credit Unions",
            "subcategory":"Bank",
            "type":"Services"
        }
    ],
    "sg:phone":"+1 503 484 1802",
    "sg:postcode":"97209",
    "sg:province":"OR",
    "sg:website":"www.bankofamerica.com",
    "wof:name":"Bank of America",
    "wof:placetype":"venue"
},
  "geometry": {"coordinates":[-122.68385499999999,45.530069],"type":"Point"}
}