{
  "type": "Feature",
  "properties": {
    "addr:full":"3315 SE 15th Ave Portland OR 97202",
    "addr:housenumber":"3315",
    "addr:postcode":"97202",
    "addr:street":"Se 15Th Ave",
    "iso:country":"US",
    "sg:address":"3315 SE 15th Ave",
    "sg:city":"Portland",
    "sg:classifiers":[
        {
            "category":"Building & Trades",
            "subcategory":"Cleaning & Sanitation",
            "type":"Services"
        }
    ],
    "sg:phone":"+1 503 235 1991",
    "sg:postcode":"97202",
    "sg:province":"OR",
    "sg:tags":[
        "house"
    ],
    "wof:name":"Fresh Start Cleaning Svc",
    "wof:placetype":"venue"
},
  "geometry": {"coordinates":[-122.650233,45.49921],"type":"Point"}
}