{
  "type": "Feature",
  "properties": {
    "addr:full":"73256 SE 56th St Pendleton OR 97801",
    "addr:postcode":"73256;97801",
    "addr:street":"Se 56Th St",
    "iso:country":"US",
    "sg:address":"73256 SE 56th St",
    "sg:city":"Pendleton",
    "sg:classifiers":[
        {
            "category":"Building & Trades",
            "subcategory":"Construction",
            "type":"Services"
        }
    ],
    "sg:phone":"+1 541 276 0680",
    "sg:postcode":"97801",
    "sg:province":"OR",
    "sg:tags":[
        "special",
        "contractor"
    ],
    "wof:name":"Chris Roop",
    "wof:placetype":"venue"
},
  "geometry": {"coordinates":[-118.725561,45.666671],"type":"Point"}
}