{
  "type": "Feature",
  "properties": {
    "addr:full":"3005 SE Carlton St Portland OR 97202",
    "addr:housenumber":"3005",
    "addr:postcode":"97202",
    "addr:street":"Se Carlton St",
    "iso:country":"US",
    "sg:address":"3005 SE Carlton St",
    "sg:city":"Portland",
    "sg:classifiers":[
        {
            "category":"Professional",
            "subcategory":"Lawyer & Legal Services",
            "type":"Services"
        }
    ],
    "sg:phone":"+1 503 223 7884",
    "sg:postcode":"97202",
    "sg:province":"OR",
    "sg:tags":[
        "divorce",
        "law",
        "family"
    ],
    "wof:name":"Dillon Helen C Atty",
    "wof:placetype":"venue"
},
  "geometry": {"coordinates":[-122.632268,45.477661],"type":"Point"}
}