{
  "type": "Feature",
  "properties": {
    "iso:country":"US",
    "sg:address":"3200 NE Hogan Dr",
    "sg:city":"Gresham",
    "sg:classifiers":[
        {
            "category":"Social Services",
            "subcategory":"Child Care",
            "type":"Services"
        }
    ],
    "sg:phone":"+1 503 661 2974",
    "sg:postcode":"97030",
    "sg:province":"OR",
    "sg:tags":[
        "elementary",
        "school"
    ],
    "wof:name":"Children's World Learning Centers",
    "wof:placetype":"venue"
},
  "geometry": {"coordinates":[-122.412003,45.5186],"type":"Point"}
}