{
  "type": "Feature",
  "properties": {
    "iso:country":"US",
    "sg:address":"Broadway Toyota 20 NE Hancock St",
    "sg:city":"Portland",
    "sg:classifiers":[
        {
            "category":"Deli",
            "type":"Food & Drink"
        }
    ],
    "sg:phone":"+1 503 546 8231",
    "sg:postcode":"97232",
    "sg:province":"OR",
    "wof:name":"Only Way Cafe",
    "wof:placetype":"venue"
},
  "geometry": {"coordinates":[-122.666206,45.535958],"type":"Point"}
}