{
  "type": "Feature",
  "properties": {
    "addr:full":"34949 Santiam Hwy Lebanon OR 97355",
    "addr:postcode":"34949;97355",
    "addr:street":"Santiam Hwy",
    "iso:country":"US",
    "sg:address":"34949 Santiam Hwy",
    "sg:city":"Lebanon",
    "sg:classifiers":[
        {
            "category":"Freight",
            "type":"Transportation"
        }
    ],
    "sg:phone":"+1 541 258 2988",
    "sg:postcode":"97355",
    "sg:province":"OR",
    "sg:tags":[
        "hauling",
        "trucking"
    ],
    "wof:name":"Antrim's Nursery & Farms",
    "wof:placetype":"venue"
},
  "geometry": {"coordinates":[-122.92635900000001,44.588899],"type":"Point"}
}