{
  "type": "Feature",
  "properties": {
    "addr:full":"802 16th St La Grande OR 97850",
    "addr:housenumber":"802",
    "addr:postcode":"97850",
    "addr:street":"16Th St;Grande",
    "iso:country":"US",
    "sg:address":"802 16th St",
    "sg:city":"La Grande",
    "sg:classifiers":[
        {
            "category":"Shopping",
            "subcategory":"Beauty & Cosmetics",
            "type":"Retail Goods"
        }
    ],
    "sg:phone":"+1 541 963 3753",
    "sg:postcode":"97850",
    "sg:province":"OR",
    "sg:tags":[
        "merchandise"
    ],
    "wof:name":"Comfort  Debra Independent Sal",
    "wof:placetype":"venue"
},
  "geometry": {"coordinates":[-118.081553,45.318983],"type":"Point"}
}