{
  "type": "Feature",
  "properties": {
    "iso:country":"US",
    "sg:address":"4120 Washburn Way",
    "sg:city":"Klamath Falls",
    "sg:classifiers":[
        {
            "category":"Shopping",
            "type":"Retail Goods"
        }
    ],
    "sg:phone":"+1 541 273 1526",
    "sg:postcode":"97603",
    "sg:province":"OR",
    "sg:tags":[
        "seasonal"
    ],
    "wof:name":"Pinecones Inc",
    "wof:placetype":"venue"
},
  "geometry": {"coordinates":[-121.75700500000001,42.188956],"type":"Point"}
}