{
  "type": "Feature",
  "properties": {
    "iso:country":"US",
    "sg:address":"41 Stewart Ave",
    "sg:city":"Medford",
    "sg:classifiers":[
        {
            "category":"Autos & Motor Vehicles",
            "subcategory":"Auto Supplies",
            "type":"Retail Goods"
        }
    ],
    "sg:phone":"+1 541 776 5202",
    "sg:postcode":"97501",
    "sg:province":"OR",
    "sg:tags":[
        "tire"
    ],
    "wof:name":"Big O Tires",
    "wof:placetype":"venue"
},
  "geometry": {"coordinates":[-122.861745,42.312811],"type":"Point"}
}