{
  "type": "Feature",
  "properties": {
    "iso:country":"US",
    "sg:address":"1800 Prairie Rd",
    "sg:city":"Eugene",
    "sg:classifiers":[
        {
            "category":"Professional",
            "subcategory":"Advertising",
            "type":"Services"
        }
    ],
    "sg:phone":"+1 541 689 1899",
    "sg:postcode":"97402",
    "sg:province":"OR",
    "sg:tags":[
        "designer",
        "display",
        "producer"
    ],
    "wof:name":"Pacific Display Corp",
    "wof:placetype":"venue"
},
  "geometry": {"coordinates":[-123.159769,44.094476],"type":"Point"}
}