{
  "type": "Feature",
  "properties": {
    "iso:country":"US",
    "sg:address":"1715 NE 19th St",
    "sg:city":"Lincoln City",
    "sg:classifiers":[
        {
            "category":"Organizations",
            "subcategory":"Religious Organization",
            "type":"Services"
        }
    ],
    "sg:phone":"+1 541 994 2043",
    "sg:postcode":"97367",
    "sg:province":"OR",
    "wof:name":"Assembly Of God Church",
    "wof:placetype":"venue"
},
  "geometry": {"coordinates":[-124.009978,44.978621],"type":"Point"}
}