{
  "type": "Feature",
  "properties": {
    "iso:country":"US",
    "sg:address":"2161 NE Broadway Street",
    "sg:city":"Portland",
    "sg:classifiers":[
        {
            "category":"Professional",
            "subcategory":"Lawyer & Legal Services",
            "type":"Services"
        }
    ],
    "sg:phone":"+1 503 287 0870",
    "sg:postcode":"97232",
    "sg:province":"OR",
    "wof:name":"Grafe Oliveros & Associates",
    "wof:placetype":"venue"
},
  "geometry": {"coordinates":[-122.64364500000001,45.535133],"type":"Point"}
}