{
  "type": "Feature",
  "properties": {
    "iso:country":"US",
    "sg:address":"979 Young St",
    "sg:city":"Woodburn",
    "sg:classifiers":[
        {
            "category":"Health Services",
            "subcategory":"Chiropractor",
            "type":"Services"
        }
    ],
    "sg:phone":"+1 503 981 1254",
    "sg:postcode":"97071",
    "sg:province":"OR",
    "wof:name":"Roger W Popp Chiropractic",
    "wof:placetype":"venue"
},
  "geometry": {"coordinates":[-122.847066,45.138375],"type":"Point"}
}