{
  "type": "Feature",
  "properties": {
    "iso:country":"US",
    "sg:address":"17422 SW Rock Creek Rd",
    "sg:city":"Sheridan",
    "sg:classifiers":[
        {
            "category":"Health Services",
            "subcategory":"Doctor",
            "type":"Services"
        },
        {
            "category":"Health Services",
            "subcategory":"Dentist",
            "type":"Services"
        }
    ],
    "sg:phone":"+1 503 843 2966",
    "sg:postcode":"97378",
    "sg:province":"OR",
    "sg:tags":[
        "dentists-oral",
        "physician",
        "maxillofacial",
        "surgeons",
        "surgery",
        "oral"
    ],
    "wof:name":"Gary E Brooks Dmd",
    "wof:placetype":"venue"
},
  "geometry": {"coordinates":[-123.45478199999999,45.134972],"type":"Point"}
}