{
  "type": "Feature",
  "properties": {
    "iso:country":"US",
    "sg:address":"21771 Obsidian Ave",
    "sg:city":"Bend",
    "sg:classifiers":[
        {
            "category":"Building & Trades",
            "subcategory":"Cleaning & Sanitation",
            "type":"Services"
        }
    ],
    "sg:phone":"+1 541 389 8603",
    "sg:postcode":"97702",
    "sg:province":"OR",
    "sg:tags":[
        "janitor"
    ],
    "wof:name":"Alpine Building Maintenance",
    "wof:placetype":"venue"
},
  "geometry": {"coordinates":[-121.231354,44.04166],"type":"Point"}
}