{
  "type": "Feature",
  "properties": {
    "iso:country":"US",
    "sg:address":"2965 NE Sandy Boulevard",
    "sg:city":"Portland",
    "sg:classifiers":[
        {
            "category":"Shopping",
            "subcategory":"Pets & Pet Supplies",
            "type":"Retail Goods"
        }
    ],
    "sg:phone":"+1 503 230 9596",
    "sg:postcode":"97232",
    "sg:province":"OR",
    "sg:tags":[
        "training"
    ],
    "wof:name":"Townhouse Pet Care Center",
    "wof:placetype":"venue"
},
  "geometry": {"coordinates":[-122.63464999999999,45.530241],"type":"Point"}
}