{
  "type": "Feature",
  "properties": {
    "iso:country":"US",
    "sg:address":"37640 Crabtree Dr",
    "sg:city":"Crabtree",
    "sg:classifiers":[
        {
            "category":"Government",
            "subcategory":"Post Office",
            "type":"Public Place"
        }
    ],
    "sg:phone":"+1 541 926 0783",
    "sg:postcode":"97374",
    "sg:province":"OR",
    "wof:name":"US Post Office",
    "wof:placetype":"venue"
},
  "geometry": {"coordinates":[-122.89855,44.635442],"type":"Point"}
}