{
  "type": "Feature",
  "properties": {
    "iso:country":"US",
    "sg:address":"720 W Francis St",
    "sg:city":"Roseburg",
    "sg:classifiers":[
        {
            "category":"Shopping",
            "subcategory":"Used Merchandise",
            "type":"Retail Goods"
        }
    ],
    "sg:phone":"+1 541 440 9215",
    "sg:postcode":"97470",
    "sg:province":"OR",
    "sg:tags":[
        "antique"
    ],
    "wof:name":"Anniversary Antiques",
    "wof:placetype":"venue"
},
  "geometry": {"coordinates":[-123.377045,43.21325],"type":"Point"}
}