{
  "type": "Feature",
  "properties": {
    "iso:country":"US",
    "sg:address":"2208 NW Birdsdale Ave",
    "sg:city":"Gresham",
    "sg:classifiers":[
        {
            "category":"Wholesale",
            "subcategory":"Non-durable Goods",
            "type":"Manufacturing & Wholesale Goods"
        }
    ],
    "sg:phone":"+1 503 667 9081",
    "sg:postcode":"97030",
    "sg:province":"OR",
    "wof:name":"Errico & Errico",
    "wof:placetype":"venue"
},
  "geometry": {"coordinates":[-122.454989,45.512555],"type":"Point"}
}