{
  "type": "Feature",
  "properties": {
    "addr:full":"3075 SW 234th Ave Ste 206 Hillsboro OR 97123",
    "addr:housenumber":"3075",
    "addr:postcode":"97123",
    "addr:street":"Sw 234Th Ave Ste 206",
    "iso:country":"US",
    "sg:address":"3075 SW 234th Ave Ste 206",
    "sg:city":"Hillsboro",
    "sg:classifiers":[
        {
            "category":"Building & Trades",
            "subcategory":"Cleaning & Sanitation",
            "type":"Services"
        },
        {
            "category":"Organizations",
            "subcategory":"Professional Association",
            "type":"Services"
        }
    ],
    "sg:phone":"+1 503 642 9672",
    "sg:postcode":"97123",
    "sg:province":"OR",
    "sg:tags":[
        "commercial",
        "industrial",
        "washing",
        "steam",
        "power"
    ],
    "wof:name":"American Pressure Washing Inc",
    "wof:placetype":"venue"
},
  "geometry": {"coordinates":[-122.91786999999999,45.496832],"type":"Point"}
}