{
  "type": "Feature",
  "properties": {
    "iso:country":"US",
    "sg:address":"39600 SE Allgeier Rd",
    "sg:city":"Sandy",
    "sg:classifiers":[
        {
            "category":"Building & Trades",
            "subcategory":"Construction",
            "type":"Services"
        }
    ],
    "sg:phone":"+1 503 668 5752",
    "sg:postcode":"97055",
    "sg:province":"OR",
    "sg:tags":[
        "steel",
        "erection",
        "structural"
    ],
    "wof:name":"A and E Metal Fabrication Inc",
    "wof:placetype":"venue"
},
  "geometry": {"coordinates":[-122.257297,45.360416],"type":"Point"}
}