{
  "type": "Feature",
  "properties": {
    "iso:country":"US",
    "sg:address":"1138 Cinnamon Ave",
    "sg:city":"Eugene",
    "sg:classifiers":[
        {
            "category":"Banks & Credit Unions",
            "subcategory":"Financial Services",
            "type":"Services"
        }
    ],
    "sg:phone":"+1 541 461 2182",
    "sg:postcode":"97404",
    "sg:province":"OR",
    "sg:tags":[
        "investor"
    ],
    "wof:name":"H&W Investments LLC",
    "wof:placetype":"venue"
},
  "geometry": {"coordinates":[-123.15418,44.108477],"type":"Point"}
}