{
  "type": "Feature",
  "properties": {
    "iso:country":"US",
    "sg:address":"22141 NW Imbrie Dr",
    "sg:city":"Hillsboro",
    "sg:classifiers":[
        {
            "category":"Personal",
            "subcategory":"Nail Salon",
            "type":"Services"
        }
    ],
    "sg:phone":"+1 503 693 7807",
    "sg:postcode":"97124",
    "sg:province":"OR",
    "wof:name":"Gorgeous Nails",
    "wof:placetype":"venue"
},
  "geometry": {"coordinates":[-122.905675,45.550085],"type":"Point"}
}