{
  "type": "Feature",
  "properties": {
    "iso:country":"US",
    "sg:address":"12042 SE Sunnyside Rd #415",
    "sg:city":"Clackamas",
    "sg:classifiers":[
        {
            "category":"Health Services",
            "subcategory":"Clinic",
            "type":"Services"
        }
    ],
    "sg:phone":"+1 503 762 2842",
    "sg:postcode":"97015",
    "sg:province":"OR",
    "sg:tags":[
        "medical"
    ],
    "sg:website":"pacificmedicalimaging.com",
    "wof:name":"Pacific Medical Imaging",
    "wof:placetype":"venue"
},
  "geometry": {"coordinates":[-122.539046,45.429265],"type":"Point"}
}