{
  "type": "Feature",
  "properties": {
    "iso:country":"US",
    "sg:address":"3050 SE 61st Ct",
    "sg:city":"Hillsboro",
    "sg:classifiers":[
        {
            "category":"Building & Trades",
            "subcategory":"Construction",
            "type":"Services"
        },
        {
            "category":"Manufacturing",
            "subcategory":"Tools & Machinery",
            "type":"Manufacturing & Wholesale Goods"
        }
    ],
    "sg:phone":"+1 503 649 2033",
    "sg:postcode":"97123",
    "sg:province":"OR",
    "sg:tags":[
        "plate",
        "industrial",
        "mfg",
        "work",
        "metal",
        "fabricated",
        "fabricator"
    ],
    "wof:name":"Summit Manufacturing Inc",
    "wof:placetype":"venue"
},
  "geometry": {"coordinates":[-122.919967,45.496825],"type":"Point"}
}