{
  "type": "Feature",
  "properties": {
    "addr:full":"10288 SE 43rd Ave Portland OR 97222",
    "addr:housenumber":"10288",
    "addr:postcode":"97222",
    "addr:street":"Se 43Rd Ave",
    "iso:country":"US",
    "sg:address":"10288 SE 43rd Ave",
    "sg:city":"Portland",
    "sg:classifiers":[
        {
            "category":"Building & Trades",
            "subcategory":"Construction",
            "type":"Services"
        }
    ],
    "sg:phone":"+1 503 786 2999",
    "sg:postcode":"97222",
    "sg:province":"OR",
    "sg:tags":[
        "hanging",
        "contractor"
    ],
    "wof:name":"Gods Promise Christn Daycare",
    "wof:placetype":"venue"
},
  "geometry": {"coordinates":[-122.61834899999999,45.448604],"type":"Point"}
}