{
  "type": "Feature",
  "properties": {
    "iso:country":"US",
    "sg:address":"9415 SE Stark St",
    "sg:city":"Portland",
    "sg:classifiers":[
        {
            "category":"Banks & Credit Unions",
            "subcategory":"Bank",
            "type":"Services"
        }
    ],
    "sg:phone":"+1 503 595 1313",
    "sg:postcode":"97216",
    "sg:province":"OR",
    "sg:website":"www.mbankonline.com",
    "wof:name":"M Bank",
    "wof:placetype":"venue"
},
  "geometry": {"coordinates":[-122.56616699999999,45.519127],"type":"Point"}
}