{
  "type": "Feature",
  "properties": {
    "addr:full":"9037 SW Burnham St Portland OR 97223",
    "addr:housenumber":"9037",
    "addr:postcode":"97223",
    "addr:street":"Sw Burnham St",
    "iso:country":"US",
    "sg:address":"9037 SW Burnham St",
    "sg:city":"Portland",
    "sg:classifiers":[
        {
            "category":"Professional",
            "type":"Services"
        }
    ],
    "sg:phone":"+1 503 620 9020",
    "sg:postcode":"97223",
    "sg:province":"OR",
    "sg:tags":[
        "caterer"
    ],
    "sg:website":"www.cateringbydeangelos.com",
    "wof:name":"DeAngelo's Catering & Events",
    "wof:placetype":"venue"
},
  "geometry": {"coordinates":[-122.768815,45.428844],"type":"Point"}
}