{
  "type": "Feature",
  "properties": {
    "addr:full":"4400 SW Beaverton Hillsdale Hwy Portland OR 97221",
    "addr:housenumber":"4400",
    "addr:postcode":"97221",
    "addr:street":"Sw Beaverton Hillsdale Hwy",
    "iso:country":"US",
    "sg:address":"4400 SW Beaverton Hillsdale Hwy",
    "sg:city":"Portland",
    "sg:classifiers":[
        {
            "category":"Autos & Motor Vehicles",
            "subcategory":"Auto Supplies",
            "type":"Retail Goods"
        }
    ],
    "sg:phone":"+1 503 245 5850",
    "sg:postcode":"97221",
    "sg:province":"OR",
    "sg:tags":[
        "muffler",
        "system",
        "exhaust"
    ],
    "sg:website":"http://www.edsmufflersandbrakes.com",
    "wof:name":"Eds Mufflers Unlimited Inc",
    "wof:placetype":"venue"
},
  "geometry": {"coordinates":[-122.722382,45.485695],"type":"Point"}
}