{
  "type": "Feature",
  "properties": {
    "iso:country":"US",
    "sg:address":"651 Market St",
    "sg:city":"Klamath Falls",
    "sg:classifiers":[
        {
            "category":"Manufacturing",
            "subcategory":"Printing",
            "type":"Manufacturing & Wholesale Goods"
        }
    ],
    "sg:phone":"+1 541 884 4193",
    "sg:postcode":"97601",
    "sg:province":"OR",
    "sg:tags":[
        "commercial",
        "lithographic"
    ],
    "sg:website":"www.graphicpressinc.com",
    "wof:name":"Graphic Press Inc",
    "wof:placetype":"venue"
},
  "geometry": {"coordinates":[-121.774084,42.22296],"type":"Point"}
}