{
  "type": "Feature",
  "properties": {
    "iso:country":"US",
    "sg:address":"219 SE 29th Ave",
    "sg:city":"Portland",
    "sg:classifiers":[
        {
            "category":"Recreation",
            "type":"Entertainment"
        }
    ],
    "sg:phone":"+1 503 232 6642",
    "sg:postcode":"97214",
    "sg:province":"OR",
    "wof:name":"Art & Motion",
    "wof:placetype":"venue"
},
  "geometry": {"coordinates":[-122.635966,45.520776],"type":"Point"}
}