{
  "type": "Feature",
  "properties": {
    "iso:country":"US",
    "sg:address":"8150 SW Barnes Rd",
    "sg:city":"Portland",
    "sg:classifiers":[
        {
            "category":"Real Estate",
            "subcategory":"Real Estate Agent",
            "type":"Services"
        }
    ],
    "sg:phone":"+1 503 292 1809",
    "sg:postcode":"97225",
    "sg:province":"OR",
    "wof:name":"Cannard Property MGT LLC",
    "wof:placetype":"venue"
},
  "geometry": {"coordinates":[-122.757681,45.512083],"type":"Point"}
}