{
  "type": "Feature",
  "properties": {
    "iso:country":"US",
    "sg:address":"6307 NE 15th Ave",
    "sg:city":"Portland",
    "sg:classifiers":[
        {
            "category":"Shopping",
            "type":"Retail Goods"
        }
    ],
    "sg:phone":"+1 503 240 5963",
    "sg:postcode":"97211",
    "sg:province":"OR",
    "sg:tags":[
        "art",
        "fair",
        "trade",
        "exposition",
        "gallery",
        "shows"
    ],
    "sg:website":"www.designorigins.com",
    "wof:name":"Design Origins",
    "wof:placetype":"venue"
},
  "geometry": {"coordinates":[-122.65034300000001,45.568577],"type":"Point"}
}