{
  "type": "Feature",
  "properties": {
    "addr:full":"833 Alder Creek Dr Medford OR 97504",
    "addr:housenumber":"833",
    "addr:postcode":"97504",
    "addr:street":"Alder Creek Dr",
    "iso:country":"US",
    "sg:address":"833 Alder Creek Dr",
    "sg:city":"Medford",
    "sg:classifiers":[
        {
            "category":"Insurance",
            "subcategory":"Hazard Insurance",
            "type":"Services"
        },
        {
            "category":"Insurance",
            "subcategory":"Insurance Agent",
            "type":"Services"
        }
    ],
    "sg:phone":"+1 541 770 5477",
    "sg:postcode":"97504",
    "sg:province":"OR",
    "sg:tags":[
        "carrier"
    ],
    "wof:name":"American States Insurance",
    "wof:placetype":"venue"
},
  "geometry": {"coordinates":[-122.819498,42.315333],"type":"Point"}
}