{
  "type": "Feature",
  "properties": {
    "addr:full":"1522 SE 21st Ave Portland OR 97214",
    "addr:housenumber":"1522",
    "addr:postcode":"97214",
    "addr:street":"Se 21St Ave",
    "iso:country":"US",
    "sg:address":"1522 SE 21st Ave",
    "sg:city":"Portland",
    "sg:classifiers":[
        {
            "category":"Restaurant",
            "type":"Food & Drink"
        }
    ],
    "sg:phone":"+1 503 231 1827",
    "sg:postcode":"97214",
    "sg:province":"OR",
    "sg:tags":[
        "eating",
        "caterer"
    ],
    "wof:name":"Semke's Black Tie Caterers",
    "wof:placetype":"venue"
},
  "geometry": {"coordinates":[-122.644065,45.511072],"type":"Point"}
}