{
  "type": "Feature",
  "properties": {
    "addr:full":"1155 SW Division St Ste 1 Bend OR 97702",
    "addr:housenumber":"1155",
    "addr:postcode":"97702",
    "addr:street":"Sw Division St Ste 1",
    "iso:country":"US",
    "sg:address":"1155 SW Division St Ste 1",
    "sg:city":"Bend",
    "sg:classifiers":[
        {
            "category":"Real Estate",
            "subcategory":"Real Estate Services",
            "type":"Services"
        },
        {
            "category":"Banks & Credit Unions",
            "subcategory":"Financial Services",
            "type":"Services"
        }
    ],
    "sg:phone":"+1 541 318 0739",
    "sg:postcode":"97702",
    "sg:province":"OR",
    "sg:tags":[
        "loan",
        "processing"
    ],
    "sg:website":"http://www.ncmintranet.com",
    "wof:name":"National City Mortgage Co",
    "wof:placetype":"venue"
},
  "geometry": {"coordinates":[-121.305592,44.03712],"type":"Point"}
}