{
  "type": "Feature",
  "properties": {
    "addr:full":"1205 NW 25th Ave Portland OR 97210",
    "addr:housenumber":"1205",
    "addr:postcode":"97210",
    "addr:street":"Nw 25Th Ave",
    "iso:country":"US",
    "sg:address":"1205 NW 25th Ave",
    "sg:city":"Portland",
    "sg:classifiers":[
        {
            "category":"Professional",
            "subcategory":"Lawyer & Legal Services",
            "type":"Services"
        }
    ],
    "sg:phone":"+1 503 243 5080",
    "sg:postcode":"97210",
    "sg:province":"OR",
    "wof:name":"Douglas D Hagen",
    "wof:placetype":"venue"
},
  "geometry": {"coordinates":[-122.702781,45.531822],"type":"Point"}
}