{
  "type": "Feature",
  "properties": {
    "addr:full":"1408 N Hall St La Grande OR 97850",
    "addr:housenumber":"1408",
    "addr:postcode":"97850",
    "addr:street":"N Hall St;Grande",
    "iso:country":"US",
    "sg:address":"1408 N Hall St",
    "sg:city":"La Grande",
    "sg:classifiers":[
        {
            "category":"Banks & Credit Unions",
            "subcategory":"Investment Brokerage",
            "type":"Services"
        }
    ],
    "sg:phone":"+1 541 963 5540",
    "sg:postcode":"97850",
    "sg:province":"OR",
    "sg:tags":[
        "advisory",
        "financial"
    ],
    "wof:name":"Professional Wealth Management",
    "wof:placetype":"venue"
},
  "geometry": {"coordinates":[-118.077856,45.325127],"type":"Point"}
}