{
  "type": "Feature",
  "properties": {
    "iso:country":"US",
    "sg:address":"325 NW 21st Ave",
    "sg:city":"Portland",
    "sg:classifiers":[
        {
            "category":"Social Services",
            "type":"Services"
        }
    ],
    "sg:phone":"+1 503 827 0199",
    "sg:postcode":"97209",
    "sg:province":"OR",
    "wof:name":"Bernard Dan MA",
    "wof:placetype":"venue"
},
  "geometry": {"coordinates":[-122.694463,45.52541],"type":"Point"}
}