{
  "type": "Feature",
  "properties": {
    "addr:full":"15145 Strong Rd Dallas OR 97338",
    "addr:housenumber":"15145",
    "addr:postcode":"97338",
    "addr:street":"Strong Rd",
    "iso:country":"US",
    "sg:address":"15145 Strong Rd",
    "sg:city":"Dallas",
    "sg:classifiers":[
        {
            "category":"Farming",
            "subcategory":"Farm",
            "type":"Manufacturing & Wholesale Goods"
        }
    ],
    "sg:phone":"+1 503 623 5619",
    "sg:postcode":"97338",
    "sg:province":"OR",
    "sg:tags":[
        "food",
        "covered",
        "crop",
        "general"
    ],
    "wof:name":"Mushrooms",
    "wof:placetype":"venue"
},
  "geometry": {"coordinates":[-123.340135,44.858781],"type":"Point"}
}