{
  "type": "Feature",
  "properties": {
    "addr:full":"15117 SE McLoughlin Boulevard Portland OR 97267",
    "addr:postcode":"15117;97267",
    "addr:street":"Se Mcloughlin Boulevard",
    "iso:country":"US",
    "sg:address":"15117 SE McLoughlin Boulevard",
    "sg:city":"Portland",
    "sg:classifiers":[
        {
            "category":"Restaurant",
            "type":"Food & Drink"
        }
    ],
    "sg:phone":"+1 503 659 4950",
    "sg:postcode":"97267",
    "sg:province":"OR",
    "sg:tags":[
        "italian",
        "pizza"
    ],
    "sg:website":"www.dominos.com",
    "wof:name":"Domino's Pizza",
    "wof:placetype":"venue"
},
  "geometry": {"coordinates":[-122.629903,45.413644],"type":"Point"}
}