{
  "type": "Feature",
  "properties": {
    "iso:country":"US",
    "sg:address":"19755 SW Rosa Rd",
    "sg:city":"Beaverton",
    "sg:classifiers":[
        {
            "category":"Building & Trades",
            "subcategory":"Landscaping Services",
            "type":"Services"
        }
    ],
    "sg:phone":"+1 503 356 9234",
    "sg:postcode":"97007",
    "sg:province":"OR",
    "sg:tags":[
        "tree"
    ],
    "wof:name":"My Tree Service",
    "wof:placetype":"venue"
},
  "geometry": {"coordinates":[-122.88101,45.478535],"type":"Point"}
}