{
  "type": "Feature",
  "properties": {
    "addr:full":"6412 SE Division St Portland OR 97206",
    "addr:housenumber":"6412",
    "addr:postcode":"97206",
    "addr:street":"Se Division St",
    "iso:country":"US",
    "sg:address":"6412 SE Division St",
    "sg:city":"Portland",
    "sg:classifiers":[
        {
            "category":"Real Estate",
            "subcategory":"Real Estate Operator",
            "type":"Services"
        }
    ],
    "sg:phone":"+1 503 771 5354",
    "sg:postcode":"97206",
    "sg:province":"OR",
    "sg:tags":[
        "building",
        "apartment"
    ],
    "wof:name":"Econ Properties",
    "wof:placetype":"venue"
},
  "geometry": {"coordinates":[-122.595641,45.505298],"type":"Point"}
}