{
  "type": "Feature",
  "properties": {
    "iso:country":"US",
    "sg:address":"158 Warner Milne Rd",
    "sg:city":"Oregon City",
    "sg:classifiers":[
        {
            "category":"Professional",
            "subcategory":"Management & Consulting",
            "type":"Services"
        }
    ],
    "sg:phone":"+1 503 657 8689",
    "sg:postcode":"97045",
    "sg:province":"OR",
    "wof:name":"Plesion Digital Inc",
    "wof:placetype":"venue"
},
  "geometry": {"coordinates":[-122.60112,45.336368],"type":"Point"}
}