{
  "type": "Feature",
  "properties": {
    "iso:country":"US",
    "sg:address":"203 E Main St",
    "sg:city":"Enterprise",
    "sg:classifiers":[
        {
            "category":"Professional",
            "subcategory":"Accounting & Tax Preparation",
            "type":"Services"
        }
    ],
    "sg:phone":"+1 541 426 6364",
    "sg:postcode":"97828",
    "sg:province":"OR",
    "sg:tags":[
        "accountant"
    ],
    "wof:name":"Edison & Co",
    "wof:placetype":"venue"
},
  "geometry": {"coordinates":[-117.27500499999999,45.425581],"type":"Point"}
}