{
  "type": "Feature",
  "properties": {
    "iso:country":"US",
    "sg:address":"1875 NW Juniper St",
    "sg:city":"Bend",
    "sg:classifiers":[
        {
            "category":"Building & Trades",
            "subcategory":"Construction",
            "type":"Services"
        }
    ],
    "sg:phone":"+1 541 317 9881",
    "sg:postcode":"97701",
    "sg:province":"OR",
    "sg:tags":[
        "residential",
        "general",
        "contractor"
    ],
    "wof:name":"Arcus Homes & Design LLC",
    "wof:placetype":"venue"
},
  "geometry": {"coordinates":[-121.334642,44.065216],"type":"Point"}
}