{
  "type": "Feature",
  "properties": {
    "iso:country":"US",
    "sg:address":"3715 SW 108th Ave",
    "sg:city":"Beaverton",
    "sg:classifiers":[
        {
            "category":"Social Services",
            "subcategory":"Child Care",
            "type":"Services"
        }
    ],
    "sg:phone":"+1 503 469 0507",
    "sg:postcode":"97005",
    "sg:province":"OR",
    "sg:tags":[
        "day"
    ],
    "wof:name":"Twilight Child Care",
    "wof:placetype":"venue"
},
  "geometry": {"coordinates":[-122.787391,45.491904],"type":"Point"}
}