{
  "type": "Feature",
  "properties": {
    "iso:country":"US",
    "sg:address":"11077 N Vancouver Way",
    "sg:city":"Portland",
    "sg:classifiers":[
        {
            "category":"Building & Trades",
            "subcategory":"Plumbing",
            "type":"Services"
        }
    ],
    "sg:phone":"+1 503 289 7095",
    "sg:postcode":"97217",
    "sg:province":"OR",
    "sg:tags":[
        "plumbing",
        "contractor"
    ],
    "wof:name":"Cascade Plumbing",
    "wof:placetype":"venue"
},
  "geometry": {"coordinates":[-122.67857100000001,45.603077],"type":"Point"}
}