{
  "type": "Feature",
  "properties": {
    "addr:full":"4451 SE 28th Ave Portland OR 97202",
    "addr:housenumber":"4451",
    "addr:postcode":"97202",
    "addr:street":"Se 28Th Ave",
    "iso:country":"US",
    "sg:address":"4451 SE 28th Ave",
    "sg:city":"Portland",
    "sg:classifiers":[
        {
            "category":"Education",
            "subcategory":"Music School",
            "type":"Public Place"
        }
    ],
    "sg:phone":"+1 503 238 4515",
    "sg:postcode":"97202",
    "sg:province":"OR",
    "sg:tags":[
        "instrument",
        "teacher",
        "musical"
    ],
    "sg:website":"www.kerrviolins.com/",
    "wof:name":"David Kerr Violin Shop",
    "wof:placetype":"venue"
},
  "geometry": {"coordinates":[-122.637918,45.490574],"type":"Point"}
}