{
  "type": "Feature",
  "properties": {
    "iso:country":"US",
    "sg:address":"810 Charnelton St",
    "sg:city":"Eugene",
    "sg:classifiers":[
        {
            "category":"Restaurant",
            "type":"Food & Drink"
        }
    ],
    "sg:phone":"+1 541 344 1928",
    "sg:postcode":"97401",
    "sg:province":"OR",
    "sg:tags":[
        "eating"
    ],
    "wof:name":"Lotus Garden Vegetarian Restaurant",
    "wof:placetype":"venue"
},
  "geometry": {"coordinates":[-123.095795,44.050745],"type":"Point"}
}