{
  "type": "Feature",
  "properties": {
    "iso:country":"US",
    "sg:address":"1615 Harvard Ave",
    "sg:city":"Gladstone",
    "sg:classifiers":[
        {
            "category":"Utilities",
            "subcategory":"Mobile Phone",
            "type":"Services"
        }
    ],
    "sg:phone":"+1 503 655 1870",
    "sg:postcode":"97027",
    "sg:province":"OR",
    "sg:tags":[
        "telephone",
        "cellular"
    ],
    "wof:name":"Wireless Services Intl",
    "wof:placetype":"venue"
},
  "geometry": {"coordinates":[-122.59683099999999,45.388826],"type":"Point"}
}