{
  "type": "Feature",
  "properties": {
    "iso:country":"US",
    "sg:address":"59257 High Valley Rd",
    "sg:city":"Union",
    "sg:classifiers":[
        {
            "category":"Farming",
            "subcategory":"Livestock Farm",
            "type":"Manufacturing & Wholesale Goods"
        }
    ],
    "sg:phone":"+1 541 562 6122",
    "sg:postcode":"97883",
    "sg:province":"OR",
    "sg:tags":[
        "beef",
        "feedlot",
        "cattle"
    ],
    "wof:name":"Sunnybrook Ranch",
    "wof:placetype":"venue"
},
  "geometry": {"coordinates":[-117.825858,45.203218],"type":"Point"}
}