{
  "type": "Feature",
  "properties": {
    "iso:country":"US",
    "sg:address":"1155 Mission St SE",
    "sg:city":"Salem",
    "sg:classifiers":[
        {
            "category":"Health Services",
            "subcategory":"Doctor",
            "type":"Services"
        }
    ],
    "sg:phone":"+1 503 364 6821",
    "sg:postcode":"97302",
    "sg:province":"OR",
    "sg:tags":[
        "physician",
        "surgeon"
    ],
    "wof:name":"Pacific Pathology Assoc",
    "wof:placetype":"venue"
},
  "geometry": {"coordinates":[-123.031176,44.930363],"type":"Point"}
}