{
  "type": "Feature",
  "properties": {
    "addr:full":"23100 Schatz Rd Sheridan OR 97378",
    "addr:postcode":"23100;97378",
    "addr:street":"Schatz Rd",
    "iso:country":"US",
    "sg:address":"23100 Schatz Rd",
    "sg:city":"Sheridan",
    "sg:classifiers":[
        {
            "category":"Retail",
            "subcategory":"Auto Repair",
            "type":"Services"
        }
    ],
    "sg:phone":"+1 503 843 4003",
    "sg:postcode":"97378",
    "sg:province":"OR",
    "sg:tags":[
        "wrecker"
    ],
    "wof:name":"O K Motor Sales Inc",
    "wof:placetype":"venue"
},
  "geometry": {"coordinates":[-123.38153800000001,45.093239],"type":"Point"}
}