{
  "type": "Feature",
  "properties": {
    "iso:country":"US",
    "sg:address":"11255 SE 312th Ave",
    "sg:city":"Boring",
    "sg:classifiers":[
        {
            "category":"Banks & Credit Unions",
            "subcategory":"Financial Services",
            "type":"Services"
        }
    ],
    "sg:phone":"+1 503 663 4416",
    "sg:postcode":"97009",
    "sg:province":"OR",
    "sg:tags":[
        "investor"
    ],
    "wof:name":"Pettyjohn Investments LLC",
    "wof:placetype":"venue"
},
  "geometry": {"coordinates":[-122.341976,45.441631],"type":"Point"}
}