{
  "type": "Feature",
  "properties": {
    "iso:country":"US",
    "sg:address":"237 NE Broadway Ste 101",
    "sg:city":"Portland",
    "sg:classifiers":[
        {
            "category":"Banks & Credit Unions",
            "subcategory":"Financial Services",
            "type":"Services"
        }
    ],
    "sg:phone":"+1 503 288 9284",
    "sg:postcode":"97232",
    "sg:province":"OR",
    "sg:tags":[
        "broker",
        "mortgage"
    ],
    "wof:name":"Equity Home Mortgage",
    "wof:placetype":"venue"
},
  "geometry": {"coordinates":[-122.66297,45.535317],"type":"Point"}
}