{
  "type": "Feature",
  "properties": {
    "iso:country":"US",
    "sg:address":"1730 SW Skyline Blvd",
    "sg:city":"Portland",
    "sg:classifiers":[
        {
            "category":"Real Estate",
            "subcategory":"Real Estate Agent",
            "type":"Services"
        }
    ],
    "sg:phone":"+1 503 292 6332",
    "sg:postcode":"97221",
    "sg:province":"OR",
    "wof:name":"Blaine Whipple Realty",
    "wof:placetype":"venue"
},
  "geometry": {"coordinates":[-122.735269,45.511169],"type":"Point"}
}