{
  "type": "Feature",
  "properties": {
    "iso:country":"US",
    "sg:address":"1930 Ocean Blvd NW",
    "sg:city":"Coos Bay",
    "sg:classifiers":[
        {
            "category":"Retail",
            "subcategory":"Auto Repair",
            "type":"Services"
        }
    ],
    "sg:phone":"+1 541 888 3515",
    "sg:postcode":"97420",
    "sg:province":"OR",
    "sg:tags":[
        "muffler",
        "exhaust",
        "system"
    ],
    "wof:name":"J D & M Muffler Shop",
    "wof:placetype":"venue"
},
  "geometry": {"coordinates":[-124.25484899999999,43.386207],"type":"Point"}
}