{
  "type": "Feature",
  "properties": {
    "addr:full":"9415 SW Kelly Ave Portland OR 97219",
    "addr:housenumber":"9415",
    "addr:postcode":"97219",
    "addr:street":"Sw Kelly Ave",
    "iso:country":"US",
    "sg:address":"9415 SW Kelly Ave",
    "sg:city":"Portland",
    "sg:classifiers":[
        {
            "category":"Manufacturing",
            "subcategory":"Jewelry",
            "type":"Manufacturing & Wholesale Goods"
        },
        {
            "category":"Retail",
            "subcategory":"Repair Shop",
            "type":"Services"
        }
    ],
    "sg:phone":"+1 503 246 8390",
    "sg:postcode":"97219",
    "sg:province":"OR",
    "sg:tags":[
        "repairing",
        "clock"
    ],
    "wof:name":"J L Sheppard & Associates",
    "wof:placetype":"venue"
},
  "geometry": {"coordinates":[-122.675595,45.457018],"type":"Point"}
}