{
  "type": "Feature",
  "properties": {
    "iso:country":"US",
    "sg:address":"18501 SE Blanton St",
    "sg:city":"Portland",
    "sg:classifiers":[
        {
            "category":"Building & Trades",
            "subcategory":"Construction",
            "type":"Services"
        }
    ],
    "sg:phone":"+1 503 387 5111",
    "sg:postcode":"97267",
    "sg:province":"OR",
    "sg:tags":[
        "contractor"
    ],
    "sg:website":"www.buildtekexteriors.com",
    "wof:name":"Buildtek Exteriors",
    "wof:placetype":"venue"
},
  "geometry": {"coordinates":[-122.613302,45.389374],"type":"Point"}
}