{
  "type": "Feature",
  "properties": {
    "iso:country":"US",
    "sg:address":"1942 NW Kearney St Ste 24",
    "sg:city":"Portland",
    "sg:classifiers":[
        {
            "category":"Health Services",
            "subcategory":"Doctor",
            "type":"Services"
        },
        {
            "category":"Health Services",
            "subcategory":"Clinic",
            "type":"Services"
        }
    ],
    "sg:phone":"+1 503 221 7074",
    "sg:postcode":"97209",
    "sg:province":"OR",
    "sg:tags":[
        "psychological",
        "psychologist"
    ],
    "wof:name":"Neurohealth Associates, Llp",
    "wof:placetype":"venue"
},
  "geometry": {"coordinates":[-122.69134,45.529158],"type":"Point"}
}