{
  "type": "Feature",
  "properties": {
    "addr:full":"121 SW Morrison St Portland OR 97204",
    "addr:housenumber":"121",
    "addr:postcode":"97204",
    "addr:street":"Sw Morrison St",
    "iso:country":"US",
    "sg:address":"121 SW Morrison St",
    "sg:city":"Portland",
    "sg:classifiers":[
        {
            "category":"Banks & Credit Unions",
            "subcategory":"Investment Brokerage",
            "type":"Services"
        }
    ],
    "sg:phone":"+1 503 232 6020",
    "sg:postcode":"97204",
    "sg:province":"OR",
    "sg:tags":[
        "security"
    ],
    "sg:website":"www.agedwards.com",
    "wof:name":"A G Edwards & Sons Inc",
    "wof:placetype":"venue"
},
  "geometry": {"coordinates":[-122.67439,45.518008],"type":"Point"}
}