{
  "type": "Feature",
  "properties": {
    "addr:full":"2515 NW Town Center Dr Beaverton OR 97006",
    "addr:housenumber":"2515",
    "addr:postcode":"97006",
    "addr:street":"Nw Town Center Dr",
    "iso:country":"US",
    "sg:address":"2515 NW Town Center Dr",
    "sg:city":"Beaverton",
    "sg:classifiers":[
        {
            "category":"Restaurant",
            "type":"Food & Drink"
        }
    ],
    "sg:menulink":"http://www.allmenus.com/or/somerset-west-rock-creek/89657-moes-southwest-grill/menu/",
    "sg:phone":"+1 503 690 8600",
    "sg:postcode":"97006",
    "sg:province":"OR",
    "sg:tags":[
        "mexican"
    ],
    "wof:name":"Moe's Southwest Grill",
    "wof:placetype":"venue"
},
  "geometry": {"coordinates":[-122.86636900000001,45.537816],"type":"Point"}
}