{
  "type": "Feature",
  "properties": {
    "iso:country":"US",
    "sg:address":"1833 NE 2nd Ave",
    "sg:city":"Portland",
    "sg:classifiers":[
        {
            "category":"Professional",
            "subcategory":"Detective & Security Services",
            "type":"Services"
        }
    ],
    "sg:phone":"+1 503 251 2265",
    "sg:postcode":"97212",
    "sg:province":"OR",
    "sg:tags":[
        "guard"
    ],
    "wof:name":"Metro Security Services Inc",
    "wof:placetype":"venue"
},
  "geometry": {"coordinates":[-122.663738,45.536274],"type":"Point"}
}