{
  "type": "Feature",
  "properties": {
    "iso:country":"US",
    "sg:address":"8605 SW Curry Dr",
    "sg:city":"Wilsonville",
    "sg:classifiers":[
        {
            "category":"Home & Garden",
            "subcategory":"Building Materials",
            "type":"Retail Goods"
        }
    ],
    "sg:phone":"+1 503 694 2192",
    "sg:postcode":"97070",
    "sg:province":"OR",
    "sg:tags":[
        "lumber"
    ],
    "wof:name":"Heestand Enterprises Inc",
    "wof:placetype":"venue"
},
  "geometry": {"coordinates":[-122.765359,45.290017],"type":"Point"}
}