{
  "type": "Feature",
  "properties": {
    "iso:country":"US",
    "sg:address":"1309 NE 183rd Ave",
    "sg:city":"Portland",
    "sg:classifiers":[
        {
            "category":"Retail",
            "subcategory":"Laundry & Dry Cleaning",
            "type":"Services"
        },
        {
            "category":"Building & Trades",
            "subcategory":"Cleaning & Sanitation",
            "type":"Services"
        }
    ],
    "sg:phone":"+1 503 661 2626",
    "sg:postcode":"97230",
    "sg:province":"OR",
    "sg:tags":[
        "cleaner",
        "house"
    ],
    "wof:name":"Mery's Cleaning",
    "wof:placetype":"venue"
},
  "geometry": {"coordinates":[-122.474453,45.532086],"type":"Point"}
}