{
  "type": "Feature",
  "properties": {
    "iso:country":"US",
    "sg:address":"4545 NE 125th Pl",
    "sg:city":"Portland",
    "sg:classifiers":[
        {
            "category":"Building & Trades",
            "subcategory":"Locksmith",
            "type":"Services"
        }
    ],
    "sg:phone":"+1 503 715 3784",
    "sg:postcode":"97230",
    "sg:province":"OR",
    "sg:tags":[
        "key"
    ],
    "wof:name":"7 Day Anytime Locksmith",
    "wof:placetype":"venue"
},
  "geometry": {"coordinates":[-122.533444,45.555761],"type":"Point"}
}