{
  "type": "Feature",
  "properties": {
    "iso:country":"US",
    "sg:address":"59170 SE Chalet Pl",
    "sg:city":"Sandy",
    "sg:classifiers":[
        {
            "category":"Retail",
            "subcategory":"Auto Repair",
            "type":"Services"
        }
    ],
    "sg:phone":"+1 503 622 0575",
    "sg:postcode":"97055",
    "sg:province":"OR",
    "sg:tags":[
        "wrecker"
    ],
    "wof:name":"Alder Creek Towing LLC",
    "wof:placetype":"venue"
},
  "geometry": {"coordinates":[-122.05567,45.384627],"type":"Point"}
}