{
  "type": "Feature",
  "properties": {
    "iso:country":"US",
    "sg:address":"83456 Russell Ln",
    "sg:city":"Joseph",
    "sg:classifiers":[
        {
            "category":"Retail",
            "subcategory":"Animal Services",
            "type":"Services"
        }
    ],
    "sg:phone":"+1 541 432 8221",
    "sg:postcode":"97846",
    "sg:province":"OR",
    "sg:tags":[
        "pet"
    ],
    "wof:name":"Lin-Lee Kennels",
    "wof:placetype":"venue"
},
  "geometry": {"coordinates":[-117.255821,45.360159],"type":"Point"}
}