{
  "type": "Feature",
  "properties": {
    "iso:country":"US",
    "sg:address":"11266 SE 21st Avenue",
    "sg:city":"Portland",
    "sg:classifiers":[
        {
            "category":"Sports & Exercise",
            "subcategory":"Gym",
            "type":"Entertainment"
        },
        {
            "category":"Health Services",
            "subcategory":"Chiropractor",
            "type":"Services"
        }
    ],
    "sg:phone":"+1 503 659 5900",
    "sg:postcode":"97222",
    "sg:province":"OR",
    "sg:tags":[
        "yoga"
    ],
    "wof:name":"Mealey David DC",
    "wof:placetype":"venue"
},
  "geometry": {"coordinates":[-122.615562,45.441952],"type":"Point"}
}