{
  "type": "Feature",
  "properties": {
    "addr:full":"6922 N Newcastle Ave Portland OR 97217",
    "addr:housenumber":"6922",
    "addr:postcode":"97217",
    "addr:street":"N Newcastle Ave",
    "iso:country":"US",
    "sg:address":"6922 N Newcastle Ave",
    "sg:city":"Portland",
    "sg:classifiers":[
        {
            "category":"Building & Trades",
            "subcategory":"Construction",
            "type":"Services"
        }
    ],
    "sg:phone":"+1 503 239 3954",
    "sg:postcode":"97217",
    "sg:province":"OR",
    "sg:tags":[
        "plastering",
        "contractor"
    ],
    "wof:name":"F.A.T. Siding, Inc.",
    "wof:placetype":"venue"
},
  "geometry": {"coordinates":[-122.689881,45.572831],"type":"Point"}
}