{
  "type": "Feature",
  "properties": {
    "iso:country":"US",
    "sg:address":"13948 SW 159th Ter",
    "sg:city":"Portland",
    "sg:classifiers":[
        {
            "category":"Professional",
            "subcategory":"Management & Consulting",
            "type":"Services"
        }
    ],
    "sg:phone":"+1 503 579 5616",
    "sg:postcode":"97223",
    "sg:province":"OR",
    "sg:tags":[
        "communication",
        "relation",
        "public"
    ],
    "wof:name":"Tanya Chappelle Communications",
    "wof:placetype":"venue"
},
  "geometry": {"coordinates":[-122.840587,45.418868],"type":"Point"}
}