{
  "type": "Feature",
  "properties": {
    "iso:country":"US",
    "sg:address":"32253 Deberry Rd",
    "sg:city":"Creswell",
    "sg:classifiers":[
        {
            "category":"Building & Trades",
            "subcategory":"Construction",
            "type":"Services"
        }
    ],
    "sg:phone":"+1 541 895 4676",
    "sg:postcode":"97426",
    "sg:province":"OR",
    "sg:tags":[
        "cabinet",
        "carpentry",
        "maker",
        "contractor"
    ],
    "wof:name":"Campbell's Furniture & Cabinet",
    "wof:placetype":"venue"
},
  "geometry": {"coordinates":[-123.071783,43.909866],"type":"Point"}
}