{
  "type": "Feature",
  "properties": {
    "iso:country":"US",
    "sg:address":"12780 SE Stark St",
    "sg:city":"Portland",
    "sg:classifiers":[
        {
            "category":"Social Services",
            "type":"Services"
        }
    ],
    "sg:phone":"+1 503 257 9958",
    "sg:postcode":"97233",
    "sg:province":"OR",
    "wof:name":"Holt Allen Counseling",
    "wof:placetype":"venue"
},
  "geometry": {"coordinates":[-122.53223,45.518979],"type":"Point"}
}