{
  "type": "Feature",
  "properties": {
    "iso:country":"US",
    "sg:address":"4750 SE Rockwood St",
    "sg:city":"Portland",
    "sg:classifiers":[
        {
            "category":"Organizations",
            "subcategory":"Membership Organization",
            "type":"Services"
        },
        {
            "category":"Sports & Exercise",
            "subcategory":"Golf",
            "type":"Entertainment"
        }
    ],
    "sg:phone":"+1 503 653 7859",
    "sg:postcode":"97222",
    "sg:province":"OR",
    "sg:tags":[
        "club",
        "instruction",
        "private"
    ],
    "wof:name":"Oak Grove Garden Club Inc",
    "wof:placetype":"venue"
},
  "geometry": {"coordinates":[-122.614485,45.453252],"type":"Point"}
}