{
  "type": "Feature",
  "properties": {
    "iso:country":"US",
    "sg:address":"369 Silver Hills Cir SE",
    "sg:city":"Salem",
    "sg:classifiers":[
        {
            "category":"Education",
            "subcategory":"Special Training",
            "type":"Public Place"
        }
    ],
    "sg:phone":"+1 503 364 6702",
    "sg:postcode":"97306",
    "sg:province":"OR",
    "sg:tags":[
        "instrument",
        "musical"
    ],
    "sg:website":"www.flamtrap.com",
    "wof:name":"Flam Trap",
    "wof:placetype":"venue"
},
  "geometry": {"coordinates":[-123.05288299999999,44.878045],"type":"Point"}
}