{
  "type": "Feature",
  "properties": {
    "iso:country":"US",
    "sg:address":"910 NW Hoyt St",
    "sg:city":"Portland",
    "sg:classifiers":[
        {
            "category":"Professional",
            "subcategory":"Art Services",
            "type":"Services"
        }
    ],
    "sg:phone":"+1 503 228 7930",
    "sg:postcode":"97209",
    "sg:province":"OR",
    "sg:tags":[
        "graphic",
        "designer"
    ],
    "wof:name":"Fieldtrip",
    "wof:placetype":"venue"
},
  "geometry": {"coordinates":[-122.68118699999999,45.527181],"type":"Point"}
}