{
  "type": "Feature",
  "properties": {
    "iso:country":"US",
    "sg:address":"46180 Hwy 19",
    "sg:city":"Fossil",
    "sg:classifiers":[
        {
            "category":"Manufacturing",
            "subcategory":"Lumber",
            "type":"Manufacturing & Wholesale Goods"
        }
    ],
    "sg:phone":"+1 541 763 2131",
    "sg:postcode":"97830",
    "sg:province":"OR",
    "sg:tags":[
        "water",
        "tender",
        "forest",
        "fire",
        "on"
    ],
    "wof:name":"H2h2o",
    "wof:placetype":"venue"
},
  "geometry": {"coordinates":[-120.141211,44.962834],"type":"Point"}
}