{
  "type": "Feature",
  "properties": {
    "iso:country":"US",
    "sg:address":"3510 NE 57th Ave",
    "sg:city":"Portland",
    "sg:classifiers":[
        {
            "category":"Health Services",
            "subcategory":"Optometrist",
            "type":"Services"
        }
    ],
    "sg:phone":"+1 503 282 3070",
    "sg:postcode":"97213",
    "sg:province":"OR",
    "wof:name":"Alameda Vision Center",
    "wof:placetype":"venue"
},
  "geometry": {"coordinates":[-122.603996,45.548401],"type":"Point"}
}