{
  "type": "Feature",
  "properties": {
    "iso:country":"US",
    "sg:address":"573 Parsons Dr",
    "sg:city":"Medford",
    "sg:classifiers":[
        {
            "category":"Government",
            "subcategory":"Office",
            "type":"Public Place"
        }
    ],
    "sg:phone":"+1 541 776 4267",
    "sg:postcode":"97501",
    "sg:province":"OR",
    "sg:tags":[
        "federal"
    ],
    "wof:name":"Natural Resources Conservation",
    "wof:placetype":"venue"
},
  "geometry": {"coordinates":[-122.892653,42.338496],"type":"Point"}
}