{
  "type": "Feature",
  "properties": {
    "addr:full":"209 SW 1st Ave Milton Freewater OR 97862",
    "addr:housenumber":"209",
    "addr:postcode":"97862",
    "addr:street":"Sw 1St Ave;Freewater",
    "iso:country":"US",
    "sg:address":"209 SW 1st Ave",
    "sg:city":"Milton Freewater",
    "sg:classifiers":[
        {
            "category":"Organizations",
            "subcategory":"Religious Organization",
            "type":"Services"
        }
    ],
    "sg:phone":"+1 541 938 3111",
    "sg:postcode":"97862",
    "sg:province":"OR",
    "wof:name":"Bethel Cnsrvtive Baptst Church",
    "wof:placetype":"venue"
},
  "geometry": {"coordinates":[-118.395709,45.936361],"type":"Point"}
}