{
  "type": "Feature",
  "properties": {
    "addr:full":"1114 NE Hidden Valley Dr Bend OR 97701",
    "addr:housenumber":"1114",
    "addr:postcode":"97701",
    "addr:street":"Ne Hidden Valley Dr",
    "iso:country":"US",
    "sg:address":"1114 NE Hidden Valley Dr",
    "sg:city":"Bend",
    "sg:classifiers":[
        {
            "category":"Manufacturing",
            "subcategory":"Food",
            "type":"Manufacturing & Wholesale Goods"
        }
    ],
    "sg:phone":"+1 541 312 2102",
    "sg:postcode":"97701",
    "sg:province":"OR",
    "sg:tags":[
        "product",
        "mfg"
    ],
    "wof:name":"Sweet Baby Janes Inc",
    "wof:placetype":"venue"
},
  "geometry": {"coordinates":[-121.289297,44.078089],"type":"Point"}
}