{
  "type": "Feature",
  "properties": {
    "addr:full":"193 Laneda Ave Manzanita OR 97130",
    "addr:housenumber":"193",
    "addr:postcode":"97130",
    "addr:street":"Laneda Ave",
    "iso:country":"US",
    "sg:address":"193 Laneda Ave",
    "sg:city":"Manzanita",
    "sg:classifiers":[
        {
            "category":"Food & Beverages",
            "subcategory":"Groceries & Convenience Stores",
            "type":"Retail Goods"
        }
    ],
    "sg:phone":"+1 503 368 5362",
    "sg:postcode":"97130",
    "sg:province":"OR",
    "sg:tags":[
        "grocer"
    ],
    "wof:name":"Manzanita Grocery & Deli",
    "wof:placetype":"venue"
},
  "geometry": {"coordinates":[-123.936763,45.718442],"type":"Point"}
}