{
  "type": "Feature",
  "properties": {
    "addr:full":"23290 S Unger Rd Colton OR 97017",
    "addr:housenumber":"23290",
    "addr:postcode":"97017",
    "addr:street":"S Unger Rd",
    "iso:country":"US",
    "sg:address":"23290 S Unger Rd",
    "sg:city":"Colton",
    "sg:classifiers":[
        {
            "category":"Manufacturing",
            "subcategory":"Lumber",
            "type":"Manufacturing & Wholesale Goods"
        }
    ],
    "sg:phone":"+1 503 630 6015",
    "sg:postcode":"97017",
    "sg:province":"OR",
    "sg:tags":[
        "operation",
        "timber",
        "tract"
    ],
    "wof:name":"Charles Almond",
    "wof:placetype":"venue"
},
  "geometry": {"coordinates":[-122.39324000000001,45.205619],"type":"Point"}
}