{
  "type": "Feature",
  "properties": {
    "iso:country":"US",
    "sg:address":"8159 SW 41st Ave",
    "sg:city":"Portland",
    "sg:classifiers":[
        {
            "category":"Arts & Performance",
            "subcategory":"Theater",
            "type":"Entertainment"
        }
    ],
    "sg:phone":"+1 503 245 6919",
    "sg:postcode":"97219",
    "sg:province":"OR",
    "sg:tags":[
        "theatre"
    ],
    "wof:name":"Tapestry Theatre Co",
    "wof:placetype":"venue"
},
  "geometry": {"coordinates":[-122.719257,45.465516],"type":"Point"}
}