{
  "type": "Feature",
  "properties": {
    "iso:country":"US",
    "sg:address":"118 S K St",
    "sg:city":"Lakeview",
    "sg:classifiers":[
        {
            "category":"Professional",
            "type":"Services"
        }
    ],
    "sg:phone":"+1 541 947 2797",
    "sg:postcode":"97630",
    "sg:province":"OR",
    "wof:name":"Et Inc",
    "wof:placetype":"venue"
},
  "geometry": {"coordinates":[-120.351994,42.188039],"type":"Point"}
}