{
  "type": "Feature",
  "properties": {
    "iso:country":"US",
    "sg:address":"189 S Main St",
    "sg:city":"Jefferson",
    "sg:classifiers":[
        {
            "category":"Government",
            "subcategory":"Fire Station",
            "type":"Public Place"
        }
    ],
    "sg:phone":"+1 541 327 2822",
    "sg:postcode":"97352",
    "sg:province":"OR",
    "sg:tags":[
        "department"
    ],
    "wof:name":"Jefferson Fire Dept",
    "wof:placetype":"venue"
},
  "geometry": {"coordinates":[-123.01172200000001,44.716568],"type":"Point"}
}