{
  "type": "Feature",
  "properties": {
    "iso:country":"US",
    "sg:address":"947 Nightingale Ct NE",
    "sg:city":"Salem",
    "sg:classifiers":[
        {
            "category":"Manufacturing",
            "subcategory":"Tools & Machinery",
            "type":"Manufacturing & Wholesale Goods"
        }
    ],
    "sg:phone":"+1 503 393 1916",
    "sg:postcode":"97303",
    "sg:province":"OR",
    "sg:tags":[
        "industry",
        "mfg"
    ],
    "wof:name":"Gary Hurd",
    "wof:placetype":"venue"
},
  "geometry": {"coordinates":[-123.021631,45.018337],"type":"Point"}
}