{
  "type": "Feature",
  "properties": {
    "addr:full":"1598 Bentley St E Monmouth OR 97361",
    "addr:housenumber":"1598",
    "addr:postcode":"97361",
    "addr:street":"Bentley St E",
    "iso:country":"US",
    "sg:address":"1598 Bentley St E",
    "sg:city":"Monmouth",
    "sg:classifiers":[
        {
            "category":"Building & Trades",
            "subcategory":"Construction",
            "type":"Services"
        }
    ],
    "sg:phone":"+1 503 606 0711",
    "sg:postcode":"97361",
    "sg:province":"OR",
    "sg:tags":[
        "house",
        "handyman"
    ],
    "wof:name":"Wilson Repairs & Installations",
    "wof:placetype":"venue"
},
  "geometry": {"coordinates":[-123.217844,44.84478],"type":"Point"}
}