{
  "type": "Feature",
  "properties": {
    "addr:full":"14577 NW Joseph Ct Portland OR 97229",
    "addr:housenumber":"14577",
    "addr:postcode":"97229",
    "addr:street":"Nw Joseph Ct",
    "iso:country":"US",
    "sg:address":"14577 NW Joseph Ct",
    "sg:city":"Portland",
    "sg:classifiers":[
        {
            "category":"Professional",
            "subcategory":"Management & Consulting",
            "type":"Services"
        }
    ],
    "sg:phone":"+1 503 645 0752",
    "sg:postcode":"97229",
    "sg:province":"OR",
    "wof:name":"Jack Mumford",
    "wof:placetype":"venue"
},
  "geometry": {"coordinates":[-122.82688899999999,45.551757],"type":"Point"}
}