{
  "type": "Feature",
  "properties": {
    "addr:full":"17137 SW Rider Ln Beaverton OR 97007",
    "addr:housenumber":"17137",
    "addr:postcode":"97007",
    "addr:street":"Sw Rider Ln",
    "iso:country":"US",
    "sg:address":"17137 SW Rider Ln",
    "sg:city":"Beaverton",
    "sg:classifiers":[
        {
            "category":"Professional",
            "type":"Services"
        }
    ],
    "sg:phone":"+1 503 297 0694",
    "sg:postcode":"97007",
    "sg:province":"OR",
    "wof:name":"Northwest Works Inc",
    "wof:placetype":"venue"
},
  "geometry": {"coordinates":[-122.85459400000001,45.436934],"type":"Point"}
}