{
  "type": "Feature",
  "properties": {
    "addr:full":"911 N Riverside Ave Medford OR 97501",
    "addr:housenumber":"911",
    "addr:postcode":"97501",
    "addr:street":"N Riverside Ave",
    "iso:country":"US",
    "sg:address":"911 N Riverside Ave",
    "sg:city":"Medford",
    "sg:classifiers":[
        {
            "category":"Manufacturing",
            "subcategory":"Signs",
            "type":"Manufacturing & Wholesale Goods"
        }
    ],
    "sg:phone":"+1 541 858 2701",
    "sg:postcode":"97501",
    "sg:province":"OR",
    "sg:tags":[
        "advertising",
        "specialty"
    ],
    "wof:name":"Sign Dude",
    "wof:placetype":"venue"
},
  "geometry": {"coordinates":[-122.87491300000001,42.335917],"type":"Point"}
}