{
  "type": "Feature",
  "properties": {
    "iso:country":"US",
    "sg:address":"470 2nd St",
    "sg:city":"Lake Oswego",
    "sg:classifiers":[
        {
            "category":"Banks & Credit Unions",
            "subcategory":"Bank",
            "type":"Services"
        }
    ],
    "sg:phone":"+1 503 675 2333",
    "sg:postcode":"97034",
    "sg:province":"OR",
    "sg:tags":[
        "mortgage"
    ],
    "wof:name":"Trust First Mortgage",
    "wof:placetype":"venue"
},
  "geometry": {"coordinates":[-122.66544,45.419886],"type":"Point"}
}