{
  "type": "Feature",
  "properties": {
    "iso:country":"US",
    "sg:address":"1341 NW 9th St",
    "sg:city":"Corvallis",
    "sg:classifiers":[
        {
            "category":"Personal",
            "subcategory":"Beauty Salon",
            "type":"Services"
        }
    ],
    "sg:phone":"+1 541 752 5815",
    "sg:postcode":"97330",
    "sg:province":"OR",
    "sg:tags":[
        "shop"
    ],
    "wof:name":"Gloria's Beauty Salon",
    "wof:placetype":"venue"
},
  "geometry": {"coordinates":[-123.259928,44.579529],"type":"Point"}
}