{
  "type": "Feature",
  "properties": {
    "iso:country":"US",
    "sg:address":"581 SW 33rd St",
    "sg:city":"Ontario",
    "sg:classifiers":[
        {
            "category":"Farming",
            "subcategory":"Livestock Farm",
            "type":"Manufacturing & Wholesale Goods"
        }
    ],
    "sg:phone":"+1 541 889 2311",
    "sg:postcode":"97914",
    "sg:province":"OR",
    "sg:tags":[
        "beef",
        "feedlot",
        "cattle"
    ],
    "wof:name":"Crowley Ranch",
    "wof:placetype":"venue"
},
  "geometry": {"coordinates":[-117.012688,44.024823],"type":"Point"}
}