{
  "type": "Feature",
  "properties": {
    "iso:country":"US",
    "sg:address":"3220 SW Obsidian Ave",
    "sg:city":"Redmond",
    "sg:classifiers":[
        {
            "category":"Social Services",
            "subcategory":"Child Care",
            "type":"Services"
        }
    ],
    "sg:phone":"+1 541 923 1500",
    "sg:postcode":"97756",
    "sg:province":"OR",
    "sg:tags":[
        "day"
    ],
    "wof:name":"Country Critters",
    "wof:placetype":"venue"
},
  "geometry": {"coordinates":[-121.206086,44.261847],"type":"Point"}
}