{
  "type": "Feature",
  "properties": {
    "addr:full":"2785 N 32nd St Springfield OR 97477",
    "addr:housenumber":"2785",
    "addr:postcode":"97477",
    "addr:street":"N 32Nd St",
    "iso:country":"US",
    "sg:address":"2785 N 32nd St",
    "sg:city":"Springfield",
    "sg:classifiers":[
        {
            "category":"Professional",
            "subcategory":"Business Services",
            "type":"Services"
        }
    ],
    "sg:phone":"+1 951 324 9695",
    "sg:postcode":"97477",
    "sg:province":"OR",
    "sg:tags":[
        "brokerage",
        "computer"
    ],
    "wof:name":"It Alliance Group Inc",
    "wof:placetype":"venue"
},
  "geometry": {"coordinates":[-122.979569,44.075238],"type":"Point"}
}