{
  "type": "Feature",
  "properties": {
    "iso:country":"US",
    "sg:address":"9931 S Highway 211",
    "sg:city":"Canby",
    "sg:classifiers":[
        {
            "category":"Home & Garden",
            "subcategory":"Garden Supply",
            "type":"Retail Goods"
        }
    ],
    "sg:phone":"+1 503 651 2251",
    "sg:postcode":"97013",
    "sg:province":"OR",
    "sg:tags":[
        "tree",
        "christmas"
    ],
    "wof:name":"White's Christmas Tree Farm",
    "wof:placetype":"venue"
},
  "geometry": {"coordinates":[-122.661467,45.151028],"type":"Point"}
}