{
  "type": "Feature",
  "properties": {
    "iso:country":"US",
    "sg:address":"2348 NW Lovejoy Street",
    "sg:city":"Portland",
    "sg:classifiers":[
        {
            "category":"Health Services",
            "subcategory":"Health Practitioner",
            "type":"Services"
        }
    ],
    "sg:phone":"+1 503 224 7224",
    "sg:postcode":"97210",
    "sg:province":"OR",
    "sg:tags":[
        "acupuncture"
    ],
    "wof:name":"Cory Cindy Lac",
    "wof:placetype":"venue"
},
  "geometry": {"coordinates":[-122.699501,45.529887],"type":"Point"}
}