{
  "type": "Feature",
  "properties": {
    "iso:country":"US",
    "sg:address":"1854 SW Angeline Ave",
    "sg:city":"Gresham",
    "sg:classifiers":[
        {
            "category":"Professional",
            "subcategory":"Business Services",
            "type":"Services"
        }
    ],
    "sg:phone":"+1 503 667 0431",
    "sg:postcode":"97080",
    "sg:province":"OR",
    "wof:name":"Dormandy & Neal Enterprises",
    "wof:placetype":"venue"
},
  "geometry": {"coordinates":[-122.448632,45.482936],"type":"Point"}
}