{
  "type": "Feature",
  "properties": {
    "iso:country":"US",
    "sg:address":"1815 NE 148th Ave",
    "sg:city":"Portland",
    "sg:classifiers":[
        {
            "category":"Real Estate",
            "subcategory":"Real Estate Operator",
            "type":"Services"
        }
    ],
    "sg:phone":"+1 503 255 0784",
    "sg:postcode":"97230",
    "sg:province":"OR",
    "sg:tags":[
        "property",
        "lessor"
    ],
    "wof:name":"Bensene Family LLC",
    "wof:placetype":"venue"
},
  "geometry": {"coordinates":[-122.510418,45.536885],"type":"Point"}
}