{
  "type": "Feature",
  "properties": {
    "iso:country":"US",
    "sg:address":"501 Main Ave",
    "sg:city":"Tillamook",
    "sg:classifiers":[
        {
            "category":"Autos & Motor Vehicles",
            "subcategory":"Automobile Sales",
            "type":"Retail Goods"
        }
    ],
    "sg:phone":"+1 503 842 4475",
    "sg:postcode":"97141",
    "sg:province":"OR",
    "sg:tags":[
        "car",
        "dealer"
    ],
    "sg:website":"www.dealersaway.com",
    "wof:name":"Tillamook Motor Co",
    "wof:placetype":"venue"
},
  "geometry": {"coordinates":[-123.843964,45.454861],"type":"Point"}
}