{
  "type": "Feature",
  "properties": {
    "iso:country":"US",
    "sg:address":"18302 SE Clinton St",
    "sg:city":"Gresham",
    "sg:classifiers":[
        {
            "category":"Building & Trades",
            "subcategory":"Construction",
            "type":"Services"
        }
    ],
    "sg:phone":"+1 503 667 3243",
    "sg:postcode":"97030",
    "sg:province":"OR",
    "sg:tags":[
        "contractor"
    ],
    "wof:name":"Vinyl Exteriors",
    "wof:placetype":"venue"
},
  "geometry": {"coordinates":[-122.47318,45.502626],"type":"Point"}
}