{
  "type": "Feature",
  "properties": {
    "iso:country":"US",
    "sg:address":"1585 N Pacific Hwy",
    "sg:city":"Woodburn",
    "sg:classifiers":[
        {
            "category":"Restaurant",
            "type":"Food & Drink"
        }
    ],
    "sg:phone":"+1 503 981 0645",
    "sg:postcode":"97071",
    "sg:province":"OR",
    "sg:tags":[
        "delicatessen"
    ],
    "wof:name":"Fonzi's Deli",
    "wof:placetype":"venue"
},
  "geometry": {"coordinates":[-122.83263100000001,45.149857],"type":"Point"}
}