{
  "type": "Feature",
  "properties": {
    "addr:full":"519 SW Park Avenue Portland OR 97204",
    "addr:housenumber":"519",
    "addr:postcode":"97204",
    "addr:street":"Sw Park Avenue",
    "iso:country":"US",
    "sg:address":"519 SW Park Avenue",
    "sg:city":"Portland",
    "sg:classifiers":[
        {
            "category":"Professional",
            "subcategory":"Computer Services",
            "type":"Services"
        }
    ],
    "sg:phone":"+1 347 537 2777",
    "sg:postcode":"97204",
    "sg:province":"OR",
    "sg:tags":[
        "web-app-development---ios-development---android-development---ruby-on-rails---web-apps"
    ],
    "sg:website":"http://www.re-mondes.com",
    "wof:name":"Re-Mondes",
    "wof:placetype":"venue"
},
  "geometry": {"coordinates":[-122.68024699999999,45.520422],"type":"Point"}
}