{
  "type": "Feature",
  "properties": {
    "iso:country":"US",
    "sg:address":"146 N 12th St",
    "sg:city":"Philomath",
    "sg:classifiers":[
        {
            "category":"Organizations",
            "subcategory":"Labor Organization",
            "type":"Services"
        }
    ],
    "sg:phone":"+1 541 929 5118",
    "sg:postcode":"97370",
    "sg:province":"OR",
    "wof:name":"Corvallis Education Assn",
    "wof:placetype":"venue"
},
  "geometry": {"coordinates":[-123.369269,44.540502],"type":"Point"}
}