{
  "type": "Feature",
  "properties": {
    "iso:country":"US",
    "sg:address":"5250 Linn Ln",
    "sg:city":"West Linn",
    "sg:classifiers":[
        {
            "category":"Home & Garden",
            "subcategory":"Hardware",
            "type":"Retail Goods"
        }
    ],
    "sg:phone":"+1 503 655 5862",
    "sg:postcode":"97068",
    "sg:province":"OR",
    "wof:name":"Damascus True Value Hardware",
    "wof:placetype":"venue"
},
  "geometry": {"coordinates":[-122.632925,45.367506],"type":"Point"}
}