{
  "type": "Feature",
  "properties": {
    "iso:country":"US",
    "sg:address":"13036 SE Stark St",
    "sg:city":"Portland",
    "sg:classifiers":[
        {
            "category":"Personal",
            "subcategory":"Tanning Parlor",
            "type":"Services"
        }
    ],
    "sg:phone":"+1 503 252 3669",
    "sg:postcode":"97233",
    "sg:province":"OR",
    "sg:tags":[
        "salon"
    ],
    "wof:name":"Tan Down Under",
    "wof:placetype":"venue"
},
  "geometry": {"coordinates":[-122.528737,45.519159],"type":"Point"}
}