{
  "type": "Feature",
  "properties": {
    "addr:full":"10760 SW Canyon Rd Beaverton OR 97005",
    "addr:housenumber":"10760",
    "addr:postcode":"97005",
    "addr:street":"Sw Canyon Rd",
    "iso:country":"US",
    "sg:address":"10760 SW Canyon Rd",
    "sg:city":"Beaverton",
    "sg:classifiers":[
        {
            "category":"Autos & Motor Vehicles",
            "subcategory":"Automobile Sales",
            "type":"Retail Goods"
        },
        {
            "category":"Autos & Motor Vehicles",
            "subcategory":"Auto Supplies",
            "type":"Retail Goods"
        },
        {
            "category":"Retail",
            "subcategory":"Auto Repair",
            "type":"Services"
        }
    ],
    "sg:phone":"+1 888 355 6752",
    "sg:postcode":"97005",
    "sg:province":"OR",
    "sg:tags":[
        "car",
        "part"
    ],
    "sg:website":"www.beavertonhonda.com",
    "wof:name":"Beaverton Honda",
    "wof:placetype":"venue"
},
  "geometry": {"coordinates":[-122.787678,45.490961],"type":"Point"}
}