{
  "type": "Feature",
  "properties": {
    "addr:full":"5409 SE Center St Portland OR 97206",
    "addr:housenumber":"5409",
    "addr:postcode":"97206",
    "addr:street":"Se Center St",
    "iso:country":"US",
    "sg:address":"5409 SE Center St",
    "sg:city":"Portland",
    "sg:classifiers":[
        {
            "category":"Professional",
            "subcategory":"Business Services",
            "type":"Services"
        }
    ],
    "sg:phone":"+1 503 774 6632",
    "sg:postcode":"97206",
    "sg:province":"OR",
    "wof:name":"NW Outdoor Sales Inc",
    "wof:placetype":"venue"
},
  "geometry": {"coordinates":[-122.605452,45.493955],"type":"Point"}
}