{
  "type": "Feature",
  "properties": {
    "iso:country":"US",
    "sg:address":"51 NE Holladay St",
    "sg:city":"Portland",
    "sg:classifiers":[
        {
            "category":"Restaurant",
            "type":"Food & Drink"
        }
    ],
    "sg:phone":"+1 503 232 4276",
    "sg:postcode":"97232",
    "sg:province":"OR",
    "sg:tags":[
        "shop",
        "coffee"
    ],
    "wof:name":"Sharif's Coffee",
    "wof:placetype":"venue"
},
  "geometry": {"coordinates":[-122.665341,45.530088],"type":"Point"}
}