{
  "type": "Feature",
  "properties": {
    "addr:full":"1254 NE 2nd St Bend OR 97701",
    "addr:housenumber":"1254",
    "addr:postcode":"97701",
    "addr:street":"Ne 2Nd St",
    "iso:country":"US",
    "sg:address":"1254 NE 2nd St",
    "sg:city":"Bend",
    "sg:classifiers":[
        {
            "category":"Retail",
            "subcategory":"Auto Repair",
            "type":"Services"
        }
    ],
    "sg:phone":"+1 541 382 4127",
    "sg:postcode":"97701",
    "sg:province":"OR",
    "sg:tags":[
        "truck"
    ],
    "wof:name":"Fisher Fleet Repair",
    "wof:placetype":"venue"
},
  "geometry": {"coordinates":[-121.30382,44.062685],"type":"Point"}
}