{
  "type": "Feature",
  "properties": {
    "iso:country":"US",
    "sg:address":"4780 Crater Lake Ave",
    "sg:city":"Medford",
    "sg:classifiers":[
        {
            "category":"Professional",
            "subcategory":"Accounting & Tax Preparation",
            "type":"Services"
        }
    ],
    "sg:phone":"+1 541 858 9854",
    "sg:postcode":"97504",
    "sg:province":"OR",
    "wof:name":"Paper Trail Bookkeeping Svc",
    "wof:placetype":"venue"
},
  "geometry": {"coordinates":[-122.85557,42.387526],"type":"Point"}
}