{
  "type": "Feature",
  "properties": {
    "iso:country":"US",
    "sg:address":"13405 NW Cornell Rd",
    "sg:city":"Portland",
    "sg:classifiers":[
        {
            "category":"Professional",
            "subcategory":"Accounting & Tax Preparation",
            "type":"Services"
        }
    ],
    "sg:phone":"+1 503 646 5600",
    "sg:postcode":"97229",
    "sg:province":"OR",
    "sg:tags":[
        "accountant"
    ],
    "sg:website":"www.pnwtax.com",
    "wof:name":"Pacific Northwest Tax Service",
    "wof:placetype":"venue"
},
  "geometry": {"coordinates":[-122.81300400000001,45.526299],"type":"Point"}
}