{
  "type": "Feature",
  "properties": {
    "addr:full":"230 NW 6th St Grants Pass OR 97526",
    "addr:housenumber":"230",
    "addr:postcode":"97526",
    "addr:street":"Nw 6Th St",
    "iso:country":"US",
    "sg:address":"230 NW 6th St",
    "sg:city":"Grants Pass",
    "sg:classifiers":[
        {
            "category":"Retail",
            "subcategory":"Animal Services",
            "type":"Services"
        }
    ],
    "sg:phone":"+1 541 474 7297",
    "sg:postcode":"97526",
    "sg:province":"OR",
    "sg:tags":[
        "pet",
        "grooming",
        "washing"
    ],
    "wof:name":"Waggin' Tails Pet Shoppe",
    "wof:placetype":"venue"
},
  "geometry": {"coordinates":[-123.32644500000001,42.440262],"type":"Point"}
}