{
  "type": "Feature",
  "properties": {
    "iso:country":"US",
    "sg:address":"361 S Tarrybrook Ct",
    "sg:city":"Cornelius",
    "sg:classifiers":[
        {
            "category":"Wholesale",
            "subcategory":"Scrap",
            "type":"Manufacturing & Wholesale Goods"
        }
    ],
    "sg:phone":"+1 503 992 0224",
    "sg:postcode":"97113",
    "sg:province":"OR",
    "sg:tags":[
        "recycling",
        "center"
    ],
    "wof:name":"Northwest Anti Freeze Rcyclrs",
    "wof:placetype":"venue"
},
  "geometry": {"coordinates":[-123.067994,45.514707],"type":"Point"}
}