{
  "type": "Feature",
  "properties": {
    "addr:full":"1289 SE 2nd St Ontario OR 97914",
    "addr:housenumber":"1289",
    "addr:postcode":"97914",
    "addr:street":"Se 2Nd St",
    "iso:country":"US",
    "sg:address":"1289 SE 2nd St",
    "sg:city":"Ontario",
    "sg:classifiers":[
        {
            "category":"Manufacturing",
            "subcategory":"Tools & Machinery",
            "type":"Manufacturing & Wholesale Goods"
        }
    ],
    "sg:phone":"+1 541 889 8976",
    "sg:postcode":"97914",
    "sg:province":"OR",
    "sg:tags":[
        "equipment",
        "mfg"
    ],
    "wof:name":"Touch Of Oak By Yasuda",
    "wof:placetype":"venue"
},
  "geometry": {"coordinates":[-116.960656,44.0142],"type":"Point"}
}