{
  "type": "Feature",
  "properties": {
    "iso:country":"US",
    "sg:address":"18990 Sandlake Rd",
    "sg:city":"Cloverdale",
    "sg:classifiers":[
        {
            "category":"Farming",
            "subcategory":"Dairy Farm",
            "type":"Manufacturing & Wholesale Goods"
        }
    ],
    "sg:phone":"+1 503 965 6944",
    "sg:postcode":"97112",
    "sg:province":"OR",
    "wof:name":"Jack Daniel Farms",
    "wof:placetype":"venue"
},
  "geometry": {"coordinates":[-123.921967,45.318204],"type":"Point"}
}