{
  "type": "Feature",
  "properties": {
    "iso:country":"US",
    "sg:address":"339 Glen Ct",
    "sg:city":"Winston",
    "sg:classifiers":[
        {
            "category":"Professional",
            "subcategory":"Management & Consulting",
            "type":"Services"
        }
    ],
    "sg:phone":"+1 541 679 3973",
    "sg:postcode":"97496",
    "sg:province":"OR",
    "sg:tags":[
        "consultant",
        "training"
    ],
    "wof:name":"Douglas Resident Training",
    "wof:placetype":"venue"
},
  "geometry": {"coordinates":[-123.416222,43.126503],"type":"Point"}
}