{
  "type": "Feature",
  "properties": {
    "iso:country":"US",
    "sg:address":"1214 Wallace Rd NW",
    "sg:city":"Salem",
    "sg:classifiers":[
        {
            "category":"Retail",
            "subcategory":"Repair Shop",
            "type":"Services"
        }
    ],
    "sg:phone":"+1 503 763 1777",
    "sg:postcode":"97304",
    "sg:province":"OR",
    "sg:tags":[
        "drycleaning",
        "plant"
    ],
    "wof:name":"ABC Cleaners",
    "wof:placetype":"venue"
},
  "geometry": {"coordinates":[-123.052047,44.951838],"type":"Point"}
}