{
  "type": "Feature",
  "properties": {
    "iso:country":"US",
    "sg:address":"831 Lancaster Dr NE Ste 177",
    "sg:city":"Salem",
    "sg:classifiers":[
        {
            "category":"Shopping",
            "subcategory":"Clothing, Apparel, & Fashions",
            "type":"Retail Goods"
        },
        {
            "category":"Shopping",
            "subcategory":"Shoes",
            "type":"Retail Goods"
        }
    ],
    "sg:phone":"+1 503 362 9214",
    "sg:postcode":"97301",
    "sg:province":"OR",
    "sg:tags":[
        "sportswear",
        "store"
    ],
    "sg:website":"http://www.footlocker.com",
    "wof:name":"Foot Locker",
    "wof:placetype":"venue"
},
  "geometry": {"coordinates":[-122.98321199999999,44.941913],"type":"Point"}
}