{
  "type": "Feature",
  "properties": {
    "addr:full":"1736 SE 36th Ave Portland OR 97214",
    "addr:housenumber":"1736",
    "addr:postcode":"97214",
    "addr:street":"Se 36Th Ave",
    "iso:country":"US",
    "sg:address":"1736 SE 36th Ave",
    "sg:city":"Portland",
    "sg:classifiers":[
        {
            "category":"Professional",
            "type":"Services"
        }
    ],
    "sg:phone":"+1 503 232 6022",
    "sg:postcode":"97214",
    "sg:province":"OR",
    "wof:name":"Naillig",
    "wof:placetype":"venue"
},
  "geometry": {"coordinates":[-122.62657400000001,45.510343],"type":"Point"}
}