{
  "type": "Feature",
  "properties": {
    "iso:country":"US",
    "sg:address":"1714 Maple St",
    "sg:city":"Myrtle Point",
    "sg:classifiers":[
        {
            "category":"Building & Trades",
            "subcategory":"Construction",
            "type":"Services"
        }
    ],
    "sg:phone":"+1 541 572 2380",
    "sg:postcode":"97458",
    "sg:province":"OR",
    "sg:tags":[
        "carpentry",
        "product",
        "contractor",
        "mfg"
    ],
    "wof:name":"Uht Creative Crafts",
    "wof:placetype":"venue"
},
  "geometry": {"coordinates":[-124.13030999999999,43.063781],"type":"Point"}
}