{
  "type": "Feature",
  "properties": {
    "addr:full":"3217 NE 64th Ave Portland OR 97213",
    "addr:housenumber":"3217",
    "addr:postcode":"97213",
    "addr:street":"Ne 64Th Ave",
    "iso:country":"US",
    "sg:address":"3217 NE 64th Ave",
    "sg:city":"Portland",
    "sg:classifiers":[
        {
            "category":"Professional",
            "type":"Services"
        }
    ],
    "sg:phone":"+1 503 774 9800",
    "sg:postcode":"97213",
    "sg:province":"OR",
    "wof:name":"Portland First Aid",
    "wof:placetype":"venue"
},
  "geometry": {"coordinates":[-122.597436,45.545979],"type":"Point"}
}