{
  "type": "Feature",
  "properties": {
    "iso:country":"US",
    "sg:address":"32994 Hwy 99E",
    "sg:city":"Tangent",
    "sg:classifiers":[
        {
            "category":"Bars & Pubs",
            "type":"Food & Drink"
        }
    ],
    "sg:phone":"+1 541 926 2767",
    "sg:postcode":"97389",
    "sg:province":"OR",
    "sg:tags":[
        "drinking"
    ],
    "wof:name":"Dixie Creek Saloon",
    "wof:placetype":"venue"
},
  "geometry": {"coordinates":[-123.11013,44.542539],"type":"Point"}
}