{
  "type": "Feature",
  "properties": {
    "addr:full":"20 E 13th Ave Eugene OR 97401",
    "addr:housenumber":"20",
    "addr:postcode":"97401",
    "addr:street":"E 13Th Ave",
    "iso:country":"US",
    "sg:address":"20 E 13th Ave",
    "sg:city":"Eugene",
    "sg:classifiers":[
        {
            "category":"Social Services",
            "type":"Services"
        }
    ],
    "sg:phone":"+1 541 484 4428",
    "sg:postcode":"97401",
    "sg:province":"OR",
    "wof:name":"Looking Glass Counseling Ctr",
    "wof:placetype":"venue"
},
  "geometry": {"coordinates":[-123.092196,44.045444],"type":"Point"}
}