{
  "type": "Feature",
  "properties": {
    "iso:country":"US",
    "sg:address":"26515 S Hillockburn Rd",
    "sg:city":"Estacada",
    "sg:classifiers":[
        {
            "category":"Farming",
            "subcategory":"Livestock Farm",
            "type":"Manufacturing & Wholesale Goods"
        }
    ],
    "sg:phone":"+1 503 236 3766",
    "sg:postcode":"97023",
    "sg:province":"OR",
    "sg:tags":[
        "equine"
    ],
    "wof:name":"Wish Upon A Pony",
    "wof:placetype":"venue"
},
  "geometry": {"coordinates":[-122.31999500000001,45.221648],"type":"Point"}
}