{
  "type": "Feature",
  "properties": {
    "addr:full":"3955 SE 112th Ave Portland OR 97266",
    "addr:housenumber":"3955",
    "addr:postcode":"97266",
    "addr:street":"Se 112Th Ave",
    "iso:country":"US",
    "sg:address":"3955 SE 112th Ave",
    "sg:city":"Portland",
    "sg:classifiers":[
        {
            "category":"Building & Trades",
            "subcategory":"Construction",
            "type":"Services"
        }
    ],
    "sg:phone":"+1 503 760 0501",
    "sg:postcode":"97266",
    "sg:province":"OR",
    "sg:tags":[
        "contractor"
    ],
    "wof:name":"Skanska USA Builders",
    "wof:placetype":"venue"
},
  "geometry": {"coordinates":[-122.548057,45.494586],"type":"Point"}
}