{
  "type": "Feature",
  "properties": {
    "addr:full":"3902 NE Sandy Blvd Ste 100 Portland OR 97232",
    "addr:housenumber":"3902",
    "addr:postcode":"97232",
    "addr:street":"Ne Sandy Blvd Ste 100",
    "iso:country":"US",
    "sg:address":"3902 NE Sandy Blvd Ste 100",
    "sg:city":"Portland",
    "sg:classifiers":[
        {
            "category":"Banks & Credit Unions",
            "subcategory":"Financial Services",
            "type":"Services"
        }
    ],
    "sg:phone":"+1 503 659 9900",
    "sg:postcode":"97232",
    "sg:province":"OR",
    "sg:tags":[
        "loan",
        "mortgage"
    ],
    "wof:name":"Premier Mortgage Resources",
    "wof:placetype":"venue"
},
  "geometry": {"coordinates":[-122.62288700000001,45.53487],"type":"Point"}
}