{
  "type": "Feature",
  "properties": {
    "addr:full":"17620 Pilkington Rd Lake Oswego OR 97035",
    "addr:housenumber":"17620",
    "addr:postcode":"97035",
    "addr:street":"Pilkington Rd",
    "iso:country":"US",
    "sg:address":"17620 Pilkington Rd",
    "sg:city":"Lake Oswego",
    "sg:classifiers":[
        {
            "category":"Health Services",
            "subcategory":"Chiropractor",
            "type":"Services"
        }
    ],
    "sg:phone":"+1 503 636 2265",
    "sg:postcode":"97035",
    "sg:province":"OR",
    "sg:website":"www.lakegrovechiropractic.com",
    "wof:name":"Lake Grove Chiropractic",
    "wof:placetype":"venue"
},
  "geometry": {"coordinates":[-122.733088,45.398398],"type":"Point"}
}