{
  "type": "Feature",
  "properties": {
    "addr:full":"224 NW D St Grants Pass OR 97526",
    "addr:housenumber":"224",
    "addr:postcode":"97526",
    "addr:street":"Nw D St",
    "iso:country":"US",
    "sg:address":"224 NW D St",
    "sg:city":"Grants Pass",
    "sg:classifiers":[
        {
            "category":"Organizations",
            "subcategory":"Religious Organization",
            "type":"Services"
        }
    ],
    "sg:phone":"+1 541 476 2493",
    "sg:postcode":"97526",
    "sg:province":"OR",
    "wof:name":"St Lukes Episcopal Church",
    "wof:placetype":"venue"
},
  "geometry": {"coordinates":[-123.32786299999999,42.442212],"type":"Point"}
}