{
  "type": "Feature",
  "properties": {
    "iso:country":"US",
    "sg:address":"1498 Bay St",
    "sg:city":"Florence",
    "sg:classifiers":[
        {
            "category":"Bars & Pubs",
            "type":"Food & Drink"
        },
        {
            "category":"Restaurant",
            "type":"Food & Drink"
        },
        {
            "category":"Bars & Pubs",
            "subcategory":"Lounge",
            "type":"Food & Drink"
        }
    ],
    "sg:phone":"+1 541 997 7978",
    "sg:postcode":"97439",
    "sg:province":"OR",
    "sg:tags":[
        "seafood",
        "cocktail"
    ],
    "wof:name":"I C M",
    "wof:placetype":"venue"
},
  "geometry": {"coordinates":[-124.104286,43.967072],"type":"Point"}
}