{
  "type": "Feature",
  "properties": {
    "iso:country":"US",
    "sg:address":"579 Lancaster Dr NE",
    "sg:city":"Salem",
    "sg:classifiers":[
        {
            "category":"Personal",
            "subcategory":"Beauty Salon",
            "type":"Services"
        }
    ],
    "sg:phone":"+1 503 363 3836",
    "sg:postcode":"97301",
    "sg:province":"OR",
    "sg:tags":[
        "shop",
        "fitness",
        "physical",
        "facility"
    ],
    "wof:name":"Mr Charles Styling Salon",
    "wof:placetype":"venue"
},
  "geometry": {"coordinates":[-122.983112,44.937422],"type":"Point"}
}