{
  "type": "Feature",
  "properties": {
    "iso:country":"US",
    "sg:address":"4710 SW Kelly Ave",
    "sg:city":"Portland",
    "sg:phone":"+1 503 595 5550",
    "sg:postcode":"97239",
    "sg:province":"OR",
    "wof:name":"Engaging Media Inc",
    "wof:placetype":"venue"
},
  "geometry": {"coordinates":[-122.674713,45.489144],"type":"Point"}
}