{
  "type": "Feature",
  "properties": {
    "addr:full":"1163 NE 3rd Ave Hillsboro OR 97124",
    "addr:housenumber":"1163",
    "addr:postcode":"97124",
    "addr:street":"Ne 3Rd Ave",
    "iso:country":"US",
    "sg:address":"1163 NE 3rd Ave",
    "sg:city":"Hillsboro",
    "sg:classifiers":[
        {
            "category":"Building & Trades",
            "subcategory":"Construction",
            "type":"Services"
        }
    ],
    "sg:phone":"+1 503 681 2079",
    "sg:postcode":"97124",
    "sg:province":"OR",
    "sg:tags":[
        "house"
    ],
    "wof:name":"Gcl Construction",
    "wof:placetype":"venue"
},
  "geometry": {"coordinates":[-122.98592600000001,45.531815],"type":"Point"}
}