{
  "type": "Feature",
  "properties": {
    "iso:country":"US",
    "sg:address":"4886 Silverton Rd NE",
    "sg:city":"Salem",
    "sg:classifiers":[
        {
            "category":"Real Estate",
            "subcategory":"Real Estate Operator",
            "type":"Services"
        }
    ],
    "sg:phone":"+1 503 581 3194",
    "sg:postcode":"97305",
    "sg:province":"OR",
    "sg:tags":[
        "building",
        "apartment"
    ],
    "wof:name":"Middlegrove Apartments",
    "wof:placetype":"venue"
},
  "geometry": {"coordinates":[-122.963549,44.9695],"type":"Point"}
}