{
  "type": "Feature",
  "properties": {
    "addr:full":"9722 SE Washington Street Portland OR 97216",
    "addr:housenumber":"9722",
    "addr:postcode":"97216",
    "addr:street":"Se Washington Street",
    "iso:country":"US",
    "sg:address":"9722 SE Washington Street",
    "sg:city":"Portland",
    "sg:classifiers":[
        {
            "category":"Restaurant",
            "type":"Food & Drink"
        }
    ],
    "sg:phone":"+1 503 255 2722",
    "sg:postcode":"97216",
    "sg:province":"OR",
    "sg:tags":[
        "seafood"
    ],
    "wof:name":"Newport Bay Restaurants",
    "wof:placetype":"venue"
},
  "geometry": {"coordinates":[-122.56291899999999,45.518215],"type":"Point"}
}