{
  "type": "Feature",
  "properties": {
    "iso:country":"US",
    "sg:address":"5935 N Minnesota Ave",
    "sg:city":"Portland",
    "sg:classifiers":[
        {
            "category":"Organizations",
            "subcategory":"Religious Organization",
            "type":"Services"
        }
    ],
    "sg:phone":"+1 503 289 2364",
    "sg:postcode":"97217",
    "sg:province":"OR",
    "sg:tags":[
        "church"
    ],
    "wof:name":"Antioch Missionary Baptist Chr",
    "wof:placetype":"venue"
},
  "geometry": {"coordinates":[-122.67921699999999,45.56609],"type":"Point"}
}