{
  "type": "Feature",
  "properties": {
    "iso:country":"US",
    "sg:address":"17530 NE Terrys Ln",
    "sg:city":"Newberg",
    "sg:classifiers":[
        {
            "category":"Retail",
            "subcategory":"Auto Repair",
            "type":"Services"
        }
    ],
    "sg:phone":"+1 503 554 9048",
    "sg:postcode":"97132",
    "sg:province":"OR",
    "sg:tags":[
        "repairing",
        "automobile",
        "general"
    ],
    "wof:name":"V G I Engine Specialists",
    "wof:placetype":"venue"
},
  "geometry": {"coordinates":[-123.05825,45.323507],"type":"Point"}
}