{
  "type": "Feature",
  "properties": {
    "iso:country":"US",
    "sg:address":"307 NE Broadway",
    "sg:city":"Portland",
    "sg:classifiers":[
        {
            "category":"Autos & Motor Vehicles",
            "subcategory":"Automobile Sales",
            "type":"Retail Goods"
        }
    ],
    "sg:phone":"+1 503 542 0404",
    "sg:postcode":"97232",
    "sg:province":"OR",
    "sg:tags":[
        "car"
    ],
    "wof:name":"Broadway Kia",
    "wof:placetype":"venue"
},
  "geometry": {"coordinates":[-122.66259599999999,45.535106],"type":"Point"}
}