{
  "type": "Feature",
  "properties": {
    "iso:country":"US",
    "sg:address":"1825 Front St NE",
    "sg:city":"Salem",
    "sg:classifiers":[
        {
            "category":"Manufacturing",
            "subcategory":"Signs",
            "type":"Manufacturing & Wholesale Goods"
        }
    ],
    "sg:phone":"+1 503 371 6362",
    "sg:postcode":"97301",
    "sg:province":"OR",
    "sg:tags":[
        "mfg",
        "advertising",
        "specialty"
    ],
    "wof:name":"Salem Sign Co Inc",
    "wof:placetype":"venue"
},
  "geometry": {"coordinates":[-123.034187,44.958265],"type":"Point"}
}