{
  "type": "Feature",
  "properties": {
    "iso:country":"US",
    "sg:address":"14107 SE Redwood Ave",
    "sg:city":"Oak Grove",
    "sg:classifiers":[
        {
            "category":"Health Services",
            "subcategory":"Nursing And Care Facility",
            "type":"Services"
        }
    ],
    "sg:phone":"+1 503 659 1077",
    "sg:postcode":"97267",
    "sg:province":"OR",
    "sg:tags":[
        "home",
        "retirement",
        "community"
    ],
    "wof:name":"Milwaukee Care Ctr",
    "wof:placetype":"venue"
},
  "geometry": {"coordinates":[-122.631317,45.421341],"type":"Point"}
}