{
  "type": "Feature",
  "properties": {
    "addr:full":"869 NW Eastwind Dr Troutdale OR 97060",
    "addr:housenumber":"869",
    "addr:postcode":"97060",
    "addr:street":"Nw Eastwind Dr",
    "iso:country":"US",
    "sg:address":"869 NW Eastwind Dr",
    "sg:city":"Troutdale",
    "sg:classifiers":[
        {
            "category":"Utilities",
            "subcategory":"Refuse",
            "type":"Services"
        }
    ],
    "sg:phone":"+1 503 667 5264",
    "sg:postcode":"97060",
    "sg:province":"OR",
    "sg:tags":[
        "system"
    ],
    "wof:name":"Recycle Amer A Svc Waste Manag",
    "wof:placetype":"venue"
},
  "geometry": {"coordinates":[-122.41590100000001,45.547276],"type":"Point"}
}