{
  "type": "Feature",
  "properties": {
    "iso:country":"US",
    "sg:address":"220 NW 29th St",
    "sg:city":"Corvallis",
    "sg:classifiers":[
        {
            "category":"Manufacturing",
            "subcategory":"Printing",
            "type":"Manufacturing & Wholesale Goods"
        }
    ],
    "sg:phone":"+1 541 758 5760",
    "sg:postcode":"97330",
    "sg:province":"OR",
    "sg:tags":[
        "music",
        "book",
        "sheet",
        "publishing"
    ],
    "wof:name":"Earthsongs",
    "wof:placetype":"venue"
},
  "geometry": {"coordinates":[-123.283731,44.570581],"type":"Point"}
}