{
  "type": "Feature",
  "properties": {
    "iso:country":"US",
    "sg:address":"270 E Oregon Ave",
    "sg:city":"Creswell",
    "sg:classifiers":[
        {
            "category":"Restaurant",
            "type":"Food & Drink"
        }
    ],
    "sg:phone":"+1 541 895 5565",
    "sg:postcode":"97426",
    "sg:province":"OR",
    "wof:name":"Brown Dog Deli",
    "wof:placetype":"venue"
},
  "geometry": {"coordinates":[-123.017176,43.91794],"type":"Point"}
}