{
  "type": "Feature",
  "properties": {
    "iso:country":"US",
    "sg:address":"674 Stearman St",
    "sg:city":"Independence",
    "sg:classifiers":[
        {
            "category":"Airline",
            "type":"Transportation"
        }
    ],
    "sg:phone":"+1 503 838 5286",
    "sg:postcode":"97351",
    "sg:province":"OR",
    "sg:tags":[
        "courier",
        "air"
    ],
    "wof:name":"Hml Air Services",
    "wof:placetype":"venue"
},
  "geometry": {"coordinates":[-123.19614900000001,44.869507],"type":"Point"}
}