{
  "type": "Feature",
  "properties": {
    "addr:full":"1200 NE Broadway St Portland OR 97232",
    "addr:housenumber":"1200",
    "addr:postcode":"97232",
    "addr:street":"Ne Broadway St",
    "iso:country":"US",
    "sg:address":"1200 NE Broadway St",
    "sg:city":"Portland",
    "sg:classifiers":[
        {
            "category":"Building & Trades",
            "subcategory":"Locksmith",
            "type":"Services"
        }
    ],
    "sg:phone":"+1 503 867 8214",
    "sg:postcode":"97232",
    "sg:province":"OR",
    "sg:tags":[
        "key"
    ],
    "wof:name":"24 Hour Emergency Locksmith",
    "wof:placetype":"venue"
},
  "geometry": {"coordinates":[-122.65318499999999,45.534913],"type":"Point"}
}