{
  "type": "Feature",
  "properties": {
    "addr:full":"1495 Edgewater St NW Suite 125 Salem OR 97304",
    "addr:housenumber":"1495",
    "addr:postcode":"97304",
    "addr:street":"Edgewater St Nw Suite 125",
    "iso:country":"US",
    "sg:address":"1495 Edgewater St NW Suite 125",
    "sg:city":"Salem",
    "sg:classifiers":[
        {
            "category":"Airline",
            "type":"Transportation"
        },
        {
            "category":"Travel",
            "subcategory":"Travel Agent",
            "type":"Entertainment"
        }
    ],
    "sg:phone":"+1 503 877 5904",
    "sg:postcode":"97304",
    "sg:province":"OR",
    "sg:tags":[
        "agency"
    ],
    "sg:website":"http://www.travelbureausalem.com",
    "wof:name":"Travel Bureau",
    "wof:placetype":"venue"
},
  "geometry": {"coordinates":[-123.06370099999999,44.937883],"type":"Point"}
}