{
  "type": "Feature",
  "properties": {
    "iso:country":"US",
    "sg:address":"622 Pine Ave",
    "sg:city":"Coos Bay",
    "sg:classifiers":[
        {
            "category":"Freight",
            "type":"Transportation"
        }
    ],
    "sg:phone":"+1 541 269 2015",
    "sg:postcode":"97420",
    "sg:province":"OR",
    "sg:tags":[
        "operator",
        "trucking"
    ],
    "wof:name":"TP Freight Lines",
    "wof:placetype":"venue"
},
  "geometry": {"coordinates":[-124.221359,43.382704],"type":"Point"}
}