{
  "type": "Feature",
  "properties": {
    "addr:full":"18890 Pinehurst Rd Bend OR 97701",
    "addr:housenumber":"18890",
    "addr:postcode":"97701",
    "addr:street":"Pinehurst Rd",
    "iso:country":"US",
    "sg:address":"18890 Pinehurst Rd",
    "sg:city":"Bend",
    "sg:classifiers":[
        {
            "category":"Autos & Motor Vehicles",
            "subcategory":"Auto Supplies",
            "type":"Retail Goods"
        }
    ],
    "sg:phone":"+1 541 382 7488",
    "sg:postcode":"97701",
    "sg:province":"OR",
    "sg:tags":[
        "automobile",
        "part"
    ],
    "sg:website":"http://www.eztouring.com",
    "wof:name":"E Z Touring",
    "wof:placetype":"venue"
},
  "geometry": {"coordinates":[-121.378141,44.152793],"type":"Point"}
}