{
  "type": "Feature",
  "properties": {
    "addr:full":"2938 SE Laura Ave Gresham OR 97080",
    "addr:housenumber":"2938",
    "addr:postcode":"97080",
    "addr:street":"Se Laura Ave",
    "iso:country":"US",
    "sg:address":"2938 SE Laura Ave",
    "sg:city":"Gresham",
    "sg:classifiers":[
        {
            "category":"Professional",
            "subcategory":"Management & Consulting",
            "type":"Services"
        }
    ],
    "sg:phone":"+1 503 201 3707",
    "sg:postcode":"97080",
    "sg:province":"OR",
    "sg:tags":[
        "consultant"
    ],
    "wof:name":"Sbsi",
    "wof:placetype":"venue"
},
  "geometry": {"coordinates":[-122.389628,45.475991],"type":"Point"}
}