{
  "type": "Feature",
  "properties": {
    "addr:full":"8787 SW Spruce St Portland OR 97223",
    "addr:housenumber":"8787",
    "addr:postcode":"97223",
    "addr:street":"Sw Spruce St",
    "iso:country":"US",
    "sg:address":"8787 SW Spruce St",
    "sg:city":"Portland",
    "sg:classifiers":[
        {
            "category":"Social Services",
            "subcategory":"Adult Care",
            "type":"Services"
        }
    ],
    "sg:phone":"+1 503 246 0484",
    "sg:postcode":"97223",
    "sg:province":"OR",
    "sg:tags":[
        "residential"
    ],
    "wof:name":"Marias A F H II",
    "wof:placetype":"venue"
},
  "geometry": {"coordinates":[-122.766845,45.442158],"type":"Point"}
}