{
  "type": "Feature",
  "properties": {
    "iso:country":"US",
    "sg:address":"5550 NW Innisbrook Pl",
    "sg:city":"Portland",
    "sg:classifiers":[
        {
            "category":"Building & Trades",
            "subcategory":"Cleaning & Sanitation",
            "type":"Services"
        }
    ],
    "sg:phone":"+1 503 617 9129",
    "sg:postcode":"97229",
    "sg:province":"OR",
    "sg:tags":[
        "janitorial"
    ],
    "wof:name":"Angel Cleaning",
    "wof:placetype":"venue"
},
  "geometry": {"coordinates":[-122.88293299999999,45.558966],"type":"Point"}
}