{
  "type": "Feature",
  "properties": {
    "iso:country":"US",
    "sg:address":"7975 SW Nyberg St",
    "sg:city":"Tualatin",
    "sg:classifiers":[
        {
            "category":"Banks & Credit Unions",
            "subcategory":"Bank",
            "type":"Services"
        }
    ],
    "sg:phone":"+1 503 885 1911",
    "sg:postcode":"97062",
    "sg:province":"OR",
    "sg:tags":[
        "depository",
        "banking"
    ],
    "wof:name":"Check Into Cash",
    "wof:placetype":"venue"
},
  "geometry": {"coordinates":[-122.75922300000001,45.38271],"type":"Point"}
}