{
  "type": "Feature",
  "properties": {
    "iso:country":"US",
    "sg:address":"187 SW Court St",
    "sg:city":"Dallas",
    "sg:classifiers":[
        {
            "category":"Social Services",
            "type":"Services"
        }
    ],
    "sg:phone":"+1 503 623 6419",
    "sg:postcode":"97338",
    "sg:province":"OR",
    "sg:tags":[
        "youth",
        "organization",
        "center"
    ],
    "wof:name":"Kids Inc",
    "wof:placetype":"venue"
},
  "geometry": {"coordinates":[-123.31702300000001,44.920407],"type":"Point"}
}