{
  "type": "Feature",
  "properties": {
    "iso:country":"US",
    "sg:address":"4287 SE International Way",
    "sg:city":"Portland",
    "sg:classifiers":[
        {
            "category":"Shopping",
            "subcategory":"Gifts & Souvenirs",
            "type":"Retail Goods"
        }
    ],
    "sg:phone":"+1 503 723 7578",
    "sg:postcode":"97222",
    "sg:province":"OR",
    "sg:tags":[
        "flower"
    ],
    "wof:name":"Rkd Premium Products Inc",
    "wof:placetype":"venue"
},
  "geometry": {"coordinates":[-122.61900300000001,45.438202],"type":"Point"}
}