{
  "type": "Feature",
  "properties": {
    "addr:full":"160 NW 2nd St Hermiston OR 97838",
    "addr:housenumber":"160",
    "addr:postcode":"97838",
    "addr:street":"Nw 2Nd St",
    "iso:country":"US",
    "sg:address":"160 NW 2nd St",
    "sg:city":"Hermiston",
    "sg:classifiers":[
        {
            "category":"Organizations",
            "subcategory":"Community Association",
            "type":"Services"
        }
    ],
    "sg:phone":"+1 541 567 2909",
    "sg:postcode":"97838",
    "sg:province":"OR",
    "sg:tags":[
        "club"
    ],
    "wof:name":"Eagles Lodge",
    "wof:placetype":"venue"
},
  "geometry": {"coordinates":[-119.293423,45.84166],"type":"Point"}
}