{
  "type": "Feature",
  "properties": {
    "iso:country":"US",
    "sg:address":"1380 Walton Way",
    "sg:city":"Woodburn",
    "sg:classifiers":[
        {
            "category":"Government",
            "subcategory":"Office",
            "type":"Public Place"
        }
    ],
    "sg:phone":"+1 503 981 3483",
    "sg:postcode":"97071",
    "sg:province":"OR",
    "sg:tags":[
        "international",
        "affairs"
    ],
    "wof:name":"In Depth Enterprizes",
    "wof:placetype":"venue"
},
  "geometry": {"coordinates":[-122.86422399999999,45.15298],"type":"Point"}
}