{
  "type": "Feature",
  "properties": {
    "iso:country":"US",
    "sg:address":"3500 NW Glenridge Dr",
    "sg:city":"Corvallis",
    "sg:classifiers":[
        {
            "category":"Professional",
            "subcategory":"Engineering",
            "type":"Services"
        }
    ],
    "sg:phone":"+1 541 752 9651",
    "sg:postcode":"97330",
    "sg:province":"OR",
    "sg:tags":[
        "management",
        "marine"
    ],
    "wof:name":"Eager & Associates",
    "wof:placetype":"venue"
},
  "geometry": {"coordinates":[-123.302056,44.601782],"type":"Point"}
}