{
  "type": "Feature",
  "properties": {
    "addr:full":"19137 SE Stark St Portland OR 97233",
    "addr:postcode":"19137;97233",
    "addr:street":"Se Stark St",
    "iso:country":"US",
    "sg:address":"19137 SE Stark St",
    "sg:city":"Portland",
    "sg:classifiers":[
        {
            "category":"Shopping",
            "type":"Retail Goods"
        }
    ],
    "sg:phone":"+1 503 669 8070",
    "sg:postcode":"97233",
    "sg:province":"OR",
    "sg:tags":[
        "hearing",
        "equipment",
        "supply",
        "impaired"
    ],
    "wof:name":"Mt Hood Hearing Aid Clinic",
    "wof:placetype":"venue"
},
  "geometry": {"coordinates":[-122.46625299999999,45.519231],"type":"Point"}
}