{
  "type": "Feature",
  "properties": {
    "iso:country":"US",
    "sg:address":"1830 Tamarack Way",
    "sg:city":"Forest Grove",
    "sg:classifiers":[
        {
            "category":"Insurance",
            "subcategory":"Insurance Agent",
            "type":"Services"
        }
    ],
    "sg:phone":"+1 503 359 7532",
    "sg:postcode":"97116",
    "sg:province":"OR",
    "wof:name":"Dna Insurance Inc",
    "wof:placetype":"venue"
},
  "geometry": {"coordinates":[-123.07928099999999,45.517442],"type":"Point"}
}