{
  "type": "Feature",
  "properties": {
    "addr:full":"310 NW 6th Avenue Portland OR 97209",
    "addr:housenumber":"310",
    "addr:postcode":"97209",
    "addr:street":"Nw 6Th Avenue",
    "iso:country":"US",
    "sg:address":"310 NW 6th Avenue",
    "sg:city":"Portland",
    "sg:classifiers":[
        {
            "category":"Real Estate",
            "subcategory":"Real Estate Operator",
            "type":"Services"
        }
    ],
    "sg:phone":"+1 503 228 4550",
    "sg:postcode":"97209",
    "sg:province":"OR",
    "sg:tags":[
        "apartment"
    ],
    "wof:name":"Biltmore Apartments",
    "wof:placetype":"venue"
},
  "geometry": {"coordinates":[-122.68429500000001,45.52693],"type":"Point"}
}