{
  "type": "Feature",
  "properties": {
    "addr:full":"4134 N Vancouver Ave Portland OR 97217",
    "addr:housenumber":"4134",
    "addr:postcode":"97217",
    "addr:street":"N Vancouver Ave",
    "iso:country":"US",
    "sg:address":"4134 N Vancouver Ave",
    "sg:city":"Portland",
    "sg:classifiers":[
        {
            "category":"Shopping",
            "subcategory":"Stationery & Office Supplies",
            "type":"Retail Goods"
        },
        {
            "category":"Wholesale",
            "subcategory":"Office Equipment",
            "type":"Manufacturing & Wholesale Goods"
        }
    ],
    "sg:phone":"+1 503 546 0439",
    "sg:postcode":"97217",
    "sg:province":"OR",
    "sg:tags":[
        "equipment-wholesale",
        "manufacturer",
        "furniture"
    ],
    "wof:name":"Indian Country Office Products, Inc.",
    "wof:placetype":"venue"
},
  "geometry": {"coordinates":[-122.667957,45.553544],"type":"Point"}
}