{
  "type": "Feature",
  "properties": {
    "iso:country":"US",
    "sg:address":"1797 SW Pleasant View Dr",
    "sg:city":"Gresham",
    "sg:classifiers":[
        {
            "category":"Home & Garden",
            "subcategory":"Garden Supply",
            "type":"Retail Goods"
        }
    ],
    "sg:phone":"+1 971 570 4511",
    "sg:postcode":"97080",
    "sg:province":"OR",
    "sg:tags":[
        "lawn",
        "mower"
    ],
    "wof:name":"Master-Tech",
    "wof:placetype":"venue"
},
  "geometry": {"coordinates":[-122.467645,45.486003],"type":"Point"}
}