{
  "type": "Feature",
  "properties": {
    "addr:full":"863 E Powell Blvd Gresham OR 97030",
    "addr:housenumber":"863",
    "addr:postcode":"97030",
    "addr:street":"E Powell Blvd",
    "iso:country":"US",
    "sg:address":"863 E Powell Blvd",
    "sg:city":"Gresham",
    "sg:classifiers":[
        {
            "category":"Food & Beverages",
            "subcategory":"Specialty",
            "type":"Retail Goods"
        }
    ],
    "sg:phone":"+1 503 492 5643",
    "sg:postcode":"97030",
    "sg:province":"OR",
    "wof:name":"Legal Addiction Espresso",
    "wof:placetype":"venue"
},
  "geometry": {"coordinates":[-122.421406,45.498096],"type":"Point"}
}