{
  "type": "Feature",
  "properties": {
    "iso:country":"US",
    "sg:address":"221 B St",
    "sg:city":"Springfield",
    "sg:classifiers":[
        {
            "category":"Social Services",
            "subcategory":"Child Care",
            "type":"Services"
        }
    ],
    "sg:phone":"+1 541 747 2425",
    "sg:postcode":"97477",
    "sg:province":"OR",
    "sg:tags":[
        "start",
        "head",
        "center"
    ],
    "wof:name":"Head Start Of Lane County",
    "wof:placetype":"venue"
},
  "geometry": {"coordinates":[-123.02234199999999,44.047876],"type":"Point"}
}