{
  "type": "Feature",
  "properties": {
    "iso:country":"US",
    "sg:address":"168 NE 167th Pl",
    "sg:city":"Portland",
    "sg:classifiers":[
        {
            "category":"Building & Trades",
            "subcategory":"Construction",
            "type":"Services"
        }
    ],
    "sg:phone":"+1 503 761 2000",
    "sg:postcode":"97230",
    "sg:province":"OR",
    "sg:tags":[
        "general",
        "painting",
        "painter",
        "contractor"
    ],
    "wof:name":"Portland Painting Inc",
    "wof:placetype":"venue"
},
  "geometry": {"coordinates":[-122.49072099999999,45.524377],"type":"Point"}
}