{
  "type": "Feature",
  "properties": {
    "iso:country":"US",
    "sg:address":"39120 Mountain Man Ln",
    "sg:city":"Lebanon",
    "sg:classifiers":[
        {
            "category":"Professional",
            "subcategory":"Business Services",
            "type":"Services"
        }
    ],
    "sg:phone":"+1 541 259 3241",
    "sg:postcode":"97355",
    "sg:province":"OR",
    "wof:name":"Mountain Man Enterprises",
    "wof:placetype":"venue"
},
  "geometry": {"coordinates":[-122.83064,44.526667],"type":"Point"}
}