{
  "type": "Feature",
  "properties": {
    "iso:country":"US",
    "sg:address":"11811 SE Highway 212 Building A1",
    "sg:city":"Clackamas",
    "sg:classifiers":[
        {
            "category":"Manufacturing",
            "subcategory":"Chemicals & Compounds",
            "type":"Manufacturing & Wholesale Goods"
        },
        {
            "category":"Building & Trades",
            "subcategory":"Cleaning & Sanitation",
            "type":"Services"
        },
        {
            "category":"Retail",
            "subcategory":"Auto Repair",
            "type":"Services"
        }
    ],
    "sg:phone":"+1 503 784 0989",
    "sg:postcode":"97015",
    "sg:province":"OR",
    "sg:tags":[
        "body",
        "classic",
        "automobile",
        "metal",
        "paint",
        "sandblasting",
        "removing",
        "painting",
        "repairing",
        "restoration-antique"
    ],
    "wof:name":"A-Diversified Blasting Company",
    "wof:placetype":"venue"
},
  "geometry": {"coordinates":[-122.541563,45.407864],"type":"Point"}
}