{
  "type": "Feature",
  "properties": {
    "addr:full":"233 Jackson Creek Rd Tiller OR 97484",
    "addr:housenumber":"233",
    "addr:postcode":"97484",
    "addr:street":"Jackson Creek Rd",
    "iso:country":"US",
    "sg:address":"233 Jackson Creek Rd",
    "sg:city":"Tiller",
    "sg:classifiers":[
        {
            "category":"Travel",
            "subcategory":"Campground",
            "type":"Entertainment"
        }
    ],
    "sg:phone":"+1 541 825 3271",
    "sg:postcode":"97484",
    "sg:province":"OR",
    "sg:tags":[
        "trailer"
    ],
    "wof:name":"Kalles Family Ranch",
    "wof:placetype":"venue"
},
  "geometry": {"coordinates":[-122.879313,42.969132],"type":"Point"}
}