{
  "type": "Feature",
  "properties": {
    "iso:country":"US",
    "sg:address":"4812 S Pacific Hwy",
    "sg:city":"Phoenix",
    "sg:classifiers":[
        {
            "category":"Place Of Worship",
            "subcategory":"Church",
            "type":"Public Place"
        },
        {
            "category":"Place Of Worship",
            "type":"Public Place"
        }
    ],
    "sg:phone":"+1 541 535 3350",
    "sg:postcode":"97535",
    "sg:province":"OR",
    "sg:tags":[
        "churches-interdenominational",
        "churches-various",
        "denomination"
    ],
    "wof:name":"South Valley Church Inc",
    "wof:placetype":"venue"
},
  "geometry": {"coordinates":[-122.81138,42.270151],"type":"Point"}
}