{
  "type": "Feature",
  "properties": {
    "iso:country":"US",
    "sg:address":"5315 SE Division St",
    "sg:city":"Portland",
    "sg:classifiers":[
        {
            "category":"Professional",
            "subcategory":"Art Services",
            "type":"Services"
        }
    ],
    "sg:phone":"+1 503 753 9359",
    "sg:postcode":"97206",
    "sg:province":"OR",
    "sg:tags":[
        "commercial",
        "design"
    ],
    "wof:name":"Utz Creative LLC",
    "wof:placetype":"venue"
},
  "geometry": {"coordinates":[-122.60714299999999,45.505401],"type":"Point"}
}