{
  "type": "Feature",
  "properties": {
    "iso:country":"US",
    "sg:address":"1311 SW Park Ave",
    "sg:city":"Portland",
    "sg:classifiers":[
        {
            "category":"Professional",
            "subcategory":"Business Services",
            "type":"Services"
        }
    ],
    "sg:phone":"+1 503 241 2150",
    "sg:postcode":"97201",
    "sg:province":"OR",
    "wof:name":"Applied Proactive Technologies",
    "wof:placetype":"venue"
},
  "geometry": {"coordinates":[-122.683026,45.514988],"type":"Point"}
}