{
  "type": "Feature",
  "properties": {
    "iso:country":"US",
    "sg:address":"720 NE Grand Ave",
    "sg:city":"Portland",
    "sg:classifiers":[
        {
            "category":"Building & Trades",
            "subcategory":"Locksmith",
            "type":"Services"
        }
    ],
    "sg:phone":"+1 971 327 9848",
    "sg:postcode":"97232",
    "sg:province":"OR",
    "sg:tags":[
        "key"
    ],
    "wof:name":"24 7 Lockout Locksmith",
    "wof:placetype":"venue"
},
  "geometry": {"coordinates":[-122.660472,45.528097],"type":"Point"}
}