{
  "type": "Feature",
  "properties": {
    "addr:full":"601 1st St Lake Oswego OR 97034",
    "addr:housenumber":"601",
    "addr:postcode":"97034",
    "addr:street":"1St St",
    "iso:country":"US",
    "sg:address":"601 1st St",
    "sg:city":"Lake Oswego",
    "sg:classifiers":[
        {
            "category":"Health Services",
            "subcategory":"Chiropractor",
            "type":"Services"
        }
    ],
    "sg:phone":"+1 503 636 6600",
    "sg:postcode":"97034",
    "sg:province":"OR",
    "wof:name":"OREGON Natural Health Clinic",
    "wof:placetype":"venue"
},
  "geometry": {"coordinates":[-122.663403,45.423169],"type":"Point"}
}