{
  "type": "Feature",
  "properties": {
    "iso:country":"US",
    "sg:address":"25400 S Beeson Rd",
    "sg:city":"Beavercreek",
    "sg:classifiers":[
        {
            "category":"Farming",
            "subcategory":"Farm",
            "type":"Manufacturing & Wholesale Goods"
        }
    ],
    "sg:phone":"+1 503 632 8005",
    "sg:postcode":"97004",
    "sg:province":"OR",
    "sg:tags":[
        "food",
        "covered",
        "crop"
    ],
    "wof:name":"Beeson Hill Farms",
    "wof:placetype":"venue"
},
  "geometry": {"coordinates":[-122.429476,45.238874],"type":"Point"}
}