{
  "type": "Feature",
  "properties": {
    "iso:country":"US",
    "sg:address":"2003 1st St",
    "sg:city":"Condon",
    "sg:classifiers":[
        {
            "category":"Wholesale",
            "subcategory":"Farm Supplies",
            "type":"Manufacturing & Wholesale Goods"
        }
    ],
    "sg:phone":"+1 541 384 2121",
    "sg:postcode":"97814",
    "sg:province":"OR",
    "sg:tags":[
        "bean"
    ],
    "wof:name":"Warehouse",
    "wof:placetype":"venue"
},
  "geometry": {"coordinates":[-117.83105500000001,44.778099],"type":"Point"}
}