{
  "type": "Feature",
  "properties": {
    "iso:country":"US",
    "sg:address":"9265 SW Center St",
    "sg:city":"Tigard",
    "sg:classifiers":[
        {
            "category":"Professional",
            "subcategory":"Computer Services",
            "type":"Services"
        }
    ],
    "sg:phone":"+1 503 341 1381",
    "sg:postcode":"97223",
    "sg:province":"OR",
    "sg:tags":[
        "website",
        "design"
    ],
    "wof:name":"Baireynet Web Design",
    "wof:placetype":"venue"
},
  "geometry": {"coordinates":[-122.771919,45.432619],"type":"Point"}
}