{
  "type": "Feature",
  "properties": {
    "iso:country":"US",
    "sg:address":"8686 Lakeside Dr NE",
    "sg:city":"Salem",
    "sg:classifiers":[
        {
            "category":"Farming",
            "subcategory":"Nursery",
            "type":"Manufacturing & Wholesale Goods"
        }
    ],
    "sg:phone":"+1 503 393 5512",
    "sg:postcode":"97305",
    "sg:province":"OR",
    "sg:tags":[
        "ornamental",
        "grower",
        "nursery-wholesale"
    ],
    "wof:name":"Mel Franke Nursery Inc",
    "wof:placetype":"venue"
},
  "geometry": {"coordinates":[-122.93141,45.04247],"type":"Point"}
}