{
  "type": "Feature",
  "properties": {
    "iso:country":"US",
    "sg:address":"5415 SW Westgate Dr",
    "sg:city":"Portland",
    "sg:classifiers":[
        {
            "category":"Health Services",
            "subcategory":"Doctor",
            "type":"Services"
        }
    ],
    "sg:phone":"+1 503 292 8824",
    "sg:postcode":"97221",
    "sg:province":"OR",
    "sg:tags":[
        "dentist"
    ],
    "wof:name":"Stephen P Clemens DDS",
    "wof:placetype":"venue"
},
  "geometry": {"coordinates":[-122.73324,45.51078],"type":"Point"}
}