{
  "type": "Feature",
  "properties": {
    "iso:country":"US",
    "sg:address":"3800 Davis Dr",
    "sg:city":"Hood River",
    "sg:classifiers":[
        {
            "category":"Organizations",
            "subcategory":"Religious Organization",
            "type":"Services"
        }
    ],
    "sg:phone":"+1 541 354 2495",
    "sg:postcode":"97031",
    "sg:province":"OR",
    "wof:name":"Bible Fellowship",
    "wof:placetype":"venue"
},
  "geometry": {"coordinates":[-121.553923,45.62536],"type":"Point"}
}