{
  "type": "Feature",
  "properties": {
    "addr:full":"204 Residence St Enterprise OR 97828",
    "addr:housenumber":"204",
    "addr:postcode":"97828",
    "addr:street":"Residence St",
    "iso:country":"US",
    "sg:address":"204 Residence St",
    "sg:city":"Enterprise",
    "sg:classifiers":[
        {
            "category":"Health Services",
            "subcategory":"Doctor",
            "type":"Services"
        }
    ],
    "sg:phone":"+1 541 426 3531",
    "sg:postcode":"97828",
    "sg:province":"OR",
    "wof:name":"Bruce K Cummings Dmd PC",
    "wof:placetype":"venue"
},
  "geometry": {"coordinates":[-117.27589500000001,45.421082],"type":"Point"}
}