{
  "type": "Feature",
  "properties": {
    "iso:country":"US",
    "sg:address":"1414 Marine Dr",
    "sg:city":"Astoria",
    "sg:classifiers":[
        {
            "category":"Health Services",
            "subcategory":"Doctor",
            "type":"Services"
        }
    ],
    "sg:phone":"+1 503 325 0310",
    "sg:postcode":"97103",
    "sg:province":"OR",
    "sg:tags":[
        "dentist"
    ],
    "sg:website":"www.smileastoria.net",
    "wof:name":"Advanced Aesthetic Dentistry",
    "wof:placetype":"venue"
},
  "geometry": {"coordinates":[-123.827383,46.189497],"type":"Point"}
}