{
  "type": "Feature",
  "properties": {
    "addr:full":"1728 SW Jefferson Street Portland OR 97201",
    "addr:housenumber":"1728",
    "addr:postcode":"97201",
    "addr:street":"Sw Jefferson Street",
    "iso:country":"US",
    "sg:address":"1728 SW Jefferson Street",
    "sg:city":"Portland",
    "sg:classifiers":[
        {
            "category":"Fast Food",
            "type":"Food & Drink"
        },
        {
            "category":"Restaurant",
            "type":"Food & Drink"
        },
        {
            "category":"Food & Beverages",
            "subcategory":"Bakery",
            "type":"Retail Goods"
        },
        {
            "category":"Food & Beverages",
            "subcategory":"Groceries & Convenience Stores",
            "type":"Retail Goods"
        }
    ],
    "sg:phone":"+1 503 294 0337",
    "sg:postcode":"97201",
    "sg:province":"OR",
    "sg:tags":[
        "shop",
        "american",
        "sandwich",
        "take"
    ],
    "sg:website":"www.subway.com",
    "wof:name":"Subway",
    "wof:placetype":"venue"
},
  "geometry": {"coordinates":[-122.691827,45.517829],"type":"Point"}
}