{
  "type": "Feature",
  "properties": {
    "addr:full":"1457 SW 4th Ave Ontario OR 97914",
    "addr:housenumber":"1457",
    "addr:postcode":"97914",
    "addr:street":"Sw 4Th Ave",
    "iso:country":"US",
    "sg:address":"1457 SW 4th Ave",
    "sg:city":"Ontario",
    "sg:classifiers":[
        {
            "category":"Professional",
            "subcategory":"Accounting & Tax Preparation",
            "type":"Services"
        },
        {
            "category":"Banks & Credit Unions",
            "subcategory":"Financial Services",
            "type":"Services"
        }
    ],
    "sg:phone":"+1 541 889 5056",
    "sg:postcode":"97914",
    "sg:province":"OR",
    "sg:tags":[
        "return",
        "preparation-business",
        "taxes-consultants",
        "loan",
        "reporting",
        "representative",
        "alternative",
        "bookkeeping"
    ],
    "sg:website":"http://www.hrblock.com",
    "wof:name":"H&R Block",
    "wof:placetype":"venue"
},
  "geometry": {"coordinates":[-116.98674800000001,44.024769],"type":"Point"}
}