{
  "type": "Feature",
  "properties": {
    "iso:country":"US",
    "sg:address":"3880 SW 170th Ave",
    "sg:city":"Beaverton",
    "sg:classifiers":[
        {
            "category":"Building & Trades",
            "subcategory":"Locksmith",
            "type":"Services"
        }
    ],
    "sg:phone":"+1 503 848 9100",
    "sg:postcode":"97007",
    "sg:province":"OR",
    "sg:tags":[
        "key"
    ],
    "sg:website":"www.davislock.com",
    "wof:name":"A Automotive & Commercial Locksmith",
    "wof:placetype":"venue"
},
  "geometry": {"coordinates":[-122.851997,45.491402],"type":"Point"}
}