{
  "type": "Feature",
  "properties": {
    "iso:country":"US",
    "sg:address":"3915 SE 42nd Ave",
    "sg:city":"Portland",
    "sg:classifiers":[
        {
            "category":"Professional",
            "type":"Services"
        }
    ],
    "sg:phone":"+1 503 772 9748",
    "sg:postcode":"97206",
    "sg:province":"OR",
    "wof:name":"Dian Goldsmith",
    "wof:placetype":"venue"
},
  "geometry": {"coordinates":[-122.619006,45.494314],"type":"Point"}
}