{
  "type": "Feature",
  "properties": {
    "iso:country":"US",
    "sg:address":"5916 SE 91st Ave",
    "sg:city":"Portland",
    "sg:classifiers":[
        {
            "category":"Home & Garden",
            "subcategory":"Home Furnishings",
            "type":"Retail Goods"
        }
    ],
    "sg:phone":"+1 503 772 8300",
    "sg:postcode":"97266",
    "sg:province":"OR",
    "sg:tags":[
        "draperies",
        "vertical",
        "blinds-venetian",
        "window",
        "treatment",
        "curtain"
    ],
    "wof:name":"Edmondson's Drapery Inc",
    "wof:placetype":"venue"
},
  "geometry": {"coordinates":[-122.569591,45.479949],"type":"Point"}
}