{
  "type": "Feature",
  "properties": {
    "addr:full":"17007 SE Stark St Unit 30 Portland OR 97233",
    "addr:housenumber":"30",
    "addr:postcode":"17007;97233",
    "addr:street":"Se Stark St Unit",
    "iso:country":"US",
    "sg:address":"17007 SE Stark St Unit 30",
    "sg:city":"Portland",
    "sg:classifiers":[
        {
            "category":"Building & Trades",
            "subcategory":"Construction",
            "type":"Services"
        },
        {
            "category":"Recreation",
            "subcategory":"Campground",
            "type":"Entertainment"
        }
    ],
    "sg:phone":"+1 503 408 5791",
    "sg:postcode":"97233",
    "sg:province":"OR",
    "sg:tags":[
        "manufactured",
        "housing-communities",
        "recreational",
        "park",
        "vehicle"
    ],
    "wof:name":"Fair Haven Mobile Home Park",
    "wof:placetype":"venue"
},
  "geometry": {"coordinates":[-122.487949,45.51915],"type":"Point"}
}