{
  "type": "Feature",
  "properties": {
    "addr:full":"1656 City View St Eugene OR 97402",
    "addr:housenumber":"1656",
    "addr:postcode":"97402",
    "addr:street":"City View St",
    "iso:country":"US",
    "sg:address":"1656 City View St",
    "sg:city":"Eugene",
    "sg:classifiers":[
        {
            "category":"Education",
            "subcategory":"Library",
            "type":"Public Place"
        }
    ],
    "sg:phone":"+1 541 681 9665",
    "sg:postcode":"97402",
    "sg:province":"OR",
    "wof:name":"Carrie Camp Memorial Library",
    "wof:placetype":"venue"
},
  "geometry": {"coordinates":[-123.127914,44.042009],"type":"Point"}
}