{
  "type": "Feature",
  "properties": {
    "addr:full":"7220 SE 39th Ave Portland OR 97202",
    "addr:housenumber":"7220",
    "addr:postcode":"97202",
    "addr:street":"Se 39Th Ave",
    "iso:country":"US",
    "sg:address":"7220 SE 39th Ave",
    "sg:city":"Portland",
    "sg:classifiers":[
        {
            "category":"Organizations",
            "subcategory":"Religious Organization",
            "type":"Services"
        }
    ],
    "sg:phone":"+1 503 774 6781",
    "sg:postcode":"97202",
    "sg:province":"OR",
    "wof:name":"Holy Trinity Lutheran Church",
    "wof:placetype":"venue"
},
  "geometry": {"coordinates":[-122.62251500000001,45.470641],"type":"Point"}
}