{
  "type": "Feature",
  "properties": {
    "iso:country":"US",
    "sg:address":"1643 Foots Creek Left Fork Rd",
    "sg:city":"Gold Hill",
    "sg:classifiers":[
        {
            "category":"Recreation",
            "type":"Entertainment"
        }
    ],
    "sg:phone":"+1 541 582 3613",
    "sg:postcode":"97525",
    "sg:province":"OR",
    "wof:name":"Oachs Guide Service",
    "wof:placetype":"venue"
},
  "geometry": {"coordinates":[-123.139183,42.382193],"type":"Point"}
}