{
  "type": "Feature",
  "properties": {
    "addr:full":"22027 S Schram Rd Beavercreek OR 97004",
    "addr:housenumber":"22027",
    "addr:postcode":"97004",
    "addr:street":"S Schram Rd",
    "iso:country":"US",
    "sg:address":"22027 S Schram Rd",
    "sg:city":"Beavercreek",
    "sg:classifiers":[
        {
            "category":"Retail",
            "subcategory":"Laundry & Dry Cleaning",
            "type":"Services"
        }
    ],
    "sg:phone":"+1 503 632 7457",
    "sg:postcode":"97004",
    "sg:province":"OR",
    "wof:name":"Sewing Alterations Jus Fo",
    "wof:placetype":"venue"
},
  "geometry": {"coordinates":[-122.407583,45.230013],"type":"Point"}
}