{
  "type": "Feature",
  "properties": {
    "addr:full":"234 SW Broadway Portland OR 97253",
    "addr:housenumber":"234",
    "addr:postcode":"97253",
    "addr:street":"Sw Broadway",
    "iso:country":"US",
    "sg:address":"234 SW Broadway",
    "sg:city":"Portland",
    "sg:classifiers":[
        {
            "category":"Manufacturing",
            "subcategory":"Printing",
            "type":"Manufacturing & Wholesale Goods"
        }
    ],
    "sg:phone":"+1 503 222 5144",
    "sg:postcode":"97253",
    "sg:province":"OR",
    "sg:tags":[
        "print",
        "medium",
        "periodical"
    ],
    "sg:website":"www.portlandmonthlymag.com",
    "wof:name":"Portland Monthly Magazine",
    "wof:placetype":"venue"
},
  "geometry": {"coordinates":[-122.67797899999999,45.522392],"type":"Point"}
}