{
  "type": "Feature",
  "properties": {
    "iso:country":"US",
    "sg:address":"89584 Demming Rd",
    "sg:city":"Elmira",
    "sg:classifiers":[
        {
            "category":"Building & Trades",
            "subcategory":"Construction",
            "type":"Services"
        }
    ],
    "sg:phone":"+1 541 935 9747",
    "sg:postcode":"97437",
    "sg:province":"OR",
    "sg:tags":[
        "residential"
    ],
    "wof:name":"Scott Harple Construction",
    "wof:placetype":"venue"
},
  "geometry": {"coordinates":[-123.35143600000001,44.08979],"type":"Point"}
}