{
  "type": "Feature",
  "properties": {
    "addr:full":"1497 E Main St Ashland OR 97520",
    "addr:housenumber":"1497",
    "addr:postcode":"97520",
    "addr:street":"E Main St",
    "iso:country":"US",
    "sg:address":"1497 E Main St",
    "sg:city":"Ashland",
    "sg:classifiers":[
        {
            "category":"Education",
            "subcategory":"School",
            "type":"Public Place"
        }
    ],
    "sg:phone":"+1 541 488 2684",
    "sg:postcode":"97520",
    "sg:province":"OR",
    "wof:name":"School Ashland Public",
    "wof:placetype":"venue"
},
  "geometry": {"coordinates":[-122.690712,42.194828],"type":"Point"}
}