{
  "type": "Feature",
  "properties": {
    "iso:country":"US",
    "sg:address":"10402 NE Sandy Blvd",
    "sg:city":"Portland",
    "sg:classifiers":[
        {
            "category":"Social Services",
            "type":"Services"
        }
    ],
    "sg:phone":"+1 503 251 5920",
    "sg:postcode":"97220",
    "sg:province":"OR",
    "wof:name":"Advantage Mental Health",
    "wof:placetype":"venue"
},
  "geometry": {"coordinates":[-122.554744,45.558773],"type":"Point"}
}