{
  "type": "Feature",
  "properties": {
    "iso:country":"US",
    "sg:address":"211 W C St",
    "sg:city":"Silverton",
    "sg:classifiers":[
        {
            "category":"Shopping",
            "subcategory":"Music",
            "type":"Retail Goods"
        }
    ],
    "sg:phone":"+1 503 873 3765",
    "sg:postcode":"97381",
    "sg:province":"OR",
    "wof:name":"Silver Creek Video",
    "wof:placetype":"venue"
},
  "geometry": {"coordinates":[-122.787588,45.008274],"type":"Point"}
}