{
  "type": "Feature",
  "properties": {
    "iso:country":"US",
    "sg:address":"3218 Pringle Rd SE",
    "sg:city":"Salem",
    "sg:classifiers":[
        {
            "category":"Government",
            "subcategory":"Office",
            "type":"Public Place"
        }
    ],
    "sg:phone":"+1 503 378 5816",
    "sg:postcode":"97302",
    "sg:province":"OR",
    "sg:tags":[
        "sector",
        "regulation",
        "commercial",
        "miscellaneous"
    ],
    "sg:website":"www.oregon.gov/obce",
    "wof:name":"Chiropractic Examiners",
    "wof:placetype":"venue"
},
  "geometry": {"coordinates":[-123.026082,44.909372],"type":"Point"}
}