{
  "type": "Feature",
  "properties": {
    "iso:country":"US",
    "sg:address":"266 NE Plymouth Cir",
    "sg:city":"Corvallis",
    "sg:classifiers":[
        {
            "category":"Personal",
            "subcategory":"Beauty Salon",
            "type":"Services"
        }
    ],
    "sg:phone":"+1 541 754 6414",
    "sg:postcode":"97330",
    "sg:province":"OR",
    "sg:tags":[
        "shop"
    ],
    "wof:name":"T L C Nails",
    "wof:placetype":"venue"
},
  "geometry": {"coordinates":[-123.24493200000001,44.598038],"type":"Point"}
}