{
  "type": "Feature",
  "properties": {
    "iso:country":"US",
    "sg:address":"76122 Rosenberg Rd",
    "sg:city":"Echo",
    "sg:classifiers":[
        {
            "category":"Farming",
            "subcategory":"Livestock Farm",
            "type":"Manufacturing & Wholesale Goods"
        }
    ],
    "sg:phone":"+1 541 376 8696",
    "sg:postcode":"97826",
    "sg:province":"OR",
    "sg:tags":[
        "beef",
        "feedlot",
        "cattle"
    ],
    "wof:name":"Mt Fanny Farms Inc",
    "wof:placetype":"venue"
},
  "geometry": {"coordinates":[-119.279702,45.741161],"type":"Point"}
}