{
  "type": "Feature",
  "properties": {
    "iso:country":"US",
    "sg:address":"880 18th Ave",
    "sg:city":"Sweet Home",
    "sg:classifiers":[
        {
            "category":"Social Services",
            "type":"Services"
        }
    ],
    "sg:phone":"+1 541 367 4775",
    "sg:postcode":"97386",
    "sg:province":"OR",
    "sg:tags":[
        "executive"
    ],
    "wof:name":"Sweet Home Senior Center",
    "wof:placetype":"venue"
},
  "geometry": {"coordinates":[-122.723102,44.396837],"type":"Point"}
}