{
  "type": "Feature",
  "properties": {
    "iso:country":"US",
    "sg:address":"2166 NE 3rd St",
    "sg:city":"Prineville",
    "sg:classifiers":[
        {
            "category":"Building & Trades",
            "subcategory":"Plumbing",
            "type":"Services"
        }
    ],
    "sg:phone":"+1 541 447 6160",
    "sg:postcode":"97754",
    "sg:province":"OR",
    "sg:tags":[
        "heat",
        "pump",
        "contractor"
    ],
    "wof:name":"Prineville Heating & Cooling",
    "wof:placetype":"venue"
},
  "geometry": {"coordinates":[-120.819796,44.30291],"type":"Point"}
}