{
  "type": "Feature",
  "properties": {
    "iso:country":"US",
    "sg:address":"3620 Gateway St",
    "sg:city":"Springfield",
    "sg:classifiers":[
        {
            "category":"Professional",
            "subcategory":"Testing Lab",
            "type":"Services"
        }
    ],
    "sg:phone":"+1 541 726 2590",
    "sg:postcode":"97477",
    "sg:province":"OR",
    "sg:tags":[
        "crime"
    ],
    "wof:name":"O S P Crime Lab",
    "wof:placetype":"venue"
},
  "geometry": {"coordinates":[-123.041746,44.084758],"type":"Point"}
}