{
  "type": "Feature",
  "properties": {
    "iso:country":"US",
    "sg:address":"910 Town Centre Dr",
    "sg:city":"Medford",
    "sg:classifiers":[
        {
            "category":"Banks & Credit Unions",
            "subcategory":"Bank",
            "type":"Services"
        }
    ],
    "sg:phone":"+1 541 608 2160",
    "sg:postcode":"97504",
    "sg:province":"OR",
    "sg:website":"www.golfsavingsbank.com",
    "wof:name":"Golf Savings Bank",
    "wof:placetype":"venue"
},
  "geometry": {"coordinates":[-122.867901,42.338759],"type":"Point"}
}