{
  "type": "Feature",
  "properties": {
    "addr:full":"5924 NW Front Ave Portland OR 97210",
    "addr:housenumber":"5924",
    "addr:postcode":"97210",
    "addr:street":"Nw Front Ave",
    "iso:country":"US",
    "sg:address":"5924 NW Front Ave",
    "sg:city":"Portland",
    "sg:classifiers":[
        {
            "category":"Autos & Motor Vehicles",
            "subcategory":"Fuel & Gas Station",
            "type":"Retail Goods"
        },
        {
            "category":"Food & Beverages",
            "subcategory":"Groceries & Convenience Stores",
            "type":"Retail Goods"
        }
    ],
    "sg:phone":"+1 503 221 7714",
    "sg:postcode":"97210",
    "sg:province":"OR",
    "sg:website":"http://www.chevron.com/products/",
    "wof:name":"Chevron",
    "wof:placetype":"venue"
},
  "geometry": {"coordinates":[-122.740033,45.56471],"type":"Point"}
}