{
  "type": "Feature",
  "properties": {
    "addr:full":"120 N Everest Rd Newberg OR 97132",
    "addr:housenumber":"120",
    "addr:postcode":"97132",
    "addr:street":"N Everest Rd",
    "iso:country":"US",
    "sg:address":"120 N Everest Rd",
    "sg:city":"Newberg",
    "sg:classifiers":[
        {
            "category":"Social Services",
            "type":"Services"
        }
    ],
    "sg:phone":"+1 503 538 7647",
    "sg:postcode":"97132",
    "sg:province":"OR",
    "sg:tags":[
        "guidance",
        "child"
    ],
    "wof:name":"First Step Adolescent Ctr",
    "wof:placetype":"venue"
},
  "geometry": {"coordinates":[-122.960605,45.301746],"type":"Point"}
}