{
  "type": "Feature",
  "properties": {
    "iso:country":"US",
    "sg:address":"3437 NE 13th Ave",
    "sg:city":"Portland",
    "sg:classifiers":[
        {
            "category":"Retail",
            "subcategory":"Animal Services",
            "type":"Services"
        }
    ],
    "sg:phone":"+1 503 281 4500",
    "sg:postcode":"97212",
    "sg:province":"OR",
    "sg:tags":[
        "pet",
        "exercising",
        "sitting"
    ],
    "wof:name":"Dogs On Run",
    "wof:placetype":"venue"
},
  "geometry": {"coordinates":[-122.652415,45.547779],"type":"Point"}
}