{
  "type": "Feature",
  "properties": {
    "iso:country":"US",
    "sg:address":"216 SW Washington St",
    "sg:city":"Dallas",
    "sg:classifiers":[
        {
            "category":"Food & Beverages",
            "subcategory":"Groceries & Convenience Stores",
            "type":"Retail Goods"
        }
    ],
    "sg:phone":"+1 503 831 5380",
    "sg:postcode":"97338",
    "sg:province":"OR",
    "wof:name":"Center Market",
    "wof:placetype":"venue"
},
  "geometry": {"coordinates":[-123.319929,44.919523],"type":"Point"}
}