{
  "type": "Feature",
  "properties": {
    "iso:country":"US",
    "sg:address":"3660 Brophy Rd",
    "sg:city":"Eagle Point",
    "sg:classifiers":[
        {
            "category":"Farming",
            "subcategory":"Livestock Farm",
            "type":"Manufacturing & Wholesale Goods"
        }
    ],
    "sg:phone":"+1 541 826 1500",
    "sg:postcode":"97524",
    "sg:province":"OR",
    "sg:tags":[
        "ranch"
    ],
    "wof:name":"St Laurent Land & Cattle",
    "wof:placetype":"venue"
},
  "geometry": {"coordinates":[-122.74773500000001,42.488257],"type":"Point"}
}