{
  "type": "Feature",
  "properties": {
    "iso:country":"US",
    "sg:address":"1829 SE Haig St",
    "sg:city":"Portland",
    "sg:classifiers":[
        {
            "category":"Wholesale",
            "subcategory":"Machinery & Supplies",
            "type":"Manufacturing & Wholesale Goods"
        }
    ],
    "sg:phone":"+1 503 231 7908",
    "sg:postcode":"97202",
    "sg:province":"OR",
    "sg:tags":[
        "janitor"
    ],
    "wof:name":"Cleanup Inc",
    "wof:placetype":"venue"
},
  "geometry": {"coordinates":[-122.645777,45.498197],"type":"Point"}
}