{
  "type": "Feature",
  "properties": {
    "iso:country":"US",
    "sg:address":"401 NE 4th St",
    "sg:city":"Enterprise",
    "sg:classifiers":[
        {
            "category":"Retail",
            "subcategory":"Auto Repair",
            "type":"Services"
        }
    ],
    "sg:phone":"+1 541 426 4919",
    "sg:postcode":"97828",
    "sg:province":"OR",
    "sg:tags":[
        "truck"
    ],
    "wof:name":"Stangel Industries & Machine",
    "wof:placetype":"venue"
},
  "geometry": {"coordinates":[-117.272199,45.429199],"type":"Point"}
}