{
  "type": "Feature",
  "properties": {
    "iso:country":"US",
    "sg:address":"725 SE 9th Ave",
    "sg:city":"Portland",
    "sg:classifiers":[
        {
            "category":"Professional",
            "type":"Services"
        }
    ],
    "sg:phone":"+1 503 730 1467",
    "sg:postcode":"97214",
    "sg:province":"OR",
    "sg:tags":[
        "establishment"
    ],
    "wof:name":"Kym Hughes Design",
    "wof:placetype":"venue"
},
  "geometry": {"coordinates":[-122.656761,45.517388],"type":"Point"}
}