{
  "type": "Feature",
  "properties": {
    "addr:full":"2700 SW 175th Ave Beaverton OR 97006",
    "addr:housenumber":"2700",
    "addr:postcode":"97006",
    "addr:street":"Sw 175Th Ave",
    "iso:country":"US",
    "sg:address":"2700 SW 175th Ave",
    "sg:city":"Beaverton",
    "sg:classifiers":[
        {
            "category":"Manufacturing",
            "subcategory":"Buildings",
            "type":"Manufacturing & Wholesale Goods"
        },
        {
            "category":"Building & Trades",
            "subcategory":"Construction",
            "type":"Services"
        }
    ],
    "sg:phone":"+1 503 330 0772",
    "sg:postcode":"97006",
    "sg:province":"OR",
    "sg:tags":[
        "home",
        "builder",
        "contractor"
    ],
    "wof:name":"Drl Homes",
    "wof:placetype":"venue"
},
  "geometry": {"coordinates":[-122.85790299999999,45.500226],"type":"Point"}
}