{
  "type": "Feature",
  "properties": {
    "addr:full":"21128 State Hwy 99E NE Aurora OR 97002",
    "addr:housenumber":"21128",
    "addr:postcode":"97002",
    "addr:street":"State Hwy 99E Ne",
    "iso:country":"US",
    "sg:address":"21128 State Hwy 99E NE",
    "sg:city":"Aurora",
    "sg:classifiers":[
        {
            "category":"Manufacturing",
            "subcategory":"Wood Products",
            "type":"Manufacturing & Wholesale Goods"
        }
    ],
    "sg:phone":"+1 503 678 2299",
    "sg:postcode":"97002",
    "sg:province":"OR",
    "wof:name":"B P Industries Inc",
    "wof:placetype":"venue"
},
  "geometry": {"coordinates":[-122.757886,45.225445],"type":"Point"}
}