{
  "type": "Feature",
  "properties": {
    "iso:country":"US",
    "sg:address":"161 Carly Cir",
    "sg:city":"Medford",
    "sg:classifiers":[
        {
            "category":"Real Estate",
            "subcategory":"Real Estate Agent",
            "type":"Services"
        }
    ],
    "sg:phone":"+1 541 858 2952",
    "sg:postcode":"97504",
    "sg:province":"OR",
    "wof:name":"Brookingscaptains Quarters",
    "wof:placetype":"venue"
},
  "geometry": {"coordinates":[-122.80745,42.335768],"type":"Point"}
}