{
  "type": "Feature",
  "properties": {
    "iso:country":"US",
    "sg:address":"55347 State Hwy 207",
    "sg:city":"Heppner",
    "sg:classifiers":[
        {
            "category":"Farming",
            "subcategory":"Livestock Farm",
            "type":"Manufacturing & Wholesale Goods"
        }
    ],
    "sg:phone":"+1 541 676 5875",
    "sg:postcode":"97836",
    "sg:province":"OR",
    "sg:tags":[
        "wheat",
        "beef",
        "crop",
        "field",
        "cattle",
        "feedlot"
    ],
    "wof:name":"Horseshoe Hereford Ranch Inc",
    "wof:placetype":"venue"
},
  "geometry": {"coordinates":[-119.57257199999999,45.370592],"type":"Point"}
}