{
  "type": "Feature",
  "properties": {
    "iso:country":"US",
    "sg:address":"1656 Ashland Ct NW",
    "sg:city":"Salem",
    "sg:classifiers":[
        {
            "category":"Wholesale",
            "subcategory":"Vending Machines",
            "type":"Manufacturing & Wholesale Goods"
        }
    ],
    "sg:phone":"+1 503 362 1645",
    "sg:postcode":"97304",
    "sg:province":"OR",
    "wof:name":"M & K Vending",
    "wof:placetype":"venue"
},
  "geometry": {"coordinates":[-123.069727,44.95667],"type":"Point"}
}