{
  "type": "Feature",
  "properties": {
    "iso:country":"US",
    "sg:address":"11615 SW Pacific Hwy",
    "sg:city":"Portland",
    "sg:classifiers":[
        {
            "category":"Restaurant",
            "type":"Food & Drink"
        }
    ],
    "sg:phone":"+1 503 620 2125",
    "sg:postcode":"97223",
    "sg:province":"OR",
    "sg:tags":[
        "japanese"
    ],
    "wof:name":"House of Teriyaki",
    "wof:placetype":"venue"
},
  "geometry": {"coordinates":[-122.75384699999999,45.438448],"type":"Point"}
}