{
  "type": "Feature",
  "properties": {
    "iso:country":"US",
    "sg:address":"293 N Front St",
    "sg:city":"Woodburn",
    "sg:classifiers":[
        {
            "category":"Restaurant",
            "type":"Food & Drink"
        }
    ],
    "sg:phone":"+1 503 982 4361",
    "sg:postcode":"97071",
    "sg:province":"OR",
    "sg:tags":[
        "eating"
    ],
    "wof:name":"Carbajal Farms",
    "wof:placetype":"venue"
},
  "geometry": {"coordinates":[-122.857175,45.142033],"type":"Point"}
}