{
  "type": "Feature",
  "properties": {
    "iso:country":"US",
    "sg:address":"1814 SW Elm St",
    "sg:city":"Portland",
    "sg:classifiers":[
        {
            "category":"Health Services",
            "subcategory":"Doctor",
            "type":"Services"
        }
    ],
    "sg:phone":"+1 503 220 8557",
    "sg:postcode":"97201",
    "sg:province":"OR",
    "sg:tags":[
        "medicine",
        "physician",
        "practice",
        "surgeons",
        "family"
    ],
    "wof:name":"Jonathan Purnell",
    "wof:placetype":"venue"
},
  "geometry": {"coordinates":[-122.697092,45.509537],"type":"Point"}
}