{
  "type": "Feature",
  "properties": {
    "iso:country":"US",
    "sg:address":"1722 NW Raleigh St Ste 110",
    "sg:city":"Portland",
    "sg:classifiers":[
        {
            "category":"Shopping",
            "subcategory":"Clothing, Apparel, & Fashions",
            "type":"Retail Goods"
        },
        {
            "category":"Personal",
            "type":"Services"
        }
    ],
    "sg:phone":"+1 503 380 1419",
    "sg:postcode":"97209",
    "sg:province":"OR",
    "sg:tags":[
        "designer",
        "tailoring",
        "sewing",
        "alteration",
        "women's",
        "wedding",
        "apparel"
    ],
    "sg:website":"lindsaypantano.com",
    "wof:name":"Magnolia Designs",
    "wof:placetype":"venue"
},
  "geometry": {"coordinates":[-122.68885,45.534264],"type":"Point"}
}