{
  "type": "Feature",
  "properties": {
    "iso:country":"US",
    "sg:address":"1911 Woodland Ter",
    "sg:city":"Lake Oswego",
    "sg:classifiers":[
        {
            "category":"Professional",
            "type":"Services"
        }
    ],
    "sg:phone":"+1 503 636 9529",
    "sg:postcode":"97034",
    "sg:province":"OR",
    "wof:name":"Carl Hurner & Son Inc",
    "wof:placetype":"venue"
},
  "geometry": {"coordinates":[-122.696119,45.40298],"type":"Point"}
}