{
  "type": "Feature",
  "properties": {
    "addr:full":"32700 SE Leewood Ln Boring OR 97009",
    "addr:postcode":"32700;97009",
    "addr:street":"Se Leewood Ln",
    "iso:country":"US",
    "sg:address":"32700 SE Leewood Ln",
    "sg:city":"Boring",
    "sg:classifiers":[
        {
            "category":"Manufacturing",
            "subcategory":"Lumber",
            "type":"Manufacturing & Wholesale Goods"
        }
    ],
    "sg:phone":"+1 503 668 8501",
    "sg:postcode":"97009",
    "sg:province":"OR",
    "sg:tags":[
        "logging"
    ],
    "wof:name":"Timberland Tree Service",
    "wof:placetype":"venue"
},
  "geometry": {"coordinates":[-122.32234099999999,45.374783],"type":"Point"}
}