{
  "type": "Feature",
  "properties": {
    "addr:full":"5330 Donald St Eugene OR 97405",
    "addr:housenumber":"5330",
    "addr:postcode":"97405",
    "addr:street":"Donald St",
    "iso:country":"US",
    "sg:address":"5330 Donald St",
    "sg:city":"Eugene",
    "sg:classifiers":[
        {
            "category":"Professional",
            "subcategory":"Management & Consulting",
            "type":"Services"
        }
    ],
    "sg:phone":"+1 541 345 2088",
    "sg:postcode":"97405",
    "sg:province":"OR",
    "sg:tags":[
        "counselor",
        "public",
        "relations"
    ],
    "wof:name":"Insight Northwest",
    "wof:placetype":"venue"
},
  "geometry": {"coordinates":[-123.090441,43.998864],"type":"Point"}
}