{
  "type": "Feature",
  "properties": {
    "addr:full":"10025 NW Glencoe Rd North Plains OR 97133",
    "addr:housenumber":"10025",
    "addr:postcode":"97133",
    "addr:street":"Nw Glencoe Rd North",
    "iso:country":"US",
    "sg:address":"10025 NW Glencoe Rd",
    "sg:city":"North Plains",
    "sg:classifiers":[
        {
            "category":"Restaurant",
            "type":"Food & Drink"
        }
    ],
    "sg:phone":"+1 503 647 7476",
    "sg:postcode":"97133",
    "sg:province":"OR",
    "sg:tags":[
        "shop",
        "coffee"
    ],
    "wof:name":"Realtime",
    "wof:placetype":"venue"
},
  "geometry": {"coordinates":[-122.99564599999999,45.59321],"type":"Point"}
}