{
  "type": "Feature",
  "properties": {
    "addr:full":"31136 Gowdyville Rd Cottage Grove OR 97424",
    "addr:postcode":"31136;97424",
    "addr:street":"Gowdyville Rd",
    "iso:country":"US",
    "sg:address":"31136 Gowdyville Rd",
    "sg:city":"Cottage Grove",
    "sg:classifiers":[
        {
            "category":"Building & Trades",
            "subcategory":"Construction",
            "type":"Services"
        }
    ],
    "sg:phone":"+1 541 942 9826",
    "sg:postcode":"97424",
    "sg:province":"OR",
    "sg:tags":[
        "logging",
        "road"
    ],
    "wof:name":"Harris R D Road Construction",
    "wof:placetype":"venue"
},
  "geometry": {"coordinates":[-123.11157,43.795946],"type":"Point"}
}