{
  "type": "Feature",
  "properties": {
    "addr:full":"9415 Wilsonville Rd Wilsonville OR 97070",
    "addr:postcode":"9415;97070",
    "addr:street":"Wilsonville Rd",
    "iso:country":"US",
    "sg:address":"9415 Wilsonville Rd",
    "sg:city":"Wilsonville",
    "sg:classifiers":[
        {
            "category":"Local Transit",
            "type":"Transportation"
        }
    ],
    "sg:phone":"+1 503 682 7790",
    "sg:postcode":"97070",
    "sg:province":"OR",
    "sg:tags":[
        "bus",
        "line"
    ],
    "sg:website":"www.ridesmart.com",
    "wof:name":"Smart TRANSIT",
    "wof:placetype":"venue"
},
  "geometry": {"coordinates":[-122.772789,45.303038],"type":"Point"}
}