{
  "type": "Feature",
  "properties": {
    "iso:country":"US",
    "sg:address":"4285 Commercial St SE",
    "sg:city":"Salem",
    "sg:classifiers":[
        {
            "category":"Banks & Credit Unions",
            "subcategory":"Bank",
            "type":"Services"
        }
    ],
    "sg:phone":"+1 503 763 0905",
    "sg:postcode":"97302",
    "sg:province":"OR",
    "sg:tags":[
        "loan",
        "real estate"
    ],
    "wof:name":"Windermere Mortgage",
    "wof:placetype":"venue"
},
  "geometry": {"coordinates":[-123.03583500000001,44.893116],"type":"Point"}
}