{
  "type": "Feature",
  "properties": {
    "addr:full":"735 NW 8th St Redmond OR 97756",
    "addr:housenumber":"735",
    "addr:postcode":"97756",
    "addr:street":"Nw 8Th St",
    "iso:country":"US",
    "sg:address":"735 NW 8th St",
    "sg:city":"Redmond",
    "sg:classifiers":[
        {
            "category":"Professional",
            "subcategory":"Business Services",
            "type":"Services"
        }
    ],
    "sg:phone":"+1 541 923 1049",
    "sg:postcode":"97756",
    "sg:province":"OR",
    "wof:name":"Karstop",
    "wof:placetype":"venue"
},
  "geometry": {"coordinates":[-121.17653199999999,44.28314],"type":"Point"}
}