{
  "type": "Feature",
  "properties": {
    "addr:full":"110 NW Broadway Portland OR 97209",
    "addr:housenumber":"110",
    "addr:postcode":"97209",
    "addr:street":"Nw Broadway",
    "iso:country":"US",
    "sg:address":"110 NW Broadway",
    "sg:city":"Portland",
    "sg:classifiers":[
        {
            "category":"Bars & Pubs",
            "type":"Food & Drink"
        }
    ],
    "sg:phone":"+1 503 222 3082",
    "sg:postcode":"97209",
    "sg:province":"OR",
    "sg:tags":[
        "lounge",
        "gay",
        "cocktail"
    ],
    "sg:website":"www.emberspdx.net/",
    "wof:name":"Embers",
    "wof:placetype":"venue"
},
  "geometry": {"coordinates":[-122.677002,45.5238],"type":"Point"}
}