{
  "type": "Feature",
  "properties": {
    "addr:full":"4005 N Colonial Ave Portland OR 97227",
    "addr:housenumber":"4005",
    "addr:postcode":"97227",
    "addr:street":"N Colonial Ave",
    "iso:country":"US",
    "sg:address":"4005 N Colonial Ave",
    "sg:city":"Portland",
    "sg:classifiers":[
        {
            "category":"Professional",
            "subcategory":"Engineering",
            "type":"Services"
        }
    ],
    "sg:phone":"+1 503 249 7728",
    "sg:postcode":"97227",
    "sg:province":"OR",
    "sg:tags":[
        "consulting",
        "engineer"
    ],
    "wof:name":"Cynthia Sulaski",
    "wof:placetype":"venue"
},
  "geometry": {"coordinates":[-122.684163,45.553359],"type":"Point"}
}