{
  "type": "Feature",
  "properties": {
    "addr:full":"1783 Belmont Ave Hood River OR 97031",
    "addr:housenumber":"1783",
    "addr:postcode":"97031",
    "addr:street":"Belmont Ave",
    "iso:country":"US",
    "sg:address":"1783 Belmont Ave",
    "sg:city":"Hood River",
    "sg:classifiers":[
        {
            "category":"Retail",
            "subcategory":"Auto Repair",
            "type":"Services"
        }
    ],
    "sg:phone":"+1 541 386 3672",
    "sg:postcode":"97031",
    "sg:province":"OR",
    "sg:tags":[
        "wheel",
        "exhaust",
        "brake",
        "alignment"
    ],
    "wof:name":"Buntings Exhaust Inc",
    "wof:placetype":"venue"
},
  "geometry": {"coordinates":[-121.528959,45.699557],"type":"Point"}
}