{
  "type": "Feature",
  "properties": {
    "iso:country":"US",
    "sg:address":"22113 State Hwy 62",
    "sg:city":"Shady Cove",
    "sg:classifiers":[
        {
            "category":"Building & Trades",
            "subcategory":"Landscaping Services",
            "type":"Services"
        }
    ],
    "sg:phone":"+1 541 878 4800",
    "sg:postcode":"97539",
    "sg:province":"OR",
    "sg:tags":[
        "tree"
    ],
    "wof:name":"All In-Hall",
    "wof:placetype":"venue"
},
  "geometry": {"coordinates":[-122.810524,42.618243],"type":"Point"}
}