{
  "type": "Feature",
  "properties": {
    "addr:full":"19350 SW Boones Ferry Rd Tualatin OR 97062",
    "addr:housenumber":"19350",
    "addr:postcode":"97062",
    "addr:street":"Sw Boones Ferry Rd",
    "iso:country":"US",
    "sg:address":"19350 SW Boones Ferry Rd",
    "sg:city":"Tualatin",
    "sg:classifiers":[
        {
            "category":"Manufacturing",
            "subcategory":"Food",
            "type":"Manufacturing & Wholesale Goods"
        }
    ],
    "sg:phone":"+1 503 885 8641",
    "sg:postcode":"97062",
    "sg:province":"OR",
    "sg:tags":[
        "donut",
        "product",
        "restaurant",
        "mfg"
    ],
    "wof:name":"Doughnut Land",
    "wof:placetype":"venue"
},
  "geometry": {"coordinates":[-122.764999,45.380299],"type":"Point"}
}