{
  "type": "Feature",
  "properties": {
    "iso:country":"US",
    "sg:address":"2820 SE 39th Loop Ste H",
    "sg:city":"Hillsboro",
    "sg:classifiers":[
        {
            "category":"Wholesale",
            "subcategory":"Machinery & Supplies",
            "type":"Manufacturing & Wholesale Goods"
        },
        {
            "category":"Retail",
            "subcategory":"Auto Repair",
            "type":"Services"
        }
    ],
    "sg:phone":"+1 503 844 6100",
    "sg:postcode":"97123",
    "sg:province":"OR",
    "sg:tags":[
        "shop",
        "automobile",
        "machine",
        "industrial",
        "equipment"
    ],
    "wof:name":"Ken Waddington Machine",
    "wof:placetype":"venue"
},
  "geometry": {"coordinates":[-122.94444900000001,45.498351],"type":"Point"}
}