{
  "type": "Feature",
  "properties": {
    "iso:country":"US",
    "sg:address":"1775 E Main St",
    "sg:city":"Cottage Grove",
    "sg:classifiers":[
        {
            "category":"Real Estate",
            "subcategory":"Real Estate Agent",
            "type":"Services"
        }
    ],
    "sg:phone":"+1 541 942 3293",
    "sg:postcode":"97424",
    "sg:province":"OR",
    "wof:name":"Inter-State Realty",
    "wof:placetype":"venue"
},
  "geometry": {"coordinates":[-123.049294,43.797131],"type":"Point"}
}