{
  "type": "Feature",
  "properties": {
    "iso:country":"US",
    "sg:address":"3501 Olympic St",
    "sg:city":"Springfield",
    "sg:classifiers":[
        {
            "category":"Freight",
            "type":"Transportation"
        }
    ],
    "sg:phone":"+1 541 726 0623",
    "sg:postcode":"97478",
    "sg:province":"OR",
    "sg:tags":[
        "commercial",
        "storage"
    ],
    "wof:name":"Stor-N-Lok",
    "wof:placetype":"venue"
},
  "geometry": {"coordinates":[-122.970461,44.057926],"type":"Point"}
}