{
  "type": "Feature",
  "properties": {
    "iso:country":"US",
    "sg:address":"14279 S Firethorn Ct",
    "sg:city":"Oregon City",
    "sg:classifiers":[
        {
            "category":"Retail",
            "subcategory":"Photofinishing",
            "type":"Services"
        }
    ],
    "sg:phone":"+1 503 632 0611",
    "sg:postcode":"97045",
    "sg:province":"OR",
    "sg:tags":[
        "laboratory"
    ],
    "wof:name":"Marv Binegar Photo",
    "wof:placetype":"venue"
},
  "geometry": {"coordinates":[-122.573465,45.288834],"type":"Point"}
}