{
  "type": "Feature",
  "properties": {
    "addr:full":"61479 S Hwy 97 Bend OR 97702",
    "addr:housenumber":"61479",
    "addr:postcode":"97702",
    "addr:street":"S Hwy 97",
    "iso:country":"US",
    "sg:address":"61479 S Hwy 97",
    "sg:city":"Bend",
    "sg:classifiers":[
        {
            "category":"Restaurant",
            "type":"Food & Drink"
        }
    ],
    "sg:phone":"+1 541 388 1964",
    "sg:postcode":"97702",
    "sg:province":"OR",
    "sg:tags":[
        "mexican",
        "fast"
    ],
    "sg:website":"www.tacotime.com",
    "wof:name":"Taco Time",
    "wof:placetype":"venue"
},
  "geometry": {"coordinates":[-121.31114100000001,44.030055],"type":"Point"}
}