{
  "type": "Feature",
  "properties": {
    "addr:full":"2379 Oakmont Way Eugene OR 97401",
    "addr:housenumber":"2379",
    "addr:postcode":"97401",
    "addr:street":"Oakmont Way",
    "iso:country":"US",
    "sg:address":"2379 Oakmont Way",
    "sg:city":"Eugene",
    "sg:classifiers":[
        {
            "category":"Insurance",
            "subcategory":"Insurance Agent",
            "type":"Services"
        }
    ],
    "sg:phone":"+1 541 343 6030",
    "sg:postcode":"97401",
    "sg:province":"OR",
    "wof:name":"State Farm Insurance",
    "wof:placetype":"venue"
},
  "geometry": {"coordinates":[-123.078217,44.067777],"type":"Point"}
}