{
  "type": "Feature",
  "properties": {
    "iso:country":"US",
    "sg:address":"2013 SE Kane Ave",
    "sg:city":"Gresham",
    "sg:classifiers":[
        {
            "category":"Building & Trades",
            "subcategory":"Construction",
            "type":"Services"
        }
    ],
    "sg:phone":"+1 503 669 7406",
    "sg:postcode":"97080",
    "sg:province":"OR",
    "sg:tags":[
        "contractor"
    ],
    "wof:name":"Chuck Rice Installations",
    "wof:placetype":"venue"
},
  "geometry": {"coordinates":[-122.401088,45.482744],"type":"Point"}
}