{
  "type": "Feature",
  "properties": {
    "addr:full":"31400 SW Laurelview Rd Hillsboro OR 97123",
    "addr:housenumber":"31400",
    "addr:postcode":"97123",
    "addr:street":"Sw Laurelview Rd",
    "iso:country":"US",
    "sg:address":"31400 SW Laurelview Rd",
    "sg:city":"Hillsboro",
    "sg:classifiers":[
        {
            "category":"Building & Trades",
            "subcategory":"Construction",
            "type":"Services"
        }
    ],
    "sg:phone":"+1 503 628 6033",
    "sg:postcode":"97123",
    "sg:province":"OR",
    "sg:tags":[
        "contractor"
    ],
    "wof:name":"Trina Rogowski",
    "wof:placetype":"venue"
},
  "geometry": {"coordinates":[-123.004924,45.401482],"type":"Point"}
}