{
  "type": "Feature",
  "properties": {
    "iso:country":"US",
    "sg:address":"42525 Stringtown Rd",
    "sg:city":"Astoria",
    "sg:classifiers":[
        {
            "category":"Personal",
            "subcategory":"Beauty Salon",
            "type":"Services"
        }
    ],
    "sg:phone":"+1 503 458 6939",
    "sg:postcode":"97103",
    "sg:province":"OR",
    "sg:tags":[
        "shop"
    ],
    "wof:name":"Donnas Hair Fashions",
    "wof:placetype":"venue"
},
  "geometry": {"coordinates":[-123.56588600000001,46.174274],"type":"Point"}
}