{
  "type": "Feature",
  "properties": {
    "iso:country":"US",
    "sg:address":"14125 NE Fremont Ct",
    "sg:city":"Portland",
    "sg:classifiers":[
        {
            "category":"Professional",
            "subcategory":"Advertising",
            "type":"Services"
        }
    ],
    "sg:phone":"+1 503 261 1600",
    "sg:postcode":"97230",
    "sg:province":"OR",
    "sg:tags":[
        "counselor"
    ],
    "wof:name":"Jeffrey Calvin & Assoc",
    "wof:placetype":"venue"
},
  "geometry": {"coordinates":[-122.516812,45.547403],"type":"Point"}
}