{
  "type": "Feature",
  "properties": {
    "addr:full":"5701 SW Multnomah Blvd Portland OR 97219",
    "addr:housenumber":"5701",
    "addr:postcode":"97219",
    "addr:street":"Sw Multnomah Blvd",
    "iso:country":"US",
    "sg:address":"5701 SW Multnomah Blvd",
    "sg:city":"Portland",
    "sg:classifiers":[
        {
            "category":"Health Services",
            "subcategory":"Clinic",
            "type":"Services"
        }
    ],
    "sg:phone":"+1 503 246 1505",
    "sg:postcode":"97219",
    "sg:province":"OR",
    "sg:tags":[
        "information",
        "alcoholism",
        "treatment"
    ],
    "wof:name":"Infinity Rehab",
    "wof:placetype":"venue"
},
  "geometry": {"coordinates":[-122.73513,45.467522],"type":"Point"}
}