{
  "type": "Feature",
  "properties": {
    "addr:full":"1780 Water St NE Salem OR 97301",
    "addr:housenumber":"1780",
    "addr:postcode":"97301",
    "addr:street":"Water St Ne",
    "iso:country":"US",
    "sg:address":"1780 Water St NE",
    "sg:city":"Salem",
    "sg:classifiers":[
        {
            "category":"Building & Trades",
            "subcategory":"Plumbing",
            "type":"Services"
        }
    ],
    "sg:phone":"+1 503 588 0235",
    "sg:postcode":"97301",
    "sg:province":"OR",
    "sg:tags":[
        "plumbing",
        "contractor"
    ],
    "wof:name":"Paladin Plumbing Inc",
    "wof:placetype":"venue"
},
  "geometry": {"coordinates":[-123.035335,44.956734],"type":"Point"}
}