{
  "type": "Feature",
  "properties": {
    "iso:country":"US",
    "sg:address":"1811 SE Haig St",
    "sg:city":"Portland",
    "sg:classifiers":[
        {
            "category":"Building & Trades",
            "subcategory":"Equipment Rental",
            "type":"Services"
        }
    ],
    "sg:phone":"+1 503 233 9438",
    "sg:postcode":"97202",
    "sg:province":"OR",
    "sg:tags":[
        "scaffolding"
    ],
    "wof:name":"Scaffold Erectors Inc",
    "wof:placetype":"venue"
},
  "geometry": {"coordinates":[-122.64570500000001,45.498196],"type":"Point"}
}