{
  "type": "Feature",
  "properties": {
    "addr:full":"1550 SE 14th St Lincoln City OR 97367",
    "addr:housenumber":"1550",
    "addr:postcode":"97367",
    "addr:street":"Se 14Th St",
    "iso:country":"US",
    "sg:address":"1550 SE 14th St",
    "sg:city":"Lincoln City",
    "sg:classifiers":[
        {
            "category":"Real Estate",
            "subcategory":"Real Estate Operator",
            "type":"Services"
        }
    ],
    "sg:phone":"+1 541 994 4202",
    "sg:postcode":"97367",
    "sg:province":"OR",
    "sg:tags":[
        "apartment"
    ],
    "wof:name":"Sea Haven Apartments",
    "wof:placetype":"venue"
},
  "geometry": {"coordinates":[-124.012073,44.957568],"type":"Point"}
}