{
  "type": "Feature",
  "properties": {
    "addr:full":"2024 N Argyle St Portland OR 97217",
    "addr:housenumber":"2024",
    "addr:postcode":"97217",
    "addr:street":"N Argyle St",
    "iso:country":"US",
    "sg:address":"2024 N Argyle St",
    "sg:city":"Portland",
    "sg:classifiers":[
        {
            "category":"Professional",
            "subcategory":"Business Services",
            "type":"Services"
        }
    ],
    "sg:phone":"+1 503 289 8203",
    "sg:postcode":"97217",
    "sg:province":"OR",
    "sg:tags":[
        "holding"
    ],
    "wof:name":"Zenith Industries Inc",
    "wof:placetype":"venue"
},
  "geometry": {"coordinates":[-122.68724,45.584539],"type":"Point"}
}