{
  "type": "Feature",
  "properties": {
    "iso:country":"US",
    "sg:address":"24050 SE Stark St",
    "sg:city":"Gresham",
    "sg:classifiers":[
        {
            "category":"Building & Trades",
            "subcategory":"Construction",
            "type":"Services"
        }
    ],
    "sg:phone":"+1 503 492 9263",
    "sg:postcode":"97030",
    "sg:province":"OR",
    "sg:tags":[
        "house"
    ],
    "wof:name":"Deross Construction",
    "wof:placetype":"venue"
},
  "geometry": {"coordinates":[-122.412579,45.519],"type":"Point"}
}