{
  "type": "Feature",
  "properties": {
    "addr:full":"20 N 4th St Central Point OR 97502",
    "addr:housenumber":"20",
    "addr:postcode":"97502",
    "addr:street":"N 4Th St",
    "iso:country":"US",
    "sg:address":"20 N 4th St",
    "sg:city":"Central Point",
    "sg:classifiers":[
        {
            "category":"Professional",
            "type":"Services"
        }
    ],
    "sg:phone":"+1 541 665 2513",
    "sg:postcode":"97502",
    "sg:province":"OR",
    "sg:tags":[
        "establishment"
    ],
    "wof:name":"American's Bulletin",
    "wof:placetype":"venue"
},
  "geometry": {"coordinates":[-122.915148,42.376343],"type":"Point"}
}