{
  "type": "Feature",
  "properties": {
    "addr:full":"35635 Cochran Creek Dr Brownsville OR 97327",
    "addr:housenumber":"35635",
    "addr:postcode":"97327",
    "addr:street":"Cochran Creek Dr",
    "iso:country":"US",
    "sg:address":"35635 Cochran Creek Dr",
    "sg:city":"Brownsville",
    "sg:classifiers":[
        {
            "category":"Shopping",
            "subcategory":"Bicycles & Sporting Goods",
            "type":"Retail Goods"
        }
    ],
    "sg:phone":"+1 541 466 5272",
    "sg:postcode":"97327",
    "sg:province":"OR",
    "wof:name":"Pioneer Sports Center",
    "wof:placetype":"venue"
},
  "geometry": {"coordinates":[-122.965541,44.429813],"type":"Point"}
}