{
  "type": "Feature",
  "properties": {
    "addr:full":"738 E Burnside St Portland OR 97214",
    "addr:housenumber":"738",
    "addr:postcode":"97214",
    "addr:street":"E Burnside St",
    "iso:country":"US",
    "sg:address":"738 E Burnside St",
    "sg:city":"Portland",
    "sg:classifiers":[
        {
            "category":"Restaurant",
            "type":"Food & Drink"
        }
    ],
    "sg:phone":"+1 503 546 8796",
    "sg:postcode":"97214",
    "sg:province":"OR",
    "sg:tags":[
        "new",
        "american",
        "french"
    ],
    "sg:website":"www.lepigeon.com",
    "wof:name":"Le Pigeon",
    "wof:placetype":"venue"
},
  "geometry": {"coordinates":[-122.657912,45.522915],"type":"Point"}
}