{
  "type": "Feature",
  "properties": {
    "iso:country":"US",
    "sg:address":"18925 SE El Camino Ter",
    "sg:city":"Damascus",
    "sg:classifiers":[
        {
            "category":"Real Estate",
            "subcategory":"Real Estate Services",
            "type":"Services"
        }
    ],
    "sg:phone":"+1 503 467 6257",
    "sg:postcode":"97089",
    "sg:province":"OR",
    "sg:tags":[
        "home",
        "inspector"
    ],
    "sg:website":"www.mthoodhomeinspections.com",
    "wof:name":"Mt. Hood Home Inspections Inc",
    "wof:placetype":"venue"
},
  "geometry": {"coordinates":[-122.468041,45.426013],"type":"Point"}
}