{
  "type": "Feature",
  "properties": {
    "iso:country":"US",
    "sg:address":"16200 SW Pacific Hwy",
    "sg:city":"Tigard",
    "sg:classifiers":[
        {
            "category":"Coffee & Tea",
            "type":"Food & Drink"
        }
    ],
    "sg:phone":"+1 503 684 5397",
    "sg:postcode":"97224",
    "sg:province":"OR",
    "wof:name":"Starbucks",
    "wof:placetype":"venue"
},
  "geometry": {"coordinates":[-122.79532,45.403249],"type":"Point"}
}