{
  "type": "Feature",
  "properties": {
    "iso:country":"US",
    "sg:address":"857 28th St",
    "sg:city":"Springfield",
    "sg:classifiers":[
        {
            "category":"Manufacturing",
            "subcategory":"Tools & Machinery",
            "type":"Manufacturing & Wholesale Goods"
        }
    ],
    "sg:phone":"+1 541 747 8512",
    "sg:postcode":"97477",
    "sg:province":"OR",
    "sg:tags":[
        "physician",
        "surgeon"
    ],
    "sg:website":"www.conixresearch.com",
    "wof:name":"Conix Research",
    "wof:placetype":"venue"
},
  "geometry": {"coordinates":[-122.98661800000001,44.053329],"type":"Point"}
}