{
  "type": "Feature",
  "properties": {
    "addr:full":"527 NW Elm Ave Redmond OR 97756",
    "addr:housenumber":"527",
    "addr:postcode":"97756",
    "addr:street":"Nw Elm Ave",
    "iso:country":"US",
    "sg:address":"527 NW Elm Ave",
    "sg:city":"Redmond",
    "sg:classifiers":[
        {
            "category":"Restaurant",
            "type":"Food & Drink"
        }
    ],
    "sg:phone":"+1 541 548 6300",
    "sg:postcode":"97756",
    "sg:province":"OR",
    "wof:name":"Geno's New York Pizza",
    "wof:placetype":"venue"
},
  "geometry": {"coordinates":[-121.174027,44.280212],"type":"Point"}
}