{
  "type": "Feature",
  "properties": {
    "addr:full":"2615 Wiard St Klamath Falls OR 97603",
    "addr:housenumber":"2615",
    "addr:postcode":"97603",
    "addr:street":"Wiard St",
    "iso:country":"US",
    "sg:address":"2615 Wiard St",
    "sg:city":"Klamath Falls",
    "sg:classifiers":[
        {
            "category":"Freight",
            "type":"Transportation"
        }
    ],
    "sg:phone":"+1 541 884 8632",
    "sg:postcode":"97603",
    "sg:province":"OR",
    "sg:tags":[
        "car",
        "pilot"
    ],
    "wof:name":"A-1 Pilot Escort Svc",
    "wof:placetype":"venue"
},
  "geometry": {"coordinates":[-121.727591,42.202892],"type":"Point"}
}