{
  "type": "Feature",
  "properties": {
    "addr:full":"5800 N Fork Siuslaw Rd Florence OR 97439",
    "addr:housenumber":"5800",
    "addr:postcode":"97439",
    "addr:street":"N;Siuslaw Rd",
    "iso:country":"US",
    "sg:address":"5800 N Fork Siuslaw Rd",
    "sg:city":"Florence",
    "sg:classifiers":[
        {
            "category":"Manufacturing",
            "subcategory":"Petroleum Products",
            "type":"Manufacturing & Wholesale Goods"
        }
    ],
    "sg:phone":"+1 541 997 9617",
    "sg:postcode":"97439",
    "sg:province":"OR",
    "sg:tags":[
        "roofing",
        "material",
        "mfg"
    ],
    "wof:name":"North Fork Roofing Materials",
    "wof:placetype":"venue"
},
  "geometry": {"coordinates":[-124.07406,43.989119],"type":"Point"}
}