{
  "type": "Feature",
  "properties": {
    "iso:country":"US",
    "sg:address":"3608 NE Auto Mall Dr",
    "sg:city":"Portland",
    "sg:classifiers":[
        {
            "category":"Autos & Motor Vehicles",
            "subcategory":"Automobile Sales",
            "type":"Retail Goods"
        }
    ],
    "sg:phone":"+1 503 230 1490",
    "sg:postcode":"97201",
    "sg:province":"OR",
    "sg:tags":[
        "car"
    ],
    "sg:website":"www.nissanusa.com",
    "wof:name":"Alan Webb Nissan",
    "wof:placetype":"venue"
},
  "geometry": {"coordinates":[-122.59837,45.648181],"type":"Point"}
}