{
  "type": "Feature",
  "properties": {
    "iso:country":"US",
    "sg:address":"14525 SW Millikan Way",
    "sg:city":"Beaverton",
    "sg:classifiers":[
        {
            "category":"Professional",
            "subcategory":"Business Services",
            "type":"Services"
        },
        {
            "category":"Real Estate",
            "subcategory":"Architect",
            "type":"Services"
        }
    ],
    "sg:phone":"+1 503 828 9410",
    "sg:postcode":"97005",
    "sg:province":"OR",
    "sg:tags":[
        "record",
        "document",
        "destruction"
    ],
    "sg:website":"http://www.shrednations.com",
    "wof:name":"Shred Nations Shredding Service",
    "wof:placetype":"venue"
},
  "geometry": {"coordinates":[-122.82562,45.494293],"type":"Point"}
}