{
  "type": "Feature",
  "properties": {
    "iso:country":"US",
    "sg:address":"1694 Lincoln St",
    "sg:city":"North Bend",
    "sg:classifiers":[
        {
            "category":"Shopping",
            "subcategory":"Beauty & Cosmetics",
            "type":"Retail Goods"
        }
    ],
    "sg:phone":"+1 541 756 4609",
    "sg:postcode":"97459",
    "sg:province":"OR",
    "sg:tags":[
        "merchandise"
    ],
    "wof:name":"Merle Kyelberg Constructi",
    "wof:placetype":"venue"
},
  "geometry": {"coordinates":[-124.24919800000001,43.410935],"type":"Point"}
}