{
  "type": "Feature",
  "properties": {
    "iso:country":"US",
    "sg:address":"6105 NE M L King Boulevard",
    "sg:city":"Portland",
    "sg:classifiers":[
        {
            "category":"Retail",
            "subcategory":"Auto Repair",
            "type":"Services"
        }
    ],
    "sg:phone":"+1 503 285 4145",
    "sg:postcode":"97211",
    "sg:province":"OR",
    "wof:name":"Art of Maintenance",
    "wof:placetype":"venue"
},
  "geometry": {"coordinates":[-122.66145400000001,45.566931],"type":"Point"}
}