{
  "type": "Feature",
  "properties": {
    "addr:full":"2123 SE Division St Portland OR 97202",
    "addr:housenumber":"2123",
    "addr:postcode":"97202",
    "addr:street":"Se Division St",
    "iso:country":"US",
    "sg:address":"2123 SE Division St",
    "sg:city":"Portland",
    "sg:classifiers":[
        {
            "category":"Professional",
            "subcategory":"Advertising",
            "type":"Services"
        }
    ],
    "sg:phone":"+1 503 247 3510",
    "sg:postcode":"97202",
    "sg:province":"OR",
    "sg:tags":[
        "advertising-promotional",
        "product"
    ],
    "sg:website":"https://www.butlerpromotions.com",
    "wof:name":"Butler Promotions",
    "wof:placetype":"venue"
},
  "geometry": {"coordinates":[-122.64438800000001,45.504822],"type":"Point"}
}