{
  "type": "Feature",
  "properties": {
    "iso:country":"US",
    "sg:address":"1802 12th St",
    "sg:city":"Hood River",
    "sg:classifiers":[
        {
            "category":"Autos & Motor Vehicles",
            "subcategory":"Automobile Sales",
            "type":"Retail Goods"
        }
    ],
    "sg:phone":"+1 541 386 5277",
    "sg:postcode":"97031",
    "sg:province":"OR",
    "sg:tags":[
        "car",
        "dealer"
    ],
    "sg:website":"www.hoodriverford.com",
    "wof:name":"Hood River Ford Mercury",
    "wof:placetype":"venue"
},
  "geometry": {"coordinates":[-121.52368,45.696564],"type":"Point"}
}