{
  "type": "Feature",
  "properties": {
    "iso:country":"US",
    "sg:address":"25200 SE Stark St",
    "sg:city":"Gresham",
    "sg:classifiers":[
        {
            "category":"Social Services",
            "subcategory":"Adult Care",
            "type":"Services"
        }
    ],
    "sg:phone":"+1 503 665 4300",
    "sg:postcode":"97030",
    "sg:province":"OR",
    "sg:tags":[
        "home",
        "residential"
    ],
    "sg:website":"www.assisted.com",
    "wof:name":"Alterra Wynwood",
    "wof:placetype":"venue"
},
  "geometry": {"coordinates":[-122.405613,45.519064],"type":"Point"}
}