{
  "type": "Feature",
  "properties": {
    "iso:country":"US",
    "sg:address":"4107 NE 33rd Ave",
    "sg:city":"Portland",
    "sg:classifiers":[
        {
            "category":"Professional",
            "subcategory":"Computer Services",
            "type":"Services"
        }
    ],
    "sg:phone":"+1 503 335 8074",
    "sg:postcode":"97211",
    "sg:province":"OR",
    "sg:tags":[
        "web",
        "via",
        "process",
        "processing",
        "datum",
        "integrate",
        "technology"
    ],
    "wof:name":"Lawrence Tazzo Carlyle",
    "wof:placetype":"venue"
},
  "geometry": {"coordinates":[-122.63067599999999,45.553079],"type":"Point"}
}