{
  "type": "Feature",
  "properties": {
    "addr:full":"14450 SE Johnson Rd Milwaukie OR 97267",
    "addr:postcode":"14450;97267",
    "addr:street":"Se Johnson Rd",
    "iso:country":"US",
    "sg:address":"14450 SE Johnson Rd",
    "sg:city":"Milwaukie",
    "sg:classifiers":[
        {
            "category":"Education",
            "subcategory":"School",
            "type":"Public Place"
        }
    ],
    "sg:phone":"+1 503 353 5925",
    "sg:postcode":"97267",
    "sg:province":"OR",
    "sg:website":"www.newurban.org",
    "wof:name":"New Urban High School",
    "wof:placetype":"venue"
},
  "geometry": {"coordinates":[-122.57938900000001,45.417585],"type":"Point"}
}