{
  "type": "Feature",
  "properties": {
    "iso:country":"US",
    "sg:address":"36440 NW Harrington Rd",
    "sg:city":"Cornelius",
    "sg:classifiers":[
        {
            "category":"Banks & Credit Unions",
            "subcategory":"Bank",
            "type":"Services"
        }
    ],
    "sg:phone":"+1 503 648 5409",
    "sg:postcode":"97113",
    "sg:province":"OR",
    "sg:tags":[
        "personal",
        "institution"
    ],
    "wof:name":"Financial Wellness Assoc LLC",
    "wof:placetype":"venue"
},
  "geometry": {"coordinates":[-123.050214,45.588854],"type":"Point"}
}