{
  "type": "Feature",
  "properties": {
    "iso:country":"US",
    "sg:address":"39390 Griggs Dr",
    "sg:city":"Lebanon",
    "sg:classifiers":[
        {
            "category":"Utilities",
            "subcategory":"Refuse",
            "type":"Services"
        }
    ],
    "sg:phone":"+1 541 259 5454",
    "sg:postcode":"97355",
    "sg:province":"OR",
    "sg:tags":[
        "material",
        "system"
    ],
    "wof:name":"Recycling Depot Inc",
    "wof:placetype":"venue"
},
  "geometry": {"coordinates":[-122.831633,44.614214],"type":"Point"}
}