{
  "type": "Feature",
  "properties": {
    "iso:country":"US",
    "sg:address":"38201 Weirich Dr",
    "sg:city":"Lebanon",
    "sg:classifiers":[
        {
            "category":"Retail",
            "subcategory":"Auto Repair",
            "type":"Services"
        }
    ],
    "sg:phone":"+1 541 259 3950",
    "sg:postcode":"97355",
    "sg:province":"OR",
    "sg:tags":[
        "general"
    ],
    "wof:name":"Hagemans Garage",
    "wof:placetype":"venue"
},
  "geometry": {"coordinates":[-122.870439,44.508076],"type":"Point"}
}