{
  "type": "Feature",
  "properties": {
    "iso:country":"US",
    "sg:address":"1924 Nebraska Ave",
    "sg:city":"Grants Pass",
    "sg:classifiers":[
        {
            "category":"Professional",
            "type":"Services"
        }
    ],
    "sg:phone":"+1 541 471 1184",
    "sg:postcode":"97527",
    "sg:province":"OR",
    "wof:name":"Care Around Clock",
    "wof:placetype":"venue"
},
  "geometry": {"coordinates":[-123.347385,42.415538],"type":"Point"}
}