{
  "type": "Feature",
  "properties": {
    "addr:full":"15051 NW Orchard View Rd Mcminnville OR 97128",
    "addr:housenumber":"15051",
    "addr:postcode":"97128",
    "addr:street":"Nw Orchard View Rd",
    "iso:country":"US",
    "sg:address":"15051 NW Orchard View Rd",
    "sg:city":"Mcminnville",
    "sg:classifiers":[
        {
            "category":"Building & Trades",
            "subcategory":"Construction",
            "type":"Services"
        }
    ],
    "sg:phone":"+1 503 472 8845",
    "sg:postcode":"97128",
    "sg:province":"OR",
    "sg:tags":[
        "house",
        "nonresidential"
    ],
    "wof:name":"McMinnville Woodworking",
    "wof:placetype":"venue"
},
  "geometry": {"coordinates":[-123.26929800000001,45.237664],"type":"Point"}
}