{
  "type": "Feature",
  "properties": {
    "addr:full":"538 NW 19th St Ontario OR 97914",
    "addr:housenumber":"538",
    "addr:postcode":"97914",
    "addr:street":"Nw 19Th St",
    "iso:country":"US",
    "sg:address":"538 NW 19th St",
    "sg:city":"Ontario",
    "sg:classifiers":[
        {
            "category":"Professional",
            "subcategory":"Management & Consulting",
            "type":"Services"
        }
    ],
    "sg:phone":"+1 541 881 1593",
    "sg:postcode":"97914",
    "sg:province":"OR",
    "sg:tags":[
        "engineering"
    ],
    "wof:name":"Fredrick L Negus",
    "wof:placetype":"venue"
},
  "geometry": {"coordinates":[-116.99225199999999,44.03329],"type":"Point"}
}