{
  "type": "Feature",
  "properties": {
    "iso:country":"US",
    "sg:address":"8414 SW Barbur Blvd",
    "sg:city":"Portland",
    "sg:classifiers":[
        {
            "category":"Wholesale",
            "subcategory":"Motor Vehicles",
            "type":"Manufacturing & Wholesale Goods"
        }
    ],
    "sg:phone":"+1 503 245 9060",
    "sg:postcode":"97219",
    "sg:province":"OR",
    "sg:tags":[
        "automobile",
        "truck",
        "broker"
    ],
    "wof:name":"James Baker",
    "wof:placetype":"venue"
},
  "geometry": {"coordinates":[-122.70091600000001,45.463782],"type":"Point"}
}