{
  "type": "Feature",
  "properties": {
    "iso:country":"US",
    "sg:address":"35024 Maple St",
    "sg:city":"Saint Helens",
    "sg:classifiers":[
        {
            "category":"Building & Trades",
            "subcategory":"Construction",
            "type":"Services"
        }
    ],
    "sg:phone":"+1 503 397 3722",
    "sg:postcode":"97051",
    "sg:province":"OR",
    "sg:tags":[
        "general",
        "contractor"
    ],
    "wof:name":"Jim Rensch Construction",
    "wof:placetype":"venue"
},
  "geometry": {"coordinates":[-122.84485100000001,45.846325],"type":"Point"}
}