{
  "type": "Feature",
  "properties": {
    "iso:country":"US",
    "sg:address":"9810 E Burnside St",
    "sg:city":"Portland",
    "sg:classifiers":[
        {
            "category":"Shopping",
            "subcategory":"Clothing, Apparel, & Fashions",
            "type":"Retail Goods"
        }
    ],
    "sg:phone":"+1 503 255 8897",
    "sg:postcode":"97216",
    "sg:province":"OR",
    "sg:tags":[
        "building",
        "work",
        "nonresidential",
        "op"
    ],
    "wof:name":"Uniforms Etc Inc",
    "wof:placetype":"venue"
},
  "geometry": {"coordinates":[-122.56276699999999,45.522555],"type":"Point"}
}