{
  "type": "Feature",
  "properties": {
    "addr:full":"8898 SW Stono Dr Tualatin OR 97062",
    "addr:housenumber":"8898",
    "addr:postcode":"97062",
    "addr:street":"Sw Stono Dr",
    "iso:country":"US",
    "sg:address":"8898 SW Stono Dr",
    "sg:city":"Tualatin",
    "sg:classifiers":[
        {
            "category":"Shopping",
            "subcategory":"Books",
            "type":"Retail Goods"
        }
    ],
    "sg:phone":"+1 503 692 5206",
    "sg:postcode":"97062",
    "sg:province":"OR",
    "sg:tags":[
        "dealer"
    ],
    "wof:name":"Teacher's Toolbox",
    "wof:placetype":"venue"
},
  "geometry": {"coordinates":[-122.76825700000001,45.355056],"type":"Point"}
}