{
  "type": "Feature",
  "properties": {
    "iso:country":"US",
    "sg:address":"7645 SW Bonita Road Apt 21",
    "sg:city":"Portland",
    "sg:classifiers":[
        {
            "category":"Real Estate",
            "subcategory":"Real Estate Operator",
            "type":"Services"
        }
    ],
    "sg:phone":"+1 503 620 7451",
    "sg:postcode":"97224",
    "sg:province":"OR",
    "sg:tags":[
        "apartment"
    ],
    "wof:name":"Creekside Commons Apts",
    "wof:placetype":"venue"
},
  "geometry": {"coordinates":[-122.756389,45.415203],"type":"Point"}
}