{
  "type": "Feature",
  "properties": {
    "addr:full":"38930 Highway 226 Scio OR 97374",
    "addr:housenumber":"38930",
    "addr:postcode":"97374",
    "addr:street":"Highway 226",
    "iso:country":"US",
    "sg:address":"38930 Highway 226",
    "sg:city":"Scio",
    "sg:classifiers":[
        {
            "category":"Building & Trades",
            "subcategory":"Construction",
            "type":"Services"
        }
    ],
    "sg:phone":"+1 503 394 2899",
    "sg:postcode":"97374",
    "sg:province":"OR",
    "sg:tags":[
        "system",
        "contractor",
        "air conditioning"
    ],
    "wof:name":"Traeger Heating & Cooling Inc",
    "wof:placetype":"venue"
},
  "geometry": {"coordinates":[-122.848776,44.70267],"type":"Point"}
}