{
  "type": "Feature",
  "properties": {
    "iso:country":"US",
    "sg:address":"1019 SW 1st Ave",
    "sg:city":"Canby",
    "sg:classifiers":[
        {
            "category":"Sports & Exercise",
            "subcategory":"Gym",
            "type":"Entertainment"
        }
    ],
    "sg:phone":"+1 503 263 6449",
    "sg:postcode":"97013",
    "sg:province":"OR",
    "sg:tags":[
        "fitness",
        "physical",
        "facility"
    ],
    "wof:name":"Akea School of Self Defense",
    "wof:placetype":"venue"
},
  "geometry": {"coordinates":[-122.703791,45.256457],"type":"Point"}
}