{
  "type": "Feature",
  "properties": {
    "addr:full":"1815 NW 169th Pl Ste 3060 Beaverton OR 97006",
    "addr:housenumber":"1815",
    "addr:postcode":"97006",
    "addr:street":"Nw 169Th Pl Ste 3060",
    "iso:country":"US",
    "sg:address":"1815 NW 169th Pl Ste 3060",
    "sg:city":"Beaverton",
    "sg:classifiers":[
        {
            "category":"Wholesale",
            "subcategory":"Computers",
            "type":"Manufacturing & Wholesale Goods"
        }
    ],
    "sg:phone":"+1 503 614 9000",
    "sg:postcode":"97006",
    "sg:province":"OR",
    "wof:name":"MacNaughton Inc",
    "wof:placetype":"venue"
},
  "geometry": {"coordinates":[-122.851997,45.533001],"type":"Point"}
}