{
  "type": "Feature",
  "properties": {
    "addr:full":"312 E 1st St Mcminnville OR 97128",
    "addr:housenumber":"312",
    "addr:postcode":"97128",
    "addr:street":"E 1St St",
    "iso:country":"US",
    "sg:address":"312 E 1st St",
    "sg:city":"Mcminnville",
    "sg:classifiers":[
        {
            "category":"Shopping",
            "type":"Retail Goods"
        }
    ],
    "sg:phone":"+1 503 538 1529",
    "sg:postcode":"97128",
    "sg:province":"OR",
    "sg:tags":[
        "merchandise"
    ],
    "wof:name":"Rampant Lion",
    "wof:placetype":"venue"
},
  "geometry": {"coordinates":[-123.196716,45.208516],"type":"Point"}
}