{
  "type": "Feature",
  "properties": {
    "iso:country":"US",
    "sg:address":"10418 NE Shaver St",
    "sg:city":"Portland",
    "sg:classifiers":[
        {
            "category":"Building & Trades",
            "subcategory":"Cleaning & Sanitation",
            "type":"Services"
        }
    ],
    "sg:phone":"+1 503 254 3498",
    "sg:postcode":"97220",
    "sg:province":"OR",
    "sg:tags":[
        "maintenance"
    ],
    "wof:name":"Alex & Mila Janitorial Service",
    "wof:placetype":"venue"
},
  "geometry": {"coordinates":[-122.555504,45.551697],"type":"Point"}
}