{
  "type": "Feature",
  "properties": {
    "iso:country":"US",
    "sg:address":"17555 65th Ave",
    "sg:city":"Lake Oswego",
    "sg:classifiers":[
        {
            "category":"Wholesale",
            "subcategory":"Medical Equipment & Supplies",
            "type":"Manufacturing & Wholesale Goods"
        }
    ],
    "sg:phone":"+1 503 620 5625",
    "sg:postcode":"97035",
    "sg:province":"OR",
    "sg:tags":[
        "hospital"
    ],
    "wof:name":"Tri-Medical",
    "wof:placetype":"venue"
},
  "geometry": {"coordinates":[-122.743958,45.400661],"type":"Point"}
}