{
  "type": "Feature",
  "properties": {
    "addr:full":"4720 SW Watson Ave Beaverton OR 97005",
    "addr:housenumber":"4720",
    "addr:postcode":"97005",
    "addr:street":"Sw Watson Ave",
    "iso:country":"US",
    "sg:address":"4720 SW Watson Ave",
    "sg:city":"Beaverton",
    "sg:classifiers":[
        {
            "category":"Health Services",
            "subcategory":"Health Practitioner",
            "type":"Services"
        }
    ],
    "sg:phone":"+1 503 526 0397",
    "sg:postcode":"97005",
    "sg:province":"OR",
    "sg:tags":[
        "acupuncture",
        "naturopathic/holistic"
    ],
    "wof:name":"Stargrove Mitchell Bebel Nd L Ac",
    "wof:placetype":"venue"
},
  "geometry": {"coordinates":[-122.806999,45.4855],"type":"Point"}
}