{
  "type": "Feature",
  "properties": {
    "iso:country":"US",
    "sg:address":"4903 NE Sandy Blvd",
    "sg:city":"Portland",
    "sg:classifiers":[
        {
            "category":"Manufacturing",
            "subcategory":"Signs",
            "type":"Manufacturing & Wholesale Goods"
        }
    ],
    "sg:phone":"+1 503 288 4360",
    "sg:postcode":"97213",
    "sg:province":"OR",
    "sg:tags":[
        "specialty",
        "mfg"
    ],
    "wof:name":"Sunsigns",
    "wof:placetype":"venue"
},
  "geometry": {"coordinates":[-122.61197799999999,45.539517],"type":"Point"}
}