{
  "type": "Feature",
  "properties": {
    "iso:country":"US",
    "sg:address":"72760 Apiary-Market Rd",
    "sg:city":"Rainier",
    "sg:classifiers":[
        {
            "category":"Building & Trades",
            "subcategory":"Construction",
            "type":"Services"
        }
    ],
    "sg:phone":"+1 503 556 3289",
    "sg:postcode":"97048",
    "sg:province":"OR",
    "sg:tags":[
        "heavy",
        "contractor"
    ],
    "wof:name":"D McCoys Logging Co",
    "wof:placetype":"venue"
},
  "geometry": {"coordinates":[-123.030646,46.054995],"type":"Point"}
}