{
  "type": "Feature",
  "properties": {
    "addr:full":"28111 SE Wally Rd Boring OR 97009",
    "addr:postcode":"28111;97009",
    "addr:street":"Se Wally Rd",
    "iso:country":"US",
    "sg:address":"28111 SE Wally Rd",
    "sg:city":"Boring",
    "sg:classifiers":[
        {
            "category":"Manufacturing",
            "subcategory":"Musical Instruments",
            "type":"Manufacturing & Wholesale Goods"
        }
    ],
    "sg:phone":"+1 503 663 7265",
    "sg:postcode":"97009",
    "sg:province":"OR",
    "sg:tags":[
        "instruments-industrial-repairing"
    ],
    "sg:website":"http://www.advancedcalibration.com",
    "wof:name":"Advanced Calibration Tech",
    "wof:placetype":"venue"
},
  "geometry": {"coordinates":[-122.375129,45.430334],"type":"Point"}
}