{
  "type": "Feature",
  "properties": {
    "addr:full":"180 Fenton St Apt 19 Molalla OR 97038",
    "addr:housenumber":"180;19",
    "addr:postcode":"97038",
    "addr:street":"Fenton St Apt",
    "iso:country":"US",
    "sg:address":"180 Fenton St Apt 19",
    "sg:city":"Molalla",
    "sg:classifiers":[
        {
            "category":"Real Estate",
            "subcategory":"Real Estate Services",
            "type":"Services"
        },
        {
            "category":"Real Estate",
            "subcategory":"Real Estate Operator",
            "type":"Services"
        }
    ],
    "sg:phone":"+1 503 829 7206",
    "sg:postcode":"97038",
    "sg:province":"OR",
    "sg:tags":[
        "apartment",
        "vacancy",
        "listing",
        "rental",
        "finder"
    ],
    "wof:name":"Rondel Court Apartments",
    "wof:placetype":"venue"
},
  "geometry": {"coordinates":[-122.571253,45.148574],"type":"Point"}
}