{
  "type": "Feature",
  "properties": {
    "addr:full":"421 NW 10th Ave Portland OR 97209",
    "addr:housenumber":"421",
    "addr:postcode":"97209",
    "addr:street":"Nw 10Th Ave",
    "iso:country":"US",
    "sg:address":"421 NW 10th Ave",
    "sg:city":"Portland",
    "sg:classifiers":[
        {
            "category":"Food & Beverages",
            "subcategory":"Candy",
            "type":"Retail Goods"
        },
        {
            "category":"Food & Beverages",
            "subcategory":"Chocolate",
            "type":"Retail Goods"
        }
    ],
    "sg:phone":"+1 503 525 9400",
    "sg:postcode":"97209",
    "sg:province":"OR",
    "sg:tags":[
        "shop",
        "chocolatiers",
        "store"
    ],
    "sg:website":"www.verdunchocolates.com",
    "wof:name":"Verdun Fine Chocolate",
    "wof:placetype":"venue"
},
  "geometry": {"coordinates":[-122.68123300000001,45.526457],"type":"Point"}
}