{
  "type": "Feature",
  "properties": {
    "addr:full":"777 NW 9th St Corvallis OR 97330",
    "addr:housenumber":"777",
    "addr:postcode":"97330",
    "addr:street":"Nw 9Th St",
    "iso:country":"US",
    "sg:address":"777 NW 9th St",
    "sg:city":"Corvallis",
    "sg:classifiers":[
        {
            "category":"Insurance",
            "subcategory":"Insurance Agent",
            "type":"Services"
        }
    ],
    "sg:phone":"+1 541 757 8500",
    "sg:postcode":"97330",
    "sg:province":"OR",
    "wof:name":"Pawlowski Financial Group",
    "wof:placetype":"venue"
},
  "geometry": {"coordinates":[-123.264369,44.571378],"type":"Point"}
}