{
  "type": "Feature",
  "properties": {
    "addr:full":"4144B SE 60th Ave Portland OR 97206",
    "addr:housenumber":"4144b",
    "addr:postcode":"97206",
    "addr:street":"Se 60Th Ave",
    "iso:country":"US",
    "sg:address":"4144B SE 60th Ave",
    "sg:city":"Portland",
    "sg:classifiers":[
        {
            "category":"Insurance",
            "subcategory":"Insurance Agent",
            "type":"Services"
        },
        {
            "category":"Insurance",
            "subcategory":"Hazard Insurance",
            "type":"Services"
        },
        {
            "category":"Insurance",
            "subcategory":"Title Insurance",
            "type":"Services"
        },
        {
            "category":"Insurance",
            "subcategory":"Life Insurance",
            "type":"Services"
        }
    ],
    "sg:phone":"+1 503 777 1784",
    "sg:postcode":"97206",
    "sg:province":"OR",
    "sg:tags":[
        "business",
        "auto",
        "commercial",
        "homeowner",
        "motorcycle",
        "renter"
    ],
    "wof:name":"Allstate Insurance Company - Lanhuong Tran",
    "wof:placetype":"venue"
},
  "geometry": {"coordinates":[-122.601761,45.492738],"type":"Point"}
}