{
  "type": "Feature",
  "properties": {
    "iso:country":"US",
    "sg:address":"2360 S 6th St",
    "sg:city":"Klamath Falls",
    "sg:phone":"+1 541 273 2700",
    "sg:postcode":"97603",
    "sg:province":"OR",
    "sg:tags":[
        "oil"
    ],
    "wof:name":"Ezell-Suty Fuel",
    "wof:placetype":"venue"
},
  "geometry": {"coordinates":[-121.76083800000001,42.213008],"type":"Point"}
}