{
  "type": "Feature",
  "properties": {
    "iso:country":"US",
    "sg:address":"5690 Commercial St SE",
    "sg:city":"Salem",
    "sg:classifiers":[
        {
            "category":"Bars & Pubs",
            "type":"Food & Drink"
        }
    ],
    "sg:phone":"+1 503 364 6835",
    "sg:postcode":"97306",
    "sg:province":"OR",
    "sg:tags":[
        "tavern"
    ],
    "wof:name":"Stone Front Tavern",
    "wof:placetype":"venue"
},
  "geometry": {"coordinates":[-123.023881,44.871887],"type":"Point"}
}