{
  "type": "Feature",
  "properties": {
    "addr:full":"266 SE 9th St Grants Pass OR 97526",
    "addr:housenumber":"266",
    "addr:postcode":"97526",
    "addr:street":"Se 9Th St",
    "iso:country":"US",
    "sg:address":"266 SE 9th St",
    "sg:city":"Grants Pass",
    "sg:classifiers":[
        {
            "category":"Personal",
            "subcategory":"Beauty Salon",
            "type":"Services"
        }
    ],
    "sg:phone":"+1 541 476 2111",
    "sg:postcode":"97526",
    "sg:province":"OR",
    "wof:name":"House Of Charles",
    "wof:placetype":"venue"
},
  "geometry": {"coordinates":[-123.323736,42.437271],"type":"Point"}
}