{
  "type": "Feature",
  "properties": {
    "addr:full":"10 N Central Ave Medford OR 97501",
    "addr:housenumber":"10",
    "addr:postcode":"97501",
    "addr:street":"N Central Ave",
    "iso:country":"US",
    "sg:address":"10 N Central Ave",
    "sg:city":"Medford",
    "sg:classifiers":[
        {
            "category":"Personal",
            "subcategory":"Day Spa",
            "type":"Services"
        }
    ],
    "sg:phone":"+1 541 858 8177",
    "sg:postcode":"97501",
    "sg:province":"OR",
    "wof:name":"Lostus Hair Body & Soul",
    "wof:placetype":"venue"
},
  "geometry": {"coordinates":[-122.872107,42.326703],"type":"Point"}
}