{
  "type": "Feature",
  "properties": {
    "iso:country":"US",
    "sg:address":"29990 SE Eagle Creek Rd",
    "sg:city":"Estacada",
    "sg:classifiers":[
        {
            "category":"Professional",
            "subcategory":"Management & Consulting",
            "type":"Services"
        }
    ],
    "sg:phone":"+1 503 630 2720",
    "sg:postcode":"97023",
    "sg:province":"OR",
    "wof:name":"Hanson Enterprises",
    "wof:placetype":"venue"
},
  "geometry": {"coordinates":[-122.338877,45.306006],"type":"Point"}
}