{
  "type": "Feature",
  "properties": {
    "iso:country":"US",
    "sg:address":"11605 SW Beaverton Hillsdale Hwy",
    "sg:city":"Beaverton",
    "sg:classifiers":[
        {
            "category":"Building & Trades",
            "subcategory":"Locksmith",
            "type":"Services"
        }
    ],
    "sg:phone":"+1 503 643 3664",
    "sg:postcode":"97005",
    "sg:province":"OR",
    "sg:tags":[
        "locksmiths-commercial",
        "industrial",
        "supply",
        "lock",
        "equipment"
    ],
    "wof:name":"A Sap Wholesale Locksmith",
    "wof:placetype":"venue"
},
  "geometry": {"coordinates":[-122.796086,45.486519],"type":"Point"}
}