{
  "type": "Feature",
  "properties": {
    "addr:full":"15348 US Hwy 101 Brookings OR 97415",
    "addr:housenumber":"15348",
    "addr:postcode":"97415",
    "addr:street":"Us Hwy 101",
    "iso:country":"US",
    "sg:address":"15348 US Hwy 101",
    "sg:city":"Brookings",
    "sg:classifiers":[
        {
            "category":"Travel",
            "subcategory":"Hotels & Motels",
            "type":"Entertainment"
        }
    ],
    "sg:phone":"+1 541 469 3494",
    "sg:postcode":"97415",
    "sg:province":"OR",
    "sg:tags":[
        "resort"
    ],
    "wof:name":"Chetco River Resort",
    "wof:placetype":"venue"
},
  "geometry": {"coordinates":[-124.23070199999999,42.026093],"type":"Point"}
}