{
  "type": "Feature",
  "properties": {
    "iso:country":"US",
    "sg:address":"2375 McGilchrist St SE",
    "sg:city":"Salem",
    "sg:classifiers":[
        {
            "category":"Wholesale",
            "subcategory":"Electrical",
            "type":"Manufacturing & Wholesale Goods"
        }
    ],
    "sg:phone":"+1 503 585 7411",
    "sg:postcode":"97302",
    "sg:province":"OR",
    "sg:tags":[
        "transmission",
        "equipment",
        "power"
    ],
    "sg:website":"www.mill-supply.com",
    "wof:name":"Mill Supply Corp",
    "wof:placetype":"venue"
},
  "geometry": {"coordinates":[-123.012921,44.916675],"type":"Point"}
}