{
  "type": "Feature",
  "properties": {
    "addr:full":"11172 Wheatland Rd NE Gervais OR 97026",
    "addr:housenumber":"11172",
    "addr:postcode":"97026",
    "addr:street":"Wheatland Rd Ne",
    "iso:country":"US",
    "sg:address":"11172 Wheatland Rd NE",
    "sg:city":"Gervais",
    "sg:classifiers":[
        {
            "category":"Building & Trades",
            "subcategory":"Equipment Rental",
            "type":"Services"
        }
    ],
    "sg:phone":"+1 503 463 6594",
    "sg:postcode":"97026",
    "sg:province":"OR",
    "sg:tags":[
        "camping"
    ],
    "wof:name":"A A Tent Co",
    "wof:placetype":"venue"
},
  "geometry": {"coordinates":[-123.03155,45.080839],"type":"Point"}
}