{
  "type": "Feature",
  "properties": {
    "iso:country":"US",
    "sg:address":"1889 N Bayshore Dr",
    "sg:city":"Coos Bay",
    "sg:classifiers":[
        {
            "category":"Retail",
            "subcategory":"Auto Rental",
            "type":"Services"
        }
    ],
    "sg:phone":"+1 541 267 5653",
    "sg:postcode":"97420",
    "sg:province":"OR",
    "sg:tags":[
        "renting",
        "truck",
        "leasing"
    ],
    "wof:name":"Budget Truck Rental",
    "wof:placetype":"venue"
},
  "geometry": {"coordinates":[-124.21942900000001,43.38121],"type":"Point"}
}