{
  "type": "Feature",
  "properties": {
    "addr:full":"6623 NE 82nd Ave Portland OR 97220",
    "addr:housenumber":"6623",
    "addr:postcode":"97220",
    "addr:street":"Ne 82Nd Ave",
    "iso:country":"US",
    "sg:address":"6623 NE 82nd Ave",
    "sg:city":"Portland",
    "sg:classifiers":[
        {
            "category":"Organizations",
            "subcategory":"Professional Association",
            "type":"Services"
        }
    ],
    "sg:phone":"+1 503 251 8170",
    "sg:postcode":"97220",
    "sg:province":"OR",
    "sg:website":"www.westa1.org",
    "wof:name":"Westa",
    "wof:placetype":"venue"
},
  "geometry": {"coordinates":[-122.577763,45.569328],"type":"Point"}
}