{
  "type": "Feature",
  "properties": {
    "iso:country":"US",
    "sg:address":"9344 Mount Ashland Ski Rd",
    "sg:city":"Ashland",
    "sg:classifiers":[
        {
            "category":"Manufacturing",
            "subcategory":"Furniture",
            "type":"Manufacturing & Wholesale Goods"
        }
    ],
    "sg:phone":"+1 541 482 3522",
    "sg:postcode":"97520",
    "sg:province":"OR",
    "sg:tags":[
        "wood",
        "mfg"
    ],
    "wof:name":"Frenzel Company",
    "wof:placetype":"venue"
},
  "geometry": {"coordinates":[-122.614195,42.070783],"type":"Point"}
}