{
  "type": "Feature",
  "properties": {
    "iso:country":"US",
    "sg:address":"645 SW Marshall St",
    "sg:city":"Madras",
    "sg:classifiers":[
        {
            "category":"Real Estate",
            "subcategory":"Real Estate Services",
            "type":"Services"
        },
        {
            "category":"Real Estate",
            "subcategory":"Real Estate Operator",
            "type":"Services"
        }
    ],
    "sg:phone":"+1 541 475 5743",
    "sg:postcode":"97741",
    "sg:province":"OR",
    "sg:tags":[
        "vacancy",
        "apartment",
        "rental",
        "finder",
        "listing"
    ],
    "wof:name":"Madras Townhomes",
    "wof:placetype":"venue"
},
  "geometry": {"coordinates":[-121.137664,44.626344],"type":"Point"}
}