{
  "type": "Feature",
  "properties": {
    "addr:full":"3671 Fifteen Mile Rd The Dalles OR 97058",
    "addr:housenumber":"3671",
    "addr:postcode":"97058",
    "addr:street":"Fifteen Mile Rd",
    "iso:country":"US",
    "sg:address":"3671 Fifteen Mile Rd",
    "sg:city":"The Dalles",
    "sg:classifiers":[
        {
            "category":"Real Estate",
            "subcategory":"Real Estate Operator",
            "type":"Services"
        }
    ],
    "sg:phone":"+1 541 296 5588",
    "sg:postcode":"97058",
    "sg:province":"OR",
    "sg:tags":[
        "property",
        "lessor"
    ],
    "wof:name":"Anderson Enterprises",
    "wof:placetype":"venue"
},
  "geometry": {"coordinates":[-121.108926,45.608818],"type":"Point"}
}