{
  "type": "Feature",
  "properties": {
    "addr:full":"67585 SW Cline Falls Rd Redmond OR 97756",
    "addr:housenumber":"67585",
    "addr:postcode":"97756",
    "addr:street":"Sw Cline Falls Rd",
    "iso:country":"US",
    "sg:address":"67585 SW Cline Falls Rd",
    "sg:city":"Redmond",
    "sg:classifiers":[
        {
            "category":"Wholesale",
            "subcategory":"Construction Materials",
            "type":"Manufacturing & Wholesale Goods"
        }
    ],
    "sg:phone":"+1 541 548 1455",
    "sg:postcode":"97756",
    "sg:province":"OR",
    "sg:tags":[
        "rock"
    ],
    "wof:name":"Cline Butte Rock Pit",
    "wof:placetype":"venue"
},
  "geometry": {"coordinates":[-121.292203,44.237652],"type":"Point"}
}