{
  "type": "Feature",
  "properties": {
    "addr:full":"400 Highland Ave Coos Bay OR 97420",
    "addr:housenumber":"400",
    "addr:postcode":"97420",
    "addr:street":"Highland Ave",
    "iso:country":"US",
    "sg:address":"400 Highland Ave",
    "sg:city":"Coos Bay",
    "sg:classifiers":[
        {
            "category":"Organizations",
            "subcategory":"Religious Organization",
            "type":"Services"
        }
    ],
    "sg:phone":"+1 541 269 5829",
    "sg:postcode":"97420",
    "sg:province":"OR",
    "sg:tags":[
        "church"
    ],
    "wof:name":"Emmanuel Episcopal Church",
    "wof:placetype":"venue"
},
  "geometry": {"coordinates":[-124.216537,43.369941],"type":"Point"}
}