{
  "type": "Feature",
  "properties": {
    "iso:country":"US",
    "sg:address":"220 NE 20th Ave",
    "sg:city":"Portland",
    "sg:classifiers":[
        {
            "category":"Professional",
            "subcategory":"Art Services",
            "type":"Services"
        }
    ],
    "sg:phone":"+1 503 236 0116",
    "sg:postcode":"97232",
    "sg:province":"OR",
    "sg:tags":[
        "graphic",
        "designer"
    ],
    "wof:name":"Lloyd Appleton Inc",
    "wof:placetype":"venue"
},
  "geometry": {"coordinates":[-122.645402,45.524876],"type":"Point"}
}