{
  "type": "Feature",
  "properties": {
    "iso:country":"US",
    "sg:address":"1 Centerpointe Dr",
    "sg:city":"Lake Oswego",
    "sg:classifiers":[
        {
            "category":"Organizations",
            "subcategory":"Professional Association",
            "type":"Services"
        }
    ],
    "sg:phone":"+1 503 718 6700",
    "sg:postcode":"97035",
    "sg:province":"OR",
    "wof:name":"Surplus Line Assn",
    "wof:placetype":"venue"
},
  "geometry": {"coordinates":[-122.74026499999999,45.423345],"type":"Point"}
}