{
  "type": "Feature",
  "properties": {
    "iso:country":"US",
    "sg:address":"165 S Miller St",
    "sg:city":"Rockaway Beach",
    "sg:classifiers":[
        {
            "category":"Real Estate",
            "subcategory":"Real Estate Agent",
            "type":"Services"
        }
    ],
    "sg:phone":"+1 503 355 8400",
    "sg:postcode":"97136",
    "sg:province":"OR",
    "sg:tags":[
        "rental",
        "vacation"
    ],
    "wof:name":"Ocean Breeze Vacation Rentals",
    "wof:placetype":"venue"
},
  "geometry": {"coordinates":[-123.944394,45.611871],"type":"Point"}
}