{
  "type": "Feature",
  "properties": {
    "iso:country":"US",
    "sg:address":"145 Macarthur St",
    "sg:city":"Saint Helens",
    "sg:classifiers":[
        {
            "category":"Manufacturing",
            "subcategory":"Lumber",
            "type":"Manufacturing & Wholesale Goods"
        }
    ],
    "sg:phone":"+1 603 397 0895",
    "sg:postcode":"97051",
    "sg:province":"OR",
    "sg:tags":[
        "forestry"
    ],
    "wof:name":"Gunn & Sons Contract Logging",
    "wof:placetype":"venue"
},
  "geometry": {"coordinates":[-122.830268,45.860382],"type":"Point"}
}