{
  "type": "Feature",
  "properties": {
    "iso:country":"US",
    "sg:address":"382 SE Washington St",
    "sg:city":"Hillsboro",
    "sg:classifiers":[
        {
            "category":"Manufacturing",
            "subcategory":"Electronics",
            "type":"Manufacturing & Wholesale Goods"
        }
    ],
    "sg:phone":"+1 503 693 1221",
    "sg:postcode":"97123",
    "sg:province":"OR",
    "sg:tags":[
        "equipment",
        "heat",
        "exchanger"
    ],
    "sg:website":"http://www.courtneyandnye.com",
    "wof:name":"Courtney & Nye Inc",
    "wof:placetype":"venue"
},
  "geometry": {"coordinates":[-122.984674,45.521335],"type":"Point"}
}