{
  "type": "Feature",
  "properties": {
    "iso:country":"US",
    "sg:address":"14154 SE Stark St",
    "sg:city":"Portland",
    "sg:classifiers":[
        {
            "category":"Insurance",
            "subcategory":"Hazard Insurance",
            "type":"Services"
        }
    ],
    "sg:phone":"+1 503 253 2110",
    "sg:postcode":"97233",
    "sg:province":"OR",
    "sg:website":"http://statefarm.mqgroup.com/url.asp?usr=37969E",
    "wof:name":"State Farm Insurance Agent-Will McCreery",
    "wof:placetype":"venue"
},
  "geometry": {"coordinates":[-122.517731,45.519119],"type":"Point"}
}