{
  "type": "Feature",
  "properties": {
    "iso:country":"US",
    "sg:address":"3225 Boardman Ave",
    "sg:city":"Klamath Falls",
    "sg:classifiers":[
        {
            "category":"Restaurant",
            "type":"Food & Drink"
        }
    ],
    "sg:phone":"+1 541 884 5427",
    "sg:postcode":"97603",
    "sg:province":"OR",
    "sg:tags":[
        "sandwich"
    ],
    "wof:name":"Randy's Sandwiches",
    "wof:placetype":"venue"
},
  "geometry": {"coordinates":[-121.750012,42.203029],"type":"Point"}
}