{
  "type": "Feature",
  "properties": {
    "iso:country":"US",
    "sg:address":"34850 Resort Dr",
    "sg:city":"Cloverdale",
    "sg:classifiers":[
        {
            "category":"Farming",
            "subcategory":"Dairy Farm",
            "type":"Manufacturing & Wholesale Goods"
        }
    ],
    "sg:phone":"+1 503 965 6336",
    "sg:postcode":"97112",
    "sg:province":"OR",
    "wof:name":"Martella S&E Dairy",
    "wof:placetype":"venue"
},
  "geometry": {"coordinates":[-123.94909800000001,45.205105],"type":"Point"}
}