{
  "type": "Feature",
  "properties": {
    "iso:country":"US",
    "sg:address":"1295 Johnson St NE",
    "sg:city":"Salem",
    "sg:classifiers":[
        {
            "category":"Industrial Area",
            "type":"Public Place"
        }
    ],
    "sg:phone":"+1 503 362 5558",
    "sg:postcode":"97301",
    "sg:province":"OR",
    "sg:tags":[
        "development"
    ],
    "wof:name":"Capital Warehouse Co.",
    "wof:placetype":"venue"
},
  "geometry": {"coordinates":[-123.01689,44.966171],"type":"Point"}
}