{
  "type": "Feature",
  "properties": {
    "addr:full":"237 SW Emigrant Ave Pendleton OR 97801",
    "addr:housenumber":"237",
    "addr:postcode":"97801",
    "addr:street":"Sw Emigrant Ave",
    "iso:country":"US",
    "sg:address":"237 SW Emigrant Ave",
    "sg:city":"Pendleton",
    "sg:classifiers":[
        {
            "category":"Food & Beverages",
            "subcategory":"Liquor & Beverages",
            "type":"Retail Goods"
        }
    ],
    "sg:phone":"+1 541 276 1202",
    "sg:postcode":"97801",
    "sg:province":"OR",
    "wof:name":"Pendleton Liquor Stores",
    "wof:placetype":"venue"
},
  "geometry": {"coordinates":[-118.788453,45.669996],"type":"Point"}
}