{
  "type": "Feature",
  "properties": {
    "addr:full":"9347 N Peninsular Ave Portland OR 97217",
    "addr:housenumber":"9347",
    "addr:postcode":"97217",
    "addr:street":"N Peninsular Ave",
    "iso:country":"US",
    "sg:address":"9347 N Peninsular Ave",
    "sg:city":"Portland",
    "sg:classifiers":[
        {
            "category":"Wholesale",
            "subcategory":"Hardware",
            "type":"Manufacturing & Wholesale Goods"
        }
    ],
    "sg:phone":"+1 503 251 1247",
    "sg:postcode":"97217",
    "sg:province":"OR",
    "sg:tags":[
        "refrigerating"
    ],
    "sg:website":"www.equipmentwholesalers.com",
    "wof:name":"Equipment Wholesalers",
    "wof:placetype":"venue"
},
  "geometry": {"coordinates":[-122.69729100000001,45.588627],"type":"Point"}
}