{
  "type": "Feature",
  "properties": {
    "iso:country":"US",
    "sg:address":"5289 NE Elam Young Pkwy",
    "sg:city":"Hillsboro",
    "sg:classifiers":[
        {
            "category":"Building & Trades",
            "subcategory":"Construction",
            "type":"Services"
        }
    ],
    "sg:phone":"+1 503 693 8185",
    "sg:postcode":"97124",
    "sg:province":"OR",
    "sg:tags":[
        "contractor"
    ],
    "wof:name":"Zellweger Analytics",
    "wof:placetype":"venue"
},
  "geometry": {"coordinates":[-122.931006,45.52953],"type":"Point"}
}