{
  "type": "Feature",
  "properties": {
    "iso:country":"US",
    "sg:address":"21282 SW Makah Ct",
    "sg:city":"Tualatin",
    "sg:classifiers":[
        {
            "category":"Professional",
            "type":"Services"
        }
    ],
    "sg:phone":"+1 503 692 3185",
    "sg:postcode":"97062",
    "sg:province":"OR",
    "wof:name":"Terrys Attic",
    "wof:placetype":"venue"
},
  "geometry": {"coordinates":[-122.762545,45.365163],"type":"Point"}
}