{
  "type": "Feature",
  "properties": {
    "addr:full":"12755 SW Beaverdam Rd Beaverton OR 97005",
    "addr:housenumber":"12755",
    "addr:postcode":"97005",
    "addr:street":"Sw Beaverdam Rd",
    "iso:country":"US",
    "sg:address":"12755 SW Beaverdam Rd",
    "sg:city":"Beaverton",
    "sg:classifiers":[
        {
            "category":"Personal",
            "subcategory":"Beauty Salon",
            "type":"Services"
        }
    ],
    "sg:phone":"+1 503 643 5907",
    "sg:postcode":"97005",
    "sg:province":"OR",
    "sg:tags":[
        "nail"
    ],
    "wof:name":"Tokyo Beauty",
    "wof:placetype":"venue"
},
  "geometry": {"coordinates":[-122.807999,45.488701],"type":"Point"}
}