{
  "type": "Feature",
  "properties": {
    "iso:country":"US",
    "sg:address":"4466 Great Plains Dr NE",
    "sg:city":"Salem",
    "sg:classifiers":[
        {
            "category":"Building & Trades",
            "subcategory":"Construction",
            "type":"Services"
        }
    ],
    "sg:phone":"+1 503 304 2952",
    "sg:postcode":"97305",
    "sg:province":"OR",
    "sg:tags":[
        "house"
    ],
    "wof:name":"Aquila Construction Group Inc",
    "wof:placetype":"venue"
},
  "geometry": {"coordinates":[-122.961859,44.983565],"type":"Point"}
}