{
  "type": "Feature",
  "properties": {
    "iso:country":"US",
    "sg:address":"1515 SW 5th Ave Suite 600",
    "sg:city":"Portland",
    "sg:classifiers":[
        {
            "category":"Professional",
            "subcategory":"Lawyer & Legal Services",
            "type":"Services"
        }
    ],
    "sg:phone":"+1 503 295 2668",
    "sg:postcode":"97201",
    "sg:province":"OR",
    "sg:tags":[
        "litigation",
        "tort",
        "attorney"
    ],
    "wof:name":"Duncan, M Elizabeth - Greene & Markley",
    "wof:placetype":"venue"
},
  "geometry": {"coordinates":[-122.680509,45.513374],"type":"Point"}
}