{
  "type": "Feature",
  "properties": {
    "iso:country":"US",
    "sg:address":"2827 NE M L King Boulevard",
    "sg:city":"Portland",
    "sg:classifiers":[
        {
            "category":"Real Estate",
            "subcategory":"Architect",
            "type":"Services"
        }
    ],
    "sg:phone":"+1 503 282 7674",
    "sg:postcode":"97212",
    "sg:province":"OR",
    "wof:name":"MacKenzie Hilary Architect",
    "wof:placetype":"venue"
},
  "geometry": {"coordinates":[-122.661783,45.543324],"type":"Point"}
}