{
  "type": "Feature",
  "properties": {
    "addr:full":"6161 Riordan Rd Prineville OR 97754",
    "addr:housenumber":"6161",
    "addr:postcode":"97754",
    "addr:street":"Riordan Rd",
    "iso:country":"US",
    "sg:address":"6161 Riordan Rd",
    "sg:city":"Prineville",
    "sg:classifiers":[
        {
            "category":"Home & Garden",
            "subcategory":"Home Furnishings",
            "type":"Retail Goods"
        }
    ],
    "sg:phone":"+1 541 447 5517",
    "sg:postcode":"97754",
    "sg:province":"OR",
    "sg:tags":[
        "glassware",
        "chinaware"
    ],
    "wof:name":"Princess House Inc",
    "wof:placetype":"venue"
},
  "geometry": {"coordinates":[-120.776438,44.218303],"type":"Point"}
}