{
  "type": "Feature",
  "properties": {
    "addr:full":"7110 SW Fir Loop Ste 125 Portland OR 97223",
    "addr:housenumber":"7110",
    "addr:postcode":"97223",
    "addr:street":"Sw Fir Loop Ste 125",
    "iso:country":"US",
    "sg:address":"7110 SW Fir Loop Ste 125",
    "sg:city":"Portland",
    "sg:classifiers":[
        {
            "category":"Wholesale",
            "subcategory":"Office Equipment",
            "type":"Manufacturing & Wholesale Goods"
        },
        {
            "category":"Shopping",
            "subcategory":"Stationery & Office Supplies",
            "type":"Retail Goods"
        },
        {
            "category":"Professional",
            "subcategory":"Business Services",
            "type":"Services"
        },
        {
            "category":"Shopping",
            "subcategory":"Computers & Home Electronics",
            "type":"Retail Goods"
        },
        {
            "category":"Professional",
            "subcategory":"Printing & Photocopies",
            "type":"Services"
        }
    ],
    "sg:phone":"+1 503 639 6279",
    "sg:postcode":"97223",
    "sg:province":"OR",
    "sg:tags":[
        "scanning",
        "printer",
        "form",
        "register",
        "autographic",
        "system",
        "printers-business",
        "plotting"
    ],
    "wof:name":"Form Analysis",
    "wof:placetype":"venue"
},
  "geometry": {"coordinates":[-122.749931,45.422946],"type":"Point"}
}