{
  "type": "Feature",
  "properties": {
    "addr:full":"2305 NE Strawberry Ln Corvallis OR 97330",
    "addr:housenumber":"2305",
    "addr:postcode":"97330",
    "addr:street":"Ne Strawberry Ln",
    "iso:country":"US",
    "sg:address":"2305 NE Strawberry Ln",
    "sg:city":"Corvallis",
    "sg:classifiers":[
        {
            "category":"Building & Trades",
            "subcategory":"Construction",
            "type":"Services"
        }
    ],
    "sg:phone":"+1 541 753 6597",
    "sg:postcode":"97330",
    "sg:province":"OR",
    "sg:tags":[
        "contractor"
    ],
    "wof:name":"Smith Brothers Roofing Inc",
    "wof:placetype":"venue"
},
  "geometry": {"coordinates":[-123.20120799999999,44.591903],"type":"Point"}
}