{
  "type": "Feature",
  "properties": {
    "iso:country":"US",
    "sg:address":"80801 Rich Ln",
    "sg:city":"Hermiston",
    "sg:classifiers":[
        {
            "category":"Retail",
            "subcategory":"Auto Repair",
            "type":"Services"
        }
    ],
    "sg:phone":"+1 541 567 7762",
    "sg:postcode":"97838",
    "sg:province":"OR",
    "sg:tags":[
        "general"
    ],
    "wof:name":"Whites Automotive Repair",
    "wof:placetype":"venue"
},
  "geometry": {"coordinates":[-119.23797,45.871695],"type":"Point"}
}