{
  "type": "Feature",
  "properties": {
    "iso:country":"US",
    "sg:address":"6747 S 6th St",
    "sg:city":"Klamath Falls",
    "sg:classifiers":[
        {
            "category":"Shopping",
            "type":"Retail Goods"
        }
    ],
    "sg:phone":"+1 541 273 4787",
    "sg:postcode":"97603",
    "sg:province":"OR",
    "sg:tags":[
        "merchandise"
    ],
    "wof:name":"Joes Budget Store LLC",
    "wof:placetype":"venue"
},
  "geometry": {"coordinates":[-121.70642599999999,42.201815],"type":"Point"}
}