{
  "type": "Feature",
  "properties": {
    "addr:full":"510 SE Grand Avenue Portland OR 97214",
    "addr:housenumber":"510",
    "addr:postcode":"97214",
    "addr:street":"Se Grand Avenue",
    "iso:country":"US",
    "sg:address":"510 SE Grand Avenue",
    "sg:city":"Portland",
    "sg:classifiers":[
        {
            "category":"Retail",
            "subcategory":"Car Wash",
            "type":"Services"
        }
    ],
    "sg:phone":"+1 503 235 9740",
    "sg:postcode":"97214",
    "sg:province":"OR",
    "wof:name":"Mr Car Wash",
    "wof:placetype":"venue"
},
  "geometry": {"coordinates":[-122.660889,45.519064],"type":"Point"}
}