{
  "type": "Feature",
  "properties": {
    "addr:full":"2729 N Lombard St Portland OR 97217",
    "addr:housenumber":"2729",
    "addr:postcode":"97217",
    "addr:street":"N Lombard St",
    "iso:country":"US",
    "sg:address":"2729 N Lombard St",
    "sg:city":"Portland",
    "sg:classifiers":[
        {
            "category":"Travel",
            "subcategory":"Travel Agent",
            "type":"Entertainment"
        }
    ],
    "sg:phone":"+1 503 283 6228",
    "sg:postcode":"97217",
    "sg:province":"OR",
    "sg:tags":[
        "agency",
        "services-commercial"
    ],
    "wof:name":"C & A Servicio Latino",
    "wof:placetype":"venue"
},
  "geometry": {"coordinates":[-122.694926,45.577122],"type":"Point"}
}