{
  "type": "Feature",
  "properties": {
    "iso:country":"US",
    "sg:address":"1412 13th St",
    "sg:city":"Hood River",
    "sg:classifiers":[
        {
            "category":"Personal",
            "subcategory":"Beauty Salon",
            "type":"Services"
        }
    ],
    "sg:phone":"+1 541 386 6888",
    "sg:postcode":"97031",
    "sg:province":"OR",
    "sg:tags":[
        "unisex",
        "hair"
    ],
    "wof:name":"Studio 10",
    "wof:placetype":"venue"
},
  "geometry": {"coordinates":[-121.524771,45.700154],"type":"Point"}
}