{
  "type": "Feature",
  "properties": {
    "addr:full":"2410 NW Carden Ave Pendleton OR 97801",
    "addr:housenumber":"2410",
    "addr:postcode":"97801",
    "addr:street":"Nw Carden Ave",
    "iso:country":"US",
    "sg:address":"2410 NW Carden Ave",
    "sg:city":"Pendleton",
    "sg:classifiers":[
        {
            "category":"Real Estate",
            "subcategory":"Real Estate Operator",
            "type":"Services"
        }
    ],
    "sg:phone":"+1 541 276 5237",
    "sg:postcode":"97801",
    "sg:province":"OR",
    "sg:tags":[
        "building",
        "apartment"
    ],
    "wof:name":"Mountain View Apartments",
    "wof:placetype":"venue"
},
  "geometry": {"coordinates":[-118.81217100000001,45.673048],"type":"Point"}
}