{
  "type": "Feature",
  "properties": {
    "iso:country":"US",
    "sg:address":"11376 Ramsey Rd",
    "sg:city":"Gold Hill",
    "sg:classifiers":[
        {
            "category":"Farming",
            "subcategory":"Farm",
            "type":"Manufacturing & Wholesale Goods"
        }
    ],
    "sg:phone":"+1 541 855 9872",
    "sg:postcode":"97525",
    "sg:province":"OR",
    "sg:tags":[
        "crop",
        "general"
    ],
    "wof:name":"Don E Haney",
    "wof:placetype":"venue"
},
  "geometry": {"coordinates":[-123.000085,42.52703],"type":"Point"}
}