{
  "type": "Feature",
  "properties": {
    "iso:country":"US",
    "sg:address":"8501 NE Killingsworth St",
    "sg:city":"Portland",
    "sg:classifiers":[
        {
            "category":"Retail",
            "subcategory":"Car Wash",
            "type":"Services"
        }
    ],
    "sg:phone":"+1 503 314 7063",
    "sg:postcode":"97220",
    "sg:province":"OR",
    "sg:tags":[
        "carwash",
        "auto",
        "body"
    ],
    "wof:name":"All Phase Mobile",
    "wof:placetype":"venue"
},
  "geometry": {"coordinates":[-122.574065,45.562762],"type":"Point"}
}