{
  "type": "Feature",
  "properties": {
    "iso:country":"US",
    "sg:address":"9429 SW 8th Dr",
    "sg:city":"Portland",
    "sg:classifiers":[
        {
            "category":"Building & Trades",
            "subcategory":"Construction",
            "type":"Services"
        },
        {
            "category":"Manufacturing",
            "subcategory":"Building Materials",
            "type":"Manufacturing & Wholesale Goods"
        }
    ],
    "sg:phone":"+1 503 244 9277",
    "sg:postcode":"97219",
    "sg:province":"OR",
    "sg:tags":[
        "pumice",
        "brick",
        "concrete",
        "brick-clay-common",
        "face"
    ],
    "wof:name":"Northwest Pool Tile And Brick",
    "wof:placetype":"venue"
},
  "geometry": {"coordinates":[-122.688829,45.457045],"type":"Point"}
}