{
  "type": "Feature",
  "properties": {
    "iso:country":"US",
    "sg:address":"1820 SE Front St",
    "sg:city":"Astoria",
    "sg:classifiers":[
        {
            "category":"Restaurant",
            "type":"Food & Drink"
        }
    ],
    "sg:phone":"+1 503 325 1981",
    "sg:postcode":"97103",
    "sg:province":"OR",
    "wof:name":"Tide Point",
    "wof:placetype":"venue"
},
  "geometry": {"coordinates":[-123.81679699999999,46.171427],"type":"Point"}
}