{
  "type": "Feature",
  "properties": {
    "addr:full":"10505 SW Barbur Blvd Portland OR 97219",
    "addr:housenumber":"10505",
    "addr:postcode":"97219",
    "addr:street":"Sw Barbur Blvd",
    "iso:country":"US",
    "sg:address":"10505 SW Barbur Blvd",
    "sg:city":"Portland",
    "sg:classifiers":[
        {
            "category":"Organizations",
            "subcategory":"Non-profit Organization",
            "type":"Services"
        },
        {
            "category":"Government",
            "subcategory":"Office",
            "type":"Public Place"
        }
    ],
    "sg:phone":"+1 503 229 5033",
    "sg:postcode":"97219",
    "sg:province":"OR",
    "sg:tags":[
        "commission",
        "dairy"
    ],
    "sg:website":"www.oregondairycouncil.org",
    "wof:name":"Oregon Dairy Products Comm",
    "wof:placetype":"venue"
},
  "geometry": {"coordinates":[-122.72907499999999,45.448406],"type":"Point"}
}