{
  "type": "Feature",
  "properties": {
    "iso:country":"US",
    "sg:address":"19510 S Central Point Rd",
    "sg:city":"Oregon City",
    "sg:classifiers":[
        {
            "category":"Building & Trades",
            "subcategory":"Landscaping Services",
            "type":"Services"
        }
    ],
    "sg:phone":"+1 503 723 6998",
    "sg:postcode":"97045",
    "sg:province":"OR",
    "sg:tags":[
        "landscape"
    ],
    "wof:name":"A J Earthscapes",
    "wof:placetype":"venue"
},
  "geometry": {"coordinates":[-122.622231,45.323612],"type":"Point"}
}