{
  "type": "Feature",
  "properties": {
    "iso:country":"US",
    "sg:address":"9416 SW Washington Dr",
    "sg:city":"Portland",
    "sg:classifiers":[
        {
            "category":"Shopping",
            "subcategory":"Clothing, Apparel, & Fashions",
            "type":"Retail Goods"
        }
    ],
    "sg:phone":"+1 503 684 5466",
    "sg:postcode":"97223",
    "sg:province":"OR",
    "wof:name":"Claires",
    "wof:placetype":"venue"
},
  "geometry": {"coordinates":[-122.765889,45.452281],"type":"Point"}
}