{
  "type": "Feature",
  "properties": {
    "addr:full":"33920 Hwy 101 S Cloverdale OR 97112",
    "addr:housenumber":"33920",
    "addr:postcode":"97112",
    "addr:street":"Hwy 101 S",
    "iso:country":"US",
    "sg:address":"33920 Hwy 101 S",
    "sg:city":"Cloverdale",
    "sg:classifiers":[
        {
            "category":"Shopping",
            "subcategory":"Used Merchandise",
            "type":"Retail Goods"
        }
    ],
    "sg:phone":"+1 503 392 3973",
    "sg:postcode":"97112",
    "sg:province":"OR",
    "sg:tags":[
        "flea",
        "market"
    ],
    "wof:name":"Red Barn Flea Mart",
    "wof:placetype":"venue"
},
  "geometry": {"coordinates":[-123.881873,45.208918],"type":"Point"}
}