{
  "type": "Feature",
  "properties": {
    "iso:country":"US",
    "sg:address":"2126 SE 302nd Ave",
    "sg:city":"Troutdale",
    "sg:classifiers":[
        {
            "category":"Wholesale",
            "subcategory":"Groceries",
            "type":"Manufacturing & Wholesale Goods"
        }
    ],
    "sg:phone":"+1 503 665 1528",
    "sg:postcode":"97060",
    "sg:province":"OR",
    "sg:tags":[
        "general"
    ],
    "wof:name":"A S Burns Farms",
    "wof:placetype":"venue"
},
  "geometry": {"coordinates":[-122.352085,45.50692],"type":"Point"}
}