{
  "type": "Feature",
  "properties": {
    "addr:full":"15869 NW Sellers Rd Banks OR 97106",
    "addr:housenumber":"15869",
    "addr:postcode":"97106",
    "addr:street":"Nw Sellers Rd",
    "iso:country":"US",
    "sg:address":"15869 NW Sellers Rd",
    "sg:city":"Banks",
    "sg:classifiers":[
        {
            "category":"Home & Garden",
            "subcategory":"Building Materials",
            "type":"Retail Goods"
        }
    ],
    "sg:phone":"+1 503 844 8688",
    "sg:postcode":"97106",
    "sg:province":"OR",
    "sg:tags":[
        "roofing"
    ],
    "sg:website":"www.northamericanmetal.com",
    "wof:name":"North American Metals",
    "wof:placetype":"venue"
},
  "geometry": {"coordinates":[-123.11442099999999,45.636585],"type":"Point"}
}