{
  "type": "Feature",
  "properties": {
    "iso:country":"US",
    "sg:address":"4355 Thompson Creek Rd",
    "sg:city":"Selma",
    "sg:classifiers":[
        {
            "category":"Retail",
            "subcategory":"Auto Repair",
            "type":"Services"
        }
    ],
    "sg:phone":"+1 541 597 4487",
    "sg:postcode":"97538",
    "sg:province":"OR",
    "sg:tags":[
        "body",
        "automobile",
        "painting"
    ],
    "wof:name":"Recycled Auto Works",
    "wof:placetype":"venue"
},
  "geometry": {"coordinates":[-123.52299499999999,42.217513],"type":"Point"}
}