{
  "type": "Feature",
  "properties": {
    "iso:country":"US",
    "sg:address":"32525 Hst Columbia River Hwy",
    "sg:city":"Corbett",
    "sg:classifiers":[
        {
            "category":"Shopping",
            "subcategory":"Gifts & Souvenirs",
            "type":"Retail Goods"
        }
    ],
    "sg:phone":"+1 503 695 5239",
    "sg:postcode":"97019",
    "sg:province":"OR",
    "wof:name":"Scenic Creations LLC",
    "wof:placetype":"venue"
},
  "geometry": {"coordinates":[-122.328228,45.517909],"type":"Point"}
}