{
  "type": "Feature",
  "properties": {
    "iso:country":"US",
    "sg:address":"3688 NE Azalea St",
    "sg:city":"Hillsboro",
    "sg:classifiers":[
        {
            "category":"Personal",
            "subcategory":"Beauty Salon",
            "type":"Services"
        }
    ],
    "sg:phone":"+1 503 648 4569",
    "sg:postcode":"97124",
    "sg:province":"OR",
    "sg:tags":[
        "shop"
    ],
    "wof:name":"Loom Room",
    "wof:placetype":"venue"
},
  "geometry": {"coordinates":[-122.944435,45.52233],"type":"Point"}
}