{
  "type": "Feature",
  "properties": {
    "iso:country":"US",
    "sg:address":"4436 Ryan St",
    "sg:city":"Eugene",
    "sg:classifiers":[
        {
            "category":"Building & Trades",
            "subcategory":"Construction",
            "type":"Services"
        }
    ],
    "sg:phone":"+1 541 689 5753",
    "sg:postcode":"97404",
    "sg:province":"OR",
    "sg:tags":[
        "dry wall",
        "contractor"
    ],
    "wof:name":"Mudlark Dry-Wall",
    "wof:placetype":"venue"
},
  "geometry": {"coordinates":[-123.148409,44.125496],"type":"Point"}
}