{
  "type": "Feature",
  "properties": {
    "iso:country":"US",
    "sg:address":"131 E Main St",
    "sg:city":"John Day",
    "sg:classifiers":[
        {
            "category":"Manufacturing",
            "subcategory":"Printing",
            "type":"Manufacturing & Wholesale Goods"
        }
    ],
    "sg:phone":"+1 541 575 0012",
    "sg:postcode":"97845",
    "sg:province":"OR",
    "sg:tags":[
        "commercial"
    ],
    "wof:name":"Strawberry Mountain Graphics",
    "wof:placetype":"venue"
},
  "geometry": {"coordinates":[-119.10351900000001,44.713667],"type":"Point"}
}