{
  "type": "Feature",
  "properties": {
    "iso:country":"US",
    "sg:address":"1839 Molalla Ave",
    "sg:city":"Oregon City",
    "sg:classifiers":[
        {
            "category":"Personal",
            "subcategory":"Shoe Repair & Shine",
            "type":"Services"
        }
    ],
    "sg:phone":"+1 503 650 3883",
    "sg:postcode":"97045",
    "sg:province":"OR",
    "sg:tags":[
        "repairing",
        "boot"
    ],
    "wof:name":"Oregon City Shoe Repair",
    "wof:placetype":"venue"
},
  "geometry": {"coordinates":[-122.586465,45.331455],"type":"Point"}
}