{
  "type": "Feature",
  "properties": {
    "addr:full":"3026 SE 112th Ave Portland OR 97266",
    "addr:housenumber":"3026",
    "addr:postcode":"97266",
    "addr:street":"Se 112Th Ave",
    "iso:country":"US",
    "sg:address":"3026 SE 112th Ave",
    "sg:city":"Portland",
    "sg:classifiers":[
        {
            "category":"Building & Trades",
            "subcategory":"Construction",
            "type":"Services"
        }
    ],
    "sg:phone":"+1 503 760 3873",
    "sg:postcode":"97266",
    "sg:province":"OR",
    "sg:tags":[
        "excavation",
        "contractor"
    ],
    "wof:name":"Andy Davidson Co",
    "wof:placetype":"venue"
},
  "geometry": {"coordinates":[-122.547934,45.500143],"type":"Point"}
}