{
  "type": "Feature",
  "properties": {
    "addr:full":"65 Division Ave Eugene OR 97404",
    "addr:housenumber":"65",
    "addr:postcode":"97404",
    "addr:street":"Division Ave",
    "iso:country":"US",
    "sg:address":"65 Division Ave",
    "sg:city":"Eugene",
    "sg:classifiers":[
        {
            "category":"Building & Trades",
            "subcategory":"Cleaning & Sanitation",
            "type":"Services"
        }
    ],
    "sg:phone":"+1 541 484 0321",
    "sg:postcode":"97404",
    "sg:province":"OR",
    "sg:tags":[
        "maintenance"
    ],
    "wof:name":"Executive Cleaning Services",
    "wof:placetype":"venue"
},
  "geometry": {"coordinates":[-123.12639900000001,44.099097],"type":"Point"}
}