{
  "type": "Feature",
  "properties": {
    "iso:country":"US",
    "sg:address":"1230 NE 3rd St",
    "sg:city":"Bend",
    "sg:classifiers":[
        {
            "category":"Health Services",
            "subcategory":"Chiropractor",
            "type":"Services"
        },
        {
            "category":"Health Services",
            "subcategory":"Doctor",
            "type":"Services"
        }
    ],
    "sg:phone":"+1 541 389 3072",
    "sg:postcode":"97701",
    "sg:province":"OR",
    "sg:tags":[
        "clinic",
        "medical"
    ],
    "wof:name":"Lind Chiropractic Clinic",
    "wof:placetype":"venue"
},
  "geometry": {"coordinates":[-121.302432,44.06264],"type":"Point"}
}