{
  "type": "Feature",
  "properties": {
    "iso:country":"US",
    "sg:address":"360 Patrick Rd",
    "sg:city":"Grants Pass",
    "sg:classifiers":[
        {
            "category":"Health Services",
            "subcategory":"Nursing And Care Facility",
            "type":"Services"
        }
    ],
    "sg:phone":"+1 541 471 7199",
    "sg:postcode":"97527",
    "sg:province":"OR",
    "wof:name":"Donna Likens",
    "wof:placetype":"venue"
},
  "geometry": {"coordinates":[-123.38897,42.3918],"type":"Point"}
}