{
  "type": "Feature",
  "properties": {
    "iso:country":"US",
    "sg:address":"14362 SW Tewkesbury Dr",
    "sg:city":"Portland",
    "sg:classifiers":[
        {
            "category":"Education",
            "subcategory":"Music School",
            "type":"Public Place"
        },
        {
            "category":"Arts & Performance",
            "subcategory":"Arts Center",
            "type":"Entertainment"
        },
        {
            "category":"Arts & Performance",
            "subcategory":"Jazz & Blues",
            "type":"Entertainment"
        }
    ],
    "sg:phone":"+1 206 349 0758",
    "sg:postcode":"97224",
    "sg:province":"OR",
    "sg:tags":[
        "instrument",
        "performing",
        "teacher",
        "musical"
    ],
    "sg:website":"www.dennismossmusic.com/",
    "wof:name":"Dennis Moss",
    "wof:placetype":"venue"
},
  "geometry": {"coordinates":[-122.824769,45.405924],"type":"Point"}
}