{
  "type": "Feature",
  "properties": {
    "addr:full":"4711 N Lagoon Avenue Portland OR 97217",
    "addr:housenumber":"4711",
    "addr:postcode":"97217",
    "addr:street":"N Lagoon Avenue",
    "iso:country":"US",
    "sg:address":"4711 N Lagoon Avenue",
    "sg:city":"Portland",
    "sg:classifiers":[
        {
            "category":"Restaurant",
            "type":"Food & Drink"
        }
    ],
    "sg:phone":"+1 503 289 8888",
    "sg:postcode":"97217",
    "sg:province":"OR",
    "sg:website":"www.subway.com",
    "wof:name":"Subway Sandwiches & Salads",
    "wof:placetype":"venue"
},
  "geometry": {"coordinates":[-122.702291,45.557283],"type":"Point"}
}