{
  "type": "Feature",
  "properties": {
    "iso:country":"US",
    "sg:address":"21995 SW Finnigan Hill Rd",
    "sg:city":"Hillsboro",
    "sg:classifiers":[
        {
            "category":"Farming",
            "subcategory":"Berry Farm",
            "type":"Manufacturing & Wholesale Goods"
        }
    ],
    "sg:phone":"+1 503 628 1614",
    "sg:postcode":"97123",
    "sg:province":"OR",
    "sg:tags":[
        "dried",
        "grower"
    ],
    "wof:name":"Weaver Family Trust",
    "wof:placetype":"venue"
},
  "geometry": {"coordinates":[-123.01652799999999,45.378368],"type":"Point"}
}