{
  "type": "Feature",
  "properties": {
    "iso:country":"US",
    "sg:address":"4682 Liberty Rd S",
    "sg:city":"Salem",
    "sg:classifiers":[
        {
            "category":"Bars & Pubs",
            "type":"Food & Drink"
        },
        {
            "category":"Restaurant",
            "type":"Food & Drink"
        },
        {
            "category":"Bars & Pubs",
            "subcategory":"Lounge",
            "type":"Food & Drink"
        }
    ],
    "sg:phone":"+1 503 363 2739",
    "sg:postcode":"97302",
    "sg:province":"OR",
    "sg:tags":[
        "tavern",
        "grill",
        "brew",
        "cocktail"
    ],
    "wof:name":"South Liberty Road Bar & Grill",
    "wof:placetype":"venue"
},
  "geometry": {"coordinates":[-123.05981300000001,44.890966],"type":"Point"}
}