{
  "type": "Feature",
  "properties": {
    "iso:country":"US",
    "sg:address":"625 SW 9th St",
    "sg:city":"Dundee",
    "sg:classifiers":[
        {
            "category":"Real Estate",
            "subcategory":"Real Estate Operator",
            "type":"Services"
        }
    ],
    "sg:phone":"+1 503 538 3061",
    "sg:postcode":"97115",
    "sg:province":"OR",
    "sg:tags":[
        "mobile",
        "home",
        "site",
        "community"
    ],
    "wof:name":"Dundee Hills Estate",
    "wof:placetype":"venue"
},
  "geometry": {"coordinates":[-123.018479,45.278898],"type":"Point"}
}