{
  "type": "Feature",
  "properties": {
    "iso:country":"US",
    "sg:address":"17235 NW Corridor Ct",
    "sg:city":"Beaverton",
    "sg:classifiers":[
        {
            "category":"Shopping",
            "subcategory":"Stationery & Office Supplies",
            "type":"Retail Goods"
        },
        {
            "category":"Home & Garden",
            "subcategory":"Furniture",
            "type":"Retail Goods"
        }
    ],
    "sg:phone":"+1 503 533 5391",
    "sg:postcode":"97006",
    "sg:province":"OR",
    "sg:tags":[
        "equipment",
        "store"
    ],
    "wof:name":"Office Furniture Unlimited",
    "wof:placetype":"venue"
},
  "geometry": {"coordinates":[-122.853996,45.5354],"type":"Point"}
}