{
  "type": "Feature",
  "properties": {
    "iso:country":"US",
    "sg:address":"1700 NE 3rd St",
    "sg:city":"Bend",
    "sg:classifiers":[
        {
            "category":"Banks & Credit Unions",
            "subcategory":"Bank",
            "type":"Services"
        }
    ],
    "sg:phone":"+1 541 389 7701",
    "sg:postcode":"97701",
    "sg:province":"OR",
    "sg:tags":[
        "saving",
        "commercial"
    ],
    "sg:website":"http://www.botc.com",
    "wof:name":"Bank Of The Cascades",
    "wof:placetype":"venue"
},
  "geometry": {"coordinates":[-121.302528,44.066639],"type":"Point"}
}