{
  "type": "Feature",
  "properties": {
    "iso:country":"US",
    "sg:address":"617 N Morton St",
    "sg:city":"Newberg",
    "sg:classifiers":[
        {
            "category":"Professional",
            "type":"Services"
        }
    ],
    "sg:phone":"+1 503 537 1007",
    "sg:postcode":"97132",
    "sg:province":"OR",
    "sg:tags":[
        "establishment"
    ],
    "wof:name":"Page's Place",
    "wof:placetype":"venue"
},
  "geometry": {"coordinates":[-122.981779,45.305739],"type":"Point"}
}