{
  "type": "Feature",
  "properties": {
    "iso:country":"US",
    "sg:address":"826A NW 21st Ave",
    "sg:city":"Portland",
    "sg:classifiers":[
        {
            "category":"Building & Trades",
            "subcategory":"Locksmith",
            "type":"Services"
        }
    ],
    "sg:phone":"+1 503 715 3818",
    "sg:postcode":"97209",
    "sg:province":"OR",
    "sg:tags":[
        "key"
    ],
    "wof:name":"A-1 Locksmith",
    "wof:placetype":"venue"
},
  "geometry": {"coordinates":[-122.69430199999999,45.528637],"type":"Point"}
}