{
  "type": "Feature",
  "properties": {
    "iso:country":"US",
    "sg:address":"1399 Pansy Ln",
    "sg:city":"Grants Pass",
    "sg:classifiers":[
        {
            "category":"Autos & Motor Vehicles",
            "subcategory":"Motorcycle Sales",
            "type":"Retail Goods"
        }
    ],
    "sg:phone":"+1 541 479 7337",
    "sg:postcode":"97527",
    "sg:province":"OR",
    "wof:name":"H P Racing",
    "wof:placetype":"venue"
},
  "geometry": {"coordinates":[-123.350605,42.422437],"type":"Point"}
}