{
  "type": "Feature",
  "properties": {
    "iso:country":"US",
    "sg:address":"12875 SW Watkins Ave",
    "sg:city":"Portland",
    "sg:classifiers":[
        {
            "category":"Wholesale",
            "subcategory":"Computers",
            "type":"Manufacturing & Wholesale Goods"
        }
    ],
    "sg:phone":"+1 503 620 7806",
    "sg:postcode":"97223",
    "sg:province":"OR",
    "wof:name":"Edwards JD Co",
    "wof:placetype":"venue"
},
  "geometry": {"coordinates":[-122.78327400000001,45.428597],"type":"Point"}
}