{
  "type": "Feature",
  "properties": {
    "iso:country":"US",
    "sg:address":"3220 Northwest Way",
    "sg:city":"Redmond",
    "sg:classifiers":[
        {
            "category":"Professional",
            "type":"Services"
        }
    ],
    "sg:phone":"+1 541 923 0484",
    "sg:postcode":"97756",
    "sg:province":"OR",
    "wof:name":"Kim V Delashmutt",
    "wof:placetype":"venue"
},
  "geometry": {"coordinates":[-121.203778,44.30928],"type":"Point"}
}