{
  "type": "Feature",
  "properties": {
    "iso:country":"US",
    "sg:address":"109 Elkay Dr",
    "sg:city":"Eugene",
    "sg:classifiers":[
        {
            "category":"Shopping",
            "subcategory":"Gifts & Souvenirs",
            "type":"Retail Goods"
        }
    ],
    "sg:phone":"+1 541 689 6290",
    "sg:postcode":"97404",
    "sg:province":"OR",
    "wof:name":"Blue Moon Dreams & Gifts",
    "wof:placetype":"venue"
},
  "geometry": {"coordinates":[-123.122367,44.076798],"type":"Point"}
}