{
  "type": "Feature",
  "properties": {
    "addr:full":"557 Pacific Ave Springfield OR 97477",
    "addr:housenumber":"557",
    "addr:postcode":"97477",
    "addr:street":"Pacific Ave",
    "iso:country":"US",
    "sg:address":"557 Pacific Ave",
    "sg:city":"Springfield",
    "sg:classifiers":[
        {
            "category":"Building & Trades",
            "subcategory":"Construction",
            "type":"Services"
        }
    ],
    "sg:phone":"+1 541 726 5106",
    "sg:postcode":"97477",
    "sg:province":"OR",
    "sg:tags":[
        "house"
    ],
    "wof:name":"Vintage Builders",
    "wof:placetype":"venue"
},
  "geometry": {"coordinates":[-123.03204100000001,44.060116],"type":"Point"}
}