{
  "type": "Feature",
  "properties": {
    "iso:country":"US",
    "sg:address":"4805 NE Glisan St",
    "sg:city":"Portland",
    "sg:classifiers":[
        {
            "category":"Health Services",
            "subcategory":"Hospital",
            "type":"Services"
        }
    ],
    "sg:postcode":"97213",
    "sg:province":"OR",
    "wof:name":"Providence Maternity Ward",
    "wof:placetype":"venue"
},
  "geometry": {"coordinates":[-122.61353699999999,45.527336],"type":"Point"}
}