{
  "type": "Feature",
  "properties": {
    "iso:country":"US",
    "sg:address":"528 NE Santiam Blvd",
    "sg:city":"Mill City",
    "sg:classifiers":[
        {
            "category":"Wholesale",
            "subcategory":"Motor Vehicles",
            "type":"Manufacturing & Wholesale Goods"
        }
    ],
    "sg:phone":"+1 503 897 3410",
    "sg:postcode":"97360",
    "sg:province":"OR",
    "sg:tags":[
        "automobile",
        "truck",
        "broker"
    ],
    "wof:name":"Falen's Trucking",
    "wof:placetype":"venue"
},
  "geometry": {"coordinates":[-122.470547,44.755524],"type":"Point"}
}