{
  "type": "Feature",
  "properties": {
    "iso:country":"US",
    "sg:address":"2630 W 6th St",
    "sg:city":"The Dalles",
    "sg:classifiers":[
        {
            "category":"Restaurant",
            "type":"Food & Drink"
        }
    ],
    "sg:menulink":"http://www.allmenus.com/or/the-dalles/175494-arbys/menu/",
    "sg:phone":"+1 503 296 1011",
    "sg:postcode":"97058",
    "sg:province":"OR",
    "sg:tags":[
        "burger",
        "american"
    ],
    "wof:name":"Arby's",
    "wof:placetype":"venue"
},
  "geometry": {"coordinates":[-121.210947,45.61808],"type":"Point"}
}