{
  "type": "Feature",
  "properties": {
    "iso:country":"US",
    "sg:address":"2265 NW Shevlin Park Rd",
    "sg:city":"Bend",
    "sg:classifiers":[
        {
            "category":"Place Of Worship",
            "subcategory":"Church",
            "type":"Public Place"
        },
        {
            "category":"Place Of Worship",
            "type":"Public Place"
        }
    ],
    "sg:phone":"+1 541 382 6862",
    "sg:postcode":"97701",
    "sg:province":"OR",
    "sg:tags":[
        "lutheran",
        "america",
        "churches-lutheran",
        "churches-lutheran-evangelical"
    ],
    "sg:website":"http://www.gflcbend.org",
    "wof:name":"Grace First Lutheran Church",
    "wof:placetype":"venue"
},
  "geometry": {"coordinates":[-121.33878300000001,44.062382],"type":"Point"}
}