{
  "type": "Feature",
  "properties": {
    "addr:full":"1960 Ranch Rd Reedsport OR 97467",
    "addr:housenumber":"1960",
    "addr:postcode":"97467",
    "addr:street":"Ranch Rd",
    "iso:country":"US",
    "sg:address":"1960 Ranch Rd",
    "sg:city":"Reedsport",
    "sg:classifiers":[
        {
            "category":"Freight",
            "type":"Transportation"
        }
    ],
    "sg:phone":"+1 541 271 3929",
    "sg:postcode":"97467",
    "sg:province":"OR",
    "sg:tags":[
        "operator",
        "trucking"
    ],
    "wof:name":"Parent Feed",
    "wof:placetype":"venue"
},
  "geometry": {"coordinates":[-124.126287,43.711289],"type":"Point"}
}