{
  "type": "Feature",
  "properties": {
    "iso:country":"US",
    "sg:address":"224 N Molalla Ave",
    "sg:city":"Molalla",
    "sg:classifiers":[
        {
            "category":"Professional",
            "subcategory":"Business Services",
            "type":"Services"
        }
    ],
    "sg:phone":"+1 503 829 3910",
    "sg:postcode":"97038",
    "sg:province":"OR",
    "sg:tags":[
        "packaging"
    ],
    "wof:name":"Boxes Unlimited",
    "wof:placetype":"venue"
},
  "geometry": {"coordinates":[-122.576849,45.148995],"type":"Point"}
}