{
  "type": "Feature",
  "properties": {
    "iso:country":"US",
    "sg:address":"26841 Doble Dr",
    "sg:city":"Eugene",
    "sg:classifiers":[
        {
            "category":"Professional",
            "subcategory":"Business Services",
            "type":"Services"
        }
    ],
    "sg:phone":"+1 541 935 3375",
    "sg:postcode":"97402",
    "sg:province":"OR",
    "wof:name":"Jtw Enterprises Inc",
    "wof:placetype":"venue"
},
  "geometry": {"coordinates":[-123.282374,44.021442],"type":"Point"}
}