{
  "type": "Feature",
  "properties": {
    "iso:country":"US",
    "sg:address":"3849 SW Canby St",
    "sg:city":"Portland",
    "sg:classifiers":[
        {
            "category":"Professional",
            "subcategory":"Management & Consulting",
            "type":"Services"
        }
    ],
    "sg:phone":"+1 503 977 5555",
    "sg:postcode":"97219",
    "sg:province":"OR",
    "sg:tags":[
        "business"
    ],
    "wof:name":"Lifestyling",
    "wof:placetype":"venue"
},
  "geometry": {"coordinates":[-122.715913,45.469041],"type":"Point"}
}