{
  "type": "Feature",
  "properties": {
    "addr:full":"1702 6th St La Grande OR 97850",
    "addr:housenumber":"1702",
    "addr:postcode":"97850",
    "addr:street":"6Th St;Grande",
    "iso:country":"US",
    "sg:address":"1702 6th St",
    "sg:city":"La Grande",
    "sg:classifiers":[
        {
            "category":"Social Services",
            "subcategory":"Child Care",
            "type":"Services"
        }
    ],
    "sg:phone":"+1 541 963 8795",
    "sg:postcode":"97850",
    "sg:province":"OR",
    "wof:name":"Heidi Ho Preschool",
    "wof:placetype":"venue"
},
  "geometry": {"coordinates":[-118.09444999999999,45.327372],"type":"Point"}
}