{
  "type": "Feature",
  "properties": {
    "iso:country":"US",
    "sg:address":"8200 Upper Applegate Rd",
    "sg:city":"Jacksonville",
    "sg:classifiers":[
        {
            "category":"Building & Trades",
            "subcategory":"Construction",
            "type":"Services"
        }
    ],
    "sg:phone":"+1 541 899 7856",
    "sg:postcode":"97530",
    "sg:province":"OR",
    "sg:tags":[
        "drywall",
        "contractor"
    ],
    "wof:name":"Roy Gray",
    "wof:placetype":"venue"
},
  "geometry": {"coordinates":[-123.065308,42.131583],"type":"Point"}
}