{
  "type": "Feature",
  "properties": {
    "iso:country":"US",
    "sg:address":"117 Commercial St NE",
    "sg:city":"Salem",
    "sg:classifiers":[
        {
            "category":"Shopping",
            "subcategory":"Gifts & Souvenirs",
            "type":"Retail Goods"
        }
    ],
    "sg:phone":"+1 503 391 1866",
    "sg:postcode":"97301",
    "sg:province":"OR",
    "sg:tags":[
        "shop"
    ],
    "sg:website":"www.oregongiftstore.com",
    "wof:name":"Oregon Gift Store",
    "wof:placetype":"venue"
},
  "geometry": {"coordinates":[-123.040075,44.94134],"type":"Point"}
}