{
  "type": "Feature",
  "properties": {
    "addr:full":"12645 SW 135th Ave Portland OR 97223",
    "addr:housenumber":"12645",
    "addr:postcode":"97223",
    "addr:street":"Sw 135Th Ave",
    "iso:country":"US",
    "sg:address":"12645 SW 135th Ave",
    "sg:city":"Portland",
    "sg:classifiers":[
        {
            "category":"Building & Trades",
            "subcategory":"Cleaning & Sanitation",
            "type":"Services"
        }
    ],
    "sg:phone":"+1 503 590 4166",
    "sg:postcode":"97223",
    "sg:province":"OR",
    "sg:tags":[
        "maintenance"
    ],
    "wof:name":"Gmbm Inc",
    "wof:placetype":"venue"
},
  "geometry": {"coordinates":[-122.815821,45.429633],"type":"Point"}
}