{
  "type": "Feature",
  "properties": {
    "iso:country":"US",
    "sg:address":"354 N Bridge St",
    "sg:city":"Sheridan",
    "sg:classifiers":[
        {
            "category":"Professional",
            "type":"Services"
        }
    ],
    "sg:phone":"+1 503 843 4271",
    "sg:postcode":"97378",
    "sg:province":"OR",
    "wof:name":"Doggiebagcom",
    "wof:placetype":"venue"
},
  "geometry": {"coordinates":[-123.395577,45.102634],"type":"Point"}
}