{
  "type": "Feature",
  "properties": {
    "addr:full":"3445 SW Carolina St Portland OR 97239",
    "addr:housenumber":"3445",
    "addr:postcode":"97239",
    "addr:street":"Sw Carolina St",
    "iso:country":"US",
    "sg:address":"3445 SW Carolina St",
    "sg:city":"Portland",
    "sg:classifiers":[
        {
            "category":"Professional",
            "subcategory":"Management & Consulting",
            "type":"Services"
        }
    ],
    "sg:phone":"+1 503 977 0556",
    "sg:postcode":"97239",
    "sg:province":"OR",
    "wof:name":"Susan K Clark",
    "wof:placetype":"venue"
},
  "geometry": {"coordinates":[-122.71255499999999,45.478763],"type":"Point"}
}