{
  "type": "Feature",
  "properties": {
    "iso:country":"US",
    "sg:address":"5135 River Rd S",
    "sg:city":"Salem",
    "sg:classifiers":[
        {
            "category":"Building & Trades",
            "subcategory":"Landscaping Services",
            "type":"Services"
        }
    ],
    "sg:phone":"+1 503 364 3391",
    "sg:postcode":"97302",
    "sg:province":"OR",
    "sg:tags":[
        "lawn",
        "garden"
    ],
    "wof:name":"Precision Landscape",
    "wof:placetype":"venue"
},
  "geometry": {"coordinates":[-123.137297,44.881602],"type":"Point"}
}