{
  "type": "Feature",
  "properties": {
    "iso:country":"US",
    "sg:address":"19767 SW 72nd Ave Ste 100",
    "sg:city":"Tualatin",
    "sg:classifiers":[
        {
            "category":"Real Estate",
            "subcategory":"Real Estate Services",
            "type":"Services"
        },
        {
            "category":"Industrial Area",
            "type":"Public Place"
        }
    ],
    "sg:phone":"+1 503 245 1976",
    "sg:postcode":"97062",
    "sg:province":"OR",
    "sg:tags":[
        "development",
        "management"
    ],
    "wof:name":"Lo 136",
    "wof:placetype":"venue"
},
  "geometry": {"coordinates":[-122.752348,45.377144],"type":"Point"}
}