{
  "type": "Feature",
  "properties": {
    "iso:country":"US",
    "sg:address":"5100 SW 19th Dr",
    "sg:city":"Portland",
    "sg:classifiers":[
        {
            "category":"Building & Trades",
            "subcategory":"Construction",
            "type":"Services"
        }
    ],
    "sg:phone":"+1 503 892 3692",
    "sg:postcode":"97239",
    "sg:province":"OR",
    "sg:tags":[
        "floor",
        "laying",
        "contractor"
    ],
    "wof:name":"Pacific NW Surfacing",
    "wof:placetype":"venue"
},
  "geometry": {"coordinates":[-122.697481,45.485568],"type":"Point"}
}