{
  "type": "Feature",
  "properties": {
    "iso:country":"US",
    "sg:address":"532 NE Lafayette Ave",
    "sg:city":"Bend",
    "sg:classifiers":[
        {
            "category":"Professional",
            "subcategory":"Engineering",
            "type":"Services"
        }
    ],
    "sg:phone":"+1 541 382 7550",
    "sg:postcode":"97701",
    "sg:province":"OR",
    "sg:tags":[
        "engineer"
    ],
    "wof:name":"Silver Sage Engineering",
    "wof:placetype":"venue"
},
  "geometry": {"coordinates":[-121.297731,44.062036],"type":"Point"}
}