{
  "type": "Feature",
  "properties": {
    "iso:country":"US",
    "sg:address":"9500 SW Wilsonville Rd",
    "sg:city":"Wilsonville",
    "sg:classifiers":[
        {
            "category":"Autos & Motor Vehicles",
            "subcategory":"Auto Supplies",
            "type":"Retail Goods"
        },
        {
            "category":"Wholesale",
            "subcategory":"Electrical",
            "type":"Manufacturing & Wholesale Goods"
        }
    ],
    "sg:phone":"+1 503 682 2253",
    "sg:postcode":"97070",
    "sg:province":"OR",
    "sg:tags":[
        "battery",
        "automobile",
        "part",
        "accessory"
    ],
    "wof:name":"Napa Auto Parts",
    "wof:placetype":"venue"
},
  "geometry": {"coordinates":[-122.774342,45.302887],"type":"Point"}
}