{
  "type": "Feature",
  "properties": {
    "addr:full":"2326 N Flint Ave Portland OR 97227",
    "addr:housenumber":"2326",
    "addr:postcode":"97227",
    "addr:street":"N Flint Ave",
    "iso:country":"US",
    "sg:address":"2326 N Flint Ave",
    "sg:city":"Portland",
    "sg:classifiers":[
        {
            "category":"Manufacturing",
            "subcategory":"Tools & Machinery",
            "type":"Manufacturing & Wholesale Goods"
        }
    ],
    "sg:phone":"+1 503 232 5526",
    "sg:postcode":"97227",
    "sg:province":"OR",
    "sg:tags":[
        "die",
        "casting"
    ],
    "sg:website":"http://www.eleekinc.com",
    "wof:name":"Eleek Inc",
    "wof:placetype":"venue"
},
  "geometry": {"coordinates":[-122.66870900000001,45.539723],"type":"Point"}
}