{
  "type": "Feature",
  "properties": {
    "iso:country":"US",
    "sg:address":"82571 Greenwood St",
    "sg:city":"Creswell",
    "sg:classifiers":[
        {
            "category":"Building & Trades",
            "subcategory":"Construction",
            "type":"Services"
        }
    ],
    "sg:phone":"+1 541 895 2841",
    "sg:postcode":"97426",
    "sg:province":"OR",
    "sg:tags":[
        "house"
    ],
    "wof:name":"Shamrock Construction",
    "wof:placetype":"venue"
},
  "geometry": {"coordinates":[-123.00569299999999,43.904434],"type":"Point"}
}