{
  "type": "Feature",
  "properties": {
    "addr:full":"4819 SW Vermont St Portland OR 97219",
    "addr:housenumber":"4819",
    "addr:postcode":"97219",
    "addr:street":"Sw Vermont St",
    "iso:country":"US",
    "sg:address":"4819 SW Vermont St",
    "sg:city":"Portland",
    "sg:classifiers":[
        {
            "category":"Professional",
            "type":"Services"
        }
    ],
    "sg:phone":"+1 503 452 4047",
    "sg:postcode":"97219",
    "sg:province":"OR",
    "wof:name":"Blosser Center For Impro Disle",
    "wof:placetype":"venue"
},
  "geometry": {"coordinates":[-122.72720700000001,45.47635],"type":"Point"}
}