{
  "type": "Feature",
  "properties": {
    "iso:country":"US",
    "sg:address":"200 W Highland Ave",
    "sg:city":"Hermiston",
    "sg:classifiers":[
        {
            "category":"Recreation",
            "type":"Entertainment"
        }
    ],
    "sg:phone":"+1 541 567 8532",
    "sg:postcode":"97838",
    "sg:province":"OR",
    "sg:tags":[
        "historical"
    ],
    "wof:name":"Maxwell Siding Railroad",
    "wof:placetype":"venue"
},
  "geometry": {"coordinates":[-119.293633,45.834993],"type":"Point"}
}