{
  "type": "Feature",
  "properties": {
    "iso:country":"US",
    "sg:address":"19245 Indian Summer Rd",
    "sg:city":"Bend",
    "sg:classifiers":[
        {
            "category":"Building & Trades",
            "subcategory":"Construction",
            "type":"Services"
        }
    ],
    "sg:phone":"+1 541 948 3445",
    "sg:postcode":"97702",
    "sg:province":"OR",
    "sg:tags":[
        "house"
    ],
    "wof:name":"Jk D Construction",
    "wof:placetype":"venue"
},
  "geometry": {"coordinates":[-121.363261,43.991495],"type":"Point"}
}