{
  "type": "Feature",
  "properties": {
    "iso:country":"US",
    "sg:address":"340 Grandview Ave",
    "sg:city":"Scotts Mills",
    "sg:classifiers":[
        {
            "category":"Food & Beverages",
            "subcategory":"Groceries & Convenience Stores",
            "type":"Retail Goods"
        }
    ],
    "sg:phone":"+1 503 873 5926",
    "sg:postcode":"97375",
    "sg:province":"OR",
    "sg:tags":[
        "grocer"
    ],
    "wof:name":"Scotts Mills Market",
    "wof:placetype":"venue"
},
  "geometry": {"coordinates":[-122.66809499999999,45.043061],"type":"Point"}
}