{
  "type": "Feature",
  "properties": {
    "addr:full":"463 Washington St Eugene OR 97401",
    "addr:housenumber":"463",
    "addr:postcode":"97401",
    "addr:street":"Washington St",
    "iso:country":"US",
    "sg:address":"463 Washington St",
    "sg:city":"Eugene",
    "sg:classifiers":[
        {
            "category":"Manufacturing",
            "subcategory":"Signs",
            "type":"Manufacturing & Wholesale Goods"
        }
    ],
    "sg:phone":"+1 541 686 9366",
    "sg:postcode":"97401",
    "sg:province":"OR",
    "wof:name":"Sign Pro",
    "wof:placetype":"venue"
},
  "geometry": {"coordinates":[-123.10026999999999,44.054689],"type":"Point"}
}