{
  "type": "Feature",
  "properties": {
    "iso:country":"US",
    "sg:address":"16246 SE 82nd Dr",
    "sg:city":"Clackamas",
    "sg:classifiers":[
        {
            "category":"Education",
            "subcategory":"Dance Studio",
            "type":"Public Place"
        }
    ],
    "sg:phone":"+1 503 722 5320",
    "sg:postcode":"97015",
    "sg:province":"OR",
    "sg:tags":[
        "art",
        "performing",
        "instruction",
        "dancing"
    ],
    "sg:website":"www.dancevisionusa.com",
    "wof:name":"Dance Vision",
    "wof:placetype":"venue"
},
  "geometry": {"coordinates":[-122.568645,45.405022],"type":"Point"}
}