{
  "type": "Feature",
  "properties": {
    "iso:country":"US",
    "sg:address":"4115 NE Fair Acres St",
    "sg:city":"Corvallis",
    "sg:classifiers":[
        {
            "category":"Building & Trades",
            "subcategory":"Construction",
            "type":"Services"
        }
    ],
    "sg:phone":"+1 541 754 7118",
    "sg:postcode":"97330",
    "sg:province":"OR",
    "sg:tags":[
        "downspouts",
        "gutter"
    ],
    "wof:name":"Gutter Guys",
    "wof:placetype":"venue"
},
  "geometry": {"coordinates":[-123.219617,44.600384],"type":"Point"}
}