{
  "type": "Feature",
  "properties": {
    "iso:country":"US",
    "sg:address":"1640 9th Ave SE",
    "sg:city":"Albany",
    "sg:classifiers":[
        {
            "category":"Home & Garden",
            "subcategory":"Household Appliances",
            "type":"Retail Goods"
        }
    ],
    "sg:phone":"+1 541 967 9613",
    "sg:postcode":"97322",
    "sg:province":"OR",
    "sg:tags":[
        "repair",
        "cleaner",
        "sewing",
        "machine",
        "machines-service",
        "vacuum"
    ],
    "wof:name":"Vac World",
    "wof:placetype":"venue"
},
  "geometry": {"coordinates":[-123.084234,44.63333],"type":"Point"}
}