{
  "type": "Feature",
  "properties": {
    "addr:full":"1126 S I St Lakeview OR 97630",
    "addr:housenumber":"1126",
    "addr:postcode":"97630",
    "addr:street":"S I St",
    "iso:country":"US",
    "sg:address":"1126 S I St",
    "sg:city":"Lakeview",
    "sg:classifiers":[
        {
            "category":"Personal",
            "subcategory":"Beauty Salon",
            "type":"Services"
        }
    ],
    "sg:phone":"+1 541 947 5008",
    "sg:postcode":"97630",
    "sg:province":"OR",
    "sg:tags":[
        "shop"
    ],
    "wof:name":"Sharis Cleaning",
    "wof:placetype":"venue"
},
  "geometry": {"coordinates":[-120.350166,42.173263],"type":"Point"}
}