{
  "type": "Feature",
  "properties": {
    "iso:country":"US",
    "sg:address":"399 S Water St",
    "sg:city":"Silverton",
    "sg:classifiers":[
        {
            "category":"Manufacturing",
            "subcategory":"Printing",
            "type":"Manufacturing & Wholesale Goods"
        }
    ],
    "sg:phone":"+1 503 845 6121",
    "sg:postcode":"97381",
    "sg:province":"OR",
    "sg:tags":[
        "newspaper"
    ],
    "wof:name":"Mt Angel News",
    "wof:placetype":"venue"
},
  "geometry": {"coordinates":[-122.781561,45.003323],"type":"Point"}
}