{
  "type": "Feature",
  "properties": {
    "iso:country":"US",
    "sg:address":"5102 SW 45th Ave",
    "sg:city":"Portland",
    "sg:classifiers":[
        {
            "category":"Professional",
            "subcategory":"Business Services",
            "type":"Services"
        }
    ],
    "sg:phone":"+1 503 892 8793",
    "sg:postcode":"97221",
    "sg:province":"OR",
    "wof:name":"Ruby Gallagher",
    "wof:placetype":"venue"
},
  "geometry": {"coordinates":[-122.723148,45.486271],"type":"Point"}
}