{
  "type": "Feature",
  "properties": {
    "addr:full":"5102 SW 45th Ave Portland OR 97221",
    "addr:housenumber":"5102",
    "addr:postcode":"97221",
    "addr:street":"Sw 45Th Ave",
    "iso:country":"US",
    "sg:address":"5102 SW 45th Ave",
    "sg:city":"Portland",
    "sg:classifiers":[
        {
            "category":"Professional",
            "subcategory":"Business Services",
            "type":"Services"
        }
    ],
    "sg:phone":"+1 503 892 8793",
    "sg:postcode":"97221",
    "sg:province":"OR",
    "wof:name":"Ruby Gallagher",
    "wof:placetype":"venue"
},
  "geometry": {"coordinates":[-122.72314799999999,45.486271],"type":"Point"}
}