{
  "type": "Feature",
  "properties": {
    "iso:country":"US",
    "sg:address":"107 SE Washington St # 440",
    "sg:city":"Portland",
    "sg:classifiers":[
        {
            "category":"Travel",
            "subcategory":"Hotels & Motels",
            "type":"Entertainment"
        }
    ],
    "sg:phone":"+1 503 477 5340",
    "sg:postcode":"97214",
    "sg:province":"OR",
    "wof:name":"Cloud Four",
    "wof:placetype":"venue"
},
  "geometry": {"coordinates":[-122.66476900000001,45.518669],"type":"Point"}
}