{
  "type": "Feature",
  "properties": {
    "addr:full":"565 N Vernonia Rd St Helens OR 97051",
    "addr:housenumber":"565",
    "addr:postcode":"97051",
    "addr:street":"N Vernonia Rd",
    "iso:country":"US",
    "sg:address":"565 N Vernonia Rd",
    "sg:city":"St Helens",
    "sg:classifiers":[
        {
            "category":"Building & Trades",
            "subcategory":"Construction",
            "type":"Services"
        }
    ],
    "sg:phone":"+1 503 397 1314",
    "sg:postcode":"97051",
    "sg:province":"OR",
    "sg:tags":[
        "general",
        "contractor"
    ],
    "wof:name":"Warner Werings & Stauffer Inc",
    "wof:placetype":"venue"
},
  "geometry": {"coordinates":[-122.83836599999999,45.863311],"type":"Point"}
}