{
  "type": "Feature",
  "properties": {
    "addr:full":"2222 State Hwy 99 N Eugene OR 97402",
    "addr:housenumber":"2222",
    "addr:postcode":"97402",
    "addr:street":"State Hwy 99 N",
    "iso:country":"US",
    "sg:address":"2222 State Hwy 99 N",
    "sg:city":"Eugene",
    "sg:classifiers":[
        {
            "category":"Bars & Pubs",
            "type":"Food & Drink"
        }
    ],
    "sg:phone":"+1 541 461 0413",
    "sg:postcode":"97402",
    "sg:province":"OR",
    "wof:name":"Brew & Cue Inc",
    "wof:placetype":"venue"
},
  "geometry": {"coordinates":[-123.15983799999999,44.089942],"type":"Point"}
}