{
  "type": "Feature",
  "properties": {
    "addr:full":"6500 SE Johnson Creek Blvd Portland OR 97206",
    "addr:housenumber":"6500",
    "addr:postcode":"97206",
    "addr:street":"Se Johnson Creek Blvd",
    "iso:country":"US",
    "sg:address":"6500 SE Johnson Creek Blvd",
    "sg:city":"Portland",
    "sg:classifiers":[
        {
            "category":"Building & Trades",
            "subcategory":"Plumbing",
            "type":"Services"
        },
        {
            "category":"Home & Garden",
            "subcategory":"Building Materials",
            "type":"Retail Goods"
        },
        {
            "category":"Building & Trades",
            "subcategory":"Construction",
            "type":"Services"
        },
        {
            "category":"Manufacturing",
            "subcategory":"Building Materials",
            "type":"Manufacturing & Wholesale Goods"
        }
    ],
    "sg:phone":"+1 503 771 4848",
    "sg:postcode":"97206",
    "sg:province":"OR",
    "sg:tags":[
        "product",
        "tank",
        "products-wholesale",
        "septic",
        "system",
        "contractor",
        "concrete",
        "sand",
        "staining",
        "gravel",
        "manufacturer"
    ],
    "wof:name":"Johnson Concrete Products Inc",
    "wof:placetype":"venue"
},
  "geometry": {"coordinates":[-122.595692,45.455978],"type":"Point"}
}