{
  "type": "Feature",
  "properties": {
    "addr:full":"167 Cleveland St Eugene OR 97402",
    "addr:housenumber":"167",
    "addr:postcode":"97402",
    "addr:street":"Cleveland St",
    "iso:country":"US",
    "sg:address":"167 Cleveland St",
    "sg:city":"Eugene",
    "sg:classifiers":[
        {
            "category":"Building & Trades",
            "subcategory":"Construction",
            "type":"Services"
        }
    ],
    "sg:phone":"+1 541 687 2033",
    "sg:postcode":"97402",
    "sg:province":"OR",
    "sg:tags":[
        "plastering",
        "contractor"
    ],
    "wof:name":"Spence Plastering Inc",
    "wof:placetype":"venue"
},
  "geometry": {"coordinates":[-123.127199,44.05783],"type":"Point"}
}