{
  "type": "Feature",
  "properties": {
    "addr:full":"2455 SE 89th Ave Portland OR 97216",
    "addr:housenumber":"2455",
    "addr:postcode":"97216",
    "addr:street":"Se 89Th Ave",
    "iso:country":"US",
    "sg:address":"2455 SE 89th Ave",
    "sg:city":"Portland",
    "sg:classifiers":[
        {
            "category":"Professional",
            "type":"Services"
        }
    ],
    "sg:phone":"+1 503 788 3498",
    "sg:postcode":"97216",
    "sg:province":"OR",
    "wof:name":"J F Metalwerx",
    "wof:placetype":"venue"
},
  "geometry": {"coordinates":[-122.57232999999999,45.507271],"type":"Point"}
}