{
  "type": "Feature",
  "properties": {
    "iso:country":"US",
    "sg:address":"3664 SW 3rd St",
    "sg:city":"Corvallis",
    "sg:classifiers":[
        {
            "category":"Building & Trades",
            "subcategory":"Plumbing",
            "type":"Services"
        }
    ],
    "sg:phone":"+1 541 757 0058",
    "sg:postcode":"97333",
    "sg:province":"OR",
    "sg:tags":[
        "metal",
        "work",
        "sheet",
        "heating",
        "contractor"
    ],
    "wof:name":"Central Valley Heating & Sheet Metal Inc",
    "wof:placetype":"venue"
},
  "geometry": {"coordinates":[-123.267861,44.527275],"type":"Point"}
}