{
  "type": "Feature",
  "properties": {
    "iso:country":"US",
    "sg:address":"26127 Marina Rd",
    "sg:city":"Veneta",
    "sg:classifiers":[
        {
            "category":"Building & Trades",
            "subcategory":"Construction",
            "type":"Services"
        }
    ],
    "sg:phone":"+1 541 935 7403",
    "sg:postcode":"97487",
    "sg:province":"OR",
    "sg:tags":[
        "access",
        "road"
    ],
    "wof:name":"Tom Borland Inc",
    "wof:placetype":"venue"
},
  "geometry": {"coordinates":[-123.31300899999999,44.060223],"type":"Point"}
}