{
  "type": "Feature",
  "properties": {
    "iso:country":"US",
    "sg:address":"926 Anderson Ln",
    "sg:city":"Springfield",
    "sg:classifiers":[
        {
            "category":"Recreation",
            "type":"Entertainment"
        }
    ],
    "sg:phone":"+1 541 988 9017",
    "sg:postcode":"97477",
    "sg:province":"OR",
    "wof:name":"Get Outside",
    "wof:placetype":"venue"
},
  "geometry": {"coordinates":[-123.047955,44.055373],"type":"Point"}
}