{
  "type": "Feature",
  "properties": {
    "iso:country":"US",
    "sg:address":"1001 SW 5th Avenue",
    "sg:city":"Portland",
    "sg:classifiers":[
        {
            "category":"Professional",
            "subcategory":"Lawyer & Legal Services",
            "type":"Services"
        }
    ],
    "sg:phone":"+1 503 228 6277",
    "sg:postcode":"97204",
    "sg:province":"OR",
    "sg:tags":[
        "personal",
        "injury"
    ],
    "wof:name":"Crowder Joanne L Atty",
    "wof:placetype":"venue"
},
  "geometry": {"coordinates":[-122.678684,45.516817],"type":"Point"}
}