{
  "type": "Feature",
  "properties": {
    "iso:country":"US",
    "sg:address":"1132 Commercial St",
    "sg:city":"Astoria",
    "sg:classifiers":[
        {
            "category":"Food & Beverages",
            "subcategory":"Bakery",
            "type":"Retail Goods"
        },
        {
            "category":"Bakery",
            "type":"Food & Drink"
        }
    ],
    "sg:phone":"+1 503 325 3657",
    "sg:postcode":"97103",
    "sg:province":"OR",
    "sg:tags":[
        "bakers-wholesale"
    ],
    "wof:name":"Lindstrom's Danish Maid Bakery",
    "wof:placetype":"venue"
},
  "geometry": {"coordinates":[-123.83124100000001,46.189039],"type":"Point"}
}