{
  "type": "Feature",
  "properties": {
    "iso:country":"US",
    "sg:address":"10625 SE 362nd Ave C37",
    "sg:city":"Boring",
    "sg:classifiers":[
        {
            "category":"Building & Trades",
            "subcategory":"Construction",
            "type":"Services"
        }
    ],
    "sg:phone":"+1 503 663 5979",
    "sg:postcode":"97009",
    "sg:province":"OR",
    "sg:tags":[
        "manufactured",
        "housing-communities"
    ],
    "sg:website":"http://www.cwres.com",
    "wof:name":"Pioneer Mobile Home Park",
    "wof:placetype":"venue"
},
  "geometry": {"coordinates":[-122.290581,45.445873],"type":"Point"}
}