{
  "type": "Feature",
  "properties": {
    "addr:full":"2303 Lloyd Center Portland OR 97232",
    "addr:housenumber":"2303",
    "addr:postcode":"97232",
    "addr:street":"Lloyd",
    "iso:country":"US",
    "sg:address":"2303 Lloyd Center",
    "sg:city":"Portland",
    "sg:classifiers":[
        {
            "category":"Restaurant",
            "type":"Food & Drink"
        }
    ],
    "sg:phone":"+1 503 284 1110",
    "sg:postcode":"97232",
    "sg:province":"OR",
    "wof:name":"Wazwan",
    "wof:placetype":"venue"
},
  "geometry": {"coordinates":[-122.65463699999999,45.531642],"type":"Point"}
}