{
  "type": "Feature",
  "properties": {
    "addr:full":"1481 Gateway Blvd Cottage Grove OR 97424",
    "addr:housenumber":"1481",
    "addr:postcode":"97424",
    "addr:street":"Gateway Blvd",
    "iso:country":"US",
    "sg:address":"1481 Gateway Blvd",
    "sg:city":"Cottage Grove",
    "sg:classifiers":[
        {
            "category":"Travel",
            "subcategory":"Travel Agent",
            "type":"Entertainment"
        }
    ],
    "sg:phone":"+1 541 942 2289",
    "sg:postcode":"97424",
    "sg:province":"OR",
    "sg:tags":[
        "agency",
        "bureau"
    ],
    "wof:name":"Affordable Travel",
    "wof:placetype":"venue"
},
  "geometry": {"coordinates":[-123.054089,43.786754],"type":"Point"}
}