{
  "type": "Feature",
  "properties": {
    "iso:country":"US",
    "sg:address":"600 W Burnside St",
    "sg:city":"Portland",
    "sg:classifiers":[
        {
            "category":"Building & Trades",
            "subcategory":"Locksmith",
            "type":"Services"
        }
    ],
    "sg:phone":"+1 503 974 1279",
    "sg:postcode":"97209",
    "sg:province":"OR",
    "sg:tags":[
        "key"
    ],
    "wof:name":"24-7 Emergency Locksmith Portland",
    "wof:placetype":"venue"
},
  "geometry": {"coordinates":[-122.676474,45.522978],"type":"Point"}
}