{
  "type": "Feature",
  "properties": {
    "iso:country":"US",
    "sg:address":"17020 Pilkington Rd",
    "sg:city":"Lake Oswego",
    "sg:classifiers":[
        {
            "category":"Banks & Credit Unions",
            "subcategory":"Investment Brokerage",
            "type":"Services"
        }
    ],
    "sg:phone":"+1 503 697 7800",
    "sg:postcode":"97035",
    "sg:province":"OR",
    "sg:tags":[
        "advisory",
        "financial"
    ],
    "wof:name":"Durig Capital",
    "wof:placetype":"venue"
},
  "geometry": {"coordinates":[-122.73335299999999,45.400753],"type":"Point"}
}