{
  "type": "Feature",
  "properties": {
    "addr:full":"730 Main St Phoenix OR 97535",
    "addr:housenumber":"730",
    "addr:postcode":"97535",
    "addr:street":"Main St",
    "iso:country":"US",
    "sg:address":"730 Main St",
    "sg:city":"Phoenix",
    "sg:classifiers":[
        {
            "category":"Professional",
            "subcategory":"Business Services",
            "type":"Services"
        }
    ],
    "sg:phone":"+1 541 512 2869",
    "sg:postcode":"97535",
    "sg:province":"OR",
    "sg:tags":[
        "liquidator"
    ],
    "wof:name":"Land & Sea Cargo Liquidators",
    "wof:placetype":"venue"
},
  "geometry": {"coordinates":[-122.821367,42.279398],"type":"Point"}
}