{
  "type": "Feature",
  "properties": {
    "iso:country":"US",
    "sg:address":"10120 SW Hall Blvd",
    "sg:city":"Portland",
    "sg:classifiers":[
        {
            "category":"Health Services",
            "subcategory":"Doctor",
            "type":"Services"
        }
    ],
    "sg:phone":"+1 503 245 8220",
    "sg:postcode":"97223",
    "sg:province":"OR",
    "wof:name":"Thompson Curtis T MD & Associates",
    "wof:placetype":"venue"
},
  "geometry": {"coordinates":[-122.765415,45.447138],"type":"Point"}
}