{
  "type": "Feature",
  "properties": {
    "iso:country":"US",
    "sg:address":"4945 NE 7th Ave",
    "sg:city":"Portland",
    "sg:classifiers":[
        {
            "category":"Health Services",
            "subcategory":"Hospital",
            "type":"Services"
        }
    ],
    "sg:phone":"+1 503 258 4555",
    "sg:postcode":"97211",
    "sg:province":"OR",
    "sg:tags":[
        "mental"
    ],
    "wof:name":"Morrison Child & Family Svc",
    "wof:placetype":"venue"
},
  "geometry": {"coordinates":[-122.658607,45.557798],"type":"Point"}
}