{
  "type": "Feature",
  "properties": {
    "addr:full":"1228 SE Harlow Ave Troutdale OR 97060",
    "addr:housenumber":"1228",
    "addr:postcode":"97060",
    "addr:street":"Se Harlow Ave",
    "iso:country":"US",
    "sg:address":"1228 SE Harlow Ave",
    "sg:city":"Troutdale",
    "sg:classifiers":[
        {
            "category":"Shopping",
            "subcategory":"Gifts & Souvenirs",
            "type":"Retail Goods"
        }
    ],
    "sg:phone":"+1 503 667 1577",
    "sg:postcode":"97060",
    "sg:province":"OR",
    "sg:tags":[
        "cards",
        "greeting"
    ],
    "wof:name":"Holiday Card Shoppe Inc",
    "wof:placetype":"venue"
},
  "geometry": {"coordinates":[-122.38628799999999,45.532937],"type":"Point"}
}