{
  "type": "Feature",
  "properties": {
    "addr:full":"2106 NE 4th St Bend OR 97701",
    "addr:housenumber":"2106",
    "addr:postcode":"97701",
    "addr:street":"Ne 4Th St",
    "iso:country":"US",
    "sg:address":"2106 NE 4th St",
    "sg:city":"Bend",
    "sg:classifiers":[
        {
            "category":"Banks & Credit Unions",
            "subcategory":"Bank",
            "type":"Services"
        }
    ],
    "sg:phone":"+1 541 330 1339",
    "sg:postcode":"97701",
    "sg:province":"OR",
    "sg:tags":[
        "loan",
        "real estate"
    ],
    "wof:name":"Bend River Mortgage Inc",
    "wof:placetype":"venue"
},
  "geometry": {"coordinates":[-121.30065999999999,44.071453],"type":"Point"}
}