{
  "type": "Feature",
  "properties": {
    "iso:country":"US",
    "sg:address":"1001 Molalla Ave",
    "sg:city":"Oregon City",
    "sg:classifiers":[
        {
            "category":"Real Estate",
            "subcategory":"Real Estate Agent",
            "type":"Services"
        }
    ],
    "sg:phone":"+1 503 655 1661",
    "sg:postcode":"97045",
    "sg:province":"OR",
    "wof:name":"Automobile Appraisal Group",
    "wof:placetype":"venue"
},
  "geometry": {"coordinates":[-122.593597,45.340467],"type":"Point"}
}