{
  "type": "Feature",
  "properties": {
    "iso:country":"US",
    "sg:address":"255 Capitol St NE",
    "sg:city":"Salem",
    "sg:classifiers":[
        {
            "category":"Government",
            "subcategory":"Office",
            "type":"Public Place"
        }
    ],
    "sg:phone":"+1 503 378 8648",
    "sg:postcode":"97301",
    "sg:province":"OR",
    "sg:tags":[
        "to",
        "educational",
        "college",
        "community"
    ],
    "wof:name":"Office Community College Svcs",
    "wof:placetype":"venue"
},
  "geometry": {"coordinates":[-123.028036,44.939677],"type":"Point"}
}