{
  "type": "Feature",
  "properties": {
    "addr:full":"32494 Danville Rd Creswell OR 97426",
    "addr:housenumber":"32494",
    "addr:postcode":"97426",
    "addr:street":"Danville Rd",
    "iso:country":"US",
    "sg:address":"32494 Danville Rd",
    "sg:city":"Creswell",
    "sg:classifiers":[
        {
            "category":"Building & Trades",
            "subcategory":"Landscaping Services",
            "type":"Services"
        }
    ],
    "sg:phone":"+1 541 895 4281",
    "sg:postcode":"97426",
    "sg:province":"OR",
    "wof:name":"Landscape Construction",
    "wof:placetype":"venue"
},
  "geometry": {"coordinates":[-123.060287,43.924317],"type":"Point"}
}