{
  "type": "Feature",
  "properties": {
    "addr:full":"27060 Louden Ln Junction City OR 97448",
    "addr:postcode":"27060;97448",
    "addr:street":"Louden Ln",
    "iso:country":"US",
    "sg:address":"27060 Louden Ln",
    "sg:city":"Junction City",
    "sg:classifiers":[
        {
            "category":"Building & Trades",
            "subcategory":"Construction",
            "type":"Services"
        }
    ],
    "sg:phone":"+1 541 689 1429",
    "sg:postcode":"97448",
    "sg:province":"OR",
    "sg:tags":[
        "contractor"
    ],
    "wof:name":"Ace Continuous Gutters",
    "wof:placetype":"venue"
},
  "geometry": {"coordinates":[-123.27613100000001,44.121982],"type":"Point"}
}