{
  "type": "Feature",
  "properties": {
    "iso:country":"US",
    "sg:address":"10650 SW 121st Avenue Apt 7",
    "sg:city":"Portland",
    "sg:classifiers":[
        {
            "category":"Real Estate",
            "subcategory":"Real Estate Operator",
            "type":"Services"
        }
    ],
    "sg:phone":"+1 503 590 1542",
    "sg:postcode":"97223",
    "sg:province":"OR",
    "sg:tags":[
        "apartment"
    ],
    "wof:name":"Westwood Green Apts",
    "wof:placetype":"venue"
},
  "geometry": {"coordinates":[-122.800264,45.44364],"type":"Point"}
}