{
  "type": "Feature",
  "properties": {
    "iso:country":"US",
    "sg:address":"5065 SW Scholls Ferry Rd",
    "sg:city":"Portland",
    "sg:classifiers":[
        {
            "category":"Autos & Motor Vehicles",
            "subcategory":"Fuel & Gas Station",
            "type":"Retail Goods"
        },
        {
            "category":"Food & Beverages",
            "subcategory":"Groceries & Convenience Stores",
            "type":"Retail Goods"
        }
    ],
    "sg:phone":"+1 503 297 3720",
    "sg:postcode":"97225",
    "sg:province":"OR",
    "wof:name":"Scholls Ferry Unocal Fast Svc",
    "wof:placetype":"venue"
},
  "geometry": {"coordinates":[-122.75496699999999,45.483379],"type":"Point"}
}