{
  "type": "Feature",
  "properties": {
    "iso:country":"US",
    "sg:address":"820 NW 12th Ave #210",
    "sg:city":"Portland",
    "sg:classifiers":[
        {
            "category":"Personal",
            "subcategory":"Nail Salon",
            "type":"Services"
        }
    ],
    "sg:phone":"+1 503 309 2971",
    "sg:postcode":"97209",
    "sg:province":"OR",
    "wof:name":"Rhonda Martini Nail Artistry",
    "wof:placetype":"venue"
},
  "geometry": {"coordinates":[-122.683363,45.528796],"type":"Point"}
}