{
  "type": "Feature",
  "properties": {
    "iso:country":"US",
    "sg:address":"1263 Bay St",
    "sg:city":"Florence",
    "sg:classifiers":[
        {
            "category":"Restaurant",
            "type":"Food & Drink"
        }
    ],
    "sg:phone":"+1 541 997 2800",
    "sg:postcode":"97439",
    "sg:province":"OR",
    "sg:tags":[
        "eating"
    ],
    "wof:name":"Firehouse Restaurant",
    "wof:placetype":"venue"
},
  "geometry": {"coordinates":[-124.10758199999999,43.96643],"type":"Point"}
}