{
  "type": "Feature",
  "properties": {
    "iso:country":"US",
    "sg:address":"1000 Main Ave",
    "sg:city":"Tillamook",
    "sg:classifiers":[
        {
            "category":"Autos & Motor Vehicles",
            "subcategory":"Motorcycle Sales",
            "type":"Retail Goods"
        }
    ],
    "sg:phone":"+1 503 842 5593",
    "sg:postcode":"97141",
    "sg:province":"OR",
    "sg:tags":[
        "all",
        "watercraft"
    ],
    "wof:name":"Honda Polaris of Tillamook",
    "wof:placetype":"venue"
},
  "geometry": {"coordinates":[-123.84396099999999,45.451152],"type":"Point"}
}