{
  "type": "Feature",
  "properties": {
    "addr:full":"6650 SW Redwood Ln Portland OR 97224",
    "addr:housenumber":"6650",
    "addr:postcode":"97224",
    "addr:street":"Sw Redwood Ln",
    "iso:country":"US",
    "sg:address":"6650 SW Redwood Ln",
    "sg:city":"Portland",
    "sg:classifiers":[
        {
            "category":"Professional",
            "subcategory":"Management & Consulting",
            "type":"Services"
        }
    ],
    "sg:phone":"+1 503 293 8425",
    "sg:postcode":"97224",
    "sg:province":"OR",
    "wof:name":"Cigna",
    "wof:placetype":"venue"
},
  "geometry": {"coordinates":[-122.746239,45.409665],"type":"Point"}
}