{
  "type": "Feature",
  "properties": {
    "iso:country":"US",
    "sg:address":"1200 NW Marshall St Ste 502",
    "sg:city":"Portland",
    "sg:classifiers":[
        {
            "category":"Professional",
            "subcategory":"Business Services",
            "type":"Services"
        }
    ],
    "sg:phone":"+1 503 701 4531",
    "sg:postcode":"97209",
    "sg:province":"OR",
    "sg:tags":[
        "food",
        "delivery"
    ],
    "sg:website":"www.dinneratyourdoor.com",
    "wof:name":"Dinner At Your Door",
    "wof:placetype":"venue"
},
  "geometry": {"coordinates":[-122.683621,45.530669],"type":"Point"}
}