{
  "type": "Feature",
  "properties": {
    "iso:country":"US",
    "sg:address":"2250 NE Highway 20",
    "sg:city":"Bend",
    "sg:classifiers":[
        {
            "category":"Autos & Motor Vehicles",
            "subcategory":"Automobile Sales",
            "type":"Retail Goods"
        }
    ],
    "sg:phone":"+1 541 749 4025",
    "sg:postcode":"97701",
    "sg:province":"OR",
    "sg:tags":[
        "car",
        "used"
    ],
    "wof:name":"Smolich Used Car Ctr",
    "wof:placetype":"venue"
},
  "geometry": {"coordinates":[-121.26931,44.054934],"type":"Point"}
}