{
  "type": "Feature",
  "properties": {
    "iso:country":"US",
    "sg:address":"32408 Gift Pl",
    "sg:city":"Scappoose",
    "sg:classifiers":[
        {
            "category":"Farming",
            "subcategory":"Livestock Farm",
            "type":"Manufacturing & Wholesale Goods"
        }
    ],
    "sg:phone":"+1 503 543 3541",
    "sg:postcode":"97056",
    "sg:province":"OR",
    "wof:name":"Mcguire Livestock Service",
    "wof:placetype":"venue"
},
  "geometry": {"coordinates":[-122.898,45.78664],"type":"Point"}
}