{
  "type": "Feature",
  "properties": {
    "addr:full":"15300 SW Royalty Parkway Portland OR 97224",
    "addr:housenumber":"15300",
    "addr:postcode":"97224",
    "addr:street":"Sw Royalty Parkway",
    "iso:country":"US",
    "sg:address":"15300 SW Royalty Parkway",
    "sg:city":"Portland",
    "sg:classifiers":[
        {
            "category":"Autos & Motor Vehicles",
            "subcategory":"Fuel & Gas Station",
            "type":"Retail Goods"
        }
    ],
    "sg:phone":"+1 503 639 1846",
    "sg:postcode":"97224",
    "sg:province":"OR",
    "wof:name":"King City Arco Service Center",
    "wof:placetype":"venue"
},
  "geometry": {"coordinates":[-122.79535300000001,45.408345],"type":"Point"}
}