{
  "type": "Feature",
  "properties": {
    "addr:full":"2830 10th St Baker City OR 97814",
    "addr:housenumber":"2830",
    "addr:postcode":"97814",
    "addr:street":"10Th St",
    "iso:country":"US",
    "sg:address":"2830 10th St",
    "sg:city":"Baker City",
    "sg:classifiers":[
        {
            "category":"Retail",
            "subcategory":"Laundry & Dry Cleaning",
            "type":"Services"
        }
    ],
    "sg:phone":"+1 541 523 6677",
    "sg:postcode":"97814",
    "sg:province":"OR",
    "sg:tags":[
        "diaper"
    ],
    "wof:name":"Baby Fresh Svc",
    "wof:placetype":"venue"
},
  "geometry": {"coordinates":[-117.84107400000001,44.785051],"type":"Point"}
}