{
  "type": "Feature",
  "properties": {
    "iso:country":"US",
    "sg:address":"2830 10th St",
    "sg:city":"Baker City",
    "sg:classifiers":[
        {
            "category":"Retail",
            "subcategory":"Laundry & Dry Cleaning",
            "type":"Services"
        }
    ],
    "sg:phone":"+1 541 523 6677",
    "sg:postcode":"97814",
    "sg:province":"OR",
    "sg:tags":[
        "diaper"
    ],
    "wof:name":"Baby Fresh Svc",
    "wof:placetype":"venue"
},
  "geometry": {"coordinates":[-117.841074,44.785051],"type":"Point"}
}