{
  "type": "Feature",
  "properties": {
    "addr:full":"203 NW 2nd Avenue Portland OR 97209",
    "addr:housenumber":"203",
    "addr:postcode":"97209",
    "addr:street":"Nw 2Nd Avenue",
    "iso:country":"US",
    "sg:address":"203 NW 2nd Avenue",
    "sg:city":"Portland",
    "sg:classifiers":[
        {
            "category":"Personal",
            "subcategory":"Beauty Salon",
            "type":"Services"
        },
        {
            "category":"Personal",
            "subcategory":"Hair Removal",
            "type":"Services"
        },
        {
            "category":"Personal",
            "subcategory":"Nail Salon",
            "type":"Services"
        }
    ],
    "sg:phone":"+1 503 226 9500",
    "sg:postcode":"97209",
    "sg:province":"OR",
    "wof:name":"Northwest Orchid Salon",
    "wof:placetype":"venue"
},
  "geometry": {"coordinates":[-122.672578,45.52462],"type":"Point"}
}