{
  "type": "Feature",
  "properties": {
    "iso:country":"US",
    "sg:address":"561 SE Oak St",
    "sg:city":"Hillsboro",
    "sg:classifiers":[
        {
            "category":"Health Services",
            "subcategory":"Doctor",
            "type":"Services"
        },
        {
            "category":"Health Services",
            "subcategory":"Clinic",
            "type":"Services"
        }
    ],
    "sg:phone":"+1 503 693 8007",
    "sg:postcode":"97123",
    "sg:province":"OR",
    "sg:tags":[
        "physician",
        "surgeon",
        "osteopathic"
    ],
    "wof:name":"Joseth D Mccarthy Md",
    "wof:placetype":"venue"
},
  "geometry": {"coordinates":[-122.98154700000001,45.518803],"type":"Point"}
}