{
  "type": "Feature",
  "properties": {
    "iso:country":"US",
    "sg:address":"3735 Crater Lake Hwy",
    "sg:city":"Medford",
    "sg:classifiers":[
        {
            "category":"Autos & Motor Vehicles",
            "subcategory":"Motorcycle Sales",
            "type":"Retail Goods"
        }
    ],
    "sg:phone":"+1 888 353 5550",
    "sg:postcode":"97504",
    "sg:province":"OR",
    "sg:tags":[
        "ski",
        "terrain",
        "generator",
        "jet"
    ],
    "sg:website":"www.itsyourroad.com",
    "wof:name":"Kawasaki & Honda of Medford",
    "wof:placetype":"venue"
},
  "geometry": {"coordinates":[-122.856003,42.372799],"type":"Point"}
}