{
  "type": "Feature",
  "properties": {
    "iso:country":"US",
    "sg:address":"27660 SW Lepley Ln",
    "sg:city":"Hillsboro",
    "sg:classifiers":[
        {
            "category":"Manufacturing",
            "subcategory":"Building Materials",
            "type":"Manufacturing & Wholesale Goods"
        }
    ],
    "sg:phone":"+1 503 628 1339",
    "sg:postcode":"97123",
    "sg:province":"OR",
    "sg:tags":[
        "cabinet"
    ],
    "wof:name":"Midway Custom Cabinets Inc",
    "wof:placetype":"venue"
},
  "geometry": {"coordinates":[-122.960845,45.403166],"type":"Point"}
}