{
  "type": "Feature",
  "properties": {
    "iso:country":"US",
    "sg:address":"7108 Bethel Rd SE",
    "sg:city":"Salem",
    "sg:classifiers":[
        {
            "category":"Building & Trades",
            "subcategory":"Construction",
            "type":"Services"
        }
    ],
    "sg:phone":"+1 503 315 8620",
    "sg:postcode":"97317",
    "sg:province":"OR",
    "sg:tags":[
        "house"
    ],
    "wof:name":"Express Remodeling",
    "wof:placetype":"venue"
},
  "geometry": {"coordinates":[-122.916635,44.917552],"type":"Point"}
}