{
  "type": "Feature",
  "properties": {
    "addr:full":"8527 SE 82nd Ave Portland OR 97266",
    "addr:housenumber":"8527",
    "addr:postcode":"97266",
    "addr:street":"Se 82Nd Ave",
    "iso:country":"US",
    "sg:address":"8527 SE 82nd Ave",
    "sg:city":"Portland",
    "sg:classifiers":[
        {
            "category":"Building & Trades",
            "subcategory":"Construction",
            "type":"Services"
        }
    ],
    "sg:phone":"+1 503 772 1217",
    "sg:postcode":"97266",
    "sg:province":"OR",
    "sg:tags":[
        "general",
        "contractor"
    ],
    "wof:name":"Metro Homes Inc",
    "wof:placetype":"venue"
},
  "geometry": {"coordinates":[-122.57900100000001,45.451457],"type":"Point"}
}