{
  "type": "Feature",
  "properties": {
    "addr:full":"3643 SW Iowa St Portland OR 97221",
    "addr:housenumber":"3643",
    "addr:postcode":"97221",
    "addr:street":"Sw Iowa St",
    "iso:country":"US",
    "sg:address":"3643 SW Iowa St",
    "sg:city":"Portland",
    "sg:classifiers":[
        {
            "category":"Wholesale",
            "subcategory":"Non-durable Goods",
            "type":"Manufacturing & Wholesale Goods"
        },
        {
            "category":"Professional",
            "subcategory":"Business Services",
            "type":"Services"
        }
    ],
    "sg:phone":"+1 503 246 4571",
    "sg:postcode":"97221",
    "sg:province":"OR",
    "sg:tags":[
        "broker",
        "merchandise",
        "merchandise-wholesale"
    ],
    "wof:name":"Sabra Interprises",
    "wof:placetype":"venue"
},
  "geometry": {"coordinates":[-122.715098,45.48028],"type":"Point"}
}