{
  "type": "Feature",
  "properties": {
    "iso:country":"US",
    "sg:address":"2585 Roosevelt Blvd",
    "sg:city":"Eugene",
    "sg:classifiers":[
        {
            "category":"Building & Trades",
            "subcategory":"Landscaping Services",
            "type":"Services"
        }
    ],
    "sg:phone":"+1 541 343 9154",
    "sg:postcode":"97402",
    "sg:province":"OR",
    "sg:tags":[
        "lawn",
        "maintenance",
        "grounds"
    ],
    "wof:name":"Greg's Landscape Svc & Constr",
    "wof:placetype":"venue"
},
  "geometry": {"coordinates":[-123.134216,44.063746],"type":"Point"}
}