{
  "type": "Feature",
  "properties": {
    "iso:country":"US",
    "sg:address":"1385 Goodpasture Island Rd",
    "sg:city":"Eugene",
    "sg:classifiers":[
        {
            "category":"Shopping",
            "type":"Retail Goods"
        }
    ],
    "sg:phone":"+1 541 232 7070",
    "sg:postcode":"97401",
    "sg:province":"OR",
    "wof:name":"Simply Replacement",
    "wof:placetype":"venue"
},
  "geometry": {"coordinates":[-123.094089,44.084162],"type":"Point"}
}