{
  "type": "Feature",
  "properties": {
    "iso:country":"US",
    "sg:address":"1601 2nd St",
    "sg:city":"Tillamook",
    "sg:classifiers":[
        {
            "category":"Building & Trades",
            "subcategory":"Construction",
            "type":"Services"
        }
    ],
    "sg:phone":"+1 503 815 8333",
    "sg:postcode":"97141",
    "sg:province":"OR",
    "sg:tags":[
        "refinishing",
        "floor",
        "builder",
        "laying",
        "resurfacing",
        "operative"
    ],
    "wof:name":"Olson-Noteboom Construction",
    "wof:placetype":"venue"
},
  "geometry": {"coordinates":[-123.848145,45.457077],"type":"Point"}
}