{
  "type": "Feature",
  "properties": {
    "iso:country":"US",
    "sg:address":"752 Edina Ln NE",
    "sg:city":"Salem",
    "sg:classifiers":[
        {
            "category":"Manufacturing",
            "subcategory":"Lumber",
            "type":"Manufacturing & Wholesale Goods"
        }
    ],
    "sg:phone":"+1 503 581 6317",
    "sg:postcode":"97301",
    "sg:province":"OR",
    "sg:tags":[
        "forestry"
    ],
    "wof:name":"R & R Contracting Inc",
    "wof:placetype":"venue"
},
  "geometry": {"coordinates":[-122.99648000000001,44.941572],"type":"Point"}
}