{
  "type": "Feature",
  "properties": {
    "iso:country":"US",
    "sg:address":"3303 Washburn Way",
    "sg:city":"Klamath Falls",
    "sg:classifiers":[
        {
            "category":"Autos & Motor Vehicles",
            "subcategory":"Fuel & Gas Station",
            "type":"Retail Goods"
        }
    ],
    "sg:phone":"+1 541 850 9809",
    "sg:postcode":"97603",
    "sg:province":"OR",
    "sg:tags":[
        "oil"
    ],
    "wof:name":"Clough Oil Retail",
    "wof:placetype":"venue"
},
  "geometry": {"coordinates":[-121.757047,42.19639],"type":"Point"}
}