{
  "type": "Feature",
  "properties": {
    "addr:full":"27424 SE Eagle Creek Rd Estacada OR 97023",
    "addr:postcode":"27424;97023",
    "addr:street":"Se Eagle Creek Rd",
    "iso:country":"US",
    "sg:address":"27424 SE Eagle Creek Rd",
    "sg:city":"Estacada",
    "sg:classifiers":[
        {
            "category":"Building & Trades",
            "subcategory":"Construction",
            "type":"Services"
        }
    ],
    "sg:phone":"+1 503 572 9614",
    "sg:postcode":"97023",
    "sg:province":"OR",
    "sg:tags":[
        "painting",
        "contractor"
    ],
    "wof:name":"G&L Exteriors, Inc.",
    "wof:placetype":"venue"
},
  "geometry": {"coordinates":[-122.343493,45.322422],"type":"Point"}
}