{
  "type": "Feature",
  "properties": {
    "iso:country":"US",
    "sg:address":"8221 Sw 45th",
    "sg:city":"Portland",
    "sg:classifiers":[
        {
            "category":"Building & Trades",
            "subcategory":"Construction",
            "type":"Services"
        }
    ],
    "sg:phone":"+1 503 896 9202",
    "sg:postcode":"97219",
    "sg:province":"OR",
    "sg:tags":[
        "painter",
        "contractor"
    ],
    "sg:website":"www.colorfastpaintspdx.com",
    "wof:name":"Colorfast Custom Painting",
    "wof:placetype":"venue"
},
  "geometry": {"coordinates":[-122.723399,45.46507],"type":"Point"}
}