{
  "type": "Feature",
  "properties": {
    "iso:country":"US",
    "sg:address":"920 SW 3rd Ave",
    "sg:city":"Portland",
    "sg:classifiers":[
        {
            "category":"Shopping",
            "subcategory":"Computers & Home Electronics",
            "type":"Retail Goods"
        }
    ],
    "sg:phone":"+1 503 293 8346",
    "sg:postcode":"97204",
    "sg:province":"OR",
    "sg:tags":[
        "software"
    ],
    "wof:name":"Novell Inc",
    "wof:placetype":"venue"
},
  "geometry": {"coordinates":[-122.67650399999999,45.516365],"type":"Point"}
}