{
  "type": "Feature",
  "properties": {
    "iso:country":"US",
    "sg:address":"3635 N Farragut St",
    "sg:city":"Portland",
    "sg:classifiers":[
        {
            "category":"Professional",
            "subcategory":"Art Services",
            "type":"Services"
        }
    ],
    "sg:phone":"+1 503 241 7382",
    "sg:postcode":"97217",
    "sg:province":"OR",
    "sg:tags":[
        "commercial",
        "design"
    ],
    "sg:website":"www.chadcrowe.com",
    "wof:name":"Chad Crowe Illustration",
    "wof:placetype":"venue"
},
  "geometry": {"coordinates":[-122.704538,45.579416],"type":"Point"}
}