{
  "type": "Feature",
  "properties": {
    "iso:country":"US",
    "sg:address":"2838 S 6th St",
    "sg:city":"Klamath Falls",
    "sg:classifiers":[
        {
            "category":"Cinema",
            "subcategory":"Movie Rental",
            "type":"Entertainment"
        }
    ],
    "sg:phone":"+1 541 883 5221",
    "sg:postcode":"97603",
    "sg:province":"OR",
    "sg:tags":[
        "leasing",
        "video",
        "disc",
        "tape"
    ],
    "wof:name":"Blockbuster Video",
    "wof:placetype":"venue"
},
  "geometry": {"coordinates":[-121.754659,42.209987],"type":"Point"}
}