{
  "type": "Feature",
  "properties": {
    "iso:country":"US",
    "sg:address":"3930 SE Division Street",
    "sg:city":"Portland",
    "sg:classifiers":[
        {
            "category":"Health Services",
            "subcategory":"Doctor",
            "type":"Services"
        }
    ],
    "sg:phone":"+1 503 418 3900",
    "sg:postcode":"97202",
    "sg:province":"OR",
    "sg:tags":[
        "practice",
        "family"
    ],
    "wof:name":"McQueen Cristin PA",
    "wof:placetype":"venue"
},
  "geometry": {"coordinates":[-122.622215,45.504657],"type":"Point"}
}