{
  "type": "Feature",
  "properties": {
    "iso:country":"US",
    "sg:address":"64657 Bruce Ave",
    "sg:city":"Bend",
    "sg:classifiers":[
        {
            "category":"Shopping",
            "subcategory":"Bicycles & Sporting Goods",
            "type":"Retail Goods"
        }
    ],
    "sg:phone":"+1 541 389 2079",
    "sg:postcode":"97701",
    "sg:province":"OR",
    "sg:tags":[
        "shop",
        "tack"
    ],
    "wof:name":"Custom Equine Inc",
    "wof:placetype":"venue"
},
  "geometry": {"coordinates":[-121.33188800000001,44.148593],"type":"Point"}
}