{
  "type": "Feature",
  "properties": {
    "iso:country":"US",
    "sg:address":"24274 Neuman Rd",
    "sg:city":"Corvallis",
    "sg:classifiers":[
        {
            "category":"Manufacturing",
            "subcategory":"Lumber",
            "type":"Manufacturing & Wholesale Goods"
        }
    ],
    "sg:phone":"+1 541 929 5830",
    "sg:postcode":"97333",
    "sg:province":"OR",
    "sg:tags":[
        "operation",
        "timber",
        "tract"
    ],
    "wof:name":"Valley View Tree Ranch",
    "wof:placetype":"venue"
},
  "geometry": {"coordinates":[-123.404124,44.462696],"type":"Point"}
}