{
  "type": "Feature",
  "properties": {
    "addr:full":"17435 SW Johnson St Beaverton OR 97006",
    "addr:housenumber":"17435",
    "addr:postcode":"97006",
    "addr:street":"Sw Johnson St",
    "iso:country":"US",
    "sg:address":"17435 SW Johnson St",
    "sg:city":"Beaverton",
    "sg:classifiers":[
        {
            "category":"Home & Garden",
            "subcategory":"Household Appliances",
            "type":"Retail Goods"
        }
    ],
    "sg:phone":"+1 503 649 2214",
    "sg:postcode":"97006",
    "sg:province":"OR",
    "sg:tags":[
        "re",
        "trade",
        "electrical",
        "contractor"
    ],
    "wof:name":"A-Appliance Analyst",
    "wof:placetype":"venue"
},
  "geometry": {"coordinates":[-122.857572,45.499659],"type":"Point"}
}