{
  "type": "Feature",
  "properties": {
    "iso:country":"US",
    "sg:address":"11805 Williams Hwy",
    "sg:city":"Grants Pass",
    "sg:classifiers":[
        {
            "category":"Building & Trades",
            "subcategory":"Electrical",
            "type":"Services"
        }
    ],
    "sg:phone":"+1 541 846 9125",
    "sg:postcode":"97527",
    "sg:province":"OR",
    "sg:tags":[
        "electrical",
        "contractor"
    ],
    "wof:name":"PM Unlimited",
    "wof:placetype":"venue"
},
  "geometry": {"coordinates":[-123.274897,42.313362],"type":"Point"}
}