{
  "type": "Feature",
  "properties": {
    "iso:country":"US",
    "sg:address":"449 N Star Ln",
    "sg:city":"Sutherlin",
    "sg:classifiers":[
        {
            "category":"Education",
            "subcategory":"Dance Studio",
            "type":"Public Place"
        }
    ],
    "sg:phone":"+1 541 679 0752",
    "sg:postcode":"97479",
    "sg:province":"OR",
    "wof:name":"Celebration Street Dance",
    "wof:placetype":"venue"
},
  "geometry": {"coordinates":[-123.319991,43.356352],"type":"Point"}
}