{
  "type": "Feature",
  "properties": {
    "addr:full":"10244 S Rosewood Way Molalla OR 97038",
    "addr:housenumber":"10244",
    "addr:postcode":"97038",
    "addr:street":"S Rosewood Way",
    "iso:country":"US",
    "sg:address":"10244 S Rosewood Way",
    "sg:city":"Molalla",
    "sg:classifiers":[
        {
            "category":"Manufacturing",
            "subcategory":"Lumber",
            "type":"Manufacturing & Wholesale Goods"
        }
    ],
    "sg:phone":"+1 503 829 5185",
    "sg:postcode":"97038",
    "sg:province":"OR",
    "sg:tags":[
        "reforestation"
    ],
    "wof:name":"Pablo Anfilofieff",
    "wof:placetype":"venue"
},
  "geometry": {"coordinates":[-122.653941,45.094697],"type":"Point"}
}