{
  "type": "Feature",
  "properties": {
    "iso:country":"US",
    "sg:address":"8950 SW Burnham St",
    "sg:city":"Tigard",
    "sg:classifiers":[
        {
            "category":"Building & Trades",
            "subcategory":"Equipment Rental",
            "type":"Services"
        }
    ],
    "sg:phone":"+1 503 644 9442",
    "sg:postcode":"97223",
    "sg:province":"OR",
    "sg:tags":[
        "leasing"
    ],
    "sg:website":"www.bancorleasing.com",
    "wof:name":"Bancor Of Oregon",
    "wof:placetype":"venue"
},
  "geometry": {"coordinates":[-122.767382,45.426471],"type":"Point"}
}