{
  "type": "Feature",
  "properties": {
    "iso:country":"US",
    "sg:address":"19040 S Fernwood Rd",
    "sg:city":"Molalla",
    "sg:classifiers":[
        {
            "category":"Manufacturing",
            "subcategory":"Lumber",
            "type":"Manufacturing & Wholesale Goods"
        }
    ],
    "sg:phone":"+1 503 829 5351",
    "sg:postcode":"97038",
    "sg:province":"OR",
    "sg:tags":[
        "logging"
    ],
    "wof:name":"Schroeder Cutting Inc",
    "wof:placetype":"venue"
},
  "geometry": {"coordinates":[-122.473689,45.123539],"type":"Point"}
}