{
  "type": "Feature",
  "properties": {
    "addr:full":"40 N State St Lake Oswego OR 97034",
    "addr:housenumber":"40",
    "addr:postcode":"97034",
    "addr:street":"N State St",
    "iso:country":"US",
    "sg:address":"40 N State St",
    "sg:city":"Lake Oswego",
    "sg:classifiers":[
        {
            "category":"Restaurant",
            "type":"Food & Drink"
        }
    ],
    "sg:phone":"+1 503 636 4561",
    "sg:postcode":"97034",
    "sg:province":"OR",
    "sg:tags":[
        "seafood",
        "steakhouse"
    ],
    "sg:website":"oswegolakehouse.com/",
    "wof:name":"Oswego Lake House",
    "wof:placetype":"venue"
},
  "geometry": {"coordinates":[-122.66386900000001,45.416286],"type":"Point"}
}