{
  "type": "Feature",
  "properties": {
    "iso:country":"US",
    "sg:address":"7451 SE Hacienda St",
    "sg:city":"Hillsboro",
    "sg:classifiers":[
        {
            "category":"Professional",
            "subcategory":"Business Services",
            "type":"Services"
        }
    ],
    "sg:phone":"+1 503 649 9553",
    "sg:postcode":"97123",
    "sg:province":"OR",
    "wof:name":"Interiors By Renee",
    "wof:placetype":"venue"
},
  "geometry": {"coordinates":[-122.905235,45.505095],"type":"Point"}
}