{
  "type": "Feature",
  "properties": {
    "addr:full":"8225 SE 162nd Ave Portland OR 97236",
    "addr:housenumber":"8225",
    "addr:postcode":"97236",
    "addr:street":"Se 162Nd Ave",
    "iso:country":"US",
    "sg:address":"8225 SE 162nd Ave",
    "sg:city":"Portland",
    "sg:classifiers":[
        {
            "category":"Manufacturing",
            "subcategory":"Retail Goods",
            "type":"Manufacturing & Wholesale Goods"
        }
    ],
    "sg:phone":"+1 503 761 7678",
    "sg:postcode":"97236",
    "sg:province":"OR",
    "sg:tags":[
        "product",
        "mfg"
    ],
    "wof:name":"Pelagic",
    "wof:placetype":"venue"
},
  "geometry": {"coordinates":[-122.496832,45.463562],"type":"Point"}
}