{
  "type": "Feature",
  "properties": {
    "iso:country":"US",
    "sg:address":"16100 SW Century Dr",
    "sg:city":"Sherwood",
    "sg:classifiers":[
        {
            "category":"Banks & Credit Unions",
            "subcategory":"Bank",
            "type":"Services"
        }
    ],
    "sg:phone":"+1 503 625 9804",
    "sg:postcode":"97140",
    "sg:province":"OR",
    "sg:tags":[
        "mortgage"
    ],
    "wof:name":"1st Millennium Mortgage",
    "wof:placetype":"venue"
},
  "geometry": {"coordinates":[-122.839467,45.36474],"type":"Point"}
}