{
  "type": "Feature",
  "properties": {
    "iso:country":"US",
    "sg:address":"470 T St",
    "sg:city":"Springfield",
    "sg:classifiers":[
        {
            "category":"Shopping",
            "subcategory":"Stationery & Office Supplies",
            "type":"Retail Goods"
        }
    ],
    "sg:phone":"+1 541 736 5781",
    "sg:postcode":"97477",
    "sg:province":"OR",
    "wof:name":"ML Business Svc",
    "wof:placetype":"venue"
},
  "geometry": {"coordinates":[-123.021086,44.06655],"type":"Point"}
}