{
  "type": "Feature",
  "properties": {
    "addr:full":"5616 N Burrage Ave Portland OR 97217",
    "addr:housenumber":"5616",
    "addr:postcode":"97217",
    "addr:street":"N Burrage Ave",
    "iso:country":"US",
    "sg:address":"5616 N Burrage Ave",
    "sg:city":"Portland",
    "sg:classifiers":[
        {
            "category":"Communications",
            "subcategory":"Film & Video Production",
            "type":"Services"
        }
    ],
    "sg:phone":"+1 503 289 2087",
    "sg:postcode":"97217",
    "sg:province":"OR",
    "sg:tags":[
        "tv",
        "radio",
        "services-commercial",
        "companies-film"
    ],
    "wof:name":"Burrage Ave Productions",
    "wof:placetype":"venue"
},
  "geometry": {"coordinates":[-122.69459000000001,45.5638],"type":"Point"}
}