{
  "type": "Feature",
  "properties": {
    "iso:country":"US",
    "sg:address":"8416 SE Sunnyside Rd",
    "sg:city":"Clackamas",
    "sg:classifiers":[
        {
            "category":"Bars & Pubs",
            "type":"Food & Drink"
        },
        {
            "category":"Restaurant",
            "type":"Food & Drink"
        }
    ],
    "sg:menulink":"http://www.allmenus.com/or/northwest-clackamas/5201-stanfords-restaurant--bar/menu/",
    "sg:phone":"+1 503 653 9400",
    "sg:postcode":"97015",
    "sg:province":"OR",
    "sg:tags":[
        "american"
    ],
    "wof:name":"Stanford's Restaurant & Bar",
    "wof:placetype":"venue"
},
  "geometry": {"coordinates":[-122.576599,45.433112],"type":"Point"}
}