{
  "type": "Feature",
  "properties": {
    "addr:full":"620 SE Water Ave Portland OR 97214",
    "addr:housenumber":"620",
    "addr:postcode":"97214",
    "addr:street":"Se Water Ave",
    "iso:country":"US",
    "sg:address":"620 SE Water Ave",
    "sg:city":"Portland",
    "sg:classifiers":[
        {
            "category":"Manufacturing",
            "subcategory":"Apparel",
            "type":"Manufacturing & Wholesale Goods"
        }
    ],
    "sg:phone":"+1 503 235 1188",
    "sg:postcode":"97214",
    "sg:province":"OR",
    "sg:tags":[
        "canvas",
        "product",
        "related"
    ],
    "sg:website":"www.mcgeeawnings.com",
    "wof:name":"Mc Gee Blind & Awnings Shades",
    "wof:placetype":"venue"
},
  "geometry": {"coordinates":[-122.665741,45.51848],"type":"Point"}
}