{
  "type": "Feature",
  "properties": {
    "addr:full":"3973 Cherry Ln Medford OR 97504",
    "addr:housenumber":"3973",
    "addr:postcode":"97504",
    "addr:street":"Cherry Ln",
    "iso:country":"US",
    "sg:address":"3973 Cherry Ln",
    "sg:city":"Medford",
    "sg:classifiers":[
        {
            "category":"Real Estate",
            "subcategory":"Real Estate Agent",
            "type":"Services"
        }
    ],
    "sg:phone":"+1 541 772 1132",
    "sg:postcode":"97504",
    "sg:province":"OR",
    "wof:name":"Alice H. Anderson Revocable Tr",
    "wof:placetype":"venue"
},
  "geometry": {"coordinates":[-122.80623300000001,42.326801],"type":"Point"}
}