{
  "type": "Feature",
  "properties": {
    "iso:country":"US",
    "sg:address":"1500 Tierra Lynn Dr",
    "sg:city":"Woodburn",
    "sg:classifiers":[
        {
            "category":"Professional",
            "subcategory":"Business Services",
            "type":"Services"
        }
    ],
    "sg:phone":"+1 503 981 2168",
    "sg:postcode":"97071",
    "sg:province":"OR",
    "sg:tags":[
        "organizing",
        "services-household"
    ],
    "wof:name":"Manage-Ing Property Services",
    "wof:placetype":"venue"
},
  "geometry": {"coordinates":[-122.83875999999999,45.149441],"type":"Point"}
}