{
  "type": "Feature",
  "properties": {
    "iso:country":"US",
    "sg:address":"3650 Crater Lake Ave",
    "sg:city":"Medford",
    "sg:classifiers":[
        {
            "category":"Autos & Motor Vehicles",
            "subcategory":"Automobile Sales",
            "type":"Retail Goods"
        }
    ],
    "sg:phone":"+1 541 857 2822",
    "sg:postcode":"97504",
    "sg:province":"OR",
    "sg:tags":[
        "car",
        "dealer"
    ],
    "wof:name":"National Auto Mart",
    "wof:placetype":"venue"
},
  "geometry": {"coordinates":[-122.855409,42.366557],"type":"Point"}
}