{
  "type": "Feature",
  "properties": {
    "addr:full":"1130 SW Morrison St Ste 417 Portland OR 97205",
    "addr:housenumber":"1130",
    "addr:postcode":"97205",
    "addr:street":"Sw Morrison St Ste 417",
    "iso:country":"US",
    "sg:address":"1130 SW Morrison St Ste 417",
    "sg:city":"Portland",
    "sg:classifiers":[
        {
            "category":"Health Services",
            "subcategory":"Health Practitioner",
            "type":"Services"
        },
        {
            "category":"Health Services",
            "subcategory":"Chiropractor",
            "type":"Services"
        }
    ],
    "sg:phone":"+1 503 987 0775",
    "sg:postcode":"97205",
    "sg:province":"OR",
    "sg:tags":[
        "naturopathic/holistic"
    ],
    "sg:website":"www.allergyasthmawellness.com",
    "wof:name":"Allergy & Asthma Wellness Center",
    "wof:placetype":"venue"
},
  "geometry": {"coordinates":[-122.683886,45.520417],"type":"Point"}
}