{
  "type": "Feature",
  "properties": {
    "iso:country":"US",
    "sg:address":"910 SE Wilson Ave Ste B2",
    "sg:city":"Bend",
    "sg:classifiers":[
        {
            "category":"Communications",
            "subcategory":"Newspaper",
            "type":"Services"
        }
    ],
    "sg:phone":"+1 541 382 6210",
    "sg:postcode":"97702",
    "sg:province":"OR",
    "sg:tags":[
        "feature",
        "syndicate"
    ],
    "sg:website":"http://www.thebereancall.org",
    "wof:name":"The Berean Call Inc",
    "wof:placetype":"venue"
},
  "geometry": {"coordinates":[-121.29057299999999,44.044312],"type":"Point"}
}