{
  "type": "Feature",
  "properties": {
    "addr:full":"12850 SW Dale Cir Beaverton OR 97008",
    "addr:housenumber":"12850",
    "addr:postcode":"97008",
    "addr:street":"Sw Dale Cir",
    "iso:country":"US",
    "sg:address":"12850 SW Dale Cir",
    "sg:city":"Beaverton",
    "sg:classifiers":[
        {
            "category":"Autos & Motor Vehicles",
            "subcategory":"Fuel & Gas Station",
            "type":"Retail Goods"
        }
    ],
    "sg:phone":"+1 503 646 8129",
    "sg:postcode":"97008",
    "sg:province":"OR",
    "sg:tags":[
        "station",
        "gasoline"
    ],
    "wof:name":"BP Fabrications",
    "wof:placetype":"venue"
},
  "geometry": {"coordinates":[-122.808891,45.475385],"type":"Point"}
}