{
  "type": "Feature",
  "properties": {
    "iso:country":"US",
    "sg:address":"1180 Gate Park Dr",
    "sg:city":"Central Point",
    "sg:classifiers":[
        {
            "category":"Building & Trades",
            "subcategory":"Pest Control",
            "type":"Services"
        }
    ],
    "sg:phone":"+1 541 773 6488",
    "sg:postcode":"97502",
    "sg:province":"OR",
    "wof:name":"Bill's Bug E Inc",
    "wof:placetype":"venue"
},
  "geometry": {"coordinates":[-122.89145600000001,42.36501],"type":"Point"}
}