{
  "type": "Feature",
  "properties": {
    "iso:country":"US",
    "sg:address":"2538 10th Ave",
    "sg:city":"Forest Grove",
    "sg:classifiers":[
        {
            "category":"Building & Trades",
            "subcategory":"Construction",
            "type":"Services"
        }
    ],
    "sg:phone":"+1 503 357 7755",
    "sg:postcode":"97116",
    "sg:province":"OR",
    "sg:tags":[
        "maker",
        "cabinet"
    ],
    "sg:website":"www.haroldscustomcabinets.com",
    "wof:name":"Harold's Custom Cabinets Inc",
    "wof:placetype":"venue"
},
  "geometry": {"coordinates":[-123.10284799999999,45.508644],"type":"Point"}
}