{
  "type": "Feature",
  "properties": {
    "addr:full":"10255 SW Canyon Rd Beaverton OR 97005",
    "addr:housenumber":"10255",
    "addr:postcode":"97005",
    "addr:street":"Sw Canyon Rd",
    "iso:country":"US",
    "sg:address":"10255 SW Canyon Rd",
    "sg:city":"Beaverton",
    "sg:classifiers":[
        {
            "category":"Coffee & Tea",
            "type":"Food & Drink"
        },
        {
            "category":"Food & Beverages",
            "subcategory":"Meat & Fish",
            "type":"Retail Goods"
        },
        {
            "category":"Food & Beverages",
            "subcategory":"Groceries & Convenience Stores",
            "type":"Retail Goods"
        }
    ],
    "sg:phone":"+1 503 641 1352",
    "sg:postcode":"97005",
    "sg:province":"OR",
    "sg:tags":[
        "shop"
    ],
    "sg:website":"www.oregonbazaar.com",
    "wof:name":"Bazaar",
    "wof:placetype":"venue"
},
  "geometry": {"coordinates":[-122.781998,45.492802],"type":"Point"}
}