{
  "type": "Feature",
  "properties": {
    "iso:country":"US",
    "sg:address":"1480 W 12th Ave Apt 2",
    "sg:city":"Eugene",
    "sg:classifiers":[
        {
            "category":"Professional",
            "subcategory":"Accounting & Tax Preparation",
            "type":"Services"
        }
    ],
    "sg:phone":"+1 541 686 6528",
    "sg:postcode":"97402",
    "sg:province":"OR",
    "sg:tags":[
        "bookkeeping",
        "billing"
    ],
    "wof:name":"4 Ace Bookkeeping Solutions",
    "wof:placetype":"venue"
},
  "geometry": {"coordinates":[-123.115489,44.046636],"type":"Point"}
}