{
  "type": "Feature",
  "properties": {
    "addr:full":"4920 SW Vermont Street Portland OR 97219",
    "addr:housenumber":"4920",
    "addr:postcode":"97219",
    "addr:street":"Sw Vermont Street",
    "iso:country":"US",
    "sg:address":"4920 SW Vermont Street",
    "sg:city":"Portland",
    "sg:classifiers":[
        {
            "category":"Social Services",
            "subcategory":"Child Care",
            "type":"Services"
        },
        {
            "category":"Education",
            "subcategory":"Preschool",
            "type":"Public Place"
        },
        {
            "category":"Education",
            "subcategory":"School",
            "type":"Public Place"
        }
    ],
    "sg:phone":"+1 503 246 5495",
    "sg:postcode":"97219",
    "sg:province":"OR",
    "sg:tags":[
        "elementary",
        "day"
    ],
    "wof:name":"Montessori School West Hills Schools",
    "wof:placetype":"venue"
},
  "geometry": {"coordinates":[-122.727248,45.476266],"type":"Point"}
}