{
  "type": "Feature",
  "properties": {
    "addr:full":"12 NE 78th Ave Portland OR 97213",
    "addr:housenumber":"12",
    "addr:postcode":"97213",
    "addr:street":"Ne 78Th Ave",
    "iso:country":"US",
    "sg:address":"12 NE 78th Ave",
    "sg:city":"Portland",
    "sg:classifiers":[
        {
            "category":"Building & Trades",
            "subcategory":"Construction",
            "type":"Services"
        }
    ],
    "sg:phone":"+1 503 257 2479",
    "sg:postcode":"97213",
    "sg:province":"OR",
    "sg:tags":[
        "hanging",
        "contractor"
    ],
    "wof:name":"Eurostyle Painting",
    "wof:placetype":"venue"
},
  "geometry": {"coordinates":[-122.583444,45.524564],"type":"Point"}
}