{
  "type": "Feature",
  "properties": {
    "addr:full":"800 Liberty St. Ashland OR 97520",
    "addr:housenumber":"800",
    "addr:postcode":"97520",
    "addr:street":"Liberty St.",
    "iso:country":"US",
    "sg:address":"800 Liberty St.",
    "sg:city":"Ashland",
    "sg:classifiers":[
        {
            "category":"Professional",
            "subcategory":"Business Services",
            "type":"Services"
        }
    ],
    "sg:phone":"+1 800 304 7507",
    "sg:postcode":"97520",
    "sg:province":"OR",
    "sg:tags":[
        "business-development",
        "project-management",
        "web-development",
        "web-design",
        "business-plans",
        "marketing-plans"
    ],
    "sg:website":"http://www.gbds.us",
    "wof:name":"Global Business Development Services",
    "wof:placetype":"venue"
},
  "geometry": {"coordinates":[-122.703299,42.18179],"type":"Point"}
}