{
  "type": "Feature",
  "properties": {
    "addr:full":"104 SW 2nd Avenue Portland OR 97204",
    "addr:housenumber":"104",
    "addr:postcode":"97204",
    "addr:street":"Sw 2Nd Avenue",
    "iso:country":"US",
    "sg:address":"104 SW 2nd Avenue",
    "sg:city":"Portland",
    "sg:classifiers":[
        {
            "category":"Shopping",
            "subcategory":"Music",
            "type":"Retail Goods"
        },
        {
            "category":"Shopping",
            "subcategory":"Computers & Home Electronics",
            "type":"Retail Goods"
        }
    ],
    "sg:phone":"+1 503 222 9166",
    "sg:postcode":"97204",
    "sg:province":"OR",
    "sg:tags":[
        "dvd's"
    ],
    "wof:name":"Platinum Records Lights & Sound",
    "wof:placetype":"venue"
},
  "geometry": {"coordinates":[-122.672558,45.522003],"type":"Point"}
}