{
  "type": "Feature",
  "properties": {
    "iso:country":"US",
    "sg:address":"1668 Resort St",
    "sg:city":"Baker City",
    "sg:classifiers":[
        {
            "category":"Personal",
            "subcategory":"Beauty Salon",
            "type":"Services"
        }
    ],
    "sg:phone":"+1 541 523 4118",
    "sg:postcode":"97814",
    "sg:province":"OR",
    "wof:name":"Hairitage Beauty Salon",
    "wof:placetype":"venue"
},
  "geometry": {"coordinates":[-117.82897699999999,44.774415],"type":"Point"}
}