{
  "type": "Feature",
  "properties": {
    "addr:full":"12530 SE 93rd Ave Clackamas OR 97015",
    "addr:postcode":"12530;97015",
    "addr:street":"Se 93Rd Ave",
    "iso:country":"US",
    "sg:address":"12530 SE 93rd Ave",
    "sg:city":"Clackamas",
    "sg:classifiers":[
        {
            "category":"Restaurant",
            "type":"Food & Drink"
        }
    ],
    "sg:phone":"+1 503 659 1048",
    "sg:postcode":"97015",
    "sg:province":"OR",
    "sg:website":"www.redrobin.com",
    "wof:name":"Red Robin America's Gourmet Burgers & Spirits",
    "wof:placetype":"venue"
},
  "geometry": {"coordinates":[-122.568001,45.431801],"type":"Point"}
}