{
  "type": "Feature",
  "properties": {
    "iso:country":"US",
    "sg:address":"4400 SE Roethe Rd",
    "sg:city":"Portland",
    "sg:classifiers":[
        {
            "category":"Real Estate",
            "subcategory":"Developer",
            "type":"Services"
        }
    ],
    "sg:phone":"+1 503 659 0418",
    "sg:postcode":"97267",
    "sg:province":"OR",
    "sg:tags":[
        "mobile",
        "manufactured",
        "housing-communities",
        "home"
    ],
    "wof:name":"Altramar Mobil Home Parks",
    "wof:placetype":"venue"
},
  "geometry": {"coordinates":[-122.61817600000001,45.398975],"type":"Point"}
}