{
  "type": "Feature",
  "properties": {
    "addr:full":"16518 Emerald Green Ln SE Jefferson OR 97352",
    "addr:housenumber":"16518",
    "addr:postcode":"97352",
    "addr:street":"Emerald Green Ln Se",
    "iso:country":"US",
    "sg:address":"16518 Emerald Green Ln SE",
    "sg:city":"Jefferson",
    "sg:classifiers":[
        {
            "category":"Social Services",
            "type":"Services"
        }
    ],
    "sg:phone":"+1 541 327 3723",
    "sg:postcode":"97352",
    "sg:province":"OR",
    "wof:name":"Pathways Inc",
    "wof:placetype":"venue"
},
  "geometry": {"coordinates":[-122.980709,44.715415],"type":"Point"}
}