{
  "type": "Feature",
  "properties": {
    "iso:country":"US",
    "sg:address":"21953 S Saling Rd",
    "sg:city":"Estacada",
    "sg:classifiers":[
        {
            "category":"Building & Trades",
            "subcategory":"Construction",
            "type":"Services"
        }
    ],
    "sg:phone":"+1 503 630 3764",
    "sg:postcode":"97023",
    "sg:province":"OR",
    "sg:tags":[
        "nonresidential"
    ],
    "wof:name":"L B Beeler Construction",
    "wof:placetype":"venue"
},
  "geometry": {"coordinates":[-122.354029,45.288261],"type":"Point"}
}