{
  "type": "Feature",
  "properties": {
    "iso:country":"US",
    "sg:address":"1504 Sherman Ave",
    "sg:city":"North Bend",
    "sg:classifiers":[
        {
            "category":"Travel",
            "subcategory":"Hotels & Motels",
            "type":"Entertainment"
        }
    ],
    "sg:phone":"+1 541 756 6398",
    "sg:postcode":"97459",
    "sg:province":"OR",
    "sg:tags":[
        "operation"
    ],
    "wof:name":"Itty Bitty Inn",
    "wof:placetype":"venue"
},
  "geometry": {"coordinates":[-124.224089,43.413049],"type":"Point"}
}