{
  "type": "Feature",
  "properties": {
    "iso:country":"US",
    "sg:address":"12750 NE Marx St",
    "sg:city":"Portland",
    "sg:classifiers":[
        {
            "category":"Manufacturing",
            "subcategory":"Printing",
            "type":"Manufacturing & Wholesale Goods"
        }
    ],
    "sg:phone":"+1 503 255 4122",
    "sg:postcode":"97230",
    "sg:province":"OR",
    "sg:tags":[
        "printer"
    ],
    "wof:name":"Marathon Printing Inc",
    "wof:placetype":"venue"
},
  "geometry": {"coordinates":[-122.536455,45.559212],"type":"Point"}
}