{
  "type": "Feature",
  "properties": {
    "addr:full":"909 Meadowlawn Pl Molalla OR 97038",
    "addr:housenumber":"909",
    "addr:postcode":"97038",
    "addr:street":"Meadowlawn Pl",
    "iso:country":"US",
    "sg:address":"909 Meadowlawn Pl",
    "sg:city":"Molalla",
    "sg:classifiers":[
        {
            "category":"Manufacturing",
            "subcategory":"Apparel",
            "type":"Manufacturing & Wholesale Goods"
        }
    ],
    "sg:phone":"+1 503 829 3023",
    "sg:postcode":"97038",
    "sg:province":"OR",
    "wof:name":"HMS Machine Quilting",
    "wof:placetype":"venue"
},
  "geometry": {"coordinates":[-122.594528,45.157193],"type":"Point"}
}