{
  "type": "Feature",
  "properties": {
    "iso:country":"US",
    "sg:address":"2 Centerpointe Dr Ste 110",
    "sg:city":"Lake Oswego",
    "sg:classifiers":[
        {
            "category":"Real Estate",
            "subcategory":"Real Estate Services",
            "type":"Services"
        }
    ],
    "sg:phone":"+1 503 639 4904",
    "sg:postcode":"97035",
    "sg:province":"OR",
    "sg:tags":[
        "management",
        "property"
    ],
    "sg:website":"www.cbre.com",
    "wof:name":"Cb Richard Ellis",
    "wof:placetype":"venue"
},
  "geometry": {"coordinates":[-122.74011400000001,45.423483],"type":"Point"}
}