{
  "type": "Feature",
  "properties": {
    "addr:full":"21378 NW Bendemeer Rd Hillsboro OR 97124",
    "addr:housenumber":"21378",
    "addr:postcode":"97124",
    "addr:street":"Nw Bendemeer Rd",
    "iso:country":"US",
    "sg:address":"21378 NW Bendemeer Rd",
    "sg:city":"Hillsboro",
    "sg:classifiers":[
        {
            "category":"Building & Trades",
            "subcategory":"Landscaping Services",
            "type":"Services"
        }
    ],
    "sg:phone":"+1 503 648 0918",
    "sg:postcode":"97124",
    "sg:province":"OR",
    "sg:tags":[
        "landscape"
    ],
    "wof:name":"Walts Tree Service and Ldscpg",
    "wof:placetype":"venue"
},
  "geometry": {"coordinates":[-122.895785,45.572673],"type":"Point"}
}