{
  "type": "Feature",
  "properties": {
    "iso:country":"US",
    "sg:address":"10860 SE Oak St",
    "sg:city":"Portland",
    "sg:classifiers":[
        {
            "category":"Building & Trades",
            "subcategory":"Locksmith",
            "type":"Services"
        }
    ],
    "sg:phone":"+1 971 220 9363",
    "sg:postcode":"97222",
    "sg:province":"OR",
    "sg:tags":[
        "key"
    ],
    "wof:name":"24 Hour & 7 Day Portland Emergency Locksmith",
    "wof:placetype":"venue"
},
  "geometry": {"coordinates":[-122.628737,45.444181],"type":"Point"}
}