{
  "type": "Feature",
  "properties": {
    "iso:country":"US",
    "sg:address":"1340 9th St",
    "sg:city":"Florence",
    "sg:classifiers":[
        {
            "category":"Real Estate",
            "subcategory":"Real Estate Operator",
            "type":"Services"
        }
    ],
    "sg:phone":"+1 541 997 6479",
    "sg:postcode":"97439",
    "sg:province":"OR",
    "sg:tags":[
        "apartment"
    ],
    "wof:name":"Sunset Apartments Of Oregon",
    "wof:placetype":"venue"
},
  "geometry": {"coordinates":[-124.106517,43.974583],"type":"Point"}
}