{
  "type": "Feature",
  "properties": {
    "addr:full":"430 SW 13th St Portland OR 97205",
    "addr:housenumber":"430",
    "addr:postcode":"97205",
    "addr:street":"Sw 13Th St",
    "iso:country":"US",
    "sg:address":"430 SW 13th St",
    "sg:city":"Portland",
    "sg:classifiers":[
        {
            "category":"Travel",
            "subcategory":"Hotels & Motels",
            "type":"Entertainment"
        },
        {
            "category":"Real Estate",
            "subcategory":"Real Estate Operator",
            "type":"Services"
        }
    ],
    "sg:phone":"+1 503 546 1286",
    "sg:postcode":"97205",
    "sg:province":"OR",
    "sg:tags":[
        "apartment"
    ],
    "sg:website":"www.indigo12west.com/",
    "wof:name":"The Indigo - 12 West",
    "wof:placetype":"venue"
},
  "geometry": {"coordinates":[-122.684155,45.522405],"type":"Point"}
}