{
  "type": "Feature",
  "properties": {
    "iso:country":"US",
    "sg:address":"18009 SE Brooklyn St",
    "sg:city":"Portland",
    "sg:classifiers":[
        {
            "category":"Education",
            "subcategory":"School",
            "type":"Public Place"
        }
    ],
    "sg:phone":"+1 503 762 3200",
    "sg:postcode":"97236",
    "sg:province":"OR",
    "sg:tags":[
        "elementary"
    ],
    "wof:name":"Lynch Meadows Elementary School",
    "wof:placetype":"venue"
},
  "geometry": {"coordinates":[-122.477958,45.501083],"type":"Point"}
}