{
  "type": "Feature",
  "properties": {
    "iso:country":"US",
    "sg:address":"16080 Cattle Dr",
    "sg:city":"Sisters",
    "sg:classifiers":[
        {
            "category":"Building & Trades",
            "subcategory":"Construction",
            "type":"Services"
        }
    ],
    "sg:phone":"+1 541 549 9764",
    "sg:postcode":"97759",
    "sg:province":"OR",
    "sg:tags":[
        "house"
    ],
    "wof:name":"John P Pierce General Contg",
    "wof:placetype":"venue"
},
  "geometry": {"coordinates":[-121.52664900000001,44.322116],"type":"Point"}
}