{
  "type": "Feature",
  "properties": {
    "iso:country":"US",
    "sg:address":"708 Main St",
    "sg:city":"Oregon City",
    "sg:classifiers":[
        {
            "category":"Government",
            "subcategory":"Office",
            "type":"Public Place"
        }
    ],
    "sg:phone":"+1 503 655 8616",
    "sg:postcode":"97045",
    "sg:province":"OR",
    "wof:name":"Clackamas Victims' Assistance",
    "wof:placetype":"venue"
},
  "geometry": {"coordinates":[-122.60795,45.35798],"type":"Point"}
}