{
  "type": "Feature",
  "properties": {
    "iso:country":"US",
    "sg:address":"22821 Boones Ferry Rd NE",
    "sg:city":"Aurora",
    "sg:classifiers":[
        {
            "category":"Building & Trades",
            "subcategory":"Landscaping Services",
            "type":"Services"
        }
    ],
    "sg:phone":"+1 503 678 7990",
    "sg:postcode":"97002",
    "sg:province":"OR",
    "sg:tags":[
        "landscape",
        "contractor"
    ],
    "sg:website":"www.crownlandscape.com",
    "wof:name":"Erosion Control Northwest Inc",
    "wof:placetype":"venue"
},
  "geometry": {"coordinates":[-122.77458300000001,45.250458],"type":"Point"}
}