{
  "type": "Feature",
  "properties": {
    "addr:full":"7314 N Leavitt Ave Portland OR 97203",
    "addr:housenumber":"7314",
    "addr:postcode":"97203",
    "addr:street":"N Leavitt Ave",
    "iso:country":"US",
    "sg:address":"7314 N Leavitt Ave",
    "sg:city":"Portland",
    "sg:classifiers":[
        {
            "category":"Personal",
            "subcategory":"Beauty Salon",
            "type":"Services"
        }
    ],
    "sg:phone":"+1 503 289 2755",
    "sg:postcode":"97203",
    "sg:province":"OR",
    "sg:tags":[
        "tanning"
    ],
    "wof:name":"Bahama Mama's",
    "wof:placetype":"venue"
},
  "geometry": {"coordinates":[-122.754183,45.589342],"type":"Point"}
}