{
  "type": "Feature",
  "properties": {
    "addr:full":"7201 NE Glisan St Ste A Portland OR 97213",
    "addr:housenumber":"7201",
    "addr:postcode":"97213",
    "addr:street":"Ne Glisan St Ste A",
    "iso:country":"US",
    "sg:address":"7201 NE Glisan St Ste A",
    "sg:city":"Portland",
    "sg:classifiers":[
        {
            "category":"Professional",
            "subcategory":"Employment Agencies",
            "type":"Services"
        }
    ],
    "sg:phone":"+1 503 239 6038",
    "sg:postcode":"97213",
    "sg:province":"OR",
    "wof:name":"Integration & Independence",
    "wof:placetype":"venue"
},
  "geometry": {"coordinates":[-122.588353,45.526686],"type":"Point"}
}