{
  "type": "Feature",
  "properties": {
    "iso:country":"US",
    "sg:address":"31461 NE Bell Rd",
    "sg:city":"Sherwood",
    "sg:classifiers":[
        {
            "category":"Shopping",
            "subcategory":"Gifts & Souvenirs",
            "type":"Retail Goods"
        }
    ],
    "sg:phone":"+1 503 554 9060",
    "sg:postcode":"97140",
    "sg:province":"OR",
    "wof:name":"Your Northwest Inc",
    "wof:placetype":"venue"
},
  "geometry": {"coordinates":[-122.918296,45.331897],"type":"Point"}
}