{
  "type": "Feature",
  "properties": {
    "addr:full":"1328 NW Kings Blvd Corvallis OR 97330",
    "addr:housenumber":"1328",
    "addr:postcode":"97330",
    "addr:street":"Nw Kings Blvd",
    "iso:country":"US",
    "sg:address":"1328 NW Kings Blvd",
    "sg:city":"Corvallis",
    "sg:classifiers":[
        {
            "category":"Wholesale",
            "subcategory":"Electrical",
            "type":"Manufacturing & Wholesale Goods"
        }
    ],
    "sg:phone":"+1 541 758 9341",
    "sg:postcode":"97330",
    "sg:province":"OR",
    "wof:name":"S Kincaid Digital Audio",
    "wof:placetype":"venue"
},
  "geometry": {"coordinates":[-123.276031,44.580214],"type":"Point"}
}