{
  "type": "Feature",
  "properties": {
    "addr:full":"3804 NE 148th Avenue Portland OR 97230",
    "addr:housenumber":"3804",
    "addr:postcode":"97230",
    "addr:street":"Ne 148Th Avenue",
    "iso:country":"US",
    "sg:address":"3804 NE 148th Avenue",
    "sg:city":"Portland",
    "sg:classifiers":[
        {
            "category":"Home & Garden",
            "subcategory":"Garden Supply",
            "type":"Retail Goods"
        }
    ],
    "sg:phone":"+1 503 253 0033",
    "sg:postcode":"97230",
    "sg:province":"OR",
    "sg:tags":[
        "nursery",
        "gardening"
    ],
    "wof:name":"Grow West",
    "wof:placetype":"venue"
},
  "geometry": {"coordinates":[-122.510143,45.552491],"type":"Point"}
}