{
  "type": "Feature",
  "properties": {
    "iso:country":"US",
    "sg:address":"2428 W Harvard Ave",
    "sg:city":"Roseburg",
    "sg:classifiers":[
        {
            "category":"Retail",
            "subcategory":"Repair Shop",
            "type":"Services"
        }
    ],
    "sg:phone":"+1 541 957 3727",
    "sg:postcode":"97470",
    "sg:province":"OR",
    "sg:tags":[
        "laundry",
        "coin",
        "electrical"
    ],
    "wof:name":"Roseburg Laundromat",
    "wof:placetype":"venue"
},
  "geometry": {"coordinates":[-123.37986100000001,43.214172],"type":"Point"}
}