{
  "type": "Feature",
  "properties": {
    "iso:country":"US",
    "sg:address":"2064 E Main St",
    "sg:city":"Hillsboro",
    "sg:classifiers":[
        {
            "category":"Professional",
            "type":"Services"
        }
    ],
    "sg:phone":"+1 503 648 0289",
    "sg:postcode":"97123",
    "sg:province":"OR",
    "wof:name":"Candice L Snell",
    "wof:placetype":"venue"
},
  "geometry": {"coordinates":[-122.96017000000001,45.52112],"type":"Point"}
}