{
  "type": "Feature",
  "properties": {
    "addr:full":"5829 Jean Rd Lake Oswego OR 97035",
    "addr:housenumber":"5829",
    "addr:postcode":"97035",
    "addr:street":"Jean Rd",
    "iso:country":"US",
    "sg:address":"5829 Jean Rd",
    "sg:city":"Lake Oswego",
    "sg:classifiers":[
        {
            "category":"Shopping",
            "subcategory":"Clothing, Apparel, & Fashions",
            "type":"Retail Goods"
        }
    ],
    "sg:phone":"+1 503 635 6856",
    "sg:postcode":"97035",
    "sg:province":"OR",
    "sg:tags":[
        "item",
        "boutique"
    ],
    "wof:name":"Lucy Palmer Btq Corporate Gift",
    "wof:placetype":"venue"
},
  "geometry": {"coordinates":[-122.736754,45.397127],"type":"Point"}
}