{
  "type": "Feature",
  "properties": {
    "iso:country":"US",
    "sg:address":"37783 Alexander Rd",
    "sg:city":"Philomath",
    "sg:classifiers":[
        {
            "category":"Organizations",
            "subcategory":"Religious Organization",
            "type":"Services"
        }
    ],
    "sg:phone":"+1 541 487 4091",
    "sg:postcode":"97370",
    "sg:province":"OR",
    "wof:name":"Alsea Bible Fellowship",
    "wof:placetype":"venue"
},
  "geometry": {"coordinates":[-123.454476,44.665685],"type":"Point"}
}