{
  "type": "Feature",
  "properties": {
    "iso:country":"US",
    "sg:address":"631 S Canyon Blvd",
    "sg:city":"John Day",
    "sg:classifiers":[
        {
            "category":"Retail",
            "subcategory":"Auto Repair",
            "type":"Services"
        }
    ],
    "sg:phone":"+1 541 575 5823",
    "sg:postcode":"97845",
    "sg:province":"OR",
    "sg:tags":[
        "repairing",
        "automobile",
        "general"
    ],
    "wof:name":"Clayton's Auto Repair",
    "wof:placetype":"venue"
},
  "geometry": {"coordinates":[-118.951285,44.409001],"type":"Point"}
}