{
  "type": "Feature",
  "properties": {
    "addr:full":"2186 Quail Run Ave Stayton OR 97383",
    "addr:housenumber":"2186",
    "addr:postcode":"97383",
    "addr:street":"Quail Run Ave",
    "iso:country":"US",
    "sg:address":"2186 Quail Run Ave",
    "sg:city":"Stayton",
    "sg:classifiers":[
        {
            "category":"Manufacturing",
            "subcategory":"Motor Vehicles & Parts",
            "type":"Manufacturing & Wholesale Goods"
        }
    ],
    "sg:phone":"+1 503 767 8851",
    "sg:postcode":"97383",
    "sg:province":"OR",
    "sg:tags":[
        "equipment",
        "transportation",
        "mfg"
    ],
    "wof:name":"Atv Addictions",
    "wof:placetype":"venue"
},
  "geometry": {"coordinates":[-122.812915,44.812053],"type":"Point"}
}