{
  "type": "Feature",
  "properties": {
    "addr:full":"1101 Hull St Hood River OR 97031",
    "addr:housenumber":"1101",
    "addr:postcode":"97031",
    "addr:street":"Hull St",
    "iso:country":"US",
    "sg:address":"1101 Hull St",
    "sg:city":"Hood River",
    "sg:classifiers":[
        {
            "category":"Retail",
            "subcategory":"Animal Services",
            "type":"Services"
        }
    ],
    "sg:phone":"+1 541 308 0688",
    "sg:postcode":"97031",
    "sg:province":"OR",
    "sg:tags":[
        "pet",
        "grooming",
        "washing"
    ],
    "wof:name":"Top Dog Grooming",
    "wof:placetype":"venue"
},
  "geometry": {"coordinates":[-121.522143,45.701111],"type":"Point"}
}