{
  "type": "Feature",
  "properties": {
    "addr:full":"6890 SE Bixel Way Portland OR 97267",
    "addr:housenumber":"6890",
    "addr:postcode":"97267",
    "addr:street":"Se Bixel Way",
    "iso:country":"US",
    "sg:address":"6890 SE Bixel Way",
    "sg:city":"Portland",
    "sg:classifiers":[
        {
            "category":"Restaurant",
            "type":"Food & Drink"
        }
    ],
    "sg:phone":"+1 503 654 8117",
    "sg:postcode":"97267",
    "sg:province":"OR",
    "sg:tags":[
        "eating"
    ],
    "wof:name":"Grandma Chars Bed & Breakfast",
    "wof:placetype":"venue"
},
  "geometry": {"coordinates":[-122.592383,45.409397],"type":"Point"}
}