{
  "type": "Feature",
  "properties": {
    "iso:country":"US",
    "sg:address":"28610 SE Eagle Creek Rd",
    "sg:city":"Estacada",
    "sg:classifiers":[
        {
            "category":"Wholesale",
            "subcategory":"Non-durable Goods",
            "type":"Manufacturing & Wholesale Goods"
        }
    ],
    "sg:phone":"+1 503 630 3631",
    "sg:postcode":"97023",
    "sg:province":"OR",
    "sg:tags":[
        "advertising"
    ],
    "wof:name":"Media Marketing Of Oregon",
    "wof:placetype":"venue"
},
  "geometry": {"coordinates":[-122.343138,45.316312],"type":"Point"}
}