{
  "type": "Feature",
  "properties": {
    "iso:country":"US",
    "sg:address":"1150 Ort Ln",
    "sg:city":"Merlin",
    "sg:classifiers":[
        {
            "category":"Manufacturing",
            "subcategory":"Lumber",
            "type":"Manufacturing & Wholesale Goods"
        }
    ],
    "sg:phone":"+1 541 476 0033",
    "sg:postcode":"97526",
    "sg:province":"OR",
    "sg:tags":[
        "forester"
    ],
    "wof:name":"Grayback Forestry Inc",
    "wof:placetype":"venue"
},
  "geometry": {"coordinates":[-123.406954,42.508068],"type":"Point"}
}