{
  "type": "Feature",
  "properties": {
    "iso:country":"US",
    "sg:address":"3033 NW Yeon Ave",
    "sg:city":"Portland",
    "sg:classifiers":[
        {
            "category":"Manufacturing",
            "subcategory":"Printing",
            "type":"Manufacturing & Wholesale Goods"
        }
    ],
    "sg:phone":"+1 503 223 2035",
    "sg:postcode":"97210",
    "sg:province":"OR",
    "sg:tags":[
        "bookbinder"
    ],
    "sg:website":"www.lincolnandallen.com",
    "wof:name":"Lincoln & Allen Co",
    "wof:placetype":"venue"
},
  "geometry": {"coordinates":[-122.701717,45.542944],"type":"Point"}
}