{
  "type": "Feature",
  "properties": {
    "iso:country":"US",
    "sg:address":"1303 Front St",
    "sg:city":"Tillamook",
    "sg:classifiers":[
        {
            "category":"Wholesale",
            "subcategory":"Machinery & Supplies",
            "type":"Manufacturing & Wholesale Goods"
        }
    ],
    "sg:phone":"+1 503 842 5300",
    "sg:postcode":"97141",
    "sg:province":"OR",
    "sg:tags":[
        "equipment"
    ],
    "wof:name":"North Coast Door Co",
    "wof:placetype":"venue"
},
  "geometry": {"coordinates":[-123.850291,45.458492],"type":"Point"}
}