{
  "type": "Feature",
  "properties": {
    "iso:country":"US",
    "sg:address":"4600 NE Cornell Rd",
    "sg:city":"Lake Oswego",
    "sg:classifiers":[
        {
            "category":"Social Services",
            "subcategory":"Child Care",
            "type":"Services"
        },
        {
            "category":"Education",
            "subcategory":"Preschool",
            "type":"Public Place"
        },
        {
            "category":"Education",
            "subcategory":"School",
            "type":"Public Place"
        }
    ],
    "sg:phone":"+1 503 648 2443",
    "sg:postcode":"97034",
    "sg:province":"OR",
    "sg:tags":[
        "elementary",
        "day"
    ],
    "sg:website":"www.kindercare.com",
    "wof:name":"Kindercare Learning Centers",
    "wof:placetype":"venue"
},
  "geometry": {"coordinates":[-122.67800099999999,45.407501],"type":"Point"}
}