{
  "type": "Feature",
  "properties": {
    "iso:country":"US",
    "sg:address":"925 Sundance St",
    "sg:city":"Eugene",
    "sg:classifiers":[
        {
            "category":"Professional",
            "subcategory":"Business Services",
            "type":"Services"
        }
    ],
    "sg:phone":"+1 541 484 1568",
    "sg:postcode":"97405",
    "sg:province":"OR",
    "wof:name":"Jag Group",
    "wof:placetype":"venue"
},
  "geometry": {"coordinates":[-123.107506,44.012268],"type":"Point"}
}