{
  "type": "Feature",
  "properties": {
    "addr:full":"1803 NW Candler Ave Grants Pass OR 97526",
    "addr:housenumber":"1803",
    "addr:postcode":"97526",
    "addr:street":"Nw Candler Ave",
    "iso:country":"US",
    "sg:address":"1803 NW Candler Ave",
    "sg:city":"Grants Pass",
    "sg:classifiers":[
        {
            "category":"Social Services",
            "subcategory":"Child Care",
            "type":"Services"
        }
    ],
    "sg:phone":"+1 541 479 6205",
    "sg:postcode":"97526",
    "sg:province":"OR",
    "sg:tags":[
        "day"
    ],
    "wof:name":"Honey Tree",
    "wof:placetype":"venue"
},
  "geometry": {"coordinates":[-123.336907,42.458703],"type":"Point"}
}