{
  "type": "Feature",
  "properties": {
    "iso:country":"US",
    "sg:address":"550 E Arlington St",
    "sg:city":"Gladstone",
    "sg:classifiers":[
        {
            "category":"Organizations",
            "subcategory":"Religious Organization",
            "type":"Services"
        }
    ],
    "sg:phone":"+1 503 656 5076",
    "sg:postcode":"97027",
    "sg:province":"OR",
    "wof:name":"Catholic Daughters of America",
    "wof:placetype":"venue"
},
  "geometry": {"coordinates":[-122.585751,45.38083],"type":"Point"}
}