{
  "type": "Feature",
  "properties": {
    "addr:full":"3716 Oregon Ave Springfield OR 97478",
    "addr:housenumber":"3716",
    "addr:postcode":"97478",
    "addr:street":"Oregon Ave",
    "iso:country":"US",
    "sg:address":"3716 Oregon Ave",
    "sg:city":"Springfield",
    "sg:classifiers":[
        {
            "category":"Social Services",
            "type":"Services"
        }
    ],
    "sg:phone":"+1 541 744 5542",
    "sg:postcode":"97478",
    "sg:province":"OR",
    "wof:name":"Grace B Almeieda",
    "wof:placetype":"venue"
},
  "geometry": {"coordinates":[-122.97327199999999,44.043795],"type":"Point"}
}