{
  "type": "Feature",
  "properties": {
    "iso:country":"US",
    "sg:address":"308 E 3rd St",
    "sg:city":"The Dalles",
    "sg:classifiers":[
        {
            "category":"Banks & Credit Unions",
            "subcategory":"Investment Brokerage",
            "type":"Services"
        },
        {
            "category":"Insurance",
            "subcategory":"Insurance Agent",
            "type":"Services"
        }
    ],
    "sg:phone":"+1 541 296 6669",
    "sg:postcode":"97058",
    "sg:province":"OR",
    "sg:tags":[
        "consultant",
        "planning",
        "financial"
    ],
    "sg:website":"www.vonborstel.net",
    "wof:name":"Von Borstel & Associates",
    "wof:placetype":"venue"
},
  "geometry": {"coordinates":[-121.18252200000001,45.600552],"type":"Point"}
}