{
  "type": "Feature",
  "properties": {
    "iso:country":"US",
    "sg:address":"7100 SW Hampton St",
    "sg:city":"Tigard",
    "sg:classifiers":[
        {
            "category":"Professional",
            "subcategory":"Computer Services",
            "type":"Services"
        }
    ],
    "sg:phone":"+1 503 624 0554",
    "sg:postcode":"97223",
    "sg:province":"OR",
    "sg:tags":[
        "processing",
        "datum"
    ],
    "wof:name":"Information Management Inc",
    "wof:placetype":"venue"
},
  "geometry": {"coordinates":[-122.750445,45.42755],"type":"Point"}
}