{
  "type": "Feature",
  "properties": {
    "iso:country":"US",
    "sg:address":"38097 Hwy 97 N",
    "sg:city":"Chiloquin",
    "sg:classifiers":[
        {
            "category":"Real Estate",
            "subcategory":"Real Estate Agent",
            "type":"Services"
        }
    ],
    "sg:phone":"+1 541 783 2019",
    "sg:postcode":"97624",
    "sg:province":"OR",
    "wof:name":"Winema Real Estate",
    "wof:placetype":"venue"
},
  "geometry": {"coordinates":[-121.883159,42.561747],"type":"Point"}
}