{
  "type": "Feature",
  "properties": {
    "iso:country":"US",
    "sg:address":"1920 Resort St",
    "sg:city":"Baker City",
    "sg:classifiers":[
        {
            "category":"Shopping",
            "subcategory":"Pharmacy",
            "type":"Retail Goods"
        }
    ],
    "sg:phone":"+1 541 523 7227",
    "sg:postcode":"97814",
    "sg:province":"OR",
    "wof:name":"Bakers Pill Box",
    "wof:placetype":"venue"
},
  "geometry": {"coordinates":[-117.82893900000001,44.776935],"type":"Point"}
}