{
  "type": "Feature",
  "properties": {
    "iso:country":"US",
    "sg:address":"105 W Main St",
    "sg:city":"Carlton",
    "sg:classifiers":[
        {
            "category":"Food & Beverages",
            "subcategory":"Liquor & Beverages",
            "type":"Retail Goods"
        }
    ],
    "sg:phone":"+1 503 852 6733",
    "sg:postcode":"97111",
    "sg:province":"OR",
    "sg:tags":[
        "beer",
        "spirit",
        "wine"
    ],
    "wof:name":"Tasting Room In Carlton",
    "wof:placetype":"venue"
},
  "geometry": {"coordinates":[-123.22199999999999,45.290798],"type":"Point"}
}