{
  "type": "Feature",
  "properties": {
    "addr:full":"33304 SE Lusted Rd Gresham OR 97080",
    "addr:postcode":"33304;97080",
    "addr:street":"Se Lusted Rd",
    "iso:country":"US",
    "sg:address":"33304 SE Lusted Rd",
    "sg:city":"Gresham",
    "sg:classifiers":[
        {
            "category":"Wholesale",
            "subcategory":"Plants",
            "type":"Manufacturing & Wholesale Goods"
        }
    ],
    "sg:phone":"+1 503 663 3019",
    "sg:postcode":"97080",
    "sg:province":"OR",
    "sg:tags":[
        "supply"
    ],
    "wof:name":"Old Home Place Nursery The",
    "wof:placetype":"venue"
},
  "geometry": {"coordinates":[-122.32120399999999,45.475914],"type":"Point"}
}