{
  "type": "Feature",
  "properties": {
    "addr:full":"24076 SE Stark St Suite 100 Gresham OR 97080",
    "addr:postcode":"24076;97080",
    "addr:street":"Se Stark St Suite 100",
    "iso:country":"US",
    "sg:address":"24076 SE Stark St Suite 100",
    "sg:city":"Gresham",
    "sg:classifiers":[
        {
            "category":"Shopping",
            "subcategory":"Pharmacy",
            "type":"Retail Goods"
        }
    ],
    "sg:phone":"+1 503 491 0117",
    "sg:postcode":"97080",
    "sg:province":"OR",
    "sg:tags":[
        "drugstore"
    ],
    "sg:website":"www.mygnp.com",
    "wof:name":"Gresham Professional Pharmacy",
    "wof:placetype":"venue"
},
  "geometry": {"coordinates":[-122.414659,45.519097],"type":"Point"}
}