{
  "type": "Feature",
  "properties": {
    "iso:country":"US",
    "sg:address":"1220 SW Morrison St",
    "sg:city":"Portland",
    "sg:classifiers":[
        {
            "category":"Insurance",
            "subcategory":"Insurance Agent",
            "type":"Services"
        }
    ],
    "sg:phone":"+1 503 226 1422",
    "sg:postcode":"97205",
    "sg:province":"OR",
    "sg:tags":[
        "agency"
    ],
    "sg:website":"www.keelson.com",
    "wof:name":"Keelson Partners Inc",
    "wof:placetype":"venue"
},
  "geometry": {"coordinates":[-122.685076,45.520707],"type":"Point"}
}