{
  "type": "Feature",
  "properties": {
    "addr:full":"3508 Williams St Portland OR 97227",
    "addr:housenumber":"3508",
    "addr:postcode":"97227",
    "addr:street":"Williams St",
    "iso:country":"US",
    "sg:address":"3508 Williams St",
    "sg:city":"Portland",
    "sg:classifiers":[
        {
            "category":"Food & Beverages",
            "subcategory":"Groceries & Convenience Stores",
            "type":"Retail Goods"
        }
    ],
    "sg:postcode":"97227",
    "sg:province":"OR",
    "wof:name":"Williams Street Market",
    "wof:placetype":"venue"
},
  "geometry": {"coordinates":[-122.666494,45.54856],"type":"Point"}
}