{
  "type": "Feature",
  "properties": {
    "addr:full":"1613 NW Jolie Pl Portland OR 97229",
    "addr:housenumber":"1613",
    "addr:postcode":"97229",
    "addr:street":"Nw Jolie Pl",
    "iso:country":"US",
    "sg:address":"1613 NW Jolie Pl",
    "sg:city":"Portland",
    "sg:classifiers":[
        {
            "category":"Professional",
            "subcategory":"Management & Consulting",
            "type":"Services"
        }
    ],
    "sg:phone":"+1 971 570 6917",
    "sg:postcode":"97229",
    "sg:province":"OR",
    "sg:tags":[
        "environmental",
        "engineering"
    ],
    "wof:name":"Scott Wells",
    "wof:placetype":"venue"
},
  "geometry": {"coordinates":[-122.789751,45.531068],"type":"Point"}
}