{
  "type": "Feature",
  "properties": {
    "iso:country":"US",
    "sg:address":"2092 NW Aloclek Dr",
    "sg:city":"Hillsboro",
    "sg:classifiers":[
        {
            "category":"Wholesale",
            "subcategory":"Metals & Minerals",
            "type":"Manufacturing & Wholesale Goods"
        }
    ],
    "sg:phone":"+1 503 614 2826",
    "sg:postcode":"97124",
    "sg:province":"OR",
    "sg:tags":[
        "steel",
        "warehouse"
    ],
    "wof:name":"Nw Metal Deck Inc",
    "wof:placetype":"venue"
},
  "geometry": {"coordinates":[-122.896458,45.534695],"type":"Point"}
}