{
  "type": "Feature",
  "properties": {
    "iso:country":"US",
    "sg:address":"1001 N Schmeer Road",
    "sg:city":"Portland",
    "sg:classifiers":[
        {
            "category":"Arena",
            "subcategory":"Stadium",
            "type":"Entertainment"
        }
    ],
    "sg:phone":"+1 503 737 1000",
    "sg:postcode":"97217",
    "sg:province":"OR",
    "sg:website":"www.portlandmeadows.com/",
    "wof:name":"Portland Meadows Race Track",
    "wof:placetype":"venue"
},
  "geometry": {"coordinates":[-122.67447900000001,45.589926],"type":"Point"}
}