{
  "type": "Feature",
  "properties": {
    "addr:full":"5925 SW Spruce Ave Beaverton OR 97005",
    "addr:housenumber":"5925",
    "addr:postcode":"97005",
    "addr:street":"Sw Spruce Ave",
    "iso:country":"US",
    "sg:address":"5925 SW Spruce Ave",
    "sg:city":"Beaverton",
    "sg:classifiers":[
        {
            "category":"Real Estate",
            "subcategory":"Real Estate Operator",
            "type":"Services"
        }
    ],
    "sg:phone":"+1 503 292 2499",
    "sg:postcode":"97005",
    "sg:province":"OR",
    "sg:tags":[
        "building",
        "nonresidential"
    ],
    "wof:name":"Bly Properties LLC",
    "wof:placetype":"venue"
},
  "geometry": {"coordinates":[-122.772666,45.477391],"type":"Point"}
}