{
  "type": "Feature",
  "properties": {
    "iso:country":"US",
    "sg:address":"12470 SW 1st St",
    "sg:city":"Beaverton",
    "sg:classifiers":[
        {
            "category":"Education",
            "subcategory":"Special Training",
            "type":"Public Place"
        }
    ],
    "sg:phone":"+1 503 350 0202",
    "sg:postcode":"97005",
    "sg:province":"OR",
    "wof:name":"JC Driving School",
    "wof:placetype":"venue"
},
  "geometry": {"coordinates":[-122.80461699999999,45.486162],"type":"Point"}
}