{
  "type": "Feature",
  "properties": {
    "addr:full":"12719 NE Whitaker Way Portland OR 97230",
    "addr:housenumber":"12719",
    "addr:postcode":"97230",
    "addr:street":"Ne Whitaker Way",
    "iso:country":"US",
    "sg:address":"12719 NE Whitaker Way",
    "sg:city":"Portland",
    "sg:classifiers":[
        {
            "category":"Manufacturing",
            "subcategory":"Furniture",
            "type":"Manufacturing & Wholesale Goods"
        }
    ],
    "sg:phone":"+1 503 253 8130",
    "sg:postcode":"97230",
    "sg:province":"OR",
    "sg:tags":[
        "wooden",
        "mfg"
    ],
    "sg:website":"www.rosemontdesigngroup.com",
    "wof:name":"Rosemont Design Group",
    "wof:placetype":"venue"
},
  "geometry": {"coordinates":[-122.533264,45.561486],"type":"Point"}
}