{
  "type": "Feature",
  "properties": {
    "iso:country":"US",
    "sg:address":"3201 NE Wynooski Rd",
    "sg:city":"Newberg",
    "sg:classifiers":[
        {
            "category":"Utilities",
            "subcategory":"Telephone",
            "type":"Services"
        },
        {
            "category":"Professional",
            "subcategory":"Business Services",
            "type":"Services"
        }
    ],
    "sg:phone":"+1 503 554 9492",
    "sg:postcode":"97132",
    "sg:province":"OR",
    "sg:tags":[
        "messaging",
        "voice",
        "telecommunication",
        "equipment"
    ],
    "wof:name":"Telephone Company of Oregon",
    "wof:placetype":"venue"
},
  "geometry": {"coordinates":[-122.94638399999999,45.286201],"type":"Point"}
}