{
  "type": "Feature",
  "properties": {
    "addr:full":"21420 S Upper Highland Rd Beavercreek OR 97004",
    "addr:housenumber":"21420",
    "addr:postcode":"97004",
    "addr:street":"S Upper Highland Rd",
    "iso:country":"US",
    "sg:address":"21420 S Upper Highland Rd",
    "sg:city":"Beavercreek",
    "sg:classifiers":[
        {
            "category":"Shopping",
            "subcategory":"Bicycles & Sporting Goods",
            "type":"Retail Goods"
        }
    ],
    "sg:phone":"+1 503 632 7365",
    "sg:postcode":"97004",
    "sg:province":"OR",
    "wof:name":"Costom Bows By Wes Wallace",
    "wof:placetype":"venue"
},
  "geometry": {"coordinates":[-122.42057200000001,45.247948],"type":"Point"}
}