{
  "type": "Feature",
  "properties": {
    "iso:country":"US",
    "sg:address":"1121 SW Salmon St Ste 400",
    "sg:city":"Portland",
    "sg:classifiers":[
        {
            "category":"Professional",
            "subcategory":"Art Services",
            "type":"Services"
        }
    ],
    "sg:phone":"+1 503 228 8476",
    "sg:postcode":"97205",
    "sg:province":"OR",
    "sg:tags":[
        "agent",
        "artist"
    ],
    "wof:name":"Fountain Assoc Inc",
    "wof:placetype":"venue"
},
  "geometry": {"coordinates":[-122.684399,45.518344],"type":"Point"}
}