{
  "type": "Feature",
  "properties": {
    "iso:country":"US",
    "sg:address":"3625 NE Canterbury Cir",
    "sg:city":"Corvallis",
    "sg:classifiers":[
        {
            "category":"Manufacturing",
            "subcategory":"Toys & Sporting Goods",
            "type":"Manufacturing & Wholesale Goods"
        }
    ],
    "sg:phone":"+1 541 753 9352",
    "sg:postcode":"97330",
    "sg:province":"OR",
    "wof:name":"Heartfelt Toys",
    "wof:placetype":"venue"
},
  "geometry": {"coordinates":[-123.24021399999999,44.600904],"type":"Point"}
}