{
  "type": "Feature",
  "properties": {
    "iso:country":"US",
    "sg:address":"605 Pompadour Dr",
    "sg:city":"Ashland",
    "sg:classifiers":[
        {
            "category":"Professional",
            "subcategory":"Computer Services",
            "type":"Services"
        }
    ],
    "sg:phone":"+1 541 488 5493",
    "sg:postcode":"97520",
    "sg:province":"OR",
    "sg:tags":[
        "writes",
        "dental",
        "for",
        "software"
    ],
    "wof:name":"Three Star Dental Systems",
    "wof:placetype":"venue"
},
  "geometry": {"coordinates":[-122.665768,42.210285],"type":"Point"}
}