{
  "type": "Feature",
  "properties": {
    "iso:country":"US",
    "sg:address":"7913 SW Nimbus Ave",
    "sg:city":"Beaverton",
    "sg:classifiers":[
        {
            "category":"Building & Trades",
            "subcategory":"Pest Control",
            "type":"Services"
        }
    ],
    "sg:phone":"+1 503 350 1440",
    "sg:postcode":"97008",
    "sg:province":"OR",
    "sg:tags":[
        "mothproofing"
    ],
    "wof:name":"Moles Nevermore",
    "wof:placetype":"venue"
},
  "geometry": {"coordinates":[-122.788552,45.462471],"type":"Point"}
}