{
  "type": "Feature",
  "properties": {
    "iso:country":"US",
    "sg:address":"164 NW 3rd Ave",
    "sg:city":"Canby",
    "sg:classifiers":[
        {
            "category":"Wholesale",
            "subcategory":"Construction Materials",
            "type":"Manufacturing & Wholesale Goods"
        }
    ],
    "sg:phone":"+1 503 266 8416",
    "sg:postcode":"97013",
    "sg:province":"OR",
    "sg:tags":[
        "lumber"
    ],
    "wof:name":"West Shore Forest Products",
    "wof:placetype":"venue"
},
  "geometry": {"coordinates":[-122.694548,45.26418],"type":"Point"}
}