{
  "type": "Feature",
  "properties": {
    "iso:country":"US",
    "sg:address":"3005 Cummings Ln",
    "sg:city":"Medford",
    "sg:classifiers":[
        {
            "category":"Real Estate",
            "subcategory":"Real Estate Operator",
            "type":"Services"
        }
    ],
    "sg:phone":"+1 541 776 8704",
    "sg:postcode":"97501",
    "sg:province":"OR",
    "sg:tags":[
        "apartment"
    ],
    "wof:name":"Lilac Meadow",
    "wof:placetype":"venue"
},
  "geometry": {"coordinates":[-122.882316,42.35844],"type":"Point"}
}