{
  "type": "Feature",
  "properties": {
    "iso:country":"US",
    "sg:address":"10504 Mount Angel Gervais Rd NE",
    "sg:city":"Gervais",
    "sg:classifiers":[
        {
            "category":"Farming",
            "subcategory":"Livestock Farm",
            "type":"Manufacturing & Wholesale Goods"
        }
    ],
    "sg:phone":"+1 503 792 4419",
    "sg:postcode":"97026",
    "sg:province":"OR",
    "sg:tags":[
        "general"
    ],
    "wof:name":"G & C Ranch Inc",
    "wof:placetype":"venue"
},
  "geometry": {"coordinates":[-122.845958,45.090944],"type":"Point"}
}