{
  "type": "Feature",
  "properties": {
    "iso:country":"US",
    "sg:address":"2905 NE Broadway St",
    "sg:city":"Portland",
    "sg:classifiers":[
        {
            "category":"Banks & Credit Unions",
            "subcategory":"Investment Brokerage",
            "type":"Services"
        }
    ],
    "sg:phone":"+1 503 595 0070",
    "sg:postcode":"97232",
    "sg:province":"OR",
    "sg:tags":[
        "consultant",
        "planning",
        "financial"
    ],
    "wof:name":"American Express Financial Adv",
    "wof:placetype":"venue"
},
  "geometry": {"coordinates":[-122.635623,45.535236],"type":"Point"}
}