{
  "type": "Feature",
  "properties": {
    "iso:country":"US",
    "sg:address":"906 Winchester Ave",
    "sg:city":"Reedsport",
    "sg:classifiers":[
        {
            "category":"Freight",
            "type":"Transportation"
        }
    ],
    "sg:phone":"+1 541 271 1724",
    "sg:postcode":"97467",
    "sg:province":"OR",
    "sg:tags":[
        "commercial",
        "storage"
    ],
    "wof:name":"Winchester Ave Mini Storage",
    "wof:placetype":"venue"
},
  "geometry": {"coordinates":[-124.103309,43.699808],"type":"Point"}
}