{
  "type": "Feature",
  "properties": {
    "iso:country":"US",
    "sg:address":"109 W 6th Ave",
    "sg:city":"Eugene",
    "sg:classifiers":[
        {
            "category":"Personal",
            "subcategory":"Beauty Salon",
            "type":"Services"
        }
    ],
    "sg:phone":"+1 541 344 6459",
    "sg:postcode":"97401",
    "sg:province":"OR",
    "wof:name":"Lux Studio",
    "wof:placetype":"venue"
},
  "geometry": {"coordinates":[-123.094926,44.053314],"type":"Point"}
}