{
  "type": "Feature",
  "properties": {
    "iso:country":"US",
    "sg:address":"1120 NW 14th Ave",
    "sg:city":"Portland",
    "sg:classifiers":[
        {
            "category":"Wholesale",
            "subcategory":"Home Furnishings",
            "type":"Manufacturing & Wholesale Goods"
        }
    ],
    "sg:phone":"+1 866 726 8051",
    "sg:postcode":"97209",
    "sg:province":"OR",
    "sg:tags":[
        "contractor",
        "closet",
        "accessory"
    ],
    "sg:website":"cabinetmakerinportland.info",
    "wof:name":"Portland Closet Company",
    "wof:placetype":"venue"
},
  "geometry": {"coordinates":[-122.68544300000001,45.530883],"type":"Point"}
}