{
  "type": "Feature",
  "properties": {
    "iso:country":"US",
    "sg:address":"1094 Glenbrook Loop Rd",
    "sg:city":"Riddle",
    "sg:classifiers":[
        {
            "category":"Manufacturing",
            "subcategory":"Signs",
            "type":"Manufacturing & Wholesale Goods"
        }
    ],
    "sg:phone":"+1 541 874 2671",
    "sg:postcode":"97469",
    "sg:province":"OR",
    "wof:name":"Douglas County Sign & Awning",
    "wof:placetype":"venue"
},
  "geometry": {"coordinates":[-123.371549,42.934432],"type":"Point"}
}