{
  "type": "Feature",
  "properties": {
    "iso:country":"US",
    "sg:address":"311 NE Dayton St",
    "sg:city":"John Day",
    "sg:classifiers":[
        {
            "category":"Organizations",
            "subcategory":"Religious Organization",
            "type":"Services"
        }
    ],
    "sg:phone":"+1 541 575 1202",
    "sg:postcode":"97845",
    "sg:province":"OR",
    "wof:name":"First Chrstn Chrch of John Day",
    "wof:placetype":"venue"
},
  "geometry": {"coordinates":[-118.951093,44.418982],"type":"Point"}
}