{
  "type": "Feature",
  "properties": {
    "iso:country":"US",
    "sg:address":"2947 NW Conifer Pl",
    "sg:city":"Corvallis",
    "sg:classifiers":[
        {
            "category":"Professional",
            "subcategory":"Accounting & Tax Preparation",
            "type":"Services"
        }
    ],
    "sg:phone":"+1 541 758 4081",
    "sg:postcode":"97330",
    "sg:province":"OR",
    "sg:tags":[
        "return",
        "filing"
    ],
    "wof:name":"Advanced Business Svc",
    "wof:placetype":"venue"
},
  "geometry": {"coordinates":[-123.251922,44.597143],"type":"Point"}
}