{
  "type": "Feature",
  "properties": {
    "iso:country":"US",
    "sg:address":"63650 Johnson Ranch Rd",
    "sg:city":"Bend",
    "sg:phone":"+1 541 382 5456",
    "sg:postcode":"97701",
    "sg:province":"OR",
    "sg:tags":[
        "beef",
        "farm",
        "crop",
        "field",
        "cattle",
        "feedlot"
    ],
    "wof:name":"Miltenberger Farm",
    "wof:placetype":"venue"
},
  "geometry": {"coordinates":[-121.027086,44.105999],"type":"Point"}
}