{
  "type": "Feature",
  "properties": {
    "addr:full":"60488 Umatilla Cir Bend OR 97702",
    "addr:postcode":"60488;97702",
    "addr:street":"Umatilla Cir",
    "iso:country":"US",
    "sg:address":"60488 Umatilla Cir",
    "sg:city":"Bend",
    "sg:classifiers":[
        {
            "category":"Utilities",
            "subcategory":"Cable",
            "type":"Services"
        }
    ],
    "sg:phone":"+1 541 330 2189",
    "sg:postcode":"97702",
    "sg:province":"OR",
    "sg:tags":[
        "television"
    ],
    "wof:name":"High Mountain Cable Contr",
    "wof:placetype":"venue"
},
  "geometry": {"coordinates":[-121.35350699999999,43.994688],"type":"Point"}
}