{
  "type": "Feature",
  "properties": {
    "iso:country":"US",
    "sg:address":"3803 US Hwy 101",
    "sg:city":"Lincoln City",
    "sg:classifiers":[
        {
            "category":"Travel",
            "subcategory":"Hotels & Motels",
            "type":"Entertainment"
        }
    ],
    "sg:phone":"+1 541 996 3606",
    "sg:postcode":"97367",
    "sg:province":"OR",
    "sg:website":"www.esterlee.com",
    "wof:name":"Ester Lee Motel",
    "wof:placetype":"venue"
},
  "geometry": {"coordinates":[-124.006439,44.993997],"type":"Point"}
}