{
  "type": "Feature",
  "properties": {
    "iso:country":"US",
    "sg:address":"1251 NE Centurion Dr",
    "sg:city":"Gresham",
    "sg:classifiers":[
        {
            "category":"Building & Trades",
            "subcategory":"Construction",
            "type":"Services"
        }
    ],
    "sg:phone":"+1 503 667 3018",
    "sg:postcode":"97030",
    "sg:province":"OR",
    "sg:tags":[
        "carpentry",
        "contractor"
    ],
    "wof:name":"His & Hers Design & Const Inc",
    "wof:placetype":"venue"
},
  "geometry": {"coordinates":[-122.39390899999999,45.506353],"type":"Point"}
}