{
  "type": "Feature",
  "properties": {
    "addr:full":"Northeast Cascades Parkway & Mount Hood Avenue Portland OR 97220",
    "addr:postcode":"97220",
    "addr:street":"Northeast Cascades Parkway & Mount Hood Avenue",
    "iso:country":"US",
    "sg:address":"Northeast Cascades Parkway & Mount Hood Avenue",
    "sg:city":"Portland",
    "sg:classifiers":[
        {
            "category":"Local Transit",
            "type":"Transportation"
        }
    ],
    "sg:postcode":"97220",
    "sg:province":"OR",
    "sg:tags":[
        "public"
    ],
    "wof:name":"Mt Hood Avenue Station",
    "wof:placetype":"venue"
},
  "geometry": {"coordinates":[-122.56714599999999,45.577102],"type":"Point"}
}