{
  "type": "Feature",
  "properties": {
    "iso:country":"US",
    "sg:address":"7413 SE Mill St",
    "sg:city":"Portland",
    "sg:classifiers":[
        {
            "category":"Manufacturing",
            "subcategory":"Toys & Sporting Goods",
            "type":"Manufacturing & Wholesale Goods"
        }
    ],
    "sg:phone":"+1 503 788 0067",
    "sg:postcode":"97215",
    "sg:province":"OR",
    "sg:tags":[
        "toys-wholesale",
        "manufacturer"
    ],
    "wof:name":"Toy-Fairycom",
    "wof:placetype":"venue"
},
  "geometry": {"coordinates":[-122.586865,45.510261],"type":"Point"}
}