{
  "type": "Feature",
  "properties": {
    "addr:full":"1502 Willamette St Eugene OR 97401",
    "addr:housenumber":"1502",
    "addr:postcode":"97401",
    "addr:street":"Willamette St",
    "iso:country":"US",
    "sg:address":"1502 Willamette St",
    "sg:city":"Eugene",
    "sg:classifiers":[
        {
            "category":"Shopping",
            "subcategory":"Jewelry",
            "type":"Retail Goods"
        }
    ],
    "sg:phone":"+1 541 302 1868",
    "sg:postcode":"97401",
    "sg:province":"OR",
    "wof:name":"Woolwine Jewelers",
    "wof:placetype":"venue"
},
  "geometry": {"coordinates":[-123.092827,44.042251],"type":"Point"}
}