{
  "type": "Feature",
  "properties": {
    "iso:country":"US",
    "sg:address":"13910 SE Callahan Rd",
    "sg:city":"Portland",
    "sg:classifiers":[
        {
            "category":"Building & Trades",
            "subcategory":"Construction",
            "type":"Services"
        }
    ],
    "sg:phone":"+1 503 789 3837",
    "sg:postcode":"97236",
    "sg:province":"OR",
    "sg:tags":[
        "hanging",
        "contractor"
    ],
    "wof:name":"Popma Painting",
    "wof:placetype":"venue"
},
  "geometry": {"coordinates":[-122.522231,45.454084],"type":"Point"}
}