{
  "type": "Feature",
  "properties": {
    "iso:country":"US",
    "sg:address":"1 SW Columbia St Ste 1800",
    "sg:city":"Portland",
    "sg:classifiers":[
        {
            "category":"Professional",
            "subcategory":"Lawyer & Legal Services",
            "type":"Services"
        }
    ],
    "sg:phone":"+1 503 224 7077",
    "sg:postcode":"97258",
    "sg:province":"OR",
    "sg:tags":[
        "divorce",
        "attorney",
        "law",
        "family"
    ],
    "wof:name":"Brown Sarah J",
    "wof:placetype":"venue"
},
  "geometry": {"coordinates":[-122.67517100000001,45.512821],"type":"Point"}
}