{
  "type": "Feature",
  "properties": {
    "addr:full":"67439 Hwy 20 Bend OR 97701",
    "addr:housenumber":"67439",
    "addr:postcode":"97701",
    "addr:street":"Hwy 20",
    "iso:country":"US",
    "sg:address":"67439 Hwy 20",
    "sg:city":"Bend",
    "sg:classifiers":[
        {
            "category":"Building & Trades",
            "subcategory":"Construction",
            "type":"Services"
        }
    ],
    "sg:phone":"+1 541 389 3514",
    "sg:postcode":"97701",
    "sg:province":"OR",
    "sg:tags":[
        "concrete",
        "contractor"
    ],
    "wof:name":"Concrete Innovations Inc",
    "wof:placetype":"venue"
},
  "geometry": {"coordinates":[-121.479522,44.246193],"type":"Point"}
}