{
  "type": "Feature",
  "properties": {
    "iso:country":"US",
    "sg:address":"1130 NW 22nd Ave",
    "sg:city":"Portland",
    "sg:classifiers":[
        {
            "category":"Health Services",
            "subcategory":"Doctor",
            "type":"Services"
        }
    ],
    "sg:phone":"+1 503 229 7137",
    "sg:postcode":"97210",
    "sg:province":"OR",
    "sg:tags":[
        "physician",
        "surgeon"
    ],
    "wof:name":"Northwest Gastroenterology",
    "wof:placetype":"venue"
},
  "geometry": {"coordinates":[-122.69655299999999,45.531035],"type":"Point"}
}