{
  "type": "Feature",
  "properties": {
    "addr:full":"8609 N Gilbert Ave Portland OR 97203",
    "addr:housenumber":"8609",
    "addr:postcode":"97203",
    "addr:street":"N Gilbert Ave",
    "iso:country":"US",
    "sg:address":"8609 N Gilbert Ave",
    "sg:city":"Portland",
    "sg:classifiers":[
        {
            "category":"Social Services",
            "subcategory":"Adult Care",
            "type":"Services"
        }
    ],
    "sg:phone":"+1 503 283 0624",
    "sg:postcode":"97203",
    "sg:province":"OR",
    "sg:tags":[
        "residential"
    ],
    "wof:name":"Lauries Jewels",
    "wof:placetype":"venue"
},
  "geometry": {"coordinates":[-122.734274,45.588962],"type":"Point"}
}