{
  "type": "Feature",
  "properties": {
    "iso:country":"US",
    "sg:address":"5745 Shasta Way",
    "sg:city":"Klamath Falls",
    "sg:classifiers":[
        {
            "category":"Food & Beverages",
            "subcategory":"Groceries & Convenience Stores",
            "type":"Retail Goods"
        }
    ],
    "sg:phone":"+1 541 882 7442",
    "sg:postcode":"97603",
    "sg:province":"OR",
    "sg:tags":[
        "grocer"
    ],
    "wof:name":"Shasta Market",
    "wof:placetype":"venue"
},
  "geometry": {"coordinates":[-121.719168,42.213915],"type":"Point"}
}