{
  "type": "Feature",
  "properties": {
    "iso:country":"US",
    "sg:address":"16165 Nola Ct",
    "sg:city":"Lake Oswego",
    "sg:classifiers":[
        {
            "category":"Professional",
            "subcategory":"Computer Services",
            "type":"Services"
        }
    ],
    "sg:phone":"+1 503 534 2677",
    "sg:postcode":"97035",
    "sg:province":"OR",
    "sg:tags":[
        "development",
        "software"
    ],
    "wof:name":"Alex Electronics",
    "wof:placetype":"venue"
},
  "geometry": {"coordinates":[-122.719897,45.408248],"type":"Point"}
}