{
  "type": "Feature",
  "properties": {
    "iso:country":"US",
    "sg:address":"9917 NE Campaign St",
    "sg:city":"Portland",
    "sg:classifiers":[
        {
            "category":"Organizations",
            "subcategory":"Membership Organization",
            "type":"Services"
        }
    ],
    "sg:phone":"+1 503 253 9207",
    "sg:postcode":"97220",
    "sg:province":"OR",
    "wof:name":"Ventura Chapel Association",
    "wof:placetype":"venue"
},
  "geometry": {"coordinates":[-122.557894,45.554598],"type":"Point"}
}