{
  "type": "Feature",
  "properties": {
    "iso:country":"US",
    "sg:address":"2355 Bailey Hill Rd",
    "sg:city":"Eugene",
    "sg:classifiers":[
        {
            "category":"Professional",
            "type":"Services"
        }
    ],
    "sg:phone":"+1 541 683 0976",
    "sg:postcode":"97405",
    "sg:province":"OR",
    "sg:tags":[
        "arts",
        "artist"
    ],
    "wof:name":"Jim Daly Studio",
    "wof:placetype":"venue"
},
  "geometry": {"coordinates":[-123.15926,44.033451],"type":"Point"}
}