{
  "type": "Feature",
  "properties": {
    "iso:country":"US",
    "sg:address":"2200 E Baseline St",
    "sg:city":"Cornelius",
    "sg:classifiers":[
        {
            "category":"Shopping",
            "subcategory":"Optical Goods",
            "type":"Retail Goods"
        }
    ],
    "sg:phone":"+1 503 359 0336",
    "sg:postcode":"97113",
    "sg:province":"OR",
    "wof:name":"National Vision",
    "wof:placetype":"venue"
},
  "geometry": {"coordinates":[-123.04385600000001,45.520064],"type":"Point"}
}