{
  "type": "Feature",
  "properties": {
    "iso:country":"US",
    "sg:address":"2238 SE 104th Dr",
    "sg:city":"Portland",
    "sg:classifiers":[
        {
            "category":"Professional",
            "subcategory":"Advertising",
            "type":"Services"
        }
    ],
    "sg:phone":"+1 503 255 5279",
    "sg:postcode":"97216",
    "sg:province":"OR",
    "sg:tags":[
        "picture",
        "product",
        "business",
        "agency",
        "motion",
        "advertising-promotional"
    ],
    "wof:name":"Boaz Group Marketing Projects",
    "wof:placetype":"venue"
},
  "geometry": {"coordinates":[-122.556072,45.506644],"type":"Point"}
}