{
  "type": "Feature",
  "properties": {
    "iso:country":"US",
    "sg:address":"108 W Burnside Street",
    "sg:city":"Portland",
    "sg:classifiers":[
        {
            "category":"Arts & Performance",
            "subcategory":"Art Gallery",
            "type":"Entertainment"
        }
    ],
    "sg:phone":"503560520",
    "sg:postcode":"97209",
    "sg:province":"OR",
    "wof:name":"Cultural Elements",
    "wof:placetype":"venue"
},
  "geometry": {"coordinates":[-122.671668,45.522959],"type":"Point"}
}