{
  "type": "Feature",
  "properties": {
    "addr:full":"527 Fairmount St Medford OR 97501",
    "addr:housenumber":"527",
    "addr:postcode":"97501",
    "addr:street":"Fairmount St",
    "iso:country":"US",
    "sg:address":"527 Fairmount St",
    "sg:city":"Medford",
    "sg:classifiers":[
        {
            "category":"Building & Trades",
            "subcategory":"Construction",
            "type":"Services"
        }
    ],
    "sg:phone":"+1 541 779 1636",
    "sg:postcode":"97501",
    "sg:province":"OR",
    "sg:tags":[
        "house"
    ],
    "wof:name":"Libby Construction",
    "wof:placetype":"venue"
},
  "geometry": {"coordinates":[-122.88963099999999,42.329152],"type":"Point"}
}