{
  "type": "Feature",
  "properties": {
    "iso:country":"US",
    "sg:address":"7905 SW Nimbus Ave",
    "sg:city":"Beaverton",
    "sg:classifiers":[
        {
            "category":"Professional",
            "subcategory":"Business Services",
            "type":"Services"
        },
        {
            "category":"Wholesale",
            "subcategory":"Electrical",
            "type":"Manufacturing & Wholesale Goods"
        }
    ],
    "sg:phone":"+1 503 643 3127",
    "sg:postcode":"97008",
    "sg:province":"OR",
    "sg:tags":[
        "fire",
        "alarm",
        "system"
    ],
    "wof:name":"D T S Systems Inc",
    "wof:placetype":"venue"
},
  "geometry": {"coordinates":[-122.78863200000001,45.461562],"type":"Point"}
}