{
  "type": "Feature",
  "properties": {
    "iso:country":"US",
    "sg:address":"2157 SE Scott Ave",
    "sg:city":"Gresham",
    "sg:classifiers":[
        {
            "category":"Professional",
            "subcategory":"Business Services",
            "type":"Services"
        }
    ],
    "sg:phone":"+1 503 706 1751",
    "sg:postcode":"97080",
    "sg:province":"OR",
    "sg:tags":[
        "wholesale",
        "sales",
        "car"
    ],
    "wof:name":"N W Auto Consulting Inc",
    "wof:placetype":"venue"
},
  "geometry": {"coordinates":[-122.397396,45.482132],"type":"Point"}
}