{
  "type": "Feature",
  "properties": {
    "addr:full":"333 NE Lincoln St Hillsboro OR 97124",
    "addr:housenumber":"333",
    "addr:postcode":"97124",
    "addr:street":"Ne Lincoln St",
    "iso:country":"US",
    "sg:address":"333 NE Lincoln St",
    "sg:city":"Hillsboro",
    "sg:classifiers":[
        {
            "category":"Manufacturing",
            "subcategory":"Metals",
            "type":"Manufacturing & Wholesale Goods"
        }
    ],
    "sg:phone":"+1 503 505 6572",
    "sg:postcode":"97124",
    "sg:province":"OR",
    "sg:tags":[
        "product",
        "mfg",
        "commercial",
        "fabricated",
        "artist"
    ],
    "sg:website":"http://www.waterjetdesign.com",
    "wof:name":"Water Jet Design",
    "wof:placetype":"venue"
},
  "geometry": {"coordinates":[-122.985542,45.523876],"type":"Point"}
}