{
  "type": "Feature",
  "properties": {
    "iso:country":"US",
    "sg:address":"7428 N Saint Louis Ave",
    "sg:city":"Portland",
    "sg:classifiers":[
        {
            "category":"Utilities",
            "subcategory":"Refuse",
            "type":"Services"
        },
        {
            "category":"Building & Trades",
            "subcategory":"Construction",
            "type":"Services"
        }
    ],
    "sg:phone":"+1 503 735 2177",
    "sg:postcode":"97203",
    "sg:province":"OR",
    "sg:tags":[
        "excavation",
        "truck",
        "dump",
        "contractor"
    ],
    "wof:name":"Barnes Trucking & Excavating",
    "wof:placetype":"venue"
},
  "geometry": {"coordinates":[-122.75709000000001,45.593187],"type":"Point"}
}