{
  "type": "Feature",
  "properties": {
    "iso:country":"US",
    "sg:address":"115 1st Ave E",
    "sg:city":"Albany",
    "sg:classifiers":[
        {
            "category":"Shopping",
            "type":"Retail Goods"
        }
    ],
    "sg:phone":"+1 541 926 0301",
    "sg:postcode":"97321",
    "sg:province":"OR",
    "sg:tags":[
        "trophy",
        "award"
    ],
    "wof:name":"Janos Awards Inc",
    "wof:placetype":"venue"
},
  "geometry": {"coordinates":[-123.103829,44.637623],"type":"Point"}
}