{
  "type": "Feature",
  "properties": {
    "addr:full":"8700 SW Creekside Pl Ste B Beaverton OR 97008",
    "addr:housenumber":"8700",
    "addr:postcode":"97008",
    "addr:street":"Sw Creekside Pl Ste B",
    "iso:country":"US",
    "sg:address":"8700 SW Creekside Pl Ste B",
    "sg:city":"Beaverton",
    "sg:classifiers":[
        {
            "category":"Real Estate",
            "subcategory":"Real Estate Services",
            "type":"Services"
        },
        {
            "category":"Real Estate",
            "subcategory":"Real Estate Agent",
            "type":"Services"
        }
    ],
    "sg:phone":"+1 503 646 5006",
    "sg:postcode":"97008",
    "sg:province":"OR",
    "sg:tags":[
        "management"
    ],
    "wof:name":"Oregon First Commercial & Inve",
    "wof:placetype":"venue"
},
  "geometry": {"coordinates":[-122.792908,45.457966],"type":"Point"}
}