{
  "type": "Feature",
  "properties": {
    "iso:country":"US",
    "sg:address":"611 E Highland Ave",
    "sg:city":"Hermiston",
    "sg:classifiers":[
        {
            "category":"Personal",
            "subcategory":"Beauty Salon",
            "type":"Services"
        }
    ],
    "sg:phone":"+1 541 567 2003",
    "sg:postcode":"97838",
    "sg:province":"OR",
    "sg:tags":[
        "shop"
    ],
    "wof:name":"Loretta Mlllers Shear Illsions",
    "wof:placetype":"venue"
},
  "geometry": {"coordinates":[-119.281689,45.834993],"type":"Point"}
}