{
  "type": "Feature",
  "properties": {
    "addr:full":"7927 SW Cirrus Dr Beaverton OR 97008",
    "addr:housenumber":"7927",
    "addr:postcode":"97008",
    "addr:street":"Sw Cirrus Dr",
    "iso:country":"US",
    "sg:address":"7927 SW Cirrus Dr",
    "sg:city":"Beaverton",
    "sg:classifiers":[
        {
            "category":"Wholesale",
            "subcategory":"Home Furnishings",
            "type":"Manufacturing & Wholesale Goods"
        }
    ],
    "sg:phone":"+1 503 350 1213",
    "sg:postcode":"97008",
    "sg:province":"OR",
    "sg:tags":[
        "book"
    ],
    "wof:name":"Collection Connection",
    "wof:placetype":"venue"
},
  "geometry": {"coordinates":[-122.790695,45.461178],"type":"Point"}
}