{
  "type": "Feature",
  "properties": {
    "addr:full":"8383 NE Sandy Blvd Portland OR 97220",
    "addr:housenumber":"8383",
    "addr:postcode":"97220",
    "addr:street":"Ne Sandy Blvd",
    "iso:country":"US",
    "sg:address":"8383 NE Sandy Blvd",
    "sg:city":"Portland",
    "sg:classifiers":[
        {
            "category":"Banks & Credit Unions",
            "subcategory":"Bank",
            "type":"Services"
        }
    ],
    "sg:phone":"+1 503 253 0058",
    "sg:postcode":"97220",
    "sg:province":"OR",
    "sg:tags":[
        "loan",
        "real estate"
    ],
    "wof:name":"Western Capital",
    "wof:placetype":"venue"
},
  "geometry": {"coordinates":[-122.57682,45.553115],"type":"Point"}
}