{
  "type": "Feature",
  "properties": {
    "iso:country":"US",
    "sg:address":"17 SW Gibbs St",
    "sg:city":"Portland",
    "sg:classifiers":[
        {
            "category":"Utilities",
            "subcategory":"Telephone",
            "type":"Services"
        },
        {
            "category":"Manufacturing",
            "subcategory":"Electronics",
            "type":"Manufacturing & Wholesale Goods"
        },
        {
            "category":"Communications",
            "type":"Services"
        }
    ],
    "sg:phone":"+1 503 242 1543",
    "sg:postcode":"97239",
    "sg:province":"OR",
    "sg:tags":[
        "telecommunications-equipment",
        "systems-repair",
        "supply",
        "system",
        "equipment"
    ],
    "wof:name":"Superior Tel",
    "wof:placetype":"venue"
},
  "geometry": {"coordinates":[-122.67758499999999,45.499371],"type":"Point"}
}