{
  "type": "Feature",
  "properties": {
    "iso:country":"US",
    "sg:address":"8900 SW Commercial St",
    "sg:city":"Portland",
    "sg:classifiers":[
        {
            "category":"Wholesale",
            "subcategory":"Toys & Hobbies",
            "type":"Manufacturing & Wholesale Goods"
        },
        {
            "category":"Recreation",
            "type":"Entertainment"
        }
    ],
    "sg:phone":"+1 503 968 9579",
    "sg:postcode":"97223",
    "sg:province":"OR",
    "sg:tags":[
        "paint",
        "sport",
        "ball"
    ],
    "wof:name":"Hit 'n Run Paintballs Inc",
    "wof:placetype":"venue"
},
  "geometry": {"coordinates":[-122.76892599999999,45.430219],"type":"Point"}
}