{
  "type": "Feature",
  "properties": {
    "addr:full":"2200 NW Amberbrook Dr Beaverton OR 97006",
    "addr:housenumber":"2200",
    "addr:postcode":"97006",
    "addr:street":"Nw Amberbrook Dr",
    "iso:country":"US",
    "sg:address":"2200 NW Amberbrook Dr",
    "sg:city":"Beaverton",
    "sg:classifiers":[
        {
            "category":"Personal",
            "type":"Services"
        },
        {
            "category":"Sports & Exercise",
            "subcategory":"Gym",
            "type":"Entertainment"
        },
        {
            "category":"Arena",
            "subcategory":"Sports Club",
            "type":"Entertainment"
        }
    ],
    "sg:phone":"+1 503 476 3300",
    "sg:postcode":"97006",
    "sg:province":"OR",
    "sg:tags":[
        "trainer",
        "consultant",
        "gymnasium",
        "program",
        "health",
        "fitness",
        "physical"
    ],
    "sg:website":"http://clickserve.dartsearch.net/link/click?lid=43000000196565615",
    "wof:name":"Bally Total Fitness",
    "wof:placetype":"venue"
},
  "geometry": {"coordinates":[-122.884638,45.53625],"type":"Point"}
}