{
  "type": "Feature",
  "properties": {
    "iso:country":"US",
    "sg:address":"2961 SE 64th Ave",
    "sg:city":"Portland",
    "sg:classifiers":[
        {
            "category":"Wholesale",
            "subcategory":"Durable Goods & Equipment",
            "type":"Manufacturing & Wholesale Goods"
        }
    ],
    "sg:phone":"+1 503 772 3321",
    "sg:postcode":"97206",
    "sg:province":"OR",
    "wof:name":"B&F Wholesale Inc",
    "wof:placetype":"venue"
},
  "geometry": {"coordinates":[-122.59801,45.501145],"type":"Point"}
}