{
  "type": "Feature",
  "properties": {
    "addr:full":"SW Council Crest Dr and SW Patrick Pl Portland OR 97239",
    "addr:postcode":"97239",
    "addr:street":"Crest;Patrick Pl",
    "iso:country":"US",
    "sg:address":"SW Council Crest Dr and SW Patrick Pl",
    "sg:city":"Portland",
    "sg:classifiers":[
        {
            "category":"Government",
            "subcategory":"City Hall",
            "type":"Public Place"
        }
    ],
    "sg:postcode":"97239",
    "sg:province":"OR",
    "sg:website":"www.portlandonline.com/parks/fin...",
    "wof:name":"Healy Heights Park",
    "wof:placetype":"venue"
},
  "geometry": {"coordinates":[-122.698531,45.492713],"type":"Point"}
}