{
  "type": "Feature",
  "properties": {
    "addr:full":"160 NW Burnside Rd Gresham OR 97030",
    "addr:housenumber":"160",
    "addr:postcode":"97030",
    "addr:street":"Nw Burnside Rd",
    "iso:country":"US",
    "sg:address":"160 NW Burnside Rd",
    "sg:city":"Gresham",
    "sg:classifiers":[
        {
            "category":"Personal",
            "subcategory":"Beauty Salon",
            "type":"Services"
        }
    ],
    "sg:phone":"+1 503 618 1921",
    "sg:postcode":"97030",
    "sg:province":"OR",
    "sg:tags":[
        "shop"
    ],
    "wof:name":"Max Tan Hair & Nails",
    "wof:placetype":"venue"
},
  "geometry": {"coordinates":[-122.43313000000001,45.509191],"type":"Point"}
}