{
  "type": "Feature",
  "properties": {
    "iso:country":"US",
    "sg:address":"9923 SW Arctic Dr",
    "sg:city":"Beaverton",
    "sg:classifiers":[
        {
            "category":"Manufacturing",
            "subcategory":"Tools & Machinery",
            "type":"Manufacturing & Wholesale Goods"
        }
    ],
    "sg:phone":"+1 503 644 1002",
    "sg:postcode":"97005",
    "sg:province":"OR",
    "sg:tags":[
        "food",
        "product"
    ],
    "wof:name":"MTM Systems Inc",
    "wof:placetype":"venue"
},
  "geometry": {"coordinates":[-122.78055500000001,45.481328],"type":"Point"}
}