{
  "type": "Feature",
  "properties": {
    "iso:country":"US",
    "sg:address":"5401 Chenoweth Rd",
    "sg:city":"The Dalles",
    "sg:phone":"+1 541 296 4173",
    "sg:postcode":"97058",
    "sg:province":"OR",
    "sg:tags":[
        "equipment",
        "commercial"
    ],
    "wof:name":"Ellett Equipment Company",
    "wof:placetype":"venue"
},
  "geometry": {"coordinates":[-121.255588,45.621578],"type":"Point"}
}