{
  "type": "Feature",
  "properties": {
    "iso:country":"US",
    "sg:address":"1130 NW 22nd Avenue Suite 220",
    "sg:city":"Portland",
    "sg:classifiers":[
        {
            "category":"Health Services",
            "subcategory":"Doctor",
            "type":"Services"
        },
        {
            "category":"Health Services",
            "subcategory":"Hospital",
            "type":"Services"
        }
    ],
    "sg:phone":"+1 503 413 8988",
    "sg:postcode":"97210",
    "sg:province":"OR",
    "sg:tags":[
        "physician",
        "surgeon"
    ],
    "wof:name":"Marr Curtis MD",
    "wof:placetype":"venue"
},
  "geometry": {"coordinates":[-122.696595,45.530763],"type":"Point"}
}