{
  "type": "Feature",
  "properties": {
    "addr:full":"34970 Brooten Rd Cloverdale OR 97112",
    "addr:postcode":"34970;97112",
    "addr:street":"Brooten Rd",
    "iso:country":"US",
    "sg:address":"34970 Brooten Rd",
    "sg:city":"Cloverdale",
    "sg:classifiers":[
        {
            "category":"Shopping",
            "subcategory":"Gifts & Souvenirs",
            "type":"Retail Goods"
        }
    ],
    "sg:phone":"+1 503 965 7229",
    "sg:postcode":"97112",
    "sg:province":"OR",
    "sg:tags":[
        "shop"
    ],
    "wof:name":"Pacific City Imports",
    "wof:placetype":"venue"
},
  "geometry": {"coordinates":[-123.96193100000001,45.202396],"type":"Point"}
}