{
  "type": "Feature",
  "properties": {
    "iso:country":"US",
    "sg:address":"8305 SE Monterey Ave",
    "sg:city":"Portland",
    "sg:classifiers":[
        {
            "category":"Insurance",
            "subcategory":"Insurance Agent",
            "type":"Services"
        }
    ],
    "sg:phone":"+1 503 653 6392",
    "sg:postcode":"97086",
    "sg:province":"OR",
    "wof:name":"State Farm Insurance",
    "wof:placetype":"venue"
},
  "geometry": {"coordinates":[-122.576169,45.438383],"type":"Point"}
}