{
  "type": "Feature",
  "properties": {
    "iso:country":"US",
    "sg:address":"2150 Friendly St",
    "sg:city":"Eugene",
    "sg:classifiers":[
        {
            "category":"Building & Trades",
            "subcategory":"Construction",
            "type":"Services"
        }
    ],
    "sg:phone":"+1 541 345 2753",
    "sg:postcode":"97405",
    "sg:province":"OR",
    "sg:tags":[
        "residential",
        "commercial",
        "gen",
        "contractor"
    ],
    "wof:name":"Glover Marv Design & Cnstr",
    "wof:placetype":"venue"
},
  "geometry": {"coordinates":[-123.105592,44.036093],"type":"Point"}
}