{
  "type": "Feature",
  "properties": {
    "addr:full":"109 E A St Rainier OR 97048",
    "addr:housenumber":"109",
    "addr:postcode":"97048",
    "addr:street":"E A St",
    "iso:country":"US",
    "sg:address":"109 E A St",
    "sg:city":"Rainier",
    "sg:classifiers":[
        {
            "category":"Home & Garden",
            "subcategory":"Household Appliances",
            "type":"Retail Goods"
        }
    ],
    "sg:phone":"+1 503 556 3005",
    "sg:postcode":"97048",
    "sg:province":"OR",
    "wof:name":"Rainier Appliance",
    "wof:placetype":"venue"
},
  "geometry": {"coordinates":[-122.93458,46.089704],"type":"Point"}
}