{
  "type": "Feature",
  "properties": {
    "addr:full":"33497 Pittsburg Rd Saint Helens OR 97051",
    "addr:postcode":"33497;97051",
    "addr:street":"Pittsburg Rd",
    "iso:country":"US",
    "sg:address":"33497 Pittsburg Rd",
    "sg:city":"Saint Helens",
    "sg:classifiers":[
        {
            "category":"Wholesale",
            "subcategory":"Farm Supplies",
            "type":"Manufacturing & Wholesale Goods"
        }
    ],
    "sg:phone":"+1 503 397 1370",
    "sg:postcode":"97051",
    "sg:province":"OR",
    "sg:tags":[
        "livestock"
    ],
    "wof:name":"Yankton Polled Herfords",
    "wof:placetype":"venue"
},
  "geometry": {"coordinates":[-122.87478900000001,45.866242],"type":"Point"}
}