{
  "type": "Feature",
  "properties": {
    "addr:full":"1152 Marine Dr Astoria OR 97103",
    "addr:housenumber":"1152",
    "addr:postcode":"97103",
    "addr:street":"Marine Dr",
    "iso:country":"US",
    "sg:address":"1152 Marine Dr",
    "sg:city":"Astoria",
    "sg:classifiers":[
        {
            "category":"Organizations",
            "subcategory":"Professional Association",
            "type":"Services"
        }
    ],
    "sg:phone":"+1 503 325 4444",
    "sg:postcode":"97103",
    "sg:province":"OR",
    "sg:tags":[
        "business",
        "trade"
    ],
    "wof:name":"Seattle 2000",
    "wof:placetype":"venue"
},
  "geometry": {"coordinates":[-123.83113899999999,46.189785],"type":"Point"}
}