{
  "type": "Feature",
  "properties": {
    "iso:country":"US",
    "sg:address":"164 W Cardinal St",
    "sg:city":"Roseburg",
    "sg:classifiers":[
        {
            "category":"Retail",
            "subcategory":"Repair Shop",
            "type":"Services"
        }
    ],
    "sg:phone":"+1 541 673 0803",
    "sg:postcode":"97470",
    "sg:province":"OR",
    "wof:name":"Horn Again Music",
    "wof:placetype":"venue"
},
  "geometry": {"coordinates":[-123.38528,43.219352],"type":"Point"}
}