{
  "type": "Feature",
  "properties": {
    "iso:country":"US",
    "sg:address":"30499 Fayetteville Dr",
    "sg:city":"Shedd",
    "sg:classifiers":[
        {
            "category":"Professional",
            "subcategory":"Management & Consulting",
            "type":"Services"
        }
    ],
    "sg:phone":"+1 541 491 1007",
    "sg:postcode":"97377",
    "sg:province":"OR",
    "sg:tags":[
        "farm"
    ],
    "wof:name":"Delmar Seufert",
    "wof:placetype":"venue"
},
  "geometry": {"coordinates":[-123.163399,44.460861],"type":"Point"}
}