{
  "type": "Feature",
  "properties": {
    "addr:full":"5214 N Maryland Ave. Portland OR 97217",
    "addr:housenumber":"5214",
    "addr:postcode":"97217",
    "addr:street":"N Maryland Ave.",
    "iso:country":"US",
    "sg:address":"5214 N Maryland Ave.",
    "sg:city":"Portland",
    "sg:classifiers":[
        {
            "category":"Real Estate",
            "subcategory":"Real Estate Agent",
            "type":"Services"
        }
    ],
    "sg:phone":"+1 503 758 8581",
    "sg:postcode":"97217",
    "sg:province":"OR",
    "wof:name":"Paris Group Realty, LLC",
    "wof:placetype":"venue"
},
  "geometry": {"coordinates":[-122.68076600000001,45.560707],"type":"Point"}
}