{
  "type": "Feature",
  "properties": {
    "addr:full":"457 NW Garden Valley Blvd Roseburg OR 97470",
    "addr:housenumber":"457",
    "addr:postcode":"97470",
    "addr:street":"Nw Garden Valley Blvd",
    "iso:country":"US",
    "sg:address":"457 NW Garden Valley Blvd",
    "sg:city":"Roseburg",
    "sg:classifiers":[
        {
            "category":"Shopping",
            "subcategory":"Tobacco",
            "type":"Retail Goods"
        }
    ],
    "sg:phone":"+1 541 673 1601",
    "sg:postcode":"97470",
    "sg:province":"OR",
    "sg:tags":[
        "cigarette",
        "cigar",
        "dealer"
    ],
    "wof:name":"News & Smokes",
    "wof:placetype":"venue"
},
  "geometry": {"coordinates":[-123.361839,43.22696],"type":"Point"}
}