{
  "type": "Feature",
  "properties": {
    "iso:country":"US",
    "sg:address":"8835 SW Canyon Ln",
    "sg:city":"Portland",
    "sg:classifiers":[
        {
            "category":"Building & Trades",
            "subcategory":"Construction",
            "type":"Services"
        }
    ],
    "sg:phone":"+1 503 292 2107",
    "sg:postcode":"97225",
    "sg:province":"OR",
    "sg:tags":[
        "contractor"
    ],
    "wof:name":"Young Donald & Associates Inc",
    "wof:placetype":"venue"
},
  "geometry": {"coordinates":[-122.76799800000001,45.497898],"type":"Point"}
}