{
  "type": "Feature",
  "properties": {
    "iso:country":"US",
    "sg:address":"750 Oxyoke Rd",
    "sg:city":"Grants Pass",
    "sg:classifiers":[
        {
            "category":"Retail",
            "subcategory":"Self-service Laundry",
            "type":"Services"
        }
    ],
    "sg:phone":"+1 541 956 0589",
    "sg:postcode":"97526",
    "sg:province":"OR",
    "sg:tags":[
        "coin"
    ],
    "wof:name":"Wild River Soaps",
    "wof:placetype":"venue"
},
  "geometry": {"coordinates":[-123.38574199999999,42.573884],"type":"Point"}
}