{
  "type": "Feature",
  "properties": {
    "iso:country":"US",
    "sg:address":"12535 SW Main St",
    "sg:city":"Portland",
    "sg:classifiers":[
        {
            "category":"Shopping",
            "subcategory":"Jewelry",
            "type":"Retail Goods"
        }
    ],
    "sg:phone":"+1 503 598 0144",
    "sg:postcode":"97223",
    "sg:province":"OR",
    "sg:tags":[
        "repair",
        "jeweler"
    ],
    "wof:name":"Sherrie's Jewelry Box",
    "wof:placetype":"venue"
},
  "geometry": {"coordinates":[-122.774589,45.429017],"type":"Point"}
}