{
  "type": "Feature",
  "properties": {
    "iso:country":"US",
    "sg:address":"2500 S 6th St",
    "sg:city":"Klamath Falls",
    "sg:classifiers":[
        {
            "category":"Travel",
            "subcategory":"Hotels & Motels",
            "type":"Entertainment"
        }
    ],
    "sg:phone":"+1 541 884 9999",
    "sg:postcode":"97603",
    "sg:province":"OR",
    "wof:name":"Holiday Inn Express Klmth Flls",
    "wof:placetype":"venue"
},
  "geometry": {"coordinates":[-121.758573,42.211927],"type":"Point"}
}