{
  "type": "Feature",
  "properties": {
    "iso:country":"US",
    "sg:address":"601 State St",
    "sg:city":"Hood River",
    "sg:classifiers":[
        {
            "category":"Building & Trades",
            "subcategory":"Plumbing",
            "type":"Services"
        }
    ],
    "sg:phone":"+1 541 386 9504",
    "sg:postcode":"97031",
    "sg:province":"OR",
    "sg:tags":[
        "plumbing",
        "contractor"
    ],
    "wof:name":"Jiffy Rooter Svc",
    "wof:placetype":"venue"
},
  "geometry": {"coordinates":[-121.516366,45.708121],"type":"Point"}
}