{
  "type": "Feature",
  "properties": {
    "iso:country":"US",
    "sg:address":"509 N Mill St",
    "sg:city":"Joseph",
    "sg:classifiers":[
        {
            "category":"Building & Trades",
            "subcategory":"Landscaping Services",
            "type":"Services"
        }
    ],
    "sg:phone":"+1 541 432 4605",
    "sg:postcode":"97846",
    "sg:province":"OR",
    "sg:tags":[
        "tree"
    ],
    "wof:name":"Tree Care North",
    "wof:placetype":"venue"
},
  "geometry": {"coordinates":[-117.231279,45.356259],"type":"Point"}
}