{
  "type": "Feature",
  "properties": {
    "iso:country":"US",
    "sg:address":"3709 Franklin Blvd",
    "sg:city":"Eugene",
    "sg:classifiers":[
        {
            "category":"Autos & Motor Vehicles",
            "subcategory":"Auto Supplies",
            "type":"Retail Goods"
        }
    ],
    "sg:phone":"+1 541 746 4193",
    "sg:postcode":"97403",
    "sg:province":"OR",
    "wof:name":"Big B Tire",
    "wof:placetype":"venue"
},
  "geometry": {"coordinates":[-123.037546,44.045081],"type":"Point"}
}