{
  "type": "Feature",
  "properties": {
    "addr:full":"3709 Franklin Blvd Eugene OR 97403",
    "addr:housenumber":"3709",
    "addr:postcode":"97403",
    "addr:street":"Franklin Blvd",
    "iso:country":"US",
    "sg:address":"3709 Franklin Blvd",
    "sg:city":"Eugene",
    "sg:classifiers":[
        {
            "category":"Autos & Motor Vehicles",
            "subcategory":"Auto Supplies",
            "type":"Retail Goods"
        }
    ],
    "sg:phone":"+1 541 746 4193",
    "sg:postcode":"97403",
    "sg:province":"OR",
    "wof:name":"Big B Tire",
    "wof:placetype":"venue"
},
  "geometry": {"coordinates":[-123.03754600000001,44.045081],"type":"Point"}
}