{
  "type": "Feature",
  "properties": {
    "iso:country":"US",
    "sg:address":"4074 Pacific Hwy",
    "sg:city":"Hubbard",
    "sg:classifiers":[
        {
            "category":"Building & Trades",
            "subcategory":"Construction",
            "type":"Services"
        }
    ],
    "sg:phone":"+1 503 981 7741",
    "sg:postcode":"97032",
    "sg:province":"OR",
    "sg:tags":[
        "hanging",
        "contractor"
    ],
    "wof:name":"Associated Painting",
    "wof:placetype":"venue"
},
  "geometry": {"coordinates":[-122.802039,45.184039],"type":"Point"}
}