{
  "type": "Feature",
  "properties": {
    "iso:country":"US",
    "sg:address":"905 Main St",
    "sg:city":"Klamath Falls",
    "sg:classifiers":[
        {
            "category":"Professional",
            "subcategory":"Secretarial Services",
            "type":"Services"
        }
    ],
    "sg:phone":"+1 541 882 4344",
    "sg:postcode":"97601",
    "sg:province":"OR",
    "sg:tags":[
        "job",
        "reporting"
    ],
    "wof:name":"AAA Resume & Vocational Servic",
    "wof:placetype":"venue"
},
  "geometry": {"coordinates":[-121.779993,42.227043],"type":"Point"}
}