{
  "type": "Feature",
  "properties": {
    "addr:full":"1321 Linden Ave Springfield OR 97477",
    "addr:housenumber":"1321",
    "addr:postcode":"97477",
    "addr:street":"Linden Ave",
    "iso:country":"US",
    "sg:address":"1321 Linden Ave",
    "sg:city":"Springfield",
    "sg:classifiers":[
        {
            "category":"Social Services",
            "subcategory":"Child Care",
            "type":"Services"
        }
    ],
    "sg:phone":"+1 541 747 2798",
    "sg:postcode":"97477",
    "sg:province":"OR",
    "sg:tags":[
        "day"
    ],
    "wof:name":"Ready Set Go Day Care Center",
    "wof:placetype":"venue"
},
  "geometry": {"coordinates":[-123.044567,44.059881],"type":"Point"}
}