{
  "type": "Feature",
  "properties": {
    "iso:country":"US",
    "sg:address":"1029 Pool St",
    "sg:city":"Eugene",
    "sg:classifiers":[
        {
            "category":"Home & Garden",
            "subcategory":"Carpets & Floor Coverings",
            "type":"Retail Goods"
        }
    ],
    "sg:phone":"+1 541 344 6277",
    "sg:postcode":"97401",
    "sg:province":"OR",
    "wof:name":"Floorcovering Concepts",
    "wof:placetype":"venue"
},
  "geometry": {"coordinates":[-123.094249,44.069152],"type":"Point"}
}