{
  "type": "Feature",
  "properties": {
    "addr:full":"254 Wallis St Eugene OR 97402",
    "addr:housenumber":"254",
    "addr:postcode":"97402",
    "addr:street":"Wallis St",
    "iso:country":"US",
    "sg:address":"254 Wallis St",
    "sg:city":"Eugene",
    "sg:classifiers":[
        {
            "category":"Arts & Performance",
            "subcategory":"Theater",
            "type":"Entertainment"
        }
    ],
    "sg:phone":"+1 541 687 2210",
    "sg:postcode":"97402",
    "sg:province":"OR",
    "sg:tags":[
        "magician"
    ],
    "wof:name":"Magic Touch",
    "wof:placetype":"venue"
},
  "geometry": {"coordinates":[-123.15453100000001,44.053721],"type":"Point"}
}