{
  "type": "Feature",
  "properties": {
    "iso:country":"US",
    "sg:address":"60410 Gosney Rd",
    "sg:city":"Bend",
    "sg:classifiers":[
        {
            "category":"Farming",
            "subcategory":"Livestock Farm",
            "type":"Manufacturing & Wholesale Goods"
        }
    ],
    "sg:phone":"+1 541 318 0087",
    "sg:postcode":"97702",
    "sg:province":"OR",
    "sg:tags":[
        "animal",
        "general"
    ],
    "wof:name":"Little Piece of Heaven Ranch",
    "wof:placetype":"venue"
},
  "geometry": {"coordinates":[-121.193702,43.998831],"type":"Point"}
}