{
  "type": "Feature",
  "properties": {
    "addr:full":"2721 NE Charlois Dr Hillsboro OR 97124",
    "addr:housenumber":"2721",
    "addr:postcode":"97124",
    "addr:street":"Ne Charlois Dr",
    "iso:country":"US",
    "sg:address":"2721 NE Charlois Dr",
    "sg:city":"Hillsboro",
    "sg:classifiers":[
        {
            "category":"Professional",
            "subcategory":"Business Services",
            "type":"Services"
        }
    ],
    "sg:phone":"+1 503 846 1641",
    "sg:postcode":"97124",
    "sg:province":"OR",
    "wof:name":"Scanvue Technologies LLC",
    "wof:placetype":"venue"
},
  "geometry": {"coordinates":[-122.974964,45.544362],"type":"Point"}
}