{
  "type": "Feature",
  "properties": {
    "iso:country":"US",
    "sg:address":"610 NW Merrie Dr",
    "sg:city":"Corvallis",
    "sg:classifiers":[
        {
            "category":"Professional",
            "subcategory":"Research",
            "type":"Services"
        }
    ],
    "sg:phone":"+1 541 738 0766",
    "sg:postcode":"97330",
    "sg:province":"OR",
    "sg:tags":[
        "biological"
    ],
    "wof:name":"Jessica Adine",
    "wof:placetype":"venue"
},
  "geometry": {"coordinates":[-123.29332100000001,44.575478],"type":"Point"}
}