{
  "type": "Feature",
  "properties": {
    "addr:full":"9019 SW 15th Ave Portland OR 97219",
    "addr:housenumber":"9019",
    "addr:postcode":"97219",
    "addr:street":"Sw 15Th Ave",
    "iso:country":"US",
    "sg:address":"9019 SW 15th Ave",
    "sg:city":"Portland",
    "sg:classifiers":[
        {
            "category":"Manufacturing",
            "subcategory":"Tools & Machinery",
            "type":"Manufacturing & Wholesale Goods"
        }
    ],
    "sg:phone":"+1 503 234 6570",
    "sg:postcode":"97219",
    "sg:province":"OR",
    "sg:tags":[
        "machine",
        "manufacturer"
    ],
    "wof:name":"Tri Tec Corporation",
    "wof:placetype":"venue"
},
  "geometry": {"coordinates":[-122.694061,45.459548],"type":"Point"}
}