{
  "type": "Feature",
  "properties": {
    "addr:full":"4611 SE 48th Ave Portland OR 97206",
    "addr:housenumber":"4611",
    "addr:postcode":"97206",
    "addr:street":"Se 48Th Ave",
    "iso:country":"US",
    "sg:address":"4611 SE 48th Ave",
    "sg:city":"Portland",
    "sg:classifiers":[
        {
            "category":"Professional",
            "subcategory":"Management & Consulting",
            "type":"Services"
        }
    ],
    "sg:phone":"+1 503 771 0482",
    "sg:postcode":"97206",
    "sg:province":"OR",
    "sg:tags":[
        "business"
    ],
    "wof:name":"Adam Fischler Consulting",
    "wof:placetype":"venue"
},
  "geometry": {"coordinates":[-122.61299,45.489489],"type":"Point"}
}