{
  "type": "Feature",
  "properties": {
    "addr:full":"534 SW 3rd Ave Portland OR 97204",
    "addr:housenumber":"534",
    "addr:postcode":"97204",
    "addr:street":"Sw 3Rd Ave",
    "iso:country":"US",
    "sg:address":"534 SW 3rd Ave",
    "sg:city":"Portland",
    "sg:classifiers":[
        {
            "category":"Retail",
            "subcategory":"Repair Shop",
            "type":"Services"
        }
    ],
    "sg:phone":"+1 503 274 1474",
    "sg:postcode":"97204",
    "sg:province":"OR",
    "sg:tags":[
        "jewelry"
    ],
    "wof:name":"T E Jewelers",
    "wof:placetype":"venue"
},
  "geometry": {"coordinates":[-122.67501799999999,45.519125],"type":"Point"}
}