{
  "type": "Feature",
  "properties": {
    "iso:country":"US",
    "sg:address":"2051 Robertson Bridge Rd",
    "sg:city":"Grants Pass",
    "sg:classifiers":[
        {
            "category":"Manufacturing",
            "subcategory":"Apparel",
            "type":"Manufacturing & Wholesale Goods"
        }
    ],
    "sg:phone":"+1 541 474 6852",
    "sg:postcode":"97526",
    "sg:province":"OR",
    "sg:tags":[
        "textile",
        "product",
        "fabricated",
        "mfg"
    ],
    "wof:name":"Gallop n Glitz",
    "wof:placetype":"venue"
},
  "geometry": {"coordinates":[-123.451069,42.503404],"type":"Point"}
}