{
  "type": "Feature",
  "properties": {
    "addr:full":"61825 Dobbin Rd Bend OR 97702",
    "addr:housenumber":"61825",
    "addr:postcode":"97702",
    "addr:street":"Dobbin Rd",
    "iso:country":"US",
    "sg:address":"61825 Dobbin Rd",
    "sg:city":"Bend",
    "sg:classifiers":[
        {
            "category":"Retail",
            "subcategory":"Repair Shop",
            "type":"Services"
        }
    ],
    "sg:phone":"+1 541 382 2769",
    "sg:postcode":"97702",
    "sg:province":"OR",
    "sg:tags":[
        "electrical"
    ],
    "wof:name":"High Desert Radio LLC",
    "wof:placetype":"venue"
},
  "geometry": {"coordinates":[-121.242019,44.045332],"type":"Point"}
}