{
  "type": "Feature",
  "properties": {
    "iso:country":"US",
    "sg:address":"10800 SE 82nd Ave",
    "sg:city":"Portland",
    "sg:classifiers":[
        {
            "category":"Home & Garden",
            "subcategory":"Furniture",
            "type":"Retail Goods"
        }
    ],
    "sg:phone":"+1 503 655 4474",
    "sg:postcode":"97086",
    "sg:province":"OR",
    "wof:name":"Marquis Your Casual Living",
    "wof:placetype":"venue"
},
  "geometry": {"coordinates":[-122.578906,45.444861],"type":"Point"}
}