{
  "type": "Feature",
  "properties": {
    "iso:country":"US",
    "sg:address":"2865 SE Division St",
    "sg:city":"Portland",
    "sg:classifiers":[
        {
            "category":"Shopping",
            "subcategory":"Florist",
            "type":"Retail Goods"
        }
    ],
    "sg:phone":"+1 503 236 3344",
    "sg:postcode":"97202",
    "sg:province":"OR",
    "wof:name":"Urban Flora",
    "wof:placetype":"venue"
},
  "geometry": {"coordinates":[-122.636261,45.504774],"type":"Point"}
}