{
  "type": "Feature",
  "properties": {
    "addr:full":"7919 SE Stark St Portland OR 97215",
    "addr:housenumber":"7919",
    "addr:postcode":"97215",
    "addr:street":"Se Stark St",
    "iso:country":"US",
    "sg:address":"7919 SE Stark St",
    "sg:city":"Portland",
    "sg:classifiers":[
        {
            "category":"Food & Beverages",
            "subcategory":"Candy",
            "type":"Retail Goods"
        },
        {
            "category":"Shopping",
            "subcategory":"Party Supplies",
            "type":"Retail Goods"
        },
        {
            "category":"Restaurant",
            "type":"Food & Drink"
        },
        {
            "category":"Bakery",
            "type":"Food & Drink"
        }
    ],
    "sg:phone":"+1 503 254 5433",
    "sg:postcode":"97215",
    "sg:province":"OR",
    "sg:tags":[
        "cake",
        "dessert",
        "pastry",
        "wedding"
    ],
    "wof:name":"Pastrygirl",
    "wof:placetype":"venue"
},
  "geometry": {"coordinates":[-122.581974,45.519171],"type":"Point"}
}