{
  "type": "Feature",
  "properties": {
    "iso:country":"US",
    "sg:address":"225 5th St",
    "sg:city":"Springfield",
    "sg:classifiers":[
        {
            "category":"Local Transit",
            "type":"Transportation"
        }
    ],
    "sg:phone":"+1 541 726 3636",
    "sg:postcode":"97477",
    "sg:province":"OR",
    "sg:tags":[
        "fire",
        "passenger",
        "protection"
    ],
    "wof:name":"Firemed",
    "wof:placetype":"venue"
},
  "geometry": {"coordinates":[-123.01944399999999,44.047719],"type":"Point"}
}