{
  "type": "Feature",
  "properties": {
    "iso:country":"US",
    "sg:address":"3407 NW Raleigh St",
    "sg:city":"Portland",
    "sg:classifiers":[
        {
            "category":"Building & Trades",
            "subcategory":"Construction",
            "type":"Services"
        }
    ],
    "sg:phone":"+1 503 497 1071",
    "sg:postcode":"97210",
    "sg:province":"OR",
    "sg:tags":[
        "builder",
        "operative"
    ],
    "wof:name":"Charles Metcalf",
    "wof:placetype":"venue"
},
  "geometry": {"coordinates":[-122.71798800000001,45.533766],"type":"Point"}
}