{
  "type": "Feature",
  "properties": {
    "iso:country":"US",
    "sg:address":"1750 SE Ochoco St",
    "sg:city":"Portland",
    "sg:classifiers":[
        {
            "category":"Food & Beverages",
            "subcategory":"Dairy",
            "type":"Retail Goods"
        }
    ],
    "sg:phone":"+1 503 653 1232",
    "sg:postcode":"97222",
    "sg:province":"OR",
    "sg:tags":[
        "products-wholesale"
    ],
    "wof:name":"Darigold",
    "wof:placetype":"venue"
},
  "geometry": {"coordinates":[-122.646441,45.458672],"type":"Point"}
}