{
  "type": "Feature",
  "properties": {
    "iso:country":"US",
    "sg:address":"3100 Crosby Ave",
    "sg:city":"Klamath Falls",
    "sg:classifiers":[
        {
            "category":"Freight",
            "type":"Transportation"
        }
    ],
    "sg:phone":"+1 541 884 7667",
    "sg:postcode":"97603",
    "sg:province":"OR",
    "sg:tags":[
        "general"
    ],
    "wof:name":"Holing Family Partners",
    "wof:placetype":"venue"
},
  "geometry": {"coordinates":[-121.750855,42.205293],"type":"Point"}
}