{
  "type": "Feature",
  "properties": {
    "addr:full":"63 Coburg Rd Eugene OR 97401",
    "addr:housenumber":"63",
    "addr:postcode":"97401",
    "addr:street":"Coburg Rd",
    "iso:country":"US",
    "sg:address":"63 Coburg Rd",
    "sg:city":"Eugene",
    "sg:classifiers":[
        {
            "category":"Retail",
            "subcategory":"Animal Services",
            "type":"Services"
        }
    ],
    "sg:phone":"+1 541 687 7907",
    "sg:postcode":"97401",
    "sg:province":"OR",
    "sg:tags":[
        "pet",
        "grooming",
        "washing"
    ],
    "wof:name":"Oregon Trail Pet Corral",
    "wof:placetype":"venue"
},
  "geometry": {"coordinates":[-123.080051,44.062177],"type":"Point"}
}