{
  "type": "Feature",
  "properties": {
    "iso:country":"US",
    "sg:address":"20792 SW Nettle Pl",
    "sg:city":"Sherwood",
    "sg:classifiers":[
        {
            "category":"Building & Trades",
            "subcategory":"Construction",
            "type":"Services"
        }
    ],
    "sg:phone":"+1 503 625 5181",
    "sg:postcode":"97140",
    "sg:province":"OR",
    "sg:tags":[
        "general"
    ],
    "wof:name":"Stellar Homes Inc",
    "wof:placetype":"venue"
},
  "geometry": {"coordinates":[-122.850422,45.369921],"type":"Point"}
}