{
  "type": "Feature",
  "properties": {
    "addr:full":"31816 Meadowlark Loop Tangent OR 97389",
    "addr:housenumber":"31816",
    "addr:postcode":"97389",
    "addr:street":"Meadowlark Loop",
    "iso:country":"US",
    "sg:address":"31816 Meadowlark Loop",
    "sg:city":"Tangent",
    "sg:classifiers":[
        {
            "category":"Freight",
            "type":"Transportation"
        }
    ],
    "sg:phone":"+1 541 967 9585",
    "sg:postcode":"97389",
    "sg:province":"OR",
    "sg:tags":[
        "operator",
        "local",
        "trucking"
    ],
    "wof:name":"Erich Schoen Trucking",
    "wof:placetype":"venue"
},
  "geometry": {"coordinates":[-123.11318300000001,44.543205],"type":"Point"}
}