{
  "type": "Feature",
  "properties": {
    "iso:country":"US",
    "sg:address":"12602 Fry Rd NE",
    "sg:city":"Aurora",
    "sg:classifiers":[
        {
            "category":"Building & Trades",
            "subcategory":"Construction",
            "type":"Services"
        }
    ],
    "sg:phone":"+1 503 678 2640",
    "sg:postcode":"97002",
    "sg:province":"OR",
    "sg:tags":[
        "contractor",
        "painting",
        "hanging"
    ],
    "sg:website":"http://www.womaninmoon.com",
    "wof:name":"Woman In Moon",
    "wof:placetype":"venue"
},
  "geometry": {"coordinates":[-122.801868,45.214164],"type":"Point"}
}