{
  "type": "Feature",
  "properties": {
    "iso:country":"US",
    "sg:address":"2461 NW Monroe Ave",
    "sg:city":"Corvallis",
    "sg:classifiers":[
        {
            "category":"Sports & Exercise",
            "subcategory":"Bowling",
            "type":"Entertainment"
        }
    ],
    "sg:phone":"+1 541 757 7356",
    "sg:postcode":"97330",
    "sg:province":"OR",
    "sg:tags":[
        "center"
    ],
    "wof:name":"Shogun Bowl",
    "wof:placetype":"venue"
},
  "geometry": {"coordinates":[-123.278279,44.568676],"type":"Point"}
}