{
  "type": "Feature",
  "properties": {
    "iso:country":"US",
    "sg:address":"1138 NW Stannium Rd",
    "sg:city":"Bend",
    "sg:classifiers":[
        {
            "category":"Recreation",
            "type":"Entertainment"
        }
    ],
    "sg:phone":"+1 541 330 0607",
    "sg:postcode":"97701",
    "sg:province":"OR",
    "wof:name":"Yoga & The Healing Arts",
    "wof:placetype":"venue"
},
  "geometry": {"coordinates":[-121.338565,44.058702],"type":"Point"}
}