{
  "type": "Feature",
  "properties": {
    "iso:country":"US",
    "sg:address":"35582 Zephyr Way",
    "sg:city":"Pleasant Hill",
    "sg:classifiers":[
        {
            "category":"Education",
            "subcategory":"School",
            "type":"Public Place"
        }
    ],
    "sg:phone":"+1 541 746 1708",
    "sg:postcode":"97455",
    "sg:province":"OR",
    "sg:tags":[
        "elementary",
        "secondary"
    ],
    "wof:name":"Emerald Junior Academy",
    "wof:placetype":"venue"
},
  "geometry": {"coordinates":[-122.94667800000001,43.97987],"type":"Point"}
}