{
  "type": "Feature",
  "properties": {
    "iso:country":"US",
    "sg:address":"1295 Oregon Ave SE",
    "sg:city":"Bandon",
    "sg:classifiers":[
        {
            "category":"Health Services",
            "subcategory":"Doctor",
            "type":"Services"
        }
    ],
    "sg:phone":"+1 541 347 9042",
    "sg:postcode":"97411",
    "sg:province":"OR",
    "sg:tags":[
        "physician",
        "surgeon"
    ],
    "wof:name":"Gregory A Aitchison MD",
    "wof:placetype":"venue"
},
  "geometry": {"coordinates":[-124.415029,43.111553],"type":"Point"}
}