{
  "type": "Feature",
  "properties": {
    "iso:country":"US",
    "sg:address":"164 NE 4th Ave",
    "sg:city":"Hillsboro",
    "sg:classifiers":[
        {
            "category":"Building & Trades",
            "subcategory":"Cleaning & Sanitation",
            "type":"Services"
        }
    ],
    "sg:phone":"+1 503 681 4964",
    "sg:postcode":"97124",
    "sg:province":"OR",
    "sg:tags":[
        "window",
        "maintenance"
    ],
    "wof:name":"Robert's Window Cleaning Svc",
    "wof:placetype":"venue"
},
  "geometry": {"coordinates":[-122.984258,45.523033],"type":"Point"}
}