{
  "type": "Feature",
  "properties": {
    "iso:country":"US",
    "sg:address":"1770 McCormick Loop Rd",
    "sg:city":"Tillamook",
    "sg:classifiers":[
        {
            "category":"Professional",
            "subcategory":"Business Services",
            "type":"Services"
        }
    ],
    "sg:phone":"+1 503 842 1416",
    "sg:postcode":"97141",
    "sg:province":"OR",
    "wof:name":"Sue M Jacob",
    "wof:placetype":"venue"
},
  "geometry": {"coordinates":[-123.80124499999999,45.443348],"type":"Point"}
}