{
  "type": "Feature",
  "properties": {
    "iso:country":"US",
    "sg:address":"21524 SW Wallace Pl",
    "sg:city":"Sherwood",
    "sg:classifiers":[
        {
            "category":"Professional",
            "subcategory":"Business Services",
            "type":"Services"
        }
    ],
    "sg:phone":"+1 503 625 9004",
    "sg:postcode":"97140",
    "sg:province":"OR",
    "sg:tags":[
        "real estate"
    ],
    "wof:name":"Elite Home Inspection",
    "wof:placetype":"venue"
},
  "geometry": {"coordinates":[-122.843835,45.363883],"type":"Point"}
}