{
  "type": "Feature",
  "properties": {
    "iso:country":"US",
    "sg:address":"71888 E Linden Rd",
    "sg:city":"Rhododendron",
    "sg:classifiers":[
        {
            "category":"Building & Trades",
            "subcategory":"Construction",
            "type":"Services"
        }
    ],
    "sg:phone":"+1 503 622 5851",
    "sg:postcode":"97049",
    "sg:province":"OR",
    "sg:tags":[
        "house"
    ],
    "wof:name":"Jordan River Construction",
    "wof:placetype":"venue"
},
  "geometry": {"coordinates":[-121.92518200000001,45.368683],"type":"Point"}
}