{
  "type": "Feature",
  "properties": {
    "iso:country":"US",
    "sg:address":"205 3rd St",
    "sg:city":"Hood River",
    "sg:classifiers":[
        {
            "category":"Professional",
            "subcategory":"Lawyer & Legal Services",
            "type":"Services"
        }
    ],
    "sg:phone":"+1 541 386 1311",
    "sg:postcode":"97031",
    "sg:province":"OR",
    "sg:tags":[
        "attorney"
    ],
    "wof:name":"Jaques Sharp Sherrerd",
    "wof:placetype":"venue"
},
  "geometry": {"coordinates":[-121.513231,45.708823],"type":"Point"}
}