{
  "type": "Feature",
  "properties": {
    "iso:country":"US",
    "sg:address":"116 Lithia Way",
    "sg:city":"Ashland",
    "sg:classifiers":[
        {
            "category":"Professional",
            "subcategory":"Management & Consulting",
            "type":"Services"
        },
        {
            "category":"Organizations",
            "subcategory":"Community Association",
            "type":"Services"
        }
    ],
    "sg:phone":"+1 541 482 4878",
    "sg:postcode":"97520",
    "sg:province":"OR",
    "sg:tags":[
        "environmental",
        "business",
        "org"
    ],
    "wof:name":"World Wildlife Fund",
    "wof:placetype":"venue"
},
  "geometry": {"coordinates":[-122.713329,42.197129],"type":"Point"}
}