{
  "type": "Feature",
  "properties": {
    "iso:country":"US",
    "sg:address":"1570 Lancaster Dr NE",
    "sg:city":"Salem",
    "sg:classifiers":[
        {
            "category":"Recreation",
            "type":"Entertainment"
        }
    ],
    "sg:phone":"+1 503 589 9640",
    "sg:postcode":"97301",
    "sg:province":"OR",
    "wof:name":"Maria Irma Luna",
    "wof:placetype":"venue"
},
  "geometry": {"coordinates":[-122.98362899999999,44.948097],"type":"Point"}
}