{
  "type": "Feature",
  "properties": {
    "iso:country":"US",
    "sg:address":"2602 SE 28th Place",
    "sg:city":"Portland",
    "sg:classifiers":[
        {
            "category":"Real Estate",
            "subcategory":"Architect",
            "type":"Services"
        }
    ],
    "sg:phone":"+1 503 238 7777",
    "sg:postcode":"97202",
    "sg:province":"OR",
    "wof:name":"John Cava Architect",
    "wof:placetype":"venue"
},
  "geometry": {"coordinates":[-122.636751,45.504038],"type":"Point"}
}