{
  "type": "Feature",
  "properties": {
    "addr:full":"12010 SW Allen Blvd Beaverton OR 97005",
    "addr:housenumber":"12010",
    "addr:postcode":"97005",
    "addr:street":"Sw Allen Blvd",
    "iso:country":"US",
    "sg:address":"12010 SW Allen Blvd",
    "sg:city":"Beaverton",
    "sg:classifiers":[
        {
            "category":"Shopping",
            "subcategory":"Clothing, Apparel, & Fashions",
            "type":"Retail Goods"
        }
    ],
    "sg:phone":"+1 503 526 8501",
    "sg:postcode":"97005",
    "sg:province":"OR",
    "wof:name":"Firme Clothing",
    "wof:placetype":"venue"
},
  "geometry": {"coordinates":[-122.804084,45.476402],"type":"Point"}
}