{
  "type": "Feature",
  "properties": {
    "iso:country":"US",
    "sg:address":"1250 Siskiyou Blvd",
    "sg:city":"Medford",
    "sg:classifiers":[
        {
            "category":"Manufacturing",
            "subcategory":"Printing",
            "type":"Manufacturing & Wholesale Goods"
        }
    ],
    "sg:phone":"+1 541 552 6307",
    "sg:postcode":"97504",
    "sg:province":"OR",
    "sg:tags":[
        "newspaper"
    ],
    "wof:name":"SOU-Siskiyou Newspaper",
    "wof:placetype":"venue"
},
  "geometry": {"coordinates":[-122.858333,42.32146],"type":"Point"}
}