{
  "type": "Feature",
  "properties": {
    "iso:country":"US",
    "sg:address":"321 SW 4th Ave",
    "sg:city":"Portland",
    "sg:classifiers":[
        {
            "category":"Professional",
            "subcategory":"Management & Consulting",
            "type":"Services"
        }
    ],
    "sg:phone":"+1 503 224 9033",
    "sg:postcode":"97204",
    "sg:province":"OR",
    "sg:tags":[
        "fuel"
    ],
    "wof:name":"Mesch Capital Management",
    "wof:placetype":"venue"
},
  "geometry": {"coordinates":[-122.675494,45.520689],"type":"Point"}
}