{
  "type": "Feature",
  "properties": {
    "addr:full":"110 S 2nd St Silverton OR 97381",
    "addr:housenumber":"110",
    "addr:postcode":"97381",
    "addr:street":"S 2Nd St",
    "iso:country":"US",
    "sg:address":"110 S 2nd St",
    "sg:city":"Silverton",
    "sg:classifiers":[
        {
            "category":"Retail",
            "subcategory":"Auto Repair",
            "type":"Services"
        }
    ],
    "sg:phone":"+1 503 873 3995",
    "sg:postcode":"97381",
    "sg:province":"OR",
    "sg:tags":[
        "automotive",
        "general"
    ],
    "wof:name":"Redhead Engines",
    "wof:placetype":"venue"
},
  "geometry": {"coordinates":[-122.780884,45.005917],"type":"Point"}
}