{
  "type": "Feature",
  "properties": {
    "iso:country":"US",
    "sg:address":"909 N Tomahawk Island Drive",
    "sg:city":"Portland",
    "sg:classifiers":[
        {
            "category":"Travel",
            "subcategory":"Hotels & Motels",
            "type":"Entertainment"
        }
    ],
    "sg:phone":"+1 503 283 4466",
    "sg:postcode":"97217",
    "sg:province":"OR",
    "wof:name":"Shennanigans Restaurant & Lounge On the Columbia River",
    "wof:placetype":"venue"
},
  "geometry": {"coordinates":[-122.675611,45.610017],"type":"Point"}
}