{
  "type": "Feature",
  "properties": {
    "iso:country":"US",
    "sg:address":"381 Hogan Rd",
    "sg:city":"Oakland",
    "sg:classifiers":[
        {
            "category":"Food & Beverages",
            "subcategory":"Liquor & Beverages",
            "type":"Retail Goods"
        }
    ],
    "sg:phone":"+1 541 459 4499",
    "sg:postcode":"97462",
    "sg:province":"OR",
    "sg:tags":[
        "alcoholic"
    ],
    "wof:name":"Umpqua Valley Wine Center",
    "wof:placetype":"venue"
},
  "geometry": {"coordinates":[-123.288744,43.487541],"type":"Point"}
}