{
  "type": "Feature",
  "properties": {
    "addr:full":"1391 NE Village St Fairview OR 97024",
    "addr:housenumber":"1391",
    "addr:postcode":"97024",
    "addr:street":"Ne Village St",
    "iso:country":"US",
    "sg:address":"1391 NE Village St",
    "sg:city":"Fairview",
    "sg:classifiers":[
        {
            "category":"Wholesale",
            "subcategory":"Non-durable Goods",
            "type":"Manufacturing & Wholesale Goods"
        }
    ],
    "sg:phone":"+1 503 492 1719",
    "sg:postcode":"97024",
    "sg:province":"OR",
    "sg:tags":[
        "badge"
    ],
    "wof:name":"Quick Badge & Sign Co",
    "wof:placetype":"venue"
},
  "geometry": {"coordinates":[-122.43932,45.531412],"type":"Point"}
}