{
  "type": "Feature",
  "properties": {
    "addr:full":"16759 Boones Ferry Rd Lake Oswego OR 97035",
    "addr:housenumber":"16759",
    "addr:postcode":"97035",
    "addr:street":"Boones Ferry Rd",
    "iso:country":"US",
    "sg:address":"16759 Boones Ferry Rd",
    "sg:city":"Lake Oswego",
    "sg:classifiers":[
        {
            "category":"Professional",
            "subcategory":"Advertising",
            "type":"Services"
        }
    ],
    "sg:phone":"+1 503 699 9702",
    "sg:postcode":"97035",
    "sg:province":"OR",
    "wof:name":"Ask The Red Head",
    "wof:placetype":"venue"
},
  "geometry": {"coordinates":[-122.730306,45.404371],"type":"Point"}
}