{
  "type": "Feature",
  "properties": {
    "iso:country":"US",
    "sg:address":"1200 NW Marshall St",
    "sg:city":"Portland",
    "sg:classifiers":[
        {
            "category":"Real Estate",
            "subcategory":"Real Estate Operator",
            "type":"Services"
        }
    ],
    "sg:phone":"+1 503 243 3600",
    "sg:postcode":"97209",
    "sg:province":"OR",
    "sg:tags":[
        "apartment"
    ],
    "wof:name":"ASA Flats and Lofts",
    "wof:placetype":"venue"
},
  "geometry": {"coordinates":[-122.683404,45.530653],"type":"Point"}
}