{
  "type": "Feature",
  "properties": {
    "iso:country":"US",
    "sg:address":"884 S Broadway",
    "sg:city":"Coos Bay",
    "sg:classifiers":[
        {
            "category":"Retail",
            "subcategory":"Repair Shop",
            "type":"Services"
        }
    ],
    "sg:phone":"+1 541 269 5285",
    "sg:postcode":"97420",
    "sg:province":"OR",
    "sg:tags":[
        "lock",
        "safe",
        "work",
        "key"
    ],
    "wof:name":"Johns Safe & Service Repair",
    "wof:placetype":"venue"
},
  "geometry": {"coordinates":[-124.213195,43.35979],"type":"Point"}
}