{
  "type": "Feature",
  "properties": {
    "iso:country":"US",
    "sg:address":"2011 25th St SE",
    "sg:city":"Salem",
    "sg:classifiers":[
        {
            "category":"Autos & Motor Vehicles",
            "subcategory":"Automobile Sales",
            "type":"Retail Goods"
        }
    ],
    "sg:phone":"+1 503 399 0058",
    "sg:postcode":"97301",
    "sg:province":"OR",
    "sg:tags":[
        "car",
        "dealer"
    ],
    "wof:name":"Capitol Auto Group Fleet Sales",
    "wof:placetype":"venue"
},
  "geometry": {"coordinates":[-123.010375,44.916794],"type":"Point"}
}