{
  "type": "Feature",
  "properties": {
    "addr:full":"2085 Pacific Blvd SW Albany OR 97321",
    "addr:housenumber":"2085",
    "addr:postcode":"97321",
    "addr:street":"Pacific Blvd Sw",
    "iso:country":"US",
    "sg:address":"2085 Pacific Blvd SW",
    "sg:city":"Albany",
    "sg:classifiers":[
        {
            "category":"Professional",
            "type":"Services"
        },
        {
            "category":"Retail",
            "subcategory":"Auto Rental",
            "type":"Services"
        },
        {
            "category":"Building & Trades",
            "subcategory":"Equipment Rental",
            "type":"Services"
        },
        {
            "category":"Retail",
            "subcategory":"Storage",
            "type":"Services"
        }
    ],
    "sg:phone":"+1 866 205 7339",
    "sg:postcode":"97321",
    "sg:province":"OR",
    "sg:tags":[
        "renting",
        "moving-self",
        "leasing",
        "material",
        "moving",
        "services-labor",
        "truck",
        "trailer"
    ],
    "sg:website":"http://www.pensketruckrental.com/personal_rental/?cid=Yptmlist",
    "wof:name":"Penske Truck Rental",
    "wof:placetype":"venue"
},
  "geometry": {"coordinates":[-123.111481,44.621273],"type":"Point"}
}