{
  "type": "Feature",
  "properties": {
    "iso:country":"US",
    "sg:address":"2873 SW Labbe Ave",
    "sg:city":"Portland",
    "sg:classifiers":[
        {
            "category":"Structure",
            "subcategory":"Office Building",
            "type":"Public Place"
        }
    ],
    "sg:phone":"+1 503 224 5678",
    "sg:postcode":"97221",
    "sg:province":"OR",
    "sg:tags":[
        "park"
    ],
    "wof:name":"Evergreen Innovations",
    "wof:placetype":"venue"
},
  "geometry": {"coordinates":[-122.71569599999999,45.502145],"type":"Point"}
}