{
  "type": "Feature",
  "properties": {
    "addr:full":"3600 N Interstate Ave Portland OR 97227",
    "addr:housenumber":"3600",
    "addr:postcode":"97227",
    "addr:street":"N Interstate Ave",
    "iso:country":"US",
    "sg:address":"3600 N Interstate Ave",
    "sg:city":"Portland",
    "sg:phone":"+1 503 285 9321",
    "sg:postcode":"97227",
    "sg:province":"OR",
    "sg:website":"http://www.kaiserpermanente.org",
    "wof:name":"Kaiser Permanente Health Care",
    "wof:placetype":"venue"
},
  "geometry": {"coordinates":[-122.68087,45.547798],"type":"Point"}
}