{
  "type": "Feature",
  "properties": {
    "iso:country":"US",
    "sg:address":"16671 SW Henderson Ct",
    "sg:city":"Beaverton",
    "sg:classifiers":[
        {
            "category":"Food & Beverages",
            "subcategory":"Groceries & Convenience Stores",
            "type":"Retail Goods"
        }
    ],
    "sg:phone":"+1 503 848 6456",
    "sg:postcode":"97007",
    "sg:province":"OR",
    "wof:name":"Finer Lines Inc",
    "wof:placetype":"venue"
},
  "geometry": {"coordinates":[-122.847921,45.464278],"type":"Point"}
}