{
  "type": "Feature",
  "properties": {
    "addr:full":"150 N Marple St Coos Bay OR 97420",
    "addr:housenumber":"150",
    "addr:postcode":"97420",
    "addr:street":"N Marple St",
    "iso:country":"US",
    "sg:address":"150 N Marple St",
    "sg:city":"Coos Bay",
    "sg:classifiers":[
        {
            "category":"Education",
            "subcategory":"School",
            "type":"Public Place"
        }
    ],
    "sg:phone":"+1 541 269 1191",
    "sg:postcode":"97420",
    "sg:province":"OR",
    "wof:name":"Coos Bay Public School Dst",
    "wof:placetype":"venue"
},
  "geometry": {"coordinates":[-124.275667,43.393358],"type":"Point"}
}