{
  "type": "Feature",
  "properties": {
    "iso:country":"US",
    "sg:address":"486 Walnut Dr S",
    "sg:city":"Monmouth",
    "sg:classifiers":[
        {
            "category":"Building & Trades",
            "subcategory":"Construction",
            "type":"Services"
        }
    ],
    "sg:phone":"+1 503 838 5759",
    "sg:postcode":"97361",
    "sg:province":"OR",
    "sg:tags":[
        "concrete",
        "contractor"
    ],
    "wof:name":"Canning R A General Contractor",
    "wof:placetype":"venue"
},
  "geometry": {"coordinates":[-123.244769,44.845296],"type":"Point"}
}