{
  "type": "Feature",
  "properties": {
    "addr:full":"6665 SW Hampton St Tigard OR 97223",
    "addr:housenumber":"6665",
    "addr:postcode":"97223",
    "addr:street":"Sw Hampton St",
    "iso:country":"US",
    "sg:address":"6665 SW Hampton St",
    "sg:city":"Tigard",
    "sg:classifiers":[
        {
            "category":"Real Estate",
            "subcategory":"Surveying",
            "type":"Services"
        }
    ],
    "sg:phone":"+1 503 209 0558",
    "sg:postcode":"97223",
    "sg:province":"OR",
    "sg:tags":[
        "surveyor"
    ],
    "wof:name":"Bluedot Group",
    "wof:placetype":"venue"
},
  "geometry": {"coordinates":[-122.74528100000001,45.427564],"type":"Point"}
}