{
  "type": "Feature",
  "properties": {
    "iso:country":"US",
    "sg:address":"76 Oregon City Shopping Center",
    "sg:city":"Oregon City",
    "sg:classifiers":[
        {
            "category":"Restaurant",
            "type":"Food & Drink"
        }
    ],
    "sg:menulink":"http://www.allmenus.com/or/northwest-clackamas/49839-la-hacienda/menu/",
    "sg:phone":"+1 503 656 2210",
    "sg:postcode":"97045",
    "sg:province":"OR",
    "sg:tags":[
        "peruvian"
    ],
    "wof:name":"La Hacienda",
    "wof:placetype":"venue"
},
  "geometry": {"coordinates":[-122.569576,45.372585],"type":"Point"}
}