{
  "type": "Feature",
  "properties": {
    "addr:full":"11125 SE Foster Rd Portland OR 97266",
    "addr:housenumber":"11125",
    "addr:postcode":"97266",
    "addr:street":"Se Foster Rd",
    "iso:country":"US",
    "sg:address":"11125 SE Foster Rd",
    "sg:city":"Portland",
    "sg:classifiers":[
        {
            "category":"Home & Garden",
            "subcategory":"Building Materials",
            "type":"Retail Goods"
        }
    ],
    "sg:phone":"+1 503 760 8242",
    "sg:postcode":"97266",
    "sg:province":"OR",
    "sg:tags":[
        "supply",
        "heating",
        "system",
        "equipment",
        "part",
        "furnace"
    ],
    "wof:name":"Abilco C & L",
    "wof:placetype":"venue"
},
  "geometry": {"coordinates":[-122.548598,45.476142],"type":"Point"}
}