{
  "type": "Feature",
  "properties": {
    "iso:country":"US",
    "sg:address":"13515 SW Millikan Way",
    "sg:city":"Beaverton",
    "sg:classifiers":[
        {
            "category":"Building & Trades",
            "subcategory":"Cleaning & Sanitation",
            "type":"Services"
        }
    ],
    "sg:phone":"+1 503 520 1660",
    "sg:postcode":"97005",
    "sg:province":"OR",
    "sg:tags":[
        "janitorial"
    ],
    "sg:website":"http://www.cbm-sys.com",
    "wof:name":"Cbm Of Oregon",
    "wof:placetype":"venue"
},
  "geometry": {"coordinates":[-122.817196,45.492099],"type":"Point"}
}