{
  "type": "Feature",
  "properties": {
    "addr:full":"102 S St Halfway OR 97838",
    "addr:housenumber":"102",
    "addr:postcode":"97838",
    "addr:street":"S St",
    "iso:country":"US",
    "sg:address":"102 S St",
    "sg:city":"Halfway",
    "sg:classifiers":[
        {
            "category":"Retail",
            "subcategory":"Repair Shop",
            "type":"Services"
        }
    ],
    "sg:phone":"+1 541 742 2233",
    "sg:postcode":"97838",
    "sg:province":"OR",
    "wof:name":"Blue Sky Gun Works",
    "wof:placetype":"venue"
},
  "geometry": {"coordinates":[-119.310588,45.829549],"type":"Point"}
}