{
  "type": "Feature",
  "properties": {
    "addr:full":"2106 NE 40th Ave Portland OR 97212",
    "addr:housenumber":"2106",
    "addr:postcode":"97212",
    "addr:street":"Ne 40Th Ave",
    "iso:country":"US",
    "sg:address":"2106 NE 40th Ave",
    "sg:city":"Portland",
    "sg:classifiers":[
        {
            "category":"Social Services",
            "type":"Services"
        }
    ],
    "sg:phone":"+1 503 249 9997",
    "sg:postcode":"97212",
    "sg:province":"OR",
    "sg:tags":[
        "counselor",
        "marriage",
        "family"
    ],
    "wof:name":"Patrick Welly",
    "wof:placetype":"venue"
},
  "geometry": {"coordinates":[-122.621877,45.539],"type":"Point"}
}