{
  "type": "Feature",
  "properties": {
    "iso:country":"US",
    "sg:address":"208 S River St",
    "sg:city":"Enterprise",
    "sg:classifiers":[
        {
            "category":"Building & Trades",
            "subcategory":"Electrical",
            "type":"Services"
        }
    ],
    "sg:phone":"+1 541 426 3344",
    "sg:postcode":"97828",
    "sg:province":"OR",
    "sg:tags":[
        "electric",
        "contractor"
    ],
    "wof:name":"J B Bane & Co",
    "wof:placetype":"venue"
},
  "geometry": {"coordinates":[-117.277638,45.424531],"type":"Point"}
}