{
  "type": "Feature",
  "properties": {
    "addr:full":"804 Hillview Dr Ashland OR 97520",
    "addr:housenumber":"804",
    "addr:postcode":"97520",
    "addr:street":"Hillview Dr",
    "iso:country":"US",
    "sg:address":"804 Hillview Dr",
    "sg:city":"Ashland",
    "sg:classifiers":[
        {
            "category":"Place Of Worship",
            "subcategory":"Synagogue",
            "type":"Public Place"
        },
        {
            "category":"Place Of Worship",
            "type":"Public Place"
        }
    ],
    "sg:phone":"+1 541 482 2778",
    "sg:postcode":"97520",
    "sg:province":"OR",
    "sg:tags":[
        "synagogues-reform",
        "church"
    ],
    "wof:name":"Chabad Jewish Center Of Southe",
    "wof:placetype":"venue"
},
  "geometry": {"coordinates":[-122.683637,42.181283],"type":"Point"}
}