{
  "type": "Feature",
  "properties": {
    "iso:country":"US",
    "sg:address":"905 Queen Ave SW",
    "sg:city":"Albany",
    "sg:classifiers":[
        {
            "category":"Health Services",
            "subcategory":"Chiropractor",
            "type":"Services"
        }
    ],
    "sg:phone":"+1 541 928 8262",
    "sg:postcode":"97321",
    "sg:province":"OR",
    "sg:tags":[
        "therapist",
        "massage"
    ],
    "wof:name":"Gross Chiropractic Clinic",
    "wof:placetype":"venue"
},
  "geometry": {"coordinates":[-123.112674,44.623789],"type":"Point"}
}