{
  "type": "Feature",
  "properties": {
    "iso:country":"US",
    "sg:address":"4079 NW Logan Rd",
    "sg:city":"Lincoln City",
    "sg:classifiers":[
        {
            "category":"Shopping",
            "subcategory":"Optical Goods",
            "type":"Retail Goods"
        }
    ],
    "sg:phone":"+1 541 994 6442",
    "sg:postcode":"97367",
    "sg:province":"OR",
    "wof:name":"CHS Optical",
    "wof:placetype":"venue"
},
  "geometry": {"coordinates":[-124.005285,44.997682],"type":"Point"}
}