{
  "type": "Feature",
  "properties": {
    "iso:country":"US",
    "sg:address":"2114 SE Clinton St",
    "sg:city":"Portland",
    "sg:classifiers":[
        {
            "category":"Professional",
            "subcategory":"Management & Consulting",
            "type":"Services"
        }
    ],
    "sg:phone":"+1 503 234 7710",
    "sg:postcode":"97202",
    "sg:province":"OR",
    "sg:tags":[
        "marketing"
    ],
    "wof:name":"Polaris Inc",
    "wof:placetype":"venue"
},
  "geometry": {"coordinates":[-122.643704,45.503315],"type":"Point"}
}