{
  "type": "Feature",
  "properties": {
    "addr:full":"1236 Lloyd Center Portland OR 97232",
    "addr:housenumber":"1236",
    "addr:postcode":"97232",
    "addr:street":"Lloyd",
    "iso:country":"US",
    "sg:address":"1236 Lloyd Center",
    "sg:city":"Portland",
    "sg:classifiers":[
        {
            "category":"Cinema",
            "subcategory":"Movie Rental",
            "type":"Entertainment"
        }
    ],
    "sg:phone":"+1 503 288 8797",
    "sg:postcode":"97232",
    "sg:province":"OR",
    "sg:tags":[
        "game",
        "video"
    ],
    "wof:name":"Suncoast Motion Picture Company #3239",
    "wof:placetype":"venue"
},
  "geometry": {"coordinates":[-122.65435600000001,45.531777],"type":"Point"}
}