{
  "type": "Feature",
  "properties": {
    "iso:country":"US",
    "sg:address":"256 E Olive St",
    "sg:city":"Newport",
    "sg:classifiers":[
        {
            "category":"Home & Garden",
            "subcategory":"Furniture",
            "type":"Retail Goods"
        }
    ],
    "sg:phone":"+1 541 265 4460",
    "sg:postcode":"97365",
    "sg:province":"OR",
    "sg:tags":[
        "mattress"
    ],
    "wof:name":"Factory Mattress Outlet Inc",
    "wof:placetype":"venue"
},
  "geometry": {"coordinates":[-124.050156,44.636237],"type":"Point"}
}