{
  "type": "Feature",
  "properties": {
    "addr:full":"14567 SE Creekside Dr Milwaukie OR 97267",
    "addr:housenumber":"14567",
    "addr:postcode":"97267",
    "addr:street":"Se Creekside Dr",
    "iso:country":"US",
    "sg:address":"14567 SE Creekside Dr",
    "sg:city":"Milwaukie",
    "sg:classifiers":[
        {
            "category":"Retail",
            "subcategory":"Repair Shop",
            "type":"Services"
        }
    ],
    "sg:phone":"+1 503 661 5044",
    "sg:postcode":"97267",
    "sg:province":"OR",
    "sg:tags":[
        "instrument",
        "musical"
    ],
    "wof:name":"Sandy River Guitar Repair",
    "wof:placetype":"venue"
},
  "geometry": {"coordinates":[-122.597504,45.41764],"type":"Point"}
}