{
  "type": "Feature",
  "properties": {
    "addr:full":"6841 E Ct Springfield OR 97478",
    "addr:housenumber":"6841",
    "addr:postcode":"97478",
    "addr:street":"E Ct",
    "iso:country":"US",
    "sg:address":"6841 E Ct",
    "sg:city":"Springfield",
    "sg:classifiers":[
        {
            "category":"Travel",
            "subcategory":"Travel Agent",
            "type":"Entertainment"
        }
    ],
    "sg:phone":"+1 541 747 8947",
    "sg:postcode":"97478",
    "sg:province":"OR",
    "sg:tags":[
        "operator",
        "tour"
    ],
    "wof:name":"Cruise Tour & Travel Head",
    "wof:placetype":"venue"
},
  "geometry": {"coordinates":[-122.905342,44.051275],"type":"Point"}
}