{
  "type": "Feature",
  "properties": {
    "addr:full":"191 51st St Springfield OR 97478",
    "addr:housenumber":"191",
    "addr:postcode":"97478",
    "addr:street":"51St St",
    "iso:country":"US",
    "sg:address":"191 51st St",
    "sg:city":"Springfield",
    "sg:classifiers":[
        {
            "category":"Retail",
            "subcategory":"Repair Shop",
            "type":"Services"
        }
    ],
    "sg:phone":"+1 541 744 1422",
    "sg:postcode":"97478",
    "sg:province":"OR",
    "sg:tags":[
        "appliance"
    ],
    "wof:name":"Appliance Repair",
    "wof:placetype":"venue"
},
  "geometry": {"coordinates":[-122.94251199999999,44.047088],"type":"Point"}
}