{
  "type": "Feature",
  "properties": {
    "iso:country":"US",
    "sg:address":"431 Oak St",
    "sg:city":"Central Point",
    "sg:classifiers":[
        {
            "category":"Real Estate",
            "subcategory":"Surveying",
            "type":"Services"
        }
    ],
    "sg:phone":"+1 541 664 5599",
    "sg:postcode":"97502",
    "sg:province":"OR",
    "sg:tags":[
        "surveyor"
    ],
    "wof:name":"Farber Surveying",
    "wof:placetype":"venue"
},
  "geometry": {"coordinates":[-122.913108,42.375121],"type":"Point"}
}