{
  "type": "Feature",
  "properties": {
    "iso:country":"US",
    "sg:address":"1190 State Hwy 99 N",
    "sg:city":"Eugene",
    "sg:classifiers":[
        {
            "category":"Shopping",
            "subcategory":"Computers & Home Electronics",
            "type":"Retail Goods"
        }
    ],
    "sg:phone":"+1 541 465 1794",
    "sg:postcode":"97402",
    "sg:province":"OR",
    "sg:tags":[
        "equipment",
        "dealer"
    ],
    "wof:name":"Lbs Computer & Peripherals",
    "wof:placetype":"venue"
},
  "geometry": {"coordinates":[-123.14977,44.077694],"type":"Point"}
}