{
  "type": "Feature",
  "properties": {
    "iso:country":"US",
    "sg:address":"4813 Chameleon Ct NE",
    "sg:city":"Salem",
    "sg:classifiers":[
        {
            "category":"Building & Trades",
            "subcategory":"Cleaning & Sanitation",
            "type":"Services"
        }
    ],
    "sg:phone":"+1 503 393 0118",
    "sg:postcode":"97305",
    "sg:province":"OR",
    "sg:tags":[
        "maintenance"
    ],
    "wof:name":"Pacific Maintenance Services",
    "wof:placetype":"venue"
},
  "geometry": {"coordinates":[-122.963778,44.974435],"type":"Point"}
}