{
  "type": "Feature",
  "properties": {
    "iso:country":"US",
    "sg:address":"5655 Commercial St SE",
    "sg:city":"Salem",
    "sg:phone":"+1 503 581 4169",
    "sg:postcode":"97306",
    "sg:province":"OR",
    "sg:tags":[
        "equipment",
        "commercial"
    ],
    "wof:name":"Salem Restaurant Equipment",
    "wof:placetype":"venue"
},
  "geometry": {"coordinates":[-123.024714,44.87306],"type":"Point"}
}