{
  "type": "Feature",
  "properties": {
    "addr:full":"1940 NE 10th St Hermiston OR 97838",
    "addr:housenumber":"1940",
    "addr:postcode":"97838",
    "addr:street":"Ne 10Th St",
    "iso:country":"US",
    "sg:address":"1940 NE 10th St",
    "sg:city":"Hermiston",
    "sg:classifiers":[
        {
            "category":"Organizations",
            "subcategory":"Religious Organization",
            "type":"Services"
        }
    ],
    "sg:phone":"+1 541 567 4494",
    "sg:postcode":"97838",
    "sg:province":"OR",
    "sg:tags":[
        "church"
    ],
    "wof:name":"Victory Lighthouse Church",
    "wof:placetype":"venue"
},
  "geometry": {"coordinates":[-119.269223,45.858293],"type":"Point"}
}