{
  "type": "Feature",
  "properties": {
    "iso:country":"US",
    "sg:address":"3975 Commercial St SE",
    "sg:city":"Salem",
    "sg:classifiers":[
        {
            "category":"Social Services",
            "type":"Services"
        }
    ],
    "sg:phone":"+1 503 378 6327",
    "sg:postcode":"97302",
    "sg:province":"OR",
    "sg:tags":[
        "government"
    ],
    "wof:name":"Adult & Family Svc",
    "wof:placetype":"venue"
},
  "geometry": {"coordinates":[-123.038887,44.899721],"type":"Point"}
}