{
  "type": "Feature",
  "properties": {
    "addr:full":"321 Clay St Spc 39 Ashland OR 97520",
    "addr:housenumber":"321;39",
    "addr:postcode":"97520",
    "addr:street":"Clay St",
    "iso:country":"US",
    "sg:address":"321 Clay St Spc 39",
    "sg:city":"Ashland",
    "sg:classifiers":[
        {
            "category":"Building & Trades",
            "subcategory":"Construction",
            "type":"Services"
        }
    ],
    "sg:phone":"+1 541 324 1013",
    "sg:postcode":"97520",
    "sg:province":"OR",
    "sg:tags":[
        "wallcoverings-installation",
        "wallpaper"
    ],
    "wof:name":"Interr Pntng Dg Hm",
    "wof:placetype":"venue"
},
  "geometry": {"coordinates":[-122.676422,42.188837],"type":"Point"}
}