{
  "type": "Feature",
  "properties": {
    "iso:country":"US",
    "sg:address":"2300 SE Harrison St",
    "sg:city":"Milwaukie",
    "sg:classifiers":[
        {
            "category":"Education",
            "subcategory":"School",
            "type":"Public Place"
        }
    ],
    "sg:phone":"+1 503 654 2200",
    "sg:postcode":"97222",
    "sg:province":"OR",
    "wof:name":"Portland Waldorf School",
    "wof:placetype":"venue"
},
  "geometry": {"coordinates":[-122.63812299999999,45.446424],"type":"Point"}
}