{
  "type": "Feature",
  "properties": {
    "addr:full":"850 NW Wall St Bend OR 97701",
    "addr:housenumber":"850",
    "addr:postcode":"97701",
    "addr:street":"Nw Wall St",
    "iso:country":"US",
    "sg:address":"850 NW Wall St",
    "sg:city":"Bend",
    "sg:classifiers":[
        {
            "category":"Shopping",
            "subcategory":"Clothing, Apparel, & Fashions",
            "type":"Retail Goods"
        }
    ],
    "sg:phone":"+1 541 389 2613",
    "sg:postcode":"97701",
    "sg:province":"OR",
    "sg:tags":[
        "swimwear",
        "accessory"
    ],
    "wof:name":"At The Beach",
    "wof:placetype":"venue"
},
  "geometry": {"coordinates":[-121.31456799999999,44.058412],"type":"Point"}
}