{
  "type": "Feature",
  "properties": {
    "addr:full":"6311 SW Huber St Portland OR 97219",
    "addr:housenumber":"6311",
    "addr:postcode":"97219",
    "addr:street":"Sw Huber St",
    "iso:country":"US",
    "sg:address":"6311 SW Huber St",
    "sg:city":"Portland",
    "sg:classifiers":[
        {
            "category":"Professional",
            "subcategory":"Secretarial Services",
            "type":"Services"
        }
    ],
    "sg:phone":"+1 503 682 2652",
    "sg:postcode":"97219",
    "sg:province":"OR",
    "sg:tags":[
        "resume"
    ],
    "wof:name":"Jan Harvey Secretarial Svc",
    "wof:placetype":"venue"
},
  "geometry": {"coordinates":[-122.742908,45.452766],"type":"Point"}
}