{
  "type": "Feature",
  "properties": {
    "addr:full":"1800 NW 167th Pl Beaverton OR 97006",
    "addr:housenumber":"1800",
    "addr:postcode":"97006",
    "addr:street":"Nw 167Th Pl",
    "iso:country":"US",
    "sg:address":"1800 NW 167th Pl",
    "sg:city":"Beaverton",
    "sg:classifiers":[
        {
            "category":"Professional",
            "subcategory":"Computer Services",
            "type":"Services"
        }
    ],
    "sg:phone":"+1 503 466 9921",
    "sg:postcode":"97006",
    "sg:province":"OR",
    "sg:tags":[
        "information",
        "consulting",
        "retrieval",
        "business"
    ],
    "wof:name":"Internet Partners",
    "wof:placetype":"venue"
},
  "geometry": {"coordinates":[-122.848906,45.53279],"type":"Point"}
}