{
  "type": "Feature",
  "properties": {
    "iso:country":"US",
    "sg:address":"4693 SE Tualatin Valley Hwy",
    "sg:city":"Hillsboro",
    "sg:classifiers":[
        {
            "category":"Restaurant",
            "type":"Food & Drink"
        }
    ],
    "sg:phone":"+1 503 846 9434",
    "sg:postcode":"97123",
    "sg:province":"OR",
    "sg:tags":[
        "eating"
    ],
    "wof:name":"Buzz Espresso",
    "wof:placetype":"venue"
},
  "geometry": {"coordinates":[-122.93514999999999,45.500993],"type":"Point"}
}