{
  "type": "Feature",
  "properties": {
    "iso:country":"US",
    "sg:address":"1314 Center Dr",
    "sg:city":"Medford",
    "sg:classifiers":[
        {
            "category":"Real Estate",
            "subcategory":"Real Estate Agent",
            "type":"Services"
        }
    ],
    "sg:phone":"+1 541 857 1010",
    "sg:postcode":"97501",
    "sg:province":"OR",
    "wof:name":"Trf Real Estate",
    "wof:placetype":"venue"
},
  "geometry": {"coordinates":[-122.858054,42.31363],"type":"Point"}
}