{
  "type": "Feature",
  "properties": {
    "iso:country":"US",
    "sg:address":"10908 Kahut Ln NE",
    "sg:city":"Woodburn",
    "sg:classifiers":[
        {
            "category":"Farming",
            "subcategory":"Farm",
            "type":"Manufacturing & Wholesale Goods"
        }
    ],
    "sg:phone":"+1 503 981 1304",
    "sg:postcode":"97071",
    "sg:province":"OR",
    "sg:tags":[
        "crop",
        "general"
    ],
    "wof:name":"Bauman Farms",
    "wof:placetype":"venue"
},
  "geometry": {"coordinates":[-122.839625,45.111961],"type":"Point"}
}