{
  "type": "Feature",
  "properties": {
    "addr:full":"10306 SE Market Dr Portland OR 97216",
    "addr:postcode":"10306;97216",
    "addr:street":"Se Market Dr",
    "iso:country":"US",
    "sg:address":"10306 SE Market Dr",
    "sg:city":"Portland",
    "sg:classifiers":[
        {
            "category":"Restaurant",
            "type":"Food & Drink"
        }
    ],
    "sg:phone":"+1 503 262 0825",
    "sg:postcode":"97216",
    "sg:province":"OR",
    "sg:tags":[
        "eating"
    ],
    "wof:name":"Catering By Shannan",
    "wof:placetype":"venue"
},
  "geometry": {"coordinates":[-122.55630499999999,45.510505],"type":"Point"}
}