{
  "type": "Feature",
  "properties": {
    "iso:country":"US",
    "sg:address":"179 NW 10th St",
    "sg:city":"Toledo",
    "sg:classifiers":[
        {
            "category":"Professional",
            "subcategory":"Computer Services",
            "type":"Services"
        }
    ],
    "sg:phone":"+1 541 336 0198",
    "sg:postcode":"97391",
    "sg:province":"OR",
    "sg:tags":[
        "related"
    ],
    "wof:name":"Wickstrom Consulting",
    "wof:placetype":"venue"
},
  "geometry": {"coordinates":[-123.937838,44.627056],"type":"Point"}
}