{
  "type": "Feature",
  "properties": {
    "addr:full":"7035 NE Glisan St Portland OR 97213",
    "addr:housenumber":"7035",
    "addr:postcode":"97213",
    "addr:street":"Ne Glisan St",
    "iso:country":"US",
    "sg:address":"7035 NE Glisan St",
    "sg:city":"Portland",
    "sg:classifiers":[
        {
            "category":"Recreation",
            "type":"Entertainment"
        }
    ],
    "sg:phone":"+1 503 253 4428",
    "sg:postcode":"97213",
    "sg:province":"OR",
    "sg:tags":[
        "club",
        "membership"
    ],
    "wof:name":"12 X 12 Club",
    "wof:placetype":"venue"
},
  "geometry": {"coordinates":[-122.59023000000001,45.526535],"type":"Point"}
}