{
  "type": "Feature",
  "properties": {
    "iso:country":"US",
    "sg:address":"687 Court St NE",
    "sg:city":"Salem",
    "sg:classifiers":[
        {
            "category":"Professional",
            "subcategory":"Lawyer & Legal Services",
            "type":"Services"
        }
    ],
    "sg:phone":"+1 503 362 3359",
    "sg:postcode":"97301",
    "sg:province":"OR",
    "sg:tags":[
        "attorney"
    ],
    "wof:name":"Brian R Nielsen",
    "wof:placetype":"venue"
},
  "geometry": {"coordinates":[-123.034795,44.940251],"type":"Point"}
}