{
  "type": "Feature",
  "properties": {
    "iso:country":"US",
    "sg:address":"16 NE Hogan Dr",
    "sg:city":"Gresham",
    "sg:classifiers":[
        {
            "category":"Professional",
            "subcategory":"Computer Services",
            "type":"Services"
        }
    ],
    "sg:phone":"+1 503 665 8402",
    "sg:postcode":"97030",
    "sg:province":"OR",
    "sg:tags":[
        "programing",
        "custom"
    ],
    "wof:name":"I Systems",
    "wof:placetype":"venue"
},
  "geometry": {"coordinates":[-122.413827,45.499444],"type":"Point"}
}