{
  "type": "Feature",
  "properties": {
    "iso:country":"US",
    "sg:address":"14800 SW Murray Scholls Dr Ste 104",
    "sg:city":"Beaverton",
    "sg:classifiers":[
        {
            "category":"Banks & Credit Unions",
            "subcategory":"Bank",
            "type":"Services"
        }
    ],
    "sg:phone":"+1 503 352 3750",
    "sg:postcode":"97007",
    "sg:province":"OR",
    "sg:website":"www.bannerbank.com",
    "wof:name":"Banner Bank",
    "wof:placetype":"venue"
},
  "geometry": {"coordinates":[-122.82720500000001,45.438662],"type":"Point"}
}