{
  "type": "Feature",
  "properties": {
    "addr:full":"235 Gale St Heppner OR 97836",
    "addr:housenumber":"235",
    "addr:postcode":"97836",
    "addr:street":"Gale St",
    "iso:country":"US",
    "sg:address":"235 Gale St",
    "sg:city":"Heppner",
    "sg:classifiers":[
        {
            "category":"Social Services",
            "subcategory":"Adult Care",
            "type":"Services"
        }
    ],
    "sg:phone":"+1 541 676 5883",
    "sg:postcode":"97836",
    "sg:province":"OR",
    "sg:tags":[
        "foster"
    ],
    "wof:name":"Gingerbread House",
    "wof:placetype":"venue"
},
  "geometry": {"coordinates":[-119.554835,45.355474],"type":"Point"}
}