{
  "type": "Feature",
  "properties": {
    "addr:full":"2314 SW Spence Ct Troutdale OR 97060",
    "addr:housenumber":"2314",
    "addr:postcode":"97060",
    "addr:street":"Sw Spence Ct",
    "iso:country":"US",
    "sg:address":"2314 SW Spence Ct",
    "sg:city":"Troutdale",
    "sg:classifiers":[
        {
            "category":"Building & Trades",
            "subcategory":"Construction",
            "type":"Services"
        }
    ],
    "sg:phone":"+1 503 665 7452",
    "sg:postcode":"97060",
    "sg:province":"OR",
    "sg:tags":[
        "house"
    ],
    "wof:name":"Hershey Construction Inc",
    "wof:placetype":"venue"
},
  "geometry": {"coordinates":[-122.387952,45.524228],"type":"Point"}
}