{
  "type": "Feature",
  "properties": {
    "iso:country":"US",
    "sg:address":"20 S Stage Rd",
    "sg:city":"Medford",
    "sg:phone":"+1 541 772 6213",
    "sg:postcode":"97501",
    "sg:province":"OR",
    "sg:tags":[
        "product",
        "petroleum"
    ],
    "wof:name":"Colvin Oil Company",
    "wof:placetype":"venue"
},
  "geometry": {"coordinates":[-122.844632,42.293029],"type":"Point"}
}