{
  "type": "Feature",
  "properties": {
    "addr:full":"264 NW Irving Ave Bend OR 97701",
    "addr:housenumber":"264",
    "addr:postcode":"97701",
    "addr:street":"Nw Irving Ave",
    "iso:country":"US",
    "sg:address":"264 NW Irving Ave",
    "sg:city":"Bend",
    "sg:classifiers":[
        {
            "category":"Professional",
            "subcategory":"Accounting & Tax Preparation",
            "type":"Services"
        }
    ],
    "sg:phone":"+1 541 388 2154",
    "sg:postcode":"97701",
    "sg:province":"OR",
    "sg:tags":[
        "accountant"
    ],
    "wof:name":"Kenneth F Graham Cpa Pc",
    "wof:placetype":"venue"
},
  "geometry": {"coordinates":[-121.311211,44.058941],"type":"Point"}
}