{
  "type": "Feature",
  "properties": {
    "addr:full":"4257 Barger Dr Eugene OR 97402",
    "addr:housenumber":"4257",
    "addr:postcode":"97402",
    "addr:street":"Barger Dr",
    "iso:country":"US",
    "sg:address":"4257 Barger Dr",
    "sg:city":"Eugene",
    "sg:classifiers":[
        {
            "category":"Building & Trades",
            "subcategory":"Landscaping Services",
            "type":"Services"
        }
    ],
    "sg:phone":"+1 541 463 9400",
    "sg:postcode":"97402",
    "sg:province":"OR",
    "sg:tags":[
        "landscape",
        "contractor"
    ],
    "wof:name":"Green Earth Landscape Mntnc",
    "wof:placetype":"venue"
},
  "geometry": {"coordinates":[-123.171246,44.08451],"type":"Point"}
}