{
  "type": "Feature",
  "properties": {
    "iso:country":"US",
    "sg:address":"1244 S Riverside Ave",
    "sg:city":"Medford",
    "sg:classifiers":[
        {
            "category":"Banks & Credit Unions",
            "subcategory":"Bank",
            "type":"Services"
        }
    ],
    "sg:phone":"+1 541 774 1790",
    "sg:postcode":"97501",
    "sg:province":"OR",
    "sg:tags":[
        "loan"
    ],
    "wof:name":"Northwest Title Loans",
    "wof:placetype":"venue"
},
  "geometry": {"coordinates":[-122.861774,42.314947],"type":"Point"}
}