{
  "type": "Feature",
  "properties": {
    "addr:full":"2321 Ashland St Ashland OR 97520",
    "addr:housenumber":"2321",
    "addr:postcode":"97520",
    "addr:street":"Ashland St",
    "iso:country":"US",
    "sg:address":"2321 Ashland St",
    "sg:city":"Ashland",
    "sg:classifiers":[
        {
            "category":"Restaurant",
            "type":"Food & Drink"
        }
    ],
    "sg:menulink":"http://www.allmenus.com/or/ashland/128332-subway/menu/",
    "sg:phone":"+1 541 488 7868",
    "sg:postcode":"97520",
    "sg:province":"OR",
    "sg:tags":[
        "american",
        "sandwich"
    ],
    "wof:name":"Subway",
    "wof:placetype":"venue"
},
  "geometry": {"coordinates":[-122.67191699999999,42.185375],"type":"Point"}
}