{
  "type": "Feature",
  "properties": {
    "iso:country":"US",
    "sg:address":"25 SE Dorion Ave",
    "sg:city":"Pendleton",
    "sg:classifiers":[
        {
            "category":"Food & Beverages",
            "subcategory":"Specialty",
            "type":"Retail Goods"
        }
    ],
    "sg:phone":"+1 541 276 2251",
    "sg:postcode":"97801",
    "sg:province":"OR",
    "sg:tags":[
        "product",
        "supplement",
        "health",
        "vitamin",
        "diet"
    ],
    "wof:name":"The Health Nuts",
    "wof:placetype":"venue"
},
  "geometry": {"coordinates":[-118.78667900000001,45.671717],"type":"Point"}
}