{
  "type": "Feature",
  "properties": {
    "iso:country":"US",
    "sg:address":"3608 W 1st Ave",
    "sg:city":"Eugene",
    "sg:classifiers":[
        {
            "category":"Real Estate",
            "subcategory":"Real Estate Operator",
            "type":"Services"
        }
    ],
    "sg:phone":"+1 541 686 8582",
    "sg:postcode":"97402",
    "sg:province":"OR",
    "sg:tags":[
        "building",
        "apartment"
    ],
    "wof:name":"Village Oaks Apartments",
    "wof:placetype":"venue"
},
  "geometry": {"coordinates":[-123.156357,44.058296],"type":"Point"}
}