{
  "type": "Feature",
  "properties": {
    "iso:country":"US",
    "sg:address":"2209 SE Hawthorne Blvd",
    "sg:city":"Portland",
    "sg:classifiers":[
        {
            "category":"Food & Beverages",
            "subcategory":"Groceries & Convenience Stores",
            "type":"Retail Goods"
        }
    ],
    "sg:phone":"+1 503 235 9188",
    "sg:postcode":"97214",
    "sg:province":"OR",
    "wof:name":"Plaid Pantry 95",
    "wof:placetype":"venue"
},
  "geometry": {"coordinates":[-122.643214,45.512152],"type":"Point"}
}