{
  "type": "Feature",
  "properties": {
    "addr:full":"11439 SW Beaverton-Hillsdale Hwy Beaverton OR 97005",
    "addr:housenumber":"11439",
    "addr:postcode":"97005",
    "addr:street":"Sw Beaverton-Hillsdale Hwy",
    "iso:country":"US",
    "sg:address":"11439 SW Beaverton-Hillsdale Hwy",
    "sg:city":"Beaverton",
    "sg:classifiers":[
        {
            "category":"Home & Garden",
            "subcategory":"Household Appliances",
            "type":"Retail Goods"
        }
    ],
    "sg:phone":"+1 503 643 4666",
    "sg:postcode":"97005",
    "sg:province":"OR",
    "sg:tags":[
        "machine",
        "sewing",
        "supply"
    ],
    "sg:website":"www.sewingcenterwest.com",
    "wof:name":"Sewing Center West Inc",
    "wof:placetype":"venue"
},
  "geometry": {"coordinates":[-122.79403499999999,45.486607],"type":"Point"}
}