{
  "type": "Feature",
  "properties": {
    "iso:country":"US",
    "sg:address":"226 Illinois River Rd",
    "sg:city":"Selma",
    "sg:classifiers":[
        {
            "category":"Building & Trades",
            "subcategory":"Plumbing",
            "type":"Services"
        }
    ],
    "sg:phone":"+1 541 597 4741",
    "sg:postcode":"97538",
    "sg:province":"OR",
    "sg:tags":[
        "plumbing",
        "contractor"
    ],
    "wof:name":"Illinois Valley Plumbing",
    "wof:placetype":"venue"
},
  "geometry": {"coordinates":[-123.619081,42.279291],"type":"Point"}
}