{
  "type": "Feature",
  "properties": {
    "iso:country":"US",
    "sg:address":"10200 SW Greenburg Rd Ste 110",
    "sg:city":"Portland",
    "sg:classifiers":[
        {
            "category":"Banks & Credit Unions",
            "subcategory":"Financial Services",
            "type":"Services"
        },
        {
            "category":"Insurance",
            "subcategory":"Hazard Insurance",
            "type":"Services"
        },
        {
            "category":"Insurance",
            "subcategory":"Title Insurance",
            "type":"Services"
        },
        {
            "category":"Real Estate",
            "subcategory":"Real Estate Services",
            "type":"Services"
        }
    ],
    "sg:phone":"+1 503 977 3685",
    "sg:postcode":"97223",
    "sg:province":"OR",
    "sg:tags":[
        "mortgage",
        "escrow"
    ],
    "sg:website":"http://www.acssys.com",
    "wof:name":"Fidelity National Title",
    "wof:placetype":"venue"
},
  "geometry": {"coordinates":[-122.77637300000001,45.446084],"type":"Point"}
}