{
  "type": "Feature",
  "properties": {
    "iso:country":"US",
    "sg:address":"406 N Main St",
    "sg:city":"Newberg",
    "sg:classifiers":[
        {
            "category":"Retail",
            "subcategory":"Auto Repair",
            "type":"Services"
        }
    ],
    "sg:phone":"+1 503 538 3810",
    "sg:postcode":"97132",
    "sg:province":"OR",
    "sg:tags":[
        "exhaust"
    ],
    "wof:name":"Muffler Works",
    "wof:placetype":"venue"
},
  "geometry": {"coordinates":[-122.979045,45.30331],"type":"Point"}
}