{
  "type": "Feature",
  "properties": {
    "addr:full":"2483 NW 185th Ave Hillsboro OR 97124",
    "addr:housenumber":"2483",
    "addr:postcode":"97124",
    "addr:street":"Nw 185Th Ave",
    "iso:country":"US",
    "sg:address":"2483 NW 185th Ave",
    "sg:city":"Hillsboro",
    "sg:classifiers":[
        {
            "category":"Home & Garden",
            "subcategory":"Furniture",
            "type":"Retail Goods"
        }
    ],
    "sg:phone":"+1 503 690 4980",
    "sg:postcode":"97124",
    "sg:province":"OR",
    "sg:tags":[
        "store"
    ],
    "wof:name":"Pier 1 Imports",
    "wof:placetype":"venue"
},
  "geometry": {"coordinates":[-122.86799600000001,45.537701],"type":"Point"}
}