{
  "type": "Feature",
  "properties": {
    "iso:country":"US",
    "sg:address":"12000 SE 82nd Ave",
    "sg:city":"Portland",
    "sg:classifiers":[
        {
            "category":"Shopping",
            "subcategory":"Jewelry",
            "type":"Retail Goods"
        }
    ],
    "sg:phone":"+1 503 654 7724",
    "sg:postcode":"97086",
    "sg:province":"OR",
    "sg:website":"www.gordonsjewelers.com",
    "wof:name":"Gordon's Jewelers",
    "wof:placetype":"venue"
},
  "geometry": {"coordinates":[-122.57651,45.436899],"type":"Point"}
}