{
  "type": "Feature",
  "properties": {
    "iso:country":"US",
    "sg:address":"300 E Main St",
    "sg:city":"Ashland",
    "sg:classifiers":[
        {
            "category":"Shopping",
            "subcategory":"Clothing, Apparel, & Fashions",
            "type":"Retail Goods"
        }
    ],
    "sg:phone":"+1 541 488 2204",
    "sg:postcode":"97520",
    "sg:province":"OR",
    "sg:tags":[
        "furnishing"
    ],
    "wof:name":"Wolf & Son",
    "wof:placetype":"venue"
},
  "geometry": {"coordinates":[-122.711686,42.195311],"type":"Point"}
}