{
  "type": "Feature",
  "properties": {
    "addr:full":"514 SW Nevada St Portland OR 97219",
    "addr:housenumber":"514",
    "addr:postcode":"97219",
    "addr:street":"Sw Nevada St",
    "iso:country":"US",
    "sg:address":"514 SW Nevada St",
    "sg:city":"Portland",
    "sg:classifiers":[
        {
            "category":"Professional",
            "subcategory":"Lawyer & Legal Services",
            "type":"Services"
        }
    ],
    "sg:phone":"+1 503 245 2965",
    "sg:postcode":"97219",
    "sg:province":"OR",
    "wof:name":"William A Berdan",
    "wof:placetype":"venue"
},
  "geometry": {"coordinates":[-122.671486,45.472972],"type":"Point"}
}