{
  "type": "Feature",
  "properties": {
    "addr:full":"2652 Silver Falls Dr SE Silverton OR 97381",
    "addr:housenumber":"2652",
    "addr:postcode":"97381",
    "addr:street":"Silver Falls Dr Se",
    "iso:country":"US",
    "sg:address":"2652 Silver Falls Dr SE",
    "sg:city":"Silverton",
    "sg:classifiers":[
        {
            "category":"Professional",
            "subcategory":"Business Services",
            "type":"Services"
        }
    ],
    "sg:phone":"+1 503 393 8823",
    "sg:postcode":"97381",
    "sg:province":"OR",
    "wof:name":"Rutherfords Wreaths Direct",
    "wof:placetype":"venue"
},
  "geometry": {"coordinates":[-122.648736,44.903272],"type":"Point"}
}