{
  "type": "Feature",
  "properties": {
    "iso:country":"US",
    "sg:address":"324 SE 31st Ave",
    "sg:city":"Portland",
    "sg:classifiers":[
        {
            "category":"Arts & Performance",
            "subcategory":"Theater",
            "type":"Entertainment"
        },
        {
            "category":"Retail",
            "subcategory":"Photofinishing",
            "type":"Services"
        }
    ],
    "sg:phone":"+1 503 231 5776",
    "sg:postcode":"97214",
    "sg:province":"OR",
    "sg:tags":[
        "entertainer",
        "laboratory",
        "business"
    ],
    "wof:name":"Caricatures By Clark",
    "wof:placetype":"venue"
},
  "geometry": {"coordinates":[-122.632873,45.519477],"type":"Point"}
}