{
  "type": "Feature",
  "properties": {
    "iso:country":"US",
    "sg:address":"28998 Hwy 99E",
    "sg:city":"Shedd",
    "sg:classifiers":[
        {
            "category":"Farming",
            "subcategory":"Farm & Veterinary Services",
            "type":"Manufacturing & Wholesale Goods"
        }
    ],
    "sg:phone":"+1 541 491 1018",
    "sg:postcode":"97377",
    "sg:province":"OR",
    "sg:tags":[
        "preparation",
        "crop",
        "for",
        "market"
    ],
    "wof:name":"Linn West Seed Processors",
    "wof:placetype":"venue"
},
  "geometry": {"coordinates":[-123.110479,44.433872],"type":"Point"}
}