{
  "type": "Feature",
  "properties": {
    "iso:country":"US",
    "sg:address":"6841 S 6th St",
    "sg:city":"Klamath Falls",
    "sg:classifiers":[
        {
            "category":"Retail",
            "subcategory":"Animal Services",
            "type":"Services"
        }
    ],
    "sg:phone":"+1 541 884 0616",
    "sg:postcode":"97603",
    "sg:province":"OR",
    "wof:name":"Elegant Pooch",
    "wof:placetype":"venue"
},
  "geometry": {"coordinates":[-121.70517100000001,42.200794],"type":"Point"}
}