{
  "type": "Feature",
  "properties": {
    "iso:country":"US",
    "sg:address":"4566 NE 87th Ave",
    "sg:city":"Portland",
    "sg:classifiers":[
        {
            "category":"Organizations",
            "subcategory":"Religious Organization",
            "type":"Services"
        }
    ],
    "sg:phone":"+1 503 253 2270",
    "sg:postcode":"97220",
    "sg:province":"OR",
    "sg:tags":[
        "church"
    ],
    "wof:name":"Portland Hispanic Seventh Day",
    "wof:placetype":"venue"
},
  "geometry": {"coordinates":[-122.573626,45.555852],"type":"Point"}
}