{
  "type": "Feature",
  "properties": {
    "iso:country":"US",
    "sg:address":"700 Molalla Ave",
    "sg:city":"Oregon City",
    "sg:classifiers":[
        {
            "category":"Wholesale",
            "subcategory":"Medical Equipment & Supplies",
            "type":"Manufacturing & Wholesale Goods"
        }
    ],
    "sg:phone":"+1 503 723 9797",
    "sg:postcode":"97045",
    "sg:province":"OR",
    "wof:name":"Warner Group Inc",
    "wof:placetype":"venue"
},
  "geometry": {"coordinates":[-122.596715,45.347371],"type":"Point"}
}