{
  "type": "Feature",
  "properties": {
    "iso:country":"US",
    "sg:address":"8111 NE Columbia Blvd",
    "sg:city":"Portland",
    "sg:classifiers":[
        {
            "category":"Restaurant",
            "type":"Food & Drink"
        }
    ],
    "sg:phone":"+1 503 285 9877",
    "sg:postcode":"97218",
    "sg:province":"OR",
    "sg:tags":[
        "cafeteria",
        "resort",
        "hotel",
        "vending",
        "d"
    ],
    "wof:name":"Imperial Vending",
    "wof:placetype":"venue"
},
  "geometry": {"coordinates":[-122.57861,45.564955],"type":"Point"}
}