{
  "type": "Feature",
  "properties": {
    "iso:country":"US",
    "sg:address":"400 High St SE",
    "sg:city":"Salem",
    "sg:classifiers":[
        {
            "category":"Insurance",
            "subcategory":"Hazard Insurance",
            "type":"Services"
        }
    ],
    "sg:phone":"+1 503 373 8376",
    "sg:postcode":"97301",
    "sg:province":"OR",
    "sg:tags":[
        "carrier"
    ],
    "wof:name":"Safe Corporation",
    "wof:placetype":"venue"
},
  "geometry": {"coordinates":[-123.038461,44.936973],"type":"Point"}
}