{
  "type": "Feature",
  "properties": {
    "iso:country":"US",
    "sg:address":"2915 SW Quartz Ave",
    "sg:city":"Redmond",
    "sg:classifiers":[
        {
            "category":"Building & Trades",
            "subcategory":"Construction",
            "type":"Services"
        }
    ],
    "sg:phone":"+1 541 923 2973",
    "sg:postcode":"97756",
    "sg:province":"OR",
    "sg:tags":[
        "hanging",
        "contractor"
    ],
    "wof:name":"Mandich Painting",
    "wof:placetype":"venue"
},
  "geometry": {"coordinates":[-121.204297,44.258378],"type":"Point"}
}