{
  "type": "Feature",
  "properties": {
    "addr:full":"117 E Main St Enterprise OR 97828",
    "addr:housenumber":"117",
    "addr:postcode":"97828",
    "addr:street":"E Main St",
    "iso:country":"US",
    "sg:address":"117 E Main St",
    "sg:city":"Enterprise",
    "sg:classifiers":[
        {
            "category":"Professional",
            "subcategory":"Lawyer & Legal Services",
            "type":"Services"
        }
    ],
    "sg:phone":"+1 541 426 2080",
    "sg:postcode":"97828",
    "sg:province":"OR",
    "sg:tags":[
        "attorney"
    ],
    "wof:name":"Williams, Mona K Attorney At Law",
    "wof:placetype":"venue"
},
  "geometry": {"coordinates":[-117.27737,45.42551],"type":"Point"}
}