{
  "type": "Feature",
  "properties": {
    "iso:country":"US",
    "sg:address":"1958 Pacific Blvd SE",
    "sg:city":"Albany",
    "sg:classifiers":[
        {
            "category":"Personal",
            "subcategory":"Beauty Salon",
            "type":"Services"
        }
    ],
    "sg:phone":"+1 541 967 9325",
    "sg:postcode":"97321",
    "sg:province":"OR",
    "sg:tags":[
        "shop"
    ],
    "wof:name":"Wild Hair Techniques",
    "wof:placetype":"venue"
},
  "geometry": {"coordinates":[-123.082128,44.634434],"type":"Point"}
}