{
  "type": "Feature",
  "properties": {
    "iso:country":"US",
    "sg:address":"6311 SW Capitol Hwy",
    "sg:city":"Portland",
    "sg:classifiers":[
        {
            "category":"Personal",
            "subcategory":"Shoe Repair & Shine",
            "type":"Services"
        }
    ],
    "sg:phone":"+1 503 244 3153",
    "sg:postcode":"97239",
    "sg:province":"OR",
    "wof:name":"Hillsdale Shoe Repair",
    "wof:placetype":"venue"
},
  "geometry": {"coordinates":[-122.694754,45.478363],"type":"Point"}
}