{
  "type": "Feature",
  "properties": {
    "iso:country":"US",
    "sg:address":"7325 SW Scholls Ferry Rd",
    "sg:city":"Beaverton",
    "sg:classifiers":[
        {
            "category":"Retail",
            "subcategory":"Repair Shop",
            "type":"Services"
        }
    ],
    "sg:phone":"+1 503 644 1966",
    "sg:postcode":"97008",
    "sg:province":"OR",
    "sg:tags":[
        "refinishing",
        "furniture"
    ],
    "wof:name":"Family Cane Shop",
    "wof:placetype":"venue"
},
  "geometry": {"coordinates":[-122.77768,45.465879],"type":"Point"}
}