{
  "type": "Feature",
  "properties": {
    "iso:country":"US",
    "sg:address":"1500 SW 1st Ave",
    "sg:city":"Portland",
    "sg:classifiers":[
        {
            "category":"Banks & Credit Unions",
            "subcategory":"Investment Brokerage",
            "type":"Services"
        }
    ],
    "sg:phone":"+1 503 226 6700",
    "sg:postcode":"97201",
    "sg:province":"OR",
    "sg:tags":[
        "security"
    ],
    "sg:website":"www.mkgfinancial.com",
    "wof:name":"MKG Financial Group Inc",
    "wof:placetype":"venue"
},
  "geometry": {"coordinates":[-122.676973,45.51172],"type":"Point"}
}