{
  "type": "Feature",
  "properties": {
    "iso:country":"US",
    "sg:address":"610 SW Broadway",
    "sg:city":"Portland",
    "sg:classifiers":[
        {
            "category":"Professional",
            "subcategory":"Management & Consulting",
            "type":"Services"
        }
    ],
    "sg:phone":"+1 503 669 8213",
    "sg:postcode":"97205",
    "sg:province":"OR",
    "sg:tags":[
        "consultant",
        "business"
    ],
    "wof:name":"Judith Clarke & Assoc",
    "wof:placetype":"venue"
},
  "geometry": {"coordinates":[-122.679525,45.519387],"type":"Point"}
}