{
  "type": "Feature",
  "properties": {
    "addr:full":"3917 W 18th Ave Eugene OR 97402",
    "addr:housenumber":"3917",
    "addr:postcode":"97402",
    "addr:street":"W 18Th Ave",
    "iso:country":"US",
    "sg:address":"3917 W 18th Ave",
    "sg:city":"Eugene",
    "sg:classifiers":[
        {
            "category":"Social Services",
            "subcategory":"Child Care",
            "type":"Services"
        }
    ],
    "sg:phone":"+1 541 683 8225",
    "sg:postcode":"97402",
    "sg:province":"OR",
    "sg:tags":[
        "day"
    ],
    "wof:name":"Bettinas Cafe Jump Start",
    "wof:placetype":"venue"
},
  "geometry": {"coordinates":[-123.16061000000001,44.038429],"type":"Point"}
}