{
  "type": "Feature",
  "properties": {
    "iso:country":"US",
    "sg:address":"2652 SW Ridge Dr",
    "sg:city":"Portland",
    "sg:classifiers":[
        {
            "category":"Building & Trades",
            "subcategory":"Landscaping Services",
            "type":"Services"
        }
    ],
    "sg:phone":"+1 503 244 2698",
    "sg:postcode":"97219",
    "sg:province":"OR",
    "sg:tags":[
        "landscape"
    ],
    "wof:name":"Eduardo Leiva",
    "wof:placetype":"venue"
},
  "geometry": {"coordinates":[-122.706276,45.454187],"type":"Point"}
}