{
  "type": "Feature",
  "properties": {
    "iso:country":"US",
    "sg:address":"4421 NE Sandy Blvd",
    "sg:city":"Portland",
    "sg:classifiers":[
        {
            "category":"Food & Beverages",
            "subcategory":"Specialty",
            "type":"Retail Goods"
        }
    ],
    "sg:phone":"+1 503 249 7926",
    "sg:postcode":"97213",
    "sg:province":"OR",
    "sg:tags":[
        "tea",
        "coffee"
    ],
    "wof:name":"Caffe Uno",
    "wof:placetype":"venue"
},
  "geometry": {"coordinates":[-122.61711099999999,45.537435],"type":"Point"}
}