{
  "type": "Feature",
  "properties": {
    "addr:full":"2019 River Rd Eugene OR 97404",
    "addr:housenumber":"2019",
    "addr:postcode":"97404",
    "addr:street":"River Rd",
    "iso:country":"US",
    "sg:address":"2019 River Rd",
    "sg:city":"Eugene",
    "sg:classifiers":[
        {
            "category":"Shopping",
            "type":"Retail Goods"
        }
    ],
    "sg:phone":"+1 541 689 6822",
    "sg:postcode":"97404",
    "sg:province":"OR",
    "sg:tags":[
        "ice"
    ],
    "wof:name":"Union Ice Co",
    "wof:placetype":"venue"
},
  "geometry": {"coordinates":[-123.12712999999999,44.093604],"type":"Point"}
}