{
  "type": "Feature",
  "properties": {
    "addr:full":"8070 NE Airtrans Way Portland OR 97218",
    "addr:housenumber":"8070",
    "addr:postcode":"97218",
    "addr:street":"Ne Airtrans Way",
    "iso:country":"US",
    "sg:address":"8070 NE Airtrans Way",
    "sg:city":"Portland",
    "sg:classifiers":[
        {
            "category":"Airline",
            "type":"Transportation"
        }
    ],
    "sg:phone":"+1 503 249 4114",
    "sg:postcode":"97218",
    "sg:province":"OR",
    "sg:tags":[
        "company"
    ],
    "wof:name":"Horizon Air Industries Inc",
    "wof:placetype":"venue"
},
  "geometry": {"coordinates":[-122.60594399999999,45.583463],"type":"Point"}
}