{
  "type": "Feature",
  "properties": {
    "iso:country":"US",
    "sg:address":"7587 SW Mohawk St",
    "sg:city":"Tualatin",
    "sg:classifiers":[
        {
            "category":"Health Services",
            "subcategory":"Medical Lab",
            "type":"Services"
        }
    ],
    "sg:phone":"+1 503 692 2700",
    "sg:postcode":"97062",
    "sg:province":"OR",
    "sg:tags":[
        "laboratory"
    ],
    "wof:name":"Legacy Laboratory Svc",
    "wof:placetype":"venue"
},
  "geometry": {"coordinates":[-122.757149,45.378291],"type":"Point"}
}