{
  "type": "Feature",
  "properties": {
    "iso:country":"US",
    "sg:address":"2425 E Whiteaker Ave",
    "sg:city":"Cottage Grove",
    "sg:classifiers":[
        {
            "category":"Manufacturing",
            "subcategory":"Tools & Machinery",
            "type":"Manufacturing & Wholesale Goods"
        }
    ],
    "sg:phone":"+1 541 942 5828",
    "sg:postcode":"97424",
    "sg:province":"OR",
    "sg:tags":[
        "model",
        "maker"
    ],
    "sg:website":"www.captainsmodels.com",
    "wof:name":"Captain's Models",
    "wof:placetype":"venue"
},
  "geometry": {"coordinates":[-123.042766,43.798018],"type":"Point"}
}