{
  "type": "Feature",
  "properties": {
    "addr:full":"13 SW H St Madras OR 97741",
    "addr:housenumber":"13",
    "addr:postcode":"97741",
    "addr:street":"Sw H St",
    "iso:country":"US",
    "sg:address":"13 SW H St",
    "sg:city":"Madras",
    "sg:classifiers":[
        {
            "category":"Home & Garden",
            "subcategory":"Hardware",
            "type":"Retail Goods"
        }
    ],
    "sg:phone":"+1 541 475 9392",
    "sg:postcode":"97741",
    "sg:province":"OR",
    "sg:tags":[
        "store"
    ],
    "wof:name":"Phils Hardware",
    "wof:placetype":"venue"
},
  "geometry": {"coordinates":[-121.130522,44.627536],"type":"Point"}
}