{
  "type": "Feature",
  "properties": {
    "addr:full":"1015 SE Woodward St Portland OR 97202",
    "addr:housenumber":"1015",
    "addr:postcode":"97202",
    "addr:street":"Se Woodward St",
    "iso:country":"US",
    "sg:address":"1015 SE Woodward St",
    "sg:city":"Portland",
    "sg:classifiers":[
        {
            "category":"Professional",
            "subcategory":"Business Services",
            "type":"Services"
        }
    ],
    "sg:phone":"+1 503 236 4137",
    "sg:postcode":"97202",
    "sg:province":"OR",
    "sg:tags":[
        "repossessing"
    ],
    "sg:website":"www.portlandrepossessions.com",
    "wof:name":"Allied Recovery",
    "wof:placetype":"venue"
},
  "geometry": {"coordinates":[-122.654229,45.502115],"type":"Point"}
}