{
  "type": "Feature",
  "properties": {
    "iso:country":"US",
    "sg:address":"402 SE 52nd Ave",
    "sg:city":"Portland",
    "sg:classifiers":[
        {
            "category":"Communications",
            "type":"Services"
        }
    ],
    "sg:phone":"+1 503 238 2575",
    "sg:postcode":"97215",
    "sg:province":"OR",
    "wof:name":"Azulfuego Media",
    "wof:placetype":"venue"
},
  "geometry": {"coordinates":[-122.610252,45.51987],"type":"Point"}
}