{
  "type": "Feature",
  "properties": {
    "iso:country":"US",
    "sg:address":"3315 NE Marine Dr",
    "sg:city":"Portland",
    "sg:classifiers":[
        {
            "category":"Education",
            "subcategory":"Junior College",
            "type":"Public Place"
        },
        {
            "category":"Recreation",
            "type":"Entertainment"
        }
    ],
    "sg:phone":"+1 503 281 6529",
    "sg:postcode":"97211",
    "sg:province":"OR",
    "sg:tags":[
        "technical",
        "institute"
    ],
    "wof:name":"Portland Sailing Center",
    "wof:placetype":"venue"
},
  "geometry": {"coordinates":[-122.56328600000001,45.583366],"type":"Point"}
}