{
  "type": "Feature",
  "properties": {
    "addr:full":"15500 SW Jay St Beaverton OR 97006",
    "addr:housenumber":"15500",
    "addr:postcode":"97006",
    "addr:street":"Sw Jay St",
    "iso:country":"US",
    "sg:address":"15500 SW Jay St",
    "sg:city":"Beaverton",
    "sg:classifiers":[
        {
            "category":"Real Estate",
            "subcategory":"Real Estate Agent",
            "type":"Services"
        }
    ],
    "sg:phone":"+1 503 352 0637",
    "sg:postcode":"97006",
    "sg:province":"OR",
    "sg:tags":[
        "management"
    ],
    "wof:name":"D & W Properties",
    "wof:placetype":"venue"
},
  "geometry": {"coordinates":[-122.839834,45.509727],"type":"Point"}
}