{
  "type": "Feature",
  "properties": {
    "addr:full":"7555 SW Hermoso Way # 10 Portland OR 97223",
    "addr:housenumber":"7555;10",
    "addr:postcode":"97223",
    "addr:street":"Sw Hermoso Way #",
    "iso:country":"US",
    "sg:address":"7555 SW Hermoso Way # 10",
    "sg:city":"Portland",
    "sg:classifiers":[
        {
            "category":"Wholesale",
            "subcategory":"Office Equipment",
            "type":"Manufacturing & Wholesale Goods"
        },
        {
            "category":"Professional",
            "subcategory":"Printing & Photocopies",
            "type":"Services"
        },
        {
            "category":"Shopping",
            "subcategory":"Computers & Home Electronics",
            "type":"Retail Goods"
        }
    ],
    "sg:phone":"+1 503 620 5203",
    "sg:postcode":"97223",
    "sg:province":"OR",
    "sg:tags":[
        "scanning",
        "printer",
        "supply",
        "duplicating",
        "copying",
        "lithographer",
        "plotting"
    ],
    "sg:website":"http://www.minutemanpress.com",
    "wof:name":"Minuteman Press",
    "wof:placetype":"venue"
},
  "geometry": {"coordinates":[-122.754333,45.430054],"type":"Point"}
}