{
  "type": "Feature",
  "properties": {
    "addr:full":"3395 River Rd N Keizer OR 97303",
    "addr:housenumber":"3395",
    "addr:postcode":"97303",
    "addr:street":"River Rd N",
    "iso:country":"US",
    "sg:address":"3395 River Rd N",
    "sg:city":"Keizer",
    "sg:classifiers":[
        {
            "category":"Personal",
            "subcategory":"Beauty Salon",
            "type":"Services"
        }
    ],
    "sg:phone":"+1 503 463 1192",
    "sg:postcode":"97303",
    "sg:province":"OR",
    "wof:name":"Styles Salon",
    "wof:placetype":"venue"
},
  "geometry": {"coordinates":[-123.02744800000001,44.974988],"type":"Point"}
}