{
  "type": "Feature",
  "properties": {
    "iso:country":"US",
    "sg:address":"12876 SE Kronan Dr",
    "sg:city":"Clackamas",
    "sg:classifiers":[
        {
            "category":"Building & Trades",
            "subcategory":"Construction",
            "type":"Services"
        }
    ],
    "sg:phone":"+1 503 698 6793",
    "sg:postcode":"97015",
    "sg:province":"OR",
    "wof:name":"Mel Hamilton Construction",
    "wof:placetype":"venue"
},
  "geometry": {"coordinates":[-122.530708,45.413468],"type":"Point"}
}