{
  "type": "Feature",
  "properties": {
    "addr:full":"11715 SW 134th Ter Portland OR 97223",
    "addr:housenumber":"11715",
    "addr:postcode":"97223",
    "addr:street":"Sw 134Th Ter",
    "iso:country":"US",
    "sg:address":"11715 SW 134th Ter",
    "sg:city":"Portland",
    "sg:classifiers":[
        {
            "category":"Shopping",
            "subcategory":"Gifts & Souvenirs",
            "type":"Retail Goods"
        }
    ],
    "sg:phone":"+1 503 223 9064",
    "sg:postcode":"97223",
    "sg:province":"OR",
    "sg:tags":[
        "clothing"
    ],
    "wof:name":"Crispins Import Gallery",
    "wof:placetype":"venue"
},
  "geometry": {"coordinates":[-122.814046,45.435202],"type":"Point"}
}