{
  "type": "Feature",
  "properties": {
    "iso:country":"US",
    "sg:address":"2237 Ironwood St",
    "sg:city":"Sweet Home",
    "sg:classifiers":[
        {
            "category":"Professional",
            "subcategory":"Computer Services",
            "type":"Services"
        }
    ],
    "sg:phone":"+1 541 367 5830",
    "sg:postcode":"97386",
    "sg:province":"OR",
    "wof:name":"Cyberdoc",
    "wof:placetype":"venue"
},
  "geometry": {"coordinates":[-122.71782,44.39529],"type":"Point"}
}