{
  "type": "Feature",
  "properties": {
    "iso:country":"US",
    "sg:address":"317 SE 62nd Ave",
    "sg:city":"Portland",
    "sg:classifiers":[
        {
            "category":"Real Estate",
            "subcategory":"Architect",
            "type":"Services"
        }
    ],
    "sg:phone":"+1 503 235 3515",
    "sg:postcode":"97215",
    "sg:province":"OR",
    "sg:tags":[
        "architectural"
    ],
    "wof:name":"Architect Alfred Sthli Faia/Em",
    "wof:placetype":"venue"
},
  "geometry": {"coordinates":[-122.599672,45.520799],"type":"Point"}
}