{
  "type": "Feature",
  "properties": {
    "iso:country":"US",
    "sg:address":"2350 SW 257th Ave",
    "sg:city":"Troutdale",
    "sg:classifiers":[
        {
            "category":"Retail",
            "subcategory":"Portrait Studio",
            "type":"Services"
        }
    ],
    "sg:phone":"+1 503 665 6074",
    "sg:postcode":"97060",
    "sg:province":"OR",
    "sg:tags":[
        "photo"
    ],
    "wof:name":"Just 4u Photography",
    "wof:placetype":"venue"
},
  "geometry": {"coordinates":[-122.398349,45.525942],"type":"Point"}
}