{
  "type": "Feature",
  "properties": {
    "iso:country":"US",
    "sg:address":"2858 Harding Ct NW",
    "sg:city":"Salem",
    "sg:classifiers":[
        {
            "category":"Banks & Credit Unions",
            "subcategory":"Financial Services",
            "type":"Services"
        }
    ],
    "sg:phone":"+1 503 362 4379",
    "sg:postcode":"97304",
    "sg:province":"OR",
    "sg:tags":[
        "investor"
    ],
    "wof:name":"Homeland Investments",
    "wof:placetype":"venue"
},
  "geometry": {"coordinates":[-123.089311,44.946064],"type":"Point"}
}