{
  "type": "Feature",
  "properties": {
    "iso:country":"US",
    "sg:address":"4725 Village Plz Lp",
    "sg:city":"Eugene",
    "sg:classifiers":[
        {
            "category":"Professional",
            "subcategory":"Accounting & Tax Preparation",
            "type":"Services"
        }
    ],
    "sg:phone":"+1 541 242 3788",
    "sg:postcode":"97401",
    "sg:province":"OR",
    "wof:name":"Lydon Enterprises",
    "wof:placetype":"venue"
},
  "geometry": {"coordinates":[-123.105033,44.088028],"type":"Point"}
}