{
  "type": "Feature",
  "properties": {
    "iso:country":"US",
    "sg:address":"1834 Pacific Ave",
    "sg:city":"Forest Grove",
    "sg:classifiers":[
        {
            "category":"Shopping",
            "subcategory":"Shoes",
            "type":"Retail Goods"
        }
    ],
    "sg:phone":"+1 503 680 4865",
    "sg:postcode":"97116",
    "sg:province":"OR",
    "wof:name":"Faces To Feet",
    "wof:placetype":"venue"
},
  "geometry": {"coordinates":[-123.114456,45.519597],"type":"Point"}
}