{
  "type": "Feature",
  "properties": {
    "iso:country":"US",
    "sg:address":"12000 SE 82nd Ave",
    "sg:city":"Portland",
    "sg:classifiers":[
        {
            "category":"Shopping",
            "subcategory":"Shoes",
            "type":"Retail Goods"
        }
    ],
    "sg:phone":"+1 503 659 1177",
    "sg:postcode":"97266",
    "sg:province":"OR",
    "sg:tags":[
        "store"
    ],
    "wof:name":"Vans 178",
    "wof:placetype":"venue"
},
  "geometry": {"coordinates":[-122.579002,45.435902],"type":"Point"}
}