{
  "type": "Feature",
  "properties": {
    "addr:full":"11855 N.E. Glenn Widing Drive Portland OR 97220",
    "addr:housenumber":"11855",
    "addr:postcode":"97220",
    "addr:street":"N.E. Glenn Widing Drive",
    "iso:country":"US",
    "sg:address":"11855 N.E. Glenn Widing Drive",
    "sg:city":"Portland",
    "sg:classifiers":[
        {
            "category":"Professional",
            "subcategory":"Computer Services",
            "type":"Services"
        }
    ],
    "sg:phone":"+1 503 710 9772",
    "sg:postcode":"97220",
    "sg:province":"OR",
    "sg:website":"http://www.revolttechnology.com",
    "wof:name":"Revolt Technology",
    "wof:placetype":"venue"
},
  "geometry": {"coordinates":[-122.54488600000001,45.569001],"type":"Point"}
}