{
  "type": "Feature",
  "properties": {
    "iso:country":"US",
    "sg:address":"261 E 12th Ave Ste 210",
    "sg:city":"Eugene",
    "sg:classifiers":[
        {
            "category":"Education",
            "subcategory":"Library",
            "type":"Public Place"
        }
    ],
    "sg:phone":"+1 541 345 0404",
    "sg:postcode":"97401",
    "sg:province":"OR",
    "sg:tags":[
        "research"
    ],
    "sg:website":"http://www.deschutesresearch.com",
    "wof:name":"Deschutesresearch.Com",
    "wof:placetype":"venue"
},
  "geometry": {"coordinates":[-123.088791,44.046619],"type":"Point"}
}