{
  "type": "Feature",
  "properties": {
    "addr:full":"4805 SE Chase Rd Gresham OR 97080",
    "addr:housenumber":"4805",
    "addr:postcode":"97080",
    "addr:street":"Se Chase Rd",
    "iso:country":"US",
    "sg:address":"4805 SE Chase Rd",
    "sg:city":"Gresham",
    "sg:classifiers":[
        {
            "category":"Building & Trades",
            "subcategory":"Plumbing",
            "type":"Services"
        }
    ],
    "sg:phone":"+1 503 663 2901",
    "sg:postcode":"97080",
    "sg:province":"OR",
    "sg:tags":[
        "contractor"
    ],
    "wof:name":"Hoodland Plumbing",
    "wof:placetype":"venue"
},
  "geometry": {"coordinates":[-122.38249999999999,45.478649],"type":"Point"}
}