{
  "type": "Feature",
  "properties": {
    "iso:country":"US",
    "sg:address":"1818 Cherry Heights Rd",
    "sg:city":"The Dalles",
    "sg:classifiers":[
        {
            "category":"Freight",
            "type":"Transportation"
        }
    ],
    "sg:phone":"+1 541 298 7800",
    "sg:postcode":"97058",
    "sg:province":"OR",
    "sg:tags":[
        "operator",
        "local",
        "trucking"
    ],
    "wof:name":"Delivery Nans",
    "wof:placetype":"venue"
},
  "geometry": {"coordinates":[-121.209709,45.598597],"type":"Point"}
}