{
  "type": "Feature",
  "properties": {
    "iso:country":"US",
    "sg:address":"256 E Hurlburt Ave",
    "sg:city":"Hermiston",
    "sg:classifiers":[
        {
            "category":"Real Estate",
            "subcategory":"Real Estate Agent",
            "type":"Services"
        }
    ],
    "sg:phone":"+1 541 567 8249",
    "sg:postcode":"97838",
    "sg:province":"OR",
    "wof:name":"C Holt Real Estate",
    "wof:placetype":"venue"
},
  "geometry": {"coordinates":[-119.287896,45.839505],"type":"Point"}
}