{
  "type": "Feature",
  "properties": {
    "iso:country":"US",
    "sg:address":"62910 N Rolla Rd",
    "sg:city":"Bend",
    "sg:classifiers":[
        {
            "category":"Government",
            "subcategory":"Jail",
            "type":"Public Place"
        }
    ],
    "sg:phone":"+1 541 388 6155",
    "sg:postcode":"97754",
    "sg:province":"OR",
    "sg:tags":[
        "govt",
        "state",
        "institution"
    ],
    "wof:name":"Oregon Youth Authority",
    "wof:placetype":"venue"
},
  "geometry": {"coordinates":[-120.84777800000001,44.321363],"type":"Point"}
}