{
  "type": "Feature",
  "properties": {
    "iso:country":"US",
    "sg:address":"500 NE Martin Luther King Jr Blvd",
    "sg:city":"Portland",
    "sg:classifiers":[
        {
            "category":"Bars & Pubs",
            "subcategory":"Sports Bar",
            "type":"Food & Drink"
        }
    ],
    "sg:postcode":"97214",
    "sg:province":"OR",
    "sg:website":"ripcitybar.com",
    "wof:name":"Rip City",
    "wof:placetype":"venue"
},
  "geometry": {"coordinates":[-122.66176900000001,45.519334],"type":"Point"}
}