{
  "type": "Feature",
  "properties": {
    "iso:country":"US",
    "sg:address":"1105 NW Lovejoy Street",
    "sg:city":"Portland",
    "sg:classifiers":[
        {
            "category":"Restaurant",
            "type":"Food & Drink"
        }
    ],
    "sg:phone":"+1 503 222 7327",
    "sg:postcode":"97209",
    "sg:province":"OR",
    "sg:tags":[
        "chinese"
    ],
    "sg:website":"wwwseresrestaurant.com",
    "wof:name":"Seres Chinese Restaurant",
    "wof:placetype":"venue"
},
  "geometry": {"coordinates":[-122.68241999999999,45.530102],"type":"Point"}
}