{
  "type": "Feature",
  "properties": {
    "addr:full":"3104 20th Ave SE Albany OR 97322",
    "addr:housenumber":"3104",
    "addr:postcode":"97322",
    "addr:street":"20Th Ave Se",
    "iso:country":"US",
    "sg:address":"3104 20th Ave SE",
    "sg:city":"Albany",
    "sg:classifiers":[
        {
            "category":"Banks & Credit Unions",
            "subcategory":"Financial Services",
            "type":"Services"
        }
    ],
    "sg:phone":"+1 541 619 0931",
    "sg:postcode":"97322",
    "sg:province":"OR",
    "sg:tags":[
        "investor"
    ],
    "wof:name":"E & L Investments LLC",
    "wof:placetype":"venue"
},
  "geometry": {"coordinates":[-123.067589,44.623511],"type":"Point"}
}