{
  "type": "Feature",
  "properties": {
    "addr:full":"800 Willamette St Eugene OR 97401",
    "addr:housenumber":"800",
    "addr:postcode":"97401",
    "addr:street":"Willamette St",
    "iso:country":"US",
    "sg:address":"800 Willamette St",
    "sg:city":"Eugene",
    "sg:classifiers":[
        {
            "category":"Banks & Credit Unions",
            "subcategory":"Investment Brokerage",
            "type":"Services"
        }
    ],
    "sg:phone":"+1 541 344 4224",
    "sg:postcode":"97401",
    "sg:province":"OR",
    "sg:tags":[
        "consultant",
        "planning",
        "financial"
    ],
    "wof:name":"Piper Jaffray Co",
    "wof:placetype":"venue"
},
  "geometry": {"coordinates":[-123.092738,44.050468],"type":"Point"}
}