{
  "type": "Feature",
  "properties": {
    "iso:country":"US",
    "sg:address":"519 Main St",
    "sg:city":"Klamath Falls",
    "sg:classifiers":[
        {
            "category":"Real Estate",
            "subcategory":"Real Estate Agent",
            "type":"Services"
        },
        {
            "category":"Real Estate",
            "subcategory":"Real Estate Operator",
            "type":"Services"
        }
    ],
    "sg:phone":"+1 541 885 4400",
    "sg:postcode":"97601",
    "sg:province":"OR",
    "sg:tags":[
        "company",
        "holding"
    ],
    "sg:website":"www.klamath-windermere.com",
    "wof:name":"Windermere Real Estate Inc",
    "wof:placetype":"venue"
},
  "geometry": {"coordinates":[-121.78272,42.224664],"type":"Point"}
}