{
  "type": "Feature",
  "properties": {
    "iso:country":"US",
    "sg:address":"860 W 6th Ave",
    "sg:city":"Eugene",
    "sg:classifiers":[
        {
            "category":"Recreation",
            "type":"Entertainment"
        }
    ],
    "sg:phone":"+1 541 345 5277",
    "sg:postcode":"97402",
    "sg:province":"OR",
    "wof:name":"Pierce Family Kung Fu",
    "wof:placetype":"venue"
},
  "geometry": {"coordinates":[-123.105682,44.053175],"type":"Point"}
}