{
  "type": "Feature",
  "properties": {
    "iso:country":"US",
    "sg:address":"543 Lawrence St",
    "sg:city":"Eugene",
    "sg:classifiers":[
        {
            "category":"Professional",
            "type":"Services"
        }
    ],
    "sg:phone":"+1 541 683 8577",
    "sg:postcode":"97401",
    "sg:province":"OR",
    "wof:name":"Roberts & Woods Inc",
    "wof:placetype":"venue"
},
  "geometry": {"coordinates":[-123.098744,44.054273],"type":"Point"}
}