{
  "type": "Feature",
  "properties": {
    "addr:full":"231 N V St Lakeview OR 97630",
    "addr:housenumber":"231",
    "addr:postcode":"97630",
    "addr:street":"N V St",
    "iso:country":"US",
    "sg:address":"231 N V St",
    "sg:city":"Lakeview",
    "sg:classifiers":[
        {
            "category":"Retail",
            "subcategory":"Auto Repair",
            "type":"Services"
        }
    ],
    "sg:phone":"+1 541 947 3970",
    "sg:postcode":"97630",
    "sg:province":"OR",
    "sg:tags":[
        "general"
    ],
    "wof:name":"Mikes Automotive Service",
    "wof:placetype":"venue"
},
  "geometry": {"coordinates":[-120.36510800000001,42.193199],"type":"Point"}
}