{
  "type": "Feature",
  "properties": {
    "iso:country":"US",
    "sg:address":"26012 Vista Dr",
    "sg:city":"Veneta",
    "sg:classifiers":[
        {
            "category":"Building & Trades",
            "subcategory":"Construction",
            "type":"Services"
        }
    ],
    "sg:phone":"+1 541 687 1733",
    "sg:postcode":"97487",
    "sg:province":"OR",
    "sg:tags":[
        "hanging",
        "contractor"
    ],
    "wof:name":"Am Discount Painting Inc",
    "wof:placetype":"venue"
},
  "geometry": {"coordinates":[-123.316417,44.061497],"type":"Point"}
}