{
  "type": "Feature",
  "properties": {
    "iso:country":"US",
    "sg:address":"1728 NE 40th Ave",
    "sg:city":"Portland",
    "sg:classifiers":[
        {
            "category":"Bars & Pubs",
            "type":"Food & Drink"
        },
        {
            "category":"Brewery",
            "type":"Food & Drink"
        }
    ],
    "sg:menulink":"http://www.allmenus.com/or/portland/5816-laurelwood-public-house--brewery/menu/",
    "sg:phone":"+1 503 282 0622",
    "sg:postcode":"97212",
    "sg:province":"OR",
    "sg:tags":[
        "american"
    ],
    "wof:name":"Laurelwood Public House & Brewery",
    "wof:placetype":"venue"
},
  "geometry": {"coordinates":[-122.621961,45.53552],"type":"Point"}
}