{
  "type": "Feature",
  "properties": {
    "iso:country":"US",
    "sg:address":"1041 Janeta Ave",
    "sg:city":"Nyssa",
    "sg:classifiers":[
        {
            "category":"Farming",
            "subcategory":"Farm & Veterinary Services",
            "type":"Manufacturing & Wholesale Goods"
        }
    ],
    "sg:phone":"+1 541 372 5025",
    "sg:postcode":"97913",
    "sg:province":"OR",
    "sg:tags":[
        "livestock"
    ],
    "wof:name":"Hkg Cattle Co",
    "wof:placetype":"venue"
},
  "geometry": {"coordinates":[-117.12424300000001,43.816389],"type":"Point"}
}