{
  "type": "Feature",
  "properties": {
    "iso:country":"US",
    "sg:address":"1144 Madison St NE",
    "sg:city":"Salem",
    "sg:classifiers":[
        {
            "category":"Communications",
            "subcategory":"Television Station",
            "type":"Services"
        }
    ],
    "sg:phone":"+1 503 362 0862",
    "sg:postcode":"97301",
    "sg:province":"OR",
    "sg:tags":[
        "broadcast",
        "representative"
    ],
    "sg:website":"http://www.ncbtv.org",
    "wof:name":"Northwest Christian Broadcasting",
    "wof:placetype":"venue"
},
  "geometry": {"coordinates":[-123.018728,44.95365],"type":"Point"}
}