{
  "type": "Feature",
  "properties": {
    "iso:country":"US",
    "sg:address":"616 Crater Lake Ave",
    "sg:city":"Medford",
    "sg:classifiers":[
        {
            "category":"Deli",
            "type":"Food & Drink"
        }
    ],
    "sg:phone":"+1 541 772 7489",
    "sg:postcode":"97504",
    "sg:province":"OR",
    "sg:website":"www.squeezeinndeli.com/",
    "wof:name":"Squeeze Inn",
    "wof:placetype":"venue"
},
  "geometry": {"coordinates":[-122.86199999999999,42.334999],"type":"Point"}
}