{
  "type": "Feature",
  "properties": {
    "addr:full":"111 SW 5th Avenue Portland OR 97204",
    "addr:housenumber":"111",
    "addr:postcode":"97204",
    "addr:street":"Sw 5Th Avenue",
    "iso:country":"US",
    "sg:address":"111 SW 5th Avenue",
    "sg:city":"Portland",
    "sg:classifiers":[
        {
            "category":"Banks & Credit Unions",
            "subcategory":"Bank",
            "type":"Services"
        }
    ],
    "sg:phone":"+1 503 275 4020",
    "sg:postcode":"97204",
    "sg:province":"OR",
    "wof:name":"U S Bank Sba Division",
    "wof:placetype":"venue"
},
  "geometry": {"coordinates":[-122.67555,45.522554],"type":"Point"}
}