{
  "type": "Feature",
  "properties": {
    "addr:full":"333 SW Taylor St Portland OR 97204",
    "addr:housenumber":"333",
    "addr:postcode":"97204",
    "addr:street":"Sw Taylor St",
    "iso:country":"US",
    "sg:address":"333 SW Taylor St",
    "sg:city":"Portland",
    "sg:classifiers":[
        {
            "category":"Education",
            "subcategory":"School",
            "type":"Public Place"
        }
    ],
    "sg:phone":"+1 503 219 8100",
    "sg:postcode":"97204",
    "sg:province":"OR",
    "wof:name":"West Portland Junior Baseball",
    "wof:placetype":"venue"
},
  "geometry": {"coordinates":[-122.67702,45.517175],"type":"Point"}
}