{
  "type": "Feature",
  "properties": {
    "iso:country":"US",
    "sg:address":"2386 Jacksonville Hwy",
    "sg:city":"Medford",
    "sg:classifiers":[
        {
            "category":"Retail",
            "subcategory":"Laundry & Dry Cleaning",
            "type":"Services"
        }
    ],
    "sg:phone":"+1 541 245 4055",
    "sg:postcode":"97501",
    "sg:province":"OR",
    "sg:tags":[
        "cleaners"
    ],
    "wof:name":"Weldon's Cleaning Ctr",
    "wof:placetype":"venue"
},
  "geometry": {"coordinates":[-122.900854,42.323717],"type":"Point"}
}