{
  "type": "Feature",
  "properties": {
    "addr:full":"750 Meadow Lark Ln Grants Pass OR 97526",
    "addr:housenumber":"750",
    "addr:postcode":"97526",
    "addr:street":"Meadow Lark Ln",
    "iso:country":"US",
    "sg:address":"750 Meadow Lark Ln",
    "sg:city":"Grants Pass",
    "sg:classifiers":[
        {
            "category":"Banks & Credit Unions",
            "subcategory":"Financial Services",
            "type":"Services"
        }
    ],
    "sg:phone":"+1 541 476 6567",
    "sg:postcode":"97526",
    "sg:province":"OR",
    "sg:tags":[
        "trust",
        "management"
    ],
    "wof:name":"Garinger Living Trust",
    "wof:placetype":"venue"
},
  "geometry": {"coordinates":[-123.32786299999999,42.505989],"type":"Point"}
}