{
  "type": "Feature",
  "properties": {
    "iso:country":"US",
    "sg:address":"528 SW 4th St",
    "sg:city":"Redmond",
    "sg:classifiers":[
        {
            "category":"Shopping",
            "subcategory":"Florist",
            "type":"Retail Goods"
        }
    ],
    "sg:phone":"+1 541 504 1400",
    "sg:postcode":"97756",
    "sg:province":"OR",
    "wof:name":"Countryside Crafts",
    "wof:placetype":"venue"
},
  "geometry": {"coordinates":[-121.17203600000001,44.271764],"type":"Point"}
}