{
  "type": "Feature",
  "properties": {
    "iso:country":"US",
    "sg:address":"5320 SW Macadam Ave",
    "sg:city":"Portland",
    "sg:classifiers":[
        {
            "category":"Professional",
            "subcategory":"Advertising",
            "type":"Services"
        }
    ],
    "sg:phone":"+1 503 236 3486",
    "sg:postcode":"97219",
    "sg:province":"OR",
    "sg:tags":[
        "counselor",
        "agency"
    ],
    "wof:name":"Lloyd Maris Advertising Inc",
    "wof:placetype":"venue"
},
  "geometry": {"coordinates":[-122.674542,45.484081],"type":"Point"}
}