{
  "type": "Feature",
  "properties": {
    "addr:full":"2006 Oregon Ave Klamath Falls OR 97601",
    "addr:housenumber":"2006",
    "addr:postcode":"97601",
    "addr:street":"Oregon Ave",
    "iso:country":"US",
    "sg:address":"2006 Oregon Ave",
    "sg:city":"Klamath Falls",
    "sg:classifiers":[
        {
            "category":"Retail",
            "subcategory":"Repair Shop",
            "type":"Services"
        }
    ],
    "sg:phone":"+1 541 885 4010",
    "sg:postcode":"97601",
    "sg:province":"OR",
    "sg:tags":[
        "electrical"
    ],
    "wof:name":"High Country Appliance & Spa",
    "wof:placetype":"venue"
},
  "geometry": {"coordinates":[-121.79109,42.238558],"type":"Point"}
}