{
  "type": "Feature",
  "properties": {
    "addr:full":"39380 Gary St Sandy OR 97055",
    "addr:housenumber":"39380",
    "addr:postcode":"97055",
    "addr:street":"Gary St",
    "iso:country":"US",
    "sg:address":"39380 Gary St",
    "sg:city":"Sandy",
    "sg:classifiers":[
        {
            "category":"Professional",
            "subcategory":"Engineering",
            "type":"Services"
        }
    ],
    "sg:phone":"+1 503 668 8095",
    "sg:postcode":"97055",
    "sg:province":"OR",
    "wof:name":"Kleinschmidt Associates",
    "wof:placetype":"venue"
},
  "geometry": {"coordinates":[-122.25852399999999,45.391911],"type":"Point"}
}