{
  "type": "Feature",
  "properties": {
    "addr:full":"3405 Camellia Dr S Salem OR 97302",
    "addr:housenumber":"3405",
    "addr:postcode":"97302",
    "addr:street":"Camellia Dr S",
    "iso:country":"US",
    "sg:address":"3405 Camellia Dr S",
    "sg:city":"Salem",
    "sg:classifiers":[
        {
            "category":"Shopping",
            "subcategory":"Gifts & Souvenirs",
            "type":"Retail Goods"
        }
    ],
    "sg:phone":"+1 503 391 4248",
    "sg:postcode":"97302",
    "sg:province":"OR",
    "sg:tags":[
        "cards"
    ],
    "wof:name":"Chuckles Special Occasions",
    "wof:placetype":"venue"
},
  "geometry": {"coordinates":[-123.064933,44.908939],"type":"Point"}
}