{
  "type": "Feature",
  "properties": {
    "iso:country":"US",
    "sg:address":"22120 SW 82nd Ave",
    "sg:city":"Tualatin",
    "sg:classifiers":[
        {
            "category":"Building & Trades",
            "subcategory":"Construction",
            "type":"Services"
        }
    ],
    "sg:phone":"+1 503 638 8110",
    "sg:postcode":"97062",
    "sg:province":"OR",
    "sg:tags":[
        "excavating",
        "contractor"
    ],
    "wof:name":"C & W Grading Inc",
    "wof:placetype":"venue"
},
  "geometry": {"coordinates":[-122.7606,45.360802],"type":"Point"}
}