{
  "type": "Feature",
  "properties": {
    "iso:country":"US",
    "sg:address":"6903 SE Mall St",
    "sg:city":"Portland",
    "sg:classifiers":[
        {
            "category":"Restaurant",
            "type":"Food & Drink"
        }
    ],
    "sg:phone":"+1 503 232 4447",
    "sg:postcode":"97206",
    "sg:province":"OR",
    "sg:tags":[
        "traditional",
        "american"
    ],
    "wof:name":"Kay's Bar & Grill",
    "wof:placetype":"venue"
},
  "geometry": {"coordinates":[-122.59200300000001,45.4911],"type":"Point"}
}