{
  "type": "Feature",
  "properties": {
    "addr:full":"800 NE Dekum Street Portland OR 97211",
    "addr:housenumber":"800",
    "addr:postcode":"97211",
    "addr:street":"Ne Dekum Street",
    "iso:country":"US",
    "sg:address":"800 NE Dekum Street",
    "sg:city":"Portland",
    "sg:classifiers":[
        {
            "category":"Restaurant",
            "type":"Food & Drink"
        }
    ],
    "sg:phone":"+1 503 285 7400",
    "sg:postcode":"97211",
    "sg:province":"OR",
    "sg:tags":[
        "pizza"
    ],
    "sg:website":"goodneighborpizzeria.com/",
    "wof:name":"Good Neighbor Pizzeria",
    "wof:placetype":"venue"
},
  "geometry": {"coordinates":[-122.657295,45.571655],"type":"Point"}
}