{
  "type": "Feature",
  "properties": {
    "addr:full":"7003 SE Molt St Portland OR 97267",
    "addr:housenumber":"7003",
    "addr:postcode":"97267",
    "addr:street":"Se Molt St",
    "iso:country":"US",
    "sg:address":"7003 SE Molt St",
    "sg:city":"Portland",
    "sg:classifiers":[
        {
            "category":"Professional",
            "subcategory":"Accounting & Tax Preparation",
            "type":"Services"
        }
    ],
    "sg:phone":"+1 503 653 6149",
    "sg:postcode":"97267",
    "sg:province":"OR",
    "wof:name":"Accounting Systems & Services",
    "wof:placetype":"venue"
},
  "geometry": {"coordinates":[-122.593152,45.413007],"type":"Point"}
}