{
  "type": "Feature",
  "properties": {
    "addr:full":"777 NW 9th St Suite 200 Corvallis OR 97330",
    "addr:housenumber":"777",
    "addr:postcode":"97330",
    "addr:street":"Nw 9Th St Suite 200",
    "iso:country":"US",
    "sg:address":"777 NW 9th St Suite 200",
    "sg:city":"Corvallis",
    "sg:classifiers":[
        {
            "category":"Personal",
            "subcategory":"Beauty Salon",
            "type":"Services"
        },
        {
            "category":"Personal",
            "subcategory":"Hair Removal",
            "type":"Services"
        },
        {
            "category":"Personal",
            "subcategory":"Skin Care",
            "type":"Services"
        },
        {
            "category":"Personal",
            "subcategory":"Nail Salon",
            "type":"Services"
        }
    ],
    "sg:phone":"+1 541 738 7328",
    "sg:postcode":"97330",
    "sg:province":"OR",
    "sg:tags":[
        "stylist"
    ],
    "sg:website":"http://www.theretreatonline.com",
    "wof:name":"The Retreat Day Spa & Salon",
    "wof:placetype":"venue"
},
  "geometry": {"coordinates":[-123.26422700000001,44.571954],"type":"Point"}
}