{
  "type": "Feature",
  "properties": {
    "addr:full":"2002 NE 13th Ave Portland OR 97212",
    "addr:housenumber":"2002",
    "addr:postcode":"97212",
    "addr:street":"Ne 13Th Ave",
    "iso:country":"US",
    "sg:address":"2002 NE 13th Ave",
    "sg:city":"Portland",
    "sg:classifiers":[
        {
            "category":"Professional",
            "subcategory":"Computer Services",
            "type":"Services"
        }
    ],
    "sg:phone":"+1 503 460 2908",
    "sg:postcode":"97212",
    "sg:province":"OR",
    "sg:tags":[
        "home",
        "consulting",
        "page",
        "dev",
        "internet"
    ],
    "wof:name":"Edge Productions",
    "wof:placetype":"venue"
},
  "geometry": {"coordinates":[-122.65242499999999,45.536948],"type":"Point"}
}