{
  "type": "Feature",
  "properties": {
    "iso:country":"US",
    "sg:address":"4012 SE Tolman St",
    "sg:city":"Portland",
    "sg:classifiers":[
        {
            "category":"Manufacturing",
            "subcategory":"Printing",
            "type":"Manufacturing & Wholesale Goods"
        }
    ],
    "sg:phone":"+1 503 774 4290",
    "sg:postcode":"97202",
    "sg:province":"OR",
    "sg:tags":[
        "lithographic",
        "commercial"
    ],
    "wof:name":"Ideal Screen Prtg Productions",
    "wof:placetype":"venue"
},
  "geometry": {"coordinates":[-122.620752,45.476949],"type":"Point"}
}