{
  "type": "Feature",
  "properties": {
    "iso:country":"US",
    "sg:address":"1808 Belmont Ave",
    "sg:city":"Hood River",
    "sg:classifiers":[
        {
            "category":"Building & Trades",
            "subcategory":"Construction",
            "type":"Services"
        }
    ],
    "sg:phone":"+1 541 387 2832",
    "sg:postcode":"97031",
    "sg:province":"OR",
    "sg:tags":[
        "dry wall",
        "contractor"
    ],
    "wof:name":"Stintzi Drywall",
    "wof:placetype":"venue"
},
  "geometry": {"coordinates":[-121.531034,45.699751],"type":"Point"}
}