{
  "type": "Feature",
  "properties": {
    "iso:country":"US",
    "sg:address":"201 B Ave Ste 285",
    "sg:city":"Lake Oswego",
    "sg:classifiers":[
        {
            "category":"Health Services",
            "subcategory":"Doctor",
            "type":"Services"
        }
    ],
    "sg:phone":"+1 503 974 9328",
    "sg:postcode":"97034",
    "sg:province":"OR",
    "wof:name":"Chenoweth John P MD PC",
    "wof:placetype":"venue"
},
  "geometry": {"coordinates":[-122.665211,45.420956],"type":"Point"}
}