{
  "type": "Feature",
  "properties": {
    "iso:country":"US",
    "sg:address":"68 NE 89th Ct",
    "sg:city":"Newport",
    "sg:classifiers":[
        {
            "category":"Professional",
            "subcategory":"Credit Reporting & Collection",
            "type":"Services"
        }
    ],
    "sg:phone":"+1 541 265 6880",
    "sg:postcode":"97365",
    "sg:province":"OR",
    "sg:tags":[
        "adjustment"
    ],
    "wof:name":"Account Collection Bureau Inc",
    "wof:placetype":"venue"
},
  "geometry": {"coordinates":[-124.06116,44.701715],"type":"Point"}
}