{
  "type": "Feature",
  "properties": {
    "iso:country":"US",
    "sg:address":"2294 NW Kings Blvd",
    "sg:city":"Corvallis",
    "sg:classifiers":[
        {
            "category":"Health Services",
            "subcategory":"Doctor",
            "type":"Services"
        }
    ],
    "sg:phone":"+1 541 754 1415",
    "sg:postcode":"97330",
    "sg:province":"OR",
    "sg:tags":[
        "physician",
        "surgeon"
    ],
    "wof:name":"Sandra J Hufsmith MD",
    "wof:placetype":"venue"
},
  "geometry": {"coordinates":[-123.276104,44.588425],"type":"Point"}
}