{
  "type": "Feature",
  "properties": {
    "iso:country":"US",
    "sg:address":"7420 SW Bridgeport Rd Ste 204",
    "sg:city":"Portland",
    "sg:classifiers":[
        {
            "category":"Professional",
            "subcategory":"Lawyer & Legal Services",
            "type":"Services"
        }
    ],
    "sg:phone":"+1 503 670 0443",
    "sg:postcode":"97224",
    "sg:province":"OR",
    "sg:tags":[
        "divorce",
        "law",
        "family"
    ],
    "wof:name":"Perry & Winegar Llc",
    "wof:placetype":"venue"
},
  "geometry": {"coordinates":[-122.751999,45.3946],"type":"Point"}
}