{
  "type": "Feature",
  "properties": {
    "addr:full":"590 NW Eastman Pkwy Gresham OR 97030",
    "addr:housenumber":"590",
    "addr:postcode":"97030",
    "addr:street":"Nw Eastman Pkwy",
    "iso:country":"US",
    "sg:address":"590 NW Eastman Pkwy",
    "sg:city":"Gresham",
    "sg:classifiers":[
        {
            "category":"Professional",
            "subcategory":"Accounting & Tax Preparation",
            "type":"Services"
        },
        {
            "category":"Banks & Credit Unions",
            "subcategory":"Financial Services",
            "type":"Services"
        }
    ],
    "sg:phone":"+1 503 492 0210",
    "sg:postcode":"97030",
    "sg:province":"OR",
    "sg:tags":[
        "return",
        "preparation-business",
        "taxes-consultants",
        "loan",
        "reporting",
        "representative",
        "alternative",
        "bookkeeping"
    ],
    "sg:website":"http://www.hrblock.com",
    "wof:name":"H&R Block",
    "wof:placetype":"venue"
},
  "geometry": {"coordinates":[-122.436142,45.501839],"type":"Point"}
}