{
  "type": "Feature",
  "properties": {
    "iso:country":"US",
    "sg:address":"2138 SE Lois Ln",
    "sg:city":"Roseburg",
    "sg:classifiers":[
        {
            "category":"Professional",
            "subcategory":"Advertising",
            "type":"Services"
        }
    ],
    "sg:phone":"+1 541 677 9019",
    "sg:postcode":"97470",
    "sg:province":"OR",
    "sg:tags":[
        "counselor"
    ],
    "wof:name":"Lazarus Media Group",
    "wof:placetype":"venue"
},
  "geometry": {"coordinates":[-123.32700699999999,43.204279],"type":"Point"}
}