{
  "type": "Feature",
  "properties": {
    "addr:full":"482 NE 18th Ave Hillsboro OR 97124",
    "addr:housenumber":"482",
    "addr:postcode":"97124",
    "addr:street":"Ne 18Th Ave",
    "iso:country":"US",
    "sg:address":"482 NE 18th Ave",
    "sg:city":"Hillsboro",
    "sg:classifiers":[
        {
            "category":"Retail",
            "subcategory":"Repair Shop",
            "type":"Services"
        }
    ],
    "sg:phone":"+1 503 681 9619",
    "sg:postcode":"97124",
    "sg:province":"OR",
    "sg:tags":[
        "appliance"
    ],
    "wof:name":"A Metro Appliance Svc",
    "wof:placetype":"venue"
},
  "geometry": {"coordinates":[-122.96357500000001,45.526918],"type":"Point"}
}