{
  "type": "Feature",
  "properties": {
    "iso:country":"US",
    "sg:address":"7704 NW Blue Pointe Ln",
    "sg:city":"Portland",
    "sg:classifiers":[
        {
            "category":"Professional",
            "subcategory":"Art Services",
            "type":"Services"
        }
    ],
    "sg:phone":"+1 503 296 7831",
    "sg:postcode":"97229",
    "sg:province":"OR",
    "sg:tags":[
        "commercial",
        "artist"
    ],
    "wof:name":"Remnanworks",
    "wof:placetype":"venue"
},
  "geometry": {"coordinates":[-122.757882,45.53222],"type":"Point"}
}