{
  "type": "Feature",
  "properties": {
    "addr:full":"3384 NW Maxine Cir Corvallis OR 97330",
    "addr:housenumber":"3384",
    "addr:postcode":"97330",
    "addr:street":"Nw Maxine Cir",
    "iso:country":"US",
    "sg:address":"3384 NW Maxine Cir",
    "sg:city":"Corvallis",
    "sg:classifiers":[
        {
            "category":"Food & Beverages",
            "subcategory":"Bakery",
            "type":"Retail Goods"
        }
    ],
    "sg:phone":"+1 541 757 7018",
    "sg:postcode":"97330",
    "sg:province":"OR",
    "wof:name":"Desert Dozen LLC",
    "wof:placetype":"venue"
},
  "geometry": {"coordinates":[-123.260318,44.600026],"type":"Point"}
}