{
  "type": "Feature",
  "properties": {
    "iso:country":"US",
    "sg:address":"777 NW Beach Dr",
    "sg:city":"Newport",
    "sg:classifiers":[
        {
            "category":"Arts & Performance",
            "subcategory":"Art Gallery",
            "type":"Entertainment"
        },
        {
            "category":"Shopping",
            "subcategory":"Crafts & Fabrics",
            "type":"Retail Goods"
        }
    ],
    "sg:phone":"+1 541 265 6540",
    "sg:postcode":"97365",
    "sg:province":"OR",
    "sg:tags":[
        "consultant",
        "galleries",
        "instruction"
    ],
    "sg:website":"http://www.coastarts.org",
    "wof:name":"Newport Visual Art Center",
    "wof:placetype":"venue"
},
  "geometry": {"coordinates":[-124.062539,44.638955],"type":"Point"}
}