{
  "type": "Feature",
  "properties": {
    "addr:full":"19082 S Lyons Rd Oregon City OR 97045",
    "addr:housenumber":"19082",
    "addr:postcode":"97045",
    "addr:street":"S Lyons Rd",
    "iso:country":"US",
    "sg:address":"19082 S Lyons Rd",
    "sg:city":"Oregon City",
    "sg:classifiers":[
        {
            "category":"Building & Trades",
            "subcategory":"Construction",
            "type":"Services"
        }
    ],
    "sg:phone":"+1 503 631 2767",
    "sg:postcode":"97045",
    "sg:province":"OR",
    "sg:tags":[
        "excavation",
        "excavating",
        "contractor"
    ],
    "wof:name":"Warner Bobcat Backhoe Service",
    "wof:placetype":"venue"
},
  "geometry": {"coordinates":[-122.474288,45.302096],"type":"Point"}
}