{
  "type": "Feature",
  "properties": {
    "addr:full":"11673 Ehlen Rd NE Aurora OR 97002",
    "addr:housenumber":"11673",
    "addr:postcode":"97002",
    "addr:street":"Ehlen Rd Ne",
    "iso:country":"US",
    "sg:address":"11673 Ehlen Rd NE",
    "sg:city":"Aurora",
    "sg:classifiers":[
        {
            "category":"Farming",
            "subcategory":"Poultry Farm",
            "type":"Manufacturing & Wholesale Goods"
        }
    ],
    "sg:phone":"+1 503 678 2909",
    "sg:postcode":"97002",
    "sg:province":"OR",
    "sg:tags":[
        "chicken"
    ],
    "wof:name":"Fircrest Farms 4",
    "wof:placetype":"venue"
},
  "geometry": {"coordinates":[-122.82341099999999,45.231508],"type":"Point"}
}