{
  "type": "Feature",
  "properties": {
    "iso:country":"US",
    "sg:address":"270 Lancaster Dr NE",
    "sg:city":"Salem",
    "sg:classifiers":[
        {
            "category":"Retail",
            "subcategory":"Car Wash",
            "type":"Services"
        }
    ],
    "sg:phone":"+1 503 304 1051",
    "sg:postcode":"97301",
    "sg:province":"OR",
    "sg:tags":[
        "polishing",
        "washing"
    ],
    "wof:name":"Splash'n Dash Car Washes",
    "wof:placetype":"venue"
},
  "geometry": {"coordinates":[-122.983155,44.931776],"type":"Point"}
}