{
  "type": "Feature",
  "properties": {
    "addr:full":"4314 Goodrich Hwy Oakland OR 97462",
    "addr:housenumber":"4314",
    "addr:postcode":"97462",
    "addr:street":"Goodrich Hwy",
    "iso:country":"US",
    "sg:address":"4314 Goodrich Hwy",
    "sg:city":"Oakland",
    "sg:classifiers":[
        {
            "category":"Home & Garden",
            "subcategory":"Garden Supply",
            "type":"Retail Goods"
        }
    ],
    "sg:phone":"+1 541 459 1361",
    "sg:postcode":"97462",
    "sg:province":"OR",
    "sg:tags":[
        "nurseryman"
    ],
    "wof:name":"Oakhill Farms",
    "wof:placetype":"venue"
},
  "geometry": {"coordinates":[-123.29311300000001,43.50237],"type":"Point"}
}