{
  "type": "Feature",
  "properties": {
    "iso:country":"US",
    "sg:address":"2525 W 7th Pl",
    "sg:city":"Eugene",
    "sg:classifiers":[
        {
            "category":"Food & Beverages",
            "subcategory":"Fruits & Vegetables",
            "type":"Retail Goods"
        }
    ],
    "sg:phone":"+1 541 342 2136",
    "sg:postcode":"97402",
    "sg:province":"OR",
    "sg:tags":[
        "produce"
    ],
    "wof:name":"Emerald Fruit & Produce Co",
    "wof:placetype":"venue"
},
  "geometry": {"coordinates":[-123.13351400000001,44.051866],"type":"Point"}
}