{
  "type": "Feature",
  "properties": {
    "iso:country":"US",
    "sg:address":"31455 Tide Creek Rd",
    "sg:city":"Rainier",
    "sg:classifiers":[
        {
            "category":"Utilities",
            "subcategory":"Water",
            "type":"Services"
        },
        {
            "category":"Sports & Exercise",
            "subcategory":"Race Track",
            "type":"Entertainment"
        }
    ],
    "sg:phone":"+1 503 556 0107",
    "sg:postcode":"97048",
    "sg:province":"OR",
    "sg:tags":[
        "equipment",
        "horse",
        "barn"
    ],
    "wof:name":"Tide Creek Nursery & Tack Shop",
    "wof:placetype":"venue"
},
  "geometry": {"coordinates":[-122.91616999999999,45.966561],"type":"Point"}
}