{
  "type": "Feature",
  "properties": {
    "iso:country":"US",
    "sg:address":"621 SW 16th Avenue",
    "sg:city":"Portland",
    "sg:classifiers":[
        {
            "category":"Food & Beverages",
            "subcategory":"Groceries & Convenience Stores",
            "type":"Retail Goods"
        }
    ],
    "sg:phone":"+1 503 224 9661",
    "sg:postcode":"97205",
    "sg:province":"OR",
    "wof:name":"Commodore Grocery",
    "wof:placetype":"venue"
},
  "geometry": {"coordinates":[-122.68786299999999,45.522163],"type":"Point"}
}