{
  "type": "Feature",
  "properties": {
    "iso:country":"US",
    "sg:address":"1463 SW 20th Ct",
    "sg:city":"Gresham",
    "sg:classifiers":[
        {
            "category":"Professional",
            "subcategory":"Management & Consulting",
            "type":"Services"
        }
    ],
    "sg:phone":"+1 503 667 8496",
    "sg:postcode":"97080",
    "sg:province":"OR",
    "wof:name":"Gobble Shults & Associates",
    "wof:placetype":"venue"
},
  "geometry": {"coordinates":[-122.446382,45.481956],"type":"Point"}
}