{
  "type": "Feature",
  "properties": {
    "iso:country":"US",
    "sg:address":"213 SW Ash St Ste 204",
    "sg:city":"Portland",
    "sg:classifiers":[
        {
            "category":"Organizations",
            "subcategory":"Community Association",
            "type":"Services"
        }
    ],
    "sg:phone":"+1 503 827 5700",
    "sg:postcode":"97204",
    "sg:province":"OR",
    "wof:name":"Trout Unlimited",
    "wof:placetype":"venue"
},
  "geometry": {"coordinates":[-122.67252000000001,45.522024],"type":"Point"}
}