{
  "type": "Feature",
  "properties": {
    "iso:country":"US",
    "sg:address":"14835 SE Barkley Ct",
    "sg:city":"Boring",
    "sg:classifiers":[
        {
            "category":"Building & Trades",
            "subcategory":"Landscaping Services",
            "type":"Services"
        }
    ],
    "sg:phone":"+1 503 658 3277",
    "sg:postcode":"97089",
    "sg:province":"OR",
    "sg:tags":[
        "tree"
    ],
    "wof:name":"Affordable Tree Svc",
    "wof:placetype":"venue"
},
  "geometry": {"coordinates":[-122.44116,45.415959],"type":"Point"}
}