{
  "type": "Feature",
  "properties": {
    "addr:full":"9627 SW Washington Square Road Portland OR 97223",
    "addr:housenumber":"9627",
    "addr:postcode":"97223",
    "addr:street":"Sw Washington Square Road",
    "iso:country":"US",
    "sg:address":"9627 SW Washington Square Road",
    "sg:city":"Portland",
    "sg:classifiers":[
        {
            "category":"Restaurant",
            "type":"Food & Drink"
        }
    ],
    "sg:phone":"+1 503 684 3453",
    "sg:postcode":"97223",
    "sg:province":"OR",
    "wof:name":"Rainier Roaster",
    "wof:placetype":"venue"
},
  "geometry": {"coordinates":[-122.78295199999999,45.449224],"type":"Point"}
}