{
  "type": "Feature",
  "properties": {
    "iso:country":"US",
    "sg:address":"97839 Shopping Center Ave",
    "sg:city":"Brookings",
    "sg:classifiers":[
        {
            "category":"Health Services",
            "subcategory":"Doctor",
            "type":"Services"
        }
    ],
    "sg:phone":"+1 541 469 2015",
    "sg:postcode":"97415",
    "sg:province":"OR",
    "sg:tags":[
        "medicine",
        "physician",
        "practice",
        "surgeons",
        "family"
    ],
    "wof:name":"Kosche, Kathleen A Lcsw",
    "wof:placetype":"venue"
},
  "geometry": {"coordinates":[-124.263367,42.05122],"type":"Point"}
}