{
  "type": "Feature",
  "properties": {
    "iso:country":"US",
    "sg:address":"585 Newmark Ave",
    "sg:city":"Coos Bay",
    "sg:classifiers":[
        {
            "category":"Retail",
            "subcategory":"Auto Repair",
            "type":"Services"
        }
    ],
    "sg:phone":"+1 541 888 1179",
    "sg:postcode":"97420",
    "sg:province":"OR",
    "sg:tags":[
        "repairing",
        "automobile"
    ],
    "wof:name":"R & R Automotive",
    "wof:placetype":"venue"
},
  "geometry": {"coordinates":[-124.275228,43.392373],"type":"Point"}
}