{
  "type": "Feature",
  "properties": {
    "iso:country":"US",
    "sg:address":"6808 SE 144th Ave",
    "sg:city":"Portland",
    "sg:classifiers":[
        {
            "category":"Landmark",
            "subcategory":"Tourist Information",
            "type":"Public Place"
        }
    ],
    "sg:phone":"+1 503 762 4399",
    "sg:postcode":"97236",
    "sg:province":"OR",
    "sg:tags":[
        "promoter",
        "tours-operators"
    ],
    "wof:name":"America Pacific International",
    "wof:placetype":"venue"
},
  "geometry": {"coordinates":[-122.515095,45.473282],"type":"Point"}
}