{
  "type": "Feature",
  "properties": {
    "iso:country":"US",
    "sg:address":"8762 SW Illahee Dr",
    "sg:city":"Wilsonville",
    "sg:classifiers":[
        {
            "category":"Building & Trades",
            "subcategory":"Cleaning & Sanitation",
            "type":"Services"
        }
    ],
    "sg:phone":"+1 503 694 2281",
    "sg:postcode":"97070",
    "sg:province":"OR",
    "sg:tags":[
        "maintenance"
    ],
    "wof:name":"Crystal Clear Window Cleaning",
    "wof:placetype":"venue"
},
  "geometry": {"coordinates":[-122.767094,45.289572],"type":"Point"}
}