{
  "type": "Feature",
  "properties": {
    "addr:full":"4252 SE International Way Ste B Portland OR 97222",
    "addr:housenumber":"4252",
    "addr:postcode":"97222",
    "addr:street":"Se International Way Ste B",
    "iso:country":"US",
    "sg:address":"4252 SE International Way Ste B",
    "sg:city":"Portland",
    "sg:classifiers":[
        {
            "category":"Manufacturing",
            "subcategory":"Tools & Machinery",
            "type":"Manufacturing & Wholesale Goods"
        }
    ],
    "sg:phone":"+1 503 257 3321",
    "sg:postcode":"97222",
    "sg:province":"OR",
    "sg:tags":[
        "machine",
        "manufacturer"
    ],
    "wof:name":"Tool & Gage Associates, Inc.",
    "wof:placetype":"venue"
},
  "geometry": {"coordinates":[-122.61872099999999,45.438893],"type":"Point"}
}