{
  "type": "Feature",
  "properties": {
    "iso:country":"US",
    "sg:address":"PO Box 10532",
    "sg:city":"Portland",
    "sg:classifiers":[
        {
            "category":"Manufacturing",
            "subcategory":"Electronics",
            "type":"Manufacturing & Wholesale Goods"
        }
    ],
    "sg:phone":"+1 866 620 3120",
    "sg:postcode":"97296",
    "sg:province":"OR",
    "sg:website":"http://balllogic.com/",
    "wof:name":"BallLogic",
    "wof:placetype":"venue"
},
  "geometry": {"coordinates":[-122.374776,45.580557],"type":"Point"}
}