{
  "type": "Feature",
  "properties": {
    "iso:country":"US",
    "sg:address":"7940 Gladstone Ave",
    "sg:city":"White City",
    "sg:classifiers":[
        {
            "category":"Professional",
            "type":"Services"
        }
    ],
    "sg:phone":"+1 541 826 8942",
    "sg:postcode":"97503",
    "sg:province":"OR",
    "wof:name":"Greg Culver",
    "wof:placetype":"venue"
},
  "geometry": {"coordinates":[-122.839376,42.43419],"type":"Point"}
}