{
  "type": "Feature",
  "properties": {
    "addr:full":"213 Water Ave NW Albany OR 97321",
    "addr:housenumber":"213",
    "addr:postcode":"97321",
    "addr:street":"Water Ave Nw",
    "iso:country":"US",
    "sg:address":"213 Water Ave NW",
    "sg:city":"Albany",
    "sg:classifiers":[
        {
            "category":"Social Services",
            "type":"Services"
        }
    ],
    "sg:phone":"+1 541 928 8090",
    "sg:postcode":"97321",
    "sg:province":"OR",
    "sg:tags":[
        "counselor",
        "marriage",
        "family"
    ],
    "wof:name":"Terry Eheler",
    "wof:placetype":"venue"
},
  "geometry": {"coordinates":[-123.106517,44.638101],"type":"Point"}
}