{
  "type": "Feature",
  "properties": {
    "iso:country":"US",
    "sg:address":"11300 SW Bellevue Hwy",
    "sg:city":"Amity",
    "sg:classifiers":[
        {
            "category":"Building & Trades",
            "subcategory":"Construction",
            "type":"Services"
        }
    ],
    "sg:phone":"+1 503 835 3113",
    "sg:postcode":"97101",
    "sg:province":"OR",
    "sg:tags":[
        "wallcoverings-installation",
        "wallpaper",
        "painting",
        "contractor"
    ],
    "wof:name":"Carl Bragiel's Painting",
    "wof:placetype":"venue"
},
  "geometry": {"coordinates":[-123.22582199999999,45.114176],"type":"Point"}
}