{
  "type": "Feature",
  "properties": {
    "addr:full":"3011 SE Milwaukie Ave Portland OR 97202",
    "addr:housenumber":"3011",
    "addr:postcode":"97202",
    "addr:street":"Se Milwaukie Ave",
    "iso:country":"US",
    "sg:address":"3011 SE Milwaukie Ave",
    "sg:city":"Portland",
    "sg:classifiers":[
        {
            "category":"Professional",
            "type":"Services"
        }
    ],
    "sg:phone":"+1 503 775 0800",
    "sg:postcode":"97202",
    "sg:province":"OR",
    "wof:name":"Opus East Sheet Music",
    "wof:placetype":"venue"
},
  "geometry": {"coordinates":[-122.654293,45.500318],"type":"Point"}
}