{
  "type": "Feature",
  "properties": {
    "addr:full":"85367 US Hwy 101 Florence OR 97439",
    "addr:postcode":"85367;97439",
    "addr:street":"Us Hwy 101",
    "iso:country":"US",
    "sg:address":"85367 US Hwy 101",
    "sg:city":"Florence",
    "sg:classifiers":[
        {
            "category":"Shopping",
            "type":"Retail Goods"
        }
    ],
    "sg:phone":"+1 541 997 8011",
    "sg:postcode":"97439",
    "sg:province":"OR",
    "sg:tags":[
        "merchandise"
    ],
    "wof:name":"Oregon Water Service",
    "wof:placetype":"venue"
},
  "geometry": {"coordinates":[-124.10422,43.954858],"type":"Point"}
}