{
  "type": "Feature",
  "properties": {
    "addr:full":"3395 48th Ave NE Salem OR 97305",
    "addr:housenumber":"3395",
    "addr:postcode":"97305",
    "addr:street":"48Th Ave Ne",
    "iso:country":"US",
    "sg:address":"3395 48th Ave NE",
    "sg:city":"Salem",
    "sg:classifiers":[
        {
            "category":"Professional",
            "subcategory":"Business Services",
            "type":"Services"
        }
    ],
    "sg:phone":"+1 503 581 9788",
    "sg:postcode":"97305",
    "sg:province":"OR",
    "sg:tags":[
        "process",
        "serving"
    ],
    "wof:name":"Northwest Cvil Process Serving",
    "wof:placetype":"venue"
},
  "geometry": {"coordinates":[-122.96512800000001,44.969578],"type":"Point"}
}