{
  "type": "Feature",
  "properties": {
    "addr:full":"8635 SE 17th Ave Portland OR 97202",
    "addr:housenumber":"8635",
    "addr:postcode":"97202",
    "addr:street":"Se 17Th Ave",
    "iso:country":"US",
    "sg:address":"8635 SE 17th Ave",
    "sg:city":"Portland",
    "sg:classifiers":[
        {
            "category":"Retail",
            "subcategory":"Auto Repair",
            "type":"Services"
        }
    ],
    "sg:phone":"+1 503 233 3637",
    "sg:postcode":"97202",
    "sg:province":"OR",
    "wof:name":"D & J's Economy Garage",
    "wof:placetype":"venue"
},
  "geometry": {"coordinates":[-122.64707199999999,45.460509],"type":"Point"}
}