{
  "type": "Feature",
  "properties": {
    "addr:full":"859 7th St NW Salem OR 97304",
    "addr:housenumber":"859",
    "addr:postcode":"97304",
    "addr:street":"7Th St Nw",
    "iso:country":"US",
    "sg:address":"859 7th St NW",
    "sg:city":"Salem",
    "sg:classifiers":[
        {
            "category":"Manufacturing",
            "subcategory":"Tools & Machinery",
            "type":"Manufacturing & Wholesale Goods"
        },
        {
            "category":"Retail",
            "subcategory":"Repair Shop",
            "type":"Services"
        },
        {
            "category":"Retail",
            "subcategory":"Auto Repair",
            "type":"Services"
        }
    ],
    "sg:phone":"+1 503 364 3952",
    "sg:postcode":"97304",
    "sg:province":"OR",
    "sg:tags":[
        "machine",
        "automobile",
        "machinery-rebuild"
    ],
    "sg:website":"http://www.hanard.com",
    "wof:name":"Hanard Machine Inc",
    "wof:placetype":"venue"
},
  "geometry": {"coordinates":[-123.05521299999999,44.947655],"type":"Point"}
}