{
  "type": "Feature",
  "properties": {
    "iso:country":"US",
    "sg:address":"491 Lancaster Dr NE",
    "sg:city":"Salem",
    "sg:classifiers":[
        {
            "category":"Organizations",
            "subcategory":"Religious Organization",
            "type":"Services"
        }
    ],
    "sg:phone":"+1 503 363 3303",
    "sg:postcode":"97301",
    "sg:province":"OR",
    "wof:name":"Lancaster Bible Church",
    "wof:placetype":"venue"
},
  "geometry": {"coordinates":[-122.98317299999999,44.935424],"type":"Point"}
}