{
  "type": "Feature",
  "properties": {
    "addr:full":"82461 N Pacific Hwy Creswell OR 97426",
    "addr:housenumber":"82461",
    "addr:postcode":"97426",
    "addr:street":"N Pacific Hwy",
    "iso:country":"US",
    "sg:address":"82461 N Pacific Hwy",
    "sg:city":"Creswell",
    "sg:classifiers":[
        {
            "category":"Home & Garden",
            "subcategory":"Furniture",
            "type":"Retail Goods"
        }
    ],
    "sg:phone":"+1 541 895 5154",
    "sg:postcode":"97426",
    "sg:province":"OR",
    "sg:tags":[
        "wood",
        "mfg"
    ],
    "wof:name":"Countertops & More Inc",
    "wof:placetype":"venue"
},
  "geometry": {"coordinates":[-123.019372,43.90179],"type":"Point"}
}