{
  "type": "Feature",
  "properties": {
    "addr:full":"8600 SE Stark St Portland OR 97216",
    "addr:housenumber":"8600",
    "addr:postcode":"97216",
    "addr:street":"Se Stark St",
    "iso:country":"US",
    "sg:address":"8600 SE Stark St",
    "sg:city":"Portland",
    "sg:classifiers":[
        {
            "category":"Food & Beverages",
            "subcategory":"Groceries & Convenience Stores",
            "type":"Retail Goods"
        }
    ],
    "sg:phone":"+1 503 254 7273",
    "sg:postcode":"97216",
    "sg:province":"OR",
    "wof:name":"Beach House Coffee",
    "wof:placetype":"venue"
},
  "geometry": {"coordinates":[-122.57393399999999,45.519099],"type":"Point"}
}