{
  "type": "Feature",
  "properties": {
    "iso:country":"US",
    "sg:address":"12670 NW Barnes Rd",
    "sg:city":"Portland",
    "sg:classifiers":[
        {
            "category":"Professional",
            "subcategory":"Lawyer & Legal Services",
            "type":"Services"
        }
    ],
    "sg:phone":"+1 503 574 3100",
    "sg:postcode":"97229",
    "sg:province":"OR",
    "wof:name":"Smith-Hill & Bedell PC",
    "wof:placetype":"venue"
},
  "geometry": {"coordinates":[-122.80796100000001,45.523742],"type":"Point"}
}