{
  "type": "Feature",
  "properties": {
    "addr:full":"211 SE Oak St Portland OR 97214",
    "addr:housenumber":"211",
    "addr:postcode":"97214",
    "addr:street":"Se Oak St",
    "iso:country":"US",
    "sg:address":"211 SE Oak St",
    "sg:city":"Portland",
    "sg:classifiers":[
        {
            "category":"Autos & Motor Vehicles",
            "subcategory":"Auto Supplies",
            "type":"Retail Goods"
        }
    ],
    "sg:phone":"+1 503 808 9450",
    "sg:postcode":"97214",
    "sg:province":"OR",
    "sg:tags":[
        "automobile",
        "parts",
        "part",
        "accessories-wholesale",
        "manufacturer"
    ],
    "wof:name":"Marix Distributing",
    "wof:placetype":"venue"
},
  "geometry": {"coordinates":[-122.663685,45.520087],"type":"Point"}
}