{
  "type": "Feature",
  "properties": {
    "iso:country":"US",
    "sg:address":"12350 SW Winterview Dr",
    "sg:city":"Portland",
    "sg:classifiers":[
        {
            "category":"Restaurant",
            "type":"Food & Drink"
        }
    ],
    "sg:phone":"+1 503 531 0580",
    "sg:postcode":"97224",
    "sg:province":"OR",
    "sg:tags":[
        "asian",
        "chinese",
        "pan"
    ],
    "wof:name":"Mongolian Barbeque",
    "wof:placetype":"venue"
},
  "geometry": {"coordinates":[-122.804209,45.413159],"type":"Point"}
}