{
  "type": "Feature",
  "properties": {
    "iso:country":"US",
    "sg:address":"1004 S Central Ave",
    "sg:city":"Medford",
    "sg:classifiers":[
        {
            "category":"Utilities",
            "subcategory":"Telephone",
            "type":"Services"
        }
    ],
    "sg:phone":"+1 541 773 6448",
    "sg:postcode":"97501",
    "sg:province":"OR",
    "sg:tags":[
        "company"
    ],
    "wof:name":"General Telephone-The Nrthwst",
    "wof:placetype":"venue"
},
  "geometry": {"coordinates":[-122.863337,42.316713],"type":"Point"}
}