{
  "type": "Feature",
  "properties": {
    "addr:full":"6901 SE Lake Rd Portland OR 97267",
    "addr:housenumber":"6901",
    "addr:postcode":"97267",
    "addr:street":"Se Lake Rd",
    "iso:country":"US",
    "sg:address":"6901 SE Lake Rd",
    "sg:city":"Portland",
    "sg:classifiers":[
        {
            "category":"Banks & Credit Unions",
            "subcategory":"Bank",
            "type":"Services"
        }
    ],
    "sg:phone":"+1 503 786 1494",
    "sg:postcode":"97267",
    "sg:province":"OR",
    "sg:tags":[
        "mortgage",
        "loan",
        "broker",
        "real estate"
    ],
    "sg:website":"www.sweethomemortgage.com",
    "wof:name":"Sweethome Mortgage Inc",
    "wof:placetype":"venue"
},
  "geometry": {"coordinates":[-122.590548,45.423335],"type":"Point"}
}