{
  "type": "Feature",
  "properties": {
    "addr:full":"43775 NW Greenville Rd Forest Grove OR 97116",
    "addr:housenumber":"43775",
    "addr:postcode":"97116",
    "addr:street":"Nw Greenville Rd",
    "iso:country":"US",
    "sg:address":"43775 NW Greenville Rd",
    "sg:city":"Forest Grove",
    "sg:classifiers":[
        {
            "category":"Farming",
            "subcategory":"Farm",
            "type":"Manufacturing & Wholesale Goods"
        }
    ],
    "sg:phone":"+1 503 359 4763",
    "sg:postcode":"97116",
    "sg:province":"OR",
    "sg:tags":[
        "crop",
        "general"
    ],
    "wof:name":"Thomas Duyck & Vickie A D",
    "wof:placetype":"venue"
},
  "geometry": {"coordinates":[-123.12465899999999,45.592865],"type":"Point"}
}