{
  "type": "Feature",
  "properties": {
    "addr:full":"13370 SW Barlow Rd Beaverton OR 97008",
    "addr:housenumber":"13370",
    "addr:postcode":"97008",
    "addr:street":"Sw Barlow Rd",
    "iso:country":"US",
    "sg:address":"13370 SW Barlow Rd",
    "sg:city":"Beaverton",
    "sg:classifiers":[
        {
            "category":"Wholesale",
            "subcategory":"Stationery",
            "type":"Manufacturing & Wholesale Goods"
        }
    ],
    "sg:phone":"+1 503 671 9194",
    "sg:postcode":"97008",
    "sg:province":"OR",
    "sg:tags":[
        "paper",
        "products-wholesale",
        "manufacturer"
    ],
    "sg:website":"http://www.premiumpaperrolls.com",
    "wof:name":"Premium Paper & Supply Inc",
    "wof:placetype":"venue"
},
  "geometry": {"coordinates":[-122.81425900000001,45.470154],"type":"Point"}
}