{
  "type": "Feature",
  "properties": {
    "iso:country":"US",
    "sg:address":"10 W Q St Ste D",
    "sg:city":"Springfield",
    "sg:classifiers":[
        {
            "category":"Professional",
            "subcategory":"Art Services",
            "type":"Services"
        },
        {
            "category":"Building & Trades",
            "subcategory":"Construction",
            "type":"Services"
        },
        {
            "category":"Home & Garden",
            "subcategory":"Furniture",
            "type":"Retail Goods"
        }
    ],
    "sg:phone":"+1 541 726 3013",
    "sg:postcode":"97477",
    "sg:province":"OR",
    "sg:tags":[
        "interior",
        "designer",
        "store",
        "decorator",
        "contractor"
    ],
    "sg:website":"http://www.lanemarbleinteriors.com",
    "wof:name":"Lane Marble Interiors Inc",
    "wof:placetype":"venue"
},
  "geometry": {"coordinates":[-123.026246,44.0621],"type":"Point"}
}