{
  "type": "Feature",
  "properties": {
    "addr:full":"5041 Brooklake Rd NE Salem OR 97305",
    "addr:housenumber":"5041",
    "addr:postcode":"97305",
    "addr:street":"Brooklake Rd Ne",
    "iso:country":"US",
    "sg:address":"5041 Brooklake Rd NE",
    "sg:city":"Salem",
    "sg:classifiers":[
        {
            "category":"Personal",
            "subcategory":"Beauty Salon",
            "type":"Services"
        }
    ],
    "sg:phone":"+1 503 393 6555",
    "sg:postcode":"97305",
    "sg:province":"OR",
    "wof:name":"Brooks Family Hair Care Ctr",
    "wof:placetype":"venue"
},
  "geometry": {"coordinates":[-122.958309,45.048023],"type":"Point"}
}