{
  "type": "Feature",
  "properties": {
    "addr:full":"1505 N Lake Rd Lakeside OR 97449",
    "addr:housenumber":"1505",
    "addr:postcode":"97449",
    "addr:street":"N Lake Rd",
    "iso:country":"US",
    "sg:address":"1505 N Lake Rd",
    "sg:city":"Lakeside",
    "sg:classifiers":[
        {
            "category":"Travel",
            "subcategory":"Campground",
            "type":"Entertainment"
        }
    ],
    "sg:phone":"+1 541 759 2801",
    "sg:postcode":"97449",
    "sg:province":"OR",
    "sg:website":"www.ospreypoint.net",
    "wof:name":"Osprey Point Rv Resort",
    "wof:placetype":"venue"
},
  "geometry": {"coordinates":[-124.16711100000001,43.577445],"type":"Point"}
}