{
  "type": "Feature",
  "properties": {
    "iso:country":"US",
    "sg:address":"28772 US Hwy 730",
    "sg:city":"Umatilla",
    "sg:classifiers":[
        {
            "category":"Building & Trades",
            "subcategory":"Construction",
            "type":"Services"
        }
    ],
    "sg:phone":"+1 541 922 2730",
    "sg:postcode":"97882",
    "sg:province":"OR",
    "sg:tags":[
        "house"
    ],
    "wof:name":"Columbia River Construction",
    "wof:placetype":"venue"
},
  "geometry": {"coordinates":[-119.3835,45.912112],"type":"Point"}
}