{
  "type": "Feature",
  "properties": {
    "iso:country":"US",
    "sg:address":"1122 NE 48th Ave",
    "sg:city":"Portland",
    "sg:classifiers":[
        {
            "category":"Restaurant",
            "type":"Food & Drink"
        }
    ],
    "sg:phone":"+1 503 284 7284",
    "sg:postcode":"97213",
    "sg:province":"OR",
    "sg:tags":[
        "eating",
        "pizza"
    ],
    "sg:website":"http://www.vinniespizza.com",
    "wof:name":"Vinnies Pizza",
    "wof:placetype":"venue"
},
  "geometry": {"coordinates":[-122.61369500000001,45.530792],"type":"Point"}
}