{
  "type": "Feature",
  "properties": {
    "iso:country":"US",
    "sg:address":"62980 Boyd Acres Rd",
    "sg:city":"Bend",
    "sg:classifiers":[
        {
            "category":"Government",
            "subcategory":"Fire Station",
            "type":"Public Place"
        }
    ],
    "sg:phone":"+1 541 312 4201",
    "sg:postcode":"97701",
    "sg:province":"OR",
    "sg:tags":[
        "relief",
        "disaster",
        "recovery"
    ],
    "wof:name":"P Gc Building & Design",
    "wof:placetype":"venue"
},
  "geometry": {"coordinates":[-121.295531,44.087077],"type":"Point"}
}