{
  "type": "Feature",
  "properties": {
    "iso:country":"US",
    "sg:address":"28833 Douglas Dr",
    "sg:city":"Eugene",
    "sg:classifiers":[
        {
            "category":"Government",
            "subcategory":"Office",
            "type":"Public Place"
        }
    ],
    "sg:phone":"+1 541 607 4600",
    "sg:postcode":"97402",
    "sg:province":"OR",
    "sg:tags":[
        "control",
        "government-united",
        "state",
        "tower"
    ],
    "sg:website":"http://www.faa.gov",
    "wof:name":"Airport Traffic Control Tower",
    "wof:placetype":"venue"
},
  "geometry": {"coordinates":[-123.212594,44.118383],"type":"Point"}
}