{
  "type": "Feature",
  "properties": {
    "iso:country":"US",
    "sg:address":"24900 SE Stark St Ste 205",
    "sg:city":"Gresham",
    "sg:classifiers":[
        {
            "category":"Health Services",
            "subcategory":"Doctor",
            "type":"Services"
        }
    ],
    "sg:phone":"+1 503 661 2000",
    "sg:postcode":"97030",
    "sg:province":"OR",
    "wof:name":"Willis Brian R MD",
    "wof:placetype":"venue"
},
  "geometry": {"coordinates":[-122.407197,45.518913],"type":"Point"}
}