{
  "type": "Feature",
  "properties": {
    "iso:country":"US",
    "sg:address":"239 NE Lincoln St",
    "sg:city":"Hillsboro",
    "sg:classifiers":[
        {
            "category":"Insurance",
            "subcategory":"Insurance Agent",
            "type":"Services"
        }
    ],
    "sg:phone":"+1 503 640 4123",
    "sg:postcode":"97124",
    "sg:province":"OR",
    "wof:name":"Gardner Lyell Insurance",
    "wof:placetype":"venue"
},
  "geometry": {"coordinates":[-122.986735,45.523972],"type":"Point"}
}