{
  "type": "Feature",
  "properties": {
    "addr:full":"2525 NE Broadway Ste 200 Portland OR 97232",
    "addr:housenumber":"2525",
    "addr:postcode":"97232",
    "addr:street":"Ne Broadway Ste 200",
    "iso:country":"US",
    "sg:address":"2525 NE Broadway Ste 200",
    "sg:city":"Portland",
    "sg:classifiers":[
        {
            "category":"Health Services",
            "subcategory":"Dentist",
            "type":"Services"
        }
    ],
    "sg:phone":"+1 503 234 7870",
    "sg:postcode":"97232",
    "sg:province":"OR",
    "sg:tags":[
        "cosmetic"
    ],
    "sg:website":"drpauleortizdmd.com",
    "wof:name":"Paul Ortiz, DMD, PC",
    "wof:placetype":"venue"
},
  "geometry": {"coordinates":[-122.63986800000001,45.535177],"type":"Point"}
}