{
  "type": "Feature",
  "properties": {
    "iso:country":"US",
    "sg:address":"601 Center St",
    "sg:city":"Oregon City",
    "sg:classifiers":[
        {
            "category":"Health Services",
            "subcategory":"Doctor",
            "type":"Services"
        }
    ],
    "sg:phone":"+1 503 656 1905",
    "sg:postcode":"97045",
    "sg:province":"OR",
    "sg:tags":[
        "dentist"
    ],
    "wof:name":"Christopher Veley Fam & Gnrl",
    "wof:placetype":"venue"
},
  "geometry": {"coordinates":[-122.606285,45.35641],"type":"Point"}
}