{
  "type": "Feature",
  "properties": {
    "iso:country":"US",
    "sg:address":"16564 SE Gordon Court",
    "sg:city":"Portland",
    "sg:classifiers":[
        {
            "category":"Building & Trades",
            "subcategory":"Cleaning & Sanitation",
            "type":"Services"
        }
    ],
    "sg:phone":"+1 503 786 4364",
    "sg:postcode":"97267",
    "sg:province":"OR",
    "sg:tags":[
        "carpet"
    ],
    "wof:name":"Genie Cleaning Services",
    "wof:placetype":"venue"
},
  "geometry": {"coordinates":[-122.612801,45.403485],"type":"Point"}
}