{
  "type": "Feature",
  "properties": {
    "iso:country":"US",
    "sg:address":"1190 Crater Lake Ave",
    "sg:city":"Medford",
    "sg:classifiers":[
        {
            "category":"Retail",
            "subcategory":"Auto Repair",
            "type":"Services"
        }
    ],
    "sg:phone":"+1 541 734 2207",
    "sg:postcode":"97504",
    "sg:province":"OR",
    "wof:name":"Eastside Automotive",
    "wof:placetype":"venue"
},
  "geometry": {"coordinates":[-122.861,42.340599],"type":"Point"}
}