{
  "type": "Feature",
  "properties": {
    "iso:country":"US",
    "sg:address":"560 S 5th St",
    "sg:city":"Harrisburg",
    "sg:classifiers":[
        {
            "category":"Social Services",
            "subcategory":"Child Care",
            "type":"Services"
        }
    ],
    "sg:phone":"+1 541 995 5103",
    "sg:postcode":"97446",
    "sg:province":"OR",
    "sg:tags":[
        "nursery",
        "day"
    ],
    "wof:name":"Kid's Corner Preschool & Child Care",
    "wof:placetype":"venue"
},
  "geometry": {"coordinates":[-123.169033,44.268162],"type":"Point"}
}