{
  "type": "Feature",
  "properties": {
    "iso:country":"US",
    "sg:address":"23 NW Depot Rd",
    "sg:city":"Madras",
    "sg:classifiers":[
        {
            "category":"Real Estate",
            "subcategory":"Developer",
            "type":"Services"
        }
    ],
    "sg:phone":"+1 541 475 3976",
    "sg:postcode":"97741",
    "sg:province":"OR",
    "sg:tags":[
        "mobile",
        "home"
    ],
    "wof:name":"Tops Trailer Park",
    "wof:placetype":"venue"
},
  "geometry": {"coordinates":[-121.12930900000001,44.651997],"type":"Point"}
}