{
  "type": "Feature",
  "properties": {
    "iso:country":"US",
    "sg:address":"3495 W 18th Ave",
    "sg:city":"Eugene",
    "sg:classifiers":[
        {
            "category":"Organizations",
            "subcategory":"Religious Organization",
            "type":"Services"
        }
    ],
    "sg:phone":"+1 541 345 8054",
    "sg:postcode":"97402",
    "sg:province":"OR",
    "wof:name":"Eugene Friends Church",
    "wof:placetype":"venue"
},
  "geometry": {"coordinates":[-123.143428,44.040762],"type":"Point"}
}