{
  "type": "Feature",
  "properties": {
    "addr:full":"693 Ewe Creek Rd Grants Pass OR 97526",
    "addr:housenumber":"693",
    "addr:postcode":"97526",
    "addr:street":"Ewe Creek Rd",
    "iso:country":"US",
    "sg:address":"693 Ewe Creek Rd",
    "sg:city":"Grants Pass",
    "sg:classifiers":[
        {
            "category":"Building & Trades",
            "subcategory":"Electrical",
            "type":"Services"
        }
    ],
    "sg:phone":"+1 541 479 8016",
    "sg:postcode":"97526",
    "sg:province":"OR",
    "sg:tags":[
        "electrical",
        "electric",
        "contractor"
    ],
    "wof:name":"Wally Schmidt Electric Inc",
    "wof:placetype":"venue"
},
  "geometry": {"coordinates":[-123.44533699999999,42.485069],"type":"Point"}
}