{
  "type": "Feature",
  "properties": {
    "iso:country":"US",
    "sg:address":"5770 Main St",
    "sg:city":"Springfield",
    "sg:classifiers":[
        {
            "category":"Shopping",
            "subcategory":"Discount & Variety Stores",
            "type":"Retail Goods"
        }
    ],
    "sg:phone":"+1 541 988 9766",
    "sg:postcode":"97478",
    "sg:province":"OR",
    "wof:name":"Dollar Store",
    "wof:placetype":"venue"
},
  "geometry": {"coordinates":[-122.927662,44.045757],"type":"Point"}
}