{
  "type": "Feature",
  "properties": {
    "iso:country":"US",
    "sg:address":"1365 SE 10th St",
    "sg:city":"Warrenton",
    "sg:classifiers":[
        {
            "category":"Building & Trades",
            "subcategory":"Electrical",
            "type":"Services"
        }
    ],
    "sg:phone":"+1 503 861 1688",
    "sg:postcode":"97146",
    "sg:province":"OR",
    "sg:tags":[
        "electrical",
        "contractor"
    ],
    "wof:name":"U S Manufacturing & Dist",
    "wof:placetype":"venue"
},
  "geometry": {"coordinates":[-123.904475,46.156631],"type":"Point"}
}