{
  "type": "Feature",
  "properties": {
    "addr:full":"1541 Elm Ave Klamath Falls OR 97601",
    "addr:housenumber":"1541",
    "addr:postcode":"97601",
    "addr:street":"Elm Ave",
    "iso:country":"US",
    "sg:address":"1541 Elm Ave",
    "sg:city":"Klamath Falls",
    "sg:classifiers":[
        {
            "category":"Building & Trades",
            "subcategory":"Construction",
            "type":"Services"
        }
    ],
    "sg:phone":"+1 541 884 6253",
    "sg:postcode":"97601",
    "sg:province":"OR",
    "sg:tags":[
        "home",
        "general",
        "commercial",
        "family",
        "contractor"
    ],
    "wof:name":"Brosterhous Construction Co",
    "wof:placetype":"venue"
},
  "geometry": {"coordinates":[-121.77314800000001,42.222545],"type":"Point"}
}