{
  "type": "Feature",
  "properties": {
    "iso:country":"US",
    "sg:address":"715 Parkmeadow Loop NE",
    "sg:city":"Keizer",
    "sg:classifiers":[
        {
            "category":"Professional",
            "subcategory":"Detective & Security Services",
            "type":"Services"
        }
    ],
    "sg:phone":"+1 503 390 1631",
    "sg:postcode":"97303",
    "sg:province":"OR",
    "sg:tags":[
        "information",
        "bureau"
    ],
    "wof:name":"Willamette Valley Property Services",
    "wof:placetype":"venue"
},
  "geometry": {"coordinates":[-123.02406000000001,45.024873],"type":"Point"}
}