{
  "type": "Feature",
  "properties": {
    "iso:country":"US",
    "sg:address":"940 N Alder St",
    "sg:city":"Canby",
    "sg:classifiers":[
        {
            "category":"Structure",
            "subcategory":"Office Building",
            "type":"Public Place"
        }
    ],
    "sg:phone":"+1 503 266 1977",
    "sg:postcode":"97013",
    "sg:province":"OR",
    "sg:tags":[
        "park"
    ],
    "wof:name":"Jaww Properties",
    "wof:placetype":"venue"
},
  "geometry": {"coordinates":[-122.70878999999999,45.269841],"type":"Point"}
}