{
  "type": "Feature",
  "properties": {
    "iso:country":"US",
    "sg:address":"3740 NE Columbia Blvd",
    "sg:city":"Portland",
    "sg:classifiers":[
        {
            "category":"Manufacturing",
            "subcategory":"Tools & Machinery",
            "type":"Manufacturing & Wholesale Goods"
        }
    ],
    "sg:phone":"+1 503 288 6454",
    "sg:postcode":"97211",
    "sg:province":"OR",
    "sg:tags":[
        "paper",
        "industrial",
        "mfg"
    ],
    "wof:name":"Bag Parts International Corp",
    "wof:placetype":"venue"
},
  "geometry": {"coordinates":[-122.623068,45.572417],"type":"Point"}
}