{
  "type": "Feature",
  "properties": {
    "addr:full":"3855 SE 1st Pl Gresham OR 97080",
    "addr:housenumber":"3855",
    "addr:postcode":"97080",
    "addr:street":"Se 1St Pl",
    "iso:country":"US",
    "sg:address":"3855 SE 1st Pl",
    "sg:city":"Gresham",
    "sg:classifiers":[
        {
            "category":"Manufacturing",
            "subcategory":"Apparel",
            "type":"Manufacturing & Wholesale Goods"
        }
    ],
    "sg:phone":"+1 503 666 1578",
    "sg:postcode":"97080",
    "sg:province":"OR",
    "sg:tags":[
        "hats-wholesale",
        "hat",
        "manufacturer",
        "mfg"
    ],
    "wof:name":"John Aranda Products",
    "wof:placetype":"venue"
},
  "geometry": {"coordinates":[-122.39311600000001,45.49691],"type":"Point"}
}