{
  "type": "Feature",
  "properties": {
    "addr:full":"6956 SW Hampton Street Portland OR 97223",
    "addr:housenumber":"6956",
    "addr:postcode":"97223",
    "addr:street":"Sw Hampton Street",
    "iso:country":"US",
    "sg:address":"6956 SW Hampton Street",
    "sg:city":"Portland",
    "sg:classifiers":[
        {
            "category":"Health Services",
            "subcategory":"Chiropractor",
            "type":"Services"
        }
    ],
    "sg:phone":"+1 503 443 6100",
    "sg:postcode":"97223",
    "sg:province":"OR",
    "wof:name":"Hryciw Cheryl Ms Np",
    "wof:placetype":"venue"
},
  "geometry": {"coordinates":[-122.74884,45.427618],"type":"Point"}
}