{
  "type": "Feature",
  "properties": {
    "iso:country":"US",
    "sg:address":"4728 el Cedro Loop NE",
    "sg:city":"Salem",
    "sg:classifiers":[
        {
            "category":"Utilities",
            "subcategory":"Cable",
            "type":"Services"
        }
    ],
    "sg:phone":"+1 503 363 8557",
    "sg:postcode":"97305",
    "sg:province":"OR",
    "sg:tags":[
        "television"
    ],
    "wof:name":"One Way Cable",
    "wof:placetype":"venue"
},
  "geometry": {"coordinates":[-122.966733,44.95817],"type":"Point"}
}