{
  "type": "Feature",
  "properties": {
    "iso:country":"US",
    "sg:address":"4132 Adelaide Ave",
    "sg:city":"Klamath Falls",
    "sg:classifiers":[
        {
            "category":"Wholesale",
            "subcategory":"Computers",
            "type":"Manufacturing & Wholesale Goods"
        }
    ],
    "sg:phone":"+1 541 273 0677",
    "sg:postcode":"97603",
    "sg:province":"OR",
    "wof:name":"D J Design",
    "wof:placetype":"venue"
},
  "geometry": {"coordinates":[-121.739361,42.218364],"type":"Point"}
}