{
  "type": "Feature",
  "properties": {
    "addr:full":"30170 SW Ore Pac Ave Wilsonville OR 97070",
    "addr:housenumber":"30170",
    "addr:postcode":"97070",
    "addr:street":"Sw;Pac Ave",
    "iso:country":"US",
    "sg:address":"30170 SW Ore Pac Ave",
    "sg:city":"Wilsonville",
    "sg:classifiers":[
        {
            "category":"Wholesale",
            "subcategory":"Construction Materials",
            "type":"Manufacturing & Wholesale Goods"
        }
    ],
    "sg:phone":"+1 503 685 5499",
    "sg:postcode":"97070",
    "sg:province":"OR",
    "sg:tags":[
        "building"
    ],
    "sg:website":"www.orepac.com",
    "wof:name":"Ore Pac",
    "wof:placetype":"venue"
},
  "geometry": {"coordinates":[-122.779234,45.301589],"type":"Point"}
}