{
  "type": "Feature",
  "properties": {
    "iso:country":"US",
    "sg:address":"254 N 1st Ave",
    "sg:city":"Hillsboro",
    "sg:classifiers":[
        {
            "category":"Professional",
            "subcategory":"Lawyer & Legal Services",
            "type":"Services"
        }
    ],
    "sg:phone":"+1 503 681 2388",
    "sg:postcode":"97124",
    "sg:province":"OR",
    "sg:tags":[
        "attorney"
    ],
    "wof:name":"Washington County Defenders",
    "wof:placetype":"venue"
},
  "geometry": {"coordinates":[-122.989642,45.524501],"type":"Point"}
}