{
  "type": "Feature",
  "properties": {
    "iso:country":"US",
    "sg:address":"1045 Gateway Loop",
    "sg:city":"Springfield",
    "sg:classifiers":[
        {
            "category":"Wholesale",
            "subcategory":"Groceries",
            "type":"Manufacturing & Wholesale Goods"
        }
    ],
    "sg:phone":"+1 541 741 3102",
    "sg:postcode":"97477",
    "sg:province":"OR",
    "sg:tags":[
        "general"
    ],
    "wof:name":"Sysco",
    "wof:placetype":"venue"
},
  "geometry": {"coordinates":[-123.045244,44.078735],"type":"Point"}
}