{
  "type": "Feature",
  "properties": {
    "addr:full":"NW 10th Ave & Marshall St Portland OR 97209",
    "addr:postcode":"97209",
    "addr:street":"Nw 10Th Ave & Marshall St",
    "iso:country":"US",
    "sg:address":"NW 10th Ave & Marshall St",
    "sg:city":"Portland",
    "sg:classifiers":[
        {
            "category":"Park",
            "type":"Public Place"
        }
    ],
    "sg:postcode":"97209",
    "sg:province":"OR",
    "sg:website":"www.portlandonline.com/parks/fin...",
    "wof:name":"Tanner Springs Park",
    "wof:placetype":"venue"
},
  "geometry": {"coordinates":[-122.681415,45.53083],"type":"Point"}
}