{
  "type": "Feature",
  "properties": {
    "addr:full":"7800 SW Durham Rd Portland OR 97224",
    "addr:housenumber":"7800",
    "addr:postcode":"97224",
    "addr:street":"Sw Durham Rd",
    "iso:country":"US",
    "sg:address":"7800 SW Durham Rd",
    "sg:city":"Portland",
    "sg:classifiers":[
        {
            "category":"Professional",
            "type":"Services"
        }
    ],
    "sg:phone":"+1 503 620 8855",
    "sg:postcode":"97224",
    "sg:province":"OR",
    "sg:tags":[
        "caterer"
    ],
    "sg:website":"www.portlandcateringcompany.com",
    "wof:name":"Portland Catering Company",
    "wof:placetype":"venue"
},
  "geometry": {"coordinates":[-122.757238,45.404087],"type":"Point"}
}