{
  "type": "Feature",
  "properties": {
    "iso:country":"US",
    "sg:address":"8620 SW Gayle Lane",
    "sg:city":"Portland",
    "sg:classifiers":[
        {
            "category":"Professional",
            "subcategory":"Lawyer & Legal Services",
            "type":"Services"
        }
    ],
    "sg:phone":"+1 503 227 6266",
    "sg:postcode":"97225",
    "sg:province":"OR",
    "wof:name":"Platten Jack R",
    "wof:placetype":"venue"
},
  "geometry": {"coordinates":[-122.766137,45.504984],"type":"Point"}
}