{
  "type": "Feature",
  "properties": {
    "addr:full":"696 N Bayview Loop Waldport OR 97394",
    "addr:housenumber":"696",
    "addr:postcode":"97394",
    "addr:street":"N Bayview Loop",
    "iso:country":"US",
    "sg:address":"696 N Bayview Loop",
    "sg:city":"Waldport",
    "sg:classifiers":[
        {
            "category":"Building & Trades",
            "subcategory":"Construction",
            "type":"Services"
        }
    ],
    "sg:phone":"+1 541 563 3656",
    "sg:postcode":"97394",
    "sg:province":"OR",
    "sg:tags":[
        "excavation",
        "contractor"
    ],
    "wof:name":"Lee Trucking Excavating",
    "wof:placetype":"venue"
},
  "geometry": {"coordinates":[-124.016926,44.44735],"type":"Point"}
}