{
  "type": "Feature",
  "properties": {
    "iso:country":"US",
    "sg:address":"68609 Motanic Rd",
    "sg:city":"Pilot Rock",
    "sg:classifiers":[
        {
            "category":"Sports & Exercise",
            "subcategory":"Gym",
            "type":"Entertainment"
        }
    ],
    "sg:phone":"+1 541 966 4157",
    "sg:postcode":"97801",
    "sg:province":"OR",
    "sg:tags":[
        "club",
        "health",
        "studio",
        "gymnasium"
    ],
    "wof:name":"Express Fitness",
    "wof:placetype":"venue"
},
  "geometry": {"coordinates":[-118.70460799999999,45.534124],"type":"Point"}
}