{
  "type": "Feature",
  "properties": {
    "iso:country":"US",
    "sg:address":"63037 Terry Dr",
    "sg:city":"Bend",
    "sg:classifiers":[
        {
            "category":"Home & Garden",
            "subcategory":"Garden Supply",
            "type":"Retail Goods"
        }
    ],
    "sg:phone":"+1 541 382 1372",
    "sg:postcode":"97701",
    "sg:province":"OR",
    "sg:tags":[
        "center",
        "sculptor"
    ],
    "sg:website":"www.victorian-angel-garden.com",
    "wof:name":"Victorian Angel Garden",
    "wof:placetype":"venue"
},
  "geometry": {"coordinates":[-121.160577,44.089886],"type":"Point"}
}