{
  "type": "Feature",
  "properties": {
    "addr:full":"315 Holley Rd Sweet Home OR 97386",
    "addr:housenumber":"315",
    "addr:postcode":"97386",
    "addr:street":"Holley Rd",
    "iso:country":"US",
    "sg:address":"315 Holley Rd",
    "sg:city":"Sweet Home",
    "sg:classifiers":[
        {
            "category":"Health Services",
            "subcategory":"Nursing And Care Facility",
            "type":"Services"
        }
    ],
    "sg:phone":"+1 541 367 8999",
    "sg:postcode":"97386",
    "sg:province":"OR",
    "sg:tags":[
        "skilled"
    ],
    "wof:name":"Caring Hands Adult Care Home",
    "wof:placetype":"venue"
},
  "geometry": {"coordinates":[-122.739643,44.395875],"type":"Point"}
}