{
  "type": "Feature",
  "properties": {
    "addr:full":"6408 S 6th St Klamath Falls OR 97603",
    "addr:housenumber":"6408",
    "addr:postcode":"97603",
    "addr:street":"S 6Th St",
    "iso:country":"US",
    "sg:address":"6408 S 6th St",
    "sg:city":"Klamath Falls",
    "sg:classifiers":[
        {
            "category":"Professional",
            "subcategory":"Accounting & Tax Preparation",
            "type":"Services"
        }
    ],
    "sg:phone":"+1 541 884 2008",
    "sg:postcode":"97603",
    "sg:province":"OR",
    "sg:tags":[
        "return",
        "filing"
    ],
    "wof:name":"Walker Accounting & Tax",
    "wof:placetype":"venue"
},
  "geometry": {"coordinates":[-121.710435,42.204507],"type":"Point"}
}