{
  "type": "Feature",
  "properties": {
    "iso:country":"US",
    "sg:address":"21155 S Hwy 99W",
    "sg:city":"Amity",
    "sg:phone":"+1 503 835 7131",
    "sg:postcode":"97101",
    "sg:province":"OR",
    "sg:tags":[
        "farm",
        "field",
        "crop"
    ],
    "wof:name":"Roy Brubaker",
    "wof:placetype":"venue"
},
  "geometry": {"coordinates":[-123.20750700000001,45.107268],"type":"Point"}
}