{
  "type": "Feature",
  "properties": {
    "addr:full":"8954 SE Sunnyside Rd Clackamas OR 97015",
    "addr:housenumber":"8954",
    "addr:postcode":"97015",
    "addr:street":"Se Sunnyside Rd",
    "iso:country":"US",
    "sg:address":"8954 SE Sunnyside Rd",
    "sg:city":"Clackamas",
    "sg:classifiers":[
        {
            "category":"Shopping",
            "subcategory":"Computers & Home Electronics",
            "type":"Retail Goods"
        }
    ],
    "sg:phone":"+1 503 513 4708",
    "sg:postcode":"97015",
    "sg:province":"OR",
    "sg:tags":[
        "game",
        "video"
    ],
    "wof:name":"Game Stop Corp",
    "wof:placetype":"venue"
},
  "geometry": {"coordinates":[-122.572714,45.433193],"type":"Point"}
}