{
  "type": "Feature",
  "properties": {
    "iso:country":"US",
    "sg:address":"60760 Tekampe Rd",
    "sg:city":"Bend",
    "sg:classifiers":[
        {
            "category":"Professional",
            "subcategory":"Management & Consulting",
            "type":"Services"
        }
    ],
    "sg:phone":"+1 541 388 4338",
    "sg:postcode":"97702",
    "sg:province":"OR",
    "wof:name":"ABC Services",
    "wof:placetype":"venue"
},
  "geometry": {"coordinates":[-121.284038,44.004458],"type":"Point"}
}