{
  "type": "Feature",
  "properties": {
    "addr:full":"18865 SW Lisa Dr Beaverton OR 97006",
    "addr:housenumber":"18865",
    "addr:postcode":"97006",
    "addr:street":"Sw Lisa Dr",
    "iso:country":"US",
    "sg:address":"18865 SW Lisa Dr",
    "sg:city":"Beaverton",
    "sg:classifiers":[
        {
            "category":"Building & Trades",
            "subcategory":"Locksmith",
            "type":"Services"
        }
    ],
    "sg:phone":"+1 503 715 3892",
    "sg:postcode":"97006",
    "sg:province":"OR",
    "sg:tags":[
        "key"
    ],
    "wof:name":"A Plus Locksmith",
    "wof:placetype":"venue"
},
  "geometry": {"coordinates":[-122.871229,45.5172],"type":"Point"}
}