{
  "type": "Feature",
  "properties": {
    "iso:country":"US",
    "sg:address":"1223 SE Stark St",
    "sg:city":"Portland",
    "sg:phone":"+1 503 232 4628",
    "sg:postcode":"97214",
    "sg:province":"OR",
    "wof:name":"Scapegoat Tattoo",
    "wof:placetype":"venue"
},
  "geometry": {"coordinates":[-122.65340500000001,45.519346],"type":"Point"}
}