{
  "type": "Feature",
  "properties": {
    "iso:country":"US",
    "sg:address":"6735 SE 32nd Ave",
    "sg:city":"Portland",
    "sg:classifiers":[
        {
            "category":"Retail",
            "subcategory":"Auto Repair",
            "type":"Services"
        }
    ],
    "sg:phone":"+1 503 771 2663",
    "sg:postcode":"97202",
    "sg:province":"OR",
    "sg:tags":[
        "alternator",
        "automotive",
        "generators-automotive"
    ],
    "wof:name":"Start Merf Inc",
    "wof:placetype":"venue"
},
  "geometry": {"coordinates":[-122.630368,45.474431],"type":"Point"}
}