{
  "type": "Feature",
  "properties": {
    "iso:country":"US",
    "sg:address":"2 Main Ave",
    "sg:city":"Tillamook",
    "sg:classifiers":[
        {
            "category":"Home & Garden",
            "subcategory":"Building Materials",
            "type":"Retail Goods"
        }
    ],
    "sg:phone":"+1 503 842 4434",
    "sg:postcode":"97141",
    "sg:province":"OR",
    "wof:name":"Rosenberg Builders Supply Inc",
    "wof:placetype":"venue"
},
  "geometry": {"coordinates":[-123.844213,45.45912],"type":"Point"}
}