{
  "type": "Feature",
  "properties": {
    "addr:full":"1805 SE 58th Ave Portland OR 97215",
    "addr:housenumber":"1805",
    "addr:postcode":"97215",
    "addr:street":"Se 58Th Ave",
    "iso:country":"US",
    "sg:address":"1805 SE 58th Ave",
    "sg:city":"Portland",
    "sg:classifiers":[
        {
            "category":"Communications",
            "subcategory":"Film & Video Production",
            "type":"Services"
        }
    ],
    "sg:phone":"+1 503 232 3346",
    "sg:postcode":"97215",
    "sg:province":"OR",
    "sg:tags":[
        "motion"
    ],
    "wof:name":"Very Sirius Productions",
    "wof:placetype":"venue"
},
  "geometry": {"coordinates":[-122.6036,45.509983],"type":"Point"}
}