{
  "type": "Feature",
  "properties": {
    "addr:full":"627 SW Deschutes Ave Redmond OR 97756",
    "addr:housenumber":"627",
    "addr:postcode":"97756",
    "addr:street":"Sw Deschutes Ave",
    "iso:country":"US",
    "sg:address":"627 SW Deschutes Ave",
    "sg:city":"Redmond",
    "sg:classifiers":[
        {
            "category":"Professional",
            "subcategory":"Lawyer & Legal Services",
            "type":"Services"
        }
    ],
    "sg:phone":"+1 541 548 8188",
    "sg:postcode":"97756",
    "sg:province":"OR",
    "sg:tags":[
        "attorney"
    ],
    "wof:name":"Stanley E Clark PC",
    "wof:placetype":"venue"
},
  "geometry": {"coordinates":[-121.175079,44.273625],"type":"Point"}
}