{
  "type": "Feature",
  "properties": {
    "addr:full":"13600 Kruse Oaks Blvd Lake Oswego OR 97035",
    "addr:housenumber":"13600",
    "addr:postcode":"97035",
    "addr:street":"Kruse Oaks Blvd",
    "iso:country":"US",
    "sg:address":"13600 Kruse Oaks Blvd",
    "sg:city":"Lake Oswego",
    "sg:classifiers":[
        {
            "category":"Place Of Worship",
            "subcategory":"Church",
            "type":"Public Place"
        }
    ],
    "sg:phone":"+1 503 624 9322",
    "sg:postcode":"97035",
    "sg:province":"OR",
    "sg:website":"www.ldschurchtemples.com/portland",
    "wof:name":"Church of Jesus Christ of Latter-Day Saints - Portland Temple",
    "wof:placetype":"venue"
},
  "geometry": {"coordinates":[-122.74099699999999,45.425098],"type":"Point"}
}