{
  "type": "Feature",
  "properties": {
    "iso:country":"US",
    "sg:address":"107 N Meyers Butte Rd",
    "sg:city":"Powell Butte",
    "sg:classifiers":[
        {
            "category":"Building & Trades",
            "subcategory":"Construction",
            "type":"Services"
        }
    ],
    "sg:phone":"+1 541 447 5320",
    "sg:postcode":"97753",
    "sg:province":"OR",
    "sg:tags":[
        "residential"
    ],
    "wof:name":"Keith N Garber Construction",
    "wof:placetype":"venue"
},
  "geometry": {"coordinates":[-120.962485,44.300086],"type":"Point"}
}