{
  "type": "Feature",
  "properties": {
    "iso:country":"US",
    "sg:address":"116 S College St",
    "sg:city":"Newberg",
    "sg:classifiers":[
        {
            "category":"Communications",
            "subcategory":"Film & Video Production",
            "type":"Services"
        }
    ],
    "sg:phone":"+1 503 538 5089",
    "sg:postcode":"97132",
    "sg:province":"OR",
    "sg:tags":[
        "taping"
    ],
    "wof:name":"H & R Video Productions",
    "wof:placetype":"venue"
},
  "geometry": {"coordinates":[-122.97273800000001,45.300169],"type":"Point"}
}