{
  "type": "Feature",
  "properties": {
    "addr:full":"3420 SW 121st Ave Beaverton OR 97005",
    "addr:housenumber":"3420",
    "addr:postcode":"97005",
    "addr:street":"Sw 121St Ave",
    "iso:country":"US",
    "sg:address":"3420 SW 121st Ave",
    "sg:city":"Beaverton",
    "sg:classifiers":[
        {
            "category":"Farming",
            "subcategory":"Fish & Marine Products",
            "type":"Manufacturing & Wholesale Goods"
        }
    ],
    "sg:phone":"+1 503 644 5683",
    "sg:postcode":"97005",
    "sg:province":"OR",
    "sg:tags":[
        "management"
    ],
    "wof:name":"Kumduck",
    "wof:placetype":"venue"
},
  "geometry": {"coordinates":[-122.80095300000001,45.495813],"type":"Point"}
}