{
  "type": "Feature",
  "properties": {
    "iso:country":"US",
    "sg:address":"1931 SE Morrison St",
    "sg:city":"Portland",
    "sg:classifiers":[
        {
            "category":"Arts & Performance",
            "subcategory":"Theater",
            "type":"Entertainment"
        }
    ],
    "sg:phone":"+1 503 238 4525",
    "sg:postcode":"97214",
    "sg:province":"OR",
    "sg:tags":[
        "audio",
        "video",
        "multimedia"
    ],
    "wof:name":"Rex Post",
    "wof:placetype":"venue"
},
  "geometry": {"coordinates":[-122.645787,45.517252],"type":"Point"}
}