{
  "type": "Feature",
  "properties": {
    "addr:full":"3340 Aster St NW Salem OR 97304",
    "addr:housenumber":"3340",
    "addr:postcode":"97304",
    "addr:street":"Aster St Nw",
    "iso:country":"US",
    "sg:address":"3340 Aster St NW",
    "sg:city":"Salem",
    "sg:classifiers":[
        {
            "category":"Travel",
            "subcategory":"Hotels & Motels",
            "type":"Entertainment"
        }
    ],
    "sg:phone":"+1 503 393 6000",
    "sg:postcode":"97304",
    "sg:province":"OR",
    "wof:name":"Best Value",
    "wof:placetype":"venue"
},
  "geometry": {"coordinates":[-123.10136300000001,44.94048],"type":"Point"}
}