{
  "type": "Feature",
  "properties": {
    "addr:full":"5500 SW Meadows Rd Lake Oswego OR 97034",
    "addr:housenumber":"5500",
    "addr:postcode":"97034",
    "addr:street":"Sw Meadows Rd",
    "iso:country":"US",
    "sg:address":"5500 SW Meadows Rd",
    "sg:city":"Lake Oswego",
    "sg:classifiers":[
        {
            "category":"Building & Trades",
            "subcategory":"Locksmith",
            "type":"Services"
        }
    ],
    "sg:phone":"+1 503 207 0766",
    "sg:postcode":"97034",
    "sg:province":"OR",
    "sg:tags":[
        "key"
    ],
    "wof:name":"0 Hassle Locksmith Service",
    "wof:placetype":"venue"
},
  "geometry": {"coordinates":[-122.734106,45.417523],"type":"Point"}
}