{
  "type": "Feature",
  "properties": {
    "addr:full":"441 NW Hilltop Dr Portland OR 97210",
    "addr:housenumber":"441",
    "addr:postcode":"97210",
    "addr:street":"Nw Hilltop Dr",
    "iso:country":"US",
    "sg:address":"441 NW Hilltop Dr",
    "sg:city":"Portland",
    "sg:classifiers":[
        {
            "category":"Building & Trades",
            "subcategory":"Construction",
            "type":"Services"
        }
    ],
    "sg:phone":"+1 503 274 9040",
    "sg:postcode":"97210",
    "sg:province":"OR",
    "sg:tags":[
        "contractor"
    ],
    "wof:name":"Green Gables",
    "wof:placetype":"venue"
},
  "geometry": {"coordinates":[-122.723561,45.524197],"type":"Point"}
}