{
  "type": "Feature",
  "properties": {
    "iso:country":"US",
    "sg:address":"872 S Hwy 395",
    "sg:city":"Hermiston",
    "sg:classifiers":[
        {
            "category":"Food & Beverages",
            "subcategory":"Specialty",
            "type":"Retail Goods"
        }
    ],
    "sg:phone":"+1 541 564 6091",
    "sg:postcode":"97838",
    "sg:province":"OR",
    "sg:tags":[
        "gourmet",
        "shop"
    ],
    "wof:name":"Hickory Farms",
    "wof:placetype":"venue"
},
  "geometry": {"coordinates":[-119.286546,45.834388],"type":"Point"}
}