{
  "type": "Feature",
  "properties": {
    "iso:country":"US",
    "sg:address":"3829 SW Hall Blvd",
    "sg:city":"Beaverton",
    "sg:classifiers":[
        {
            "category":"Restaurant",
            "type":"Food & Drink"
        }
    ],
    "sg:phone":"+1 503 277 2229",
    "sg:postcode":"97005",
    "sg:province":"OR",
    "sg:tags":[
        "thai"
    ],
    "sg:website":"www.kaowthai.com",
    "wof:name":"Kaow Thai",
    "wof:placetype":"venue"
},
  "geometry": {"coordinates":[-122.80652600000001,45.492696],"type":"Point"}
}