{
  "type": "Feature",
  "properties": {
    "addr:full":"1476 SW Birdie Dr Corvallis OR 97333",
    "addr:housenumber":"1476",
    "addr:postcode":"97333",
    "addr:street":"Sw Birdie Dr",
    "iso:country":"US",
    "sg:address":"1476 SW Birdie Dr",
    "sg:city":"Corvallis",
    "sg:classifiers":[
        {
            "category":"Recreation",
            "type":"Entertainment"
        }
    ],
    "sg:phone":"+1 541 757 7135",
    "sg:postcode":"97333",
    "sg:province":"OR",
    "wof:name":"Kinderkinetics",
    "wof:placetype":"venue"
},
  "geometry": {"coordinates":[-123.290188,44.550968],"type":"Point"}
}