{
  "type": "Feature",
  "properties": {
    "iso:country":"US",
    "sg:address":"4606 Redwood Ave",
    "sg:city":"Grants Pass",
    "sg:classifiers":[
        {
            "category":"Building & Trades",
            "subcategory":"Construction",
            "type":"Services"
        }
    ],
    "sg:phone":"+1 541 479 7122",
    "sg:postcode":"97527",
    "sg:province":"OR",
    "sg:tags":[
        "glass",
        "screen",
        "repair"
    ],
    "wof:name":"Rogue Glass & Screen Inc",
    "wof:placetype":"venue"
},
  "geometry": {"coordinates":[-123.417031,42.417501],"type":"Point"}
}