{
  "type": "Feature",
  "properties": {
    "iso:country":"US",
    "sg:address":"19717 SW Murphy St",
    "sg:city":"Beaverton",
    "sg:classifiers":[
        {
            "category":"Professional",
            "subcategory":"Lawyer & Legal Services",
            "type":"Services"
        }
    ],
    "sg:phone":"+1 503 259 9395",
    "sg:postcode":"97007",
    "sg:province":"OR",
    "sg:tags":[
        "attorney"
    ],
    "wof:name":"Premire Bankruptcy Specialists",
    "wof:placetype":"venue"
},
  "geometry": {"coordinates":[-122.879661,45.475528],"type":"Point"}
}