{
  "type": "Feature",
  "properties": {
    "addr:full":"803 E Sheridan St Newberg OR 97132",
    "addr:housenumber":"803",
    "addr:postcode":"97132",
    "addr:street":"E Sheridan St",
    "iso:country":"US",
    "sg:address":"803 E Sheridan St",
    "sg:city":"Newberg",
    "sg:classifiers":[
        {
            "category":"Organizations",
            "subcategory":"Community Association",
            "type":"Services"
        }
    ],
    "sg:phone":"+1 503 538 2805",
    "sg:postcode":"97132",
    "sg:province":"OR",
    "wof:name":"Order of Amrnth Chhalem Crt 35",
    "wof:placetype":"venue"
},
  "geometry": {"coordinates":[-122.971582,45.302028],"type":"Point"}
}