{
  "type": "Feature",
  "properties": {
    "iso:country":"US",
    "sg:address":"6005 SE 17th Ave",
    "sg:city":"Portland",
    "sg:classifiers":[
        {
            "category":"Manufacturing",
            "subcategory":"Furniture",
            "type":"Manufacturing & Wholesale Goods"
        }
    ],
    "sg:phone":"+1 503 233 8021",
    "sg:postcode":"97202",
    "sg:province":"OR",
    "sg:tags":[
        "wood",
        "cabinet"
    ],
    "wof:name":"Eric C Butler",
    "wof:placetype":"venue"
},
  "geometry": {"coordinates":[-122.64823199999999,45.477407],"type":"Point"}
}