{
  "type": "Feature",
  "properties": {
    "iso:country":"US",
    "sg:address":"40336 Crawfordsville Dr",
    "sg:city":"Sweet Home",
    "sg:classifiers":[
        {
            "category":"Education",
            "subcategory":"School",
            "type":"Public Place"
        }
    ],
    "sg:phone":"+1 541 367 7162",
    "sg:postcode":"97386",
    "sg:province":"OR",
    "sg:tags":[
        "elementary"
    ],
    "wof:name":"Holley Elementary School",
    "wof:placetype":"venue"
},
  "geometry": {"coordinates":[-122.783653,44.35954],"type":"Point"}
}