{
  "type": "Feature",
  "properties": {
    "addr:full":"1020 SE 11th Ave Portland OR 97214",
    "addr:housenumber":"1020",
    "addr:postcode":"97214",
    "addr:street":"Se 11Th Ave",
    "iso:country":"US",
    "sg:address":"1020 SE 11th Ave",
    "sg:city":"Portland",
    "sg:classifiers":[
        {
            "category":"Manufacturing",
            "subcategory":"Furniture",
            "type":"Manufacturing & Wholesale Goods"
        }
    ],
    "sg:phone":"+1 503 238 1508",
    "sg:postcode":"97214",
    "sg:province":"OR",
    "sg:tags":[
        "case",
        "gr",
        "mfg",
        "commercial",
        "cabinet",
        "wood",
        "sign",
        "display"
    ],
    "wof:name":"Gxi Graphics",
    "wof:placetype":"venue"
},
  "geometry": {"coordinates":[-122.654594,45.515931],"type":"Point"}
}