{
  "type": "Feature",
  "properties": {
    "iso:country":"US",
    "sg:address":"4120 SE International Way",
    "sg:city":"Milwaukie",
    "sg:classifiers":[
        {
            "category":"Retail",
            "subcategory":"Portrait Studio",
            "type":"Services"
        }
    ],
    "sg:phone":"+1 503 786 8206",
    "sg:postcode":"97222",
    "sg:province":"OR",
    "sg:tags":[
        "photographer",
        "photo"
    ],
    "wof:name":"Krista Blythe Photography",
    "wof:placetype":"venue"
},
  "geometry": {"coordinates":[-122.618745,45.439095],"type":"Point"}
}