{
  "type": "Feature",
  "properties": {
    "addr:full":"7119 SW Macadam Ave Portland OR 97219",
    "addr:housenumber":"7119",
    "addr:postcode":"97219",
    "addr:street":"Sw Macadam Ave",
    "iso:country":"US",
    "sg:address":"7119 SW Macadam Ave",
    "sg:city":"Portland",
    "sg:classifiers":[
        {
            "category":"Professional",
            "type":"Services"
        },
        {
            "category":"Restaurant",
            "type":"Food & Drink"
        }
    ],
    "sg:phone":"+1 503 719 4626",
    "sg:postcode":"97219",
    "sg:province":"OR",
    "sg:tags":[
        "delivery",
        "pizza"
    ],
    "sg:website":"http://portland.citysearch.com/profile/external/603282142/portland_or/rovente_pizzeria.html?publisher=yellowpages&reference_id=1&placement=ypwebsitemip",
    "wof:name":"Rovente Pizzeria",
    "wof:placetype":"venue"
},
  "geometry": {"coordinates":[-122.67147300000001,45.472663],"type":"Point"}
}