{
  "type": "Feature",
  "properties": {
    "iso:country":"US",
    "sg:address":"700 N Rosa Parks Way",
    "sg:city":"Portland",
    "sg:classifiers":[
        {
            "category":"Arena",
            "subcategory":"Sports Club",
            "type":"Entertainment"
        }
    ],
    "sg:phone":"+1 503 314 7884",
    "sg:postcode":"97217",
    "sg:province":"OR",
    "sg:tags":[
        "soccer"
    ],
    "wof:name":"Peninsula Wrestling Club",
    "wof:placetype":"venue"
},
  "geometry": {"coordinates":[-122.67379800000001,45.569931],"type":"Point"}
}