{
  "type": "Feature",
  "properties": {
    "iso:country":"US",
    "sg:address":"7420 SW Bridgeport Rd",
    "sg:city":"Portland",
    "sg:classifiers":[
        {
            "category":"Professional",
            "subcategory":"Business Services",
            "type":"Services"
        }
    ],
    "sg:phone":"+1 503 691 8414",
    "sg:postcode":"97224",
    "sg:province":"OR",
    "sg:tags":[
        "legal"
    ],
    "wof:name":"Perry Mrrill Wngar Butte Attys",
    "wof:placetype":"venue"
},
  "geometry": {"coordinates":[-122.755386,45.393363],"type":"Point"}
}