{
  "type": "Feature",
  "properties": {
    "iso:country":"US",
    "sg:address":"530 Meadow Ln",
    "sg:city":"Creswell",
    "sg:classifiers":[
        {
            "category":"Wholesale",
            "subcategory":"Groceries",
            "type":"Manufacturing & Wholesale Goods"
        }
    ],
    "sg:phone":"+1 541 895 3417",
    "sg:postcode":"97426",
    "sg:province":"OR",
    "wof:name":"Larson Distributing",
    "wof:placetype":"venue"
},
  "geometry": {"coordinates":[-123.031597,43.923397],"type":"Point"}
}