{
  "type": "Feature",
  "properties": {
    "iso:country":"US",
    "sg:address":"2542 S Hwy 97",
    "sg:city":"Redmond",
    "sg:classifiers":[
        {
            "category":"Banks & Credit Unions",
            "subcategory":"Bank",
            "type":"Services"
        }
    ],
    "sg:phone":"+1 541 548 4000",
    "sg:postcode":"97756",
    "sg:province":"OR",
    "wof:name":"Bank Of The Cascades",
    "wof:placetype":"venue"
},
  "geometry": {"coordinates":[-121.18380999999999,44.25222],"type":"Point"}
}