{
  "type": "Feature",
  "properties": {
    "iso:country":"US",
    "sg:address":"8334 SW Nimbus Ave",
    "sg:city":"Beaverton",
    "sg:classifiers":[
        {
            "category":"Professional",
            "subcategory":"Computer Services",
            "type":"Services"
        }
    ],
    "sg:phone":"+1 503 350 0258",
    "sg:postcode":"97008",
    "sg:province":"OR",
    "sg:tags":[
        "repair"
    ],
    "wof:name":"Sms Systems Maintenance Services",
    "wof:placetype":"venue"
},
  "geometry": {"coordinates":[-122.78915600000001,45.459602],"type":"Point"}
}