{
  "type": "Feature",
  "properties": {
    "iso:country":"US",
    "sg:address":"1120 Sheraton Dr",
    "sg:city":"Eugene",
    "sg:classifiers":[
        {
            "category":"Building & Trades",
            "subcategory":"Construction",
            "type":"Services"
        }
    ],
    "sg:phone":"+1 541 485 6524",
    "sg:postcode":"97401",
    "sg:province":"OR",
    "sg:tags":[
        "residential",
        "general",
        "contractor"
    ],
    "wof:name":"Hauck & Sons Construction",
    "wof:placetype":"venue"
},
  "geometry": {"coordinates":[-123.051832,44.075575],"type":"Point"}
}