{
  "type": "Feature",
  "properties": {
    "iso:country":"US",
    "sg:address":"972 Candlelight Dr",
    "sg:city":"Eugene",
    "sg:classifiers":[
        {
            "category":"Freight",
            "type":"Transportation"
        }
    ],
    "sg:phone":"+1 541 688 6887",
    "sg:postcode":"97402",
    "sg:province":"OR",
    "sg:tags":[
        "special"
    ],
    "wof:name":"Smartlube",
    "wof:placetype":"venue"
},
  "geometry": {"coordinates":[-123.18111399999999,44.070405],"type":"Point"}
}