{
  "type": "Feature",
  "properties": {
    "iso:country":"US",
    "sg:address":"301 Canyon Dr",
    "sg:city":"Grants Pass",
    "sg:classifiers":[
        {
            "category":"Building & Trades",
            "subcategory":"Pest Control",
            "type":"Services"
        }
    ],
    "sg:phone":"+1 541 858 7957",
    "sg:postcode":"97527",
    "sg:province":"OR",
    "wof:name":"Tri Rivers Constrc",
    "wof:placetype":"venue"
},
  "geometry": {"coordinates":[-123.29403600000001,42.420849],"type":"Point"}
}