{
  "type": "Feature",
  "properties": {
    "iso:country":"US",
    "sg:address":"685 Marion St NE",
    "sg:city":"Salem",
    "sg:classifiers":[
        {
            "category":"Social Services",
            "type":"Services"
        }
    ],
    "sg:phone":"+1 503 364 2856",
    "sg:postcode":"97301",
    "sg:province":"OR",
    "sg:tags":[
        "senior",
        "citizen"
    ],
    "wof:name":"Senior Town House Meals-Wheels",
    "wof:placetype":"venue"
},
  "geometry": {"coordinates":[-123.033064,44.9436],"type":"Point"}
}