{
  "type": "Feature",
  "properties": {
    "addr:full":"4777 SW 11th St Ofc Gresham OR 97080",
    "addr:housenumber":"4777",
    "addr:postcode":"97080",
    "addr:street":"Sw 11Th St",
    "iso:country":"US",
    "sg:address":"4777 SW 11th St Ofc",
    "sg:city":"Gresham",
    "sg:classifiers":[
        {
            "category":"Real Estate",
            "subcategory":"Real Estate Operator",
            "type":"Services"
        }
    ],
    "sg:phone":"+1 503 661 5320",
    "sg:postcode":"97080",
    "sg:province":"OR",
    "sg:tags":[
        "apartment"
    ],
    "wof:name":"Silverwood Apts",
    "wof:placetype":"venue"
},
  "geometry": {"coordinates":[-122.480003,45.488602],"type":"Point"}
}