{
  "type": "Feature",
  "properties": {
    "iso:country":"US",
    "sg:address":"7319 N Leavitt Ave",
    "sg:city":"Portland",
    "sg:classifiers":[
        {
            "category":"Professional",
            "subcategory":"Lawyer & Legal Services",
            "type":"Services"
        },
        {
            "category":"Banks & Credit Unions",
            "subcategory":"Financial Services",
            "type":"Services"
        }
    ],
    "sg:phone":"+1 503 309 1134",
    "sg:postcode":"97203",
    "sg:province":"OR",
    "sg:tags":[
        "attorney",
        "law",
        "bankruptcy"
    ],
    "wof:name":"Oregon Affordable Bankruptcy",
    "wof:placetype":"venue"
},
  "geometry": {"coordinates":[-122.754166,45.589368],"type":"Point"}
}