{
  "type": "Feature",
  "properties": {
    "addr:full":"16579 SE Webster Rd Portland OR 97267",
    "addr:housenumber":"16579",
    "addr:postcode":"97267",
    "addr:street":"Se Webster Rd",
    "iso:country":"US",
    "sg:address":"16579 SE Webster Rd",
    "sg:city":"Portland",
    "sg:classifiers":[
        {
            "category":"Building & Trades",
            "subcategory":"Construction",
            "type":"Services"
        }
    ],
    "sg:phone":"+1 503 554 6692",
    "sg:postcode":"97267",
    "sg:province":"OR",
    "sg:tags":[
        "contractor"
    ],
    "sg:website":"portlandwindows.com/",
    "wof:name":"Windows America of Portland",
    "wof:placetype":"venue"
},
  "geometry": {"coordinates":[-122.58581100000001,45.402587],"type":"Point"}
}