{
  "type": "Feature",
  "properties": {
    "iso:country":"US",
    "sg:address":"1613 NW Kearney St",
    "sg:city":"Portland",
    "sg:classifiers":[
        {
            "category":"Taxi",
            "type":"Transportation"
        }
    ],
    "sg:phone":"+1 503 227 1212",
    "sg:postcode":"97209",
    "sg:province":"OR",
    "sg:website":"www.radiocab.net/",
    "wof:name":"Radio Cab",
    "wof:placetype":"venue"
},
  "geometry": {"coordinates":[-122.68800400000001,45.529202],"type":"Point"}
}