{
  "type": "Feature",
  "properties": {
    "iso:country":"US",
    "sg:address":"4910 Macleay Rd SE",
    "sg:city":"Salem",
    "sg:classifiers":[
        {
            "category":"Education",
            "subcategory":"School",
            "type":"Public Place"
        }
    ],
    "sg:phone":"+1 503 363 7764",
    "sg:postcode":"97301",
    "sg:province":"OR",
    "wof:name":"Willamette Educational Mnstrs",
    "wof:placetype":"venue"
},
  "geometry": {"coordinates":[-122.962219,44.916734],"type":"Point"}
}