{
  "type": "Feature",
  "properties": {
    "iso:country":"US",
    "sg:address":"9576 NW Marvin Ln",
    "sg:city":"Portland",
    "sg:classifiers":[
        {
            "category":"Real Estate",
            "subcategory":"Architect",
            "type":"Services"
        }
    ],
    "sg:phone":"+1 503 296 8527",
    "sg:postcode":"97229",
    "sg:province":"OR",
    "wof:name":"Leslie Rosenberg",
    "wof:placetype":"venue"
},
  "geometry": {"coordinates":[-122.775109,45.531853],"type":"Point"}
}