{
  "type": "Feature",
  "properties": {
    "addr:full":"29822 Ellensburg Ave Gold Beach OR 97444",
    "addr:postcode":"29822;97444",
    "addr:street":"Ellensburg Ave",
    "iso:country":"US",
    "sg:address":"29822 Ellensburg Ave",
    "sg:city":"Gold Beach",
    "sg:classifiers":[
        {
            "category":"Government",
            "subcategory":"Office",
            "type":"Public Place"
        }
    ],
    "sg:phone":"+1 541 247 0247",
    "sg:postcode":"97444",
    "sg:province":"OR",
    "sg:tags":[
        "state",
        "resource"
    ],
    "wof:name":"Human Resources Dept",
    "wof:placetype":"venue"
},
  "geometry": {"coordinates":[-124.419658,42.416922],"type":"Point"}
}