{
  "type": "Feature",
  "properties": {
    "iso:country":"US",
    "sg:address":"561 N 1st Ave",
    "sg:city":"Stayton",
    "sg:classifiers":[
        {
            "category":"Personal",
            "subcategory":"Barber",
            "type":"Services"
        }
    ],
    "sg:phone":"+1 503 769 2959",
    "sg:postcode":"97383",
    "sg:province":"OR",
    "sg:tags":[
        "shop",
        "beauty"
    ],
    "wof:name":"Clippers Unlimited",
    "wof:placetype":"venue"
},
  "geometry": {"coordinates":[-122.794414,44.798913],"type":"Point"}
}