{
  "type": "Feature",
  "properties": {
    "addr:full":"34839 Sykes Rd St Helens OR 97051",
    "addr:housenumber":"34839",
    "addr:postcode":"97051",
    "addr:street":"Sykes Rd",
    "iso:country":"US",
    "sg:address":"34839 Sykes Rd",
    "sg:city":"St Helens",
    "sg:classifiers":[
        {
            "category":"Retail",
            "subcategory":"Repair Shop",
            "type":"Services"
        },
        {
            "category":"Wholesale",
            "subcategory":"Photographic Equipment",
            "type":"Manufacturing & Wholesale Goods"
        }
    ],
    "sg:phone":"+1 503 397 1266",
    "sg:postcode":"97051",
    "sg:province":"OR",
    "sg:tags":[
        "home",
        "communication",
        "audio",
        "entertainment"
    ],
    "wof:name":"Columbia Audio Specialties",
    "wof:placetype":"venue"
},
  "geometry": {"coordinates":[-122.84645,45.855404],"type":"Point"}
}