{
  "type": "Feature",
  "properties": {
    "addr:full":"3050 SW Cedar Hills Blvd Beaverton OR 97005",
    "addr:housenumber":"3050",
    "addr:postcode":"97005",
    "addr:street":"Sw Cedar Hills Blvd",
    "iso:country":"US",
    "sg:address":"3050 SW Cedar Hills Blvd",
    "sg:city":"Beaverton",
    "sg:classifiers":[
        {
            "category":"Autos & Motor Vehicles",
            "subcategory":"Auto Supplies",
            "type":"Retail Goods"
        },
        {
            "category":"Wholesale",
            "subcategory":"Auto Parts",
            "type":"Manufacturing & Wholesale Goods"
        }
    ],
    "sg:phone":"+1 503 643 9666",
    "sg:postcode":"97005",
    "sg:province":"OR",
    "sg:tags":[
        "body",
        "automobile",
        "truck",
        "equipment",
        "accessory"
    ],
    "sg:website":"http://www.oreillyauto.com?utm_source=yellowpages&utm_medium=iyp&utm_campaign=2513",
    "wof:name":"Schuck's O'Reilly Auto Parts",
    "wof:placetype":"venue"
},
  "geometry": {"coordinates":[-122.807891,45.498054],"type":"Point"}
}