{
  "type": "Feature",
  "properties": {
    "iso:country":"US",
    "sg:address":"14757 S Holcomb Blvd",
    "sg:city":"Oregon City",
    "sg:classifiers":[
        {
            "category":"Professional",
            "subcategory":"Business Services",
            "type":"Services"
        }
    ],
    "sg:phone":"+1 503 656 9862",
    "sg:postcode":"97045",
    "sg:province":"OR",
    "wof:name":"Phillips Enterprises",
    "wof:placetype":"venue"
},
  "geometry": {"coordinates":[-122.563828,45.372063],"type":"Point"}
}