{
  "type": "Feature",
  "properties": {
    "iso:country":"US",
    "sg:address":"2002 Washington St",
    "sg:city":"Oregon City",
    "sg:classifiers":[
        {
            "category":"Home & Garden",
            "subcategory":"Building Materials",
            "type":"Retail Goods"
        }
    ],
    "sg:phone":"+1 503 723 3181",
    "sg:postcode":"97045",
    "sg:province":"OR",
    "sg:tags":[
        "center"
    ],
    "wof:name":"Home Depot",
    "wof:placetype":"venue"
},
  "geometry": {"coordinates":[-122.591435,45.368907],"type":"Point"}
}