{
  "type": "Feature",
  "properties": {
    "iso:country":"US",
    "sg:address":"7700 SW Beaverton Hillsdale Hwy",
    "sg:city":"Portland",
    "sg:classifiers":[
        {
            "category":"Building & Trades",
            "subcategory":"Locksmith",
            "type":"Services"
        }
    ],
    "sg:phone":"+1 971 228 5031",
    "sg:postcode":"97225",
    "sg:province":"OR",
    "sg:tags":[
        "key"
    ],
    "wof:name":"30 Minute Response Locksmith",
    "wof:placetype":"venue"
},
  "geometry": {"coordinates":[-122.756564,45.485993],"type":"Point"}
}