{
  "type": "Feature",
  "properties": {
    "iso:country":"US",
    "sg:address":"11945 SW Pacific Hwy",
    "sg:city":"Portland",
    "sg:classifiers":[
        {
            "category":"Restaurant",
            "type":"Food & Drink"
        },
        {
            "category":"Food & Beverages",
            "subcategory":"Bakery",
            "type":"Retail Goods"
        }
    ],
    "sg:phone":"+1 503 639 7770",
    "sg:postcode":"97223",
    "sg:province":"OR",
    "sg:tags":[
        "sandwich",
        "vietnamese"
    ],
    "wof:name":"Lucky Deli",
    "wof:placetype":"venue"
},
  "geometry": {"coordinates":[-122.766178,45.434842],"type":"Point"}
}