{
  "type": "Feature",
  "properties": {
    "iso:country":"US",
    "sg:address":"75 W 5th Ave",
    "sg:city":"Eugene",
    "sg:classifiers":[
        {
            "category":"Government",
            "subcategory":"Jail",
            "type":"Public Place"
        }
    ],
    "sg:phone":"+1 541 682 2297",
    "sg:postcode":"97401",
    "sg:province":"OR",
    "sg:tags":[
        "correctional",
        "institution"
    ],
    "wof:name":"Corrections Oregon Department",
    "wof:placetype":"venue"
},
  "geometry": {"coordinates":[-123.093342,44.054406],"type":"Point"}
}