{
  "type": "Feature",
  "properties": {
    "iso:country":"US",
    "sg:address":"1888 McCarter Ln",
    "sg:city":"Grants Pass",
    "sg:classifiers":[
        {
            "category":"Professional",
            "subcategory":"Business Services",
            "type":"Services"
        }
    ],
    "sg:phone":"+1 541 955 1823",
    "sg:postcode":"97527",
    "sg:province":"OR",
    "sg:tags":[
        "appraiser"
    ],
    "wof:name":"Works Appraisal Svc",
    "wof:placetype":"venue"
},
  "geometry": {"coordinates":[-123.34586299999999,42.417378],"type":"Point"}
}