{
  "type": "Feature",
  "properties": {
    "iso:country":"US",
    "sg:address":"4255 Boston Ln",
    "sg:city":"Eugene",
    "sg:classifiers":[
        {
            "category":"Professional",
            "type":"Services"
        }
    ],
    "sg:phone":"+1 541 689 6487",
    "sg:postcode":"97402",
    "sg:province":"OR",
    "wof:name":"Acme Birds",
    "wof:placetype":"venue"
},
  "geometry": {"coordinates":[-123.169494,44.081749],"type":"Point"}
}