{
  "type": "Feature",
  "properties": {
    "addr:full":"7410 SW Oleson Rd Portland OR 97223",
    "addr:housenumber":"7410",
    "addr:postcode":"97223",
    "addr:street":"Sw Oleson Rd",
    "iso:country":"US",
    "sg:address":"7410 SW Oleson Rd",
    "sg:city":"Portland",
    "sg:classifiers":[
        {
            "category":"Professional",
            "subcategory":"Management & Consulting",
            "type":"Services"
        }
    ],
    "sg:phone":"+1 503 245 5077",
    "sg:postcode":"97223",
    "sg:province":"OR",
    "sg:tags":[
        "information",
        "technology",
        "telecommunication"
    ],
    "wof:name":"Carrier Solutions Inc",
    "wof:placetype":"venue"
},
  "geometry": {"coordinates":[-122.75248499999999,45.466871],"type":"Point"}
}