{
  "type": "Feature",
  "properties": {
    "iso:country":"US",
    "sg:address":"7909 SW Cirrus Dr Bldg 27",
    "sg:city":"Beaverton",
    "sg:classifiers":[
        {
            "category":"Professional",
            "subcategory":"Testing Lab",
            "type":"Services"
        }
    ],
    "sg:phone":"+1 503 626 8000",
    "sg:postcode":"97008",
    "sg:province":"OR",
    "sg:tags":[
        "apparatus"
    ],
    "sg:website":"http://www.bioanalogics.com",
    "wof:name":"Bioanalogics",
    "wof:placetype":"venue"
},
  "geometry": {"coordinates":[-122.790504,45.462241],"type":"Point"}
}