{
  "type": "Feature",
  "properties": {
    "addr:full":"2856 S Santiam Hwy Lebanon OR 97355",
    "addr:housenumber":"2856",
    "addr:postcode":"97355",
    "addr:street":"S Santiam Hwy",
    "iso:country":"US",
    "sg:address":"2856 S Santiam Hwy",
    "sg:city":"Lebanon",
    "sg:classifiers":[
        {
            "category":"Banks & Credit Unions",
            "subcategory":"Bank",
            "type":"Services"
        }
    ],
    "sg:phone":"+1 541 258 2137",
    "sg:postcode":"97355",
    "sg:province":"OR",
    "sg:tags":[
        "state",
        "commercial"
    ],
    "wof:name":"US Bank",
    "wof:placetype":"venue"
},
  "geometry": {"coordinates":[-122.903668,44.520367],"type":"Point"}
}