{
  "type": "Feature",
  "properties": {
    "addr:full":"11725 SW Queen Elizabeth St Portland OR 97224",
    "addr:housenumber":"11725",
    "addr:postcode":"97224",
    "addr:street":"Sw;St",
    "iso:country":"US",
    "sg:address":"11725 SW Queen Elizabeth St",
    "sg:city":"Portland",
    "sg:classifiers":[
        {
            "category":"Real Estate",
            "subcategory":"Real Estate Agent",
            "type":"Services"
        }
    ],
    "sg:phone":"+1 503 684 1412",
    "sg:postcode":"97224",
    "sg:province":"OR",
    "wof:name":"Wright Properties Inc",
    "wof:placetype":"venue"
},
  "geometry": {"coordinates":[-122.79959100000001,45.406905],"type":"Point"}
}