{
  "type": "Feature",
  "properties": {
    "addr:full":"1207 Willis Creek Rd Winston OR 97496",
    "addr:housenumber":"1207",
    "addr:postcode":"97496",
    "addr:street":"Willis Creek Rd",
    "iso:country":"US",
    "sg:address":"1207 Willis Creek Rd",
    "sg:city":"Winston",
    "sg:classifiers":[
        {
            "category":"Professional",
            "type":"Services"
        }
    ],
    "sg:phone":"+1 541 784 2109",
    "sg:postcode":"97496",
    "sg:province":"OR",
    "wof:name":"Doyle Poole",
    "wof:placetype":"venue"
},
  "geometry": {"coordinates":[-123.42265399999999,43.087117],"type":"Point"}
}