{
  "type": "Feature",
  "properties": {
    "iso:country":"US",
    "sg:address":"7900 SE Pleasant Home Rd",
    "sg:city":"Gresham",
    "sg:classifiers":[
        {
            "category":"Shopping",
            "subcategory":"Used Merchandise",
            "type":"Retail Goods"
        }
    ],
    "sg:phone":"+1 503 663 7530",
    "sg:postcode":"97080",
    "sg:province":"OR",
    "wof:name":"Carlas Antique Treasures",
    "wof:placetype":"venue"
},
  "geometry": {"coordinates":[-122.336741,45.466025],"type":"Point"}
}