{
  "type": "Feature",
  "properties": {
    "iso:country":"US",
    "sg:address":"4305 NE Davis St",
    "sg:city":"Portland",
    "sg:classifiers":[
        {
            "category":"Manufacturing",
            "subcategory":"Lumber",
            "type":"Manufacturing & Wholesale Goods"
        }
    ],
    "sg:phone":"+1 503 235 9999",
    "sg:postcode":"97213",
    "sg:province":"OR",
    "sg:tags":[
        "fire"
    ],
    "wof:name":"Pj Kelly Consutling LLC",
    "wof:placetype":"venue"
},
  "geometry": {"coordinates":[-122.61731399999999,45.524832],"type":"Point"}
}