{
  "type": "Feature",
  "properties": {
    "iso:country":"US",
    "sg:address":"13600 SE Taylor Ct",
    "sg:city":"Portland",
    "sg:classifiers":[
        {
            "category":"Professional",
            "subcategory":"Business Services",
            "type":"Services"
        }
    ],
    "sg:phone":"+1 503 252 8015",
    "sg:postcode":"97233",
    "sg:province":"OR",
    "wof:name":"P D W Design",
    "wof:placetype":"venue"
},
  "geometry": {"coordinates":[-122.523377,45.515692],"type":"Point"}
}