{
  "type": "Feature",
  "properties": {
    "iso:country":"US",
    "sg:address":"1330 Madison St NE",
    "sg:city":"Salem",
    "sg:classifiers":[
        {
            "category":"Home & Garden",
            "subcategory":"Building Materials",
            "type":"Retail Goods"
        },
        {
            "category":"Building & Trades",
            "subcategory":"Construction",
            "type":"Services"
        }
    ],
    "sg:phone":"+1 503 378 1401",
    "sg:postcode":"97301",
    "sg:province":"OR",
    "sg:tags":[
        "foundation",
        "industrial",
        "chimneys-prefabricated",
        "contractor",
        "contractors-commercial",
        "masonry",
        "mason",
        "chimney"
    ],
    "sg:website":"http://www.fredinburgmasonry.com",
    "wof:name":"Fredinburg Masonry Inc",
    "wof:placetype":"venue"
},
  "geometry": {"coordinates":[-123.01693899999999,44.953208],"type":"Point"}
}