{
  "type": "Feature",
  "properties": {
    "iso:country":"US",
    "sg:address":"40833 Huntley Rd SE",
    "sg:city":"Stayton",
    "sg:classifiers":[
        {
            "category":"Building & Trades",
            "subcategory":"Construction",
            "type":"Services"
        }
    ],
    "sg:phone":"+1 503 769 2977",
    "sg:postcode":"97383",
    "sg:province":"OR",
    "sg:tags":[
        "house"
    ],
    "wof:name":"Kaeb Construction Gary",
    "wof:placetype":"venue"
},
  "geometry": {"coordinates":[-122.744667,44.764817],"type":"Point"}
}