{
  "type": "Feature",
  "properties": {
    "iso:country":"US",
    "sg:address":"140 SW Arthur St",
    "sg:city":"Portland",
    "sg:classifiers":[
        {
            "category":"Professional",
            "subcategory":"Lawyer & Legal Services",
            "type":"Services"
        }
    ],
    "sg:phone":"+1 503 228 7306",
    "sg:postcode":"97201",
    "sg:province":"OR",
    "wof:name":"Donald P Roach",
    "wof:placetype":"venue"
},
  "geometry": {"coordinates":[-122.67867699999999,45.503712],"type":"Point"}
}