{
  "type": "Feature",
  "properties": {
    "iso:country":"US",
    "sg:address":"1964 SW 20th Ct",
    "sg:city":"Gresham",
    "sg:classifiers":[
        {
            "category":"Building & Trades",
            "subcategory":"Construction",
            "type":"Services"
        }
    ],
    "sg:phone":"+1 503 665 3814",
    "sg:postcode":"97080",
    "sg:province":"OR",
    "sg:tags":[
        "hanging",
        "contractor"
    ],
    "wof:name":"Alpha Painting",
    "wof:placetype":"venue"
},
  "geometry": {"coordinates":[-122.452506,45.48184],"type":"Point"}
}