{
  "type": "Feature",
  "properties": {
    "iso:country":"US",
    "sg:address":"8237 NW Oxbow Dr",
    "sg:city":"Corvallis",
    "sg:classifiers":[
        {
            "category":"Social Services",
            "subcategory":"Job Training",
            "type":"Services"
        }
    ],
    "sg:phone":"+1 541 757 0585",
    "sg:postcode":"97330",
    "sg:province":"OR",
    "wof:name":"William J Ellison",
    "wof:placetype":"venue"
},
  "geometry": {"coordinates":[-123.346856,44.587418],"type":"Point"}
}