{
  "type": "Feature",
  "properties": {
    "iso:country":"US",
    "sg:address":"710 Howard St SE",
    "sg:city":"Salem",
    "sg:classifiers":[
        {
            "category":"Education",
            "subcategory":"School",
            "type":"Public Place"
        }
    ],
    "sg:phone":"+1 503 399 3408",
    "sg:postcode":"97302",
    "sg:province":"OR",
    "sg:tags":[
        "elementary",
        "secondary"
    ],
    "wof:name":"Howard Street Charter School",
    "wof:placetype":"venue"
},
  "geometry": {"coordinates":[-123.03795599999999,44.923425],"type":"Point"}
}