{
  "type": "Feature",
  "properties": {
    "iso:country":"US",
    "sg:address":"598 N 4th Ct",
    "sg:city":"Coos Bay",
    "sg:classifiers":[
        {
            "category":"Building & Trades",
            "subcategory":"Landscaping Services",
            "type":"Services"
        }
    ],
    "sg:phone":"+1 541 269 9039",
    "sg:postcode":"97420",
    "sg:province":"OR",
    "sg:tags":[
        "designer",
        "landscape"
    ],
    "wof:name":"Vaughan Landscape Design",
    "wof:placetype":"venue"
},
  "geometry": {"coordinates":[-124.21617,43.371798],"type":"Point"}
}