{
  "type": "Feature",
  "properties": {
    "iso:country":"US",
    "sg:address":"3003 E 2nd St",
    "sg:city":"The Dalles",
    "sg:classifiers":[
        {
            "category":"Shopping",
            "type":"Retail Goods"
        }
    ],
    "sg:phone":"+1 541 296 5386",
    "sg:postcode":"97058",
    "sg:province":"OR",
    "sg:tags":[
        "ice"
    ],
    "wof:name":"Gem Ice",
    "wof:placetype":"venue"
},
  "geometry": {"coordinates":[-121.13690200000001,45.601304],"type":"Point"}
}