{
  "type": "Feature",
  "properties": {
    "iso:country":"US",
    "sg:address":"4628 SW Palatine St",
    "sg:city":"Portland",
    "sg:classifiers":[
        {
            "category":"Personal",
            "subcategory":"Beauty Salon",
            "type":"Services"
        }
    ],
    "sg:phone":"+1 503 312 6398",
    "sg:postcode":"97219",
    "sg:province":"OR",
    "sg:tags":[
        "hair"
    ],
    "wof:name":"Ron's Hair Design",
    "wof:placetype":"venue"
},
  "geometry": {"coordinates":[-122.724797,45.443839],"type":"Point"}
}