{
  "type": "Feature",
  "properties": {
    "addr:full":"31847 State Hwy 213 Molalla OR 97038",
    "addr:housenumber":"31847",
    "addr:postcode":"97038",
    "addr:street":"State Hwy 213",
    "iso:country":"US",
    "sg:address":"31847 State Hwy 213",
    "sg:city":"Molalla",
    "sg:classifiers":[
        {
            "category":"Building & Trades",
            "subcategory":"Electrical",
            "type":"Services"
        }
    ],
    "sg:phone":"+1 503 829 3978",
    "sg:postcode":"97038",
    "sg:province":"OR",
    "sg:tags":[
        "electric",
        "contractor"
    ],
    "wof:name":"Portland General Electric",
    "wof:placetype":"venue"
},
  "geometry": {"coordinates":[-122.60902900000001,45.145722],"type":"Point"}
}