{
  "type": "Feature",
  "properties": {
    "iso:country":"US",
    "sg:address":"515 SW 12th St",
    "sg:city":"Pendleton",
    "sg:classifiers":[
        {
            "category":"Social Services",
            "subcategory":"Child Care",
            "type":"Services"
        }
    ],
    "sg:phone":"+1 541 278 4718",
    "sg:postcode":"97801",
    "sg:province":"OR",
    "sg:tags":[
        "day"
    ],
    "wof:name":"LIl Angels Child Care & Pre-S",
    "wof:placetype":"venue"
},
  "geometry": {"coordinates":[-118.79672100000001,45.665817],"type":"Point"}
}