{
  "type": "Feature",
  "properties": {
    "addr:full":"1909 SE Elliott Ave Portland OR 97214",
    "addr:housenumber":"1909",
    "addr:postcode":"97214",
    "addr:street":"Se Elliott",
    "iso:country":"US",
    "sg:address":"1909 SE Elliott Ave",
    "sg:city":"Portland",
    "sg:classifiers":[
        {
            "category":"Professional",
            "type":"Services"
        }
    ],
    "sg:phone":"+1 503 292 5749",
    "sg:postcode":"97214",
    "sg:province":"OR",
    "sg:tags":[
        "writer",
        "publication",
        "editorial"
    ],
    "wof:name":"Jeff Landers Creative Solutions",
    "wof:placetype":"venue"
},
  "geometry": {"coordinates":[-122.648279,45.509446],"type":"Point"}
}