{
  "type": "Feature",
  "properties": {
    "iso:country":"US",
    "sg:address":"25184 Webster Ave",
    "sg:city":"Monroe",
    "sg:classifiers":[
        {
            "category":"Organizations",
            "subcategory":"Religious Organization",
            "type":"Services"
        }
    ],
    "sg:phone":"+1 541 424 5074",
    "sg:postcode":"97456",
    "sg:province":"OR",
    "sg:tags":[
        "place",
        "worship",
        "church"
    ],
    "wof:name":"Alpine Assembly Of God Inc",
    "wof:placetype":"venue"
},
  "geometry": {"coordinates":[-123.36079599999999,44.329999],"type":"Point"}
}