{
  "type": "Feature",
  "properties": {
    "addr:full":"17 SW Frazer Ave Pendleton OR 97801",
    "addr:housenumber":"17",
    "addr:postcode":"97801",
    "addr:street":"Sw Frazer Ave",
    "iso:country":"US",
    "sg:address":"17 SW Frazer Ave",
    "sg:city":"Pendleton",
    "sg:classifiers":[
        {
            "category":"Professional",
            "subcategory":"Lawyer & Legal Services",
            "type":"Services"
        }
    ],
    "sg:phone":"+1 541 276 8128",
    "sg:postcode":"97801",
    "sg:province":"OR",
    "sg:tags":[
        "attorney"
    ],
    "wof:name":"Ransom Gilbertson & Martin",
    "wof:placetype":"venue"
},
  "geometry": {"coordinates":[-118.785961,45.669982],"type":"Point"}
}