{
  "type": "Feature",
  "properties": {
    "iso:country":"US",
    "sg:address":"4321 SW Corbett Ave Ste B",
    "sg:city":"Portland",
    "sg:classifiers":[
        {
            "category":"Personal",
            "subcategory":"Beauty Salon",
            "type":"Services"
        },
        {
            "category":"Personal",
            "subcategory":"Barber",
            "type":"Services"
        }
    ],
    "sg:phone":"+1 503 294 1948",
    "sg:postcode":"97239",
    "sg:province":"OR",
    "wof:name":"Over The Landing",
    "wof:placetype":"venue"
},
  "geometry": {"coordinates":[-122.676204,45.492203],"type":"Point"}
}