{
  "type": "Feature",
  "properties": {
    "addr:full":"70 Water St Ashland OR 97520",
    "addr:housenumber":"70",
    "addr:postcode":"97520",
    "addr:street":"Water St",
    "iso:country":"US",
    "sg:address":"70 Water St",
    "sg:city":"Ashland",
    "sg:classifiers":[
        {
            "category":"Travel",
            "subcategory":"Hotels & Motels",
            "type":"Entertainment"
        }
    ],
    "sg:phone":"+1 541 482 3315",
    "sg:postcode":"97520",
    "sg:province":"OR",
    "sg:tags":[
        "operation"
    ],
    "sg:website":"www.ashlandcreekinn.com",
    "wof:name":"Ashland Creek Inn",
    "wof:placetype":"venue"
},
  "geometry": {"coordinates":[-122.71383299999999,42.200894],"type":"Point"}
}