{
  "type": "Feature",
  "properties": {
    "addr:full":"1220 NW 21st Ave Portland OR 97209",
    "addr:housenumber":"1220",
    "addr:postcode":"97209",
    "addr:street":"Nw 21St Ave",
    "iso:country":"US",
    "sg:address":"1220 NW 21st Ave",
    "sg:city":"Portland",
    "sg:classifiers":[
        {
            "category":"Personal",
            "subcategory":"Beauty Salon",
            "type":"Services"
        }
    ],
    "sg:phone":"+1 503 243 2430",
    "sg:postcode":"97209",
    "sg:province":"OR",
    "sg:tags":[
        "hair",
        "shop",
        "stylist"
    ],
    "sg:website":"www.facebook.com/pages/Portland-...",
    "wof:name":"Hair Mechanix",
    "wof:placetype":"venue"
},
  "geometry": {"coordinates":[-122.69449899999999,45.531529],"type":"Point"}
}