{
  "type": "Feature",
  "properties": {
    "iso:country":"US",
    "sg:address":"34386 Slavens Rd",
    "sg:city":"Warren",
    "sg:classifiers":[
        {
            "category":"Retail",
            "subcategory":"Auto Repair",
            "type":"Services"
        }
    ],
    "sg:phone":"+1 503 397 3344",
    "sg:postcode":"97053",
    "sg:province":"OR",
    "sg:tags":[
        "automotive",
        "tune"
    ],
    "sg:website":"http://www.napaautocare.com/",
    "wof:name":"Warren Automotive",
    "wof:placetype":"venue"
},
  "geometry": {"coordinates":[-122.858437,45.806209],"type":"Point"}
}