{
  "type": "Feature",
  "properties": {
    "iso:country":"US",
    "sg:address":"1301 12th St",
    "sg:city":"Hood River",
    "sg:classifiers":[
        {
            "category":"Personal",
            "subcategory":"Beauty Salon",
            "type":"Services"
        }
    ],
    "sg:phone":"+1 541 386 1810",
    "sg:postcode":"97031",
    "sg:province":"OR",
    "wof:name":"Uptown Salon",
    "wof:placetype":"venue"
},
  "geometry": {"coordinates":[-121.523629,45.700928],"type":"Point"}
}