{
  "type": "Feature",
  "properties": {
    "iso:country":"US",
    "sg:address":"19355 E Highway 26",
    "sg:city":"Mitchell",
    "sg:classifiers":[
        {
            "category":"Restaurant",
            "type":"Food & Drink"
        }
    ],
    "sg:phone":"+1 541 462 3000",
    "sg:postcode":"97750",
    "sg:province":"OR",
    "wof:name":"Aseven Bar Ranch",
    "wof:placetype":"venue"
},
  "geometry": {"coordinates":[-120.12200799999999,44.564378],"type":"Point"}
}