{
  "type": "Feature",
  "properties": {
    "iso:country":"US",
    "sg:address":"19555 Chandler Ln",
    "sg:city":"Baker City",
    "sg:classifiers":[
        {
            "category":"Farming",
            "subcategory":"Farm & Veterinary Services",
            "type":"Manufacturing & Wholesale Goods"
        }
    ],
    "sg:phone":"+1 541 523 2066",
    "sg:postcode":"97814",
    "sg:province":"OR",
    "sg:tags":[
        "livestock"
    ],
    "wof:name":"Perkins Ranch",
    "wof:placetype":"venue"
},
  "geometry": {"coordinates":[-117.830367,44.861738],"type":"Point"}
}