{
  "type": "Feature",
  "properties": {
    "addr:full":"407 Brooks St Silverton OR 97381",
    "addr:housenumber":"407",
    "addr:postcode":"97381",
    "addr:street":"Brooks St",
    "iso:country":"US",
    "sg:address":"407 Brooks St",
    "sg:city":"Silverton",
    "sg:classifiers":[
        {
            "category":"Professional",
            "subcategory":"Management & Consulting",
            "type":"Services"
        }
    ],
    "sg:phone":"+1 503 873 5201",
    "sg:postcode":"97381",
    "sg:province":"OR",
    "sg:tags":[
        "sales",
        "veterinary",
        "direct",
        "retail"
    ],
    "wof:name":"Pollys Natural Products",
    "wof:placetype":"venue"
},
  "geometry": {"coordinates":[-122.792323,45.007967],"type":"Point"}
}