{
  "type": "Feature",
  "properties": {
    "addr:full":"804 Main St Oregon City OR 97045",
    "addr:housenumber":"804",
    "addr:postcode":"97045",
    "addr:street":"Main St",
    "iso:country":"US",
    "sg:address":"804 Main St",
    "sg:city":"Oregon City",
    "sg:classifiers":[
        {
            "category":"Home & Garden",
            "subcategory":"Furniture",
            "type":"Retail Goods"
        }
    ],
    "sg:phone":"+1 503 656 2621",
    "sg:postcode":"97045",
    "sg:province":"OR",
    "sg:tags":[
        "household",
        "appliance"
    ],
    "wof:name":"Tom Busch Home Furnishings",
    "wof:placetype":"venue"
},
  "geometry": {"coordinates":[-122.606853,45.358521],"type":"Point"}
}