{
  "type": "Feature",
  "properties": {
    "iso:country":"US",
    "sg:address":"6291 NE Breyman Orchards Rd",
    "sg:city":"Dayton",
    "sg:classifiers":[
        {
            "category":"Professional",
            "subcategory":"Accounting & Tax Preparation",
            "type":"Services"
        }
    ],
    "sg:phone":"+1 503 864 2131",
    "sg:postcode":"97114",
    "sg:province":"OR",
    "sg:tags":[
        "public",
        "accountants-certified"
    ],
    "wof:name":"Jim Crawford Cpa Pa",
    "wof:placetype":"venue"
},
  "geometry": {"coordinates":[-123.062681,45.260755],"type":"Point"}
}