{
  "type": "Feature",
  "properties": {
    "addr:full":"3730 N Suttle Rd Portland OR 97217",
    "addr:housenumber":"3730",
    "addr:postcode":"97217",
    "addr:street":"N Suttle Rd",
    "iso:country":"US",
    "sg:address":"3730 N Suttle Rd",
    "sg:city":"Portland",
    "sg:classifiers":[
        {
            "category":"Wholesale",
            "subcategory":"Machinery & Supplies",
            "type":"Manufacturing & Wholesale Goods"
        }
    ],
    "sg:phone":"+1 503 234 4044",
    "sg:postcode":"97217",
    "sg:province":"OR",
    "sg:tags":[
        "pressure",
        "washing",
        "equipment"
    ],
    "wof:name":"Apw Distributing",
    "wof:placetype":"venue"
},
  "geometry": {"coordinates":[-122.714388,45.615594],"type":"Point"}
}