{
  "type": "Feature",
  "properties": {
    "iso:country":"US",
    "sg:address":"588 16th St",
    "sg:city":"Astoria",
    "sg:classifiers":[
        {
            "category":"Education",
            "subcategory":"College",
            "type":"Public Place"
        }
    ],
    "sg:phone":"+1 503 338 2370",
    "sg:postcode":"97103",
    "sg:province":"OR",
    "sg:tags":[
        "academic",
        "school"
    ],
    "wof:name":"Upward Bound",
    "wof:placetype":"venue"
},
  "geometry": {"coordinates":[-123.825548,46.187247],"type":"Point"}
}