{
  "type": "Feature",
  "properties": {
    "iso:country":"US",
    "sg:address":"2295 Gable Rd",
    "sg:city":"St Helens",
    "sg:classifiers":[
        {
            "category":"Utilities",
            "subcategory":"Mobile Phone",
            "type":"Services"
        }
    ],
    "sg:phone":"+1 503 366 1088",
    "sg:postcode":"97051",
    "sg:province":"OR",
    "sg:tags":[
        "telephone",
        "cellular"
    ],
    "wof:name":"D C Wireless",
    "wof:placetype":"venue"
},
  "geometry": {"coordinates":[-122.830029,45.847849],"type":"Point"}
}