{
  "type": "Feature",
  "properties": {
    "addr:full":"15050 Keno Worden Rd Klamath Falls OR 97603",
    "addr:housenumber":"15050",
    "addr:postcode":"97603",
    "addr:street":"Keno Worden Rd",
    "iso:country":"US",
    "sg:address":"15050 Keno Worden Rd",
    "sg:city":"Klamath Falls",
    "sg:classifiers":[
        {
            "category":"Retail",
            "subcategory":"Repair Shop",
            "type":"Services"
        }
    ],
    "sg:phone":"+1 541 883 3799",
    "sg:postcode":"97603",
    "sg:province":"OR",
    "wof:name":"All Tools Indus Sharpening",
    "wof:placetype":"venue"
},
  "geometry": {"coordinates":[-121.901173,42.088545],"type":"Point"}
}