{
  "type": "Feature",
  "properties": {
    "iso:country":"US",
    "sg:address":"5355 N Fork Siuslaw Rd",
    "sg:city":"Florence",
    "sg:classifiers":[
        {
            "category":"Shopping",
            "subcategory":"Gifts & Souvenirs",
            "type":"Retail Goods"
        }
    ],
    "sg:phone":"+1 541 997 3531",
    "sg:postcode":"97439",
    "sg:province":"OR",
    "wof:name":"Freddies Ceramics Gifts",
    "wof:placetype":"venue"
},
  "geometry": {"coordinates":[-124.083438,43.977387],"type":"Point"}
}