{
  "type": "Feature",
  "properties": {
    "iso:country":"US",
    "sg:address":"2742 SE 36th Ave",
    "sg:city":"Portland",
    "sg:classifiers":[
        {
            "category":"Education",
            "subcategory":"Special Training",
            "type":"Public Place"
        }
    ],
    "sg:phone":"+1 503 232 2046",
    "sg:postcode":"97202",
    "sg:province":"OR",
    "sg:tags":[
        "program"
    ],
    "wof:name":"Resource Performance",
    "wof:placetype":"venue"
},
  "geometry": {"coordinates":[-122.62615700000001,45.502239],"type":"Point"}
}