{
  "type": "Feature",
  "properties": {
    "iso:country":"US",
    "sg:address":"63455 N Hwy 97",
    "sg:city":"Bend",
    "sg:classifiers":[
        {
            "category":"Shopping",
            "subcategory":"Shoes",
            "type":"Retail Goods"
        }
    ],
    "sg:phone":"+1 541 385 8479",
    "sg:postcode":"97701",
    "sg:province":"OR",
    "wof:name":"Foot Locker",
    "wof:placetype":"venue"
},
  "geometry": {"coordinates":[-121.296262,44.107551],"type":"Point"}
}