{
  "type": "Feature",
  "properties": {
    "addr:full":"3216 Northeast 78th Ave Portland OR 97213",
    "addr:housenumber":"3216",
    "addr:postcode":"97213",
    "addr:street":"Northeast 78Th Ave",
    "iso:country":"US",
    "sg:address":"3216 Northeast 78th Ave",
    "sg:city":"Portland",
    "sg:classifiers":[
        {
            "category":"Building & Trades",
            "subcategory":"Construction",
            "type":"Services"
        }
    ],
    "sg:phone":"+1 503 252 9672",
    "sg:postcode":"97213",
    "sg:province":"OR",
    "sg:tags":[
        "air",
        "heating",
        "conditioning/hvac"
    ],
    "wof:name":"R H Heating & Cooling",
    "wof:placetype":"venue"
},
  "geometry": {"coordinates":[-122.582545,45.545669],"type":"Point"}
}