{
  "type": "Feature",
  "properties": {
    "addr:full":"4336 S 6th St Klamath Falls OR 97603",
    "addr:housenumber":"4336",
    "addr:postcode":"97603",
    "addr:street":"S 6Th St",
    "iso:country":"US",
    "sg:address":"4336 S 6th St",
    "sg:city":"Klamath Falls",
    "sg:classifiers":[
        {
            "category":"Personal",
            "subcategory":"Beauty Salon",
            "type":"Services"
        }
    ],
    "sg:phone":"+1 541 885 5561",
    "sg:postcode":"97603",
    "sg:province":"OR",
    "sg:tags":[
        "shop"
    ],
    "wof:name":"Backdoor Beauty Salon",
    "wof:placetype":"venue"
},
  "geometry": {"coordinates":[-121.73547499999999,42.206417],"type":"Point"}
}