{
  "type": "Feature",
  "properties": {
    "addr:full":"20 E Ash St Lebanon OR 97355",
    "addr:housenumber":"20",
    "addr:postcode":"97355",
    "addr:street":"E Ash St",
    "iso:country":"US",
    "sg:address":"20 E Ash St",
    "sg:city":"Lebanon",
    "sg:classifiers":[
        {
            "category":"Organizations",
            "subcategory":"Community Association",
            "type":"Services"
        }
    ],
    "sg:phone":"+1 541 258 5253",
    "sg:postcode":"97355",
    "sg:province":"OR",
    "wof:name":"Independent Order Odd Fellows",
    "wof:placetype":"venue"
},
  "geometry": {"coordinates":[-122.905765,44.539962],"type":"Point"}
}