{
  "type": "Feature",
  "properties": {
    "iso:country":"US",
    "sg:address":"5724 NW Front Ave",
    "sg:city":"Portland",
    "sg:classifiers":[
        {
            "category":"Wholesale",
            "subcategory":"Chemicals & Plastics",
            "type":"Manufacturing & Wholesale Goods"
        }
    ],
    "sg:phone":"+1 503 242 0200",
    "sg:postcode":"97210",
    "sg:province":"OR",
    "wof:name":"G W Technical",
    "wof:placetype":"venue"
},
  "geometry": {"coordinates":[-122.737031,45.562334],"type":"Point"}
}