{
  "type": "Feature",
  "properties": {
    "addr:full":"11933 SE Sunny Way Clackamas OR 97086",
    "addr:postcode":"11933;97086",
    "addr:street":"Se Sunny Way",
    "iso:country":"US",
    "sg:address":"11933 SE Sunny Way",
    "sg:city":"Clackamas",
    "sg:classifiers":[
        {
            "category":"Building & Trades",
            "subcategory":"Construction",
            "type":"Services"
        }
    ],
    "sg:phone":"+1 503 698 3444",
    "sg:postcode":"97086",
    "sg:province":"OR",
    "sg:tags":[
        "residential",
        "commercial",
        "remodeling",
        "gen",
        "contractor"
    ],
    "wof:name":"Skandia Remodeling",
    "wof:placetype":"venue"
},
  "geometry": {"coordinates":[-122.540227,45.436835],"type":"Point"}
}