{
  "type": "Feature",
  "properties": {
    "addr:full":"1657 Delrose Ave Springfield OR 97477",
    "addr:housenumber":"1657",
    "addr:postcode":"97477",
    "addr:street":"Delrose Ave",
    "iso:country":"US",
    "sg:address":"1657 Delrose Ave",
    "sg:city":"Springfield",
    "sg:classifiers":[
        {
            "category":"Professional",
            "subcategory":"Art Services",
            "type":"Services"
        }
    ],
    "sg:phone":"+1 541 726 4753",
    "sg:postcode":"97477",
    "sg:province":"OR",
    "sg:tags":[
        "photography",
        "commercial"
    ],
    "wof:name":"David Loveall Photography",
    "wof:placetype":"venue"
},
  "geometry": {"coordinates":[-123.000439,44.073208],"type":"Point"}
}