{
  "type": "Feature",
  "properties": {
    "iso:country":"US",
    "sg:address":"1201 SW 14th Ct",
    "sg:city":"Gresham",
    "sg:classifiers":[
        {
            "category":"Real Estate",
            "subcategory":"Real Estate Agent",
            "type":"Services"
        }
    ],
    "sg:phone":"+1 503 661 0707",
    "sg:postcode":"97080",
    "sg:province":"OR",
    "wof:name":"Francis Rentals",
    "wof:placetype":"venue"
},
  "geometry": {"coordinates":[-122.44451599999999,45.48665],"type":"Point"}
}