{
  "type": "Feature",
  "properties": {
    "iso:country":"US",
    "sg:address":"1780 NW Poppy Hills Dr",
    "sg:city":"Mcminnville",
    "sg:classifiers":[
        {
            "category":"Building & Trades",
            "subcategory":"Construction",
            "type":"Services"
        }
    ],
    "sg:phone":"+1 503 472 8894",
    "sg:postcode":"97128",
    "sg:province":"OR",
    "sg:tags":[
        "residential"
    ],
    "wof:name":"Ammon Construction Compan",
    "wof:placetype":"venue"
},
  "geometry": {"coordinates":[-123.22113,45.214319],"type":"Point"}
}