{
  "type": "Feature",
  "properties": {
    "iso:country":"US",
    "sg:address":"1092 S Redwood St",
    "sg:city":"Canby",
    "sg:classifiers":[
        {
            "category":"Professional",
            "subcategory":"Engineering",
            "type":"Services"
        }
    ],
    "sg:phone":"+1 503 263 3280",
    "sg:postcode":"97013",
    "sg:province":"OR",
    "wof:name":"Anderson Engineering",
    "wof:placetype":"venue"
},
  "geometry": {"coordinates":[-122.677044,45.25515],"type":"Point"}
}