{
  "type": "Feature",
  "properties": {
    "iso:country":"US",
    "sg:address":"2021 12th St",
    "sg:city":"Florence",
    "sg:classifiers":[
        {
            "category":"Real Estate",
            "subcategory":"Real Estate Operator",
            "type":"Services"
        },
        {
            "category":"Building & Trades",
            "subcategory":"Plumbing",
            "type":"Services"
        }
    ],
    "sg:phone":"+1 541 997 2661",
    "sg:postcode":"97439",
    "sg:province":"OR",
    "sg:tags":[
        "apartment",
        "contractor"
    ],
    "wof:name":"Munsel Park Apartments",
    "wof:placetype":"venue"
},
  "geometry": {"coordinates":[-124.097724,43.977467],"type":"Point"}
}