{
  "type": "Feature",
  "properties": {
    "iso:country":"US",
    "sg:address":"730 SE Cass Ave",
    "sg:city":"Roseburg",
    "sg:classifiers":[
        {
            "category":"Professional",
            "subcategory":"Management & Consulting",
            "type":"Services"
        }
    ],
    "sg:phone":"+1 541 229 0980",
    "sg:postcode":"97470",
    "sg:province":"OR",
    "wof:name":"Neil Management Team",
    "wof:placetype":"venue"
},
  "geometry": {"coordinates":[-123.34631899999999,43.208612],"type":"Point"}
}