{
  "type": "Feature",
  "properties": {
    "iso:country":"US",
    "sg:address":"3711 N Willis Blvd",
    "sg:city":"Portland",
    "sg:classifiers":[
        {
            "category":"Taxi",
            "type":"Transportation"
        },
        {
            "category":"Local Transit",
            "type":"Transportation"
        }
    ],
    "sg:phone":"+1 503 253 2277",
    "sg:postcode":"97217",
    "sg:province":"OR",
    "sg:tags":[
        "shuttle"
    ],
    "wof:name":"AAA Plus Towncar & Shuttle",
    "wof:placetype":"venue"
},
  "geometry": {"coordinates":[-122.704764,45.584312],"type":"Point"}
}