{
  "type": "Feature",
  "properties": {
    "addr:full":"13224 SE Comanche Ct Clackamas OR 97015",
    "addr:postcode":"13224;97015",
    "addr:street":"Se Comanche Ct",
    "iso:country":"US",
    "sg:address":"13224 SE Comanche Ct",
    "sg:city":"Clackamas",
    "sg:classifiers":[
        {
            "category":"Professional",
            "subcategory":"Engineering",
            "type":"Services"
        }
    ],
    "sg:phone":"+1 503 698 2784",
    "sg:postcode":"97015",
    "sg:province":"OR",
    "sg:tags":[
        "engineer"
    ],
    "wof:name":"West Coast Engineering LLC",
    "wof:placetype":"venue"
},
  "geometry": {"coordinates":[-122.528159,45.414726],"type":"Point"}
}