{
  "type": "Feature",
  "properties": {
    "iso:country":"US",
    "sg:address":"212 Kimeron St SE",
    "sg:city":"Salem",
    "sg:classifiers":[
        {
            "category":"Banks & Credit Unions",
            "subcategory":"Financial Services",
            "type":"Services"
        }
    ],
    "sg:phone":"+1 503 371 3881",
    "sg:postcode":"97306",
    "sg:province":"OR",
    "sg:tags":[
        "trust",
        "investment",
        "real estate"
    ],
    "wof:name":"Ocallghan Claire Charitable Tr",
    "wof:placetype":"venue"
},
  "geometry": {"coordinates":[-123.057728,44.882578],"type":"Point"}
}