{
  "type": "Feature",
  "properties": {
    "iso:country":"US",
    "sg:address":"21459 S Jubb Rd",
    "sg:city":"Estacada",
    "sg:classifiers":[
        {
            "category":"Building & Trades",
            "subcategory":"Landscaping Services",
            "type":"Services"
        }
    ],
    "sg:phone":"+1 503 631 3701",
    "sg:postcode":"97023",
    "sg:province":"OR",
    "sg:tags":[
        "landscape"
    ],
    "wof:name":"Snowy River Landscape & For",
    "wof:placetype":"venue"
},
  "geometry": {"coordinates":[-122.386139,45.294518],"type":"Point"}
}