{
  "type": "Feature",
  "properties": {
    "iso:country":"US",
    "sg:address":"121 S 9th St",
    "sg:city":"Klamath Falls",
    "sg:classifiers":[
        {
            "category":"Professional",
            "type":"Services"
        }
    ],
    "sg:phone":"+1 541 882 3057",
    "sg:postcode":"97601",
    "sg:province":"OR",
    "wof:name":"Scrapbook Garden Too",
    "wof:placetype":"venue"
},
  "geometry": {"coordinates":[-121.780096,42.226732],"type":"Point"}
}