{
  "type": "Feature",
  "properties": {
    "addr:full":"14910 SE Morning Way Clackamas OR 97015",
    "addr:postcode":"14910;97015",
    "addr:street":"Se Morning Way",
    "iso:country":"US",
    "sg:address":"14910 SE Morning Way",
    "sg:city":"Clackamas",
    "sg:classifiers":[
        {
            "category":"Building & Trades",
            "subcategory":"Pest Control",
            "type":"Services"
        }
    ],
    "sg:phone":"+1 800 922 6409",
    "sg:postcode":"97015",
    "sg:province":"OR",
    "wof:name":"Orkin Pest Control",
    "wof:placetype":"venue"
},
  "geometry": {"coordinates":[-122.510002,45.410801],"type":"Point"}
}