{
  "type": "Feature",
  "properties": {
    "iso:country":"US",
    "sg:address":"311 Main St",
    "sg:city":"Unity",
    "sg:classifiers":[
        {
            "category":"Government",
            "subcategory":"Fire Station",
            "type":"Public Place"
        }
    ],
    "sg:phone":"+1 541 446 3544",
    "sg:postcode":"97884",
    "sg:province":"OR",
    "sg:tags":[
        "department"
    ],
    "wof:name":"Unity Fire Dept",
    "wof:placetype":"venue"
},
  "geometry": {"coordinates":[-118.182433,44.43719],"type":"Point"}
}