{
  "type": "Feature",
  "properties": {
    "iso:country":"US",
    "sg:address":"8525 SW Barbur Blvd",
    "sg:city":"Portland",
    "sg:classifiers":[
        {
            "category":"Building & Trades",
            "subcategory":"Plumbing",
            "type":"Services"
        }
    ],
    "sg:phone":"+1 503 244 1900",
    "sg:postcode":"97219",
    "sg:province":"OR",
    "sg:tags":[
        "plumbing",
        "contractor"
    ],
    "wof:name":"Power Plumbing",
    "wof:placetype":"venue"
},
  "geometry": {"coordinates":[-122.702558,45.462993],"type":"Point"}
}