{
  "type": "Feature",
  "properties": {
    "iso:country":"US",
    "sg:address":"9221 SW Barbur Blvd Suite 310",
    "sg:city":"Portland",
    "sg:classifiers":[
        {
            "category":"Professional",
            "subcategory":"Detective & Security Services",
            "type":"Services"
        }
    ],
    "sg:phone":"+1 503 867 8640",
    "sg:postcode":"97219",
    "sg:province":"OR",
    "sg:tags":[
        "control",
        "monitoring",
        "system",
        "guard",
        "patrol"
    ],
    "sg:website":"http://www.reliantsecurity.net",
    "wof:name":"Reliant Security",
    "wof:placetype":"venue"
},
  "geometry": {"coordinates":[-122.709424,45.458912],"type":"Point"}
}