{
  "type": "Feature",
  "properties": {
    "addr:full":"9220 SW Barbur Blvd Portland OR 97219",
    "addr:housenumber":"9220",
    "addr:postcode":"97219",
    "addr:street":"Sw Barbur Blvd",
    "iso:country":"US",
    "sg:address":"9220 SW Barbur Blvd",
    "sg:city":"Portland",
    "sg:classifiers":[
        {
            "category":"Utilities",
            "subcategory":"Mobile Phone",
            "type":"Services"
        }
    ],
    "sg:phone":"+1 503 223 2355",
    "sg:postcode":"97219",
    "sg:province":"OR",
    "sg:tags":[
        "telephone",
        "cellular"
    ],
    "wof:name":"Cellular One",
    "wof:placetype":"venue"
},
  "geometry": {"coordinates":[-122.709907,45.458549],"type":"Point"}
}