{
  "type": "Feature",
  "properties": {
    "addr:full":"796 3rd Ave Seaside OR 97138",
    "addr:housenumber":"796",
    "addr:postcode":"97138",
    "addr:street":"3Rd Ave",
    "iso:country":"US",
    "sg:address":"796 3rd Ave",
    "sg:city":"Seaside",
    "sg:classifiers":[
        {
            "category":"Shopping",
            "subcategory":"Party Supplies",
            "type":"Retail Goods"
        },
        {
            "category":"Professional",
            "subcategory":"Lawyer & Legal Services",
            "type":"Services"
        },
        {
            "category":"Sports & Exercise",
            "subcategory":"Skate Park",
            "type":"Entertainment"
        }
    ],
    "sg:phone":"+1 503 286 9854",
    "sg:postcode":"97138",
    "sg:province":"OR",
    "sg:tags":[
        "children's",
        "magician",
        "planning",
        "clown"
    ],
    "sg:website":"http://www.jollymolly.com",
    "wof:name":"Jolly Molly the Clown",
    "wof:placetype":"venue"
},
  "geometry": {"coordinates":[-123.921458,45.995855],"type":"Point"}
}