{
  "type": "Feature",
  "properties": {
    "addr:full":"222 SW Columbia St # 1670 Portland OR 97201",
    "addr:housenumber":"222;# 1670",
    "addr:postcode":"97201",
    "addr:street":"Sw;St",
    "iso:country":"US",
    "sg:address":"222 SW Columbia St # 1670",
    "sg:city":"Portland",
    "sg:classifiers":[
        {
            "category":"Real Estate",
            "subcategory":"Real Estate Services",
            "type":"Services"
        },
        {
            "category":"Banks & Credit Unions",
            "subcategory":"Financial Services",
            "type":"Services"
        }
    ],
    "sg:phone":"+1 503 223 7667",
    "sg:postcode":"97201",
    "sg:province":"OR",
    "sg:tags":[
        "loan",
        "processing"
    ],
    "wof:name":"Resource Management Inc",
    "wof:placetype":"venue"
},
  "geometry": {"coordinates":[-122.67730899999999,45.513373],"type":"Point"}
}