{
  "type": "Feature",
  "properties": {
    "addr:full":"1461 W 24th Pl Eugene OR 97405",
    "addr:housenumber":"1461",
    "addr:postcode":"97405",
    "addr:street":"W 24Th Pl",
    "iso:country":"US",
    "sg:address":"1461 W 24th Pl",
    "sg:city":"Eugene",
    "sg:classifiers":[
        {
            "category":"Professional",
            "type":"Services"
        }
    ],
    "sg:phone":"+1 541 687 8118",
    "sg:postcode":"97405",
    "sg:province":"OR",
    "wof:name":"Quirks of Art",
    "wof:placetype":"venue"
},
  "geometry": {"coordinates":[-123.114158,44.032353],"type":"Point"}
}