{
  "type": "Feature",
  "properties": {
    "addr:full":"550 Main St SE Albany OR 97321",
    "addr:housenumber":"550",
    "addr:postcode":"97321",
    "addr:street":"Main St Se",
    "iso:country":"US",
    "sg:address":"550 Main St SE",
    "sg:city":"Albany",
    "sg:classifiers":[
        {
            "category":"Shopping",
            "subcategory":"Discount & Variety Stores",
            "type":"Retail Goods"
        }
    ],
    "sg:phone":"+1 541 926 8884",
    "sg:postcode":"97321",
    "sg:province":"OR",
    "wof:name":"Variety Thrift Store",
    "wof:placetype":"venue"
},
  "geometry": {"coordinates":[-123.091527,44.63538],"type":"Point"}
}