{
  "type": "Feature",
  "properties": {
    "iso:country":"US",
    "sg:address":"5720 SW Barnes Rd",
    "sg:city":"Portland",
    "sg:classifiers":[
        {
            "category":"Wholesale",
            "subcategory":"Stationery",
            "type":"Manufacturing & Wholesale Goods"
        }
    ],
    "sg:phone":"+1 503 292 1908",
    "sg:postcode":"97221",
    "sg:province":"OR",
    "sg:tags":[
        "mill",
        "paper",
        "broker",
        "representative"
    ],
    "wof:name":"American Fibre Supplies Inc",
    "wof:placetype":"venue"
},
  "geometry": {"coordinates":[-122.737148,45.517692],"type":"Point"}
}