{
  "type": "Feature",
  "properties": {
    "iso:country":"US",
    "sg:address":"3205 SW Cedar Hills Blvd",
    "sg:city":"Beaverton",
    "sg:classifiers":[
        {
            "category":"Restaurant",
            "type":"Food & Drink"
        }
    ],
    "sg:phone":"+1 503 646 5431",
    "sg:postcode":"97005",
    "sg:province":"OR",
    "sg:tags":[
        "japanese"
    ],
    "wof:name":"Waka Sushi",
    "wof:placetype":"venue"
},
  "geometry": {"coordinates":[-122.809093,45.496021],"type":"Point"}
}