{
  "type": "Feature",
  "properties": {
    "iso:country":"US",
    "sg:address":"4660 Upper Dr",
    "sg:city":"Lake Oswego",
    "sg:classifiers":[
        {
            "category":"Professional",
            "type":"Services"
        }
    ],
    "sg:phone":"+1 503 697 3619",
    "sg:postcode":"97035",
    "sg:province":"OR",
    "wof:name":"Creativ A Tees",
    "wof:placetype":"venue"
},
  "geometry": {"coordinates":[-122.724396,45.405581],"type":"Point"}
}