{
  "type": "Feature",
  "properties": {
    "iso:country":"US",
    "sg:address":"636 E Olive St",
    "sg:city":"Newport",
    "sg:classifiers":[
        {
            "category":"Building & Trades",
            "subcategory":"Construction",
            "type":"Services"
        }
    ],
    "sg:phone":"+1 541 265 7975",
    "sg:postcode":"97365",
    "sg:province":"OR",
    "sg:tags":[
        "general",
        "contractor"
    ],
    "wof:name":"Whitlock Construction",
    "wof:placetype":"venue"
},
  "geometry": {"coordinates":[-124.044951,44.636231],"type":"Point"}
}