{
  "type": "Feature",
  "properties": {
    "addr:full":"17873 State Hwy 211 Molalla OR 97038",
    "addr:housenumber":"17873",
    "addr:postcode":"97038",
    "addr:street":"State Hwy 211",
    "iso:country":"US",
    "sg:address":"17873 State Hwy 211",
    "sg:city":"Molalla",
    "sg:classifiers":[
        {
            "category":"Retail",
            "subcategory":"Animal Services",
            "type":"Services"
        }
    ],
    "sg:phone":"+1 503 829 9089",
    "sg:postcode":"97038",
    "sg:province":"OR",
    "wof:name":"Selah Farms",
    "wof:placetype":"venue"
},
  "geometry": {"coordinates":[-122.500079,45.159159],"type":"Point"}
}