{
  "type": "Feature",
  "properties": {
    "addr:full":"101 SW Main St Ste 360 Portland OR 97204",
    "addr:housenumber":"101",
    "addr:postcode":"97204",
    "addr:street":"Sw Main St Ste 360",
    "iso:country":"US",
    "sg:address":"101 SW Main St Ste 360",
    "sg:city":"Portland",
    "sg:classifiers":[
        {
            "category":"Real Estate",
            "subcategory":"Real Estate Services",
            "type":"Services"
        },
        {
            "category":"Real Estate",
            "subcategory":"Real Estate Agent",
            "type":"Services"
        }
    ],
    "sg:phone":"+1 503 295 5555",
    "sg:postcode":"97204",
    "sg:province":"OR",
    "sg:tags":[
        "management"
    ],
    "wof:name":"Gateway Crestwood Inc",
    "wof:placetype":"venue"
},
  "geometry": {"coordinates":[-122.675546,45.515191],"type":"Point"}
}