{
  "type": "Feature",
  "properties": {
    "iso:country":"US",
    "sg:address":"1020 SW Taylor St Ste 880",
    "sg:city":"Portland",
    "sg:classifiers":[
        {
            "category":"Professional",
            "subcategory":"Lawyer & Legal Services",
            "type":"Services"
        }
    ],
    "sg:phone":"+1 503 224 0900",
    "sg:postcode":"97205",
    "sg:province":"OR",
    "sg:tags":[
        "divorce",
        "law",
        "family"
    ],
    "wof:name":"Strom Trina J",
    "wof:placetype":"venue"
},
  "geometry": {"coordinates":[-122.68306800000001,45.518603],"type":"Point"}
}