{
  "type": "Feature",
  "properties": {
    "addr:full":"8316 SW 8th Ave Portland OR 97219",
    "addr:housenumber":"8316",
    "addr:postcode":"97219",
    "addr:street":"Sw 8Th Ave",
    "iso:country":"US",
    "sg:address":"8316 SW 8th Ave",
    "sg:city":"Portland",
    "sg:classifiers":[
        {
            "category":"Freight",
            "type":"Transportation"
        }
    ],
    "sg:phone":"+1 503 245 0371",
    "sg:postcode":"97219",
    "sg:province":"OR",
    "wof:name":"Joe & Connie Poleo Shipping",
    "wof:placetype":"venue"
},
  "geometry": {"coordinates":[-122.68642699999999,45.464934],"type":"Point"}
}