{
  "type": "Feature",
  "properties": {
    "iso:country":"US",
    "sg:address":"8316 SW 8th Ave",
    "sg:city":"Portland",
    "sg:classifiers":[
        {
            "category":"Freight",
            "type":"Transportation"
        }
    ],
    "sg:phone":"+1 503 245 0371",
    "sg:postcode":"97219",
    "sg:province":"OR",
    "wof:name":"Joe & Connie Poleo Shipping",
    "wof:placetype":"venue"
},
  "geometry": {"coordinates":[-122.686427,45.464934],"type":"Point"}
}