{
  "type": "Feature",
  "properties": {
    "addr:full":"1403 Jantzen Beach Center Portland OR 97217",
    "addr:housenumber":"1403",
    "addr:postcode":"97217",
    "addr:street":"Jantzen Beach",
    "iso:country":"US",
    "sg:address":"1403 Jantzen Beach Center",
    "sg:city":"Portland",
    "sg:classifiers":[
        {
            "category":"Shopping",
            "subcategory":"Clothing, Apparel, & Fashions",
            "type":"Retail Goods"
        }
    ],
    "sg:phone":"+1 503 247 8474",
    "sg:postcode":"97217",
    "sg:province":"OR",
    "sg:tags":[
        "accessory",
        "clothing",
        "women's"
    ],
    "sg:website":"www.catherines.com",
    "wof:name":"Catherine's Store",
    "wof:placetype":"venue"
},
  "geometry": {"coordinates":[-122.685332,45.612556],"type":"Point"}
}