{
  "type": "Feature",
  "properties": {
    "iso:country":"US",
    "sg:address":"133 Beverly Ct",
    "sg:city":"Roseburg",
    "sg:classifiers":[
        {
            "category":"Social Services",
            "subcategory":"Child Care",
            "type":"Services"
        }
    ],
    "sg:phone":"+1 541 679 4721",
    "sg:postcode":"97470",
    "sg:province":"OR",
    "sg:tags":[
        "day"
    ],
    "wof:name":"Tracy S Day Care",
    "wof:placetype":"venue"
},
  "geometry": {"coordinates":[-123.37853,43.157471],"type":"Point"}
}