{
  "type": "Feature",
  "properties": {
    "addr:full":"5000 SE 113th Ave Portland OR 97266",
    "addr:housenumber":"5000",
    "addr:postcode":"97266",
    "addr:street":"Se 113Th Ave",
    "iso:country":"US",
    "sg:address":"5000 SE 113th Ave",
    "sg:city":"Portland",
    "sg:classifiers":[
        {
            "category":"Manufacturing",
            "subcategory":"Petroleum Products",
            "type":"Manufacturing & Wholesale Goods"
        }
    ],
    "sg:phone":"+1 503 804 1074",
    "sg:postcode":"97266",
    "sg:province":"OR",
    "sg:tags":[
        "contract"
    ],
    "wof:name":"Roman Industries",
    "wof:placetype":"venue"
},
  "geometry": {"coordinates":[-122.54718,45.486055],"type":"Point"}
}