{
  "type": "Feature",
  "properties": {
    "addr:full":"7145 SE Amity Dayton Hwy Amity OR 97101",
    "addr:housenumber":"7145",
    "addr:postcode":"97101",
    "addr:street":"Se;Dayton Hwy",
    "iso:country":"US",
    "sg:address":"7145 SE Amity Dayton Hwy",
    "sg:city":"Amity",
    "sg:classifiers":[
        {
            "category":"Professional",
            "subcategory":"Business Services",
            "type":"Services"
        }
    ],
    "sg:phone":"+1 503 835 7591",
    "sg:postcode":"97101",
    "sg:province":"OR",
    "wof:name":"Kauer Sky",
    "wof:placetype":"venue"
},
  "geometry": {"coordinates":[-123.16437000000001,45.156474],"type":"Point"}
}