{
  "type": "Feature",
  "properties": {
    "iso:country":"US",
    "sg:address":"18740 E Aschoff Rd",
    "sg:city":"Rhododendron",
    "sg:classifiers":[
        {
            "category":"Professional",
            "subcategory":"Testing Lab",
            "type":"Services"
        }
    ],
    "sg:phone":"+1 503 622 3443",
    "sg:postcode":"97049",
    "sg:province":"OR",
    "sg:tags":[
        "laboratory"
    ],
    "wof:name":"Precision Measurement",
    "wof:placetype":"venue"
},
  "geometry": {"coordinates":[-121.90919599999999,45.38742],"type":"Point"}
}