{
  "type": "Feature",
  "properties": {
    "iso:country":"US",
    "sg:address":"205 SE Davis Ave",
    "sg:city":"Bend",
    "sg:classifiers":[
        {
            "category":"Health Services",
            "subcategory":"Health Practitioner",
            "type":"Services"
        }
    ],
    "sg:phone":"+1 541 318 6338",
    "sg:postcode":"97702",
    "sg:province":"OR",
    "sg:tags":[
        "midwife"
    ],
    "wof:name":"Heart & Hands Midwifery Svc",
    "wof:placetype":"venue"
},
  "geometry": {"coordinates":[-121.302688,44.049005],"type":"Point"}
}