{
  "type": "Feature",
  "properties": {
    "iso:country":"US",
    "sg:address":"2222 NW Lovejoy St",
    "sg:city":"Portland",
    "sg:classifiers":[
        {
            "category":"Health Services",
            "subcategory":"Doctor",
            "type":"Services"
        }
    ],
    "sg:phone":"+1 503 229 7603",
    "sg:postcode":"97210",
    "sg:province":"OR",
    "sg:tags":[
        "medical"
    ],
    "wof:name":"John G Buckmaster MD",
    "wof:placetype":"venue"
},
  "geometry": {"coordinates":[-122.69828800000001,45.529723],"type":"Point"}
}