{
  "type": "Feature",
  "properties": {
    "addr:full":"916 W. Burnside St. Portland OR 97209",
    "addr:housenumber":"916",
    "addr:postcode":"97209",
    "addr:street":"W. Burnside St.",
    "iso:country":"US",
    "sg:address":"916 W. Burnside St.",
    "sg:city":"Portland",
    "sg:classifiers":[
        {
            "category":"Shopping",
            "subcategory":"Antiques",
            "type":"Retail Goods"
        }
    ],
    "sg:phone":"+1 503 360 1142",
    "sg:postcode":"97209",
    "sg:province":"OR",
    "sg:website":"www.store.lulusvintage.com",
    "wof:name":"Lulu's Vintage",
    "wof:placetype":"venue"
},
  "geometry": {"coordinates":[-122.68026999999999,45.522976],"type":"Point"}
}