{
  "type": "Feature",
  "properties": {
    "addr:full":"41044 Big Fall Creek Rd Fall Creek OR 97438",
    "addr:housenumber":"41044",
    "addr:postcode":"97438",
    "addr:street":"Big Fall Creek Rd",
    "iso:country":"US",
    "sg:address":"41044 Big Fall Creek Rd",
    "sg:city":"Fall Creek",
    "sg:classifiers":[
        {
            "category":"Bars & Pubs",
            "type":"Food & Drink"
        }
    ],
    "sg:phone":"+1 541 937 2962",
    "sg:postcode":"97438",
    "sg:province":"OR",
    "wof:name":"Fall Creek Tavern",
    "wof:placetype":"venue"
},
  "geometry": {"coordinates":[-122.71801600000001,43.956451],"type":"Point"}
}