{
  "type": "Feature",
  "properties": {
    "iso:country":"US",
    "sg:address":"2244 E Burnside St",
    "sg:city":"Portland",
    "sg:classifiers":[
        {
            "category":"Wholesale",
            "subcategory":"Motor Vehicles",
            "type":"Manufacturing & Wholesale Goods"
        }
    ],
    "sg:phone":"+1 503 238 2429",
    "sg:postcode":"97214",
    "sg:province":"OR",
    "wof:name":"Auto Solution",
    "wof:placetype":"venue"
},
  "geometry": {"coordinates":[-122.64175,45.522793],"type":"Point"}
}