{
  "type": "Feature",
  "properties": {
    "iso:country":"US",
    "sg:address":"21323 SW Sherwood Blvd",
    "sg:city":"Sherwood",
    "sg:classifiers":[
        {
            "category":"Wholesale",
            "subcategory":"Medical Equipment & Supplies",
            "type":"Manufacturing & Wholesale Goods"
        },
        {
            "category":"Retail",
            "subcategory":"Repair Shop",
            "type":"Services"
        },
        {
            "category":"Health Services",
            "subcategory":"Health Practitioner",
            "type":"Services"
        }
    ],
    "sg:phone":"+1 503 625 4111",
    "sg:postcode":"97140",
    "sg:province":"OR",
    "sg:tags":[
        "repairing",
        "aids-parts",
        "hearing",
        "device",
        "assistive",
        "aid",
        "audiologists"
    ],
    "sg:website":"http://www.oregonhearing.com",
    "wof:name":"Oregon Hearing Solutions",
    "wof:placetype":"venue"
},
  "geometry": {"coordinates":[-122.847047,45.365488],"type":"Point"}
}