{
  "type": "Feature",
  "properties": {
    "addr:full":"870 N Main St Independence OR 97351",
    "addr:housenumber":"870",
    "addr:postcode":"97351",
    "addr:street":"N Main St",
    "iso:country":"US",
    "sg:address":"870 N Main St",
    "sg:city":"Independence",
    "sg:classifiers":[
        {
            "category":"Restaurant",
            "type":"Food & Drink"
        }
    ],
    "sg:phone":"+1 503 838 0170",
    "sg:postcode":"97351",
    "sg:province":"OR",
    "sg:tags":[
        "mexican"
    ],
    "wof:name":"Casa Tequila",
    "wof:placetype":"venue"
},
  "geometry": {"coordinates":[-123.184669,44.861544],"type":"Point"}
}