{
  "type": "Feature",
  "properties": {
    "addr:full":"1915 NE 7th Ave Portland OR 97212",
    "addr:housenumber":"1915",
    "addr:postcode":"97212",
    "addr:street":"Ne 7Th Ave",
    "iso:country":"US",
    "sg:address":"1915 NE 7th Ave",
    "sg:city":"Portland",
    "sg:classifiers":[
        {
            "category":"Wholesale",
            "subcategory":"Machinery & Supplies",
            "type":"Manufacturing & Wholesale Goods"
        }
    ],
    "sg:phone":"+1 503 249 2888",
    "sg:postcode":"97212",
    "sg:province":"OR",
    "sg:tags":[
        "tool"
    ],
    "sg:website":"www.bassettind.com",
    "wof:name":"Bassett Industrial Supply Co",
    "wof:placetype":"venue"
},
  "geometry": {"coordinates":[-122.658697,45.536974],"type":"Point"}
}