{
  "type": "Feature",
  "properties": {
    "iso:country":"US",
    "sg:address":"216 SE 103rd Ave Apt 108",
    "sg:city":"Portland",
    "sg:classifiers":[
        {
            "category":"Education",
            "subcategory":"Music School",
            "type":"Public Place"
        }
    ],
    "sg:phone":"+1 503 528 1551",
    "sg:postcode":"97216",
    "sg:province":"OR",
    "sg:tags":[
        "instruction-instrumental"
    ],
    "wof:name":"Irene Huang Music Studio",
    "wof:placetype":"venue"
},
  "geometry": {"coordinates":[-122.55703,45.520933],"type":"Point"}
}