{
  "type": "Feature",
  "properties": {
    "addr:full":"SW 10th Ave and SW Washington St Portland OR 97205",
    "addr:postcode":"97205",
    "addr:street":"Sw 10Th Ave And Sw Washington St",
    "iso:country":"US",
    "sg:address":"SW 10th Ave and SW Washington St",
    "sg:city":"Portland",
    "sg:classifiers":[
        {
            "category":"Food Court",
            "type":"Food & Drink"
        },
        {
            "category":"Food & Beverages",
            "subcategory":"Bakery",
            "type":"Retail Goods"
        }
    ],
    "sg:phone":"+1 503 260 0328",
    "sg:postcode":"97205",
    "sg:province":"OR",
    "sg:tags":[
        "sandwich",
        "stand"
    ],
    "sg:website":"www.wethotbeef.com",
    "wof:name":"Wet Hot Beef",
    "wof:placetype":"venue"
},
  "geometry": {"coordinates":[-122.67620700000001,45.523452],"type":"Point"}
}