{
  "type": "Feature",
  "properties": {
    "iso:country":"US",
    "sg:address":"16240 SW Chinook Dr",
    "sg:city":"Terrebonne",
    "sg:classifiers":[
        {
            "category":"Building & Trades",
            "subcategory":"Construction",
            "type":"Services"
        }
    ],
    "sg:phone":"+1 541 923 6086",
    "sg:postcode":"97760",
    "sg:province":"OR",
    "sg:tags":[
        "siding",
        "contractor"
    ],
    "wof:name":"Channel & Co Construction",
    "wof:placetype":"venue"
},
  "geometry": {"coordinates":[-121.240033,44.404067],"type":"Point"}
}