{
  "type": "Feature",
  "properties": {
    "addr:full":"2075 NW Glisan St Portland OR 97209",
    "addr:housenumber":"2075",
    "addr:postcode":"97209",
    "addr:street":"Nw Glisan St",
    "iso:country":"US",
    "sg:address":"2075 NW Glisan St",
    "sg:city":"Portland",
    "sg:classifiers":[
        {
            "category":"Bars & Pubs",
            "subcategory":"Lounge",
            "type":"Food & Drink"
        }
    ],
    "sg:phone":"+1 503 222 1056",
    "sg:postcode":"97209",
    "sg:province":"OR",
    "sg:website":"popehouselounge.com",
    "wof:name":"Pope House Bourbon Lounge",
    "wof:placetype":"venue"
},
  "geometry": {"coordinates":[-122.694019,45.526532],"type":"Point"}
}