{
  "type": "Feature",
  "properties": {
    "iso:country":"US",
    "sg:address":"38415 US Hwy 26",
    "sg:city":"Sandy",
    "sg:classifiers":[
        {
            "category":"Retail",
            "subcategory":"Car Wash",
            "type":"Services"
        }
    ],
    "sg:phone":"+1 971 253 0002",
    "sg:postcode":"97055",
    "sg:province":"OR",
    "sg:tags":[
        "automobile",
        "detail",
        "clean"
    ],
    "wof:name":"Suburban Auto Detail",
    "wof:placetype":"venue"
},
  "geometry": {"coordinates":[-122.268162,45.397409],"type":"Point"}
}