{
  "type": "Feature",
  "properties": {
    "iso:country":"US",
    "sg:address":"713 SW Filbert St",
    "sg:city":"Mcminnville",
    "sg:classifiers":[
        {
            "category":"Building & Trades",
            "subcategory":"Electrical",
            "type":"Services"
        }
    ],
    "sg:phone":"+1 503 474 0242",
    "sg:postcode":"97128",
    "sg:province":"OR",
    "sg:tags":[
        "electrical",
        "contractor"
    ],
    "wof:name":"Omega Electric Inc",
    "wof:placetype":"venue"
},
  "geometry": {"coordinates":[-123.224402,45.203726],"type":"Point"}
}