{
  "type": "Feature",
  "properties": {
    "iso:country":"US",
    "sg:address":"18010 S Holly Ln",
    "sg:city":"Oregon City",
    "sg:classifiers":[
        {
            "category":"Building & Trades",
            "subcategory":"Plumbing",
            "type":"Services"
        }
    ],
    "sg:phone":"+1 503 780 6807",
    "sg:postcode":"97045",
    "sg:province":"OR",
    "sg:tags":[
        "contractor"
    ],
    "wof:name":"AC Power Services Inc",
    "wof:placetype":"venue"
},
  "geometry": {"coordinates":[-122.573567,45.34506],"type":"Point"}
}