{
  "type": "Feature",
  "properties": {
    "iso:country":"US",
    "sg:address":"5000 Cirrus Dr",
    "sg:city":"Medford",
    "sg:classifiers":[
        {
            "category":"Education",
            "subcategory":"Special Training",
            "type":"Public Place"
        }
    ],
    "sg:phone":"+1 541 858 0427",
    "sg:postcode":"97504",
    "sg:province":"OR",
    "sg:tags":[
        "aircraft",
        "school"
    ],
    "wof:name":"Great Pacfic Aviation",
    "wof:placetype":"venue"
},
  "geometry": {"coordinates":[-122.881523,42.376782],"type":"Point"}
}