{
  "type": "Feature",
  "properties": {
    "addr:full":"20462 Sawyer Rd Shady Cove OR 97539",
    "addr:housenumber":"20462",
    "addr:postcode":"97539",
    "addr:street":"Sawyer Rd",
    "iso:country":"US",
    "sg:address":"20462 Sawyer Rd",
    "sg:city":"Shady Cove",
    "sg:classifiers":[
        {
            "category":"Freight",
            "type":"Transportation"
        }
    ],
    "sg:phone":"+1 541 878 2948",
    "sg:postcode":"97539",
    "sg:province":"OR",
    "sg:tags":[
        "courier"
    ],
    "wof:name":"Grey Oaks Development",
    "wof:placetype":"venue"
},
  "geometry": {"coordinates":[-122.827125,42.617413],"type":"Point"}
}