{
  "type": "Feature",
  "properties": {
    "iso:country":"US",
    "sg:address":"709 W Stewart Ave",
    "sg:city":"Medford",
    "sg:classifiers":[
        {
            "category":"Restaurant",
            "type":"Food & Drink"
        }
    ],
    "sg:phone":"+1 541 858 9000",
    "sg:postcode":"97501",
    "sg:province":"OR",
    "sg:tags":[
        "pizza"
    ],
    "sg:website":"www.papamurphys.com",
    "wof:name":"Papa Murphy's Take 'n' Bake Pizza",
    "wof:placetype":"venue"
},
  "geometry": {"coordinates":[-122.87750699999999,42.312683],"type":"Point"}
}