{
  "type": "Feature",
  "properties": {
    "addr:full":"43530 Shetland Ct Pendleton OR 97801",
    "addr:housenumber":"43530",
    "addr:postcode":"97801",
    "addr:street":"Shetland Ct",
    "iso:country":"US",
    "sg:address":"43530 Shetland Ct",
    "sg:city":"Pendleton",
    "sg:classifiers":[
        {
            "category":"Real Estate",
            "subcategory":"Real Estate Services",
            "type":"Services"
        },
        {
            "category":"Real Estate",
            "subcategory":"Real Estate Agent",
            "type":"Services"
        }
    ],
    "sg:phone":"+1 541 276 8031",
    "sg:postcode":"97801",
    "sg:province":"OR",
    "sg:tags":[
        "management"
    ],
    "wof:name":"Joseph Cunha Ranch",
    "wof:placetype":"venue"
},
  "geometry": {"coordinates":[-118.802429,45.608214],"type":"Point"}
}