{
  "type": "Feature",
  "properties": {
    "iso:country":"US",
    "sg:address":"33901 SE Peoria Rd",
    "sg:city":"Corvallis",
    "sg:classifiers":[
        {
            "category":"Retail",
            "subcategory":"Auto Repair",
            "type":"Services"
        }
    ],
    "sg:phone":"+1 541 753 9191",
    "sg:postcode":"97333",
    "sg:province":"OR",
    "sg:tags":[
        "starter"
    ],
    "wof:name":"Peoria Electric",
    "wof:placetype":"venue"
},
  "geometry": {"coordinates":[-123.227276,44.555051],"type":"Point"}
}