{
  "type": "Feature",
  "properties": {
    "iso:country":"US",
    "sg:address":"195 E 17th Ave",
    "sg:city":"Eugene",
    "sg:classifiers":[
        {
            "category":"Restaurant",
            "type":"Food & Drink"
        }
    ],
    "sg:phone":"+1 541 485 0700",
    "sg:postcode":"97401",
    "sg:province":"OR",
    "wof:name":"Dog House Resteraunt",
    "wof:placetype":"venue"
},
  "geometry": {"coordinates":[-123.09070800000001,44.041207],"type":"Point"}
}