{
  "type": "Feature",
  "properties": {
    "addr:full":"4320 US Hwy 101 Seaside OR 97138",
    "addr:housenumber":"4320",
    "addr:postcode":"97138",
    "addr:street":"Us Hwy 101",
    "iso:country":"US",
    "sg:address":"4320 US Hwy 101",
    "sg:city":"Seaside",
    "sg:classifiers":[
        {
            "category":"Home & Garden",
            "subcategory":"Building Materials",
            "type":"Retail Goods"
        }
    ],
    "sg:phone":"+1 503 738 3366",
    "sg:postcode":"97138",
    "sg:province":"OR",
    "wof:name":"Gearhart",
    "wof:placetype":"venue"
},
  "geometry": {"coordinates":[-123.913287,46.036725],"type":"Point"}
}