{
  "type": "Feature",
  "properties": {
    "iso:country":"US",
    "sg:address":"5621 SW Homesteader Rd",
    "sg:city":"Wilsonville",
    "sg:classifiers":[
        {
            "category":"Wholesale",
            "subcategory":"Plants",
            "type":"Manufacturing & Wholesale Goods"
        }
    ],
    "sg:phone":"+1 503 638 8222",
    "sg:postcode":"97070",
    "sg:province":"OR",
    "sg:tags":[
        "nursery",
        "tree"
    ],
    "wof:name":"Eby Nursery Inc",
    "wof:placetype":"venue"
},
  "geometry": {"coordinates":[-122.73389,45.332091],"type":"Point"}
}