{
  "type": "Feature",
  "properties": {
    "iso:country":"US",
    "sg:address":"61545 Newberry Dr",
    "sg:city":"Bend",
    "sg:classifiers":[
        {
            "category":"Manufacturing",
            "subcategory":"Furniture",
            "type":"Manufacturing & Wholesale Goods"
        }
    ],
    "sg:phone":"+1 541 389 1802",
    "sg:postcode":"97702",
    "sg:province":"OR",
    "sg:tags":[
        "mfg",
        "wood",
        "general",
        "contractor"
    ],
    "wof:name":"Akamai Woodworkers",
    "wof:placetype":"venue"
},
  "geometry": {"coordinates":[-121.281389,44.035215],"type":"Point"}
}