{
  "type": "Feature",
  "properties": {
    "addr:full":"1711 SW High St Portland OR 97201",
    "addr:housenumber":"1711",
    "addr:postcode":"97201",
    "addr:street":"Sw High St",
    "iso:country":"US",
    "sg:address":"1711 SW High St",
    "sg:city":"Portland",
    "sg:classifiers":[
        {
            "category":"Professional",
            "subcategory":"Engineering",
            "type":"Services"
        }
    ],
    "sg:phone":"+1 503 227 6408",
    "sg:postcode":"97201",
    "sg:province":"OR",
    "sg:tags":[
        "consulting",
        "engineer"
    ],
    "wof:name":"Jf Holtz Engineering",
    "wof:placetype":"venue"
},
  "geometry": {"coordinates":[-122.69793,45.506712],"type":"Point"}
}