{
  "type": "Feature",
  "properties": {
    "iso:country":"US",
    "sg:address":"250 Division St NE",
    "sg:city":"Salem",
    "sg:classifiers":[
        {
            "category":"Real Estate",
            "subcategory":"Real Estate Services",
            "type":"Services"
        }
    ],
    "sg:phone":"+1 503 587 4778",
    "sg:postcode":"97301",
    "sg:province":"OR",
    "sg:tags":[
        "commercial"
    ],
    "wof:name":"Rhoten Commercial Real Estate",
    "wof:placetype":"venue"
},
  "geometry": {"coordinates":[-123.037904,44.947312],"type":"Point"}
}