{
  "type": "Feature",
  "properties": {
    "addr:full":"287 N Columbia St Milton Freewater OR 97862",
    "addr:housenumber":"287",
    "addr:postcode":"97862",
    "addr:street":"N Columbia St;Freewater",
    "iso:country":"US",
    "sg:address":"287 N Columbia St",
    "sg:city":"Milton Freewater",
    "sg:classifiers":[
        {
            "category":"Real Estate",
            "subcategory":"Real Estate Services",
            "type":"Services"
        }
    ],
    "sg:phone":"+1 541 938 3005",
    "sg:postcode":"97862",
    "sg:province":"OR",
    "sg:tags":[
        "abstract",
        "insurance",
        "title"
    ],
    "wof:name":"Amerititle Inc",
    "wof:placetype":"venue"
},
  "geometry": {"coordinates":[-118.387702,45.938134],"type":"Point"}
}