{
  "type": "Feature",
  "properties": {
    "iso:country":"US",
    "sg:address":"680 Alderbrook Ln",
    "sg:city":"Grants Pass",
    "sg:classifiers":[
        {
            "category":"Banks & Credit Unions",
            "subcategory":"Financial Services",
            "type":"Services"
        }
    ],
    "sg:phone":"+1 541 479 6447",
    "sg:postcode":"97527",
    "sg:province":"OR",
    "sg:tags":[
        "investor"
    ],
    "wof:name":"Redwood Property Investments",
    "wof:placetype":"venue"
},
  "geometry": {"coordinates":[-123.386428,42.435465],"type":"Point"}
}