{
  "type": "Feature",
  "properties": {
    "iso:country":"US",
    "sg:address":"219 Madrona Ave SE",
    "sg:city":"Salem",
    "sg:classifiers":[
        {
            "category":"Professional",
            "type":"Services"
        }
    ],
    "sg:phone":"+1 503 581 1055",
    "sg:postcode":"97302",
    "sg:province":"OR",
    "wof:name":"Brad Fields",
    "wof:placetype":"venue"
},
  "geometry": {"coordinates":[-123.049637,44.904815],"type":"Point"}
}