{
  "type": "Feature",
  "properties": {
    "iso:country":"US",
    "sg:address":"2409 SE Taylor St",
    "sg:city":"Portland",
    "sg:classifiers":[
        {
            "category":"Arts & Performance",
            "subcategory":"Music",
            "type":"Entertainment"
        }
    ],
    "sg:phone":"+1 971 344 2022",
    "sg:postcode":"97214",
    "sg:province":"OR",
    "sg:tags":[
        "dj"
    ],
    "sg:website":"www.bollywoodpdx.com",
    "wof:name":"Bollywood Dreams Entertainment",
    "wof:placetype":"venue"
},
  "geometry": {"coordinates":[-122.640973,45.515249],"type":"Point"}
}