{
  "type": "Feature",
  "properties": {
    "iso:country":"US",
    "sg:address":"508 Main St",
    "sg:city":"Oregon City",
    "sg:classifiers":[
        {
            "category":"Education",
            "subcategory":"Special Training",
            "type":"Public Place"
        }
    ],
    "sg:phone":"+1 503 657 7440",
    "sg:postcode":"97045",
    "sg:province":"OR",
    "wof:name":"Music School Inc",
    "wof:placetype":"venue"
},
  "geometry": {"coordinates":[-122.609635,45.356925],"type":"Point"}
}