{
  "type": "Feature",
  "properties": {
    "addr:full":"443 NE Stephens St Roseburg OR 97470",
    "addr:housenumber":"443",
    "addr:postcode":"97470",
    "addr:street":"Ne Stephens St",
    "iso:country":"US",
    "sg:address":"443 NE Stephens St",
    "sg:city":"Roseburg",
    "sg:classifiers":[
        {
            "category":"Shopping",
            "subcategory":"Used Merchandise",
            "type":"Retail Goods"
        },
        {
            "category":"Shopping",
            "subcategory":"Bicycles & Sporting Goods",
            "type":"Retail Goods"
        }
    ],
    "sg:phone":"+1 541 673 0123",
    "sg:postcode":"97470",
    "sg:province":"OR",
    "sg:tags":[
        "gun",
        "gunsmith"
    ],
    "wof:name":"Associated Buyers LLC",
    "wof:placetype":"venue"
},
  "geometry": {"coordinates":[-123.342518,43.215697],"type":"Point"}
}