{
  "type": "Feature",
  "properties": {
    "iso:country":"US",
    "sg:address":"7495 SW Hergert Rd",
    "sg:city":"Cornelius",
    "sg:classifiers":[
        {
            "category":"Professional",
            "subcategory":"Art Services",
            "type":"Services"
        }
    ],
    "sg:phone":"+1 503 357 3977",
    "sg:postcode":"97113",
    "sg:province":"OR",
    "sg:tags":[
        "designer",
        "display",
        "producer"
    ],
    "wof:name":"Sassy Sachels By Design Llp",
    "wof:placetype":"venue"
},
  "geometry": {"coordinates":[-123.06980900000001,45.468686],"type":"Point"}
}