{
  "type": "Feature",
  "properties": {
    "iso:country":"US",
    "sg:address":"1432 NE Highland St",
    "sg:city":"Portland",
    "sg:classifiers":[
        {
            "category":"Building & Trades",
            "subcategory":"Locksmith",
            "type":"Services"
        }
    ],
    "sg:phone":"+1 503 821 0934",
    "sg:postcode":"97211",
    "sg:province":"OR",
    "sg:tags":[
        "key"
    ],
    "wof:name":"20 Minute A Locksmith",
    "wof:placetype":"venue"
},
  "geometry": {"coordinates":[-122.65058500000001,45.568989],"type":"Point"}
}