{
  "type": "Feature",
  "properties": {
    "addr:full":"600 N Grape St Medford OR 97501",
    "addr:housenumber":"600",
    "addr:postcode":"97501",
    "addr:street":"N Grape St",
    "iso:country":"US",
    "sg:address":"600 N Grape St",
    "sg:city":"Medford",
    "sg:classifiers":[
        {
            "category":"Wholesale",
            "subcategory":"Books, Periodicals, & Newspapers",
            "type":"Manufacturing & Wholesale Goods"
        }
    ],
    "sg:phone":"+1 541 779 0016",
    "sg:postcode":"97501",
    "sg:province":"OR",
    "sg:tags":[
        "publisher"
    ],
    "wof:name":"Educational Systems & Resources",
    "wof:placetype":"venue"
},
  "geometry": {"coordinates":[-122.879723,42.32991],"type":"Point"}
}