{
  "type": "Feature",
  "properties": {
    "addr:full":"17427 SW Rivendell Dr Portland OR 97224",
    "addr:housenumber":"17427",
    "addr:postcode":"97224",
    "addr:street":"Sw Rivendell Dr",
    "iso:country":"US",
    "sg:address":"17427 SW Rivendell Dr",
    "sg:city":"Portland",
    "sg:classifiers":[
        {
            "category":"Building & Trades",
            "subcategory":"Construction",
            "type":"Services"
        }
    ],
    "sg:phone":"+1 503 784 1683",
    "sg:postcode":"97224",
    "sg:province":"OR",
    "sg:tags":[
        "general",
        "contractor"
    ],
    "wof:name":"R H Oathes Construction",
    "wof:placetype":"venue"
},
  "geometry": {"coordinates":[-122.75894099999999,45.393844],"type":"Point"}
}