{
  "type": "Feature",
  "properties": {
    "iso:country":"US",
    "sg:address":"10202 SE 32nd Avenue Suite 201",
    "sg:city":"Portland",
    "sg:classifiers":[
        {
            "category":"Health Services",
            "subcategory":"Doctor",
            "type":"Services"
        }
    ],
    "sg:phone":"+1 503 653 0770",
    "sg:postcode":"97222",
    "sg:province":"OR",
    "wof:name":"Fortlage Donald W MD",
    "wof:placetype":"venue"
},
  "geometry": {"coordinates":[-122.615562,45.441952],"type":"Point"}
}