{
  "type": "Feature",
  "properties": {
    "iso:country":"US",
    "sg:address":"4147 Salmon River Hwy",
    "sg:city":"Otis",
    "sg:classifiers":[
        {
            "category":"Retail",
            "subcategory":"Auto Repair",
            "type":"Services"
        }
    ],
    "sg:phone":"+1 541 994 5806",
    "sg:postcode":"97368",
    "sg:province":"OR",
    "sg:tags":[
        "body",
        "automobile",
        "painting",
        "repairing"
    ],
    "wof:name":"Babb's Body Shop",
    "wof:placetype":"venue"
},
  "geometry": {"coordinates":[-123.888452,45.005093],"type":"Point"}
}