{
  "type": "Feature",
  "properties": {
    "addr:full":"2925 NW Nicolai St Portland OR 97210",
    "addr:housenumber":"2925",
    "addr:postcode":"97210",
    "addr:street":"Nw Nicolai St",
    "iso:country":"US",
    "sg:address":"2925 NW Nicolai St",
    "sg:city":"Portland",
    "sg:classifiers":[
        {
            "category":"Retail",
            "subcategory":"Auto Repair",
            "type":"Services"
        }
    ],
    "sg:phone":"+1 503 255 5542",
    "sg:postcode":"97210",
    "sg:province":"OR",
    "sg:tags":[
        "rental"
    ],
    "wof:name":"Foreign & Domestic Motor Works",
    "wof:placetype":"venue"
},
  "geometry": {"coordinates":[-122.71132900000001,45.538607],"type":"Point"}
}