{
  "type": "Feature",
  "properties": {
    "iso:country":"US",
    "sg:address":"2925 NW Nicolai St",
    "sg:city":"Portland",
    "sg:classifiers":[
        {
            "category":"Retail",
            "subcategory":"Auto Repair",
            "type":"Services"
        }
    ],
    "sg:phone":"+1 503 255 5542",
    "sg:postcode":"97210",
    "sg:province":"OR",
    "sg:tags":[
        "rental"
    ],
    "wof:name":"Foreign & Domestic Motor Works",
    "wof:placetype":"venue"
},
  "geometry": {"coordinates":[-122.711329,45.538607],"type":"Point"}
}