{
  "type": "Feature",
  "properties": {
    "iso:country":"US",
    "sg:address":"10652 NE Holman St",
    "sg:city":"Portland",
    "sg:phone":"+1 503 258 8888",
    "sg:postcode":"97220",
    "sg:province":"OR",
    "sg:website":"http://www.portlandmotorcycle.com",
    "wof:name":"Portland Motorcycle Co",
    "wof:placetype":"venue"
},
  "geometry": {"coordinates":[-122.553866,45.567],"type":"Point"}
}