{
  "type": "Feature",
  "properties": {
    "iso:country":"US",
    "sg:address":"111 Fir St",
    "sg:city":"Myrtle Creek",
    "sg:classifiers":[
        {
            "category":"Manufacturing",
            "subcategory":"Printing",
            "type":"Manufacturing & Wholesale Goods"
        }
    ],
    "sg:phone":"+1 541 863 5234",
    "sg:postcode":"97457",
    "sg:province":"OR",
    "sg:tags":[
        "periodical"
    ],
    "wof:name":"Umpqua Free Press",
    "wof:placetype":"venue"
},
  "geometry": {"coordinates":[-123.293147,43.012344],"type":"Point"}
}