{
  "type": "Feature",
  "properties": {
    "iso:country":"US",
    "sg:address":"15115 SW Sequoia Parkway",
    "sg:city":"Portland",
    "sg:classifiers":[
        {
            "category":"Professional",
            "subcategory":"Computer Services",
            "type":"Services"
        }
    ],
    "sg:phone":"+1 503 603 0932",
    "sg:postcode":"97224",
    "sg:province":"OR",
    "sg:tags":[
        "repair"
    ],
    "wof:name":"Northwest It Services",
    "wof:placetype":"venue"
},
  "geometry": {"coordinates":[-122.746859,45.409675],"type":"Point"}
}