{
  "type": "Feature",
  "properties": {
    "iso:country":"US",
    "sg:address":"35 NW A St",
    "sg:city":"Madras",
    "sg:classifiers":[
        {
            "category":"Autos & Motor Vehicles",
            "subcategory":"Auto Supplies",
            "type":"Retail Goods"
        }
    ],
    "sg:phone":"+1 541 475 2256",
    "sg:postcode":"97741",
    "sg:province":"OR",
    "sg:tags":[
        "automobile",
        "parts"
    ],
    "wof:name":"Madras Auto Parts Inc",
    "wof:placetype":"venue"
},
  "geometry": {"coordinates":[-121.129986,44.637033],"type":"Point"}
}