{
  "type": "Feature",
  "properties": {
    "addr:full":"192 Norman Ave Coos Bay OR 97420",
    "addr:housenumber":"192",
    "addr:postcode":"97420",
    "addr:street":"Norman Ave",
    "iso:country":"US",
    "sg:address":"192 Norman Ave",
    "sg:city":"Coos Bay",
    "sg:classifiers":[
        {
            "category":"Personal",
            "subcategory":"Beauty Salon",
            "type":"Services"
        }
    ],
    "sg:phone":"+1 541 888 5858",
    "sg:postcode":"97420",
    "sg:province":"OR",
    "sg:tags":[
        "shop"
    ],
    "wof:name":"Arees' Beauty Salon",
    "wof:placetype":"venue"
},
  "geometry": {"coordinates":[-124.26083199999999,43.390154],"type":"Point"}
}