{
  "type": "Feature",
  "properties": {
    "iso:country":"US",
    "sg:address":"2250 14th Ave SE",
    "sg:city":"Albany",
    "sg:classifiers":[
        {
            "category":"Shopping",
            "subcategory":"Hobbies, Toys, & Games",
            "type":"Retail Goods"
        }
    ],
    "sg:phone":"+1 541 791 2300",
    "sg:postcode":"97322",
    "sg:province":"OR",
    "sg:tags":[
        "supply"
    ],
    "wof:name":"Fantasy Knights",
    "wof:placetype":"venue"
},
  "geometry": {"coordinates":[-123.082358,44.628678],"type":"Point"}
}