{
  "type": "Feature",
  "properties": {
    "iso:country":"US",
    "sg:address":"15858 S Redland Rd",
    "sg:city":"Oregon City",
    "sg:classifiers":[
        {
            "category":"Retail",
            "subcategory":"Auto Repair",
            "type":"Services"
        }
    ],
    "sg:phone":"+1 503 631 4204",
    "sg:postcode":"97045",
    "sg:province":"OR",
    "sg:tags":[
        "repairing",
        "automobile"
    ],
    "wof:name":"Toms Auto Repair",
    "wof:placetype":"venue"
},
  "geometry": {"coordinates":[-122.540177,45.352448],"type":"Point"}
}