{
  "type": "Feature",
  "properties": {
    "addr:full":"5651 NE Farmcrest St Hillsboro OR 97124",
    "addr:housenumber":"5651",
    "addr:postcode":"97124",
    "addr:street":"Ne Farmcrest St",
    "iso:country":"US",
    "sg:address":"5651 NE Farmcrest St",
    "sg:city":"Hillsboro",
    "sg:classifiers":[
        {
            "category":"Organizations",
            "subcategory":"Political Organization",
            "type":"Services"
        }
    ],
    "sg:phone":"+1 503 640 3780",
    "sg:postcode":"97124",
    "sg:province":"OR",
    "sg:tags":[
        "campaign"
    ],
    "wof:name":"Senator Bruce Starr",
    "wof:placetype":"venue"
},
  "geometry": {"coordinates":[-122.92360499999999,45.535058],"type":"Point"}
}