{
  "type": "Feature",
  "properties": {
    "addr:full":"21360 NW Amberwood Dr Hillsboro OR 97124",
    "addr:housenumber":"21360",
    "addr:postcode":"97124",
    "addr:street":"Nw Amberwood Dr",
    "iso:country":"US",
    "sg:address":"21360 NW Amberwood Dr",
    "sg:city":"Hillsboro",
    "sg:classifiers":[
        {
            "category":"Building & Trades",
            "subcategory":"Construction",
            "type":"Services"
        }
    ],
    "sg:phone":"+1 503 645 8531",
    "sg:postcode":"97124",
    "sg:province":"OR",
    "sg:tags":[
        "home",
        "builder",
        "contractor"
    ],
    "sg:website":"www.robcon.com",
    "wof:name":"Robinson Construction Co",
    "wof:placetype":"venue"
},
  "geometry": {"coordinates":[-122.896742,45.537477],"type":"Point"}
}