{
  "type": "Feature",
  "properties": {
    "iso:country":"US",
    "sg:address":"29328 Dane Ln",
    "sg:city":"Junction City",
    "sg:classifiers":[
        {
            "category":"Real Estate",
            "subcategory":"Real Estate Operator",
            "type":"Services"
        }
    ],
    "sg:phone":"+1 541 998 9724",
    "sg:postcode":"97448",
    "sg:province":"OR",
    "sg:tags":[
        "building",
        "nonresidential"
    ],
    "wof:name":"D&R Properties",
    "wof:placetype":"venue"
},
  "geometry": {"coordinates":[-123.198241,44.225811],"type":"Point"}
}