{
  "type": "Feature",
  "properties": {
    "iso:country":"US",
    "sg:address":"4055 Skyline Rd",
    "sg:city":"The Dalles",
    "sg:classifiers":[
        {
            "category":"Wholesale",
            "subcategory":"Fruits & Vegetables",
            "type":"Manufacturing & Wholesale Goods"
        }
    ],
    "sg:phone":"+1 541 296 5007",
    "sg:postcode":"97058",
    "sg:province":"OR",
    "sg:tags":[
        "broker"
    ],
    "wof:name":"Grant J Hunt Company",
    "wof:placetype":"venue"
},
  "geometry": {"coordinates":[-121.212069,45.57569],"type":"Point"}
}