{
  "type": "Feature",
  "properties": {
    "iso:country":"US",
    "sg:address":"21131 Main St NE",
    "sg:city":"Aurora",
    "sg:classifiers":[
        {
            "category":"Retail",
            "subcategory":"Auto Repair",
            "type":"Services"
        }
    ],
    "sg:phone":"+1 503 678 2589",
    "sg:postcode":"97002",
    "sg:province":"OR",
    "sg:tags":[
        "body"
    ],
    "wof:name":"Aurora Auto Works Co",
    "wof:placetype":"venue"
},
  "geometry": {"coordinates":[-122.755967,45.225507],"type":"Point"}
}