{
  "type": "Feature",
  "properties": {
    "iso:country":"US",
    "sg:address":"520 SW 6th Ave Ste 1010",
    "sg:city":"Portland",
    "sg:classifiers":[
        {
            "category":"Professional",
            "subcategory":"Lawyer & Legal Services",
            "type":"Services"
        }
    ],
    "sg:phone":"+1 503 546 5504",
    "sg:postcode":"97204",
    "sg:province":"OR",
    "sg:tags":[
        "attorney",
        "law",
        "immigration"
    ],
    "sg:website":"http://portland.citysearch.com/profile/46627458/portland_or/katrina_m_caldwell_esq_.html?publisher=yellowpages&reference_id=1&placement=ypwebsitemip",
    "wof:name":"Katrina M. Caldwell, Esq.",
    "wof:placetype":"venue"
},
  "geometry": {"coordinates":[-122.677916,45.520233],"type":"Point"}
}