{
  "type": "Feature",
  "properties": {
    "iso:country":"US",
    "sg:address":"1339 Pacific Ave",
    "sg:city":"Forest Grove",
    "sg:classifiers":[
        {
            "category":"Building & Trades",
            "subcategory":"Cleaning & Sanitation",
            "type":"Services"
        }
    ],
    "sg:phone":"+1 503 359 2410",
    "sg:postcode":"97116",
    "sg:province":"OR",
    "sg:tags":[
        "maintenance"
    ],
    "wof:name":"ServiceMaster",
    "wof:placetype":"venue"
},
  "geometry": {"coordinates":[-123.123627,45.520069],"type":"Point"}
}