{
  "type": "Feature",
  "properties": {
    "iso:country":"US",
    "sg:address":"1122 NE 122nd Avenue",
    "sg:city":"Portland",
    "sg:classifiers":[
        {
            "category":"Real Estate",
            "subcategory":"Architect",
            "type":"Services"
        }
    ],
    "sg:phone":"+1 503 257 7332",
    "sg:postcode":"97230",
    "sg:province":"OR",
    "wof:name":"Hamblin M Leon",
    "wof:placetype":"venue"
},
  "geometry": {"coordinates":[-122.537672,45.530481],"type":"Point"}
}