{
  "type": "Feature",
  "properties": {
    "iso:country":"US",
    "sg:address":"12447 SW 69th Ave",
    "sg:city":"Portland",
    "sg:classifiers":[
        {
            "category":"Banks & Credit Unions",
            "subcategory":"Bank",
            "type":"Services"
        }
    ],
    "sg:phone":"+1 503 245 5595",
    "sg:postcode":"97223",
    "sg:province":"OR",
    "sg:tags":[
        "bankcards"
    ],
    "wof:name":"Bankcard",
    "wof:placetype":"venue"
},
  "geometry": {"coordinates":[-122.747884,45.430938],"type":"Point"}
}