{
  "type": "Feature",
  "properties": {
    "iso:country":"US",
    "sg:address":"9570 SW Beaverton-Hillsdale Hwy",
    "sg:city":"Beaverton",
    "sg:classifiers":[
        {
            "category":"Travel",
            "subcategory":"Hotels & Motels",
            "type":"Entertainment"
        }
    ],
    "sg:phone":"+1 503 626 9990",
    "sg:postcode":"97005",
    "sg:province":"OR",
    "wof:name":"Lockhart Investments",
    "wof:placetype":"venue"
},
  "geometry": {"coordinates":[-122.775132,45.486427],"type":"Point"}
}