{
  "type": "Feature",
  "properties": {
    "iso:country":"US",
    "sg:address":"12702 NE Marx St",
    "sg:city":"Portland",
    "sg:classifiers":[
        {
            "category":"Wholesale",
            "subcategory":"Medical Equipment & Supplies",
            "type":"Manufacturing & Wholesale Goods"
        }
    ],
    "sg:phone":"+1 503 252 9777",
    "sg:postcode":"97230",
    "sg:province":"OR",
    "sg:tags":[
        "repair"
    ],
    "wof:name":"Burkhart Dental Supply Co",
    "wof:placetype":"venue"
},
  "geometry": {"coordinates":[-122.53618,45.559161],"type":"Point"}
}