{
  "type": "Feature",
  "properties": {
    "iso:country":"US",
    "sg:address":"5670 SW Erickson Ave",
    "sg:city":"Beaverton",
    "sg:classifiers":[
        {
            "category":"Real Estate",
            "subcategory":"Real Estate Operator",
            "type":"Services"
        }
    ],
    "sg:phone":"+1 503 469 9750",
    "sg:postcode":"97005",
    "sg:province":"OR",
    "sg:tags":[
        "building",
        "apartment"
    ],
    "wof:name":"Erickson Place Apartments",
    "wof:placetype":"venue"
},
  "geometry": {"coordinates":[-122.81192299999999,45.478816],"type":"Point"}
}