{
  "type": "Feature",
  "properties": {
    "addr:full":"7680 SW 92nd Pl Portland OR 97223",
    "addr:housenumber":"7680",
    "addr:postcode":"97223",
    "addr:street":"Sw 92Nd Pl",
    "iso:country":"US",
    "sg:address":"7680 SW 92nd Pl",
    "sg:city":"Portland",
    "sg:classifiers":[
        {
            "category":"Professional",
            "subcategory":"Advertising",
            "type":"Services"
        }
    ],
    "sg:phone":"+1 503 293 0860",
    "sg:postcode":"97223",
    "sg:province":"OR",
    "sg:tags":[
        "agency"
    ],
    "wof:name":"Adrinaline Avanue",
    "wof:placetype":"venue"
},
  "geometry": {"coordinates":[-122.771345,45.465244],"type":"Point"}
}