{
  "type": "Feature",
  "properties": {
    "iso:country":"US",
    "sg:address":"4742 N Syracuse St",
    "sg:city":"Portland",
    "sg:classifiers":[
        {
            "category":"Building & Trades",
            "subcategory":"Construction",
            "type":"Services"
        }
    ],
    "sg:phone":"+1 503 286 2540",
    "sg:postcode":"97203",
    "sg:province":"OR",
    "sg:tags":[
        "concrete",
        "cutting",
        "breaking",
        "sawing"
    ],
    "wof:name":"Malone Concrete",
    "wof:placetype":"venue"
},
  "geometry": {"coordinates":[-122.719735,45.577442],"type":"Point"}
}