{
  "type": "Feature",
  "properties": {
    "addr:full":"1003 Valley River Way Eugene OR 97401",
    "addr:housenumber":"1003",
    "addr:postcode":"97401",
    "addr:street":"Valley River Way",
    "iso:country":"US",
    "sg:address":"1003 Valley River Way",
    "sg:city":"Eugene",
    "sg:classifiers":[
        {
            "category":"Restaurant",
            "type":"Food & Drink"
        }
    ],
    "sg:menulink":"http://www.allmenus.com/or/eugene-springfield/19965-el-torito/menu/",
    "sg:phone":"+1 541 683 7294",
    "sg:postcode":"97401",
    "sg:province":"OR",
    "sg:tags":[
        "mexican"
    ],
    "wof:name":"El Torito",
    "wof:placetype":"venue"
},
  "geometry": {"coordinates":[-123.10362499999999,44.070048],"type":"Point"}
}