{
  "type": "Feature",
  "properties": {
    "iso:country":"US",
    "sg:address":"515 NW Saltzman Road",
    "sg:city":"Portland",
    "sg:classifiers":[
        {
            "category":"Professional",
            "subcategory":"Lawyer & Legal Services",
            "type":"Services"
        }
    ],
    "sg:phone":"+1 503 644 8504",
    "sg:postcode":"97229",
    "sg:province":"OR",
    "sg:tags":[
        "notary"
    ],
    "wof:name":"Mailboxes & More",
    "wof:placetype":"venue"
},
  "geometry": {"coordinates":[-122.806264,45.524284],"type":"Point"}
}