{
  "type": "Feature",
  "properties": {
    "iso:country":"US",
    "sg:address":"3201 19th Ave",
    "sg:city":"Forest Grove",
    "sg:classifiers":[
        {
            "category":"Health Services",
            "subcategory":"Doctor",
            "type":"Services"
        }
    ],
    "sg:phone":"+1 503 359 6153",
    "sg:postcode":"97116",
    "sg:province":"OR",
    "sg:tags":[
        "medical"
    ],
    "wof:name":"Forrest E Bump MD",
    "wof:placetype":"venue"
},
  "geometry": {"coordinates":[-123.08990900000001,45.518288],"type":"Point"}
}