{
  "type": "Feature",
  "properties": {
    "iso:country":"US",
    "sg:address":"2441 NW Eleven Mile Ave",
    "sg:city":"Gresham",
    "sg:classifiers":[
        {
            "category":"Manufacturing",
            "subcategory":"Tools & Machinery",
            "type":"Manufacturing & Wholesale Goods"
        }
    ],
    "sg:phone":"+1 503 666 3510",
    "sg:postcode":"97030",
    "sg:province":"OR",
    "sg:tags":[
        "machine",
        "shop",
        "parts",
        "aerospace",
        "specializing"
    ],
    "wof:name":"Pro-Met Machining Inc",
    "wof:placetype":"venue"
},
  "geometry": {"coordinates":[-122.458444,45.51031],"type":"Point"}
}