{
  "type": "Feature",
  "properties": {
    "iso:country":"US",
    "sg:address":"5825 SW Arctic Dr",
    "sg:city":"Beaverton",
    "sg:classifiers":[
        {
            "category":"Wholesale",
            "subcategory":"Wine & Distilled Alcoholic Beverages",
            "type":"Manufacturing & Wholesale Goods"
        },
        {
            "category":"Manufacturing",
            "subcategory":"Food",
            "type":"Manufacturing & Wholesale Goods"
        }
    ],
    "sg:phone":"+1 503 646 7500",
    "sg:postcode":"97005",
    "sg:province":"OR",
    "sg:tags":[
        "mfg"
    ],
    "wof:name":"Valley Wine Company",
    "wof:placetype":"venue"
},
  "geometry": {"coordinates":[-122.778758,45.476684],"type":"Point"}
}