{
  "type": "Feature",
  "properties": {
    "iso:country":"US",
    "sg:address":"809 S McLoughlin Blvd",
    "sg:city":"Oregon City",
    "sg:classifiers":[
        {
            "category":"Wholesale",
            "subcategory":"Auto Parts",
            "type":"Manufacturing & Wholesale Goods"
        }
    ],
    "sg:phone":"+1 503 722 4157",
    "sg:postcode":"97045",
    "sg:province":"OR",
    "sg:tags":[
        "truck"
    ],
    "wof:name":"Widgets Unlimited",
    "wof:placetype":"venue"
},
  "geometry": {"coordinates":[-122.62483,45.346582],"type":"Point"}
}