{
  "type": "Feature",
  "properties": {
    "addr:full":"1639 NW Spruce Ave Redmond OR 97756",
    "addr:housenumber":"1639",
    "addr:postcode":"97756",
    "addr:street":"Nw Spruce Ave",
    "iso:country":"US",
    "sg:address":"1639 NW Spruce Ave",
    "sg:city":"Redmond",
    "sg:classifiers":[
        {
            "category":"Building & Trades",
            "subcategory":"Construction",
            "type":"Services"
        }
    ],
    "sg:phone":"+1 541 408 5763",
    "sg:postcode":"97756",
    "sg:province":"OR",
    "sg:tags":[
        "dry wall",
        "contractor"
    ],
    "wof:name":"Fast Patch Drywall Svc",
    "wof:placetype":"venue"
},
  "geometry": {"coordinates":[-121.18452499999999,44.299246],"type":"Point"}
}