{
  "type": "Feature",
  "properties": {
    "iso:country":"US",
    "sg:address":"2927 Applewood Ln",
    "sg:city":"Eugene",
    "sg:classifiers":[
        {
            "category":"Shopping",
            "subcategory":"Hobbies, Toys, & Games",
            "type":"Retail Goods"
        }
    ],
    "sg:phone":"+1 541 342 8494",
    "sg:postcode":"97408",
    "sg:province":"OR",
    "sg:tags":[
        "craft"
    ],
    "wof:name":"Ring Around The Roses",
    "wof:placetype":"venue"
},
  "geometry": {"coordinates":[-123.092337,44.095548],"type":"Point"}
}