{
  "type": "Feature",
  "properties": {
    "addr:full":"888 NW Hill St Bend OR 97701",
    "addr:housenumber":"888",
    "addr:postcode":"97701",
    "addr:street":"Nw Hill St",
    "iso:country":"US",
    "sg:address":"888 NW Hill St",
    "sg:city":"Bend",
    "sg:classifiers":[
        {
            "category":"Manufacturing",
            "subcategory":"Jewelry",
            "type":"Manufacturing & Wholesale Goods"
        }
    ],
    "sg:phone":"+1 541 382 2532",
    "sg:postcode":"97701",
    "sg:province":"OR",
    "sg:tags":[
        "mfg"
    ],
    "wof:name":"Nichols Roger Jewelry",
    "wof:placetype":"venue"
},
  "geometry": {"coordinates":[-121.308697,44.058051],"type":"Point"}
}