{
  "type": "Feature",
  "properties": {
    "addr:full":"2850 SW Cedar Hills Blvd #217 Beaverton OR 97005",
    "addr:housenumber":"2850",
    "addr:postcode":"97005",
    "addr:street":"Sw Cedar Hills Blvd # 217",
    "iso:country":"US",
    "sg:address":"2850 SW Cedar Hills Blvd #217",
    "sg:city":"Beaverton",
    "sg:classifiers":[
        {
            "category":"Education",
            "subcategory":"Special Training",
            "type":"Public Place"
        }
    ],
    "sg:phone":"+1 503 928 4529",
    "sg:postcode":"97005",
    "sg:province":"OR",
    "sg:tags":[
        "adult"
    ],
    "sg:website":"createdlife.com",
    "wof:name":"Created Life Strategies LLC",
    "wof:placetype":"venue"
},
  "geometry": {"coordinates":[-122.80701000000001,45.499487],"type":"Point"}
}