{
  "type": "Feature",
  "properties": {
    "addr:full":"1740 Ocean Blvd NW Coos Bay OR 97420",
    "addr:housenumber":"1740",
    "addr:postcode":"97420",
    "addr:street":"Ocean Blvd Nw",
    "iso:country":"US",
    "sg:address":"1740 Ocean Blvd NW",
    "sg:city":"Coos Bay",
    "sg:classifiers":[
        {
            "category":"Freight",
            "type":"Transportation"
        }
    ],
    "sg:phone":"+1 541 888 0482",
    "sg:postcode":"97420",
    "sg:province":"OR",
    "sg:tags":[
        "special"
    ],
    "wof:name":"Abba Storage",
    "wof:placetype":"venue"
},
  "geometry": {"coordinates":[-124.258413,43.387738],"type":"Point"}
}