{
  "type": "Feature",
  "properties": {
    "iso:country":"US",
    "sg:address":"256 E Main St",
    "sg:city":"Hillsboro",
    "sg:classifiers":[
        {
            "category":"Shopping",
            "subcategory":"Shoes",
            "type":"Retail Goods"
        }
    ],
    "sg:phone":"+1 503 640 5866",
    "sg:postcode":"97123",
    "sg:province":"OR",
    "wof:name":"Gimre's Shoe Store",
    "wof:placetype":"venue"
},
  "geometry": {"coordinates":[-122.987003,45.522553],"type":"Point"}
}