{
  "type": "Feature",
  "properties": {
    "iso:country":"US",
    "sg:address":"24370 NE Airport Rd",
    "sg:city":"Aurora",
    "sg:classifiers":[
        {
            "category":"Shopping",
            "type":"Retail Goods"
        }
    ],
    "sg:phone":"+1 503 678 5524",
    "sg:postcode":"97002",
    "sg:province":"OR",
    "sg:tags":[
        "product",
        "metal",
        "fabricated",
        "merchandise",
        "mfg"
    ],
    "wof:name":"National Security Safe NW",
    "wof:placetype":"venue"
},
  "geometry": {"coordinates":[-122.764209,45.272768],"type":"Point"}
}