{
  "type": "Feature",
  "properties": {
    "iso:country":"US",
    "sg:address":"5974 Deer Creek Rd",
    "sg:city":"Selma",
    "sg:classifiers":[
        {
            "category":"Travel",
            "subcategory":"Travel Agent",
            "type":"Entertainment"
        }
    ],
    "sg:phone":"+1 541 597 4507",
    "sg:postcode":"97538",
    "sg:province":"OR",
    "sg:tags":[
        "tours",
        "promoter"
    ],
    "wof:name":"Lake Selmac Outfitters",
    "wof:placetype":"venue"
},
  "geometry": {"coordinates":[-123.485584,42.271243],"type":"Point"}
}