{
  "type": "Feature",
  "properties": {
    "iso:country":"US",
    "sg:address":"1767 12th St",
    "sg:city":"Hood River",
    "sg:classifiers":[
        {
            "category":"Professional",
            "subcategory":"Advertising",
            "type":"Services"
        }
    ],
    "sg:phone":"+1 541 386 7055",
    "sg:postcode":"97031",
    "sg:province":"OR",
    "sg:tags":[
        "mailing",
        "shipping"
    ],
    "wof:name":"UPS Store",
    "wof:placetype":"venue"
},
  "geometry": {"coordinates":[-121.523532,45.695985],"type":"Point"}
}