{
  "type": "Feature",
  "properties": {
    "addr:full":"1506 NE 1st St Bend OR 97701",
    "addr:housenumber":"1506",
    "addr:postcode":"97701",
    "addr:street":"Ne 1St St",
    "iso:country":"US",
    "sg:address":"1506 NE 1st St",
    "sg:city":"Bend",
    "sg:classifiers":[
        {
            "category":"Professional",
            "subcategory":"Engineering",
            "type":"Services"
        }
    ],
    "sg:phone":"+1 541 318 0404",
    "sg:postcode":"97701",
    "sg:province":"OR",
    "sg:tags":[
        "engineer"
    ],
    "wof:name":"CEA Consulting Engineers",
    "wof:placetype":"venue"
},
  "geometry": {"coordinates":[-121.305513,44.065357],"type":"Point"}
}