{
  "type": "Feature",
  "properties": {
    "iso:country":"US",
    "sg:address":"2940 NW Highland Dr",
    "sg:city":"Corvallis",
    "sg:classifiers":[
        {
            "category":"Professional",
            "subcategory":"Computer Services",
            "type":"Services"
        }
    ],
    "sg:phone":"+1 541 738 0879",
    "sg:postcode":"97330",
    "sg:province":"OR",
    "sg:tags":[
        "datum"
    ],
    "wof:name":"Taktos Ltd",
    "wof:placetype":"venue"
},
  "geometry": {"coordinates":[-123.26263899999999,44.596566],"type":"Point"}
}