{
  "type": "Feature",
  "properties": {
    "iso:country":"US",
    "sg:address":"16100 SW 72nd Ave",
    "sg:city":"Portland",
    "sg:classifiers":[
        {
            "category":"Building & Trades",
            "subcategory":"Equipment Rental",
            "type":"Services"
        }
    ],
    "sg:phone":"+1 503 684 6328",
    "sg:postcode":"97223",
    "sg:province":"OR",
    "sg:tags":[
        "terminal",
        "capture",
        "datum",
        "lease"
    ],
    "wof:name":"Verifone Leasing",
    "wof:placetype":"venue"
},
  "geometry": {"coordinates":[-122.74897900000001,45.400523],"type":"Point"}
}