{
  "type": "Feature",
  "properties": {
    "iso:country":"US",
    "sg:address":"1515 W Harvard Ave",
    "sg:city":"Roseburg",
    "sg:classifiers":[
        {
            "category":"Building & Trades",
            "subcategory":"Construction",
            "type":"Services"
        }
    ],
    "sg:phone":"+1 541 673 8022",
    "sg:postcode":"97470",
    "sg:province":"OR",
    "sg:tags":[
        "home",
        "general",
        "family",
        "contractor"
    ],
    "wof:name":"T-Mart",
    "wof:placetype":"venue"
},
  "geometry": {"coordinates":[-123.36631199999999,43.213586],"type":"Point"}
}