{
  "type": "Feature",
  "properties": {
    "iso:country":"US",
    "sg:address":"2023 NW Hoyt Street",
    "sg:city":"Portland",
    "sg:classifiers":[
        {
            "category":"Health Services",
            "subcategory":"Clinic",
            "type":"Services"
        },
        {
            "category":"Organizations",
            "subcategory":"Non-profit Organization",
            "type":"Services"
        }
    ],
    "sg:phone":"+1 503 226 3021",
    "sg:postcode":"97209",
    "sg:province":"OR",
    "sg:tags":[
        "counseling",
        "community",
        "mental",
        "service/non-profit"
    ],
    "sg:website":"www.williamtemple.org",
    "wof:name":"William Temple House",
    "wof:placetype":"venue"
},
  "geometry": {"coordinates":[-122.692938,45.527045],"type":"Point"}
}