{
  "type": "Feature",
  "properties": {
    "iso:country":"US",
    "sg:address":"8205 Tippin Rd",
    "sg:city":"Tillamook",
    "sg:classifiers":[
        {
            "category":"Freight",
            "type":"Transportation"
        }
    ],
    "sg:phone":"+1 503 842 2877",
    "sg:postcode":"97141",
    "sg:province":"OR",
    "sg:tags":[
        "operator",
        "trucking"
    ],
    "wof:name":"Kenneth L Hale",
    "wof:placetype":"venue"
},
  "geometry": {"coordinates":[-123.779923,45.437348],"type":"Point"}
}