{
  "type": "Feature",
  "properties": {
    "iso:country":"US",
    "sg:address":"10931 Martin Ln NE",
    "sg:city":"Aurora",
    "sg:classifiers":[
        {
            "category":"Farming",
            "subcategory":"Farm",
            "type":"Manufacturing & Wholesale Goods"
        }
    ],
    "sg:phone":"+1 503 678 5444",
    "sg:postcode":"97002",
    "sg:province":"OR",
    "sg:tags":[
        "crop",
        "general"
    ],
    "wof:name":"Sequoia Farm LLC",
    "wof:placetype":"venue"
},
  "geometry": {"coordinates":[-122.83810800000001,45.264466],"type":"Point"}
}