{
  "type": "Feature",
  "properties": {
    "iso:country":"US",
    "sg:address":"15850 Nw Central Dr",
    "sg:city":"Portland",
    "sg:classifiers":[
        {
            "category":"Personal",
            "subcategory":"Massage",
            "type":"Services"
        }
    ],
    "sg:phone":"+1 503 431 1414",
    "sg:postcode":"97229",
    "sg:province":"OR",
    "wof:name":"Ai Zen at Bethany Village",
    "wof:placetype":"venue"
},
  "geometry": {"coordinates":[-122.840739,45.555034],"type":"Point"}
}