{
  "type": "Feature",
  "properties": {
    "iso:country":"US",
    "sg:address":"715 NE 16th Ave",
    "sg:city":"Canby",
    "sg:classifiers":[
        {
            "category":"Professional",
            "subcategory":"Accounting & Tax Preparation",
            "type":"Services"
        }
    ],
    "sg:phone":"+1 503 263 6540",
    "sg:postcode":"97013",
    "sg:province":"OR",
    "sg:tags":[
        "bookkeeping",
        "general"
    ],
    "wof:name":"Shamrock Bookkeeping & Acctg",
    "wof:placetype":"venue"
},
  "geometry": {"coordinates":[-122.684398,45.275281],"type":"Point"}
}