{
  "type": "Feature",
  "properties": {
    "iso:country":"US",
    "sg:address":"4170 Cordon Rd NE",
    "sg:city":"Salem",
    "sg:classifiers":[
        {
            "category":"Building & Trades",
            "subcategory":"Landscaping Services",
            "type":"Services"
        }
    ],
    "sg:phone":"+1 503 364 1642",
    "sg:postcode":"97305",
    "sg:province":"OR",
    "sg:tags":[
        "operator",
        "trucking"
    ],
    "wof:name":"Caudles Tree Service",
    "wof:placetype":"venue"
},
  "geometry": {"coordinates":[-122.957067,44.977491],"type":"Point"}
}