{
  "type": "Feature",
  "properties": {
    "iso:country":"US",
    "sg:address":"2632 E 12th St",
    "sg:city":"The Dalles",
    "sg:classifiers":[
        {
            "category":"Building & Trades",
            "subcategory":"Equipment Rental",
            "type":"Services"
        }
    ],
    "sg:phone":"+1 541 993 0228",
    "sg:postcode":"97058",
    "sg:province":"OR",
    "sg:tags":[
        "heavy",
        "broker"
    ],
    "wof:name":"Oregon Heavy Equipment",
    "wof:placetype":"venue"
},
  "geometry": {"coordinates":[-121.152922,45.593344],"type":"Point"}
}