{
  "type": "Feature",
  "properties": {
    "iso:country":"US",
    "sg:address":"2339 SE 92nd Ave",
    "sg:city":"Portland",
    "sg:classifiers":[
        {
            "category":"Social Services",
            "subcategory":"Child Care",
            "type":"Services"
        }
    ],
    "sg:phone":"+1 503 774 4610",
    "sg:postcode":"97216",
    "sg:province":"OR",
    "wof:name":"Marys Daycare",
    "wof:placetype":"venue"
},
  "geometry": {"coordinates":[-122.568979,45.506874],"type":"Point"}
}