{
  "type": "Feature",
  "properties": {
    "iso:country":"US",
    "sg:address":"231 71st St",
    "sg:city":"Springfield",
    "sg:classifiers":[
        {
            "category":"Autos & Motor Vehicles",
            "subcategory":"Auto Supplies",
            "type":"Retail Goods"
        }
    ],
    "sg:phone":"+1 541 746 5761",
    "sg:postcode":"97478",
    "sg:province":"OR",
    "sg:tags":[
        "forklift"
    ],
    "wof:name":"McKenzie Forklift",
    "wof:placetype":"venue"
},
  "geometry": {"coordinates":[-122.90071,44.046998],"type":"Point"}
}