{
  "type": "Feature",
  "properties": {
    "iso:country":"US",
    "sg:address":"12941 SE Foster Rd",
    "sg:city":"Portland",
    "sg:classifiers":[
        {
            "category":"Real Estate",
            "subcategory":"Real Estate Operator",
            "type":"Services"
        }
    ],
    "sg:phone":"+1 503 762 4559",
    "sg:postcode":"97236",
    "sg:province":"OR",
    "sg:tags":[
        "apartment"
    ],
    "wof:name":"Silver Bells Apts",
    "wof:placetype":"venue"
},
  "geometry": {"coordinates":[-122.530225,45.476881],"type":"Point"}
}