{
  "type": "Feature",
  "properties": {
    "iso:country":"US",
    "sg:address":"642 NW Colorado Ave",
    "sg:city":"Bend",
    "sg:classifiers":[
        {
            "category":"Travel",
            "subcategory":"Hotels & Motels",
            "type":"Entertainment"
        }
    ],
    "sg:phone":"+1 541 389 9198",
    "sg:postcode":"97701",
    "sg:province":"OR",
    "sg:tags":[
        "breakfast",
        "operation",
        "bed",
        "accommodation"
    ],
    "wof:name":"Mill Inn Bed and Breakfast",
    "wof:placetype":"venue"
},
  "geometry": {"coordinates":[-121.315767,44.052393],"type":"Point"}
}