{
  "type": "Feature",
  "properties": {
    "iso:country":"US",
    "sg:address":"2348 Colorado St",
    "sg:city":"North Bend",
    "sg:classifiers":[
        {
            "category":"Government",
            "subcategory":"Office",
            "type":"Public Place"
        }
    ],
    "sg:phone":"+1 541 756 3204",
    "sg:postcode":"97459",
    "sg:province":"OR",
    "sg:tags":[
        "federal"
    ],
    "wof:name":"US Transportation Dept",
    "wof:placetype":"venue"
},
  "geometry": {"coordinates":[-124.244186,43.413304],"type":"Point"}
}