{
  "type": "Feature",
  "properties": {
    "iso:country":"US",
    "sg:address":"2143 NE Broadway Street",
    "sg:city":"Portland",
    "sg:classifiers":[
        {
            "category":"Health Services",
            "subcategory":"Health Practitioner",
            "type":"Services"
        }
    ],
    "sg:phone":"+1 503 331 1553",
    "sg:postcode":"97232",
    "sg:province":"OR",
    "sg:tags":[
        "acupuncture"
    ],
    "wof:name":"Dehen Joanna M Lac",
    "wof:placetype":"venue"
},
  "geometry": {"coordinates":[-122.643754,45.535133],"type":"Point"}
}