{
  "type": "Feature",
  "properties": {
    "addr:full":"17268 NE Sacramento St Portland OR 97230",
    "addr:housenumber":"17268",
    "addr:postcode":"97230",
    "addr:street":"Ne Sacramento St",
    "iso:country":"US",
    "sg:address":"17268 NE Sacramento St",
    "sg:city":"Portland",
    "sg:classifiers":[
        {
            "category":"Real Estate",
            "subcategory":"Real Estate Services",
            "type":"Services"
        },
        {
            "category":"Building & Trades",
            "subcategory":"Cleaning & Sanitation",
            "type":"Services"
        }
    ],
    "sg:phone":"+1 503 254 7855",
    "sg:postcode":"97230",
    "sg:province":"OR",
    "sg:tags":[
        "cleaners-interior",
        "cleaning-industrial",
        "janitorial",
        "maintenance",
        "contractor"
    ],
    "sg:website":"http://www.varsitycontractors.com",
    "wof:name":"Varsity Contractors Inc.",
    "wof:placetype":"venue"
},
  "geometry": {"coordinates":[-122.485497,45.54078],"type":"Point"}
}