{
  "type": "Feature",
  "properties": {
    "iso:country":"US",
    "sg:address":"2718 SW Kelly Ave",
    "sg:city":"Portland",
    "sg:classifiers":[
        {
            "category":"Professional",
            "subcategory":"Computer Services",
            "type":"Services"
        }
    ],
    "sg:phone":"+1 503 796 1368",
    "sg:postcode":"97201",
    "sg:province":"OR",
    "sg:tags":[
        "development",
        "software"
    ],
    "wof:name":"Research Software Design",
    "wof:placetype":"venue"
},
  "geometry": {"coordinates":[-122.67679699999999,45.503241],"type":"Point"}
}