{
  "type": "Feature",
  "properties": {
    "addr:full":"12020 SW Barnes Rd Portland OR 97225",
    "addr:housenumber":"12020",
    "addr:postcode":"97225",
    "addr:street":"Sw Barnes Rd",
    "iso:country":"US",
    "sg:address":"12020 SW Barnes Rd",
    "sg:city":"Portland",
    "sg:classifiers":[
        {
            "category":"Manufacturing",
            "subcategory":"Tools & Machinery",
            "type":"Manufacturing & Wholesale Goods"
        }
    ],
    "sg:phone":"+1 503 469 8324",
    "sg:postcode":"97225",
    "sg:province":"OR",
    "sg:tags":[
        "industry",
        "mfg"
    ],
    "wof:name":"N W Water Technology",
    "wof:placetype":"venue"
},
  "geometry": {"coordinates":[-122.799992,45.51871],"type":"Point"}
}