{
  "type": "Feature",
  "properties": {
    "iso:country":"US",
    "sg:address":"91317 Coburg Industrial Way",
    "sg:city":"Coburg",
    "sg:classifiers":[
        {
            "category":"Autos & Motor Vehicles",
            "subcategory":"Automobile Sales",
            "type":"Retail Goods"
        }
    ],
    "sg:phone":"+1 541 686 6060",
    "sg:postcode":"97408",
    "sg:province":"OR",
    "sg:tags":[
        "truck"
    ],
    "wof:name":"TEC Equipment",
    "wof:placetype":"venue"
},
  "geometry": {"coordinates":[-123.057444,44.14771],"type":"Point"}
}