{
  "type": "Feature",
  "properties": {
    "addr:full":"4134 N Kerby Ave Portland OR 97217",
    "addr:housenumber":"4134",
    "addr:postcode":"97217",
    "addr:street":"N Kerby Ave",
    "iso:country":"US",
    "sg:address":"4134 N Kerby Ave",
    "sg:city":"Portland",
    "sg:classifiers":[
        {
            "category":"Professional",
            "subcategory":"Accounting & Tax Preparation",
            "type":"Services"
        }
    ],
    "sg:phone":"+1 503 781 0325",
    "sg:postcode":"97217",
    "sg:province":"OR",
    "sg:tags":[
        "consultation",
        "research"
    ],
    "wof:name":"Mountain Measurement Inc",
    "wof:placetype":"venue"
},
  "geometry": {"coordinates":[-122.672225,45.554367],"type":"Point"}
}