{
  "type": "Feature",
  "properties": {
    "addr:full":"17840 SE Yamhill St Portland OR 97233",
    "addr:postcode":"17840;97233",
    "addr:street":"Se Yamhill St",
    "iso:country":"US",
    "sg:address":"17840 SE Yamhill St",
    "sg:city":"Portland",
    "sg:classifiers":[
        {
            "category":"Building & Trades",
            "subcategory":"Locksmith",
            "type":"Services"
        }
    ],
    "sg:phone":"+1 503 715 3797",
    "sg:postcode":"97233",
    "sg:province":"OR",
    "sg:tags":[
        "key"
    ],
    "wof:name":"111 Locksmith",
    "wof:placetype":"venue"
},
  "geometry": {"coordinates":[-122.47971800000001,45.515383],"type":"Point"}
}