{
  "type": "Feature",
  "properties": {
    "addr:full":"4746 Amherst Ct Lake Oswego OR 97035",
    "addr:housenumber":"4746",
    "addr:postcode":"97035",
    "addr:street":"Amherst Ct",
    "iso:country":"US",
    "sg:address":"4746 Amherst Ct",
    "sg:city":"Lake Oswego",
    "sg:classifiers":[
        {
            "category":"Real Estate",
            "subcategory":"Real Estate Agent",
            "type":"Services"
        }
    ],
    "sg:phone":"+1 503 638 8907",
    "sg:postcode":"97035",
    "sg:province":"OR",
    "wof:name":"Lynn Murray Lee Real Estate",
    "wof:placetype":"venue"
},
  "geometry": {"coordinates":[-122.7252,45.426392],"type":"Point"}
}