{
  "type": "Feature",
  "properties": {
    "iso:country":"US",
    "sg:address":"20130 SW Finnigan Hill Rd",
    "sg:city":"Hillsboro",
    "sg:classifiers":[
        {
            "category":"Freight",
            "type":"Transportation"
        }
    ],
    "sg:phone":"+1 503 538 5142",
    "sg:postcode":"97123",
    "sg:province":"OR",
    "sg:tags":[
        "operator",
        "local",
        "trucking"
    ],
    "wof:name":"Michael Mishler Trucking",
    "wof:placetype":"venue"
},
  "geometry": {"coordinates":[-123.029938,45.37702],"type":"Point"}
}