{
  "type": "Feature",
  "properties": {
    "addr:full":"4747 Lancaster Dr NE Salem OR 97305",
    "addr:housenumber":"4747",
    "addr:postcode":"97305",
    "addr:street":"Lancaster Dr Ne",
    "iso:country":"US",
    "sg:address":"4747 Lancaster Dr NE",
    "sg:city":"Salem",
    "sg:classifiers":[
        {
            "category":"Home & Garden",
            "subcategory":"Mobile Homes",
            "type":"Retail Goods"
        },
        {
            "category":"Building & Trades",
            "subcategory":"Construction",
            "type":"Services"
        }
    ],
    "sg:phone":"+1 503 393 0169",
    "sg:postcode":"97305",
    "sg:province":"OR",
    "sg:tags":[
        "residential",
        "parts"
    ],
    "wof:name":"Marquez Axle",
    "wof:placetype":"venue"
},
  "geometry": {"coordinates":[-122.983088,44.992335],"type":"Point"}
}