{
  "type": "Feature",
  "properties": {
    "addr:full":"1310 Leo St NE Salem OR 97303",
    "addr:housenumber":"1310",
    "addr:postcode":"97303",
    "addr:street":"Leo St Ne",
    "iso:country":"US",
    "sg:address":"1310 Leo St NE",
    "sg:city":"Salem",
    "sg:classifiers":[
        {
            "category":"Building & Trades",
            "subcategory":"Construction",
            "type":"Services"
        }
    ],
    "sg:phone":"+1 503 588 9899",
    "sg:postcode":"97303",
    "sg:province":"OR",
    "sg:tags":[
        "house"
    ],
    "wof:name":"Principle Homes LLC",
    "wof:placetype":"venue"
},
  "geometry": {"coordinates":[-123.021064,44.98591],"type":"Point"}
}