{
  "type": "Feature",
  "properties": {
    "addr:full":"3644 SW Troy St Portland OR 97219",
    "addr:housenumber":"3644",
    "addr:postcode":"97219",
    "addr:street":"Sw Troy St",
    "iso:country":"US",
    "sg:address":"3644 SW Troy St",
    "sg:city":"Portland",
    "sg:classifiers":[
        {
            "category":"Wholesale",
            "subcategory":"Electrical",
            "type":"Manufacturing & Wholesale Goods"
        }
    ],
    "sg:phone":"+1 503 246 3390",
    "sg:postcode":"97219",
    "sg:province":"OR",
    "sg:tags":[
        "equipment",
        "electric",
        "supply"
    ],
    "wof:name":"Suma Electric Supply",
    "wof:placetype":"venue"
},
  "geometry": {"coordinates":[-122.71499799999999,45.468179],"type":"Point"}
}