{
  "type": "Feature",
  "properties": {
    "iso:country":"US",
    "sg:address":"7409 SW Capitol Hwy",
    "sg:city":"Portland",
    "sg:classifiers":[
        {
            "category":"Social Services",
            "type":"Services"
        }
    ],
    "sg:phone":"+1 503 452 5058",
    "sg:postcode":"97219",
    "sg:province":"OR",
    "sg:tags":[
        "counselor",
        "marriage",
        "family"
    ],
    "wof:name":"Jody Swisher Lcsw",
    "wof:placetype":"venue"
},
  "geometry": {"coordinates":[-122.70777,45.470718],"type":"Point"}
}