{
  "type": "Feature",
  "properties": {
    "iso:country":"US",
    "sg:address":"25117 SE Stark St",
    "sg:city":"Troutdale",
    "sg:classifiers":[
        {
            "category":"Banks & Credit Unions",
            "subcategory":"Bank",
            "type":"Services"
        }
    ],
    "sg:phone":"+1 503 405 9940",
    "sg:postcode":"97060",
    "sg:province":"OR",
    "sg:tags":[
        "saving",
        "commercial"
    ],
    "sg:website":"http://www.key.com",
    "wof:name":"Troutdale Key Bank",
    "wof:placetype":"venue"
},
  "geometry": {"coordinates":[-122.404662,45.519051],"type":"Point"}
}