{
  "type": "Feature",
  "properties": {
    "iso:country":"US",
    "sg:address":"12881 SE Kronan Dr",
    "sg:city":"Clackamas",
    "sg:classifiers":[
        {
            "category":"Building & Trades",
            "subcategory":"Landscaping Services",
            "type":"Services"
        }
    ],
    "sg:phone":"+1 503 698 4455",
    "sg:postcode":"97015",
    "sg:province":"OR",
    "sg:tags":[
        "landscape"
    ],
    "wof:name":"Brian Shannon Landscape",
    "wof:placetype":"venue"
},
  "geometry": {"coordinates":[-122.53085799999999,45.413496],"type":"Point"}
}