{
  "type": "Feature",
  "properties": {
    "iso:country":"US",
    "sg:address":"256 SE Stephens St",
    "sg:city":"Roseburg",
    "sg:classifiers":[
        {
            "category":"Organizations",
            "subcategory":"Non-profit Organization",
            "type":"Services"
        }
    ],
    "sg:phone":"+1 541 957 5646",
    "sg:postcode":"97470",
    "sg:province":"OR",
    "sg:tags":[
        "information",
        "abuse",
        "treatment",
        "child"
    ],
    "wof:name":"Douglas Cares Unit",
    "wof:placetype":"venue"
},
  "geometry": {"coordinates":[-123.343974,43.212306],"type":"Point"}
}