{
  "type": "Feature",
  "properties": {
    "addr:full":"10005 Wells Landing Rd Independence OR 97351",
    "addr:housenumber":"10005",
    "addr:postcode":"97351",
    "addr:street":"Wells Landing Rd",
    "iso:country":"US",
    "sg:address":"10005 Wells Landing Rd",
    "sg:city":"Independence",
    "sg:classifiers":[
        {
            "category":"Building & Trades",
            "subcategory":"Construction",
            "type":"Services"
        }
    ],
    "sg:phone":"+1 503 838 3169",
    "sg:postcode":"97351",
    "sg:province":"OR",
    "sg:tags":[
        "carpenter"
    ],
    "wof:name":"Mark Prescott",
    "wof:placetype":"venue"
},
  "geometry": {"coordinates":[-123.133087,44.789749],"type":"Point"}
}