{
  "type": "Feature",
  "properties": {
    "iso:country":"US",
    "sg:address":"4640 SW MacAdam Avenue Suite 200",
    "sg:city":"Portland",
    "sg:classifiers":[
        {
            "category":"Professional",
            "subcategory":"Lawyer & Legal Services",
            "type":"Services"
        }
    ],
    "sg:phone":"+1 503 226 2966",
    "sg:postcode":"97239",
    "sg:province":"OR",
    "wof:name":"Gregory Betsy Attys",
    "wof:placetype":"venue"
},
  "geometry": {"coordinates":[-122.673666,45.489791],"type":"Point"}
}