{
  "type": "Feature",
  "properties": {
    "iso:country":"US",
    "sg:address":"103 High St",
    "sg:city":"Ashland",
    "sg:classifiers":[
        {
            "category":"Professional",
            "subcategory":"Management & Consulting",
            "type":"Services"
        }
    ],
    "sg:phone":"+1 541 482 8610",
    "sg:postcode":"97520",
    "sg:province":"OR",
    "sg:tags":[
        "consultant",
        "business"
    ],
    "wof:name":"Ashland Institute-Strategic",
    "wof:placetype":"venue"
},
  "geometry": {"coordinates":[-122.718326,42.198821],"type":"Point"}
}