{
  "type": "Feature",
  "properties": {
    "iso:country":"US",
    "sg:address":"156 SW Ash St",
    "sg:city":"Dallas",
    "sg:classifiers":[
        {
            "category":"Retail",
            "subcategory":"Auto Repair",
            "type":"Services"
        }
    ],
    "sg:phone":"+1 503 831 1655",
    "sg:postcode":"97338",
    "sg:province":"OR",
    "sg:tags":[
        "body",
        "automobile",
        "painting"
    ],
    "wof:name":"Ash Street Auto Body",
    "wof:placetype":"venue"
},
  "geometry": {"coordinates":[-123.316925,44.917512],"type":"Point"}
}