{
  "type": "Feature",
  "properties": {
    "iso:country":"US",
    "sg:address":"1186 N Pacific Hwy",
    "sg:city":"Woodburn",
    "sg:classifiers":[
        {
            "category":"Restaurant",
            "type":"Food & Drink"
        }
    ],
    "sg:phone":"+1 503 981 2100",
    "sg:postcode":"97071",
    "sg:province":"OR",
    "sg:tags":[
        "eating"
    ],
    "wof:name":"Gina's Restaurant",
    "wof:placetype":"venue"
},
  "geometry": {"coordinates":[-122.836271,45.145436],"type":"Point"}
}