{
  "type": "Feature",
  "properties": {
    "addr:full":"1502 NW 19th Ave Portland OR 97209",
    "addr:housenumber":"1502",
    "addr:postcode":"97209",
    "addr:street":"Nw 19Th Ave",
    "iso:country":"US",
    "sg:address":"1502 NW 19th Ave",
    "sg:city":"Portland",
    "sg:classifiers":[
        {
            "category":"Building & Trades",
            "subcategory":"Locksmith",
            "type":"Services"
        }
    ],
    "sg:phone":"+1 503 715 1799",
    "sg:postcode":"97209",
    "sg:province":"OR",
    "sg:tags":[
        "lock",
        "industrial",
        "locksmiths-commercial"
    ],
    "wof:name":"000 A Locksmith Service",
    "wof:placetype":"venue"
},
  "geometry": {"coordinates":[-122.690613,45.533515],"type":"Point"}
}