{
  "type": "Feature",
  "properties": {
    "iso:country":"US",
    "sg:address":"5215 SE Duke St",
    "sg:city":"Portland",
    "sg:classifiers":[
        {
            "category":"Banks & Credit Unions",
            "subcategory":"Bank",
            "type":"Services"
        }
    ],
    "sg:phone":"+1 503 788 0992",
    "sg:postcode":"97206",
    "sg:province":"OR",
    "sg:tags":[
        "trade",
        "barter",
        "exchange"
    ],
    "wof:name":"Time Traders",
    "wof:placetype":"venue"
},
  "geometry": {"coordinates":[-122.60865699999999,45.475819],"type":"Point"}
}