{
  "type": "Feature",
  "properties": {
    "iso:country":"US",
    "sg:address":"76478 Ash St",
    "sg:city":"Oakridge",
    "sg:classifiers":[
        {
            "category":"Retail",
            "subcategory":"Funeral Services",
            "type":"Services"
        }
    ],
    "sg:phone":"+1 541 782 4328",
    "sg:postcode":"97463",
    "sg:province":"OR",
    "sg:tags":[
        "director"
    ],
    "wof:name":"Oakridge Chapel Of The Woods",
    "wof:placetype":"venue"
},
  "geometry": {"coordinates":[-122.457262,43.747713],"type":"Point"}
}