{
  "type": "Feature",
  "properties": {
    "iso:country":"US",
    "sg:address":"700 NE 87th Ave",
    "sg:city":"Portland",
    "sg:classifiers":[
        {
            "category":"Health Services",
            "subcategory":"Doctor",
            "type":"Services"
        }
    ],
    "sg:phone":"+1 503 289 4353",
    "sg:postcode":"97220",
    "sg:province":"OR",
    "sg:tags":[
        "clinic"
    ],
    "sg:website":"www.thevancouverclinic.com",
    "wof:name":"Vancouver Clinic Inc Ps",
    "wof:placetype":"venue"
},
  "geometry": {"coordinates":[-122.573601,45.530173],"type":"Point"}
}