{
  "type": "Feature",
  "properties": {
    "addr:full":"633 NW 23rd Ave Portland OR 97210",
    "addr:housenumber":"633",
    "addr:postcode":"97210",
    "addr:street":"Nw 23Rd Ave",
    "iso:country":"US",
    "sg:address":"633 NW 23rd Ave",
    "sg:city":"Portland",
    "sg:classifiers":[
        {
            "category":"Shopping",
            "subcategory":"Shoes",
            "type":"Retail Goods"
        }
    ],
    "sg:phone":"+1 503 226 0363",
    "sg:postcode":"97210",
    "sg:province":"OR",
    "sg:tags":[
        "store"
    ],
    "wof:name":"Zelda's Shoe Bar",
    "wof:placetype":"venue"
},
  "geometry": {"coordinates":[-122.69899700000001,45.5275],"type":"Point"}
}