{
  "type": "Feature",
  "properties": {
    "addr:full":"600 Airport Rd Medford OR 97504",
    "addr:housenumber":"600",
    "addr:postcode":"97504",
    "addr:street":"Airport Rd",
    "iso:country":"US",
    "sg:address":"600 Airport Rd",
    "sg:city":"Medford",
    "sg:classifiers":[
        {
            "category":"Professional",
            "type":"Services"
        }
    ],
    "sg:phone":"+1 541 773 3123",
    "sg:postcode":"97504",
    "sg:province":"OR",
    "sg:tags":[
        "establishment"
    ],
    "wof:name":"Mega Pacific",
    "wof:placetype":"venue"
},
  "geometry": {"coordinates":[-122.88517899999999,42.370148],"type":"Point"}
}