{
  "type": "Feature",
  "properties": {
    "iso:country":"US",
    "sg:address":"9364 SW Washington Square Road",
    "sg:city":"Portland",
    "sg:classifiers":[
        {
            "category":"Shopping",
            "subcategory":"Optician",
            "type":"Retail Goods"
        }
    ],
    "sg:phone":"+1 503 968 2802",
    "sg:postcode":"97223",
    "sg:province":"OR",
    "sg:tags":[
        "eyewear"
    ],
    "wof:name":"Occhiali Da Soles",
    "wof:placetype":"venue"
},
  "geometry": {"coordinates":[-122.783671,45.450492],"type":"Point"}
}