{
  "type": "Feature",
  "properties": {
    "iso:country":"US",
    "sg:address":"212 Kings Way",
    "sg:city":"Central Point",
    "sg:classifiers":[
        {
            "category":"Wholesale",
            "subcategory":"Apparel",
            "type":"Manufacturing & Wholesale Goods"
        }
    ],
    "sg:phone":"+1 541 664 6881",
    "sg:postcode":"97502",
    "sg:province":"OR",
    "sg:tags":[
        "clothing"
    ],
    "wof:name":"Sisters Boutique",
    "wof:placetype":"venue"
},
  "geometry": {"coordinates":[-122.923807,42.382341],"type":"Point"}
}