{
  "type": "Feature",
  "properties": {
    "iso:country":"US",
    "sg:address":"1001 SW 5th Avenue Suite 1300",
    "sg:city":"Portland",
    "sg:classifiers":[
        {
            "category":"Professional",
            "subcategory":"Lawyer & Legal Services",
            "type":"Services"
        }
    ],
    "sg:phone":"+1 503 220 1604",
    "sg:postcode":"97204",
    "sg:province":"OR",
    "wof:name":"Law Offices of G Phillips-Cox and Assoicates",
    "wof:placetype":"venue"
},
  "geometry": {"coordinates":[-122.678684,45.516817],"type":"Point"}
}