{
  "type": "Feature",
  "properties": {
    "addr:full":"88812 Blue Heron Rd Seaside OR 97138",
    "addr:housenumber":"88812",
    "addr:postcode":"97138",
    "addr:street":"Blue Heron Rd",
    "iso:country":"US",
    "sg:address":"88812 Blue Heron Rd",
    "sg:city":"Seaside",
    "sg:classifiers":[
        {
            "category":"Building & Trades",
            "subcategory":"Construction",
            "type":"Services"
        }
    ],
    "sg:phone":"+1 503 738 9547",
    "sg:postcode":"97138",
    "sg:province":"OR",
    "sg:tags":[
        "house"
    ],
    "wof:name":"Seeborg Design & Construction",
    "wof:placetype":"venue"
},
  "geometry": {"coordinates":[-123.91789300000001,46.050332],"type":"Point"}
}