{
  "type": "Feature",
  "properties": {
    "iso:country":"US",
    "sg:address":"14725 S Teasel Creek Rd",
    "sg:city":"Molalla",
    "sg:classifiers":[
        {
            "category":"Building & Trades",
            "subcategory":"Construction",
            "type":"Services"
        }
    ],
    "sg:phone":"+1 503 829 7624",
    "sg:postcode":"97038",
    "sg:province":"OR",
    "sg:tags":[
        "general",
        "contractor"
    ],
    "wof:name":"Carlson Brothers Construction",
    "wof:placetype":"venue"
},
  "geometry": {"coordinates":[-122.56589,45.103524],"type":"Point"}
}