{
  "type": "Feature",
  "properties": {
    "addr:full":"3901 NE Martin Luther King Jr. Blvd Portland OR 97212",
    "addr:housenumber":"3901",
    "addr:postcode":"97212",
    "addr:street":"Ne Martin Luther King Jr. Blvd",
    "iso:country":"US",
    "sg:address":"3901 NE Martin Luther King Jr. Blvd",
    "sg:city":"Portland",
    "sg:classifiers":[
        {
            "category":"Restaurant",
            "type":"Food & Drink"
        },
        {
            "category":"Food & Beverages",
            "subcategory":"Meat & Fish",
            "type":"Retail Goods"
        }
    ],
    "sg:phone":"+1 503 493 4537",
    "sg:postcode":"97212",
    "sg:province":"OR",
    "sg:tags":[
        "hot",
        "dog"
    ],
    "sg:website":"wayneschicagoredhots.com/",
    "wof:name":"Wayne's Chicago Red Hots",
    "wof:placetype":"venue"
},
  "geometry": {"coordinates":[-122.66162,45.550823],"type":"Point"}
}