{
  "type": "Feature",
  "properties": {
    "iso:country":"US",
    "sg:address":"540 Stables Rd",
    "sg:city":"Reedsport",
    "sg:classifiers":[
        {
            "category":"Building & Trades",
            "subcategory":"Construction",
            "type":"Services"
        }
    ],
    "sg:phone":"+1 541 271 1361",
    "sg:postcode":"97467",
    "sg:province":"OR",
    "sg:tags":[
        "hanging",
        "contractor"
    ],
    "wof:name":"R & N Painting & Repair",
    "wof:placetype":"venue"
},
  "geometry": {"coordinates":[-124.09804800000001,43.719495],"type":"Point"}
}