{
  "type": "Feature",
  "properties": {
    "addr:full":"1930 SE Hawthorne Boulevard Portland OR 97214",
    "addr:housenumber":"1930",
    "addr:postcode":"97214",
    "addr:street":"Se Hawthorne Boulevard",
    "iso:country":"US",
    "sg:address":"1930 SE Hawthorne Boulevard",
    "sg:city":"Portland",
    "sg:classifiers":[
        {
            "category":"Food & Beverages",
            "subcategory":"Groceries & Convenience Stores",
            "type":"Retail Goods"
        }
    ],
    "sg:phone":"+1 503 234 0129",
    "sg:postcode":"97214",
    "sg:province":"OR",
    "wof:name":"Seven-Eleven Food Stores",
    "wof:placetype":"venue"
},
  "geometry": {"coordinates":[-122.645785,45.512067],"type":"Point"}
}