{
  "type": "Feature",
  "properties": {
    "iso:country":"US",
    "sg:address":"14700 SW Murray Scholls Dr Ste 104",
    "sg:city":"Beaverton",
    "sg:classifiers":[
        {
            "category":"Shopping",
            "subcategory":"Pets & Pet Supplies",
            "type":"Retail Goods"
        }
    ],
    "sg:phone":"+1 503 579 2403",
    "sg:postcode":"97007",
    "sg:province":"OR",
    "sg:tags":[
        "store"
    ],
    "sg:website":"www.NaturesPetMarket.com",
    "wof:name":"Nature's Pet",
    "wof:placetype":"venue"
},
  "geometry": {"coordinates":[-122.82786900000001,45.438235],"type":"Point"}
}