{
  "type": "Feature",
  "properties": {
    "iso:country":"US",
    "sg:address":"35641 Shoreview Dr",
    "sg:city":"Dorena",
    "sg:classifiers":[
        {
            "category":"Building & Trades",
            "subcategory":"Plumbing",
            "type":"Services"
        }
    ],
    "sg:phone":"+1 541 767 2855",
    "sg:postcode":"97434",
    "sg:province":"OR",
    "sg:tags":[
        "contractor"
    ],
    "wof:name":"Dean Heating & AC",
    "wof:placetype":"venue"
},
  "geometry": {"coordinates":[-122.937443,43.76968],"type":"Point"}
}