{
  "type": "Feature",
  "properties": {
    "addr:full":"1060 Tangent St Lebanon OR 97355",
    "addr:housenumber":"1060",
    "addr:postcode":"97355",
    "addr:street":"Tangent St",
    "iso:country":"US",
    "sg:address":"1060 Tangent St",
    "sg:city":"Lebanon",
    "sg:classifiers":[
        {
            "category":"Freight",
            "type":"Transportation"
        }
    ],
    "sg:phone":"+1 541 451 1795",
    "sg:postcode":"97355",
    "sg:province":"OR",
    "sg:tags":[
        "trucking"
    ],
    "wof:name":"Pruitt Transfer Inc",
    "wof:placetype":"venue"
},
  "geometry": {"coordinates":[-122.922392,44.544948],"type":"Point"}
}