{
  "type": "Feature",
  "properties": {
    "iso:country":"US",
    "sg:address":"9200 NE Fremont St",
    "sg:city":"Portland",
    "sg:classifiers":[
        {
            "category":"Organizations",
            "subcategory":"Religious Organization",
            "type":"Services"
        }
    ],
    "sg:phone":"+1 503 252 4634",
    "sg:postcode":"97220",
    "sg:province":"OR",
    "wof:name":"Mfi",
    "wof:placetype":"venue"
},
  "geometry": {"coordinates":[-122.56659999999999,45.549315],"type":"Point"}
}