{
  "type": "Feature",
  "properties": {
    "addr:full":"2302 NE 144th Ave Portland OR 97230",
    "addr:housenumber":"2302",
    "addr:postcode":"97230",
    "addr:street":"Ne 144Th Ave",
    "iso:country":"US",
    "sg:address":"2302 NE 144th Ave",
    "sg:city":"Portland",
    "sg:classifiers":[
        {
            "category":"Professional",
            "subcategory":"Management & Consulting",
            "type":"Services"
        }
    ],
    "sg:phone":"+1 503 262 6505",
    "sg:postcode":"97230",
    "sg:province":"OR",
    "sg:tags":[
        "communication",
        "consultant",
        "marketing"
    ],
    "wof:name":"Dornan Communications Inc",
    "wof:placetype":"venue"
},
  "geometry": {"coordinates":[-122.51393,45.53878],"type":"Point"}
}