{
  "type": "Feature",
  "properties": {
    "addr:full":"1173 NE Division St Gresham OR 97030",
    "addr:housenumber":"1173",
    "addr:postcode":"97030",
    "addr:street":"Ne Division St",
    "iso:country":"US",
    "sg:address":"1173 NE Division St",
    "sg:city":"Gresham",
    "sg:classifiers":[
        {
            "category":"Shopping",
            "subcategory":"Tobacco",
            "type":"Retail Goods"
        }
    ],
    "sg:phone":"+1 503 661 2290",
    "sg:postcode":"97030",
    "sg:province":"OR",
    "sg:tags":[
        "cigarette",
        "cigar",
        "dealer"
    ],
    "wof:name":"Tobacco Outlet",
    "wof:placetype":"venue"
},
  "geometry": {"coordinates":[-122.418252,45.504861],"type":"Point"}
}