{
  "type": "Feature",
  "properties": {
    "addr:full":"18200 NW Cornell Rd Beaverton OR 97006",
    "addr:housenumber":"18200",
    "addr:postcode":"97006",
    "addr:street":"Nw Cornell Rd",
    "iso:country":"US",
    "sg:address":"18200 NW Cornell Rd",
    "sg:city":"Beaverton",
    "sg:classifiers":[
        {
            "category":"Real Estate",
            "subcategory":"Real Estate Operator",
            "type":"Services"
        }
    ],
    "sg:phone":"+1 503 645 2640",
    "sg:postcode":"97006",
    "sg:province":"OR",
    "sg:tags":[
        "apartment"
    ],
    "wof:name":"The Lakes Apartments",
    "wof:placetype":"venue"
},
  "geometry": {"coordinates":[-122.864998,45.5341],"type":"Point"}
}