{
  "type": "Feature",
  "properties": {
    "iso:country":"US",
    "sg:address":"2275 SW Eastwood Ave",
    "sg:city":"Gresham",
    "sg:classifiers":[
        {
            "category":"Professional",
            "type":"Services"
        }
    ],
    "sg:phone":"+1 503 256 5591",
    "sg:postcode":"97080",
    "sg:province":"OR",
    "wof:name":"Fit By Monday",
    "wof:placetype":"venue"
},
  "geometry": {"coordinates":[-122.46189,45.480067],"type":"Point"}
}