{
  "type": "Feature",
  "properties": {
    "iso:country":"US",
    "sg:address":"300 E Pine St",
    "sg:city":"Central Point",
    "sg:classifiers":[
        {
            "category":"Banks & Credit Unions",
            "subcategory":"Bank",
            "type":"Services"
        }
    ],
    "sg:phone":"+1 541 665 2201",
    "sg:postcode":"97502",
    "sg:province":"OR",
    "wof:name":"Premierwest Bank",
    "wof:placetype":"venue"
},
  "geometry": {"coordinates":[-122.915001,42.375198],"type":"Point"}
}