{
  "type": "Feature",
  "properties": {
    "iso:country":"US",
    "sg:address":"1134 Moneda Ave N",
    "sg:city":"Salem",
    "sg:classifiers":[
        {
            "category":"Building & Trades",
            "subcategory":"Construction",
            "type":"Services"
        }
    ],
    "sg:phone":"+1 503 390 7607",
    "sg:postcode":"97303",
    "sg:province":"OR",
    "sg:tags":[
        "concrete",
        "contractor"
    ],
    "wof:name":"D & E Flooring Inc",
    "wof:placetype":"venue"
},
  "geometry": {"coordinates":[-123.045115,44.993097],"type":"Point"}
}