{
  "type": "Feature",
  "properties": {
    "addr:full":"1382 Dixie Ln Medford OR 97501",
    "addr:housenumber":"1382",
    "addr:postcode":"97501",
    "addr:street":"Dixie Ln",
    "iso:country":"US",
    "sg:address":"1382 Dixie Ln",
    "sg:city":"Medford",
    "sg:classifiers":[
        {
            "category":"Retail",
            "subcategory":"Car Wash",
            "type":"Services"
        }
    ],
    "sg:phone":"+1 541 779 7987",
    "sg:postcode":"97501",
    "sg:province":"OR",
    "sg:tags":[
        "carwash"
    ],
    "wof:name":"Pressure Washing Unlimited",
    "wof:placetype":"venue"
},
  "geometry": {"coordinates":[-122.8925,42.310427],"type":"Point"}
}