{
  "type": "Feature",
  "properties": {
    "iso:country":"US",
    "sg:address":"257 SW Madison Ave",
    "sg:city":"Corvallis",
    "sg:classifiers":[
        {
            "category":"Social Services",
            "type":"Services"
        }
    ],
    "sg:phone":"+1 541 752 0667",
    "sg:postcode":"97333",
    "sg:province":"OR",
    "sg:tags":[
        "referral"
    ],
    "wof:name":"Linn Benton Lincoln Regl Hsng",
    "wof:placetype":"venue"
},
  "geometry": {"coordinates":[-123.260876,44.563289],"type":"Point"}
}