{
  "type": "Feature",
  "properties": {
    "iso:country":"US",
    "sg:address":"2215 NW Allie Ave",
    "sg:city":"Hillsboro",
    "sg:classifiers":[
        {
            "category":"Restaurant",
            "type":"Food & Drink"
        }
    ],
    "sg:phone":"+1 503 629 1815",
    "sg:postcode":"97124",
    "sg:province":"OR",
    "sg:tags":[
        "japanese"
    ],
    "sg:website":"www.koji.com",
    "wof:name":"Koji Osakaya",
    "wof:placetype":"venue"
},
  "geometry": {"coordinates":[-122.877689,45.536885],"type":"Point"}
}