{
  "type": "Feature",
  "properties": {
    "addr:full":"13800 SE McLoughlin Blvd Portland OR 97222",
    "addr:housenumber":"13800",
    "addr:postcode":"97222",
    "addr:street":"Se Mcloughlin Blvd",
    "iso:country":"US",
    "sg:address":"13800 SE McLoughlin Blvd",
    "sg:city":"Portland",
    "sg:classifiers":[
        {
            "category":"Building & Trades",
            "subcategory":"Locksmith",
            "type":"Services"
        }
    ],
    "sg:phone":"+1 503 715 3739",
    "sg:postcode":"97222",
    "sg:province":"OR",
    "sg:tags":[
        "key"
    ],
    "wof:name":"Always AAA Locksmith",
    "wof:placetype":"venue"
},
  "geometry": {"coordinates":[-122.633377,45.42366],"type":"Point"}
}