{
  "type": "Feature",
  "properties": {
    "iso:country":"US",
    "sg:address":"61232 King Solomon Ln",
    "sg:city":"Bend",
    "sg:classifiers":[
        {
            "category":"Building & Trades",
            "subcategory":"Construction",
            "type":"Services"
        }
    ],
    "sg:phone":"+1 541 389 0062",
    "sg:postcode":"97702",
    "sg:province":"OR",
    "sg:tags":[
        "house"
    ],
    "wof:name":"Reliable Home Repair",
    "wof:placetype":"venue"
},
  "geometry": {"coordinates":[-121.276039,44.024412],"type":"Point"}
}