{
  "type": "Feature",
  "properties": {
    "addr:full":"9980 SE Washington St Portland OR 97216",
    "addr:housenumber":"9980",
    "addr:postcode":"97216",
    "addr:street":"Se Washington St",
    "iso:country":"US",
    "sg:address":"9980 SE Washington St",
    "sg:city":"Portland",
    "sg:classifiers":[
        {
            "category":"Restaurant",
            "type":"Food & Drink"
        }
    ],
    "sg:phone":"+1 503 255 6255",
    "sg:postcode":"97216",
    "sg:province":"OR",
    "sg:tags":[
        "eating"
    ],
    "wof:name":"Subway",
    "wof:placetype":"venue"
},
  "geometry": {"coordinates":[-122.561582,45.518248],"type":"Point"}
}