{
  "type": "Feature",
  "properties": {
    "iso:country":"US",
    "sg:address":"6308 SE Foster Rd",
    "sg:city":"Portland",
    "sg:classifiers":[
        {
            "category":"Manufacturing",
            "subcategory":"Printing",
            "type":"Manufacturing & Wholesale Goods"
        }
    ],
    "sg:phone":"+1 503 775 7707",
    "sg:postcode":"97206",
    "sg:province":"OR",
    "sg:tags":[
        "lithographing",
        "ink"
    ],
    "wof:name":"Quickliner",
    "wof:placetype":"venue"
},
  "geometry": {"coordinates":[-122.597875,45.490114],"type":"Point"}
}