{
  "type": "Feature",
  "properties": {
    "addr:full":"18402 S Holly Ln Oregon City OR 97045",
    "addr:housenumber":"18402",
    "addr:postcode":"97045",
    "addr:street":"S Holly Ln",
    "iso:country":"US",
    "sg:address":"18402 S Holly Ln",
    "sg:city":"Oregon City",
    "sg:classifiers":[
        {
            "category":"Retail",
            "subcategory":"Auto Repair",
            "type":"Services"
        }
    ],
    "sg:phone":"+1 503 656 2010",
    "sg:postcode":"97045",
    "sg:province":"OR",
    "sg:tags":[
        "automotive"
    ],
    "wof:name":"Dales Auto Wrecking",
    "wof:placetype":"venue"
},
  "geometry": {"coordinates":[-122.572157,45.341803],"type":"Point"}
}