{
  "type": "Feature",
  "properties": {
    "iso:country":"US",
    "sg:address":"660 S Main St",
    "sg:city":"Banks",
    "sg:classifiers":[
        {
            "category":"Food & Beverages",
            "subcategory":"Groceries & Convenience Stores",
            "type":"Retail Goods"
        }
    ],
    "sg:phone":"+1 503 324 2171",
    "sg:postcode":"97106",
    "sg:province":"OR",
    "sg:tags":[
        "grocer"
    ],
    "wof:name":"Jim's Sentry Super Market",
    "wof:placetype":"venue"
},
  "geometry": {"coordinates":[-123.114362,45.611292],"type":"Point"}
}