{
  "type": "Feature",
  "properties": {
    "iso:country":"US",
    "sg:address":"4309 Oakridge Rd",
    "sg:city":"Lake Oswego",
    "sg:classifiers":[
        {
            "category":"Health Services",
            "subcategory":"Doctor",
            "type":"Services"
        }
    ],
    "sg:phone":"+1 503 636 9687",
    "sg:postcode":"97035",
    "sg:province":"OR",
    "wof:name":"Pollack Family Investments Llc",
    "wof:placetype":"venue"
},
  "geometry": {"coordinates":[-122.720645,45.410937],"type":"Point"}
}