{
  "type": "Feature",
  "properties": {
    "addr:full":"10075 SW Barbur Blvd Portland OR 97219",
    "addr:housenumber":"10075",
    "addr:postcode":"97219",
    "addr:street":"Sw Barbur Blvd",
    "iso:country":"US",
    "sg:address":"10075 SW Barbur Blvd",
    "sg:city":"Portland",
    "sg:classifiers":[
        {
            "category":"Banks & Credit Unions",
            "subcategory":"Bank",
            "type":"Services"
        }
    ],
    "sg:phone":"+1 503 452 5000",
    "sg:postcode":"97219",
    "sg:province":"OR",
    "sg:tags":[
        "depository",
        "banking",
        "loan"
    ],
    "wof:name":"Anyday's Payday",
    "wof:placetype":"venue"
},
  "geometry": {"coordinates":[-122.72410499999999,45.452506],"type":"Point"}
}