{
  "type": "Feature",
  "properties": {
    "iso:country":"US",
    "sg:address":"602 Colinwood Ct",
    "sg:city":"Medford",
    "sg:classifiers":[
        {
            "category":"Building & Trades",
            "subcategory":"Landscaping Services",
            "type":"Services"
        }
    ],
    "sg:phone":"+1 541 779 0071",
    "sg:postcode":"97501",
    "sg:province":"OR",
    "sg:tags":[
        "landscape",
        "contractor"
    ],
    "wof:name":"Brier Patch",
    "wof:placetype":"venue"
},
  "geometry": {"coordinates":[-122.893644,42.317323],"type":"Point"}
}