{
  "type": "Feature",
  "properties": {
    "iso:country":"US",
    "sg:address":"1680 Irving Rd",
    "sg:city":"Eugene",
    "sg:classifiers":[
        {
            "category":"Manufacturing",
            "subcategory":"Rubber & Plastics",
            "type":"Manufacturing & Wholesale Goods"
        }
    ],
    "sg:phone":"+1 541 461 5000",
    "sg:postcode":"97402",
    "sg:province":"OR",
    "sg:tags":[
        "process",
        "injected",
        "mfg",
        "through",
        "molding"
    ],
    "wof:name":"Paktech",
    "wof:placetype":"venue"
},
  "geometry": {"coordinates":[-123.164652,44.103173],"type":"Point"}
}