{
  "type": "Feature",
  "properties": {
    "iso:country":"US",
    "sg:address":"16629 SE Naegeli Dr",
    "sg:city":"Portland",
    "sg:classifiers":[
        {
            "category":"Organizations",
            "subcategory":"Religious Organization",
            "type":"Services"
        }
    ],
    "sg:phone":"+1 503 236 5911",
    "sg:postcode":"97236",
    "sg:province":"OR",
    "sg:tags":[
        "church"
    ],
    "sg:website":"www.circleoflifechurch.us",
    "wof:name":"Circle Of Life Church",
    "wof:placetype":"venue"
},
  "geometry": {"coordinates":[-122.49228599999999,45.493065],"type":"Point"}
}