{
  "type": "Feature",
  "properties": {
    "addr:full":"1555 NE 3rd St Prineville OR 97754",
    "addr:housenumber":"1555",
    "addr:postcode":"97754",
    "addr:street":"Ne 3Rd St",
    "iso:country":"US",
    "sg:address":"1555 NE 3rd St",
    "sg:city":"Prineville",
    "sg:classifiers":[
        {
            "category":"Recreation",
            "type":"Entertainment"
        }
    ],
    "sg:phone":"+1 541 447 4211",
    "sg:postcode":"97754",
    "sg:province":"OR",
    "sg:tags":[
        "lottery",
        "agent"
    ],
    "wof:name":"Debbie Sue's Deli & Lottery",
    "wof:placetype":"venue"
},
  "geometry": {"coordinates":[-120.829128,44.303014],"type":"Point"}
}