{
  "type": "Feature",
  "properties": {
    "iso:country":"US",
    "sg:address":"307 Main Ave",
    "sg:city":"Tillamook",
    "sg:classifiers":[
        {
            "category":"Shopping",
            "subcategory":"Jewelry",
            "type":"Retail Goods"
        }
    ],
    "sg:phone":"+1 503 842 7940",
    "sg:postcode":"97141",
    "sg:province":"OR",
    "sg:tags":[
        "precious",
        "semi-precious",
        "stone",
        "jeweler"
    ],
    "wof:name":"Art Diamond Jewelers Inc",
    "wof:placetype":"venue"
},
  "geometry": {"coordinates":[-123.843941,45.456275],"type":"Point"}
}