{
  "type": "Feature",
  "properties": {
    "addr:full":"1507 NW 24th Avenue Portland OR 97210",
    "addr:housenumber":"1507",
    "addr:postcode":"97210",
    "addr:street":"Nw 24Th Avenue",
    "iso:country":"US",
    "sg:address":"1507 NW 24th Avenue",
    "sg:city":"Portland",
    "sg:classifiers":[
        {
            "category":"Building & Trades",
            "subcategory":"Construction",
            "type":"Services"
        }
    ],
    "sg:phone":"+1 503 222 1948",
    "sg:postcode":"97210",
    "sg:province":"OR",
    "sg:tags":[
        "interior",
        "design"
    ],
    "wof:name":"Hermanson Design Group",
    "wof:placetype":"venue"
},
  "geometry": {"coordinates":[-122.700772,45.533364],"type":"Point"}
}