{
  "type": "Feature",
  "properties": {
    "iso:country":"US",
    "sg:address":"3387 SE Teal Dr",
    "sg:city":"Gresham",
    "sg:classifiers":[
        {
            "category":"Shopping",
            "subcategory":"Florist",
            "type":"Retail Goods"
        }
    ],
    "sg:phone":"+1 503 516 4207",
    "sg:postcode":"97080",
    "sg:province":"OR",
    "wof:name":"Van K Ngo Flowers",
    "wof:placetype":"venue"
},
  "geometry": {"coordinates":[-122.368627,45.472989],"type":"Point"}
}