{
  "type": "Feature",
  "properties": {
    "iso:country":"US",
    "sg:address":"66281 White Rock Loop",
    "sg:city":"Bend",
    "sg:classifiers":[
        {
            "category":"Building & Trades",
            "subcategory":"Construction",
            "type":"Services"
        }
    ],
    "sg:phone":"+1 541 420 5995",
    "sg:postcode":"97701",
    "sg:province":"OR",
    "sg:tags":[
        "excavation",
        "contractor"
    ],
    "wof:name":"Robert T Seliger Excavation",
    "wof:placetype":"venue"
},
  "geometry": {"coordinates":[-121.307869,44.203333],"type":"Point"}
}