{
  "type": "Feature",
  "properties": {
    "iso:country":"US",
    "sg:address":"500 SE 10th Ave",
    "sg:city":"Hillsboro",
    "sg:classifiers":[
        {
            "category":"Professional",
            "subcategory":"Accounting & Tax Preparation",
            "type":"Services"
        }
    ],
    "sg:phone":"+1 503 640 0851",
    "sg:postcode":"97123",
    "sg:province":"OR",
    "sg:tags":[
        "return",
        "filing"
    ],
    "wof:name":"Jackson Hewitt Tax Svc",
    "wof:placetype":"venue"
},
  "geometry": {"coordinates":[-122.974,45.51676],"type":"Point"}
}