{
  "type": "Feature",
  "properties": {
    "iso:country":"US",
    "sg:address":"4741 Liberty Rd S",
    "sg:city":"Salem",
    "sg:classifiers":[
        {
            "category":"Insurance",
            "subcategory":"Insurance Agent",
            "type":"Services"
        },
        {
            "category":"Insurance",
            "subcategory":"Hazard Insurance",
            "type":"Services"
        }
    ],
    "sg:phone":"+1 503 371 8115",
    "sg:postcode":"97302",
    "sg:province":"OR",
    "sg:tags":[
        "consultant",
        "commercial",
        "analyst",
        "business"
    ],
    "sg:website":"http://www.alliedinsurance.com",
    "wof:name":"Premier Insurance Inc",
    "wof:placetype":"venue"
},
  "geometry": {"coordinates":[-123.060512,44.889778],"type":"Point"}
}