{
  "type": "Feature",
  "properties": {
    "iso:country":"US",
    "sg:address":"1151 May St",
    "sg:city":"Hood River",
    "sg:classifiers":[
        {
            "category":"Health Services",
            "subcategory":"Doctor",
            "type":"Services"
        }
    ],
    "sg:phone":"+1 541 387 6326",
    "sg:postcode":"97031",
    "sg:province":"OR",
    "sg:tags":[
        "physician",
        "surgeon"
    ],
    "wof:name":"Providence Cardiovascular",
    "wof:placetype":"venue"
},
  "geometry": {"coordinates":[-121.52283199999999,45.704031],"type":"Point"}
}