{
  "type": "Feature",
  "properties": {
    "iso:country":"US",
    "sg:address":"1801 NW Upshur St",
    "sg:city":"Portland",
    "sg:classifiers":[
        {
            "category":"Professional",
            "subcategory":"Engineering",
            "type":"Services"
        }
    ],
    "sg:phone":"+1 503 222 3031",
    "sg:postcode":"97209",
    "sg:province":"OR",
    "sg:tags":[
        "engineer"
    ],
    "wof:name":"Gregory Laird & Assoc",
    "wof:placetype":"venue"
},
  "geometry": {"coordinates":[-122.690497,45.536358],"type":"Point"}
}