{
  "type": "Feature",
  "properties": {
    "addr:full":"17270 SE Mcloughlin Blvd Portland OR 97267",
    "addr:housenumber":"17270",
    "addr:postcode":"97267",
    "addr:street":"Se Mcloughlin Blvd",
    "iso:country":"US",
    "sg:address":"17270 SE Mcloughlin Blvd",
    "sg:city":"Portland",
    "sg:classifiers":[
        {
            "category":"Autos & Motor Vehicles",
            "subcategory":"Automobile Sales",
            "type":"Retail Goods"
        },
        {
            "category":"Retail",
            "subcategory":"Auto Rental",
            "type":"Services"
        },
        {
            "category":"Building & Trades",
            "subcategory":"Equipment Rental",
            "type":"Services"
        }
    ],
    "sg:phone":"+1 503 278 4138",
    "sg:postcode":"97267",
    "sg:province":"OR",
    "sg:tags":[
        "truck",
        "used",
        "moving"
    ],
    "sg:website":"http://budgettruck.com/IYP_tl",
    "wof:name":"Autostart Ii DBA/Budget Truck Rental",
    "wof:placetype":"venue"
},
  "geometry": {"coordinates":[-122.617881,45.39773],"type":"Point"}
}