{
  "type": "Feature",
  "properties": {
    "iso:country":"US",
    "sg:address":"107 1st St",
    "sg:city":"Phoenix",
    "sg:classifiers":[
        {
            "category":"Real Estate",
            "subcategory":"Developer",
            "type":"Services"
        }
    ],
    "sg:phone":"+1 541 535 6592",
    "sg:postcode":"97535",
    "sg:province":"OR",
    "wof:name":"Excelsior Development Company",
    "wof:placetype":"venue"
},
  "geometry": {"coordinates":[-122.815459,42.273827],"type":"Point"}
}