{
  "type": "Feature",
  "properties": {
    "addr:full":"529 SW Broadway Portland OR 97205",
    "addr:housenumber":"529",
    "addr:postcode":"97205",
    "addr:street":"Sw Broadway",
    "iso:country":"US",
    "sg:address":"529 SW Broadway",
    "sg:city":"Portland",
    "sg:classifiers":[
        {
            "category":"Shopping",
            "subcategory":"Jewelry",
            "type":"Retail Goods"
        }
    ],
    "sg:phone":"+1 503 295 0705",
    "sg:postcode":"97205",
    "sg:province":"OR",
    "sg:tags":[
        "diamond",
        "jeweler"
    ],
    "sg:website":"www.kassabjewelers.com",
    "wof:name":"Kassab Jewelers",
    "wof:placetype":"venue"
},
  "geometry": {"coordinates":[-122.678856,45.520439],"type":"Point"}
}