{
  "type": "Feature",
  "properties": {
    "iso:country":"US",
    "sg:address":"2210 S Santiam Hwy",
    "sg:city":"Lebanon",
    "sg:classifiers":[
        {
            "category":"Restaurant",
            "type":"Food & Drink"
        }
    ],
    "sg:phone":"+1 541 258 7755",
    "sg:postcode":"97355",
    "sg:province":"OR",
    "sg:tags":[
        "eating"
    ],
    "wof:name":"KFC",
    "wof:placetype":"venue"
},
  "geometry": {"coordinates":[-122.90715299999999,44.524662],"type":"Point"}
}