{
  "type": "Feature",
  "properties": {
    "iso:country":"US",
    "sg:address":"4131 Coal Mine Rd",
    "sg:city":"Medford",
    "sg:classifiers":[
        {
            "category":"Utilities",
            "subcategory":"Telephone",
            "type":"Services"
        }
    ],
    "sg:phone":"+1 541 245 9399",
    "sg:postcode":"97504",
    "sg:province":"OR",
    "sg:tags":[
        "communications"
    ],
    "wof:name":"MCI",
    "wof:placetype":"venue"
},
  "geometry": {"coordinates":[-122.800898,42.307164],"type":"Point"}
}