{
  "type": "Feature",
  "properties": {
    "iso:country":"US",
    "sg:address":"10643 NE Simpson St",
    "sg:city":"Portland",
    "sg:classifiers":[
        {
            "category":"Building & Trades",
            "subcategory":"Plumbing",
            "type":"Services"
        }
    ],
    "sg:phone":"+1 503 656 2632",
    "sg:postcode":"97220",
    "sg:province":"OR",
    "sg:tags":[
        "septic"
    ],
    "wof:name":"Enviroclear",
    "wof:placetype":"venue"
},
  "geometry": {"coordinates":[-122.552043,45.565371],"type":"Point"}
}