{
  "type": "Feature",
  "properties": {
    "iso:country":"US",
    "sg:address":"4204 NE Riverside Ave",
    "sg:city":"Pendleton",
    "sg:classifiers":[
        {
            "category":"Building & Trades",
            "subcategory":"Construction",
            "type":"Services"
        }
    ],
    "sg:phone":"+1 541 276 4683",
    "sg:postcode":"97801",
    "sg:province":"OR",
    "sg:tags":[
        "contractor"
    ],
    "wof:name":"Mac & Jack Construction",
    "wof:placetype":"venue"
},
  "geometry": {"coordinates":[-118.74121100000001,45.676124],"type":"Point"}
}