{
  "type": "Feature",
  "properties": {
    "iso:country":"US",
    "sg:address":"1430 Monmouth St",
    "sg:city":"Independence",
    "sg:classifiers":[
        {
            "category":"Health Services",
            "subcategory":"Doctor",
            "type":"Services"
        }
    ],
    "sg:phone":"+1 503 838 1133",
    "sg:postcode":"97351",
    "sg:province":"OR",
    "sg:tags":[
        "physician",
        "surgeon"
    ],
    "wof:name":"Monmouth Family Practice",
    "wof:placetype":"venue"
},
  "geometry": {"coordinates":[-123.208566,44.851281],"type":"Point"}
}