{
  "type": "Feature",
  "properties": {
    "addr:full":"1773 NE 3rd St Prineville OR 97754",
    "addr:housenumber":"1773",
    "addr:postcode":"97754",
    "addr:street":"Ne 3Rd St",
    "iso:country":"US",
    "sg:address":"1773 NE 3rd St",
    "sg:city":"Prineville",
    "sg:classifiers":[
        {
            "category":"Taxi",
            "type":"Transportation"
        }
    ],
    "sg:phone":"+1 541 416 8400",
    "sg:postcode":"97754",
    "sg:province":"OR",
    "sg:tags":[
        "taxicab"
    ],
    "wof:name":"Country Cab",
    "wof:placetype":"venue"
},
  "geometry": {"coordinates":[-120.825969,44.303002],"type":"Point"}
}