{
  "type": "Feature",
  "properties": {
    "iso:country":"US",
    "sg:address":"862 E 36th Ave",
    "sg:city":"Eugene",
    "sg:classifiers":[
        {
            "category":"Building & Trades",
            "subcategory":"Cleaning & Sanitation",
            "type":"Services"
        },
        {
            "category":"Building & Trades",
            "subcategory":"Construction",
            "type":"Services"
        }
    ],
    "sg:phone":"+1 541 344 5571",
    "sg:postcode":"97405",
    "sg:province":"OR",
    "sg:tags":[
        "stonework",
        "masonry",
        "other",
        "fireplace",
        "chimney"
    ],
    "wof:name":"Jolly Good Chimney Sweeps",
    "wof:placetype":"venue"
},
  "geometry": {"coordinates":[-123.077969,44.017265],"type":"Point"}
}