{
  "type": "Feature",
  "properties": {
    "addr:full":"221 Wallis St Eugene OR 97402",
    "addr:housenumber":"221",
    "addr:postcode":"97402",
    "addr:street":"Wallis St",
    "iso:country":"US",
    "sg:address":"221 Wallis St",
    "sg:city":"Eugene",
    "sg:classifiers":[
        {
            "category":"Retail",
            "subcategory":"Auto Repair",
            "type":"Services"
        }
    ],
    "sg:phone":"+1 541 513 3368",
    "sg:postcode":"97402",
    "sg:province":"OR",
    "sg:tags":[
        "body",
        "automotive",
        "painting",
        "automobile"
    ],
    "wof:name":"Empire Auto Works",
    "wof:placetype":"venue"
},
  "geometry": {"coordinates":[-123.15436200000001,44.057343],"type":"Point"}
}