{
  "type": "Feature",
  "properties": {
    "addr:full":"91934 Lampa Ln Myrtle Point OR 97458",
    "addr:postcode":"91934;97458",
    "addr:street":"Lampa Ln",
    "iso:country":"US",
    "sg:address":"91934 Lampa Ln",
    "sg:city":"Myrtle Point",
    "sg:classifiers":[
        {
            "category":"Restaurant",
            "type":"Food & Drink"
        }
    ],
    "sg:phone":"+1 541 572 5620",
    "sg:postcode":"97458",
    "sg:province":"OR",
    "sg:tags":[
        "eating"
    ],
    "wof:name":"Pam's Kitchen",
    "wof:placetype":"venue"
},
  "geometry": {"coordinates":[-124.206158,43.100651],"type":"Point"}
}