{
  "type": "Feature",
  "properties": {
    "iso:country":"US",
    "sg:address":"7455 SW Bridgeport Rd Ste 230",
    "sg:city":"Portland",
    "sg:classifiers":[
        {
            "category":"Health Services",
            "subcategory":"Doctor",
            "type":"Services"
        },
        {
            "category":"Health Services",
            "subcategory":"Dentist",
            "type":"Services"
        }
    ],
    "sg:phone":"+1 503 747 3689",
    "sg:postcode":"97224",
    "sg:province":"OR",
    "sg:tags":[
        "surgeon",
        "oral",
        "pediatric"
    ],
    "sg:website":"www.bridgeport-village.com/docum...",
    "wof:name":"Bridgeport Smiles Family Dentistry",
    "wof:placetype":"venue"
},
  "geometry": {"coordinates":[-122.75409399999999,45.393549],"type":"Point"}
}