{
  "type": "Feature",
  "properties": {
    "iso:country":"US",
    "sg:address":"86187 Hoya Ln",
    "sg:city":"Eugene",
    "sg:classifiers":[
        {
            "category":"Wholesale",
            "subcategory":"Wine & Distilled Alcoholic Beverages",
            "type":"Manufacturing & Wholesale Goods"
        }
    ],
    "sg:phone":"+1 541 747 4681",
    "sg:postcode":"97405",
    "sg:province":"OR",
    "wof:name":"Houston Vineyards Inc",
    "wof:placetype":"venue"
},
  "geometry": {"coordinates":[-122.988337,44.005017],"type":"Point"}
}