{
  "type": "Feature",
  "properties": {
    "iso:country":"US",
    "sg:address":"8830 SE Otty Rd",
    "sg:city":"Portland",
    "sg:classifiers":[
        {
            "category":"Retail",
            "subcategory":"Auto Repair",
            "type":"Services"
        }
    ],
    "sg:phone":"+1 503 777 3212",
    "sg:postcode":"97266",
    "sg:province":"OR",
    "wof:name":"Spain's Auto Repair & Complete Muffler Service",
    "wof:placetype":"venue"
},
  "geometry": {"coordinates":[-122.572998,45.451302],"type":"Point"}
}