{
  "type": "Feature",
  "properties": {
    "addr:full":"409 Center St Oregon City OR 97045",
    "addr:housenumber":"409",
    "addr:postcode":"97045",
    "addr:street":"Center St",
    "iso:country":"US",
    "sg:address":"409 Center St",
    "sg:city":"Oregon City",
    "sg:classifiers":[
        {
            "category":"Professional",
            "subcategory":"Lawyer & Legal Services",
            "type":"Services"
        }
    ],
    "sg:phone":"+1 503 656 0355",
    "sg:postcode":"97045",
    "sg:province":"OR",
    "sg:tags":[
        "attorney"
    ],
    "wof:name":"John Henry Hingson III",
    "wof:placetype":"venue"
},
  "geometry": {"coordinates":[-122.607518,45.355271],"type":"Point"}
}