{
  "type": "Feature",
  "properties": {
    "iso:country":"US",
    "sg:address":"5811 Southgate Dr",
    "sg:city":"Klamath Falls",
    "sg:classifiers":[
        {
            "category":"Shopping",
            "subcategory":"Catalog Store",
            "type":"Retail Goods"
        }
    ],
    "sg:phone":"+1 541 884 4738",
    "sg:postcode":"97603",
    "sg:province":"OR",
    "sg:tags":[
        "house",
        "mail"
    ],
    "wof:name":"Authorized Sears Retail Dlrshp",
    "wof:placetype":"venue"
},
  "geometry": {"coordinates":[-121.716989,42.191514],"type":"Point"}
}