{
  "type": "Feature",
  "properties": {
    "iso:country":"US",
    "sg:address":"1080 S Riverside Ave",
    "sg:city":"Medford",
    "sg:classifiers":[
        {
            "category":"Restaurant",
            "type":"Food & Drink"
        }
    ],
    "sg:phone":"+1 541 773 5568",
    "sg:postcode":"97501",
    "sg:province":"OR",
    "sg:tags":[
        "pizza"
    ],
    "sg:website":"www.abbys.com",
    "wof:name":"Abby's Legendary Pizza",
    "wof:placetype":"venue"
},
  "geometry": {"coordinates":[-122.862999,42.315498],"type":"Point"}
}