{
  "type": "Feature",
  "properties": {
    "iso:country":"US",
    "sg:address":"790 Wallace Rd NW",
    "sg:city":"Salem",
    "sg:classifiers":[
        {
            "category":"Building & Trades",
            "subcategory":"Equipment Rental",
            "type":"Services"
        }
    ],
    "sg:phone":"+1 503 581 3704",
    "sg:postcode":"97304",
    "sg:province":"OR",
    "wof:name":"A-Addie Rentals",
    "wof:placetype":"venue"
},
  "geometry": {"coordinates":[-123.05119000000001,44.948884],"type":"Point"}
}