{
  "type": "Feature",
  "properties": {
    "iso:country":"US",
    "sg:address":"30135 Heather Oak Dr",
    "sg:city":"Junction City",
    "sg:classifiers":[
        {
            "category":"Professional",
            "subcategory":"Business Services",
            "type":"Services"
        }
    ],
    "sg:phone":"+1 541 998 1822",
    "sg:postcode":"97448",
    "sg:province":"OR",
    "wof:name":"M Ward Limited Partnership",
    "wof:placetype":"venue"
},
  "geometry": {"coordinates":[-123.160325,44.165433],"type":"Point"}
}