{
  "type": "Feature",
  "properties": {
    "iso:country":"US",
    "sg:address":"1890 Fall Creek Rd",
    "sg:city":"Glide",
    "sg:classifiers":[
        {
            "category":"Wholesale",
            "subcategory":"Durable Goods & Equipment",
            "type":"Manufacturing & Wholesale Goods"
        }
    ],
    "sg:phone":"+1 541 496 3171",
    "sg:postcode":"97443",
    "sg:province":"OR",
    "sg:tags":[
        "log",
        "supply",
        "firewood",
        "gun",
        "pole",
        "shooting",
        "whole"
    ],
    "wof:name":"Fall Creek Ranch",
    "wof:placetype":"venue"
},
  "geometry": {"coordinates":[-123.078175,43.244353],"type":"Point"}
}