{
  "type": "Feature",
  "properties": {
    "addr:full":"697 Nebraska St Eugene OR 97402",
    "addr:housenumber":"697",
    "addr:postcode":"97402",
    "addr:street":"Nebraska St",
    "iso:country":"US",
    "sg:address":"697 Nebraska St",
    "sg:city":"Eugene",
    "sg:classifiers":[
        {
            "category":"Retail",
            "subcategory":"Auto Repair",
            "type":"Services"
        }
    ],
    "sg:phone":"+1 541 232 5470",
    "sg:postcode":"97402",
    "sg:province":"OR",
    "sg:tags":[
        "repairing",
        "automobile"
    ],
    "wof:name":"Michael The Mobile Mechanic",
    "wof:placetype":"venue"
},
  "geometry": {"coordinates":[-123.168037,44.06682],"type":"Point"}
}