{
  "type": "Feature",
  "properties": {
    "iso:country":"US",
    "sg:address":"1127 NE Broadway St",
    "sg:city":"Portland",
    "sg:classifiers":[
        {
            "category":"Food & Beverages",
            "subcategory":"Bakery",
            "type":"Retail Goods"
        }
    ],
    "sg:phone":"+1 503 221 1776",
    "sg:postcode":"97232",
    "sg:province":"OR",
    "wof:name":"Shortest Route Inc",
    "wof:placetype":"venue"
},
  "geometry": {"coordinates":[-122.653716,45.535123],"type":"Point"}
}