{
  "type": "Feature",
  "properties": {
    "iso:country":"US",
    "sg:address":"8812 SW Brightfield Cir",
    "sg:city":"Portland",
    "sg:classifiers":[
        {
            "category":"Food & Beverages",
            "subcategory":"Chocolate",
            "type":"Retail Goods"
        }
    ],
    "sg:phone":"+1 503 419 7283",
    "sg:postcode":"97223",
    "sg:province":"OR",
    "sg:tags":[
        "cocoa"
    ],
    "wof:name":"Healthy Chocolate",
    "wof:placetype":"venue"
},
  "geometry": {"coordinates":[-122.779517,45.457021],"type":"Point"}
}