{
  "type": "Feature",
  "properties": {
    "iso:country":"US",
    "sg:address":"5140 SE Circle Ave Ste A",
    "sg:city":"Portland",
    "sg:classifiers":[
        {
            "category":"Professional",
            "subcategory":"Management & Consulting",
            "type":"Services"
        }
    ],
    "sg:phone":"+1 503 969 3900",
    "sg:postcode":"97236",
    "sg:province":"OR",
    "sg:tags":[
        "science",
        "consultant",
        "academic"
    ],
    "wof:name":"Environmental Business Solutions Inc",
    "wof:placetype":"venue"
},
  "geometry": {"coordinates":[-122.48671,45.485451],"type":"Point"}
}