{
  "type": "Feature",
  "properties": {
    "iso:country":"US",
    "sg:address":"15818 SE 114th Ave",
    "sg:city":"Clackamas",
    "sg:classifiers":[
        {
            "category":"Shopping",
            "subcategory":"Discount & Variety Stores",
            "type":"Retail Goods"
        }
    ],
    "sg:phone":"+1 503 557 8515",
    "sg:postcode":"97015",
    "sg:province":"OR",
    "sg:tags":[
        "salvage",
        "surplus",
        "merchandise"
    ],
    "wof:name":"Salvage Groups, The",
    "wof:placetype":"venue"
},
  "geometry": {"coordinates":[-122.546313,45.408107],"type":"Point"}
}