{
  "type": "Feature",
  "properties": {
    "iso:country":"US",
    "sg:address":"966 SW 6th St",
    "sg:city":"Grants Pass",
    "sg:classifiers":[
        {
            "category":"Ferry",
            "type":"Transportation"
        }
    ],
    "sg:phone":"+1 541 479 7204",
    "sg:postcode":"97526",
    "sg:province":"OR",
    "sg:tags":[
        "water",
        "passenger",
        "tourism",
        "boat",
        "for"
    ],
    "wof:name":"Hellgate Jetboats Excursions",
    "wof:placetype":"venue"
},
  "geometry": {"coordinates":[-123.330549,42.433377],"type":"Point"}
}