{
  "type": "Feature",
  "properties": {
    "addr:full":"1420 E McAndrews Rd Medford OR 97504",
    "addr:housenumber":"1420",
    "addr:postcode":"97504",
    "addr:street":"E Mcandrews Rd",
    "iso:country":"US",
    "sg:address":"1420 E McAndrews Rd",
    "sg:city":"Medford",
    "sg:classifiers":[
        {
            "category":"Banks & Credit Unions",
            "subcategory":"Bank",
            "type":"Services"
        }
    ],
    "sg:phone":"+1 541 779 1903",
    "sg:postcode":"97504",
    "sg:province":"OR",
    "sg:website":"www.sterlingsavingsbank.com",
    "wof:name":"Sterling Savings Bank",
    "wof:placetype":"venue"
},
  "geometry": {"coordinates":[-122.866698,42.340943],"type":"Point"}
}