{
  "type": "Feature",
  "properties": {
    "iso:country":"US",
    "sg:address":"19447 Grim Rd NE",
    "sg:city":"Aurora",
    "sg:classifiers":[
        {
            "category":"Manufacturing",
            "subcategory":"Tools & Machinery",
            "type":"Manufacturing & Wholesale Goods"
        }
    ],
    "sg:phone":"+1 503 981 1474",
    "sg:postcode":"97002",
    "sg:province":"OR",
    "sg:tags":[
        "equipment",
        "commercial",
        "clea",
        "laundry",
        "mfg"
    ],
    "wof:name":"Ballweber Industries Inc",
    "wof:placetype":"venue"
},
  "geometry": {"coordinates":[-122.783096,45.200854],"type":"Point"}
}