{
  "type": "Feature",
  "properties": {
    "addr:full":"19205 US Hwy 101 N Rockaway Beach OR 97136",
    "addr:postcode":"19205;97136",
    "addr:street":"Us Hwy 101 N",
    "iso:country":"US",
    "sg:address":"19205 US Hwy 101 N",
    "sg:city":"Rockaway Beach",
    "sg:classifiers":[
        {
            "category":"Bus Charters",
            "type":"Transportation"
        }
    ],
    "sg:phone":"+1 503 355 2008",
    "sg:postcode":"97136",
    "sg:province":"OR",
    "sg:tags":[
        "rental"
    ],
    "wof:name":"First Student Inc",
    "wof:placetype":"venue"
},
  "geometry": {"coordinates":[-123.946596,45.597117],"type":"Point"}
}