{
  "type": "Feature",
  "properties": {
    "iso:country":"US",
    "sg:address":"5240 SE King Road",
    "sg:city":"Portland",
    "sg:classifiers":[
        {
            "category":"Social Services",
            "subcategory":"Child Care",
            "type":"Services"
        },
        {
            "category":"Education",
            "subcategory":"Preschool",
            "type":"Public Place"
        },
        {
            "category":"Education",
            "subcategory":"School",
            "type":"Public Place"
        }
    ],
    "sg:phone":"+1 503 653 2191",
    "sg:postcode":"97222",
    "sg:province":"OR",
    "sg:tags":[
        "elementary",
        "day"
    ],
    "wof:name":"Learning Lollipops Preschool",
    "wof:placetype":"venue"
},
  "geometry": {"coordinates":[-122.608363,45.447891],"type":"Point"}
}