{
  "type": "Feature",
  "properties": {
    "addr:full":"239 SE 6th Ave Portland OR 97214",
    "addr:housenumber":"239",
    "addr:postcode":"97214",
    "addr:street":"Se 6Th Ave",
    "iso:country":"US",
    "sg:address":"239 SE 6th Ave",
    "sg:city":"Portland",
    "sg:classifiers":[
        {
            "category":"Shopping",
            "subcategory":"Music",
            "type":"Retail Goods"
        }
    ],
    "sg:phone":"+1 503 232 6200",
    "sg:postcode":"97214",
    "sg:province":"OR",
    "sg:tags":[
        "store"
    ],
    "wof:name":"Down Slow Records",
    "wof:placetype":"venue"
},
  "geometry": {"coordinates":[-122.659704,45.521232],"type":"Point"}
}