{
  "type": "Feature",
  "properties": {
    "iso:country":"US",
    "sg:address":"960 US Hwy 101",
    "sg:city":"Lincoln City",
    "sg:classifiers":[
        {
            "category":"Building & Trades",
            "subcategory":"Construction",
            "type":"Services"
        }
    ],
    "sg:phone":"+1 541 996 4994",
    "sg:postcode":"97367",
    "sg:province":"OR",
    "sg:tags":[
        "contractor"
    ],
    "wof:name":"Tub Man",
    "wof:placetype":"venue"
},
  "geometry": {"coordinates":[-124.01365,44.97301],"type":"Point"}
}