{
  "type": "Feature",
  "properties": {
    "iso:country":"US",
    "sg:address":"16074 SE McLoughlin Blvd",
    "sg:city":"Portland",
    "sg:classifiers":[
        {
            "category":"Personal",
            "subcategory":"Beauty Salon",
            "type":"Services"
        }
    ],
    "sg:phone":"+1 503 786 4050",
    "sg:postcode":"97267",
    "sg:province":"OR",
    "sg:tags":[
        "shop"
    ],
    "wof:name":"Shelby Schefstrom",
    "wof:placetype":"venue"
},
  "geometry": {"coordinates":[-122.624052,45.406089],"type":"Point"}
}