{
  "type": "Feature",
  "properties": {
    "iso:country":"US",
    "sg:address":"1142 Willagillespie Rd",
    "sg:city":"Eugene",
    "sg:classifiers":[
        {
            "category":"Real Estate",
            "subcategory":"Real Estate Agent",
            "type":"Services"
        }
    ],
    "sg:phone":"+1 541 343 6100",
    "sg:postcode":"97401",
    "sg:province":"OR",
    "sg:tags":[
        "appraiser"
    ],
    "wof:name":"First Appraisals",
    "wof:placetype":"venue"
},
  "geometry": {"coordinates":[-123.100402,44.0728],"type":"Point"}
}