{
  "type": "Feature",
  "properties": {
    "iso:country":"US",
    "sg:address":"20518 Murray Rd",
    "sg:city":"Bend",
    "sg:classifiers":[
        {
            "category":"Manufacturing",
            "subcategory":"Building Materials",
            "type":"Manufacturing & Wholesale Goods"
        },
        {
            "category":"Manufacturing",
            "subcategory":"Jewelry",
            "type":"Manufacturing & Wholesale Goods"
        },
        {
            "category":"Wholesale",
            "subcategory":"Construction Materials",
            "type":"Manufacturing & Wholesale Goods"
        },
        {
            "category":"Utilities",
            "subcategory":"Natural Gas",
            "type":"Services"
        }
    ],
    "sg:phone":"+1 541 317 1398",
    "sg:postcode":"97701",
    "sg:province":"OR",
    "sg:tags":[
        "stone",
        "supply",
        "materials-wholesale",
        "natural-wholesale",
        "equipment",
        "masonry",
        "manufacturer"
    ],
    "wof:name":"Natural Stone Designs",
    "wof:placetype":"venue"
},
  "geometry": {"coordinates":[-121.296752,44.083889],"type":"Point"}
}