{
  "type": "Feature",
  "properties": {
    "addr:full":"833 SW 11th Ave Ste 925 Portland OR 97205",
    "addr:housenumber":"833",
    "addr:postcode":"97205",
    "addr:street":"Sw 11Th Ave Ste 925",
    "iso:country":"US",
    "sg:address":"833 SW 11th Ave Ste 925",
    "sg:city":"Portland",
    "sg:classifiers":[
        {
            "category":"Health Services",
            "subcategory":"Clinic",
            "type":"Services"
        }
    ],
    "sg:phone":"+1 503 223 7620",
    "sg:postcode":"97205",
    "sg:province":"OR",
    "sg:tags":[
        "counseling",
        "mental"
    ],
    "sg:website":"www.spinw.com",
    "wof:name":"Sport Psychology Institute Northwest",
    "wof:placetype":"venue"
},
  "geometry": {"coordinates":[-122.683629,45.519346],"type":"Point"}
}