{
  "type": "Feature",
  "properties": {
    "addr:full":"1000 Main Ave Tillamook OR 97141",
    "addr:housenumber":"1000",
    "addr:postcode":"97141",
    "addr:street":"Main Ave",
    "iso:country":"US",
    "sg:address":"1000 Main Ave",
    "sg:city":"Tillamook",
    "sg:classifiers":[
        {
            "category":"Shopping",
            "subcategory":"Clothing, Apparel, & Fashions",
            "type":"Retail Goods"
        }
    ],
    "sg:phone":"+1 503 842 4327",
    "sg:postcode":"97141",
    "sg:province":"OR",
    "wof:name":"Baby Gear & Maternity",
    "wof:placetype":"venue"
},
  "geometry": {"coordinates":[-123.84396099999999,45.451152],"type":"Point"}
}