{
  "type": "Feature",
  "properties": {
    "addr:full":"3957 N Mississippi Ave Portland OR 97227",
    "addr:housenumber":"3957",
    "addr:postcode":"97227",
    "addr:street":"N Mississippi Ave",
    "iso:country":"US",
    "sg:address":"3957 N Mississippi Ave",
    "sg:city":"Portland",
    "sg:classifiers":[
        {
            "category":"Restaurant",
            "type":"Food & Drink"
        }
    ],
    "sg:phone":"+1 503 287 8800",
    "sg:postcode":"97227",
    "sg:province":"OR",
    "sg:tags":[
        "breakfast",
        "brunch"
    ],
    "wof:name":"Gravy",
    "wof:placetype":"venue"
},
  "geometry": {"coordinates":[-122.675529,45.551552],"type":"Point"}
}