{
  "type": "Feature",
  "properties": {
    "iso:country":"US",
    "sg:address":"501 N Graham Street Suite 375",
    "sg:city":"Portland",
    "sg:classifiers":[
        {
            "category":"Health Services",
            "subcategory":"Doctor",
            "type":"Services"
        },
        {
            "category":"Health Services",
            "subcategory":"Hospital",
            "type":"Services"
        }
    ],
    "sg:phone":"+1 503 413 1600",
    "sg:postcode":"97227",
    "sg:province":"OR",
    "wof:name":"Hansen James MD",
    "wof:placetype":"venue"
},
  "geometry": {"coordinates":[-122.670447,45.542848],"type":"Point"}
}