{
  "type": "Feature",
  "properties": {
    "addr:full":"3526 Southvillage Dr Medford OR 97504",
    "addr:housenumber":"3526",
    "addr:postcode":"97504",
    "addr:street":"Southvillage Dr",
    "iso:country":"US",
    "sg:address":"3526 Southvillage Dr",
    "sg:city":"Medford",
    "sg:classifiers":[
        {
            "category":"Professional",
            "subcategory":"Management & Consulting",
            "type":"Services"
        }
    ],
    "sg:phone":"+1 541 858 0305",
    "sg:postcode":"97504",
    "sg:province":"OR",
    "sg:tags":[
        "business"
    ],
    "wof:name":"Videre Consulting",
    "wof:placetype":"venue"
},
  "geometry": {"coordinates":[-122.816558,42.326586],"type":"Point"}
}