{
  "type": "Feature",
  "properties": {
    "addr:full":"2570 Lawrence St Eugene OR 97405",
    "addr:housenumber":"2570",
    "addr:postcode":"97405",
    "addr:street":"Lawrence St",
    "iso:country":"US",
    "sg:address":"2570 Lawrence St",
    "sg:city":"Eugene",
    "sg:classifiers":[
        {
            "category":"Professional",
            "subcategory":"Computer Services",
            "type":"Services"
        }
    ],
    "sg:phone":"+1 541 484 0438",
    "sg:postcode":"97405",
    "sg:province":"OR",
    "sg:tags":[
        "programming",
        "system",
        "integration"
    ],
    "wof:name":"Microcomputer Associates",
    "wof:placetype":"venue"
},
  "geometry": {"coordinates":[-123.098513,44.031106],"type":"Point"}
}