{
  "type": "Feature",
  "properties": {
    "iso:country":"US",
    "sg:address":"1780 SE Willamette St",
    "sg:city":"Sherwood",
    "sg:classifiers":[
        {
            "category":"Banks & Credit Unions",
            "subcategory":"Investment Brokerage",
            "type":"Services"
        }
    ],
    "sg:phone":"+1 503 293 0714",
    "sg:postcode":"97140",
    "sg:province":"OR",
    "sg:tags":[
        "advisory",
        "financial"
    ],
    "wof:name":"Rome Co Enterprises",
    "wof:placetype":"venue"
},
  "geometry": {"coordinates":[-122.826809,45.356443],"type":"Point"}
}