{
  "type": "Feature",
  "properties": {
    "iso:country":"US",
    "sg:address":"1000 SE Bay Blvd",
    "sg:city":"Newport",
    "sg:classifiers":[
        {
            "category":"Recreation",
            "type":"Entertainment"
        }
    ],
    "sg:phone":"+1 541 265 6800",
    "sg:postcode":"97365",
    "sg:province":"OR",
    "sg:tags":[
        "sporting",
        "good",
        "charter",
        "boat"
    ],
    "sg:website":"http://www.yaquinabaycharters.com",
    "wof:name":"Yaquina Bay Charters",
    "wof:placetype":"venue"
},
  "geometry": {"coordinates":[-124.039688,44.630779],"type":"Point"}
}