{
  "type": "Feature",
  "properties": {
    "iso:country":"US",
    "sg:address":"5490 SW Minter Bridge Rd",
    "sg:city":"Hillsboro",
    "sg:classifiers":[
        {
            "category":"Wholesale",
            "subcategory":"Plants",
            "type":"Manufacturing & Wholesale Goods"
        }
    ],
    "sg:phone":"+1 503 844 0688",
    "sg:postcode":"97123",
    "sg:province":"OR",
    "sg:tags":[
        "supply"
    ],
    "wof:name":"European Nursery",
    "wof:placetype":"venue"
},
  "geometry": {"coordinates":[-122.982372,45.484761],"type":"Point"}
}