{
  "type": "Feature",
  "properties": {
    "iso:country":"US",
    "sg:address":"1519 N Adair St",
    "sg:city":"Cornelius",
    "sg:classifiers":[
        {
            "category":"Retail",
            "subcategory":"Auto Repair",
            "type":"Services"
        }
    ],
    "sg:phone":"+1 503 992 7000",
    "sg:postcode":"97113",
    "sg:province":"OR",
    "sg:tags":[
        "general"
    ],
    "wof:name":"Prestige Auto Inc",
    "wof:placetype":"venue"
},
  "geometry": {"coordinates":[-123.05244999999999,45.52083],"type":"Point"}
}