{
  "type": "Feature",
  "properties": {
    "iso:country":"US",
    "sg:address":"1230 SE 7th Avenue",
    "sg:city":"Portland",
    "sg:classifiers":[
        {
            "category":"Professional",
            "type":"Services"
        }
    ],
    "sg:phone":"+1 503 232 4408",
    "sg:postcode":"97214",
    "sg:province":"OR",
    "sg:tags":[
        "caterer"
    ],
    "wof:name":"Eat Your Heart Out Catering Company",
    "wof:placetype":"venue"
},
  "geometry": {"coordinates":[-122.65884800000001,45.514232],"type":"Point"}
}