{
  "type": "Feature",
  "properties": {
    "addr:full":"5098 Briarwood Cir N Keizer OR 97303",
    "addr:housenumber":"5098",
    "addr:postcode":"97303",
    "addr:street":"Briarwood Cir N",
    "iso:country":"US",
    "sg:address":"5098 Briarwood Cir N",
    "sg:city":"Keizer",
    "sg:classifiers":[
        {
            "category":"Real Estate",
            "subcategory":"Real Estate Operator",
            "type":"Services"
        }
    ],
    "sg:phone":"+1 503 393 3450",
    "sg:postcode":"97303",
    "sg:province":"OR",
    "sg:tags":[
        "mobile",
        "home",
        "community"
    ],
    "wof:name":"Briarwood Estates",
    "wof:placetype":"venue"
},
  "geometry": {"coordinates":[-123.04892,44.998519],"type":"Point"}
}