{
  "type": "Feature",
  "properties": {
    "addr:full":"17495 NE McDougall Rd Dayton OR 97114",
    "addr:housenumber":"17495",
    "addr:postcode":"97114",
    "addr:street":"Ne Mcdougall Rd",
    "iso:country":"US",
    "sg:address":"17495 NE McDougall Rd",
    "sg:city":"Dayton",
    "sg:classifiers":[
        {
            "category":"Building & Trades",
            "subcategory":"Construction",
            "type":"Services"
        }
    ],
    "sg:phone":"+1 503 435 1145",
    "sg:postcode":"97114",
    "sg:province":"OR",
    "sg:tags":[
        "carpentry",
        "contractor"
    ],
    "wof:name":"Acro Construction LLC",
    "wof:placetype":"venue"
},
  "geometry": {"coordinates":[-123.059335,45.242093],"type":"Point"}
}