{
  "type": "Feature",
  "properties": {
    "iso:country":"US",
    "sg:address":"3800 Ferry St",
    "sg:city":"Eugene",
    "sg:classifiers":[
        {
            "category":"Organizations",
            "subcategory":"Religious Organization",
            "type":"Services"
        }
    ],
    "sg:phone":"+1 541 334 6772",
    "sg:postcode":"97405",
    "sg:province":"OR",
    "sg:tags":[
        "synagogue"
    ],
    "wof:name":"Ahavas Torah",
    "wof:placetype":"venue"
},
  "geometry": {"coordinates":[-123.084316,44.013338],"type":"Point"}
}