{
  "type": "Feature",
  "properties": {
    "addr:full":"2927 SW 6th Ave Ontario OR 97914",
    "addr:housenumber":"2927",
    "addr:postcode":"97914",
    "addr:street":"Sw 6Th Ave",
    "iso:country":"US",
    "sg:address":"2927 SW 6th Ave",
    "sg:city":"Ontario",
    "sg:classifiers":[
        {
            "category":"Government",
            "subcategory":"Office",
            "type":"Public Place"
        }
    ],
    "sg:phone":"+1 541 889 7377",
    "sg:postcode":"97914",
    "sg:province":"OR",
    "sg:tags":[
        "agency"
    ],
    "wof:name":"Social Security Administration",
    "wof:placetype":"venue"
},
  "geometry": {"coordinates":[-117.004963,44.023122],"type":"Point"}
}