{
  "type": "Feature",
  "properties": {
    "iso:country":"US",
    "sg:address":"513 E Main St",
    "sg:city":"Klamath Falls",
    "sg:classifiers":[
        {
            "category":"Restaurant",
            "type":"Food & Drink"
        }
    ],
    "sg:phone":"+1 541 882 3829",
    "sg:postcode":"97601",
    "sg:province":"OR",
    "sg:tags":[
        "eating"
    ],
    "wof:name":"Las Morenas",
    "wof:placetype":"venue"
},
  "geometry": {"coordinates":[-121.765207,42.224556],"type":"Point"}
}