{
  "type": "Feature",
  "properties": {
    "addr:full":"1401 SW Naito Pkwy Portland OR 97201",
    "addr:housenumber":"1401",
    "addr:postcode":"97201",
    "addr:street":"Sw Naito Pkwy",
    "iso:country":"US",
    "sg:address":"1401 SW Naito Pkwy",
    "sg:city":"Portland",
    "sg:classifiers":[
        {
            "category":"Retail",
            "subcategory":"Laundry & Dry Cleaning",
            "type":"Services"
        }
    ],
    "sg:phone":"+1 503 499 6330",
    "sg:postcode":"97201",
    "sg:province":"OR",
    "sg:tags":[
        "supply",
        "uniform"
    ],
    "wof:name":"Mile High Valet Service",
    "wof:placetype":"venue"
},
  "geometry": {"coordinates":[-122.67517100000001,45.512821],"type":"Point"}
}