{
  "type": "Feature",
  "properties": {
    "iso:country":"US",
    "sg:address":"6544 SW Firlock Way Apt 8",
    "sg:city":"Portland",
    "sg:classifiers":[
        {
            "category":"Building & Trades",
            "subcategory":"Cleaning & Sanitation",
            "type":"Services"
        }
    ],
    "sg:phone":"+1 503 678 1336",
    "sg:postcode":"97223",
    "sg:province":"OR",
    "sg:tags":[
        "cleaning-industrial",
        "contractor"
    ],
    "wof:name":"Jetwash",
    "wof:placetype":"venue"
},
  "geometry": {"coordinates":[-122.75657699999999,45.472832],"type":"Point"}
}