{
  "type": "Feature",
  "properties": {
    "addr:full":"18640 Tumalo Reservoir Rd Bend OR 97701",
    "addr:postcode":"18640;97701",
    "addr:street":"Tumalo Reservoir Rd",
    "iso:country":"US",
    "sg:address":"18640 Tumalo Reservoir Rd",
    "sg:city":"Bend",
    "sg:classifiers":[
        {
            "category":"Building & Trades",
            "subcategory":"Construction",
            "type":"Services"
        }
    ],
    "sg:phone":"+1 541 389 4635",
    "sg:postcode":"97701",
    "sg:province":"OR",
    "sg:tags":[
        "general",
        "contractor"
    ],
    "wof:name":"Bob Schmidt Construction",
    "wof:placetype":"venue"
},
  "geometry": {"coordinates":[-121.391712,44.1383],"type":"Point"}
}