{
  "type": "Feature",
  "properties": {
    "iso:country":"US",
    "sg:address":"2395 Redwood Ave",
    "sg:city":"Grants Pass",
    "sg:classifiers":[
        {
            "category":"Shopping",
            "subcategory":"Gifts & Souvenirs",
            "type":"Retail Goods"
        }
    ],
    "sg:phone":"+1 541 476 5736",
    "sg:postcode":"97527",
    "sg:province":"OR",
    "wof:name":"Davichs Magnificent Gifts",
    "wof:placetype":"venue"
},
  "geometry": {"coordinates":[-123.37477,42.422287],"type":"Point"}
}