{
  "type": "Feature",
  "properties": {
    "iso:country":"US",
    "sg:address":"4107 SE Hillyard Rd",
    "sg:city":"Gresham",
    "sg:classifiers":[
        {
            "category":"Social Services",
            "subcategory":"Adult Care",
            "type":"Services"
        }
    ],
    "sg:phone":"+1 503 663 5829",
    "sg:postcode":"97080",
    "sg:province":"OR",
    "sg:tags":[
        "handicapped",
        "residential",
        "for"
    ],
    "wof:name":"Hillyard Group Home",
    "wof:placetype":"venue"
},
  "geometry": {"coordinates":[-122.390308,45.476996],"type":"Point"}
}