{
  "type": "Feature",
  "properties": {
    "iso:country":"US",
    "sg:address":"211 W 1st St",
    "sg:city":"Newberg",
    "sg:classifiers":[
        {
            "category":"Retail",
            "subcategory":"Repair Shop",
            "type":"Services"
        }
    ],
    "sg:phone":"+1 503 538 3532",
    "sg:postcode":"97132",
    "sg:province":"OR",
    "wof:name":"Correa Rmon Furn Rfinishing RE",
    "wof:placetype":"venue"
},
  "geometry": {"coordinates":[-122.98112500000001,45.300411],"type":"Point"}
}