{
  "type": "Feature",
  "properties": {
    "iso:country":"US",
    "sg:address":"1640 SE 10th Ave",
    "sg:city":"Portland",
    "sg:classifiers":[
        {
            "category":"Wholesale",
            "subcategory":"Sporting Goods",
            "type":"Manufacturing & Wholesale Goods"
        }
    ],
    "sg:phone":"+1 503 238 0829",
    "sg:postcode":"97214",
    "sg:province":"OR",
    "sg:tags":[
        "bicycle"
    ],
    "wof:name":"Acme Paint Shop",
    "wof:placetype":"venue"
},
  "geometry": {"coordinates":[-122.65564000000001,45.511082],"type":"Point"}
}