{
  "type": "Feature",
  "properties": {
    "addr:full":"1020 Circle Star Ln Roseburg OR 97470",
    "addr:housenumber":"1020",
    "addr:postcode":"97470",
    "addr:street":"Circle Star Ln",
    "iso:country":"US",
    "sg:address":"1020 Circle Star Ln",
    "sg:city":"Roseburg",
    "sg:classifiers":[
        {
            "category":"Professional",
            "subcategory":"Management & Consulting",
            "type":"Services"
        }
    ],
    "sg:phone":"+1 541 660 4027",
    "sg:postcode":"97470",
    "sg:province":"OR",
    "sg:tags":[
        "business"
    ],
    "wof:name":"Bem Products Inc",
    "wof:placetype":"venue"
},
  "geometry": {"coordinates":[-123.28851299999999,43.134881],"type":"Point"}
}