{
  "type": "Feature",
  "properties": {
    "iso:country":"US",
    "sg:address":"SE 40th Ave and Johnson Creek Blvd",
    "sg:city":"Portland",
    "sg:classifiers":[
        {
            "category":"Restaurant",
            "type":"Food & Drink"
        }
    ],
    "sg:postcode":"97202",
    "sg:province":"OR",
    "sg:tags":[
        "flavor",
        "local"
    ],
    "wof:name":"Trees and Swag",
    "wof:placetype":"venue"
},
  "geometry": {"coordinates":[-122.622027,45.460593],"type":"Point"}
}