{
  "type": "Feature",
  "properties": {
    "iso:country":"US",
    "sg:address":"17438 Cardinal Dr",
    "sg:city":"Lake Oswego",
    "sg:classifiers":[
        {
            "category":"Banks & Credit Unions",
            "subcategory":"Investment Brokerage",
            "type":"Services"
        }
    ],
    "sg:phone":"+1 503 697 7108",
    "sg:postcode":"97034",
    "sg:province":"OR",
    "sg:tags":[
        "security"
    ],
    "wof:name":"Capital Markets Solutions LLC",
    "wof:placetype":"venue"
},
  "geometry": {"coordinates":[-122.71484700000001,45.399173],"type":"Point"}
}