{
  "type": "Feature",
  "properties": {
    "iso:country":"US",
    "sg:address":"6135 SE 82nd Ave",
    "sg:city":"Portland",
    "sg:classifiers":[
        {
            "category":"Autos & Motor Vehicles",
            "subcategory":"Automobile Sales",
            "type":"Retail Goods"
        }
    ],
    "sg:phone":"+1 503 774 7121",
    "sg:postcode":"97266",
    "sg:province":"OR",
    "sg:tags":[
        "new",
        "car"
    ],
    "wof:name":"Car Store Inc",
    "wof:placetype":"venue"
},
  "geometry": {"coordinates":[-122.57902300000001,45.478693],"type":"Point"}
}