{
  "type": "Feature",
  "properties": {
    "addr:full":"1600 NW Skyline Blvd Portland OR 97229",
    "addr:housenumber":"1600",
    "addr:postcode":"97229",
    "addr:street":"Nw Skyline Blvd",
    "iso:country":"US",
    "sg:address":"1600 NW Skyline Blvd",
    "sg:city":"Portland",
    "sg:classifiers":[
        {
            "category":"Professional",
            "type":"Services"
        },
        {
            "category":"Professional",
            "subcategory":"Business Services",
            "type":"Services"
        }
    ],
    "sg:phone":"+1 503 297 1660",
    "sg:postcode":"97229",
    "sg:province":"OR",
    "sg:tags":[
        "forestry",
        "consultant",
        "consulting",
        "coach"
    ],
    "wof:name":"Genetechs",
    "wof:placetype":"venue"
},
  "geometry": {"coordinates":[-122.756725,45.532733],"type":"Point"}
}