{
  "type": "Feature",
  "properties": {
    "iso:country":"US",
    "sg:address":"7910 SW Nimbus Ave",
    "sg:city":"Beaverton",
    "sg:classifiers":[
        {
            "category":"Manufacturing",
            "subcategory":"Rubber & Plastics",
            "type":"Manufacturing & Wholesale Goods"
        }
    ],
    "sg:phone":"+1 503 646 1285",
    "sg:postcode":"97008",
    "sg:province":"OR",
    "sg:tags":[
        "product"
    ],
    "wof:name":"Evergreen Plastics Inc",
    "wof:placetype":"venue"
},
  "geometry": {"coordinates":[-122.788552,45.462474],"type":"Point"}
}