{
  "type": "Feature",
  "properties": {
    "iso:country":"US",
    "sg:address":"825 NE 20th Ave",
    "sg:city":"Portland",
    "sg:classifiers":[
        {
            "category":"Professional",
            "type":"Services"
        }
    ],
    "sg:phone":"+1 503 236 3423",
    "sg:postcode":"97232",
    "sg:province":"OR",
    "sg:tags":[
        "establishment"
    ],
    "wof:name":"Car Crash Hotline",
    "wof:placetype":"venue"
},
  "geometry": {"coordinates":[-122.64552500000001,45.529108],"type":"Point"}
}