{
  "type": "Feature",
  "properties": {
    "iso:country":"US",
    "sg:address":"1600 NW Washington Blvd",
    "sg:city":"Grants Pass",
    "sg:classifiers":[
        {
            "category":"Manufacturing",
            "subcategory":"Tools & Machinery",
            "type":"Manufacturing & Wholesale Goods"
        }
    ],
    "sg:phone":"+1 541 471 7111",
    "sg:postcode":"97526",
    "sg:province":"OR",
    "sg:tags":[
        "c",
        "temperature",
        "mfg",
        "meteorological",
        "devices",
        "instrument",
        "portable"
    ],
    "sg:website":"www.metone.com",
    "wof:name":"Met One Instruments Inc",
    "wof:placetype":"venue"
},
  "geometry": {"coordinates":[-123.325232,42.458023],"type":"Point"}
}