{
  "type": "Feature",
  "properties": {
    "addr:full":"9331 NE Colfax Ste 201 Portland OR 97220",
    "addr:housenumber":"9331",
    "addr:postcode":"97220",
    "addr:street":"Ne;Ste 201",
    "iso:country":"US",
    "sg:address":"9331 NE Colfax Ste 201",
    "sg:city":"Portland",
    "sg:classifiers":[
        {
            "category":"Personal",
            "type":"Services"
        },
        {
            "category":"Professional",
            "subcategory":"Business Services",
            "type":"Services"
        }
    ],
    "sg:phone":"+1 503 980 4489",
    "sg:postcode":"97220",
    "sg:province":"OR",
    "sg:tags":[
        "delivery",
        "mover",
        "courier"
    ],
    "sg:website":"www.lionsprideservices.com",
    "wof:name":"LionsPride Services",
    "wof:placetype":"venue"
},
  "geometry": {"coordinates":[-122.566187,45.568003],"type":"Point"}
}