{
  "type": "Feature",
  "properties": {
    "addr:full":"421 NW Saltzman Rd Portland OR 97229",
    "addr:housenumber":"421",
    "addr:postcode":"97229",
    "addr:street":"Nw Saltzman Rd",
    "iso:country":"US",
    "sg:address":"421 NW Saltzman Rd",
    "sg:city":"Portland",
    "sg:classifiers":[
        {
            "category":"Restaurant",
            "type":"Food & Drink"
        }
    ],
    "sg:phone":"+1 503 641 6135",
    "sg:postcode":"97229",
    "sg:province":"OR",
    "sg:tags":[
        "japanese",
        "filipino"
    ],
    "wof:name":"Teriyaki Beef Bowl",
    "wof:placetype":"venue"
},
  "geometry": {"coordinates":[-122.80593500000001,45.523395],"type":"Point"}
}