{
  "type": "Feature",
  "properties": {
    "iso:country":"US",
    "sg:address":"5441 SE Belmont St",
    "sg:city":"Portland",
    "sg:classifiers":[
        {
            "category":"Education",
            "subcategory":"School",
            "type":"Public Place"
        }
    ],
    "sg:phone":"+1 503 249 8582",
    "sg:postcode":"97215",
    "sg:province":"OR",
    "sg:tags":[
        "high",
        "middle",
        "elementary"
    ],
    "wof:name":"Community Transitional School",
    "wof:placetype":"venue"
},
  "geometry": {"coordinates":[-122.607353,45.516912],"type":"Point"}
}