{
  "type": "Feature",
  "properties": {
    "iso:country":"US",
    "sg:address":"14640 SE 82nd Dr",
    "sg:city":"Clackamas",
    "sg:classifiers":[
        {
            "category":"Home & Garden",
            "subcategory":"Furniture",
            "type":"Retail Goods"
        }
    ],
    "sg:phone":"+1 503 657 3883",
    "sg:postcode":"97015",
    "sg:province":"OR",
    "wof:name":"Henley Home Furnishing LLC",
    "wof:placetype":"venue"
},
  "geometry": {"coordinates":[-122.569123,45.414912],"type":"Point"}
}