{
  "type": "Feature",
  "properties": {
    "iso:country":"US",
    "sg:address":"3165 E Main St",
    "sg:city":"Ashland",
    "sg:classifiers":[
        {
            "category":"Manufacturing",
            "subcategory":"Motor Vehicles & Parts",
            "type":"Manufacturing & Wholesale Goods"
        }
    ],
    "sg:phone":"+1 541 488 8226",
    "sg:postcode":"97520",
    "sg:province":"OR",
    "sg:tags":[
        "mountain",
        "electric",
        "mfg",
        "battery",
        "charger",
        "bike"
    ],
    "wof:name":"Denali Cycles",
    "wof:placetype":"venue"
},
  "geometry": {"coordinates":[-122.65896600000001,42.185777],"type":"Point"}
}