{
  "type": "Feature",
  "properties": {
    "iso:country":"US",
    "sg:address":"407 NE Hwy 11",
    "sg:city":"Pendleton",
    "sg:classifiers":[
        {
            "category":"Recreation",
            "type":"Entertainment"
        }
    ],
    "sg:phone":"+1 541 276 2132",
    "sg:postcode":"97801",
    "sg:province":"OR",
    "sg:tags":[
        "skating",
        "rink"
    ],
    "wof:name":"Pendleton Skate City",
    "wof:placetype":"venue"
},
  "geometry": {"coordinates":[-118.756871,45.6769],"type":"Point"}
}