{
  "type": "Feature",
  "properties": {
    "addr:full":"24375 Dodds Rd Bend OR 97701",
    "addr:housenumber":"24375",
    "addr:postcode":"97701",
    "addr:street":"Dodds Rd",
    "iso:country":"US",
    "sg:address":"24375 Dodds Rd",
    "sg:city":"Bend",
    "sg:classifiers":[
        {
            "category":"Farming",
            "subcategory":"Livestock Farm",
            "type":"Manufacturing & Wholesale Goods"
        }
    ],
    "sg:phone":"+1 541 388 2661",
    "sg:postcode":"97701",
    "sg:province":"OR",
    "sg:tags":[
        "animal",
        "general"
    ],
    "wof:name":"Bar O Ranch",
    "wof:placetype":"venue"
},
  "geometry": {"coordinates":[-121.104107,44.02943],"type":"Point"}
}