{
  "type": "Feature",
  "properties": {
    "addr:full":"1701 W Main St Medford OR 97501",
    "addr:housenumber":"1701",
    "addr:postcode":"97501",
    "addr:street":"W Main St",
    "iso:country":"US",
    "sg:address":"1701 W Main St",
    "sg:city":"Medford",
    "sg:classifiers":[
        {
            "category":"Organizations",
            "subcategory":"Religious Organization",
            "type":"Services"
        }
    ],
    "sg:phone":"+1 541 772 9640",
    "sg:postcode":"97501",
    "sg:province":"OR",
    "wof:name":"Church Of Christ",
    "wof:placetype":"venue"
},
  "geometry": {"coordinates":[-122.892589,42.323668],"type":"Point"}
}