{
  "type": "Feature",
  "properties": {
    "iso:country":"US",
    "sg:address":"727 Foxtail Rd",
    "sg:city":"Adrian",
    "sg:phone":"+1 541 724 6414",
    "sg:postcode":"97901",
    "sg:province":"OR",
    "sg:tags":[
        "farm",
        "field",
        "crop"
    ],
    "wof:name":"Fox Tail Farms",
    "wof:placetype":"venue"
},
  "geometry": {"coordinates":[-117.064002,43.715287],"type":"Point"}
}