{
  "type": "Feature",
  "properties": {
    "iso:country":"US",
    "sg:address":"198 Liberty St SE",
    "sg:city":"Salem",
    "sg:classifiers":[
        {
            "category":"Banks & Credit Unions",
            "subcategory":"Bank",
            "type":"Services"
        }
    ],
    "sg:phone":"+1 541 746 5090",
    "sg:postcode":"97301",
    "sg:province":"OR",
    "sg:tags":[
        "depository",
        "banking"
    ],
    "wof:name":"ACE Cash Express",
    "wof:placetype":"venue"
},
  "geometry": {"coordinates":[-123.03886,44.939969],"type":"Point"}
}