{
  "type": "Feature",
  "properties": {
    "addr:full":"969 Hiwan Ct Eugene OR 97405",
    "addr:housenumber":"969",
    "addr:postcode":"97405",
    "addr:street":"Hiwan Ct",
    "iso:country":"US",
    "sg:address":"969 Hiwan Ct",
    "sg:city":"Eugene",
    "sg:classifiers":[
        {
            "category":"Insurance",
            "subcategory":"Insurance Agent",
            "type":"Services"
        }
    ],
    "sg:phone":"+1 541 343 8120",
    "sg:postcode":"97405",
    "sg:province":"OR",
    "sg:website":"http://www.hgins.net",
    "wof:name":"Harvey Ginsburg Insurance",
    "wof:placetype":"venue"
},
  "geometry": {"coordinates":[-123.077237,44.008475],"type":"Point"}
}