{
  "type": "Feature",
  "properties": {
    "iso:country":"US",
    "sg:address":"825 River Ave",
    "sg:city":"Eugene",
    "sg:classifiers":[
        {
            "category":"Autos & Motor Vehicles",
            "subcategory":"Automobile Sales",
            "type":"Retail Goods"
        }
    ],
    "sg:phone":"+1 541 689 6717",
    "sg:postcode":"97404",
    "sg:province":"OR",
    "wof:name":"Pacific Northwest Auto Whl",
    "wof:placetype":"venue"
},
  "geometry": {"coordinates":[-123.11094,44.096712],"type":"Point"}
}