{
  "type": "Feature",
  "properties": {
    "addr:full":"1139 NE Grand Ave Portland OR 97232",
    "addr:housenumber":"1139",
    "addr:postcode":"97232",
    "addr:street":"Ne Grand Ave",
    "iso:country":"US",
    "sg:address":"1139 NE Grand Ave",
    "sg:city":"Portland",
    "sg:classifiers":[
        {
            "category":"Fast Food",
            "type":"Food & Drink"
        }
    ],
    "sg:phone":"+1 503 231 9223",
    "sg:postcode":"97232",
    "sg:province":"OR",
    "sg:tags":[
        "burger"
    ],
    "wof:name":"Red Robin America's Gourmet Burgers & Spirits",
    "wof:placetype":"venue"
},
  "geometry": {"coordinates":[-122.661143,45.531279],"type":"Point"}
}