{
  "type": "Feature",
  "properties": {
    "iso:country":"US",
    "sg:address":"232 E Pine St",
    "sg:city":"Central Point",
    "sg:classifiers":[
        {
            "category":"Shopping",
            "subcategory":"Used Merchandise",
            "type":"Retail Goods"
        }
    ],
    "sg:phone":"+1 541 665 2169",
    "sg:postcode":"97502",
    "sg:province":"OR",
    "wof:name":"Jay Bailey Antiques",
    "wof:placetype":"venue"
},
  "geometry": {"coordinates":[-122.915504,42.374975],"type":"Point"}
}