{
  "type": "Feature",
  "properties": {
    "iso:country":"US",
    "sg:address":"3240 Fisher Rd NE",
    "sg:city":"Salem",
    "sg:classifiers":[
        {
            "category":"Building & Trades",
            "subcategory":"Construction",
            "type":"Services"
        }
    ],
    "sg:phone":"+1 503 378 0674",
    "sg:postcode":"97305",
    "sg:province":"OR",
    "sg:tags":[
        "insulation",
        "heat",
        "contractor"
    ],
    "wof:name":"Falls Insulation Inc",
    "wof:placetype":"venue"
},
  "geometry": {"coordinates":[-122.988524,44.96746],"type":"Point"}
}