{
  "type": "Feature",
  "properties": {
    "addr:full":"1310 Main St E Monmouth OR 97361",
    "addr:housenumber":"1310",
    "addr:postcode":"97361",
    "addr:street":"Main St E",
    "iso:country":"US",
    "sg:address":"1310 Main St E",
    "sg:city":"Monmouth",
    "sg:classifiers":[
        {
            "category":"Banks & Credit Unions",
            "subcategory":"Bank",
            "type":"Services"
        }
    ],
    "sg:phone":"+1 503 606 2704",
    "sg:postcode":"97361",
    "sg:province":"OR",
    "sg:tags":[
        "state"
    ],
    "wof:name":"Oregon First Community Credit",
    "wof:placetype":"venue"
},
  "geometry": {"coordinates":[-123.220358,44.84858],"type":"Point"}
}