{
  "type": "Feature",
  "properties": {
    "iso:country":"US",
    "sg:address":"8971 SE 76th Dr",
    "sg:city":"Portland",
    "sg:classifiers":[
        {
            "category":"Manufacturing",
            "subcategory":"Metals",
            "type":"Manufacturing & Wholesale Goods"
        }
    ],
    "sg:phone":"+1 503 251 3393",
    "sg:postcode":"97206",
    "sg:province":"OR",
    "sg:tags":[
        "steel"
    ],
    "wof:name":"J C's Manufacturing",
    "wof:placetype":"venue"
},
  "geometry": {"coordinates":[-122.585795,45.458011],"type":"Point"}
}