{
  "type": "Feature",
  "properties": {
    "iso:country":"US",
    "sg:address":"2625 SE 39th Loop",
    "sg:city":"Hillsboro",
    "sg:classifiers":[
        {
            "category":"Retail",
            "subcategory":"Auto Repair",
            "type":"Services"
        }
    ],
    "sg:phone":"+1 503 648 1260",
    "sg:postcode":"97123",
    "sg:province":"OR",
    "sg:tags":[
        "general"
    ],
    "wof:name":"Bert & Jose Auto Repair",
    "wof:placetype":"venue"
},
  "geometry": {"coordinates":[-122.944031,45.499098],"type":"Point"}
}