{
  "type": "Feature",
  "properties": {
    "iso:country":"US",
    "sg:address":"3925 State St",
    "sg:city":"Salem",
    "sg:classifiers":[
        {
            "category":"Retail",
            "subcategory":"Repair Shop",
            "type":"Services"
        }
    ],
    "sg:phone":"+1 503 363 5505",
    "sg:postcode":"97301",
    "sg:province":"OR",
    "sg:tags":[
        "shaver"
    ],
    "wof:name":"Burroughs Electric Razor Ctr",
    "wof:placetype":"venue"
},
  "geometry": {"coordinates":[-122.985495,44.928017],"type":"Point"}
}