{
  "type": "Feature",
  "properties": {
    "iso:country":"US",
    "sg:address":"1633 N Rosa Parks Way",
    "sg:city":"Portland",
    "sg:classifiers":[
        {
            "category":"Shopping",
            "type":"Retail Goods"
        },
        {
            "category":"Home & Garden",
            "subcategory":"Furniture",
            "type":"Retail Goods"
        }
    ],
    "sg:phone":"+1 503 286 3120",
    "sg:postcode":"97217",
    "sg:province":"OR",
    "sg:tags":[
        "renting",
        "rent-to-own",
        "leasing",
        "store"
    ],
    "wof:name":"Dass Home Rentals",
    "wof:placetype":"venue"
},
  "geometry": {"coordinates":[-122.684029,45.569889],"type":"Point"}
}