{
  "type": "Feature",
  "properties": {
    "iso:country":"US",
    "sg:address":"1465 NW 138th Ave",
    "sg:city":"Portland",
    "sg:classifiers":[
        {
            "category":"Professional",
            "subcategory":"Computer Services",
            "type":"Services"
        }
    ],
    "sg:phone":"+1 503 526 8968",
    "sg:postcode":"97229",
    "sg:province":"OR",
    "sg:tags":[
        "prepackaged",
        "software"
    ],
    "wof:name":"Acknowledge Software",
    "wof:placetype":"venue"
},
  "geometry": {"coordinates":[-122.81870600000001,45.530944],"type":"Point"}
}