{
  "type": "Feature",
  "properties": {
    "addr:full":"10900 SW 69th Ave Portland OR 97223",
    "addr:housenumber":"10900",
    "addr:postcode":"97223",
    "addr:street":"Sw 69Th Ave",
    "iso:country":"US",
    "sg:address":"10900 SW 69th Ave",
    "sg:city":"Portland",
    "sg:classifiers":[
        {
            "category":"Restaurant",
            "type":"Food & Drink"
        }
    ],
    "sg:phone":"+1 503 246 5588",
    "sg:postcode":"97223",
    "sg:province":"OR",
    "sg:tags":[
        "traditional",
        "american"
    ],
    "wof:name":"Main Street Restaurant & Lounge",
    "wof:placetype":"venue"
},
  "geometry": {"coordinates":[-122.748001,45.440899],"type":"Point"}
}