{
  "type": "Feature",
  "properties": {
    "iso:country":"US",
    "sg:address":"333 Broadalbin St SW",
    "sg:city":"Albany",
    "sg:classifiers":[
        {
            "category":"Utilities",
            "subcategory":"Water",
            "type":"Services"
        }
    ],
    "sg:phone":"+1 541 917 7547",
    "sg:postcode":"97321",
    "sg:province":"OR",
    "sg:tags":[
        "company",
        "sewage"
    ],
    "wof:name":"Albany Water Sewer Billing",
    "wof:placetype":"venue"
},
  "geometry": {"coordinates":[-123.106986,44.635314],"type":"Point"}
}