{
  "type": "Feature",
  "properties": {
    "iso:country":"US",
    "sg:address":"6440 N Greeley Ave",
    "sg:city":"Portland",
    "sg:classifiers":[
        {
            "category":"Building & Trades",
            "subcategory":"Construction",
            "type":"Services"
        }
    ],
    "sg:phone":"+1 503 283 4448",
    "sg:postcode":"97217",
    "sg:province":"OR",
    "sg:tags":[
        "wallcoverings-installation",
        "wallpaper",
        "painting",
        "contractor"
    ],
    "wof:name":"Bruce Sanders Inc",
    "wof:placetype":"venue"
},
  "geometry": {"coordinates":[-122.695572,45.56955],"type":"Point"}
}