{
  "type": "Feature",
  "properties": {
    "addr:full":"7235 Wheatland Rd N Salem OR 97303",
    "addr:housenumber":"7235",
    "addr:postcode":"97303",
    "addr:street":"Wheatland Rd N",
    "iso:country":"US",
    "sg:address":"7235 Wheatland Rd N",
    "sg:city":"Salem",
    "sg:classifiers":[
        {
            "category":"Real Estate",
            "subcategory":"Real Estate Agent",
            "type":"Services"
        }
    ],
    "sg:phone":"+1 503 999 3388",
    "sg:postcode":"97303",
    "sg:province":"OR",
    "wof:name":"Property Alternatives",
    "wof:placetype":"venue"
},
  "geometry": {"coordinates":[-123.02529800000001,45.023903],"type":"Point"}
}