{
  "type": "Feature",
  "properties": {
    "iso:country":"US",
    "sg:address":"1555 NW 136th Ave",
    "sg:city":"Portland",
    "sg:classifiers":[
        {
            "category":"Building & Trades",
            "subcategory":"Construction",
            "type":"Services"
        }
    ],
    "sg:phone":"+1 503 310 2499",
    "sg:postcode":"97229",
    "sg:province":"OR",
    "sg:tags":[
        "house"
    ],
    "wof:name":"Herman Enterprises",
    "wof:placetype":"venue"
},
  "geometry": {"coordinates":[-122.81677999999999,45.531806],"type":"Point"}
}