{
  "type": "Feature",
  "properties": {
    "addr:full":"1606 SE Glenwood Street Portland OR 97202",
    "addr:housenumber":"1606",
    "addr:postcode":"97202",
    "addr:street":"Se Glenwood Street",
    "iso:country":"US",
    "sg:address":"1606 SE Glenwood Street",
    "sg:city":"Portland",
    "sg:classifiers":[
        {
            "category":"Professional",
            "subcategory":"Lawyer & Legal Services",
            "type":"Services"
        }
    ],
    "sg:phone":"+1 503 233 4991",
    "sg:postcode":"97202",
    "sg:province":"OR",
    "wof:name":"St Louis Gary M Atty",
    "wof:placetype":"venue"
},
  "geometry": {"coordinates":[-122.64959899999999,45.474322],"type":"Point"}
}