{
  "type": "Feature",
  "properties": {
    "iso:country":"US",
    "sg:address":"620 Spruce St",
    "sg:city":"Myrtle Point",
    "sg:classifiers":[
        {
            "category":"Cinema",
            "subcategory":"Movie Rental",
            "type":"Entertainment"
        }
    ],
    "sg:phone":"+1 541 572 3322",
    "sg:postcode":"97458",
    "sg:province":"OR",
    "sg:tags":[
        "tackle",
        "video",
        "cassette",
        "shop"
    ],
    "wof:name":"Skyline Video & Tackle",
    "wof:placetype":"venue"
},
  "geometry": {"coordinates":[-124.140754,43.064842],"type":"Point"}
}