{
  "type": "Feature",
  "properties": {
    "iso:country":"US",
    "sg:address":"7621 SE Crystal Springs Blvd",
    "sg:city":"Portland",
    "sg:classifiers":[
        {
            "category":"Building & Trades",
            "subcategory":"Landscaping Services",
            "type":"Services"
        }
    ],
    "sg:phone":"+1 503 788 9271",
    "sg:postcode":"97206",
    "sg:province":"OR",
    "sg:tags":[
        "landscape",
        "contractor"
    ],
    "wof:name":"Munoz Brothers Landscaping",
    "wof:placetype":"venue"
},
  "geometry": {"coordinates":[-122.583743,45.465155],"type":"Point"}
}