{
  "type": "Feature",
  "properties": {
    "iso:country":"US",
    "sg:address":"310 E 1st St",
    "sg:city":"Newberg",
    "sg:classifiers":[
        {
            "category":"Shopping",
            "subcategory":"Jewelry",
            "type":"Retail Goods"
        }
    ],
    "sg:phone":"+1 503 554 5997",
    "sg:postcode":"97132",
    "sg:province":"OR",
    "sg:tags":[
        "jeweler"
    ],
    "wof:name":"Gem Nitch",
    "wof:placetype":"venue"
},
  "geometry": {"coordinates":[-122.977034,45.300256],"type":"Point"}
}