{
  "type": "Feature",
  "properties": {
    "addr:full":"1080 NW Wallace Rd Mcminnville OR 97128",
    "addr:housenumber":"1080",
    "addr:postcode":"97128",
    "addr:street":"Nw Wallace Rd",
    "iso:country":"US",
    "sg:address":"1080 NW Wallace Rd",
    "sg:city":"Mcminnville",
    "sg:classifiers":[
        {
            "category":"Wholesale",
            "subcategory":"Hardware",
            "type":"Manufacturing & Wholesale Goods"
        }
    ],
    "sg:phone":"+1 503 435 2659",
    "sg:postcode":"97128",
    "sg:province":"OR",
    "sg:tags":[
        "tool"
    ],
    "wof:name":"Davis Tool & Equipment",
    "wof:placetype":"venue"
},
  "geometry": {"coordinates":[-123.210156,45.213694],"type":"Point"}
}