{
  "type": "Feature",
  "properties": {
    "addr:full":"13915 SW Aerie Dr Portland OR 97223",
    "addr:housenumber":"13915",
    "addr:postcode":"97223",
    "addr:street":"Sw Aerie Dr",
    "iso:country":"US",
    "sg:address":"13915 SW Aerie Dr",
    "sg:city":"Portland",
    "sg:classifiers":[
        {
            "category":"Home & Garden",
            "subcategory":"Garden Supply",
            "type":"Retail Goods"
        }
    ],
    "sg:phone":"+1 503 524 6951",
    "sg:postcode":"97223",
    "sg:province":"OR",
    "sg:tags":[
        "embroidery"
    ],
    "wof:name":"Campus Activewear Corp",
    "wof:placetype":"venue"
},
  "geometry": {"coordinates":[-122.805379,45.419318],"type":"Point"}
}