{
  "type": "Feature",
  "properties": {
    "addr:full":"2029 NE Burnside Rd Gresham OR 97030",
    "addr:housenumber":"2029",
    "addr:postcode":"97030",
    "addr:street":"Ne Burnside Rd",
    "iso:country":"US",
    "sg:address":"2029 NE Burnside Rd",
    "sg:city":"Gresham",
    "sg:classifiers":[
        {
            "category":"Banks & Credit Unions",
            "subcategory":"Financial Services",
            "type":"Services"
        }
    ],
    "sg:phone":"+1 503 669 1334",
    "sg:postcode":"97030",
    "sg:province":"OR",
    "sg:tags":[
        "cashing",
        "loan",
        "payday",
        "alternative",
        "check"
    ],
    "sg:website":"http://www.acecashexpress.com",
    "wof:name":"ACE Cash Express",
    "wof:placetype":"venue"
},
  "geometry": {"coordinates":[-122.412075,45.500012],"type":"Point"}
}