{
  "type": "Feature",
  "properties": {
    "addr:full":"2567 SE Tualatin Valley Hwy Hillsboro OR 97123",
    "addr:housenumber":"2567",
    "addr:postcode":"97123",
    "addr:street":"Se Tualatin Valley Hwy",
    "iso:country":"US",
    "sg:address":"2567 SE Tualatin Valley Hwy",
    "sg:city":"Hillsboro",
    "sg:classifiers":[
        {
            "category":"Personal",
            "subcategory":"Beauty Salon",
            "type":"Services"
        }
    ],
    "sg:phone":"+1 503 640 0115",
    "sg:postcode":"97123",
    "sg:province":"OR",
    "sg:tags":[
        "shop"
    ],
    "wof:name":"Supercuts",
    "wof:placetype":"venue"
},
  "geometry": {"coordinates":[-122.957435,45.505717],"type":"Point"}
}