{
  "type": "Feature",
  "properties": {
    "iso:country":"US",
    "sg:address":"575 US Hwy 101",
    "sg:city":"Florence",
    "sg:classifiers":[
        {
            "category":"Shopping",
            "subcategory":"Used Merchandise",
            "type":"Retail Goods"
        }
    ],
    "sg:phone":"+1 541 902 7986",
    "sg:postcode":"97439",
    "sg:province":"OR",
    "sg:tags":[
        "antique"
    ],
    "wof:name":"Brown Dog Gifts & Antiques",
    "wof:placetype":"venue"
},
  "geometry": {"coordinates":[-124.105812,43.970914],"type":"Point"}
}