{
  "type": "Feature",
  "properties": {
    "iso:country":"US",
    "sg:address":"3 Monroe Pkwy",
    "sg:city":"Lake Oswego",
    "sg:classifiers":[
        {
            "category":"Building & Trades",
            "subcategory":"Locksmith",
            "type":"Services"
        }
    ],
    "sg:phone":"+1 503 447 5704",
    "sg:postcode":"97035",
    "sg:province":"OR",
    "sg:tags":[
        "key"
    ],
    "wof:name":"Locksmith",
    "wof:placetype":"venue"
},
  "geometry": {"coordinates":[-122.702737,45.432355],"type":"Point"}
}