{
  "type": "Feature",
  "properties": {
    "addr:full":"1655 SW Odem Medo Rd Redmond OR 97756",
    "addr:housenumber":"1655",
    "addr:postcode":"97756",
    "addr:street":"Sw;Medo Rd",
    "iso:country":"US",
    "sg:address":"1655 SW Odem Medo Rd",
    "sg:city":"Redmond",
    "sg:classifiers":[
        {
            "category":"Restaurant",
            "type":"Food & Drink"
        }
    ],
    "sg:phone":"+1 541 548 6808",
    "sg:postcode":"97756",
    "sg:province":"OR",
    "sg:tags":[
        "eating"
    ],
    "wof:name":"Irls Place",
    "wof:placetype":"venue"
},
  "geometry": {"coordinates":[-121.18494,44.252016],"type":"Point"}
}