{
  "type": "Feature",
  "properties": {
    "iso:country":"US",
    "sg:address":"15844 SE 114th Ave",
    "sg:city":"Clackamas",
    "sg:classifiers":[
        {
            "category":"Wholesale",
            "subcategory":"Groceries",
            "type":"Manufacturing & Wholesale Goods"
        }
    ],
    "sg:phone":"+1 503 557 1172",
    "sg:postcode":"97015",
    "sg:province":"OR",
    "sg:tags":[
        "product",
        "meat",
        "processing",
        "equipment",
        "cure",
        "spice"
    ],
    "wof:name":"Clark Meat Processing Products",
    "wof:placetype":"venue"
},
  "geometry": {"coordinates":[-122.551902,45.407916],"type":"Point"}
}