{
  "type": "Feature",
  "properties": {
    "iso:country":"US",
    "sg:address":"1404 S Beaver Creek Rd",
    "sg:city":"Seal Rock",
    "sg:classifiers":[
        {
            "category":"Manufacturing",
            "subcategory":"Lumber",
            "type":"Manufacturing & Wholesale Goods"
        }
    ],
    "sg:phone":"+1 541 563 4731",
    "sg:postcode":"97376",
    "sg:province":"OR",
    "sg:tags":[
        "logging"
    ],
    "wof:name":"Peterson Timber Cutting",
    "wof:placetype":"venue"
},
  "geometry": {"coordinates":[-124.050913,44.506373],"type":"Point"}
}