{
  "type": "Feature",
  "properties": {
    "iso:country":"US",
    "sg:address":"57300 N Bank Rd",
    "sg:city":"Mc Kenzie Bridge",
    "sg:classifiers":[
        {
            "category":"Wholesale",
            "subcategory":"Toys & Hobbies",
            "type":"Manufacturing & Wholesale Goods"
        }
    ],
    "sg:phone":"+1 541 822 6223",
    "sg:postcode":"97413",
    "sg:province":"OR",
    "sg:tags":[
        "wholesaler"
    ],
    "wof:name":"Galt Enterprises LTD",
    "wof:placetype":"venue"
},
  "geometry": {"coordinates":[-122.144893,44.178886],"type":"Point"}
}