{
  "type": "Feature",
  "properties": {
    "iso:country":"US",
    "sg:address":"2650 NE M L King Boulevard",
    "sg:city":"Portland",
    "sg:classifiers":[
        {
            "category":"Shopping",
            "subcategory":"Bicycles & Sporting Goods",
            "type":"Retail Goods"
        },
        {
            "category":"Shopping",
            "subcategory":"Shoes",
            "type":"Retail Goods"
        }
    ],
    "sg:phone":"+1 503 281 5901",
    "sg:postcode":"97212",
    "sg:province":"OR",
    "sg:tags":[
        "store"
    ],
    "wof:name":"Nike Factory Outlet",
    "wof:placetype":"venue"
},
  "geometry": {"coordinates":[-122.661379,45.541678],"type":"Point"}
}