{
  "type": "Feature",
  "properties": {
    "addr:full":"Legacy Emanuel Hospital and Health Center 2801 N. Gantenbein Avenue, Room 2012 Portland OR 97227",
    "addr:housenumber":"2801;2012",
    "addr:postcode":"portland;97227",
    "addr:street":"N. Gantenbein Avenue Room",
    "iso:country":"US",
    "sg:address":"Legacy Emanuel Hospital and Health Center 2801 N. Gantenbein Avenue, Room 2012",
    "sg:city":"Portland",
    "sg:classifiers":[
        {
            "category":"Education",
            "subcategory":"Special Training",
            "type":"Public Place"
        }
    ],
    "sg:phone":"+1 503 413 4960",
    "sg:postcode":"97227",
    "sg:province":"OR",
    "sg:tags":[
        "school",
        "specialty"
    ],
    "sg:website":"www.legacyhealth.org/body.cfm?id...",
    "wof:name":"Trauma Nurses Talk Tough",
    "wof:placetype":"venue"
},
  "geometry": {"coordinates":[-122.671038,45.544511],"type":"Point"}
}