{
  "type": "Feature",
  "properties": {
    "iso:country":"US",
    "sg:address":"9845 SW Barbur Boulevard",
    "sg:city":"Portland",
    "sg:classifiers":[
        {
            "category":"Food & Beverages",
            "subcategory":"Ethnic Foods",
            "type":"Retail Goods"
        },
        {
            "category":"Food & Beverages",
            "subcategory":"Groceries & Convenience Stores",
            "type":"Retail Goods"
        }
    ],
    "sg:phone":"+1 503 244 0670",
    "sg:postcode":"97219",
    "sg:province":"OR",
    "sg:website":"www.barburworldfoods.com/",
    "wof:name":"Barbur World Foods",
    "wof:placetype":"venue"
},
  "geometry": {"coordinates":[-122.71816,45.454607],"type":"Point"}
}