{
  "type": "Feature",
  "properties": {
    "addr:full":"1148 Walker Rd NE Salem OR 97301",
    "addr:housenumber":"1148",
    "addr:postcode":"97301",
    "addr:street":"Walker Rd Ne",
    "iso:country":"US",
    "sg:address":"1148 Walker Rd NE",
    "sg:city":"Salem",
    "sg:classifiers":[
        {
            "category":"Home & Garden",
            "subcategory":"Building Materials",
            "type":"Retail Goods"
        },
        {
            "category":"Building & Trades",
            "subcategory":"Construction",
            "type":"Services"
        }
    ],
    "sg:phone":"+1 503 585 9391",
    "sg:postcode":"97301",
    "sg:province":"OR",
    "sg:tags":[
        "concrete",
        "staining",
        "contractor"
    ],
    "wof:name":"Lee, Jerome Concrete Finshg Co Inc",
    "wof:placetype":"venue"
},
  "geometry": {"coordinates":[-122.96314700000001,44.943362],"type":"Point"}
}