{
  "type": "Feature",
  "properties": {
    "iso:country":"US",
    "sg:address":"2310 Perkins St NE",
    "sg:city":"Salem",
    "sg:classifiers":[
        {
            "category":"Social Services",
            "subcategory":"Child Care",
            "type":"Services"
        }
    ],
    "sg:phone":"+1 503 390 8486",
    "sg:postcode":"97303",
    "sg:province":"OR",
    "sg:tags":[
        "school",
        "nursery",
        "day"
    ],
    "wof:name":"Ch Nursery",
    "wof:placetype":"venue"
},
  "geometry": {"coordinates":[-123.004074,45.027942],"type":"Point"}
}