{
  "type": "Feature",
  "properties": {
    "iso:country":"US",
    "sg:address":"4690 Old Dillard Rd",
    "sg:city":"Eugene",
    "sg:classifiers":[
        {
            "category":"Health Services",
            "subcategory":"Doctor",
            "type":"Services"
        }
    ],
    "sg:phone":"+1 541 344 8507",
    "sg:postcode":"97405",
    "sg:province":"OR",
    "sg:tags":[
        "medical",
        "care"
    ],
    "wof:name":"William Gutheim",
    "wof:placetype":"venue"
},
  "geometry": {"coordinates":[-123.069499,44.000678],"type":"Point"}
}