{
  "type": "Feature",
  "properties": {
    "iso:country":"US",
    "sg:address":"2194 Maplewood Dr S",
    "sg:city":"Salem",
    "sg:classifiers":[
        {
            "category":"Autos & Motor Vehicles",
            "subcategory":"Automobile Sales",
            "type":"Retail Goods"
        }
    ],
    "sg:phone":"+1 503 364 7045",
    "sg:postcode":"97306",
    "sg:province":"OR",
    "sg:tags":[
        "painting",
        "contractor"
    ],
    "wof:name":"Gallaghers Auto Sales",
    "wof:placetype":"venue"
},
  "geometry": {"coordinates":[-123.074535,44.877029],"type":"Point"}
}