{
  "type": "Feature",
  "properties": {
    "iso:country":"US",
    "sg:address":"41558 Sass Rd",
    "sg:city":"Richland",
    "sg:classifiers":[
        {
            "category":"Farming",
            "subcategory":"Farm",
            "type":"Manufacturing & Wholesale Goods"
        }
    ],
    "sg:phone":"+1 541 893 6789",
    "sg:postcode":"97870",
    "sg:province":"OR",
    "sg:tags":[
        "crop",
        "general"
    ],
    "wof:name":"Sue Clemens",
    "wof:placetype":"venue"
},
  "geometry": {"coordinates":[-117.177024,44.754539],"type":"Point"}
}