{
  "type": "Feature",
  "properties": {
    "addr:full":"2401 NE M L King Blvd Portland OR 97212",
    "addr:housenumber":"2401",
    "addr:postcode":"97212",
    "addr:street":"Ne M L King Blvd",
    "iso:country":"US",
    "sg:address":"2401 NE M L King Blvd",
    "sg:city":"Portland",
    "sg:classifiers":[
        {
            "category":"Structure",
            "subcategory":"Office Building",
            "type":"Public Place"
        }
    ],
    "sg:phone":"+1 503 282 4696",
    "sg:postcode":"97212",
    "sg:province":"OR",
    "sg:tags":[
        "park"
    ],
    "wof:name":"Bartoo Properties",
    "wof:placetype":"venue"
},
  "geometry": {"coordinates":[-122.66165100000001,45.539989],"type":"Point"}
}