{
  "type": "Feature",
  "properties": {
    "iso:country":"US",
    "sg:address":"1045 Commercial St SE",
    "sg:city":"Salem",
    "sg:classifiers":[
        {
            "category":"Professional",
            "type":"Services"
        }
    ],
    "sg:phone":"+1 503 375 5777",
    "sg:postcode":"97302",
    "sg:province":"OR",
    "wof:name":"A New ERA Mobile Dj Services",
    "wof:placetype":"venue"
},
  "geometry": {"coordinates":[-123.044161,44.930678],"type":"Point"}
}