{
  "type": "Feature",
  "properties": {
    "iso:country":"US",
    "sg:address":"8080 S C St",
    "sg:city":"Springfield",
    "sg:classifiers":[
        {
            "category":"Professional",
            "type":"Services"
        }
    ],
    "sg:phone":"+1 541 744 4459",
    "sg:postcode":"97478",
    "sg:province":"OR",
    "wof:name":"Teas To Please",
    "wof:placetype":"venue"
},
  "geometry": {"coordinates":[-122.88253899999999,44.044622],"type":"Point"}
}