{
  "type": "Feature",
  "properties": {
    "iso:country":"US",
    "sg:address":"1005 NE 17th Ave",
    "sg:city":"Hillsboro",
    "sg:classifiers":[
        {
            "category":"Health Services",
            "subcategory":"Nursing And Care Facility",
            "type":"Services"
        },
        {
            "category":"Social Services",
            "subcategory":"Retirement Home",
            "type":"Services"
        },
        {
            "category":"Social Services",
            "subcategory":"Adult Care",
            "type":"Services"
        }
    ],
    "sg:phone":"+1 503 640 2884",
    "sg:postcode":"97124",
    "sg:province":"OR",
    "sg:tags":[
        "living",
        "apartment",
        "people",
        "assisted",
        "hotel",
        "community",
        "elder",
        "homes-elderly"
    ],
    "sg:website":"http://www.cornell-estates.com",
    "wof:name":"Cornell Estates Retirement & Assisted Living",
    "wof:placetype":"venue"
},
  "geometry": {"coordinates":[-122.964476,45.531691],"type":"Point"}
}