{
  "type": "Feature",
  "properties": {
    "addr:full":"2900 SE Steele St Portland OR 97202",
    "addr:housenumber":"2900",
    "addr:postcode":"97202",
    "addr:street":"Se Steele St",
    "iso:country":"US",
    "sg:address":"2900 SE Steele St",
    "sg:city":"Portland",
    "sg:classifiers":[
        {
            "category":"Health Services",
            "subcategory":"Doctor",
            "type":"Services"
        }
    ],
    "sg:phone":"+1 503 230 2501",
    "sg:postcode":"97202",
    "sg:province":"OR",
    "wof:name":"Eastmoreland Osteopathic Services",
    "wof:placetype":"venue"
},
  "geometry": {"coordinates":[-122.636002,45.484699],"type":"Point"}
}