{
  "type": "Feature",
  "properties": {
    "addr:full":"775 E Vilas Rd Central Point OR 97502",
    "addr:housenumber":"775",
    "addr:postcode":"97502",
    "addr:street":"E Vilas Rd",
    "iso:country":"US",
    "sg:address":"775 E Vilas Rd",
    "sg:city":"Central Point",
    "sg:classifiers":[
        {
            "category":"Professional",
            "type":"Services"
        }
    ],
    "sg:phone":"+1 541 772 6377",
    "sg:postcode":"97502",
    "sg:province":"OR",
    "wof:name":"Mobile Fleet Service",
    "wof:placetype":"venue"
},
  "geometry": {"coordinates":[-122.8686,42.389288],"type":"Point"}
}