{
  "type": "Feature",
  "properties": {
    "iso:country":"US",
    "sg:address":"1216 SW Hart St",
    "sg:city":"Madras",
    "sg:classifiers":[
        {
            "category":"Manufacturing",
            "subcategory":"Tools & Machinery",
            "type":"Manufacturing & Wholesale Goods"
        }
    ],
    "sg:phone":"+1 541 475 3107",
    "sg:postcode":"97741",
    "sg:province":"OR",
    "sg:tags":[
        "machine",
        "shop",
        "welding",
        "supply"
    ],
    "wof:name":"Hart Machine Co",
    "wof:placetype":"venue"
},
  "geometry": {"coordinates":[-121.1356,44.618633],"type":"Point"}
}