{
  "type": "Feature",
  "properties": {
    "iso:country":"US",
    "sg:address":"201 NE Savage St",
    "sg:city":"Grants Pass",
    "sg:classifiers":[
        {
            "category":"Social Services",
            "type":"Services"
        }
    ],
    "sg:phone":"+1 541 956 9560",
    "sg:postcode":"97526",
    "sg:province":"OR",
    "sg:tags":[
        "counselor",
        "marriage",
        "family"
    ],
    "wof:name":"Wellspring Counseling Ctr",
    "wof:placetype":"venue"
},
  "geometry": {"coordinates":[-123.31762500000001,42.451461],"type":"Point"}
}