{
  "type": "Feature",
  "properties": {
    "addr:full":"63375 Boyd Acres Rd Bend OR 97701",
    "addr:housenumber":"63375",
    "addr:postcode":"97701",
    "addr:street":"Boyd Acres Rd",
    "iso:country":"US",
    "sg:address":"63375 Boyd Acres Rd",
    "sg:city":"Bend",
    "sg:classifiers":[
        {
            "category":"Professional",
            "subcategory":"Business Services",
            "type":"Services"
        }
    ],
    "sg:phone":"+1 541 388 2250",
    "sg:postcode":"97701",
    "sg:province":"OR",
    "wof:name":"Dlh Construction",
    "wof:placetype":"venue"
},
  "geometry": {"coordinates":[-121.28828,44.101354],"type":"Point"}
}