{
  "type": "Feature",
  "properties": {
    "iso:country":"US",
    "sg:address":"1280 W Airway Rd",
    "sg:city":"Lebanon",
    "sg:classifiers":[
        {
            "category":"Building & Trades",
            "subcategory":"Plumbing",
            "type":"Services"
        }
    ],
    "sg:phone":"+1 541 451 1441",
    "sg:postcode":"97355",
    "sg:province":"OR",
    "sg:tags":[
        "contractor"
    ],
    "wof:name":"Ti Tech Specialties",
    "wof:placetype":"venue"
},
  "geometry": {"coordinates":[-122.927865,44.533905],"type":"Point"}
}