{
  "type": "Feature",
  "properties": {
    "addr:full":"9665 SW Allen Blvd Beaverton OR 97005",
    "addr:housenumber":"9665",
    "addr:postcode":"97005",
    "addr:street":"Sw Allen Blvd",
    "iso:country":"US",
    "sg:address":"9665 SW Allen Blvd",
    "sg:city":"Beaverton",
    "sg:classifiers":[
        {
            "category":"Sports & Exercise",
            "subcategory":"Golf",
            "type":"Entertainment"
        },
        {
            "category":"Building & Trades",
            "subcategory":"Construction",
            "type":"Services"
        }
    ],
    "sg:phone":"+1 503 644 7676",
    "sg:postcode":"97005",
    "sg:province":"OR",
    "sg:tags":[
        "course",
        "public"
    ],
    "sg:website":"www.allseasonsgolf.com",
    "wof:name":"All Seasons Putting Greens",
    "wof:placetype":"venue"
},
  "geometry": {"coordinates":[-122.77845600000001,45.474361],"type":"Point"}
}