{
  "type": "Feature",
  "properties": {
    "iso:country":"US",
    "sg:address":"5200 SW Macadam Ave Ste 470",
    "sg:city":"Portland",
    "sg:classifiers":[
        {
            "category":"Organizations",
            "subcategory":"Non-profit Organization",
            "type":"Services"
        }
    ],
    "sg:phone":"+1 503 221 5117",
    "sg:postcode":"97239",
    "sg:province":"OR",
    "sg:tags":[
        "charity",
        "foundations-educational",
        "philanthropic",
        "research"
    ],
    "wof:name":"Merli & Ellen Morgan Gift Fund",
    "wof:placetype":"venue"
},
  "geometry": {"coordinates":[-122.675392,45.48568],"type":"Point"}
}