{
  "type": "Feature",
  "properties": {
    "iso:country":"US",
    "sg:address":"150 Patrick Ln",
    "sg:city":"Ashland",
    "sg:classifiers":[
        {
            "category":"Home & Garden",
            "subcategory":"Building Materials",
            "type":"Retail Goods"
        },
        {
            "category":"Manufacturing",
            "subcategory":"Glass & Minerals",
            "type":"Manufacturing & Wholesale Goods"
        }
    ],
    "sg:phone":"+1 541 488 0666",
    "sg:postcode":"97520",
    "sg:province":"OR",
    "sg:tags":[
        "product",
        "leaded",
        "mfg"
    ],
    "wof:name":"Canterbury Stained Glass Co",
    "wof:placetype":"venue"
},
  "geometry": {"coordinates":[-122.742588,42.210542],"type":"Point"}
}