{
  "type": "Feature",
  "properties": {
    "iso:country":"US",
    "sg:address":"7440 N Denver Avenue",
    "sg:city":"Portland",
    "sg:classifiers":[
        {
            "category":"Retail",
            "subcategory":"Portrait Studio",
            "type":"Services"
        },
        {
            "category":"Shopping",
            "subcategory":"Pharmacy",
            "type":"Retail Goods"
        }
    ],
    "sg:phone":"+1 503 286 5680",
    "sg:postcode":"97217",
    "sg:province":"OR",
    "sg:tags":[
        "photography",
        "drugstore",
        "store"
    ],
    "sg:website":"www.riteaid.com",
    "wof:name":"Rite Aid Pharmacies",
    "wof:placetype":"venue"
},
  "geometry": {"coordinates":[-122.687423,45.576717],"type":"Point"}
}