{
  "type": "Feature",
  "properties": {
    "iso:country":"US",
    "sg:address":"170 N Main St",
    "sg:city":"Prineville",
    "sg:classifiers":[
        {
            "category":"Social Services",
            "type":"Services"
        }
    ],
    "sg:phone":"+1 541 447 6429",
    "sg:postcode":"97754",
    "sg:province":"OR",
    "wof:name":"Soroptimist Shuttle Bus",
    "wof:placetype":"venue"
},
  "geometry": {"coordinates":[-120.846981,44.301407],"type":"Point"}
}