{
  "type": "Feature",
  "properties": {
    "iso:country":"US",
    "sg:address":"18154 SW Arborcrest Ct",
    "sg:city":"Beaverton",
    "sg:classifiers":[
        {
            "category":"Professional",
            "subcategory":"Management & Consulting",
            "type":"Services"
        }
    ],
    "sg:phone":"+1 503 356 9810",
    "sg:postcode":"97006",
    "sg:province":"OR",
    "wof:name":"JPS Direct Marketing",
    "wof:placetype":"venue"
},
  "geometry": {"coordinates":[-122.863799,45.498983],"type":"Point"}
}