{
  "type": "Feature",
  "properties": {
    "iso:country":"US",
    "sg:address":"245 Blair Blvd",
    "sg:city":"Eugene",
    "sg:classifiers":[
        {
            "category":"Manufacturing",
            "subcategory":"Printing",
            "type":"Manufacturing & Wholesale Goods"
        }
    ],
    "sg:phone":"+1 541 484 6928",
    "sg:postcode":"97402",
    "sg:province":"OR",
    "sg:tags":[
        "multimedia"
    ],
    "wof:name":"Northwest Beat",
    "wof:placetype":"venue"
},
  "geometry": {"coordinates":[-123.110996,44.057455],"type":"Point"}
}