{
  "type": "Feature",
  "properties": {
    "iso:country":"US",
    "sg:address":"1925 River Rd",
    "sg:city":"Eugene",
    "sg:classifiers":[
        {
            "category":"Wholesale",
            "subcategory":"Machinery & Supplies",
            "type":"Manufacturing & Wholesale Goods"
        }
    ],
    "sg:phone":"+1 541 689 3513",
    "sg:postcode":"97404",
    "sg:province":"OR",
    "sg:tags":[
        "printer",
        "cartridge"
    ],
    "wof:name":"Rapid Refill Ink",
    "wof:placetype":"venue"
},
  "geometry": {"coordinates":[-123.12685500000001,44.092818],"type":"Point"}
}