{
  "type": "Feature",
  "properties": {
    "iso:country":"US",
    "sg:address":"29765 Clear Lake Rd",
    "sg:city":"Eugene",
    "sg:classifiers":[
        {
            "category":"Professional",
            "subcategory":"Detective & Security Services",
            "type":"Services"
        }
    ],
    "sg:phone":"+1 541 461 5992",
    "sg:postcode":"97402",
    "sg:province":"OR",
    "sg:tags":[
        "information",
        "bureau"
    ],
    "wof:name":"Adept Professional Services",
    "wof:placetype":"venue"
},
  "geometry": {"coordinates":[-123.173976,44.103249],"type":"Point"}
}