{
  "type": "Feature",
  "properties": {
    "iso:country":"US",
    "sg:address":"5251 Commercial St SE",
    "sg:city":"Salem",
    "sg:classifiers":[
        {
            "category":"Personal",
            "subcategory":"Beauty Salon",
            "type":"Services"
        }
    ],
    "sg:phone":"+1 503 371 6288",
    "sg:postcode":"97306",
    "sg:province":"OR",
    "sg:tags":[
        "shop"
    ],
    "wof:name":"Salon Gorgeous",
    "wof:placetype":"venue"
},
  "geometry": {"coordinates":[-123.028368,44.879213],"type":"Point"}
}