{
  "type": "Feature",
  "properties": {
    "addr:full":"1096 E Juniper Ave Hermiston OR 97838",
    "addr:housenumber":"1096",
    "addr:postcode":"97838",
    "addr:street":"E Juniper Ave",
    "iso:country":"US",
    "sg:address":"1096 E Juniper Ave",
    "sg:city":"Hermiston",
    "sg:classifiers":[
        {
            "category":"Real Estate",
            "subcategory":"Architect",
            "type":"Services"
        }
    ],
    "sg:phone":"+1 541 567 2730",
    "sg:postcode":"97838",
    "sg:province":"OR",
    "sg:tags":[
        "architectural"
    ],
    "wof:name":"B & W Design",
    "wof:placetype":"venue"
},
  "geometry": {"coordinates":[-119.26674300000001,45.836746],"type":"Point"}
}