{
  "type": "Feature",
  "properties": {
    "iso:country":"US",
    "sg:address":"1030 NW Hillside Dr",
    "sg:city":"Grants Pass",
    "sg:classifiers":[
        {
            "category":"Building & Trades",
            "subcategory":"Construction",
            "type":"Services"
        }
    ],
    "sg:phone":"+1 541 476 3044",
    "sg:postcode":"97526",
    "sg:province":"OR",
    "sg:tags":[
        "clearing",
        "land",
        "leveling"
    ],
    "wof:name":"Tim Cayton General Contracting",
    "wof:placetype":"venue"
},
  "geometry": {"coordinates":[-123.336901,42.448319],"type":"Point"}
}