{
  "type": "Feature",
  "properties": {
    "iso:country":"US",
    "sg:address":"5921 NW Alfalfa Dr",
    "sg:city":"Portland",
    "sg:classifiers":[
        {
            "category":"Banks & Credit Unions",
            "subcategory":"Bank",
            "type":"Services"
        }
    ],
    "sg:phone":"+1 503 502 8006",
    "sg:postcode":"97229",
    "sg:province":"OR",
    "sg:tags":[
        "broker",
        "mortgage"
    ],
    "wof:name":"Holden Mortgage Services Corp",
    "wof:placetype":"venue"
},
  "geometry": {"coordinates":[-122.839097,45.562875],"type":"Point"}
}