{
  "type": "Feature",
  "properties": {
    "iso:country":"US",
    "sg:address":"21970 NW Imbrie Dr",
    "sg:city":"Hillsboro",
    "sg:classifiers":[
        {
            "category":"Personal",
            "type":"Services"
        }
    ],
    "sg:phone":"+1 503 693 9169",
    "sg:postcode":"97124",
    "sg:province":"OR",
    "sg:tags":[
        "consultant",
        "program",
        "health",
        "fitness"
    ],
    "wof:name":"Body Of Change",
    "wof:placetype":"venue"
},
  "geometry": {"coordinates":[-122.90772699999999,45.549253],"type":"Point"}
}