{
  "type": "Feature",
  "properties": {
    "iso:country":"US",
    "sg:address":"800 NW Starker Ave",
    "sg:city":"Corvallis",
    "sg:classifiers":[
        {
            "category":"Manufacturing",
            "subcategory":"Printing",
            "type":"Manufacturing & Wholesale Goods"
        }
    ],
    "sg:phone":"+1 541 753 4179",
    "sg:postcode":"97330",
    "sg:province":"OR",
    "sg:tags":[
        "multimedia"
    ],
    "wof:name":"Path Works Inc",
    "wof:placetype":"venue"
},
  "geometry": {"coordinates":[-123.259552,44.578693],"type":"Point"}
}