{
  "type": "Feature",
  "properties": {
    "iso:country":"US",
    "sg:address":"5155 Silverton Rd NE",
    "sg:city":"Salem",
    "sg:classifiers":[
        {
            "category":"Government",
            "subcategory":"Office",
            "type":"Public Place"
        }
    ],
    "sg:phone":"+1 503 588 5084",
    "sg:postcode":"97305",
    "sg:province":"OR",
    "wof:name":"Brooks Community Sewer Dist",
    "wof:placetype":"venue"
},
  "geometry": {"coordinates":[-122.95489000000001,44.97372],"type":"Point"}
}