{
  "type": "Feature",
  "properties": {
    "iso:country":"US",
    "sg:address":"577 W Monroe St",
    "sg:city":"Burns",
    "sg:classifiers":[
        {
            "category":"Travel",
            "subcategory":"Hotels & Motels",
            "type":"Entertainment"
        }
    ],
    "sg:phone":"+1 541 573 2047",
    "sg:postcode":"97720",
    "sg:province":"OR",
    "sg:tags":[
        "lodging"
    ],
    "sg:website":"http://www.daysinn.com",
    "wof:name":"Days Inn Burns",
    "wof:placetype":"venue"
},
  "geometry": {"coordinates":[-119.060563,43.585732],"type":"Point"}
}