{
  "type": "Feature",
  "properties": {
    "iso:country":"US",
    "sg:address":"17688 S Anderson Rd",
    "sg:city":"Oregon City",
    "sg:classifiers":[
        {
            "category":"Freight",
            "type":"Transportation"
        }
    ],
    "sg:phone":"+1 503 631 8874",
    "sg:postcode":"97045",
    "sg:province":"OR",
    "sg:tags":[
        "operator",
        "local",
        "trucking"
    ],
    "wof:name":"Steve Graham Trucking Inc",
    "wof:placetype":"venue"
},
  "geometry": {"coordinates":[-122.538105,45.349646],"type":"Point"}
}