{
  "type": "Feature",
  "properties": {
    "addr:full":"84506 Edwards Rd Milton Freewater OR 97862",
    "addr:housenumber":"84506",
    "addr:postcode":"97862",
    "addr:street":"Edwards Rd;Freewater",
    "iso:country":"US",
    "sg:address":"84506 Edwards Rd",
    "sg:city":"Milton Freewater",
    "sg:classifiers":[
        {
            "category":"Wholesale",
            "subcategory":"Groceries",
            "type":"Manufacturing & Wholesale Goods"
        }
    ],
    "sg:phone":"+1 541 938 6101",
    "sg:postcode":"97862",
    "sg:province":"OR",
    "sg:tags":[
        "general"
    ],
    "wof:name":"Martinez Produce",
    "wof:placetype":"venue"
},
  "geometry": {"coordinates":[-118.46021399999999,45.975845],"type":"Point"}
}