{
  "type": "Feature",
  "properties": {
    "addr:full":"400 Lake Creek Lp Rd Eagle Point OR 97524",
    "addr:housenumber":"400",
    "addr:postcode":"97524",
    "addr:street":"Lake Creek Lp Rd",
    "iso:country":"US",
    "sg:address":"400 Lake Creek Lp Rd",
    "sg:city":"Eagle Point",
    "sg:classifiers":[
        {
            "category":"Banks & Credit Unions",
            "subcategory":"Financial Services",
            "type":"Services"
        }
    ],
    "sg:phone":"+1 541 826 9532",
    "sg:postcode":"97524",
    "sg:province":"OR",
    "sg:tags":[
        "trust",
        "management"
    ],
    "wof:name":"Wj Trust",
    "wof:placetype":"venue"
},
  "geometry": {"coordinates":[-122.605114,42.428346],"type":"Point"}
}