{
  "type": "Feature",
  "properties": {
    "iso:country":"US",
    "sg:address":"201 Cascade Ave",
    "sg:city":"Hood River",
    "sg:classifiers":[
        {
            "category":"Shopping",
            "subcategory":"Bicycles & Sporting Goods",
            "type":"Retail Goods"
        }
    ],
    "sg:phone":"+1 541 386 3861",
    "sg:postcode":"97031",
    "sg:province":"OR",
    "sg:tags":[
        "equipment",
        "surfing",
        "wind"
    ],
    "wof:name":"Windwing Design",
    "wof:placetype":"venue"
},
  "geometry": {"coordinates":[-121.513295,45.709568],"type":"Point"}
}