{
  "type": "Feature",
  "properties": {
    "addr:full":"491 Country Club Rd Lake Oswego OR 97034",
    "addr:housenumber":"491",
    "addr:postcode":"97034",
    "addr:street":"Country Club Rd",
    "iso:country":"US",
    "sg:address":"491 Country Club Rd",
    "sg:city":"Lake Oswego",
    "sg:classifiers":[
        {
            "category":"Professional",
            "subcategory":"Lawyer & Legal Services",
            "type":"Services"
        }
    ],
    "sg:phone":"+1 503 636 1403",
    "sg:postcode":"97034",
    "sg:province":"OR",
    "wof:name":"Luetjen Calvin H Atty",
    "wof:placetype":"venue"
},
  "geometry": {"coordinates":[-122.67800099999999,45.422501],"type":"Point"}
}