{
  "type": "Feature",
  "properties": {
    "addr:full":"7745 NE Sandy Boulevard Portland OR 97213",
    "addr:housenumber":"7745",
    "addr:postcode":"97213",
    "addr:street":"Ne Sandy Boulevard",
    "iso:country":"US",
    "sg:address":"7745 NE Sandy Boulevard",
    "sg:city":"Portland",
    "sg:classifiers":[
        {
            "category":"Retail",
            "subcategory":"Auto Repair",
            "type":"Services"
        }
    ],
    "sg:phone":"+1 503 288 8101",
    "sg:postcode":"97213",
    "sg:province":"OR",
    "wof:name":"Sports Car Center",
    "wof:placetype":"venue"
},
  "geometry": {"coordinates":[-122.583172,45.550729],"type":"Point"}
}