{
  "type": "Feature",
  "properties": {
    "iso:country":"US",
    "sg:address":"1680 S Crestline Dr",
    "sg:city":"Waldport",
    "sg:phone":"+1 541 563 3020",
    "sg:postcode":"97394",
    "sg:province":"OR",
    "sg:website":"http://www.crestviewhillsgolf.com",
    "wof:name":"Crestview Golf Course",
    "wof:placetype":"venue"
},
  "geometry": {"coordinates":[-124.06473699999999,44.416162],"type":"Point"}
}