{
  "type": "Feature",
  "properties": {
    "addr:full":"2808 NE 7th Ave Portland OR 97212",
    "addr:housenumber":"2808",
    "addr:postcode":"97212",
    "addr:street":"Ne 7Th Ave",
    "iso:country":"US",
    "sg:address":"2808 NE 7th Ave",
    "sg:city":"Portland",
    "sg:classifiers":[
        {
            "category":"Professional",
            "subcategory":"Employment Agencies",
            "type":"Services"
        }
    ],
    "sg:phone":"+1 503 331 7507",
    "sg:postcode":"97212",
    "sg:province":"OR",
    "wof:name":"Brister & Associates Inc",
    "wof:placetype":"venue"
},
  "geometry": {"coordinates":[-122.658506,45.543668],"type":"Point"}
}