{
  "type": "Feature",
  "properties": {
    "iso:country":"US",
    "sg:address":"6100 NE Campus Ct",
    "sg:city":"Hillsboro",
    "sg:classifiers":[
        {
            "category":"Wholesale",
            "subcategory":"Machinery & Supplies",
            "type":"Manufacturing & Wholesale Goods"
        }
    ],
    "sg:phone":"+1 503 648 8389",
    "sg:postcode":"97124",
    "sg:province":"OR",
    "sg:tags":[
        "mill",
        "paper"
    ],
    "sg:website":"www.trimnozzle.com",
    "wof:name":"M L Gatewood Co",
    "wof:placetype":"venue"
},
  "geometry": {"coordinates":[-122.918153,45.531378],"type":"Point"}
}