{
  "type": "Feature",
  "properties": {
    "iso:country":"US",
    "sg:address":"1410 NE 106th Ave",
    "sg:city":"Portland",
    "sg:classifiers":[
        {
            "category":"Professional",
            "subcategory":"Accounting & Tax Preparation",
            "type":"Services"
        }
    ],
    "sg:phone":"+1 503 255 4233",
    "sg:postcode":"97220",
    "sg:province":"OR",
    "sg:tags":[
        "return",
        "filing"
    ],
    "wof:name":"Beutelschies and Co",
    "wof:placetype":"venue"
},
  "geometry": {"coordinates":[-122.553556,45.532474],"type":"Point"}
}