{
  "type": "Feature",
  "properties": {
    "iso:country":"US",
    "sg:address":"2893 12th St SE",
    "sg:city":"Salem",
    "sg:classifiers":[
        {
            "category":"Personal",
            "subcategory":"Beauty Salon",
            "type":"Services"
        }
    ],
    "sg:phone":"+1 503 362 3363",
    "sg:postcode":"97302",
    "sg:province":"OR",
    "sg:tags":[
        "shop"
    ],
    "wof:name":"Appearance Designing",
    "wof:placetype":"venue"
},
  "geometry": {"coordinates":[-123.030873,44.911804],"type":"Point"}
}