{
  "type": "Feature",
  "properties": {
    "iso:country":"US",
    "sg:address":"6605 SW Macadam Ave",
    "sg:city":"Portland",
    "sg:classifiers":[
        {
            "category":"Manufacturing",
            "subcategory":"Electronics",
            "type":"Manufacturing & Wholesale Goods"
        }
    ],
    "sg:phone":"+1 503 452 8577",
    "sg:postcode":"97219",
    "sg:province":"OR",
    "wof:name":"Autotime Corporation",
    "wof:placetype":"venue"
},
  "geometry": {"coordinates":[-122.671978,45.476506],"type":"Point"}
}