{
  "type": "Feature",
  "properties": {
    "iso:country":"US",
    "sg:address":"9939 SE Stark St",
    "sg:city":"Portland",
    "sg:classifiers":[
        {
            "category":"Bars & Pubs",
            "type":"Food & Drink"
        }
    ],
    "sg:phone":"+1 503 256 0527",
    "sg:postcode":"97216",
    "sg:province":"OR",
    "sg:tags":[
        "adult",
        "entertainment"
    ],
    "sg:website":"club205portland.com",
    "wof:name":"Club 205",
    "wof:placetype":"venue"
},
  "geometry": {"coordinates":[-122.561387,45.519298],"type":"Point"}
}