{
  "type": "Feature",
  "properties": {
    "addr:full":"31446 S Grays Hill Rd Colton OR 97017",
    "addr:housenumber":"31446",
    "addr:postcode":"97017",
    "addr:street":"S Grays Hill Rd",
    "iso:country":"US",
    "sg:address":"31446 S Grays Hill Rd",
    "sg:city":"Colton",
    "sg:classifiers":[
        {
            "category":"Shopping",
            "subcategory":"Hobbies, Toys, & Games",
            "type":"Retail Goods"
        },
        {
            "category":"Professional",
            "type":"Services"
        }
    ],
    "sg:phone":"+1 503 824 4225",
    "sg:postcode":"97017",
    "sg:province":"OR",
    "sg:tags":[
        "craft",
        "supply"
    ],
    "wof:name":"Ceramics N More",
    "wof:placetype":"venue"
},
  "geometry": {"coordinates":[-122.414339,45.14957],"type":"Point"}
}