{
  "type": "Feature",
  "properties": {
    "addr:full":"1083 24th St NE Salem OR 97301",
    "addr:housenumber":"1083",
    "addr:postcode":"97301",
    "addr:street":"24Th St Ne",
    "iso:country":"US",
    "sg:address":"1083 24th St NE",
    "sg:city":"Salem",
    "sg:classifiers":[
        {
            "category":"Taxi",
            "type":"Transportation"
        }
    ],
    "sg:phone":"+1 503 363 9712",
    "sg:postcode":"97301",
    "sg:province":"OR",
    "sg:tags":[
        "delivery"
    ],
    "wof:name":"Asap Delivery Service",
    "wof:placetype":"venue"
},
  "geometry": {"coordinates":[-123.00494,44.944186],"type":"Point"}
}