{
  "type": "Feature",
  "properties": {
    "addr:full":"80207 Patriot Ln Hermiston OR 97838",
    "addr:postcode":"80207;97838",
    "addr:street":"Patriot Ln",
    "iso:country":"US",
    "sg:address":"80207 Patriot Ln",
    "sg:city":"Hermiston",
    "sg:classifiers":[
        {
            "category":"Personal",
            "type":"Services"
        }
    ],
    "sg:phone":"+1 541 667 8819",
    "sg:postcode":"97838",
    "sg:province":"OR",
    "wof:name":"Mark Johnson Consulting Inc",
    "wof:placetype":"venue"
},
  "geometry": {"coordinates":[-119.23100700000001,45.85881],"type":"Point"}
}