{
  "type": "Feature",
  "properties": {
    "iso:country":"US",
    "sg:address":"2304 E Burnside St Ste 4",
    "sg:city":"Portland",
    "sg:classifiers":[
        {
            "category":"Health Services",
            "subcategory":"Clinic",
            "type":"Services"
        },
        {
            "category":"Shopping",
            "subcategory":"Pets & Pet Supplies",
            "type":"Retail Goods"
        }
    ],
    "sg:phone":"+1 503 265 9390",
    "sg:postcode":"97214",
    "sg:province":"OR",
    "sg:tags":[
        "counseling",
        "mental"
    ],
    "sg:website":"www.katedavismsw.net",
    "wof:name":"Kate Davis, MSW, L.C.S.W.",
    "wof:placetype":"venue"
},
  "geometry": {"coordinates":[-122.64223699999999,45.522641],"type":"Point"}
}