{
  "type": "Feature",
  "properties": {
    "iso:country":"US",
    "sg:address":"4925 NW Woody Way",
    "sg:city":"Newport",
    "sg:classifiers":[
        {
            "category":"Travel",
            "subcategory":"Hotels & Motels",
            "type":"Entertainment"
        }
    ],
    "sg:phone":"+1 541 265 8953",
    "sg:postcode":"97365",
    "sg:province":"OR",
    "sg:tags":[
        "breakfast",
        "accommodation",
        "bed",
        "lodging"
    ],
    "sg:website":"www.tyeelodge.com",
    "wof:name":"Tyee Lodge Bed & Breakfast",
    "wof:placetype":"venue"
},
  "geometry": {"coordinates":[-124.060411,44.67313],"type":"Point"}
}