{
  "type": "Feature",
  "properties": {
    "addr:full":"412 SW I St Grants Pass OR 97526",
    "addr:housenumber":"412",
    "addr:postcode":"97526",
    "addr:street":"Sw I St",
    "iso:country":"US",
    "sg:address":"412 SW I St",
    "sg:city":"Grants Pass",
    "sg:classifiers":[
        {
            "category":"Building & Trades",
            "subcategory":"Plumbing",
            "type":"Services"
        }
    ],
    "sg:phone":"+1 541 479 5181",
    "sg:postcode":"97526",
    "sg:province":"OR",
    "sg:tags":[
        "contractor"
    ],
    "wof:name":"Mobile Home Heating & Air",
    "wof:placetype":"venue"
},
  "geometry": {"coordinates":[-123.33471299999999,42.439081],"type":"Point"}
}