{
  "type": "Feature",
  "properties": {
    "addr:full":"212 SW 5th St Madras OR 97741",
    "addr:housenumber":"212",
    "addr:postcode":"97741",
    "addr:street":"Sw 5Th St",
    "iso:country":"US",
    "sg:address":"212 SW 5th St",
    "sg:city":"Madras",
    "sg:classifiers":[
        {
            "category":"Shopping",
            "subcategory":"Jewelry",
            "type":"Retail Goods"
        }
    ],
    "sg:phone":"+1 541 475 5287",
    "sg:postcode":"97741",
    "sg:province":"OR",
    "sg:tags":[
        "jeweler"
    ],
    "wof:name":"Reynoso Jewelry",
    "wof:placetype":"venue"
},
  "geometry": {"coordinates":[-121.129637,44.633229],"type":"Point"}
}