{
  "type": "Feature",
  "properties": {
    "iso:country":"US",
    "sg:address":"501 N Graham St Ste 100",
    "sg:city":"Portland",
    "sg:classifiers":[
        {
            "category":"Health Services",
            "subcategory":"Doctor",
            "type":"Services"
        }
    ],
    "sg:phone":"+1 503 249 5780",
    "sg:postcode":"97227",
    "sg:province":"OR",
    "sg:tags":[
        "medicine",
        "internal"
    ],
    "sg:website":"www.cascadephysicians.com",
    "wof:name":"Cascade Physicians PC",
    "wof:placetype":"venue"
},
  "geometry": {"coordinates":[-122.670464,45.542828],"type":"Point"}
}