{
  "type": "Feature",
  "properties": {
    "iso:country":"US",
    "sg:address":"191 E Main St",
    "sg:city":"Carlton",
    "sg:classifiers":[
        {
            "category":"Government",
            "subcategory":"Office",
            "type":"Public Place"
        }
    ],
    "sg:phone":"+1 503 852 6562",
    "sg:postcode":"97111",
    "sg:province":"OR",
    "sg:tags":[
        "village"
    ],
    "wof:name":"Carlton City",
    "wof:placetype":"venue"
},
  "geometry": {"coordinates":[-123.175732,45.294276],"type":"Point"}
}