{
  "type": "Feature",
  "properties": {
    "iso:country":"US",
    "sg:address":"10487 SW Cascade Ave",
    "sg:city":"Portland",
    "sg:classifiers":[
        {
            "category":"Home & Garden",
            "subcategory":"Furniture",
            "type":"Retail Goods"
        }
    ],
    "sg:phone":"+1 503 684 8595",
    "sg:postcode":"97223",
    "sg:province":"OR",
    "sg:tags":[
        "store"
    ],
    "wof:name":"Wickes Furniture Company  Inc",
    "wof:placetype":"venue"
},
  "geometry": {"coordinates":[-122.780078,45.441826],"type":"Point"}
}