{
  "type": "Feature",
  "properties": {
    "addr:full":"94760 N Bank Rogue River Rd Gold Beach OR 97444",
    "addr:housenumber":"94760",
    "addr:postcode":"97444",
    "addr:street":"N Bank Rogue River Rd",
    "iso:country":"US",
    "sg:address":"94760 N Bank Rogue River Rd",
    "sg:city":"Gold Beach",
    "sg:classifiers":[
        {
            "category":"Professional",
            "subcategory":"Advertising",
            "type":"Services"
        }
    ],
    "sg:phone":"+1 541 247 0936",
    "sg:postcode":"97444",
    "sg:province":"OR",
    "wof:name":"Lasrock Media LLC",
    "wof:placetype":"venue"
},
  "geometry": {"coordinates":[-124.389466,42.445286],"type":"Point"}
}