{
  "type": "Feature",
  "properties": {
    "addr:full":"108 E Hersey St Ashland OR 97520",
    "addr:housenumber":"108",
    "addr:postcode":"97520",
    "addr:street":"E Hersey St",
    "iso:country":"US",
    "sg:address":"108 E Hersey St",
    "sg:city":"Ashland",
    "sg:classifiers":[
        {
            "category":"Personal",
            "type":"Services"
        }
    ],
    "sg:phone":"+1 541 482 4746",
    "sg:postcode":"97520",
    "sg:province":"OR",
    "sg:tags":[
        "therapist",
        "massage"
    ],
    "wof:name":"Marsha Easterday",
    "wof:placetype":"venue"
},
  "geometry": {"coordinates":[-122.70867,42.201283],"type":"Point"}
}