{
  "type": "Feature",
  "properties": {
    "iso:country":"US",
    "sg:address":"12143 NE Halsey Street",
    "sg:city":"Portland",
    "sg:classifiers":[
        {
            "category":"Real Estate",
            "subcategory":"Real Estate Services",
            "type":"Services"
        },
        {
            "category":"Banks & Credit Unions",
            "subcategory":"Financial Services",
            "type":"Services"
        }
    ],
    "sg:phone":"+1 503 253 3299",
    "sg:postcode":"97220",
    "sg:province":"OR",
    "sg:tags":[
        "loan",
        "processing",
        "broker",
        "mortgage"
    ],
    "wof:name":"Agape Home Mortgage George Elliot",
    "wof:placetype":"venue"
},
  "geometry": {"coordinates":[-122.537198,45.533683],"type":"Point"}
}