{
  "type": "Feature",
  "properties": {
    "addr:full":"80780 Victor Rd Maupin OR 97037",
    "addr:housenumber":"80780",
    "addr:postcode":"97037",
    "addr:street":"Victor Rd",
    "iso:country":"US",
    "sg:address":"80780 Victor Rd",
    "sg:city":"Maupin",
    "sg:phone":"+1 541 328 6267",
    "sg:postcode":"97037",
    "sg:province":"OR",
    "sg:tags":[
        "farm",
        "wheat"
    ],
    "wof:name":"Ray McCorkle",
    "wof:placetype":"venue"
},
  "geometry": {"coordinates":[-121.24417699999999,45.168763],"type":"Point"}
}