{
  "type": "Feature",
  "properties": {
    "iso:country":"US",
    "sg:address":"20048 NE San Rafael St",
    "sg:city":"Portland",
    "sg:classifiers":[
        {
            "category":"Communications",
            "subcategory":"Film & Video Production",
            "type":"Services"
        }
    ],
    "sg:phone":"+1 503 491 8480",
    "sg:postcode":"97230",
    "sg:province":"OR",
    "sg:tags":[
        "record",
        "tapes-wholesale",
        "manufacturer",
        "cd's"
    ],
    "sg:website":"http://www.allegro-music.com",
    "wof:name":"Allegro Media Group",
    "wof:placetype":"venue"
},
  "geometry": {"coordinates":[-122.456885,45.536911],"type":"Point"}
}