{
  "type": "Feature",
  "properties": {
    "iso:country":"US",
    "sg:address":"3242 NE 82nd Ave",
    "sg:city":"Portland",
    "sg:classifiers":[
        {
            "category":"Personal",
            "type":"Services"
        }
    ],
    "sg:phone":"+1 503 257 0622",
    "sg:postcode":"97220",
    "sg:province":"OR",
    "sg:tags":[
        "salon",
        "tanning"
    ],
    "wof:name":"Xotic Tan",
    "wof:placetype":"venue"
},
  "geometry": {"coordinates":[-122.578716,45.54503],"type":"Point"}
}