{
  "type": "Feature",
  "properties": {
    "iso:country":"US",
    "sg:address":"2193 Midway Ave",
    "sg:city":"Grants Pass",
    "sg:classifiers":[
        {
            "category":"Organizations",
            "subcategory":"Religious Organization",
            "type":"Services"
        }
    ],
    "sg:phone":"+1 541 476 1502",
    "sg:postcode":"97527",
    "sg:province":"OR",
    "sg:tags":[
        "church"
    ],
    "wof:name":"Calvary Church",
    "wof:placetype":"venue"
},
  "geometry": {"coordinates":[-123.412681,42.41246],"type":"Point"}
}