{
  "type": "Feature",
  "properties": {
    "iso:country":"US",
    "sg:address":"2888 E Baseline St",
    "sg:city":"Cornelius",
    "sg:classifiers":[
        {
            "category":"Autos & Motor Vehicles",
            "subcategory":"Fuel & Gas Station",
            "type":"Retail Goods"
        }
    ],
    "sg:phone":"+1 503 681 4640",
    "sg:postcode":"97113",
    "sg:province":"OR",
    "sg:tags":[
        "station",
        "gasoline"
    ],
    "wof:name":"Cornelius Arco",
    "wof:placetype":"venue"
},
  "geometry": {"coordinates":[-123.036214,45.520081],"type":"Point"}
}