{
  "type": "Feature",
  "properties": {
    "iso:country":"US",
    "sg:address":"201 Oak St",
    "sg:city":"Hood River",
    "sg:classifiers":[
        {
            "category":"Wholesale",
            "subcategory":"Apparel",
            "type":"Manufacturing & Wholesale Goods"
        }
    ],
    "sg:phone":"+1 541 386 5117",
    "sg:postcode":"97031",
    "sg:province":"OR",
    "sg:tags":[
        "footwear"
    ],
    "wof:name":"Sportsmens Den",
    "wof:placetype":"venue"
},
  "geometry": {"coordinates":[-121.513306,45.708853],"type":"Point"}
}