{
  "type": "Feature",
  "properties": {
    "iso:country":"US",
    "sg:address":"3090 Granite Hill Rd",
    "sg:city":"Grants Pass",
    "sg:classifiers":[
        {
            "category":"Real Estate",
            "subcategory":"Real Estate Operator",
            "type":"Services"
        }
    ],
    "sg:phone":"+1 541 472 1375",
    "sg:postcode":"97526",
    "sg:province":"OR",
    "sg:tags":[
        "mobile",
        "home",
        "site"
    ],
    "wof:name":"Frontier Mobile Estates LLC",
    "wof:placetype":"venue"
},
  "geometry": {"coordinates":[-123.320914,42.503716],"type":"Point"}
}