{
  "type": "Feature",
  "properties": {
    "iso:country":"US",
    "sg:address":"2161 NW Fillmore Ave",
    "sg:city":"Corvallis",
    "sg:classifiers":[
        {
            "category":"Professional",
            "subcategory":"Research",
            "type":"Services"
        }
    ],
    "sg:phone":"+1 541 758 5777",
    "sg:postcode":"97330",
    "sg:province":"OR",
    "sg:tags":[
        "environmental",
        "ecological"
    ],
    "wof:name":"E & S Environmental Chemistry",
    "wof:placetype":"venue"
},
  "geometry": {"coordinates":[-123.27751499999999,44.575554],"type":"Point"}
}