{
  "type": "Feature",
  "properties": {
    "addr:full":"12386 SW Main St Portland OR 97223",
    "addr:housenumber":"12386",
    "addr:postcode":"97223",
    "addr:street":"Sw Main St",
    "iso:country":"US",
    "sg:address":"12386 SW Main St",
    "sg:city":"Portland",
    "sg:classifiers":[
        {
            "category":"Restaurant",
            "type":"Food & Drink"
        }
    ],
    "sg:phone":"+1 503 684 0130",
    "sg:postcode":"97223",
    "sg:province":"OR",
    "wof:name":"Cafe Allegro",
    "wof:placetype":"venue"
},
  "geometry": {"coordinates":[-122.771004,45.430599],"type":"Point"}
}