{
  "type": "Feature",
  "properties": {
    "iso:country":"US",
    "sg:address":"89472 Demming Rd",
    "sg:city":"Elmira",
    "sg:classifiers":[
        {
            "category":"Professional",
            "subcategory":"Secretarial Services",
            "type":"Services"
        }
    ],
    "sg:phone":"+1 541 935 5618",
    "sg:postcode":"97437",
    "sg:province":"OR",
    "sg:tags":[
        "reporting"
    ],
    "wof:name":"Webster Suzan",
    "wof:placetype":"venue"
},
  "geometry": {"coordinates":[-123.351519,44.083438],"type":"Point"}
}