{
  "type": "Feature",
  "properties": {
    "addr:full":"12708 SE Stephens St Portland OR 97233",
    "addr:housenumber":"12708",
    "addr:postcode":"97233",
    "addr:street":"Se Stephens St",
    "iso:country":"US",
    "sg:address":"12708 SE Stephens St",
    "sg:city":"Portland",
    "sg:classifiers":[
        {
            "category":"Social Services",
            "type":"Services"
        }
    ],
    "sg:phone":"+1 503 252 3955",
    "sg:postcode":"97233",
    "sg:province":"OR",
    "sg:tags":[
        "information",
        "cancer"
    ],
    "wof:name":"Making Memories Breast Cancer",
    "wof:placetype":"venue"
},
  "geometry": {"coordinates":[-122.535352,45.508978],"type":"Point"}
}