{
  "type": "Feature",
  "properties": {
    "iso:country":"US",
    "sg:address":"2500 Jumpoff Joe Creek Rd",
    "sg:city":"Grants Pass",
    "sg:classifiers":[
        {
            "category":"Social Services",
            "type":"Services"
        }
    ],
    "sg:phone":"+1 541 955 8450",
    "sg:postcode":"97526",
    "sg:province":"OR",
    "sg:tags":[
        "youth",
        "organization",
        "center"
    ],
    "wof:name":"Cascade Boys Ranch",
    "wof:placetype":"venue"
},
  "geometry": {"coordinates":[-123.338638,42.574561],"type":"Point"}
}