{
  "type": "Feature",
  "properties": {
    "iso:country":"US",
    "sg:address":"1809 Maple St",
    "sg:city":"Forest Grove",
    "sg:classifiers":[
        {
            "category":"Health Services",
            "subcategory":"Clinic",
            "type":"Services"
        }
    ],
    "sg:phone":"+1 503 359 6969",
    "sg:postcode":"97116",
    "sg:province":"OR",
    "sg:tags":[
        "hospital",
        "specialty",
        "outpatient",
        "general"
    ],
    "wof:name":"Armstrong Scott C MD",
    "wof:placetype":"venue"
},
  "geometry": {"coordinates":[-123.091173,45.517106],"type":"Point"}
}