{
  "type": "Feature",
  "properties": {
    "iso:country":"US",
    "sg:address":"1104 N Gazley Rd",
    "sg:city":"Myrtle Creek",
    "sg:classifiers":[
        {
            "category":"Wholesale",
            "subcategory":"Construction Materials",
            "type":"Manufacturing & Wholesale Goods"
        }
    ],
    "sg:phone":"+1 541 839 4304",
    "sg:postcode":"97457",
    "sg:province":"OR",
    "wof:name":"R Dunbar Co",
    "wof:placetype":"venue"
},
  "geometry": {"coordinates":[-123.265783,42.955329],"type":"Point"}
}