{
  "type": "Feature",
  "properties": {
    "addr:full":"910 NW Carpathian Dr Corvallis OR 97330",
    "addr:housenumber":"910",
    "addr:postcode":"97330",
    "addr:street":"Nw Carpathian Dr",
    "iso:country":"US",
    "sg:address":"910 NW Carpathian Dr",
    "sg:city":"Corvallis",
    "sg:classifiers":[
        {
            "category":"Building & Trades",
            "subcategory":"Construction",
            "type":"Services"
        }
    ],
    "sg:phone":"+1 541 745 5299",
    "sg:postcode":"97330",
    "sg:province":"OR",
    "sg:tags":[
        "general",
        "contractor"
    ],
    "wof:name":"Big Bear Construction",
    "wof:placetype":"venue"
},
  "geometry": {"coordinates":[-123.25964999999999,44.642478],"type":"Point"}
}