{
  "type": "Feature",
  "properties": {
    "iso:country":"US",
    "sg:address":"910 NW Carpathian Dr",
    "sg:city":"Corvallis",
    "sg:classifiers":[
        {
            "category":"Building & Trades",
            "subcategory":"Construction",
            "type":"Services"
        }
    ],
    "sg:phone":"+1 541 745 5299",
    "sg:postcode":"97330",
    "sg:province":"OR",
    "sg:tags":[
        "general",
        "contractor"
    ],
    "wof:name":"Big Bear Construction",
    "wof:placetype":"venue"
},
  "geometry": {"coordinates":[-123.25965,44.642478],"type":"Point"}
}