{
  "type": "Feature",
  "properties": {
    "addr:full":"1120 SW 14th St Lincoln City OR 97367",
    "addr:housenumber":"1120",
    "addr:postcode":"97367",
    "addr:street":"Sw 14Th St",
    "iso:country":"US",
    "sg:address":"1120 SW 14th St",
    "sg:city":"Lincoln City",
    "sg:classifiers":[
        {
            "category":"Building & Trades",
            "subcategory":"Cleaning & Sanitation",
            "type":"Services"
        }
    ],
    "sg:phone":"+1 541 994 3738",
    "sg:postcode":"97367",
    "sg:province":"OR",
    "sg:tags":[
        "maintenance"
    ],
    "wof:name":"Windows Deluxe",
    "wof:placetype":"venue"
},
  "geometry": {"coordinates":[-124.01581899999999,44.957565],"type":"Point"}
}