{
  "type": "Feature",
  "properties": {
    "iso:country":"US",
    "sg:address":"1120 SW 14th St",
    "sg:city":"Lincoln City",
    "sg:classifiers":[
        {
            "category":"Building & Trades",
            "subcategory":"Cleaning & Sanitation",
            "type":"Services"
        }
    ],
    "sg:phone":"+1 541 994 3738",
    "sg:postcode":"97367",
    "sg:province":"OR",
    "sg:tags":[
        "maintenance"
    ],
    "wof:name":"Windows Deluxe",
    "wof:placetype":"venue"
},
  "geometry": {"coordinates":[-124.015819,44.957565],"type":"Point"}
}