{
  "type": "Feature",
  "properties": {
    "addr:full":"11827 SE Stark Street Portland OR 97216",
    "addr:housenumber":"11827",
    "addr:postcode":"97216",
    "addr:street":"Se Stark Street",
    "iso:country":"US",
    "sg:address":"11827 SE Stark Street",
    "sg:city":"Portland",
    "sg:classifiers":[
        {
            "category":"Home & Garden",
            "subcategory":"Garden Supply",
            "type":"Retail Goods"
        }
    ],
    "sg:phone":"+1 503 255 5393",
    "sg:postcode":"97216",
    "sg:province":"OR",
    "wof:name":"Stark Street Lawn & Garden Equipment",
    "wof:placetype":"venue"
},
  "geometry": {"coordinates":[-122.540542,45.519124],"type":"Point"}
}