{
  "type": "Feature",
  "properties": {
    "addr:full":"6506 S 6th St Klamath Falls OR 97603",
    "addr:housenumber":"6506",
    "addr:postcode":"97603",
    "addr:street":"S 6Th St",
    "iso:country":"US",
    "sg:address":"6506 S 6th St",
    "sg:city":"Klamath Falls",
    "sg:classifiers":[
        {
            "category":"Personal",
            "subcategory":"Beauty Salon",
            "type":"Services"
        }
    ],
    "sg:phone":"+1 541 884 6400",
    "sg:postcode":"97603",
    "sg:province":"OR",
    "sg:tags":[
        "manicuring"
    ],
    "wof:name":"O B Nails",
    "wof:placetype":"venue"
},
  "geometry": {"coordinates":[-121.709153,42.203676],"type":"Point"}
}