{
  "type": "Feature",
  "properties": {
    "addr:full":"14864 SE Webster Rd Portland OR 97267",
    "addr:postcode":"14864;97267",
    "addr:street":"Se Webster Rd",
    "iso:country":"US",
    "sg:address":"14864 SE Webster Rd",
    "sg:city":"Portland",
    "sg:classifiers":[
        {
            "category":"Professional",
            "subcategory":"Advertising",
            "type":"Services"
        }
    ],
    "sg:phone":"+1 503 659 6180",
    "sg:postcode":"97267",
    "sg:province":"OR",
    "sg:tags":[
        "mailing",
        "shipping"
    ],
    "wof:name":"Pacific Mailing & Shipping",
    "wof:placetype":"venue"
},
  "geometry": {"coordinates":[-122.59233500000001,45.415326],"type":"Point"}
}