{
  "type": "Feature",
  "properties": {
    "iso:country":"US",
    "sg:address":"6405 Rosewood St",
    "sg:city":"Lake Oswego",
    "sg:classifiers":[
        {
            "category":"Building & Trades",
            "subcategory":"Locksmith",
            "type":"Services"
        }
    ],
    "sg:phone":"+1 503 914 0714",
    "sg:postcode":"97035",
    "sg:province":"OR",
    "sg:tags":[
        "key"
    ],
    "wof:name":"All Day All Night Locksmith",
    "wof:placetype":"venue"
},
  "geometry": {"coordinates":[-122.741624,45.400871],"type":"Point"}
}