{
  "type": "Feature",
  "properties": {
    "addr:full":"1218 NW Glisan St Portland OR 97209",
    "addr:housenumber":"1218",
    "addr:postcode":"97209",
    "addr:street":"Nw Glisan St",
    "iso:country":"US",
    "sg:address":"1218 NW Glisan St",
    "sg:city":"Portland",
    "sg:classifiers":[
        {
            "category":"Shopping",
            "subcategory":"Clothing, Apparel, & Fashions",
            "type":"Retail Goods"
        }
    ],
    "sg:phone":"+1 503 242 0079",
    "sg:postcode":"97209",
    "sg:province":"OR",
    "sg:tags":[
        "sheepskin",
        "specialty"
    ],
    "sg:website":"http://www.sheepskinoforegon.com",
    "wof:name":"Sheepskin Of Oregon",
    "wof:placetype":"venue"
},
  "geometry": {"coordinates":[-122.683441,45.526505],"type":"Point"}
}