{
  "type": "Feature",
  "properties": {
    "iso:country":"US",
    "sg:address":"51163 Bankston Rd",
    "sg:city":"Scappoose",
    "sg:classifiers":[
        {
            "category":"Organizations",
            "subcategory":"Political Organization",
            "type":"Services"
        }
    ],
    "sg:phone":"+1 503 543 7312",
    "sg:postcode":"97056",
    "sg:province":"OR",
    "wof:name":"Elect Bob Ekstrom Committ",
    "wof:placetype":"venue"
},
  "geometry": {"coordinates":[-122.953467,45.738376],"type":"Point"}
}