{
  "type": "Feature",
  "properties": {
    "iso:country":"US",
    "sg:address":"343 SE 3rd Ave",
    "sg:city":"Hillsboro",
    "sg:classifiers":[
        {
            "category":"Personal",
            "type":"Services"
        }
    ],
    "sg:phone":"+1 503 844 9355",
    "sg:postcode":"97123",
    "sg:province":"OR",
    "sg:tags":[
        "therapist",
        "massage"
    ],
    "wof:name":"Hillsboro Wellness Ctr Inc",
    "wof:placetype":"venue"
},
  "geometry": {"coordinates":[-122.98629,45.519984],"type":"Point"}
}