{
  "type": "Feature",
  "properties": {
    "iso:country":"US",
    "sg:address":"16400 Bryant Rd",
    "sg:city":"Lake Oswego",
    "sg:classifiers":[
        {
            "category":"Organizations",
            "subcategory":"Professional Association",
            "type":"Services"
        }
    ],
    "sg:phone":"+1 503 635 8718",
    "sg:postcode":"97035",
    "sg:province":"OR",
    "sg:tags":[
        "business"
    ],
    "wof:name":"Professional Fire Fighter",
    "wof:placetype":"venue"
},
  "geometry": {"coordinates":[-122.72303700000001,45.407543],"type":"Point"}
}