{
  "type": "Feature",
  "properties": {
    "iso:country":"US",
    "sg:address":"28332 Historic Columbia River Hwy",
    "sg:city":"Troutdale",
    "sg:classifiers":[
        {
            "category":"Professional",
            "subcategory":"Advertising",
            "type":"Services"
        }
    ],
    "sg:phone":"+1 503 492 2348",
    "sg:postcode":"97060",
    "sg:province":"OR",
    "sg:tags":[
        "promotion",
        "sale"
    ],
    "sg:website":"http://www.sandyrivermarketing.com",
    "wof:name":"Sandy River Marketing, Inc.",
    "wof:placetype":"venue"
},
  "geometry": {"coordinates":[-122.37058,45.514979],"type":"Point"}
}