{
  "type": "Feature",
  "properties": {
    "iso:country":"US",
    "sg:address":"4110 W 11th Ave",
    "sg:city":"Eugene",
    "sg:classifiers":[
        {
            "category":"Autos & Motor Vehicles",
            "subcategory":"Recreational Vehicle Sales",
            "type":"Retail Goods"
        }
    ],
    "sg:phone":"+1 541 684 8728",
    "sg:postcode":"97402",
    "sg:province":"OR",
    "wof:name":"Cruise America Inc",
    "wof:placetype":"venue"
},
  "geometry": {"coordinates":[-123.166068,44.047958],"type":"Point"}
}