{
  "type": "Feature",
  "properties": {
    "addr:full":"1614 NW 4th St Bend OR 97701",
    "addr:housenumber":"1614",
    "addr:postcode":"97701",
    "addr:street":"Nw 4Th St",
    "iso:country":"US",
    "sg:address":"1614 NW 4th St",
    "sg:city":"Bend",
    "sg:classifiers":[
        {
            "category":"Professional",
            "subcategory":"Business Services",
            "type":"Services"
        }
    ],
    "sg:phone":"+1 541 312 2494",
    "sg:postcode":"97701",
    "sg:province":"OR",
    "wof:name":"Hr Online Enterprises",
    "wof:placetype":"venue"
},
  "geometry": {"coordinates":[-121.317849,44.065307],"type":"Point"}
}