{
  "type": "Feature",
  "properties": {
    "addr:full":"449 Annex Rd Ontario OR 97914",
    "addr:housenumber":"449",
    "addr:postcode":"97914",
    "addr:street":"Annex Rd",
    "iso:country":"US",
    "sg:address":"449 Annex Rd",
    "sg:city":"Ontario",
    "sg:classifiers":[
        {
            "category":"Farming",
            "subcategory":"Farm & Veterinary Services",
            "type":"Manufacturing & Wholesale Goods"
        }
    ],
    "sg:phone":"+1 541 262 3966",
    "sg:postcode":"97914",
    "sg:province":"OR",
    "sg:tags":[
        "livestock"
    ],
    "wof:name":"Wiedmenman Cattle Ranch",
    "wof:placetype":"venue"
},
  "geometry": {"coordinates":[-116.99664199999999,44.236078],"type":"Point"}
}