{
  "type": "Feature",
  "properties": {
    "iso:country":"US",
    "sg:address":"81080 Shadybrook Rd",
    "sg:city":"Tygh Valley",
    "sg:classifiers":[
        {
            "category":"Manufacturing",
            "subcategory":"Lumber",
            "type":"Manufacturing & Wholesale Goods"
        }
    ],
    "sg:phone":"+1 541 483 2443",
    "sg:postcode":"97063",
    "sg:province":"OR",
    "sg:tags":[
        "forester"
    ],
    "wof:name":"Hillside Fire & Forestry",
    "wof:placetype":"venue"
},
  "geometry": {"coordinates":[-121.232781,45.268474],"type":"Point"}
}