{
  "type": "Feature",
  "properties": {
    "addr:full":"825 Monroe St Eugene OR 97402",
    "addr:housenumber":"825",
    "addr:postcode":"97402",
    "addr:street":"Monroe St",
    "iso:country":"US",
    "sg:address":"825 Monroe St",
    "sg:city":"Eugene",
    "sg:classifiers":[
        {
            "category":"Education",
            "subcategory":"Special Training",
            "type":"Public Place"
        }
    ],
    "sg:phone":"+1 541 343 5920",
    "sg:postcode":"97402",
    "sg:province":"OR",
    "sg:tags":[
        "instruction",
        "music"
    ],
    "wof:name":"Hands On Rhythm & Drum School",
    "wof:placetype":"venue"
},
  "geometry": {"coordinates":[-123.104842,44.050202],"type":"Point"}
}