{
  "type": "Feature",
  "properties": {
    "iso:country":"US",
    "sg:address":"15050 SW Koll Pkwy",
    "sg:city":"Beaverton",
    "sg:classifiers":[
        {
            "category":"Health Services",
            "subcategory":"Doctor",
            "type":"Services"
        }
    ],
    "sg:phone":"+1 503 297 8039",
    "sg:postcode":"97006",
    "sg:province":"OR",
    "sg:tags":[
        "physician",
        "surgeon"
    ],
    "sg:website":"www.mindmatterspc.com",
    "wof:name":"Mind Matters PC Inc",
    "wof:placetype":"venue"
},
  "geometry": {"coordinates":[-122.834004,45.512577],"type":"Point"}
}