{
  "type": "Feature",
  "properties": {
    "iso:country":"US",
    "sg:address":"17700 SW Upper Boones Ferry Rd Suite 100",
    "sg:city":"Portland",
    "sg:classifiers":[
        {
            "category":"Real Estate",
            "subcategory":"Developer",
            "type":"Services"
        },
        {
            "category":"Real Estate",
            "subcategory":"Real Estate Agent",
            "type":"Services"
        }
    ],
    "sg:phone":"+1 503 502 5072",
    "sg:postcode":"97224",
    "sg:province":"OR",
    "sg:tags":[
        "investing"
    ],
    "sg:website":"http://www.NathanWyllie.com",
    "wof:name":"The Wyllie Group, Keller Williams Portland Premiere",
    "wof:placetype":"venue"
},
  "geometry": {"coordinates":[-122.755791,45.392262],"type":"Point"}
}