{
  "type": "Feature",
  "properties": {
    "iso:country":"US",
    "sg:address":"25 82nd Dr",
    "sg:city":"Gladstone",
    "sg:classifiers":[
        {
            "category":"Banks & Credit Unions",
            "subcategory":"Financial Services",
            "type":"Services"
        },
        {
            "category":"Insurance",
            "subcategory":"Health Insurance",
            "type":"Services"
        }
    ],
    "sg:phone":"+1 503 786 4697",
    "sg:postcode":"97027",
    "sg:province":"OR",
    "sg:tags":[
        "company",
        "contract",
        "preferred",
        "holding",
        "provider",
        "organization"
    ],
    "wof:name":"Healthcare Direct LLC",
    "wof:placetype":"venue"
},
  "geometry": {"coordinates":[-122.584362,45.379518],"type":"Point"}
}