{
  "type": "Feature",
  "properties": {
    "iso:country":"US",
    "sg:address":"10200 SW Hoodview Dr",
    "sg:city":"Portland",
    "sg:classifiers":[
        {
            "category":"Wholesale",
            "subcategory":"Apparel",
            "type":"Manufacturing & Wholesale Goods"
        }
    ],
    "sg:phone":"+1 503 860 2117",
    "sg:postcode":"97224",
    "sg:province":"OR",
    "wof:name":"A Day In The Park Clothing",
    "wof:placetype":"venue"
},
  "geometry": {"coordinates":[-122.78381899999999,45.409989],"type":"Point"}
}