{
  "type": "Feature",
  "properties": {
    "addr:full":"7355 SW Wickiup Ave Redmond OR 97756",
    "addr:housenumber":"7355",
    "addr:postcode":"97756",
    "addr:street":"Sw Wickiup Ave",
    "iso:country":"US",
    "sg:address":"7355 SW Wickiup Ave",
    "sg:city":"Redmond",
    "sg:classifiers":[
        {
            "category":"Education",
            "subcategory":"School",
            "type":"Public Place"
        }
    ],
    "sg:phone":"+1 541 923 6719",
    "sg:postcode":"97756",
    "sg:province":"OR",
    "wof:name":"High Valley Enterprises",
    "wof:placetype":"venue"
},
  "geometry": {"coordinates":[-121.25898100000001,44.247567],"type":"Point"}
}