{
  "type": "Feature",
  "properties": {
    "addr:full":"7160 SW Hazelfern Rd Tigard OR 97224",
    "addr:housenumber":"7160",
    "addr:postcode":"97224",
    "addr:street":"Sw Hazelfern Rd",
    "iso:country":"US",
    "sg:address":"7160 SW Hazelfern Rd",
    "sg:city":"Tigard",
    "sg:classifiers":[
        {
            "category":"Insurance",
            "subcategory":"Insurance Agent",
            "type":"Services"
        }
    ],
    "sg:phone":"+1 503 601 2070",
    "sg:postcode":"97224",
    "sg:province":"OR",
    "wof:name":"Ted Johnson",
    "wof:placetype":"venue"
},
  "geometry": {"coordinates":[-122.751135,45.394627],"type":"Point"}
}