{
  "type": "Feature",
  "properties": {
    "addr:full":"4206 SE Martins St Portland OR 97206",
    "addr:housenumber":"4206",
    "addr:postcode":"97206",
    "addr:street":"Se Martins St",
    "iso:country":"US",
    "sg:address":"4206 SE Martins St",
    "sg:city":"Portland",
    "sg:classifiers":[
        {
            "category":"Building & Trades",
            "subcategory":"Construction",
            "type":"Services"
        }
    ],
    "sg:phone":"+1 503 708 9530",
    "sg:postcode":"97206",
    "sg:province":"OR",
    "sg:tags":[
        "wallcoverings-installation",
        "wallpaper",
        "painting",
        "contractor"
    ],
    "wof:name":"Jacoby & Rogue Paint Removal, Inc.",
    "wof:placetype":"venue"
},
  "geometry": {"coordinates":[-122.61935699999999,45.47844],"type":"Point"}
}