{
  "type": "Feature",
  "properties": {
    "addr:full":"9663 SW Barbur Blvd Portland OR 97219",
    "addr:housenumber":"9663",
    "addr:postcode":"97219",
    "addr:street":"Sw Barbur Blvd",
    "iso:country":"US",
    "sg:address":"9663 SW Barbur Blvd",
    "sg:city":"Portland",
    "sg:classifiers":[
        {
            "category":"Health Services",
            "subcategory":"Clinic",
            "type":"Services"
        }
    ],
    "sg:phone":"+1 866 374 0017",
    "sg:postcode":"97219",
    "sg:province":"OR",
    "sg:tags":[
        "welfare"
    ],
    "sg:website":"http://www.advancedfootclinic.org",
    "wof:name":"Advanced Foot Clinic",
    "wof:placetype":"venue"
},
  "geometry": {"coordinates":[-122.717039,45.45538],"type":"Point"}
}