{
  "type": "Feature",
  "properties": {
    "iso:country":"US",
    "sg:address":"2525 US Hwy 101",
    "sg:city":"Seaside",
    "sg:classifiers":[
        {
            "category":"Building & Trades",
            "subcategory":"Equipment Rental",
            "type":"Services"
        }
    ],
    "sg:phone":"+1 503 738 7368",
    "sg:postcode":"97138",
    "sg:province":"OR",
    "sg:website":"www.ur.com",
    "wof:name":"United Rentals",
    "wof:placetype":"venue"
},
  "geometry": {"coordinates":[-123.91075499999999,46.012921],"type":"Point"}
}