{
  "type": "Feature",
  "properties": {
    "iso:country":"US",
    "sg:address":"9440 SW Beaverton-Hillsdale Hwy",
    "sg:city":"Portland",
    "sg:classifiers":[
        {
            "category":"Professional",
            "subcategory":"Employment Agencies",
            "type":"Services"
        }
    ],
    "sg:phone":"+1 503 297 7730",
    "sg:postcode":"97005",
    "sg:province":"OR",
    "sg:tags":[
        "modeling"
    ],
    "wof:name":"John Casablancas Modeling",
    "wof:placetype":"venue"
},
  "geometry": {"coordinates":[-122.771956,45.486374],"type":"Point"}
}