{
  "type": "Feature",
  "properties": {
    "addr:full":"1017 SW Morrison St. Suite 510 Portland OR 97205",
    "addr:housenumber":"1017",
    "addr:postcode":"97205",
    "addr:street":"Sw Morrison St. Suite 510",
    "iso:country":"US",
    "sg:address":"1017 SW Morrison St. Suite 510",
    "sg:city":"Portland",
    "sg:classifiers":[
        {
            "category":"Personal",
            "subcategory":"Massage",
            "type":"Services"
        }
    ],
    "sg:phone":"+1 503 830 1903",
    "sg:postcode":"97205",
    "sg:province":"OR",
    "sg:website":"www.davidemerymassage.com",
    "wof:name":"David Leon Emery Massage",
    "wof:placetype":"venue"
},
  "geometry": {"coordinates":[-122.682517,45.520161],"type":"Point"}
}