{
  "type": "Feature",
  "properties": {
    "addr:full":"6371 Sunnyview Rd NE Salem OR 97305",
    "addr:housenumber":"6371",
    "addr:postcode":"97305",
    "addr:street":"Sunnyview Rd Ne",
    "iso:country":"US",
    "sg:address":"6371 Sunnyview Rd NE",
    "sg:city":"Salem",
    "sg:classifiers":[
        {
            "category":"Manufacturing",
            "subcategory":"Chemicals & Compounds",
            "type":"Manufacturing & Wholesale Goods"
        }
    ],
    "sg:phone":"+1 503 399 1139",
    "sg:postcode":"97305",
    "sg:province":"OR",
    "sg:tags":[
        "industrial",
        "organic",
        "mfg"
    ],
    "wof:name":"Renu Chemical Company",
    "wof:placetype":"venue"
},
  "geometry": {"coordinates":[-122.92997800000001,44.955923],"type":"Point"}
}