{
  "type": "Feature",
  "properties": {
    "addr:full":"6973 Birchwood Ct N Keizer OR 97303",
    "addr:housenumber":"6973",
    "addr:postcode":"97303",
    "addr:street":"Birchwood Ct N",
    "iso:country":"US",
    "sg:address":"6973 Birchwood Ct N",
    "sg:city":"Keizer",
    "sg:classifiers":[
        {
            "category":"Wholesale",
            "subcategory":"Home Furnishings",
            "type":"Manufacturing & Wholesale Goods"
        }
    ],
    "sg:phone":"+1 503 399 1856",
    "sg:postcode":"97303",
    "sg:province":"OR",
    "sg:tags":[
        "closet",
        "accessory"
    ],
    "wof:name":"Beyer Closet Co",
    "wof:placetype":"venue"
},
  "geometry": {"coordinates":[-123.02646799999999,45.018875],"type":"Point"}
}