{
  "type": "Feature",
  "properties": {
    "iso:country":"US",
    "sg:address":"51690 Gates Brg E",
    "sg:city":"Gates",
    "sg:classifiers":[
        {
            "category":"Professional",
            "subcategory":"Management & Consulting",
            "type":"Services"
        }
    ],
    "sg:phone":"+1 503 897 2441",
    "sg:postcode":"97346",
    "sg:province":"OR",
    "sg:tags":[
        "consultant",
        "educational"
    ],
    "wof:name":"Cady & Assos",
    "wof:placetype":"venue"
},
  "geometry": {"coordinates":[-122.37962400000001,44.750509],"type":"Point"}
}