{
  "type": "Feature",
  "properties": {
    "iso:country":"US",
    "sg:address":"2727 Darrow Ave",
    "sg:city":"Klamath Falls",
    "sg:classifiers":[
        {
            "category":"Building & Trades",
            "subcategory":"Cleaning & Sanitation",
            "type":"Services"
        }
    ],
    "sg:phone":"+1 541 882 5490",
    "sg:postcode":"97603",
    "sg:province":"OR",
    "sg:tags":[
        "maintenance"
    ],
    "wof:name":"Carpenters Thuro Kleen",
    "wof:placetype":"venue"
},
  "geometry": {"coordinates":[-121.75599,42.221219],"type":"Point"}
}