{
  "type": "Feature",
  "properties": {
    "iso:country":"US",
    "sg:address":"405 SW 6th St",
    "sg:city":"Redmond",
    "sg:classifiers":[
        {
            "category":"Banks & Credit Unions",
            "subcategory":"Investment Brokerage",
            "type":"Services"
        }
    ],
    "sg:phone":"+1 541 504 2389",
    "sg:postcode":"97756",
    "sg:province":"OR",
    "sg:tags":[
        "stock",
        "bond"
    ],
    "wof:name":"A G Edwards & Sons Inc",
    "wof:placetype":"venue"
},
  "geometry": {"coordinates":[-121.174363,44.27351],"type":"Point"}
}