{
  "type": "Feature",
  "properties": {
    "iso:country":"US",
    "sg:address":"1609 S Main Ave",
    "sg:city":"Warrenton",
    "sg:classifiers":[
        {
            "category":"Restaurant",
            "type":"Food & Drink"
        }
    ],
    "sg:phone":"+1 503 861 0520",
    "sg:postcode":"97146",
    "sg:province":"OR",
    "wof:name":"Arnie's Cafe",
    "wof:placetype":"venue"
},
  "geometry": {"coordinates":[-123.928121,46.14939],"type":"Point"}
}