{
  "type": "Feature",
  "properties": {
    "iso:country":"US",
    "sg:address":"752 SE 148th Ave",
    "sg:city":"Portland",
    "sg:classifiers":[
        {
            "category":"Retail",
            "subcategory":"Laundry & Dry Cleaning",
            "type":"Services"
        }
    ],
    "sg:phone":"+1 503 262 8030",
    "sg:postcode":"97233",
    "sg:province":"OR",
    "sg:tags":[
        "cleaner",
        "rug",
        "carpet"
    ],
    "wof:name":"Professional Carpet Cleaners",
    "wof:placetype":"venue"
},
  "geometry": {"coordinates":[-122.510745,45.517401],"type":"Point"}
}