{
  "type": "Feature",
  "properties": {
    "addr:full":"6539 Ganon Rd SE Salem OR 97301",
    "addr:housenumber":"6539",
    "addr:postcode":"97301",
    "addr:street":"Ganon Rd Se",
    "iso:country":"US",
    "sg:address":"6539 Ganon Rd SE",
    "sg:city":"Salem",
    "sg:classifiers":[
        {
            "category":"Building & Trades",
            "subcategory":"Plumbing",
            "type":"Services"
        }
    ],
    "sg:phone":"+1 503 362 1973",
    "sg:postcode":"97301",
    "sg:province":"OR",
    "sg:tags":[
        "contractor"
    ],
    "wof:name":"Cortez Plumbing",
    "wof:placetype":"venue"
},
  "geometry": {"coordinates":[-122.92863800000001,44.900414],"type":"Point"}
}