{
  "type": "Feature",
  "properties": {
    "addr:full":"414 Williamson Way Ashland OR 97520",
    "addr:housenumber":"414",
    "addr:postcode":"97520",
    "addr:street":"Williamson Way",
    "iso:country":"US",
    "sg:address":"414 Williamson Way",
    "sg:city":"Ashland",
    "sg:classifiers":[
        {
            "category":"Manufacturing",
            "subcategory":"Glass & Minerals",
            "type":"Manufacturing & Wholesale Goods"
        }
    ],
    "sg:phone":"+1 541 482 3752",
    "sg:postcode":"97520",
    "sg:province":"OR",
    "sg:tags":[
        "cast",
        "stone",
        "mfg"
    ],
    "wof:name":"Thomas-Boyd Industrial Corp",
    "wof:placetype":"venue"
},
  "geometry": {"coordinates":[-122.70402799999999,42.200442],"type":"Point"}
}