{
  "type": "Feature",
  "properties": {
    "addr:full":"5078 Henderer Rd Elkton OR 97436",
    "addr:housenumber":"5078",
    "addr:postcode":"97436",
    "addr:street":"Henderer Rd",
    "iso:country":"US",
    "sg:address":"5078 Henderer Rd",
    "sg:city":"Elkton",
    "sg:classifiers":[
        {
            "category":"Banks & Credit Unions",
            "subcategory":"Bank",
            "type":"Services"
        }
    ],
    "sg:phone":"+1 541 584 2408",
    "sg:postcode":"97436",
    "sg:province":"OR",
    "sg:tags":[
        "broker",
        "mortgage"
    ],
    "wof:name":"Continental Funding USA",
    "wof:placetype":"venue"
},
  "geometry": {"coordinates":[-123.656842,43.638659],"type":"Point"}
}