{
  "type": "Feature",
  "properties": {
    "iso:country":"US",
    "sg:address":"1919 NW Beca Ave",
    "sg:city":"Corvallis",
    "sg:classifiers":[
        {
            "category":"Professional",
            "subcategory":"Lawyer & Legal Services",
            "type":"Services"
        }
    ],
    "sg:phone":"+1 541 757 8959",
    "sg:postcode":"97330",
    "sg:province":"OR",
    "sg:tags":[
        "attorney"
    ],
    "wof:name":"David B Connell PC",
    "wof:placetype":"venue"
},
  "geometry": {"coordinates":[-123.27331100000001,44.578219],"type":"Point"}
}