{
  "type": "Feature",
  "properties": {
    "iso:country":"US",
    "sg:address":"301 W 5th Ave",
    "sg:city":"Eugene",
    "sg:classifiers":[
        {
            "category":"Personal",
            "subcategory":"Barber",
            "type":"Services"
        },
        {
            "category":"Personal",
            "subcategory":"Day Spa",
            "type":"Services"
        },
        {
            "category":"Personal",
            "subcategory":"Nail Salon",
            "type":"Services"
        },
        {
            "category":"Personal",
            "subcategory":"Skin Care",
            "type":"Services"
        },
        {
            "category":"Personal",
            "subcategory":"Beauty Salon",
            "type":"Services"
        },
        {
            "category":"Personal",
            "subcategory":"Massage",
            "type":"Services"
        }
    ],
    "sg:phone":"+1 541 334 6533",
    "sg:postcode":"97401",
    "sg:province":"OR",
    "sg:tags":[
        "therapist"
    ],
    "sg:website":"http://www.gervaiseugene.com",
    "wof:name":"Gervais Salon",
    "wof:placetype":"venue"
},
  "geometry": {"coordinates":[-123.09729799999999,44.05434],"type":"Point"}
}