{
  "type": "Feature",
  "properties": {
    "addr:full":"1160 NW Elliot Ct Bend OR 97701",
    "addr:housenumber":"1160",
    "addr:postcode":"97701",
    "addr:street":"Nw Elliot Ct",
    "iso:country":"US",
    "sg:address":"1160 NW Elliot Ct",
    "sg:city":"Bend",
    "sg:classifiers":[
        {
            "category":"Professional",
            "subcategory":"Computer Services",
            "type":"Services"
        }
    ],
    "sg:phone":"+1 541 330 0343",
    "sg:postcode":"97701",
    "sg:province":"OR",
    "sg:tags":[
        "consultant",
        "designer"
    ],
    "wof:name":"Intel Corp",
    "wof:placetype":"venue"
},
  "geometry": {"coordinates":[-121.329032,44.079326],"type":"Point"}
}