{
  "type": "Feature",
  "properties": {
    "iso:country":"US",
    "sg:address":"394 Main St",
    "sg:city":"Dallas",
    "sg:classifiers":[
        {
            "category":"Sports & Exercise",
            "subcategory":"Bowling",
            "type":"Entertainment"
        }
    ],
    "sg:phone":"+1 503 623 4267",
    "sg:postcode":"97338",
    "sg:province":"OR",
    "sg:tags":[
        "center"
    ],
    "wof:name":"Starlite Lanes",
    "wof:placetype":"venue"
},
  "geometry": {"coordinates":[-123.31503600000001,44.926207],"type":"Point"}
}