{
  "type": "Feature",
  "properties": {
    "iso:country":"US",
    "sg:address":"15060 SE Robinette Ct",
    "sg:city":"Portland",
    "sg:classifiers":[
        {
            "category":"Manufacturing",
            "subcategory":"Metals",
            "type":"Manufacturing & Wholesale Goods"
        }
    ],
    "sg:phone":"+1 503 708 3152",
    "sg:postcode":"97267",
    "sg:province":"OR",
    "sg:tags":[
        "work",
        "iron"
    ],
    "wof:name":"Slavik Iron Works",
    "wof:placetype":"venue"
},
  "geometry": {"coordinates":[-122.600357,45.41335],"type":"Point"}
}