{
  "type": "Feature",
  "properties": {
    "iso:country":"US",
    "sg:address":"6 NE Tillamook Street",
    "sg:city":"Portland",
    "sg:classifiers":[
        {
            "category":"Professional",
            "subcategory":"Employment Agencies",
            "type":"Services"
        }
    ],
    "sg:phone":"+1 503 284 3450",
    "sg:postcode":"97212",
    "sg:province":"OR",
    "wof:name":"Anytime Labor",
    "wof:placetype":"venue"
},
  "geometry": {"coordinates":[-122.666471,45.537941],"type":"Point"}
}