{
  "type": "Feature",
  "properties": {
    "iso:country":"US",
    "sg:address":"2650 Montello Ave",
    "sg:city":"Hood River",
    "sg:classifiers":[
        {
            "category":"Organizations",
            "subcategory":"Religious Organization",
            "type":"Services"
        }
    ],
    "sg:phone":"+1 541 386 2812",
    "sg:postcode":"97031",
    "sg:province":"OR",
    "wof:name":"Hood River Alliance Church",
    "wof:placetype":"venue"
},
  "geometry": {"coordinates":[-121.538357,45.705663],"type":"Point"}
}