{
  "type": "Feature",
  "properties": {
    "addr:full":"4130 SW 110th Ave Beaverton OR 97005",
    "addr:housenumber":"4130",
    "addr:postcode":"97005",
    "addr:street":"Sw 110Th Ave",
    "iso:country":"US",
    "sg:address":"4130 SW 110th Ave",
    "sg:city":"Beaverton",
    "sg:classifiers":[
        {
            "category":"Health Services",
            "subcategory":"Dentist",
            "type":"Services"
        }
    ],
    "sg:phone":"+1 503 626 0998",
    "sg:postcode":"97005",
    "sg:province":"OR",
    "wof:name":"Kloucek John DMD",
    "wof:placetype":"venue"
},
  "geometry": {"coordinates":[-122.790001,45.490501],"type":"Point"}
}