{
  "type": "Feature",
  "properties": {
    "addr:full":"290 W Gloucester St Gladstone OR 97027",
    "addr:housenumber":"290",
    "addr:postcode":"97027",
    "addr:street":"W Gloucester St",
    "iso:country":"US",
    "sg:address":"290 W Gloucester St",
    "sg:city":"Gladstone",
    "sg:classifiers":[
        {
            "category":"Education",
            "subcategory":"Preschool",
            "type":"Public Place"
        },
        {
            "category":"Education",
            "subcategory":"School",
            "type":"Public Place"
        }
    ],
    "sg:phone":"+1 503 656 8194",
    "sg:postcode":"97027",
    "sg:province":"OR",
    "sg:tags":[
        "elementary"
    ],
    "wof:name":"St Stephen Lutheran Church",
    "wof:placetype":"venue"
},
  "geometry": {"coordinates":[-122.59899900000001,45.381199],"type":"Point"}
}