{
  "type": "Feature",
  "properties": {
    "addr:full":"15211 SE 130th Dr Clackamas OR 97015",
    "addr:postcode":"15211;97015",
    "addr:street":"Se 130Th Dr",
    "iso:country":"US",
    "sg:address":"15211 SE 130th Dr",
    "sg:city":"Clackamas",
    "sg:classifiers":[
        {
            "category":"Building & Trades",
            "subcategory":"Construction",
            "type":"Services"
        }
    ],
    "sg:phone":"+1 503 698 3379",
    "sg:postcode":"97015",
    "sg:province":"OR",
    "sg:tags":[
        "glazier",
        "contractor"
    ],
    "wof:name":"Art Glass By Dale Rohrer",
    "wof:placetype":"venue"
},
  "geometry": {"coordinates":[-122.52977,45.412565],"type":"Point"}
}