{
  "type": "Feature",
  "properties": {
    "iso:country":"US",
    "sg:address":"9643 SW Alsea Dr",
    "sg:city":"Tualatin",
    "sg:classifiers":[
        {
            "category":"Professional",
            "subcategory":"Business Services",
            "type":"Services"
        }
    ],
    "sg:phone":"+1 503 691 9844",
    "sg:postcode":"97062",
    "sg:province":"OR",
    "wof:name":"Smartreply",
    "wof:placetype":"venue"
},
  "geometry": {"coordinates":[-122.778984,45.363949],"type":"Point"}
}