{
  "type": "Feature",
  "properties": {
    "iso:country":"US",
    "sg:address":"345 E Historic Columbia River Hwy",
    "sg:city":"Troutdale",
    "sg:classifiers":[
        {
            "category":"Shopping",
            "subcategory":"Used Merchandise",
            "type":"Retail Goods"
        }
    ],
    "sg:phone":"+1 503 661 0123",
    "sg:postcode":"97060",
    "sg:province":"OR",
    "sg:tags":[
        "antique"
    ],
    "wof:name":"Nostalgia Antiques & Cllctbls",
    "wof:placetype":"venue"
},
  "geometry": {"coordinates":[-122.37264399999999,45.536463],"type":"Point"}
}