{
  "type": "Feature",
  "properties": {
    "iso:country":"US",
    "sg:address":"29200 Hwy 140 W",
    "sg:city":"Klamath Falls",
    "sg:classifiers":[
        {
            "category":"Shopping",
            "subcategory":"Bicycles & Sporting Goods",
            "type":"Retail Goods"
        }
    ],
    "sg:phone":"+1 541 356 2155",
    "sg:postcode":"97601",
    "sg:province":"OR",
    "sg:tags":[
        "operation"
    ],
    "wof:name":"Pyramid Motel & Gas Mart",
    "wof:placetype":"venue"
},
  "geometry": {"coordinates":[-122.099239,42.444729],"type":"Point"}
}