{
  "type": "Feature",
  "properties": {
    "iso:country":"US",
    "sg:address":"229 King St",
    "sg:city":"Brookings",
    "sg:classifiers":[
        {
            "category":"Retail",
            "subcategory":"Auto Repair",
            "type":"Services"
        }
    ],
    "sg:phone":"+1 541 469 3040",
    "sg:postcode":"97415",
    "sg:province":"OR",
    "sg:tags":[
        "body",
        "automobile",
        "painting"
    ],
    "wof:name":"Suiter's Paint & Body",
    "wof:placetype":"venue"
},
  "geometry": {"coordinates":[-124.284904,42.048444],"type":"Point"}
}