{
  "type": "Feature",
  "properties": {
    "iso:country":"US",
    "sg:address":"3334 N Terry St",
    "sg:city":"Portland",
    "sg:classifiers":[
        {
            "category":"Food & Beverages",
            "subcategory":"Liquor & Beverages",
            "type":"Retail Goods"
        },
        {
            "category":"Wholesale",
            "subcategory":"Wine & Distilled Alcoholic Beverages",
            "type":"Manufacturing & Wholesale Goods"
        }
    ],
    "sg:phone":"+1 503 679 0379",
    "sg:postcode":"97217",
    "sg:province":"OR",
    "sg:tags":[
        "broker"
    ],
    "wof:name":"Atlas Wine Products",
    "wof:placetype":"venue"
},
  "geometry": {"coordinates":[-122.70125899999999,45.579861],"type":"Point"}
}