{
  "type": "Feature",
  "properties": {
    "addr:full":"9620 SW 166th Ave Beaverton OR 97007",
    "addr:housenumber":"9620",
    "addr:postcode":"97007",
    "addr:street":"Sw 166Th Ave",
    "iso:country":"US",
    "sg:address":"9620 SW 166th Ave",
    "sg:city":"Beaverton",
    "sg:classifiers":[
        {
            "category":"Wholesale",
            "subcategory":"Groceries",
            "type":"Manufacturing & Wholesale Goods"
        }
    ],
    "sg:phone":"+1 503 590 3145",
    "sg:postcode":"97007",
    "sg:province":"OR",
    "sg:tags":[
        "food",
        "broker"
    ],
    "wof:name":"Doraul Marketing Associates",
    "wof:placetype":"venue"
},
  "geometry": {"coordinates":[-122.84726999999999,45.450654],"type":"Point"}
}