{
  "type": "Feature",
  "properties": {
    "addr:full":"5011 NE 13th Ave Portland OR 97211",
    "addr:housenumber":"5011",
    "addr:postcode":"97211",
    "addr:street":"Ne 13Th Ave",
    "iso:country":"US",
    "sg:address":"5011 NE 13th Ave",
    "sg:city":"Portland",
    "sg:classifiers":[
        {
            "category":"Personal",
            "subcategory":"Beauty Salon",
            "type":"Services"
        }
    ],
    "sg:phone":"+1 503 719 7930",
    "sg:postcode":"97211",
    "sg:province":"OR",
    "sg:tags":[
        "hair"
    ],
    "sg:website":"redmagnoliasalon.com/",
    "wof:name":"Red Magnolia Salon",
    "wof:placetype":"venue"
},
  "geometry": {"coordinates":[-122.65295399999999,45.55934],"type":"Point"}
}