{
  "type": "Feature",
  "properties": {
    "addr:full":"357 Glenn St Ashland OR 97520",
    "addr:housenumber":"357",
    "addr:postcode":"97520",
    "addr:street":"Glenn St",
    "iso:country":"US",
    "sg:address":"357 Glenn St",
    "sg:city":"Ashland",
    "sg:classifiers":[
        {
            "category":"Arts & Performance",
            "subcategory":"Theater",
            "type":"Entertainment"
        }
    ],
    "sg:phone":"+1 541 482 9563",
    "sg:postcode":"97520",
    "sg:province":"OR",
    "wof:name":"Oregon Cabaret Theatre",
    "wof:placetype":"venue"
},
  "geometry": {"coordinates":[-122.71932200000001,42.20598],"type":"Point"}
}