{
  "type": "Feature",
  "properties": {
    "addr:full":"10788 SW Oriole Cir Beaverton OR 97007",
    "addr:housenumber":"10788",
    "addr:postcode":"97007",
    "addr:street":"Sw Oriole Cir",
    "iso:country":"US",
    "sg:address":"10788 SW Oriole Cir",
    "sg:city":"Beaverton",
    "sg:classifiers":[
        {
            "category":"Insurance",
            "subcategory":"Insurance Agent",
            "type":"Services"
        }
    ],
    "sg:phone":"+1 503 646 1174",
    "sg:postcode":"97007",
    "sg:province":"OR",
    "sg:website":"www.smartinsurance.com",
    "wof:name":"Farmers Insurance Group",
    "wof:placetype":"venue"
},
  "geometry": {"coordinates":[-122.839455,45.442314],"type":"Point"}
}