{
  "type": "Feature",
  "properties": {
    "iso:country":"US",
    "sg:address":"445 E 33rd Ave",
    "sg:city":"Eugene",
    "sg:classifiers":[
        {
            "category":"Professional",
            "subcategory":"Business Services",
            "type":"Services"
        }
    ],
    "sg:phone":"+1 541 683 6102",
    "sg:postcode":"97405",
    "sg:province":"OR",
    "sg:tags":[
        "translator",
        "interpreter"
    ],
    "wof:name":"East Meets West Japanese",
    "wof:placetype":"venue"
},
  "geometry": {"coordinates":[-123.085768,44.021058],"type":"Point"}
}