{
  "type": "Feature",
  "properties": {
    "iso:country":"US",
    "sg:address":"912 12th St SE",
    "sg:city":"Salem",
    "sg:classifiers":[
        {
            "category":"Personal",
            "subcategory":"Beauty Salon",
            "type":"Services"
        }
    ],
    "sg:phone":"+1 503 371 8177",
    "sg:postcode":"97302",
    "sg:province":"OR",
    "sg:tags":[
        "shop"
    ],
    "wof:name":"Mojo Salon & Spa",
    "wof:placetype":"venue"
},
  "geometry": {"coordinates":[-123.030556,44.928383],"type":"Point"}
}