{
  "type": "Feature",
  "properties": {
    "addr:full":"1675 SW Marlow Ave Portland OR 97225",
    "addr:housenumber":"1675",
    "addr:postcode":"97225",
    "addr:street":"Sw Marlow Ave",
    "iso:country":"US",
    "sg:address":"1675 SW Marlow Ave",
    "sg:city":"Portland",
    "sg:classifiers":[
        {
            "category":"Organizations",
            "subcategory":"Non-profit Organization",
            "type":"Services"
        }
    ],
    "sg:phone":"+1 503 644 5383",
    "sg:postcode":"97225",
    "sg:province":"OR",
    "wof:name":"EXYP",
    "wof:placetype":"venue"
},
  "geometry": {"coordinates":[-122.783834,45.508485],"type":"Point"}
}