{
  "type": "Feature",
  "properties": {
    "iso:country":"US",
    "sg:address":"34 SE 70th Ave",
    "sg:city":"Portland",
    "sg:classifiers":[
        {
            "category":"Professional",
            "subcategory":"Management & Consulting",
            "type":"Services"
        }
    ],
    "sg:phone":"+1 503 251 8960",
    "sg:postcode":"97215",
    "sg:province":"OR",
    "wof:name":"Burnside Capital MGT LLC",
    "wof:placetype":"venue"
},
  "geometry": {"coordinates":[-122.590816,45.522025],"type":"Point"}
}