{
  "type": "Feature",
  "properties": {
    "addr:full":"8840 SW Citizens Dr Wilsonville OR 97070",
    "addr:housenumber":"8840",
    "addr:postcode":"97070",
    "addr:street":"Sw Citizens Dr",
    "iso:country":"US",
    "sg:address":"8840 SW Citizens Dr",
    "sg:city":"Wilsonville",
    "sg:classifiers":[
        {
            "category":"Travel",
            "subcategory":"Hotels & Motels",
            "type":"Entertainment"
        }
    ],
    "sg:phone":"+1 503 682 1737",
    "sg:postcode":"97070",
    "sg:province":"OR",
    "sg:website":"www.westoverinns.com",
    "wof:name":"Westover Inns",
    "wof:placetype":"venue"
},
  "geometry": {"coordinates":[-122.767803,45.303906],"type":"Point"}
}