{
  "type": "Feature",
  "properties": {
    "iso:country":"US",
    "sg:address":"2103 10th St",
    "sg:city":"Tillamook",
    "sg:classifiers":[
        {
            "category":"Health Services",
            "subcategory":"Doctor",
            "type":"Services"
        }
    ],
    "sg:phone":"+1 503 842 5320",
    "sg:postcode":"97141",
    "sg:province":"OR",
    "wof:name":"Dennis S Wagner DMD PC",
    "wof:placetype":"venue"
},
  "geometry": {"coordinates":[-123.843125,45.451081],"type":"Point"}
}