{
  "type": "Feature",
  "properties": {
    "iso:country":"US",
    "sg:address":"25 E Main St",
    "sg:city":"Ashland",
    "sg:classifiers":[
        {
            "category":"Shopping",
            "subcategory":"Clothing, Apparel, & Fashions",
            "type":"Retail Goods"
        }
    ],
    "sg:phone":"+1 541 482 3621",
    "sg:postcode":"97520",
    "sg:province":"OR",
    "sg:tags":[
        "jewelry",
        "clothing",
        "boys'",
        "gift",
        "shoe"
    ],
    "sg:website":"http://www.clubnimbus.net",
    "wof:name":"Nimbus",
    "wof:placetype":"venue"
},
  "geometry": {"coordinates":[-122.71459400000001,42.197101],"type":"Point"}
}