{
  "type": "Feature",
  "properties": {
    "iso:country":"US",
    "sg:address":"11115 SE Pembroke Ct",
    "sg:city":"Milwaukie",
    "sg:classifiers":[
        {
            "category":"Building & Trades",
            "subcategory":"Construction",
            "type":"Services"
        }
    ],
    "sg:phone":"+1 503 659 8419",
    "sg:postcode":"97222",
    "sg:province":"OR",
    "sg:tags":[
        "repairing",
        "house",
        "remodeling",
        "contractor"
    ],
    "wof:name":"Olson Brothers Remodeling",
    "wof:placetype":"venue"
},
  "geometry": {"coordinates":[-122.593095,45.441702],"type":"Point"}
}