{
  "type": "Feature",
  "properties": {
    "addr:full":"64623 Spur Loop Heppner OR 97836",
    "addr:housenumber":"64623",
    "addr:postcode":"97836",
    "addr:street":"Spur Loop",
    "iso:country":"US",
    "sg:address":"64623 Spur Loop",
    "sg:city":"Heppner",
    "sg:classifiers":[
        {
            "category":"Manufacturing",
            "subcategory":"Pet Food",
            "type":"Manufacturing & Wholesale Goods"
        }
    ],
    "sg:phone":"+1 541 676 9014",
    "sg:postcode":"97836",
    "sg:province":"OR",
    "sg:tags":[
        "feed",
        "mfg",
        "prepared"
    ],
    "wof:name":"Kirk & Robinson Ranch",
    "wof:placetype":"venue"
},
  "geometry": {"coordinates":[-119.488563,45.477982],"type":"Point"}
}