{
  "type": "Feature",
  "properties": {
    "iso:country":"US",
    "sg:address":"277 Edwards Rd",
    "sg:city":"Monmouth",
    "sg:classifiers":[
        {
            "category":"Building & Trades",
            "subcategory":"Construction",
            "type":"Services"
        }
    ],
    "sg:phone":"+1 503 606 9025",
    "sg:postcode":"97361",
    "sg:province":"OR",
    "sg:tags":[
        "residential",
        "builder",
        "home"
    ],
    "wof:name":"Scholze Taylor Builders Inc",
    "wof:placetype":"venue"
},
  "geometry": {"coordinates":[-123.218788,44.846571],"type":"Point"}
}