{
  "type": "Feature",
  "properties": {
    "addr:full":"1725 Geary St SE Albany OR 97322",
    "addr:housenumber":"1725",
    "addr:postcode":"97322",
    "addr:street":"Geary St Se",
    "iso:country":"US",
    "sg:address":"1725 Geary St SE",
    "sg:city":"Albany",
    "sg:classifiers":[
        {
            "category":"Professional",
            "type":"Services"
        },
        {
            "category":"Wholesale",
            "subcategory":"Durable Goods & Equipment",
            "type":"Manufacturing & Wholesale Goods"
        }
    ],
    "sg:phone":"+1 541 704 2299",
    "sg:postcode":"97322",
    "sg:province":"OR",
    "sg:tags":[
        "instrument",
        "scientific",
        "apparatus"
    ],
    "wof:name":"PMS Instruments Co",
    "wof:placetype":"venue"
},
  "geometry": {"coordinates":[-123.08320000000001,44.625759],"type":"Point"}
}