{
  "type": "Feature",
  "properties": {
    "iso:country":"US",
    "sg:address":"15821 NE Rose Pkwy",
    "sg:city":"Portland",
    "sg:classifiers":[
        {
            "category":"Manufacturing",
            "subcategory":"Signs",
            "type":"Manufacturing & Wholesale Goods"
        }
    ],
    "sg:phone":"+1 503 232 2115",
    "sg:postcode":"97230",
    "sg:province":"OR",
    "wof:name":"Columbia Neon Co",
    "wof:placetype":"venue"
},
  "geometry": {"coordinates":[-122.498057,45.543324],"type":"Point"}
}