{
  "type": "Feature",
  "properties": {
    "addr:full":"920 Westpoint Rd Lake Oswego OR 97034",
    "addr:housenumber":"920",
    "addr:postcode":"97034",
    "addr:street":"Westpoint Rd",
    "iso:country":"US",
    "sg:address":"920 Westpoint Rd",
    "sg:city":"Lake Oswego",
    "sg:classifiers":[
        {
            "category":"Professional",
            "subcategory":"Business Services",
            "type":"Services"
        }
    ],
    "sg:phone":"+1 503 635 7630",
    "sg:postcode":"97034",
    "sg:province":"OR",
    "sg:tags":[
        "interior",
        "consultant",
        "design",
        "decorator"
    ],
    "wof:name":"Details",
    "wof:placetype":"venue"
},
  "geometry": {"coordinates":[-122.67570600000001,45.413087],"type":"Point"}
}