{
  "type": "Feature",
  "properties": {
    "iso:country":"US",
    "sg:address":"920 Westpoint Rd",
    "sg:city":"Lake Oswego",
    "sg:classifiers":[
        {
            "category":"Professional",
            "subcategory":"Business Services",
            "type":"Services"
        }
    ],
    "sg:phone":"+1 503 635 7630",
    "sg:postcode":"97034",
    "sg:province":"OR",
    "sg:tags":[
        "interior",
        "consultant",
        "design",
        "decorator"
    ],
    "wof:name":"Details",
    "wof:placetype":"venue"
},
  "geometry": {"coordinates":[-122.675706,45.413087],"type":"Point"}
}