{
  "type": "Feature",
  "properties": {
    "iso:country":"US",
    "sg:address":"1577 Holly Ave",
    "sg:city":"Eugene",
    "sg:classifiers":[
        {
            "category":"Professional",
            "type":"Services"
        }
    ],
    "sg:phone":"+1 541 686 2186",
    "sg:postcode":"97408",
    "sg:province":"OR",
    "sg:tags":[
        "technical",
        "consulting",
        "writing"
    ],
    "wof:name":"Lynn Bonner Consulting",
    "wof:placetype":"venue"
},
  "geometry": {"coordinates":[-123.091077,44.091925],"type":"Point"}
}