{
  "type": "Feature",
  "properties": {
    "iso:country":"US",
    "sg:address":"1905 N Maple St",
    "sg:city":"Canby",
    "sg:classifiers":[
        {
            "category":"Education",
            "subcategory":"School",
            "type":"Public Place"
        }
    ],
    "sg:phone":"+1 503 266 7818",
    "sg:postcode":"97013",
    "sg:province":"OR",
    "wof:name":"First Baptist Church School",
    "wof:placetype":"venue"
},
  "geometry": {"coordinates":[-122.68684500000001,45.278867],"type":"Point"}
}