{
  "type": "Feature",
  "properties": {
    "iso:country":"US",
    "sg:address":"71046 Hwy 82",
    "sg:city":"Elgin",
    "sg:classifiers":[
        {
            "category":"Manufacturing",
            "subcategory":"Lumber",
            "type":"Manufacturing & Wholesale Goods"
        }
    ],
    "sg:phone":"+1 541 437 9561",
    "sg:postcode":"97827",
    "sg:province":"OR",
    "sg:tags":[
        "product",
        "forest",
        "gathering"
    ],
    "wof:name":"E R Sudway",
    "wof:placetype":"venue"
},
  "geometry": {"coordinates":[-117.917086,45.552883],"type":"Point"}
}