{
  "type": "Feature",
  "properties": {
    "iso:country":"US",
    "sg:address":"1015 Glenview Way NW",
    "sg:city":"Salem",
    "sg:classifiers":[
        {
            "category":"Building & Trades",
            "subcategory":"Construction",
            "type":"Services"
        }
    ],
    "sg:phone":"+1 503 588 1210",
    "sg:postcode":"97304",
    "sg:province":"OR",
    "sg:tags":[
        "house"
    ],
    "wof:name":"Cary Hammer",
    "wof:placetype":"venue"
},
  "geometry": {"coordinates":[-123.06274000000001,44.949829],"type":"Point"}
}