{
  "type": "Feature",
  "properties": {
    "iso:country":"US",
    "sg:address":"9170 NW Sargent Rd",
    "sg:city":"Gales Creek",
    "sg:classifiers":[
        {
            "category":"Organizations",
            "subcategory":"Religious Organization",
            "type":"Services"
        }
    ],
    "sg:phone":"+1 503 357 8873",
    "sg:postcode":"97117",
    "sg:province":"OR",
    "wof:name":"Gales Creek Community Church",
    "wof:placetype":"venue"
},
  "geometry": {"coordinates":[-123.21502700000001,45.586627],"type":"Point"}
}