{
  "type": "Feature",
  "properties": {
    "iso:country":"US",
    "sg:address":"333 SW Taylor St",
    "sg:city":"Portland",
    "sg:classifiers":[
        {
            "category":"Professional",
            "subcategory":"Management & Consulting",
            "type":"Services"
        }
    ],
    "sg:phone":"+1 503 243 6858",
    "sg:postcode":"97204",
    "sg:province":"OR",
    "sg:tags":[
        "fuel",
        "organizing",
        "business",
        "services-household"
    ],
    "wof:name":"Pacific Ore Management",
    "wof:placetype":"venue"
},
  "geometry": {"coordinates":[-122.676604,45.517018],"type":"Point"}
}