{
  "type": "Feature",
  "properties": {
    "iso:country":"US",
    "sg:address":"19754 Foster Ln",
    "sg:city":"Bend",
    "sg:classifiers":[
        {
            "category":"Food & Beverages",
            "subcategory":"Bakery",
            "type":"Retail Goods"
        }
    ],
    "sg:phone":"+1 541 765 2629",
    "sg:postcode":"97702",
    "sg:province":"OR",
    "wof:name":"Lincoln Beach Bagel Co",
    "wof:placetype":"venue"
},
  "geometry": {"coordinates":[-121.342415,44.00142],"type":"Point"}
}