{
  "type": "Feature",
  "properties": {
    "addr:full":"198 Commercial St SE Salem OR 97301",
    "addr:housenumber":"198",
    "addr:postcode":"97301",
    "addr:street":"Commercial St Se",
    "iso:country":"US",
    "sg:address":"198 Commercial St SE",
    "sg:city":"Salem",
    "sg:classifiers":[
        {
            "category":"Banks & Credit Unions",
            "subcategory":"Bank",
            "type":"Services"
        }
    ],
    "sg:phone":"+1 503 620 4471",
    "sg:postcode":"97301",
    "sg:province":"OR",
    "sg:tags":[
        "mortgage",
        "loan",
        "broker",
        "real estate"
    ],
    "wof:name":"Sunset Mortgage Co Inc",
    "wof:placetype":"venue"
},
  "geometry": {"coordinates":[-123.04049999999999,44.94037],"type":"Point"}
}