{
  "type": "Feature",
  "properties": {
    "addr:full":"818 SW 3rd Ave 244 Portland OR 97204",
    "addr:housenumber":"818;244",
    "addr:postcode":"97204",
    "addr:street":"Sw 3Rd Ave",
    "iso:country":"US",
    "sg:address":"818 SW 3rd Ave 244",
    "sg:city":"Portland",
    "sg:classifiers":[
        {
            "category":"Real Estate",
            "subcategory":"Real Estate Services",
            "type":"Services"
        },
        {
            "category":"Real Estate",
            "subcategory":"Real Estate Agent",
            "type":"Services"
        }
    ],
    "sg:phone":"+1 503 517 0244",
    "sg:postcode":"97204",
    "sg:province":"OR",
    "sg:tags":[
        "buyer",
        "broker"
    ],
    "wof:name":"Meadowlark Real Est",
    "wof:placetype":"venue"
},
  "geometry": {"coordinates":[-122.675984,45.517468],"type":"Point"}
}