{
  "type": "Feature",
  "properties": {
    "iso:country":"US",
    "sg:address":"9003 N Columbia Blvd",
    "sg:city":"Portland",
    "sg:classifiers":[
        {
            "category":"Manufacturing",
            "subcategory":"Metals",
            "type":"Manufacturing & Wholesale Goods"
        },
        {
            "category":"Retail",
            "subcategory":"Auto Repair",
            "type":"Services"
        }
    ],
    "sg:phone":"+1 503 737 1572",
    "sg:postcode":"97203",
    "sg:province":"OR",
    "sg:tags":[
        "co",
        "automobile",
        "drive",
        "transporter",
        "fabrication",
        "structural"
    ],
    "wof:name":"C J & M Transport Inc",
    "wof:placetype":"venue"
},
  "geometry": {"coordinates":[-122.750067,45.603916],"type":"Point"}
}