{
  "type": "Feature",
  "properties": {
    "iso:country":"US",
    "sg:address":"5119 River Rd N",
    "sg:city":"Salem",
    "sg:classifiers":[
        {
            "category":"Health Services",
            "subcategory":"Clinic",
            "type":"Services"
        }
    ],
    "sg:phone":"+1 503 390 5904",
    "sg:postcode":"97303",
    "sg:province":"OR",
    "sg:tags":[
        "residential",
        "specialty",
        "outpatient",
        "care"
    ],
    "wof:name":"Sahallie Nntch Cnfdrted Tribes",
    "wof:placetype":"venue"
},
  "geometry": {"coordinates":[-123.026709,44.999173],"type":"Point"}
}