{
  "type": "Feature",
  "properties": {
    "addr:full":"2141 NW 25th Ave Portland OR 97210",
    "addr:housenumber":"2141",
    "addr:postcode":"97210",
    "addr:street":"Nw 25Th Ave",
    "iso:country":"US",
    "sg:address":"2141 NW 25th Ave",
    "sg:city":"Portland",
    "sg:classifiers":[
        {
            "category":"Home & Garden",
            "subcategory":"Building Materials",
            "type":"Retail Goods"
        }
    ],
    "sg:phone":"+1 503 226 7341",
    "sg:postcode":"97210",
    "sg:province":"OR",
    "sg:tags":[
        "metal",
        "sheet",
        "equipment",
        "supply"
    ],
    "sg:website":"http://www.escocorp.com",
    "wof:name":"Stainless Steel Dist Group",
    "wof:placetype":"venue"
},
  "geometry": {"coordinates":[-122.702873,45.539051],"type":"Point"}
}