{
  "type": "Feature",
  "properties": {
    "addr:full":"147 NE 87th Ave Portland OR 97220",
    "addr:housenumber":"147",
    "addr:postcode":"97220",
    "addr:street":"Ne 87Th Ave",
    "iso:country":"US",
    "sg:address":"147 NE 87th Ave",
    "sg:city":"Portland",
    "sg:classifiers":[
        {
            "category":"Manufacturing",
            "subcategory":"Apparel",
            "type":"Manufacturing & Wholesale Goods"
        }
    ],
    "sg:phone":"+1 503 255 9898",
    "sg:postcode":"97220",
    "sg:province":"OR",
    "wof:name":"B D I",
    "wof:placetype":"venue"
},
  "geometry": {"coordinates":[-122.573949,45.52411],"type":"Point"}
}