{
  "type": "Feature",
  "properties": {
    "addr:full":"7319 N. John Ave. Suite 102 Portland OR 97203",
    "addr:housenumber":"7319",
    "addr:postcode":"97203",
    "addr:street":"N. John Ave. Suite 102",
    "iso:country":"US",
    "sg:address":"7319 N. John Ave. Suite 102",
    "sg:city":"Portland",
    "sg:classifiers":[
        {
            "category":"Personal",
            "subcategory":"Tanning Parlor",
            "type":"Services"
        }
    ],
    "sg:phone":"+1 503 860 8122",
    "sg:postcode":"97203",
    "sg:province":"OR",
    "wof:name":"MarTani Tanning Salon",
    "wof:placetype":"venue"
},
  "geometry": {"coordinates":[-122.75325599999999,45.589075],"type":"Point"}
}