{
  "type": "Feature",
  "properties": {
    "iso:country":"US",
    "sg:address":"17900 NE San Rafael St",
    "sg:city":"Portland",
    "sg:classifiers":[
        {
            "category":"Shopping",
            "subcategory":"Gifts & Souvenirs",
            "type":"Retail Goods"
        }
    ],
    "sg:phone":"+1 503 492 6551",
    "sg:postcode":"97230",
    "sg:province":"OR",
    "wof:name":"Trail Blazers",
    "wof:placetype":"venue"
},
  "geometry": {"coordinates":[-122.478931,45.537049],"type":"Point"}
}