{
  "type": "Feature",
  "properties": {
    "addr:full":"61150 27th St Bend OR 97702",
    "addr:housenumber":"61150",
    "addr:postcode":"97702",
    "addr:street":"27Th St",
    "iso:country":"US",
    "sg:address":"61150 27th St",
    "sg:city":"Bend",
    "sg:classifiers":[
        {
            "category":"Utilities",
            "subcategory":"Refuse",
            "type":"Services"
        }
    ],
    "sg:phone":"+1 541 388 6581",
    "sg:postcode":"97702",
    "sg:province":"OR",
    "sg:tags":[
        "executive",
        "system"
    ],
    "wof:name":"Road Department",
    "wof:placetype":"venue"
},
  "geometry": {"coordinates":[-121.263756,44.027902],"type":"Point"}
}