{
  "type": "Feature",
  "properties": {
    "iso:country":"US",
    "sg:address":"109 E 2nd St",
    "sg:city":"The Dalles",
    "sg:classifiers":[
        {
            "category":"Shopping",
            "subcategory":"Computers & Home Electronics",
            "type":"Retail Goods"
        }
    ],
    "sg:phone":"+1 541 296 2928",
    "sg:postcode":"97058",
    "sg:province":"OR",
    "sg:tags":[
        "television",
        "radio"
    ],
    "wof:name":"Harry's Radio & TV Svc",
    "wof:placetype":"venue"
},
  "geometry": {"coordinates":[-121.184113,45.602401],"type":"Point"}
}