{
  "type": "Feature",
  "properties": {
    "iso:country":"US",
    "sg:address":"1845 SE Ladd Ave",
    "sg:city":"Portland",
    "sg:classifiers":[
        {
            "category":"Arts & Performance",
            "subcategory":"Theater",
            "type":"Entertainment"
        }
    ],
    "sg:phone":"+1 503 232 9748",
    "sg:postcode":"97214",
    "sg:province":"OR",
    "sg:tags":[
        "musician",
        "group"
    ],
    "sg:website":"http://www.freakmountain.com",
    "wof:name":"Freak Mountain Ramblers",
    "wof:placetype":"venue"
},
  "geometry": {"coordinates":[-122.65093,45.509795],"type":"Point"}
}