{
  "type": "Feature",
  "properties": {
    "addr:full":"29899 SW Boones Ferry Rd Wilsonville OR 97070",
    "addr:housenumber":"29899",
    "addr:postcode":"97070",
    "addr:street":"Sw Boones Ferry Rd",
    "iso:country":"US",
    "sg:address":"29899 SW Boones Ferry Rd",
    "sg:city":"Wilsonville",
    "sg:classifiers":[
        {
            "category":"Professional",
            "subcategory":"Advertising",
            "type":"Services"
        }
    ],
    "sg:phone":"+1 503 685 9267",
    "sg:postcode":"97070",
    "sg:province":"OR",
    "sg:tags":[
        "distribution"
    ],
    "wof:name":"Tab Wharehouse",
    "wof:placetype":"venue"
},
  "geometry": {"coordinates":[-122.771049,45.304385],"type":"Point"}
}