{
  "type": "Feature",
  "properties": {
    "addr:full":"5655 Commercial St SE Salem OR 97306",
    "addr:housenumber":"5655",
    "addr:postcode":"97306",
    "addr:street":"Commercial St Se",
    "iso:country":"US",
    "sg:address":"5655 Commercial St SE",
    "sg:city":"Salem",
    "sg:classifiers":[
        {
            "category":"Recreation",
            "subcategory":"Marina",
            "type":"Entertainment"
        },
        {
            "category":"Manufacturing",
            "subcategory":"Watercraft",
            "type":"Manufacturing & Wholesale Goods"
        }
    ],
    "sg:phone":"+1 503 378 9064",
    "sg:postcode":"97306",
    "sg:province":"OR",
    "sg:tags":[
        "repairing",
        "repair",
        "boat"
    ],
    "wof:name":"Britton Boat Repair Inc",
    "wof:placetype":"venue"
},
  "geometry": {"coordinates":[-123.024714,44.87306],"type":"Point"}
}