{
  "type": "Feature",
  "properties": {
    "addr:full":"2299 Marine Dr Astoria OR 97103",
    "addr:housenumber":"2299",
    "addr:postcode":"97103",
    "addr:street":"Marine Dr",
    "iso:country":"US",
    "sg:address":"2299 Marine Dr",
    "sg:city":"Astoria",
    "sg:classifiers":[
        {
            "category":"Food & Beverages",
            "subcategory":"Liquor & Beverages",
            "type":"Retail Goods"
        }
    ],
    "sg:phone":"+1 503 325 4784",
    "sg:postcode":"97103",
    "sg:province":"OR",
    "sg:tags":[
        "store"
    ],
    "wof:name":"Liquor Stores",
    "wof:placetype":"venue"
},
  "geometry": {"coordinates":[-123.815752,46.188693],"type":"Point"}
}