{
  "type": "Feature",
  "properties": {
    "addr:full":"4233 SE 182nd Ave Gresham OR 97030",
    "addr:housenumber":"4233",
    "addr:postcode":"97030",
    "addr:street":"Se 182Nd Ave",
    "iso:country":"US",
    "sg:address":"4233 SE 182nd Ave",
    "sg:city":"Gresham",
    "sg:classifiers":[
        {
            "category":"Government",
            "subcategory":"Post Office",
            "type":"Public Place"
        }
    ],
    "sg:phone":"+1 503 666 7416",
    "sg:postcode":"97030",
    "sg:province":"OR",
    "wof:name":"Mailbox Depot & Gifts Llc",
    "wof:placetype":"venue"
},
  "geometry": {"coordinates":[-122.47574899999999,45.491397],"type":"Point"}
}