{
  "type": "Feature",
  "properties": {
    "iso:country":"US",
    "sg:address":"2338 Pacific Ave",
    "sg:city":"Forest Grove",
    "sg:classifiers":[
        {
            "category":"Restaurant",
            "type":"Food & Drink"
        }
    ],
    "sg:phone":"+1 503 357 1820",
    "sg:postcode":"97116",
    "sg:province":"OR",
    "sg:tags":[
        "eating"
    ],
    "wof:name":"Mandarin China Restaurant",
    "wof:placetype":"venue"
},
  "geometry": {"coordinates":[-123.105346,45.519564],"type":"Point"}
}