{
  "type": "Feature",
  "properties": {
    "iso:country":"US",
    "sg:address":"13955 SE String Town Rd",
    "sg:city":"Dayton",
    "sg:classifiers":[
        {
            "category":"Professional",
            "subcategory":"Management & Consulting",
            "type":"Services"
        }
    ],
    "sg:phone":"+1 503 864 8148",
    "sg:postcode":"97114",
    "sg:province":"OR",
    "sg:tags":[
        "educational"
    ],
    "wof:name":"Northwest Backflow",
    "wof:placetype":"venue"
},
  "geometry": {"coordinates":[-123.09634,45.196698],"type":"Point"}
}