{
  "type": "Feature",
  "properties": {
    "addr:full":"1722 SW Hensley Rd Troutdale OR 97060",
    "addr:housenumber":"1722",
    "addr:postcode":"97060",
    "addr:street":"Sw Hensley Rd",
    "iso:country":"US",
    "sg:address":"1722 SW Hensley Rd",
    "sg:city":"Troutdale",
    "sg:classifiers":[
        {
            "category":"Home & Garden",
            "subcategory":"Home Furnishings",
            "type":"Retail Goods"
        }
    ],
    "sg:phone":"+1 503 665 7626",
    "sg:postcode":"97060",
    "sg:province":"OR",
    "wof:name":"Truly Yours Interiors",
    "wof:placetype":"venue"
},
  "geometry": {"coordinates":[-122.393258,45.529599],"type":"Point"}
}