{
  "type": "Feature",
  "properties": {
    "addr:full":"13195 SW Cinder Dr Terrebonne OR 97760",
    "addr:housenumber":"13195",
    "addr:postcode":"97760",
    "addr:street":"Sw Cinder Dr",
    "iso:country":"US",
    "sg:address":"13195 SW Cinder Dr",
    "sg:city":"Terrebonne",
    "sg:classifiers":[
        {
            "category":"Shopping",
            "subcategory":"Gifts & Souvenirs",
            "type":"Retail Goods"
        }
    ],
    "sg:phone":"+1 541 504 4345",
    "sg:postcode":"97760",
    "sg:province":"OR",
    "wof:name":"Just Essentials",
    "wof:placetype":"venue"
},
  "geometry": {"coordinates":[-121.29021899999999,44.447136],"type":"Point"}
}