{
  "type": "Feature",
  "properties": {
    "iso:country":"US",
    "sg:address":"2960 E St",
    "sg:city":"Baker City",
    "sg:classifiers":[
        {
            "category":"Shopping",
            "subcategory":"Gifts & Souvenirs",
            "type":"Retail Goods"
        }
    ],
    "sg:phone":"+1 541 524 9380",
    "sg:postcode":"97814",
    "sg:province":"OR",
    "wof:name":"Laurels Handmade Gifts",
    "wof:placetype":"venue"
},
  "geometry": {"coordinates":[-117.841865,44.786291],"type":"Point"}
}