{
  "type": "Feature",
  "properties": {
    "iso:country":"US",
    "sg:address":"84 4th St",
    "sg:city":"Ashland",
    "sg:classifiers":[
        {
            "category":"Organizations",
            "subcategory":"Community Association",
            "type":"Services"
        }
    ],
    "sg:phone":"+1 541 482 3069",
    "sg:postcode":"97520",
    "sg:province":"OR",
    "sg:tags":[
        "environmental",
        "org"
    ],
    "sg:website":"www.landconserve.org",
    "wof:name":"Southern Oregon Land Conserve",
    "wof:placetype":"venue"
},
  "geometry": {"coordinates":[-122.708118,42.195407],"type":"Point"}
}