{
  "type": "Feature",
  "properties": {
    "addr:full":"4572 Commercial St SE Salem OR 97302",
    "addr:housenumber":"4572",
    "addr:postcode":"97302",
    "addr:street":"Commercial St Se",
    "iso:country":"US",
    "sg:address":"4572 Commercial St SE",
    "sg:city":"Salem",
    "sg:classifiers":[
        {
            "category":"Personal",
            "subcategory":"Beauty Salon",
            "type":"Services"
        }
    ],
    "sg:phone":"+1 503 581 5770",
    "sg:postcode":"97302",
    "sg:province":"OR",
    "sg:tags":[
        "shop"
    ],
    "wof:name":"Perfect Look Salon 28",
    "wof:placetype":"venue"
},
  "geometry": {"coordinates":[-123.03424200000001,44.889889],"type":"Point"}
}