{
  "type": "Feature",
  "properties": {
    "iso:country":"US",
    "sg:address":"420 SW Washington St",
    "sg:city":"Portland",
    "sg:classifiers":[
        {
            "category":"Building & Trades",
            "subcategory":"Electrical",
            "type":"Services"
        }
    ],
    "sg:phone":"+1 503 231 1763",
    "sg:postcode":"97204",
    "sg:province":"OR",
    "sg:tags":[
        "electrician",
        "electric",
        "contractor"
    ],
    "wof:name":"Acme Electric",
    "wof:placetype":"venue"
},
  "geometry": {"coordinates":[-122.67600299999999,45.519901],"type":"Point"}
}