{
  "type": "Feature",
  "properties": {
    "iso:country":"US",
    "sg:address":"13810 SW 31st Ct",
    "sg:city":"Beaverton",
    "sg:classifiers":[
        {
            "category":"Insurance",
            "subcategory":"Hazard Insurance",
            "type":"Services"
        },
        {
            "category":"Insurance",
            "subcategory":"Insurance Agent",
            "type":"Services"
        }
    ],
    "sg:phone":"+1 503 671 9172",
    "sg:postcode":"97008",
    "sg:province":"OR",
    "sg:tags":[
        "fidelity",
        "bond"
    ],
    "wof:name":"Brem Bonding & Insurance Inc",
    "wof:placetype":"venue"
},
  "geometry": {"coordinates":[-122.820181,45.465065],"type":"Point"}
}