{
  "type": "Feature",
  "properties": {
    "addr:full":"5936 NE 37th Ave Portland OR 97211",
    "addr:housenumber":"5936",
    "addr:postcode":"97211",
    "addr:street":"Ne 37Th Ave",
    "iso:country":"US",
    "sg:address":"5936 NE 37th Ave",
    "sg:city":"Portland",
    "sg:classifiers":[
        {
            "category":"Building & Trades",
            "subcategory":"Construction",
            "type":"Services"
        }
    ],
    "sg:phone":"+1 503 288 4848",
    "sg:postcode":"97211",
    "sg:province":"OR",
    "sg:tags":[
        "pointing",
        "tuck"
    ],
    "wof:name":"Immediate Enviromental Recovery Solutions",
    "wof:placetype":"venue"
},
  "geometry": {"coordinates":[-122.62553200000001,45.56558],"type":"Point"}
}