{
  "type": "Feature",
  "properties": {
    "iso:country":"US",
    "sg:address":"315 SW Montgomery St",
    "sg:city":"Portland",
    "sg:classifiers":[
        {
            "category":"Wholesale",
            "subcategory":"Non-durable Goods",
            "type":"Manufacturing & Wholesale Goods"
        }
    ],
    "sg:phone":"+1 503 226 6542",
    "sg:postcode":"97201",
    "sg:province":"OR",
    "wof:name":"Orient Expression",
    "wof:placetype":"venue"
},
  "geometry": {"coordinates":[-122.674855,45.509667],"type":"Point"}
}