{
  "type": "Feature",
  "properties": {
    "addr:full":"3095 Canal Ave Grants Pass OR 97527",
    "addr:housenumber":"3095",
    "addr:postcode":"97527",
    "addr:street":"Canal Ave",
    "iso:country":"US",
    "sg:address":"3095 Canal Ave",
    "sg:city":"Grants Pass",
    "sg:classifiers":[
        {
            "category":"Professional",
            "subcategory":"Computer Services",
            "type":"Services"
        }
    ],
    "sg:phone":"+1 541 282 7100",
    "sg:postcode":"97527",
    "sg:province":"OR",
    "sg:tags":[
        "information",
        "retrieval"
    ],
    "wof:name":"Sprint Job Line",
    "wof:placetype":"venue"
},
  "geometry": {"coordinates":[-123.388496,42.414983],"type":"Point"}
}