{
  "type": "Feature",
  "properties": {
    "addr:full":"304 E Sheridan St Newberg OR 97132",
    "addr:housenumber":"304",
    "addr:postcode":"97132",
    "addr:street":"E Sheridan St",
    "iso:country":"US",
    "sg:address":"304 E Sheridan St",
    "sg:city":"Newberg",
    "sg:classifiers":[
        {
            "category":"Professional",
            "type":"Services"
        }
    ],
    "sg:phone":"+1 503 538 7036",
    "sg:postcode":"97132",
    "sg:province":"OR",
    "wof:name":"Creative-Oasiscom",
    "wof:placetype":"venue"
},
  "geometry": {"coordinates":[-122.977104,45.301877],"type":"Point"}
}