{
  "type": "Feature",
  "properties": {
    "iso:country":"US",
    "sg:address":"2045 Mckinley St",
    "sg:city":"Eugene",
    "sg:classifiers":[
        {
            "category":"Professional",
            "type":"Services"
        }
    ],
    "sg:phone":"+1 541 343 6978",
    "sg:postcode":"97405",
    "sg:province":"OR",
    "sg:tags":[
        "forestry",
        "consulting"
    ],
    "wof:name":"Steve Holmes Forestry",
    "wof:placetype":"venue"
},
  "geometry": {"coordinates":[-123.12950600000001,44.037892],"type":"Point"}
}