{
  "type": "Feature",
  "properties": {
    "addr:full":"2606 N Newark St Portland OR 97217",
    "addr:housenumber":"2606",
    "addr:postcode":"97217",
    "addr:street":"N Newark St",
    "iso:country":"US",
    "sg:address":"2606 N Newark St",
    "sg:city":"Portland",
    "sg:classifiers":[
        {
            "category":"Autos & Motor Vehicles",
            "subcategory":"Auto Supplies",
            "type":"Retail Goods"
        },
        {
            "category":"Retail",
            "subcategory":"Auto Repair",
            "type":"Services"
        }
    ],
    "sg:phone":"+1 503 285 1669",
    "sg:postcode":"97217",
    "sg:province":"OR",
    "sg:tags":[
        "recap",
        "retread",
        "tire"
    ],
    "wof:name":"Teague's Tire Service, Inc.",
    "wof:placetype":"venue"
},
  "geometry": {"coordinates":[-122.693894,45.590099],"type":"Point"}
}