{
  "type": "Feature",
  "properties": {
    "iso:country":"US",
    "sg:address":"121 SW Salmon St",
    "sg:city":"Portland",
    "sg:classifiers":[
        {
            "category":"Professional",
            "subcategory":"Business Services",
            "type":"Services"
        }
    ],
    "sg:phone":"+1 503 790 2200",
    "sg:postcode":"97204",
    "sg:province":"OR",
    "sg:tags":[
        "translator",
        "interpreter"
    ],
    "wof:name":"CTS Language Link",
    "wof:placetype":"venue"
},
  "geometry": {"coordinates":[-122.67547,45.516009],"type":"Point"}
}