{
  "type": "Feature",
  "properties": {
    "iso:country":"US",
    "sg:address":"3407 SE 108th Ave",
    "sg:city":"Portland",
    "sg:classifiers":[
        {
            "category":"Professional",
            "subcategory":"Management & Consulting",
            "type":"Services"
        }
    ],
    "sg:phone":"+1 503 761 0015",
    "sg:postcode":"97266",
    "sg:province":"OR",
    "wof:name":"Amusment Consulting Services",
    "wof:placetype":"venue"
},
  "geometry": {"coordinates":[-122.552635,45.497312],"type":"Point"}
}