{
  "type": "Feature",
  "properties": {
    "iso:country":"US",
    "sg:address":"1265 NW 334th Ave",
    "sg:city":"Hillsboro",
    "sg:phone":"+1 503 640 5425",
    "sg:postcode":"97124",
    "sg:province":"OR",
    "sg:tags":[
        "farm",
        "field",
        "crop"
    ],
    "wof:name":"James Vuylesteke",
    "wof:placetype":"venue"
},
  "geometry": {"coordinates":[-123.018608,45.522804],"type":"Point"}
}