{
  "type": "Feature",
  "properties": {
    "iso:country":"US",
    "sg:address":"655 N Oregon St",
    "sg:city":"Jacksonville",
    "sg:classifiers":[
        {
            "category":"Building & Trades",
            "subcategory":"Plumbing",
            "type":"Services"
        }
    ],
    "sg:phone":"+1 541 899 3968",
    "sg:postcode":"97530",
    "sg:province":"OR",
    "sg:tags":[
        "contractor"
    ],
    "wof:name":"Sun Stream Energy LLC",
    "wof:placetype":"venue"
},
  "geometry": {"coordinates":[-122.96545500000001,42.319835],"type":"Point"}
}