{
  "type": "Feature",
  "properties": {
    "iso:country":"US",
    "sg:address":"1050 SW Baseline St",
    "sg:city":"Hillsboro",
    "sg:classifiers":[
        {
            "category":"Insurance",
            "subcategory":"Insurance Agent",
            "type":"Services"
        }
    ],
    "sg:phone":"+1 503 640 0600",
    "sg:postcode":"97123",
    "sg:province":"OR",
    "wof:name":"Aim Insurance",
    "wof:placetype":"venue"
},
  "geometry": {"coordinates":[-122.997525,45.520013],"type":"Point"}
}