{
  "type": "Feature",
  "properties": {
    "addr:full":"1921 SE 44th Ave Portland OR 97215",
    "addr:housenumber":"1921",
    "addr:postcode":"97215",
    "addr:street":"Se 44Th Ave",
    "iso:country":"US",
    "sg:address":"1921 SE 44th Ave",
    "sg:city":"Portland",
    "sg:classifiers":[
        {
            "category":"Manufacturing",
            "subcategory":"Rubber & Plastics",
            "type":"Manufacturing & Wholesale Goods"
        }
    ],
    "sg:phone":"+1 503 957 6071",
    "sg:postcode":"97215",
    "sg:province":"OR",
    "sg:tags":[
        "product",
        "foam",
        "mfg"
    ],
    "wof:name":"C M Clemen & Co",
    "wof:placetype":"venue"
},
  "geometry": {"coordinates":[-122.617237,45.510796],"type":"Point"}
}