{
  "type": "Feature",
  "properties": {
    "iso:country":"US",
    "sg:address":"45478 NE Hwy 11",
    "sg:city":"Pendleton",
    "sg:classifiers":[
        {
            "category":"Wholesale",
            "subcategory":"Motor Vehicles",
            "type":"Manufacturing & Wholesale Goods"
        }
    ],
    "sg:phone":"+1 541 278 6028",
    "sg:postcode":"97801",
    "sg:province":"OR",
    "sg:tags":[
        "used",
        "distributes",
        "truck",
        "trailer"
    ],
    "wof:name":"N W B Sales LLC",
    "wof:placetype":"venue"
},
  "geometry": {"coordinates":[-118.725511,45.685114],"type":"Point"}
}