{
  "type": "Feature",
  "properties": {
    "addr:full":"5241 NW Thatcher Rd Forest Grove OR 97116",
    "addr:housenumber":"5241",
    "addr:postcode":"97116",
    "addr:street":"Nw Thatcher Rd",
    "iso:country":"US",
    "sg:address":"5241 NW Thatcher Rd",
    "sg:city":"Forest Grove",
    "sg:classifiers":[
        {
            "category":"Social Services",
            "subcategory":"Adult Care",
            "type":"Services"
        }
    ],
    "sg:phone":"+1 503 359 4983",
    "sg:postcode":"97116",
    "sg:province":"OR",
    "sg:tags":[
        "residential"
    ],
    "wof:name":"Silver Cloud Rnch Rtirement HM",
    "wof:placetype":"venue"
},
  "geometry": {"coordinates":[-123.141418,45.562054],"type":"Point"}
}