{
  "type": "Feature",
  "properties": {
    "addr:full":"3087 US Hwy 101 Florence OR 97439",
    "addr:housenumber":"3087",
    "addr:postcode":"97439",
    "addr:street":"Us Hwy 101",
    "iso:country":"US",
    "sg:address":"3087 US Hwy 101",
    "sg:city":"Florence",
    "sg:classifiers":[
        {
            "category":"Retail",
            "subcategory":"Auto Repair",
            "type":"Services"
        }
    ],
    "sg:phone":"+1 541 997 1811",
    "sg:postcode":"97439",
    "sg:province":"OR",
    "sg:tags":[
        "automotive",
        "wrecker"
    ],
    "wof:name":"Mast Bros Towing & Recovering",
    "wof:placetype":"venue"
},
  "geometry": {"coordinates":[-124.101418,43.992806],"type":"Point"}
}