{
  "type": "Feature",
  "properties": {
    "iso:country":"US",
    "sg:address":"5516 SE Foster Road",
    "sg:city":"Portland",
    "sg:classifiers":[
        {
            "category":"Education",
            "subcategory":"Music School",
            "type":"Public Place"
        }
    ],
    "sg:phone":"+1 503 775 4351",
    "sg:postcode":"97206",
    "sg:province":"OR",
    "sg:tags":[
        "instrument",
        "teacher",
        "musical"
    ],
    "wof:name":"Day Music Company",
    "wof:placetype":"venue"
},
  "geometry": {"coordinates":[-122.605976,45.494096],"type":"Point"}
}