{
  "type": "Feature",
  "properties": {
    "addr:full":"2189 NW Wilson St Portland OR 97210",
    "addr:housenumber":"2189",
    "addr:postcode":"97210",
    "addr:street":"Nw Wilson St",
    "iso:country":"US",
    "sg:address":"2189 NW Wilson St",
    "sg:city":"Portland",
    "sg:classifiers":[
        {
            "category":"Social Services",
            "type":"Services"
        }
    ],
    "sg:phone":"+1 503 238 4522",
    "sg:postcode":"97210",
    "sg:province":"OR",
    "wof:name":"P T A Clothing Center",
    "wof:placetype":"venue"
},
  "geometry": {"coordinates":[-122.69630600000001,45.537742],"type":"Point"}
}