{
  "type": "Feature",
  "properties": {
    "iso:country":"US",
    "sg:address":"2625 NE Butler Market Rd",
    "sg:city":"Bend",
    "sg:classifiers":[
        {
            "category":"Wholesale",
            "subcategory":"Machinery & Supplies",
            "type":"Manufacturing & Wholesale Goods"
        }
    ],
    "sg:phone":"+1 541 383 1906",
    "sg:postcode":"97701",
    "sg:province":"OR",
    "sg:tags":[
        "equipment",
        "industrial"
    ],
    "wof:name":"U Artistic",
    "wof:placetype":"venue"
},
  "geometry": {"coordinates":[-121.261078,44.086483],"type":"Point"}
}