{
  "type": "Feature",
  "properties": {
    "iso:country":"US",
    "sg:address":"26962 Cantrell Rd",
    "sg:city":"Eugene",
    "sg:phone":"+1 541 935 9526",
    "sg:postcode":"97402",
    "sg:province":"OR",
    "sg:tags":[
        "farm",
        "field",
        "crop"
    ],
    "wof:name":"Heitzman Farms",
    "wof:placetype":"venue"
},
  "geometry": {"coordinates":[-123.27634,44.041297],"type":"Point"}
}