{
  "type": "Feature",
  "properties": {
    "iso:country":"US",
    "sg:address":"4120 SE 115th Ave",
    "sg:city":"Portland",
    "sg:classifiers":[
        {
            "category":"Building & Trades",
            "subcategory":"Cleaning & Sanitation",
            "type":"Services"
        }
    ],
    "sg:phone":"+1 503 653 8380",
    "sg:postcode":"97266",
    "sg:province":"OR",
    "sg:tags":[
        "house"
    ],
    "wof:name":"Portland Maids",
    "wof:placetype":"venue"
},
  "geometry": {"coordinates":[-122.544471,45.494026],"type":"Point"}
}