{
  "type": "Feature",
  "properties": {
    "iso:country":"US",
    "sg:address":"1701 NW Thurman St",
    "sg:city":"Portland",
    "sg:classifiers":[
        {
            "category":"Communications",
            "type":"Services"
        }
    ],
    "sg:phone":"+1 503 227 3756",
    "sg:postcode":"97209",
    "sg:province":"OR",
    "wof:name":"Habitat Media",
    "wof:placetype":"venue"
},
  "geometry": {"coordinates":[-122.688683,45.535679],"type":"Point"}
}