{
  "type": "Feature",
  "properties": {
    "iso:country":"US",
    "sg:address":"15 82nd Dr",
    "sg:city":"Gladstone",
    "sg:classifiers":[
        {
            "category":"Real Estate",
            "subcategory":"Real Estate Operator",
            "type":"Services"
        }
    ],
    "sg:phone":"+1 503 650 9500",
    "sg:postcode":"97027",
    "sg:province":"OR",
    "sg:tags":[
        "building",
        "computer",
        "nonresidential"
    ],
    "wof:name":"Mainlander Investments",
    "wof:placetype":"venue"
},
  "geometry": {"coordinates":[-122.584299,45.379582],"type":"Point"}
}