{
  "type": "Feature",
  "properties": {
    "iso:country":"US",
    "sg:address":"1532 SW Fellows St",
    "sg:city":"Mcminnville",
    "sg:classifiers":[
        {
            "category":"Building & Trades",
            "subcategory":"Construction",
            "type":"Services"
        }
    ],
    "sg:phone":"+1 503 472 1536",
    "sg:postcode":"97128",
    "sg:province":"OR",
    "sg:tags":[
        "house"
    ],
    "wof:name":"WD Construction & Remodeling",
    "wof:placetype":"venue"
},
  "geometry": {"coordinates":[-123.214699,45.201825],"type":"Point"}
}