{
  "type": "Feature",
  "properties": {
    "addr:full":"450 S Main St Banks OR 97106",
    "addr:housenumber":"450",
    "addr:postcode":"97106",
    "addr:street":"S Main St",
    "iso:country":"US",
    "sg:address":"450 S Main St",
    "sg:city":"Banks",
    "sg:classifiers":[
        {
            "category":"Education",
            "subcategory":"School",
            "type":"Public Place"
        }
    ],
    "sg:phone":"+1 503 324 2281",
    "sg:postcode":"97106",
    "sg:province":"OR",
    "sg:tags":[
        "high"
    ],
    "wof:name":"Banks High School",
    "wof:placetype":"venue"
},
  "geometry": {"coordinates":[-123.114451,45.614192],"type":"Point"}
}