{
  "type": "Feature",
  "properties": {
    "iso:country":"US",
    "sg:address":"4850 SW Scholls Ferry Rd Ste 201",
    "sg:city":"Portland",
    "sg:classifiers":[
        {
            "category":"Health Services",
            "subcategory":"Health Practitioner",
            "type":"Services"
        }
    ],
    "sg:phone":"+1 503 515 2657",
    "sg:postcode":"97225",
    "sg:province":"OR",
    "sg:tags":[
        "acupuncture"
    ],
    "sg:website":"www.lisasacupuncture.com",
    "wof:name":"Lisa Thorborg, L.Ac., P.T.",
    "wof:placetype":"venue"
},
  "geometry": {"coordinates":[-122.75155599999999,45.484569],"type":"Point"}
}