{
  "type": "Feature",
  "properties": {
    "iso:country":"US",
    "sg:address":"38530 SE Howard Rd",
    "sg:city":"Corbett",
    "sg:classifiers":[
        {
            "category":"Building & Trades",
            "subcategory":"Construction",
            "type":"Services"
        }
    ],
    "sg:phone":"+1 503 695 5778",
    "sg:postcode":"97019",
    "sg:province":"OR",
    "sg:tags":[
        "house"
    ],
    "wof:name":"Lee Strickland Construction",
    "wof:placetype":"venue"
},
  "geometry": {"coordinates":[-122.266829,45.515157],"type":"Point"}
}