{
  "type": "Feature",
  "properties": {
    "addr:full":"5301 NE Portland Hwy Portland OR 97218",
    "addr:housenumber":"5301",
    "addr:postcode":"97218",
    "addr:street":"Ne Portland Hwy",
    "iso:country":"US",
    "sg:address":"5301 NE Portland Hwy",
    "sg:city":"Portland",
    "sg:classifiers":[
        {
            "category":"Bars & Pubs",
            "type":"Food & Drink"
        },
        {
            "category":"Bars & Pubs",
            "subcategory":"Dive Bar",
            "type":"Food & Drink"
        },
        {
            "category":"Bars & Pubs",
            "subcategory":"Lounge",
            "type":"Food & Drink"
        }
    ],
    "sg:phone":"+1 503 282 8000",
    "sg:postcode":"97218",
    "sg:province":"OR",
    "sg:tags":[
        "karaoke"
    ],
    "wof:name":"Railside Pub",
    "wof:placetype":"venue"
},
  "geometry": {"coordinates":[-122.60900599999999,45.568589],"type":"Point"}
}