{
  "type": "Feature",
  "properties": {
    "iso:country":"US",
    "sg:address":"1631 NE 2nd St",
    "sg:city":"Bend",
    "sg:classifiers":[
        {
            "category":"Professional",
            "subcategory":"Credit Reporting & Collection",
            "type":"Services"
        }
    ],
    "sg:phone":"+1 541 389 9771",
    "sg:postcode":"97701",
    "sg:province":"OR",
    "sg:tags":[
        "agency"
    ],
    "wof:name":"Pacific Coast Credit Agency",
    "wof:placetype":"venue"
},
  "geometry": {"coordinates":[-121.30398599999999,44.066417],"type":"Point"}
}