{
  "type": "Feature",
  "properties": {
    "iso:country":"US",
    "sg:address":"3644 Old Hwy 99 S",
    "sg:city":"Roseburg",
    "sg:classifiers":[
        {
            "category":"Retail",
            "subcategory":"Animal Services",
            "type":"Services"
        }
    ],
    "sg:phone":"+1 541 679 6484",
    "sg:postcode":"97470",
    "sg:province":"OR",
    "sg:tags":[
        "cat",
        "dog",
        "kennel"
    ],
    "sg:website":"www.veachshouseofboxers.com",
    "wof:name":"Highway 99 Boarding Kennels",
    "wof:placetype":"venue"
},
  "geometry": {"coordinates":[-123.36784900000001,43.162738],"type":"Point"}
}