{
  "type": "Feature",
  "properties": {
    "iso:country":"US",
    "sg:address":"1120 SE 14th Ave",
    "sg:city":"Portland",
    "sg:classifiers":[
        {
            "category":"Professional",
            "subcategory":"Business Services",
            "type":"Services"
        }
    ],
    "sg:phone":"+1 503 239 5299",
    "sg:postcode":"97214",
    "sg:province":"OR",
    "sg:tags":[
        "engineering",
        "drafting"
    ],
    "wof:name":"Industrial Design Drafting Inc",
    "wof:placetype":"venue"
},
  "geometry": {"coordinates":[-122.65155900000001,45.514489],"type":"Point"}
}