{
  "type": "Feature",
  "properties": {
    "addr:full":"17044 E Burnside St Portland OR 97233",
    "addr:housenumber":"17044",
    "addr:postcode":"97233",
    "addr:street":"E Burnside St",
    "iso:country":"US",
    "sg:address":"17044 E Burnside St",
    "sg:city":"Portland",
    "sg:classifiers":[
        {
            "category":"Social Services",
            "subcategory":"Job Training",
            "type":"Services"
        }
    ],
    "sg:phone":"+1 503 254 0204",
    "sg:postcode":"97233",
    "sg:province":"OR",
    "sg:tags":[
        "rehabilitation"
    ],
    "wof:name":"Coast Rehab Svc",
    "wof:placetype":"venue"
},
  "geometry": {"coordinates":[-122.48942599999999,45.521969],"type":"Point"}
}