{
  "type": "Feature",
  "properties": {
    "iso:country":"US",
    "sg:address":"7133 N Chase Ave",
    "sg:city":"Portland",
    "sg:classifiers":[
        {
            "category":"Communications",
            "subcategory":"Film & Video Production",
            "type":"Services"
        }
    ],
    "sg:phone":"+1 503 283 8075",
    "sg:postcode":"97217",
    "sg:province":"OR",
    "sg:tags":[
        "motion"
    ],
    "wof:name":"Take 2 Production SE",
    "wof:placetype":"venue"
},
  "geometry": {"coordinates":[-122.704909,45.576331],"type":"Point"}
}