{
  "type": "Feature",
  "properties": {
    "iso:country":"US",
    "sg:address":"760 Ivy St",
    "sg:city":"Junction City",
    "sg:classifiers":[
        {
            "category":"Autos & Motor Vehicles",
            "subcategory":"Auto Supplies",
            "type":"Retail Goods"
        }
    ],
    "sg:phone":"+1 541 998 6669",
    "sg:postcode":"97448",
    "sg:province":"OR",
    "sg:tags":[
        "automobile",
        "parts"
    ],
    "wof:name":"Junction City Auto & Truck",
    "wof:placetype":"venue"
},
  "geometry": {"coordinates":[-123.204673,44.220354],"type":"Point"}
}