{
  "type": "Feature",
  "properties": {
    "iso:country":"US",
    "sg:address":"46620 NW Sell Rd",
    "sg:city":"Banks",
    "sg:classifiers":[
        {
            "category":"Social Services",
            "type":"Services"
        }
    ],
    "sg:phone":"+1 503 324 0111",
    "sg:postcode":"97106",
    "sg:province":"OR",
    "wof:name":"Assoc of Cpr Instructors",
    "wof:placetype":"venue"
},
  "geometry": {"coordinates":[-123.154331,45.657787],"type":"Point"}
}