{
  "type": "Feature",
  "properties": {
    "iso:country":"US",
    "sg:address":"1717 NE 42nd Ave Ste 3200",
    "sg:city":"Portland",
    "sg:classifiers":[
        {
            "category":"Health Services",
            "subcategory":"Chiropractor",
            "type":"Services"
        }
    ],
    "sg:phone":"+1 503 688 1219",
    "sg:postcode":"97213",
    "sg:province":"OR",
    "sg:website":"www.happyspinepdx.com/",
    "wof:name":"Russ Family Chiropractic",
    "wof:placetype":"venue"
},
  "geometry": {"coordinates":[-122.61993,45.535427],"type":"Point"}
}