{
  "type": "Feature",
  "properties": {
    "iso:country":"US",
    "sg:address":"2227 Sandy Dr",
    "sg:city":"Eugene",
    "sg:classifiers":[
        {
            "category":"Manufacturing",
            "subcategory":"Wood Products",
            "type":"Manufacturing & Wholesale Goods"
        }
    ],
    "sg:phone":"+1 541 915 5009",
    "sg:postcode":"97401",
    "sg:province":"OR",
    "sg:tags":[
        "preserving"
    ],
    "wof:name":"Mgo Woodproducts LLC",
    "wof:placetype":"venue"
},
  "geometry": {"coordinates":[-123.076949,44.074903],"type":"Point"}
}