{
  "type": "Feature",
  "properties": {
    "iso:country":"US",
    "sg:address":"410 NE Harney St",
    "sg:city":"Newport",
    "sg:classifiers":[
        {
            "category":"Government",
            "subcategory":"Office",
            "type":"Public Place"
        }
    ],
    "sg:phone":"+1 541 265 4900",
    "sg:postcode":"97365",
    "sg:province":"OR",
    "sg:tags":[
        "county",
        "govt",
        "program"
    ],
    "wof:name":"Lincoln County Transit",
    "wof:placetype":"venue"
},
  "geometry": {"coordinates":[-124.042631,44.638488],"type":"Point"}
}