{
  "type": "Feature",
  "properties": {
    "iso:country":"US",
    "sg:address":"19630 SW 90th Ct",
    "sg:city":"Tualatin",
    "sg:classifiers":[
        {
            "category":"Wholesale",
            "subcategory":"Auto Parts",
            "type":"Manufacturing & Wholesale Goods"
        }
    ],
    "sg:phone":"+1 503 692 0462",
    "sg:postcode":"97062",
    "sg:province":"OR",
    "sg:tags":[
        "dealer"
    ],
    "wof:name":"Northwest Express Delivery LLC",
    "wof:placetype":"venue"
},
  "geometry": {"coordinates":[-122.770332,45.379966],"type":"Point"}
}