{
  "type": "Feature",
  "properties": {
    "iso:country":"US",
    "sg:address":"3415 N Hwy 101",
    "sg:city":"Depoe Bay",
    "sg:classifiers":[
        {
            "category":"Manufacturing",
            "subcategory":"Retail Goods",
            "type":"Manufacturing & Wholesale Goods"
        }
    ],
    "sg:phone":"+1 541 764 5260",
    "sg:postcode":"97341",
    "sg:province":"OR",
    "sg:tags":[
        "product",
        "mfg"
    ],
    "wof:name":"Stacked Deck",
    "wof:placetype":"venue"
},
  "geometry": {"coordinates":[-124.046738,44.846009],"type":"Point"}
}