{
  "type": "Feature",
  "properties": {
    "iso:country":"US",
    "sg:address":"207 SW 1st Ave",
    "sg:city":"Canby",
    "sg:classifiers":[
        {
            "category":"Building & Trades",
            "subcategory":"Construction",
            "type":"Services"
        }
    ],
    "sg:phone":"+1 503 266 5740",
    "sg:postcode":"97013",
    "sg:province":"OR",
    "wof:name":"Steel Storage Systems",
    "wof:placetype":"venue"
},
  "geometry": {"coordinates":[-122.69313699999999,45.261717],"type":"Point"}
}