{
  "type": "Feature",
  "properties": {
    "iso:country":"US",
    "sg:address":"4055 SW Garden Home Rd",
    "sg:city":"Portland",
    "sg:classifiers":[
        {
            "category":"Health Services",
            "subcategory":"Health Practitioner",
            "type":"Services"
        }
    ],
    "sg:phone":"+1 503 293 5000",
    "sg:postcode":"97219",
    "sg:province":"OR",
    "sg:tags":[
        "naturopathic/holistic"
    ],
    "wof:name":"Kreger-Lozano Yvonne Nd",
    "wof:placetype":"venue"
},
  "geometry": {"coordinates":[-122.71700300000001,45.4669],"type":"Point"}
}