{
  "type": "Feature",
  "properties": {
    "addr:full":"16809 Timber Rd E Vernonia OR 97064",
    "addr:housenumber":"16809",
    "addr:postcode":"97064",
    "addr:street":"Timber Rd E Vernonia",
    "iso:country":"US",
    "sg:address":"16809 Timber Rd E",
    "sg:city":"Vernonia",
    "sg:classifiers":[
        {
            "category":"Manufacturing",
            "subcategory":"Paper Products",
            "type":"Manufacturing & Wholesale Goods"
        }
    ],
    "sg:phone":"+1 503 429 2605",
    "sg:postcode":"97064",
    "sg:province":"OR",
    "wof:name":"Longview Fibre Co",
    "wof:placetype":"venue"
},
  "geometry": {"coordinates":[-123.2199,45.841981],"type":"Point"}
}