{
  "type": "Feature",
  "properties": {
    "iso:country":"US",
    "sg:address":"115 Fir St",
    "sg:city":"Myrtle Creek",
    "sg:classifiers":[
        {
            "category":"Professional",
            "subcategory":"Lawyer & Legal Services",
            "type":"Services"
        }
    ],
    "sg:phone":"+1 541 863 5192",
    "sg:postcode":"97457",
    "sg:province":"OR",
    "sg:tags":[
        "attorney"
    ],
    "wof:name":"Fred Zimmers Law Office",
    "wof:placetype":"venue"
},
  "geometry": {"coordinates":[-123.293047,43.012342],"type":"Point"}
}