{
  "type": "Feature",
  "properties": {
    "iso:country":"US",
    "sg:address":"13220 Homedale Rd",
    "sg:city":"Klamath Falls",
    "sg:classifiers":[
        {
            "category":"Farming",
            "subcategory":"Livestock Farm",
            "type":"Manufacturing & Wholesale Goods"
        }
    ],
    "sg:phone":"+1 541 882 4916",
    "sg:postcode":"97603",
    "sg:province":"OR",
    "sg:tags":[
        "feedlot",
        "field",
        "crop",
        "beef",
        "cattle"
    ],
    "wof:name":"Scotch Acre",
    "wof:placetype":"venue"
},
  "geometry": {"coordinates":[-121.718042,42.106044],"type":"Point"}
}