{
  "type": "Feature",
  "properties": {
    "addr:full":"1220 NE Kelly Ave Gresham OR 97030",
    "addr:housenumber":"1220",
    "addr:postcode":"97030",
    "addr:street":"Ne Kelly Ave",
    "iso:country":"US",
    "sg:address":"1220 NE Kelly Ave",
    "sg:city":"Gresham",
    "sg:classifiers":[
        {
            "category":"Recreation",
            "type":"Entertainment"
        }
    ],
    "sg:phone":"+1 503 667 6543",
    "sg:postcode":"97030",
    "sg:province":"OR",
    "sg:tags":[
        "skating",
        "eating",
        "rink"
    ],
    "sg:website":"www.skateworldonline.com",
    "wof:name":"Gresham Skate World Inc",
    "wof:placetype":"venue"
},
  "geometry": {"coordinates":[-122.425867,45.506973],"type":"Point"}
}