{
  "type": "Feature",
  "properties": {
    "iso:country":"US",
    "sg:address":"9235 SE Clackamas Rd",
    "sg:city":"Clackamas",
    "sg:classifiers":[
        {
            "category":"Personal",
            "type":"Services"
        },
        {
            "category":"Personal",
            "subcategory":"Tattoo Parlor",
            "type":"Services"
        }
    ],
    "sg:phone":"+1 503 313 5644",
    "sg:postcode":"97015",
    "sg:province":"OR",
    "sg:tags":[
        "tattooing"
    ],
    "wof:name":"Graveyard Tattoos",
    "wof:placetype":"venue"
},
  "geometry": {"coordinates":[-122.568405,45.410714],"type":"Point"}
}