{
  "type": "Feature",
  "properties": {
    "iso:country":"US",
    "sg:address":"4967 SW 76th Avenue",
    "sg:city":"Portland",
    "sg:classifiers":[
        {
            "category":"Food & Beverages",
            "subcategory":"Liquor & Beverages",
            "type":"Retail Goods"
        }
    ],
    "sg:phone":"+1 503 292 1572",
    "sg:postcode":"97225",
    "sg:province":"OR",
    "sg:tags":[
        "beer",
        "spirit",
        "wine"
    ],
    "wof:name":"Raleigh Hills Liquor Store",
    "wof:placetype":"venue"
},
  "geometry": {"coordinates":[-122.754938,45.48371],"type":"Point"}
}