{
  "type": "Feature",
  "properties": {
    "iso:country":"US",
    "sg:address":"2030 River Rd",
    "sg:city":"Eugene",
    "sg:classifiers":[
        {
            "category":"Shopping",
            "subcategory":"Discount & Variety Stores",
            "type":"Retail Goods"
        }
    ],
    "sg:phone":"+1 541 687 7600",
    "sg:postcode":"97404",
    "sg:province":"OR",
    "sg:tags":[
        "merchandise",
        "general"
    ],
    "wof:name":"Bi-Mart Corporation",
    "wof:placetype":"venue"
},
  "geometry": {"coordinates":[-123.127071,44.093326],"type":"Point"}
}