{
  "type": "Feature",
  "properties": {
    "addr:full":"965 SW Emkay Dr Bend OR 97702",
    "addr:housenumber":"965",
    "addr:postcode":"97702",
    "addr:street":"Sw Emkay Dr",
    "iso:country":"US",
    "sg:address":"965 SW Emkay Dr",
    "sg:city":"Bend",
    "sg:classifiers":[
        {
            "category":"Health Services",
            "subcategory":"Doctor",
            "type":"Services"
        },
        {
            "category":"Social Services",
            "type":"Services"
        },
        {
            "category":"Personal",
            "type":"Services"
        },
        {
            "category":"Education",
            "subcategory":"University",
            "type":"Public Place"
        }
    ],
    "sg:phone":"+1 541 389 2242",
    "sg:postcode":"97702",
    "sg:province":"OR",
    "sg:tags":[
        "college",
        "family",
        "psychologist",
        "individual",
        "marriage",
        "child",
        "counseling",
        "counselor"
    ],
    "wof:name":"Talley Pamella J MA",
    "wof:placetype":"venue"
},
  "geometry": {"coordinates":[-121.325445,44.045222],"type":"Point"}
}