{
  "type": "Feature",
  "properties": {
    "iso:country":"US",
    "sg:address":"3785 SW 5th Dr",
    "sg:city":"Gresham",
    "sg:classifiers":[
        {
            "category":"Professional",
            "subcategory":"Detective & Security Services",
            "type":"Services"
        }
    ],
    "sg:phone":"+1 503 667 3321",
    "sg:postcode":"97030",
    "sg:province":"OR",
    "sg:tags":[
        "car"
    ],
    "wof:name":"Monte Bello Adult Foster Home",
    "wof:placetype":"venue"
},
  "geometry": {"coordinates":[-122.47157900000001,45.493434],"type":"Point"}
}