{
  "type": "Feature",
  "properties": {
    "addr:full":"2656 NE Maple Ave Gresham OR 97030",
    "addr:housenumber":"2656",
    "addr:postcode":"97030",
    "addr:street":"Ne Maple Ave",
    "iso:country":"US",
    "sg:address":"2656 NE Maple Ave",
    "sg:city":"Gresham",
    "sg:classifiers":[
        {
            "category":"Professional",
            "type":"Services"
        }
    ],
    "sg:phone":"+1 503 491 1111",
    "sg:postcode":"97030",
    "sg:province":"OR",
    "wof:name":"Exclusives Inc",
    "wof:placetype":"venue"
},
  "geometry": {"coordinates":[-122.41733000000001,45.515768],"type":"Point"}
}