{
  "type": "Feature",
  "properties": {
    "addr:full":"1127 Palace Dr NE Salem OR 97301",
    "addr:housenumber":"1127",
    "addr:postcode":"97301",
    "addr:street":"Palace Dr Ne",
    "iso:country":"US",
    "sg:address":"1127 Palace Dr NE",
    "sg:city":"Salem",
    "sg:classifiers":[
        {
            "category":"Freight",
            "type":"Transportation"
        }
    ],
    "sg:phone":"+1 503 881 0989",
    "sg:postcode":"97301",
    "sg:province":"OR",
    "sg:tags":[
        "operator",
        "local",
        "trucking"
    ],
    "wof:name":"Frio Express Inc",
    "wof:placetype":"venue"
},
  "geometry": {"coordinates":[-122.96717099999999,44.944725],"type":"Point"}
}