{
  "type": "Feature",
  "properties": {
    "addr:full":"594 63rd Ave NE Salem OR 97317",
    "addr:housenumber":"594",
    "addr:postcode":"97317",
    "addr:street":"63Rd Ave Ne",
    "iso:country":"US",
    "sg:address":"594 63rd Ave NE",
    "sg:city":"Salem",
    "sg:classifiers":[
        {
            "category":"Transit Center",
            "subcategory":"Freight",
            "type":"Transportation"
        },
        {
            "category":"Freight",
            "type":"Transportation"
        }
    ],
    "sg:phone":"+1 503 391 6846",
    "sg:postcode":"97317",
    "sg:province":"OR",
    "sg:tags":[
        "local",
        "trucking-motor",
        "trucking"
    ],
    "wof:name":"G.T.L.C. Trucking",
    "wof:placetype":"venue"
},
  "geometry": {"coordinates":[-122.93114799999999,44.936961],"type":"Point"}
}