{
  "type": "Feature",
  "properties": {
    "iso:country":"US",
    "sg:address":"2531 SE Micah Pl",
    "sg:city":"Corvallis",
    "sg:classifiers":[
        {
            "category":"Professional",
            "type":"Services"
        }
    ],
    "sg:phone":"+1 541 760 8706",
    "sg:postcode":"97333",
    "sg:province":"OR",
    "sg:tags":[
        "paper",
        "conservation"
    ],
    "wof:name":"Paper Renaissance LLC",
    "wof:placetype":"venue"
},
  "geometry": {"coordinates":[-123.26250899999999,44.540874],"type":"Point"}
}