{
  "type": "Feature",
  "properties": {
    "addr:full":"555 NW Park Ave Portland OR 97209",
    "addr:housenumber":"555",
    "addr:postcode":"97209",
    "addr:street":"Nw Park",
    "iso:country":"US",
    "sg:address":"555 NW Park Ave",
    "sg:city":"Portland",
    "sg:classifiers":[
        {
            "category":"Government",
            "subcategory":"Office",
            "type":"Public Place"
        }
    ],
    "sg:phone":"+1 503 224 3472",
    "sg:postcode":"97209",
    "sg:province":"OR",
    "sg:tags":[
        "wildlife",
        "conservation"
    ],
    "wof:name":"Tillamook Rainforest Coalition",
    "wof:placetype":"venue"
},
  "geometry": {"coordinates":[-122.67930800000001,45.527281],"type":"Point"}
}