{
  "type": "Feature",
  "properties": {
    "iso:country":"US",
    "sg:address":"8152 SW Hall Blvd",
    "sg:city":"Beaverton",
    "sg:classifiers":[
        {
            "category":"Professional",
            "type":"Services"
        }
    ],
    "sg:phone":"+1 503 233 9700",
    "sg:postcode":"97008",
    "sg:province":"OR",
    "sg:tags":[
        "establishment"
    ],
    "wof:name":"Access Direct",
    "wof:placetype":"venue"
},
  "geometry": {"coordinates":[-122.793753,45.4607],"type":"Point"}
}