{
  "type": "Feature",
  "properties": {
    "iso:country":"US",
    "sg:address":"2384 13th St SE",
    "sg:city":"Salem",
    "sg:classifiers":[
        {
            "category":"Professional",
            "subcategory":"Management & Consulting",
            "type":"Services"
        }
    ],
    "sg:phone":"+1 503 391 7074",
    "sg:postcode":"97302",
    "sg:province":"OR",
    "sg:tags":[
        "development",
        "industrial"
    ],
    "wof:name":"Reco Business Park",
    "wof:placetype":"venue"
},
  "geometry": {"coordinates":[-123.029274,44.916903],"type":"Point"}
}