{
  "type": "Feature",
  "properties": {
    "addr:full":"6457 SE Amity Rd Amity OR 97101",
    "addr:housenumber":"6457",
    "addr:postcode":"97101",
    "addr:street":"Se Amity Rd",
    "iso:country":"US",
    "sg:address":"6457 SE Amity Rd",
    "sg:city":"Amity",
    "sg:classifiers":[
        {
            "category":"Professional",
            "subcategory":"Management & Consulting",
            "type":"Services"
        }
    ],
    "sg:phone":"+1 503 835 1470",
    "sg:postcode":"97101",
    "sg:province":"OR",
    "sg:tags":[
        "farm"
    ],
    "wof:name":"Premier Pacific Vineyard",
    "wof:placetype":"venue"
},
  "geometry": {"coordinates":[-123.17192799999999,45.113827],"type":"Point"}
}