{
  "type": "Feature",
  "properties": {
    "addr:full":"405 N 1st St Woodburn OR 97071",
    "addr:housenumber":"405",
    "addr:postcode":"97071",
    "addr:street":"N 1St St",
    "iso:country":"US",
    "sg:address":"405 N 1st St",
    "sg:city":"Woodburn",
    "sg:classifiers":[
        {
            "category":"Food & Beverages",
            "subcategory":"Bakery",
            "type":"Retail Goods"
        }
    ],
    "sg:phone":"+1 503 982 4513",
    "sg:postcode":"97071",
    "sg:province":"OR",
    "sg:tags":[
        "baker"
    ],
    "wof:name":"Salvador's Bakery",
    "wof:placetype":"venue"
},
  "geometry": {"coordinates":[-122.85631600000001,45.143878],"type":"Point"}
}