{
  "type": "Feature",
  "properties": {
    "iso:country":"US",
    "sg:address":"1050 S Bridge St",
    "sg:city":"Baker City",
    "sg:classifiers":[
        {
            "category":"Government",
            "subcategory":"Police Station",
            "type":"Public Place"
        }
    ],
    "sg:phone":"+1 541 523 5848",
    "sg:postcode":"97814",
    "sg:province":"OR",
    "sg:tags":[
        "state",
        "district"
    ],
    "wof:name":"District IV Headquarters",
    "wof:placetype":"venue"
},
  "geometry": {"coordinates":[-117.824119,44.768644],"type":"Point"}
}