{
  "type": "Feature",
  "properties": {
    "iso:country":"US",
    "sg:address":"5030 River Rd N",
    "sg:city":"Keizer",
    "sg:classifiers":[
        {
            "category":"Insurance",
            "subcategory":"Insurance Agent",
            "type":"Services"
        }
    ],
    "sg:phone":"+1 503 393 0806",
    "sg:postcode":"97303",
    "sg:province":"OR",
    "wof:name":"Kramer Insurance",
    "wof:placetype":"venue"
},
  "geometry": {"coordinates":[-123.02656500000001,44.997378],"type":"Point"}
}