{
  "type": "Feature",
  "properties": {
    "iso:country":"US",
    "sg:address":"1533 Wasco Ave",
    "sg:city":"Hood River",
    "sg:classifiers":[
        {
            "category":"Building & Trades",
            "subcategory":"Construction",
            "type":"Services"
        }
    ],
    "sg:phone":"+1 541 386 7220",
    "sg:postcode":"97031",
    "sg:province":"OR",
    "sg:tags":[
        "residential"
    ],
    "wof:name":"DC 3",
    "wof:placetype":"venue"
},
  "geometry": {"coordinates":[-121.52627,45.711371],"type":"Point"}
}