{
  "type": "Feature",
  "properties": {
    "iso:country":"US",
    "sg:address":"1625 E McAndrews Rd",
    "sg:city":"Medford",
    "sg:classifiers":[
        {
            "category":"Health Services",
            "subcategory":"Doctor",
            "type":"Services"
        }
    ],
    "sg:phone":"+1 541 779 3003",
    "sg:postcode":"97504",
    "sg:province":"OR",
    "sg:tags":[
        "dentist"
    ],
    "wof:name":"Gary J May DDS",
    "wof:placetype":"venue"
},
  "geometry": {"coordinates":[-122.861163,42.341131],"type":"Point"}
}