{
  "type": "Feature",
  "properties": {
    "iso:country":"US",
    "sg:address":"17000 State Hwy 224",
    "sg:city":"Clackamas",
    "sg:classifiers":[
        {
            "category":"Wholesale",
            "subcategory":"Electrical",
            "type":"Manufacturing & Wholesale Goods"
        }
    ],
    "sg:phone":"+1 503 658 5056",
    "sg:postcode":"97015",
    "sg:province":"OR",
    "sg:tags":[
        "telecommunication"
    ],
    "sg:website":"www.kiplingrockfarm.com",
    "wof:name":"Kipling Communications",
    "wof:placetype":"venue"
},
  "geometry": {"coordinates":[-122.48798600000001,45.396102],"type":"Point"}
}