{
  "type": "Feature",
  "properties": {
    "iso:country":"US",
    "sg:address":"8514 N Van Houten Ave",
    "sg:city":"Portland",
    "sg:classifiers":[
        {
            "category":"Retail",
            "subcategory":"Repair Shop",
            "type":"Services"
        },
        {
            "category":"Home & Garden",
            "subcategory":"Furniture",
            "type":"Retail Goods"
        }
    ],
    "sg:phone":"+1 503 206 7768",
    "sg:postcode":"97203",
    "sg:province":"OR",
    "sg:tags":[
        "refacing",
        "resurfacing",
        "cabinets-refinishing",
        "cabinet"
    ],
    "wof:name":"Barrett Cabinet Install & Services INC",
    "wof:placetype":"venue"
},
  "geometry": {"coordinates":[-122.723354,45.586087],"type":"Point"}
}