{
  "type": "Feature",
  "properties": {
    "iso:country":"US",
    "sg:address":"147 N Front St",
    "sg:city":"Medford",
    "sg:classifiers":[
        {
            "category":"Restaurant",
            "type":"Food & Drink"
        }
    ],
    "sg:phone":"+1 541 857 1910",
    "sg:postcode":"97501",
    "sg:province":"OR",
    "sg:tags":[
        "seafood",
        "steakhouse"
    ],
    "sg:website":"www.porterstrainstation.com",
    "wof:name":"Porters",
    "wof:placetype":"venue"
},
  "geometry": {"coordinates":[-122.874877,42.327675],"type":"Point"}
}