{
  "type": "Feature",
  "properties": {
    "addr:full":"4720 Long Prairie Rd Tillamook OR 97141",
    "addr:housenumber":"4720",
    "addr:postcode":"97141",
    "addr:street":"Long Prairie Rd",
    "iso:country":"US",
    "sg:address":"4720 Long Prairie Rd",
    "sg:city":"Tillamook",
    "sg:classifiers":[
        {
            "category":"Professional",
            "subcategory":"Business Services",
            "type":"Services"
        }
    ],
    "sg:phone":"+1 503 842 4805",
    "sg:postcode":"97141",
    "sg:province":"OR",
    "wof:name":"Jonathan E Dyk",
    "wof:placetype":"venue"
},
  "geometry": {"coordinates":[-123.817699,45.42694],"type":"Point"}
}