{
  "type": "Feature",
  "properties": {
    "iso:country":"US",
    "sg:address":"2104 NW Everett St",
    "sg:city":"Portland",
    "sg:classifiers":[
        {
            "category":"Social Services",
            "type":"Services"
        }
    ],
    "sg:phone":"+1 503 222 1426",
    "sg:postcode":"97210",
    "sg:province":"OR",
    "sg:tags":[
        "counselor",
        "marriage",
        "family"
    ],
    "wof:name":"Portland Agoraphobia Ctr",
    "wof:placetype":"venue"
},
  "geometry": {"coordinates":[-122.69633399999999,45.524764],"type":"Point"}
}