{
  "type": "Feature",
  "properties": {
    "addr:full":"1120 Ort Ln Merlin OR 97532",
    "addr:housenumber":"1120",
    "addr:postcode":"97532",
    "addr:street":"Ort Ln",
    "iso:country":"US",
    "sg:address":"1120 Ort Ln",
    "sg:city":"Merlin",
    "sg:classifiers":[
        {
            "category":"Retail",
            "subcategory":"Auto Repair",
            "type":"Services"
        }
    ],
    "sg:phone":"+1 541 471 9323",
    "sg:postcode":"97532",
    "sg:province":"OR",
    "sg:tags":[
        "body",
        "painting",
        "repairing",
        "automobile"
    ],
    "wof:name":"Darren's Williamson's Auto Body",
    "wof:placetype":"venue"
},
  "geometry": {"coordinates":[-123.408365,42.508427],"type":"Point"}
}