{
  "type": "Feature",
  "properties": {
    "addr:full":"500 W 12th St The Dalles OR 97058",
    "addr:housenumber":"500",
    "addr:postcode":"97058",
    "addr:street":"W 12Th St",
    "iso:country":"US",
    "sg:address":"500 W 12th St",
    "sg:city":"The Dalles",
    "sg:classifiers":[
        {
            "category":"Organizations",
            "subcategory":"Religious Organization",
            "type":"Services"
        }
    ],
    "sg:phone":"+1 541 298 5548",
    "sg:postcode":"97058",
    "sg:province":"OR",
    "sg:tags":[
        "clergy"
    ],
    "wof:name":"Tim Foster Sr",
    "wof:placetype":"venue"
},
  "geometry": {"coordinates":[-121.19609199999999,45.598752],"type":"Point"}
}