{
  "type": "Feature",
  "properties": {
    "addr:full":"64412 7th Dr Cove OR 97824",
    "addr:housenumber":"64412",
    "addr:postcode":"97824",
    "addr:street":"7Th Dr Cove",
    "iso:country":"US",
    "sg:address":"64412 7th Dr",
    "sg:city":"Cove",
    "sg:classifiers":[
        {
            "category":"Manufacturing",
            "subcategory":"Lumber",
            "type":"Manufacturing & Wholesale Goods"
        }
    ],
    "sg:phone":"+1 541 963 3387",
    "sg:postcode":"97824",
    "sg:province":"OR",
    "sg:tags":[
        "fire",
        "forest",
        "fighting"
    ],
    "wof:name":"Inter Mountain Wildfire",
    "wof:placetype":"venue"
},
  "geometry": {"coordinates":[-117.974531,45.4056],"type":"Point"}
}