{
  "type": "Feature",
  "properties": {
    "iso:country":"US",
    "sg:address":"301 E Main St",
    "sg:city":"Medford",
    "sg:classifiers":[
        {
            "category":"Shopping",
            "subcategory":"Gifts & Souvenirs",
            "type":"Retail Goods"
        }
    ],
    "sg:phone":"+1 541 776 1215",
    "sg:postcode":"97501",
    "sg:province":"OR",
    "sg:tags":[
        "shop"
    ],
    "wof:name":"Exclusive Accents Gallery",
    "wof:placetype":"venue"
},
  "geometry": {"coordinates":[-122.870603,42.3274],"type":"Point"}
}