{
  "type": "Feature",
  "properties": {
    "addr:full":"1560 Pacific Blvd SE Albany OR 97321",
    "addr:housenumber":"1560",
    "addr:postcode":"97321",
    "addr:street":"Pacific Blvd Se",
    "iso:country":"US",
    "sg:address":"1560 Pacific Blvd SE",
    "sg:city":"Albany",
    "sg:classifiers":[
        {
            "category":"Restaurant",
            "type":"Food & Drink"
        }
    ],
    "sg:menulink":"http://www.allmenus.com/or/albany/164477-wendys/menu/",
    "sg:phone":"+1 541 926 0679",
    "sg:postcode":"97321",
    "sg:province":"OR",
    "sg:tags":[
        "burger",
        "american",
        "soup"
    ],
    "wof:name":"Wendy's",
    "wof:placetype":"venue"
},
  "geometry": {"coordinates":[-123.08573,44.63389],"type":"Point"}
}