{
  "type": "Feature",
  "properties": {
    "iso:country":"US",
    "sg:address":"2373 NW 185th Ave",
    "sg:city":"Hillsboro",
    "sg:classifiers":[
        {
            "category":"Home & Garden",
            "subcategory":"Building Materials",
            "type":"Retail Goods"
        }
    ],
    "sg:phone":"+1 503 924 7620",
    "sg:postcode":"97124",
    "sg:province":"OR",
    "sg:tags":[
        "garage",
        "opener",
        "door"
    ],
    "wof:name":"Garage Doors Repair Gates",
    "wof:placetype":"venue"
},
  "geometry": {"coordinates":[-122.867493,45.537305],"type":"Point"}
}