{
  "type": "Feature",
  "properties": {
    "iso:country":"US",
    "sg:address":"1710 Lancaster Dr NE",
    "sg:city":"Salem",
    "sg:classifiers":[
        {
            "category":"Autos & Motor Vehicles",
            "subcategory":"Auto Supplies",
            "type":"Retail Goods"
        }
    ],
    "sg:phone":"+1 503 363 9214",
    "sg:postcode":"97305",
    "sg:province":"OR",
    "sg:tags":[
        "tire"
    ],
    "sg:website":"www.lesschwab.com",
    "wof:name":"Les Schwab Tire Center",
    "wof:placetype":"venue"
},
  "geometry": {"coordinates":[-122.983615,44.950769],"type":"Point"}
}