{
  "type": "Feature",
  "properties": {
    "addr:full":"2510 NE Sandy Blvd Portland OR 97232",
    "addr:housenumber":"2510",
    "addr:postcode":"97232",
    "addr:street":"Ne Sandy Blvd",
    "iso:country":"US",
    "sg:address":"2510 NE Sandy Blvd",
    "sg:city":"Portland",
    "sg:classifiers":[
        {
            "category":"Autos & Motor Vehicles",
            "subcategory":"Automobile Sales",
            "type":"Retail Goods"
        },
        {
            "category":"Autos & Motor Vehicles",
            "subcategory":"Auto Supplies",
            "type":"Retail Goods"
        },
        {
            "category":"Retail",
            "subcategory":"Auto Repair",
            "type":"Services"
        }
    ],
    "sg:phone":"+1 503 969 3134",
    "sg:postcode":"97232",
    "sg:province":"OR",
    "sg:tags":[
        "transmission",
        "used",
        "brake",
        "car"
    ],
    "sg:website":"www.atomicauto.biz",
    "wof:name":"Atomic Auto",
    "wof:placetype":"venue"
},
  "geometry": {"coordinates":[-122.639489,45.527993],"type":"Point"}
}