{
  "type": "Feature",
  "properties": {
    "addr:full":"3817 NE 33rd Ave Portland OR 97212",
    "addr:housenumber":"3817",
    "addr:postcode":"97212",
    "addr:street":"Ne 33Rd Ave",
    "iso:country":"US",
    "sg:address":"3817 NE 33rd Ave",
    "sg:city":"Portland",
    "sg:classifiers":[
        {
            "category":"Juice Bar",
            "subcategory":"None",
            "type":"Food & Drink"
        },
        {
            "category":"Professional",
            "subcategory":"Management & Consulting",
            "type":"Services"
        }
    ],
    "sg:phone":"+1 503 577 3773",
    "sg:postcode":"97212",
    "sg:province":"OR",
    "sg:tags":[
        "smoothy",
        "marketing",
        "consultant"
    ],
    "sg:website":"rennie.mymonavie.com/",
    "wof:name":"MonaVie",
    "wof:placetype":"venue"
},
  "geometry": {"coordinates":[-122.631024,45.550446],"type":"Point"}
}