{
  "type": "Feature",
  "properties": {
    "addr:full":"8640 67th Ave NE Salem OR 97305",
    "addr:housenumber":"8640",
    "addr:postcode":"97305",
    "addr:street":"67Th Ave Ne",
    "iso:country":"US",
    "sg:address":"8640 67th Ave NE",
    "sg:city":"Salem",
    "sg:classifiers":[
        {
            "category":"Building & Trades",
            "subcategory":"Construction",
            "type":"Services"
        }
    ],
    "sg:phone":"+1 503 393 2115",
    "sg:postcode":"97305",
    "sg:province":"OR",
    "sg:tags":[
        "contractor"
    ],
    "wof:name":"Duro Shield Roofing Co",
    "wof:placetype":"venue"
},
  "geometry": {"coordinates":[-122.91916399999999,45.043615],"type":"Point"}
}