{
  "type": "Feature",
  "properties": {
    "iso:country":"US",
    "sg:address":"1925 NW Amberglen Pkwy Ste 153",
    "sg:city":"Beaverton",
    "sg:classifiers":[
        {
            "category":"Real Estate",
            "subcategory":"Real Estate Services",
            "type":"Services"
        },
        {
            "category":"Insurance",
            "subcategory":"Hazard Insurance",
            "type":"Services"
        },
        {
            "category":"Insurance",
            "subcategory":"Title Insurance",
            "type":"Services"
        },
        {
            "category":"Banks & Credit Unions",
            "subcategory":"Financial Services",
            "type":"Services"
        }
    ],
    "sg:phone":"+1 503 219 1061",
    "sg:postcode":"97006",
    "sg:province":"OR",
    "sg:tags":[
        "mortgage",
        "escrow"
    ],
    "sg:website":"http://www.ticorpdx.com",
    "wof:name":"Ticor Title Insurance",
    "wof:placetype":"venue"
},
  "geometry": {"coordinates":[-122.87962400000001,45.533202],"type":"Point"}
}