{
  "type": "Feature",
  "properties": {
    "iso:country":"US",
    "sg:address":"410 Hilda St",
    "sg:city":"Oregon City",
    "sg:classifiers":[
        {
            "category":"Real Estate",
            "subcategory":"Real Estate Agent",
            "type":"Services"
        }
    ],
    "sg:phone":"+1 503 657 4563",
    "sg:postcode":"97045",
    "sg:province":"OR",
    "sg:tags":[
        "management"
    ],
    "wof:name":"Surety Management Inc",
    "wof:placetype":"venue"
},
  "geometry": {"coordinates":[-122.593942,45.342899],"type":"Point"}
}