{
  "type": "Feature",
  "properties": {
    "iso:country":"US",
    "sg:address":"16063 SE Goosehollow Dr",
    "sg:city":"Clackamas",
    "sg:classifiers":[
        {
            "category":"Building & Trades",
            "subcategory":"Construction",
            "type":"Services"
        }
    ],
    "sg:phone":"+1 503 658 8464",
    "sg:postcode":"97089",
    "sg:province":"OR",
    "sg:tags":[
        "carpentry",
        "contractor"
    ],
    "wof:name":"Kurtz Construction",
    "wof:placetype":"venue"
},
  "geometry": {"coordinates":[-122.498923,45.40655],"type":"Point"}
}