{
  "type": "Feature",
  "properties": {
    "iso:country":"US",
    "sg:address":"407 W Main St #3",
    "sg:city":"Carlton",
    "sg:classifiers":[
        {
            "category":"Food & Beverages",
            "subcategory":"Specialty",
            "type":"Retail Goods"
        }
    ],
    "sg:phone":"+1 503 395 5261",
    "sg:postcode":"97111",
    "sg:province":"OR",
    "sg:website":"www.facebook.com/RepublicofJam",
    "wof:name":"Republic of Jam",
    "wof:placetype":"venue"
},
  "geometry": {"coordinates":[-123.180042,45.294498],"type":"Point"}
}