{
  "type": "Feature",
  "properties": {
    "addr:full":"5736 NE 33rd Ave Portland OR 97211",
    "addr:housenumber":"5736",
    "addr:postcode":"97211",
    "addr:street":"Ne 33Rd Ave",
    "iso:country":"US",
    "sg:address":"5736 NE 33rd Ave",
    "sg:city":"Portland",
    "sg:classifiers":[
        {
            "category":"Restaurant",
            "type":"Food & Drink"
        }
    ],
    "sg:phone":"+1 503 288 2117",
    "sg:postcode":"97211",
    "sg:province":"OR",
    "sg:website":"www.mcmenamin.com",
    "wof:name":"Mc Menamin's Pubs",
    "wof:placetype":"venue"
},
  "geometry": {"coordinates":[-122.63058100000001,45.564247],"type":"Point"}
}