{
  "type": "Feature",
  "properties": {
    "addr:full":"953 Rogue River Hwy Gold Hill OR 97525",
    "addr:housenumber":"953",
    "addr:postcode":"97525",
    "addr:street":"Rogue River Hwy",
    "iso:country":"US",
    "sg:address":"953 Rogue River Hwy",
    "sg:city":"Gold Hill",
    "sg:classifiers":[
        {
            "category":"Building & Trades",
            "subcategory":"Construction",
            "type":"Services"
        }
    ],
    "sg:phone":"+1 541 855 7002",
    "sg:postcode":"97525",
    "sg:province":"OR",
    "sg:tags":[
        "hanging",
        "contractor"
    ],
    "wof:name":"Gary Toews",
    "wof:placetype":"venue"
},
  "geometry": {"coordinates":[-123.11566500000001,42.425858],"type":"Point"}
}