{
  "type": "Feature",
  "properties": {
    "iso:country":"US",
    "sg:address":"19641 S Kalal Ct",
    "sg:city":"Oregon City",
    "sg:classifiers":[
        {
            "category":"Airline",
            "type":"Transportation"
        }
    ],
    "sg:phone":"+1 503 655 8935",
    "sg:postcode":"97045",
    "sg:province":"OR",
    "sg:tags":[
        "nonscheduled",
        "school",
        "vocational",
        "air"
    ],
    "wof:name":"Jade Air",
    "wof:placetype":"venue"
},
  "geometry": {"coordinates":[-122.607225,45.323112],"type":"Point"}
}