{
  "type": "Feature",
  "properties": {
    "iso:country":"US",
    "sg:address":"3461 NW Yeon Ave",
    "sg:city":"Portland",
    "sg:classifiers":[
        {
            "category":"Building & Trades",
            "subcategory":"Equipment Rental",
            "type":"Services"
        },
        {
            "category":"Professional",
            "subcategory":"Printing & Photocopies",
            "type":"Services"
        }
    ],
    "sg:phone":"+1 503 223 5011",
    "sg:postcode":"97210",
    "sg:province":"OR",
    "sg:tags":[
        "blueprinting",
        "copying",
        "supply",
        "duplicating",
        "architectural"
    ],
    "sg:website":"http://www.wpbinc.com",
    "wof:name":"Willamette Print And Blueprint Company, Inc.",
    "wof:placetype":"venue"
},
  "geometry": {"coordinates":[-122.71161499999999,45.546782],"type":"Point"}
}