{
  "type": "Feature",
  "properties": {
    "iso:country":"US",
    "sg:address":"11825 SW Katherine St",
    "sg:city":"Portland",
    "sg:classifiers":[
        {
            "category":"Wholesale",
            "subcategory":"Farm Supplies",
            "type":"Manufacturing & Wholesale Goods"
        }
    ],
    "sg:phone":"+1 503 524 7289",
    "sg:postcode":"97223",
    "sg:province":"OR",
    "sg:tags":[
        "lawn",
        "garden",
        "tool",
        "equipment",
        "horticultural",
        "import"
    ],
    "wof:name":"Zenport Industries Inc",
    "wof:placetype":"venue"
},
  "geometry": {"coordinates":[-122.797786,45.433947],"type":"Point"}
}