{
  "type": "Feature",
  "properties": {
    "iso:country":"US",
    "sg:address":"5310 Pacific Blvd SW",
    "sg:city":"Albany",
    "sg:classifiers":[
        {
            "category":"Building & Trades",
            "subcategory":"Construction",
            "type":"Services"
        }
    ],
    "sg:phone":"+1 541 924 1924",
    "sg:postcode":"97321",
    "sg:province":"OR",
    "sg:tags":[
        "home",
        "builder"
    ],
    "wof:name":"Schneider Homes Inc",
    "wof:placetype":"venue"
},
  "geometry": {"coordinates":[-123.113329,44.596743],"type":"Point"}
}