{
  "type": "Feature",
  "properties": {
    "iso:country":"US",
    "sg:address":"712 Niagara Ave",
    "sg:city":"Astoria",
    "sg:classifiers":[
        {
            "category":"Shopping",
            "subcategory":"Discount & Variety Stores",
            "type":"Retail Goods"
        }
    ],
    "sg:phone":"+1 503 325 2143",
    "sg:postcode":"97103",
    "sg:province":"OR",
    "sg:tags":[
        "grocery",
        "merchandise"
    ],
    "wof:name":"Peter Pan Market",
    "wof:placetype":"venue"
},
  "geometry": {"coordinates":[-123.835863,46.181249],"type":"Point"}
}