{
  "type": "Feature",
  "properties": {
    "iso:country":"US",
    "sg:address":"11677 S Macksburg Rd",
    "sg:city":"Canby",
    "sg:classifiers":[
        {
            "category":"Real Estate",
            "subcategory":"Real Estate Agent",
            "type":"Services"
        }
    ],
    "sg:phone":"+1 503 263 7422",
    "sg:postcode":"97013",
    "sg:province":"OR",
    "wof:name":"American Business & Rsdntl",
    "wof:placetype":"venue"
},
  "geometry": {"coordinates":[-122.62817200000001,45.215954],"type":"Point"}
}