{
  "type": "Feature",
  "properties": {
    "iso:country":"US",
    "sg:address":"230 E Main St",
    "sg:city":"Athena",
    "sg:classifiers":[
        {
            "category":"Manufacturing",
            "subcategory":"Printing",
            "type":"Manufacturing & Wholesale Goods"
        }
    ],
    "sg:phone":"+1 541 566 3238",
    "sg:postcode":"97813",
    "sg:province":"OR",
    "sg:tags":[
        "newspaper"
    ],
    "wof:name":"Eastern Perspective",
    "wof:placetype":"venue"
},
  "geometry": {"coordinates":[-118.491569,45.811651],"type":"Point"}
}