{
  "type": "Feature",
  "properties": {
    "iso:country":"US",
    "sg:address":"1393 Meridian Dr Suite 1",
    "sg:city":"Woodburn",
    "sg:classifiers":[
        {
            "category":"Health Services",
            "subcategory":"Dentist",
            "type":"Services"
        }
    ],
    "sg:phone":"+1 503 981 1360",
    "sg:postcode":"97071",
    "sg:province":"OR",
    "sg:tags":[
        "dentists-cosmetic",
        "dentistry"
    ],
    "wof:name":"Bowman Family Dental",
    "wof:placetype":"venue"
},
  "geometry": {"coordinates":[-122.854354,45.151326],"type":"Point"}
}