{
  "type": "Feature",
  "properties": {
    "addr:full":"811 13th St Hood River OR 97031",
    "addr:housenumber":"811",
    "addr:postcode":"97031",
    "addr:street":"13Th St",
    "iso:country":"US",
    "sg:address":"811 13th St",
    "sg:city":"Hood River",
    "sg:classifiers":[
        {
            "category":"Health Services",
            "subcategory":"Medical Lab",
            "type":"Services"
        }
    ],
    "sg:phone":"+1 541 387 6478",
    "sg:postcode":"97031",
    "sg:province":"OR",
    "sg:tags":[
        "detection",
        "equipment",
        "drug"
    ],
    "wof:name":"Hood River Memorial Hospital",
    "wof:placetype":"venue"
},
  "geometry": {"coordinates":[-121.525204,45.704799],"type":"Point"}
}