{
  "type": "Feature",
  "properties": {
    "iso:country":"US",
    "sg:address":"17888 SW McEwan Ave",
    "sg:city":"Portland",
    "sg:classifiers":[
        {
            "category":"Retail",
            "subcategory":"Veterinary Services",
            "type":"Services"
        },
        {
            "category":"Retail",
            "subcategory":"Pet Boarding",
            "type":"Services"
        }
    ],
    "sg:phone":"+1 503 968 6000",
    "sg:postcode":"97224",
    "sg:province":"OR",
    "sg:tags":[
        "veterinarian",
        "boarding/pet",
        "sitting"
    ],
    "sg:website":"www.catcareprofessionals.com",
    "wof:name":"Cat Care Professionals",
    "wof:placetype":"venue"
},
  "geometry": {"coordinates":[-122.746278,45.394377],"type":"Point"}
}