{
  "type": "Feature",
  "properties": {
    "iso:country":"US",
    "sg:address":"6335 N Basin Ave",
    "sg:city":"Portland",
    "sg:classifiers":[
        {
            "category":"Wholesale",
            "subcategory":"Machinery & Supplies",
            "type":"Manufacturing & Wholesale Goods"
        }
    ],
    "sg:phone":"+1 503 283 0366",
    "sg:postcode":"97217",
    "sg:province":"OR",
    "sg:tags":[
        "equipment",
        "industrial"
    ],
    "sg:website":"www.grainger.com",
    "wof:name":"Grainger Inc",
    "wof:placetype":"venue"
},
  "geometry": {"coordinates":[-122.711411,45.568501],"type":"Point"}
}