{
  "type": "Feature",
  "properties": {
    "iso:country":"US",
    "sg:address":"11640 SW Pacific Hwy",
    "sg:city":"Tigard",
    "sg:classifiers":[
        {
            "category":"Fast Food",
            "type":"Food & Drink"
        }
    ],
    "sg:phone":"+1 503 639 8029",
    "sg:postcode":"97223",
    "sg:province":"OR",
    "sg:tags":[
        "burger"
    ],
    "wof:name":"George's Giant Hamburgers",
    "wof:placetype":"venue"
},
  "geometry": {"coordinates":[-122.75413399999999,45.438441],"type":"Point"}
}