{
  "type": "Feature",
  "properties": {
    "iso:country":"US",
    "sg:address":"7110 SW Fir Loop Ste 110",
    "sg:city":"Portland",
    "sg:classifiers":[
        {
            "category":"Shopping",
            "subcategory":"Books",
            "type":"Retail Goods"
        },
        {
            "category":"Wholesale",
            "subcategory":"Books, Periodicals, & Newspapers",
            "type":"Manufacturing & Wholesale Goods"
        }
    ],
    "sg:phone":"+1 503 624 8014",
    "sg:postcode":"97223",
    "sg:province":"OR",
    "sg:tags":[
        "publisher",
        "publishers-periodical",
        "store"
    ],
    "sg:website":"http://www.informedguides.com",
    "wof:name":"Informed Inc.",
    "wof:placetype":"venue"
},
  "geometry": {"coordinates":[-122.749931,45.422946],"type":"Point"}
}