{
  "type": "Feature",
  "properties": {
    "addr:full":"11840 SE Brookside Dr Portland OR 97266",
    "addr:housenumber":"11840",
    "addr:postcode":"97266",
    "addr:street":"Se Brookside Dr",
    "iso:country":"US",
    "sg:address":"11840 SE Brookside Dr",
    "sg:city":"Portland",
    "sg:classifiers":[
        {
            "category":"Professional",
            "subcategory":"Computer Services",
            "type":"Services"
        }
    ],
    "sg:phone":"+1 503 294 1845",
    "sg:postcode":"97266",
    "sg:province":"OR",
    "sg:tags":[
        "isp",
        "provider",
        "internet"
    ],
    "wof:name":"Pacific Showcase",
    "wof:placetype":"venue"
},
  "geometry": {"coordinates":[-122.540314,45.472739],"type":"Point"}
}