{
  "type": "Feature",
  "properties": {
    "addr:full":"16630 SE Lillian Way Portland OR 97236",
    "addr:postcode":"16630;97236",
    "addr:street":"Se Lillian Way",
    "iso:country":"US",
    "sg:address":"16630 SE Lillian Way",
    "sg:city":"Portland",
    "sg:classifiers":[
        {
            "category":"Building & Trades",
            "subcategory":"Construction",
            "type":"Services"
        }
    ],
    "sg:phone":"+1 503 492 2885",
    "sg:postcode":"97236",
    "sg:province":"OR",
    "sg:tags":[
        "house"
    ],
    "wof:name":"A Best Construction",
    "wof:placetype":"venue"
},
  "geometry": {"coordinates":[-122.49217,45.490787],"type":"Point"}
}