{
  "type": "Feature",
  "properties": {
    "addr:full":"1010 Airport Rd SE Albany OR 97322",
    "addr:housenumber":"1010",
    "addr:postcode":"97322",
    "addr:street":"Airport Rd Se",
    "iso:country":"US",
    "sg:address":"1010 Airport Rd SE",
    "sg:city":"Albany",
    "sg:classifiers":[
        {
            "category":"Banks & Credit Unions",
            "subcategory":"Bank",
            "type":"Services"
        }
    ],
    "sg:phone":"+1 541 791 4184",
    "sg:postcode":"97322",
    "sg:province":"OR",
    "sg:tags":[
        "broker",
        "mortgage"
    ],
    "wof:name":"Resolve Financial LLC",
    "wof:placetype":"venue"
},
  "geometry": {"coordinates":[-123.062777,44.63194],"type":"Point"}
}