{
  "type": "Feature",
  "properties": {
    "addr:full":"56842 Venture Ln Bend OR 97707",
    "addr:housenumber":"56842",
    "addr:postcode":"97707",
    "addr:street":"Venture Ln",
    "iso:country":"US",
    "sg:address":"56842 Venture Ln",
    "sg:city":"Bend",
    "sg:classifiers":[
        {
            "category":"Real Estate",
            "subcategory":"Real Estate Services",
            "type":"Services"
        },
        {
            "category":"Real Estate",
            "subcategory":"Real Estate Agent",
            "type":"Services"
        }
    ],
    "sg:phone":"+1 541 593 6300",
    "sg:postcode":"97707",
    "sg:province":"OR",
    "sg:tags":[
        "management"
    ],
    "wof:name":"Bennington Properties",
    "wof:placetype":"venue"
},
  "geometry": {"coordinates":[-121.43493700000001,43.86462],"type":"Point"}
}