{
  "type": "Feature",
  "properties": {
    "iso:country":"US",
    "sg:address":"5764 SE 115th Ave",
    "sg:city":"Portland",
    "sg:classifiers":[
        {
            "category":"Social Services",
            "subcategory":"Child Care",
            "type":"Services"
        }
    ],
    "sg:phone":"+1 503 760 4444",
    "sg:postcode":"97266",
    "sg:province":"OR",
    "sg:tags":[
        "day"
    ],
    "wof:name":"Florences Day Nurs Kndergarten",
    "wof:placetype":"venue"
},
  "geometry": {"coordinates":[-122.54485699999999,45.481067],"type":"Point"}
}