{
  "type": "Feature",
  "properties": {
    "addr:full":"1415 Adams Ave La Grande OR 97850",
    "addr:housenumber":"1415",
    "addr:postcode":"97850",
    "addr:street":"Adams Ave",
    "iso:country":"US",
    "sg:address":"1415 Adams Ave",
    "sg:city":"La Grande",
    "sg:classifiers":[
        {
            "category":"Autos & Motor Vehicles",
            "subcategory":"Automobile Sales",
            "type":"Retail Goods"
        }
    ],
    "sg:phone":"+1 541 963 4161",
    "sg:postcode":"97850",
    "sg:province":"OR",
    "sg:tags":[
        "car",
        "dealer"
    ],
    "sg:website":"www.gossmotors.com",
    "wof:name":"M J Goss Motor Co",
    "wof:placetype":"venue"
},
  "geometry": {"coordinates":[-118.092162,45.327214],"type":"Point"}
}