{
  "type": "Feature",
  "properties": {
    "iso:country":"US",
    "sg:address":"4701 Rawhide Ct NE",
    "sg:city":"Salem",
    "sg:classifiers":[
        {
            "category":"Building & Trades",
            "subcategory":"Construction",
            "type":"Services"
        }
    ],
    "sg:phone":"+1 503 390 7370",
    "sg:postcode":"97305",
    "sg:province":"OR",
    "sg:tags":[
        "floor",
        "laying",
        "contractor"
    ],
    "wof:name":"Jerry McHorse",
    "wof:placetype":"venue"
},
  "geometry": {"coordinates":[-122.965547,44.993389],"type":"Point"}
}