{
  "type": "Feature",
  "properties": {
    "iso:country":"US",
    "sg:address":"2205 Hwy 101 N",
    "sg:city":"Tillamook",
    "sg:classifiers":[
        {
            "category":"Restaurant",
            "type":"Food & Drink"
        }
    ],
    "sg:phone":"+1 503 842 7277",
    "sg:postcode":"97141",
    "sg:province":"OR",
    "sg:tags":[
        "eating"
    ],
    "wof:name":"Main Street Pizza Co",
    "wof:placetype":"venue"
},
  "geometry": {"coordinates":[-123.844155,45.473342],"type":"Point"}
}