{
  "type": "Feature",
  "properties": {
    "addr:full":"409 Montello Ave Hood River OR 97031",
    "addr:housenumber":"409",
    "addr:postcode":"97031",
    "addr:street":"Montello Ave",
    "iso:country":"US",
    "sg:address":"409 Montello Ave",
    "sg:city":"Hood River",
    "sg:classifiers":[
        {
            "category":"Professional",
            "subcategory":"Engineering",
            "type":"Services"
        }
    ],
    "sg:phone":"+1 541 386 1455",
    "sg:postcode":"97031",
    "sg:province":"OR",
    "wof:name":"Warren Engineering",
    "wof:placetype":"venue"
},
  "geometry": {"coordinates":[-121.51468300000001,45.705512],"type":"Point"}
}