{
  "type": "Feature",
  "properties": {
    "iso:country":"US",
    "sg:address":"31681 Brinn Rd",
    "sg:city":"Saint Helens",
    "sg:classifiers":[
        {
            "category":"Shopping",
            "type":"Retail Goods"
        }
    ],
    "sg:phone":"+1 503 397 3175",
    "sg:postcode":"97051",
    "sg:province":"OR",
    "sg:tags":[
        "merchandise"
    ],
    "wof:name":"Annies Impressions",
    "wof:placetype":"venue"
},
  "geometry": {"coordinates":[-122.916916,45.869756],"type":"Point"}
}