{
  "type": "Feature",
  "properties": {
    "addr:full":"200 W 2nd St Halsey OR 97348",
    "addr:housenumber":"200",
    "addr:postcode":"97348",
    "addr:street":"W 2Nd St",
    "iso:country":"US",
    "sg:address":"200 W 2nd St",
    "sg:city":"Halsey",
    "sg:classifiers":[
        {
            "category":"Wholesale",
            "subcategory":"Plants",
            "type":"Manufacturing & Wholesale Goods"
        }
    ],
    "sg:phone":"+1 541 369 3550",
    "sg:postcode":"97348",
    "sg:province":"OR",
    "sg:tags":[
        "florist"
    ],
    "wof:name":"Continental Floral Greens",
    "wof:placetype":"venue"
},
  "geometry": {"coordinates":[-123.109776,44.387562],"type":"Point"}
}