{
  "type": "Feature",
  "properties": {
    "addr:full":"205 SE Spokane St Portland OR 97202",
    "addr:housenumber":"205",
    "addr:postcode":"97202",
    "addr:street":"Se Spokane St",
    "iso:country":"US",
    "sg:address":"205 SE Spokane St",
    "sg:city":"Portland",
    "sg:classifiers":[
        {
            "category":"Organizations",
            "subcategory":"Non-profit Organization",
            "type":"Services"
        }
    ],
    "sg:phone":"+1 503 848 3893",
    "sg:postcode":"97202",
    "sg:province":"OR",
    "sg:tags":[
        "charity",
        "foundations-educational",
        "philanthropic",
        "research"
    ],
    "wof:name":"The Morgan Family Foundation",
    "wof:placetype":"venue"
},
  "geometry": {"coordinates":[-122.66272499999999,45.465029],"type":"Point"}
}