{
  "type": "Feature",
  "properties": {
    "addr:full":"858 Lancaster Dr NE Salem OR 97301",
    "addr:housenumber":"858",
    "addr:postcode":"97301",
    "addr:street":"Lancaster Dr Ne",
    "iso:country":"US",
    "sg:address":"858 Lancaster Dr NE",
    "sg:city":"Salem",
    "sg:classifiers":[
        {
            "category":"Insurance",
            "subcategory":"Insurance Agent",
            "type":"Services"
        }
    ],
    "sg:phone":"+1 503 585 1610",
    "sg:postcode":"97301",
    "sg:province":"OR",
    "wof:name":"Farmers Insurance",
    "wof:placetype":"venue"
},
  "geometry": {"coordinates":[-122.98320099999999,44.942397],"type":"Point"}
}