{
  "type": "Feature",
  "properties": {
    "iso:country":"US",
    "sg:address":"PO Box 5126",
    "sg:city":"Central Point",
    "sg:classifiers":[
        {
            "category":"Communications",
            "type":"Services"
        }
    ],
    "sg:phone":"+1 541 773 7820",
    "sg:postcode":"97502",
    "sg:province":"OR",
    "sg:tags":[
        "recording",
        "rehearsal",
        "studio"
    ],
    "wof:name":"Sleepy Hollow Productions",
    "wof:placetype":"venue"
},
  "geometry": {"coordinates":[-122.925003,42.385899],"type":"Point"}
}