{
  "type": "Feature",
  "properties": {
    "iso:country":"US",
    "sg:address":"15920 SE Stark St",
    "sg:city":"Portland",
    "sg:classifiers":[
        {
            "category":"Bars & Pubs",
            "type":"Food & Drink"
        }
    ],
    "sg:phone":"+1 503 253 8765",
    "sg:postcode":"97233",
    "sg:province":"OR",
    "sg:tags":[
        "drinking"
    ],
    "wof:name":"Dream On Saloon Inc",
    "wof:placetype":"venue"
},
  "geometry": {"coordinates":[-122.49929,45.51908],"type":"Point"}
}