{
  "type": "Feature",
  "properties": {
    "iso:country":"US",
    "sg:address":"3555 River Rd N",
    "sg:city":"Keizer",
    "sg:classifiers":[
        {
            "category":"Autos & Motor Vehicles",
            "subcategory":"Automobile Sales",
            "type":"Retail Goods"
        }
    ],
    "sg:phone":"+1 503 463 4853",
    "sg:postcode":"97303",
    "sg:province":"OR",
    "sg:tags":[
        "car",
        "dealer"
    ],
    "wof:name":"Skyline Ford Sales Inc",
    "wof:placetype":"venue"
},
  "geometry": {"coordinates":[-123.02676700000001,44.977085],"type":"Point"}
}