{
  "type": "Feature",
  "properties": {
    "iso:country":"US",
    "sg:address":"48 S Stage Rd",
    "sg:city":"Medford",
    "sg:classifiers":[
        {
            "category":"Manufacturing",
            "subcategory":"Food",
            "type":"Manufacturing & Wholesale Goods"
        }
    ],
    "sg:phone":"+1 541 535 7055",
    "sg:postcode":"97501",
    "sg:province":"OR",
    "sg:tags":[
        "product",
        "mfg",
        "potato"
    ],
    "wof:name":"Fresh Potato Products",
    "wof:placetype":"venue"
},
  "geometry": {"coordinates":[-122.84303,42.293116],"type":"Point"}
}