{
  "type": "Feature",
  "properties": {
    "iso:country":"US",
    "sg:address":"10221 NE Mattey Ln",
    "sg:city":"McMinnville",
    "sg:classifiers":[
        {
            "category":"Travel",
            "subcategory":"Hotels & Motels",
            "type":"Entertainment"
        }
    ],
    "sg:phone":"+1 503 434 5058",
    "sg:postcode":"97128",
    "sg:province":"OR",
    "sg:tags":[
        "breakfast",
        "inn",
        "bed",
        "accommodation"
    ],
    "sg:website":"www.matteyhouse.com",
    "wof:name":"Mattey House Inn",
    "wof:placetype":"venue"
},
  "geometry": {"coordinates":[-123.13400300000001,45.242298],"type":"Point"}
}