{
  "type": "Feature",
  "properties": {
    "iso:country":"US",
    "sg:address":"38 N Central Ave #100",
    "sg:city":"Medford",
    "sg:classifiers":[
        {
            "category":"Insurance",
            "subcategory":"Insurance Agent",
            "type":"Services"
        },
        {
            "category":"Insurance",
            "subcategory":"Hazard Insurance",
            "type":"Services"
        },
        {
            "category":"Insurance",
            "subcategory":"Title Insurance",
            "type":"Services"
        },
        {
            "category":"Insurance",
            "subcategory":"Health Insurance",
            "type":"Services"
        },
        {
            "category":"Insurance",
            "subcategory":"Life Insurance",
            "type":"Services"
        }
    ],
    "sg:phone":"+1 541 779 1321",
    "sg:postcode":"97501",
    "sg:province":"OR",
    "sg:tags":[
        "business",
        "auto",
        "dental",
        "commercial",
        "homeowner",
        "compensation",
        "worker",
        "property",
        "disability",
        "casualty"
    ],
    "sg:website":"http://www.wsi-insurance.com",
    "wof:name":"Western States Insurance Agency",
    "wof:placetype":"venue"
},
  "geometry": {"coordinates":[-122.872643,42.326986],"type":"Point"}
}