{
  "type": "Feature",
  "properties": {
    "iso:country":"US",
    "sg:address":"32891 Merrill Ln",
    "sg:city":"Lebanon",
    "sg:classifiers":[
        {
            "category":"Real Estate",
            "subcategory":"Real Estate Operator",
            "type":"Services"
        }
    ],
    "sg:phone":"+1 541 258 5582",
    "sg:postcode":"97355",
    "sg:province":"OR",
    "sg:tags":[
        "logging",
        "commercial",
        "contractor"
    ],
    "wof:name":"Merrill Development Inc",
    "wof:placetype":"venue"
},
  "geometry": {"coordinates":[-122.859039,44.537603],"type":"Point"}
}