{
  "type": "Feature",
  "properties": {
    "addr:full":"3400 State St Suite G720 Salem OR 97301",
    "addr:housenumber":"3400",
    "addr:postcode":"97301",
    "addr:street":"State St Suite G720",
    "iso:country":"US",
    "sg:address":"3400 State St Suite G720",
    "sg:city":"Salem",
    "sg:classifiers":[
        {
            "category":"Professional",
            "subcategory":"Employment Agencies",
            "type":"Services"
        }
    ],
    "sg:phone":"+1 503 364 5189",
    "sg:postcode":"97301",
    "sg:province":"OR",
    "sg:tags":[
        "opportunity"
    ],
    "sg:website":"http://projob.com/",
    "wof:name":"Brown & Dunton Inc",
    "wof:placetype":"venue"
},
  "geometry": {"coordinates":[-122.993652,44.927898],"type":"Point"}
}