{
  "type": "Feature",
  "properties": {
    "iso:country":"US",
    "sg:address":"6590 Thurston Rd",
    "sg:city":"Springfield",
    "sg:classifiers":[
        {
            "category":"Food & Beverages",
            "subcategory":"Groceries & Convenience Stores",
            "type":"Retail Goods"
        }
    ],
    "sg:phone":"+1 541 746 7002",
    "sg:postcode":"97478",
    "sg:province":"OR",
    "sg:tags":[
        "grocer"
    ],
    "wof:name":"Thurston Market",
    "wof:placetype":"venue"
},
  "geometry": {"coordinates":[-122.911717,44.053229],"type":"Point"}
}