{
  "type": "Feature",
  "properties": {
    "iso:country":"US",
    "sg:address":"511 SW 10th Ave Ste 500",
    "sg:city":"Portland",
    "sg:classifiers":[
        {
            "category":"Health Services",
            "subcategory":"Optometrist",
            "type":"Services"
        }
    ],
    "sg:phone":"+1 503 352 2500",
    "sg:postcode":"97205",
    "sg:province":"OR",
    "wof:name":"Pacific University",
    "wof:placetype":"venue"
},
  "geometry": {"coordinates":[-122.681425,45.521282],"type":"Point"}
}