{
  "type": "Feature",
  "properties": {
    "addr:full":"12755 SW 2nd St Ste A Beaverton OR 97005",
    "addr:housenumber":"12755",
    "addr:postcode":"97005",
    "addr:street":"Sw 2Nd St Ste A",
    "iso:country":"US",
    "sg:address":"12755 SW 2nd St Ste A",
    "sg:city":"Beaverton",
    "sg:classifiers":[
        {
            "category":"Health Services",
            "subcategory":"Dentist",
            "type":"Services"
        }
    ],
    "sg:phone":"+1 503 644 1953",
    "sg:postcode":"97005",
    "sg:province":"OR",
    "sg:website":"www.morellidentistry.com",
    "wof:name":"Morelli Dentistry",
    "wof:placetype":"venue"
},
  "geometry": {"coordinates":[-122.807864,45.485875],"type":"Point"}
}