{
  "type": "Feature",
  "properties": {
    "addr:full":"2140 Hill St SE Albany OR 97322",
    "addr:housenumber":"2140",
    "addr:postcode":"97322",
    "addr:street":"Hill St Se",
    "iso:country":"US",
    "sg:address":"2140 Hill St SE",
    "sg:city":"Albany",
    "sg:classifiers":[
        {
            "category":"Organizations",
            "subcategory":"Religious Organization",
            "type":"Services"
        }
    ],
    "sg:phone":"+1 541 928 2133",
    "sg:postcode":"97322",
    "sg:province":"OR",
    "sg:tags":[
        "church"
    ],
    "wof:name":"Riverside Baptist Church",
    "wof:placetype":"venue"
},
  "geometry": {"coordinates":[-123.090492,44.620948],"type":"Point"}
}