{
  "type": "Feature",
  "properties": {
    "iso:country":"US",
    "sg:address":"1045 N Main St",
    "sg:city":"Ashland",
    "sg:classifiers":[
        {
            "category":"Professional",
            "subcategory":"Management & Consulting",
            "type":"Services"
        }
    ],
    "sg:phone":"+1 541 488 5075",
    "sg:postcode":"97520",
    "sg:province":"OR",
    "sg:tags":[
        "marketing",
        "program"
    ],
    "wof:name":"Kingsley Lewis & Assoc",
    "wof:placetype":"venue"
},
  "geometry": {"coordinates":[-122.728426,42.211894],"type":"Point"}
}