{
  "type": "Feature",
  "properties": {
    "addr:full":"3443 Hilyard St Eugene OR 97405",
    "addr:housenumber":"3443",
    "addr:postcode":"97405",
    "addr:street":"Hilyard St",
    "iso:country":"US",
    "sg:address":"3443 Hilyard St",
    "sg:city":"Eugene",
    "sg:classifiers":[
        {
            "category":"Retail",
            "subcategory":"Laundry & Dry Cleaning",
            "type":"Services"
        }
    ],
    "sg:phone":"+1 541 342 7746",
    "sg:postcode":"97405",
    "sg:province":"OR",
    "wof:name":"Spin City Laundry",
    "wof:placetype":"venue"
},
  "geometry": {"coordinates":[-123.08145,44.018801],"type":"Point"}
}