{
  "type": "Feature",
  "properties": {
    "addr:full":"981 Chemawa Rd NE Keizer OR 97303",
    "addr:housenumber":"981",
    "addr:postcode":"97303",
    "addr:street":"Chemawa Rd Ne",
    "iso:country":"US",
    "sg:address":"981 Chemawa Rd NE",
    "sg:city":"Keizer",
    "sg:classifiers":[
        {
            "category":"Professional",
            "subcategory":"Accounting & Tax Preparation",
            "type":"Services"
        }
    ],
    "sg:phone":"+1 503 393 2877",
    "sg:postcode":"97303",
    "sg:province":"OR",
    "sg:tags":[
        "return",
        "filing"
    ],
    "wof:name":"My Enterprises Inc",
    "wof:placetype":"venue"
},
  "geometry": {"coordinates":[-123.019171,44.996959],"type":"Point"}
}