{
  "type": "Feature",
  "properties": {
    "iso:country":"US",
    "sg:address":"12388 SW Center St.",
    "sg:city":"Beaverton",
    "sg:classifiers":[
        {
            "category":"Real Estate",
            "subcategory":"Real Estate Operator",
            "type":"Services"
        }
    ],
    "sg:phone":"+1 503 626 6607",
    "sg:postcode":"97005",
    "sg:province":"OR",
    "sg:tags":[
        "apartment"
    ],
    "sg:website":"www.beavertonoregonapartments.com",
    "wof:name":"Center Plaza Apartments",
    "wof:placetype":"venue"
},
  "geometry": {"coordinates":[-122.80411100000001,45.493683],"type":"Point"}
}