{
  "type": "Feature",
  "properties": {
    "iso:country":"US",
    "sg:address":"2612 E Barnett Rd",
    "sg:city":"Medford",
    "sg:classifiers":[
        {
            "category":"Professional",
            "subcategory":"Management & Consulting",
            "type":"Services"
        }
    ],
    "sg:phone":"+1 541 773 3191",
    "sg:postcode":"97504",
    "sg:province":"OR",
    "sg:tags":[
        "personnel",
        "consultant"
    ],
    "wof:name":"Mind Your Business",
    "wof:placetype":"venue"
},
  "geometry": {"coordinates":[-122.83549600000001,42.316489],"type":"Point"}
}