{
  "type": "Feature",
  "properties": {
    "iso:country":"US",
    "sg:address":"975 Fruitdale Dr",
    "sg:city":"Grants Pass",
    "sg:classifiers":[
        {
            "category":"Professional",
            "type":"Services"
        }
    ],
    "sg:phone":"+1 541 476 9864",
    "sg:postcode":"97527",
    "sg:province":"OR",
    "wof:name":"Mike Richardson",
    "wof:placetype":"venue"
},
  "geometry": {"coordinates":[-123.32110299999999,42.422406],"type":"Point"}
}