{
  "type": "Feature",
  "properties": {
    "iso:country":"US",
    "sg:address":"PO Box 66533",
    "sg:city":"Portland",
    "sg:classifiers":[
        {
            "category":"Building & Trades",
            "subcategory":"Construction",
            "type":"Services"
        }
    ],
    "sg:phone":"+1 503 772 1110",
    "sg:postcode":"97290",
    "sg:province":"OR",
    "sg:tags":[
        "painter"
    ],
    "sg:website":"www.torgersonpainting.com",
    "wof:name":"Torgerson Painting",
    "wof:placetype":"venue"
},
  "geometry": {"coordinates":[-122.658997,45.562599],"type":"Point"}
}