{
  "type": "Feature",
  "properties": {
    "iso:country":"US",
    "sg:address":"40504 Fox Valley Rd",
    "sg:city":"Lyons",
    "sg:classifiers":[
        {
            "category":"Building & Trades",
            "subcategory":"Equipment Rental",
            "type":"Services"
        }
    ],
    "sg:phone":"+1 503 859 3356",
    "sg:postcode":"97358",
    "sg:province":"OR",
    "wof:name":"Fox Valley Properties LLC",
    "wof:placetype":"venue"
},
  "geometry": {"coordinates":[-122.573608,44.758544],"type":"Point"}
}