{
  "type": "Feature",
  "properties": {
    "iso:country":"US",
    "sg:address":"409 E Main St",
    "sg:city":"Athena",
    "sg:classifiers":[
        {
            "category":"Autos & Motor Vehicles",
            "subcategory":"Auto Supplies",
            "type":"Retail Goods"
        }
    ],
    "sg:phone":"+1 541 566 3633",
    "sg:postcode":"97813",
    "sg:province":"OR",
    "sg:tags":[
        "automobile",
        "parts"
    ],
    "wof:name":"Athena Auto Parts Inc",
    "wof:placetype":"venue"
},
  "geometry": {"coordinates":[-118.488907,45.811786],"type":"Point"}
}