{
  "type": "Feature",
  "properties": {
    "iso:country":"US",
    "sg:address":"Washington Square MA",
    "sg:city":"Portland",
    "sg:classifiers":[
        {
            "category":"Shopping",
            "subcategory":"Optician",
            "type":"Retail Goods"
        }
    ],
    "sg:phone":"+1 503 968 5437",
    "sg:postcode":"97223",
    "sg:province":"OR",
    "sg:tags":[
        "eyewear"
    ],
    "sg:website":"www.binyons.com",
    "wof:name":"Binyon's",
    "wof:placetype":"venue"
},
  "geometry": {"coordinates":[-122.77920899999999,45.441388],"type":"Point"}
}