{
  "type": "Feature",
  "properties": {
    "iso:country":"US",
    "sg:address":"532 W Umpqua St",
    "sg:city":"Roseburg",
    "sg:classifiers":[
        {
            "category":"Health Services",
            "subcategory":"Doctor",
            "type":"Services"
        }
    ],
    "sg:phone":"+1 541 673 0133",
    "sg:postcode":"97470",
    "sg:province":"OR",
    "sg:tags":[
        "medical"
    ],
    "wof:name":"Gombart Augustin MD Inc",
    "wof:placetype":"venue"
},
  "geometry": {"coordinates":[-123.35915799999999,43.215673],"type":"Point"}
}