{
  "type": "Feature",
  "properties": {
    "iso:country":"US",
    "sg:address":"1166 F St",
    "sg:city":"Springfield",
    "sg:classifiers":[
        {
            "category":"Professional",
            "subcategory":"Management & Consulting",
            "type":"Services"
        }
    ],
    "sg:phone":"+1 541 741 2109",
    "sg:postcode":"97477",
    "sg:province":"OR",
    "sg:tags":[
        "product",
        "retail",
        "dairy",
        "direct",
        "sales"
    ],
    "wof:name":"Tcs Delivery",
    "wof:placetype":"venue"
},
  "geometry": {"coordinates":[-123.01191799999999,44.051502],"type":"Point"}
}