{
  "type": "Feature",
  "properties": {
    "iso:country":"US",
    "sg:address":"2047 NW Aloclek Dr",
    "sg:city":"Hillsboro",
    "sg:classifiers":[
        {
            "category":"Wholesale",
            "subcategory":"Construction Materials",
            "type":"Manufacturing & Wholesale Goods"
        }
    ],
    "sg:phone":"+1 503 439 9858",
    "sg:postcode":"97124",
    "sg:province":"OR",
    "sg:tags":[
        "mfg",
        "wood",
        "structural"
    ],
    "wof:name":"Stellar Structures LLC",
    "wof:placetype":"venue"
},
  "geometry": {"coordinates":[-122.895319,45.534984],"type":"Point"}
}