{
  "type": "Feature",
  "properties": {
    "addr:full":"10540 SW 80th Ave Portland OR 97223",
    "addr:housenumber":"10540",
    "addr:postcode":"97223",
    "addr:street":"Sw 80Th Ave",
    "iso:country":"US",
    "sg:address":"10540 SW 80th Ave",
    "sg:city":"Portland",
    "sg:classifiers":[
        {
            "category":"Wholesale",
            "subcategory":"Home Furnishings",
            "type":"Manufacturing & Wholesale Goods"
        }
    ],
    "sg:phone":"+1 503 922 0938",
    "sg:postcode":"97223",
    "sg:province":"OR",
    "sg:tags":[
        "blind",
        "shade"
    ],
    "wof:name":"Builders Secret",
    "wof:placetype":"venue"
},
  "geometry": {"coordinates":[-122.759021,45.443788],"type":"Point"}
}