{
  "type": "Feature",
  "properties": {
    "iso:country":"US",
    "sg:address":"1520 Coburg Rd",
    "sg:city":"Eugene",
    "sg:phone":"+1 541 255 3176",
    "sg:postcode":"97401",
    "sg:province":"OR",
    "sg:website":"http://www.shamrockflowersandgifts.net",
    "wof:name":"Shamrock Flowers",
    "wof:placetype":"venue"
},
  "geometry": {"coordinates":[-123.069388,44.077292],"type":"Point"}
}