{
  "type": "Feature",
  "properties": {
    "addr:full":"860 Elm Dr Eugene OR 97404",
    "addr:housenumber":"860",
    "addr:postcode":"97404",
    "addr:street":"Elm Dr",
    "iso:country":"US",
    "sg:address":"860 Elm Dr",
    "sg:city":"Eugene",
    "sg:classifiers":[
        {
            "category":"Manufacturing",
            "subcategory":"Metals",
            "type":"Manufacturing & Wholesale Goods"
        }
    ],
    "sg:phone":"+1 541 607 1818",
    "sg:postcode":"97404",
    "sg:province":"OR",
    "sg:tags":[
        "equipment",
        "heating",
        "mfg"
    ],
    "wof:name":"Windstream Solar",
    "wof:placetype":"venue"
},
  "geometry": {"coordinates":[-123.142904,44.089601],"type":"Point"}
}