{
  "type": "Feature",
  "properties": {
    "iso:country":"US",
    "sg:address":"945 S Ivy St",
    "sg:city":"Medford",
    "sg:classifiers":[
        {
            "category":"Mining & Drilling",
            "type":"Manufacturing & Wholesale Goods"
        }
    ],
    "sg:phone":"+1 541 773 7152",
    "sg:postcode":"97501",
    "sg:province":"OR",
    "sg:tags":[
        "construction"
    ],
    "wof:name":"Ron Register Construction",
    "wof:placetype":"venue"
},
  "geometry": {"coordinates":[-122.87068,42.314059],"type":"Point"}
}