{
  "type": "Feature",
  "properties": {
    "addr:full":"1804 NE Broadway St Portland OR 97232",
    "addr:housenumber":"1804",
    "addr:postcode":"97232",
    "addr:street":"Ne Broadway St",
    "iso:country":"US",
    "sg:address":"1804 NE Broadway St",
    "sg:city":"Portland",
    "sg:classifiers":[
        {
            "category":"Home & Garden",
            "subcategory":"Building Materials",
            "type":"Retail Goods"
        },
        {
            "category":"Retail",
            "subcategory":"Auto Repair",
            "type":"Services"
        }
    ],
    "sg:phone":"+1 503 288 5964",
    "sg:postcode":"97232",
    "sg:province":"OR",
    "sg:tags":[
        "plate",
        "window",
        "replacement",
        "glass"
    ],
    "sg:website":"http://www.speedyglass.com",
    "wof:name":"Speedy Glass",
    "wof:placetype":"venue"
},
  "geometry": {"coordinates":[-122.64751099999999,45.535015],"type":"Point"}
}