{
  "type": "Feature",
  "properties": {
    "iso:country":"US",
    "sg:address":"529 Jefferson St SE",
    "sg:city":"Albany",
    "sg:classifiers":[
        {
            "category":"Organizations",
            "subcategory":"Religious Organization",
            "type":"Services"
        }
    ],
    "sg:phone":"+1 541 926 1359",
    "sg:postcode":"97321",
    "sg:province":"OR",
    "sg:tags":[
        "church"
    ],
    "wof:name":"Albany Foursquare Church Inc",
    "wof:placetype":"venue"
},
  "geometry": {"coordinates":[-123.097754,44.634772],"type":"Point"}
}