{
  "type": "Feature",
  "properties": {
    "iso:country":"US",
    "sg:address":"4136 SE Hawthorne Blvd",
    "sg:city":"Portland",
    "sg:classifiers":[
        {
            "category":"Personal",
            "subcategory":"Barber",
            "type":"Services"
        }
    ],
    "sg:phone":"+1 503 235 5632",
    "sg:postcode":"97214",
    "sg:province":"OR",
    "sg:website":"www.barber-q-oregon.com",
    "wof:name":"Barber - Q",
    "wof:placetype":"venue"
},
  "geometry": {"coordinates":[-122.61950299999999,45.511956],"type":"Point"}
}