{
  "type": "Feature",
  "properties": {
    "iso:country":"US",
    "sg:address":"86859 State Hwy 202",
    "sg:city":"Astoria",
    "sg:classifiers":[
        {
            "category":"Wholesale",
            "subcategory":"Sporting Goods",
            "type":"Manufacturing & Wholesale Goods"
        }
    ],
    "sg:phone":"+1 503 640 2669",
    "sg:postcode":"97103",
    "sg:province":"OR",
    "wof:name":"Crashpads",
    "wof:placetype":"venue"
},
  "geometry": {"coordinates":[-123.706918,46.081044],"type":"Point"}
}