{
  "type": "Feature",
  "properties": {
    "iso:country":"US",
    "sg:address":"214 SE Roosevelt Ave",
    "sg:city":"Bend",
    "sg:classifiers":[
        {
            "category":"Home & Garden",
            "subcategory":"Home Furnishings",
            "type":"Retail Goods"
        }
    ],
    "sg:phone":"+1 541 389 3594",
    "sg:postcode":"97702",
    "sg:province":"OR",
    "sg:tags":[
        "draperies",
        "curtain",
        "window",
        "treatment"
    ],
    "wof:name":"Blind Spot",
    "wof:placetype":"venue"
},
  "geometry": {"coordinates":[-121.303653,44.04248],"type":"Point"}
}