{
  "type": "Feature",
  "properties": {
    "iso:country":"US",
    "sg:address":"1310 Duane St",
    "sg:city":"Astoria",
    "sg:phone":"+1 503 325 9850",
    "sg:postcode":"97103",
    "sg:province":"OR",
    "wof:name":"Shear Expressions",
    "wof:placetype":"venue"
},
  "geometry": {"coordinates":[-123.829353,46.18841],"type":"Point"}
}