{
  "type": "Feature",
  "properties": {
    "iso:country":"US",
    "sg:address":"1885 Norkenzie Rd",
    "sg:city":"Eugene",
    "sg:classifiers":[
        {
            "category":"Professional",
            "type":"Services"
        }
    ],
    "sg:phone":"+1 541 342 4710",
    "sg:postcode":"97401",
    "sg:province":"OR",
    "sg:tags":[
        "caterer"
    ],
    "wof:name":"Smokey's Bbq",
    "wof:placetype":"venue"
},
  "geometry": {"coordinates":[-123.08804499999999,44.083935],"type":"Point"}
}