{
  "type": "Feature",
  "properties": {
    "addr:full":"1535 NE 3rd St Prineville OR 97754",
    "addr:housenumber":"1535",
    "addr:postcode":"97754",
    "addr:street":"Ne 3Rd St",
    "iso:country":"US",
    "sg:address":"1535 NE 3rd St",
    "sg:city":"Prineville",
    "sg:classifiers":[
        {
            "category":"Professional",
            "type":"Services"
        }
    ],
    "sg:phone":"+1 541 447 4023",
    "sg:postcode":"97754",
    "sg:province":"OR",
    "wof:name":"Robert K LLC",
    "wof:placetype":"venue"
},
  "geometry": {"coordinates":[-120.829303,44.303014],"type":"Point"}
}