{
  "type": "Feature",
  "properties": {
    "addr:full":"7246 Melqua Rd Umpqua OR 97486",
    "addr:housenumber":"7246",
    "addr:postcode":"97486",
    "addr:street":"Melqua Rd",
    "iso:country":"US",
    "sg:address":"7246 Melqua Rd",
    "sg:city":"Umpqua",
    "sg:classifiers":[
        {
            "category":"Farming",
            "subcategory":"Livestock Farm",
            "type":"Manufacturing & Wholesale Goods"
        }
    ],
    "sg:phone":"+1 541 673 1989",
    "sg:postcode":"97486",
    "sg:province":"OR",
    "sg:tags":[
        "beef",
        "feedlot",
        "cattle"
    ],
    "wof:name":"Black Gold Ranch LLC",
    "wof:placetype":"venue"
},
  "geometry": {"coordinates":[-123.492445,43.324427],"type":"Point"}
}