{
  "type": "Feature",
  "properties": {
    "addr:full":"28110 SE Fern Dr Boring OR 97009",
    "addr:postcode":"28110;97009",
    "addr:street":"Se Fern Dr",
    "iso:country":"US",
    "sg:address":"28110 SE Fern Dr",
    "sg:city":"Boring",
    "sg:classifiers":[
        {
            "category":"Professional",
            "subcategory":"Computer Services",
            "type":"Services"
        }
    ],
    "sg:phone":"+1 503 663 6819",
    "sg:postcode":"97009",
    "sg:province":"OR",
    "sg:tags":[
        "datum"
    ],
    "wof:name":"Palanuk & Assn Inc",
    "wof:placetype":"venue"
},
  "geometry": {"coordinates":[-122.374949,45.408924],"type":"Point"}
}