{
  "type": "Feature",
  "properties": {
    "iso:country":"US",
    "sg:address":"425 Cameo St NW",
    "sg:city":"Salem",
    "sg:classifiers":[
        {
            "category":"Professional",
            "subcategory":"Computer Services",
            "type":"Services"
        }
    ],
    "sg:phone":"+1 503 371 8425",
    "sg:postcode":"97304",
    "sg:province":"OR",
    "sg:tags":[
        "related"
    ],
    "wof:name":"J D Bytes",
    "wof:placetype":"venue"
},
  "geometry": {"coordinates":[-123.048187,44.953578],"type":"Point"}
}