{
  "type": "Feature",
  "properties": {
    "iso:country":"US",
    "sg:address":"277 N 3rd Ave",
    "sg:city":"Stayton",
    "sg:classifiers":[
        {
            "category":"Professional",
            "subcategory":"Computer Services",
            "type":"Services"
        }
    ],
    "sg:phone":"+1 503 767 4443",
    "sg:postcode":"97383",
    "sg:province":"OR",
    "sg:tags":[
        "internet"
    ],
    "wof:name":"Willamette Broadband",
    "wof:placetype":"venue"
},
  "geometry": {"coordinates":[-122.792325,44.796658],"type":"Point"}
}