{
  "type": "Feature",
  "properties": {
    "addr:full":"13933 SE Steele St Portland OR 97236",
    "addr:housenumber":"13933",
    "addr:postcode":"97236",
    "addr:street":"Se Steele St",
    "iso:country":"US",
    "sg:address":"13933 SE Steele St",
    "sg:city":"Portland",
    "sg:classifiers":[
        {
            "category":"Building & Trades",
            "subcategory":"Landscaping Services",
            "type":"Services"
        }
    ],
    "sg:phone":"+1 503 481 6458",
    "sg:postcode":"97236",
    "sg:province":"OR",
    "wof:name":"Jeds Waterscape Maintenance",
    "wof:placetype":"venue"
},
  "geometry": {"coordinates":[-122.520067,45.484378],"type":"Point"}
}