{
  "type": "Feature",
  "properties": {
    "iso:country":"US",
    "sg:address":"49 SE 9th St",
    "sg:city":"Madras",
    "sg:classifiers":[
        {
            "category":"Retail",
            "subcategory":"Portrait Studio",
            "type":"Services"
        }
    ],
    "sg:phone":"+1 541 475 2507",
    "sg:postcode":"97741",
    "sg:province":"OR",
    "sg:tags":[
        "photo"
    ],
    "wof:name":"Yaskus Photography",
    "wof:placetype":"venue"
},
  "geometry": {"coordinates":[-121.12536799999999,44.635307],"type":"Point"}
}