{
  "type": "Feature",
  "properties": {
    "addr:full":"41818 Washington Gulch Rd Baker City OR 97814",
    "addr:housenumber":"41818",
    "addr:postcode":"97814",
    "addr:street":"Washington Gulch Rd",
    "iso:country":"US",
    "sg:address":"41818 Washington Gulch Rd",
    "sg:city":"Baker City",
    "sg:classifiers":[
        {
            "category":"Farming",
            "subcategory":"Livestock Farm",
            "type":"Manufacturing & Wholesale Goods"
        }
    ],
    "sg:phone":"+1 541 523 9471",
    "sg:postcode":"97814",
    "sg:province":"OR",
    "sg:tags":[
        "equine"
    ],
    "wof:name":"C & M Arabians",
    "wof:placetype":"venue"
},
  "geometry": {"coordinates":[-117.910338,44.772138],"type":"Point"}
}