{
  "type": "Feature",
  "properties": {
    "iso:country":"US",
    "sg:address":"92456 Maki Rd",
    "sg:city":"Astoria",
    "sg:classifiers":[
        {
            "category":"Manufacturing",
            "subcategory":"Lumber",
            "type":"Manufacturing & Wholesale Goods"
        }
    ],
    "sg:phone":"+1 503 458 5159",
    "sg:postcode":"97103",
    "sg:province":"OR",
    "sg:tags":[
        "company",
        "logging"
    ],
    "wof:name":"KATT Contract Timber Fallin",
    "wof:placetype":"venue"
},
  "geometry": {"coordinates":[-123.66873,46.160914],"type":"Point"}
}