{
  "type": "Feature",
  "properties": {
    "iso:country":"US",
    "sg:address":"8200 SW Tonka St",
    "sg:city":"Tualatin",
    "sg:classifiers":[
        {
            "category":"Bars & Pubs",
            "type":"Food & Drink"
        },
        {
            "category":"Restaurant",
            "type":"Food & Drink"
        }
    ],
    "sg:phone":"+1 503 692 3982",
    "sg:postcode":"97062",
    "sg:province":"OR",
    "sg:tags":[
        "traditional",
        "american"
    ],
    "sg:website":"www.bushwhackerssaloon.com/",
    "wof:name":"Bushwhackers",
    "wof:placetype":"venue"
},
  "geometry": {"coordinates":[-122.762001,45.380199],"type":"Point"}
}