{
  "type": "Feature",
  "properties": {
    "iso:country":"US",
    "sg:address":"8700 SW 26th Ave",
    "sg:city":"Portland",
    "sg:classifiers":[
        {
            "category":"Health Services",
            "subcategory":"Medical Lab",
            "type":"Services"
        }
    ],
    "sg:phone":"+1 503 452 0540",
    "sg:postcode":"97219",
    "sg:province":"OR",
    "sg:tags":[
        "laboratory"
    ],
    "wof:name":"Excel Orthodontics",
    "wof:placetype":"venue"
},
  "geometry": {"coordinates":[-122.703356,45.462415],"type":"Point"}
}