{
  "type": "Feature",
  "properties": {
    "iso:country":"US",
    "sg:address":"7874 SW Nimbus Ave",
    "sg:city":"Beaverton",
    "sg:classifiers":[
        {
            "category":"Wholesale",
            "subcategory":"Sporting Goods",
            "type":"Manufacturing & Wholesale Goods"
        }
    ],
    "sg:phone":"+1 503 641 5417",
    "sg:postcode":"97008",
    "sg:province":"OR",
    "sg:tags":[
        "equipment",
        "golf",
        "supply"
    ],
    "wof:name":"Pacific Golf Accessories",
    "wof:placetype":"venue"
},
  "geometry": {"coordinates":[-122.78847,45.461664],"type":"Point"}
}