{
  "type": "Feature",
  "properties": {
    "iso:country":"US",
    "sg:address":"1100 Shelley St",
    "sg:city":"Springfield",
    "sg:classifiers":[
        {
            "category":"Manufacturing",
            "subcategory":"Food",
            "type":"Manufacturing & Wholesale Goods"
        }
    ],
    "sg:phone":"+1 541 726 7824",
    "sg:postcode":"97477",
    "sg:province":"OR",
    "sg:tags":[
        "canned",
        "fish",
        "cured",
        "seafood"
    ],
    "sg:website":"www.oregonlox.com",
    "wof:name":"Oregon Lox Co",
    "wof:placetype":"venue"
},
  "geometry": {"coordinates":[-123.04055,44.065084],"type":"Point"}
}