{
  "type": "Feature",
  "properties": {
    "iso:country":"US",
    "sg:address":"2081 SE Elliott Pl",
    "sg:city":"Gresham",
    "sg:classifiers":[
        {
            "category":"Building & Trades",
            "subcategory":"Construction",
            "type":"Services"
        }
    ],
    "sg:phone":"+1 503 666 5211",
    "sg:postcode":"97080",
    "sg:province":"OR",
    "sg:tags":[
        "contractor",
        "laying",
        "flooring",
        "floor"
    ],
    "wof:name":"Accent Floorcovering",
    "wof:placetype":"venue"
},
  "geometry": {"coordinates":[-122.424701,45.482429],"type":"Point"}
}