{
  "type": "Feature",
  "properties": {
    "addr:full":"2736 NE Ridgewood Dr Portland OR 97212",
    "addr:housenumber":"2736",
    "addr:postcode":"97212",
    "addr:street":"Ne Ridgewood Dr",
    "iso:country":"US",
    "sg:address":"2736 NE Ridgewood Dr",
    "sg:city":"Portland",
    "sg:classifiers":[
        {
            "category":"Professional",
            "subcategory":"Management & Consulting",
            "type":"Services"
        }
    ],
    "sg:phone":"+1 503 335 8024",
    "sg:postcode":"97212",
    "sg:province":"OR",
    "wof:name":"Catherine J Gerald",
    "wof:placetype":"venue"
},
  "geometry": {"coordinates":[-122.637452,45.548932],"type":"Point"}
}