{
  "type": "Feature",
  "properties": {
    "addr:full":"SW 9th and Alder Portland OR 97255",
    "addr:postcode":"97255",
    "addr:street":"Sw",
    "iso:country":"US",
    "sg:address":"SW 9th and Alder",
    "sg:city":"Portland",
    "sg:classifiers":[
        {
            "category":"Food Court",
            "type":"Food & Drink"
        }
    ],
    "sg:phone":"+1 503 757 2695",
    "sg:postcode":"97255",
    "sg:province":"OR",
    "sg:tags":[
        "stand"
    ],
    "sg:website":"www.thewholebowl.com",
    "wof:name":"The Whole Bowl",
    "wof:placetype":"venue"
},
  "geometry": {"coordinates":[-122.68078300000001,45.520425],"type":"Point"}
}