{
  "type": "Feature",
  "properties": {
    "iso:country":"US",
    "sg:address":"6921 SW Tierra del Mar Dr",
    "sg:city":"Beaverton",
    "sg:classifiers":[
        {
            "category":"Building & Trades",
            "subcategory":"Construction",
            "type":"Services"
        }
    ],
    "sg:phone":"+1 503 643 1675",
    "sg:postcode":"97007",
    "sg:province":"OR",
    "sg:tags":[
        "hanging",
        "contractor"
    ],
    "wof:name":"Steve Redig",
    "wof:placetype":"venue"
},
  "geometry": {"coordinates":[-122.82856200000001,45.470322],"type":"Point"}
}