{
  "type": "Feature",
  "properties": {
    "addr:full":"1906 Everett St North Bend OR 97459",
    "addr:housenumber":"1906",
    "addr:postcode":"97459",
    "addr:street":"Everett St",
    "iso:country":"US",
    "sg:address":"1906 Everett St",
    "sg:city":"North Bend",
    "sg:classifiers":[
        {
            "category":"Wholesale",
            "subcategory":"Electrical",
            "type":"Manufacturing & Wholesale Goods"
        }
    ],
    "sg:phone":"+1 541 756 0459",
    "sg:postcode":"97459",
    "sg:province":"OR",
    "sg:tags":[
        "equipment",
        "electric",
        "supply"
    ],
    "wof:name":"Platt Electric Supply Inc",
    "wof:placetype":"venue"
},
  "geometry": {"coordinates":[-124.237966,43.407707],"type":"Point"}
}