{
  "type": "Feature",
  "properties": {
    "addr:full":"429 Pine St Brookings OR 97415",
    "addr:housenumber":"429",
    "addr:postcode":"97415",
    "addr:street":"Pine St",
    "iso:country":"US",
    "sg:address":"429 Pine St",
    "sg:city":"Brookings",
    "sg:classifiers":[
        {
            "category":"Organizations",
            "subcategory":"Religious Organization",
            "type":"Services"
        }
    ],
    "sg:phone":"+1 541 469 2398",
    "sg:postcode":"97415",
    "sg:province":"OR",
    "sg:tags":[
        "science",
        "churches-religious",
        "church"
    ],
    "wof:name":"Christian Science Church",
    "wof:placetype":"venue"
},
  "geometry": {"coordinates":[-124.277687,42.055397],"type":"Point"}
}