{
  "type": "Feature",
  "properties": {
    "iso:country":"US",
    "sg:address":"16468 Finley Butte Rd",
    "sg:city":"La Pine",
    "sg:classifiers":[
        {
            "category":"Retail",
            "subcategory":"Funeral Services",
            "type":"Services"
        }
    ],
    "sg:phone":"+1 541 536 5104",
    "sg:postcode":"97739",
    "sg:province":"OR",
    "sg:tags":[
        "director"
    ],
    "wof:name":"Baird Memorial Chapel",
    "wof:placetype":"venue"
},
  "geometry": {"coordinates":[-121.50273799999999,43.667459],"type":"Point"}
}