{
  "type": "Feature",
  "properties": {
    "iso:country":"US",
    "sg:address":"1677 Lincoln St",
    "sg:city":"Eugene",
    "sg:classifiers":[
        {
            "category":"Professional",
            "subcategory":"Management & Consulting",
            "type":"Services"
        }
    ],
    "sg:phone":"+1 541 338 7898",
    "sg:postcode":"97401",
    "sg:province":"OR",
    "sg:tags":[
        "business"
    ],
    "wof:name":"Sterger Lyons Consulting Inc",
    "wof:placetype":"venue"
},
  "geometry": {"coordinates":[-123.096948,44.041985],"type":"Point"}
}