{
  "type": "Feature",
  "properties": {
    "iso:country":"US",
    "sg:address":"13755 SW 116th Pl",
    "sg:city":"Portland",
    "sg:classifiers":[
        {
            "category":"Building & Trades",
            "subcategory":"Construction",
            "type":"Services"
        }
    ],
    "sg:phone":"+1 503 968 5737",
    "sg:postcode":"97223",
    "sg:province":"OR",
    "sg:tags":[
        "hanging",
        "contractor"
    ],
    "wof:name":"Mountain Top Painting",
    "wof:placetype":"venue"
},
  "geometry": {"coordinates":[-122.79656900000001,45.42047],"type":"Point"}
}