{
  "type": "Feature",
  "properties": {
    "addr:full":"299 Mill St Falls City OR 97344",
    "addr:housenumber":"299",
    "addr:postcode":"97344",
    "addr:street":"Mill St",
    "iso:country":"US",
    "sg:address":"299 Mill St",
    "sg:city":"Falls City",
    "sg:classifiers":[
        {
            "category":"Government",
            "subcategory":"Office",
            "type":"Public Place"
        }
    ],
    "sg:phone":"+1 503 787 3631",
    "sg:postcode":"97344",
    "sg:province":"OR",
    "sg:tags":[
        "city"
    ],
    "wof:name":"Falls City City Hall",
    "wof:placetype":"venue"
},
  "geometry": {"coordinates":[-123.431465,44.865531],"type":"Point"}
}