{
  "type": "Feature",
  "properties": {
    "iso:country":"US",
    "sg:address":"01 SW Salmon St",
    "sg:city":"Portland",
    "sg:classifiers":[
        {
            "category":"Arts & Performance",
            "subcategory":"Arts Center",
            "type":"Entertainment"
        }
    ],
    "sg:phone":"+1 503 224 3900",
    "sg:postcode":"97204",
    "sg:province":"OR",
    "sg:tags":[
        "performing"
    ],
    "sg:website":"www.portlandspirit.com",
    "wof:name":"Awesome 80's Prom",
    "wof:placetype":"venue"
},
  "geometry": {"coordinates":[-122.67371,45.515496],"type":"Point"}
}