{
  "type": "Feature",
  "properties": {
    "iso:country":"US",
    "sg:address":"18989 NE Sandy Blvd",
    "sg:city":"Portland",
    "sg:classifiers":[
        {
            "category":"Shopping",
            "subcategory":"Used Merchandise",
            "type":"Retail Goods"
        }
    ],
    "sg:phone":"+1 503 492 8123",
    "sg:postcode":"97230",
    "sg:province":"OR",
    "wof:name":"River Run Books",
    "wof:placetype":"venue"
},
  "geometry": {"coordinates":[-122.46154199999999,45.54538],"type":"Point"}
}