{
  "type": "Feature",
  "properties": {
    "iso:country":"US",
    "sg:address":"12905 SW Hart Rd",
    "sg:city":"Beaverton",
    "sg:classifiers":[
        {
            "category":"Building & Trades",
            "subcategory":"Construction",
            "type":"Services"
        }
    ],
    "sg:phone":"+1 503 317 2134",
    "sg:postcode":"97008",
    "sg:province":"OR",
    "sg:tags":[
        "contractor"
    ],
    "sg:website":"www.znkhomes.com",
    "wof:name":"ZNK Homes LLC",
    "wof:placetype":"venue"
},
  "geometry": {"coordinates":[-122.80931,45.46686],"type":"Point"}
}