{
  "type": "Feature",
  "properties": {
    "iso:country":"US",
    "sg:address":"9430 SW Coral St Ste 203",
    "sg:city":"Portland",
    "sg:classifiers":[
        {
            "category":"Professional",
            "subcategory":"Management & Consulting",
            "type":"Services"
        },
        {
            "category":"Professional",
            "subcategory":"Lawyer & Legal Services",
            "type":"Services"
        },
        {
            "category":"Banks & Credit Unions",
            "subcategory":"Financial Services",
            "type":"Services"
        }
    ],
    "sg:phone":"+1 503 445 2023",
    "sg:postcode":"97223",
    "sg:province":"OR",
    "sg:tags":[
        "financing",
        "retirement",
        "sharing",
        "estate",
        "profit",
        "annuity",
        "wills",
        "attorney",
        "planning",
        "plan",
        "consultant",
        "trust",
        "insurance",
        "pension"
    ],
    "wof:name":"Pratt Weller & Associates Inc",
    "wof:placetype":"venue"
},
  "geometry": {"coordinates":[-122.773933,45.447992],"type":"Point"}
}