{
  "type": "Feature",
  "properties": {
    "iso:country":"US",
    "sg:address":"1821 SE 39th Ave",
    "sg:city":"Portland",
    "sg:classifiers":[
        {
            "category":"Organizations",
            "subcategory":"Religious Organization",
            "type":"Services"
        }
    ],
    "sg:phone":"+1 503 235 2127",
    "sg:postcode":"97214",
    "sg:province":"OR",
    "sg:tags":[
        "church"
    ],
    "wof:name":"Cathedral Of Praise",
    "wof:placetype":"venue"
},
  "geometry": {"coordinates":[-122.622851,45.510308],"type":"Point"}
}