{
  "type": "Feature",
  "properties": {
    "iso:country":"US",
    "sg:address":"104 4th Ave SW Ste 200",
    "sg:city":"Albany",
    "sg:classifiers":[
        {
            "category":"Community Center",
            "subcategory":"Youth",
            "type":"Public Place"
        },
        {
            "category":"Government",
            "subcategory":"Office",
            "type":"Public Place"
        }
    ],
    "sg:phone":"+1 541 967 3853",
    "sg:postcode":"97321",
    "sg:province":"OR",
    "sg:tags":[
        "parish",
        "government-county"
    ],
    "wof:name":"Juvenile Department",
    "wof:placetype":"venue"
},
  "geometry": {"coordinates":[-123.10445199999999,44.635045],"type":"Point"}
}