{
  "type": "Feature",
  "properties": {
    "iso:country":"US",
    "sg:address":"1042 NW Norman Ave",
    "sg:city":"Gresham",
    "sg:classifiers":[
        {
            "category":"Insurance",
            "subcategory":"Hazard Insurance",
            "type":"Services"
        },
        {
            "category":"Insurance",
            "subcategory":"Insurance Agent",
            "type":"Services"
        },
        {
            "category":"Insurance",
            "subcategory":"Life Insurance",
            "type":"Services"
        },
        {
            "category":"Insurance",
            "subcategory":"Title Insurance",
            "type":"Services"
        }
    ],
    "sg:phone":"+1 205 699 2222",
    "sg:postcode":"97030",
    "sg:province":"OR",
    "sg:tags":[
        "property",
        "casualty",
        "homeowner"
    ],
    "sg:website":"http://portland.citysearch.com/profile/external/604426382/gresham_or/cotton_states_bill_rutledge.html?publisher=yellowpages&reference_id=1&placement=ypwebsitemip",
    "wof:name":"Cotton States - Bill Rutledge",
    "wof:placetype":"venue"
},
  "geometry": {"coordinates":[-122.43809400000001,45.504716],"type":"Point"}
}