{
  "type": "Feature",
  "properties": {
    "iso:country":"US",
    "sg:address":"1700 NW 167th Pl",
    "sg:city":"Beaverton",
    "sg:classifiers":[
        {
            "category":"Manufacturing",
            "subcategory":"Electronics",
            "type":"Manufacturing & Wholesale Goods"
        }
    ],
    "sg:phone":"+1 503 456 0017",
    "sg:postcode":"97006",
    "sg:province":"OR",
    "sg:tags":[
        "semiconductor"
    ],
    "wof:name":"Intel",
    "wof:placetype":"venue"
},
  "geometry": {"coordinates":[-122.84890799999999,45.530086],"type":"Point"}
}