{
  "type": "Feature",
  "properties": {
    "addr:full":"9440 NE Colfax St Portland OR 97220",
    "addr:housenumber":"9440",
    "addr:postcode":"97220",
    "addr:street":"Ne Colfax St",
    "iso:country":"US",
    "sg:address":"9440 NE Colfax St",
    "sg:city":"Portland",
    "sg:classifiers":[
        {
            "category":"Building & Trades",
            "subcategory":"Construction",
            "type":"Services"
        }
    ],
    "sg:phone":"+1 503 257 6211",
    "sg:postcode":"97220",
    "sg:province":"OR",
    "sg:tags":[
        "maker",
        "cabinet"
    ],
    "wof:name":"Medak Corp",
    "wof:placetype":"venue"
},
  "geometry": {"coordinates":[-122.563371,45.567279],"type":"Point"}
}