{
  "type": "Feature",
  "properties": {
    "iso:country":"US",
    "sg:address":"208 NW Fir Ave",
    "sg:city":"Redmond",
    "sg:classifiers":[
        {
            "category":"Health Services",
            "subcategory":"Clinic",
            "type":"Services"
        }
    ],
    "sg:phone":"+1 541 548 0887",
    "sg:postcode":"97756",
    "sg:province":"OR",
    "wof:name":"Erin Hargrove Medical Transcri",
    "wof:placetype":"venue"
},
  "geometry": {"coordinates":[-121.169411,44.280963],"type":"Point"}
}