{
  "type": "Feature",
  "properties": {
    "iso:country":"US",
    "sg:address":"388 N Main St",
    "sg:city":"Independence",
    "sg:classifiers":[
        {
            "category":"Building & Trades",
            "subcategory":"Cleaning & Sanitation",
            "type":"Services"
        }
    ],
    "sg:phone":"+1 503 606 0216",
    "sg:postcode":"97351",
    "sg:province":"OR",
    "sg:tags":[
        "maintenance"
    ],
    "wof:name":"Mykes Janitorial",
    "wof:placetype":"venue"
},
  "geometry": {"coordinates":[-123.184832,44.856556],"type":"Point"}
}