{
  "type": "Feature",
  "properties": {
    "iso:country":"US",
    "sg:address":"1720 Redwood Ave",
    "sg:city":"Grants Pass",
    "sg:classifiers":[
        {
            "category":"Retail",
            "subcategory":"Veterinary Services",
            "type":"Services"
        }
    ],
    "sg:phone":"+1 541 471 8687",
    "sg:postcode":"97527",
    "sg:province":"OR",
    "sg:tags":[
        "veterinarian"
    ],
    "wof:name":"Action Care Mobile Veterinary",
    "wof:placetype":"venue"
},
  "geometry": {"coordinates":[-123.363157,42.42236],"type":"Point"}
}