{
  "type": "Feature",
  "properties": {
    "iso:country":"US",
    "sg:address":"1128 SE 51st Ave",
    "sg:city":"Portland",
    "sg:classifiers":[
        {
            "category":"Building & Trades",
            "subcategory":"Landscaping Services",
            "type":"Services"
        }
    ],
    "sg:phone":"+1 503 226 7143",
    "sg:postcode":"97215",
    "sg:province":"OR",
    "sg:tags":[
        "tree"
    ],
    "wof:name":"Urban Forest Professionals",
    "wof:placetype":"venue"
},
  "geometry": {"coordinates":[-122.610241,45.515072],"type":"Point"}
}