{
  "type": "Feature",
  "properties": {
    "iso:country":"US",
    "sg:address":"13131 SE 125th Ave",
    "sg:city":"Clackamas",
    "sg:classifiers":[
        {
            "category":"Personal",
            "subcategory":"Skin Care",
            "type":"Services"
        }
    ],
    "sg:phone":"+1 503 320 1712",
    "sg:postcode":"97015",
    "sg:province":"OR",
    "wof:name":"Bliss Aesthetics",
    "wof:placetype":"venue"
},
  "geometry": {"coordinates":[-122.535201,45.42753],"type":"Point"}
}