{
  "type": "Feature",
  "properties": {
    "addr:full":"3036 NW Thistle Pl Corvallis OR 97330",
    "addr:housenumber":"3036",
    "addr:postcode":"97330",
    "addr:street":"Nw Thistle Pl",
    "iso:country":"US",
    "sg:address":"3036 NW Thistle Pl",
    "sg:city":"Corvallis",
    "sg:classifiers":[
        {
            "category":"Professional",
            "type":"Services"
        }
    ],
    "sg:phone":"+1 541 753 7632",
    "sg:postcode":"97330",
    "sg:province":"OR",
    "wof:name":"Ginavee Co Inc",
    "wof:placetype":"venue"
},
  "geometry": {"coordinates":[-123.294248,44.59624],"type":"Point"}
}