{
  "type": "Feature",
  "properties": {
    "addr:full":"121 SW 19th St Ontario OR 97914",
    "addr:housenumber":"121",
    "addr:postcode":"97914",
    "addr:street":"Sw 19Th St",
    "iso:country":"US",
    "sg:address":"121 SW 19th St",
    "sg:city":"Ontario",
    "sg:classifiers":[
        {
            "category":"Wholesale",
            "subcategory":"Beer",
            "type":"Manufacturing & Wholesale Goods"
        }
    ],
    "sg:phone":"+1 541 889 3535",
    "sg:postcode":"97914",
    "sg:province":"OR",
    "sg:tags":[
        "ale"
    ],
    "wof:name":"Echanis Distributing Co",
    "wof:placetype":"venue"
},
  "geometry": {"coordinates":[-116.992633,44.027071],"type":"Point"}
}