{
  "type": "Feature",
  "properties": {
    "iso:country":"US",
    "sg:address":"1829 SE Center St",
    "sg:city":"Portland",
    "sg:classifiers":[
        {
            "category":"Freight",
            "type":"Transportation"
        }
    ],
    "sg:phone":"+1 503 230 9017",
    "sg:postcode":"97202",
    "sg:province":"OR",
    "wof:name":"Container Express-Terminal Svc",
    "wof:placetype":"venue"
},
  "geometry": {"coordinates":[-122.647775,45.494053],"type":"Point"}
}