{
  "type": "Feature",
  "properties": {
    "iso:country":"US",
    "sg:address":"210 E California St",
    "sg:city":"Jacksonville",
    "sg:classifiers":[
        {
            "category":"Restaurant",
            "type":"Food & Drink"
        }
    ],
    "sg:phone":"+1 541 899 9965",
    "sg:postcode":"97530",
    "sg:province":"OR",
    "wof:name":"Las Palmas Mexican Restaurant",
    "wof:placetype":"venue"
},
  "geometry": {"coordinates":[-122.9662,42.313691],"type":"Point"}
}