{
  "type": "Feature",
  "properties": {
    "addr:full":"205 Fruitdale Dr Grants Pass OR 97527",
    "addr:housenumber":"205",
    "addr:postcode":"97527",
    "addr:street":"Fruitdale Dr",
    "iso:country":"US",
    "sg:address":"205 Fruitdale Dr",
    "sg:city":"Grants Pass",
    "sg:classifiers":[
        {
            "category":"Banks & Credit Unions",
            "subcategory":"Investment Brokerage",
            "type":"Services"
        }
    ],
    "sg:phone":"+1 541 471 3325",
    "sg:postcode":"97527",
    "sg:province":"OR",
    "sg:tags":[
        "security"
    ],
    "wof:name":"Darel Krutsinger",
    "wof:placetype":"venue"
},
  "geometry": {"coordinates":[-123.33148,42.423539],"type":"Point"}
}