{
  "type": "Feature",
  "properties": {
    "addr:full":"6906 SE Johnson Creek Blvd Portland OR 97206",
    "addr:housenumber":"6906",
    "addr:postcode":"97206",
    "addr:street":"Se Johnson Creek Blvd",
    "iso:country":"US",
    "sg:address":"6906 SE Johnson Creek Blvd",
    "sg:city":"Portland",
    "sg:classifiers":[
        {
            "category":"Manufacturing",
            "subcategory":"Metals",
            "type":"Manufacturing & Wholesale Goods"
        }
    ],
    "sg:phone":"+1 503 285 4950",
    "sg:postcode":"97206",
    "sg:province":"OR",
    "sg:tags":[
        "mfg",
        "trade",
        "architectural",
        "special",
        "contractor"
    ],
    "wof:name":"Argo Fencing",
    "wof:placetype":"venue"
},
  "geometry": {"coordinates":[-122.591802,45.455839],"type":"Point"}
}