{
  "type": "Feature",
  "properties": {
    "iso:country":"US",
    "sg:address":"1195 NW Wall St",
    "sg:city":"Bend",
    "sg:classifiers":[
        {
            "category":"Real Estate",
            "subcategory":"Real Estate Agent",
            "type":"Services"
        }
    ],
    "sg:phone":"+1 541 948 2977",
    "sg:postcode":"97701",
    "sg:province":"OR",
    "wof:name":"Clinton Park Realtor",
    "wof:placetype":"venue"
},
  "geometry": {"coordinates":[-121.311513,44.061356],"type":"Point"}
}