{
  "type": "Feature",
  "properties": {
    "iso:country":"US",
    "sg:address":"730 NE 16th Ave",
    "sg:city":"Canby",
    "sg:classifiers":[
        {
            "category":"Professional",
            "subcategory":"Accounting & Tax Preparation",
            "type":"Services"
        }
    ],
    "sg:phone":"+1 503 266 9378",
    "sg:postcode":"97013",
    "sg:province":"OR",
    "sg:tags":[
        "bookkeeping"
    ],
    "wof:name":"Full Perspective",
    "wof:placetype":"venue"
},
  "geometry": {"coordinates":[-122.686356,45.275341],"type":"Point"}
}