{
  "type": "Feature",
  "properties": {
    "addr:full":"2603 NE Cesar E Chavez Blvd Portland OR 97212",
    "addr:housenumber":"2603",
    "addr:postcode":"97212",
    "addr:street":"Ne Cesar E Chavez Blvd",
    "iso:country":"US",
    "sg:address":"2603 NE Cesar E Chavez Blvd",
    "sg:city":"Portland",
    "sg:classifiers":[
        {
            "category":"Shopping",
            "subcategory":"Stationery & Office Supplies",
            "type":"Retail Goods"
        },
        {
            "category":"Manufacturing",
            "subcategory":"Paper Products",
            "type":"Manufacturing & Wholesale Goods"
        }
    ],
    "sg:phone":"+1 503 287 9566",
    "sg:postcode":"97212",
    "sg:province":"OR",
    "sg:tags":[
        "stationery-wholesale",
        "store",
        "manufacturer"
    ],
    "wof:name":"Print Results Inc",
    "wof:placetype":"venue"
},
  "geometry": {"coordinates":[-122.622974,45.541353],"type":"Point"}
}