{
  "type": "Feature",
  "properties": {
    "iso:country":"US",
    "sg:address":"1115 SE Cass Ave",
    "sg:city":"Roseburg",
    "sg:classifiers":[
        {
            "category":"Insurance",
            "subcategory":"Life Insurance",
            "type":"Services"
        }
    ],
    "sg:phone":"+1 541 673 2113",
    "sg:postcode":"97470",
    "sg:province":"OR",
    "sg:tags":[
        "carrier"
    ],
    "wof:name":"National Assoc of Insuran",
    "wof:placetype":"venue"
},
  "geometry": {"coordinates":[-123.343214,43.207265],"type":"Point"}
}