{
  "type": "Feature",
  "properties": {
    "iso:country":"US",
    "sg:address":"1920 SE Mulberry Ave",
    "sg:city":"Portland",
    "sg:classifiers":[
        {
            "category":"Education",
            "subcategory":"School",
            "type":"Public Place"
        },
        {
            "category":"Personal",
            "subcategory":"Adult",
            "type":"Services"
        }
    ],
    "sg:phone":"+1 503 522 0938",
    "sg:postcode":"97214",
    "sg:province":"OR",
    "sg:tags":[
        "coaching-business"
    ],
    "sg:website":"http://www.ignitechangecoaching.com",
    "wof:name":"Ignite Change Coaching",
    "wof:placetype":"venue"
},
  "geometry": {"coordinates":[-122.65212200000001,45.509342],"type":"Point"}
}