{
  "type": "Feature",
  "properties": {
    "iso:country":"US",
    "sg:address":"SW 9th and Alder",
    "sg:city":"Portland",
    "sg:classifiers":[
        {
            "category":"Food Court",
            "type":"Food & Drink"
        },
        {
            "category":"Restaurant",
            "type":"Food & Drink"
        }
    ],
    "sg:phone":"+1 503 887 5935",
    "sg:postcode":"97205",
    "sg:province":"OR",
    "sg:tags":[
        "thai",
        "stand"
    ],
    "wof:name":"Wing Star Thai BBQ",
    "wof:placetype":"venue"
},
  "geometry": {"coordinates":[-122.680802,45.520412],"type":"Point"}
}