{
  "type": "Feature",
  "properties": {
    "addr:full":"1507 N Rosa Parks Way Portland OR 97217",
    "addr:housenumber":"1507",
    "addr:postcode":"97217",
    "addr:street":"N Rosa Parks Way",
    "iso:country":"US",
    "sg:address":"1507 N Rosa Parks Way",
    "sg:city":"Portland",
    "sg:classifiers":[
        {
            "category":"Food & Beverages",
            "subcategory":"Groceries & Convenience Stores",
            "type":"Retail Goods"
        }
    ],
    "sg:phone":"+1 503 286 9146",
    "sg:postcode":"97217",
    "sg:province":"OR",
    "wof:name":"Loftis Market",
    "wof:placetype":"venue"
},
  "geometry": {"coordinates":[-122.682311,45.570027],"type":"Point"}
}