{
  "type": "Feature",
  "properties": {
    "iso:country":"US",
    "sg:address":"9369 Redwood Hwy",
    "sg:city":"Wilderville",
    "sg:classifiers":[
        {
            "category":"Professional",
            "type":"Services"
        }
    ],
    "sg:phone":"+1 541 955 8510",
    "sg:postcode":"97543",
    "sg:province":"OR",
    "wof:name":"Piper Gardens",
    "wof:placetype":"venue"
},
  "geometry": {"coordinates":[-123.499585,42.375086],"type":"Point"}
}