{
  "type": "Feature",
  "properties": {
    "addr:full":"12256 SW Garden Pl Tigard OR 97223",
    "addr:housenumber":"12256",
    "addr:postcode":"97223",
    "addr:street":"Sw Garden Pl",
    "iso:country":"US",
    "sg:address":"12256 SW Garden Pl",
    "sg:city":"Tigard",
    "sg:classifiers":[
        {
            "category":"Organizations",
            "subcategory":"Non-profit Organization",
            "type":"Services"
        }
    ],
    "sg:phone":"+1 503 598 0522",
    "sg:postcode":"97223",
    "sg:province":"OR",
    "sg:website":"www.abcpnw.org",
    "wof:name":"Associated Builders & Cntrctrs",
    "wof:placetype":"venue"
},
  "geometry": {"coordinates":[-122.76177300000001,45.432459],"type":"Point"}
}