{
  "type": "Feature",
  "properties": {
    "addr:full":"1704 S Main St Lebanon OR 97355",
    "addr:housenumber":"1704",
    "addr:postcode":"97355",
    "addr:street":"S Main St",
    "iso:country":"US",
    "sg:address":"1704 S Main St",
    "sg:city":"Lebanon",
    "sg:classifiers":[
        {
            "category":"Restaurant",
            "type":"Food & Drink"
        }
    ],
    "sg:menulink":"http://www.allmenus.com/or/lebanon/78798-pizza-hut/menu/",
    "sg:phone":"+1 541 259 4888",
    "sg:postcode":"97355",
    "sg:province":"OR",
    "sg:tags":[
        "american",
        "pizza"
    ],
    "wof:name":"Pizza Hut",
    "wof:placetype":"venue"
},
  "geometry": {"coordinates":[-122.907101,44.530435],"type":"Point"}
}