{
  "type": "Feature",
  "properties": {
    "iso:country":"US",
    "sg:address":"2444 SE Hawthorne Blvd",
    "sg:city":"Portland",
    "sg:classifiers":[
        {
            "category":"Shopping",
            "subcategory":"Books",
            "type":"Retail Goods"
        }
    ],
    "sg:phone":"+1 503 231 7351",
    "sg:postcode":"97214",
    "sg:province":"OR",
    "sg:tags":[
        "rental",
        "game",
        "comic_strip",
        "video"
    ],
    "sg:website":"www.excaliburcomics.net",
    "wof:name":"Excalibur Books & Comics",
    "wof:placetype":"venue"
},
  "geometry": {"coordinates":[-122.64099899999999,45.511902],"type":"Point"}
}