{
  "type": "Feature",
  "properties": {
    "iso:country":"US",
    "sg:address":"17575 Maupin Rd",
    "sg:city":"Malin",
    "sg:phone":"+1 541 723 2202",
    "sg:postcode":"97632",
    "sg:province":"OR",
    "sg:tags":[
        "farm",
        "field",
        "beet",
        "crop"
    ],
    "wof:name":"David King",
    "wof:placetype":"venue"
},
  "geometry": {"coordinates":[-121.399125,42.064995],"type":"Point"}
}