{
  "type": "Feature",
  "properties": {
    "iso:country":"US",
    "sg:address":"1139 Missouri Flat Rd",
    "sg:city":"Grants Pass",
    "sg:classifiers":[
        {
            "category":"Farming",
            "subcategory":"Vineyard",
            "type":"Manufacturing & Wholesale Goods"
        }
    ],
    "sg:phone":"+1 541 846 9123",
    "sg:postcode":"97527",
    "sg:province":"OR",
    "sg:tags":[
        "grape"
    ],
    "wof:name":"Appleation Applegate Vineyard",
    "wof:placetype":"venue"
},
  "geometry": {"coordinates":[-123.234268,42.325599],"type":"Point"}
}