{
  "type": "Feature",
  "properties": {
    "addr:full":"218 NW Lewisburg Ave Corvallis OR 97330",
    "addr:housenumber":"218",
    "addr:postcode":"97330",
    "addr:street":"Nw Lewisburg Ave",
    "iso:country":"US",
    "sg:address":"218 NW Lewisburg Ave",
    "sg:city":"Corvallis",
    "sg:classifiers":[
        {
            "category":"Building & Trades",
            "subcategory":"Construction",
            "type":"Services"
        }
    ],
    "sg:phone":"+1 541 929 4067",
    "sg:postcode":"97330",
    "sg:province":"OR",
    "sg:tags":[
        "house"
    ],
    "wof:name":"Smithcraft Structures",
    "wof:placetype":"venue"
},
  "geometry": {"coordinates":[-123.24523000000001,44.62892],"type":"Point"}
}