{
  "type": "Feature",
  "properties": {
    "iso:country":"US",
    "sg:address":"2204 Simpson St SE",
    "sg:city":"Salem",
    "sg:classifiers":[
        {
            "category":"Home & Garden",
            "subcategory":"Building Materials",
            "type":"Retail Goods"
        }
    ],
    "sg:phone":"+1 503 364 5274",
    "sg:postcode":"97301",
    "sg:province":"OR",
    "sg:tags":[
        "equipment",
        "supply",
        "roofing"
    ],
    "sg:website":"http://www.bruceanddana.com",
    "wof:name":"Bruce & Dana Inc",
    "wof:placetype":"venue"
},
  "geometry": {"coordinates":[-123.017793,44.928853],"type":"Point"}
}