{
  "type": "Feature",
  "properties": {
    "addr:full":"71870 US Hwy 97 Wasco OR 97065",
    "addr:postcode":"71870;97065",
    "addr:street":"Us Hwy 97",
    "iso:country":"US",
    "sg:address":"71870 US Hwy 97",
    "sg:city":"Wasco",
    "sg:classifiers":[
        {
            "category":"Wholesale",
            "subcategory":"Non-durable Goods",
            "type":"Manufacturing & Wholesale Goods"
        }
    ],
    "sg:phone":"+1 541 442 5554",
    "sg:postcode":"97065",
    "sg:province":"OR",
    "wof:name":"Moore Bros Shop",
    "wof:placetype":"venue"
},
  "geometry": {"coordinates":[-120.690787,45.556694],"type":"Point"}
}