{
  "type": "Feature",
  "properties": {
    "iso:country":"US",
    "sg:address":"36 S Central Ave",
    "sg:city":"Medford",
    "sg:classifiers":[
        {
            "category":"Organizations",
            "subcategory":"Non-profit Organization",
            "type":"Services"
        }
    ],
    "sg:phone":"+1 541 773 4848",
    "sg:postcode":"97501",
    "sg:province":"OR",
    "sg:tags":[
        "information",
        "alcoholism",
        "treatment"
    ],
    "wof:name":"Alcoholics Anonymous",
    "wof:placetype":"venue"
},
  "geometry": {"coordinates":[-122.871707,42.325968],"type":"Point"}
}