{
  "type": "Feature",
  "properties": {
    "addr:full":"800 Viewcrest Dr Eagle Point OR 97524",
    "addr:housenumber":"800",
    "addr:postcode":"97524",
    "addr:street":"Viewcrest Dr",
    "iso:country":"US",
    "sg:address":"800 Viewcrest Dr",
    "sg:city":"Eagle Point",
    "sg:classifiers":[
        {
            "category":"Professional",
            "subcategory":"Business Services",
            "type":"Services"
        }
    ],
    "sg:phone":"+1 541 826 5589",
    "sg:postcode":"97524",
    "sg:province":"OR",
    "wof:name":"Dean Belknap Enterprises",
    "wof:placetype":"venue"
},
  "geometry": {"coordinates":[-122.788404,42.454029],"type":"Point"}
}