{
  "type": "Feature",
  "properties": {
    "iso:country":"US",
    "sg:address":"3228 SE 52nd Ave",
    "sg:city":"Portland",
    "sg:classifiers":[
        {
            "category":"Recreation",
            "type":"Entertainment"
        }
    ],
    "sg:phone":"+1 503 788 8777",
    "sg:postcode":"97206",
    "sg:province":"OR",
    "wof:name":"Driving Professionals",
    "wof:placetype":"venue"
},
  "geometry": {"coordinates":[-122.608958,45.499799],"type":"Point"}
}