{
  "type": "Feature",
  "properties": {
    "addr:full":"3644 Goldstone Ct NE Salem OR 97305",
    "addr:housenumber":"3644",
    "addr:postcode":"97305",
    "addr:street":"Goldstone Ct Ne",
    "iso:country":"US",
    "sg:address":"3644 Goldstone Ct NE",
    "sg:city":"Salem",
    "sg:classifiers":[
        {
            "category":"Food & Beverages",
            "subcategory":"Specialty",
            "type":"Retail Goods"
        },
        {
            "category":"Professional",
            "subcategory":"Management & Consulting",
            "type":"Services"
        }
    ],
    "sg:phone":"+1 503 399 9626",
    "sg:postcode":"97305",
    "sg:province":"OR",
    "sg:tags":[
        "home",
        "demonstration",
        "health",
        "store",
        "dietetic"
    ],
    "wof:name":"Amway Products Distributors",
    "wof:placetype":"venue"
},
  "geometry": {"coordinates":[-122.962625,44.97098],"type":"Point"}
}