{
  "type": "Feature",
  "properties": {
    "addr:full":"525 SE Pine St Portland OR 97214",
    "addr:housenumber":"525",
    "addr:postcode":"97214",
    "addr:street":"Se Pine St",
    "iso:country":"US",
    "sg:address":"525 SE Pine St",
    "sg:city":"Portland",
    "sg:classifiers":[
        {
            "category":"Manufacturing",
            "subcategory":"Wood Products",
            "type":"Manufacturing & Wholesale Goods"
        }
    ],
    "sg:phone":"+1 503 239 8950",
    "sg:postcode":"97214",
    "sg:province":"OR",
    "sg:tags":[
        "mfg"
    ],
    "wof:name":"Woodcarver",
    "wof:placetype":"venue"
},
  "geometry": {"coordinates":[-122.659881,45.520865],"type":"Point"}
}