{
  "type": "Feature",
  "properties": {
    "addr:full":"721 6th St Umatilla OR 97882",
    "addr:housenumber":"721",
    "addr:postcode":"97882",
    "addr:street":"6Th St",
    "iso:country":"US",
    "sg:address":"721 6th St",
    "sg:city":"Umatilla",
    "sg:classifiers":[
        {
            "category":"Home & Garden",
            "subcategory":"Home Furnishings",
            "type":"Retail Goods"
        },
        {
            "category":"Home & Garden",
            "subcategory":"Building Materials",
            "type":"Retail Goods"
        },
        {
            "category":"Manufacturing",
            "subcategory":"Glass & Minerals",
            "type":"Manufacturing & Wholesale Goods"
        },
        {
            "category":"Retail",
            "subcategory":"Auto Repair",
            "type":"Services"
        }
    ],
    "sg:phone":"+1 541 922 3523",
    "sg:postcode":"97882",
    "sg:province":"OR",
    "sg:tags":[
        "plate",
        "glass-auto",
        "window",
        "mirror",
        "windshield"
    ],
    "wof:name":"A Burk & Co Glass",
    "wof:placetype":"venue"
},
  "geometry": {"coordinates":[-119.344711,45.917181],"type":"Point"}
}