{
  "type": "Feature",
  "properties": {
    "iso:country":"US",
    "sg:address":"827 Alder Creek Dr Ste B",
    "sg:city":"Medford",
    "sg:classifiers":[
        {
            "category":"Banks & Credit Unions",
            "subcategory":"Investment Brokerage",
            "type":"Services"
        },
        {
            "category":"Banks & Credit Unions",
            "subcategory":"Bank",
            "type":"Services"
        },
        {
            "category":"Banks & Credit Unions",
            "subcategory":"Financial Services",
            "type":"Services"
        }
    ],
    "sg:phone":"+1 541 857 8551",
    "sg:postcode":"97504",
    "sg:province":"OR",
    "sg:tags":[
        "advisory",
        "management",
        "broker",
        "planner",
        "bond",
        "stock"
    ],
    "sg:website":"http://www.cic-llc.com",
    "wof:name":"Cascade Investment Counsel",
    "wof:placetype":"venue"
},
  "geometry": {"coordinates":[-122.819481,42.316349],"type":"Point"}
}