{
  "type": "Feature",
  "properties": {
    "addr:full":"158 NE Greenwood Ave Ste 1 Bend OR 97701",
    "addr:housenumber":"158",
    "addr:postcode":"97701",
    "addr:street":"Ne Greenwood Ave Ste 1",
    "iso:country":"US",
    "sg:address":"158 NE Greenwood Ave Ste 1",
    "sg:city":"Bend",
    "sg:classifiers":[
        {
            "category":"Professional",
            "subcategory":"Lawyer & Legal Services",
            "type":"Services"
        }
    ],
    "sg:phone":"+1 541 318 9115",
    "sg:postcode":"97701",
    "sg:province":"OR",
    "sg:tags":[
        "attorney",
        "family",
        "estate",
        "divorce",
        "planning",
        "law"
    ],
    "sg:website":"http://bend.citysearch.com/profile/external/624569150/bend_or/stahancyk_kent_hook_p_c_.html?publisher=yellowpages&reference_id=1&placement=ypwebsitemip",
    "wof:name":"Stahancyk, Kent & Hook P.C.",
    "wof:placetype":"venue"
},
  "geometry": {"coordinates":[-121.30460100000001,44.059959],"type":"Point"}
}