{
  "type": "Feature",
  "properties": {
    "iso:country":"US",
    "sg:address":"1390 N Pacific Hwy",
    "sg:city":"Woodburn",
    "sg:classifiers":[
        {
            "category":"Restaurant",
            "type":"Food & Drink"
        }
    ],
    "sg:phone":"+1 503 982 2487",
    "sg:postcode":"97071",
    "sg:province":"OR",
    "sg:tags":[
        "eating"
    ],
    "wof:name":"Chu's Eatery",
    "wof:placetype":"venue"
},
  "geometry": {"coordinates":[-122.83389,45.147938],"type":"Point"}
}