{
  "type": "Feature",
  "properties": {
    "addr:full":"657 SW Bay Blvd Newport OR 97365",
    "addr:housenumber":"657",
    "addr:postcode":"97365",
    "addr:street":"Sw Bay Blvd",
    "iso:country":"US",
    "sg:address":"657 SW Bay Blvd",
    "sg:city":"Newport",
    "sg:classifiers":[
        {
            "category":"Restaurant",
            "type":"Food & Drink"
        }
    ],
    "sg:phone":"+1 541 265 7512",
    "sg:postcode":"97365",
    "sg:province":"OR",
    "sg:website":"http://www.moschowder.com",
    "wof:name":"Mo's Annex",
    "wof:placetype":"venue"
},
  "geometry": {"coordinates":[-124.054697,44.629153],"type":"Point"}
}