{
  "type": "Feature",
  "properties": {
    "addr:full":"416 NW 11th Ave Portland OR 97209",
    "addr:housenumber":"416",
    "addr:postcode":"97209",
    "addr:street":"Nw 11Th Ave",
    "iso:country":"US",
    "sg:address":"416 NW 11th Ave",
    "sg:city":"Portland",
    "sg:classifiers":[
        {
            "category":"Home & Garden",
            "subcategory":"Carpets & Floor Coverings",
            "type":"Retail Goods"
        }
    ],
    "sg:phone":"+1 503 223 6400",
    "sg:postcode":"97209",
    "sg:province":"OR",
    "sg:tags":[
        "house",
        "oriental",
        "furnishing",
        "rug"
    ],
    "wof:name":"Tribal Loom And Design",
    "wof:placetype":"venue"
},
  "geometry": {"coordinates":[-122.682225,45.525938],"type":"Point"}
}