{
  "type": "Feature",
  "properties": {
    "addr:full":"12505 SW Broadway St Beaverton OR 97005",
    "addr:housenumber":"12505",
    "addr:postcode":"97005",
    "addr:street":"Sw Broadway St",
    "iso:country":"US",
    "sg:address":"12505 SW Broadway St",
    "sg:city":"Beaverton",
    "sg:classifiers":[
        {
            "category":"Retail",
            "subcategory":"Auto Repair",
            "type":"Services"
        }
    ],
    "sg:phone":"+1 503 526 2126",
    "sg:postcode":"97005",
    "sg:province":"OR",
    "sg:tags":[
        "body",
        "shop"
    ],
    "wof:name":"Canyon Road Auto Body",
    "wof:placetype":"venue"
},
  "geometry": {"coordinates":[-122.805319,45.487722],"type":"Point"}
}