{
  "type": "Feature",
  "properties": {
    "iso:country":"US",
    "sg:address":"Browns Ferry Park P.O. Box 3546",
    "sg:city":"Tualatin",
    "sg:classifiers":[
        {
            "category":"Arts & Performance",
            "subcategory":"Arts Center",
            "type":"Entertainment"
        },
        {
            "category":"Education",
            "subcategory":"School",
            "type":"Public Place"
        }
    ],
    "sg:phone":"+1 503 691 6132",
    "sg:postcode":"97062",
    "sg:province":"OR",
    "sg:tags":[
        "performing"
    ],
    "sg:website":"www.willowbrookartscamp.org/inde...",
    "wof:name":"Willowbrook Arts Camp",
    "wof:placetype":"venue"
},
  "geometry": {"coordinates":[-122.73665099999999,45.383372],"type":"Point"}
}