{
  "type": "Feature",
  "properties": {
    "addr:full":"88894 Rhododendron Ln Bandon OR 97439",
    "addr:postcode":"88894;97439",
    "addr:street":"Rhododendron Ln",
    "iso:country":"US",
    "sg:address":"88894 Rhododendron Ln",
    "sg:city":"Bandon",
    "sg:classifiers":[
        {
            "category":"Home & Garden",
            "subcategory":"Building Materials",
            "type":"Retail Goods"
        }
    ],
    "sg:phone":"+1 541 347 3569",
    "sg:postcode":"97439",
    "sg:province":"OR",
    "sg:tags":[
        "door"
    ],
    "wof:name":"Garage Door Svc",
    "wof:placetype":"venue"
},
  "geometry": {"coordinates":[-124.071253,44.047476],"type":"Point"}
}