{
  "type": "Feature",
  "properties": {
    "addr:full":"8000 SW Capitol Hill Rd Portland OR 97219",
    "addr:housenumber":"8000",
    "addr:postcode":"97219",
    "addr:street":"Sw Capitol Hill Rd",
    "iso:country":"US",
    "sg:address":"8000 SW Capitol Hill Rd",
    "sg:city":"Portland",
    "sg:classifiers":[
        {
            "category":"Wholesale",
            "subcategory":"Machinery & Supplies",
            "type":"Manufacturing & Wholesale Goods"
        }
    ],
    "sg:phone":"+1 503 244 8711",
    "sg:postcode":"97219",
    "sg:province":"OR",
    "sg:tags":[
        "equipment",
        "irrigation",
        "system"
    ],
    "wof:name":"Classic Irrigation",
    "wof:placetype":"venue"
},
  "geometry": {"coordinates":[-122.69989,45.466419],"type":"Point"}
}