{
  "type": "Feature",
  "properties": {
    "iso:country":"US",
    "sg:address":"21929 NE Halsey St",
    "sg:city":"Fairview",
    "sg:classifiers":[
        {
            "category":"Freight",
            "type":"Transportation"
        }
    ],
    "sg:phone":"+1 503 661 4231",
    "sg:postcode":"97024",
    "sg:province":"OR",
    "sg:tags":[
        "operator",
        "local",
        "trucking"
    ],
    "wof:name":"H Marvel Trucking Co",
    "wof:placetype":"venue"
},
  "geometry": {"coordinates":[-122.436728,45.534466],"type":"Point"}
}