{
  "type": "Feature",
  "properties": {
    "addr:full":"1095 Commercial St SE Salem OR 97302",
    "addr:housenumber":"1095",
    "addr:postcode":"97302",
    "addr:street":"Commercial St Se",
    "iso:country":"US",
    "sg:address":"1095 Commercial St SE",
    "sg:city":"Salem",
    "sg:classifiers":[
        {
            "category":"Retail",
            "subcategory":"Auto Rental",
            "type":"Services"
        }
    ],
    "sg:phone":"+1 503 378 0849",
    "sg:postcode":"97302",
    "sg:province":"OR",
    "sg:tags":[
        "renting",
        "automobile"
    ],
    "wof:name":"Key Car Rentals Inc",
    "wof:placetype":"venue"
},
  "geometry": {"coordinates":[-123.044113,44.931193],"type":"Point"}
}