{
  "type": "Feature",
  "properties": {
    "addr:full":"3128 Ellen Ct NW Salem OR 97304",
    "addr:housenumber":"3128",
    "addr:postcode":"97304",
    "addr:street":"Ellen Ct Nw",
    "iso:country":"US",
    "sg:address":"3128 Ellen Ct NW",
    "sg:city":"Salem",
    "sg:classifiers":[
        {
            "category":"Banks & Credit Unions",
            "subcategory":"Bank",
            "type":"Services"
        }
    ],
    "sg:phone":"+1 503 999 5803",
    "sg:postcode":"97304",
    "sg:province":"OR",
    "sg:website":"http://www.pac-trade.com",
    "wof:name":"Pacific Trading Group",
    "wof:placetype":"venue"
},
  "geometry": {"coordinates":[-123.083333,44.979495],"type":"Point"}
}