{
  "type": "Feature",
  "properties": {
    "addr:full":"485 S 7th St Independence OR 97351",
    "addr:housenumber":"485",
    "addr:postcode":"97351",
    "addr:street":"S 7Th St",
    "iso:country":"US",
    "sg:address":"485 S 7th St",
    "sg:city":"Independence",
    "sg:classifiers":[
        {
            "category":"Place Of Worship",
            "subcategory":"Church",
            "type":"Public Place"
        },
        {
            "category":"Place Of Worship",
            "type":"Public Place"
        }
    ],
    "sg:phone":"+1 503 838 3293",
    "sg:postcode":"97351",
    "sg:province":"OR",
    "sg:tags":[
        "churches-non-denominational"
    ],
    "wof:name":"Church Our Lord Jesus Christ",
    "wof:placetype":"venue"
},
  "geometry": {"coordinates":[-123.19358099999999,44.84945],"type":"Point"}
}