{
  "type": "Feature",
  "properties": {
    "addr:full":"9500 SW Barbur Blvd Portland OR 97219",
    "addr:housenumber":"9500",
    "addr:postcode":"97219",
    "addr:street":"Sw Barbur Blvd",
    "iso:country":"US",
    "sg:address":"9500 SW Barbur Blvd",
    "sg:city":"Portland",
    "sg:classifiers":[
        {
            "category":"Real Estate",
            "subcategory":"Real Estate Services",
            "type":"Services"
        }
    ],
    "sg:phone":"+1 503 245 1255",
    "sg:postcode":"97219",
    "sg:province":"OR",
    "sg:tags":[
        "vacancy",
        "rental",
        "listing"
    ],
    "wof:name":"C.T.L. Management, Inc.",
    "wof:placetype":"venue"
},
  "geometry": {"coordinates":[-122.713808,45.456489],"type":"Point"}
}