{
  "type": "Feature",
  "properties": {
    "iso:country":"US",
    "sg:address":"24623 Old Peak Rd",
    "sg:city":"Philomath",
    "sg:classifiers":[
        {
            "category":"Professional",
            "subcategory":"Engineering",
            "type":"Services"
        }
    ],
    "sg:phone":"+1 541 929 4132",
    "sg:postcode":"97370",
    "sg:province":"OR",
    "sg:tags":[
        "consulting",
        "engineer"
    ],
    "wof:name":"William A Pendergrass PE",
    "wof:placetype":"venue"
},
  "geometry": {"coordinates":[-123.394899,44.536907],"type":"Point"}
}