{
  "type": "Feature",
  "properties": {
    "iso:country":"US",
    "sg:address":"12400 State Hwy 212",
    "sg:city":"Clackamas",
    "sg:classifiers":[
        {
            "category":"Professional",
            "type":"Services"
        }
    ],
    "sg:phone":"+1 503 655 0908",
    "sg:postcode":"97015",
    "sg:province":"OR",
    "sg:tags":[
        "establishment"
    ],
    "wof:name":"Fred C Gloeckner Co",
    "wof:placetype":"venue"
},
  "geometry": {"coordinates":[-122.53148400000001,45.408812],"type":"Point"}
}