{
  "type": "Feature",
  "properties": {
    "addr:full":"3222 Honeysuckle Way NE Salem OR 97303",
    "addr:housenumber":"3222",
    "addr:postcode":"97303",
    "addr:street":"Honeysuckle Way Ne",
    "iso:country":"US",
    "sg:address":"3222 Honeysuckle Way NE",
    "sg:city":"Salem",
    "sg:classifiers":[
        {
            "category":"Home & Garden",
            "subcategory":"Home Furnishings",
            "type":"Retail Goods"
        }
    ],
    "sg:phone":"+1 503 364 6309",
    "sg:postcode":"97303",
    "sg:province":"OR",
    "wof:name":"Drapery Doctor The",
    "wof:placetype":"venue"
},
  "geometry": {"coordinates":[-122.995386,44.975147],"type":"Point"}
}