{
  "type": "Feature",
  "properties": {
    "iso:country":"US",
    "sg:address":"510 Guthrie St",
    "sg:city":"Ashland",
    "sg:classifiers":[
        {
            "category":"Professional",
            "subcategory":"Business Services",
            "type":"Services"
        }
    ],
    "sg:phone":"+1 541 201 0525",
    "sg:postcode":"97520",
    "sg:province":"OR",
    "wof:name":"Guthrie Group Inc",
    "wof:placetype":"venue"
},
  "geometry": {"coordinates":[-122.710482,42.18608],"type":"Point"}
}