{
  "type": "Feature",
  "properties": {
    "iso:country":"US",
    "sg:address":"1263 N Riverside Ave",
    "sg:city":"Medford",
    "sg:classifiers":[
        {
            "category":"Personal",
            "subcategory":"Beauty Salon",
            "type":"Services"
        }
    ],
    "sg:phone":"+1 541 774 9397",
    "sg:postcode":"97501",
    "sg:province":"OR",
    "wof:name":"Elite Nails",
    "wof:placetype":"venue"
},
  "geometry": {"coordinates":[-122.876386,42.33852],"type":"Point"}
}