{
  "type": "Feature",
  "properties": {
    "iso:country":"US",
    "sg:address":"829 Chehalis Pl N",
    "sg:city":"Salem",
    "sg:classifiers":[
        {
            "category":"Building & Trades",
            "subcategory":"Construction",
            "type":"Services"
        }
    ],
    "sg:phone":"+1 503 463 8292",
    "sg:postcode":"97303",
    "sg:province":"OR",
    "sg:tags":[
        "house"
    ],
    "wof:name":"Rock Solid",
    "wof:placetype":"venue"
},
  "geometry": {"coordinates":[-123.037654,45.003304],"type":"Point"}
}