{
  "type": "Feature",
  "properties": {
    "iso:country":"US",
    "sg:address":"16396 SE 232nd Dr",
    "sg:city":"Boring",
    "sg:phone":"+1 503 658 6288",
    "sg:postcode":"97089",
    "sg:province":"OR",
    "sg:tags":[
        "farm",
        "field",
        "crop"
    ],
    "wof:name":"Green Fields Farm",
    "wof:placetype":"venue"
},
  "geometry": {"coordinates":[-122.419656,45.398802],"type":"Point"}
}