{
  "type": "Feature",
  "properties": {
    "iso:country":"US",
    "sg:address":"5543 Riverbanks Rd",
    "sg:city":"Grants Pass",
    "sg:classifiers":[
        {
            "category":"Building & Trades",
            "subcategory":"Construction",
            "type":"Services"
        }
    ],
    "sg:phone":"+1 541 474 2444",
    "sg:postcode":"97527",
    "sg:province":"OR",
    "sg:tags":[
        "contractor"
    ],
    "wof:name":"Norm Lee",
    "wof:placetype":"venue"
},
  "geometry": {"coordinates":[-123.500953,42.45293],"type":"Point"}
}