{
  "type": "Feature",
  "properties": {
    "iso:country":"US",
    "sg:address":"8000 NE Tillamook St",
    "sg:city":"Portland",
    "sg:classifiers":[
        {
            "category":"Education",
            "subcategory":"School",
            "type":"Public Place"
        }
    ],
    "sg:phone":"+1 503 916 5747",
    "sg:postcode":"97213",
    "sg:province":"OR",
    "wof:name":"Schools Public",
    "wof:placetype":"venue"
},
  "geometry": {"coordinates":[-122.58000699999999,45.536464],"type":"Point"}
}