{
  "type": "Feature",
  "properties": {
    "addr:full":"2308 Lloyd Center Portland OR 97232",
    "addr:housenumber":"2308",
    "addr:postcode":"97232",
    "addr:street":"Lloyd",
    "iso:country":"US",
    "sg:address":"2308 Lloyd Center",
    "sg:city":"Portland",
    "sg:classifiers":[
        {
            "category":"Restaurant",
            "type":"Food & Drink"
        }
    ],
    "sg:phone":"+1 503 335 0111",
    "sg:postcode":"97232",
    "sg:province":"OR",
    "sg:tags":[
        "fusion",
        "asian"
    ],
    "sg:website":"www.dumplingsandtea.com",
    "wof:name":"Steamers Asian Street Bistro",
    "wof:placetype":"venue"
},
  "geometry": {"coordinates":[-122.652074,45.531907],"type":"Point"}
}