{
  "type": "Feature",
  "properties": {
    "iso:country":"US",
    "sg:address":"142 N Ivy St",
    "sg:city":"Medford",
    "sg:classifiers":[
        {
            "category":"Wholesale",
            "subcategory":"Motor Vehicles",
            "type":"Manufacturing & Wholesale Goods"
        }
    ],
    "sg:phone":"+1 541 665 3201",
    "sg:postcode":"97501",
    "sg:province":"OR",
    "sg:tags":[
        "automobile",
        "truck",
        "broker"
    ],
    "wof:name":"Santom Trucking",
    "wof:placetype":"venue"
},
  "geometry": {"coordinates":[-122.878033,42.325497],"type":"Point"}
}