{
  "type": "Feature",
  "properties": {
    "iso:country":"US",
    "sg:address":"4019 SW 55th Dr",
    "sg:city":"Portland",
    "sg:classifiers":[
        {
            "category":"Professional",
            "subcategory":"Engineering",
            "type":"Services"
        }
    ],
    "sg:phone":"+1 503 297 7474",
    "sg:postcode":"97221",
    "sg:province":"OR",
    "wof:name":"Millwee Associates Inc",
    "wof:placetype":"venue"
},
  "geometry": {"coordinates":[-122.734418,45.493044],"type":"Point"}
}