{
  "type": "Feature",
  "properties": {
    "addr:full":"2790 Munsel Lake Rd Florence OR 97439",
    "addr:housenumber":"2790",
    "addr:postcode":"97439",
    "addr:street":"Munsel Lake Rd",
    "iso:country":"US",
    "sg:address":"2790 Munsel Lake Rd",
    "sg:city":"Florence",
    "sg:classifiers":[
        {
            "category":"Building & Trades",
            "subcategory":"Construction",
            "type":"Services"
        }
    ],
    "sg:phone":"+1 541 997 6490",
    "sg:postcode":"97439",
    "sg:province":"OR",
    "sg:tags":[
        "contractor"
    ],
    "wof:name":"Sea Storm Construction Co",
    "wof:placetype":"venue"
},
  "geometry": {"coordinates":[-124.083004,43.990588],"type":"Point"}
}