{
  "type": "Feature",
  "properties": {
    "iso:country":"US",
    "sg:address":"3725 Pleasant View Dr NE",
    "sg:city":"Keizer",
    "sg:classifiers":[
        {
            "category":"Shopping",
            "subcategory":"Used Merchandise",
            "type":"Retail Goods"
        }
    ],
    "sg:phone":"+1 503 390 0413",
    "sg:postcode":"97303",
    "sg:province":"OR",
    "sg:tags":[
        "second",
        "store",
        "hand"
    ],
    "wof:name":"Garage Sale Liquidators",
    "wof:placetype":"venue"
},
  "geometry": {"coordinates":[-123.01202000000001,44.98103],"type":"Point"}
}