{
  "type": "Feature",
  "properties": {
    "iso:country":"US",
    "sg:address":"61544 Newberry Dr",
    "sg:city":"Bend",
    "sg:classifiers":[
        {
            "category":"Building & Trades",
            "subcategory":"Construction",
            "type":"Services"
        }
    ],
    "sg:phone":"+1 541 389 5047",
    "sg:postcode":"97702",
    "sg:province":"OR",
    "sg:tags":[
        "hanging",
        "contractor"
    ],
    "wof:name":"Lone Peak Painting",
    "wof:placetype":"venue"
},
  "geometry": {"coordinates":[-121.281236,44.035732],"type":"Point"}
}