{
  "type": "Feature",
  "properties": {
    "iso:country":"US",
    "sg:address":"10151 SW Barbur Blvd",
    "sg:city":"Portland",
    "sg:classifiers":[
        {
            "category":"Professional",
            "subcategory":"Detective & Security Services",
            "type":"Services"
        }
    ],
    "sg:phone":"+1 503 892 3531",
    "sg:postcode":"97219",
    "sg:province":"OR",
    "sg:tags":[
        "investigator"
    ],
    "wof:name":"Associated Legal Investigators",
    "wof:placetype":"venue"
},
  "geometry": {"coordinates":[-122.725128,45.452102],"type":"Point"}
}