{
  "type": "Feature",
  "properties": {
    "addr:full":"2700 NE 82nd Ave Portland OR 97220",
    "addr:housenumber":"2700",
    "addr:postcode":"97220",
    "addr:street":"Ne 82Nd Ave",
    "iso:country":"US",
    "sg:address":"2700 NE 82nd Ave",
    "sg:city":"Portland",
    "sg:classifiers":[
        {
            "category":"Bars & Pubs",
            "subcategory":"Nightclub",
            "type":"Food & Drink"
        },
        {
            "category":"Sports & Exercise",
            "subcategory":"Bowling",
            "type":"Entertainment"
        }
    ],
    "sg:phone":"+1 503 255 2635",
    "sg:postcode":"97220",
    "sg:province":"OR",
    "sg:tags":[
        "nightlife"
    ],
    "wof:name":"AMF Cascade Lanes",
    "wof:placetype":"venue"
},
  "geometry": {"coordinates":[-122.579002,45.541801],"type":"Point"}
}