{
  "type": "Feature",
  "properties": {
    "iso:country":"US",
    "sg:address":"7488 Oak Knoll Rd NE",
    "sg:city":"Silverton",
    "sg:classifiers":[
        {
            "category":"Autos & Motor Vehicles",
            "subcategory":"Fuel & Gas Station",
            "type":"Retail Goods"
        }
    ],
    "sg:phone":"+1 503 873 5620",
    "sg:postcode":"97381",
    "sg:province":"OR",
    "sg:tags":[
        "station",
        "gasoline"
    ],
    "wof:name":"Conocophillips Company",
    "wof:placetype":"venue"
},
  "geometry": {"coordinates":[-122.727077,45.030912],"type":"Point"}
}