{
  "type": "Feature",
  "properties": {
    "iso:country":"US",
    "sg:address":"25261 State Hwy 170",
    "sg:city":"Canby",
    "sg:classifiers":[
        {
            "category":"Professional",
            "subcategory":"Lawyer & Legal Services",
            "type":"Services"
        }
    ],
    "sg:phone":"+1 503 263 8420",
    "sg:postcode":"97013",
    "sg:province":"OR",
    "sg:tags":[
        "attorney"
    ],
    "wof:name":"Alan Gallagher",
    "wof:placetype":"venue"
},
  "geometry": {"coordinates":[-122.68637099999999,45.240197],"type":"Point"}
}