{
  "type": "Feature",
  "properties": {
    "addr:full":"9935 SW Johnson St Portland OR 97223",
    "addr:housenumber":"9935",
    "addr:postcode":"97223",
    "addr:street":"Sw Johnson St",
    "iso:country":"US",
    "sg:address":"9935 SW Johnson St",
    "sg:city":"Portland",
    "sg:classifiers":[
        {
            "category":"Retail",
            "subcategory":"Repair Shop",
            "type":"Services"
        }
    ],
    "sg:phone":"+1 503 684 5201",
    "sg:postcode":"97223",
    "sg:province":"OR",
    "wof:name":"Borsch Electronics",
    "wof:placetype":"venue"
},
  "geometry": {"coordinates":[-122.778488,45.430201],"type":"Point"}
}