{
  "type": "Feature",
  "properties": {
    "addr:full":"2201 Spring St Medford OR 97504",
    "addr:housenumber":"2201",
    "addr:postcode":"97504",
    "addr:street":"Spring St",
    "iso:country":"US",
    "sg:address":"2201 Spring St",
    "sg:city":"Medford",
    "sg:classifiers":[
        {
            "category":"Building & Trades",
            "subcategory":"Construction",
            "type":"Services"
        }
    ],
    "sg:phone":"+1 541 774 9341",
    "sg:postcode":"97504",
    "sg:province":"OR",
    "sg:tags":[
        "siding",
        "contractor"
    ],
    "wof:name":"Jeff A Ludwick",
    "wof:placetype":"venue"
},
  "geometry": {"coordinates":[-122.83636199999999,42.338244],"type":"Point"}
}