{
  "type": "Feature",
  "properties": {
    "addr:full":"930 N 1st St Silverton OR 97381",
    "addr:housenumber":"930",
    "addr:postcode":"97381",
    "addr:street":"N 1St St",
    "iso:country":"US",
    "sg:address":"930 N 1st St",
    "sg:city":"Silverton",
    "sg:classifiers":[
        {
            "category":"Autos & Motor Vehicles",
            "subcategory":"Fuel & Gas Station",
            "type":"Retail Goods"
        }
    ],
    "sg:phone":"+1 503 873 8012",
    "sg:postcode":"97381",
    "sg:province":"OR",
    "sg:tags":[
        "oil"
    ],
    "wof:name":"Roth's Service Station",
    "wof:placetype":"venue"
},
  "geometry": {"coordinates":[-122.78526100000001,45.013128],"type":"Point"}
}