{
  "type": "Feature",
  "properties": {
    "addr:full":"4268 Albert Cir Lake Oswego OR 97035",
    "addr:housenumber":"4268",
    "addr:postcode":"97035",
    "addr:street":"Albert Cir",
    "iso:country":"US",
    "sg:address":"4268 Albert Cir",
    "sg:city":"Lake Oswego",
    "sg:classifiers":[
        {
            "category":"Professional",
            "subcategory":"Management & Consulting",
            "type":"Services"
        }
    ],
    "sg:phone":"+1 503 977 1022",
    "sg:postcode":"97035",
    "sg:province":"OR",
    "wof:name":"Aptech Inc",
    "wof:placetype":"venue"
},
  "geometry": {"coordinates":[-122.721351,45.391565],"type":"Point"}
}