{
  "type": "Feature",
  "properties": {
    "iso:country":"US",
    "sg:address":"1837 SE Spokane St",
    "sg:city":"Portland",
    "sg:classifiers":[
        {
            "category":"Retail",
            "subcategory":"Portrait Studio",
            "type":"Services"
        }
    ],
    "sg:phone":"+1 503 233 5243",
    "sg:postcode":"97202",
    "sg:province":"OR",
    "sg:tags":[
        "photo"
    ],
    "wof:name":"Galen Hayes Photography & Web",
    "wof:placetype":"venue"
},
  "geometry": {"coordinates":[-122.646008,45.465106],"type":"Point"}
}