{
  "type": "Feature",
  "properties": {
    "addr:full":"1644 Ashland St Unit 3 Ashland OR 97520",
    "addr:housenumber":"1644;3",
    "addr:postcode":"97520",
    "addr:street":"Ashland St Unit",
    "iso:country":"US",
    "sg:address":"1644 Ashland St Unit 3",
    "sg:city":"Ashland",
    "sg:phone":"+1 541 552 0720",
    "sg:postcode":"97520",
    "sg:province":"OR",
    "wof:name":"Deja Vu",
    "wof:placetype":"venue"
},
  "geometry": {"coordinates":[-122.686865,42.185427],"type":"Point"}
}