{
  "type": "Feature",
  "properties": {
    "addr:full":"3129 SW 1st Ave Portland OR 97201",
    "addr:housenumber":"3129",
    "addr:postcode":"97201",
    "addr:street":"Sw 1St Ave",
    "iso:country":"US",
    "sg:address":"3129 SW 1st Ave",
    "sg:city":"Portland",
    "sg:classifiers":[
        {
            "category":"Building & Trades",
            "subcategory":"Construction",
            "type":"Services"
        }
    ],
    "sg:phone":"+1 503 973 5030",
    "sg:postcode":"97201",
    "sg:province":"OR",
    "sg:tags":[
        "company"
    ],
    "wof:name":"Walsh Construction",
    "wof:placetype":"venue"
},
  "geometry": {"coordinates":[-122.678944,45.500331],"type":"Point"}
}