{
  "type": "Feature",
  "properties": {
    "addr:full":"67238 Miller Ln Union OR 97883",
    "addr:housenumber":"67238",
    "addr:postcode":"97883",
    "addr:street":"Miller Ln",
    "iso:country":"US",
    "sg:address":"67238 Miller Ln",
    "sg:city":"Union",
    "sg:classifiers":[
        {
            "category":"Wholesale",
            "subcategory":"Farm Supplies",
            "type":"Manufacturing & Wholesale Goods"
        }
    ],
    "sg:phone":"+1 541 562 5902",
    "sg:postcode":"97883",
    "sg:province":"OR",
    "sg:tags":[
        "livestock"
    ],
    "wof:name":"H & B Livestock Inc",
    "wof:placetype":"venue"
},
  "geometry": {"coordinates":[-117.901276,45.216768],"type":"Point"}
}