{
  "type": "Feature",
  "properties": {
    "addr:full":"3529 NE 145th Ave Portland OR 97230",
    "addr:housenumber":"3529",
    "addr:postcode":"97230",
    "addr:street":"Ne 145Th Ave",
    "iso:country":"US",
    "sg:address":"3529 NE 145th Ave",
    "sg:city":"Portland",
    "sg:classifiers":[
        {
            "category":"Real Estate",
            "subcategory":"Real Estate Agent",
            "type":"Services"
        }
    ],
    "sg:phone":"+1 503 253 0534",
    "sg:postcode":"97230",
    "sg:province":"OR",
    "wof:name":"Century 21 Moon Realty Inc",
    "wof:placetype":"venue"
},
  "geometry": {"coordinates":[-122.51346599999999,45.548902],"type":"Point"}
}