{
  "type": "Feature",
  "properties": {
    "addr:full":"161 High St SE Salem OR 97301",
    "addr:housenumber":"161",
    "addr:postcode":"97301",
    "addr:street":"High St Se",
    "iso:country":"US",
    "sg:address":"161 High St SE",
    "sg:city":"Salem",
    "sg:classifiers":[
        {
            "category":"Social Services",
            "subcategory":"Job Training",
            "type":"Services"
        }
    ],
    "sg:phone":"+1 503 364 5862",
    "sg:postcode":"97301",
    "sg:province":"OR",
    "sg:tags":[
        "rehabilitation"
    ],
    "wof:name":"Aspen Associates Inc",
    "wof:placetype":"venue"
},
  "geometry": {"coordinates":[-123.037539,44.939205],"type":"Point"}
}