{
  "type": "Feature",
  "properties": {
    "addr:full":"2120 NE Tillamook St Portland OR 97212",
    "addr:housenumber":"2120",
    "addr:postcode":"97212",
    "addr:street":"Ne Tillamook St",
    "iso:country":"US",
    "sg:address":"2120 NE Tillamook St",
    "sg:city":"Portland",
    "sg:classifiers":[
        {
            "category":"Social Services",
            "subcategory":"Child Care",
            "type":"Services"
        }
    ],
    "sg:phone":"+1 503 287 1238",
    "sg:postcode":"97212",
    "sg:province":"OR",
    "sg:tags":[
        "god",
        "religious",
        "day",
        "churches-pentecostal",
        "church"
    ],
    "wof:name":"Holladay Land Day Nursery",
    "wof:placetype":"venue"
},
  "geometry": {"coordinates":[-122.64428700000001,45.537441],"type":"Point"}
}