{
  "type": "Feature",
  "properties": {
    "iso:country":"US",
    "sg:address":"650 NE Goldie Dr",
    "sg:city":"Hillsboro",
    "sg:classifiers":[
        {
            "category":"Place Of Worship",
            "type":"Public Place"
        }
    ],
    "sg:phone":"+1 503 648 7259",
    "sg:postcode":"97124",
    "sg:province":"OR",
    "sg:tags":[
        "church"
    ],
    "wof:name":"Judah Dave",
    "wof:placetype":"venue"
},
  "geometry": {"coordinates":[-122.981808,45.538461],"type":"Point"}
}