{
  "type": "Feature",
  "properties": {
    "addr:full":"1250 Biddle Rd Ste G Medford OR 97504",
    "addr:housenumber":"1250",
    "addr:postcode":"97504",
    "addr:street":"Biddle Rd Ste G",
    "iso:country":"US",
    "sg:address":"1250 Biddle Rd Ste G",
    "sg:city":"Medford",
    "sg:classifiers":[
        {
            "category":"Retail",
            "subcategory":"Laundry & Dry Cleaning",
            "type":"Services"
        }
    ],
    "sg:phone":"+1 541 734 9247",
    "sg:postcode":"97504",
    "sg:province":"OR",
    "wof:name":"One Hour Martinizing",
    "wof:placetype":"venue"
},
  "geometry": {"coordinates":[-122.87200199999999,42.340302],"type":"Point"}
}