{
  "type": "Feature",
  "properties": {
    "addr:full":"625 SW Stark St Portland OR 97205",
    "addr:housenumber":"625",
    "addr:postcode":"97205",
    "addr:street":"Sw Stark St",
    "iso:country":"US",
    "sg:address":"625 SW Stark St",
    "sg:city":"Portland",
    "sg:classifiers":[
        {
            "category":"Real Estate",
            "subcategory":"Architect",
            "type":"Services"
        }
    ],
    "sg:phone":"+1 503 223 1848",
    "sg:postcode":"97205",
    "sg:province":"OR",
    "wof:name":"Chilless Nielsen Architect",
    "wof:placetype":"venue"
},
  "geometry": {"coordinates":[-122.678336,45.521349],"type":"Point"}
}