{
  "type": "Feature",
  "properties": {
    "addr:full":"1325 NW Flanders St Portland OR 97209",
    "addr:housenumber":"1325",
    "addr:postcode":"97209",
    "addr:street":"Nw Flanders St",
    "iso:country":"US",
    "sg:address":"1325 NW Flanders St",
    "sg:city":"Portland",
    "sg:classifiers":[
        {
            "category":"Education",
            "subcategory":"Special Training",
            "type":"Public Place"
        },
        {
            "category":"Social Services",
            "subcategory":"Child Care",
            "type":"Services"
        }
    ],
    "sg:phone":"+1 503 229 0880",
    "sg:postcode":"97209",
    "sg:province":"OR",
    "sg:tags":[
        "educational",
        "computer",
        "day",
        "software"
    ],
    "sg:website":"http://www.spryminds.com",
    "wof:name":"Spry Learning Company",
    "wof:placetype":"venue"
},
  "geometry": {"coordinates":[-122.684529,45.525775],"type":"Point"}
}