{
  "type": "Feature",
  "properties": {
    "iso:country":"US",
    "sg:address":"7807 SE 82nd Ave",
    "sg:city":"Portland",
    "sg:classifiers":[
        {
            "category":"Retail",
            "subcategory":"Auto Repair",
            "type":"Services"
        }
    ],
    "sg:phone":"+1 503 777 2036",
    "sg:postcode":"97266",
    "sg:province":"OR",
    "sg:tags":[
        "exhaust"
    ],
    "wof:name":"Marquez Mufflers",
    "wof:placetype":"venue"
},
  "geometry": {"coordinates":[-122.579119,45.465131],"type":"Point"}
}