{
  "type": "Feature",
  "properties": {
    "addr:full":"7807 SE 82nd Ave Portland OR 97266",
    "addr:housenumber":"7807",
    "addr:postcode":"97266",
    "addr:street":"Se 82Nd Ave",
    "iso:country":"US",
    "sg:address":"7807 SE 82nd Ave",
    "sg:city":"Portland",
    "sg:classifiers":[
        {
            "category":"Retail",
            "subcategory":"Auto Repair",
            "type":"Services"
        }
    ],
    "sg:phone":"+1 503 777 2036",
    "sg:postcode":"97266",
    "sg:province":"OR",
    "sg:tags":[
        "exhaust"
    ],
    "wof:name":"Marquez Mufflers",
    "wof:placetype":"venue"
},
  "geometry": {"coordinates":[-122.57911900000001,45.465131],"type":"Point"}
}