{
  "type": "Feature",
  "properties": {
    "iso:country":"US",
    "sg:address":"86441 College View Rd",
    "sg:city":"Eugene",
    "sg:classifiers":[
        {
            "category":"Professional",
            "subcategory":"Business Services",
            "type":"Services"
        }
    ],
    "sg:phone":"+1 541 746 5640",
    "sg:postcode":"97405",
    "sg:province":"OR",
    "sg:tags":[
        "event"
    ],
    "wof:name":"Hog Event Line",
    "wof:placetype":"venue"
},
  "geometry": {"coordinates":[-123.020734,44.008465],"type":"Point"}
}