{
  "type": "Feature",
  "properties": {
    "addr:full":"500 Country Club Rd Hood River OR 97031",
    "addr:housenumber":"500",
    "addr:postcode":"97031",
    "addr:street":"Country Club Rd",
    "iso:country":"US",
    "sg:address":"500 Country Club Rd",
    "sg:city":"Hood River",
    "sg:classifiers":[
        {
            "category":"Professional",
            "subcategory":"Business Services",
            "type":"Services"
        }
    ],
    "sg:phone":"+1 541 386 8846",
    "sg:postcode":"97031",
    "sg:province":"OR",
    "wof:name":"Wantok Enterprises",
    "wof:placetype":"venue"
},
  "geometry": {"coordinates":[-121.568383,45.706104],"type":"Point"}
}