{
  "type": "Feature",
  "properties": {
    "iso:country":"US",
    "sg:address":"2211 SE Hawthorne Blvd",
    "sg:city":"Portland",
    "sg:classifiers":[
        {
            "category":"Restaurant",
            "type":"Food & Drink"
        }
    ],
    "sg:phone":"+1 503 234 9999",
    "sg:postcode":"97214",
    "sg:province":"OR",
    "sg:tags":[
        "pizza"
    ],
    "sg:website":"www.hotlipspizza.com",
    "wof:name":"Hot Lips",
    "wof:placetype":"venue"
},
  "geometry": {"coordinates":[-122.643215,45.512058],"type":"Point"}
}