{
  "type": "Feature",
  "properties": {
    "addr:full":"217 S Anchor St Rockaway Beach OR 97136",
    "addr:housenumber":"217",
    "addr:postcode":"97136",
    "addr:street":"S Anchor St",
    "iso:country":"US",
    "sg:address":"217 S Anchor St",
    "sg:city":"Rockaway Beach",
    "sg:classifiers":[
        {
            "category":"Government",
            "subcategory":"Fire Station",
            "type":"Public Place"
        }
    ],
    "sg:phone":"+1 503 355 2291",
    "sg:postcode":"97136",
    "sg:province":"OR",
    "sg:tags":[
        "department"
    ],
    "wof:name":"Fire Dept",
    "wof:placetype":"venue"
},
  "geometry": {"coordinates":[-123.94391899999999,45.61142],"type":"Point"}
}