{
  "type": "Feature",
  "properties": {
    "iso:country":"US",
    "sg:address":"1630 SW Morrison St",
    "sg:city":"Portland",
    "sg:classifiers":[
        {
            "category":"Professional",
            "subcategory":"Advertising",
            "type":"Services"
        }
    ],
    "sg:phone":"+1 503 241 3822",
    "sg:postcode":"97205",
    "sg:province":"OR",
    "sg:tags":[
        "agency"
    ],
    "wof:name":"Tbwa Chiat/Day Inc (de)",
    "wof:placetype":"venue"
},
  "geometry": {"coordinates":[-122.68894899999999,45.521741],"type":"Point"}
}