{
  "type": "Feature",
  "properties": {
    "iso:country":"US",
    "sg:address":"211 N Front St",
    "sg:city":"Central Point",
    "sg:classifiers":[
        {
            "category":"Organizations",
            "subcategory":"Membership Organization",
            "type":"Services"
        },
        {
            "category":"Shopping",
            "subcategory":"Used Merchandise",
            "type":"Retail Goods"
        }
    ],
    "sg:phone":"+1 541 664 5244",
    "sg:postcode":"97502",
    "sg:province":"OR",
    "sg:tags":[
        "shop",
        "thrift"
    ],
    "wof:name":"Gleaning Network Inc",
    "wof:placetype":"venue"
},
  "geometry": {"coordinates":[-122.920357,42.376264],"type":"Point"}
}