{
  "type": "Feature",
  "properties": {
    "addr:full":"10475 SE Division St Portland OR 97266",
    "addr:postcode":"10475;97266",
    "addr:street":"Se Division St",
    "iso:country":"US",
    "sg:address":"10475 SE Division St",
    "sg:city":"Portland",
    "sg:classifiers":[
        {
            "category":"Building & Trades",
            "subcategory":"Construction",
            "type":"Services"
        }
    ],
    "sg:phone":"+1 503 257 0002",
    "sg:postcode":"97266",
    "sg:province":"OR",
    "sg:tags":[
        "floor",
        "laying",
        "contractor"
    ],
    "wof:name":"Elegant Floors Inc",
    "wof:placetype":"venue"
},
  "geometry": {"coordinates":[-122.555941,45.504344],"type":"Point"}
}