{
  "type": "Feature",
  "properties": {
    "iso:country":"US",
    "sg:address":"1905 Lana Ave NE",
    "sg:city":"Salem",
    "sg:classifiers":[
        {
            "category":"Restaurant",
            "type":"Food & Drink"
        }
    ],
    "sg:phone":"+1 503 316 0159",
    "sg:postcode":"97303",
    "sg:province":"OR",
    "wof:name":"Stop N Go Cafe",
    "wof:placetype":"venue"
},
  "geometry": {"coordinates":[-123.00517499999999,44.965046],"type":"Point"}
}