{
  "type": "Feature",
  "properties": {
    "iso:country":"US",
    "sg:address":"1800 W 2nd St",
    "sg:city":"The Dalles",
    "sg:classifiers":[
        {
            "category":"Retail",
            "subcategory":"Auto Repair",
            "type":"Services"
        }
    ],
    "sg:phone":"+1 541 296 1330",
    "sg:postcode":"97058",
    "sg:province":"OR",
    "sg:tags":[
        "transmission"
    ],
    "wof:name":"Certified Auto & Transmission",
    "wof:placetype":"venue"
},
  "geometry": {"coordinates":[-121.20312800000001,45.610829],"type":"Point"}
}