{
  "type": "Feature",
  "properties": {
    "iso:country":"US",
    "sg:address":"11211 SE 82nd Ave",
    "sg:city":"Portland",
    "sg:classifiers":[
        {
            "category":"Shopping",
            "subcategory":"Shoes",
            "type":"Retail Goods"
        }
    ],
    "sg:phone":"+1 503 652 1935",
    "sg:postcode":"97266",
    "sg:province":"OR",
    "sg:tags":[
        "store"
    ],
    "sg:website":"www.payless.com",
    "wof:name":"Payless Shoesource",
    "wof:placetype":"venue"
},
  "geometry": {"coordinates":[-122.579002,45.441799],"type":"Point"}
}