{
  "type": "Feature",
  "properties": {
    "iso:country":"US",
    "sg:address":"920 SE Main St",
    "sg:city":"Roseburg",
    "sg:classifiers":[
        {
            "category":"Manufacturing",
            "subcategory":"Chemicals & Compounds",
            "type":"Manufacturing & Wholesale Goods"
        },
        {
            "category":"Animal Shelter",
            "type":"Public Place"
        },
        {
            "category":"Building & Trades",
            "subcategory":"Pest Control",
            "type":"Services"
        }
    ],
    "sg:phone":"+1 866 549 5440",
    "sg:postcode":"97470",
    "sg:province":"OR",
    "sg:tags":[
        "industrial",
        "supply",
        "services-commercial",
        "termite",
        "bee",
        "equipment",
        "mothproofing",
        "removal"
    ],
    "sg:website":"http://www.orkin.com/",
    "wof:name":"Orkin",
    "wof:placetype":"venue"
},
  "geometry": {"coordinates":[-123.34599,43.205261],"type":"Point"}
}