{
  "type": "Feature",
  "properties": {
    "addr:full":"407 NE 12th Avenue Portland OR 97232",
    "addr:housenumber":"407",
    "addr:postcode":"97232",
    "addr:street":"Ne 12Th Avenue",
    "iso:country":"US",
    "sg:address":"407 NE 12th Avenue",
    "sg:city":"Portland",
    "sg:classifiers":[
        {
            "category":"Health Services",
            "subcategory":"Health Practitioner",
            "type":"Services"
        }
    ],
    "sg:phone":"+1 503 872 9861",
    "sg:postcode":"97232",
    "sg:province":"OR",
    "sg:tags":[
        "acupuncture"
    ],
    "sg:website":"www.heaven-earth-acupuncture.com",
    "wof:name":"Heaven-Earth Acupuncture PC",
    "wof:placetype":"venue"
},
  "geometry": {"coordinates":[-122.653587,45.525813],"type":"Point"}
}