{
  "type": "Feature",
  "properties": {
    "iso:country":"US",
    "sg:address":"337 N 9th St",
    "sg:city":"Cottage Grove",
    "sg:classifiers":[
        {
            "category":"Travel",
            "subcategory":"Hotels & Motels",
            "type":"Entertainment"
        }
    ],
    "sg:phone":"+1 541 942 1900",
    "sg:postcode":"97424",
    "sg:province":"OR",
    "sg:tags":[
        "operation"
    ],
    "wof:name":"Gray Cat Inn",
    "wof:placetype":"venue"
},
  "geometry": {"coordinates":[-123.059123,43.799316],"type":"Point"}
}