{
  "type": "Feature",
  "properties": {
    "iso:country":"US",
    "sg:address":"512 Bell Rd",
    "sg:city":"Talent",
    "sg:classifiers":[
        {
            "category":"Food & Beverages",
            "subcategory":"Groceries & Convenience Stores",
            "type":"Retail Goods"
        }
    ],
    "sg:phone":"+1 541 512 1207",
    "sg:postcode":"97540",
    "sg:province":"OR",
    "wof:name":"Curb Appeal Exteriors",
    "wof:placetype":"venue"
},
  "geometry": {"coordinates":[-122.79120500000001,42.2374],"type":"Point"}
}