{
  "type": "Feature",
  "properties": {
    "addr:full":"6706 NE Killingsworth Street Portland OR 97218",
    "addr:housenumber":"6706",
    "addr:postcode":"97218",
    "addr:street":"Ne Killingsworth Street",
    "iso:country":"US",
    "sg:address":"6706 NE Killingsworth Street",
    "sg:city":"Portland",
    "sg:classifiers":[
        {
            "category":"Real Estate",
            "subcategory":"Real Estate Operator",
            "type":"Services"
        }
    ],
    "sg:phone":"+1 503 284 3985",
    "sg:postcode":"97218",
    "sg:province":"OR",
    "sg:tags":[
        "apartment"
    ],
    "wof:name":"Villa De Clara Vista",
    "wof:placetype":"venue"
},
  "geometry": {"coordinates":[-122.59362400000001,45.562595],"type":"Point"}
}