{
  "type": "Feature",
  "properties": {
    "addr:full":"11501 SW Pacific Hwy Suite 102 Portland OR 97223",
    "addr:housenumber":"11501",
    "addr:postcode":"97223",
    "addr:street":"Sw Pacific Hwy Suite 102",
    "iso:country":"US",
    "sg:address":"11501 SW Pacific Hwy Suite 102",
    "sg:city":"Portland",
    "sg:classifiers":[
        {
            "category":"Banks & Credit Unions",
            "subcategory":"Financial Services",
            "type":"Services"
        }
    ],
    "sg:phone":"+1 503 246 4800",
    "sg:postcode":"97223",
    "sg:province":"OR",
    "sg:tags":[
        "broker",
        "mortgage"
    ],
    "wof:name":"Guild Mortgage",
    "wof:placetype":"venue"
},
  "geometry": {"coordinates":[-122.747388,45.441907],"type":"Point"}
}