{
  "type": "Feature",
  "properties": {
    "iso:country":"US",
    "sg:address":"11300 NE Halsey St # 202",
    "sg:city":"Portland",
    "sg:classifiers":[
        {
            "category":"Professional",
            "subcategory":"Accounting & Tax Preparation",
            "type":"Services"
        }
    ],
    "sg:phone":"+1 503 255 4233",
    "sg:postcode":"97220",
    "sg:province":"OR",
    "sg:tags":[
        "bookkeeping",
        "return",
        "preparation-business",
        "billing"
    ],
    "wof:name":"Beutelschies And Co",
    "wof:placetype":"venue"
},
  "geometry": {"coordinates":[-122.545372,45.533501],"type":"Point"}
}