{
  "type": "Feature",
  "properties": {
    "iso:country":"US",
    "sg:address":"8911 N Leonard St",
    "sg:city":"Portland",
    "sg:classifiers":[
        {
            "category":"Communications",
            "subcategory":"Newspaper",
            "type":"Services"
        }
    ],
    "sg:phone":"+1 503 287 3880",
    "sg:postcode":"97203",
    "sg:province":"OR",
    "sg:tags":[
        "print",
        "medium"
    ],
    "sg:website":"www.portlandsentinel.com",
    "wof:name":"The Portland Sentinel",
    "wof:placetype":"venue"
},
  "geometry": {"coordinates":[-122.754256,45.592773],"type":"Point"}
}