{
  "type": "Feature",
  "properties": {
    "iso:country":"US",
    "sg:address":"92992 Ritter Rd",
    "sg:city":"Astoria",
    "sg:classifiers":[
        {
            "category":"Government",
            "subcategory":"Office",
            "type":"Public Place"
        }
    ],
    "sg:phone":"+1 503 458 6512",
    "sg:postcode":"97103",
    "sg:province":"OR",
    "sg:tags":[
        "state"
    ],
    "wof:name":"Big Creek Fish Hatchery",
    "wof:placetype":"venue"
},
  "geometry": {"coordinates":[-123.58446600000001,46.146761],"type":"Point"}
}