{
  "type": "Feature",
  "properties": {
    "iso:country":"US",
    "sg:address":"434 Oak St",
    "sg:city":"Central Point",
    "sg:classifiers":[
        {
            "category":"Organizations",
            "subcategory":"Religious Organization",
            "type":"Services"
        }
    ],
    "sg:phone":"+1 541 664 3914",
    "sg:postcode":"97502",
    "sg:province":"OR",
    "sg:tags":[
        "church"
    ],
    "wof:name":"Jehovah's Witnesses",
    "wof:placetype":"venue"
},
  "geometry": {"coordinates":[-122.913045,42.374982],"type":"Point"}
}