{
  "type": "Feature",
  "properties": {
    "iso:country":"US",
    "sg:address":"1100 SW 6th Ave",
    "sg:city":"Portland",
    "sg:classifiers":[
        {
            "category":"Real Estate",
            "subcategory":"Real Estate Operator",
            "type":"Services"
        }
    ],
    "sg:phone":"+1 503 232 7680",
    "sg:postcode":"97204",
    "sg:province":"OR",
    "sg:tags":[
        "building",
        "nonresidential"
    ],
    "wof:name":"Winder Properties LLC",
    "wof:placetype":"venue"
},
  "geometry": {"coordinates":[-122.68040999999999,45.515737],"type":"Point"}
}