{
  "type": "Feature",
  "properties": {
    "iso:country":"US",
    "sg:address":"17165 NE Hwy 240",
    "sg:city":"Newberg",
    "sg:classifiers":[
        {
            "category":"Home & Garden",
            "subcategory":"Furniture",
            "type":"Retail Goods"
        }
    ],
    "sg:phone":"+1 503 537 9127",
    "sg:postcode":"97132",
    "sg:province":"OR",
    "sg:tags":[
        "cabinet"
    ],
    "wof:name":"Cabinet Specialties Inc",
    "wof:placetype":"venue"
},
  "geometry": {"coordinates":[-123.060953,45.318323],"type":"Point"}
}