{
  "type": "Feature",
  "properties": {
    "addr:full":"1313 S Roosevelt Dr Seaside OR 97138",
    "addr:housenumber":"1313",
    "addr:postcode":"97138",
    "addr:street":"S Roosevelt Dr",
    "iso:country":"US",
    "sg:address":"1313 S Roosevelt Dr",
    "sg:city":"Seaside",
    "sg:classifiers":[
        {
            "category":"Restaurant",
            "type":"Food & Drink"
        }
    ],
    "sg:phone":"+1 503 738 7360",
    "sg:postcode":"97138",
    "sg:province":"OR",
    "sg:tags":[
        "eating"
    ],
    "wof:name":"Muchas Gracias Mexican Food",
    "wof:placetype":"venue"
},
  "geometry": {"coordinates":[-123.923047,45.985763],"type":"Point"}
}