{
  "type": "Feature",
  "properties": {
    "addr:full":"458 N Broadway Ave Burns OR 97720",
    "addr:housenumber":"458",
    "addr:postcode":"97720",
    "addr:street":"N Broadway Ave",
    "iso:country":"US",
    "sg:address":"458 N Broadway Ave",
    "sg:city":"Burns",
    "sg:classifiers":[
        {
            "category":"Home & Garden",
            "subcategory":"Carpets & Floor Coverings",
            "type":"Retail Goods"
        }
    ],
    "sg:phone":"+1 541 573 6107",
    "sg:postcode":"97720",
    "sg:province":"OR",
    "sg:tags":[
        "dealer",
        "rug"
    ],
    "wof:name":"Trents Floors To Go",
    "wof:placetype":"venue"
},
  "geometry": {"coordinates":[-119.05449299999999,43.589406],"type":"Point"}
}