{
  "type": "Feature",
  "properties": {
    "iso:country":"US",
    "sg:address":"825 NE 20th Ave Ste 200",
    "sg:city":"Portland",
    "sg:classifiers":[
        {
            "category":"Health Services",
            "subcategory":"Doctor",
            "type":"Services"
        }
    ],
    "sg:phone":"+1 503 517 2494",
    "sg:postcode":"97232",
    "sg:province":"OR",
    "wof:name":"Maple Leaf Medical Inc",
    "wof:placetype":"venue"
},
  "geometry": {"coordinates":[-122.64563,45.528976],"type":"Point"}
}