{
  "type": "Feature",
  "properties": {
    "addr:full":"15 SE 28th Ave Portland OR 97214",
    "addr:housenumber":"15",
    "addr:postcode":"97214",
    "addr:street":"Se 28Th Ave",
    "iso:country":"US",
    "sg:address":"15 SE 28th Ave",
    "sg:city":"Portland",
    "sg:classifiers":[
        {
            "category":"Bars & Pubs",
            "type":"Food & Drink"
        },
        {
            "category":"Restaurant",
            "type":"Food & Drink"
        }
    ],
    "sg:phone":"+1 503 231 1093",
    "sg:postcode":"97214",
    "sg:province":"OR",
    "sg:tags":[
        "lounge",
        "drinking",
        "eating",
        "cocktail"
    ],
    "wof:name":"Holman's Restaurant",
    "wof:placetype":"venue"
},
  "geometry": {"coordinates":[-122.637001,45.5224],"type":"Point"}
}