{
  "type": "Feature",
  "properties": {
    "iso:country":"US",
    "sg:address":"6710 SE Foster Rd",
    "sg:city":"Portland",
    "sg:classifiers":[
        {
            "category":"Coffee & Tea",
            "type":"Food & Drink"
        }
    ],
    "sg:postcode":"97206",
    "sg:province":"OR",
    "sg:website":"www.dutchbros.com",
    "wof:name":"Dutch Brothers",
    "wof:placetype":"venue"
},
  "geometry": {"coordinates":[-122.593628,45.488334],"type":"Point"}
}