{
  "type": "Feature",
  "properties": {
    "iso:country":"US",
    "sg:address":"6531 S Hwy 97",
    "sg:city":"Redmond",
    "sg:classifiers":[
        {
            "category":"Building & Trades",
            "subcategory":"Construction",
            "type":"Services"
        }
    ],
    "sg:phone":"+1 541 389 7069",
    "sg:postcode":"97756",
    "sg:province":"OR",
    "sg:tags":[
        "excavating",
        "contractor",
        "truck",
        "dump",
        "operates"
    ],
    "wof:name":"Terry Johnson Inc",
    "wof:placetype":"venue"
},
  "geometry": {"coordinates":[-121.21668099999999,44.215695],"type":"Point"}
}