{
  "type": "Feature",
  "properties": {
    "iso:country":"US",
    "sg:address":"512 Summit Ave",
    "sg:city":"Medford",
    "sg:classifiers":[
        {
            "category":"Building & Trades",
            "subcategory":"Cleaning & Sanitation",
            "type":"Services"
        }
    ],
    "sg:phone":"+1 541 826 7129",
    "sg:postcode":"97501",
    "sg:province":"OR",
    "sg:tags":[
        "carpet"
    ],
    "sg:website":"www.cnd-carpetcleaning.com",
    "wof:name":"C&D Carpet Cleaning",
    "wof:placetype":"venue"
},
  "geometry": {"coordinates":[-122.887106,42.329863],"type":"Point"}
}