{
  "type": "Feature",
  "properties": {
    "iso:country":"US",
    "sg:address":"1601 S Adams Dr",
    "sg:city":"Madras",
    "sg:classifiers":[
        {
            "category":"Shopping",
            "subcategory":"Gifts & Souvenirs",
            "type":"Retail Goods"
        }
    ],
    "sg:phone":"+1 541 475 1277",
    "sg:postcode":"97741",
    "sg:province":"OR",
    "wof:name":"Gift Collection",
    "wof:placetype":"venue"
},
  "geometry": {"coordinates":[-121.129546,44.613334],"type":"Point"}
}