{
  "type": "Feature",
  "properties": {
    "iso:country":"US",
    "sg:address":"1113 Hill St SE",
    "sg:city":"Albany",
    "sg:classifiers":[
        {
            "category":"Health Services",
            "subcategory":"Medical Lab",
            "type":"Services"
        }
    ],
    "sg:phone":"+1 541 928 1955",
    "sg:postcode":"97322",
    "sg:province":"OR",
    "wof:name":"Albany Denture Clinic",
    "wof:placetype":"venue"
},
  "geometry": {"coordinates":[-123.091739,44.630742],"type":"Point"}
}