{
  "type": "Feature",
  "properties": {
    "iso:country":"US",
    "sg:address":"685 NE Jackson St",
    "sg:city":"Hillsboro",
    "sg:classifiers":[
        {
            "category":"Education",
            "subcategory":"School",
            "type":"Public Place"
        }
    ],
    "sg:phone":"+1 503 640 8403",
    "sg:postcode":"97124",
    "sg:province":"OR",
    "wof:name":"Hillsboro School District 1j",
    "wof:placetype":"venue"
},
  "geometry": {"coordinates":[-122.978364,45.525154],"type":"Point"}
}