{
  "type": "Feature",
  "properties": {
    "iso:country":"US",
    "sg:address":"3207 NW Chapin Dr",
    "sg:city":"Portland",
    "sg:classifiers":[
        {
            "category":"Autos & Motor Vehicles",
            "subcategory":"Auto Supplies",
            "type":"Retail Goods"
        },
        {
            "category":"Manufacturing",
            "subcategory":"Electronics",
            "type":"Manufacturing & Wholesale Goods"
        }
    ],
    "sg:phone":"+1 503 222 7330",
    "sg:postcode":"97229",
    "sg:province":"OR",
    "sg:tags":[
        "consultant",
        "robotics",
        "automation"
    ],
    "wof:name":"Ig Associates Inc",
    "wof:placetype":"venue"
},
  "geometry": {"coordinates":[-122.76879099999999,45.547642],"type":"Point"}
}