{
  "type": "Feature",
  "properties": {
    "addr:full":"1395 Bogart Ln Eugene OR 97401",
    "addr:housenumber":"1395",
    "addr:postcode":"97401",
    "addr:street":"Bogart Ln",
    "iso:country":"US",
    "sg:address":"1395 Bogart Ln",
    "sg:city":"Eugene",
    "sg:classifiers":[
        {
            "category":"Banks & Credit Unions",
            "subcategory":"Financial Services",
            "type":"Services"
        }
    ],
    "sg:phone":"+1 541 344 7704",
    "sg:postcode":"97401",
    "sg:province":"OR",
    "sg:tags":[
        "investor",
        "investment"
    ],
    "wof:name":"Wyco Investments",
    "wof:placetype":"venue"
},
  "geometry": {"coordinates":[-123.059667,44.077226],"type":"Point"}
}