{
  "type": "Feature",
  "properties": {
    "addr:full":"NE Fremont St & N Mississippi Ave Portland OR 97255",
    "addr:postcode":"97255",
    "addr:street":"Ne Fremont St & N;Ave",
    "iso:country":"US",
    "sg:address":"NE Fremont St & N Mississippi Ave",
    "sg:city":"Portland",
    "sg:classifiers":[
        {
            "category":"Food Court",
            "type":"Food & Drink"
        }
    ],
    "sg:postcode":"97255",
    "sg:province":"OR",
    "sg:tags":[
        "stand"
    ],
    "wof:name":"Son of Flavour Spot",
    "wof:placetype":"venue"
},
  "geometry": {"coordinates":[-122.675561,45.547842],"type":"Point"}
}