{
  "type": "Feature",
  "properties": {
    "iso:country":"US",
    "sg:address":"50 River Bend Rd",
    "sg:city":"Reedsport",
    "sg:classifiers":[
        {
            "category":"Home & Garden",
            "subcategory":"Building Materials",
            "type":"Retail Goods"
        }
    ],
    "sg:phone":"+1 541 271 6802",
    "sg:postcode":"97467",
    "sg:province":"OR",
    "sg:tags":[
        "glass",
        "window",
        "plate"
    ],
    "wof:name":"Dans Auto Glass",
    "wof:placetype":"venue"
},
  "geometry": {"coordinates":[-124.103525,43.699172],"type":"Point"}
}