{
  "type": "Feature",
  "properties": {
    "addr:full":"630 Chetco Ave Brookings OR 97415",
    "addr:housenumber":"630",
    "addr:postcode":"97415",
    "addr:street":"Chetco Ave",
    "iso:country":"US",
    "sg:address":"630 Chetco Ave",
    "sg:city":"Brookings",
    "sg:classifiers":[
        {
            "category":"Manufacturing",
            "subcategory":"Printing",
            "type":"Manufacturing & Wholesale Goods"
        }
    ],
    "sg:phone":"+1 541 469 5131",
    "sg:postcode":"97415",
    "sg:province":"OR",
    "sg:tags":[
        "printer"
    ],
    "wof:name":"First Impressions",
    "wof:placetype":"venue"
},
  "geometry": {"coordinates":[-124.28219900000001,42.05244],"type":"Point"}
}