{
  "type": "Feature",
  "properties": {
    "addr:full":"2487 Crater Lake Ave Medford OR 97504",
    "addr:housenumber":"2487",
    "addr:postcode":"97504",
    "addr:street":"Crater Lake Ave",
    "iso:country":"US",
    "sg:address":"2487 Crater Lake Ave",
    "sg:city":"Medford",
    "sg:classifiers":[
        {
            "category":"Home & Garden",
            "subcategory":"Building Materials",
            "type":"Retail Goods"
        }
    ],
    "sg:phone":"+1 541 779 5080",
    "sg:postcode":"97504",
    "sg:province":"OR",
    "sg:tags":[
        "door",
        "gate",
        "operating",
        "devices"
    ],
    "wof:name":"Bear Creek Over Head Doors",
    "wof:placetype":"venue"
},
  "geometry": {"coordinates":[-122.855802,42.352353],"type":"Point"}
}