{
  "type": "Feature",
  "properties": {
    "iso:country":"US",
    "sg:address":"3933 NW Sitka Pl",
    "sg:city":"Corvallis",
    "sg:classifiers":[
        {
            "category":"Professional",
            "subcategory":"Engineering",
            "type":"Services"
        }
    ],
    "sg:phone":"+1 541 757 9833",
    "sg:postcode":"97330",
    "sg:province":"OR",
    "wof:name":"Mcgee Engineering",
    "wof:placetype":"venue"
},
  "geometry": {"coordinates":[-123.29759300000001,44.598727],"type":"Point"}
}