{
  "type": "Feature",
  "properties": {
    "iso:country":"US",
    "sg:address":"16180 SE 82nd Dr",
    "sg:city":"Clackamas",
    "sg:classifiers":[
        {
            "category":"Shopping",
            "subcategory":"Florist",
            "type":"Retail Goods"
        }
    ],
    "sg:phone":"+1 503 286 1330",
    "sg:postcode":"97015",
    "sg:province":"OR",
    "wof:name":"Lombard Flowers",
    "wof:placetype":"venue"
},
  "geometry": {"coordinates":[-122.568807,45.404774],"type":"Point"}
}