{
  "type": "Feature",
  "properties": {
    "iso:country":"US",
    "sg:address":"3605 SE Division St",
    "sg:city":"Portland",
    "sg:phone":"+1 503 230 0588",
    "sg:postcode":"97202",
    "sg:province":"OR",
    "wof:name":"Metalurges",
    "wof:placetype":"venue"
},
  "geometry": {"coordinates":[-122.626244,45.504799],"type":"Point"}
}