{
  "type": "Feature",
  "properties": {
    "iso:country":"US",
    "sg:address":"2988 NW Fairway Hts",
    "sg:city":"Bend",
    "sg:classifiers":[
        {
            "category":"Banks & Credit Unions",
            "subcategory":"Bank",
            "type":"Services"
        }
    ],
    "sg:phone":"+1 541 318 7365",
    "sg:postcode":"97701",
    "sg:province":"OR",
    "sg:tags":[
        "mortgage"
    ],
    "wof:name":"Central Oregon Lending Inc",
    "wof:placetype":"venue"
},
  "geometry": {"coordinates":[-121.318556,44.079876],"type":"Point"}
}