{
  "type": "Feature",
  "properties": {
    "addr:full":"213 Gangnes Dr Talent OR 97540",
    "addr:housenumber":"213",
    "addr:postcode":"97540",
    "addr:street":"Gangnes Dr",
    "iso:country":"US",
    "sg:address":"213 Gangnes Dr",
    "sg:city":"Talent",
    "sg:phone":"+1 541 535 3792",
    "sg:postcode":"97540",
    "sg:province":"OR",
    "sg:tags":[
        "leather"
    ],
    "wof:name":"Laughing Crowe Leather Works",
    "wof:placetype":"venue"
},
  "geometry": {"coordinates":[-122.783508,42.243926],"type":"Point"}
}