{
  "type": "Feature",
  "properties": {
    "iso:country":"US",
    "sg:address":"515 SE Spruce St",
    "sg:city":"Roseburg",
    "sg:classifiers":[
        {
            "category":"Shopping",
            "subcategory":"Discount & Variety Stores",
            "type":"Retail Goods"
        }
    ],
    "sg:phone":"+1 541 672 4312",
    "sg:postcode":"97470",
    "sg:province":"OR",
    "sg:tags":[
        "sporting"
    ],
    "wof:name":"Surplus Center Inc",
    "wof:placetype":"venue"
},
  "geometry": {"coordinates":[-123.347153,43.211068],"type":"Point"}
}