{
  "type": "Feature",
  "properties": {
    "addr:full":"8305 SE Monterey Ave Portland OR 97266",
    "addr:housenumber":"8305",
    "addr:postcode":"97266",
    "addr:street":"Se Monterey Ave",
    "iso:country":"US",
    "sg:address":"8305 SE Monterey Ave",
    "sg:city":"Portland",
    "sg:classifiers":[
        {
            "category":"Professional",
            "subcategory":"Accounting & Tax Preparation",
            "type":"Services"
        }
    ],
    "sg:phone":"+1 503 654 9314",
    "sg:postcode":"97266",
    "sg:province":"OR",
    "sg:tags":[
        "accountant"
    ],
    "wof:name":"Brown Mark CPA PC",
    "wof:placetype":"venue"
},
  "geometry": {"coordinates":[-122.578003,45.438301],"type":"Point"}
}