{
  "type": "Feature",
  "properties": {
    "addr:full":"340 S Locust St Canby OR 97013",
    "addr:housenumber":"340",
    "addr:postcode":"97013",
    "addr:street":"S Locust St",
    "iso:country":"US",
    "sg:address":"340 S Locust St",
    "sg:city":"Canby",
    "sg:classifiers":[
        {
            "category":"Professional",
            "type":"Services"
        }
    ],
    "sg:phone":"+1 503 266 4881",
    "sg:postcode":"97013",
    "sg:province":"OR",
    "wof:name":"D Doty Com",
    "wof:placetype":"venue"
},
  "geometry": {"coordinates":[-122.68611,45.260754],"type":"Point"}
}