{
  "type": "Feature",
  "properties": {
    "iso:country":"US",
    "sg:address":"1 SW Columbia St",
    "sg:city":"Portland",
    "sg:classifiers":[
        {
            "category":"Banks & Credit Unions",
            "subcategory":"Investment Brokerage",
            "type":"Services"
        }
    ],
    "sg:phone":"+1 503 546 3151",
    "sg:postcode":"97201",
    "sg:province":"OR",
    "sg:tags":[
        "advisory",
        "financial"
    ],
    "wof:name":"Rubicon Investment Management",
    "wof:placetype":"venue"
},
  "geometry": {"coordinates":[-122.67613,45.51307],"type":"Point"}
}