{
  "type": "Feature",
  "properties": {
    "iso:country":"US",
    "sg:address":"940 Rowe St",
    "sg:city":"Reedsport",
    "sg:classifiers":[
        {
            "category":"Real Estate",
            "subcategory":"Real Estate Operator",
            "type":"Services"
        }
    ],
    "sg:phone":"+1 541 271 2244",
    "sg:postcode":"97467",
    "sg:province":"OR",
    "sg:tags":[
        "apartment"
    ],
    "wof:name":"Edgewood Apartment Homes",
    "wof:placetype":"venue"
},
  "geometry": {"coordinates":[-124.128583,43.687875],"type":"Point"}
}