{
  "type": "Feature",
  "properties": {
    "iso:country":"US",
    "sg:address":"1916 Lone Rock Rd",
    "sg:city":"Glide",
    "sg:classifiers":[
        {
            "category":"Professional",
            "subcategory":"Business Services",
            "type":"Services"
        }
    ],
    "sg:phone":"+1 541 677 8800",
    "sg:postcode":"97443",
    "sg:province":"OR",
    "wof:name":"North Stephens Pack & Post",
    "wof:placetype":"venue"
},
  "geometry": {"coordinates":[-123.046898,43.320546],"type":"Point"}
}