{
  "type": "Feature",
  "properties": {
    "addr:full":"1040 N Bayview Ct Waldport OR 97394",
    "addr:housenumber":"1040",
    "addr:postcode":"97394",
    "addr:street":"N Bayview Ct",
    "iso:country":"US",
    "sg:address":"1040 N Bayview Ct",
    "sg:city":"Waldport",
    "sg:classifiers":[
        {
            "category":"Professional",
            "subcategory":"Management & Consulting",
            "type":"Services"
        }
    ],
    "sg:phone":"+1 541 563 3785",
    "sg:postcode":"97394",
    "sg:province":"OR",
    "sg:tags":[
        "retail",
        "direct",
        "sales"
    ],
    "wof:name":"Pacific Pure Norhtwest Wtr Co",
    "wof:placetype":"venue"
},
  "geometry": {"coordinates":[-124.02389599999999,44.440015],"type":"Point"}
}