{
  "type": "Feature",
  "properties": {
    "addr:full":"28925 SW Fernhollow Ln Hillsboro OR 97123",
    "addr:housenumber":"28925",
    "addr:postcode":"97123",
    "addr:street":"Sw Fernhollow Ln",
    "iso:country":"US",
    "sg:address":"28925 SW Fernhollow Ln",
    "sg:city":"Hillsboro",
    "sg:classifiers":[
        {
            "category":"Shopping",
            "subcategory":"Books",
            "type":"Retail Goods"
        }
    ],
    "sg:phone":"+1 503 628 1690",
    "sg:postcode":"97123",
    "sg:province":"OR",
    "wof:name":"Country Lane Books Etc",
    "wof:placetype":"venue"
},
  "geometry": {"coordinates":[-122.974017,45.390796],"type":"Point"}
}