{
  "type": "Feature",
  "properties": {
    "iso:country":"US",
    "sg:address":"657 Hayden Bridge Pl",
    "sg:city":"Springfield",
    "sg:classifiers":[
        {
            "category":"Professional",
            "subcategory":"Business Services",
            "type":"Services"
        }
    ],
    "sg:phone":"+1 541 746 6968",
    "sg:postcode":"97477",
    "sg:province":"OR",
    "sg:tags":[
        "application",
        "addiction",
        "modality",
        "research"
    ],
    "wof:name":"Wind & Rain",
    "wof:placetype":"venue"
},
  "geometry": {"coordinates":[-123.01846,44.069959],"type":"Point"}
}