{
  "type": "Feature",
  "properties": {
    "iso:country":"US",
    "sg:address":"2510 Willakenzie Rd",
    "sg:city":"Eugene",
    "sg:classifiers":[
        {
            "category":"Shopping",
            "subcategory":"Department Store",
            "type":"Retail Goods"
        }
    ],
    "sg:phone":"+1 541 687 7610",
    "sg:postcode":"97401",
    "sg:province":"OR",
    "sg:website":"www.bimart.com",
    "wof:name":"Bi-Mart",
    "wof:placetype":"venue"
},
  "geometry": {"coordinates":[-123.074035,44.07953],"type":"Point"}
}