{
  "type": "Feature",
  "properties": {
    "addr:full":"17230 NE Sacramento St Portland OR 97230",
    "addr:housenumber":"17230",
    "addr:postcode":"97230",
    "addr:street":"Ne Sacramento St",
    "iso:country":"US",
    "sg:address":"17230 NE Sacramento St",
    "sg:city":"Portland",
    "sg:classifiers":[
        {
            "category":"Manufacturing",
            "subcategory":"Toys & Sporting Goods",
            "type":"Manufacturing & Wholesale Goods"
        }
    ],
    "sg:phone":"+1 503 255 1410",
    "sg:postcode":"97230",
    "sg:province":"OR",
    "sg:tags":[
        "athletic"
    ],
    "sg:website":"www.jones-golf.com",
    "wof:name":"Jones Golf",
    "wof:placetype":"venue"
},
  "geometry": {"coordinates":[-122.480132,45.540493],"type":"Point"}
}