{
  "type": "Feature",
  "properties": {
    "iso:country":"US",
    "sg:address":"920 E 2nd Ave",
    "sg:city":"Sutherlin",
    "sg:classifiers":[
        {
            "category":"Health Services",
            "subcategory":"Medical Lab",
            "type":"Services"
        }
    ],
    "sg:phone":"+1 541 672 2089",
    "sg:postcode":"97479",
    "sg:province":"OR",
    "sg:tags":[
        "laboratory",
        "dental"
    ],
    "wof:name":"Emv Denture Lab",
    "wof:placetype":"venue"
},
  "geometry": {"coordinates":[-123.301678,43.39422],"type":"Point"}
}