{
  "type": "Feature",
  "properties": {
    "iso:country":"US",
    "sg:address":"1750 Park Ave",
    "sg:city":"Woodburn",
    "sg:classifiers":[
        {
            "category":"Retail",
            "subcategory":"Auto Repair",
            "type":"Services"
        }
    ],
    "sg:phone":"+1 503 982 5267",
    "sg:postcode":"97071",
    "sg:province":"OR",
    "sg:tags":[
        "garage"
    ],
    "wof:name":"Public Works Garage",
    "wof:placetype":"venue"
},
  "geometry": {"coordinates":[-122.841068,45.150157],"type":"Point"}
}