{
  "type": "Feature",
  "properties": {
    "iso:country":"US",
    "sg:address":"2090 NW 101st St",
    "sg:city":"Bend",
    "sg:classifiers":[
        {
            "category":"Health Services",
            "subcategory":"Doctor",
            "type":"Services"
        }
    ],
    "sg:phone":"+1 541 382 6447",
    "sg:postcode":"97756",
    "sg:province":"OR",
    "sg:tags":[
        "physician",
        "surgeon"
    ],
    "wof:name":"Bend Urology Assoc",
    "wof:placetype":"venue"
},
  "geometry": {"coordinates":[-121.293768,44.296245],"type":"Point"}
}