{
  "type": "Feature",
  "properties": {
    "iso:country":"US",
    "sg:address":"16055 SW Walker Rd",
    "sg:city":"Beaverton",
    "sg:classifiers":[
        {
            "category":"Organizations",
            "subcategory":"Community Association",
            "type":"Services"
        }
    ],
    "sg:phone":"+1 503 984 2904",
    "sg:postcode":"97006",
    "sg:province":"OR",
    "wof:name":"American Assoc Of Professional",
    "wof:placetype":"venue"
},
  "geometry": {"coordinates":[-122.842365,45.517676],"type":"Point"}
}