{
  "type": "Feature",
  "properties": {
    "iso:country":"US",
    "sg:address":"548 High St NE",
    "sg:city":"Salem",
    "sg:classifiers":[
        {
            "category":"Shopping",
            "subcategory":"Used Merchandise",
            "type":"Retail Goods"
        }
    ],
    "sg:phone":"+1 503 362 6892",
    "sg:postcode":"97301",
    "sg:province":"OR",
    "sg:tags":[
        "shop",
        "thrift"
    ],
    "wof:name":"Humane Society Shop",
    "wof:placetype":"venue"
},
  "geometry": {"coordinates":[-123.034586,44.944545],"type":"Point"}
}