{
  "type": "Feature",
  "properties": {
    "addr:full":"3155 NW Yeon Ave Portland OR 97210",
    "addr:housenumber":"3155",
    "addr:postcode":"97210",
    "addr:street":"Nw Yeon Ave",
    "iso:country":"US",
    "sg:address":"3155 NW Yeon Ave",
    "sg:city":"Portland",
    "sg:classifiers":[
        {
            "category":"Wholesale",
            "subcategory":"Machinery & Supplies",
            "type":"Manufacturing & Wholesale Goods"
        }
    ],
    "sg:phone":"+1 503 723 7100",
    "sg:postcode":"97210",
    "sg:province":"OR",
    "sg:tags":[
        "roofing",
        "used",
        "shoes",
        "for",
        "mfg",
        "boot",
        "weighting",
        "fishing"
    ],
    "wof:name":"Korkers Products LLC",
    "wof:placetype":"venue"
},
  "geometry": {"coordinates":[-122.700783,45.542417],"type":"Point"}
}