{
  "type": "Feature",
  "properties": {
    "iso:country":"US",
    "sg:address":"440 NW 11th St",
    "sg:city":"Hermiston",
    "sg:classifiers":[
        {
            "category":"Building & Trades",
            "subcategory":"Construction",
            "type":"Services"
        }
    ],
    "sg:phone":"+1 541 567 9425",
    "sg:postcode":"97838",
    "sg:province":"OR",
    "sg:tags":[
        "carpentry",
        "contractor"
    ],
    "wof:name":"Ray Olsen Enterprises",
    "wof:placetype":"venue"
},
  "geometry": {"coordinates":[-119.310964,45.843976],"type":"Point"}
}