{
  "type": "Feature",
  "properties": {
    "iso:country":"US",
    "sg:address":"1323 SE 6th Ave",
    "sg:city":"Portland",
    "sg:classifiers":[
        {
            "category":"Building & Trades",
            "subcategory":"Construction",
            "type":"Services"
        },
        {
            "category":"Real Estate",
            "subcategory":"Architect",
            "type":"Services"
        }
    ],
    "sg:phone":"+1 503 804 1746",
    "sg:postcode":"97214",
    "sg:province":"OR",
    "sg:tags":[
        "contractor"
    ],
    "wof:name":"Green Hammer Inc",
    "wof:placetype":"venue"
},
  "geometry": {"coordinates":[-122.659938,45.513475],"type":"Point"}
}