{
  "type": "Feature",
  "properties": {
    "iso:country":"US",
    "sg:address":"1310 15th St",
    "sg:city":"Hood River",
    "sg:classifiers":[
        {
            "category":"Building & Trades",
            "subcategory":"Construction",
            "type":"Services"
        }
    ],
    "sg:phone":"+1 541 386 7210",
    "sg:postcode":"97031",
    "sg:province":"OR",
    "sg:tags":[
        "hanging",
        "contractor"
    ],
    "wof:name":"Artisan Painting",
    "wof:placetype":"venue"
},
  "geometry": {"coordinates":[-121.526827,45.700839],"type":"Point"}
}