{
  "type": "Feature",
  "properties": {
    "addr:full":"1560 NE 172nd Ave Portland OR 97230",
    "addr:housenumber":"1560",
    "addr:postcode":"97230",
    "addr:street":"Ne 172Nd Ave",
    "iso:country":"US",
    "sg:address":"1560 NE 172nd Ave",
    "sg:city":"Portland",
    "sg:classifiers":[
        {
            "category":"Travel",
            "subcategory":"Travel Agent",
            "type":"Entertainment"
        }
    ],
    "sg:phone":"+1 503 254 2484",
    "sg:postcode":"97230",
    "sg:province":"OR",
    "sg:tags":[
        "agency",
        "bureau"
    ],
    "wof:name":"Dial Travel",
    "wof:placetype":"venue"
},
  "geometry": {"coordinates":[-122.486051,45.532703],"type":"Point"}
}