{
  "type": "Feature",
  "properties": {
    "iso:country":"US",
    "sg:address":"33 SW Dorion Ave",
    "sg:city":"Pendleton",
    "sg:classifiers":[
        {
            "category":"Shopping",
            "subcategory":"Hobbies, Toys, & Games",
            "type":"Retail Goods"
        }
    ],
    "sg:phone":"+1 541 278 9533",
    "sg:postcode":"97801",
    "sg:province":"OR",
    "wof:name":"Beads Blue Hawk",
    "wof:placetype":"venue"
},
  "geometry": {"coordinates":[-118.787181,45.671619],"type":"Point"}
}