{
  "type": "Feature",
  "properties": {
    "addr:full":"W Burnside St and NW 19th St Portland OR 97209",
    "addr:postcode":"97209",
    "addr:street":"W Burnside St And Nw 19Th St",
    "iso:country":"US",
    "sg:address":"W Burnside St and NW 19th St",
    "sg:city":"Portland",
    "sg:classifiers":[
        {
            "category":"Education",
            "subcategory":"Dance Studio",
            "type":"Public Place"
        }
    ],
    "sg:phone":"+1 650 557 2095",
    "sg:postcode":"97209",
    "sg:province":"OR",
    "sg:website":"www.ballerobica.com",
    "wof:name":"Ballerobica",
    "wof:placetype":"venue"
},
  "geometry": {"coordinates":[-122.690219,45.523004],"type":"Point"}
}