{
  "type": "Feature",
  "properties": {
    "iso:country":"US",
    "sg:address":"909 Lower Klamath Lake Rd",
    "sg:city":"Klamath Falls",
    "sg:classifiers":[
        {
            "category":"Farming",
            "subcategory":"Nursery",
            "type":"Manufacturing & Wholesale Goods"
        }
    ],
    "sg:phone":"+1 541 882 3962",
    "sg:postcode":"97603",
    "sg:province":"OR",
    "sg:tags":[
        "greenhouse"
    ],
    "wof:name":"Wright Greenhouse",
    "wof:placetype":"venue"
},
  "geometry": {"coordinates":[-121.795305,42.100728],"type":"Point"}
}