{
  "type": "Feature",
  "properties": {
    "iso:country":"US",
    "sg:address":"11654 SE 31st Ave",
    "sg:city":"Portland",
    "sg:classifiers":[
        {
            "category":"Building & Trades",
            "subcategory":"Locksmith",
            "type":"Services"
        }
    ],
    "sg:phone":"+1 503 715 3742",
    "sg:postcode":"97222",
    "sg:province":"OR",
    "sg:tags":[
        "key"
    ],
    "wof:name":"A Emergency Locksmith",
    "wof:placetype":"venue"
},
  "geometry": {"coordinates":[-122.630664,45.439076],"type":"Point"}
}