{
  "type": "Feature",
  "properties": {
    "iso:country":"US",
    "sg:address":"3191 Inland Dr S",
    "sg:city":"Salem",
    "sg:classifiers":[
        {
            "category":"Professional",
            "type":"Services"
        }
    ],
    "sg:phone":"+1 503 371 3400",
    "sg:postcode":"97302",
    "sg:province":"OR",
    "wof:name":"David Metzger Music",
    "wof:placetype":"venue"
},
  "geometry": {"coordinates":[-123.09711900000001,44.890751],"type":"Point"}
}