{
  "type": "Feature",
  "properties": {
    "iso:country":"US",
    "sg:address":"7140 SE Thorburn St",
    "sg:city":"Portland",
    "sg:classifiers":[
        {
            "category":"Building & Trades",
            "subcategory":"Cleaning & Sanitation",
            "type":"Services"
        }
    ],
    "sg:phone":"+1 503 252 9963",
    "sg:postcode":"97215",
    "sg:province":"OR",
    "sg:tags":[
        "maintenance"
    ],
    "wof:name":"Air Clean Technology LLC",
    "wof:placetype":"venue"
},
  "geometry": {"coordinates":[-122.591756,45.522021],"type":"Point"}
}