{
  "type": "Feature",
  "properties": {
    "addr:full":"16081 S Winston Dr Oregon City OR 97045",
    "addr:housenumber":"16081",
    "addr:postcode":"97045",
    "addr:street":"S Winston Dr",
    "iso:country":"US",
    "sg:address":"16081 S Winston Dr",
    "sg:city":"Oregon City",
    "sg:classifiers":[
        {
            "category":"Building & Trades",
            "subcategory":"Plumbing",
            "type":"Services"
        }
    ],
    "sg:phone":"+1 503 784 0404",
    "sg:postcode":"97045",
    "sg:province":"OR",
    "sg:tags":[
        "refrigeration",
        "contractor"
    ],
    "wof:name":"Smith Systems",
    "wof:placetype":"venue"
},
  "geometry": {"coordinates":[-122.5603,45.372752],"type":"Point"}
}