{
  "type": "Feature",
  "properties": {
    "addr:full":"69612 Wheeler Ln Elgin OR 97827",
    "addr:housenumber":"69612",
    "addr:postcode":"97827",
    "addr:street":"Wheeler Ln",
    "iso:country":"US",
    "sg:address":"69612 Wheeler Ln",
    "sg:city":"Elgin",
    "sg:classifiers":[
        {
            "category":"Shopping",
            "subcategory":"Books",
            "type":"Retail Goods"
        }
    ],
    "sg:phone":"+1 541 437 8641",
    "sg:postcode":"97827",
    "sg:province":"OR",
    "wof:name":"Joy A Wheeler Books",
    "wof:placetype":"venue"
},
  "geometry": {"coordinates":[-117.768288,45.648091],"type":"Point"}
}