{
  "type": "Feature",
  "properties": {
    "addr:full":"2079 W Main St Medford OR 97501",
    "addr:housenumber":"2079",
    "addr:postcode":"97501",
    "addr:street":"W Main St",
    "iso:country":"US",
    "sg:address":"2079 W Main St",
    "sg:city":"Medford",
    "sg:classifiers":[
        {
            "category":"Home & Garden",
            "subcategory":"Hardware",
            "type":"Retail Goods"
        },
        {
            "category":"Home & Garden",
            "subcategory":"Building Materials",
            "type":"Retail Goods"
        }
    ],
    "sg:phone":"+1 541 779 2753",
    "sg:postcode":"97501",
    "sg:province":"OR",
    "sg:tags":[
        "store",
        "supply"
    ],
    "wof:name":"High Way Lumber Co Inc",
    "wof:placetype":"venue"
},
  "geometry": {"coordinates":[-122.896004,42.323601],"type":"Point"}
}