{
  "type": "Feature",
  "properties": {
    "iso:country":"US",
    "sg:address":"11527 SW Canyon Rd",
    "sg:city":"Beaverton",
    "sg:classifiers":[
        {
            "category":"Food & Beverages",
            "subcategory":"Groceries & Convenience Stores",
            "type":"Retail Goods"
        }
    ],
    "sg:phone":"+1 503 641 0381",
    "sg:postcode":"97005",
    "sg:province":"OR",
    "sg:tags":[
        "grocer"
    ],
    "wof:name":"Cost Less Food Market",
    "wof:placetype":"venue"
},
  "geometry": {"coordinates":[-122.79625799999999,45.48983],"type":"Point"}
}