{
  "type": "Feature",
  "properties": {
    "addr:full":"7117 SW Beveland Rd Ste 101 Portland OR 97223",
    "addr:housenumber":"7117",
    "addr:postcode":"97223",
    "addr:street":"Sw Beveland Rd Ste 101",
    "iso:country":"US",
    "sg:address":"7117 SW Beveland Rd Ste 101",
    "sg:city":"Portland",
    "sg:classifiers":[
        {
            "category":"Professional",
            "subcategory":"Employment Agencies",
            "type":"Services"
        }
    ],
    "sg:phone":"+1 503 624 4855",
    "sg:postcode":"97223",
    "sg:province":"OR",
    "sg:tags":[
        "opportunity",
        "contractor"
    ],
    "sg:website":"http://www.allpeo.com",
    "wof:name":"American Admin, Inc.",
    "wof:placetype":"venue"
},
  "geometry": {"coordinates":[-122.749951,45.429543],"type":"Point"}
}