{
  "type": "Feature",
  "properties": {
    "iso:country":"US",
    "sg:address":"508 Washington St",
    "sg:city":"The Dalles",
    "sg:classifiers":[
        {
            "category":"Restaurant",
            "type":"Food & Drink"
        }
    ],
    "sg:phone":"+1 541 298 1200",
    "sg:postcode":"97058",
    "sg:province":"OR",
    "sg:tags":[
        "eating"
    ],
    "wof:name":"Washington Street Coffee Spot",
    "wof:placetype":"venue"
},
  "geometry": {"coordinates":[-121.183605,45.599568],"type":"Point"}
}