{
  "type": "Feature",
  "properties": {
    "iso:country":"US",
    "sg:address":"4620 Brickyard Rd",
    "sg:city":"Tillamook",
    "sg:classifiers":[
        {
            "category":"Professional",
            "subcategory":"Business Services",
            "type":"Services"
        }
    ],
    "sg:phone":"+1 503 842 5687",
    "sg:postcode":"97141",
    "sg:province":"OR",
    "wof:name":"7 Rivers Enterprises LLC",
    "wof:placetype":"venue"
},
  "geometry": {"coordinates":[-123.781364,45.419364],"type":"Point"}
}