{
  "type": "Feature",
  "properties": {
    "iso:country":"US",
    "sg:address":"6510 Williams Hwy",
    "sg:city":"Grants Pass",
    "sg:classifiers":[
        {
            "category":"Freight",
            "type":"Transportation"
        }
    ],
    "sg:phone":"+1 541 862 2495",
    "sg:postcode":"97527",
    "sg:province":"OR",
    "sg:tags":[
        "special",
        "general"
    ],
    "wof:name":"Murphy Mini Storage",
    "wof:placetype":"venue"
},
  "geometry": {"coordinates":[-123.33271999999999,42.346216],"type":"Point"}
}