{
  "type": "Feature",
  "properties": {
    "iso:country":"US",
    "sg:address":"852 SW 21st Ave",
    "sg:city":"Portland",
    "sg:classifiers":[
        {
            "category":"Sports & Exercise",
            "subcategory":"Gym",
            "type":"Entertainment"
        }
    ],
    "sg:phone":"+1 503 248 4483",
    "sg:postcode":"97205",
    "sg:province":"OR",
    "sg:tags":[
        "fitness",
        "physical",
        "facility"
    ],
    "wof:name":"Bodies In Balance",
    "wof:placetype":"venue"
},
  "geometry": {"coordinates":[-122.69417199999999,45.522218],"type":"Point"}
}