{
  "type": "Feature",
  "properties": {
    "iso:country":"US",
    "sg:address":"2780 SE Harrison St",
    "sg:city":"Portland",
    "sg:classifiers":[
        {
            "category":"Professional",
            "subcategory":"Engineering",
            "type":"Services"
        }
    ],
    "sg:phone":"+1 503 652 9090",
    "sg:postcode":"97222",
    "sg:province":"OR",
    "sg:tags":[
        "planning",
        "consulting",
        "construction"
    ],
    "wof:name":"Cascade Dsign Prfessionals Inc",
    "wof:placetype":"venue"
},
  "geometry": {"coordinates":[-122.635884,45.446384],"type":"Point"}
}