{
  "type": "Feature",
  "properties": {
    "addr:full":"1005 9th Ave SE Albany OR 97322",
    "addr:housenumber":"1005",
    "addr:postcode":"97322",
    "addr:street":"9Th Ave Se",
    "iso:country":"US",
    "sg:address":"1005 9th Ave SE",
    "sg:city":"Albany",
    "sg:classifiers":[
        {
            "category":"Retail",
            "subcategory":"Car Wash",
            "type":"Services"
        }
    ],
    "sg:phone":"+1 541 928 3394",
    "sg:postcode":"97322",
    "sg:province":"OR",
    "wof:name":"Carcraft Auto Appearance Ctr",
    "wof:placetype":"venue"
},
  "geometry": {"coordinates":[-123.092061,44.632455],"type":"Point"}
}