{
  "type": "Feature",
  "properties": {
    "iso:country":"US",
    "sg:address":"4700 SW Macadam Ave",
    "sg:city":"Portland",
    "sg:classifiers":[
        {
            "category":"Professional",
            "subcategory":"Business Services",
            "type":"Services"
        }
    ],
    "sg:phone":"+1 503 525 9601",
    "sg:postcode":"97219",
    "sg:province":"OR",
    "sg:tags":[
        "language"
    ],
    "wof:name":"Cli",
    "wof:placetype":"venue"
},
  "geometry": {"coordinates":[-122.67464699999999,45.488721],"type":"Point"}
}