{
  "type": "Feature",
  "properties": {
    "iso:country":"US",
    "sg:address":"1800 Taylor Ave",
    "sg:city":"Cottage Grove",
    "sg:classifiers":[
        {
            "category":"Professional",
            "subcategory":"Research",
            "type":"Services"
        }
    ],
    "sg:phone":"+1 541 942 4219",
    "sg:postcode":"97424",
    "sg:province":"OR",
    "sg:tags":[
        "nonphysical",
        "commercial"
    ],
    "wof:name":"Gerald L Cates Od",
    "wof:placetype":"venue"
},
  "geometry": {"coordinates":[-123.051374,43.786704],"type":"Point"}
}