{
  "type": "Feature",
  "properties": {
    "iso:country":"US",
    "sg:address":"2627 NW Nicolai St 7",
    "sg:city":"Portland",
    "sg:classifiers":[
        {
            "category":"Retail",
            "subcategory":"Repair Shop",
            "type":"Services"
        },
        {
            "category":"Wholesale",
            "subcategory":"Construction Materials",
            "type":"Manufacturing & Wholesale Goods"
        }
    ],
    "sg:phone":"+1 503 970 2509",
    "sg:postcode":"97210",
    "sg:province":"OR",
    "sg:tags":[
        "refinish",
        "furniture",
        "caning",
        "supply"
    ],
    "wof:name":"Mpfc",
    "wof:placetype":"venue"
},
  "geometry": {"coordinates":[-122.705811,45.540066],"type":"Point"}
}