{
  "type": "Feature",
  "properties": {
    "addr:full":"2699 Roosevelt Blvd # A Eugene OR 97402",
    "addr:housenumber":"2699",
    "addr:postcode":"97402",
    "addr:street":"Roosevelt Blvd # A",
    "iso:country":"US",
    "sg:address":"2699 Roosevelt Blvd # A",
    "sg:city":"Eugene",
    "sg:classifiers":[
        {
            "category":"Shopping",
            "subcategory":"Stationery & Office Supplies",
            "type":"Retail Goods"
        },
        {
            "category":"Home & Garden",
            "subcategory":"Furniture",
            "type":"Retail Goods"
        }
    ],
    "sg:phone":"+1 541 607 6264",
    "sg:postcode":"97402",
    "sg:province":"OR",
    "sg:tags":[
        "store"
    ],
    "sg:website":"http://www.maniadeals.com",
    "wof:name":"Furniture Mania",
    "wof:placetype":"venue"
},
  "geometry": {"coordinates":[-123.136368,44.063709],"type":"Point"}
}