{
  "type": "Feature",
  "properties": {
    "iso:country":"US",
    "sg:address":"870 Pearl St",
    "sg:city":"Eugene",
    "sg:classifiers":[
        {
            "category":"Shopping",
            "subcategory":"Gifts & Souvenirs",
            "type":"Retail Goods"
        }
    ],
    "sg:phone":"+1 541 345 7547",
    "sg:postcode":"97401",
    "sg:province":"OR",
    "wof:name":"Freudian Slip Lingerie & Gifts",
    "wof:placetype":"venue"
},
  "geometry": {"coordinates":[-123.08975700000001,44.050146],"type":"Point"}
}