{
  "type": "Feature",
  "properties": {
    "addr:full":"5280 State Hwy 99 Corvallis OR 97330",
    "addr:housenumber":"5280",
    "addr:postcode":"97330",
    "addr:street":"State Hwy 99",
    "iso:country":"US",
    "sg:address":"5280 State Hwy 99",
    "sg:city":"Corvallis",
    "sg:classifiers":[
        {
            "category":"Home & Garden",
            "subcategory":"Furniture",
            "type":"Retail Goods"
        }
    ],
    "sg:phone":"+1 541 753 6395",
    "sg:postcode":"97330",
    "sg:province":"OR",
    "wof:name":"Futon Man",
    "wof:placetype":"venue"
},
  "geometry": {"coordinates":[-123.24234300000001,44.624962],"type":"Point"}
}