{
  "type": "Feature",
  "properties": {
    "iso:country":"US",
    "sg:address":"7110 SW Fir Loop Ste 240",
    "sg:city":"Portland",
    "sg:classifiers":[
        {
            "category":"Food & Beverages",
            "subcategory":"Liquor & Beverages",
            "type":"Retail Goods"
        }
    ],
    "sg:phone":"+1 503 620 0313",
    "sg:postcode":"97223",
    "sg:province":"OR",
    "sg:tags":[
        "beer",
        "spirit",
        "wine"
    ],
    "sg:website":"www.indiospirits.com",
    "wof:name":"Indio Spirits Inc",
    "wof:placetype":"venue"
},
  "geometry": {"coordinates":[-122.749656,45.423429],"type":"Point"}
}