{
  "type": "Feature",
  "properties": {
    "iso:country":"US",
    "sg:address":"13980 SW 6th St",
    "sg:city":"Beaverton",
    "sg:classifiers":[
        {
            "category":"Professional",
            "subcategory":"Business Services",
            "type":"Services"
        }
    ],
    "sg:phone":"+1 503 641 1968",
    "sg:postcode":"97005",
    "sg:province":"OR",
    "wof:name":"Zipline Design",
    "wof:placetype":"venue"
},
  "geometry": {"coordinates":[-122.821072,45.482816],"type":"Point"}
}