{
  "type": "Feature",
  "properties": {
    "iso:country":"US",
    "sg:address":"1224 NW 122nd Ave",
    "sg:city":"Portland",
    "sg:classifiers":[
        {
            "category":"Professional",
            "subcategory":"Accounting & Tax Preparation",
            "type":"Services"
        }
    ],
    "sg:phone":"+1 503 641 2277",
    "sg:postcode":"97229",
    "sg:province":"OR",
    "wof:name":"Lawrence Randall Inc",
    "wof:placetype":"venue"
},
  "geometry": {"coordinates":[-122.802261,45.528795],"type":"Point"}
}