{
  "type": "Feature",
  "properties": {
    "iso:country":"US",
    "sg:address":"300 Jackson Creek Dr",
    "sg:city":"Jacksonville",
    "sg:classifiers":[
        {
            "category":"Home & Garden",
            "subcategory":"Furniture",
            "type":"Retail Goods"
        }
    ],
    "sg:phone":"+1 707 968 9032",
    "sg:postcode":"97530",
    "sg:province":"OR",
    "wof:name":"Manor Born",
    "wof:placetype":"venue"
},
  "geometry": {"coordinates":[-122.964923,42.318432],"type":"Point"}
}