{
  "type": "Feature",
  "properties": {
    "addr:full":"15 NE Broadway St Portland OR 97232",
    "addr:housenumber":"15",
    "addr:postcode":"97232",
    "addr:street":"Ne Broadway St",
    "iso:country":"US",
    "sg:address":"15 NE Broadway St",
    "sg:city":"Portland",
    "sg:classifiers":[
        {
            "category":"Building & Trades",
            "subcategory":"Locksmith",
            "type":"Services"
        }
    ],
    "sg:phone":"+1 971 228 5099",
    "sg:postcode":"97232",
    "sg:province":"OR",
    "sg:tags":[
        "key"
    ],
    "wof:name":"Emergency Locksmith",
    "wof:placetype":"venue"
},
  "geometry": {"coordinates":[-122.66635100000001,45.535227],"type":"Point"}
}