{
  "type": "Feature",
  "properties": {
    "addr:full":"379 Bond Rd Shady Cove OR 97539",
    "addr:housenumber":"379",
    "addr:postcode":"97539",
    "addr:street":"Bond Rd",
    "iso:country":"US",
    "sg:address":"379 Bond Rd",
    "sg:city":"Shady Cove",
    "sg:classifiers":[
        {
            "category":"Professional",
            "type":"Services"
        }
    ],
    "sg:phone":"+1 541 878 2268",
    "sg:postcode":"97539",
    "sg:province":"OR",
    "wof:name":"Burns Diversified LLC",
    "wof:placetype":"venue"
},
  "geometry": {"coordinates":[-122.829525,42.599149],"type":"Point"}
}