{
  "type": "Feature",
  "properties": {
    "addr:full":"5020 SE Division St Portland OR 97206",
    "addr:housenumber":"5020",
    "addr:postcode":"97206",
    "addr:street":"Se Division St",
    "iso:country":"US",
    "sg:address":"5020 SE Division St",
    "sg:city":"Portland",
    "sg:classifiers":[
        {
            "category":"Manufacturing",
            "subcategory":"Jewelry",
            "type":"Manufacturing & Wholesale Goods"
        }
    ],
    "sg:phone":"+1 503 233 8112",
    "sg:postcode":"97206",
    "sg:province":"OR",
    "sg:tags":[
        "repair",
        "fine",
        "manufacturer"
    ],
    "wof:name":"Cascade Silversmiths",
    "wof:placetype":"venue"
},
  "geometry": {"coordinates":[-122.610169,45.505234],"type":"Point"}
}