{
  "type": "Feature",
  "properties": {
    "iso:country":"US",
    "sg:address":"1815 SE 82nd Ave",
    "sg:city":"Portland",
    "sg:classifiers":[
        {
            "category":"Restaurant",
            "type":"Food & Drink"
        }
    ],
    "sg:phone":"+1 503 774 0061",
    "sg:postcode":"97216",
    "sg:province":"OR",
    "wof:name":"Ah Fong Kitchen",
    "wof:placetype":"venue"
},
  "geometry": {"coordinates":[-122.579002,45.514599],"type":"Point"}
}