{
  "type": "Feature",
  "properties": {
    "iso:country":"US",
    "sg:address":"2410 SE 121st Ave",
    "sg:city":"Portland",
    "sg:classifiers":[
        {
            "category":"Arts & Performance",
            "subcategory":"Theater",
            "type":"Entertainment"
        }
    ],
    "sg:phone":"+1 503 761 2313",
    "sg:postcode":"97216",
    "sg:province":"OR",
    "sg:tags":[
        "entertainer"
    ],
    "wof:name":"T K BARNARD Construction LLC",
    "wof:placetype":"venue"
},
  "geometry": {"coordinates":[-122.538878,45.504635],"type":"Point"}
}