{
  "type": "Feature",
  "properties": {
    "iso:country":"US",
    "sg:address":"245 SW G St",
    "sg:city":"Grants Pass",
    "sg:classifiers":[
        {
            "category":"Wholesale",
            "subcategory":"Hardware",
            "type":"Manufacturing & Wholesale Goods"
        }
    ],
    "sg:phone":"+1 541 472 8094",
    "sg:postcode":"97526",
    "sg:province":"OR",
    "sg:tags":[
        "tool"
    ],
    "wof:name":"West Coast Ind Supply",
    "wof:placetype":"venue"
},
  "geometry": {"coordinates":[-123.32892,42.439431],"type":"Point"}
}