{
  "type": "Feature",
  "properties": {
    "addr:full":"30528 Ridge St Lebanon OR 97355",
    "addr:housenumber":"30528",
    "addr:postcode":"97355",
    "addr:street":"Ridge St",
    "iso:country":"US",
    "sg:address":"30528 Ridge St",
    "sg:city":"Lebanon",
    "sg:classifiers":[
        {
            "category":"Shopping",
            "subcategory":"Hobbies, Toys, & Games",
            "type":"Retail Goods"
        }
    ],
    "sg:phone":"+1 541 259 1175",
    "sg:postcode":"97355",
    "sg:province":"OR",
    "wof:name":"C Treasures & Gifts",
    "wof:placetype":"venue"
},
  "geometry": {"coordinates":[-122.864285,44.479287],"type":"Point"}
}