{
  "type": "Feature",
  "properties": {
    "iso:country":"US",
    "sg:address":"9307 SW Beaverton-Hillsdale Hwy",
    "sg:city":"Beaverton",
    "sg:classifiers":[
        {
            "category":"Shopping",
            "subcategory":"Department Store",
            "type":"Retail Goods"
        }
    ],
    "sg:phone":"+1 503 292 0105",
    "sg:postcode":"97225",
    "sg:province":"OR",
    "sg:tags":[
        "shop"
    ],
    "sg:website":"www.pier1.com",
    "wof:name":"Pier 1 Imports",
    "wof:placetype":"venue"
},
  "geometry": {"coordinates":[-122.77355799999999,45.486548],"type":"Point"}
}