{
  "type": "Feature",
  "properties": {
    "iso:country":"US",
    "sg:address":"850 High St NE",
    "sg:city":"Salem",
    "sg:classifiers":[
        {
            "category":"Restaurant",
            "type":"Food & Drink"
        }
    ],
    "sg:phone":"+1 503 763 6063",
    "sg:postcode":"97301",
    "sg:province":"OR",
    "wof:name":"LA Mixteca Restaurant",
    "wof:placetype":"venue"
},
  "geometry": {"coordinates":[-123.03294,44.948012],"type":"Point"}
}