{
  "type": "Feature",
  "properties": {
    "iso:country":"US",
    "sg:address":"18454 SE Stephens Cir",
    "sg:city":"Portland",
    "sg:classifiers":[
        {
            "category":"Professional",
            "type":"Services"
        }
    ],
    "sg:phone":"+1 503 666 8571",
    "sg:postcode":"97233",
    "sg:province":"OR",
    "wof:name":"All About Dogs",
    "wof:placetype":"venue"
},
  "geometry": {"coordinates":[-122.472751,45.509659],"type":"Point"}
}