{
  "type": "Feature",
  "properties": {
    "iso:country":"US",
    "sg:address":"3016 SW Willow Pkwy",
    "sg:city":"Gresham",
    "sg:classifiers":[
        {
            "category":"Wholesale",
            "subcategory":"Electrical",
            "type":"Manufacturing & Wholesale Goods"
        }
    ],
    "sg:phone":"+1 503 465 2343",
    "sg:postcode":"97080",
    "sg:province":"OR",
    "sg:tags":[
        "testing",
        "apparatus"
    ],
    "wof:name":"R/D Tech",
    "wof:placetype":"venue"
},
  "geometry": {"coordinates":[-122.462002,45.476369],"type":"Point"}
}