{
  "type": "Feature",
  "properties": {
    "addr:full":"32222 Powder House Rd Philomath OR 97370",
    "addr:housenumber":"32222",
    "addr:postcode":"97370",
    "addr:street":"Powder House Rd",
    "iso:country":"US",
    "sg:address":"32222 Powder House Rd",
    "sg:city":"Philomath",
    "sg:classifiers":[
        {
            "category":"Real Estate",
            "subcategory":"Real Estate Services",
            "type":"Services"
        },
        {
            "category":"Real Estate",
            "subcategory":"Real Estate Agent",
            "type":"Services"
        }
    ],
    "sg:phone":"+1 541 929 6870",
    "sg:postcode":"97370",
    "sg:province":"OR",
    "sg:tags":[
        "management"
    ],
    "wof:name":"H & G Enterprises, Inc.",
    "wof:placetype":"venue"
},
  "geometry": {"coordinates":[-123.366088,44.514335],"type":"Point"}
}