{
  "type": "Feature",
  "properties": {
    "iso:country":"US",
    "sg:address":"52381 Columbia River Hwy",
    "sg:city":"Scappoose",
    "sg:classifiers":[
        {
            "category":"Restaurant",
            "type":"Food & Drink"
        }
    ],
    "sg:phone":"+1 503 543 3897",
    "sg:postcode":"97056",
    "sg:province":"OR",
    "wof:name":"Carole's Place",
    "wof:placetype":"venue"
},
  "geometry": {"coordinates":[-122.877982,45.755392],"type":"Point"}
}