{
  "type": "Feature",
  "properties": {
    "addr:full":"987 Kalmia St Junction City OR 97448",
    "addr:housenumber":"987",
    "addr:postcode":"97448",
    "addr:street":"Kalmia St",
    "iso:country":"US",
    "sg:address":"987 Kalmia St",
    "sg:city":"Junction City",
    "sg:classifiers":[
        {
            "category":"Real Estate",
            "subcategory":"Real Estate Agent",
            "type":"Services"
        }
    ],
    "sg:phone":"+1 541 998 3508",
    "sg:postcode":"97448",
    "sg:province":"OR",
    "sg:tags":[
        "inspection"
    ],
    "wof:name":"Ameri Spec Home Inspection Svc",
    "wof:placetype":"venue"
},
  "geometry": {"coordinates":[-123.207033,44.22177],"type":"Point"}
}