{
  "type": "Feature",
  "properties": {
    "addr:full":"9950 SE Stark St Portland OR 97216",
    "addr:housenumber":"9950",
    "addr:postcode":"97216",
    "addr:street":"Se Stark St",
    "iso:country":"US",
    "sg:address":"9950 SE Stark St",
    "sg:city":"Portland",
    "sg:classifiers":[
        {
            "category":"Restaurant",
            "type":"Food & Drink"
        }
    ],
    "sg:phone":"+1 503 257 5998",
    "sg:postcode":"97216",
    "sg:province":"OR",
    "sg:tags":[
        "eating"
    ],
    "wof:name":"Tony Romas",
    "wof:placetype":"venue"
},
  "geometry": {"coordinates":[-122.561016,45.518976],"type":"Point"}
}