{
  "type": "Feature",
  "properties": {
    "iso:country":"US",
    "sg:address":"14320 SW 22nd St",
    "sg:city":"Beaverton",
    "sg:classifiers":[
        {
            "category":"Building & Trades",
            "subcategory":"Landscaping Services",
            "type":"Services"
        }
    ],
    "sg:phone":"+1 503 643 9399",
    "sg:postcode":"97008",
    "sg:province":"OR",
    "sg:tags":[
        "tree"
    ],
    "wof:name":"Tree Artistry",
    "wof:placetype":"venue"
},
  "geometry": {"coordinates":[-122.82413200000001,45.472113],"type":"Point"}
}