{
  "type": "Feature",
  "properties": {
    "addr:full":"10300 SW Nimbus Ave Portland OR 97223",
    "addr:housenumber":"10300",
    "addr:postcode":"97223",
    "addr:street":"Sw Nimbus Ave",
    "iso:country":"US",
    "sg:address":"10300 SW Nimbus Ave",
    "sg:city":"Portland",
    "sg:classifiers":[
        {
            "category":"Professional",
            "subcategory":"Engineering",
            "type":"Services"
        }
    ],
    "sg:phone":"+1 503 603 1000",
    "sg:postcode":"97223",
    "sg:province":"OR",
    "sg:tags":[
        "environmental",
        "engineer"
    ],
    "wof:name":"Shaw Environmental/Infrstrctr",
    "wof:placetype":"venue"
},
  "geometry": {"coordinates":[-122.787659,45.446255],"type":"Point"}
}