{
  "type": "Feature",
  "properties": {
    "addr:full":"2120 N 1st St Hermiston OR 97838",
    "addr:housenumber":"2120",
    "addr:postcode":"97838",
    "addr:street":"N 1St St",
    "iso:country":"US",
    "sg:address":"2120 N 1st St",
    "sg:city":"Hermiston",
    "sg:classifiers":[
        {
            "category":"Home & Garden",
            "subcategory":"Furniture",
            "type":"Retail Goods"
        }
    ],
    "sg:phone":"+1 541 567 7017",
    "sg:postcode":"97838",
    "sg:province":"OR",
    "sg:tags":[
        "mattress"
    ],
    "wof:name":"Simmons Comfort World",
    "wof:placetype":"venue"
},
  "geometry": {"coordinates":[-119.290408,45.862235],"type":"Point"}
}