{
  "type": "Feature",
  "properties": {
    "iso:country":"US",
    "sg:address":"1707 SE Tempest Dr",
    "sg:city":"Bend",
    "sg:classifiers":[
        {
            "category":"Building & Trades",
            "subcategory":"Construction",
            "type":"Services"
        }
    ],
    "sg:phone":"+1 541 318 0605",
    "sg:postcode":"97702",
    "sg:province":"OR",
    "sg:tags":[
        "resurfacing",
        "laying",
        "refinishing",
        "floor"
    ],
    "wof:name":"Builders Resource",
    "wof:placetype":"venue"
},
  "geometry": {"coordinates":[-121.27913599999999,44.045942],"type":"Point"}
}