{
  "type": "Feature",
  "properties": {
    "iso:country":"US",
    "sg:address":"193 NE 3rd Ave",
    "sg:city":"Canby",
    "sg:classifiers":[
        {
            "category":"Freight",
            "type":"Transportation"
        }
    ],
    "sg:phone":"+1 503 266 5127",
    "sg:postcode":"97013",
    "sg:province":"OR",
    "sg:tags":[
        "operator",
        "local",
        "trucking"
    ],
    "wof:name":"Creative Deliveries",
    "wof:placetype":"venue"
},
  "geometry": {"coordinates":[-122.693562,45.26436],"type":"Point"}
}