{
  "type": "Feature",
  "properties": {
    "iso:country":"US",
    "sg:address":"1950 Echo Hollow Rd",
    "sg:city":"Eugene",
    "sg:classifiers":[
        {
            "category":"Shopping",
            "subcategory":"Hobbies, Toys, & Games",
            "type":"Retail Goods"
        },
        {
            "category":"Shopping",
            "subcategory":"Gifts & Souvenirs",
            "type":"Retail Goods"
        }
    ],
    "sg:phone":"+1 541 461 5694",
    "sg:postcode":"97402",
    "sg:province":"OR",
    "sg:tags":[
        "supply"
    ],
    "wof:name":"Mad Fool Games",
    "wof:placetype":"venue"
},
  "geometry": {"coordinates":[-123.168183,44.083522],"type":"Point"}
}