{
  "type": "Feature",
  "properties": {
    "addr:full":"3136 SE Harrison St Milwaukie OR 97222",
    "addr:housenumber":"3136",
    "addr:postcode":"97222",
    "addr:street":"Se Harrison St",
    "iso:country":"US",
    "sg:address":"3136 SE Harrison St",
    "sg:city":"Milwaukie",
    "sg:classifiers":[
        {
            "category":"Retail",
            "subcategory":"Repair Shop",
            "type":"Services"
        },
        {
            "category":"Retail",
            "subcategory":"Auto Repair",
            "type":"Services"
        }
    ],
    "sg:phone":"+1 503 659 0389",
    "sg:postcode":"97222",
    "sg:province":"OR",
    "sg:tags":[
        "repairing",
        "automobile"
    ],
    "wof:name":"Wrench's Auto Repair",
    "wof:placetype":"venue"
},
  "geometry": {"coordinates":[-122.629983,45.446513],"type":"Point"}
}