{
  "type": "Feature",
  "properties": {
    "addr:full":"1520 NE Broadway St Portland OR 97232",
    "addr:housenumber":"1520",
    "addr:postcode":"97232",
    "addr:street":"Ne Broadway St",
    "iso:country":"US",
    "sg:address":"1520 NE Broadway St",
    "sg:city":"Portland",
    "sg:classifiers":[
        {
            "category":"Home & Garden",
            "subcategory":"Home Furnishings",
            "type":"Retail Goods"
        }
    ],
    "sg:phone":"+1 503 288 1500",
    "sg:postcode":"97232",
    "sg:province":"OR",
    "sg:tags":[
        "kitchen",
        "accessory"
    ],
    "sg:website":"www.kitchenkaboodle.com",
    "wof:name":"Kitchen Kaboodle",
    "wof:placetype":"venue"
},
  "geometry": {"coordinates":[-122.64962199999999,45.534959],"type":"Point"}
}