{
  "type": "Feature",
  "properties": {
    "addr:full":"7025 NE Riverside Dr Mcminnville OR 97128",
    "addr:housenumber":"7025",
    "addr:postcode":"97128",
    "addr:street":"Ne Riverside Dr",
    "iso:country":"US",
    "sg:address":"7025 NE Riverside Dr",
    "sg:city":"Mcminnville",
    "sg:classifiers":[
        {
            "category":"Personal",
            "type":"Services"
        }
    ],
    "sg:phone":"+1 503 472 1458",
    "sg:postcode":"97128",
    "sg:province":"OR",
    "sg:tags":[
        "control",
        "weight"
    ],
    "wof:name":"Healthy Living Weight Mgt Ctr",
    "wof:placetype":"venue"
},
  "geometry": {"coordinates":[-123.16246,45.216389],"type":"Point"}
}