{
  "type": "Feature",
  "properties": {
    "addr:full":"737 NE 160th Ave Portland OR 97230",
    "addr:housenumber":"737",
    "addr:postcode":"97230",
    "addr:street":"Ne 160Th Ave",
    "iso:country":"US",
    "sg:address":"737 NE 160th Ave",
    "sg:city":"Portland",
    "sg:classifiers":[
        {
            "category":"Building & Trades",
            "subcategory":"Construction",
            "type":"Services"
        }
    ],
    "sg:phone":"+1 503 253 9297",
    "sg:postcode":"97230",
    "sg:province":"OR",
    "sg:tags":[
        "contractor"
    ],
    "wof:name":"Stewarts Construction & Contr",
    "wof:placetype":"venue"
},
  "geometry": {"coordinates":[-122.498755,45.529661],"type":"Point"}
}