{
  "type": "Feature",
  "properties": {
    "addr:full":"4244 W 6th Ave Eugene OR 97402",
    "addr:housenumber":"4244",
    "addr:postcode":"97402",
    "addr:street":"W 6Th Ave",
    "iso:country":"US",
    "sg:address":"4244 W 6th Ave",
    "sg:city":"Eugene",
    "sg:classifiers":[
        {
            "category":"Manufacturing",
            "subcategory":"Chemicals & Compounds",
            "type":"Manufacturing & Wholesale Goods"
        }
    ],
    "sg:phone":"+1 541 683 6677",
    "sg:postcode":"97402",
    "sg:province":"OR",
    "sg:tags":[
        "adhesive",
        "sealant"
    ],
    "sg:website":"www.hot-melt.com",
    "wof:name":"Industrial Adhesives Inc",
    "wof:placetype":"venue"
},
  "geometry": {"coordinates":[-123.166631,44.052982],"type":"Point"}
}