{
  "type": "Feature",
  "properties": {
    "iso:country":"US",
    "sg:address":"43464 SE Phelps Rd",
    "sg:city":"Sandy",
    "sg:classifiers":[
        {
            "category":"Food & Beverages",
            "subcategory":"Specialty",
            "type":"Retail Goods"
        },
        {
            "category":"Restaurant",
            "type":"Food & Drink"
        },
        {
            "category":"Manufacturing",
            "subcategory":"Food",
            "type":"Manufacturing & Wholesale Goods"
        }
    ],
    "sg:phone":"+1 503 668 7713",
    "sg:postcode":"97055",
    "sg:province":"OR",
    "sg:tags":[
        "product",
        "diet",
        "spices-wholesale",
        "health",
        "manufacturer"
    ],
    "sg:website":"http://www.oregonswildharvest.com",
    "wof:name":"Oregon's Wild Harvest",
    "wof:placetype":"venue"
},
  "geometry": {"coordinates":[-122.22633500000001,45.42162],"type":"Point"}
}