{
  "type": "Feature",
  "properties": {
    "iso:country":"US",
    "sg:address":"631 SE 223rd Ave",
    "sg:city":"Gresham",
    "sg:classifiers":[
        {
            "category":"Organizations",
            "subcategory":"Religious Organization",
            "type":"Services"
        }
    ],
    "sg:phone":"+1 503 491 8275",
    "sg:postcode":"97030",
    "sg:province":"OR",
    "wof:name":"Iglesia De Dios Maranatha",
    "wof:placetype":"venue"
},
  "geometry": {"coordinates":[-122.433862,45.517593],"type":"Point"}
}