{
  "type": "Feature",
  "properties": {
    "iso:country":"US",
    "sg:address":"888 SW 5th Ave",
    "sg:city":"Portland",
    "sg:classifiers":[
        {
            "category":"Banks & Credit Unions",
            "subcategory":"Investment Brokerage",
            "type":"Services"
        }
    ],
    "sg:phone":"+1 503 243 2123",
    "sg:postcode":"97204",
    "sg:province":"OR",
    "sg:tags":[
        "stock",
        "bond"
    ],
    "sg:website":"www.wellsfargo.com",
    "wof:name":"Wells Fargo Brokerage Svc",
    "wof:placetype":"venue"
},
  "geometry": {"coordinates":[-122.678015,45.518021],"type":"Point"}
}