{
  "type": "Feature",
  "properties": {
    "iso:country":"US",
    "sg:address":"235 S 15th St",
    "sg:city":"St Helens",
    "sg:classifiers":[
        {
            "category":"Organizations",
            "subcategory":"Religious Organization",
            "type":"Services"
        }
    ],
    "sg:phone":"+1 503 366 3031",
    "sg:postcode":"97051",
    "sg:province":"OR",
    "sg:tags":[
        "church"
    ],
    "wof:name":"Riverside Baptist Church",
    "wof:placetype":"venue"
},
  "geometry": {"coordinates":[-122.81222,45.858223],"type":"Point"}
}