{
  "type": "Feature",
  "properties": {
    "iso:country":"US",
    "sg:address":"5385 Red Leaf Dr S",
    "sg:city":"Salem",
    "sg:classifiers":[
        {
            "category":"Building & Trades",
            "subcategory":"Electrical",
            "type":"Services"
        }
    ],
    "sg:phone":"+1 503 315 9936",
    "sg:postcode":"97306",
    "sg:province":"OR",
    "sg:tags":[
        "electrical",
        "contractor"
    ],
    "wof:name":"Oregon Pioneer Electric Co",
    "wof:placetype":"venue"
},
  "geometry": {"coordinates":[-123.070555,44.877528],"type":"Point"}
}