{
  "type": "Feature",
  "properties": {
    "iso:country":"US",
    "sg:address":"295 Owens St S",
    "sg:city":"Salem",
    "sg:classifiers":[
        {
            "category":"Professional",
            "subcategory":"Business Services",
            "type":"Services"
        }
    ],
    "sg:phone":"+1 503 585 2725",
    "sg:postcode":"97302",
    "sg:province":"OR",
    "wof:name":"Health Solutions",
    "wof:placetype":"venue"
},
  "geometry": {"coordinates":[-123.04627600000001,44.930366],"type":"Point"}
}