{
  "type": "Feature",
  "properties": {
    "iso:country":"US",
    "sg:address":"7005 NE Prescott St",
    "sg:city":"Portland",
    "sg:classifiers":[
        {
            "category":"Shopping",
            "subcategory":"Music",
            "type":"Retail Goods"
        }
    ],
    "sg:phone":"+1 503 284 4828",
    "sg:postcode":"97218",
    "sg:province":"OR",
    "sg:tags":[
        "dvd's"
    ],
    "sg:website":"www.jumpjump.com",
    "wof:name":"Jump Jump Music",
    "wof:placetype":"venue"
},
  "geometry": {"coordinates":[-122.59092099999999,45.555658],"type":"Point"}
}