{
  "type": "Feature",
  "properties": {
    "addr:full":"34099 Beach Shore Dr Hermiston OR 97838",
    "addr:housenumber":"34099",
    "addr:postcode":"97838",
    "addr:street":"Beach Shore Dr",
    "iso:country":"US",
    "sg:address":"34099 Beach Shore Dr",
    "sg:city":"Hermiston",
    "sg:classifiers":[
        {
            "category":"Organizations",
            "subcategory":"Community Association",
            "type":"Services"
        }
    ],
    "sg:phone":"+1 541 567 5603",
    "sg:postcode":"97838",
    "sg:province":"OR",
    "sg:tags":[
        "club"
    ],
    "wof:name":"Mc Nary Yacht Club",
    "wof:placetype":"venue"
},
  "geometry": {"coordinates":[-119.168351,45.918212],"type":"Point"}
}