{
  "type": "Feature",
  "properties": {
    "iso:country":"US",
    "sg:address":"1248 McDaniel Rd",
    "sg:city":"Powell Butte",
    "sg:classifiers":[
        {
            "category":"Building & Trades",
            "subcategory":"Construction",
            "type":"Services"
        }
    ],
    "sg:phone":"+1 541 447 5565",
    "sg:postcode":"97753",
    "sg:province":"OR",
    "sg:tags":[
        "heavy"
    ],
    "wof:name":"A G Ontko Contracting",
    "wof:placetype":"venue"
},
  "geometry": {"coordinates":[-120.977565,44.307796],"type":"Point"}
}