{
  "type": "Feature",
  "properties": {
    "iso:country":"US",
    "sg:address":"1727 NE 13th Avenue Suite 103",
    "sg:city":"Portland",
    "sg:classifiers":[
        {
            "category":"Banks & Credit Unions",
            "subcategory":"Financial Services",
            "type":"Services"
        }
    ],
    "sg:phone":"+1 503 493 1791",
    "sg:postcode":"97212",
    "sg:province":"OR",
    "sg:tags":[
        "broker",
        "mortgage"
    ],
    "wof:name":"Pdx Mortgage Company",
    "wof:placetype":"venue"
},
  "geometry": {"coordinates":[-122.652531,45.535235],"type":"Point"}
}