{
  "type": "Feature",
  "properties": {
    "addr:full":"3090 Broadway St North Bend OR 97459",
    "addr:housenumber":"3090",
    "addr:postcode":"97459",
    "addr:street":"Broadway St",
    "iso:country":"US",
    "sg:address":"3090 Broadway St",
    "sg:city":"North Bend",
    "sg:classifiers":[
        {
            "category":"Insurance",
            "subcategory":"Insurance Agent",
            "type":"Services"
        }
    ],
    "sg:phone":"+1 541 756 3118",
    "sg:postcode":"97459",
    "sg:province":"OR",
    "wof:name":"Saif Corp",
    "wof:placetype":"venue"
},
  "geometry": {"coordinates":[-124.239345,43.393937],"type":"Point"}
}