{
  "type": "Feature",
  "properties": {
    "iso:country":"US",
    "sg:address":"17252 SW Starbuck Ln",
    "sg:city":"Beaverton",
    "sg:classifiers":[
        {
            "category":"Banks & Credit Unions",
            "subcategory":"Bureau De Change",
            "type":"Services"
        }
    ],
    "sg:phone":"+1 503 941 9528",
    "sg:postcode":"97007",
    "sg:province":"OR",
    "sg:tags":[
        "factor"
    ],
    "wof:name":"North American Bancard",
    "wof:placetype":"venue"
},
  "geometry": {"coordinates":[-122.854061,45.485773],"type":"Point"}
}