{
  "type": "Feature",
  "properties": {
    "addr:full":"1234 SW 18th Ave Portland OR 97205",
    "addr:housenumber":"1234",
    "addr:postcode":"97205",
    "addr:street":"Sw 18Th Ave",
    "iso:country":"US",
    "sg:address":"1234 SW 18th Ave",
    "sg:city":"Portland",
    "sg:classifiers":[
        {
            "category":"Professional",
            "subcategory":"Business Services",
            "type":"Services"
        }
    ],
    "sg:phone":"+1 503 548 4800",
    "sg:postcode":"97205",
    "sg:province":"OR",
    "sg:tags":[
        "holding"
    ],
    "wof:name":"Rubicon Global Research",
    "wof:placetype":"venue"
},
  "geometry": {"coordinates":[-122.692527,45.518211],"type":"Point"}
}