{
  "type": "Feature",
  "properties": {
    "addr:full":"112 NW 8th St Corvallis OR 97330",
    "addr:housenumber":"112",
    "addr:postcode":"97330",
    "addr:street":"Nw 8Th St",
    "iso:country":"US",
    "sg:address":"112 NW 8th St",
    "sg:city":"Corvallis",
    "sg:classifiers":[
        {
            "category":"Organizations",
            "subcategory":"Community Association",
            "type":"Services"
        }
    ],
    "sg:phone":"+1 541 393 0070",
    "sg:postcode":"97330",
    "sg:province":"OR",
    "sg:tags":[
        "fraternal"
    ],
    "wof:name":"Basswise",
    "wof:placetype":"venue"
},
  "geometry": {"coordinates":[-123.265834,44.566601],"type":"Point"}
}