{
  "type": "Feature",
  "properties": {
    "iso:country":"US",
    "sg:address":"815 S Broadway",
    "sg:city":"Coos Bay",
    "sg:classifiers":[
        {
            "category":"Wholesale",
            "subcategory":"Machinery & Supplies",
            "type":"Manufacturing & Wholesale Goods"
        },
        {
            "category":"Recreation",
            "subcategory":"Arcade",
            "type":"Entertainment"
        }
    ],
    "sg:phone":"+1 541 267 2184",
    "sg:postcode":"97420",
    "sg:province":"OR",
    "sg:tags":[
        "used",
        "ride",
        "park",
        "devices",
        "equipment",
        "amusement",
        "table",
        "coin",
        "pool"
    ],
    "wof:name":"Martin Dodd Amusement Co",
    "wof:placetype":"venue"
},
  "geometry": {"coordinates":[-124.213336,43.360894],"type":"Point"}
}