{
  "type": "Feature",
  "properties": {
    "addr:full":"1078 Bennett Ln Eugene OR 97404",
    "addr:housenumber":"1078",
    "addr:postcode":"97404",
    "addr:street":"Bennett Ln",
    "iso:country":"US",
    "sg:address":"1078 Bennett Ln",
    "sg:city":"Eugene",
    "sg:classifiers":[
        {
            "category":"Personal",
            "subcategory":"Massage",
            "type":"Services"
        }
    ],
    "sg:phone":"+1 541 461 5950",
    "sg:postcode":"97404",
    "sg:province":"OR",
    "wof:name":"A Heavenly Touch Massage",
    "wof:placetype":"venue"
},
  "geometry": {"coordinates":[-123.147278,44.083124],"type":"Point"}
}