{
  "type": "Feature",
  "properties": {
    "iso:country":"US",
    "sg:address":"1215 Hill St SE",
    "sg:city":"Albany",
    "sg:classifiers":[
        {
            "category":"Organizations",
            "subcategory":"Non-profit Organization",
            "type":"Services"
        }
    ],
    "sg:phone":"+1 541 926 6666",
    "sg:postcode":"97322",
    "sg:province":"OR",
    "sg:website":"www.bgc-albany.org",
    "wof:name":"Boys & Girls Club Of Albany",
    "wof:placetype":"venue"
},
  "geometry": {"coordinates":[-123.091507,44.629843],"type":"Point"}
}