{
  "type": "Feature",
  "properties": {
    "iso:country":"US",
    "sg:address":"3280 SW 170th Ave Ofc",
    "sg:city":"Beaverton",
    "sg:classifiers":[
        {
            "category":"Real Estate",
            "subcategory":"Real Estate Operator",
            "type":"Services"
        }
    ],
    "sg:phone":"+1 503 642 4055",
    "sg:postcode":"97006",
    "sg:province":"OR",
    "sg:tags":[
        "apartment"
    ],
    "wof:name":"Woodcreek Apartments",
    "wof:placetype":"venue"
},
  "geometry": {"coordinates":[-122.851997,45.4958],"type":"Point"}
}