{
  "type": "Feature",
  "properties": {
    "iso:country":"US",
    "sg:address":"761 SE 202nd Ave",
    "sg:city":"Portland",
    "sg:classifiers":[
        {
            "category":"Retail",
            "subcategory":"Auto Repair",
            "type":"Services"
        }
    ],
    "sg:phone":"+1 503 465 0476",
    "sg:postcode":"97233",
    "sg:province":"OR",
    "wof:name":"Driveline Tech & Fabrication",
    "wof:placetype":"venue"
},
  "geometry": {"coordinates":[-122.45532799999999,45.517044],"type":"Point"}
}