{
  "type": "Feature",
  "properties": {
    "iso:country":"US",
    "sg:address":"4216 SE Mitchell St",
    "sg:city":"Portland",
    "sg:classifiers":[
        {
            "category":"Shopping",
            "type":"Retail Goods"
        }
    ],
    "sg:phone":"+1 503 771 1985",
    "sg:postcode":"97206",
    "sg:province":"OR",
    "sg:tags":[
        "cosmetic",
        "perfume"
    ],
    "wof:name":"Savonerie",
    "wof:placetype":"venue"
},
  "geometry": {"coordinates":[-122.61863099999999,45.485604],"type":"Point"}
}