{
  "type": "Feature",
  "properties": {
    "iso:country":"US",
    "sg:address":"2200 Wasco Ave",
    "sg:city":"Hood River",
    "sg:classifiers":[
        {
            "category":"Home & Garden",
            "subcategory":"Furniture",
            "type":"Retail Goods"
        }
    ],
    "sg:phone":"+1 541 386 2249",
    "sg:postcode":"97031",
    "sg:province":"OR",
    "sg:tags":[
        "cabinet"
    ],
    "wof:name":"Columbia Cabinets",
    "wof:placetype":"venue"
},
  "geometry": {"coordinates":[-121.535078,45.711],"type":"Point"}
}