{
  "type": "Feature",
  "properties": {
    "addr:full":"15914 Colvin Rd Clatskanie OR 97016",
    "addr:housenumber":"15914",
    "addr:postcode":"97016",
    "addr:street":"Colvin Rd",
    "iso:country":"US",
    "sg:address":"15914 Colvin Rd",
    "sg:city":"Clatskanie",
    "sg:classifiers":[
        {
            "category":"Freight",
            "type":"Transportation"
        }
    ],
    "sg:phone":"+1 503 728 2548",
    "sg:postcode":"97016",
    "sg:province":"OR",
    "sg:tags":[
        "operator",
        "local",
        "trucking"
    ],
    "wof:name":"Johnson Art L Trucking",
    "wof:placetype":"venue"
},
  "geometry": {"coordinates":[-123.267629,46.110671],"type":"Point"}
}