{
  "type": "Feature",
  "properties": {
    "iso:country":"US",
    "sg:address":"136 NW 9th St",
    "sg:city":"Toledo",
    "sg:classifiers":[
        {
            "category":"Recreation",
            "type":"Entertainment"
        }
    ],
    "sg:phone":"+1 541 336 5875",
    "sg:postcode":"97391",
    "sg:province":"OR",
    "wof:name":"Sea Quell Charters",
    "wof:placetype":"venue"
},
  "geometry": {"coordinates":[-123.939346,44.626508],"type":"Point"}
}