{
  "type": "Feature",
  "properties": {
    "iso:country":"US",
    "sg:address":"210 Boardman Ave NW",
    "sg:city":"Boardman",
    "sg:classifiers":[
        {
            "category":"Bus Charters",
            "type":"Transportation"
        }
    ],
    "sg:phone":"+1 541 481 7551",
    "sg:postcode":"97818",
    "sg:province":"OR",
    "sg:tags":[
        "rental"
    ],
    "wof:name":"Mid Columbia Bus Co",
    "wof:placetype":"venue"
},
  "geometry": {"coordinates":[-119.706914,45.83961],"type":"Point"}
}