{
  "type": "Feature",
  "properties": {
    "addr:full":"2400 SW Scenic Dr Portland OR 97225",
    "addr:housenumber":"2400",
    "addr:postcode":"97225",
    "addr:street":"Sw Scenic Dr",
    "iso:country":"US",
    "sg:address":"2400 SW Scenic Dr",
    "sg:city":"Portland",
    "sg:classifiers":[
        {
            "category":"Professional",
            "subcategory":"Management & Consulting",
            "type":"Services"
        }
    ],
    "sg:phone":"+1 503 292 2500",
    "sg:postcode":"97225",
    "sg:province":"OR",
    "wof:name":"PS Golding Inc",
    "wof:placetype":"venue"
},
  "geometry": {"coordinates":[-122.770971,45.503474],"type":"Point"}
}