{
  "type": "Feature",
  "properties": {
    "iso:country":"US",
    "sg:address":"315 Fir St",
    "sg:city":"La Grande",
    "sg:classifiers":[
        {
            "category":"Shopping",
            "subcategory":"Used Merchandise",
            "type":"Retail Goods"
        }
    ],
    "sg:phone":"+1 541 963 2941",
    "sg:postcode":"97850",
    "sg:province":"OR",
    "wof:name":"Salvation Army Thrift Store",
    "wof:placetype":"venue"
},
  "geometry": {"coordinates":[-118.09120299999999,45.328152],"type":"Point"}
}