{
  "type": "Feature",
  "properties": {
    "iso:country":"US",
    "sg:address":"11700 SW Hall Blvd",
    "sg:city":"Portland",
    "sg:classifiers":[
        {
            "category":"Shopping",
            "subcategory":"Florist",
            "type":"Retail Goods"
        }
    ],
    "sg:phone":"+1 503 639 6717",
    "sg:postcode":"97223",
    "sg:province":"OR",
    "sg:website":"flowersbydonna.com",
    "wof:name":"Flowers by Donna",
    "wof:placetype":"venue"
},
  "geometry": {"coordinates":[-122.764999,45.434799],"type":"Point"}
}