{
  "type": "Feature",
  "properties": {
    "addr:full":"2367 State St Salem OR 97301",
    "addr:housenumber":"2367",
    "addr:postcode":"97301",
    "addr:street":"State St",
    "iso:country":"US",
    "sg:address":"2367 State St",
    "sg:city":"Salem",
    "sg:classifiers":[
        {
            "category":"Professional",
            "subcategory":"Management & Consulting",
            "type":"Services"
        },
        {
            "category":"Professional",
            "subcategory":"Accounting & Tax Preparation",
            "type":"Services"
        }
    ],
    "sg:phone":"+1 503 585 1393",
    "sg:postcode":"97301",
    "sg:province":"OR",
    "sg:tags":[
        "s",
        "return",
        "filing"
    ],
    "wof:name":"Mayer Financial Group",
    "wof:placetype":"venue"
},
  "geometry": {"coordinates":[-123.01434,44.933766],"type":"Point"}
}