{
  "type": "Feature",
  "properties": {
    "iso:country":"US",
    "sg:address":"227 SE 6th St",
    "sg:city":"Madras",
    "sg:classifiers":[
        {
            "category":"Health Services",
            "subcategory":"Doctor",
            "type":"Services"
        }
    ],
    "sg:phone":"+1 541 475 5525",
    "sg:postcode":"97741",
    "sg:province":"OR",
    "sg:tags":[
        "physician",
        "surgeon"
    ],
    "wof:name":"Dr Beth Davis",
    "wof:placetype":"venue"
},
  "geometry": {"coordinates":[-121.128534,44.633186],"type":"Point"}
}