{
  "type": "Feature",
  "properties": {
    "iso:country":"US",
    "sg:address":"3930 SE 151st Ave",
    "sg:city":"Portland",
    "sg:classifiers":[
        {
            "category":"Shopping",
            "subcategory":"Crafts & Fabrics",
            "type":"Retail Goods"
        }
    ],
    "sg:phone":"+1 503 762 0946",
    "sg:postcode":"97236",
    "sg:province":"OR",
    "sg:tags":[
        "sewing"
    ],
    "wof:name":"Sew Creative",
    "wof:placetype":"venue"
},
  "geometry": {"coordinates":[-122.507318,45.493691],"type":"Point"}
}