{
  "type": "Feature",
  "properties": {
    "addr:full":"23855 SW 195th Pl Sherwood OR 97140",
    "addr:housenumber":"23855",
    "addr:postcode":"97140",
    "addr:street":"Sw 195Th Pl",
    "iso:country":"US",
    "sg:address":"23855 SW 195th Pl",
    "sg:city":"Sherwood",
    "sg:classifiers":[
        {
            "category":"Manufacturing",
            "subcategory":"Lumber",
            "type":"Manufacturing & Wholesale Goods"
        }
    ],
    "sg:phone":"+1 503 625 6052",
    "sg:postcode":"97140",
    "sg:province":"OR",
    "sg:tags":[
        "a",
        "farm",
        "tree",
        "operates",
        "as",
        "christmas"
    ],
    "wof:name":"Sleighbells Of Sherwood",
    "wof:placetype":"venue"
},
  "geometry": {"coordinates":[-122.878613,45.345907],"type":"Point"}
}