{
  "type": "Feature",
  "properties": {
    "iso:country":"US",
    "sg:address":"4349 Baldwin Creek Dr",
    "sg:city":"Mt Hood Parkdale",
    "sg:classifiers":[
        {
            "category":"Retail",
            "subcategory":"Repair Shop",
            "type":"Services"
        }
    ],
    "sg:phone":"+1 541 352 6090",
    "sg:postcode":"97041",
    "sg:province":"OR",
    "sg:tags":[
        "upholsterer"
    ],
    "wof:name":"Backstitch Upholstery",
    "wof:placetype":"venue"
},
  "geometry": {"coordinates":[-121.570326,45.558787],"type":"Point"}
}