{
  "type": "Feature",
  "properties": {
    "iso:country":"US",
    "sg:address":"827 Nadine Ave",
    "sg:city":"Eugene",
    "sg:classifiers":[
        {
            "category":"Wholesale",
            "subcategory":"Non-durable Goods",
            "type":"Manufacturing & Wholesale Goods"
        }
    ],
    "sg:phone":"+1 541 689 1146",
    "sg:postcode":"97404",
    "sg:province":"OR",
    "wof:name":"Expeditors Unlimited Corp",
    "wof:placetype":"venue"
},
  "geometry": {"coordinates":[-123.143101,44.080604],"type":"Point"}
}