{
  "type": "Feature",
  "properties": {
    "iso:country":"US",
    "sg:address":"1924 NW Division St",
    "sg:city":"Corvallis",
    "sg:classifiers":[
        {
            "category":"Social Services",
            "subcategory":"Child Care",
            "type":"Services"
        }
    ],
    "sg:phone":"+1 541 752 2868",
    "sg:postcode":"97330",
    "sg:province":"OR",
    "sg:tags":[
        "preschool"
    ],
    "wof:name":"Small World School",
    "wof:placetype":"venue"
},
  "geometry": {"coordinates":[-123.261363,44.586946],"type":"Point"}
}