{
  "type": "Feature",
  "properties": {
    "addr:full":"8260 N Interstate Ave Portland OR 97217",
    "addr:housenumber":"8260",
    "addr:postcode":"97217",
    "addr:street":"N Interstate Ave",
    "iso:country":"US",
    "sg:address":"8260 N Interstate Ave",
    "sg:city":"Portland",
    "sg:classifiers":[
        {
            "category":"Government",
            "subcategory":"Office",
            "type":"Public Place"
        }
    ],
    "sg:phone":"+1 503 299 2999",
    "sg:postcode":"97217",
    "sg:province":"OR",
    "sg:tags":[
        "government-united",
        "transportation",
        "state"
    ],
    "wof:name":"Dmv Field Office",
    "wof:placetype":"venue"
},
  "geometry": {"coordinates":[-122.682232,45.582466],"type":"Point"}
}