{
  "type": "Feature",
  "properties": {
    "iso:country":"US",
    "sg:address":"110 Deer Creek Rd",
    "sg:city":"Selma",
    "sg:classifiers":[
        {
            "category":"Food & Beverages",
            "subcategory":"Groceries & Convenience Stores",
            "type":"Retail Goods"
        }
    ],
    "sg:phone":"+1 541 597 4349",
    "sg:postcode":"97538",
    "sg:province":"OR",
    "wof:name":"Ray's Food Place 71",
    "wof:placetype":"venue"
},
  "geometry": {"coordinates":[-123.615847,42.279202],"type":"Point"}
}