{
  "type": "Feature",
  "properties": {
    "iso:country":"US",
    "sg:address":"7405 SW 84th Ave",
    "sg:city":"Portland",
    "sg:classifiers":[
        {
            "category":"Home & Garden",
            "subcategory":"Hardware",
            "type":"Retail Goods"
        },
        {
            "category":"Shopping",
            "subcategory":"Crafts & Fabrics",
            "type":"Retail Goods"
        }
    ],
    "sg:phone":"+1 503 244 7415",
    "sg:postcode":"97223",
    "sg:province":"OR",
    "sg:tags":[
        "art",
        "store",
        "supply"
    ],
    "wof:name":"Tri State Exterior Systems Incorporated",
    "wof:placetype":"venue"
},
  "geometry": {"coordinates":[-122.76375299999999,45.46611],"type":"Point"}
}