{
  "type": "Feature",
  "properties": {
    "iso:country":"US",
    "sg:address":"82403 Butte Rd",
    "sg:city":"Creswell",
    "sg:classifiers":[
        {
            "category":"Professional",
            "subcategory":"Business Services",
            "type":"Services"
        }
    ],
    "sg:phone":"+1 541 895 5089",
    "sg:postcode":"97426",
    "sg:province":"OR",
    "sg:tags":[
        "recording",
        "studio"
    ],
    "wof:name":"Shofar Sound & Recording",
    "wof:placetype":"venue"
},
  "geometry": {"coordinates":[-123.04025300000001,43.900193],"type":"Point"}
}