{
  "type": "Feature",
  "properties": {
    "addr:full":"8305 SE Monterey Ave Portland OR 97086",
    "addr:housenumber":"8305",
    "addr:postcode":"97086",
    "addr:street":"Se Monterey Ave",
    "iso:country":"US",
    "sg:address":"8305 SE Monterey Ave",
    "sg:city":"Portland",
    "sg:classifiers":[
        {
            "category":"Communications",
            "subcategory":"Newspaper",
            "type":"Services"
        }
    ],
    "sg:phone":"+1 503 594 1028",
    "sg:postcode":"97086",
    "sg:province":"OR",
    "sg:tags":[
        "magazine"
    ],
    "wof:name":"Whitelight Publications Llc",
    "wof:placetype":"venue"
},
  "geometry": {"coordinates":[-122.577787,45.438447],"type":"Point"}
}