{
  "type": "Feature",
  "properties": {
    "addr:full":"120 NW 3rd St Prineville OR 97754",
    "addr:housenumber":"120",
    "addr:postcode":"97754",
    "addr:street":"Nw 3Rd St",
    "iso:country":"US",
    "sg:address":"120 NW 3rd St",
    "sg:city":"Prineville",
    "sg:classifiers":[
        {
            "category":"Sports & Exercise",
            "subcategory":"Gym",
            "type":"Entertainment"
        }
    ],
    "sg:phone":"+1 541 416 0455",
    "sg:postcode":"97754",
    "sg:province":"OR",
    "sg:tags":[
        "trainer",
        "club",
        "consultant",
        "gymnasium",
        "studio",
        "fitness",
        "health",
        "physical"
    ],
    "sg:website":"http://www.normsxtremefitness.com",
    "wof:name":"Norm's Xtreme Fitness Ctr",
    "wof:placetype":"venue"
},
  "geometry": {"coordinates":[-120.847348,44.302879],"type":"Point"}
}