{
  "type": "Feature",
  "properties": {
    "iso:country":"US",
    "sg:address":"4131 Yaquina Bay Rd",
    "sg:city":"Newport",
    "sg:classifiers":[
        {
            "category":"Bars & Pubs",
            "type":"Food & Drink"
        }
    ],
    "sg:phone":"+1 541 265 8761",
    "sg:postcode":"97365",
    "sg:province":"OR",
    "sg:tags":[
        "tavern"
    ],
    "wof:name":"Mad Dog Country Tavern",
    "wof:placetype":"venue"
},
  "geometry": {"coordinates":[-124.009638,44.602094],"type":"Point"}
}