{
  "type": "Feature",
  "properties": {
    "iso:country":"US",
    "sg:address":"170 N 19th St",
    "sg:city":"Cottage Grove",
    "sg:classifiers":[
        {
            "category":"Building & Trades",
            "subcategory":"Construction",
            "type":"Services"
        }
    ],
    "sg:phone":"+1 541 767 3634",
    "sg:postcode":"97424",
    "sg:province":"OR",
    "sg:tags":[
        "residential",
        "contractor"
    ],
    "wof:name":"Joseph L Herman",
    "wof:placetype":"venue"
},
  "geometry": {"coordinates":[-123.04689500000001,43.798706],"type":"Point"}
}