{
  "type": "Feature",
  "properties": {
    "addr:full":"11016 NE Sandy Boulevard Portland OR 97220",
    "addr:housenumber":"11016",
    "addr:postcode":"97220",
    "addr:street":"Ne Sandy Boulevard",
    "iso:country":"US",
    "sg:address":"11016 NE Sandy Boulevard",
    "sg:city":"Portland",
    "sg:classifiers":[
        {
            "category":"Retail",
            "subcategory":"Veterinary Services",
            "type":"Services"
        }
    ],
    "sg:phone":"+1 503 253 7977",
    "sg:postcode":"97220",
    "sg:province":"OR",
    "sg:tags":[
        "veterinarian"
    ],
    "wof:name":"East Portland Veterinary Clinic",
    "wof:placetype":"venue"
},
  "geometry": {"coordinates":[-122.549391,45.558263],"type":"Point"}
}