{
  "type": "Feature",
  "properties": {
    "iso:country":"US",
    "sg:address":"11570 SW River Bend Rd",
    "sg:city":"Mcminnville",
    "sg:classifiers":[
        {
            "category":"Building & Trades",
            "subcategory":"Construction",
            "type":"Services"
        }
    ],
    "sg:phone":"+1 503 835 8989",
    "sg:postcode":"97128",
    "sg:province":"OR",
    "sg:tags":[
        "house"
    ],
    "wof:name":"Don Watts Construction Inc",
    "wof:placetype":"venue"
},
  "geometry": {"coordinates":[-123.23591,45.149035],"type":"Point"}
}