{
  "type": "Feature",
  "properties": {
    "addr:full":"2155 Cubit St Eugene OR 97402",
    "addr:housenumber":"2155",
    "addr:postcode":"97402",
    "addr:street":"Cubit St",
    "iso:country":"US",
    "sg:address":"2155 Cubit St",
    "sg:city":"Eugene",
    "sg:classifiers":[
        {
            "category":"Food & Beverages",
            "subcategory":"Groceries & Convenience Stores",
            "type":"Retail Goods"
        }
    ],
    "sg:phone":"+1 541 688 8780",
    "sg:postcode":"97402",
    "sg:province":"OR",
    "wof:name":"Am/Pm Mini Market",
    "wof:placetype":"venue"
},
  "geometry": {"coordinates":[-123.168109,44.085431],"type":"Point"}
}