{
  "type": "Feature",
  "properties": {
    "iso:country":"US",
    "sg:address":"449 S 12th Ave",
    "sg:city":"Cornelius",
    "sg:classifiers":[
        {
            "category":"Manufacturing",
            "subcategory":"Wood Products",
            "type":"Manufacturing & Wholesale Goods"
        }
    ],
    "sg:phone":"+1 503 357 7253",
    "sg:postcode":"97113",
    "sg:province":"OR",
    "sg:tags":[
        "lumber"
    ],
    "wof:name":"Paul R. Scandlyn",
    "wof:placetype":"venue"
},
  "geometry": {"coordinates":[-123.05702599999999,45.516366],"type":"Point"}
}