{
  "type": "Feature",
  "properties": {
    "iso:country":"US",
    "sg:address":"493 NE 3rd Ave Ste E300",
    "sg:city":"Canby",
    "sg:classifiers":[
        {
            "category":"Professional",
            "subcategory":"Printing & Photocopies",
            "type":"Services"
        }
    ],
    "sg:phone":"+1 503 263 2814",
    "sg:postcode":"97013",
    "sg:province":"OR",
    "sg:tags":[
        "screen"
    ],
    "wof:name":"Sherman Ink Incoropoorated",
    "wof:placetype":"venue"
},
  "geometry": {"coordinates":[-122.688945,45.266037],"type":"Point"}
}