{
  "type": "Feature",
  "properties": {
    "addr:full":"6441 SW Canyon Ct Portland OR 97221",
    "addr:housenumber":"6441",
    "addr:postcode":"97221",
    "addr:street":"Sw Canyon Ct",
    "iso:country":"US",
    "sg:address":"6441 SW Canyon Ct",
    "sg:city":"Portland",
    "sg:classifiers":[
        {
            "category":"Insurance",
            "subcategory":"Insurance Agent",
            "type":"Services"
        }
    ],
    "sg:phone":"+1 503 292 4384",
    "sg:postcode":"97221",
    "sg:province":"OR",
    "wof:name":"Dennis Corser",
    "wof:placetype":"venue"
},
  "geometry": {"coordinates":[-122.74169999999999,45.508971],"type":"Point"}
}