{
  "type": "Feature",
  "properties": {
    "iso:country":"US",
    "sg:address":"12085 SW Hall Blvd Ste C",
    "sg:city":"Portland",
    "sg:classifiers":[
        {
            "category":"Casinos & Gambling",
            "type":"Entertainment"
        }
    ],
    "sg:phone":"+1 503 620 6994",
    "sg:postcode":"97223",
    "sg:province":"OR",
    "sg:tags":[
        "ticket",
        "agency",
        "lottery"
    ],
    "wof:name":"Maddys",
    "wof:placetype":"venue"
},
  "geometry": {"coordinates":[-122.76476700000001,45.432839],"type":"Point"}
}