{
  "type": "Feature",
  "properties": {
    "iso:country":"US",
    "sg:address":"821 NW Wall St",
    "sg:city":"Bend",
    "sg:classifiers":[
        {
            "category":"Professional",
            "subcategory":"Business Services",
            "type":"Services"
        }
    ],
    "sg:phone":"+1 541 383 5006",
    "sg:postcode":"97701",
    "sg:province":"OR",
    "sg:tags":[
        "interior",
        "design",
        "showroom",
        "art",
        "gallery"
    ],
    "wof:name":"The Sage House",
    "wof:placetype":"venue"
},
  "geometry": {"coordinates":[-121.314489,44.058748],"type":"Point"}
}