{
  "type": "Feature",
  "properties": {
    "iso:country":"US",
    "sg:address":"55490 SE White Cap Ln",
    "sg:city":"Sandy",
    "sg:classifiers":[
        {
            "category":"Building & Trades",
            "subcategory":"Construction",
            "type":"Services"
        }
    ],
    "sg:phone":"+1 503 622 1306",
    "sg:postcode":"97055",
    "sg:province":"OR",
    "sg:tags":[
        "sweeping",
        "windows",
        "lot"
    ],
    "wof:name":"More For Your Money Sweeping",
    "wof:placetype":"venue"
},
  "geometry": {"coordinates":[-122.094031,45.378059],"type":"Point"}
}