{
  "type": "Feature",
  "properties": {
    "iso:country":"US",
    "sg:address":"3030 Gateway St",
    "sg:city":"Springfield",
    "sg:classifiers":[
        {
            "category":"Autos & Motor Vehicles",
            "subcategory":"Automobile Sales",
            "type":"Retail Goods"
        },
        {
            "category":"Retail",
            "subcategory":"Auto Rental",
            "type":"Services"
        }
    ],
    "sg:phone":"+1 541 988 4957",
    "sg:postcode":"97477",
    "sg:province":"OR",
    "sg:tags":[
        "car",
        "leasing",
        "van"
    ],
    "sg:website":"http://avis.com/IYP_tl",
    "wof:name":"Avis Rent A Car",
    "wof:placetype":"venue"
},
  "geometry": {"coordinates":[-123.042216,44.076332],"type":"Point"}
}