{
  "type": "Feature",
  "properties": {
    "iso:country":"US",
    "sg:address":"2110 Dalton Dr",
    "sg:city":"Eugene",
    "sg:classifiers":[
        {
            "category":"Real Estate",
            "subcategory":"Real Estate Operator",
            "type":"Services"
        }
    ],
    "sg:phone":"+1 541 607 3279",
    "sg:postcode":"97404",
    "sg:province":"OR",
    "sg:tags":[
        "building",
        "nonresidential"
    ],
    "wof:name":"Ezstoresnet",
    "wof:placetype":"venue"
},
  "geometry": {"coordinates":[-123.135193,44.096902],"type":"Point"}
}