{
  "type": "Feature",
  "properties": {
    "iso:country":"US",
    "sg:address":"402 E 2nd St",
    "sg:city":"The Dalles",
    "sg:classifiers":[
        {
            "category":"Shopping",
            "subcategory":"Used Merchandise",
            "type":"Retail Goods"
        }
    ],
    "sg:phone":"+1 541 296 5175",
    "sg:postcode":"97058",
    "sg:province":"OR",
    "sg:tags":[
        "antique"
    ],
    "wof:name":"S & S 2nd St Antiques",
    "wof:placetype":"venue"
},
  "geometry": {"coordinates":[-121.180728,45.600656],"type":"Point"}
}