{
  "type": "Feature",
  "properties": {
    "addr:full":"180 E Main St Hillsboro OR 97123",
    "addr:housenumber":"180",
    "addr:postcode":"97123",
    "addr:street":"E Main St",
    "iso:country":"US",
    "sg:address":"180 E Main St",
    "sg:city":"Hillsboro",
    "sg:classifiers":[
        {
            "category":"Government",
            "subcategory":"Office",
            "type":"Public Place"
        }
    ],
    "sg:phone":"+1 503 640 3489",
    "sg:postcode":"97123",
    "sg:province":"OR",
    "wof:name":"Washington County Veterans Svc",
    "wof:placetype":"venue"
},
  "geometry": {"coordinates":[-122.989436,45.522588],"type":"Point"}
}