{
  "type": "Feature",
  "properties": {
    "addr:full":"7426 SW 53rd Ave Portland OR 97219",
    "addr:housenumber":"7426",
    "addr:postcode":"97219",
    "addr:street":"Sw 53Rd Ave",
    "iso:country":"US",
    "sg:address":"7426 SW 53rd Ave",
    "sg:city":"Portland",
    "sg:classifiers":[
        {
            "category":"Education",
            "subcategory":"School",
            "type":"Public Place"
        }
    ],
    "sg:phone":"+1 503 245 8164",
    "sg:postcode":"97219",
    "sg:province":"OR",
    "sg:website":"www.portlandfriendsschool.org",
    "wof:name":"Portland Friends School Inc",
    "wof:placetype":"venue"
},
  "geometry": {"coordinates":[-122.731655,45.471649],"type":"Point"}
}