{
  "type": "Feature",
  "properties": {
    "iso:country":"US",
    "sg:address":"217 S Main St",
    "sg:city":"Condon",
    "sg:classifiers":[
        {
            "category":"Personal",
            "subcategory":"Beauty Salon",
            "type":"Services"
        }
    ],
    "sg:phone":"+1 541 384 2092",
    "sg:postcode":"97823",
    "sg:province":"OR",
    "wof:name":"Trim West",
    "wof:placetype":"venue"
},
  "geometry": {"coordinates":[-120.184876,45.235969],"type":"Point"}
}