{
  "type": "Feature",
  "properties": {
    "addr:full":"560 W Division Ave Hermiston OR 97838",
    "addr:housenumber":"560",
    "addr:postcode":"97838",
    "addr:street":"W Division Ave",
    "iso:country":"US",
    "sg:address":"560 W Division Ave",
    "sg:city":"Hermiston",
    "sg:classifiers":[
        {
            "category":"Professional",
            "type":"Services"
        }
    ],
    "sg:phone":"+1 541 567 7060",
    "sg:postcode":"97838",
    "sg:province":"OR",
    "wof:name":"NW Crane Service Inc",
    "wof:placetype":"venue"
},
  "geometry": {"coordinates":[-119.297391,45.832283],"type":"Point"}
}