{
  "type": "Feature",
  "properties": {
    "addr:full":"14920 SW Bozarth Rd Powell Butte OR 97753",
    "addr:housenumber":"14920",
    "addr:postcode":"97753",
    "addr:street":"Sw Bozarth Rd",
    "iso:country":"US",
    "sg:address":"14920 SW Bozarth Rd",
    "sg:city":"Powell Butte",
    "sg:classifiers":[
        {
            "category":"Building & Trades",
            "subcategory":"Construction",
            "type":"Services"
        }
    ],
    "sg:phone":"+1 541 548 6740",
    "sg:postcode":"97753",
    "sg:province":"OR",
    "sg:tags":[
        "excavating",
        "contractor"
    ],
    "wof:name":"Cinder Rock Construction",
    "wof:placetype":"venue"
},
  "geometry": {"coordinates":[-121.040639,44.254883],"type":"Point"}
}