{
  "type": "Feature",
  "properties": {
    "iso:country":"US",
    "sg:address":"340 Craven St N",
    "sg:city":"Monmouth",
    "sg:classifiers":[
        {
            "category":"Professional",
            "type":"Services"
        }
    ],
    "sg:phone":"+1 503 838 2032",
    "sg:postcode":"97361",
    "sg:province":"OR",
    "wof:name":"Blueamber Studio",
    "wof:placetype":"venue"
},
  "geometry": {"coordinates":[-123.226867,44.851426],"type":"Point"}
}