{
  "type": "Feature",
  "properties": {
    "addr:full":"17223 NE Sacramento St Portland OR 97230",
    "addr:housenumber":"17223",
    "addr:postcode":"97230",
    "addr:street":"Ne Sacramento St",
    "iso:country":"US",
    "sg:address":"17223 NE Sacramento St",
    "sg:city":"Portland",
    "sg:classifiers":[
        {
            "category":"Professional",
            "subcategory":"Secretarial Services",
            "type":"Services"
        }
    ],
    "sg:phone":"+1 503 253 1639",
    "sg:postcode":"97230",
    "sg:province":"OR",
    "sg:tags":[
        "transcription",
        "medical"
    ],
    "wof:name":"Med Quist Inc",
    "wof:placetype":"venue"
},
  "geometry": {"coordinates":[-122.479978,45.54054],"type":"Point"}
}