{
  "type": "Feature",
  "properties": {
    "addr:full":"8405 SW Nimbus Ave Ste A Beaverton OR 97008",
    "addr:housenumber":"8405",
    "addr:postcode":"97008",
    "addr:street":"Sw Nimbus Ave Ste A",
    "iso:country":"US",
    "sg:address":"8405 SW Nimbus Ave Ste A",
    "sg:city":"Beaverton",
    "sg:classifiers":[
        {
            "category":"Professional",
            "subcategory":"Business Services",
            "type":"Services"
        }
    ],
    "sg:phone":"+1 503 268 5854",
    "sg:postcode":"97008",
    "sg:province":"OR",
    "sg:tags":[
        "holding"
    ],
    "wof:name":"Cabot Holdings, Inc.",
    "wof:placetype":"venue"
},
  "geometry": {"coordinates":[-122.789664,45.458976],"type":"Point"}
}