{
  "type": "Feature",
  "properties": {
    "iso:country":"US",
    "sg:address":"1606 Dowell Rd",
    "sg:city":"Grants Pass",
    "sg:classifiers":[
        {
            "category":"Food & Beverages",
            "subcategory":"Bakery",
            "type":"Retail Goods"
        }
    ],
    "sg:phone":"+1 541 476 4321",
    "sg:postcode":"97527",
    "sg:province":"OR",
    "wof:name":"Country Pies & Pastries",
    "wof:placetype":"venue"
},
  "geometry": {"coordinates":[-123.36691,42.423202],"type":"Point"}
}