{
  "type": "Feature",
  "properties": {
    "iso:country":"US",
    "sg:address":"14523 SE Stephens St",
    "sg:city":"Portland",
    "sg:classifiers":[
        {
            "category":"Building & Trades",
            "subcategory":"Construction",
            "type":"Services"
        }
    ],
    "sg:phone":"+1 503 253 5722",
    "sg:postcode":"97233",
    "sg:province":"OR",
    "sg:tags":[
        "excavating",
        "contractor"
    ],
    "wof:name":"M & J Excavation Inc",
    "wof:placetype":"venue"
},
  "geometry": {"coordinates":[-122.51383300000001,45.509599],"type":"Point"}
}