{
  "type": "Feature",
  "properties": {
    "iso:country":"US",
    "sg:address":"421 NE Knott St",
    "sg:city":"Portland",
    "sg:classifiers":[
        {
            "category":"Coffee & Tea",
            "type":"Food & Drink"
        }
    ],
    "sg:phone":"+1 503 288 9447",
    "sg:postcode":"97212",
    "sg:province":"OR",
    "wof:name":"McMenamins Pubs",
    "wof:placetype":"venue"
},
  "geometry": {"coordinates":[-122.66100299999999,45.542198],"type":"Point"}
}