{
  "type": "Feature",
  "properties": {
    "addr:full":"31919 Berlin Rd Lebanon OR 97355",
    "addr:postcode":"31919;97355",
    "addr:street":"Berlin Rd",
    "iso:country":"US",
    "sg:address":"31919 Berlin Rd",
    "sg:city":"Lebanon",
    "sg:classifiers":[
        {
            "category":"Freight",
            "type":"Transportation"
        }
    ],
    "sg:phone":"+1 541 259 3073",
    "sg:postcode":"97355",
    "sg:province":"OR",
    "sg:tags":[
        "trucking"
    ],
    "wof:name":"Fritz Farms Inc",
    "wof:placetype":"venue"
},
  "geometry": {"coordinates":[-122.813706,44.511247],"type":"Point"}
}