{
  "type": "Feature",
  "properties": {
    "addr:full":"2311 E Burnside St Portland OR 97214",
    "addr:housenumber":"2311",
    "addr:postcode":"97214",
    "addr:street":"E Burnside St",
    "iso:country":"US",
    "sg:address":"2311 E Burnside St",
    "sg:city":"Portland",
    "sg:classifiers":[
        {
            "category":"Health Services",
            "subcategory":"Health Practitioner",
            "type":"Services"
        }
    ],
    "sg:phone":"+1 503 233 3786",
    "sg:postcode":"97214",
    "sg:province":"OR",
    "sg:tags":[
        "acupuncture"
    ],
    "wof:name":"Tami Bean",
    "wof:placetype":"venue"
},
  "geometry": {"coordinates":[-122.642224,45.522945],"type":"Point"}
}