{
  "type": "Feature",
  "properties": {
    "addr:full":"101 N Main Ave Gresham OR 97030",
    "addr:housenumber":"101",
    "addr:postcode":"97030",
    "addr:street":"N Main Ave",
    "iso:country":"US",
    "sg:address":"101 N Main Ave",
    "sg:city":"Gresham",
    "sg:phone":"+1 503 665 9545",
    "sg:postcode":"97030",
    "sg:province":"OR",
    "wof:name":"Elegantly Funky",
    "wof:placetype":"venue"
},
  "geometry": {"coordinates":[-122.43094600000001,45.498348],"type":"Point"}
}