{
  "type": "Feature",
  "properties": {
    "iso:country":"US",
    "sg:address":"420 S 2nd St",
    "sg:city":"Creswell",
    "sg:classifiers":[
        {
            "category":"Real Estate",
            "subcategory":"Real Estate Operator",
            "type":"Services"
        }
    ],
    "sg:phone":"+1 541 895 3990",
    "sg:postcode":"97426",
    "sg:province":"OR",
    "sg:tags":[
        "apartment"
    ],
    "wof:name":"Camas Place Apartments",
    "wof:placetype":"venue"
},
  "geometry": {"coordinates":[-123.021033,43.913532],"type":"Point"}
}