{
  "type": "Feature",
  "properties": {
    "addr:full":"1401 Maple Park Dr Medford OR 97501",
    "addr:housenumber":"1401",
    "addr:postcode":"97501",
    "addr:street":"Maple Park Dr",
    "iso:country":"US",
    "sg:address":"1401 Maple Park Dr",
    "sg:city":"Medford",
    "sg:classifiers":[
        {
            "category":"Manufacturing",
            "subcategory":"Glass & Minerals",
            "type":"Manufacturing & Wholesale Goods"
        }
    ],
    "sg:phone":"+1 541 779 5635",
    "sg:postcode":"97501",
    "sg:province":"OR",
    "sg:tags":[
        "mfg"
    ],
    "wof:name":"Glass Nucleus",
    "wof:placetype":"venue"
},
  "geometry": {"coordinates":[-122.899145,42.332456],"type":"Point"}
}