{
  "type": "Feature",
  "properties": {
    "addr:full":"411 NW Park Portland OR 97209",
    "addr:housenumber":"411",
    "addr:postcode":"97209",
    "addr:street":"Nw Park",
    "iso:country":"US",
    "sg:address":"411 NW Park",
    "sg:city":"Portland",
    "sg:classifiers":[
        {
            "category":"Professional",
            "subcategory":"Computer Services",
            "type":"Services"
        }
    ],
    "sg:phone":"+1 503 232 2021",
    "sg:postcode":"97209",
    "sg:province":"OR",
    "sg:tags":[
        "ecommerce",
        "shopping-cart",
        "saas"
    ],
    "sg:website":"http://shopigniter.com",
    "wof:name":"ShopIgniter",
    "wof:placetype":"venue"
},
  "geometry": {"coordinates":[-122.679271,45.52633],"type":"Point"}
}