{
  "type": "Feature",
  "properties": {
    "addr:full":"1121 W Burnside St Portland OR 97209",
    "addr:housenumber":"1121",
    "addr:postcode":"97209",
    "addr:street":"W Burnside St",
    "iso:country":"US",
    "sg:address":"1121 W Burnside St",
    "sg:city":"Portland",
    "sg:classifiers":[
        {
            "category":"Restaurant",
            "type":"Food & Drink"
        }
    ],
    "sg:phone":"+1 503 595 2252",
    "sg:postcode":"97209",
    "sg:province":"OR",
    "sg:tags":[
        "mexican"
    ],
    "wof:name":"Baja Fresh",
    "wof:placetype":"venue"
},
  "geometry": {"coordinates":[-122.681999,45.5229],"type":"Point"}
}