{
  "type": "Feature",
  "properties": {
    "addr:full":"1220 SE 190th Ave Portland OR 97233",
    "addr:housenumber":"1220",
    "addr:postcode":"97233",
    "addr:street":"Se 190Th Ave",
    "iso:country":"US",
    "sg:address":"1220 SE 190th Ave",
    "sg:city":"Portland",
    "sg:classifiers":[
        {
            "category":"Building & Trades",
            "subcategory":"Construction",
            "type":"Services"
        }
    ],
    "sg:phone":"+1 503 674 7460",
    "sg:postcode":"97233",
    "sg:province":"OR",
    "sg:tags":[
        "contractor"
    ],
    "wof:name":"Interlaken Inc",
    "wof:placetype":"venue"
},
  "geometry": {"coordinates":[-122.467777,45.512435],"type":"Point"}
}