{
  "type": "Feature",
  "properties": {
    "iso:country":"US",
    "sg:address":"68865 Craig Loop",
    "sg:city":"Summerville",
    "sg:classifiers":[
        {
            "category":"Farming",
            "subcategory":"Livestock Farm",
            "type":"Manufacturing & Wholesale Goods"
        }
    ],
    "sg:phone":"+1 541 534 2601",
    "sg:postcode":"97876",
    "sg:province":"OR",
    "sg:tags":[
        "equine"
    ],
    "wof:name":"Dennis Shea",
    "wof:placetype":"venue"
},
  "geometry": {"coordinates":[-118.040707,45.535301],"type":"Point"}
}