{
  "type": "Feature",
  "properties": {
    "iso:country":"US",
    "sg:address":"434 NW 6th Ave Ste 304",
    "sg:city":"Portland",
    "sg:classifiers":[
        {
            "category":"Professional",
            "subcategory":"Management & Consulting",
            "type":"Services"
        },
        {
            "category":"Professional",
            "subcategory":"Engineering",
            "type":"Services"
        }
    ],
    "sg:phone":"+1 503 224 0333",
    "sg:postcode":"97209",
    "sg:province":"OR",
    "sg:tags":[
        "consultant",
        "ecological",
        "engineer",
        "environmental"
    ],
    "wof:name":"S W C A",
    "wof:placetype":"venue"
},
  "geometry": {"coordinates":[-122.676542,45.526164],"type":"Point"}
}