{
  "type": "Feature",
  "properties": {
    "addr:full":"12180 SW Scholls Ferry Rd Portland OR 97223",
    "addr:housenumber":"12180",
    "addr:postcode":"97223",
    "addr:street":"Sw Scholls Ferry Rd",
    "iso:country":"US",
    "sg:address":"12180 SW Scholls Ferry Rd",
    "sg:city":"Portland",
    "sg:phone":"+1 503 579 8899",
    "sg:postcode":"97223",
    "sg:province":"OR",
    "wof:name":"Wu's Open Kitchen",
    "wof:placetype":"venue"
},
  "geometry": {"coordinates":[-122.80199,45.443955],"type":"Point"}
}