{
  "type": "Feature",
  "properties": {
    "iso:country":"US",
    "sg:address":"33461 SE Peoria Rd",
    "sg:city":"Corvallis",
    "sg:classifiers":[
        {
            "category":"Government",
            "subcategory":"Office",
            "type":"Public Place"
        }
    ],
    "sg:phone":"+1 541 758 8254",
    "sg:postcode":"97333",
    "sg:province":"OR",
    "sg:tags":[
        "executive"
    ],
    "wof:name":"Kidco Head Start Cafeteria",
    "wof:placetype":"venue"
},
  "geometry": {"coordinates":[-123.212248,44.544749],"type":"Point"}
}