{
  "type": "Feature",
  "properties": {
    "addr:full":"7030 SE Holgate Blvd Portland OR 97206",
    "addr:housenumber":"7030",
    "addr:postcode":"97206",
    "addr:street":"Se Holgate Blvd",
    "iso:country":"US",
    "sg:address":"7030 SE Holgate Blvd",
    "sg:city":"Portland",
    "sg:classifiers":[
        {
            "category":"Organizations",
            "subcategory":"Religious Organization",
            "type":"Services"
        }
    ],
    "sg:phone":"+1 503 777 6555",
    "sg:postcode":"97206",
    "sg:province":"OR",
    "sg:tags":[
        "church"
    ],
    "wof:name":"Christian Deaf Church",
    "wof:placetype":"venue"
},
  "geometry": {"coordinates":[-122.59045,45.490173],"type":"Point"}
}