{
  "type": "Feature",
  "properties": {
    "addr:full":"4404 SE Umatilla St Portland OR 97206",
    "addr:housenumber":"4404",
    "addr:postcode":"97206",
    "addr:street":"Se Umatilla St",
    "iso:country":"US",
    "sg:address":"4404 SE Umatilla St",
    "sg:city":"Portland",
    "sg:classifiers":[
        {
            "category":"Manufacturing",
            "subcategory":"Musical Instruments",
            "type":"Manufacturing & Wholesale Goods"
        }
    ],
    "sg:phone":"+1 503 775 9575",
    "sg:postcode":"97206",
    "sg:province":"OR",
    "sg:tags":[
        "mfg"
    ],
    "wof:name":"Aquila USA Inc",
    "wof:placetype":"venue"
},
  "geometry": {"coordinates":[-122.616364,45.463568],"type":"Point"}
}