{
  "type": "Feature",
  "properties": {
    "iso:country":"US",
    "sg:address":"9570 SW Barbur Blvd",
    "sg:city":"Portland",
    "sg:classifiers":[
        {
            "category":"Professional",
            "subcategory":"Accounting & Tax Preparation",
            "type":"Services"
        }
    ],
    "sg:phone":"+1 503 245 0066",
    "sg:postcode":"97219",
    "sg:province":"OR",
    "sg:tags":[
        "accountant"
    ],
    "wof:name":"Thomas J Godish CPA PC",
    "wof:placetype":"venue"
},
  "geometry": {"coordinates":[-122.71418,45.456286],"type":"Point"}
}