{
  "type": "Feature",
  "properties": {
    "addr:full":"4435 NE Fremont St Portland OR 97213",
    "addr:housenumber":"4435",
    "addr:postcode":"97213",
    "addr:street":"Ne Fremont St",
    "iso:country":"US",
    "sg:address":"4435 NE Fremont St",
    "sg:city":"Portland",
    "sg:classifiers":[
        {
            "category":"Professional",
            "subcategory":"Lawyer & Legal Services",
            "type":"Services"
        }
    ],
    "sg:phone":"+1 503 281 2471",
    "sg:postcode":"97213",
    "sg:province":"OR",
    "wof:name":"Kimberly A Kaminski",
    "wof:placetype":"venue"
},
  "geometry": {"coordinates":[-122.61721199999999,45.548367],"type":"Point"}
}