{
  "type": "Feature",
  "properties": {
    "iso:country":"US",
    "sg:address":"544 SE Oak St",
    "sg:city":"Portland",
    "sg:classifiers":[
        {
            "category":"Retail",
            "subcategory":"Repair Shop",
            "type":"Services"
        }
    ],
    "sg:phone":"+1 503 236 2260",
    "sg:postcode":"97214",
    "sg:province":"OR",
    "sg:website":"http://www.goldleafdesign.net",
    "wof:name":"Gold Leaf Restoration",
    "wof:placetype":"venue"
},
  "geometry": {"coordinates":[-122.660281,45.520081],"type":"Point"}
}