{
  "type": "Feature",
  "properties": {
    "iso:country":"US",
    "sg:address":"356 NW Autumn Pl",
    "sg:city":"Corvallis",
    "sg:classifiers":[
        {
            "category":"Wholesale",
            "subcategory":"Non-durable Goods",
            "type":"Manufacturing & Wholesale Goods"
        }
    ],
    "sg:phone":"+1 541 753 4104",
    "sg:postcode":"97330",
    "sg:province":"OR",
    "sg:tags":[
        "advertising",
        "specialty"
    ],
    "sg:website":"www.autumnleavesstudio.com",
    "wof:name":"Autumn Leaves Studio",
    "wof:placetype":"venue"
},
  "geometry": {"coordinates":[-123.251024,44.599275],"type":"Point"}
}