{
  "type": "Feature",
  "properties": {
    "iso:country":"US",
    "sg:address":"1535 SE 9th Ave",
    "sg:city":"Portland",
    "sg:classifiers":[
        {
            "category":"Home & Garden",
            "subcategory":"Carpets & Floor Coverings",
            "type":"Retail Goods"
        }
    ],
    "sg:phone":"+1 503 226 0116",
    "sg:postcode":"97214",
    "sg:province":"OR",
    "sg:tags":[
        "carpeting"
    ],
    "wof:name":"Opie James Oriental Rugs Inc",
    "wof:placetype":"venue"
},
  "geometry": {"coordinates":[-122.656998,45.512001],"type":"Point"}
}