{
  "type": "Feature",
  "properties": {
    "iso:country":"US",
    "sg:address":"365 Bush St SE",
    "sg:city":"Salem",
    "sg:classifiers":[
        {
            "category":"Personal",
            "subcategory":"Beauty Salon",
            "type":"Services"
        }
    ],
    "sg:phone":"+1 503 588 5565",
    "sg:postcode":"97302",
    "sg:province":"OR",
    "sg:tags":[
        "shop"
    ],
    "wof:name":"Designer Cut",
    "wof:placetype":"venue"
},
  "geometry": {"coordinates":[-123.042624,44.931266],"type":"Point"}
}