{
  "type": "Feature",
  "properties": {
    "iso:country":"US",
    "sg:address":"3012 Pacific Ave",
    "sg:city":"Forest Grove",
    "sg:classifiers":[
        {
            "category":"Personal",
            "subcategory":"Beauty Salon",
            "type":"Services"
        }
    ],
    "sg:phone":"+1 503 357 8460",
    "sg:postcode":"97116",
    "sg:province":"OR",
    "sg:tags":[
        "shop"
    ],
    "wof:name":"Cutting Cousins Inc",
    "wof:placetype":"venue"
},
  "geometry": {"coordinates":[-123.092908,45.520124],"type":"Point"}
}