{
  "type": "Feature",
  "properties": {
    "iso:country":"US",
    "sg:address":"911 NE Hwy 99W",
    "sg:city":"Mcminnville",
    "sg:classifiers":[
        {
            "category":"Restaurant",
            "type":"Food & Drink"
        }
    ],
    "sg:phone":"+1 503 472 8789",
    "sg:postcode":"97128",
    "sg:province":"OR",
    "sg:tags":[
        "grocery",
        "eating",
        "caterer"
    ],
    "wof:name":"Deli Yogurt Express",
    "wof:placetype":"venue"
},
  "geometry": {"coordinates":[-123.189251,45.224949],"type":"Point"}
}