{
  "type": "Feature",
  "properties": {
    "iso:country":"US",
    "sg:address":"1420 Esplanade Ave",
    "sg:city":"Klamath Falls",
    "sg:classifiers":[
        {
            "category":"Banks & Credit Unions",
            "subcategory":"Bank",
            "type":"Services"
        }
    ],
    "sg:phone":"+1 541 850 9020",
    "sg:postcode":"97601",
    "sg:province":"OR",
    "sg:tags":[
        "loan",
        "broker",
        "mortgage"
    ],
    "sg:website":"www.allseasonsloans.com",
    "wof:name":"All Seasons Mortgage Group Inc",
    "wof:placetype":"venue"
},
  "geometry": {"coordinates":[-121.775817,42.230324],"type":"Point"}
}