{
  "type": "Feature",
  "properties": {
    "iso:country":"US",
    "sg:address":"16164 SW Dewberry Ln",
    "sg:city":"Portland",
    "sg:classifiers":[
        {
            "category":"Building & Trades",
            "subcategory":"Construction",
            "type":"Services"
        }
    ],
    "sg:phone":"+1 503 939 2172",
    "sg:postcode":"97223",
    "sg:province":"OR",
    "sg:tags":[
        "finishing",
        "wood"
    ],
    "wof:name":"David Vilson Construction Inc",
    "wof:placetype":"venue"
},
  "geometry": {"coordinates":[-122.84313299999999,45.424754],"type":"Point"}
}