{
  "type": "Feature",
  "properties": {
    "addr:full":"2987 Dalewood St Eugene OR 97404",
    "addr:housenumber":"2987",
    "addr:postcode":"97404",
    "addr:street":"Dalewood St",
    "iso:country":"US",
    "sg:address":"2987 Dalewood St",
    "sg:city":"Eugene",
    "sg:classifiers":[
        {
            "category":"Manufacturing",
            "subcategory":"Printing",
            "type":"Manufacturing & Wholesale Goods"
        }
    ],
    "sg:phone":"+1 541 688 7267",
    "sg:postcode":"97404",
    "sg:province":"OR",
    "sg:tags":[
        "lithographic",
        "commercial"
    ],
    "wof:name":"Best Impressions Printing Svc",
    "wof:placetype":"venue"
},
  "geometry": {"coordinates":[-123.128805,44.108757],"type":"Point"}
}