{
  "type": "Feature",
  "properties": {
    "iso:country":"US",
    "sg:address":"2525 NE Alberta St",
    "sg:city":"Portland",
    "sg:classifiers":[
        {
            "category":"Restaurant",
            "type":"Food & Drink"
        }
    ],
    "sg:phone":"+1 503 808 9601",
    "sg:postcode":"97211",
    "sg:province":"OR",
    "sg:tags":[
        "traditional",
        "chip",
        "american",
        "fish"
    ],
    "sg:website":"www.theoriginalhalibuts.com",
    "wof:name":"Halibut's",
    "wof:placetype":"venue"
},
  "geometry": {"coordinates":[-122.63948499999999,45.559071],"type":"Point"}
}