{
  "type": "Feature",
  "properties": {
    "iso:country":"US",
    "sg:address":"9450 SW Commerce Cir",
    "sg:city":"Wilsonville",
    "sg:classifiers":[
        {
            "category":"Wholesale",
            "subcategory":"Home Furnishings",
            "type":"Manufacturing & Wholesale Goods"
        }
    ],
    "sg:phone":"+1 503 582 8402",
    "sg:postcode":"97070",
    "sg:province":"OR",
    "sg:tags":[
        "material",
        "floor"
    ],
    "wof:name":"Wellmade USA Inc",
    "wof:placetype":"venue"
},
  "geometry": {"coordinates":[-122.77217400000001,45.334908],"type":"Point"}
}