{
  "type": "Feature",
  "properties": {
    "iso:country":"US",
    "sg:address":"4625 Silverton Rd NE",
    "sg:city":"Salem",
    "sg:classifiers":[
        {
            "category":"Professional",
            "subcategory":"Business Services",
            "type":"Services"
        }
    ],
    "sg:phone":"+1 503 371 1537",
    "sg:postcode":"97305",
    "sg:province":"OR",
    "sg:tags":[
        "organizing",
        "services-household"
    ],
    "wof:name":"Family Futures Management Inc",
    "wof:placetype":"venue"
},
  "geometry": {"coordinates":[-122.969421,44.969891],"type":"Point"}
}