{
  "type": "Feature",
  "properties": {
    "addr:full":"611 W Ash St Lebanon OR 97355",
    "addr:housenumber":"611",
    "addr:postcode":"97355",
    "addr:street":"W Ash St",
    "iso:country":"US",
    "sg:address":"611 W Ash St",
    "sg:city":"Lebanon",
    "sg:classifiers":[
        {
            "category":"Retail",
            "subcategory":"Auto Repair",
            "type":"Services"
        }
    ],
    "sg:phone":"+1 541 258 7297",
    "sg:postcode":"97355",
    "sg:province":"OR",
    "sg:tags":[
        "truck"
    ],
    "wof:name":"Hallcraft Inc",
    "wof:placetype":"venue"
},
  "geometry": {"coordinates":[-122.91601799999999,44.540063],"type":"Point"}
}