{
  "type": "Feature",
  "properties": {
    "addr:full":"12360 SW Leveton Dr Tualatin OR 97062",
    "addr:housenumber":"12360",
    "addr:postcode":"97062",
    "addr:street":"Sw Leveton Dr",
    "iso:country":"US",
    "sg:address":"12360 SW Leveton Dr",
    "sg:city":"Tualatin",
    "sg:classifiers":[
        {
            "category":"Food & Beverages",
            "subcategory":"Cheese",
            "type":"Retail Goods"
        },
        {
            "category":"Food & Beverages",
            "subcategory":"Groceries & Convenience Stores",
            "type":"Retail Goods"
        }
    ],
    "sg:phone":"+1 503 692 0662",
    "sg:postcode":"97062",
    "sg:province":"OR",
    "sg:tags":[
        "shop"
    ],
    "sg:website":"www.dpispecialtyfoods.com",
    "wof:name":"DPI Specialty Foods",
    "wof:placetype":"venue"
},
  "geometry": {"coordinates":[-122.80327699999999,45.384781],"type":"Point"}
}