{
  "type": "Feature",
  "properties": {
    "iso:country":"US",
    "sg:address":"1565 N 1st St Ste 4",
    "sg:city":"Hermiston",
    "sg:classifiers":[
        {
            "category":"Personal",
            "subcategory":"Beauty Salon",
            "type":"Services"
        }
    ],
    "sg:phone":"+1 541 289 4479",
    "sg:postcode":"97838",
    "sg:province":"OR",
    "wof:name":"Meringue Salon",
    "wof:placetype":"venue"
},
  "geometry": {"coordinates":[-119.29016900000001,45.851838],"type":"Point"}
}