{
  "type": "Feature",
  "properties": {
    "addr:full":"1835 NE Hillaire Ct Hillsboro OR 97124",
    "addr:housenumber":"1835",
    "addr:postcode":"97124",
    "addr:street":"Ne Hillaire Ct",
    "iso:country":"US",
    "sg:address":"1835 NE Hillaire Ct",
    "sg:city":"Hillsboro",
    "sg:classifiers":[
        {
            "category":"Organizations",
            "subcategory":"Religious Organization",
            "type":"Services"
        }
    ],
    "sg:phone":"+1 503 648 1695",
    "sg:postcode":"97124",
    "sg:province":"OR",
    "wof:name":"United Christian Fellowsh",
    "wof:placetype":"venue"
},
  "geometry": {"coordinates":[-122.96312399999999,45.529901],"type":"Point"}
}