{
  "type": "Feature",
  "properties": {
    "iso:country":"US",
    "sg:address":"1835 NE Hillaire Ct",
    "sg:city":"Hillsboro",
    "sg:classifiers":[
        {
            "category":"Organizations",
            "subcategory":"Religious Organization",
            "type":"Services"
        }
    ],
    "sg:phone":"+1 503 648 1695",
    "sg:postcode":"97124",
    "sg:province":"OR",
    "wof:name":"United Christian Fellowsh",
    "wof:placetype":"venue"
},
  "geometry": {"coordinates":[-122.963124,45.529901],"type":"Point"}
}