{
  "type": "Feature",
  "properties": {
    "iso:country":"US",
    "sg:address":"363 Shan Creek Rd",
    "sg:city":"Grants Pass",
    "sg:classifiers":[
        {
            "category":"Farming",
            "subcategory":"Livestock Farm",
            "type":"Manufacturing & Wholesale Goods"
        }
    ],
    "sg:phone":"+1 541 476 8272",
    "sg:postcode":"97527",
    "sg:province":"OR",
    "sg:tags":[
        "animal",
        "general"
    ],
    "wof:name":"Lar-Mar",
    "wof:placetype":"venue"
},
  "geometry": {"coordinates":[-123.507696,42.452495],"type":"Point"}
}