{
  "type": "Feature",
  "properties": {
    "iso:country":"US",
    "sg:address":"204 SE Main St",
    "sg:city":"Estacada",
    "sg:classifiers":[
        {
            "category":"Organizations",
            "subcategory":"Religious Organization",
            "type":"Services"
        }
    ],
    "sg:phone":"+1 503 630 6587",
    "sg:postcode":"97023",
    "sg:province":"OR",
    "sg:tags":[
        "clergy"
    ],
    "wof:name":"Estacada United Methodist Chr",
    "wof:placetype":"venue"
},
  "geometry": {"coordinates":[-122.333893,45.288621],"type":"Point"}
}