{
  "type": "Feature",
  "properties": {
    "iso:country":"US",
    "sg:address":"7605 3rd St SE",
    "sg:city":"Turner",
    "sg:classifiers":[
        {
            "category":"Government",
            "subcategory":"Fire Station",
            "type":"Public Place"
        }
    ],
    "sg:phone":"+1 503 743 2190",
    "sg:postcode":"97392",
    "sg:province":"OR",
    "sg:tags":[
        "department"
    ],
    "wof:name":"Turner Fire Dept",
    "wof:placetype":"venue"
},
  "geometry": {"coordinates":[-122.952991,44.844807],"type":"Point"}
}