{
  "type": "Feature",
  "properties": {
    "iso:country":"US",
    "sg:address":"25990 S Beeson Rd",
    "sg:city":"Beavercreek",
    "sg:classifiers":[
        {
            "category":"Professional",
            "type":"Services"
        }
    ],
    "sg:phone":"+1 503 632 8446",
    "sg:postcode":"97004",
    "sg:province":"OR",
    "wof:name":"Frostech",
    "wof:placetype":"venue"
},
  "geometry": {"coordinates":[-122.432655,45.229366],"type":"Point"}
}