{
  "type": "Feature",
  "properties": {
    "addr:full":"5724 Crater Lake Ave Central Point OR 97502",
    "addr:housenumber":"5724",
    "addr:postcode":"97502",
    "addr:street":"Crater Lake Ave",
    "iso:country":"US",
    "sg:address":"5724 Crater Lake Ave",
    "sg:city":"Central Point",
    "sg:classifiers":[
        {
            "category":"Autos & Motor Vehicles",
            "subcategory":"Auto Supplies",
            "type":"Retail Goods"
        }
    ],
    "sg:phone":"+1 541 772 6779",
    "sg:postcode":"97502",
    "sg:province":"OR",
    "sg:tags":[
        "tire"
    ],
    "wof:name":"C & C Tires Inc",
    "wof:placetype":"venue"
},
  "geometry": {"coordinates":[-122.855003,42.3988],"type":"Point"}
}