{
  "type": "Feature",
  "properties": {
    "addr:full":"NW Couch and 2nd Portland OR 97255",
    "addr:postcode":"97255",
    "addr:street":"Nw",
    "iso:country":"US",
    "sg:address":"NW Couch and 2nd",
    "sg:city":"Portland",
    "sg:classifiers":[
        {
            "category":"Restaurant",
            "type":"Food & Drink"
        }
    ],
    "sg:postcode":"97255",
    "sg:province":"OR",
    "sg:tags":[
        "new",
        "american"
    ],
    "wof:name":"NW Burger",
    "wof:placetype":"venue"
},
  "geometry": {"coordinates":[-122.672392,45.52385],"type":"Point"}
}