{
  "type": "Feature",
  "properties": {
    "iso:country":"US",
    "sg:address":"62490 Erickson Rd",
    "sg:city":"Bend",
    "sg:classifiers":[
        {
            "category":"Building & Trades",
            "subcategory":"Construction",
            "type":"Services"
        }
    ],
    "sg:phone":"+1 541 389 6420",
    "sg:postcode":"97701",
    "sg:province":"OR",
    "sg:tags":[
        "tile",
        "dealer",
        "contractor"
    ],
    "wof:name":"Bend Ceramic Tile Inc",
    "wof:placetype":"venue"
},
  "geometry": {"coordinates":[-121.223331,44.076066],"type":"Point"}
}