{
  "type": "Feature",
  "properties": {
    "addr:full":"1818 NE Irving St Portland OR 97232",
    "addr:housenumber":"1818",
    "addr:postcode":"97232",
    "addr:street":"Ne Irving St",
    "iso:country":"US",
    "sg:address":"1818 NE Irving St",
    "sg:city":"Portland",
    "sg:classifiers":[
        {
            "category":"Professional",
            "subcategory":"Accounting & Tax Preparation",
            "type":"Services"
        }
    ],
    "sg:phone":"+1 503 232 7650",
    "sg:postcode":"97232",
    "sg:province":"OR",
    "sg:tags":[
        "bookkeeping",
        "general"
    ],
    "wof:name":"Big City Business Svc",
    "wof:placetype":"venue"
},
  "geometry": {"coordinates":[-122.646636,45.527847],"type":"Point"}
}