{
  "type": "Feature",
  "properties": {
    "iso:country":"US",
    "sg:address":"1936 Kinglet Way NE",
    "sg:city":"Keizer",
    "sg:classifiers":[
        {
            "category":"Professional",
            "subcategory":"Detective & Security Services",
            "type":"Services"
        }
    ],
    "sg:phone":"+1 503 393 3102",
    "sg:postcode":"97303",
    "sg:province":"OR",
    "sg:tags":[
        "information",
        "bureau"
    ],
    "wof:name":"Adl Tractor Service",
    "wof:placetype":"venue"
},
  "geometry": {"coordinates":[-123.007634,45.000681],"type":"Point"}
}