{
  "type": "Feature",
  "properties": {
    "iso:country":"US",
    "sg:address":"568 SE Hathaway Pl",
    "sg:city":"Corvallis",
    "sg:classifiers":[
        {
            "category":"Retail",
            "subcategory":"Animal Services",
            "type":"Services"
        }
    ],
    "sg:phone":"+1 541 753 5662",
    "sg:postcode":"97333",
    "sg:province":"OR",
    "wof:name":"Golden Leash",
    "wof:placetype":"venue"
},
  "geometry": {"coordinates":[-123.261602,44.531691],"type":"Point"}
}