{
  "type": "Feature",
  "properties": {
    "iso:country":"US",
    "sg:address":"110 NW 1st Ave",
    "sg:city":"Estacada",
    "sg:classifiers":[
        {
            "category":"Retail",
            "subcategory":"Funeral Services",
            "type":"Services"
        }
    ],
    "sg:phone":"+1 503 630 3829",
    "sg:postcode":"97023",
    "sg:province":"OR",
    "sg:tags":[
        "director"
    ],
    "wof:name":"Estacada Funeral Chapel",
    "wof:placetype":"venue"
},
  "geometry": {"coordinates":[-122.336215,45.289638],"type":"Point"}
}