{
  "type": "Feature",
  "properties": {
    "iso:country":"US",
    "sg:address":"8519 SE Hinkley Ave",
    "sg:city":"Portland",
    "sg:classifiers":[
        {
            "category":"Professional",
            "subcategory":"Management & Consulting",
            "type":"Services"
        }
    ],
    "sg:phone":"+1 503 794 9148",
    "sg:postcode":"97086",
    "sg:province":"OR",
    "wof:name":"Tom Barrett Enterprises",
    "wof:placetype":"venue"
},
  "geometry": {"coordinates":[-122.574617,45.457547],"type":"Point"}
}