{
  "type": "Feature",
  "properties": {
    "iso:country":"US",
    "sg:address":"534 SW 3rd Ave",
    "sg:city":"Portland",
    "sg:classifiers":[
        {
            "category":"Wholesale",
            "subcategory":"Jewelry",
            "type":"Manufacturing & Wholesale Goods"
        }
    ],
    "sg:phone":"+1 503 248 9118",
    "sg:postcode":"97204",
    "sg:province":"OR",
    "sg:tags":[
        "jeweler"
    ],
    "wof:name":"Tel-Aviv Diamond & Jewelry Co",
    "wof:placetype":"venue"
},
  "geometry": {"coordinates":[-122.675018,45.519125],"type":"Point"}
}