{
  "type": "Feature",
  "properties": {
    "iso:country":"US",
    "sg:address":"4072 N Williams Ave",
    "sg:city":"Portland",
    "sg:classifiers":[
        {
            "category":"Real Estate",
            "subcategory":"Architect",
            "type":"Services"
        }
    ],
    "sg:phone":"+1 503 287 2300",
    "sg:postcode":"97227",
    "sg:province":"OR",
    "wof:name":"Mosi Architecture",
    "wof:placetype":"venue"
},
  "geometry": {"coordinates":[-122.666532,45.552987],"type":"Point"}
}