{
  "type": "Feature",
  "properties": {
    "addr:full":"3439 NE Sandy Blvd #204 Portland OR 97232",
    "addr:housenumber":"3439",
    "addr:postcode":"97232",
    "addr:street":"Ne Sandy Blvd # 204",
    "iso:country":"US",
    "sg:address":"3439 NE Sandy Blvd #204",
    "sg:city":"Portland",
    "sg:classifiers":[
        {
            "category":"Communications",
            "type":"Services"
        }
    ],
    "sg:phone":"+1 503 213 3684",
    "sg:postcode":"97232",
    "sg:province":"OR",
    "sg:tags":[
        "web",
        "design"
    ],
    "sg:website":"www.bluedeerdesigns.com",
    "wof:name":"Blue Deer Designs",
    "wof:placetype":"venue"
},
  "geometry": {"coordinates":[-122.62845799999999,45.532774],"type":"Point"}
}