{
  "type": "Feature",
  "properties": {
    "addr:full":"23 W 27th Ave Eugene OR 97405",
    "addr:housenumber":"23",
    "addr:postcode":"97405",
    "addr:street":"W 27Th Ave",
    "iso:country":"US",
    "sg:address":"23 W 27th Ave",
    "sg:city":"Eugene",
    "sg:classifiers":[
        {
            "category":"Recreation",
            "type":"Entertainment"
        }
    ],
    "sg:phone":"+1 541 954 8940",
    "sg:postcode":"97405",
    "sg:province":"OR",
    "sg:website":"www.sewhappystudio.com",
    "wof:name":"Sew Happy Studio",
    "wof:placetype":"venue"
},
  "geometry": {"coordinates":[-123.09205300000001,44.029069],"type":"Point"}
}