{
  "type": "Feature",
  "properties": {
    "iso:country":"US",
    "sg:address":"6220 NW Croeni Rd",
    "sg:city":"Hillsboro",
    "sg:classifiers":[
        {
            "category":"Wholesale",
            "subcategory":"Metals & Minerals",
            "type":"Manufacturing & Wholesale Goods"
        }
    ],
    "sg:phone":"+1 503 626 2466",
    "sg:postcode":"97124",
    "sg:province":"OR",
    "sg:tags":[
        "pipe"
    ],
    "wof:name":"H D Fowler Co",
    "wof:placetype":"venue"
},
  "geometry": {"coordinates":[-122.905462,45.564347],"type":"Point"}
}