{
  "type": "Feature",
  "properties": {
    "iso:country":"US",
    "sg:address":"64748 Sylvan Loop",
    "sg:city":"Bend",
    "sg:classifiers":[
        {
            "category":"Building & Trades",
            "subcategory":"Construction",
            "type":"Services"
        }
    ],
    "sg:phone":"+1 541 389 3486",
    "sg:postcode":"97701",
    "sg:province":"OR",
    "sg:tags":[
        "house"
    ],
    "wof:name":"Tom Fisher Construction I",
    "wof:placetype":"venue"
},
  "geometry": {"coordinates":[-121.232316,44.151408],"type":"Point"}
}