{
  "type": "Feature",
  "properties": {
    "addr:full":"6720 SE Morrison St Portland OR 97215",
    "addr:housenumber":"6720",
    "addr:postcode":"97215",
    "addr:street":"Se Morrison St",
    "iso:country":"US",
    "sg:address":"6720 SE Morrison St",
    "sg:city":"Portland",
    "sg:classifiers":[
        {
            "category":"Professional",
            "subcategory":"Business Services",
            "type":"Services"
        }
    ],
    "sg:phone":"+1 503 245 7100",
    "sg:postcode":"97215",
    "sg:province":"OR",
    "wof:name":"Karen Bowery",
    "wof:placetype":"venue"
},
  "geometry": {"coordinates":[-122.593344,45.517383],"type":"Point"}
}