{
  "type": "Feature",
  "properties": {
    "iso:country":"US",
    "sg:address":"2251 NW 9th St",
    "sg:city":"Corvallis",
    "sg:classifiers":[
        {
            "category":"Wholesale",
            "subcategory":"Electrical",
            "type":"Manufacturing & Wholesale Goods"
        }
    ],
    "sg:phone":"+1 541 760 0355",
    "sg:postcode":"97330",
    "sg:province":"OR",
    "sg:tags":[
        "control",
        "security",
        "system"
    ],
    "wof:name":"Audio Visual Security",
    "wof:placetype":"venue"
},
  "geometry": {"coordinates":[-123.253571,44.591173],"type":"Point"}
}