{
  "type": "Feature",
  "properties": {
    "iso:country":"US",
    "sg:address":"796 Skipper Ave",
    "sg:city":"Eugene",
    "sg:classifiers":[
        {
            "category":"Manufacturing",
            "subcategory":"Glass & Minerals",
            "type":"Manufacturing & Wholesale Goods"
        }
    ],
    "sg:phone":"+1 541 484 6539",
    "sg:postcode":"97404",
    "sg:province":"OR",
    "sg:tags":[
        "mfg"
    ],
    "wof:name":"Mdx Inc",
    "wof:placetype":"venue"
},
  "geometry": {"coordinates":[-123.141662,44.09721],"type":"Point"}
}