{
  "type": "Feature",
  "properties": {
    "iso:country":"US",
    "sg:address":"3405 NW Orchard Ave",
    "sg:city":"Corvallis",
    "sg:classifiers":[
        {
            "category":"Professional",
            "type":"Services"
        }
    ],
    "sg:phone":"+1 541 738 6732",
    "sg:postcode":"97330",
    "sg:province":"OR",
    "wof:name":"Pengcheng Wu",
    "wof:placetype":"venue"
},
  "geometry": {"coordinates":[-123.289708,44.567951],"type":"Point"}
}