{
  "type": "Feature",
  "properties": {
    "addr:full":"1121 S Main St Milton Freewater OR 97862",
    "addr:housenumber":"1121",
    "addr:postcode":"97862",
    "addr:street":"S Main St;Freewater",
    "iso:country":"US",
    "sg:address":"1121 S Main St",
    "sg:city":"Milton Freewater",
    "sg:classifiers":[
        {
            "category":"Food & Beverages",
            "subcategory":"Groceries & Convenience Stores",
            "type":"Retail Goods"
        }
    ],
    "sg:phone":"+1 541 938 6323",
    "sg:postcode":"97862",
    "sg:province":"OR",
    "wof:name":"Circle K",
    "wof:placetype":"venue"
},
  "geometry": {"coordinates":[-118.38297300000001,45.925352],"type":"Point"}
}