{
  "type": "Feature",
  "properties": {
    "addr:full":"11300 SE 23rd Ave Portland OR 97222",
    "addr:postcode":"11300;97222",
    "addr:street":"Se 23Rd Ave",
    "iso:country":"US",
    "sg:address":"11300 SE 23rd Ave",
    "sg:city":"Portland",
    "sg:classifiers":[
        {
            "category":"Social Services",
            "type":"Services"
        }
    ],
    "sg:phone":"+1 503 709 3173",
    "sg:postcode":"97222",
    "sg:province":"OR",
    "sg:tags":[
        "worker"
    ],
    "sg:website":"http://www.juvenileassistance.org",
    "wof:name":"Clackamas County Youth Gang Ta",
    "wof:placetype":"venue"
},
  "geometry": {"coordinates":[-122.638335,45.442307],"type":"Point"}
}