{
  "type": "Feature",
  "properties": {
    "iso:country":"US",
    "sg:address":"14950 SE 82nd Dr",
    "sg:city":"Clackamas",
    "sg:classifiers":[
        {
            "category":"Restaurant",
            "type":"Food & Drink"
        }
    ],
    "sg:phone":"+1 503 656 9894",
    "sg:postcode":"97015",
    "sg:province":"OR",
    "wof:name":"Short Stop Cafe",
    "wof:placetype":"venue"
},
  "geometry": {"coordinates":[-122.568577,45.413764],"type":"Point"}
}