{
  "type": "Feature",
  "properties": {
    "iso:country":"US",
    "sg:address":"121 SW Salmon St",
    "sg:city":"Portland",
    "sg:classifiers":[
        {
            "category":"Professional",
            "subcategory":"Lawyer & Legal Services",
            "type":"Services"
        }
    ],
    "sg:phone":"+1 503 222 2510",
    "sg:postcode":"97204",
    "sg:province":"OR",
    "wof:name":"Weiselman Jacob Atty",
    "wof:placetype":"venue"
},
  "geometry": {"coordinates":[-122.674887,45.51604],"type":"Point"}
}