{
  "type": "Feature",
  "properties": {
    "iso:country":"US",
    "sg:address":"2517 SE Mailwell Dr",
    "sg:city":"Portland",
    "sg:classifiers":[
        {
            "category":"Building & Trades",
            "subcategory":"Construction",
            "type":"Services"
        }
    ],
    "sg:phone":"+1 971 233 0370",
    "sg:postcode":"97222",
    "sg:province":"OR",
    "sg:tags":[
        "repairing",
        "remodeling",
        "contractor"
    ],
    "wof:name":"John M Lake Antq Restoration",
    "wof:placetype":"venue"
},
  "geometry": {"coordinates":[-122.637004,45.454529],"type":"Point"}
}