{
  "type": "Feature",
  "properties": {
    "iso:country":"US",
    "sg:address":"12050 SW Allen Blvd",
    "sg:city":"Beaverton",
    "sg:classifiers":[
        {
            "category":"Restaurant",
            "type":"Food & Drink"
        }
    ],
    "sg:phone":"+1 503 643 3161",
    "sg:postcode":"97005",
    "sg:province":"OR",
    "sg:tags":[
        "eating"
    ],
    "wof:name":"China Town Express",
    "wof:placetype":"venue"
},
  "geometry": {"coordinates":[-122.8038,45.476408],"type":"Point"}
}