{
  "type": "Feature",
  "properties": {
    "iso:country":"US",
    "sg:address":"2517 River Rd S",
    "sg:city":"Salem",
    "sg:classifiers":[
        {
            "category":"Professional",
            "subcategory":"Management & Consulting",
            "type":"Services"
        }
    ],
    "sg:phone":"+1 503 375 2979",
    "sg:postcode":"97302",
    "sg:province":"OR",
    "sg:tags":[
        "fuel"
    ],
    "wof:name":"JDL Management Svc",
    "wof:placetype":"venue"
},
  "geometry": {"coordinates":[-123.06111900000001,44.917923],"type":"Point"}
}