{
  "type": "Feature",
  "properties": {
    "iso:country":"US",
    "sg:address":"2247 SE 30th Ave",
    "sg:city":"Portland",
    "sg:classifiers":[
        {
            "category":"Organizations",
            "subcategory":"Membership Organization",
            "type":"Services"
        }
    ],
    "sg:phone":"+1 503 231 6006",
    "sg:postcode":"97214",
    "sg:province":"OR",
    "sg:tags":[
        "charity"
    ],
    "sg:website":"http://www.kamarelief.org",
    "wof:name":"Kama Relief Corp",
    "wof:placetype":"venue"
},
  "geometry": {"coordinates":[-122.634726,45.506661],"type":"Point"}
}