{
  "type": "Feature",
  "properties": {
    "addr:full":"1056 Green Acres Rd Eugene OR 97408",
    "addr:housenumber":"1056",
    "addr:postcode":"97408",
    "addr:street":"Green Acres Rd",
    "iso:country":"US",
    "sg:address":"1056 Green Acres Rd",
    "sg:city":"Eugene",
    "sg:classifiers":[
        {
            "category":"Restaurant",
            "type":"Food & Drink"
        }
    ],
    "sg:menulink":"http://www.allmenus.com/or/eugene-springfield/128375-subway/menu/",
    "sg:phone":"+1 541 687 8808",
    "sg:postcode":"97408",
    "sg:province":"OR",
    "sg:tags":[
        "american",
        "sandwich"
    ],
    "wof:name":"Subway",
    "wof:placetype":"venue"
},
  "geometry": {"coordinates":[-123.095651,44.093459],"type":"Point"}
}