{
  "type": "Feature",
  "properties": {
    "addr:full":"1467 Filbert St Lebanon OR 97355",
    "addr:housenumber":"1467",
    "addr:postcode":"97355",
    "addr:street":"Filbert St",
    "iso:country":"US",
    "sg:address":"1467 Filbert St",
    "sg:city":"Lebanon",
    "sg:classifiers":[
        {
            "category":"Real Estate",
            "subcategory":"Developer",
            "type":"Services"
        }
    ],
    "sg:phone":"+1 541 451 3927",
    "sg:postcode":"97355",
    "sg:province":"OR",
    "sg:tags":[
        "cemetery"
    ],
    "wof:name":"Powell Cemetery Assoc Inc",
    "wof:placetype":"venue"
},
  "geometry": {"coordinates":[-122.89858700000001,44.532329],"type":"Point"}
}