{
  "type": "Feature",
  "properties": {
    "iso:country":"US",
    "sg:address":"12720 SW Walker Rd",
    "sg:city":"Beaverton",
    "sg:classifiers":[
        {
            "category":"Restaurant",
            "type":"Food & Drink"
        }
    ],
    "sg:phone":"+1 503 641 7699",
    "sg:postcode":"97005",
    "sg:province":"OR",
    "sg:tags":[
        "hawaiian"
    ],
    "sg:website":"www.facebook.com/#!/pages/Beaver...",
    "wof:name":"Roxy's Island Grill",
    "wof:placetype":"venue"
},
  "geometry": {"coordinates":[-122.807743,45.501886],"type":"Point"}
}