{
  "type": "Feature",
  "properties": {
    "addr:full":"3764 Pleasant View Dr NE Keizer OR 97303",
    "addr:housenumber":"3764",
    "addr:postcode":"97303",
    "addr:street":"Pleasant View Dr Ne",
    "iso:country":"US",
    "sg:address":"3764 Pleasant View Dr NE",
    "sg:city":"Keizer",
    "sg:classifiers":[
        {
            "category":"Building & Trades",
            "subcategory":"Construction",
            "type":"Services"
        }
    ],
    "sg:phone":"+1 503 393 7985",
    "sg:postcode":"97303",
    "sg:province":"OR",
    "sg:tags":[
        "industrial",
        "contractors-commercial",
        "contractor"
    ],
    "wof:name":"Dean A Rudishauser Inc",
    "wof:placetype":"venue"
},
  "geometry": {"coordinates":[-123.012345,44.981514],"type":"Point"}
}