{
  "type": "Feature",
  "properties": {
    "iso:country":"US",
    "sg:address":"10090 Hwy 202",
    "sg:city":"Clatskanie",
    "sg:classifiers":[
        {
            "category":"Professional",
            "subcategory":"Management & Consulting",
            "type":"Services"
        }
    ],
    "sg:phone":"+1 503 755 0800",
    "sg:postcode":"97016",
    "sg:province":"OR",
    "sg:tags":[
        "business"
    ],
    "wof:name":"One Lone Bison LLC",
    "wof:placetype":"venue"
},
  "geometry": {"coordinates":[-123.358096,45.975005],"type":"Point"}
}