{
  "type": "Feature",
  "properties": {
    "addr:full":"107 NW Richard St Sheridan OR 97378",
    "addr:housenumber":"107",
    "addr:postcode":"97378",
    "addr:street":"Nw Richard St",
    "iso:country":"US",
    "sg:address":"107 NW Richard St",
    "sg:city":"Sheridan",
    "sg:classifiers":[
        {
            "category":"Freight",
            "type":"Transportation"
        }
    ],
    "sg:phone":"+1 503 843 3213",
    "sg:postcode":"97378",
    "sg:province":"OR",
    "sg:tags":[
        "commercial",
        "storage"
    ],
    "wof:name":"Gary Acuff Storage & Rental",
    "wof:placetype":"venue"
},
  "geometry": {"coordinates":[-123.40979400000001,45.102754],"type":"Point"}
}