{
  "type": "Feature",
  "properties": {
    "iso:country":"US",
    "sg:address":"24204 SE Oak St",
    "sg:city":"Gresham",
    "sg:classifiers":[
        {
            "category":"Arts & Performance",
            "subcategory":"Theater",
            "type":"Entertainment"
        }
    ],
    "sg:phone":"+1 503 515 9501",
    "sg:postcode":"97030",
    "sg:province":"OR",
    "sg:tags":[
        "theatrical"
    ],
    "wof:name":"Fya Productions",
    "wof:placetype":"venue"
},
  "geometry": {"coordinates":[-122.414949,45.519912],"type":"Point"}
}