{
  "type": "Feature",
  "properties": {
    "addr:full":"7144 NE Killingsworth Street Portland OR 97218",
    "addr:housenumber":"7144",
    "addr:postcode":"97218",
    "addr:street":"Ne Killingsworth Street",
    "iso:country":"US",
    "sg:address":"7144 NE Killingsworth Street",
    "sg:city":"Portland",
    "sg:classifiers":[
        {
            "category":"Food & Beverages",
            "subcategory":"Groceries & Convenience Stores",
            "type":"Retail Goods"
        }
    ],
    "sg:phone":"+1 503 252 3640",
    "sg:postcode":"97218",
    "sg:province":"OR",
    "sg:website":"www.plaidpantry.com",
    "wof:name":"Plaid Pantry Markets",
    "wof:placetype":"venue"
},
  "geometry": {"coordinates":[-122.589493,45.562579],"type":"Point"}
}