{
  "type": "Feature",
  "properties": {
    "iso:country":"US",
    "sg:address":"5970 SW 90th Ave",
    "sg:city":"Portland",
    "sg:classifiers":[
        {
            "category":"Manufacturing",
            "subcategory":"Metals",
            "type":"Manufacturing & Wholesale Goods"
        }
    ],
    "sg:phone":"+1 503 384 9500",
    "sg:postcode":"97225",
    "sg:province":"OR",
    "sg:tags":[
        "steel",
        "distributor",
        "warehouse",
        "mill"
    ],
    "sg:website":"http://www.cohowind.com",
    "wof:name":"Coho Sales And Marketing Inc",
    "wof:placetype":"venue"
},
  "geometry": {"coordinates":[-122.769463,45.477037],"type":"Point"}
}