{
  "type": "Feature",
  "properties": {
    "iso:country":"US",
    "sg:address":"14010 SW Teal Blvd",
    "sg:city":"Beaverton",
    "sg:classifiers":[
        {
            "category":"Arts & Performance",
            "subcategory":"Theater",
            "type":"Entertainment"
        }
    ],
    "sg:phone":"+1 503 590 3087",
    "sg:postcode":"97008",
    "sg:province":"OR",
    "sg:tags":[
        "theatrical"
    ],
    "wof:name":"Good Medicine Inc",
    "wof:placetype":"venue"
},
  "geometry": {"coordinates":[-122.820914,45.441338],"type":"Point"}
}