{
  "type": "Feature",
  "properties": {
    "iso:country":"US",
    "sg:address":"901 Brutscher St",
    "sg:city":"Newberg",
    "sg:classifiers":[
        {
            "category":"Professional",
            "type":"Services"
        }
    ],
    "sg:phone":"+1 503 538 9743",
    "sg:postcode":"97132",
    "sg:province":"OR",
    "sg:tags":[
        "establishment"
    ],
    "sg:website":"www.discount-plants.com",
    "wof:name":"DISCOUNT-Plants.Com",
    "wof:placetype":"venue"
},
  "geometry": {"coordinates":[-122.942055,45.307933],"type":"Point"}
}