{
  "type": "Feature",
  "properties": {
    "addr:full":"17835 SE Tickle Creek Rd Boring OR 97009",
    "addr:postcode":"17835;97009",
    "addr:street":"Se Tickle Creek Rd",
    "iso:country":"US",
    "sg:address":"17835 SE Tickle Creek Rd",
    "sg:city":"Boring",
    "sg:classifiers":[
        {
            "category":"Farming",
            "subcategory":"Farm",
            "type":"Manufacturing & Wholesale Goods"
        }
    ],
    "sg:phone":"+1 503 658 5769",
    "sg:postcode":"97009",
    "sg:province":"OR",
    "sg:tags":[
        "crop",
        "general"
    ],
    "wof:name":"Schedeen Farms Inc",
    "wof:placetype":"venue"
},
  "geometry": {"coordinates":[-122.349369,45.392766],"type":"Point"}
}