{
  "type": "Feature",
  "properties": {
    "iso:country":"US",
    "sg:address":"2500 S Santiam Hwy",
    "sg:city":"Lebanon",
    "sg:classifiers":[
        {
            "category":"Restaurant",
            "type":"Food & Drink"
        }
    ],
    "sg:phone":"+1 541 259 6900",
    "sg:postcode":"97355",
    "sg:province":"OR",
    "wof:name":"Papa Murphy's Take 'N' Bake",
    "wof:placetype":"venue"
},
  "geometry": {"coordinates":[-122.905968,44.522086],"type":"Point"}
}