{
  "type": "Feature",
  "properties": {
    "iso:country":"US",
    "sg:address":"11325 SE Cruickshank Rd",
    "sg:city":"Dayton",
    "sg:classifiers":[
        {
            "category":"Food & Beverages",
            "subcategory":"Specialty",
            "type":"Retail Goods"
        }
    ],
    "sg:phone":"+1 503 864 3958",
    "sg:postcode":"97114",
    "sg:province":"OR",
    "sg:tags":[
        "gourmet",
        "shop"
    ],
    "wof:name":"Morin's Landing",
    "wof:placetype":"venue"
},
  "geometry": {"coordinates":[-123.125395,45.199641],"type":"Point"}
}