{
  "type": "Feature",
  "properties": {
    "iso:country":"US",
    "sg:address":"61235 Parrell Rd",
    "sg:city":"Bend",
    "sg:classifiers":[
        {
            "category":"Home & Garden",
            "subcategory":"Furniture",
            "type":"Retail Goods"
        }
    ],
    "sg:phone":"+1 541 312 4435",
    "sg:postcode":"97702",
    "sg:province":"OR",
    "wof:name":"Benjamins Home Furnishings",
    "wof:placetype":"venue"
},
  "geometry": {"coordinates":[-121.312427,44.023818],"type":"Point"}
}