{
  "type": "Feature",
  "properties": {
    "addr:full":"118 2nd Ave SW Albany OR 97321",
    "addr:housenumber":"118",
    "addr:postcode":"97321",
    "addr:street":"2Nd Ave Sw",
    "iso:country":"US",
    "sg:address":"118 2nd Ave SW",
    "sg:city":"Albany",
    "sg:classifiers":[
        {
            "category":"Government",
            "subcategory":"Court House",
            "type":"Public Place"
        }
    ],
    "sg:phone":"+1 541 967 2028",
    "sg:postcode":"97321",
    "sg:province":"OR",
    "sg:tags":[
        "state",
        "counsel"
    ],
    "wof:name":"Justice Dept",
    "wof:placetype":"venue"
},
  "geometry": {"coordinates":[-123.104946,44.636538],"type":"Point"}
}