{
  "type": "Feature",
  "properties": {
    "addr:full":"2511 Longwood Dr Reedsport OR 97467",
    "addr:housenumber":"2511",
    "addr:postcode":"97467",
    "addr:street":"Longwood Dr Reedsport",
    "iso:country":"US",
    "sg:address":"2511 Longwood Dr",
    "sg:city":"Reedsport",
    "sg:classifiers":[
        {
            "category":"Organizations",
            "subcategory":"Religious Organization",
            "type":"Services"
        }
    ],
    "sg:phone":"+1 541 271 3736",
    "sg:postcode":"97467",
    "sg:province":"OR",
    "sg:tags":[
        "latter-day",
        "churches-church",
        "christ",
        "saint",
        "jesus"
    ],
    "sg:website":"http://www.lds.org",
    "wof:name":"Morman Church",
    "wof:placetype":"venue"
},
  "geometry": {"coordinates":[-124.12737300000001,43.692265],"type":"Point"}
}