{
  "type": "Feature",
  "properties": {
    "addr:full":"3189 Hwy 35 Hood River OR 97031",
    "addr:housenumber":"3189",
    "addr:postcode":"97031",
    "addr:street":"Hwy 35",
    "iso:country":"US",
    "sg:address":"3189 Hwy 35",
    "sg:city":"Hood River",
    "sg:classifiers":[
        {
            "category":"Manufacturing",
            "subcategory":"Food",
            "type":"Manufacturing & Wholesale Goods"
        }
    ],
    "sg:phone":"+1 541 386 8333",
    "sg:postcode":"97031",
    "sg:province":"OR",
    "sg:tags":[
        "winery"
    ],
    "wof:name":"Mt Hood Winery",
    "wof:placetype":"venue"
},
  "geometry": {"coordinates":[-121.512857,45.63417],"type":"Point"}
}