{
  "type": "Feature",
  "properties": {
    "addr:full":"2428 Three Lakes Rd SE Albany OR 97322",
    "addr:housenumber":"2428",
    "addr:postcode":"97322",
    "addr:street":"Three Lakes Rd Se",
    "iso:country":"US",
    "sg:address":"2428 Three Lakes Rd SE",
    "sg:city":"Albany",
    "sg:classifiers":[
        {
            "category":"Home & Garden",
            "subcategory":"Household Appliances",
            "type":"Retail Goods"
        },
        {
            "category":"Building & Trades",
            "subcategory":"Plumbing",
            "type":"Services"
        }
    ],
    "sg:phone":"+1 541 928 7927",
    "sg:postcode":"97322",
    "sg:province":"OR",
    "sg:tags":[
        "major",
        "industrial",
        "plumber",
        "contractors-commercial"
    ],
    "wof:name":"Midway Plumbing Inc",
    "wof:placetype":"venue"
},
  "geometry": {"coordinates":[-123.055886,44.621502],"type":"Point"}
}