{
  "type": "Feature",
  "properties": {
    "addr:full":"12003 NE Shaver St Portland OR 97220",
    "addr:housenumber":"12003",
    "addr:postcode":"97220",
    "addr:street":"Ne Shaver St",
    "iso:country":"US",
    "sg:address":"12003 NE Shaver St",
    "sg:city":"Portland",
    "sg:classifiers":[
        {
            "category":"Education",
            "subcategory":"School",
            "type":"Public Place"
        }
    ],
    "sg:phone":"+1 503 408 2600",
    "sg:postcode":"97220",
    "sg:province":"OR",
    "sg:website":"www.parkrose.k12.or.us",
    "wof:name":"Schools Public",
    "wof:placetype":"venue"
},
  "geometry": {"coordinates":[-122.543105,45.551907],"type":"Point"}
}