{
  "type": "Feature",
  "properties": {
    "addr:full":"1920 Cliff St Baker City OR 97814",
    "addr:housenumber":"1920",
    "addr:postcode":"97814",
    "addr:street":"Cliff St",
    "iso:country":"US",
    "sg:address":"1920 Cliff St",
    "sg:city":"Baker City",
    "sg:classifiers":[
        {
            "category":"Social Services",
            "subcategory":"Child Care",
            "type":"Services"
        }
    ],
    "sg:phone":"+1 541 523 7263",
    "sg:postcode":"97814",
    "sg:province":"OR",
    "sg:tags":[
        "day"
    ],
    "wof:name":"Precious Days Child Care",
    "wof:placetype":"venue"
},
  "geometry": {"coordinates":[-117.831,44.768207],"type":"Point"}
}