{
  "type": "Feature",
  "properties": {
    "addr:full":"242 SW J St Grants Pass OR 97526",
    "addr:housenumber":"242",
    "addr:postcode":"97526",
    "addr:street":"Sw J St",
    "iso:country":"US",
    "sg:address":"242 SW J St",
    "sg:city":"Grants Pass",
    "sg:classifiers":[
        {
            "category":"Professional",
            "subcategory":"Art Services",
            "type":"Services"
        }
    ],
    "sg:phone":"+1 541 479 3503",
    "sg:postcode":"97526",
    "sg:province":"OR",
    "sg:tags":[
        "photographer"
    ],
    "sg:website":"www.lensstudio.com",
    "wof:name":"Len's Studio",
    "wof:placetype":"venue"
},
  "geometry": {"coordinates":[-123.330065,42.437452],"type":"Point"}
}