{
  "type": "Feature",
  "properties": {
    "addr:full":"2385 W 11th Ave Eugene OR 97402",
    "addr:housenumber":"2385",
    "addr:postcode":"97402",
    "addr:street":"W 11Th Ave",
    "iso:country":"US",
    "sg:address":"2385 W 11th Ave",
    "sg:city":"Eugene",
    "sg:classifiers":[
        {
            "category":"Wholesale",
            "subcategory":"Medical Equipment & Supplies",
            "type":"Manufacturing & Wholesale Goods"
        },
        {
            "category":"Health Services",
            "subcategory":"Hospital",
            "type":"Services"
        },
        {
            "category":"Shopping",
            "subcategory":"Pharmacy",
            "type":"Retail Goods"
        }
    ],
    "sg:phone":"+1 541 485 3411",
    "sg:postcode":"97402",
    "sg:province":"OR",
    "sg:tags":[
        "home",
        "care"
    ],
    "sg:website":"http://www.allmedeugene.com",
    "wof:name":"All-Med",
    "wof:placetype":"venue"
},
  "geometry": {"coordinates":[-123.12942700000001,44.047852],"type":"Point"}
}