{
  "type": "Feature",
  "properties": {
    "addr:full":"6566 Whispering Pines Ln Jacksonville OR 97530",
    "addr:housenumber":"6566",
    "addr:postcode":"97530",
    "addr:street":"Whispering Pines Ln",
    "iso:country":"US",
    "sg:address":"6566 Whispering Pines Ln",
    "sg:city":"Jacksonville",
    "sg:classifiers":[
        {
            "category":"Wholesale",
            "subcategory":"Motor Vehicles",
            "type":"Manufacturing & Wholesale Goods"
        }
    ],
    "sg:phone":"+1 541 899 7311",
    "sg:postcode":"97530",
    "sg:province":"OR",
    "sg:tags":[
        "automobile",
        "truck",
        "broker"
    ],
    "wof:name":"Alliance Trucking",
    "wof:placetype":"venue"
},
  "geometry": {"coordinates":[-123.04183500000001,42.235783],"type":"Point"}
}