{
  "type": "Feature",
  "properties": {
    "addr:full":"30976 S Paveletz Rd Molalla OR 97038",
    "addr:housenumber":"30976",
    "addr:postcode":"97038",
    "addr:street":"S Paveletz Rd",
    "iso:country":"US",
    "sg:address":"30976 S Paveletz Rd",
    "sg:city":"Molalla",
    "sg:classifiers":[
        {
            "category":"Building & Trades",
            "subcategory":"Construction",
            "type":"Services"
        }
    ],
    "sg:phone":"+1 503 829 6334",
    "sg:postcode":"97038",
    "sg:province":"OR",
    "sg:tags":[
        "house"
    ],
    "wof:name":"Moehnke Construction",
    "wof:placetype":"venue"
},
  "geometry": {"coordinates":[-122.495615,45.156705],"type":"Point"}
}