{
  "type": "Feature",
  "properties": {
    "iso:country":"US",
    "sg:address":"725 S 42nd St",
    "sg:city":"Springfield",
    "sg:classifiers":[
        {
            "category":"Social Services",
            "subcategory":"Child Care",
            "type":"Services"
        }
    ],
    "sg:phone":"+1 541 736 1809",
    "sg:postcode":"97478",
    "sg:province":"OR",
    "sg:tags":[
        "kindergarten",
        "academic",
        "school"
    ],
    "wof:name":"Head Start Of Lane County",
    "wof:placetype":"venue"
},
  "geometry": {"coordinates":[-122.961997,44.038669],"type":"Point"}
}