{
  "type": "Feature",
  "properties": {
    "iso:country":"US",
    "sg:address":"7905 SE Holgate Blvd",
    "sg:city":"Portland",
    "sg:classifiers":[
        {
            "category":"Education",
            "subcategory":"Library",
            "type":"Public Place"
        }
    ],
    "sg:phone":"+1 503 248 5389",
    "sg:postcode":"97206",
    "sg:province":"OR",
    "wof:name":"Friends of Multnomah Library",
    "wof:placetype":"venue"
},
  "geometry": {"coordinates":[-122.58200100000001,45.490398],"type":"Point"}
}