{
  "type": "Feature",
  "properties": {
    "iso:country":"US",
    "sg:address":"777 US Hwy 101",
    "sg:city":"Florence",
    "sg:classifiers":[
        {
            "category":"Banks & Credit Unions",
            "subcategory":"Bank",
            "type":"Services"
        }
    ],
    "sg:phone":"+1 541 997 3486",
    "sg:postcode":"97439",
    "sg:province":"OR",
    "sg:website":"www.clicksvb.com",
    "wof:name":"Siuslaw Valley Bank",
    "wof:placetype":"venue"
},
  "geometry": {"coordinates":[-124.104336,43.973048],"type":"Point"}
}