{
  "type": "Feature",
  "properties": {
    "iso:country":"US",
    "sg:address":"1514 NE 63rd Ave",
    "sg:city":"Hillsboro",
    "sg:classifiers":[
        {
            "category":"Professional",
            "subcategory":"Management & Consulting",
            "type":"Services"
        }
    ],
    "sg:phone":"+1 503 314 6986",
    "sg:postcode":"97124",
    "sg:province":"OR",
    "wof:name":"NW Management Sys Inc",
    "wof:placetype":"venue"
},
  "geometry": {"coordinates":[-122.915322,45.53529],"type":"Point"}
}