{
  "type": "Feature",
  "properties": {
    "addr:full":"11241 S Forest Ridge Ln Oregon City OR 97045",
    "addr:housenumber":"11241",
    "addr:postcode":"97045",
    "addr:street":"S Forest Ridge Ln",
    "iso:country":"US",
    "sg:address":"11241 S Forest Ridge Ln",
    "sg:city":"Oregon City",
    "sg:classifiers":[
        {
            "category":"Building & Trades",
            "subcategory":"Construction",
            "type":"Services"
        }
    ],
    "sg:phone":"+1 503 222 1101",
    "sg:postcode":"97045",
    "sg:province":"OR",
    "sg:tags":[
        "roofing",
        "contractor"
    ],
    "wof:name":"Doran's Roofing",
    "wof:placetype":"venue"
},
  "geometry": {"coordinates":[-122.63539299999999,45.328321],"type":"Point"}
}