{
  "type": "Feature",
  "properties": {
    "iso:country":"US",
    "sg:address":"6672 Parkshadow Ct NE",
    "sg:city":"Keizer",
    "sg:classifiers":[
        {
            "category":"Restaurant",
            "type":"Food & Drink"
        }
    ],
    "sg:phone":"+1 503 393 2575",
    "sg:postcode":"97303",
    "sg:province":"OR",
    "sg:website":"http://www.achefofyourown.com",
    "wof:name":"A Chef Of Your Own",
    "wof:placetype":"venue"
},
  "geometry": {"coordinates":[-123.016401,45.016268],"type":"Point"}
}