{
  "type": "Feature",
  "properties": {
    "iso:country":"US",
    "sg:address":"109 NW Broadway St",
    "sg:city":"Bend",
    "sg:classifiers":[
        {
            "category":"Building & Trades",
            "subcategory":"Construction",
            "type":"Services"
        }
    ],
    "sg:phone":"+1 541 389 7836",
    "sg:postcode":"97701",
    "sg:province":"OR",
    "sg:tags":[
        "company"
    ],
    "wof:name":"Ronald D Construction",
    "wof:placetype":"venue"
},
  "geometry": {"coordinates":[-121.318775,44.052113],"type":"Point"}
}