{
  "type": "Feature",
  "properties": {
    "addr:full":"12746 SE Stark St Portland OR 97233",
    "addr:postcode":"12746;97233",
    "addr:street":"Se Stark St",
    "iso:country":"US",
    "sg:address":"12746 SE Stark St",
    "sg:city":"Portland",
    "sg:classifiers":[
        {
            "category":"Health Services",
            "subcategory":"Doctor",
            "type":"Services"
        },
        {
            "category":"Personal",
            "subcategory":"Day Spa",
            "type":"Services"
        }
    ],
    "sg:phone":"+1 503 230 9627",
    "sg:postcode":"97233",
    "sg:province":"OR",
    "sg:tags":[
        "obstetrician",
        "gynecologist"
    ],
    "wof:name":"Linda C Widing, DO Facog",
    "wof:placetype":"venue"
},
  "geometry": {"coordinates":[-122.532712,45.517486],"type":"Point"}
}