{
  "type": "Feature",
  "properties": {
    "iso:country":"US",
    "sg:address":"1033 SW Yamhill St Ste 100",
    "sg:city":"Portland",
    "sg:phone":"+1 503 766 4991",
    "sg:postcode":"97205",
    "sg:province":"OR",
    "sg:website":"http://portland.citysearch.com/profile/external/44704084/portland_or/stephanie_petix_willard_l_ac_msom.html?publisher=yellowpages&reference_id=1&placement=ypwebsitemip",
    "wof:name":"Stephanie Petix Willard, L.Ac., MSOM",
    "wof:placetype":"venue"
},
  "geometry": {"coordinates":[-122.68281899999999,45.519431],"type":"Point"}
}