{
  "type": "Feature",
  "properties": {
    "iso:country":"US",
    "sg:address":"4470 Lakeview Blvd",
    "sg:city":"Lake Oswego",
    "sg:classifiers":[
        {
            "category":"Professional",
            "subcategory":"Business Services",
            "type":"Services"
        }
    ],
    "sg:phone":"+1 503 684 0770",
    "sg:postcode":"97035",
    "sg:province":"OR",
    "wof:name":"G&G Interiors",
    "wof:placetype":"venue"
},
  "geometry": {"coordinates":[-122.718711,45.406243],"type":"Point"}
}