{
  "type": "Feature",
  "properties": {
    "iso:country":"US",
    "sg:address":"8833 N Syracuse St",
    "sg:city":"Portland",
    "sg:classifiers":[
        {
            "category":"Real Estate",
            "subcategory":"Real Estate Operator",
            "type":"Services"
        }
    ],
    "sg:phone":"+1 503 285 2388",
    "sg:postcode":"97203",
    "sg:province":"OR",
    "sg:tags":[
        "apartment"
    ],
    "wof:name":"Cathredal Park Apartments",
    "wof:placetype":"venue"
},
  "geometry": {"coordinates":[-122.75787800000001,45.590767],"type":"Point"}
}