{
  "type": "Feature",
  "properties": {
    "iso:country":"US",
    "sg:address":"1313 N Bayshore Dr",
    "sg:city":"Coos Bay",
    "sg:classifiers":[
        {
            "category":"Restaurant",
            "type":"Food & Drink"
        }
    ],
    "sg:phone":"+1 541 269 4080",
    "sg:postcode":"97420",
    "sg:province":"OR",
    "sg:tags":[
        "eating"
    ],
    "wof:name":"Brickstones",
    "wof:placetype":"venue"
},
  "geometry": {"coordinates":[-124.215889,43.377367],"type":"Point"}
}