{
  "type": "Feature",
  "properties": {
    "iso:country":"US",
    "sg:address":"70 Wheatherstone",
    "sg:city":"Lake Oswego",
    "sg:classifiers":[
        {
            "category":"Professional",
            "subcategory":"Engineering",
            "type":"Services"
        }
    ],
    "sg:phone":"+1 503 635 4932",
    "sg:postcode":"97035",
    "sg:province":"OR",
    "sg:tags":[
        "consulting",
        "engineer"
    ],
    "wof:name":"Harold Linstone",
    "wof:placetype":"venue"
},
  "geometry": {"coordinates":[-122.71171099999999,45.426133],"type":"Point"}
}