{
  "type": "Feature",
  "properties": {
    "addr:full":"2324 SE Ankeny St Portland OR 97214",
    "addr:housenumber":"2324",
    "addr:postcode":"97214",
    "addr:street":"Se Ankeny St",
    "iso:country":"US",
    "sg:address":"2324 SE Ankeny St",
    "sg:city":"Portland",
    "sg:classifiers":[
        {
            "category":"Building & Trades",
            "subcategory":"Construction",
            "type":"Services"
        }
    ],
    "sg:phone":"+1 503 230 1815",
    "sg:postcode":"97214",
    "sg:province":"OR",
    "sg:tags":[
        "home",
        "family",
        "contractor"
    ],
    "wof:name":"Keller Raymond General Contr",
    "wof:placetype":"venue"
},
  "geometry": {"coordinates":[-122.642332,45.522083],"type":"Point"}
}