{
  "type": "Feature",
  "properties": {
    "addr:full":"10398 S Rosewood Way Molalla OR 97038",
    "addr:housenumber":"10398",
    "addr:postcode":"97038",
    "addr:street":"S Rosewood Way",
    "iso:country":"US",
    "sg:address":"10398 S Rosewood Way",
    "sg:city":"Molalla",
    "sg:classifiers":[
        {
            "category":"Professional",
            "subcategory":"Management & Consulting",
            "type":"Services"
        }
    ],
    "sg:phone":"+1 503 829 3146",
    "sg:postcode":"97038",
    "sg:province":"OR",
    "sg:tags":[
        "electronic"
    ],
    "wof:name":"Unicomp Inc",
    "wof:placetype":"venue"
},
  "geometry": {"coordinates":[-122.643019,45.094022],"type":"Point"}
}