{
  "type": "Feature",
  "properties": {
    "addr:full":"36701 US Hwy 26 Sandy OR 97055",
    "addr:postcode":"36701;97055",
    "addr:street":"Us Hwy 26",
    "iso:country":"US",
    "sg:address":"36701 US Hwy 26",
    "sg:city":"Sandy",
    "sg:classifiers":[
        {
            "category":"Shopping",
            "subcategory":"Pharmacy",
            "type":"Retail Goods"
        }
    ],
    "sg:phone":"+1 503 668 7452",
    "sg:postcode":"97055",
    "sg:province":"OR",
    "sg:tags":[
        "drug"
    ],
    "wof:name":"True Value Hardware",
    "wof:placetype":"venue"
},
  "geometry": {"coordinates":[-122.286368,45.403324],"type":"Point"}
}