{
  "type": "Feature",
  "properties": {
    "iso:country":"US",
    "sg:address":"11461 NE Holman St",
    "sg:city":"Portland",
    "sg:classifiers":[
        {
            "category":"Building & Trades",
            "subcategory":"Construction",
            "type":"Services"
        }
    ],
    "sg:phone":"+1 503 255 4723",
    "sg:postcode":"97220",
    "sg:province":"OR",
    "sg:tags":[
        "contractor"
    ],
    "wof:name":"Builders Inc",
    "wof:placetype":"venue"
},
  "geometry": {"coordinates":[-122.546724,45.568251],"type":"Point"}
}