{
  "type": "Feature",
  "properties": {
    "iso:country":"US",
    "sg:address":"1040 NW 22nd Ave",
    "sg:city":"Portland",
    "sg:classifiers":[
        {
            "category":"Health Services",
            "subcategory":"Doctor",
            "type":"Services"
        }
    ],
    "sg:phone":"+1 503 796 2743",
    "sg:postcode":"97210",
    "sg:province":"OR",
    "sg:tags":[
        "physician",
        "surgeon",
        "surgeons",
        "surgery-general"
    ],
    "sg:website":"http://www.columbianeurosurgical.net",
    "wof:name":"Columbia Neurosurgical Assoc",
    "wof:placetype":"venue"
},
  "geometry": {"coordinates":[-122.69658200000001,45.530128],"type":"Point"}
}