{
  "type": "Feature",
  "properties": {
    "iso:country":"US",
    "sg:address":"2701 NW Satinwood St",
    "sg:city":"Corvallis",
    "sg:classifiers":[
        {
            "category":"Social Services",
            "subcategory":"Child Care",
            "type":"Services"
        },
        {
            "category":"Social Services",
            "type":"Services"
        }
    ],
    "sg:phone":"+1 541 753 0497",
    "sg:postcode":"97330",
    "sg:province":"OR",
    "sg:tags":[
        "kindergarten",
        "academic",
        "school"
    ],
    "wof:name":"Little Beavers Wilson Center",
    "wof:placetype":"venue"
},
  "geometry": {"coordinates":[-123.257418,44.595569],"type":"Point"}
}