{
  "type": "Feature",
  "properties": {
    "iso:country":"US",
    "sg:address":"15337 State Hwy 66",
    "sg:city":"Ashland",
    "sg:classifiers":[
        {
            "category":"Education",
            "subcategory":"School",
            "type":"Public Place"
        }
    ],
    "sg:phone":"+1 541 482 1910",
    "sg:postcode":"97520",
    "sg:province":"OR",
    "sg:tags":[
        "elementary"
    ],
    "wof:name":"Pinehurst Elementary School",
    "wof:placetype":"venue"
},
  "geometry": {"coordinates":[-122.400832,42.109018],"type":"Point"}
}