{
  "type": "Feature",
  "properties": {
    "iso:country":"US",
    "sg:address":"1205 NE 7th St",
    "sg:city":"Grants Pass",
    "sg:classifiers":[
        {
            "category":"Social Services",
            "type":"Services"
        }
    ],
    "sg:phone":"+1 541 474 0514",
    "sg:postcode":"97526",
    "sg:province":"OR",
    "sg:tags":[
        "counselor",
        "marriage",
        "family"
    ],
    "wof:name":"Joanne Smith Lcsw",
    "wof:placetype":"venue"
},
  "geometry": {"coordinates":[-123.320593,42.449745],"type":"Point"}
}