{
  "type": "Feature",
  "properties": {
    "iso:country":"US",
    "sg:address":"4404 Vasend Ct NE",
    "sg:city":"Salem",
    "sg:classifiers":[
        {
            "category":"Home & Garden",
            "subcategory":"Furniture",
            "type":"Retail Goods"
        }
    ],
    "sg:phone":"+1 503 792 5800",
    "sg:postcode":"97305",
    "sg:province":"OR",
    "wof:name":"Furniture King Man",
    "wof:placetype":"venue"
},
  "geometry": {"coordinates":[-122.975067,44.959889],"type":"Point"}
}