{
  "type": "Feature",
  "properties": {
    "addr:full":"16530 S Pam Dr Oregon City OR 97045",
    "addr:housenumber":"16530",
    "addr:postcode":"97045",
    "addr:street":"S Pam Dr",
    "iso:country":"US",
    "sg:address":"16530 S Pam Dr",
    "sg:city":"Oregon City",
    "sg:classifiers":[
        {
            "category":"Building & Trades",
            "subcategory":"Construction",
            "type":"Services"
        }
    ],
    "sg:phone":"+1 503 293 0999",
    "sg:postcode":"97045",
    "sg:province":"OR",
    "sg:tags":[
        "painter"
    ],
    "sg:website":"www.spectrumpainting.org",
    "wof:name":"Original Spectrum Painting",
    "wof:placetype":"venue"
},
  "geometry": {"coordinates":[-122.547152,45.367612],"type":"Point"}
}