{
  "type": "Feature",
  "properties": {
    "addr:full":"20400 SW Avery Ct Tualatin OR 97062",
    "addr:housenumber":"20400",
    "addr:postcode":"97062",
    "addr:street":"Sw Avery Ct",
    "iso:country":"US",
    "sg:address":"20400 SW Avery Ct",
    "sg:city":"Tualatin",
    "sg:classifiers":[
        {
            "category":"Manufacturing",
            "subcategory":"Furniture",
            "type":"Manufacturing & Wholesale Goods"
        }
    ],
    "sg:phone":"+1 503 691 1554",
    "sg:postcode":"97062",
    "sg:province":"OR",
    "wof:name":"MCF Design & Mfg",
    "wof:placetype":"venue"
},
  "geometry": {"coordinates":[-122.787824,45.372011],"type":"Point"}
}