{
  "type": "Feature",
  "properties": {
    "addr:full":"5400 Hwy 66 Klamath Falls OR 97601",
    "addr:housenumber":"5400",
    "addr:postcode":"97601",
    "addr:street":"Hwy 66",
    "iso:country":"US",
    "sg:address":"5400 Hwy 66",
    "sg:city":"Klamath Falls",
    "sg:classifiers":[
        {
            "category":"Education",
            "subcategory":"School",
            "type":"Public Place"
        }
    ],
    "sg:phone":"+1 541 883 5030",
    "sg:postcode":"97601",
    "sg:province":"OR",
    "wof:name":"Fairhaven Elementary School",
    "wof:placetype":"venue"
},
  "geometry": {"coordinates":[-121.822845,42.182777],"type":"Point"}
}