{
  "type": "Feature",
  "properties": {
    "addr:full":"15862 SW 72nd Ave Portland OR 97224",
    "addr:housenumber":"15862",
    "addr:postcode":"97224",
    "addr:street":"Sw 72Nd Ave",
    "iso:country":"US",
    "sg:address":"15862 SW 72nd Ave",
    "sg:city":"Portland",
    "sg:classifiers":[
        {
            "category":"Wholesale",
            "subcategory":"Computers",
            "type":"Manufacturing & Wholesale Goods"
        }
    ],
    "sg:phone":"+1 503 968 4666",
    "sg:postcode":"97224",
    "sg:province":"OR",
    "sg:website":"www.acesnw.com",
    "wof:name":"American Computer & Electronics Services Corp",
    "wof:placetype":"venue"
},
  "geometry": {"coordinates":[-122.74881499999999,45.404798],"type":"Point"}
}