{
  "type": "Feature",
  "properties": {
    "addr:full":"5128 SE Welch Rd Gresham OR 97080",
    "addr:housenumber":"5128",
    "addr:postcode":"97080",
    "addr:street":"Se Welch Rd",
    "iso:country":"US",
    "sg:address":"5128 SE Welch Rd",
    "sg:city":"Gresham",
    "sg:classifiers":[
        {
            "category":"Retail",
            "subcategory":"Repair Shop",
            "type":"Services"
        }
    ],
    "sg:phone":"+1 503 663 5131",
    "sg:postcode":"97080",
    "sg:province":"OR",
    "sg:tags":[
        "major",
        "appliance"
    ],
    "wof:name":"Webster Appliance",
    "wof:placetype":"venue"
},
  "geometry": {"coordinates":[-122.381272,45.475719],"type":"Point"}
}