{
  "type": "Feature",
  "properties": {
    "iso:country":"US",
    "sg:address":"14698 SE 82nd Dr",
    "sg:city":"Clackamas",
    "sg:classifiers":[
        {
            "category":"Manufacturing",
            "subcategory":"Motor Vehicles & Parts",
            "type":"Manufacturing & Wholesale Goods"
        }
    ],
    "sg:phone":"+1 503 656 0455",
    "sg:postcode":"97015",
    "sg:province":"OR",
    "sg:tags":[
        "mfg"
    ],
    "wof:name":"Rhino Linings Of Clackamas",
    "wof:placetype":"venue"
},
  "geometry": {"coordinates":[-122.569385,45.415521],"type":"Point"}
}