{
  "type": "Feature",
  "properties": {
    "iso:country":"US",
    "sg:address":"2308 Island Ave",
    "sg:city":"La Grande",
    "sg:classifiers":[
        {
            "category":"Restaurant",
            "type":"Food & Drink"
        }
    ],
    "sg:menulink":"http://www.allmenus.com/or/la-grande/201109-mcdonalds/menu/",
    "sg:postcode":"97850",
    "sg:province":"OR",
    "sg:tags":[
        "burger",
        "american"
    ],
    "wof:name":"McDonald's",
    "wof:placetype":"venue"
},
  "geometry": {"coordinates":[-118.076058,45.330265],"type":"Point"}
}