{
  "type": "Feature",
  "properties": {
    "iso:country":"US",
    "sg:address":"225 Silverside Pl",
    "sg:city":"Hammond",
    "sg:classifiers":[
        {
            "category":"Manufacturing",
            "subcategory":"Metals",
            "type":"Manufacturing & Wholesale Goods"
        }
    ],
    "sg:phone":"+1 503 861 3534",
    "sg:postcode":"97121",
    "sg:province":"OR",
    "sg:tags":[
        "windows"
    ],
    "sg:website":"www.bergersonwindow.com",
    "wof:name":"Bergerson Cedar Windows Inc",
    "wof:placetype":"venue"
},
  "geometry": {"coordinates":[-123.963219,46.202286],"type":"Point"}
}