{
  "type": "Feature",
  "properties": {
    "addr:full":"1055 Marine Dr Astoria OR 97103",
    "addr:housenumber":"1055",
    "addr:postcode":"97103",
    "addr:street":"Marine Dr",
    "iso:country":"US",
    "sg:address":"1055 Marine Dr",
    "sg:city":"Astoria",
    "sg:classifiers":[
        {
            "category":"Wholesale",
            "subcategory":"Machinery & Supplies",
            "type":"Manufacturing & Wholesale Goods"
        },
        {
            "category":"Wholesale",
            "subcategory":"Stationery",
            "type":"Manufacturing & Wholesale Goods"
        }
    ],
    "sg:phone":"+1 503 325 6362",
    "sg:postcode":"97103",
    "sg:province":"OR",
    "sg:tags":[
        "paint",
        "paper",
        "janitor",
        "janitorial"
    ],
    "wof:name":"Astoria Janitor & Paper Sup Co",
    "wof:placetype":"venue"
},
  "geometry": {"coordinates":[-123.83233199999999,46.189656],"type":"Point"}
}