{
  "type": "Feature",
  "properties": {
    "addr:full":"2350 NE Griffin Oaks St Hillsboro OR 97124",
    "addr:housenumber":"2350",
    "addr:postcode":"97124",
    "addr:street":"Ne Griffin Oaks St",
    "iso:country":"US",
    "sg:address":"2350 NE Griffin Oaks St",
    "sg:city":"Hillsboro",
    "sg:classifiers":[
        {
            "category":"Education",
            "subcategory":"Library",
            "type":"Public Place"
        }
    ],
    "sg:phone":"+1 503 473 3821",
    "sg:postcode":"97124",
    "sg:province":"OR",
    "sg:tags":[
        "reading",
        "instruction"
    ],
    "sg:website":"http://www.kumon.com",
    "wof:name":"Kumon Math & Reading Center Of Hillsboro",
    "wof:placetype":"venue"
},
  "geometry": {"coordinates":[-122.959502,45.540121],"type":"Point"}
}