{
  "type": "Feature",
  "properties": {
    "addr:full":"1049 SW Baseline St Hillsboro OR 97123",
    "addr:housenumber":"1049",
    "addr:postcode":"97123",
    "addr:street":"Sw Baseline St",
    "iso:country":"US",
    "sg:address":"1049 SW Baseline St",
    "sg:city":"Hillsboro",
    "sg:classifiers":[
        {
            "category":"Professional",
            "subcategory":"Accounting & Tax Preparation",
            "type":"Services"
        }
    ],
    "sg:phone":"+1 503 844 4913",
    "sg:postcode":"97123",
    "sg:province":"OR",
    "sg:tags":[
        "accountant"
    ],
    "wof:name":"Jack Jenkins CPA",
    "wof:placetype":"venue"
},
  "geometry": {"coordinates":[-122.99758,45.520153],"type":"Point"}
}