{
  "type": "Feature",
  "properties": {
    "addr:full":"1000 Conger St Eugene OR 97402",
    "addr:housenumber":"1000",
    "addr:postcode":"97402",
    "addr:street":"Conger St",
    "iso:country":"US",
    "sg:address":"1000 Conger St",
    "sg:city":"Eugene",
    "sg:classifiers":[
        {
            "category":"Manufacturing",
            "subcategory":"Furniture",
            "type":"Manufacturing & Wholesale Goods"
        }
    ],
    "sg:phone":"+1 541 345 1984",
    "sg:postcode":"97402",
    "sg:province":"OR",
    "sg:tags":[
        "wood",
        "mfg"
    ],
    "wof:name":"Wallace Cabinets Inc",
    "wof:placetype":"venue"
},
  "geometry": {"coordinates":[-123.13382300000001,44.04789],"type":"Point"}
}