{
  "type": "Feature",
  "properties": {
    "addr:full":"2628 New Hope Rd Grants Pass OR 97527",
    "addr:housenumber":"2628",
    "addr:postcode":"97527",
    "addr:street":"New Hope Rd",
    "iso:country":"US",
    "sg:address":"2628 New Hope Rd",
    "sg:city":"Grants Pass",
    "sg:classifiers":[
        {
            "category":"Freight",
            "type":"Transportation"
        }
    ],
    "sg:phone":"+1 541 479 3191",
    "sg:postcode":"97527",
    "sg:province":"OR",
    "sg:tags":[
        "operator",
        "trucking"
    ],
    "wof:name":"Malaby Transport System",
    "wof:placetype":"venue"
},
  "geometry": {"coordinates":[-123.34779399999999,42.407105],"type":"Point"}
}