{
  "type": "Feature",
  "properties": {
    "iso:country":"US",
    "sg:address":"2125 SE 262nd Ave",
    "sg:city":"Gresham",
    "sg:classifiers":[
        {
            "category":"Shopping",
            "subcategory":"Clothing, Apparel, & Fashions",
            "type":"Retail Goods"
        }
    ],
    "sg:phone":"+1 503 666 1813",
    "sg:postcode":"97080",
    "sg:province":"OR",
    "sg:tags":[
        "alteration"
    ],
    "wof:name":"Michele's Alterations",
    "wof:placetype":"venue"
},
  "geometry": {"coordinates":[-122.393377,45.481039],"type":"Point"}
}