{
  "type": "Feature",
  "properties": {
    "iso:country":"US",
    "sg:address":"725 SE 9th Ave",
    "sg:city":"Portland",
    "sg:classifiers":[
        {
            "category":"Wholesale",
            "subcategory":"Auto Parts",
            "type":"Manufacturing & Wholesale Goods"
        }
    ],
    "sg:phone":"+1 503 231 0079",
    "sg:postcode":"97214",
    "sg:province":"OR",
    "sg:tags":[
        "equipment",
        "automotive",
        "automobile"
    ],
    "wof:name":"Martin Sales Company",
    "wof:placetype":"venue"
},
  "geometry": {"coordinates":[-122.656761,45.517388],"type":"Point"}
}