{
  "type": "Feature",
  "properties": {
    "addr:full":"535 NW Inlet Ave Lincoln City OR 97367",
    "addr:housenumber":"535",
    "addr:postcode":"97367",
    "addr:street":"Nw Inlet Ave",
    "iso:country":"US",
    "sg:address":"535 NW Inlet Ave",
    "sg:city":"Lincoln City",
    "sg:classifiers":[
        {
            "category":"Travel",
            "subcategory":"Hotels & Motels",
            "type":"Entertainment"
        }
    ],
    "sg:phone":"+1 541 994 4227",
    "sg:postcode":"97367",
    "sg:province":"OR",
    "sg:website":"www.bestwestern.com",
    "wof:name":"Best Western Lincoln Sands",
    "wof:placetype":"venue"
},
  "geometry": {"coordinates":[-124.015922,44.970681],"type":"Point"}
}