{
  "type": "Feature",
  "properties": {
    "iso:country":"US",
    "sg:address":"14360 SE Industrial Way",
    "sg:city":"Clackamas",
    "sg:classifiers":[
        {
            "category":"Building & Trades",
            "subcategory":"Construction",
            "type":"Services"
        }
    ],
    "sg:phone":"+1 503 659 8583",
    "sg:postcode":"97015",
    "sg:province":"OR",
    "sg:tags":[
        "water",
        "main",
        "contractor"
    ],
    "sg:website":"www.aadrilling.com",
    "wof:name":"A & A Drilling Svc Inc",
    "wof:placetype":"venue"
},
  "geometry": {"coordinates":[-122.56597600000001,45.418576],"type":"Point"}
}