{
  "type": "Feature",
  "properties": {
    "iso:country":"US",
    "sg:address":"100 Shane Dr",
    "sg:city":"Arlington",
    "sg:classifiers":[
        {
            "category":"Food & Beverages",
            "subcategory":"Groceries & Convenience Stores",
            "type":"Retail Goods"
        }
    ],
    "sg:phone":"+1 541 454 2711",
    "sg:postcode":"97812",
    "sg:province":"OR",
    "sg:tags":[
        "grocer"
    ],
    "wof:name":"Thrifty Food Ctr",
    "wof:placetype":"venue"
},
  "geometry": {"coordinates":[-120.192196,45.709426],"type":"Point"}
}