{
  "type": "Feature",
  "properties": {
    "iso:country":"US",
    "sg:address":"18201 NE Portal Way # 102",
    "sg:city":"Portland",
    "sg:classifiers":[
        {
            "category":"Manufacturing",
            "subcategory":"Metals",
            "type":"Manufacturing & Wholesale Goods"
        }
    ],
    "sg:phone":"+1 503 535 2770",
    "sg:postcode":"97230",
    "sg:province":"OR",
    "sg:tags":[
        "metal-wholesale",
        "manufacturer"
    ],
    "sg:website":"http://www.vistarvsa.com",
    "wof:name":"Samuel, Son & Co. Inc.",
    "wof:placetype":"venue"
},
  "geometry": {"coordinates":[-122.47599,45.551647],"type":"Point"}
}