{
  "type": "Feature",
  "properties": {
    "iso:country":"US",
    "sg:address":"745 W Hills Way NW",
    "sg:city":"Salem",
    "sg:classifiers":[
        {
            "category":"Professional",
            "subcategory":"Business Services",
            "type":"Services"
        }
    ],
    "sg:phone":"+1 503 375 0285",
    "sg:postcode":"97304",
    "sg:province":"OR",
    "wof:name":"High Ground Enterprises LLC",
    "wof:placetype":"venue"
},
  "geometry": {"coordinates":[-123.07369799999999,44.944758],"type":"Point"}
}