{
  "type": "Feature",
  "properties": {
    "iso:country":"US",
    "sg:address":"1410 SE 35th Ave",
    "sg:city":"Portland",
    "sg:classifiers":[
        {
            "category":"Professional",
            "subcategory":"Art Services",
            "type":"Services"
        }
    ],
    "sg:phone":"+1 503 358 5761",
    "sg:postcode":"97214",
    "sg:province":"OR",
    "sg:tags":[
        "commercial",
        "design"
    ],
    "wof:name":"Stretch Creative",
    "wof:placetype":"venue"
},
  "geometry": {"coordinates":[-122.628135,45.512141],"type":"Point"}
}