{
  "type": "Feature",
  "properties": {
    "iso:country":"US",
    "sg:address":"6980 Windsor Island Rd N",
    "sg:city":"Salem",
    "sg:classifiers":[
        {
            "category":"Retail",
            "subcategory":"Portrait Studio",
            "type":"Services"
        }
    ],
    "sg:phone":"+1 503 390 9048",
    "sg:postcode":"97303",
    "sg:province":"OR",
    "sg:tags":[
        "laboratory",
        "photo",
        "photofinishing",
        "photographer"
    ],
    "wof:name":"Weathers Photo Inc",
    "wof:placetype":"venue"
},
  "geometry": {"coordinates":[-123.054687,45.02005],"type":"Point"}
}