{
  "type": "Feature",
  "properties": {
    "iso:country":"US",
    "sg:address":"2555 Santiam Hwy SE",
    "sg:city":"Albany",
    "sg:classifiers":[
        {
            "category":"Food & Beverages",
            "subcategory":"Bakery",
            "type":"Retail Goods"
        }
    ],
    "sg:phone":"+1 541 926 7551",
    "sg:postcode":"97322",
    "sg:province":"OR",
    "sg:tags":[
        "doughnut"
    ],
    "wof:name":"Cork's Old Fashioned Donuts",
    "wof:placetype":"venue"
},
  "geometry": {"coordinates":[-123.074765,44.632433],"type":"Point"}
}