{
  "type": "Feature",
  "properties": {
    "iso:country":"US",
    "sg:address":"1760 Market St NE",
    "sg:city":"Salem",
    "sg:classifiers":[
        {
            "category":"Food & Beverages",
            "subcategory":"Specialty",
            "type":"Retail Goods"
        }
    ],
    "sg:phone":"+1 503 391 9081",
    "sg:postcode":"97301",
    "sg:province":"OR",
    "wof:name":"Joe Mocha",
    "wof:placetype":"venue"
},
  "geometry": {"coordinates":[-123.012732,44.948672],"type":"Point"}
}