{
  "type": "Feature",
  "properties": {
    "iso:country":"US",
    "sg:address":"619 SW Park Ave",
    "sg:city":"Portland",
    "sg:classifiers":[
        {
            "category":"Restaurant",
            "type":"Food & Drink"
        }
    ],
    "sg:menulink":"http://www.allmenus.com/or/portland/128627-subway/menu/",
    "sg:phone":"+1 971 244 0555",
    "sg:postcode":"97205",
    "sg:province":"OR",
    "sg:tags":[
        "american",
        "sandwich"
    ],
    "wof:name":"Subway",
    "wof:placetype":"venue"
},
  "geometry": {"coordinates":[-122.680431,45.519898],"type":"Point"}
}