{
  "type": "Feature",
  "properties": {
    "iso:country":"US",
    "sg:address":"3480 Harris St",
    "sg:city":"Eugene",
    "sg:classifiers":[
        {
            "category":"Recreation",
            "type":"Entertainment"
        },
        {
            "category":"Manufacturing",
            "subcategory":"Printing",
            "type":"Manufacturing & Wholesale Goods"
        }
    ],
    "sg:phone":"+1 541 484 4243",
    "sg:postcode":"97405",
    "sg:province":"OR",
    "sg:tags":[
        "martial",
        "arts",
        "instruction",
        "typesetting"
    ],
    "wof:name":"Prototype Graphics",
    "wof:placetype":"venue"
},
  "geometry": {"coordinates":[-123.077403,44.021634],"type":"Point"}
}