{
  "type": "Feature",
  "properties": {
    "addr:full":"2580 State St Salem OR 97301",
    "addr:housenumber":"2580",
    "addr:postcode":"97301",
    "addr:street":"State St",
    "iso:country":"US",
    "sg:address":"2580 State St",
    "sg:city":"Salem",
    "sg:classifiers":[
        {
            "category":"Professional",
            "subcategory":"Lawyer & Legal Services",
            "type":"Services"
        }
    ],
    "sg:phone":"+1 866 985 3944",
    "sg:postcode":"97301",
    "sg:province":"OR",
    "sg:tags":[
        "attorney",
        "law",
        "family",
        "practice",
        "immigration",
        "criminal"
    ],
    "sg:website":"http://www.jvanness.com",
    "wof:name":"Van Ness Mooney LLC",
    "wof:placetype":"venue"
},
  "geometry": {"coordinates":[-123.008202,44.931825],"type":"Point"}
}