{
  "type": "Feature",
  "properties": {
    "iso:country":"US",
    "sg:address":"7911 SE Southgate St",
    "sg:city":"Portland",
    "sg:classifiers":[
        {
            "category":"Building & Trades",
            "subcategory":"Construction",
            "type":"Services"
        }
    ],
    "sg:phone":"+1 503 235 6105",
    "sg:postcode":"97222",
    "sg:province":"OR",
    "sg:tags":[
        "wallpaper"
    ],
    "wof:name":"Abram & Davis Wallcovering",
    "wof:placetype":"venue"
},
  "geometry": {"coordinates":[-122.58250200000001,45.43472],"type":"Point"}
}