{
  "type": "Feature",
  "properties": {
    "addr:full":"4852 Saunter Loop NE Salem OR 97305",
    "addr:housenumber":"4852",
    "addr:postcode":"97305",
    "addr:street":"Saunter Loop Ne",
    "iso:country":"US",
    "sg:address":"4852 Saunter Loop NE",
    "sg:city":"Salem",
    "sg:classifiers":[
        {
            "category":"Communications",
            "subcategory":"Film & Video Production",
            "type":"Services"
        }
    ],
    "sg:phone":"+1 503 851 9922",
    "sg:postcode":"97305",
    "sg:province":"OR",
    "sg:tags":[
        "motion"
    ],
    "wof:name":"Bk Imaging",
    "wof:placetype":"venue"
},
  "geometry": {"coordinates":[-122.964438,44.962834],"type":"Point"}
}