{
  "type": "Feature",
  "properties": {
    "addr:full":"16230 SE Webster Rd Portland OR 97267",
    "addr:postcode":"16230;97267",
    "addr:street":"Se Webster Rd",
    "iso:country":"US",
    "sg:address":"16230 SE Webster Rd",
    "sg:city":"Portland",
    "sg:classifiers":[
        {
            "category":"Shopping",
            "subcategory":"Pets & Pet Supplies",
            "type":"Retail Goods"
        }
    ],
    "sg:phone":"+1 503 659 5275",
    "sg:postcode":"97267",
    "sg:province":"OR",
    "sg:tags":[
        "furnishing",
        "dog",
        "store",
        "cat"
    ],
    "sg:website":"http://www.gripleash.com",
    "wof:name":"The Gripper",
    "wof:placetype":"venue"
},
  "geometry": {"coordinates":[-122.58569199999999,45.404717],"type":"Point"}
}