{
  "type": "Feature",
  "properties": {
    "addr:full":"1628 Ash St Forest Grove OR 97116",
    "addr:housenumber":"1628",
    "addr:postcode":"97116",
    "addr:street":"Ash St",
    "iso:country":"US",
    "sg:address":"1628 Ash St",
    "sg:city":"Forest Grove",
    "sg:classifiers":[
        {
            "category":"Building & Trades",
            "subcategory":"Construction",
            "type":"Services"
        }
    ],
    "sg:phone":"+1 503 201 4733",
    "sg:postcode":"97116",
    "sg:province":"OR",
    "sg:tags":[
        "residential"
    ],
    "wof:name":"Assured Development",
    "wof:placetype":"venue"
},
  "geometry": {"coordinates":[-123.110377,45.514486],"type":"Point"}
}