{
  "type": "Feature",
  "properties": {
    "addr:full":"465 38th St Astoria OR 97103",
    "addr:housenumber":"465",
    "addr:postcode":"97103",
    "addr:street":"38Th St",
    "iso:country":"US",
    "sg:address":"465 38th St",
    "sg:city":"Astoria",
    "sg:classifiers":[
        {
            "category":"Social Services",
            "subcategory":"Child Care",
            "type":"Services"
        }
    ],
    "sg:phone":"+1 503 325 3004",
    "sg:postcode":"97103",
    "sg:province":"OR",
    "sg:tags":[
        "day"
    ],
    "wof:name":"Kidsworld Day Care",
    "wof:placetype":"venue"
},
  "geometry": {"coordinates":[-123.800043,46.192102],"type":"Point"}
}