{
  "type": "Feature",
  "properties": {
    "iso:country":"US",
    "sg:address":"1350 N 1st St",
    "sg:city":"Hermiston",
    "sg:classifiers":[
        {
            "category":"Banks & Credit Unions",
            "subcategory":"Bank",
            "type":"Services"
        }
    ],
    "sg:phone":"+1 541 564 8606",
    "sg:postcode":"97838",
    "sg:province":"OR",
    "wof:name":"Sterling Savings Bank",
    "wof:placetype":"venue"
},
  "geometry": {"coordinates":[-119.29007300000001,45.850325],"type":"Point"}
}