{
  "type": "Feature",
  "properties": {
    "iso:country":"US",
    "sg:address":"1080 SW 35th St",
    "sg:city":"Corvallis",
    "sg:classifiers":[
        {
            "category":"Professional",
            "subcategory":"Research",
            "type":"Services"
        }
    ],
    "sg:phone":"+1 541 754 9215",
    "sg:postcode":"97333",
    "sg:province":"OR",
    "sg:tags":[
        "wildlife",
        "preservation"
    ],
    "wof:name":"Courtney Drake",
    "wof:placetype":"venue"
},
  "geometry": {"coordinates":[-123.289678,44.556137],"type":"Point"}
}