{
  "type": "Feature",
  "properties": {
    "iso:country":"US",
    "sg:address":"2005 NE 27th Ave",
    "sg:city":"Portland",
    "sg:classifiers":[
        {
            "category":"Professional",
            "subcategory":"Management & Consulting",
            "type":"Services"
        }
    ],
    "sg:phone":"+1 503 249 7745",
    "sg:postcode":"97212",
    "sg:province":"OR",
    "sg:tags":[
        "logistics"
    ],
    "wof:name":"Logistics Data Group Inc",
    "wof:placetype":"venue"
},
  "geometry": {"coordinates":[-122.638215,45.536895],"type":"Point"}
}