{
  "type": "Feature",
  "properties": {
    "iso:country":"US",
    "sg:address":"1010 Lloyd Center",
    "sg:city":"Portland",
    "sg:classifiers":[
        {
            "category":"Shopping",
            "subcategory":"Clothing, Apparel, & Fashions",
            "type":"Retail Goods"
        }
    ],
    "sg:phone":"+1 503 282 4997",
    "sg:postcode":"97232",
    "sg:province":"OR",
    "sg:tags":[
        "children's",
        "clothing"
    ],
    "sg:website":"www.childrensplace.com",
    "wof:name":"Children's Place",
    "wof:placetype":"venue"
},
  "geometry": {"coordinates":[-122.65440700000001,45.531676],"type":"Point"}
}