{
  "type": "Feature",
  "properties": {
    "iso:country":"US",
    "sg:address":"60726 Golf Village Loop",
    "sg:city":"Bend",
    "sg:classifiers":[
        {
            "category":"Shopping",
            "subcategory":"Catalog Store",
            "type":"Retail Goods"
        }
    ],
    "sg:phone":"+1 541 382 0076",
    "sg:postcode":"97702",
    "sg:province":"OR",
    "sg:tags":[
        "mail",
        "house"
    ],
    "wof:name":"Jobe Company LLC",
    "wof:placetype":"venue"
},
  "geometry": {"coordinates":[-121.378433,44.011143],"type":"Point"}
}