{
  "type": "Feature",
  "properties": {
    "iso:country":"US",
    "sg:address":"20975 Young Ave",
    "sg:city":"Bend",
    "sg:classifiers":[
        {
            "category":"Farming",
            "subcategory":"Livestock Farm",
            "type":"Manufacturing & Wholesale Goods"
        }
    ],
    "sg:phone":"+1 541 410 3228",
    "sg:postcode":"97701",
    "sg:province":"OR",
    "sg:tags":[
        "horse"
    ],
    "wof:name":"Come Horse Around",
    "wof:placetype":"venue"
},
  "geometry": {"coordinates":[-121.278156,44.196251],"type":"Point"}
}