{
  "type": "Feature",
  "properties": {
    "addr:full":"60575 Billadeau Rd Bend OR 97702",
    "addr:postcode":"60575;97702",
    "addr:street":"Billadeau Rd",
    "iso:country":"US",
    "sg:address":"60575 Billadeau Rd",
    "sg:city":"Bend",
    "sg:classifiers":[
        {
            "category":"Professional",
            "subcategory":"Research",
            "type":"Services"
        },
        {
            "category":"Professional",
            "subcategory":"Business Services",
            "type":"Services"
        }
    ],
    "sg:phone":"+1 541 388 7477",
    "sg:postcode":"97702",
    "sg:province":"OR",
    "sg:tags":[
        "environmental",
        "product",
        "ecological"
    ],
    "sg:website":"http://www.spatial-solutions.com",
    "wof:name":"Spatial Solutions",
    "wof:placetype":"venue"
},
  "geometry": {"coordinates":[-121.224147,43.999515],"type":"Point"}
}