{
  "type": "Feature",
  "properties": {
    "iso:country":"US",
    "sg:address":"370 Lancaster Dr NE",
    "sg:city":"Salem",
    "sg:classifiers":[
        {
            "category":"Retail",
            "subcategory":"Car Wash",
            "type":"Services"
        }
    ],
    "sg:phone":"+1 503 463 7027",
    "sg:postcode":"97301",
    "sg:province":"OR",
    "sg:tags":[
        "auto",
        "detailing"
    ],
    "wof:name":"Triple MS Detailing Service",
    "wof:placetype":"venue"
},
  "geometry": {"coordinates":[-122.98312799999999,44.932282],"type":"Point"}
}