{
  "type": "Feature",
  "properties": {
    "addr:full":"1100 SE Waverly Dr Portland OR 97222",
    "addr:housenumber":"1100",
    "addr:postcode":"97222",
    "addr:street":"Se Waverly Dr",
    "iso:country":"US",
    "sg:address":"1100 SE Waverly Dr",
    "sg:city":"Portland",
    "sg:classifiers":[
        {
            "category":"Shopping",
            "subcategory":"Bicycles & Sporting Goods",
            "type":"Retail Goods"
        },
        {
            "category":"Organizations",
            "subcategory":"Membership Organization",
            "type":"Services"
        },
        {
            "category":"Sports & Exercise",
            "subcategory":"Golf",
            "type":"Entertainment"
        }
    ],
    "sg:phone":"+1 503 654 6521",
    "sg:postcode":"97222",
    "sg:province":"OR",
    "sg:tags":[
        "supply",
        "club",
        "private",
        "equipment",
        "courses-private",
        "course"
    ],
    "wof:name":"Waverley Country Golf Club",
    "wof:placetype":"venue"
},
  "geometry": {"coordinates":[-122.651927,45.452567],"type":"Point"}
}