{
  "type": "Feature",
  "properties": {
    "addr:full":"302 NE 122nd Avenue Portland OR 97230",
    "addr:housenumber":"302",
    "addr:postcode":"97230",
    "addr:street":"Ne 122Nd Avenue",
    "iso:country":"US",
    "sg:address":"302 NE 122nd Avenue",
    "sg:city":"Portland",
    "sg:classifiers":[
        {
            "category":"Restaurant",
            "type":"Food & Drink"
        }
    ],
    "sg:phone":"+1 503 252 3460",
    "sg:postcode":"97230",
    "sg:province":"OR",
    "wof:name":"La Isla Bonita",
    "wof:placetype":"venue"
},
  "geometry": {"coordinates":[-122.53772600000001,45.525163],"type":"Point"}
}