{
  "type": "Feature",
  "properties": {
    "iso:country":"US",
    "sg:address":"1751 Alcan Dr",
    "sg:city":"Medford",
    "sg:classifiers":[
        {
            "category":"Shopping",
            "subcategory":"Used Merchandise",
            "type":"Retail Goods"
        }
    ],
    "sg:phone":"+1 541 779 3329",
    "sg:postcode":"97504",
    "sg:province":"OR",
    "wof:name":"Grizzly Mountain Trading",
    "wof:placetype":"venue"
},
  "geometry": {"coordinates":[-122.86179300000001,42.350955],"type":"Point"}
}