{
  "type": "Feature",
  "properties": {
    "iso:country":"US",
    "sg:address":"8325 SE Harney St Ste 101",
    "sg:city":"Portland",
    "sg:classifiers":[
        {
            "category":"Health Services",
            "subcategory":"Dentist",
            "type":"Services"
        }
    ],
    "sg:phone":"+1 503 228 5059",
    "sg:postcode":"97266",
    "sg:province":"OR",
    "sg:website":"springwaterdental.com",
    "wof:name":"Springwater Dental",
    "wof:placetype":"venue"
},
  "geometry": {"coordinates":[-122.57747500000001,45.463299],"type":"Point"}
}