{
  "type": "Feature",
  "properties": {
    "iso:country":"US",
    "sg:address":"2814 SE Steele St",
    "sg:city":"Portland",
    "sg:classifiers":[
        {
            "category":"Health Services",
            "subcategory":"Doctor",
            "type":"Services"
        }
    ],
    "sg:phone":"+1 503 238 7114",
    "sg:postcode":"97202",
    "sg:province":"OR",
    "sg:tags":[
        "osteopathic"
    ],
    "wof:name":"James L Cook Do",
    "wof:placetype":"venue"
},
  "geometry": {"coordinates":[-122.634487,45.484648],"type":"Point"}
}