{
  "type": "Feature",
  "properties": {
    "addr:full":"5213 Hilltop Dr Florence OR 97439",
    "addr:housenumber":"5213",
    "addr:postcode":"97439",
    "addr:street":"Hilltop Dr",
    "iso:country":"US",
    "sg:address":"5213 Hilltop Dr",
    "sg:city":"Florence",
    "sg:classifiers":[
        {
            "category":"Manufacturing",
            "subcategory":"Buildings",
            "type":"Manufacturing & Wholesale Goods"
        },
        {
            "category":"Building & Trades",
            "subcategory":"Construction",
            "type":"Services"
        }
    ],
    "sg:phone":"+1 541 997 8335",
    "sg:postcode":"97439",
    "sg:province":"OR",
    "sg:tags":[
        "home",
        "builder",
        "contractor"
    ],
    "wof:name":"Mg O'brien Contracting",
    "wof:placetype":"venue"
},
  "geometry": {"coordinates":[-124.09871800000001,43.897499],"type":"Point"}
}