{
  "type": "Feature",
  "properties": {
    "addr:full":"2813 Tolkien Ln Lake Oswego OR 97034",
    "addr:housenumber":"2813",
    "addr:postcode":"97034",
    "addr:street":"Tolkien Ln",
    "iso:country":"US",
    "sg:address":"2813 Tolkien Ln",
    "sg:city":"Lake Oswego",
    "sg:classifiers":[
        {
            "category":"Wholesale",
            "subcategory":"Farm Supplies",
            "type":"Manufacturing & Wholesale Goods"
        }
    ],
    "sg:phone":"+1 503 638 9907",
    "sg:postcode":"97034",
    "sg:province":"OR",
    "sg:tags":[
        "grain",
        "elevator"
    ],
    "wof:name":"Cascade Grain Products",
    "wof:placetype":"venue"
},
  "geometry": {"coordinates":[-122.70579499999999,45.391082],"type":"Point"}
}