{
  "type": "Feature",
  "properties": {
    "iso:country":"US",
    "sg:address":"64 Greenridge Ct",
    "sg:city":"Lake Oswego",
    "sg:classifiers":[
        {
            "category":"Professional",
            "type":"Services"
        }
    ],
    "sg:phone":"+1 503 636 1967",
    "sg:postcode":"97035",
    "sg:province":"OR",
    "sg:tags":[
        "language",
        "for",
        "contractor",
        "individual",
        "officer",
        "english",
        "st"
    ],
    "wof:name":"Judith T Kliks",
    "wof:placetype":"venue"
},
  "geometry": {"coordinates":[-122.704778,45.432469],"type":"Point"}
}