{
  "type": "Feature",
  "properties": {
    "addr:full":"1645 16th St Baker City OR 97814",
    "addr:housenumber":"1645",
    "addr:postcode":"97814",
    "addr:street":"16Th St",
    "iso:country":"US",
    "sg:address":"1645 16th St",
    "sg:city":"Baker City",
    "sg:classifiers":[
        {
            "category":"Museum",
            "type":"Entertainment"
        }
    ],
    "sg:phone":"+1 541 523 3881",
    "sg:postcode":"97814",
    "sg:province":"OR",
    "sg:tags":[
        "frame",
        "art",
        "gallery"
    ],
    "wof:name":"Baker City Gallery",
    "wof:placetype":"venue"
},
  "geometry": {"coordinates":[-117.848522,44.774013],"type":"Point"}
}