{
  "type": "Feature",
  "properties": {
    "iso:country":"US",
    "sg:address":"15735 SW 88th Ave",
    "sg:city":"Tigard",
    "sg:classifiers":[
        {
            "category":"Insurance",
            "subcategory":"Insurance Agent",
            "type":"Services"
        }
    ],
    "sg:phone":"+1 503 639 4030",
    "sg:postcode":"97224",
    "sg:province":"OR",
    "wof:name":"Creative Insurance Marketing",
    "wof:placetype":"venue"
},
  "geometry": {"coordinates":[-122.76859899999999,45.405551],"type":"Point"}
}