{
  "type": "Feature",
  "properties": {
    "iso:country":"US",
    "sg:address":"200 Shady Dr",
    "sg:city":"Roseburg",
    "sg:classifiers":[
        {
            "category":"Shopping",
            "subcategory":"Catalog Store",
            "type":"Retail Goods"
        }
    ],
    "sg:phone":"+1 541 672 5807",
    "sg:postcode":"97470",
    "sg:province":"OR",
    "sg:tags":[
        "house",
        "mail"
    ],
    "wof:name":"Kreative Karousel",
    "wof:placetype":"venue"
},
  "geometry": {"coordinates":[-123.418317,43.242065],"type":"Point"}
}