{
  "type": "Feature",
  "properties": {
    "iso:country":"US",
    "sg:address":"3423 Honeywood St",
    "sg:city":"Eugene",
    "sg:classifiers":[
        {
            "category":"Shopping",
            "subcategory":"Gifts & Souvenirs",
            "type":"Retail Goods"
        }
    ],
    "sg:phone":"+1 541 683 3977",
    "sg:postcode":"97408",
    "sg:province":"OR",
    "wof:name":"Gingham Greetings",
    "wof:placetype":"venue"
},
  "geometry": {"coordinates":[-123.076606,44.10189],"type":"Point"}
}