{
  "type": "Feature",
  "properties": {
    "iso:country":"US",
    "sg:address":"1222 Redwood Ave",
    "sg:city":"Grants Pass",
    "sg:classifiers":[
        {
            "category":"Home & Garden",
            "subcategory":"Building Materials",
            "type":"Retail Goods"
        }
    ],
    "sg:phone":"+1 541 471 4941",
    "sg:postcode":"97527",
    "sg:province":"OR",
    "sg:tags":[
        "lumber"
    ],
    "wof:name":"Hardwoods Plus Co",
    "wof:placetype":"venue"
},
  "geometry": {"coordinates":[-123.352211,42.422518],"type":"Point"}
}