{
  "type": "Feature",
  "properties": {
    "iso:country":"US",
    "sg:address":"51 E Stewart Ave",
    "sg:city":"Medford",
    "sg:classifiers":[
        {
            "category":"Arena",
            "subcategory":"Sports Club",
            "type":"Entertainment"
        }
    ],
    "sg:phone":"+1 541 494 1378",
    "sg:postcode":"97501",
    "sg:province":"OR",
    "sg:tags":[
        "martial art"
    ],
    "wof:name":"America's Best Karate",
    "wof:placetype":"venue"
},
  "geometry": {"coordinates":[-122.858583,42.313699],"type":"Point"}
}