{
  "type": "Feature",
  "properties": {
    "addr:full":"15422 Bangy Rd Lake Oswego OR 97035",
    "addr:housenumber":"15422",
    "addr:postcode":"97035",
    "addr:street":"Bangy Rd",
    "iso:country":"US",
    "sg:address":"15422 Bangy Rd",
    "sg:city":"Lake Oswego",
    "sg:classifiers":[
        {
            "category":"Professional",
            "subcategory":"Computer Services",
            "type":"Services"
        }
    ],
    "sg:phone":"+1 503 515 6578",
    "sg:postcode":"97035",
    "sg:province":"OR",
    "sg:tags":[
        "repair"
    ],
    "sg:website":"www.mytechnologybutler.com",
    "wof:name":"Technology Butler",
    "wof:placetype":"venue"
},
  "geometry": {"coordinates":[-122.742102,45.414201],"type":"Point"}
}