{
  "type": "Feature",
  "properties": {
    "iso:country":"US",
    "sg:address":"5003 River Rd N",
    "sg:city":"Keizer",
    "sg:classifiers":[
        {
            "category":"Cinema",
            "subcategory":"Movie Rental",
            "type":"Entertainment"
        }
    ],
    "sg:phone":"+1 503 390 8646",
    "sg:postcode":"97303",
    "sg:province":"OR",
    "sg:tags":[
        "leasing",
        "video",
        "disc",
        "tape"
    ],
    "sg:website":"www.hollywoodvideo.com",
    "wof:name":"Hollywood Video",
    "wof:placetype":"venue"
},
  "geometry": {"coordinates":[-123.026715,44.997899],"type":"Point"}
}