{
  "type": "Feature",
  "properties": {
    "iso:country":"US",
    "sg:address":"420 NE Mason St",
    "sg:city":"Portland",
    "sg:classifiers":[
        {
            "category":"Place Of Worship",
            "type":"Public Place"
        }
    ],
    "sg:phone":"+1 503 335 0686",
    "sg:postcode":"97211",
    "sg:province":"OR",
    "sg:tags":[
        "church"
    ],
    "wof:name":"Irvington Covenant Alf",
    "wof:placetype":"venue"
},
  "geometry": {"coordinates":[-122.66133600000001,45.553299],"type":"Point"}
}