{
  "type": "Feature",
  "properties": {
    "iso:country":"US",
    "sg:address":"11 Main St",
    "sg:city":"Klamath Falls",
    "sg:classifiers":[
        {
            "category":"Travel",
            "subcategory":"Hotels & Motels",
            "type":"Entertainment"
        }
    ],
    "sg:phone":"+1 541 273 8668",
    "sg:postcode":"97601",
    "sg:province":"OR",
    "wof:name":"Rivers Inn Motel",
    "wof:placetype":"venue"
},
  "geometry": {"coordinates":[-121.78880100000001,42.219989],"type":"Point"}
}