{
  "type": "Feature",
  "properties": {
    "iso:country":"US",
    "sg:address":"10090 SE Washington St",
    "sg:city":"Portland",
    "sg:classifiers":[
        {
            "category":"Real Estate",
            "subcategory":"Real Estate Agent",
            "type":"Services"
        }
    ],
    "sg:phone":"+1 503 255 7274",
    "sg:postcode":"97216",
    "sg:province":"OR",
    "wof:name":"Center Oak Properties",
    "wof:placetype":"venue"
},
  "geometry": {"coordinates":[-122.559029,45.518262],"type":"Point"}
}