{
  "type": "Feature",
  "properties": {
    "addr:full":"16000 SE Division Street Portland OR 97236",
    "addr:postcode":"16000;97236",
    "addr:street":"Se Division Street",
    "iso:country":"US",
    "sg:address":"16000 SE Division Street",
    "sg:city":"Portland",
    "sg:classifiers":[
        {
            "category":"Education",
            "subcategory":"Music School",
            "type":"Public Place"
        }
    ],
    "sg:phone":"+1 503 761 1668",
    "sg:postcode":"97236",
    "sg:province":"OR",
    "sg:tags":[
        "instrument",
        "teacher",
        "musical"
    ],
    "wof:name":"Vintage Piano City",
    "wof:placetype":"venue"
},
  "geometry": {"coordinates":[-122.498335,45.504382],"type":"Point"}
}