{
  "type": "Feature",
  "properties": {
    "iso:country":"US",
    "sg:address":"9930 Hoffman Rd",
    "sg:city":"Monmouth",
    "sg:classifiers":[
        {
            "category":"Restaurant",
            "type":"Food & Drink"
        }
    ],
    "sg:phone":"+1 503 838 4578",
    "sg:postcode":"97361",
    "sg:province":"OR",
    "wof:name":"Jose B Rincon",
    "wof:placetype":"venue"
},
  "geometry": {"coordinates":[-123.23209300000001,44.864577],"type":"Point"}
}