{
  "type": "Feature",
  "properties": {
    "iso:country":"US",
    "sg:address":"700 S Canyon Blvd",
    "sg:city":"John Day",
    "sg:classifiers":[
        {
            "category":"Organizations",
            "subcategory":"Religious Organization",
            "type":"Services"
        }
    ],
    "sg:phone":"+1 541 575 2001",
    "sg:postcode":"97845",
    "sg:province":"OR",
    "sg:tags":[
        "church"
    ],
    "wof:name":"Bible Way Community Church",
    "wof:placetype":"venue"
},
  "geometry": {"coordinates":[-118.950741,44.408656],"type":"Point"}
}