{
  "type": "Feature",
  "properties": {
    "iso:country":"US",
    "sg:address":"2095 Rattler Ridge Rd",
    "sg:city":"Mosier",
    "sg:classifiers":[
        {
            "category":"Professional",
            "subcategory":"Computer Services",
            "type":"Services"
        }
    ],
    "sg:phone":"+1 541 478 2444",
    "sg:postcode":"97040",
    "sg:province":"OR",
    "sg:tags":[
        "prepackaged",
        "software"
    ],
    "wof:name":"Angloamerican Khaos",
    "wof:placetype":"venue"
},
  "geometry": {"coordinates":[-121.43460899999999,45.672146],"type":"Point"}
}