{
  "type": "Feature",
  "properties": {
    "iso:country":"US",
    "sg:address":"4090 Stewart Rd",
    "sg:city":"Eugene",
    "sg:classifiers":[
        {
            "category":"Food & Beverages",
            "subcategory":"Candy",
            "type":"Retail Goods"
        },
        {
            "category":"Manufacturing",
            "subcategory":"Food",
            "type":"Manufacturing & Wholesale Goods"
        }
    ],
    "sg:phone":"+1 541 344 4914",
    "sg:postcode":"97402",
    "sg:province":"OR",
    "sg:tags":[
        "confectionery",
        "mfg"
    ],
    "sg:website":"www.euphoriachocolate.com",
    "wof:name":"Euphoria Chocolate Company",
    "wof:placetype":"venue"
},
  "geometry": {"coordinates":[-123.157268,44.050169],"type":"Point"}
}