{
  "type": "Feature",
  "properties": {
    "iso:country":"US",
    "sg:address":"706 SE 6th Ave",
    "sg:city":"Portland",
    "sg:classifiers":[
        {
            "category":"Retail",
            "subcategory":"Portrait Studio",
            "type":"Services"
        }
    ],
    "sg:phone":"+1 503 232 8501",
    "sg:postcode":"97214",
    "sg:province":"OR",
    "sg:tags":[
        "photography",
        "store"
    ],
    "sg:website":"www.citizensphoto.com",
    "wof:name":"Citizens Photo",
    "wof:placetype":"venue"
},
  "geometry": {"coordinates":[-122.659415,45.51779],"type":"Point"}
}