{
  "type": "Feature",
  "properties": {
    "addr:full":"7414 SE Carlton St Portland OR 97206",
    "addr:housenumber":"7414",
    "addr:postcode":"97206",
    "addr:street":"Se Carlton St",
    "iso:country":"US",
    "sg:address":"7414 SE Carlton St",
    "sg:city":"Portland",
    "sg:classifiers":[
        {
            "category":"Retail",
            "subcategory":"Repair Shop",
            "type":"Services"
        }
    ],
    "sg:phone":"+1 503 777 5268",
    "sg:postcode":"97206",
    "sg:province":"OR",
    "sg:tags":[
        "electrical",
        "merchandise"
    ],
    "wof:name":"Shaving Service West",
    "wof:placetype":"venue"
},
  "geometry": {"coordinates":[-122.58425800000001,45.478169],"type":"Point"}
}