{
  "type": "Feature",
  "properties": {
    "iso:country":"US",
    "sg:address":"12612 SE Stephens St",
    "sg:city":"Portland",
    "sg:classifiers":[
        {
            "category":"Building & Trades",
            "subcategory":"Construction",
            "type":"Services"
        }
    ],
    "sg:phone":"+1 503 254 6268",
    "sg:postcode":"97233",
    "sg:province":"OR",
    "sg:tags":[
        "home",
        "remodeling",
        "family"
    ],
    "wof:name":"Gonzalez Home Services",
    "wof:placetype":"venue"
},
  "geometry": {"coordinates":[-122.53461299999999,45.508986],"type":"Point"}
}