{
  "type": "Feature",
  "properties": {
    "addr:full":"3388 Merlin Rd Grants Pass OR 97526",
    "addr:housenumber":"3388",
    "addr:postcode":"97526",
    "addr:street":"Merlin Rd",
    "iso:country":"US",
    "sg:address":"3388 Merlin Rd",
    "sg:city":"Grants Pass",
    "sg:classifiers":[
        {
            "category":"Retail",
            "subcategory":"Auto Repair",
            "type":"Services"
        }
    ],
    "sg:phone":"+1 541 866 2555",
    "sg:postcode":"97526",
    "sg:province":"OR",
    "sg:tags":[
        "automotive"
    ],
    "wof:name":"Affordable Towing & Transport",
    "wof:placetype":"venue"
},
  "geometry": {"coordinates":[-123.372586,42.496459],"type":"Point"}
}