{
  "type": "Feature",
  "properties": {
    "addr:full":"5033 NE 112th Ave Portland OR 97220",
    "addr:housenumber":"5033",
    "addr:postcode":"97220",
    "addr:street":"Ne 112Th Ave",
    "iso:country":"US",
    "sg:address":"5033 NE 112th Ave",
    "sg:city":"Portland",
    "sg:classifiers":[
        {
            "category":"Professional",
            "type":"Services"
        }
    ],
    "sg:phone":"+1 503 251 5593",
    "sg:postcode":"97220",
    "sg:province":"OR",
    "sg:tags":[
        "establishment"
    ],
    "wof:name":"David L Aldaz Specialties",
    "wof:placetype":"venue"
},
  "geometry": {"coordinates":[-122.547507,45.560058],"type":"Point"}
}