{
  "type": "Feature",
  "properties": {
    "addr:full":"2954 Florence Ave NE Salem OR 97301",
    "addr:housenumber":"2954",
    "addr:postcode":"97301",
    "addr:street":"Florence Ave Ne",
    "iso:country":"US",
    "sg:address":"2954 Florence Ave NE",
    "sg:city":"Salem",
    "sg:classifiers":[
        {
            "category":"Shopping",
            "subcategory":"Computers & Home Electronics",
            "type":"Retail Goods"
        }
    ],
    "sg:phone":"+1 503 588 4005",
    "sg:postcode":"97301",
    "sg:province":"OR",
    "sg:tags":[
        "dish",
        "satellite"
    ],
    "wof:name":"Frontier Satellite",
    "wof:placetype":"venue"
},
  "geometry": {"coordinates":[-122.999827,44.960169],"type":"Point"}
}