{
  "type": "Feature",
  "properties": {
    "iso:country":"US",
    "sg:address":"740 SE 106th Ave",
    "sg:city":"Portland",
    "sg:classifiers":[
        {
            "category":"Social Services",
            "type":"Services"
        }
    ],
    "sg:phone":"+1 503 256 2381",
    "sg:postcode":"97216",
    "sg:province":"OR",
    "sg:tags":[
        "senior",
        "citizen"
    ],
    "wof:name":"Loaves & Fishes/Meals-Wheels",
    "wof:placetype":"venue"
},
  "geometry": {"coordinates":[-122.553864,45.518214],"type":"Point"}
}