{
  "type": "Feature",
  "properties": {
    "iso:country":"US",
    "sg:address":"62555 Waugh Rd",
    "sg:city":"Bend",
    "sg:classifiers":[
        {
            "category":"Recreation",
            "type":"Entertainment"
        }
    ],
    "sg:phone":"+1 541 389 8040",
    "sg:postcode":"97701",
    "sg:province":"OR",
    "wof:name":"On Rocks",
    "wof:placetype":"venue"
},
  "geometry": {"coordinates":[-121.173373,44.085682],"type":"Point"}
}