{
  "type": "Feature",
  "properties": {
    "iso:country":"US",
    "sg:address":"14266 SE Sunnyside Rd",
    "sg:city":"Clackamas",
    "sg:classifiers":[
        {
            "category":"Insurance",
            "subcategory":"Insurance Agent",
            "type":"Services"
        }
    ],
    "sg:phone":"+1 503 659 5200",
    "sg:postcode":"97015",
    "sg:province":"OR",
    "wof:name":"Walker Pinkiy Agency",
    "wof:placetype":"venue"
},
  "geometry": {"coordinates":[-122.51612299999999,45.424828],"type":"Point"}
}