{
  "type": "Feature",
  "properties": {
    "iso:country":"US",
    "sg:address":"29805 Mary St",
    "sg:city":"Gold Beach",
    "sg:classifiers":[
        {
            "category":"Social Services",
            "type":"Services"
        }
    ],
    "sg:phone":"+1 541 247 5600",
    "sg:postcode":"97444",
    "sg:province":"OR",
    "sg:tags":[
        "organization",
        "welfare"
    ],
    "wof:name":"Curry County Comms-Children",
    "wof:placetype":"venue"
},
  "geometry": {"coordinates":[-124.420755,42.417094],"type":"Point"}
}