{
  "type": "Feature",
  "properties": {
    "iso:country":"US",
    "sg:address":"6802 SW 33rd Place",
    "sg:city":"Portland",
    "sg:classifiers":[
        {
            "category":"Real Estate",
            "subcategory":"Real Estate Services",
            "type":"Services"
        }
    ],
    "sg:phone":"+1 503 244 2977",
    "sg:postcode":"97219",
    "sg:province":"OR",
    "sg:tags":[
        "home",
        "inspector"
    ],
    "wof:name":"Naven Restoration Specialties",
    "wof:placetype":"venue"
},
  "geometry": {"coordinates":[-122.71107600000001,45.47471],"type":"Point"}
}