{
  "type": "Feature",
  "properties": {
    "addr:full":"2267 N Interstate Ave Portland OR 97227",
    "addr:housenumber":"2267",
    "addr:postcode":"97227",
    "addr:street":"N Interstate Ave",
    "iso:country":"US",
    "sg:address":"2267 N Interstate Ave",
    "sg:city":"Portland",
    "sg:classifiers":[
        {
            "category":"Professional",
            "subcategory":"Management & Consulting",
            "type":"Services"
        }
    ],
    "sg:phone":"+1 503 235 8786",
    "sg:postcode":"97227",
    "sg:province":"OR",
    "sg:tags":[
        "association"
    ],
    "sg:website":"www.oregoncommunitywarehouse.org",
    "wof:name":"Oregon Community Warehouse",
    "wof:placetype":"venue"
},
  "geometry": {"coordinates":[-122.675298,45.539283],"type":"Point"}
}