{
  "type": "Feature",
  "properties": {
    "addr:full":"14860 SW Rosario Ln Portland OR 97224",
    "addr:housenumber":"14860",
    "addr:postcode":"97224",
    "addr:street":"Sw Rosario Ln",
    "iso:country":"US",
    "sg:address":"14860 SW Rosario Ln",
    "sg:city":"Portland",
    "sg:classifiers":[
        {
            "category":"Real Estate",
            "subcategory":"Real Estate Agent",
            "type":"Services"
        }
    ],
    "sg:phone":"+1 503 590 5639",
    "sg:postcode":"97224",
    "sg:province":"OR",
    "sg:tags":[
        "property",
        "management"
    ],
    "wof:name":"All American Roofing",
    "wof:placetype":"venue"
},
  "geometry": {"coordinates":[-122.830034,45.404398],"type":"Point"}
}