{
  "type": "Feature",
  "properties": {
    "iso:country":"US",
    "sg:address":"1844 SW Troy St",
    "sg:city":"Portland",
    "sg:classifiers":[
        {
            "category":"Professional",
            "subcategory":"Management & Consulting",
            "type":"Services"
        }
    ],
    "sg:phone":"+1 503 936 2202",
    "sg:postcode":"97219",
    "sg:province":"OR",
    "sg:tags":[
        "telecommunication"
    ],
    "wof:name":"Netcity Engineering Inc",
    "wof:placetype":"venue"
},
  "geometry": {"coordinates":[-122.695532,45.468249],"type":"Point"}
}