{
  "type": "Feature",
  "properties": {
    "iso:country":"US",
    "sg:address":"305 Main St",
    "sg:city":"Klamath Falls",
    "sg:classifiers":[
        {
            "category":"Government",
            "subcategory":"Office",
            "type":"Public Place"
        }
    ],
    "sg:phone":"+1 541 883 4209",
    "sg:postcode":"97601",
    "sg:province":"OR",
    "sg:tags":[
        "executive"
    ],
    "wof:name":"Building Dept",
    "wof:placetype":"venue"
},
  "geometry": {"coordinates":[-121.784128,42.223382],"type":"Point"}
}