{
  "type": "Feature",
  "properties": {
    "iso:country":"US",
    "sg:address":"511 11th St",
    "sg:city":"Vale",
    "sg:phone":"+1 541 473 3879",
    "sg:postcode":"97918",
    "sg:province":"OR",
    "sg:website":"http://valetrailsrvpark.blogspot.com/",
    "wof:name":"Vale Trails RV Park (Formerly Prospector Rv Park)",
    "wof:placetype":"venue"
},
  "geometry": {"coordinates":[-117.236552,43.985476],"type":"Point"}
}