{
  "type": "Feature",
  "properties": {
    "iso:country":"US",
    "sg:address":"52745 E Honeyman Rd",
    "sg:city":"Scappoose",
    "sg:classifiers":[
        {
            "category":"Retail",
            "subcategory":"Animal Services",
            "type":"Services"
        }
    ],
    "sg:phone":"+1 503 543 6398",
    "sg:postcode":"97056",
    "sg:province":"OR",
    "sg:tags":[
        "pet",
        "boarding",
        "sitting"
    ],
    "wof:name":"Westend Kennels",
    "wof:placetype":"venue"
},
  "geometry": {"coordinates":[-122.823426,45.760021],"type":"Point"}
}