{
  "type": "Feature",
  "properties": {
    "iso:country":"US",
    "sg:address":"3960 Green Valley Rd",
    "sg:city":"Oakland",
    "sg:classifiers":[
        {
            "category":"Farming",
            "subcategory":"Berry Farm",
            "type":"Manufacturing & Wholesale Goods"
        }
    ],
    "sg:phone":"+1 541 459 1402",
    "sg:postcode":"97462",
    "sg:province":"OR",
    "sg:tags":[
        "crop"
    ],
    "wof:name":"Windy Knob Farms",
    "wof:placetype":"venue"
},
  "geometry": {"coordinates":[-123.35874,43.423272],"type":"Point"}
}