{
  "type": "Feature",
  "properties": {
    "addr:full":"3860 NW 171st Pl Beaverton OR 97006",
    "addr:housenumber":"3860",
    "addr:postcode":"97006",
    "addr:street":"Nw 171St Pl",
    "iso:country":"US",
    "sg:address":"3860 NW 171st Pl",
    "sg:city":"Beaverton",
    "sg:classifiers":[
        {
            "category":"Professional",
            "subcategory":"Business Services",
            "type":"Services"
        },
        {
            "category":"Professional",
            "subcategory":"Art Services",
            "type":"Services"
        }
    ],
    "sg:phone":"+1 503 645 2884",
    "sg:postcode":"97006",
    "sg:province":"OR",
    "sg:tags":[
        "commercial",
        "graphic",
        "design",
        "designer"
    ],
    "wof:name":"White Space Design Inc",
    "wof:placetype":"venue"
},
  "geometry": {"coordinates":[-122.853188,45.547955],"type":"Point"}
}