{
  "type": "Feature",
  "properties": {
    "iso:country":"US",
    "sg:address":"3521 US Hwy 101",
    "sg:city":"Lincoln City",
    "sg:classifiers":[
        {
            "category":"Restaurant",
            "type":"Food & Drink"
        }
    ],
    "sg:phone":"+1 541 996 8178",
    "sg:postcode":"97367",
    "sg:province":"OR",
    "sg:tags":[
        "eating"
    ],
    "wof:name":"Avanti Italian Cuisine",
    "wof:placetype":"venue"
},
  "geometry": {"coordinates":[-124.006445,44.992267],"type":"Point"}
}