{
  "type": "Feature",
  "properties": {
    "iso:country":"US",
    "sg:address":"3712 Elk Ln",
    "sg:city":"Grants Pass",
    "sg:classifiers":[
        {
            "category":"Building & Trades",
            "subcategory":"Equipment Rental",
            "type":"Services"
        }
    ],
    "sg:phone":"+1 541 476 4849",
    "sg:postcode":"97527",
    "sg:province":"OR",
    "wof:name":"Galloping Video",
    "wof:placetype":"venue"
},
  "geometry": {"coordinates":[-123.371849,42.393266],"type":"Point"}
}