{
  "type": "Feature",
  "properties": {
    "addr:full":"1822 SW Madison St Portland OR 97205",
    "addr:housenumber":"1822",
    "addr:postcode":"97205",
    "addr:street":"Sw Madison St",
    "iso:country":"US",
    "sg:address":"1822 SW Madison St",
    "sg:city":"Portland",
    "sg:classifiers":[
        {
            "category":"Social Services",
            "type":"Services"
        }
    ],
    "sg:phone":"+1 503 236 2892",
    "sg:postcode":"97205",
    "sg:province":"OR",
    "wof:name":"Meg Goldberg JD Mediation",
    "wof:placetype":"venue"
},
  "geometry": {"coordinates":[-122.693228,45.518811],"type":"Point"}
}