{
  "type": "Feature",
  "properties": {
    "iso:country":"US",
    "sg:address":"6085 W 11th Ave",
    "sg:city":"Eugene",
    "sg:classifiers":[
        {
            "category":"Autos & Motor Vehicles",
            "subcategory":"Fuel & Gas Station",
            "type":"Retail Goods"
        }
    ],
    "sg:phone":"+1 541 302 8009",
    "sg:postcode":"97402",
    "sg:province":"OR",
    "sg:tags":[
        "oil"
    ],
    "wof:name":"Shell Station & Food Mart",
    "wof:placetype":"venue"
},
  "geometry": {"coordinates":[-123.199235,44.049491],"type":"Point"}
}