{
  "type": "Feature",
  "properties": {
    "addr:full":"4122 NE 26th Ave Portland OR 97211",
    "addr:housenumber":"4122",
    "addr:postcode":"97211",
    "addr:street":"Ne 26Th Ave",
    "iso:country":"US",
    "sg:address":"4122 NE 26th Ave",
    "sg:city":"Portland",
    "sg:classifiers":[
        {
            "category":"Health Services",
            "subcategory":"Doctor",
            "type":"Services"
        }
    ],
    "sg:phone":"+1 503 280 8888",
    "sg:postcode":"97211",
    "sg:province":"OR",
    "sg:tags":[
        "medical"
    ],
    "wof:name":"Larry Smith MA Ncc",
    "wof:placetype":"venue"
},
  "geometry": {"coordinates":[-122.63885999999999,45.554194],"type":"Point"}
}