{
  "type": "Feature",
  "properties": {
    "iso:country":"US",
    "sg:address":"15822 S Neibur Rd",
    "sg:city":"Oregon City",
    "sg:classifiers":[
        {
            "category":"Building & Trades",
            "subcategory":"Construction",
            "type":"Services"
        }
    ],
    "sg:phone":"+1 503 631 7796",
    "sg:postcode":"97045",
    "sg:province":"OR",
    "sg:tags":[
        "woodworker"
    ],
    "wof:name":"Jay Younger Woodworks",
    "wof:placetype":"venue"
},
  "geometry": {"coordinates":[-122.541099,45.357955],"type":"Point"}
}