{
  "type": "Feature",
  "properties": {
    "iso:country":"US",
    "sg:address":"102 NW 2nd St",
    "sg:city":"Prineville",
    "sg:classifiers":[
        {
            "category":"Shopping",
            "subcategory":"Bicycles & Sporting Goods",
            "type":"Retail Goods"
        }
    ],
    "sg:phone":"+1 541 447 7970",
    "sg:postcode":"97754",
    "sg:province":"OR",
    "wof:name":"Cascade Sports Ctr",
    "wof:placetype":"venue"
},
  "geometry": {"coordinates":[-120.848277,44.301979],"type":"Point"}
}