{
  "type": "Feature",
  "properties": {
    "addr:full":"1730 SW Skyline Blvd Portland OR 97221",
    "addr:housenumber":"1730",
    "addr:postcode":"97221",
    "addr:street":"Sw Skyline Blvd",
    "iso:country":"US",
    "sg:address":"1730 SW Skyline Blvd",
    "sg:city":"Portland",
    "sg:classifiers":[
        {
            "category":"Shopping",
            "subcategory":"Computers & Home Electronics",
            "type":"Retail Goods"
        }
    ],
    "sg:phone":"+1 503 297 1621",
    "sg:postcode":"97221",
    "sg:province":"OR",
    "sg:tags":[
        "system",
        "power",
        "supply",
        "replacement",
        "back",
        "up",
        "air",
        "con"
    ],
    "wof:name":"Computer Power Solutions Inc",
    "wof:placetype":"venue"
},
  "geometry": {"coordinates":[-122.735269,45.511169],"type":"Point"}
}