{
  "type": "Feature",
  "properties": {
    "iso:country":"US",
    "sg:address":"575 Garfield St",
    "sg:city":"Eugene",
    "sg:classifiers":[
        {
            "category":"Professional",
            "subcategory":"Advertising",
            "type":"Services"
        }
    ],
    "sg:phone":"+1 541 606 2472",
    "sg:postcode":"97402",
    "sg:province":"OR",
    "sg:tags":[
        "designer",
        "display",
        "producer"
    ],
    "wof:name":"Creative Commercial Environmnt",
    "wof:placetype":"venue"
},
  "geometry": {"coordinates":[-123.12267,44.054491],"type":"Point"}
}