{
  "type": "Feature",
  "properties": {
    "addr:full":"3130 SE Hawthorne Blvd Portland OR 97214",
    "addr:housenumber":"3130",
    "addr:postcode":"97214",
    "addr:street":"Se Hawthorne Blvd",
    "iso:country":"US",
    "sg:address":"3130 SE Hawthorne Blvd",
    "sg:city":"Portland",
    "sg:classifiers":[
        {
            "category":"Shopping",
            "subcategory":"Gifts & Souvenirs",
            "type":"Retail Goods"
        },
        {
            "category":"Shopping",
            "subcategory":"Music",
            "type":"Retail Goods"
        }
    ],
    "sg:phone":"+1 503 232 1767",
    "sg:postcode":"97214",
    "sg:province":"OR",
    "sg:tags":[
        "compact",
        "record",
        "disc",
        "tape",
        "dvd's"
    ],
    "sg:website":"www.xro.com",
    "wof:name":"Crossroads Music",
    "wof:placetype":"venue"
},
  "geometry": {"coordinates":[-122.633003,45.512001],"type":"Point"}
}