{
  "type": "Feature",
  "properties": {
    "iso:country":"US",
    "sg:address":"511 SW 10th Avenue Suite 1301",
    "sg:city":"Portland",
    "sg:classifiers":[
        {
            "category":"Health Services",
            "subcategory":"Doctor",
            "type":"Services"
        }
    ],
    "sg:phone":"+1 503 228 0155",
    "sg:postcode":"97205",
    "sg:province":"OR",
    "wof:name":"Asthma Allergy Centre",
    "wof:placetype":"venue"
},
  "geometry": {"coordinates":[-122.692616,45.520333],"type":"Point"}
}