{
  "type": "Feature",
  "properties": {
    "iso:country":"US",
    "sg:address":"13145 SW Weir Rd",
    "sg:city":"Beaverton",
    "sg:classifiers":[
        {
            "category":"Shopping",
            "subcategory":"Clothing, Apparel, & Fashions",
            "type":"Retail Goods"
        }
    ],
    "sg:phone":"+1 503 803 2972",
    "sg:postcode":"97008",
    "sg:province":"OR",
    "wof:name":"Mode Design LLC",
    "wof:placetype":"venue"
},
  "geometry": {"coordinates":[-122.813166,45.447687],"type":"Point"}
}