{
  "type": "Feature",
  "properties": {
    "iso:country":"US",
    "sg:address":"1470 Westpark Plz",
    "sg:city":"Ontario",
    "sg:classifiers":[
        {
            "category":"Shopping",
            "subcategory":"Clothing, Apparel, & Fashions",
            "type":"Retail Goods"
        }
    ],
    "sg:phone":"+1 541 889 3618",
    "sg:postcode":"97914",
    "sg:province":"OR",
    "wof:name":"Maurice's",
    "wof:placetype":"venue"
},
  "geometry": {"coordinates":[-116.985509,44.024626],"type":"Point"}
}