{
  "type": "Feature",
  "properties": {
    "iso:country":"US",
    "sg:address":"5851 Bear Ln SE",
    "sg:city":"Turner",
    "sg:classifiers":[
        {
            "category":"Home & Garden",
            "subcategory":"Building Materials",
            "type":"Retail Goods"
        }
    ],
    "sg:phone":"+1 503 743 2621",
    "sg:postcode":"97392",
    "sg:province":"OR",
    "sg:tags":[
        "light",
        "lumber",
        "broker"
    ],
    "wof:name":"Wilt Frank Supply",
    "wof:placetype":"venue"
},
  "geometry": {"coordinates":[-122.938137,44.820901],"type":"Point"}
}