{
  "type": "Feature",
  "properties": {
    "iso:country":"US",
    "sg:address":"4940 Sollie Smith Rd N",
    "sg:city":"Tillamook",
    "sg:classifiers":[
        {
            "category":"Utilities",
            "subcategory":"Water",
            "type":"Services"
        }
    ],
    "sg:phone":"+1 503 842 1976",
    "sg:postcode":"97141",
    "sg:province":"OR",
    "sg:tags":[
        "company",
        "sewage"
    ],
    "wof:name":"Wilson River Water District",
    "wof:placetype":"venue"
},
  "geometry": {"coordinates":[-123.805342,45.478136],"type":"Point"}
}