{
  "type": "Feature",
  "properties": {
    "addr:full":"10007 N Central St Portland OR 97203",
    "addr:housenumber":"10007",
    "addr:postcode":"97203",
    "addr:street":"N Central St",
    "iso:country":"US",
    "sg:address":"10007 N Central St",
    "sg:city":"Portland",
    "sg:classifiers":[
        {
            "category":"Building & Trades",
            "subcategory":"Cleaning & Sanitation",
            "type":"Services"
        }
    ],
    "sg:phone":"+1 503 286 5667",
    "sg:postcode":"97203",
    "sg:province":"OR",
    "sg:tags":[
        "janitor",
        "maintenance"
    ],
    "wof:name":"Dawn Cleaning Svc",
    "wof:placetype":"venue"
},
  "geometry": {"coordinates":[-122.759807,45.599771],"type":"Point"}
}