{
  "type": "Feature",
  "properties": {
    "iso:country":"US",
    "sg:address":"155 B Ave",
    "sg:city":"Lake Oswego",
    "sg:classifiers":[
        {
            "category":"Professional",
            "subcategory":"Lawyer & Legal Services",
            "type":"Services"
        }
    ],
    "sg:phone":"+1 503 635 5244",
    "sg:postcode":"97034",
    "sg:province":"OR",
    "wof:name":"Carr John T Atty At Law",
    "wof:placetype":"venue"
},
  "geometry": {"coordinates":[-122.665001,45.420799],"type":"Point"}
}