{
  "type": "Feature",
  "properties": {
    "iso:country":"US",
    "sg:address":"1501 Kester Rd",
    "sg:city":"Roseburg",
    "sg:classifiers":[
        {
            "category":"Building & Trades",
            "subcategory":"Construction",
            "type":"Services"
        }
    ],
    "sg:phone":"+1 541 672 7275",
    "sg:postcode":"97470",
    "sg:province":"OR",
    "sg:tags":[
        "house"
    ],
    "wof:name":"Olen Bratton Construction",
    "wof:placetype":"venue"
},
  "geometry": {"coordinates":[-123.296802,43.232291],"type":"Point"}
}