{
  "type": "Feature",
  "properties": {
    "iso:country":"US",
    "sg:address":"10135 SE Foster Rd",
    "sg:city":"Portland",
    "sg:classifiers":[
        {
            "category":"Food & Beverages",
            "subcategory":"Groceries & Convenience Stores",
            "type":"Retail Goods"
        }
    ],
    "sg:phone":"+1 503 774 3040",
    "sg:postcode":"97266",
    "sg:province":"OR",
    "wof:name":"Mt Scott Market",
    "wof:placetype":"venue"
},
  "geometry": {"coordinates":[-122.55949,45.477222],"type":"Point"}
}