{
  "type": "Feature",
  "properties": {
    "iso:country":"US",
    "sg:address":"915 SW 2nd Ave",
    "sg:city":"Portland",
    "sg:classifiers":[
        {
            "category":"Bars & Pubs",
            "subcategory":"Nightclub",
            "type":"Food & Drink"
        }
    ],
    "sg:phone":"+1 503 417 8717",
    "sg:postcode":"97204",
    "sg:province":"OR",
    "sg:tags":[
        "nightlife"
    ],
    "wof:name":"Boogie Woogies",
    "wof:placetype":"venue"
},
  "geometry": {"coordinates":[-122.675651,45.516528],"type":"Point"}
}