{
  "type": "Feature",
  "properties": {
    "iso:country":"US",
    "sg:address":"13665 SE 116th Ct",
    "sg:city":"Clackamas",
    "sg:classifiers":[
        {
            "category":"Building & Trades",
            "subcategory":"Construction",
            "type":"Services"
        }
    ],
    "sg:phone":"+1 503 637 3367",
    "sg:postcode":"97015",
    "sg:province":"OR",
    "sg:tags":[
        "fabricator",
        "metal"
    ],
    "wof:name":"M & J Metal Fabrications",
    "wof:placetype":"venue"
},
  "geometry": {"coordinates":[-122.54400200000001,45.424923],"type":"Point"}
}