{
  "type": "Feature",
  "properties": {
    "iso:country":"US",
    "sg:address":"8150 SW Barnes Rd",
    "sg:city":"Portland",
    "sg:classifiers":[
        {
            "category":"Education",
            "subcategory":"Dance Studio",
            "type":"Public Place"
        }
    ],
    "sg:phone":"+1 503 999 9994",
    "sg:postcode":"97225",
    "sg:province":"OR",
    "wof:name":"Northwest Dance Company",
    "wof:placetype":"venue"
},
  "geometry": {"coordinates":[-122.75768100000001,45.512083],"type":"Point"}
}