{
  "type": "Feature",
  "properties": {
    "addr:full":"20601 SE Tara Lara Ln Eagle Creek OR 97022",
    "addr:postcode":"20601;97022",
    "addr:street":"Se;Lara Ln",
    "iso:country":"US",
    "sg:address":"20601 SE Tara Lara Ln",
    "sg:city":"Eagle Creek",
    "sg:classifiers":[
        {
            "category":"Home & Garden",
            "subcategory":"Garden Supply",
            "type":"Retail Goods"
        }
    ],
    "sg:phone":"+1 503 637 6404",
    "sg:postcode":"97022",
    "sg:province":"OR",
    "sg:tags":[
        "tree",
        "christmas"
    ],
    "wof:name":"Deep Creek Tree Farms",
    "wof:placetype":"venue"
},
  "geometry": {"coordinates":[-122.352918,45.37566],"type":"Point"}
}