{
  "type": "Feature",
  "properties": {
    "iso:country":"US",
    "sg:address":"726 NE 7th St",
    "sg:city":"Grants Pass",
    "sg:classifiers":[
        {
            "category":"Government",
            "subcategory":"Office",
            "type":"Public Place"
        }
    ],
    "sg:phone":"+1 541 474 3101",
    "sg:postcode":"97526",
    "sg:province":"OR",
    "sg:tags":[
        "human"
    ],
    "wof:name":"Adult & Family Svcs Ore Div",
    "wof:placetype":"venue"
},
  "geometry": {"coordinates":[-123.322983,42.443666],"type":"Point"}
}