{
  "type": "Feature",
  "properties": {
    "iso:country":"US",
    "sg:address":"1200 NW Naito Pkwy",
    "sg:city":"Portland",
    "sg:classifiers":[
        {
            "category":"Government",
            "subcategory":"Office",
            "type":"Public Place"
        }
    ],
    "sg:phone":"+1 503 223 3928",
    "sg:postcode":"97209",
    "sg:province":"OR",
    "sg:tags":[
        "bridge",
        "operates",
        "port",
        "district",
        "toll"
    ],
    "wof:name":"Sternwheeler Columbia Gorge",
    "wof:placetype":"venue"
},
  "geometry": {"coordinates":[-122.676728,45.531089],"type":"Point"}
}