{
  "type": "Feature",
  "properties": {
    "addr:full":"7330 N Saint Louis Avenue Portland OR 97203",
    "addr:housenumber":"7330",
    "addr:postcode":"97203",
    "addr:street":"N Saint Louis Avenue",
    "iso:country":"US",
    "sg:address":"7330 N Saint Louis Avenue",
    "sg:city":"Portland",
    "sg:classifiers":[
        {
            "category":"Food & Beverages",
            "subcategory":"Groceries & Convenience Stores",
            "type":"Retail Goods"
        }
    ],
    "sg:phone":"+1 503 283 3061",
    "sg:postcode":"97203",
    "sg:province":"OR",
    "wof:name":"Seven-Eleven Food Stores",
    "wof:placetype":"venue"
},
  "geometry": {"coordinates":[-122.75800700000001,45.592566],"type":"Point"}
}