{
  "type": "Feature",
  "properties": {
    "addr:full":"4800 Netarts Hwy W Tillamook OR 97141",
    "addr:postcode":"4800;97141",
    "addr:street":"Netarts Hwy W",
    "iso:country":"US",
    "sg:address":"4800 Netarts Hwy W",
    "sg:city":"Tillamook",
    "sg:classifiers":[
        {
            "category":"Travel",
            "subcategory":"Hotels & Motels",
            "type":"Entertainment"
        }
    ],
    "sg:phone":"+1 503 842 4003",
    "sg:postcode":"97141",
    "sg:province":"OR",
    "sg:tags":[
        "operation"
    ],
    "wof:name":"Three Capes Inn At Netarts",
    "wof:placetype":"venue"
},
  "geometry": {"coordinates":[-123.943535,45.431585],"type":"Point"}
}