{
  "type": "Feature",
  "properties": {
    "iso:country":"US",
    "sg:address":"1190 SE Flightline Dr",
    "sg:city":"Warrenton",
    "sg:classifiers":[
        {
            "category":"Manufacturing",
            "subcategory":"Tools & Machinery",
            "type":"Manufacturing & Wholesale Goods"
        }
    ],
    "sg:phone":"+1 503 861 2288",
    "sg:postcode":"97146",
    "sg:province":"OR",
    "sg:tags":[
        "handling",
        "mfg",
        "material",
        "equipment",
        "aircraft",
        "tug"
    ],
    "sg:website":"www.lektro.com",
    "wof:name":"Lektro Inc",
    "wof:placetype":"venue"
},
  "geometry": {"coordinates":[-123.881058,46.153135],"type":"Point"}
}