{
  "type": "Feature",
  "properties": {
    "iso:country":"US",
    "sg:address":"572 Henderer Rd",
    "sg:city":"Elkton",
    "sg:classifiers":[
        {
            "category":"Manufacturing",
            "subcategory":"Lumber",
            "type":"Manufacturing & Wholesale Goods"
        }
    ],
    "sg:phone":"+1 541 584 2381",
    "sg:postcode":"97436",
    "sg:province":"OR",
    "sg:tags":[
        "logging"
    ],
    "wof:name":"Cc Logging",
    "wof:placetype":"venue"
},
  "geometry": {"coordinates":[-123.57383,43.636608],"type":"Point"}
}