{
  "type": "Feature",
  "properties": {
    "addr:full":"3787 NE Jackson School Rd Hillsboro OR 97124",
    "addr:housenumber":"3787",
    "addr:postcode":"97124",
    "addr:street":"Ne Jackson School Rd",
    "iso:country":"US",
    "sg:address":"3787 NE Jackson School Rd",
    "sg:city":"Hillsboro",
    "sg:classifiers":[
        {
            "category":"Manufacturing",
            "subcategory":"Tools & Machinery",
            "type":"Manufacturing & Wholesale Goods"
        }
    ],
    "sg:phone":"+1 503 844 8669",
    "sg:postcode":"97124",
    "sg:province":"OR",
    "sg:tags":[
        "metalworking",
        "mold",
        "mfg"
    ],
    "wof:name":"Precision Rapid Tooling Inc",
    "wof:placetype":"venue"
},
  "geometry": {"coordinates":[-122.979764,45.548132],"type":"Point"}
}