{
  "type": "Feature",
  "properties": {
    "iso:country":"US",
    "sg:address":"414 E 2nd St",
    "sg:city":"The Dalles",
    "sg:classifiers":[
        {
            "category":"Personal",
            "type":"Services"
        }
    ],
    "sg:phone":"+1 541 296 7100",
    "sg:postcode":"97058",
    "sg:province":"OR",
    "sg:tags":[
        "therapist",
        "massage"
    ],
    "wof:name":"Ken Graham Massage Thrpst Lmt",
    "wof:placetype":"venue"
},
  "geometry": {"coordinates":[-121.18062500000001,45.600586],"type":"Point"}
}