{
  "type": "Feature",
  "properties": {
    "addr:full":"15121 NE Clackamas St Portland OR 97230",
    "addr:housenumber":"15121",
    "addr:postcode":"97230",
    "addr:street":"Ne Clackamas St",
    "iso:country":"US",
    "sg:address":"15121 NE Clackamas St",
    "sg:city":"Portland",
    "sg:classifiers":[
        {
            "category":"Building & Trades",
            "subcategory":"Plumbing",
            "type":"Services"
        }
    ],
    "sg:phone":"+1 503 262 8337",
    "sg:postcode":"97230",
    "sg:province":"OR",
    "sg:tags":[
        "plumbing",
        "contractor"
    ],
    "wof:name":"R H Kunselman Plumbing & Htng",
    "wof:placetype":"venue"
},
  "geometry": {"coordinates":[-122.507638,45.532718],"type":"Point"}
}