{
  "type": "Feature",
  "properties": {
    "addr:full":"2224 SE Sherman St Portland OR 97214",
    "addr:housenumber":"2224",
    "addr:postcode":"97214",
    "addr:street":"Se Sherman St",
    "iso:country":"US",
    "sg:address":"2224 SE Sherman St",
    "sg:city":"Portland",
    "sg:classifiers":[
        {
            "category":"Real Estate",
            "subcategory":"Real Estate Services",
            "type":"Services"
        }
    ],
    "sg:phone":"+1 503 260 3041",
    "sg:postcode":"97214",
    "sg:province":"OR",
    "wof:name":"Jack Ryan & Associates",
    "wof:placetype":"venue"
},
  "geometry": {"coordinates":[-122.642557,45.506026],"type":"Point"}
}