{
  "type": "Feature",
  "properties": {
    "addr:full":"16250 SW Briedwell Rd Mcminnville OR 97128",
    "addr:housenumber":"16250",
    "addr:postcode":"97128",
    "addr:street":"Sw Briedwell Rd",
    "iso:country":"US",
    "sg:address":"16250 SW Briedwell Rd",
    "sg:city":"Mcminnville",
    "sg:classifiers":[
        {
            "category":"Real Estate",
            "subcategory":"Real Estate Operator",
            "type":"Services"
        }
    ],
    "sg:phone":"+1 503 835 5146",
    "sg:postcode":"97128",
    "sg:province":"OR",
    "sg:tags":[
        "mobile",
        "home",
        "site"
    ],
    "wof:name":"Rich Fuller",
    "wof:placetype":"venue"
},
  "geometry": {"coordinates":[-123.241979,45.14341],"type":"Point"}
}