{
  "type": "Feature",
  "properties": {
    "addr:full":"625 SW Broadway 5th Fl Portland OR 97205",
    "addr:housenumber":"625",
    "addr:postcode":"97205",
    "addr:street":"Sw Broadway",
    "iso:country":"US",
    "sg:address":"625 SW Broadway 5th Fl",
    "sg:city":"Portland",
    "sg:classifiers":[
        {
            "category":"Professional",
            "subcategory":"Employment Agencies",
            "type":"Services"
        }
    ],
    "sg:phone":"+1 503 242 1300",
    "sg:postcode":"97205",
    "sg:province":"OR",
    "sg:website":"www.bolywelch.com",
    "wof:name":"Boly Welch Recruiting",
    "wof:placetype":"venue"
},
  "geometry": {"coordinates":[-122.67949400000001,45.519669],"type":"Point"}
}