{
  "type": "Feature",
  "properties": {
    "iso:country":"US",
    "sg:address":"264 Suburban Ave",
    "sg:city":"Eugene",
    "sg:classifiers":[
        {
            "category":"Building & Trades",
            "subcategory":"Cleaning & Sanitation",
            "type":"Services"
        }
    ],
    "sg:phone":"+1 541 465 1693",
    "sg:postcode":"97404",
    "sg:province":"OR",
    "sg:tags":[
        "maintenance"
    ],
    "wof:name":"Office Genie",
    "wof:placetype":"venue"
},
  "geometry": {"coordinates":[-123.133833,44.117468],"type":"Point"}
}