{
  "type": "Feature",
  "properties": {
    "addr:full":"5634 SE Center St Portland OR 97206",
    "addr:housenumber":"5634",
    "addr:postcode":"97206",
    "addr:street":"Se Center St",
    "iso:country":"US",
    "sg:address":"5634 SE Center St",
    "sg:city":"Portland",
    "sg:classifiers":[
        {
            "category":"Retail",
            "subcategory":"Auto Repair",
            "type":"Services"
        }
    ],
    "sg:phone":"+1 503 761 4437",
    "sg:postcode":"97206",
    "sg:province":"OR",
    "sg:tags":[
        "car",
        "top",
        "upholstery",
        "custom",
        "automobile"
    ],
    "wof:name":"Russ'z Upholstery",
    "wof:placetype":"venue"
},
  "geometry": {"coordinates":[-122.603785,45.494029],"type":"Point"}
}