{
  "type": "Feature",
  "properties": {
    "iso:country":"US",
    "sg:address":"733 S Main St",
    "sg:city":"Lebanon",
    "sg:classifiers":[
        {
            "category":"Professional",
            "subcategory":"Secretarial Services",
            "type":"Services"
        }
    ],
    "sg:phone":"+1 541 451 3980",
    "sg:postcode":"97355",
    "sg:province":"OR",
    "sg:tags":[
        "reporting"
    ],
    "wof:name":"Secretarial Service",
    "wof:placetype":"venue"
},
  "geometry": {"coordinates":[-122.906982,44.538853],"type":"Point"}
}