{
  "type": "Feature",
  "properties": {
    "addr:full":"99 W 10th Ave Eugene OR 97401",
    "addr:housenumber":"99",
    "addr:postcode":"97401",
    "addr:street":"W 10Th Ave",
    "iso:country":"US",
    "sg:address":"99 W 10th Ave",
    "sg:city":"Eugene",
    "sg:classifiers":[
        {
            "category":"Organizations",
            "subcategory":"Professional Association",
            "type":"Services"
        }
    ],
    "sg:phone":"+1 541 485 2278",
    "sg:postcode":"97401",
    "sg:province":"OR",
    "wof:name":"Southwestern Orgeon Chapter",
    "wof:placetype":"venue"
},
  "geometry": {"coordinates":[-123.093507,44.048815],"type":"Point"}
}