{
  "type": "Feature",
  "properties": {
    "addr:full":"3725 N Gantenbein Ave Portland OR 97227",
    "addr:housenumber":"3725",
    "addr:postcode":"97227",
    "addr:street":"N Gantenbein Ave",
    "iso:country":"US",
    "sg:address":"3725 N Gantenbein Ave",
    "sg:city":"Portland",
    "sg:classifiers":[
        {
            "category":"Organizations",
            "subcategory":"Religious Organization",
            "type":"Services"
        }
    ],
    "sg:phone":"+1 503 281 0163",
    "sg:postcode":"97227",
    "sg:province":"OR",
    "wof:name":"New Hope Mssnary Baptst Church",
    "wof:placetype":"venue"
},
  "geometry": {"coordinates":[-122.669101,45.550634],"type":"Point"}
}