{
  "type": "Feature",
  "properties": {
    "iso:country":"US",
    "sg:address":"3908 NE 135th Ave",
    "sg:city":"Portland",
    "sg:classifiers":[
        {
            "category":"Insurance",
            "subcategory":"Insurance Agent",
            "type":"Services"
        }
    ],
    "sg:phone":"+1 503 252 3911",
    "sg:postcode":"97230",
    "sg:province":"OR",
    "wof:name":"New York Life Insurance Co",
    "wof:placetype":"venue"
},
  "geometry": {"coordinates":[-122.523768,45.550944],"type":"Point"}
}