{
  "type": "Feature",
  "properties": {
    "iso:country":"US",
    "sg:address":"2367 SE 122nd Avenue",
    "sg:city":"Portland",
    "sg:classifiers":[
        {
            "category":"Restaurant",
            "type":"Food & Drink"
        }
    ],
    "sg:phone":"+1 503 252 3575",
    "sg:postcode":"97233",
    "sg:province":"OR",
    "sg:tags":[
        "chinese"
    ],
    "wof:name":"Happy Garden",
    "wof:placetype":"venue"
},
  "geometry": {"coordinates":[-122.53750100000001,45.5053],"type":"Point"}
}