{
  "type": "Feature",
  "properties": {
    "iso:country":"US",
    "sg:address":"1701 Juniper St",
    "sg:city":"Junction City",
    "sg:classifiers":[
        {
            "category":"Freight",
            "type":"Transportation"
        }
    ],
    "sg:phone":"+1 541 998 8110",
    "sg:postcode":"97448",
    "sg:province":"OR",
    "sg:tags":[
        "special"
    ],
    "wof:name":"Junction City Mini Storage",
    "wof:placetype":"venue"
},
  "geometry": {"coordinates":[-123.206202,44.227648],"type":"Point"}
}