{
  "type": "Feature",
  "properties": {
    "addr:full":"14997 SW Tualatin Sherwood Rd Sherwood OR 97140",
    "addr:housenumber":"14997",
    "addr:postcode":"97140",
    "addr:street":"Sw Tualatin Sherwood Rd",
    "iso:country":"US",
    "sg:address":"14997 SW Tualatin Sherwood Rd",
    "sg:city":"Sherwood",
    "sg:classifiers":[
        {
            "category":"Shopping",
            "subcategory":"Computers & Home Electronics",
            "type":"Retail Goods"
        }
    ],
    "sg:phone":"+1 503 925 9090",
    "sg:postcode":"97140",
    "sg:province":"OR",
    "sg:tags":[
        "television",
        "radio"
    ],
    "wof:name":"Home Theater Experts",
    "wof:placetype":"venue"
},
  "geometry": {"coordinates":[-122.831746,45.367715],"type":"Point"}
}