{
  "type": "Feature",
  "properties": {
    "iso:country":"US",
    "sg:address":"921 SW Washington Street Suite 316",
    "sg:city":"Portland",
    "sg:classifiers":[
        {
            "category":"Building & Trades",
            "subcategory":"Construction",
            "type":"Services"
        }
    ],
    "sg:phone":"+1 503 242 0956",
    "sg:postcode":"97205",
    "sg:province":"OR",
    "sg:tags":[
        "interior",
        "design"
    ],
    "wof:name":"Czopek & Erdenberger",
    "wof:placetype":"venue"
},
  "geometry": {"coordinates":[-122.68061299999999,45.52116],"type":"Point"}
}