{
  "type": "Feature",
  "properties": {
    "iso:country":"US",
    "sg:address":"8720 SW Yakima Ct",
    "sg:city":"Tualatin",
    "sg:classifiers":[
        {
            "category":"Professional",
            "type":"Services"
        }
    ],
    "sg:phone":"+1 503 235 2179",
    "sg:postcode":"97062",
    "sg:province":"OR",
    "wof:name":"Northwest Sports Broadcas",
    "wof:placetype":"venue"
},
  "geometry": {"coordinates":[-122.76655700000001,45.370112],"type":"Point"}
}