{
  "type": "Feature",
  "properties": {
    "addr:full":"655 Goodpasture Island Rd # 248 Eugene OR 97401",
    "addr:housenumber":"655",
    "addr:postcode":"97401",
    "addr:street":"Goodpasture Island Rd # 248",
    "iso:country":"US",
    "sg:address":"655 Goodpasture Island Rd # 248",
    "sg:city":"Eugene",
    "sg:classifiers":[
        {
            "category":"Shopping",
            "subcategory":"Stationery & Office Supplies",
            "type":"Retail Goods"
        }
    ],
    "sg:phone":"+1 541 653 8034",
    "sg:postcode":"97401",
    "sg:province":"OR",
    "sg:tags":[
        "envelope",
        "store"
    ],
    "wof:name":"Le Papier",
    "wof:placetype":"venue"
},
  "geometry": {"coordinates":[-123.111912,44.081454],"type":"Point"}
}