{
  "type": "Feature",
  "properties": {
    "iso:country":"US",
    "sg:address":"964 SE 54th Ave",
    "sg:city":"Hillsboro",
    "sg:classifiers":[
        {
            "category":"Building & Trades",
            "subcategory":"Landscaping Services",
            "type":"Services"
        }
    ],
    "sg:phone":"+1 503 848 3760",
    "sg:postcode":"97123",
    "sg:province":"OR",
    "wof:name":"Westside Lawn Service",
    "wof:placetype":"venue"
},
  "geometry": {"coordinates":[-122.92784899999999,45.512177],"type":"Point"}
}