{
  "type": "Feature",
  "properties": {
    "iso:country":"US",
    "sg:address":"541 Chetco Ln",
    "sg:city":"Brookings",
    "sg:classifiers":[
        {
            "category":"Personal",
            "type":"Services"
        }
    ],
    "sg:phone":"+1 541 412 7906",
    "sg:postcode":"97415",
    "sg:province":"OR",
    "wof:name":"Upper Crust Design",
    "wof:placetype":"venue"
},
  "geometry": {"coordinates":[-124.290954,42.055852],"type":"Point"}
}