{
  "type": "Feature",
  "properties": {
    "iso:country":"US",
    "sg:address":"225 Wallace Rd NW",
    "sg:city":"Salem",
    "sg:classifiers":[
        {
            "category":"Shopping",
            "subcategory":"Clothing, Apparel, & Fashions",
            "type":"Retail Goods"
        }
    ],
    "sg:phone":"+1 503 364 3713",
    "sg:postcode":"97304",
    "sg:province":"OR",
    "sg:tags":[
        "alteration"
    ],
    "wof:name":"Alterations Etc",
    "wof:placetype":"venue"
},
  "geometry": {"coordinates":[-123.04913999999999,44.945198],"type":"Point"}
}