{
  "type": "Feature",
  "properties": {
    "iso:country":"US",
    "sg:address":"8575 SW Barbur Blvd",
    "sg:city":"Portland",
    "sg:classifiers":[
        {
            "category":"Professional",
            "subcategory":"Management & Consulting",
            "type":"Services"
        }
    ],
    "sg:phone":"+1 503 244 7939",
    "sg:postcode":"97219",
    "sg:province":"OR",
    "sg:tags":[
        "travel",
        "agency"
    ],
    "wof:name":"Abracadabra Events",
    "wof:placetype":"venue"
},
  "geometry": {"coordinates":[-122.702383,45.463128],"type":"Point"}
}