{
  "type": "Feature",
  "properties": {
    "iso:country":"US",
    "sg:address":"14160 SE Mill St",
    "sg:city":"Portland",
    "sg:classifiers":[
        {
            "category":"Building & Trades",
            "subcategory":"Construction",
            "type":"Services"
        }
    ],
    "sg:phone":"+1 503 760 0302",
    "sg:postcode":"97233",
    "sg:province":"OR",
    "sg:tags":[
        "hanging",
        "contractor"
    ],
    "wof:name":"Maldens Painting",
    "wof:placetype":"venue"
},
  "geometry": {"coordinates":[-122.517132,45.510152],"type":"Point"}
}