{
  "type": "Feature",
  "properties": {
    "addr:full":"3995 NE 42nd Ave Portland OR 97213",
    "addr:housenumber":"3995",
    "addr:postcode":"97213",
    "addr:street":"Ne 42Nd Ave",
    "iso:country":"US",
    "sg:address":"3995 NE 42nd Ave",
    "sg:city":"Portland",
    "sg:classifiers":[
        {
            "category":"Building & Trades",
            "subcategory":"Construction",
            "type":"Services"
        }
    ],
    "sg:phone":"+1 503 740 3995",
    "sg:postcode":"97213",
    "sg:province":"OR",
    "sg:tags":[
        "builder",
        "treatment",
        "cleaning",
        "deck"
    ],
    "wof:name":"Deck Tek Northwest",
    "wof:placetype":"venue"
},
  "geometry": {"coordinates":[-122.620368,45.551735],"type":"Point"}
}