{
  "type": "Feature",
  "properties": {
    "addr:full":"209 Kennel St Molalla OR 97038",
    "addr:housenumber":"209",
    "addr:postcode":"97038",
    "addr:street":"Kennel St",
    "iso:country":"US",
    "sg:address":"209 Kennel St",
    "sg:city":"Molalla",
    "sg:classifiers":[
        {
            "category":"Social Services",
            "type":"Services"
        }
    ],
    "sg:phone":"+1 503 829 5920",
    "sg:postcode":"97038",
    "sg:province":"OR",
    "sg:tags":[
        "youth",
        "organization",
        "center"
    ],
    "wof:name":"Communities That Care",
    "wof:placetype":"venue"
},
  "geometry": {"coordinates":[-122.57844299999999,45.149894],"type":"Point"}
}