{
  "type": "Feature",
  "properties": {
    "iso:country":"US",
    "sg:address":"2549 Tenmile Valley Rd",
    "sg:city":"Tenmile",
    "sg:classifiers":[
        {
            "category":"Organizations",
            "subcategory":"Religious Organization",
            "type":"Services"
        }
    ],
    "sg:phone":"+1 541 679 3713",
    "sg:postcode":"97481",
    "sg:province":"OR",
    "sg:tags":[
        "church"
    ],
    "wof:name":"Mid-Valley Missionary Church",
    "wof:placetype":"venue"
},
  "geometry": {"coordinates":[-123.564992,43.099577],"type":"Point"}
}