{
  "type": "Feature",
  "properties": {
    "addr:full":"2549 Tenmile Valley Rd Tenmile OR 97481",
    "addr:housenumber":"2549",
    "addr:postcode":"97481",
    "addr:street":"Tenmile Valley Rd",
    "iso:country":"US",
    "sg:address":"2549 Tenmile Valley Rd",
    "sg:city":"Tenmile",
    "sg:classifiers":[
        {
            "category":"Organizations",
            "subcategory":"Religious Organization",
            "type":"Services"
        }
    ],
    "sg:phone":"+1 541 679 3713",
    "sg:postcode":"97481",
    "sg:province":"OR",
    "sg:tags":[
        "church"
    ],
    "wof:name":"Mid-Valley Missionary Church",
    "wof:placetype":"venue"
},
  "geometry": {"coordinates":[-123.564992,43.099577],"type":"Point"}
}