{
  "type": "Feature",
  "properties": {
    "iso:country":"US",
    "sg:address":"10100 SW Allen Blvd",
    "sg:city":"Beaverton",
    "sg:classifiers":[
        {
            "category":"Education",
            "subcategory":"School",
            "type":"Public Place"
        }
    ],
    "sg:phone":"+1 503 643 7467",
    "sg:postcode":"97005",
    "sg:province":"OR",
    "sg:website":"www.portlandtechshop.com",
    "wof:name":"Tech Shop",
    "wof:placetype":"venue"
},
  "geometry": {"coordinates":[-122.780502,45.475468],"type":"Point"}
}