{
  "type": "Feature",
  "properties": {
    "addr:full":"4900 SW Griffith Dr # 110 Beaverton OR 97005",
    "addr:housenumber":"4900",
    "addr:postcode":"97005",
    "addr:street":"Sw Griffith Dr # 110",
    "iso:country":"US",
    "sg:address":"4900 SW Griffith Dr # 110",
    "sg:city":"Beaverton",
    "sg:classifiers":[
        {
            "category":"Health Services",
            "subcategory":"Chiropractor",
            "type":"Services"
        }
    ],
    "sg:phone":"+1 503 427 1516",
    "sg:postcode":"97005",
    "sg:province":"OR",
    "sg:tags":[
        "chiropractic"
    ],
    "wof:name":"Active Living Chiropractic, P.C.",
    "wof:placetype":"venue"
},
  "geometry": {"coordinates":[-122.79521200000001,45.48407],"type":"Point"}
}