{
  "type": "Feature",
  "properties": {
    "addr:full":"1676 Medart Ln Grants Pass OR 97527",
    "addr:housenumber":"1676",
    "addr:postcode":"97527",
    "addr:street":"Medart Ln",
    "iso:country":"US",
    "sg:address":"1676 Medart Ln",
    "sg:city":"Grants Pass",
    "sg:classifiers":[
        {
            "category":"Building & Trades",
            "subcategory":"Cleaning & Sanitation",
            "type":"Services"
        }
    ],
    "sg:phone":"+1 541 471 0732",
    "sg:postcode":"97527",
    "sg:province":"OR",
    "sg:tags":[
        "janitor"
    ],
    "wof:name":"Allen Janitorial",
    "wof:placetype":"venue"
},
  "geometry": {"coordinates":[-123.373491,42.421417],"type":"Point"}
}