{
  "type": "Feature",
  "properties": {
    "iso:country":"US",
    "sg:address":"3440 Cleveland Hill Rd",
    "sg:city":"Roseburg",
    "sg:classifiers":[
        {
            "category":"Shopping",
            "subcategory":"Gifts & Souvenirs",
            "type":"Retail Goods"
        }
    ],
    "sg:phone":"+1 541 677 7369",
    "sg:postcode":"97470",
    "sg:province":"OR",
    "sg:tags":[
        "shop"
    ],
    "wof:name":"Austin Co Gifts",
    "wof:placetype":"venue"
},
  "geometry": {"coordinates":[-123.483008,43.286144],"type":"Point"}
}