{
  "type": "Feature",
  "properties": {
    "iso:country":"US",
    "sg:address":"455 W 6th Ave",
    "sg:city":"Junction City",
    "sg:classifiers":[
        {
            "category":"Health Services",
            "subcategory":"Chiropractor",
            "type":"Services"
        }
    ],
    "sg:phone":"+1 541 998 6260",
    "sg:postcode":"97448",
    "sg:province":"OR",
    "sg:tags":[
        "medical"
    ],
    "wof:name":"Junction City Chiropractic",
    "wof:placetype":"venue"
},
  "geometry": {"coordinates":[-123.205251,44.21906],"type":"Point"}
}