{
  "type": "Feature",
  "properties": {
    "iso:country":"US",
    "sg:address":"2208 SE 182nd Ave",
    "sg:city":"Portland",
    "sg:classifiers":[
        {
            "category":"Banks & Credit Unions",
            "subcategory":"Bank",
            "type":"Services"
        }
    ],
    "sg:phone":"+1 503 465 9969",
    "sg:postcode":"97233",
    "sg:province":"OR",
    "sg:tags":[
        "loan",
        "real estate"
    ],
    "wof:name":"Response Mortgage Svc",
    "wof:placetype":"venue"
},
  "geometry": {"coordinates":[-122.475519,45.504652],"type":"Point"}
}