{
  "type": "Feature",
  "properties": {
    "iso:country":"US",
    "sg:address":"2074 NW Aloclek Dr",
    "sg:city":"Hillsboro",
    "sg:classifiers":[
        {
            "category":"Wholesale",
            "subcategory":"Durable Goods & Equipment",
            "type":"Manufacturing & Wholesale Goods"
        }
    ],
    "sg:phone":"+1 503 690 2775",
    "sg:postcode":"97124",
    "sg:province":"OR",
    "sg:tags":[
        "importer"
    ],
    "wof:name":"Genmind International LLC",
    "wof:placetype":"venue"
},
  "geometry": {"coordinates":[-122.896044,45.534689],"type":"Point"}
}