{
  "type": "Feature",
  "properties": {
    "addr:full":"771 Willamette St Eugene OR 97401",
    "addr:housenumber":"771",
    "addr:postcode":"97401",
    "addr:street":"Willamette St",
    "iso:country":"US",
    "sg:address":"771 Willamette St",
    "sg:city":"Eugene",
    "sg:classifiers":[
        {
            "category":"Professional",
            "type":"Services"
        }
    ],
    "sg:phone":"+1 541 686 1775",
    "sg:postcode":"97401",
    "sg:province":"OR",
    "sg:tags":[
        "establishment"
    ],
    "wof:name":"Universe Trade Inc",
    "wof:placetype":"venue"
},
  "geometry": {"coordinates":[-123.09266100000001,44.051829],"type":"Point"}
}