{
  "type": "Feature",
  "properties": {
    "iso:country":"US",
    "sg:address":"1916 NW 24th Ave",
    "sg:city":"Portland",
    "sg:classifiers":[
        {
            "category":"Manufacturing",
            "subcategory":"Tools & Machinery",
            "type":"Manufacturing & Wholesale Goods"
        }
    ],
    "sg:phone":"+1 503 227 1888",
    "sg:postcode":"97210",
    "sg:province":"OR",
    "sg:tags":[
        "industrial",
        "mfg"
    ],
    "wof:name":"Bennett Machine Works",
    "wof:placetype":"venue"
},
  "geometry": {"coordinates":[-122.70076,45.536043],"type":"Point"}
}