{
  "type": "Feature",
  "properties": {
    "addr:full":"6205 Carman Dr Lake Oswego OR 97035",
    "addr:housenumber":"6205",
    "addr:postcode":"97035",
    "addr:street":"Carman Dr",
    "iso:country":"US",
    "sg:address":"6205 Carman Dr",
    "sg:city":"Lake Oswego",
    "sg:classifiers":[
        {
            "category":"Professional",
            "subcategory":"Business Services",
            "type":"Services"
        }
    ],
    "sg:phone":"+1 503 699 1771",
    "sg:postcode":"97035",
    "sg:province":"OR",
    "wof:name":"Unit Owners Assoc of Alex",
    "wof:placetype":"venue"
},
  "geometry": {"coordinates":[-122.741062,45.409692],"type":"Point"}
}