{
  "type": "Feature",
  "properties": {
    "iso:country":"US",
    "sg:address":"777 NE 4th Ave",
    "sg:city":"Canby",
    "sg:classifiers":[
        {
            "category":"Manufacturing",
            "subcategory":"Paper Products",
            "type":"Manufacturing & Wholesale Goods"
        }
    ],
    "sg:phone":"+1 503 266 2721",
    "sg:postcode":"97013",
    "sg:province":"OR",
    "sg:tags":[
        "mfg",
        "tie",
        "wire",
        "bag"
    ],
    "sg:website":"www.pcitotetie.com",
    "wof:name":"Package Containers Inc",
    "wof:placetype":"venue"
},
  "geometry": {"coordinates":[-122.685503,45.266673],"type":"Point"}
}