{
  "type": "Feature",
  "properties": {
    "addr:full":"2092 NW Aloclek Dr Hillsboro OR 97124",
    "addr:housenumber":"2092",
    "addr:postcode":"97124",
    "addr:street":"Nw Aloclek Dr",
    "iso:country":"US",
    "sg:address":"2092 NW Aloclek Dr",
    "sg:city":"Hillsboro",
    "sg:classifiers":[
        {
            "category":"Building & Trades",
            "subcategory":"Plumbing",
            "type":"Services"
        }
    ],
    "sg:phone":"+1 503 629 0230",
    "sg:postcode":"97124",
    "sg:province":"OR",
    "sg:tags":[
        "heating",
        "contractor"
    ],
    "wof:name":"Sky Heating & AC INC",
    "wof:placetype":"venue"
},
  "geometry": {"coordinates":[-122.896458,45.534695],"type":"Point"}
}