{
  "type": "Feature",
  "properties": {
    "addr:full":"4701 SE 24th Ave Portland OR 97202",
    "addr:housenumber":"4701",
    "addr:postcode":"97202",
    "addr:street":"Se 24Th Ave",
    "iso:country":"US",
    "sg:address":"4701 SE 24th Ave",
    "sg:city":"Portland",
    "sg:classifiers":[
        {
            "category":"Retail",
            "subcategory":"Auto Repair",
            "type":"Services"
        }
    ],
    "sg:phone":"+1 503 236 6704",
    "sg:postcode":"97202",
    "sg:province":"OR",
    "sg:tags":[
        "body",
        "automobile",
        "painting"
    ],
    "wof:name":"Auto-Tek Body & Paint",
    "wof:placetype":"venue"
},
  "geometry": {"coordinates":[-122.64162399999999,45.488951],"type":"Point"}
}