{
  "type": "Feature",
  "properties": {
    "addr:full":"4893 NW 235th Ave Hillsboro OR 97124",
    "addr:housenumber":"4893",
    "addr:postcode":"97124",
    "addr:street":"Nw 235Th Ave",
    "iso:country":"US",
    "sg:address":"4893 NW 235th Ave",
    "sg:city":"Hillsboro",
    "sg:phone":"+1 503 924 4470",
    "sg:postcode":"97124",
    "sg:province":"OR",
    "sg:website":"http://www.longbottomcoffee.com",
    "wof:name":"Long Bottom Coffee House",
    "wof:placetype":"venue"
},
  "geometry": {"coordinates":[-122.91832100000001,45.556403],"type":"Point"}
}