{
  "type": "Feature",
  "properties": {
    "iso:country":"US",
    "sg:address":"4303 NE Fremont St",
    "sg:city":"Portland",
    "sg:classifiers":[
        {
            "category":"Building & Trades",
            "subcategory":"Locksmith",
            "type":"Services"
        }
    ],
    "sg:phone":"+1 503 914 1161",
    "sg:postcode":"97213",
    "sg:province":"OR",
    "sg:tags":[
        "key"
    ],
    "wof:name":"24 Hr Locksmith",
    "wof:placetype":"venue"
},
  "geometry": {"coordinates":[-122.61931,45.548437],"type":"Point"}
}