{
  "type": "Feature",
  "properties": {
    "iso:country":"US",
    "sg:address":"713 N 21st Ave",
    "sg:city":"Cornelius",
    "sg:classifiers":[
        {
            "category":"Building & Trades",
            "subcategory":"Construction",
            "type":"Services"
        }
    ],
    "sg:phone":"+1 503 359 0911",
    "sg:postcode":"97113",
    "sg:province":"OR",
    "sg:tags":[
        "home",
        "builder"
    ],
    "wof:name":"Council Creek Estates",
    "wof:placetype":"venue"
},
  "geometry": {"coordinates":[-123.045247,45.525478],"type":"Point"}
}