{
  "type": "Feature",
  "properties": {
    "iso:country":"US",
    "sg:address":"1107 SW 33rd St",
    "sg:city":"Pendleton",
    "sg:classifiers":[
        {
            "category":"Health Services",
            "subcategory":"Doctor",
            "type":"Services"
        }
    ],
    "sg:phone":"+1 541 276 2303",
    "sg:postcode":"97801",
    "sg:province":"OR",
    "sg:tags":[
        "physician",
        "surgeon"
    ],
    "wof:name":"Don Meengs",
    "wof:placetype":"venue"
},
  "geometry": {"coordinates":[-118.818138,45.653138],"type":"Point"}
}