{
  "type": "Feature",
  "properties": {
    "iso:country":"US",
    "sg:address":"877 Windemar Dr",
    "sg:city":"Ashland",
    "sg:classifiers":[
        {
            "category":"Health Services",
            "subcategory":"Doctor",
            "type":"Services"
        }
    ],
    "sg:phone":"+1 541 488 5609",
    "sg:postcode":"97520",
    "sg:province":"OR",
    "wof:name":"Robert Zundel",
    "wof:placetype":"venue"
},
  "geometry": {"coordinates":[-122.645214,42.143905],"type":"Point"}
}