{
  "type": "Feature",
  "properties": {
    "iso:country":"US",
    "sg:address":"301 E Columbia Dr",
    "sg:city":"Newberg",
    "sg:classifiers":[
        {
            "category":"Professional",
            "subcategory":"Secretarial Services",
            "type":"Services"
        }
    ],
    "sg:phone":"+1 503 538 3695",
    "sg:postcode":"97132",
    "sg:province":"OR",
    "sg:tags":[
        "transcription",
        "medical"
    ],
    "wof:name":"John W Vonder Reith",
    "wof:placetype":"venue"
},
  "geometry": {"coordinates":[-122.97716200000001,45.313048],"type":"Point"}
}