{
  "type": "Feature",
  "properties": {
    "addr:full":"3428 SE 7th Ave Portland OR 97202",
    "addr:housenumber":"3428",
    "addr:postcode":"97202",
    "addr:street":"Se 7Th Ave",
    "iso:country":"US",
    "sg:address":"3428 SE 7th Ave",
    "sg:city":"Portland",
    "sg:classifiers":[
        {
            "category":"Retail",
            "subcategory":"Laundry & Dry Cleaning",
            "type":"Services"
        }
    ],
    "sg:phone":"+1 503 239 7267",
    "sg:postcode":"97202",
    "sg:province":"OR",
    "sg:tags":[
        "cleaners",
        "rug",
        "carpet"
    ],
    "wof:name":"A Better Cleaning Co",
    "wof:placetype":"venue"
},
  "geometry": {"coordinates":[-122.65875699999999,45.499201],"type":"Point"}
}