{
  "type": "Feature",
  "properties": {
    "iso:country":"US",
    "sg:address":"3428 SE 7th Ave",
    "sg:city":"Portland",
    "sg:classifiers":[
        {
            "category":"Retail",
            "subcategory":"Laundry & Dry Cleaning",
            "type":"Services"
        }
    ],
    "sg:phone":"+1 503 239 7267",
    "sg:postcode":"97202",
    "sg:province":"OR",
    "sg:tags":[
        "cleaners",
        "rug",
        "carpet"
    ],
    "wof:name":"A Better Cleaning Co",
    "wof:placetype":"venue"
},
  "geometry": {"coordinates":[-122.658757,45.499201],"type":"Point"}
}