{
  "type": "Feature",
  "properties": {
    "iso:country":"US",
    "sg:address":"364 N 3rd Ave",
    "sg:city":"Stayton",
    "sg:classifiers":[
        {
            "category":"Social Services",
            "type":"Services"
        }
    ],
    "sg:phone":"+1 503 769 7189",
    "sg:postcode":"97383",
    "sg:province":"OR",
    "sg:tags":[
        "notification",
        "emergency"
    ],
    "wof:name":"Santiam Canyon 911 Ctr",
    "wof:placetype":"venue"
},
  "geometry": {"coordinates":[-122.792175,44.797459],"type":"Point"}
}