{
  "type": "Feature",
  "properties": {
    "iso:country":"US",
    "sg:address":"3013 NW Stewart Pkwy",
    "sg:city":"Roseburg",
    "sg:classifiers":[
        {
            "category":"Banks & Credit Unions",
            "subcategory":"Bank",
            "type":"Services"
        }
    ],
    "sg:phone":"+1 541 677 8402",
    "sg:postcode":"97470",
    "sg:province":"OR",
    "wof:name":"US Bank",
    "wof:placetype":"venue"
},
  "geometry": {"coordinates":[-123.361845,43.240112],"type":"Point"}
}