{
  "type": "Feature",
  "properties": {
    "iso:country":"US",
    "sg:address":"10655 Old Woods Rd",
    "sg:city":"Cloverdale",
    "sg:classifiers":[
        {
            "category":"Freight",
            "type":"Transportation"
        }
    ],
    "sg:phone":"+1 503 392 3241",
    "sg:postcode":"97112",
    "sg:province":"OR",
    "sg:tags":[
        "trucking"
    ],
    "wof:name":"Han Dun Trucking",
    "wof:placetype":"venue"
},
  "geometry": {"coordinates":[-123.91589399999999,45.205542],"type":"Point"}
}