{
  "type": "Feature",
  "properties": {
    "iso:country":"US",
    "sg:address":"840 E Alabama Ave",
    "sg:city":"Vernonia",
    "sg:classifiers":[
        {
            "category":"Manufacturing",
            "subcategory":"Printing",
            "type":"Manufacturing & Wholesale Goods"
        }
    ],
    "sg:phone":"+1 503 429 1000",
    "sg:postcode":"97064",
    "sg:province":"OR",
    "sg:tags":[
        "engraver",
        "wood"
    ],
    "sg:website":"www.specializedengraving.com",
    "wof:name":"Specialized Engraving",
    "wof:placetype":"venue"
},
  "geometry": {"coordinates":[-123.175979,45.858344],"type":"Point"}
}