{
  "type": "Feature",
  "properties": {
    "iso:country":"US",
    "sg:address":"5217 SE Aldercrest Rd",
    "sg:city":"Portland",
    "sg:classifiers":[
        {
            "category":"Real Estate",
            "subcategory":"Real Estate Operator",
            "type":"Services"
        }
    ],
    "sg:phone":"+1 503 659 1761",
    "sg:postcode":"97222",
    "sg:province":"OR",
    "sg:tags":[
        "property",
        "lessor"
    ],
    "wof:name":"TLC Properties Inc",
    "wof:placetype":"venue"
},
  "geometry": {"coordinates":[-122.606711,45.422195],"type":"Point"}
}