{
  "type": "Feature",
  "properties": {
    "addr:full":"4655 SW 142nd Ave Beaverton OR 97005",
    "addr:housenumber":"4655",
    "addr:postcode":"97005",
    "addr:street":"Sw 142Nd Ave",
    "iso:country":"US",
    "sg:address":"4655 SW 142nd Ave",
    "sg:city":"Beaverton",
    "sg:classifiers":[
        {
            "category":"Restaurant",
            "type":"Food & Drink"
        }
    ],
    "sg:phone":"+1 503 641 6053",
    "sg:postcode":"97005",
    "sg:province":"OR",
    "sg:tags":[
        "eating"
    ],
    "wof:name":"Crepe House",
    "wof:placetype":"venue"
},
  "geometry": {"coordinates":[-122.822463,45.488745],"type":"Point"}
}