{
  "type": "Feature",
  "properties": {
    "iso:country":"US",
    "sg:address":"2355 NW West Hills Dr",
    "sg:city":"Mcminnville",
    "sg:classifiers":[
        {
            "category":"Social Services",
            "subcategory":"Child Care",
            "type":"Services"
        }
    ],
    "sg:phone":"+1 503 435 2092",
    "sg:postcode":"97128",
    "sg:province":"OR",
    "wof:name":"West Hills Daycare",
    "wof:placetype":"venue"
},
  "geometry": {"coordinates":[-123.232623,45.210523],"type":"Point"}
}