{
  "type": "Feature",
  "properties": {
    "addr:full":"12042 SE Sunnyside Rd. Suite 518 Clackamas OR 97015",
    "addr:postcode":"12042;97015",
    "addr:street":"Se Sunnyside Rd. Suite 518",
    "iso:country":"US",
    "sg:address":"12042 SE Sunnyside Rd. Suite 518",
    "sg:city":"Clackamas",
    "sg:classifiers":[
        {
            "category":"Professional",
            "subcategory":"Accounting & Tax Preparation",
            "type":"Services"
        },
        {
            "category":"Education",
            "subcategory":"Special Training",
            "type":"Public Place"
        }
    ],
    "sg:phone":"+1 503 885 0776",
    "sg:postcode":"97015",
    "sg:province":"OR",
    "sg:tags":[
        "accountant",
        "tutoring"
    ],
    "sg:website":"www.teachmequickbooks.com",
    "wof:name":"Essential Business Services",
    "wof:placetype":"venue"
},
  "geometry": {"coordinates":[-122.539365,45.429475],"type":"Point"}
}