{
  "type": "Feature",
  "properties": {
    "iso:country":"US",
    "sg:address":"593 Canberra Dr",
    "sg:city":"Philomath",
    "sg:classifiers":[
        {
            "category":"Recreation",
            "type":"Entertainment"
        }
    ],
    "sg:phone":"+1 541 929 3549",
    "sg:postcode":"97370",
    "sg:province":"OR",
    "sg:tags":[
        "stable"
    ],
    "wof:name":"Oasis Stables & Training",
    "wof:placetype":"venue"
},
  "geometry": {"coordinates":[-123.378454,44.544433],"type":"Point"}
}