{
  "type": "Feature",
  "properties": {
    "addr:full":"5946 SE Milwaukie Ave Portland OR 97202",
    "addr:housenumber":"5946",
    "addr:postcode":"97202",
    "addr:street":"Se Milwaukie Ave",
    "iso:country":"US",
    "sg:address":"5946 SE Milwaukie Ave",
    "sg:city":"Portland",
    "sg:classifiers":[
        {
            "category":"Professional",
            "subcategory":"Advertising",
            "type":"Services"
        }
    ],
    "sg:phone":"+1 503 957 8991",
    "sg:postcode":"97202",
    "sg:province":"OR",
    "sg:tags":[
        "agency",
        "specialty"
    ],
    "sg:website":"http://www.redhencommunications.com",
    "wof:name":"Holden Lee Tees",
    "wof:placetype":"venue"
},
  "geometry": {"coordinates":[-122.649458,45.479697],"type":"Point"}
}