{
  "type": "Feature",
  "properties": {
    "iso:country":"US",
    "sg:address":"2301 NW Suffolk St",
    "sg:city":"Portland",
    "sg:classifiers":[
        {
            "category":"Wholesale",
            "subcategory":"Machinery & Supplies",
            "type":"Manufacturing & Wholesale Goods"
        }
    ],
    "sg:phone":"+1 206 763 1130",
    "sg:postcode":"97210",
    "sg:province":"OR",
    "sg:tags":[
        "industrial",
        "machinery-new",
        "equipment",
        "used",
        "supplies-wholesale"
    ],
    "wof:name":"Waterfront Supply Corporation",
    "wof:placetype":"venue"
},
  "geometry": {"coordinates":[-122.698959,45.542419],"type":"Point"}
}