{
  "type": "Feature",
  "properties": {
    "addr:full":"2700 Industrial Ave Hubbard OR 97032",
    "addr:housenumber":"2700",
    "addr:postcode":"97032",
    "addr:street":"Industrial Ave",
    "iso:country":"US",
    "sg:address":"2700 Industrial Ave",
    "sg:city":"Hubbard",
    "sg:classifiers":[
        {
            "category":"Manufacturing",
            "subcategory":"Rubber & Plastics",
            "type":"Manufacturing & Wholesale Goods"
        }
    ],
    "sg:phone":"+1 503 981 0457",
    "sg:postcode":"97032",
    "sg:province":"OR",
    "sg:tags":[
        "product",
        "mfg"
    ],
    "wof:name":"Assured Shapes",
    "wof:placetype":"venue"
},
  "geometry": {"coordinates":[-122.80681199999999,45.174935],"type":"Point"}
}