{
  "type": "Feature",
  "properties": {
    "addr:full":"210 E 17th Ave Eugene OR 97401",
    "addr:housenumber":"210",
    "addr:postcode":"97401",
    "addr:street":"E 17Th Ave",
    "iso:country":"US",
    "sg:address":"210 E 17th Ave",
    "sg:city":"Eugene",
    "sg:classifiers":[
        {
            "category":"Utilities",
            "type":"Services"
        }
    ],
    "sg:phone":"+1 541 338 4296",
    "sg:postcode":"97401",
    "sg:province":"OR",
    "sg:tags":[
        "locating"
    ],
    "wof:name":"Locating Inc",
    "wof:placetype":"venue"
},
  "geometry": {"coordinates":[-123.089102,44.041054],"type":"Point"}
}