{
  "type": "Feature",
  "properties": {
    "iso:country":"US",
    "sg:address":"230 NW Division St",
    "sg:city":"Gresham",
    "sg:classifiers":[
        {
            "category":"Real Estate",
            "subcategory":"Real Estate Agent",
            "type":"Services"
        }
    ],
    "sg:phone":"+1 503 666 5500",
    "sg:postcode":"97030",
    "sg:province":"OR",
    "wof:name":"Mc Kenzie & Assoc",
    "wof:placetype":"venue"
},
  "geometry": {"coordinates":[-122.433769,45.504403],"type":"Point"}
}