{
  "type": "Feature",
  "properties": {
    "iso:country":"US",
    "sg:address":"19634 French Prairie Rd NE",
    "sg:city":"Woodburn",
    "sg:phone":"+1 503 633 2562",
    "sg:postcode":"97071",
    "sg:province":"OR",
    "sg:tags":[
        "farm",
        "field",
        "crop"
    ],
    "wof:name":"Kaufmann Farms",
    "wof:placetype":"venue"
},
  "geometry": {"coordinates":[-122.939183,45.201577],"type":"Point"}
}