{
  "type": "Feature",
  "properties": {
    "iso:country":"US",
    "sg:address":"37755 State Hwy 58",
    "sg:city":"Dexter",
    "sg:classifiers":[
        {
            "category":"Organizations",
            "subcategory":"Non-profit Organization",
            "type":"Services"
        }
    ],
    "sg:phone":"+1 541 726 2817",
    "sg:postcode":"97431",
    "sg:province":"OR",
    "wof:name":"Yamhill Log Scaling Bureau",
    "wof:placetype":"venue"
},
  "geometry": {"coordinates":[-122.865771,43.941868],"type":"Point"}
}