{
  "type": "Feature",
  "properties": {
    "iso:country":"US",
    "sg:address":"780 California St",
    "sg:city":"North Bend",
    "sg:classifiers":[
        {
            "category":"Organizations",
            "subcategory":"Non-profit Organization",
            "type":"Services"
        }
    ],
    "sg:phone":"+1 541 756 1359",
    "sg:postcode":"97459",
    "sg:province":"OR",
    "sg:tags":[
        "human"
    ],
    "wof:name":"SHAMA",
    "wof:placetype":"venue"
},
  "geometry": {"coordinates":[-124.224886,43.408219],"type":"Point"}
}