{
  "type": "Feature",
  "properties": {
    "addr:full":"127 NW 2nd St Corvallis OR 97330",
    "addr:housenumber":"127",
    "addr:postcode":"97330",
    "addr:street":"Nw 2Nd St",
    "iso:country":"US",
    "sg:address":"127 NW 2nd St",
    "sg:city":"Corvallis",
    "sg:classifiers":[
        {
            "category":"Retail",
            "subcategory":"Photofinishing",
            "type":"Services"
        }
    ],
    "sg:phone":"+1 541 753 5311",
    "sg:postcode":"97330",
    "sg:province":"OR",
    "sg:tags":[
        "color",
        "photographer",
        "o",
        "lab",
        "mail",
        "professional",
        "order",
        "film"
    ],
    "wof:name":"Hise Studio",
    "wof:placetype":"venue"
},
  "geometry": {"coordinates":[-123.259395,44.564797],"type":"Point"}
}