{
  "type": "Feature",
  "properties": {
    "iso:country":"US",
    "sg:address":"2821 NE Davis St",
    "sg:city":"Portland",
    "sg:classifiers":[
        {
            "category":"Autos & Motor Vehicles",
            "subcategory":"Automobile Sales",
            "type":"Retail Goods"
        }
    ],
    "sg:phone":"+1 503 233 3651",
    "sg:postcode":"97232",
    "sg:province":"OR",
    "sg:tags":[
        "car",
        "dealer"
    ],
    "wof:name":"Gateway Acceptance & Lease",
    "wof:placetype":"venue"
},
  "geometry": {"coordinates":[-122.636094,45.524401],"type":"Point"}
}