{
  "type": "Feature",
  "properties": {
    "addr:full":"2146 State St Salem OR 97301",
    "addr:housenumber":"2146",
    "addr:postcode":"97301",
    "addr:street":"State St",
    "iso:country":"US",
    "sg:address":"2146 State St",
    "sg:city":"Salem",
    "sg:classifiers":[
        {
            "category":"Professional",
            "subcategory":"Business Services",
            "type":"Services"
        }
    ],
    "sg:phone":"+1 503 363 2774",
    "sg:postcode":"97301",
    "sg:province":"OR",
    "wof:name":"Mikwin Limited Partnership",
    "wof:placetype":"venue"
},
  "geometry": {"coordinates":[-123.01568,44.933988],"type":"Point"}
}