{
  "type": "Feature",
  "properties": {
    "iso:country":"US",
    "sg:address":"240 S 19th St",
    "sg:city":"Reedsport",
    "sg:classifiers":[
        {
            "category":"Government",
            "subcategory":"Office",
            "type":"Public Place"
        }
    ],
    "sg:phone":"+1 541 584 2320",
    "sg:postcode":"97467",
    "sg:province":"OR",
    "sg:tags":[
        "federal"
    ],
    "wof:name":"US Land Management Bureau",
    "wof:placetype":"venue"
},
  "geometry": {"coordinates":[-124.118156,43.694901],"type":"Point"}
}