{
  "type": "Feature",
  "properties": {
    "iso:country":"US",
    "sg:address":"4222 Commerce St",
    "sg:city":"Eugene",
    "sg:classifiers":[
        {
            "category":"Insurance",
            "subcategory":"Insurance Agent",
            "type":"Services"
        }
    ],
    "sg:phone":"+1 541 338 8281",
    "sg:postcode":"97402",
    "sg:province":"OR",
    "wof:name":"Met Life Auto & Home",
    "wof:placetype":"venue"
},
  "geometry": {"coordinates":[-123.167156,44.048406],"type":"Point"}
}