{
  "type": "Feature",
  "properties": {
    "iso:country":"US",
    "sg:address":"1030 NE 24th St",
    "sg:city":"Gresham",
    "sg:classifiers":[
        {
            "category":"Building & Trades",
            "subcategory":"Electrical",
            "type":"Services"
        }
    ],
    "sg:phone":"+1 503 667 9525",
    "sg:postcode":"97030",
    "sg:province":"OR",
    "sg:tags":[
        "electrical",
        "contractor"
    ],
    "wof:name":"Cjt Electric",
    "wof:placetype":"venue"
},
  "geometry": {"coordinates":[-122.420918,45.514094],"type":"Point"}
}