{
  "type": "Feature",
  "properties": {
    "iso:country":"US",
    "sg:address":"2660 SW 3rd St",
    "sg:city":"Corvallis",
    "sg:classifiers":[
        {
            "category":"Autos & Motor Vehicles",
            "subcategory":"Boat Sales",
            "type":"Retail Goods"
        }
    ],
    "sg:phone":"+1 541 753 4241",
    "sg:postcode":"97333",
    "sg:province":"OR",
    "sg:tags":[
        "marine",
        "sales"
    ],
    "sg:website":"www.ssmarine.com",
    "wof:name":"Southside Marine",
    "wof:placetype":"venue"
},
  "geometry": {"coordinates":[-123.266399,44.54077],"type":"Point"}
}