{
  "type": "Feature",
  "properties": {
    "iso:country":"US",
    "sg:address":"15253 NW Mason Hill Rd",
    "sg:city":"North Plains",
    "sg:classifiers":[
        {
            "category":"Manufacturing",
            "subcategory":"Food",
            "type":"Manufacturing & Wholesale Goods"
        }
    ],
    "sg:phone":"+1 503 647 5769",
    "sg:postcode":"97133",
    "sg:province":"OR",
    "sg:tags":[
        "canned",
        "mfg"
    ],
    "wof:name":"Golden Orchard",
    "wof:placetype":"venue"
},
  "geometry": {"coordinates":[-122.94461,45.628813],"type":"Point"}
}