{
  "type": "Feature",
  "properties": {
    "iso:country":"US",
    "sg:address":"7525 SE Foster Rd",
    "sg:city":"Portland",
    "sg:classifiers":[
        {
            "category":"Personal",
            "subcategory":"Beauty Salon",
            "type":"Services"
        }
    ],
    "sg:phone":"+1 503 771 0391",
    "sg:postcode":"97206",
    "sg:province":"OR",
    "wof:name":"Hair Studio One",
    "wof:placetype":"venue"
},
  "geometry": {"coordinates":[-122.585446,45.485324],"type":"Point"}
}