{
  "type": "Feature",
  "properties": {
    "iso:country":"US",
    "sg:address":"12550 SE 93rd Avenue",
    "sg:city":"Portland",
    "sg:classifiers":[
        {
            "category":"Banks & Credit Unions",
            "subcategory":"Bank",
            "type":"Services"
        },
        {
            "category":"Banks & Credit Unions",
            "subcategory":"Financial Services",
            "type":"Services"
        }
    ],
    "sg:phone":"+1 503 353 0435",
    "sg:postcode":"97222",
    "sg:province":"OR",
    "sg:tags":[
        "broker",
        "mortgage"
    ],
    "wof:name":"Umpqua Bank",
    "wof:placetype":"venue"
},
  "geometry": {"coordinates":[-122.615562,45.441952],"type":"Point"}
}