{
  "type": "Feature",
  "properties": {
    "addr:full":"99 W 10th Ave Eugene OR 97401",
    "addr:housenumber":"99",
    "addr:postcode":"97401",
    "addr:street":"W 10Th Ave",
    "iso:country":"US",
    "sg:address":"99 W 10th Ave",
    "sg:city":"Eugene",
    "sg:classifiers":[
        {
            "category":"Government",
            "subcategory":"Office",
            "type":"Public Place"
        }
    ],
    "sg:phone":"+1 541 682 5819",
    "sg:postcode":"97401",
    "sg:province":"OR",
    "sg:tags":[
        "city",
        "planning",
        "dev"
    ],
    "wof:name":"Eugene Zoning Dept",
    "wof:placetype":"venue"
},
  "geometry": {"coordinates":[-123.093507,44.048815],"type":"Point"}
}