{
  "type": "Feature",
  "properties": {
    "addr:full":"3824 River Rd N Keizer OR 97303",
    "addr:housenumber":"3824",
    "addr:postcode":"97303",
    "addr:street":"River Rd N",
    "iso:country":"US",
    "sg:address":"3824 River Rd N",
    "sg:city":"Keizer",
    "sg:classifiers":[
        {
            "category":"Wholesale",
            "subcategory":"Computers",
            "type":"Manufacturing & Wholesale Goods"
        },
        {
            "category":"Professional",
            "subcategory":"Computer Services",
            "type":"Services"
        }
    ],
    "sg:phone":"+1 503 304 3925",
    "sg:postcode":"97303",
    "sg:province":"OR",
    "sg:tags":[
        "equipment",
        "isp",
        "internet",
        "provider"
    ],
    "wof:name":"Computer Self And Services",
    "wof:placetype":"venue"
},
  "geometry": {"coordinates":[-123.02660400000001,44.981479],"type":"Point"}
}