{
  "type": "Feature",
  "properties": {
    "iso:country":"US",
    "sg:address":"4596 Maria Ave NE",
    "sg:city":"Salem",
    "sg:classifiers":[
        {
            "category":"Building & Trades",
            "subcategory":"Construction",
            "type":"Services"
        }
    ],
    "sg:phone":"+1 503 370 6166",
    "sg:postcode":"97305",
    "sg:province":"OR",
    "sg:tags":[
        "hanging",
        "contractor"
    ],
    "wof:name":"New Dimensions Painting",
    "wof:placetype":"venue"
},
  "geometry": {"coordinates":[-122.97095400000001,44.957465],"type":"Point"}
}