{
  "type": "Feature",
  "properties": {
    "addr:full":"14400 N Rivergate Blvd Portland OR 97203",
    "addr:housenumber":"14400",
    "addr:postcode":"97203",
    "addr:street":"N Rivergate Blvd",
    "iso:country":"US",
    "sg:address":"14400 N Rivergate Blvd",
    "sg:city":"Portland",
    "sg:classifiers":[
        {
            "category":"Manufacturing",
            "subcategory":"Metals",
            "type":"Manufacturing & Wholesale Goods"
        }
    ],
    "sg:phone":"+1 503 286 9651",
    "sg:postcode":"97203",
    "sg:province":"OR",
    "sg:tags":[
        "steel",
        "mills"
    ],
    "sg:website":"www.osm.com",
    "wof:name":"Oregon Steel Div",
    "wof:placetype":"venue"
},
  "geometry": {"coordinates":[-122.778423,45.616638],"type":"Point"}
}