{
  "type": "Feature",
  "properties": {
    "addr:full":"710 NE Cleveland Ave # 190 Gresham OR 97030",
    "addr:housenumber":"710",
    "addr:postcode":"97030",
    "addr:street":"Ne Cleveland Ave # 190",
    "iso:country":"US",
    "sg:address":"710 NE Cleveland Ave # 190",
    "sg:city":"Gresham",
    "sg:classifiers":[
        {
            "category":"Industrial Area",
            "type":"Public Place"
        }
    ],
    "sg:phone":"+1 503 492 8136",
    "sg:postcode":"97030",
    "sg:province":"OR",
    "sg:tags":[
        "development"
    ],
    "wof:name":"Elmerald Point",
    "wof:placetype":"venue"
},
  "geometry": {"coordinates":[-122.421086,45.50247],"type":"Point"}
}