{
  "type": "Feature",
  "properties": {
    "iso:country":"US",
    "sg:address":"1102 SW Kings Pl",
    "sg:city":"Dallas",
    "sg:classifiers":[
        {
            "category":"Personal",
            "type":"Services"
        }
    ],
    "sg:phone":"+1 503 910 5717",
    "sg:postcode":"97338",
    "sg:province":"OR",
    "wof:name":"Body Essential",
    "wof:placetype":"venue"
},
  "geometry": {"coordinates":[-123.332013,44.924686],"type":"Point"}
}