{
  "type": "Feature",
  "properties": {
    "iso:country":"US",
    "sg:address":"1503 Whitley Ln",
    "sg:city":"Vale",
    "sg:phone":"+1 541 473 2316",
    "sg:postcode":"97918",
    "sg:province":"OR",
    "sg:tags":[
        "farm",
        "field",
        "crop"
    ],
    "wof:name":"Shane Meacham",
    "wof:placetype":"venue"
},
  "geometry": {"coordinates":[-117.186815,43.979049],"type":"Point"}
}