{
  "type": "Feature",
  "properties": {
    "addr:full":"3735 SE Milwaukie Ave Portland OR 97202",
    "addr:housenumber":"3735",
    "addr:postcode":"97202",
    "addr:street":"Se Milwaukie Ave",
    "iso:country":"US",
    "sg:address":"3735 SE Milwaukie Ave",
    "sg:city":"Portland",
    "sg:classifiers":[
        {
            "category":"Education",
            "subcategory":"Special Training",
            "type":"Public Place"
        }
    ],
    "sg:phone":"+1 503 502 1376",
    "sg:postcode":"97202",
    "sg:province":"OR",
    "sg:tags":[
        "instruction",
        "music"
    ],
    "wof:name":"Hancock Vocal Studio",
    "wof:placetype":"venue"
},
  "geometry": {"coordinates":[-122.65338,45.495721],"type":"Point"}
}