{
  "type": "Feature",
  "properties": {
    "addr:full":"820 Rogue River Hwy Gold Hill OR 97525",
    "addr:housenumber":"820",
    "addr:postcode":"97525",
    "addr:street":"Rogue River Hwy",
    "iso:country":"US",
    "sg:address":"820 Rogue River Hwy",
    "sg:city":"Gold Hill",
    "sg:classifiers":[
        {
            "category":"Education",
            "subcategory":"School",
            "type":"Public Place"
        }
    ],
    "sg:phone":"+1 541 855 5558",
    "sg:postcode":"97525",
    "sg:province":"OR",
    "wof:name":"Middle Earth Organic",
    "wof:placetype":"venue"
},
  "geometry": {"coordinates":[-123.113303,42.426978],"type":"Point"}
}