{
  "type": "Feature",
  "properties": {
    "iso:country":"US",
    "sg:address":"4025 N Juneau St",
    "sg:city":"Portland",
    "sg:classifiers":[
        {
            "category":"Retail",
            "subcategory":"Laundry & Dry Cleaning",
            "type":"Services"
        }
    ],
    "sg:phone":"+1 503 289 1666",
    "sg:postcode":"97203",
    "sg:province":"OR",
    "sg:tags":[
        "cleaner",
        "rug",
        "carpet"
    ],
    "wof:name":"Five Star Cleaning Company Of Oregon",
    "wof:placetype":"venue"
},
  "geometry": {"coordinates":[-122.708217,45.59091],"type":"Point"}
}