{
  "type": "Feature",
  "properties": {
    "iso:country":"US",
    "sg:address":"1937 W Harvard Ave",
    "sg:city":"Roseburg",
    "sg:classifiers":[
        {
            "category":"Government",
            "subcategory":"Office",
            "type":"Public Place"
        }
    ],
    "sg:phone":"+1 541 440 3322",
    "sg:postcode":"97470",
    "sg:province":"OR",
    "wof:name":"Volunteer Program DHR",
    "wof:placetype":"venue"
},
  "geometry": {"coordinates":[-123.373799,43.214088],"type":"Point"}
}