{
  "type": "Feature",
  "properties": {
    "iso:country":"US",
    "sg:address":"19290 S Badger Dr",
    "sg:city":"Oregon City",
    "sg:classifiers":[
        {
            "category":"Shopping",
            "subcategory":"Crafts & Fabrics",
            "type":"Retail Goods"
        },
        {
            "category":"Manufacturing",
            "subcategory":"Watercraft",
            "type":"Manufacturing & Wholesale Goods"
        }
    ],
    "sg:phone":"+1 503 631 3973",
    "sg:postcode":"97045",
    "sg:province":"OR",
    "sg:tags":[
        "rebuilt",
        "part",
        "boat",
        "sewing"
    ],
    "wof:name":"J-Made Looms & Weaving Acces",
    "wof:placetype":"venue"
},
  "geometry": {"coordinates":[-122.470457,45.307507],"type":"Point"}
}