{
  "type": "Feature",
  "properties": {
    "iso:country":"US",
    "sg:address":"5258 NW Shoreline Way",
    "sg:city":"Portland",
    "sg:classifiers":[
        {
            "category":"Professional",
            "subcategory":"Management & Consulting",
            "type":"Services"
        }
    ],
    "sg:phone":"+1 503 533 7785",
    "sg:postcode":"97229",
    "sg:province":"OR",
    "sg:tags":[
        "retail",
        "direct",
        "merchandise",
        "sales"
    ],
    "wof:name":"Madison Home Accents & Floral",
    "wof:placetype":"venue"
},
  "geometry": {"coordinates":[-122.871341,45.557765],"type":"Point"}
}