{
  "type": "Feature",
  "properties": {
    "iso:country":"US",
    "sg:address":"241 US Hwy 101 S",
    "sg:city":"Yachats",
    "sg:classifiers":[
        {
            "category":"Organizations",
            "subcategory":"Professional Association",
            "type":"Services"
        }
    ],
    "sg:phone":"+1 541 547 3530",
    "sg:postcode":"97498",
    "sg:province":"OR",
    "sg:tags":[
        "chambers",
        "commerce"
    ],
    "sg:website":"www.yachats.org",
    "wof:name":"Yachats Area Chamber-Commerce",
    "wof:placetype":"venue"
},
  "geometry": {"coordinates":[-124.106521,44.302617],"type":"Point"}
}