{
  "type": "Feature",
  "properties": {
    "addr:full":"4050 NE 158th Ave Portland OR 97230",
    "addr:housenumber":"4050",
    "addr:postcode":"97230",
    "addr:street":"Ne 158Th Ave",
    "iso:country":"US",
    "sg:address":"4050 NE 158th Ave",
    "sg:city":"Portland",
    "sg:classifiers":[
        {
            "category":"Food Court",
            "type":"Food & Drink"
        },
        {
            "category":"Wholesale",
            "subcategory":"Groceries",
            "type":"Manufacturing & Wholesale Goods"
        },
        {
            "category":"Home & Garden",
            "subcategory":"Kitchen Supply",
            "type":"Retail Goods"
        }
    ],
    "sg:phone":"+1 503 257 9821",
    "sg:postcode":"97230",
    "sg:province":"OR",
    "sg:tags":[
        "concession",
        "management",
        "products-wholesale",
        "concessionaire"
    ],
    "wof:name":"Blue Ribbon Food",
    "wof:placetype":"venue"
},
  "geometry": {"coordinates":[-122.500253,45.552514],"type":"Point"}
}