{
  "type": "Feature",
  "properties": {
    "iso:country":"US",
    "sg:address":"15150 Bangy Rd",
    "sg:city":"Lake Oswego",
    "sg:classifiers":[
        {
            "category":"Travel",
            "subcategory":"Travel Agent",
            "type":"Entertainment"
        }
    ],
    "sg:phone":"+1 503 620 0620",
    "sg:postcode":"97035",
    "sg:province":"OR",
    "sg:tags":[
        "agency",
        "bureau"
    ],
    "wof:name":"Uniglobe Spectrum Travel",
    "wof:placetype":"venue"
},
  "geometry": {"coordinates":[-122.742665,45.417567],"type":"Point"}
}