{
  "type": "Feature",
  "properties": {
    "addr:full":"1910 Turner Rd SE Salem OR 97302",
    "addr:housenumber":"1910",
    "addr:postcode":"97302",
    "addr:street":"Turner Rd Se",
    "iso:country":"US",
    "sg:address":"1910 Turner Rd SE",
    "sg:city":"Salem",
    "sg:classifiers":[
        {
            "category":"Restaurant",
            "type":"Food & Drink"
        }
    ],
    "sg:menulink":"http://www.allmenus.com/or/salem/240424-panda-express/menu/",
    "sg:phone":"+1 503 391 8236",
    "sg:postcode":"97302",
    "sg:province":"OR",
    "sg:tags":[
        "asian",
        "chinese"
    ],
    "wof:name":"Panda Express",
    "wof:placetype":"venue"
},
  "geometry": {"coordinates":[-123.000293,44.915755],"type":"Point"}
}