{
  "type": "Feature",
  "properties": {
    "iso:country":"US",
    "sg:address":"63029 Marsh Orchid Dr",
    "sg:city":"Bend",
    "sg:classifiers":[
        {
            "category":"Shopping",
            "subcategory":"Catalog Store",
            "type":"Retail Goods"
        }
    ],
    "sg:phone":"+1 541 383 8265",
    "sg:postcode":"97701",
    "sg:province":"OR",
    "sg:tags":[
        "mail",
        "house"
    ],
    "wof:name":"Jl Merchandising",
    "wof:placetype":"venue"
},
  "geometry": {"coordinates":[-121.277521,44.089729],"type":"Point"}
}