{
  "type": "Feature",
  "properties": {
    "iso:country":"US",
    "sg:address":"11421 SW Scholls Ferry Rd",
    "sg:city":"Beaverton",
    "sg:classifiers":[
        {
            "category":"Professional",
            "subcategory":"Employment Agencies",
            "type":"Services"
        }
    ],
    "sg:phone":"+1 503 579 7777",
    "sg:postcode":"97008",
    "sg:province":"OR",
    "wof:name":"Westaff",
    "wof:placetype":"venue"
},
  "geometry": {"coordinates":[-122.794973,45.445414],"type":"Point"}
}