{
  "type": "Feature",
  "properties": {
    "iso:country":"US",
    "sg:address":"3354 SE Hawthorne Blvd",
    "sg:city":"Portland",
    "sg:classifiers":[
        {
            "category":"Bars & Pubs",
            "type":"Food & Drink"
        }
    ],
    "sg:phone":"+1 503 235 8286",
    "sg:postcode":"97214",
    "sg:province":"OR",
    "sg:tags":[
        "sandwich"
    ],
    "wof:name":"Hawthorne Street Cafe",
    "wof:placetype":"venue"
},
  "geometry": {"coordinates":[-122.629997,45.511902],"type":"Point"}
}