{
  "type": "Feature",
  "properties": {
    "addr:full":"34599 Ranchero Ave SE Albany OR 97322",
    "addr:housenumber":"34599",
    "addr:postcode":"97322",
    "addr:street":"Ranchero Ave Se",
    "iso:country":"US",
    "sg:address":"34599 Ranchero Ave SE",
    "sg:city":"Albany",
    "sg:classifiers":[
        {
            "category":"Building & Trades",
            "subcategory":"Construction",
            "type":"Services"
        }
    ],
    "sg:phone":"+1 541 926 0926",
    "sg:postcode":"97322",
    "sg:province":"OR",
    "sg:tags":[
        "contractor",
        "painting",
        "hanging"
    ],
    "wof:name":"Spinco",
    "wof:placetype":"venue"
},
  "geometry": {"coordinates":[-123.013874,44.602323],"type":"Point"}
}