{
  "type": "Feature",
  "properties": {
    "iso:country":"US",
    "sg:address":"111 SW 5th Ave",
    "sg:city":"Portland",
    "sg:classifiers":[
        {
            "category":"Professional",
            "subcategory":"Lawyer & Legal Services",
            "type":"Services"
        }
    ],
    "sg:phone":"+1 503 243 2300",
    "sg:postcode":"97204",
    "sg:province":"OR",
    "wof:name":"Gregores George J",
    "wof:placetype":"venue"
},
  "geometry": {"coordinates":[-122.67600299999999,45.522598],"type":"Point"}
}