{
  "type": "Feature",
  "properties": {
    "addr:full":"12335 Mallory Dr Klamath Falls OR 97603",
    "addr:housenumber":"12335",
    "addr:postcode":"97603",
    "addr:street":"Mallory Dr",
    "iso:country":"US",
    "sg:address":"12335 Mallory Dr",
    "sg:city":"Klamath Falls",
    "sg:classifiers":[
        {
            "category":"Health Services",
            "subcategory":"Health Practitioner",
            "type":"Services"
        }
    ],
    "sg:phone":"+1 541 882 4990",
    "sg:postcode":"97603",
    "sg:province":"OR",
    "wof:name":"Ronald C Wegener",
    "wof:placetype":"venue"
},
  "geometry": {"coordinates":[-121.640863,42.192],"type":"Point"}
}