{
  "type": "Feature",
  "properties": {
    "addr:full":"974 W 6th Ave Eugene OR 97402",
    "addr:housenumber":"974",
    "addr:postcode":"97402",
    "addr:street":"W 6Th Ave",
    "iso:country":"US",
    "sg:address":"974 W 6th Ave",
    "sg:city":"Eugene",
    "sg:classifiers":[
        {
            "category":"Shopping",
            "type":"Retail Goods"
        }
    ],
    "sg:phone":"+1 541 344 9603",
    "sg:postcode":"97402",
    "sg:province":"OR",
    "sg:tags":[
        "pet",
        "food",
        "merchandise",
        "supply"
    ],
    "wof:name":"Mini Pet Mart",
    "wof:placetype":"venue"
},
  "geometry": {"coordinates":[-123.108844,44.053178],"type":"Point"}
}