{
  "type": "Feature",
  "properties": {
    "iso:country":"US",
    "sg:address":"165 E Dyke Rd",
    "sg:city":"Winston",
    "sg:classifiers":[
        {
            "category":"Government",
            "subcategory":"Office",
            "type":"Public Place"
        }
    ],
    "sg:phone":"+1 541 679 3000",
    "sg:postcode":"97496",
    "sg:province":"OR",
    "sg:tags":[
        "school",
        "district"
    ],
    "wof:name":"Winston-Dillard School Dst",
    "wof:placetype":"venue"
},
  "geometry": {"coordinates":[-123.431482,43.101607],"type":"Point"}
}