{
  "type": "Feature",
  "properties": {
    "addr:full":"15959 NW Blueridge Dr Beaverton OR 97006",
    "addr:housenumber":"15959",
    "addr:postcode":"97006",
    "addr:street":"Nw Blueridge Dr",
    "iso:country":"US",
    "sg:address":"15959 NW Blueridge Dr",
    "sg:city":"Beaverton",
    "sg:classifiers":[
        {
            "category":"Wholesale",
            "subcategory":"Electrical",
            "type":"Manufacturing & Wholesale Goods"
        }
    ],
    "sg:phone":"+1 503 645 3554",
    "sg:postcode":"97006",
    "sg:province":"OR",
    "sg:tags":[
        "equipment",
        "consulting",
        "business"
    ],
    "wof:name":"Blueridge Agency",
    "wof:placetype":"venue"
},
  "geometry": {"coordinates":[-122.84075300000001,45.524571],"type":"Point"}
}