{
  "type": "Feature",
  "properties": {
    "iso:country":"US",
    "sg:address":"1126 Gateway Loop",
    "sg:city":"Springfield",
    "sg:classifiers":[
        {
            "category":"Insurance",
            "subcategory":"Insurance Agent",
            "type":"Services"
        }
    ],
    "sg:phone":"+1 541 741 1999",
    "sg:postcode":"97477",
    "sg:province":"OR",
    "wof:name":"Aid Association For Lutherans",
    "wof:placetype":"venue"
},
  "geometry": {"coordinates":[-123.045244,44.078735],"type":"Point"}
}