{
  "type": "Feature",
  "properties": {
    "addr:full":"1000 NE 122nd Ave Portland OR 97230",
    "addr:housenumber":"1000",
    "addr:postcode":"97230",
    "addr:street":"Ne 122Nd Ave",
    "iso:country":"US",
    "sg:address":"1000 NE 122nd Ave",
    "sg:city":"Portland",
    "sg:classifiers":[
        {
            "category":"Organizations",
            "subcategory":"Non-profit Organization",
            "type":"Services"
        }
    ],
    "sg:phone":"+1 503 262 9794",
    "sg:postcode":"97230",
    "sg:province":"OR",
    "sg:tags":[
        "human"
    ],
    "wof:name":"Habitat For Humanity",
    "wof:placetype":"venue"
},
  "geometry": {"coordinates":[-122.53762,45.530123],"type":"Point"}
}