{
  "type": "Feature",
  "properties": {
    "addr:full":"1445 45th Ave NE Salem OR 97301",
    "addr:housenumber":"1445",
    "addr:postcode":"97301",
    "addr:street":"45Th Ave Ne",
    "iso:country":"US",
    "sg:address":"1445 45th Ave NE",
    "sg:city":"Salem",
    "sg:classifiers":[
        {
            "category":"Social Services",
            "subcategory":"Child Care",
            "type":"Services"
        }
    ],
    "sg:phone":"+1 503 399 9974",
    "sg:postcode":"97301",
    "sg:province":"OR",
    "sg:tags":[
        "day"
    ],
    "wof:name":"Berry Patch Kids",
    "wof:placetype":"venue"
},
  "geometry": {"coordinates":[-122.973651,44.948052],"type":"Point"}
}