{
  "type": "Feature",
  "properties": {
    "addr:full":"2042 NW Hill St Bend OR 97701",
    "addr:housenumber":"2042",
    "addr:postcode":"97701",
    "addr:street":"Nw Hill St",
    "iso:country":"US",
    "sg:address":"2042 NW Hill St",
    "sg:city":"Bend",
    "sg:classifiers":[
        {
            "category":"Professional",
            "subcategory":"Computer Services",
            "type":"Services"
        }
    ],
    "sg:phone":"+1 541 383 5889",
    "sg:postcode":"97701",
    "sg:province":"OR",
    "sg:tags":[
        "repair"
    ],
    "wof:name":"Computer Solutions",
    "wof:placetype":"venue"
},
  "geometry": {"coordinates":[-121.30797800000001,44.069993],"type":"Point"}
}