{
  "type": "Feature",
  "properties": {
    "iso:country":"US",
    "sg:address":"783 NW Naito Pkwy",
    "sg:city":"Portland",
    "sg:classifiers":[
        {
            "category":"Real Estate",
            "subcategory":"Real Estate Agent",
            "type":"Services"
        }
    ],
    "sg:phone":"+1 503 973 5875",
    "sg:postcode":"97209",
    "sg:province":"OR",
    "wof:name":"GSL Properties",
    "wof:placetype":"venue"
},
  "geometry": {"coordinates":[-122.67301,45.527772],"type":"Point"}
}