{
  "type": "Feature",
  "properties": {
    "iso:country":"US",
    "sg:address":"2860 NW 29th Ave",
    "sg:city":"Portland",
    "sg:classifiers":[
        {
            "category":"Freight",
            "type":"Transportation"
        }
    ],
    "sg:phone":"+1 503 227 5634",
    "sg:postcode":"97210",
    "sg:province":"OR",
    "sg:tags":[
        "commercial",
        "storage"
    ],
    "wof:name":"U-Store Self-Storage",
    "wof:placetype":"venue"
},
  "geometry": {"coordinates":[-122.71089499999999,45.542571],"type":"Point"}
}