{
  "type": "Feature",
  "properties": {
    "iso:country":"US",
    "sg:address":"7001 N Bank Rd",
    "sg:city":"Roseburg",
    "sg:classifiers":[
        {
            "category":"Professional",
            "subcategory":"Research",
            "type":"Services"
        }
    ],
    "sg:phone":"+1 541 673 1068",
    "sg:postcode":"97470",
    "sg:province":"OR",
    "wof:name":"Applied Dynamics Laboratories",
    "wof:placetype":"venue"
},
  "geometry": {"coordinates":[-123.254874,43.308917],"type":"Point"}
}