{
  "type": "Feature",
  "properties": {
    "iso:country":"US",
    "sg:address":"2397 Ironwood St",
    "sg:city":"Eugene",
    "sg:classifiers":[
        {
            "category":"Shopping",
            "subcategory":"Gifts & Souvenirs",
            "type":"Retail Goods"
        }
    ],
    "sg:phone":"+1 541 345 0779",
    "sg:postcode":"97401",
    "sg:province":"OR",
    "wof:name":"Mona Lisa Gift Baskets",
    "wof:placetype":"venue"
},
  "geometry": {"coordinates":[-123.095485,44.089484],"type":"Point"}
}