{
  "type": "Feature",
  "properties": {
    "addr:full":"1539 SE Kelly Ave Gresham OR 97080",
    "addr:housenumber":"1539",
    "addr:postcode":"97080",
    "addr:street":"Se Kelly Ave",
    "iso:country":"US",
    "sg:address":"1539 SE Kelly Ave",
    "sg:city":"Gresham",
    "sg:classifiers":[
        {
            "category":"Restaurant",
            "type":"Food & Drink"
        }
    ],
    "sg:phone":"+1 503 669 1973",
    "sg:postcode":"97080",
    "sg:province":"OR",
    "wof:name":"Popgobble Gourmet",
    "wof:placetype":"venue"
},
  "geometry": {"coordinates":[-122.425088,45.485644],"type":"Point"}
}