{
  "type": "Feature",
  "properties": {
    "addr:full":"3630 SE Division St Portland OR 97202",
    "addr:housenumber":"3630",
    "addr:postcode":"97202",
    "addr:street":"Se Division St",
    "iso:country":"US",
    "sg:address":"3630 SE Division St",
    "sg:city":"Portland",
    "sg:classifiers":[
        {
            "category":"Home & Garden",
            "subcategory":"Furniture",
            "type":"Retail Goods"
        }
    ],
    "sg:phone":"+1 503 230 2522",
    "sg:postcode":"97202",
    "sg:province":"OR",
    "sg:tags":[
        "store"
    ],
    "sg:website":"www.porticostyle.com",
    "wof:name":"Portico",
    "wof:placetype":"venue"
},
  "geometry": {"coordinates":[-122.62599899999999,45.5047],"type":"Point"}
}