{
  "type": "Feature",
  "properties": {
    "iso:country":"US",
    "sg:address":"486 Applegate Way",
    "sg:city":"Ashland",
    "sg:classifiers":[
        {
            "category":"Shopping",
            "subcategory":"Used Merchandise",
            "type":"Retail Goods"
        }
    ],
    "sg:phone":"+1 541 482 4553",
    "sg:postcode":"97520",
    "sg:province":"OR",
    "sg:tags":[
        "oriental",
        "object",
        "art",
        "rug",
        "jewelry"
    ],
    "wof:name":"East West",
    "wof:placetype":"venue"
},
  "geometry": {"coordinates":[-122.656885,42.184107],"type":"Point"}
}