{
  "type": "Feature",
  "properties": {
    "iso:country":"US",
    "sg:address":"510 NE 3rd St",
    "sg:city":"Bend",
    "sg:classifiers":[
        {
            "category":"Real Estate",
            "subcategory":"Real Estate Agent",
            "type":"Services"
        }
    ],
    "sg:phone":"+1 541 317 0123",
    "sg:postcode":"97701",
    "sg:province":"OR",
    "sg:website":"www.johnlscott.com",
    "wof:name":"John L Scott Real Estate",
    "wof:placetype":"venue"
},
  "geometry": {"coordinates":[-121.30242,44.055271],"type":"Point"}
}