{
  "type": "Feature",
  "properties": {
    "addr:full":"117 C Ct Phoenix OR 97535",
    "addr:housenumber":"117",
    "addr:postcode":"97535",
    "addr:street":"C Ct",
    "iso:country":"US",
    "sg:address":"117 C Ct",
    "sg:city":"Phoenix",
    "sg:classifiers":[
        {
            "category":"Building & Trades",
            "subcategory":"Cleaning & Sanitation",
            "type":"Services"
        }
    ],
    "sg:phone":"+1 541 535 8843",
    "sg:postcode":"97535",
    "sg:province":"OR",
    "sg:tags":[
        "maintenance"
    ],
    "wof:name":"Dreamscapes Landscape & Maint",
    "wof:placetype":"venue"
},
  "geometry": {"coordinates":[-122.815634,42.266234],"type":"Point"}
}