{
  "type": "Feature",
  "properties": {
    "addr:full":"428 Coral Cir Phoenix OR 97535",
    "addr:housenumber":"428",
    "addr:postcode":"97535",
    "addr:street":"Coral Cir",
    "iso:country":"US",
    "sg:address":"428 Coral Cir",
    "sg:city":"Phoenix",
    "sg:classifiers":[
        {
            "category":"Recreation",
            "type":"Entertainment"
        }
    ],
    "sg:phone":"+1 541 535 4918",
    "sg:postcode":"97535",
    "sg:province":"OR",
    "sg:tags":[
        "promoter",
        "tours-operators"
    ],
    "wof:name":"Dale's Guide Service",
    "wof:placetype":"venue"
},
  "geometry": {"coordinates":[-122.82523999999999,42.27062],"type":"Point"}
}