{
  "type": "Feature",
  "properties": {
    "addr:full":"95 Foothills Road Lake Oswego OR 97034",
    "addr:housenumber":"95",
    "addr:postcode":"97034",
    "addr:street":"Foothills Road",
    "iso:country":"US",
    "sg:address":"95 Foothills Road",
    "sg:city":"Lake Oswego",
    "sg:classifiers":[
        {
            "category":"Personal",
            "type":"Services"
        }
    ],
    "sg:phone":"+1 503 293 0555",
    "sg:postcode":"97034",
    "sg:province":"OR",
    "sg:tags":[
        "home"
    ],
    "sg:website":"www.omnigaragedoor.com",
    "wof:name":"Omni Garage Door",
    "wof:placetype":"venue"
},
  "geometry": {"coordinates":[-122.661109,45.420414],"type":"Point"}
}