{
  "type": "Feature",
  "properties": {
    "addr:full":"2442 SE Belmont St Portland OR 97214",
    "addr:housenumber":"2442",
    "addr:postcode":"97214",
    "addr:street":"Se Belmont St",
    "iso:country":"US",
    "sg:address":"2442 SE Belmont St",
    "sg:city":"Portland",
    "sg:classifiers":[
        {
            "category":"Organizations",
            "subcategory":"Membership Organization",
            "type":"Services"
        }
    ],
    "sg:phone":"+1 503 233 8490",
    "sg:postcode":"97214",
    "sg:province":"OR",
    "wof:name":"Working America Aflcio",
    "wof:placetype":"venue"
},
  "geometry": {"coordinates":[-122.64132499999999,45.516375],"type":"Point"}
}