{
  "type": "Feature",
  "properties": {
    "iso:country":"US",
    "sg:address":"1455 Tucker Rd",
    "sg:city":"Hood River",
    "sg:classifiers":[
        {
            "category":"Organizations",
            "subcategory":"Non-profit Organization",
            "type":"Services"
        }
    ],
    "sg:phone":"+1 541 386 1050",
    "sg:postcode":"97031",
    "sg:province":"OR",
    "sg:tags":[
        "alternative",
        "abortion"
    ],
    "wof:name":"Columbia Gorge Pregnancy Rsrce",
    "wof:placetype":"venue"
},
  "geometry": {"coordinates":[-121.534682,45.678616],"type":"Point"}
}