{
  "type": "Feature",
  "properties": {
    "iso:country":"US",
    "sg:address":"409 Union Ave",
    "sg:city":"Grants Pass",
    "sg:classifiers":[
        {
            "category":"Building & Trades",
            "subcategory":"Construction",
            "type":"Services"
        }
    ],
    "sg:phone":"+1 541 955 8885",
    "sg:postcode":"97527",
    "sg:province":"OR",
    "sg:tags":[
        "finish",
        "carpentry"
    ],
    "wof:name":"Grant Pearl Custom Cabinets",
    "wof:placetype":"venue"
},
  "geometry": {"coordinates":[-123.340485,42.422329],"type":"Point"}
}