{
  "type": "Feature",
  "properties": {
    "iso:country":"US",
    "sg:address":"363 Monitor Rd",
    "sg:city":"Silverton",
    "sg:classifiers":[
        {
            "category":"Recreation",
            "type":"Entertainment"
        }
    ],
    "sg:phone":"+1 503 873 3522",
    "sg:postcode":"97381",
    "sg:province":"OR",
    "sg:tags":[
        "club",
        "membership"
    ],
    "wof:name":"Emerald Cat Club",
    "wof:placetype":"venue"
},
  "geometry": {"coordinates":[-122.768306,45.021443],"type":"Point"}
}