{
  "type": "Feature",
  "properties": {
    "iso:country":"US",
    "sg:address":"17838 Monnier Rd NE",
    "sg:city":"Hubbard",
    "sg:classifiers":[
        {
            "category":"Wholesale",
            "subcategory":"Plants",
            "type":"Manufacturing & Wholesale Goods"
        }
    ],
    "sg:phone":"+1 503 981 6746",
    "sg:postcode":"97032",
    "sg:province":"OR",
    "sg:tags":[
        "nursery",
        "tree",
        "grower"
    ],
    "wof:name":"Dieringer Nursery Company",
    "wof:placetype":"venue"
},
  "geometry": {"coordinates":[-122.777338,45.174479],"type":"Point"}
}