{
  "type": "Feature",
  "properties": {
    "iso:country":"US",
    "sg:address":"1855 W Main St",
    "sg:city":"Cottage Grove",
    "sg:classifiers":[
        {
            "category":"Real Estate",
            "subcategory":"Developer",
            "type":"Services"
        }
    ],
    "sg:phone":"+1 541 942 9350",
    "sg:postcode":"97424",
    "sg:province":"OR",
    "sg:tags":[
        "development",
        "manufactured",
        "housing",
        "retail"
    ],
    "wof:name":"Patrick Mike & Associates LLC",
    "wof:placetype":"venue"
},
  "geometry": {"coordinates":[-123.077302,43.797498],"type":"Point"}
}