{
  "type": "Feature",
  "properties": {
    "iso:country":"US",
    "sg:address":"6803 SE Foster Road",
    "sg:city":"Portland",
    "sg:classifiers":[
        {
            "category":"Home & Garden",
            "subcategory":"Furniture",
            "type":"Retail Goods"
        }
    ],
    "sg:phone":"+1 503 771 3374",
    "sg:postcode":"97206",
    "sg:province":"OR",
    "sg:tags":[
        "store"
    ],
    "wof:name":"Buck's Stove Palace",
    "wof:placetype":"venue"
},
  "geometry": {"coordinates":[-122.59339199999999,45.488364],"type":"Point"}
}