{
  "type": "Feature",
  "properties": {
    "iso:country":"US",
    "sg:address":"115 E Highland Ave",
    "sg:city":"Hermiston",
    "sg:classifiers":[
        {
            "category":"Restaurant",
            "type":"Food & Drink"
        }
    ],
    "sg:phone":"+1 541 564 2704",
    "sg:postcode":"97838",
    "sg:province":"OR",
    "sg:tags":[
        "parlor",
        "ice",
        "cream"
    ],
    "wof:name":"Trina's Ice Cream Parlor",
    "wof:placetype":"venue"
},
  "geometry": {"coordinates":[-119.29010599999999,45.835131],"type":"Point"}
}