{
  "type": "Feature",
  "properties": {
    "iso:country":"US",
    "sg:address":"19155 Arbor Grove Rd NE",
    "sg:city":"Woodburn",
    "sg:classifiers":[
        {
            "category":"Farming",
            "subcategory":"Farm & Veterinary Services",
            "type":"Manufacturing & Wholesale Goods"
        }
    ],
    "sg:phone":"+1 503 678 2031",
    "sg:postcode":"97071",
    "sg:province":"OR",
    "sg:tags":[
        "preparation",
        "crop",
        "for",
        "market"
    ],
    "wof:name":"Sonnen Farms",
    "wof:placetype":"venue"
},
  "geometry": {"coordinates":[-122.89538,45.194089],"type":"Point"}
}