{
  "type": "Feature",
  "properties": {
    "addr:full":"1215 Main St Klamath Falls OR 97601",
    "addr:housenumber":"1215",
    "addr:postcode":"97601",
    "addr:street":"Main St",
    "iso:country":"US",
    "sg:address":"1215 Main St",
    "sg:city":"Klamath Falls",
    "sg:classifiers":[
        {
            "category":"Shopping",
            "type":"Retail Goods"
        },
        {
            "category":"Building & Trades",
            "subcategory":"Construction",
            "type":"Services"
        }
    ],
    "sg:phone":"+1 541 273 3452",
    "sg:postcode":"97601",
    "sg:province":"OR",
    "sg:tags":[
        "pond",
        "merchandise",
        "supply"
    ],
    "wof:name":"Fish Ponds & More",
    "wof:placetype":"venue"
},
  "geometry": {"coordinates":[-121.777676,42.228359],"type":"Point"}
}