{
  "type": "Feature",
  "properties": {
    "addr:full":"10101 SW Barbur Blvd # 205 Portland OR 97219",
    "addr:housenumber":"10101",
    "addr:postcode":"97219",
    "addr:street":"Sw Barbur Blvd # 205",
    "iso:country":"US",
    "sg:address":"10101 SW Barbur Blvd # 205",
    "sg:city":"Portland",
    "sg:classifiers":[
        {
            "category":"Professional",
            "subcategory":"Lawyer & Legal Services",
            "type":"Services"
        }
    ],
    "sg:phone":"+1 503 768 3900",
    "sg:postcode":"97219",
    "sg:province":"OR",
    "sg:tags":[
        "plan"
    ],
    "wof:name":"We The People Mid Atlantic Inc",
    "wof:placetype":"venue"
},
  "geometry": {"coordinates":[-122.723561,45.452604],"type":"Point"}
}