{
  "type": "Feature",
  "properties": {
    "iso:country":"US",
    "sg:address":"5235 SW Macadam Ave",
    "sg:city":"Portland",
    "sg:classifiers":[
        {
            "category":"Autos & Motor Vehicles",
            "subcategory":"Fuel & Gas Station",
            "type":"Retail Goods"
        }
    ],
    "sg:phone":"+1 503 223 8226",
    "sg:postcode":"97219",
    "sg:province":"OR",
    "sg:tags":[
        "oil"
    ],
    "wof:name":"Chevron Jackpot Food Mart",
    "wof:placetype":"venue"
},
  "geometry": {"coordinates":[-122.67539600000001,45.485569],"type":"Point"}
}