{
  "type": "Feature",
  "properties": {
    "addr:full":"17450 Boones Ferry Rd Lake Oswego OR 97035",
    "addr:housenumber":"17450",
    "addr:postcode":"97035",
    "addr:street":"Boones Ferry Rd",
    "iso:country":"US",
    "sg:address":"17450 Boones Ferry Rd",
    "sg:city":"Lake Oswego",
    "sg:classifiers":[
        {
            "category":"Bakery",
            "type":"Food & Drink"
        }
    ],
    "sg:phone":"+1 503 635 3796",
    "sg:postcode":"97035",
    "sg:province":"OR",
    "wof:name":"Entenmann's Oroweat Foods Company",
    "wof:placetype":"venue"
},
  "geometry": {"coordinates":[-122.738998,45.3992],"type":"Point"}
}