{
  "type": "Feature",
  "properties": {
    "iso:country":"US",
    "sg:address":"885 Railroad St",
    "sg:city":"Brookings",
    "sg:classifiers":[
        {
            "category":"Manufacturing",
            "subcategory":"Building Materials",
            "type":"Manufacturing & Wholesale Goods"
        }
    ],
    "sg:phone":"+1 541 469 2127",
    "sg:postcode":"97415",
    "sg:province":"OR",
    "sg:tags":[
        "plywood",
        "veneer"
    ],
    "sg:website":"www.socomi.com",
    "wof:name":"Pacific Wood Laminates",
    "wof:placetype":"venue"
},
  "geometry": {"coordinates":[-124.290733,42.052663],"type":"Point"}
}