{
  "type": "Feature",
  "properties": {
    "iso:country":"US",
    "sg:address":"21580 E Evans Creek Rd",
    "sg:city":"White City",
    "sg:classifiers":[
        {
            "category":"Health Services",
            "subcategory":"Medical Lab",
            "type":"Services"
        }
    ],
    "sg:phone":"+1 541 826 7547",
    "sg:postcode":"97503",
    "sg:province":"OR",
    "sg:tags":[
        "laboratory",
        "dental"
    ],
    "wof:name":"Gayle's Dental Lab",
    "wof:placetype":"venue"
},
  "geometry": {"coordinates":[-122.94848,42.622024],"type":"Point"}
}