{
  "type": "Feature",
  "properties": {
    "iso:country":"US",
    "sg:address":"33578 Bennett Rd",
    "sg:city":"Warren",
    "sg:classifiers":[
        {
            "category":"Professional",
            "subcategory":"Business Services",
            "type":"Services"
        }
    ],
    "sg:phone":"+1 503 397 5789",
    "sg:postcode":"97053",
    "sg:province":"OR",
    "wof:name":"Don West Enterprises",
    "wof:placetype":"venue"
},
  "geometry": {"coordinates":[-122.872945,45.833712],"type":"Point"}
}