{
  "type": "Feature",
  "properties": {
    "addr:full":"19518 Bridgeport Ln Bridgeport OR 97819",
    "addr:housenumber":"19518",
    "addr:postcode":"97819",
    "addr:street":"Bridgeport Ln",
    "iso:country":"US",
    "sg:address":"19518 Bridgeport Ln",
    "sg:city":"Bridgeport",
    "sg:classifiers":[
        {
            "category":"Travel",
            "subcategory":"Hotels & Motels",
            "type":"Entertainment"
        }
    ],
    "sg:phone":"+1 541 446 3468",
    "sg:postcode":"97819",
    "sg:province":"OR",
    "sg:tags":[
        "breakfast",
        "accommodation",
        "bed"
    ],
    "wof:name":"Bruno Ranch Bed & Breakfast",
    "wof:placetype":"venue"
},
  "geometry": {"coordinates":[-117.84128800000001,44.499992],"type":"Point"}
}