{
  "type": "Feature",
  "properties": {
    "iso:country":"US",
    "sg:address":"1420 Dillon Rd",
    "sg:city":"Hood River",
    "sg:classifiers":[
        {
            "category":"Autos & Motor Vehicles",
            "subcategory":"Fuel & Gas Station",
            "type":"Retail Goods"
        }
    ],
    "sg:phone":"+1 541 386 9099",
    "sg:postcode":"97031",
    "sg:province":"OR",
    "sg:tags":[
        "station",
        "gasoline"
    ],
    "wof:name":"Devin Hobbs Inc",
    "wof:placetype":"venue"
},
  "geometry": {"coordinates":[-121.53565500000001,45.680009],"type":"Point"}
}