{
  "type": "Feature",
  "properties": {
    "iso:country":"US",
    "sg:address":"400 Country Club Rd",
    "sg:city":"Eugene",
    "sg:classifiers":[
        {
            "category":"Banks & Credit Unions",
            "subcategory":"Investment Brokerage",
            "type":"Services"
        }
    ],
    "sg:phone":"+1 541 683 3737",
    "sg:postcode":"97401",
    "sg:province":"OR",
    "sg:tags":[
        "stock",
        "bond"
    ],
    "sg:website":"www.morganstanley.com",
    "wof:name":"Morgan Stanley",
    "wof:placetype":"venue"
},
  "geometry": {"coordinates":[-123.091317,44.06394],"type":"Point"}
}