{
  "type": "Feature",
  "properties": {
    "addr:full":"2283 NW Troost St Roseburg OR 97470",
    "addr:housenumber":"2283",
    "addr:postcode":"97470",
    "addr:street":"Nw Troost St",
    "iso:country":"US",
    "sg:address":"2283 NW Troost St",
    "sg:city":"Roseburg",
    "sg:classifiers":[
        {
            "category":"Health Services",
            "subcategory":"Health Practitioner",
            "type":"Services"
        }
    ],
    "sg:phone":"+1 541 672 4798",
    "sg:postcode":"97470",
    "sg:province":"OR",
    "sg:tags":[
        "nurse"
    ],
    "wof:name":"Aimee Hansen",
    "wof:placetype":"venue"
},
  "geometry": {"coordinates":[-123.38507,43.234591],"type":"Point"}
}