{
  "type": "Feature",
  "properties": {
    "addr:full":"1755 13th St SE Salem OR 97302",
    "addr:housenumber":"1755",
    "addr:postcode":"97302",
    "addr:street":"13Th St Se",
    "iso:country":"US",
    "sg:address":"1755 13th St SE",
    "sg:city":"Salem",
    "sg:classifiers":[
        {
            "category":"Social Services",
            "type":"Services"
        }
    ],
    "sg:phone":"+1 503 364 9936",
    "sg:postcode":"97302",
    "sg:province":"OR",
    "sg:tags":[
        "organization",
        "welfare"
    ],
    "wof:name":"Helping Hands",
    "wof:placetype":"venue"
},
  "geometry": {"coordinates":[-123.029341,44.921098],"type":"Point"}
}