{
  "type": "Feature",
  "properties": {
    "addr:full":"4524 SE 78th Ave Portland OR 97206",
    "addr:housenumber":"4524",
    "addr:postcode":"97206",
    "addr:street":"Se 78Th Ave",
    "iso:country":"US",
    "sg:address":"4524 SE 78th Ave",
    "sg:city":"Portland",
    "sg:classifiers":[
        {
            "category":"Professional",
            "type":"Services"
        }
    ],
    "sg:phone":"+1 503 772 8135",
    "sg:postcode":"97206",
    "sg:province":"OR",
    "wof:name":"Hewlett Packard-Mark Hunter",
    "wof:placetype":"venue"
},
  "geometry": {"coordinates":[-122.58327199999999,45.488945],"type":"Point"}
}