{
  "type": "Feature",
  "properties": {
    "addr:full":"15110 Boones Ferry Rd Lake Oswego OR 97035",
    "addr:housenumber":"15110",
    "addr:postcode":"97035",
    "addr:street":"Boones Ferry Rd",
    "iso:country":"US",
    "sg:address":"15110 Boones Ferry Rd",
    "sg:city":"Lake Oswego",
    "sg:classifiers":[
        {
            "category":"Social Services",
            "type":"Services"
        }
    ],
    "sg:phone":"+1 503 675 0932",
    "sg:postcode":"97035",
    "sg:province":"OR",
    "wof:name":"Caryn L Aman",
    "wof:placetype":"venue"
},
  "geometry": {"coordinates":[-122.715807,45.415763],"type":"Point"}
}