{
  "type": "Feature",
  "properties": {
    "iso:country":"US",
    "sg:address":"18674 SW Boones Ferry Rd",
    "sg:city":"Tualatin",
    "sg:classifiers":[
        {
            "category":"Restaurant",
            "type":"Food & Drink"
        }
    ],
    "sg:phone":"+1 503 885 9513",
    "sg:postcode":"97062",
    "sg:province":"OR",
    "sg:tags":[
        "eating"
    ],
    "wof:name":"Thai Spices Restaurant",
    "wof:placetype":"venue"
},
  "geometry": {"coordinates":[-122.760024,45.384541],"type":"Point"}
}