{
  "type": "Feature",
  "properties": {
    "addr:full":"777 SE Washington St Portland OR 97214",
    "addr:housenumber":"777",
    "addr:postcode":"97214",
    "addr:street":"Se Washington St",
    "iso:country":"US",
    "sg:address":"777 SE Washington St",
    "sg:city":"Portland",
    "sg:classifiers":[
        {
            "category":"Autos & Motor Vehicles",
            "subcategory":"Automobile Sales",
            "type":"Retail Goods"
        }
    ],
    "sg:phone":"+1 503 236 6989",
    "sg:postcode":"97214",
    "sg:province":"OR",
    "sg:tags":[
        "transporter",
        "used"
    ],
    "sg:website":"http://www.h-hautosales.com",
    "wof:name":"H-H Auto Transport",
    "wof:placetype":"venue"
},
  "geometry": {"coordinates":[-122.65789100000001,45.518637],"type":"Point"}
}