{
  "type": "Feature",
  "properties": {
    "addr:full":"707 SE 82nd Ave Portland OR 97216",
    "addr:housenumber":"707",
    "addr:postcode":"97216",
    "addr:street":"Se 82Nd Ave",
    "iso:country":"US",
    "sg:address":"707 SE 82nd Ave",
    "sg:city":"Portland",
    "sg:classifiers":[
        {
            "category":"Retail",
            "subcategory":"Auto Repair",
            "type":"Services"
        }
    ],
    "sg:phone":"+1 503 253 5054",
    "sg:postcode":"97216",
    "sg:province":"OR",
    "sg:tags":[
        "repairing",
        "automobile"
    ],
    "wof:name":"Mitchell's Automotive",
    "wof:placetype":"venue"
},
  "geometry": {"coordinates":[-122.579019,45.516953],"type":"Point"}
}