{
  "type": "Feature",
  "properties": {
    "addr:full":"4036 NE Hassalo St Portland OR 97232",
    "addr:housenumber":"4036",
    "addr:postcode":"97232",
    "addr:street":"Ne Hassalo St",
    "iso:country":"US",
    "sg:address":"4036 NE Hassalo St",
    "sg:city":"Portland",
    "sg:classifiers":[
        {
            "category":"Manufacturing",
            "subcategory":"Tools & Machinery",
            "type":"Manufacturing & Wholesale Goods"
        }
    ],
    "sg:phone":"+1 503 460 3027",
    "sg:postcode":"97232",
    "sg:province":"OR",
    "sg:tags":[
        "cutting",
        "gear"
    ],
    "wof:name":"Mo-Go Gear.",
    "wof:placetype":"venue"
},
  "geometry": {"coordinates":[-122.621365,45.530818],"type":"Point"}
}