{
  "type": "Feature",
  "properties": {
    "iso:country":"US",
    "sg:address":"17807 SE Kelly St",
    "sg:city":"Portland",
    "sg:classifiers":[
        {
            "category":"Building & Trades",
            "subcategory":"Construction",
            "type":"Services"
        }
    ],
    "sg:phone":"+1 503 762 2519",
    "sg:postcode":"97236",
    "sg:province":"OR",
    "sg:tags":[
        "carpentry",
        "contractor"
    ],
    "wof:name":"Rich Goetz",
    "wof:placetype":"venue"
},
  "geometry": {"coordinates":[-122.478531,45.499992],"type":"Point"}
}