{
  "type": "Feature",
  "properties": {
    "addr:full":"580 Matthews Dr Myrtle Creek OR 97457",
    "addr:housenumber":"580",
    "addr:postcode":"97457",
    "addr:street":"Matthews Dr",
    "iso:country":"US",
    "sg:address":"580 Matthews Dr",
    "sg:city":"Myrtle Creek",
    "sg:classifiers":[
        {
            "category":"Professional",
            "type":"Services"
        }
    ],
    "sg:phone":"+1 541 863 7908",
    "sg:postcode":"97457",
    "sg:province":"OR",
    "wof:name":"Richs Rods & Relics",
    "wof:placetype":"venue"
},
  "geometry": {"coordinates":[-123.333831,42.97104],"type":"Point"}
}