{
  "type": "Feature",
  "properties": {
    "iso:country":"US",
    "sg:address":"41846 Madrone St",
    "sg:city":"Springfield",
    "sg:classifiers":[
        {
            "category":"Building & Trades",
            "subcategory":"Construction",
            "type":"Services"
        }
    ],
    "sg:phone":"+1 541 896 3006",
    "sg:postcode":"97478",
    "sg:province":"OR",
    "sg:tags":[
        "house"
    ],
    "wof:name":"Tall Tree Construction",
    "wof:placetype":"venue"
},
  "geometry": {"coordinates":[-122.716267,44.088195],"type":"Point"}
}