{
  "type": "Feature",
  "properties": {
    "addr:full":"12205 SW Summer Crest Dr Portland OR 97223",
    "addr:housenumber":"12205",
    "addr:postcode":"97223",
    "addr:street":"Sw Summer Crest Dr",
    "iso:country":"US",
    "sg:address":"12205 SW Summer Crest Dr",
    "sg:city":"Portland",
    "sg:classifiers":[
        {
            "category":"Real Estate",
            "subcategory":"Real Estate Services",
            "type":"Services"
        },
        {
            "category":"Building & Trades",
            "subcategory":"Cleaning & Sanitation",
            "type":"Services"
        }
    ],
    "sg:phone":"+1 503 524 8379",
    "sg:postcode":"97223",
    "sg:province":"OR",
    "sg:tags":[
        "maintenance",
        "cleaners-interior"
    ],
    "wof:name":"Home Maintenance Specialists",
    "wof:placetype":"venue"
},
  "geometry": {"coordinates":[-122.802474,45.436383],"type":"Point"}
}