{
  "type": "Feature",
  "properties": {
    "addr:full":"45 Eagle Crest Dr Lake Oswego OR 97035",
    "addr:housenumber":"45",
    "addr:postcode":"97035",
    "addr:street":"Eagle Crest Dr",
    "iso:country":"US",
    "sg:address":"45 Eagle Crest Dr",
    "sg:city":"Lake Oswego",
    "sg:classifiers":[
        {
            "category":"Real Estate",
            "subcategory":"Real Estate Operator",
            "type":"Services"
        }
    ],
    "sg:phone":"+1 503 636 4242",
    "sg:postcode":"97035",
    "sg:province":"OR",
    "sg:tags":[
        "building",
        "apartment",
        "condominium"
    ],
    "wof:name":"Eaglecrest Condominiums",
    "wof:placetype":"venue"
},
  "geometry": {"coordinates":[-122.70850799999999,45.435744],"type":"Point"}
}