{
  "type": "Feature",
  "properties": {
    "iso:country":"US",
    "sg:address":"3749 NW Poehler Ter",
    "sg:city":"Portland",
    "sg:classifiers":[
        {
            "category":"Banks & Credit Unions",
            "subcategory":"Bank",
            "type":"Services"
        }
    ],
    "sg:phone":"+1 503 645 2404",
    "sg:postcode":"97229",
    "sg:province":"OR",
    "sg:tags":[
        "short",
        "institution",
        "business"
    ],
    "wof:name":"Four Star Funding",
    "wof:placetype":"venue"
},
  "geometry": {"coordinates":[-122.857969,45.546274],"type":"Point"}
}