{
  "type": "Feature",
  "properties": {
    "iso:country":"US",
    "sg:address":"1125 NW 16th Avenue",
    "sg:city":"Portland",
    "sg:classifiers":[
        {
            "category":"Professional",
            "subcategory":"Art Services",
            "type":"Services"
        },
        {
            "category":"Professional",
            "subcategory":"Printing & Photocopies",
            "type":"Services"
        },
        {
            "category":"Communications",
            "type":"Services"
        }
    ],
    "sg:phone":"+1 503 922 3032",
    "sg:postcode":"97209",
    "sg:province":"OR",
    "sg:tags":[
        "web",
        "graphic",
        "design"
    ],
    "sg:website":"www.localbizsolutions.net",
    "wof:name":"Local Biz Solutions",
    "wof:placetype":"venue"
},
  "geometry": {"coordinates":[-122.687512,45.531279],"type":"Point"}
}