{
  "type": "Feature",
  "properties": {
    "iso:country":"US",
    "sg:address":"1260 W 6th St",
    "sg:city":"The Dalles",
    "sg:classifiers":[
        {
            "category":"Shopping",
            "subcategory":"Discount & Variety Stores",
            "type":"Retail Goods"
        }
    ],
    "sg:phone":"+1 541 296 3232",
    "sg:postcode":"97058",
    "sg:province":"OR",
    "wof:name":"Dollar Tree",
    "wof:placetype":"venue"
},
  "geometry": {"coordinates":[-121.201449,45.606805],"type":"Point"}
}