{
  "type": "Feature",
  "properties": {
    "addr:full":"35066 Ede Rd Lebanon OR 97355",
    "addr:postcode":"35066;97355",
    "addr:street":"Ede Rd",
    "iso:country":"US",
    "sg:address":"35066 Ede Rd",
    "sg:city":"Lebanon",
    "sg:classifiers":[
        {
            "category":"Farming",
            "subcategory":"Livestock Farm",
            "type":"Manufacturing & Wholesale Goods"
        }
    ],
    "sg:phone":"+1 541 451 1786",
    "sg:postcode":"97355",
    "sg:province":"OR",
    "sg:tags":[
        "ranch"
    ],
    "wof:name":"Dancing Feather Ranch",
    "wof:placetype":"venue"
},
  "geometry": {"coordinates":[-122.760434,44.606289],"type":"Point"}
}