{
  "type": "Feature",
  "properties": {
    "iso:country":"US",
    "sg:address":"8800 SW Brabham Way",
    "sg:city":"Gaston",
    "sg:classifiers":[
        {
            "category":"Manufacturing",
            "subcategory":"Tools & Machinery",
            "type":"Manufacturing & Wholesale Goods"
        }
    ],
    "sg:phone":"+1 503 645 6217",
    "sg:postcode":"97119",
    "sg:province":"OR",
    "sg:tags":[
        "machine",
        "mfg"
    ],
    "wof:name":"Versamil Inc",
    "wof:placetype":"venue"
},
  "geometry": {"coordinates":[-123.10211,45.458218],"type":"Point"}
}