{
  "type": "Feature",
  "properties": {
    "iso:country":"US",
    "sg:address":"2850 SE 82nd Ave",
    "sg:city":"Portland",
    "sg:classifiers":[
        {
            "category":"Shopping",
            "subcategory":"Mobile Phones",
            "type":"Retail Goods"
        }
    ],
    "sg:phone":"+1 503 774 4964",
    "sg:postcode":"97266",
    "sg:province":"OR",
    "wof:name":"Activate Cellular",
    "wof:placetype":"venue"
},
  "geometry": {"coordinates":[-122.578474,45.5019],"type":"Point"}
}