{
  "type": "Feature",
  "properties": {
    "iso:country":"US",
    "sg:address":"7008 N Interstate Ave",
    "sg:city":"Portland",
    "sg:classifiers":[
        {
            "category":"Restaurant",
            "type":"Food & Drink"
        }
    ],
    "sg:phone":"+1 503 735 3741",
    "sg:postcode":"97217",
    "sg:province":"OR",
    "sg:tags":[
        "mexican"
    ],
    "wof:name":"Michoacan",
    "wof:placetype":"venue"
},
  "geometry": {"coordinates":[-122.681819,45.57409],"type":"Point"}
}