{
  "type": "Feature",
  "properties": {
    "addr:full":"201 SE 4th St Enterprise OR 97828",
    "addr:housenumber":"201",
    "addr:postcode":"97828",
    "addr:street":"Se 4Th St",
    "iso:country":"US",
    "sg:address":"201 SE 4th St",
    "sg:city":"Enterprise",
    "sg:classifiers":[
        {
            "category":"Education",
            "subcategory":"School",
            "type":"Public Place"
        }
    ],
    "sg:phone":"+1 541 426 3193",
    "sg:postcode":"97828",
    "sg:province":"OR",
    "sg:tags":[
        "high",
        "district"
    ],
    "sg:website":"http://www.enterprisehighschool.com",
    "wof:name":"Enterprise High School",
    "wof:placetype":"venue"
},
  "geometry": {"coordinates":[-117.272507,45.424568],"type":"Point"}
}