{
  "type": "Feature",
  "properties": {
    "iso:country":"US",
    "sg:address":"325 S 3rd St",
    "sg:city":"Harrisburg",
    "sg:classifiers":[
        {
            "category":"Food & Beverages",
            "subcategory":"Groceries & Convenience Stores",
            "type":"Retail Goods"
        }
    ],
    "sg:phone":"+1 541 995 8375",
    "sg:postcode":"97446",
    "sg:province":"OR",
    "wof:name":"Dari Mart",
    "wof:placetype":"venue"
},
  "geometry": {"coordinates":[-123.170863,44.270615],"type":"Point"}
}