{
  "type": "Feature",
  "properties": {
    "iso:country":"US",
    "sg:address":"621 SW Evergreen Ave",
    "sg:city":"Redmond",
    "sg:classifiers":[
        {
            "category":"Personal",
            "subcategory":"Beauty Salon",
            "type":"Services"
        }
    ],
    "sg:phone":"+1 541 504 7760",
    "sg:postcode":"97756",
    "sg:province":"OR",
    "wof:name":"Axis Salon",
    "wof:placetype":"venue"
},
  "geometry": {"coordinates":[-121.174508,44.272578],"type":"Point"}
}