{
  "type": "Feature",
  "properties": {
    "addr:full":"11858 NE Halsey St Portland OR 97220",
    "addr:housenumber":"11858",
    "addr:postcode":"97220",
    "addr:street":"Ne Halsey St",
    "iso:country":"US",
    "sg:address":"11858 NE Halsey St",
    "sg:city":"Portland",
    "sg:classifiers":[
        {
            "category":"Professional",
            "type":"Services"
        }
    ],
    "sg:phone":"+1 503 762 2693",
    "sg:postcode":"97220",
    "sg:province":"OR",
    "sg:tags":[
        "establishment"
    ],
    "wof:name":"Moscow Lights",
    "wof:placetype":"venue"
},
  "geometry": {"coordinates":[-122.540858,45.533466],"type":"Point"}
}