{
  "type": "Feature",
  "properties": {
    "iso:country":"US",
    "sg:address":"3200 SE Midvale Dr",
    "sg:city":"Corvallis",
    "sg:classifiers":[
        {
            "category":"Shopping",
            "type":"Retail Goods"
        }
    ],
    "sg:phone":"+1 541 753 7886",
    "sg:postcode":"97333",
    "sg:province":"OR",
    "sg:tags":[
        "art",
        "gallery",
        "dealer"
    ],
    "wof:name":"Art By Georgia Lawson",
    "wof:placetype":"venue"
},
  "geometry": {"coordinates":[-123.256978,44.53085],"type":"Point"}
}