{
  "type": "Feature",
  "properties": {
    "iso:country":"US",
    "sg:address":"11202 SW North Dakota St",
    "sg:city":"Portland",
    "sg:classifiers":[
        {
            "category":"Building & Trades",
            "subcategory":"Construction",
            "type":"Services"
        }
    ],
    "sg:phone":"+1 503 968 3002",
    "sg:postcode":"97223",
    "sg:province":"OR",
    "sg:tags":[
        "siding",
        "contractor"
    ],
    "wof:name":"Cdl Services",
    "wof:placetype":"venue"
},
  "geometry": {"coordinates":[-122.792175,45.439041],"type":"Point"}
}