{
  "type": "Feature",
  "properties": {
    "addr:full":"5723 Main St Springfield OR 97478",
    "addr:housenumber":"5723",
    "addr:postcode":"97478",
    "addr:street":"Main St",
    "iso:country":"US",
    "sg:address":"5723 Main St",
    "sg:city":"Springfield",
    "sg:classifiers":[
        {
            "category":"Personal",
            "subcategory":"Nail Salon",
            "type":"Services"
        }
    ],
    "sg:phone":"+1 541 746 6615",
    "sg:postcode":"97478",
    "sg:province":"OR",
    "wof:name":"New Perfect Nails",
    "wof:placetype":"venue"
},
  "geometry": {"coordinates":[-122.928017,44.045689],"type":"Point"}
}