{
  "type": "Feature",
  "properties": {
    "iso:country":"US",
    "sg:address":"9555 Trask River Rd",
    "sg:city":"Tillamook",
    "sg:classifiers":[
        {
            "category":"Farming",
            "subcategory":"Dairy Farm",
            "type":"Manufacturing & Wholesale Goods"
        }
    ],
    "sg:phone":"+1 503 842 2843",
    "sg:postcode":"97141",
    "sg:province":"OR",
    "wof:name":"Jeff Adams Dairy Farm",
    "wof:placetype":"venue"
},
  "geometry": {"coordinates":[-123.765804,45.44206],"type":"Point"}
}