{
  "type": "Feature",
  "properties": {
    "iso:country":"US",
    "sg:address":"1407 Trevitt St",
    "sg:city":"The Dalles",
    "sg:classifiers":[
        {
            "category":"Retail",
            "subcategory":"Repair Shop",
            "type":"Services"
        }
    ],
    "sg:phone":"+1 541 296 4439",
    "sg:postcode":"97058",
    "sg:province":"OR",
    "sg:tags":[
        "related"
    ],
    "wof:name":"Pro Line Lawn & Garden",
    "wof:placetype":"venue"
},
  "geometry": {"coordinates":[-121.196772,45.598129],"type":"Point"}
}