{
  "type": "Feature",
  "properties": {
    "addr:full":"985 Oakway Dr Coos Bay OR 97420",
    "addr:housenumber":"985",
    "addr:postcode":"97420",
    "addr:street":"Oakway Dr",
    "iso:country":"US",
    "sg:address":"985 Oakway Dr",
    "sg:city":"Coos Bay",
    "sg:classifiers":[
        {
            "category":"Manufacturing",
            "subcategory":"Lumber",
            "type":"Manufacturing & Wholesale Goods"
        }
    ],
    "sg:phone":"+1 541 267 4217",
    "sg:postcode":"97420",
    "sg:province":"OR",
    "sg:tags":[
        "construction",
        "logging",
        "road",
        "contractor"
    ],
    "wof:name":"Mc Carthy Brothers Inc",
    "wof:placetype":"venue"
},
  "geometry": {"coordinates":[-124.23265600000001,43.373552],"type":"Point"}
}