{
  "type": "Feature",
  "properties": {
    "iso:country":"US",
    "sg:address":"2175 NW Davis St",
    "sg:city":"Portland",
    "sg:classifiers":[
        {
            "category":"Professional",
            "subcategory":"Business Services",
            "type":"Services"
        }
    ],
    "sg:phone":"+1 503 274 9515",
    "sg:postcode":"97210",
    "sg:province":"OR",
    "wof:name":"Iverson Group",
    "wof:placetype":"venue"
},
  "geometry": {"coordinates":[-122.696033,45.524207],"type":"Point"}
}