{
  "type": "Feature",
  "properties": {
    "iso:country":"US",
    "sg:address":"1535 SW 17th Ave",
    "sg:city":"Portland",
    "sg:classifiers":[
        {
            "category":"Shopping",
            "subcategory":"Bicycles & Sporting Goods",
            "type":"Retail Goods"
        }
    ],
    "sg:phone":"+1 503 224 1215",
    "sg:postcode":"97201",
    "sg:province":"OR",
    "wof:name":"Strawberry Bike Shop",
    "wof:placetype":"venue"
},
  "geometry": {"coordinates":[-122.692345,45.516161],"type":"Point"}
}