{
  "type": "Feature",
  "properties": {
    "addr:full":"9352 SW Tonopah Ct Tualatin OR 97062",
    "addr:housenumber":"9352",
    "addr:postcode":"97062",
    "addr:street":"Sw Tonopah Ct",
    "iso:country":"US",
    "sg:address":"9352 SW Tonopah Ct",
    "sg:city":"Tualatin",
    "sg:classifiers":[
        {
            "category":"Retail",
            "subcategory":"Repair Shop",
            "type":"Services"
        }
    ],
    "sg:phone":"+1 503 692 2884",
    "sg:postcode":"97062",
    "sg:province":"OR",
    "wof:name":"M & M Distributors",
    "wof:placetype":"venue"
},
  "geometry": {"coordinates":[-122.77387,45.373367],"type":"Point"}
}