{
  "type": "Feature",
  "properties": {
    "addr:full":"2500 Foothill Blvd Grants Pass OR 97526",
    "addr:housenumber":"2500",
    "addr:postcode":"97526",
    "addr:street":"Foothill Blvd",
    "iso:country":"US",
    "sg:address":"2500 Foothill Blvd",
    "sg:city":"Grants Pass",
    "sg:phone":"+1 541 476 7731",
    "sg:postcode":"97526",
    "sg:province":"OR",
    "sg:tags":[
        "oil"
    ],
    "wof:name":"Mayfield Oil Co",
    "wof:placetype":"venue"
},
  "geometry": {"coordinates":[-123.286085,42.438134],"type":"Point"}
}