{
  "type": "Feature",
  "properties": {
    "addr:full":"858 NE Quimby Ave Bend OR 97701",
    "addr:housenumber":"858",
    "addr:postcode":"97701",
    "addr:street":"Ne Quimby Ave",
    "iso:country":"US",
    "sg:address":"858 NE Quimby Ave",
    "sg:city":"Bend",
    "sg:classifiers":[
        {
            "category":"Professional",
            "type":"Services"
        }
    ],
    "sg:phone":"+1 541 383 2342",
    "sg:postcode":"97701",
    "sg:province":"OR",
    "wof:name":"Morgan Burke Leighton",
    "wof:placetype":"venue"
},
  "geometry": {"coordinates":[-121.293156,44.066737],"type":"Point"}
}