{
  "type": "Feature",
  "properties": {
    "addr:full":"4130 Cherry Ln Medford OR 97504",
    "addr:housenumber":"4130",
    "addr:postcode":"97504",
    "addr:street":"Cherry Ln",
    "iso:country":"US",
    "sg:address":"4130 Cherry Ln",
    "sg:city":"Medford",
    "sg:classifiers":[
        {
            "category":"Professional",
            "subcategory":"Employment Agencies",
            "type":"Services"
        }
    ],
    "sg:phone":"+1 541 734 7081",
    "sg:postcode":"97504",
    "sg:province":"OR",
    "wof:name":"Search Werner Assoc",
    "wof:placetype":"venue"
},
  "geometry": {"coordinates":[-122.80110999999999,42.326697],"type":"Point"}
}