{
  "type": "Feature",
  "properties": {
    "addr:full":"25275 Vaughn Rd Veneta OR 97487",
    "addr:housenumber":"25275",
    "addr:postcode":"97487",
    "addr:street":"Vaughn Rd",
    "iso:country":"US",
    "sg:address":"25275 Vaughn Rd",
    "sg:city":"Veneta",
    "sg:classifiers":[
        {
            "category":"Retail",
            "subcategory":"Auto Repair",
            "type":"Services"
        }
    ],
    "sg:phone":"+1 541 935 7319",
    "sg:postcode":"97487",
    "sg:province":"OR",
    "sg:tags":[
        "general"
    ],
    "wof:name":"Blooms Automania",
    "wof:placetype":"venue"
},
  "geometry": {"coordinates":[-123.34130399999999,43.990631],"type":"Point"}
}