{
  "type": "Feature",
  "properties": {
    "iso:country":"US",
    "sg:address":"8705 SW Locust St",
    "sg:city":"Tigard",
    "sg:classifiers":[
        {
            "category":"Restaurant",
            "type":"Food & Drink"
        },
        {
            "category":"Food & Beverages",
            "subcategory":"Meat & Fish",
            "type":"Retail Goods"
        }
    ],
    "sg:phone":"+1 503 892 5152",
    "sg:postcode":"97223",
    "sg:province":"OR",
    "sg:tags":[
        "german",
        "shop"
    ],
    "sg:website":"www.originalbavariansausage.com",
    "wof:name":"Bavarian Sausage Delicatessen",
    "wof:placetype":"venue"
},
  "geometry": {"coordinates":[-122.766549,45.446589],"type":"Point"}
}