{
  "type": "Feature",
  "properties": {
    "addr:full":"17455 SW Farmington Rd Beaverton OR 97007",
    "addr:housenumber":"17455",
    "addr:postcode":"97007",
    "addr:street":"Sw Farmington Rd",
    "iso:country":"US",
    "sg:address":"17455 SW Farmington Rd",
    "sg:city":"Beaverton",
    "sg:classifiers":[
        {
            "category":"Real Estate",
            "subcategory":"Real Estate Agent",
            "type":"Services"
        }
    ],
    "sg:phone":"+1 503 259 2100",
    "sg:postcode":"97007",
    "sg:province":"OR",
    "wof:name":"Century 21",
    "wof:placetype":"venue"
},
  "geometry": {"coordinates":[-122.857131,45.47996],"type":"Point"}
}