{
  "type": "Feature",
  "properties": {
    "iso:country":"US",
    "sg:address":"1407 Sills Ct",
    "sg:city":"Forest Grove",
    "sg:classifiers":[
        {
            "category":"Home & Garden",
            "subcategory":"Garden Supply",
            "type":"Retail Goods"
        }
    ],
    "sg:phone":"+1 503 359 4234",
    "sg:postcode":"97116",
    "sg:province":"OR",
    "wof:name":"Steven V Gorretta Nursery",
    "wof:placetype":"venue"
},
  "geometry": {"coordinates":[-123.12186199999999,45.52934],"type":"Point"}
}