{
  "type": "Feature",
  "properties": {
    "addr:full":"3516 SW 58th Dr Portland OR 97221",
    "addr:housenumber":"3516",
    "addr:postcode":"97221",
    "addr:street":"Sw 58Th Dr",
    "iso:country":"US",
    "sg:address":"3516 SW 58th Dr",
    "sg:city":"Portland",
    "sg:classifiers":[
        {
            "category":"Health Services",
            "subcategory":"Doctor",
            "type":"Services"
        },
        {
            "category":"Health Services",
            "subcategory":"Clinic",
            "type":"Services"
        }
    ],
    "sg:phone":"+1 503 297 8727",
    "sg:postcode":"97221",
    "sg:province":"OR",
    "sg:tags":[
        "psychological",
        "psychologist"
    ],
    "wof:name":"Henry Steven L Psyd",
    "wof:placetype":"venue"
},
  "geometry": {"coordinates":[-122.73734,45.497861],"type":"Point"}
}