{
  "type": "Feature",
  "properties": {
    "iso:country":"US",
    "sg:address":"1915 SE Cesar E Chavez Blvd",
    "sg:city":"Portland",
    "sg:classifiers":[
        {
            "category":"Arts & Performance",
            "subcategory":"Dance",
            "type":"Entertainment"
        }
    ],
    "sg:phone":"+1 503 957 7899",
    "sg:postcode":"97214",
    "sg:province":"OR",
    "sg:tags":[
        "instruction",
        "dancing"
    ],
    "wof:name":"Todd Kurtzman Movement Arts",
    "wof:placetype":"venue"
},
  "geometry": {"coordinates":[-122.622775,45.50939],"type":"Point"}
}