{
  "type": "Feature",
  "properties": {
    "iso:country":"US",
    "sg:address":"1441 NE 11th St",
    "sg:city":"Lincoln City",
    "sg:classifiers":[
        {
            "category":"Building & Trades",
            "subcategory":"Construction",
            "type":"Services"
        }
    ],
    "sg:phone":"+1 541 996 4116",
    "sg:postcode":"97367",
    "sg:province":"OR",
    "sg:tags":[
        "installation",
        "maker",
        "cabinet"
    ],
    "wof:name":"Perry's Cabinets",
    "wof:placetype":"venue"
},
  "geometry": {"coordinates":[-124.013152,44.973303],"type":"Point"}
}