{
  "type": "Feature",
  "properties": {
    "addr:full":"111 N Arney Rd Woodburn OR 97071",
    "addr:housenumber":"111",
    "addr:postcode":"97071",
    "addr:street":"N Arney Rd",
    "iso:country":"US",
    "sg:address":"111 N Arney Rd",
    "sg:city":"Woodburn",
    "sg:classifiers":[
        {
            "category":"Restaurant",
            "type":"Food & Drink"
        }
    ],
    "sg:menulink":"http://www.allmenus.com/or/woodburn/116143-quiznos-sub/menu/",
    "sg:phone":"+1 503 982 4115",
    "sg:postcode":"97071",
    "sg:province":"OR",
    "sg:tags":[
        "wrap",
        "american",
        "sandwich"
    ],
    "wof:name":"Quiznos Sub",
    "wof:placetype":"venue"
},
  "geometry": {"coordinates":[-122.884078,45.152303],"type":"Point"}
}