{
  "type": "Feature",
  "properties": {
    "addr:full":"67210 Highway 20 Bend OR 97701",
    "addr:housenumber":"67210",
    "addr:postcode":"97701",
    "addr:street":"Highway 20",
    "iso:country":"US",
    "sg:address":"67210 Highway 20",
    "sg:city":"Bend",
    "sg:classifiers":[
        {
            "category":"Arts & Performance",
            "subcategory":"Dance",
            "type":"Entertainment"
        }
    ],
    "sg:phone":"+1 541 771 2508",
    "sg:postcode":"97701",
    "sg:province":"OR",
    "sg:tags":[
        "instruction",
        "dancing"
    ],
    "wof:name":"Three Sisters Dance Studio",
    "wof:placetype":"venue"
},
  "geometry": {"coordinates":[-121.48627999999999,44.249122],"type":"Point"}
}