{
  "type": "Feature",
  "properties": {
    "iso:country":"US",
    "sg:address":"19937 E Burnside St",
    "sg:city":"Portland",
    "sg:classifiers":[
        {
            "category":"Retail",
            "subcategory":"Auto Repair",
            "type":"Services"
        }
    ],
    "sg:phone":"+1 503 661 5139",
    "sg:postcode":"97233",
    "sg:province":"OR",
    "sg:tags":[
        "wheel",
        "wheels-frame",
        "servicing-automotive",
        "balancing",
        "axle",
        "wheels-aligning",
        "alignment-frame",
        "servicing-equipment"
    ],
    "sg:website":"http://www.johnsframeshop.com",
    "wof:name":"John's Frame & Alignment Shop",
    "wof:placetype":"venue"
},
  "geometry": {"coordinates":[-122.45785600000001,45.515596],"type":"Point"}
}