{
  "type": "Feature",
  "properties": {
    "iso:country":"US",
    "sg:address":"5865 Gaffin Rd SE",
    "sg:city":"Salem",
    "sg:classifiers":[
        {
            "category":"Professional",
            "subcategory":"Business Services",
            "type":"Services"
        }
    ],
    "sg:phone":"+1 503 363 6072",
    "sg:postcode":"97317",
    "sg:province":"OR",
    "sg:tags":[
        "auctioneer"
    ],
    "wof:name":"Online Auction Co",
    "wof:placetype":"venue"
},
  "geometry": {"coordinates":[-122.940883,44.9008],"type":"Point"}
}