{
  "type": "Feature",
  "properties": {
    "iso:country":"US",
    "sg:address":"4400 NE Riverside Dr",
    "sg:city":"Mcminnville",
    "sg:classifiers":[
        {
            "category":"Farming",
            "subcategory":"Farm",
            "type":"Manufacturing & Wholesale Goods"
        }
    ],
    "sg:phone":"+1 503 472 7389",
    "sg:postcode":"97128",
    "sg:province":"OR",
    "wof:name":"Jkg Farms",
    "wof:placetype":"venue"
},
  "geometry": {"coordinates":[-123.152379,45.229203],"type":"Point"}
}