{
  "type": "Feature",
  "properties": {
    "iso:country":"US",
    "sg:address":"202 Oak St",
    "sg:city":"Hood River",
    "sg:classifiers":[
        {
            "category":"Shopping",
            "subcategory":"Bicycles & Sporting Goods",
            "type":"Retail Goods"
        }
    ],
    "sg:phone":"+1 541 386 9225",
    "sg:postcode":"97031",
    "sg:province":"OR",
    "sg:tags":[
        "surfing",
        "wind"
    ],
    "wof:name":"Columbia Gorge Windsurfing",
    "wof:placetype":"venue"
},
  "geometry": {"coordinates":[-121.513291,45.708928],"type":"Point"}
}