{
  "type": "Feature",
  "properties": {
    "iso:country":"US",
    "sg:address":"25880 SE Rebman Rd",
    "sg:city":"Boring",
    "sg:classifiers":[
        {
            "category":"Farming",
            "subcategory":"Nursery",
            "type":"Manufacturing & Wholesale Goods"
        }
    ],
    "sg:phone":"+1 503 658 7088",
    "sg:postcode":"97009",
    "sg:province":"OR",
    "sg:tags":[
        "ornamental"
    ],
    "wof:name":"Vandenheed Greenhouses",
    "wof:placetype":"venue"
},
  "geometry": {"coordinates":[-122.39690299999999,45.403569],"type":"Point"}
}