{
  "type": "Feature",
  "properties": {
    "iso:country":"US",
    "sg:address":"1044 Enterprise Ave",
    "sg:city":"Nyssa",
    "sg:classifiers":[
        {
            "category":"Building & Trades",
            "subcategory":"Construction",
            "type":"Services"
        }
    ],
    "sg:phone":"+1 541 372 2610",
    "sg:postcode":"97913",
    "sg:province":"OR",
    "sg:tags":[
        "downspouts",
        "gutter"
    ],
    "wof:name":"Continuous Gutters",
    "wof:placetype":"venue"
},
  "geometry": {"coordinates":[-117.120676,43.852647],"type":"Point"}
}