{
  "type": "Feature",
  "properties": {
    "iso:country":"US",
    "sg:address":"6640 Keller Rd",
    "sg:city":"Klamath Falls",
    "sg:classifiers":[
        {
            "category":"Building & Trades",
            "subcategory":"Construction",
            "type":"Services"
        }
    ],
    "sg:phone":"+1 541 882 1209",
    "sg:postcode":"97603",
    "sg:province":"OR",
    "sg:tags":[
        "home",
        "general",
        "commercial",
        "family",
        "contractor"
    ],
    "wof:name":"Keller Construction Inc",
    "wof:placetype":"venue"
},
  "geometry": {"coordinates":[-121.708265,42.184616],"type":"Point"}
}