{
  "type": "Feature",
  "properties": {
    "addr:full":"474 Willamette St Ste 305 Eugene OR 97401",
    "addr:housenumber":"474",
    "addr:postcode":"97401",
    "addr:street":"Willamette St Ste 305",
    "iso:country":"US",
    "sg:address":"474 Willamette St Ste 305",
    "sg:city":"Eugene",
    "sg:classifiers":[
        {
            "category":"Building & Trades",
            "subcategory":"Landscaping Services",
            "type":"Services"
        }
    ],
    "sg:phone":"+1 541 683 5803",
    "sg:postcode":"97401",
    "sg:province":"OR",
    "sg:tags":[
        "consultant",
        "designer",
        "landscape"
    ],
    "sg:website":"http://www.dladesign.com",
    "wof:name":"Dougherty Landscape Archtr",
    "wof:placetype":"venue"
},
  "geometry": {"coordinates":[-123.092741,44.054402],"type":"Point"}
}