{
  "type": "Feature",
  "properties": {
    "iso:country":"US",
    "sg:address":"21585 S Lewellen Rd",
    "sg:city":"Beavercreek",
    "sg:classifiers":[
        {
            "category":"Farming",
            "subcategory":"Farm",
            "type":"Manufacturing & Wholesale Goods"
        }
    ],
    "sg:phone":"+1 503 632 6860",
    "sg:postcode":"97004",
    "sg:province":"OR",
    "sg:tags":[
        "crop",
        "general"
    ],
    "wof:name":"Burck Farms",
    "wof:placetype":"venue"
},
  "geometry": {"coordinates":[-122.42938100000001,45.235917],"type":"Point"}
}