{
  "type": "Feature",
  "properties": {
    "addr:full":"44784 Highway 58 Lowell OR 97452",
    "addr:housenumber":"44784",
    "addr:postcode":"97452",
    "addr:street":"Highway 58",
    "iso:country":"US",
    "sg:address":"44784 Highway 58",
    "sg:city":"Lowell",
    "sg:classifiers":[
        {
            "category":"Autos & Motor Vehicles",
            "subcategory":"Fuel & Gas Station",
            "type":"Retail Goods"
        }
    ],
    "sg:phone":"+1 541 782 4013",
    "sg:postcode":"97452",
    "sg:province":"OR",
    "wof:name":"Mc Arthurs Texaco & Gen Str",
    "wof:placetype":"venue"
},
  "geometry": {"coordinates":[-122.68732799999999,43.864895],"type":"Point"}
}