{
  "type": "Feature",
  "properties": {
    "iso:country":"US",
    "sg:address":"6635 N Baltimore Ave",
    "sg:city":"Portland",
    "sg:classifiers":[
        {
            "category":"Building & Trades",
            "subcategory":"Locksmith",
            "type":"Services"
        }
    ],
    "sg:phone":"+1 503 433 7007",
    "sg:postcode":"97203",
    "sg:province":"OR",
    "sg:tags":[
        "key"
    ],
    "wof:name":"Locksmith and Lockout Service Portland",
    "wof:placetype":"venue"
},
  "geometry": {"coordinates":[-122.761483,45.588593],"type":"Point"}
}