{
  "type": "Feature",
  "properties": {
    "iso:country":"US",
    "sg:address":"14335 Galice Rd",
    "sg:city":"Merlin",
    "sg:classifiers":[
        {
            "category":"Building & Trades",
            "subcategory":"Landscaping Services",
            "type":"Services"
        },
        {
            "category":"Government",
            "subcategory":"Office",
            "type":"Public Place"
        }
    ],
    "sg:phone":"+1 541 479 3735",
    "sg:postcode":"97532",
    "sg:province":"OR",
    "sg:tags":[
        "forester"
    ],
    "sg:website":"http://www.lbl.org",
    "wof:name":"Smullin Visitor Center",
    "wof:placetype":"venue"
},
  "geometry": {"coordinates":[-123.586091,42.592917],"type":"Point"}
}