{
  "type": "Feature",
  "properties": {
    "iso:country":"US",
    "sg:address":"220 H St W",
    "sg:city":"Vale",
    "sg:classifiers":[
        {
            "category":"Education",
            "subcategory":"School",
            "type":"Public Place"
        }
    ],
    "sg:phone":"+1 541 473 2734",
    "sg:postcode":"97918",
    "sg:province":"OR",
    "sg:tags":[
        "district"
    ],
    "wof:name":"Vale School District - Transportation",
    "wof:placetype":"venue"
},
  "geometry": {"coordinates":[-117.24085100000001,43.976579],"type":"Point"}
}