{
  "type": "Feature",
  "properties": {
    "addr:full":"132 High Oak Dr Medford OR 97504",
    "addr:housenumber":"132",
    "addr:postcode":"97504",
    "addr:street":"High Oak Dr",
    "iso:country":"US",
    "sg:address":"132 High Oak Dr",
    "sg:city":"Medford",
    "sg:classifiers":[
        {
            "category":"Building & Trades",
            "subcategory":"Construction",
            "type":"Services"
        }
    ],
    "sg:phone":"+1 541 826 5538",
    "sg:postcode":"97504",
    "sg:province":"OR",
    "sg:tags":[
        "contractor"
    ],
    "wof:name":"Alex Boutacoff Construction",
    "wof:placetype":"venue"
},
  "geometry": {"coordinates":[-122.808256,42.331085],"type":"Point"}
}