{
  "type": "Feature",
  "properties": {
    "iso:country":"US",
    "sg:address":"5845 SE 82nd Ave",
    "sg:city":"Portland",
    "sg:classifiers":[
        {
            "category":"Insurance",
            "subcategory":"Hazard Insurance",
            "type":"Services"
        }
    ],
    "sg:phone":"+1 503 774 1986",
    "sg:postcode":"97266",
    "sg:province":"OR",
    "sg:tags":[
        "fidelity",
        "bond"
    ],
    "wof:name":"Oregon Rapid Bonding",
    "wof:placetype":"venue"
},
  "geometry": {"coordinates":[-122.57906699999999,45.480283],"type":"Point"}
}