{
  "type": "Feature",
  "properties": {
    "addr:full":"9401 NW Germantown Rd Portland OR 97231",
    "addr:housenumber":"9401",
    "addr:postcode":"97231",
    "addr:street":"Nw Germantown Rd",
    "iso:country":"US",
    "sg:address":"9401 NW Germantown Rd",
    "sg:city":"Portland",
    "sg:classifiers":[
        {
            "category":"Professional",
            "subcategory":"Advertising",
            "type":"Services"
        }
    ],
    "sg:phone":"+1 503 283 0439",
    "sg:postcode":"97231",
    "sg:province":"OR",
    "sg:tags":[
        "agency"
    ],
    "wof:name":"Lemonade Advertising",
    "wof:placetype":"venue"
},
  "geometry": {"coordinates":[-122.77400400000001,45.587238],"type":"Point"}
}