{
  "type": "Feature",
  "properties": {
    "addr:full":"18030 E Burnside St Portland OR 97233",
    "addr:housenumber":"18030",
    "addr:postcode":"97233",
    "addr:street":"E Burnside St",
    "iso:country":"US",
    "sg:address":"18030 E Burnside St",
    "sg:city":"Portland",
    "sg:classifiers":[
        {
            "category":"Building & Trades",
            "subcategory":"Locksmith",
            "type":"Services"
        }
    ],
    "sg:phone":"+1 971 327 9851",
    "sg:postcode":"97233",
    "sg:province":"OR",
    "sg:tags":[
        "key"
    ],
    "wof:name":"30 Minute Response Locksmith",
    "wof:placetype":"venue"
},
  "geometry": {"coordinates":[-122.477906,45.52185],"type":"Point"}
}