{
  "type": "Feature",
  "properties": {
    "addr:full":"1835 NE 7th St Grants Pass OR 97526",
    "addr:housenumber":"1835",
    "addr:postcode":"97526",
    "addr:street":"Ne 7Th St",
    "iso:country":"US",
    "sg:address":"1835 NE 7th St",
    "sg:city":"Grants Pass",
    "sg:classifiers":[
        {
            "category":"Restaurant",
            "type":"Food & Drink"
        }
    ],
    "sg:menulink":"http://www.allmenus.com/or/grants-pass/170533-burger-king/menu/",
    "sg:phone":"+1 541 476 0661",
    "sg:postcode":"97526",
    "sg:province":"OR",
    "sg:tags":[
        "burger",
        "american"
    ],
    "wof:name":"Burger King",
    "wof:placetype":"venue"
},
  "geometry": {"coordinates":[-123.320744,42.460266],"type":"Point"}
}