{
  "type": "Feature",
  "properties": {
    "addr:full":"6432 SE Foster Rd Portland OR 97206",
    "addr:housenumber":"6432",
    "addr:postcode":"97206",
    "addr:street":"Se Foster Rd",
    "iso:country":"US",
    "sg:address":"6432 SE Foster Rd",
    "sg:city":"Portland",
    "sg:classifiers":[
        {
            "category":"Real Estate",
            "subcategory":"Real Estate Agent",
            "type":"Services"
        }
    ],
    "sg:phone":"+1 503 774 8893",
    "sg:postcode":"97206",
    "sg:province":"OR",
    "wof:name":"Hanna Realty Inc",
    "wof:placetype":"venue"
},
  "geometry": {"coordinates":[-122.59706,45.489696],"type":"Point"}
}