{
  "type": "Feature",
  "properties": {
    "iso:country":"US",
    "sg:address":"1420 NW Lovejoy St",
    "sg:city":"Portland",
    "sg:classifiers":[
        {
            "category":"Professional",
            "subcategory":"Research",
            "type":"Services"
        }
    ],
    "sg:phone":"+1 503 296 7713",
    "sg:postcode":"97209",
    "sg:province":"OR",
    "sg:tags":[
        "market",
        "analysis"
    ],
    "wof:name":"Muse",
    "wof:placetype":"venue"
},
  "geometry": {"coordinates":[-122.686288,45.52994],"type":"Point"}
}