{
  "type": "Feature",
  "properties": {
    "iso:country":"US",
    "sg:address":"548 G St Apt 3",
    "sg:city":"Jacksonville",
    "sg:classifiers":[
        {
            "category":"Manufacturing",
            "subcategory":"Buildings",
            "type":"Manufacturing & Wholesale Goods"
        },
        {
            "category":"Building & Trades",
            "subcategory":"Construction",
            "type":"Services"
        }
    ],
    "sg:phone":"+1 541 890 3899",
    "sg:postcode":"97530",
    "sg:province":"OR",
    "sg:tags":[
        "home",
        "builder",
        "contractor"
    ],
    "wof:name":"Derek Bates Construction",
    "wof:placetype":"venue"
},
  "geometry": {"coordinates":[-122.96069199999999,42.316842],"type":"Point"}
}