{
  "type": "Feature",
  "properties": {
    "addr:full":"38720 Proctor Blvd Sandy OR 97055",
    "addr:housenumber":"38720",
    "addr:postcode":"97055",
    "addr:street":"Proctor Blvd",
    "iso:country":"US",
    "sg:address":"38720 Proctor Blvd",
    "sg:city":"Sandy",
    "sg:classifiers":[
        {
            "category":"Manufacturing",
            "subcategory":"Lumber",
            "type":"Manufacturing & Wholesale Goods"
        }
    ],
    "sg:phone":"+1 503 668 8933",
    "sg:postcode":"97055",
    "sg:province":"OR",
    "sg:tags":[
        "operation",
        "timber",
        "tract"
    ],
    "wof:name":"Longview Fiber",
    "wof:placetype":"venue"
},
  "geometry": {"coordinates":[-122.26522300000001,45.397241],"type":"Point"}
}