{
  "type": "Feature",
  "properties": {
    "iso:country":"US",
    "sg:address":"31266 S Grays Hill Rd",
    "sg:city":"Colton",
    "sg:classifiers":[
        {
            "category":"Professional",
            "type":"Services"
        }
    ],
    "sg:phone":"+1 503 824 2620",
    "sg:postcode":"97017",
    "sg:province":"OR",
    "sg:tags":[
        "information",
        "bureau"
    ],
    "wof:name":"Integrated Garden Service Inc",
    "wof:placetype":"venue"
},
  "geometry": {"coordinates":[-122.41439099999999,45.15384],"type":"Point"}
}