{
  "type": "Feature",
  "properties": {
    "addr:full":"10448 SE Highway 212 Clackamas OR 97015",
    "addr:housenumber":"10448",
    "addr:postcode":"97015",
    "addr:street":"Se Highway 212",
    "iso:country":"US",
    "sg:address":"10448 SE Highway 212",
    "sg:city":"Clackamas",
    "sg:classifiers":[
        {
            "category":"Manufacturing",
            "subcategory":"Building Materials",
            "type":"Manufacturing & Wholesale Goods"
        }
    ],
    "sg:phone":"+1 503 657 4183",
    "sg:postcode":"97015",
    "sg:province":"OR",
    "sg:tags":[
        "product",
        "aluminum"
    ],
    "sg:website":"http://www.conmet.com",
    "wof:name":"Consolidated Metco, Inc.",
    "wof:placetype":"venue"
},
  "geometry": {"coordinates":[-122.557828,45.407784],"type":"Point"}
}