{
  "type": "Feature",
  "properties": {
    "iso:country":"US",
    "sg:address":"2290 SW 106th Pl",
    "sg:city":"Portland",
    "sg:classifiers":[
        {
            "category":"Communications",
            "type":"Services"
        }
    ],
    "sg:phone":"+1 503 203 1197",
    "sg:postcode":"97225",
    "sg:province":"OR",
    "sg:tags":[
        "apprenticeship",
        "training",
        "program"
    ],
    "wof:name":"Ntma Enterprises",
    "wof:placetype":"venue"
},
  "geometry": {"coordinates":[-122.786191,45.503281],"type":"Point"}
}