{
  "type": "Feature",
  "properties": {
    "iso:country":"US",
    "sg:address":"850 SW 7th St",
    "sg:city":"Redmond",
    "sg:classifiers":[
        {
            "category":"Health Services",
            "subcategory":"Doctor",
            "type":"Services"
        }
    ],
    "sg:phone":"+1 541 923 4577",
    "sg:postcode":"97756",
    "sg:province":"OR",
    "sg:tags":[
        "dentist"
    ],
    "wof:name":"Daniel B Howard DDS",
    "wof:placetype":"venue"
},
  "geometry": {"coordinates":[-121.175262,44.271533],"type":"Point"}
}