{
  "type": "Feature",
  "properties": {
    "iso:country":"US",
    "sg:address":"5724 SE Flavel Dr",
    "sg:city":"Portland",
    "sg:classifiers":[
        {
            "category":"Professional",
            "type":"Services"
        }
    ],
    "sg:phone":"+1 503 788 0183",
    "sg:postcode":"97206",
    "sg:province":"OR",
    "wof:name":"Jcs Sewer Connections",
    "wof:placetype":"venue"
},
  "geometry": {"coordinates":[-122.603919,45.463483],"type":"Point"}
}