{
  "type": "Feature",
  "properties": {
    "iso:country":"US",
    "sg:address":"985 Beverly Way",
    "sg:city":"Jacksonville",
    "sg:classifiers":[
        {
            "category":"Professional",
            "subcategory":"Secretarial Services",
            "type":"Services"
        }
    ],
    "sg:phone":"+1 541 899 9072",
    "sg:postcode":"97530",
    "sg:province":"OR",
    "sg:tags":[
        "reporting"
    ],
    "wof:name":"Type It Right",
    "wof:placetype":"venue"
},
  "geometry": {"coordinates":[-122.958814,42.314794],"type":"Point"}
}