{
  "type": "Feature",
  "properties": {
    "iso:country":"US",
    "sg:address":"31513 Easy Ave SW",
    "sg:city":"Albany",
    "sg:classifiers":[
        {
            "category":"Building & Trades",
            "subcategory":"Construction",
            "type":"Services"
        }
    ],
    "sg:phone":"+1 541 928 1795",
    "sg:postcode":"97321",
    "sg:province":"OR",
    "sg:tags":[
        "contractor"
    ],
    "wof:name":"Willamette Valley Plastering",
    "wof:placetype":"venue"
},
  "geometry": {"coordinates":[-123.129949,44.606319],"type":"Point"}
}