{
  "type": "Feature",
  "properties": {
    "iso:country":"US",
    "sg:address":"4531 Franklin Blvd # 112",
    "sg:city":"Eugene",
    "sg:classifiers":[
        {
            "category":"Food & Beverages",
            "subcategory":"Groceries & Convenience Stores",
            "type":"Retail Goods"
        }
    ],
    "sg:phone":"+1 541 688 0344",
    "sg:postcode":"97403",
    "sg:province":"OR",
    "wof:name":"Aday's Market",
    "wof:placetype":"venue"
},
  "geometry": {"coordinates":[-123.029167,44.041193],"type":"Point"}
}