{
  "type": "Feature",
  "properties": {
    "iso:country":"US",
    "sg:address":"1647 Hawthorne Ave NE",
    "sg:city":"Salem",
    "sg:classifiers":[
        {
            "category":"Banks & Credit Unions",
            "subcategory":"Bank",
            "type":"Services"
        }
    ],
    "sg:phone":"+1 503 581 5626",
    "sg:postcode":"97301",
    "sg:province":"OR",
    "sg:tags":[
        "loan"
    ],
    "wof:name":"Fastbucks",
    "wof:placetype":"venue"
},
  "geometry": {"coordinates":[-122.992695,44.9501],"type":"Point"}
}