{
  "type": "Feature",
  "properties": {
    "addr:full":"411 NE 18th Ave Luxe Autohaus Portland OR 97232",
    "addr:housenumber":"411",
    "addr:postcode":"97232",
    "addr:street":"Ne 18Th Ave",
    "iso:country":"US",
    "sg:address":"411 NE 18th Ave Luxe Autohaus",
    "sg:city":"Portland",
    "sg:classifiers":[
        {
            "category":"Restaurant",
            "type":"Food & Drink"
        }
    ],
    "sg:phone":"+1 503 233 5893",
    "sg:postcode":"97232",
    "sg:province":"OR",
    "sg:tags":[
        "flavor",
        "local"
    ],
    "sg:website":"www.portlandtaste.org/",
    "wof:name":"Taste of the Nation",
    "wof:placetype":"venue"
},
  "geometry": {"coordinates":[-122.647514,45.525913],"type":"Point"}
}