{
  "type": "Feature",
  "properties": {
    "iso:country":"US",
    "sg:address":"364 Caves Hwy",
    "sg:city":"Cave Junction",
    "sg:classifiers":[
        {
            "category":"Retail",
            "subcategory":"Auto Repair",
            "type":"Services"
        }
    ],
    "sg:phone":"+1 541 592 6642",
    "sg:postcode":"97523",
    "sg:province":"OR",
    "sg:tags":[
        "transmission"
    ],
    "wof:name":"Illinois Valley Transmission",
    "wof:placetype":"venue"
},
  "geometry": {"coordinates":[-123.64264300000001,42.161573],"type":"Point"}
}