{
  "type": "Feature",
  "properties": {
    "iso:country":"US",
    "sg:address":"1430 Willamette St",
    "sg:city":"Eugene",
    "sg:classifiers":[
        {
            "category":"Real Estate",
            "subcategory":"Real Estate Operator",
            "type":"Services"
        }
    ],
    "sg:phone":"+1 541 344 0698",
    "sg:postcode":"97401",
    "sg:province":"OR",
    "sg:tags":[
        "building",
        "apartment"
    ],
    "wof:name":"Jh Pantland Co",
    "wof:placetype":"venue"
},
  "geometry": {"coordinates":[-123.092825,44.043662],"type":"Point"}
}