{
  "type": "Feature",
  "properties": {
    "iso:country":"US",
    "sg:address":"3122 SE Walta Vista Ct",
    "sg:city":"Portland",
    "sg:classifiers":[
        {
            "category":"Bars & Pubs",
            "type":"Food & Drink"
        },
        {
            "category":"Travel",
            "subcategory":"Bed & Breakfast",
            "type":"Entertainment"
        }
    ],
    "sg:phone":"+1 503 232 9516",
    "sg:postcode":"97267",
    "sg:province":"OR",
    "sg:tags":[
        "tavern",
        "inn"
    ],
    "wof:name":"Dino's Inn",
    "wof:placetype":"venue"
},
  "geometry": {"coordinates":[-122.631242,45.398434],"type":"Point"}
}