{
  "type": "Feature",
  "properties": {
    "addr:full":"2950 NW 29th Ave Portland OR 97210",
    "addr:housenumber":"2950",
    "addr:postcode":"97210",
    "addr:street":"Nw 29Th Ave",
    "iso:country":"US",
    "sg:address":"2950 NW 29th Ave",
    "sg:city":"Portland",
    "sg:classifiers":[
        {
            "category":"Wholesale",
            "subcategory":"Non-durable Goods",
            "type":"Manufacturing & Wholesale Goods"
        }
    ],
    "sg:phone":"+1 503 241 7707",
    "sg:postcode":"97210",
    "sg:province":"OR",
    "sg:website":"www.pacpkg.com",
    "wof:name":"Pacific Packaging Enterprises",
    "wof:placetype":"venue"
},
  "geometry": {"coordinates":[-122.710899,45.541858],"type":"Point"}
}