{
  "type": "Feature",
  "properties": {
    "addr:full":"501 S 9th St Nyssa OR 97913",
    "addr:housenumber":"501",
    "addr:postcode":"97913",
    "addr:street":"S 9Th St",
    "iso:country":"US",
    "sg:address":"501 S 9th St",
    "sg:city":"Nyssa",
    "sg:phone":"+1 541 372 3805",
    "sg:postcode":"97913",
    "sg:province":"OR",
    "sg:tags":[
        "farm",
        "field",
        "wheat",
        "crop"
    ],
    "wof:name":"Ross L Ballard Jr",
    "wof:placetype":"venue"
},
  "geometry": {"coordinates":[-117.00361599999999,43.871511],"type":"Point"}
}