{
  "type": "Feature",
  "properties": {
    "iso:country":"US",
    "sg:address":"88 SW 2nd Ave",
    "sg:city":"Ontario",
    "sg:classifiers":[
        {
            "category":"Government",
            "subcategory":"Post Office",
            "type":"Public Place"
        }
    ],
    "sg:phone":"+1 541 889 0911",
    "sg:postcode":"97914",
    "sg:province":"OR",
    "sg:tags":[
        "postal",
        "us"
    ],
    "sg:website":"www.usps.gov",
    "wof:name":"US Post Office",
    "wof:placetype":"venue"
},
  "geometry": {"coordinates":[-116.96372,44.024806],"type":"Point"}
}