{
  "type": "Feature",
  "properties": {
    "addr:full":"901 SW King Avenue Portland OR 97205",
    "addr:housenumber":"901",
    "addr:postcode":"97205",
    "addr:street":"Sw King Avenue",
    "iso:country":"US",
    "sg:address":"901 SW King Avenue",
    "sg:city":"Portland",
    "sg:classifiers":[
        {
            "category":"Real Estate",
            "subcategory":"Real Estate Operator",
            "type":"Services"
        }
    ],
    "sg:phone":"+1 503 223 1458",
    "sg:postcode":"97205",
    "sg:province":"OR",
    "sg:tags":[
        "apartment"
    ],
    "sg:website":"www.kingtower.com",
    "wof:name":"King Tower Apartments",
    "wof:placetype":"venue"
},
  "geometry": {"coordinates":[-122.695413,45.521969],"type":"Point"}
}