{
  "type": "Feature",
  "properties": {
    "iso:country":"US",
    "sg:address":"3445 NE Broadway St",
    "sg:city":"Portland",
    "sg:classifiers":[
        {
            "category":"Professional",
            "type":"Services"
        }
    ],
    "sg:phone":"+1 503 249 7675",
    "sg:postcode":"97232",
    "sg:province":"OR",
    "wof:name":"Lagniappe",
    "wof:placetype":"venue"
},
  "geometry": {"coordinates":[-122.63066499999999,45.535159],"type":"Point"}
}