{
  "type": "Feature",
  "properties": {
    "addr:full":"3445 NE Broadway St Portland OR 97232",
    "addr:housenumber":"3445",
    "addr:postcode":"97232",
    "addr:street":"Ne Broadway St",
    "iso:country":"US",
    "sg:address":"3445 NE Broadway St",
    "sg:city":"Portland",
    "sg:classifiers":[
        {
            "category":"Professional",
            "type":"Services"
        }
    ],
    "sg:phone":"+1 503 249 7675",
    "sg:postcode":"97232",
    "sg:province":"OR",
    "wof:name":"Lagniappe",
    "wof:placetype":"venue"
},
  "geometry": {"coordinates":[-122.63066499999999,45.535159],"type":"Point"}
}