{
  "type": "Feature",
  "properties": {
    "iso:country":"US",
    "sg:address":"73807 Hwy 207",
    "sg:city":"Echo",
    "sg:classifiers":[
        {
            "category":"Manufacturing",
            "subcategory":"Tools & Machinery",
            "type":"Manufacturing & Wholesale Goods"
        }
    ],
    "sg:phone":"+1 541 376 5100",
    "sg:postcode":"97826",
    "sg:province":"OR",
    "sg:tags":[
        "farm",
        "mfg"
    ],
    "wof:name":"Hale Shop",
    "wof:placetype":"venue"
},
  "geometry": {"coordinates":[-119.359365,45.709584],"type":"Point"}
}