{
  "type": "Feature",
  "properties": {
    "addr:full":"921 SW Washington St Portland OR 97205",
    "addr:housenumber":"921",
    "addr:postcode":"97205",
    "addr:street":"Sw Washington St",
    "iso:country":"US",
    "sg:address":"921 SW Washington St",
    "sg:city":"Portland",
    "sg:classifiers":[
        {
            "category":"Health Services",
            "subcategory":"Doctor",
            "type":"Services"
        }
    ],
    "sg:phone":"+1 503 226 8918",
    "sg:postcode":"97205",
    "sg:province":"OR",
    "sg:tags":[
        "psychiatry",
        "physician",
        "medical",
        "surgeons",
        "surgeon"
    ],
    "wof:name":"Jayne Laszewski Md",
    "wof:placetype":"venue"
},
  "geometry": {"coordinates":[-122.680593,45.52115],"type":"Point"}
}