{
  "type": "Feature",
  "properties": {
    "iso:country":"US",
    "sg:address":"1200 NW 23rd Ave",
    "sg:city":"Portland",
    "sg:classifiers":[
        {
            "category":"Health Services",
            "subcategory":"Doctor",
            "type":"Services"
        }
    ],
    "sg:phone":"+1 503 413 7074",
    "sg:postcode":"97210",
    "sg:province":"OR",
    "sg:tags":[
        "medical"
    ],
    "wof:name":"Elizabeth Eckstrom MD",
    "wof:placetype":"venue"
},
  "geometry": {"coordinates":[-122.698679,45.531655],"type":"Point"}
}