{
  "type": "Feature",
  "properties": {
    "iso:country":"US",
    "sg:address":"318 SE Jackson St",
    "sg:city":"Roseburg",
    "sg:classifiers":[
        {
            "category":"Professional",
            "subcategory":"Lawyer & Legal Services",
            "type":"Services"
        }
    ],
    "sg:phone":"+1 541 673 0696",
    "sg:postcode":"97470",
    "sg:province":"OR",
    "sg:tags":[
        "plan"
    ],
    "wof:name":"Diana Wales",
    "wof:placetype":"venue"
},
  "geometry": {"coordinates":[-123.342232,43.211446],"type":"Point"}
}