{
  "type": "Feature",
  "properties": {
    "iso:country":"US",
    "sg:address":"4631 SE 51st St",
    "sg:city":"Lincoln City",
    "sg:classifiers":[
        {
            "category":"Professional",
            "subcategory":"Accounting & Tax Preparation",
            "type":"Services"
        }
    ],
    "sg:phone":"+1 541 994 8968",
    "sg:postcode":"97367",
    "sg:province":"OR",
    "wof:name":"Kaleidescope Bookkeeping",
    "wof:placetype":"venue"
},
  "geometry": {"coordinates":[-124.01113100000001,44.931516],"type":"Point"}
}