{
  "type": "Feature",
  "properties": {
    "addr:full":"7044 N Seneca St Portland OR 97203",
    "addr:housenumber":"7044",
    "addr:postcode":"97203",
    "addr:street":"N Seneca St",
    "iso:country":"US",
    "sg:address":"7044 N Seneca St",
    "sg:city":"Portland",
    "sg:classifiers":[
        {
            "category":"Manufacturing",
            "subcategory":"Tools & Machinery",
            "type":"Manufacturing & Wholesale Goods"
        }
    ],
    "sg:phone":"+1 503 283 7608",
    "sg:postcode":"97203",
    "sg:province":"OR",
    "sg:tags":[
        "mfg"
    ],
    "wof:name":"Lauras Helping Hands",
    "wof:placetype":"venue"
},
  "geometry": {"coordinates":[-122.736581,45.592199],"type":"Point"}
}