{
  "type": "Feature",
  "properties": {
    "addr:full":"875 Oak St SE Salem OR 97301",
    "addr:housenumber":"875",
    "addr:postcode":"97301",
    "addr:street":"Oak St Se",
    "iso:country":"US",
    "sg:address":"875 Oak St SE",
    "sg:city":"Salem",
    "sg:classifiers":[
        {
            "category":"Health Services",
            "subcategory":"Doctor",
            "type":"Services"
        }
    ],
    "sg:phone":"+1 503 561 8100",
    "sg:postcode":"97301",
    "sg:province":"OR",
    "sg:tags":[
        "physician",
        "surgeon"
    ],
    "wof:name":"Orthopedic Offices",
    "wof:placetype":"venue"
},
  "geometry": {"coordinates":[-123.03471999999999,44.933299],"type":"Point"}
}