{
  "type": "Feature",
  "properties": {
    "iso:country":"US",
    "sg:address":"30970 8th St",
    "sg:city":"Lebanon",
    "sg:classifiers":[
        {
            "category":"Retail",
            "subcategory":"Auto Repair",
            "type":"Services"
        }
    ],
    "sg:phone":"+1 541 258 6700",
    "sg:postcode":"97355",
    "sg:province":"OR",
    "sg:tags":[
        "body",
        "automotive",
        "painting",
        "exterior",
        "automobile"
    ],
    "wof:name":"Collision Auto Repair Oregon",
    "wof:placetype":"venue"
},
  "geometry": {"coordinates":[-122.824843,44.491675],"type":"Point"}
}