{
  "type": "Feature",
  "properties": {
    "iso:country":"US",
    "sg:address":"271 Chimney Rock Ln",
    "sg:city":"Eugene",
    "sg:classifiers":[
        {
            "category":"Professional",
            "subcategory":"Accounting & Tax Preparation",
            "type":"Services"
        }
    ],
    "sg:phone":"+1 541 688 0647",
    "sg:postcode":"97404",
    "sg:province":"OR",
    "wof:name":"D W Wall CPA",
    "wof:placetype":"venue"
},
  "geometry": {"coordinates":[-123.147337,44.122247],"type":"Point"}
}