{
  "type": "Feature",
  "properties": {
    "iso:country":"US",
    "sg:address":"26282 State Hwy 213",
    "sg:city":"Mulino",
    "sg:classifiers":[
        {
            "category":"Home & Garden",
            "subcategory":"Home Furnishings",
            "type":"Retail Goods"
        }
    ],
    "sg:phone":"+1 503 829 2005",
    "sg:postcode":"97042",
    "sg:province":"OR",
    "sg:tags":[
        "pottery"
    ],
    "wof:name":"Tickle Creek Pottery",
    "wof:placetype":"venue"
},
  "geometry": {"coordinates":[-122.581788,45.226781],"type":"Point"}
}