{
  "type": "Feature",
  "properties": {
    "iso:country":"US",
    "sg:address":"855 Monmouth Ave N",
    "sg:city":"Monmouth",
    "sg:classifiers":[
        {
            "category":"Restaurant",
            "type":"Food & Drink"
        }
    ],
    "sg:phone":"+1 503 838 8673",
    "sg:postcode":"97361",
    "sg:province":"OR",
    "sg:tags":[
        "banquet",
        "rooms"
    ],
    "wof:name":"Gentle House",
    "wof:placetype":"venue"
},
  "geometry": {"coordinates":[-123.237618,44.856153],"type":"Point"}
}