{
  "type": "Feature",
  "properties": {
    "iso:country":"US",
    "sg:address":"1410 Marine Dr",
    "sg:city":"Astoria",
    "sg:classifiers":[
        {
            "category":"Health Services",
            "subcategory":"Health Practitioner",
            "type":"Services"
        }
    ],
    "sg:phone":"+1 503 325 7401",
    "sg:postcode":"97103",
    "sg:province":"OR",
    "wof:name":"Jade River Acupuncture Clinic",
    "wof:placetype":"venue"
},
  "geometry": {"coordinates":[-123.827342,46.189486],"type":"Point"}
}