{
  "type": "Feature",
  "properties": {
    "addr:full":"720 Crater Lake Ave Medford OR 97504",
    "addr:housenumber":"720",
    "addr:postcode":"97504",
    "addr:street":"Crater Lake Ave",
    "iso:country":"US",
    "sg:address":"720 Crater Lake Ave",
    "sg:city":"Medford",
    "sg:classifiers":[
        {
            "category":"Shopping",
            "subcategory":"Bicycles & Sporting Goods",
            "type":"Retail Goods"
        }
    ],
    "sg:phone":"+1 541 779 1717",
    "sg:postcode":"97504",
    "sg:province":"OR",
    "sg:tags":[
        "repair"
    ],
    "wof:name":"Moores Pool Sales & Service",
    "wof:placetype":"venue"
},
  "geometry": {"coordinates":[-122.861211,42.336779],"type":"Point"}
}