{
  "type": "Feature",
  "properties": {
    "addr:full":"2284 Rogue River Dr Eagle Point OR 97524",
    "addr:housenumber":"2284",
    "addr:postcode":"97524",
    "addr:street":"Rogue River Dr",
    "iso:country":"US",
    "sg:address":"2284 Rogue River Dr",
    "sg:city":"Eagle Point",
    "sg:classifiers":[
        {
            "category":"Manufacturing",
            "subcategory":"Glass & Minerals",
            "type":"Manufacturing & Wholesale Goods"
        }
    ],
    "sg:phone":"+1 541 826 2344",
    "sg:postcode":"97524",
    "sg:province":"OR",
    "sg:tags":[
        "image",
        "fine",
        "sales"
    ],
    "wof:name":"Colors of Creation",
    "wof:placetype":"venue"
},
  "geometry": {"coordinates":[-122.84656099999999,42.555392],"type":"Point"}
}