{
  "type": "Feature",
  "properties": {
    "iso:country":"US",
    "sg:address":"725 Canyon Three Rd",
    "sg:city":"Ontario",
    "sg:classifiers":[
        {
            "category":"Manufacturing",
            "subcategory":"Soap",
            "type":"Manufacturing & Wholesale Goods"
        }
    ],
    "sg:phone":"+1 541 889 2406",
    "sg:postcode":"97914",
    "sg:province":"OR",
    "sg:tags":[
        "detergent"
    ],
    "wof:name":"White House Soapworks",
    "wof:placetype":"venue"
},
  "geometry": {"coordinates":[-117.050333,44.046535],"type":"Point"}
}