{
  "type": "Feature",
  "properties": {
    "addr:full":"1633 NE 108th Ave Portland OR 97220",
    "addr:housenumber":"1633",
    "addr:postcode":"97220",
    "addr:street":"Ne 108Th Ave",
    "iso:country":"US",
    "sg:address":"1633 NE 108th Ave",
    "sg:city":"Portland",
    "sg:classifiers":[
        {
            "category":"Real Estate",
            "subcategory":"Real Estate Operator",
            "type":"Services"
        }
    ],
    "sg:phone":"+1 503 252 7689",
    "sg:postcode":"97220",
    "sg:province":"OR",
    "sg:tags":[
        "apartment"
    ],
    "sg:website":"www.weidlerplaza.com",
    "wof:name":"Weidler Plaza",
    "wof:placetype":"venue"
},
  "geometry": {"coordinates":[-122.55161200000001,45.534386],"type":"Point"}
}