{
  "type": "Feature",
  "properties": {
    "iso:country":"US",
    "sg:address":"4811 SE Powell Blvd",
    "sg:city":"Portland",
    "sg:classifiers":[
        {
            "category":"Restaurant",
            "type":"Food & Drink"
        }
    ],
    "sg:phone":"+1 503 788 7918",
    "sg:postcode":"97206",
    "sg:province":"OR",
    "sg:tags":[
        "thai"
    ],
    "sg:website":"www.powellthaibbq.com",
    "wof:name":"Thai BBQ",
    "wof:placetype":"venue"
},
  "geometry": {"coordinates":[-122.613371,45.497596],"type":"Point"}
}