{
  "type": "Feature",
  "properties": {
    "iso:country":"US",
    "sg:address":"5440 SW Westgate Dr",
    "sg:city":"Portland",
    "sg:classifiers":[
        {
            "category":"Building & Trades",
            "subcategory":"Construction",
            "type":"Services"
        }
    ],
    "sg:phone":"+1 503 731 8322",
    "sg:postcode":"97221",
    "sg:province":"OR",
    "sg:tags":[
        "hanging",
        "contractor"
    ],
    "wof:name":"Odot Traffic Line",
    "wof:placetype":"venue"
},
  "geometry": {"coordinates":[-122.732326,45.510631],"type":"Point"}
}