{
  "type": "Feature",
  "properties": {
    "iso:country":"US",
    "sg:address":"10201 SE Main St",
    "sg:city":"Portland",
    "sg:classifiers":[
        {
            "category":"Health Services",
            "subcategory":"Doctor",
            "type":"Services"
        }
    ],
    "sg:phone":"+1 503 255 7550",
    "sg:postcode":"97216",
    "sg:province":"OR",
    "sg:tags":[
        "medical"
    ],
    "wof:name":"Gregory E Robinson MD",
    "wof:placetype":"venue"
},
  "geometry": {"coordinates":[-122.555058,45.514021],"type":"Point"}
}