{
  "type": "Feature",
  "properties": {
    "addr:full":"3791 River Rd N Keizer OR 97303",
    "addr:housenumber":"3791",
    "addr:postcode":"97303",
    "addr:street":"River Rd N",
    "iso:country":"US",
    "sg:address":"3791 River Rd N",
    "sg:city":"Keizer",
    "sg:classifiers":[
        {
            "category":"Insurance",
            "subcategory":"Insurance Agent",
            "type":"Services"
        }
    ],
    "sg:phone":"+1 503 463 1388",
    "sg:postcode":"97303",
    "sg:province":"OR",
    "wof:name":"Guerra Joe State Farm Ins",
    "wof:placetype":"venue"
},
  "geometry": {"coordinates":[-123.02665,44.980375],"type":"Point"}
}