{
  "type": "Feature",
  "properties": {
    "iso:country":"US",
    "sg:address":"4806 NW A Ave",
    "sg:city":"Pendleton",
    "sg:classifiers":[
        {
            "category":"Manufacturing",
            "subcategory":"Lumber",
            "type":"Manufacturing & Wholesale Goods"
        }
    ],
    "sg:phone":"+1 541 966 8560",
    "sg:postcode":"97801",
    "sg:province":"OR",
    "sg:tags":[
        "forester"
    ],
    "wof:name":"Bill Alexander Forrestry Inc",
    "wof:placetype":"venue"
},
  "geometry": {"coordinates":[-118.84501,45.688192],"type":"Point"}
}