{
  "type": "Feature",
  "properties": {
    "iso:country":"US",
    "sg:address":"21571 SE Grand Island Loop",
    "sg:city":"Dayton",
    "sg:classifiers":[
        {
            "category":"Farming",
            "subcategory":"Farm",
            "type":"Manufacturing & Wholesale Goods"
        }
    ],
    "sg:phone":"+1 503 868 7241",
    "sg:postcode":"97114",
    "sg:province":"OR",
    "sg:tags":[
        "crop",
        "general"
    ],
    "wof:name":"Hildebrandt Farms",
    "wof:placetype":"venue"
},
  "geometry": {"coordinates":[-123.0265,45.129419],"type":"Point"}
}