{
  "type": "Feature",
  "properties": {
    "iso:country":"US",
    "sg:address":"358 Green Ct",
    "sg:city":"Ontario",
    "sg:classifiers":[
        {
            "category":"Building & Trades",
            "subcategory":"Construction",
            "type":"Services"
        }
    ],
    "sg:phone":"+1 541 889 3940",
    "sg:postcode":"97914",
    "sg:province":"OR",
    "sg:tags":[
        "general",
        "contractor"
    ],
    "wof:name":"Liddle & Moeller Construction",
    "wof:placetype":"venue"
},
  "geometry": {"coordinates":[-116.986715,44.031792],"type":"Point"}
}