{
  "type": "Feature",
  "properties": {
    "iso:country":"US",
    "sg:address":"545 Holly St",
    "sg:city":"Junction City",
    "sg:classifiers":[
        {
            "category":"Professional",
            "subcategory":"Accounting & Tax Preparation",
            "type":"Services"
        }
    ],
    "sg:phone":"+1 541 998 8103",
    "sg:postcode":"97448",
    "sg:province":"OR",
    "wof:name":"Banton Business Services",
    "wof:placetype":"venue"
},
  "geometry": {"coordinates":[-123.203687,44.218792],"type":"Point"}
}