{
  "type": "Feature",
  "properties": {
    "iso:country":"US",
    "sg:address":"199 N Broadway",
    "sg:city":"Coos Bay",
    "sg:classifiers":[
        {
            "category":"Shopping",
            "subcategory":"Stationery & Office Supplies",
            "type":"Retail Goods"
        }
    ],
    "sg:phone":"+1 541 267 5114",
    "sg:postcode":"97420",
    "sg:province":"OR",
    "sg:website":"www.southcoastoffice.com",
    "wof:name":"South Coast Office Supply Inc",
    "wof:placetype":"venue"
},
  "geometry": {"coordinates":[-124.213176,43.367939],"type":"Point"}
}