{
  "type": "Feature",
  "properties": {
    "iso:country":"US",
    "sg:address":"585 SW 6th St",
    "sg:city":"Redmond",
    "sg:classifiers":[
        {
            "category":"Banks & Credit Unions",
            "subcategory":"Investment Brokerage",
            "type":"Services"
        }
    ],
    "sg:phone":"+1 541 548 6101",
    "sg:postcode":"97756",
    "sg:province":"OR",
    "sg:tags":[
        "advisory",
        "financial"
    ],
    "wof:name":"Freedom Financial",
    "wof:placetype":"venue"
},
  "geometry": {"coordinates":[-121.174344,44.27172],"type":"Point"}
}