{
  "type": "Feature",
  "properties": {
    "iso:country":"US",
    "sg:address":"229 S Front St",
    "sg:city":"Medford",
    "sg:classifiers":[
        {
            "category":"Home & Garden",
            "subcategory":"Building Materials",
            "type":"Retail Goods"
        }
    ],
    "sg:phone":"+1 541 773 1058",
    "sg:postcode":"97501",
    "sg:province":"OR",
    "sg:tags":[
        "glass",
        "window",
        "plate"
    ],
    "wof:name":"Farrell's Glass Svc",
    "wof:placetype":"venue"
},
  "geometry": {"coordinates":[-122.870898,42.323986],"type":"Point"}
}