{
  "type": "Feature",
  "properties": {
    "addr:full":"550 Wilson St Eugene OR 97402",
    "addr:housenumber":"550",
    "addr:postcode":"97402",
    "addr:street":"Wilson St",
    "iso:country":"US",
    "sg:address":"550 Wilson St",
    "sg:city":"Eugene",
    "sg:classifiers":[
        {
            "category":"Manufacturing",
            "subcategory":"Metals",
            "type":"Manufacturing & Wholesale Goods"
        }
    ],
    "sg:phone":"+1 541 342 4808",
    "sg:postcode":"97402",
    "sg:province":"OR",
    "sg:tags":[
        "valve"
    ],
    "wof:name":"Paramount Supply Co",
    "wof:placetype":"venue"
},
  "geometry": {"coordinates":[-123.131812,44.053751],"type":"Point"}
}