{
  "type": "Feature",
  "properties": {
    "addr:full":"1732 N Alberta St Portland OR 97217",
    "addr:housenumber":"1732",
    "addr:postcode":"97217",
    "addr:street":"N Alberta St",
    "iso:country":"US",
    "sg:address":"1732 N Alberta St",
    "sg:city":"Portland",
    "sg:classifiers":[
        {
            "category":"Building & Trades",
            "subcategory":"Locksmith",
            "type":"Services"
        }
    ],
    "sg:phone":"+1 503 290 0116",
    "sg:postcode":"97217",
    "sg:province":"OR",
    "sg:tags":[
        "key"
    ],
    "wof:name":"Locksmith Service",
    "wof:placetype":"venue"
},
  "geometry": {"coordinates":[-122.685121,45.558976],"type":"Point"}
}