{
  "type": "Feature",
  "properties": {
    "iso:country":"US",
    "sg:address":"16016 SE Keller Rd",
    "sg:city":"Clackamas",
    "sg:classifiers":[
        {
            "category":"Building & Trades",
            "subcategory":"Construction",
            "type":"Services"
        }
    ],
    "sg:phone":"+1 503 558 1740",
    "sg:postcode":"97015",
    "sg:province":"OR",
    "sg:tags":[
        "contractor"
    ],
    "wof:name":"Gibson Homes",
    "wof:placetype":"venue"
},
  "geometry": {"coordinates":[-122.470001,45.4063],"type":"Point"}
}