{
  "type": "Feature",
  "properties": {
    "addr:full":"515 SW Broadway Portland OR 97205",
    "addr:housenumber":"515",
    "addr:postcode":"97205",
    "addr:street":"Sw Broadway",
    "iso:country":"US",
    "sg:address":"515 SW Broadway",
    "sg:city":"Portland",
    "sg:classifiers":[
        {
            "category":"Shopping",
            "subcategory":"Clothing, Apparel, & Fashions",
            "type":"Retail Goods"
        }
    ],
    "sg:phone":"+1 503 223 1400",
    "sg:postcode":"97205",
    "sg:province":"OR",
    "sg:tags":[
        "tailoring",
        "sewing",
        "alteration",
        "wedding"
    ],
    "sg:website":"http://www.europeanmastertailor.com",
    "wof:name":"European Master Tailor",
    "wof:placetype":"venue"
},
  "geometry": {"coordinates":[-122.679001,45.520599],"type":"Point"}
}