{
  "type": "Feature",
  "properties": {
    "iso:country":"US",
    "sg:address":"2650 N 17th St",
    "sg:city":"Coos Bay",
    "sg:classifiers":[
        {
            "category":"Health Services",
            "subcategory":"Medical Lab",
            "type":"Services"
        }
    ],
    "sg:phone":"+1 541 267 5411",
    "sg:postcode":"97420",
    "sg:province":"OR",
    "sg:tags":[
        "resonance",
        "magnetic",
        "imaging"
    ],
    "wof:name":"South Coast Radiologists",
    "wof:placetype":"venue"
},
  "geometry": {"coordinates":[-124.232147,43.386494],"type":"Point"}
}