{
  "type": "Feature",
  "properties": {
    "iso:country":"US",
    "sg:address":"14211 SE McLoughlin Blvd",
    "sg:city":"Portland",
    "sg:classifiers":[
        {
            "category":"Building & Trades",
            "subcategory":"Locksmith",
            "type":"Services"
        }
    ],
    "sg:phone":"+1 503 303 6804",
    "sg:postcode":"97267",
    "sg:province":"OR",
    "sg:tags":[
        "key"
    ],
    "wof:name":"1 Alpha Lock and Key of or",
    "wof:placetype":"venue"
},
  "geometry": {"coordinates":[-122.633281,45.420527],"type":"Point"}
}