{
  "type": "Feature",
  "properties": {
    "iso:country":"US",
    "sg:address":"619 NE 3rd St",
    "sg:city":"Mcminnville",
    "sg:classifiers":[
        {
            "category":"Personal",
            "subcategory":"Beauty Salon",
            "type":"Services"
        }
    ],
    "sg:phone":"+1 503 472 5990",
    "sg:postcode":"97128",
    "sg:province":"OR",
    "wof:name":"Bradford's Barber Shop",
    "wof:placetype":"venue"
},
  "geometry": {"coordinates":[-123.193157,45.210096],"type":"Point"}
}