{
  "type": "Feature",
  "properties": {
    "iso:country":"US",
    "sg:address":"3610 Oak St SE",
    "sg:city":"Albany",
    "sg:classifiers":[
        {
            "category":"Education",
            "subcategory":"School",
            "type":"Public Place"
        }
    ],
    "sg:phone":"+1 541 967 4591",
    "sg:postcode":"97322",
    "sg:province":"OR",
    "sg:tags":[
        "elementary"
    ],
    "wof:name":"Oak Elementary School",
    "wof:placetype":"venue"
},
  "geometry": {"coordinates":[-123.085345,44.608536],"type":"Point"}
}