{
  "type": "Feature",
  "properties": {
    "iso:country":"US",
    "sg:address":"30143 Montmorence Dr",
    "sg:city":"Junction City",
    "sg:classifiers":[
        {
            "category":"Building & Trades",
            "subcategory":"Construction",
            "type":"Services"
        }
    ],
    "sg:phone":"+1 541 688 5336",
    "sg:postcode":"97448",
    "sg:province":"OR",
    "sg:tags":[
        "road"
    ],
    "wof:name":"Debbie Petree Construction",
    "wof:placetype":"venue"
},
  "geometry": {"coordinates":[-123.159637,44.160135],"type":"Point"}
}