{
  "type": "Feature",
  "properties": {
    "iso:country":"US",
    "sg:address":"11501 SW Pacific Hwy",
    "sg:city":"Tigard",
    "sg:classifiers":[
        {
            "category":"Insurance",
            "subcategory":"Insurance Agent",
            "type":"Services"
        }
    ],
    "sg:phone":"+1 503 245 1960",
    "sg:postcode":"97223",
    "sg:province":"OR",
    "sg:website":"www.aoawest.com",
    "wof:name":"AOA West Inc",
    "wof:placetype":"venue"
},
  "geometry": {"coordinates":[-122.74932,45.440888],"type":"Point"}
}