{
  "type": "Feature",
  "properties": {
    "iso:country":"US",
    "sg:address":"115 5th St",
    "sg:city":"Silverton",
    "sg:classifiers":[
        {
            "category":"Education",
            "subcategory":"Special Training",
            "type":"Public Place"
        }
    ],
    "sg:phone":"+1 503 873 6582",
    "sg:postcode":"97381",
    "sg:province":"OR",
    "sg:tags":[
        "educational"
    ],
    "wof:name":"Language Assets",
    "wof:placetype":"venue"
},
  "geometry": {"coordinates":[-122.77755500000001,45.00652],"type":"Point"}
}