{
  "type": "Feature",
  "properties": {
    "iso:country":"US",
    "sg:address":"6220 SW 112th Ave",
    "sg:city":"Beaverton",
    "sg:classifiers":[
        {
            "category":"Wholesale",
            "subcategory":"Groceries",
            "type":"Manufacturing & Wholesale Goods"
        }
    ],
    "sg:phone":"+1 503 643 4711",
    "sg:postcode":"97008",
    "sg:province":"OR",
    "sg:tags":[
        "food",
        "product"
    ],
    "wof:name":"Frito-Lay Inc",
    "wof:placetype":"venue"
},
  "geometry": {"coordinates":[-122.792631,45.475767],"type":"Point"}
}