{
  "type": "Feature",
  "properties": {
    "iso:country":"US",
    "sg:address":"1960 Mapleleaf Dr",
    "sg:city":"Lake Oswego",
    "sg:classifiers":[
        {
            "category":"Building & Trades",
            "subcategory":"Construction",
            "type":"Services"
        }
    ],
    "sg:phone":"+1 503 635 0844",
    "sg:postcode":"97034",
    "sg:province":"OR",
    "sg:tags":[
        "masonry",
        "contractor"
    ],
    "wof:name":"Daggett & Daggett Masonry",
    "wof:placetype":"venue"
},
  "geometry": {"coordinates":[-122.69729100000001,45.400434],"type":"Point"}
}