{
  "type": "Feature",
  "properties": {
    "addr:full":"56278 McDonald Rd Vernonia OR 97064",
    "addr:housenumber":"56278",
    "addr:postcode":"97064",
    "addr:street":"Mcdonald Rd",
    "iso:country":"US",
    "sg:address":"56278 McDonald Rd",
    "sg:city":"Vernonia",
    "sg:classifiers":[
        {
            "category":"Professional",
            "subcategory":"Management & Consulting",
            "type":"Services"
        }
    ],
    "sg:phone":"+1 503 429 7563",
    "sg:postcode":"97064",
    "sg:province":"OR",
    "sg:tags":[
        "business"
    ],
    "wof:name":"Rescue Training & Safety",
    "wof:placetype":"venue"
},
  "geometry": {"coordinates":[-123.194365,45.81403],"type":"Point"}
}