{
  "type": "Feature",
  "properties": {
    "iso:country":"US",
    "sg:address":"11481 SW Hall Blvd",
    "sg:city":"Portland",
    "sg:classifiers":[
        {
            "category":"Professional",
            "subcategory":"Management & Consulting",
            "type":"Services"
        }
    ],
    "sg:phone":"+1 503 684 9100",
    "sg:postcode":"97223",
    "sg:province":"OR",
    "wof:name":"Atsi Group",
    "wof:placetype":"venue"
},
  "geometry": {"coordinates":[-122.76545400000001,45.436571],"type":"Point"}
}