{
  "type": "Feature",
  "properties": {
    "iso:country":"US",
    "sg:address":"825 NE 20th Ave",
    "sg:city":"Portland",
    "sg:classifiers":[
        {
            "category":"Professional",
            "type":"Services"
        }
    ],
    "sg:phone":"+1 503 236 8544",
    "sg:postcode":"97232",
    "sg:province":"OR",
    "wof:name":"American Sales Inc",
    "wof:placetype":"venue"
},
  "geometry": {"coordinates":[-122.64546300000001,45.528866],"type":"Point"}
}