{
  "type": "Feature",
  "properties": {
    "iso:country":"US",
    "sg:address":"2099 River Rd",
    "sg:city":"Eugene",
    "sg:classifiers":[
        {
            "category":"Retail",
            "subcategory":"Auto Repair",
            "type":"Services"
        }
    ],
    "sg:phone":"+1 541 461 2645",
    "sg:postcode":"97404",
    "sg:province":"OR",
    "sg:tags":[
        "automotive",
        "lube",
        "oil"
    ],
    "wof:name":"Lube It Usa",
    "wof:placetype":"venue"
},
  "geometry": {"coordinates":[-123.12805899999999,44.095612],"type":"Point"}
}