{
  "type": "Feature",
  "properties": {
    "addr:full":"831 Railway St Silverton OR 97381",
    "addr:housenumber":"831",
    "addr:postcode":"97381",
    "addr:street":"Railway St",
    "iso:country":"US",
    "sg:address":"831 Railway St",
    "sg:city":"Silverton",
    "sg:classifiers":[
        {
            "category":"Freight",
            "type":"Transportation"
        }
    ],
    "sg:phone":"+1 503 873 8083",
    "sg:postcode":"97381",
    "sg:province":"OR",
    "sg:tags":[
        "commercial",
        "storage",
        "general"
    ],
    "wof:name":"Silver Creek Mini & Maxi Stor",
    "wof:placetype":"venue"
},
  "geometry": {"coordinates":[-122.796706,45.00525],"type":"Point"}
}