{
  "type": "Feature",
  "properties": {
    "iso:country":"US",
    "sg:address":"41030 Kingston Jordan Rd",
    "sg:city":"Scio",
    "sg:classifiers":[
        {
            "category":"Farming",
            "subcategory":"Farm & Veterinary Services",
            "type":"Manufacturing & Wholesale Goods"
        }
    ],
    "sg:phone":"+1 503 769 2673",
    "sg:postcode":"97374",
    "sg:province":"OR",
    "sg:tags":[
        "crop"
    ],
    "wof:name":"Kingston Irrigation Coop",
    "wof:placetype":"venue"
},
  "geometry": {"coordinates":[-122.773948,44.768157],"type":"Point"}
}