{
  "type": "Feature",
  "properties": {
    "iso:country":"US",
    "sg:address":"28182 Briggs Hill Rd",
    "sg:city":"Eugene",
    "sg:classifiers":[
        {
            "category":"Home & Garden",
            "subcategory":"Carpets & Floor Coverings",
            "type":"Retail Goods"
        }
    ],
    "sg:phone":"+1 541 431 4424",
    "sg:postcode":"97405",
    "sg:province":"OR",
    "wof:name":"Nationwide Floor & Window",
    "wof:placetype":"venue"
},
  "geometry": {"coordinates":[-123.235015,43.967694],"type":"Point"}
}