{
  "type": "Feature",
  "properties": {
    "addr:full":"3016 NE Broadway Street Portland OR 97232",
    "addr:housenumber":"3016",
    "addr:postcode":"97232",
    "addr:street":"Ne Broadway Street",
    "iso:country":"US",
    "sg:address":"3016 NE Broadway Street",
    "sg:city":"Portland",
    "sg:classifiers":[
        {
            "category":"Health Services",
            "subcategory":"Health Practitioner",
            "type":"Services"
        }
    ],
    "sg:phone":"+1 503 287 6636",
    "sg:postcode":"97232",
    "sg:province":"OR",
    "sg:tags":[
        "therapy",
        "physical"
    ],
    "wof:name":"Broadway Physical Therapy and Sports Rehabilitation",
    "wof:placetype":"venue"
},
  "geometry": {"coordinates":[-122.634399,45.535028],"type":"Point"}
}