{
  "type": "Feature",
  "properties": {
    "iso:country":"US",
    "sg:address":"906 NW 14th Ave",
    "sg:city":"Portland",
    "sg:classifiers":[
        {
            "category":"Shopping",
            "subcategory":"Clothing, Apparel, & Fashions",
            "type":"Retail Goods"
        }
    ],
    "sg:phone":"+1 503 274 0229",
    "sg:postcode":"97209",
    "sg:province":"OR",
    "sg:tags":[
        "accessory"
    ],
    "wof:name":"Cheeky B",
    "wof:placetype":"venue"
},
  "geometry": {"coordinates":[-122.685322,45.529982],"type":"Point"}
}