{
  "type": "Feature",
  "properties": {
    "addr:full":"4952 Parkhill St Lake Oswego OR 97035",
    "addr:housenumber":"4952",
    "addr:postcode":"97035",
    "addr:street":"Parkhill St",
    "iso:country":"US",
    "sg:address":"4952 Parkhill St",
    "sg:city":"Lake Oswego",
    "sg:classifiers":[
        {
            "category":"Wholesale",
            "subcategory":"Construction Materials",
            "type":"Manufacturing & Wholesale Goods"
        }
    ],
    "sg:phone":"+1 503 697 9454",
    "sg:postcode":"97035",
    "sg:province":"OR",
    "sg:tags":[
        "business"
    ],
    "wof:name":"Gilbert Forest Products",
    "wof:placetype":"venue"
},
  "geometry": {"coordinates":[-122.728342,45.413598],"type":"Point"}
}