{
  "type": "Feature",
  "properties": {
    "addr:full":"1204 Alameda Ave Astoria OR 97103",
    "addr:housenumber":"1204",
    "addr:postcode":"97103",
    "addr:street":"Alameda Ave",
    "iso:country":"US",
    "sg:address":"1204 Alameda Ave",
    "sg:city":"Astoria",
    "sg:classifiers":[
        {
            "category":"Professional",
            "subcategory":"Business Services",
            "type":"Services"
        }
    ],
    "sg:phone":"+1 503 325 5692",
    "sg:postcode":"97103",
    "sg:province":"OR",
    "sg:tags":[
        "machine",
        "quilting"
    ],
    "wof:name":"Astoria Quilting",
    "wof:placetype":"venue"
},
  "geometry": {"coordinates":[-123.84248100000001,46.174179],"type":"Point"}
}