{
  "type": "Feature",
  "properties": {
    "iso:country":"US",
    "sg:address":"525 NE 3rd St",
    "sg:city":"Mcminnville",
    "sg:classifiers":[
        {
            "category":"Food & Beverages",
            "subcategory":"Liquor & Beverages",
            "type":"Retail Goods"
        },
        {
            "category":"Shopping",
            "subcategory":"Gifts & Souvenirs",
            "type":"Retail Goods"
        }
    ],
    "sg:phone":"+1 503 434 2787",
    "sg:postcode":"97128",
    "sg:province":"OR",
    "sg:tags":[
        "alcoholic",
        "wine"
    ],
    "wof:name":"Old Noah's Wine Cellar",
    "wof:placetype":"venue"
},
  "geometry": {"coordinates":[-123.194202,45.210096],"type":"Point"}
}