{
  "type": "Feature",
  "properties": {
    "iso:country":"US",
    "sg:address":"29795 Ellensburg Ave",
    "sg:city":"Gold Beach",
    "sg:classifiers":[
        {
            "category":"Real Estate",
            "subcategory":"Real Estate Services",
            "type":"Services"
        }
    ],
    "sg:phone":"+1 541 247 7021",
    "sg:postcode":"97444",
    "sg:province":"OR",
    "sg:tags":[
        "company",
        "title"
    ],
    "wof:name":"Ocean Title & Escrow",
    "wof:placetype":"venue"
},
  "geometry": {"coordinates":[-124.420118,42.41607],"type":"Point"}
}