{
  "type": "Feature",
  "properties": {
    "iso:country":"US",
    "sg:address":"29682 Brownsville Rd",
    "sg:city":"Brownsville",
    "sg:classifiers":[
        {
            "category":"Retail",
            "subcategory":"Animal Services",
            "type":"Services"
        }
    ],
    "sg:phone":"+1 541 466 3154",
    "sg:postcode":"97327",
    "sg:province":"OR",
    "wof:name":"A-1 Dog Grooming",
    "wof:placetype":"venue"
},
  "geometry": {"coordinates":[-122.989128,44.451974],"type":"Point"}
}