{
  "type": "Feature",
  "properties": {
    "iso:country":"US",
    "sg:address":"2211 Canal St",
    "sg:city":"Medford",
    "sg:classifiers":[
        {
            "category":"Professional",
            "type":"Services"
        }
    ],
    "sg:phone":"+1 541 770 6728",
    "sg:postcode":"97501",
    "sg:province":"OR",
    "wof:name":"Husband For Hire",
    "wof:placetype":"venue"
},
  "geometry": {"coordinates":[-122.894368,42.298138],"type":"Point"}
}