{
  "type": "Feature",
  "properties": {
    "iso:country":"US",
    "sg:address":"970 W 7th Ave",
    "sg:city":"Eugene",
    "sg:classifiers":[
        {
            "category":"Professional",
            "subcategory":"Research",
            "type":"Services"
        }
    ],
    "sg:phone":"+1 541 687 8976",
    "sg:postcode":"97402",
    "sg:province":"OR",
    "sg:tags":[
        "nonphysical",
        "commercial"
    ],
    "wof:name":"Northwest Survey & Data Svc",
    "wof:placetype":"venue"
},
  "geometry": {"coordinates":[-123.108378,44.052077],"type":"Point"}
}