{
  "type": "Feature",
  "properties": {
    "iso:country":"US",
    "sg:address":"3361 NE Oneil Way",
    "sg:city":"Redmond",
    "sg:classifiers":[
        {
            "category":"Recreation",
            "type":"Entertainment"
        }
    ],
    "sg:phone":"+1 541 382 1819",
    "sg:postcode":"97756",
    "sg:province":"OR",
    "sg:tags":[
        "club",
        "membership"
    ],
    "wof:name":"Arabian House Club Central Ore",
    "wof:placetype":"venue"
},
  "geometry": {"coordinates":[-121.120199,44.325677],"type":"Point"}
}