{
  "type": "Feature",
  "properties": {
    "addr:full":"4717 SE Belmont Street Portland OR 97215",
    "addr:housenumber":"4717",
    "addr:postcode":"97215",
    "addr:street":"Se Belmont Street",
    "iso:country":"US",
    "sg:address":"4717 SE Belmont Street",
    "sg:city":"Portland",
    "sg:classifiers":[
        {
            "category":"Personal",
            "subcategory":"Skin Care",
            "type":"Services"
        }
    ],
    "sg:phone":"+1 503 236 5926",
    "sg:postcode":"97215",
    "sg:province":"OR",
    "wof:name":"Alexandra Avery Purely Natural Skin Care",
    "wof:placetype":"venue"
},
  "geometry": {"coordinates":[-122.613896,45.516674],"type":"Point"}
}