{
  "type": "Feature",
  "properties": {
    "addr:full":"17429 SE Franklin Ct Portland OR 97236",
    "addr:postcode":"17429;97236",
    "addr:street":"Se Franklin Ct",
    "iso:country":"US",
    "sg:address":"17429 SE Franklin Ct",
    "sg:city":"Portland",
    "sg:classifiers":[
        {
            "category":"Personal",
            "subcategory":"Beauty Salon",
            "type":"Services"
        }
    ],
    "sg:phone":"+1 503 762 6760",
    "sg:postcode":"97236",
    "sg:province":"OR",
    "sg:tags":[
        "shop"
    ],
    "wof:name":"Happy Nails",
    "wof:placetype":"venue"
},
  "geometry": {"coordinates":[-122.484476,45.499119],"type":"Point"}
}