{
  "type": "Feature",
  "properties": {
    "addr:full":"16353 SE Division St Portland OR 97236",
    "addr:postcode":"16353;97236",
    "addr:street":"Se Division St",
    "iso:country":"US",
    "sg:address":"16353 SE Division St",
    "sg:city":"Portland",
    "sg:classifiers":[
        {
            "category":"Retail",
            "subcategory":"Self-service Laundry",
            "type":"Services"
        }
    ],
    "sg:phone":"+1 503 761 0992",
    "sg:postcode":"97236",
    "sg:province":"OR",
    "wof:name":"H2o Laundry Mat",
    "wof:placetype":"venue"
},
  "geometry": {"coordinates":[-122.495858,45.504654],"type":"Point"}
}