{
  "type": "Feature",
  "properties": {
    "addr:full":"51920 SW South Rd Gaston OR 97119",
    "addr:housenumber":"51920",
    "addr:postcode":"97119",
    "addr:street":"Sw South Rd",
    "iso:country":"US",
    "sg:address":"51920 SW South Rd",
    "sg:city":"Gaston",
    "sg:phone":"+1 503 985 7628",
    "sg:postcode":"97119",
    "sg:province":"OR",
    "sg:tags":[
        "farming"
    ],
    "wof:name":"Donald L Darby",
    "wof:placetype":"venue"
},
  "geometry": {"coordinates":[-123.213339,45.433599],"type":"Point"}
}