{
  "type": "Feature",
  "properties": {
    "addr:full":"7615 SW 13th Ave Portland OR 97219",
    "addr:housenumber":"7615",
    "addr:postcode":"97219",
    "addr:street":"Sw 13Th Ave",
    "iso:country":"US",
    "sg:address":"7615 SW 13th Ave",
    "sg:city":"Portland",
    "sg:classifiers":[
        {
            "category":"Banks & Credit Unions",
            "subcategory":"Bank",
            "type":"Services"
        }
    ],
    "sg:phone":"+1 503 225 3151",
    "sg:postcode":"97219",
    "sg:province":"OR",
    "sg:tags":[
        "national",
        "commercial"
    ],
    "sg:website":"www.wellsfargo.com",
    "wof:name":"Wells Fargo",
    "wof:placetype":"venue"
},
  "geometry": {"coordinates":[-122.692438,45.469272],"type":"Point"}
}