{
  "type": "Feature",
  "properties": {
    "iso:country":"US",
    "sg:address":"382B S 58th St",
    "sg:city":"Springfield",
    "sg:classifiers":[
        {
            "category":"Social Services",
            "subcategory":"Adult Care",
            "type":"Services"
        },
        {
            "category":"Social Services",
            "subcategory":"Retirement Home",
            "type":"Services"
        }
    ],
    "sg:phone":"+1 541 747 4858",
    "sg:postcode":"97478",
    "sg:province":"OR",
    "sg:tags":[
        "living",
        "assisted",
        "convalescent",
        "nursing",
        "elder"
    ],
    "sg:website":"http://www.elderhealthandliving.com",
    "wof:name":"ElderHealth & Living",
    "wof:placetype":"venue"
},
  "geometry": {"coordinates":[-122.926727,44.042788],"type":"Point"}
}