{
  "type": "Feature",
  "properties": {
    "addr:full":"171 Steelhammer Rd Silverton OR 97381",
    "addr:housenumber":"171",
    "addr:postcode":"97381",
    "addr:street":"Steelhammer Rd",
    "iso:country":"US",
    "sg:address":"171 Steelhammer Rd",
    "sg:city":"Silverton",
    "sg:classifiers":[
        {
            "category":"Health Services",
            "subcategory":"Nursing And Care Facility",
            "type":"Services"
        }
    ],
    "sg:phone":"+1 503 873 7316",
    "sg:postcode":"97381",
    "sg:province":"OR",
    "sg:tags":[
        "home",
        "rest"
    ],
    "wof:name":"Wisdom Keepers Senior Care Hm",
    "wof:placetype":"venue"
},
  "geometry": {"coordinates":[-122.77006799999999,45.008662],"type":"Point"}
}