{
  "type": "Feature",
  "properties": {
    "iso:country":"US",
    "sg:address":"511 NW Couch St",
    "sg:city":"Portland",
    "sg:classifiers":[
        {
            "category":"Recreation",
            "subcategory":"Amusement Park",
            "type":"Entertainment"
        }
    ],
    "sg:phone":"+1 503 796 9364",
    "sg:postcode":"97209",
    "sg:province":"OR",
    "sg:tags":[
        "arcade"
    ],
    "sg:website":"www.groundkontrol.com",
    "wof:name":"Ground Kontrol",
    "wof:placetype":"venue"
},
  "geometry": {"coordinates":[-122.675872,45.523804],"type":"Point"}
}