{
  "type": "Feature",
  "properties": {
    "iso:country":"US",
    "sg:address":"1623 Orchard Rd",
    "sg:city":"Hood River",
    "sg:classifiers":[
        {
            "category":"Farming",
            "subcategory":"Orchard",
            "type":"Manufacturing & Wholesale Goods"
        }
    ],
    "sg:phone":"+1 541 386 5478",
    "sg:postcode":"97031",
    "sg:province":"OR",
    "sg:tags":[
        "fruit",
        "tree"
    ],
    "wof:name":"Shadow Fax",
    "wof:placetype":"venue"
},
  "geometry": {"coordinates":[-121.528873,45.674648],"type":"Point"}
}