{
  "type": "Feature",
  "properties": {
    "iso:country":"US",
    "sg:address":"2240 SE 82nd Ave",
    "sg:city":"Portland",
    "sg:classifiers":[
        {
            "category":"Autos & Motor Vehicles",
            "subcategory":"Auto Supplies",
            "type":"Retail Goods"
        },
        {
            "category":"Manufacturing",
            "subcategory":"Glass & Minerals",
            "type":"Manufacturing & Wholesale Goods"
        }
    ],
    "sg:phone":"+1 503 329 4948",
    "sg:postcode":"97216",
    "sg:province":"OR",
    "sg:tags":[
        "plate",
        "stereo",
        "repair",
        "automobile",
        "coating",
        "system",
        "tinting",
        "window",
        "radio",
        "replacement"
    ],
    "sg:website":"http://WWW.THETINTGUY1.COM",
    "wof:name":"THE TINT GUY",
    "wof:placetype":"venue"
},
  "geometry": {"coordinates":[-122.578678,45.506742],"type":"Point"}
}