{
  "type": "Feature",
  "properties": {
    "addr:full":"145 SW 137th Ave Beaverton OR 97006",
    "addr:housenumber":"145",
    "addr:postcode":"97006",
    "addr:street":"Sw 137Th Ave",
    "iso:country":"US",
    "sg:address":"145 SW 137th Ave",
    "sg:city":"Beaverton",
    "sg:classifiers":[
        {
            "category":"Professional",
            "subcategory":"Business Services",
            "type":"Services"
        }
    ],
    "sg:phone":"+1 503 520 9112",
    "sg:postcode":"97006",
    "sg:province":"OR",
    "wof:name":"Werth Drafting Services",
    "wof:placetype":"venue"
},
  "geometry": {"coordinates":[-122.817971,45.518197],"type":"Point"}
}