{
  "type": "Feature",
  "properties": {
    "iso:country":"US",
    "sg:address":"4755 SW Watson Ave",
    "sg:city":"Beaverton",
    "sg:classifiers":[
        {
            "category":"Social Services",
            "type":"Services"
        }
    ],
    "sg:phone":"+1 503 644 9696",
    "sg:postcode":"97005",
    "sg:province":"OR",
    "sg:tags":[
        "counseling"
    ],
    "wof:name":"Rob Solomon Consulting",
    "wof:placetype":"venue"
},
  "geometry": {"coordinates":[-122.806478,45.485402],"type":"Point"}
}