{
  "type": "Feature",
  "properties": {
    "iso:country":"US",
    "sg:address":"1014 SE 50th Ave",
    "sg:city":"Portland",
    "sg:classifiers":[
        {
            "category":"Professional",
            "subcategory":"Management & Consulting",
            "type":"Services"
        }
    ],
    "sg:phone":"+1 503 516 2785",
    "sg:postcode":"97215",
    "sg:province":"OR",
    "sg:tags":[
        "business"
    ],
    "wof:name":"Metaresource Group",
    "wof:placetype":"venue"
},
  "geometry": {"coordinates":[-122.611165,45.516071],"type":"Point"}
}