{
  "type": "Feature",
  "properties": {
    "addr:full":"940 N 10th Ave Stayton OR 97383",
    "addr:housenumber":"940",
    "addr:postcode":"97383",
    "addr:street":"N 10Th Ave",
    "iso:country":"US",
    "sg:address":"940 N 10th Ave",
    "sg:city":"Stayton",
    "sg:classifiers":[
        {
            "category":"Manufacturing",
            "subcategory":"Buildings",
            "type":"Manufacturing & Wholesale Goods"
        },
        {
            "category":"Building & Trades",
            "subcategory":"Construction",
            "type":"Services"
        }
    ],
    "sg:phone":"+1 503 769 1902",
    "sg:postcode":"97383",
    "sg:province":"OR",
    "sg:tags":[
        "home",
        "builder",
        "contractor"
    ],
    "wof:name":"Glen Meyer Construction",
    "wof:placetype":"venue"
},
  "geometry": {"coordinates":[-122.784155,44.8024],"type":"Point"}
}