{
  "type": "Feature",
  "properties": {
    "iso:country":"US",
    "sg:address":"525 A St",
    "sg:city":"Ashland",
    "sg:classifiers":[
        {
            "category":"Shopping",
            "type":"Retail Goods"
        }
    ],
    "sg:phone":"+1 541 482 2069",
    "sg:postcode":"97520",
    "sg:province":"OR",
    "sg:tags":[
        "art",
        "gallery",
        "dealer"
    ],
    "wof:name":"Davis & Cline Gallery",
    "wof:placetype":"venue"
},
  "geometry": {"coordinates":[-122.70685400000001,42.198204],"type":"Point"}
}