{
  "type": "Feature",
  "properties": {
    "addr:full":"4540 NW Sewell Rd Hillsboro OR 97124",
    "addr:housenumber":"4540",
    "addr:postcode":"97124",
    "addr:street":"Nw Sewell Rd",
    "iso:country":"US",
    "sg:address":"4540 NW Sewell Rd",
    "sg:city":"Hillsboro",
    "sg:classifiers":[
        {
            "category":"Building & Trades",
            "subcategory":"Landscaping Services",
            "type":"Services"
        }
    ],
    "sg:phone":"+1 503 648 6752",
    "sg:postcode":"97124",
    "sg:province":"OR",
    "sg:tags":[
        "landscape"
    ],
    "wof:name":"Swedes Plant Maintenance",
    "wof:placetype":"venue"
},
  "geometry": {"coordinates":[-122.952681,45.553038],"type":"Point"}
}