{
  "type": "Feature",
  "properties": {
    "iso:country":"US",
    "sg:address":"5050 Hoyt Ste 660",
    "sg:city":"Portland",
    "sg:classifiers":[
        {
            "category":"Health Services",
            "subcategory":"Clinic",
            "type":"Services"
        }
    ],
    "sg:phone":"+1 503 239 8430",
    "sg:postcode":"97213",
    "sg:province":"OR",
    "sg:tags":[
        "medical"
    ],
    "wof:name":"Dr. Mark Buehler",
    "wof:placetype":"venue"
},
  "geometry": {"coordinates":[-122.610854,45.526925],"type":"Point"}
}