{
  "type": "Feature",
  "properties": {
    "addr:full":"16900 SE 82nd Dr Clackamas OR 97015",
    "addr:postcode":"16900;97015",
    "addr:street":"Se 82Nd Dr",
    "iso:country":"US",
    "sg:address":"16900 SE 82nd Dr",
    "sg:city":"Clackamas",
    "sg:classifiers":[
        {
            "category":"Professional",
            "subcategory":"Management & Consulting",
            "type":"Services"
        }
    ],
    "sg:phone":"+1 503 722 8077",
    "sg:postcode":"97015",
    "sg:province":"OR",
    "sg:tags":[
        "veterinary",
        "business"
    ],
    "wof:name":"Veterinary Diagnostic Imgng PC",
    "wof:placetype":"venue"
},
  "geometry": {"coordinates":[-122.56903200000001,45.400136],"type":"Point"}
}