{
  "type": "Feature",
  "properties": {
    "iso:country":"US",
    "sg:address":"1000 Oregon St",
    "sg:city":"Port Orford",
    "sg:classifiers":[
        {
            "category":"Banks & Credit Unions",
            "subcategory":"Bank",
            "type":"Services"
        }
    ],
    "sg:phone":"+1 541 332 3711",
    "sg:postcode":"97465",
    "sg:province":"OR",
    "sg:tags":[
        "federal"
    ],
    "wof:name":"Chetco Federal Credit Union",
    "wof:placetype":"venue"
},
  "geometry": {"coordinates":[-124.497394,42.746609],"type":"Point"}
}