{
  "type": "Feature",
  "properties": {
    "iso:country":"US",
    "sg:address":"8433 Green Valley Rd",
    "sg:city":"Oakland",
    "sg:classifiers":[
        {
            "category":"Building & Trades",
            "subcategory":"Construction",
            "type":"Services"
        }
    ],
    "sg:phone":"+1 541 459 2040",
    "sg:postcode":"97462",
    "sg:province":"OR",
    "sg:tags":[
        "excavation",
        "contractor"
    ],
    "wof:name":"Swan Excavation",
    "wof:placetype":"venue"
},
  "geometry": {"coordinates":[-123.407242,43.468474],"type":"Point"}
}