{
  "type": "Feature",
  "properties": {
    "addr:full":"13021 SE Hubbard Rd Clackamas OR 97015",
    "addr:housenumber":"13021",
    "addr:postcode":"97015",
    "addr:street":"Se Hubbard Rd",
    "iso:country":"US",
    "sg:address":"13021 SE Hubbard Rd",
    "sg:city":"Clackamas",
    "sg:classifiers":[
        {
            "category":"Education",
            "subcategory":"School",
            "type":"Public Place"
        }
    ],
    "sg:phone":"+1 503 698 3498",
    "sg:postcode":"97015",
    "sg:province":"OR",
    "wof:name":"North Clackamus Land Lab",
    "wof:placetype":"venue"
},
  "geometry": {"coordinates":[-122.529487,45.414028],"type":"Point"}
}