{
  "type": "Feature",
  "properties": {
    "addr:full":"1598 River Loop 1 Eugene OR 97404",
    "addr:housenumber":"1598;1",
    "addr:postcode":"97404",
    "addr:street":"River Loop",
    "iso:country":"US",
    "sg:address":"1598 River Loop 1",
    "sg:city":"Eugene",
    "sg:classifiers":[
        {
            "category":"Real Estate",
            "subcategory":"Real Estate Agent",
            "type":"Services"
        }
    ],
    "sg:phone":"+1 541 689 7942",
    "sg:postcode":"97404",
    "sg:province":"OR",
    "wof:name":"Vermeer Investments Appraisal",
    "wof:placetype":"venue"
},
  "geometry": {"coordinates":[-123.11541099999999,44.124877],"type":"Point"}
}