{
  "type": "Feature",
  "properties": {
    "iso:country":"US",
    "sg:address":"821 E 13th Ave",
    "sg:city":"Eugene",
    "sg:classifiers":[
        {
            "category":"Retail",
            "subcategory":"Laundry & Dry Cleaning",
            "type":"Services"
        }
    ],
    "sg:phone":"+1 541 345 6321",
    "sg:postcode":"97401",
    "sg:province":"OR",
    "sg:tags":[
        "garment",
        "agent",
        "cleaners"
    ],
    "wof:name":"Siegmund's Cleaners",
    "wof:placetype":"venue"
},
  "geometry": {"coordinates":[-123.078959,44.045586],"type":"Point"}
}