{
  "type": "Feature",
  "properties": {
    "addr:full":"1400 Executive Pkwy Eugene OR 97401",
    "addr:housenumber":"1400",
    "addr:postcode":"97401",
    "addr:street":"Executive Pkwy",
    "iso:country":"US",
    "sg:address":"1400 Executive Pkwy",
    "sg:city":"Eugene",
    "sg:classifiers":[
        {
            "category":"Real Estate",
            "subcategory":"Real Estate Operator",
            "type":"Services"
        }
    ],
    "sg:phone":"+1 541 349 7536",
    "sg:postcode":"97401",
    "sg:province":"OR",
    "sg:tags":[
        "apartment"
    ],
    "wof:name":"Real Holdings",
    "wof:placetype":"venue"
},
  "geometry": {"coordinates":[-123.10917600000001,44.070141],"type":"Point"}
}