{
  "type": "Feature",
  "properties": {
    "addr:full":"6350 SW 124th Ave Beaverton OR 97008",
    "addr:housenumber":"6350",
    "addr:postcode":"97008",
    "addr:street":"Sw 124Th Ave",
    "iso:country":"US",
    "sg:address":"6350 SW 124th Ave",
    "sg:city":"Beaverton",
    "sg:classifiers":[
        {
            "category":"Real Estate",
            "subcategory":"Real Estate Operator",
            "type":"Services"
        }
    ],
    "sg:phone":"+1 503 469 0700",
    "sg:postcode":"97008",
    "sg:province":"OR",
    "sg:tags":[
        "apartment"
    ],
    "sg:website":"princetonproperty.com/HermitageH...",
    "wof:name":"The Hermitage",
    "wof:placetype":"venue"
},
  "geometry": {"coordinates":[-122.803988,45.474203],"type":"Point"}
}