{
  "type": "Feature",
  "properties": {
    "iso:country":"US",
    "sg:address":"5103 NE Fremont Street",
    "sg:city":"Portland",
    "sg:classifiers":[
        {
            "category":"Bars & Pubs",
            "subcategory":"Dive Bar",
            "type":"Food & Drink"
        }
    ],
    "sg:phone":"+1 503 288 2515",
    "sg:postcode":"97213",
    "sg:province":"OR",
    "wof:name":"Freemont Ridge Inn",
    "wof:placetype":"venue"
},
  "geometry": {"coordinates":[-122.610033,45.548384],"type":"Point"}
}