{
  "type": "Feature",
  "properties": {
    "iso:country":"US",
    "sg:address":"4027 Melqua Rd",
    "sg:city":"Roseburg",
    "sg:classifiers":[
        {
            "category":"Shopping",
            "subcategory":"Computers & Home Electronics",
            "type":"Retail Goods"
        }
    ],
    "sg:phone":"+1 541 440 9088",
    "sg:postcode":"97470",
    "sg:province":"OR",
    "sg:tags":[
        "parts",
        "supply"
    ],
    "wof:name":"Best Toner Cartridge Remfg",
    "wof:placetype":"venue"
},
  "geometry": {"coordinates":[-123.469306,43.288427],"type":"Point"}
}