{
  "type": "Feature",
  "properties": {
    "addr:full":"215 Oswego Summit Lake Oswego OR 97035",
    "addr:housenumber":"215",
    "addr:postcode":"97035",
    "addr:street":"Oswego Summit",
    "iso:country":"US",
    "sg:address":"215 Oswego Summit",
    "sg:city":"Lake Oswego",
    "sg:classifiers":[
        {
            "category":"Organizations",
            "subcategory":"Community Association",
            "type":"Services"
        }
    ],
    "sg:phone":"+1 503 635 4000",
    "sg:postcode":"97035",
    "sg:province":"OR",
    "sg:tags":[
        "condominium"
    ],
    "wof:name":"Oswego Summit Condominiums",
    "wof:placetype":"venue"
},
  "geometry": {"coordinates":[-122.715346,45.43497],"type":"Point"}
}