{
  "type": "Feature",
  "properties": {
    "iso:country":"US",
    "sg:address":"7 Winburn Way",
    "sg:city":"Ashland",
    "sg:classifiers":[
        {
            "category":"Shopping",
            "subcategory":"Used Merchandise",
            "type":"Retail Goods"
        }
    ],
    "sg:phone":"+1 541 488 2844",
    "sg:postcode":"97520",
    "sg:province":"OR",
    "wof:name":"Wild Rose",
    "wof:placetype":"venue"
},
  "geometry": {"coordinates":[-122.71522899999999,42.197167],"type":"Point"}
}