{
  "type": "Feature",
  "properties": {
    "iso:country":"US",
    "sg:address":"6750 NE Broadway Street",
    "sg:city":"Portland",
    "sg:classifiers":[
        {
            "category":"Food & Beverages",
            "subcategory":"Groceries & Convenience Stores",
            "type":"Retail Goods"
        }
    ],
    "sg:phone":"+1 503 251 0524",
    "sg:postcode":"97213",
    "sg:province":"OR",
    "wof:name":"Pacific Supermarkets",
    "wof:placetype":"venue"
},
  "geometry": {"coordinates":[-122.59396,45.534774],"type":"Point"}
}