{
  "type": "Feature",
  "properties": {
    "addr:full":"33810 SE Terra Cir Corvallis OR 97333",
    "addr:postcode":"33810;97333",
    "addr:street":"Se Terra Cir",
    "iso:country":"US",
    "sg:address":"33810 SE Terra Cir",
    "sg:city":"Corvallis",
    "sg:classifiers":[
        {
            "category":"Building & Trades",
            "subcategory":"Construction",
            "type":"Services"
        }
    ],
    "sg:phone":"+1 541 758 6309",
    "sg:postcode":"97333",
    "sg:province":"OR",
    "sg:tags":[
        "excavation",
        "contractor"
    ],
    "wof:name":"Linn Benton Excavation Inc",
    "wof:placetype":"venue"
},
  "geometry": {"coordinates":[-123.22022800000001,44.561502],"type":"Point"}
}