{
  "type": "Feature",
  "properties": {
    "iso:country":"US",
    "sg:address":"645 SW 56th St",
    "sg:city":"Corvallis",
    "sg:classifiers":[
        {
            "category":"Personal",
            "subcategory":"Beauty Salon",
            "type":"Services"
        }
    ],
    "sg:phone":"+1 541 738 2557",
    "sg:postcode":"97333",
    "sg:province":"OR",
    "wof:name":"Sister Act Studio & Spa",
    "wof:placetype":"venue"
},
  "geometry": {"coordinates":[-123.315226,44.560187],"type":"Point"}
}