{
  "type": "Feature",
  "properties": {
    "iso:country":"US",
    "sg:address":"1253 NW Canal Blvd",
    "sg:city":"Redmond",
    "sg:classifiers":[
        {
            "category":"Health Services",
            "subcategory":"Doctor",
            "type":"Services"
        }
    ],
    "sg:phone":"+1 541 923 0728",
    "sg:postcode":"97756",
    "sg:province":"OR",
    "sg:tags":[
        "clinic",
        "medical"
    ],
    "wof:name":"James R Karmy Inc",
    "wof:placetype":"venue"
},
  "geometry": {"coordinates":[-121.168443,44.288967],"type":"Point"}
}