{
  "type": "Feature",
  "properties": {
    "addr:full":"1439 NE 6th St Grants Pass OR 97526",
    "addr:housenumber":"1439",
    "addr:postcode":"97526",
    "addr:street":"Ne 6Th St",
    "iso:country":"US",
    "sg:address":"1439 NE 6th St",
    "sg:city":"Grants Pass",
    "sg:classifiers":[
        {
            "category":"Freight",
            "type":"Transportation"
        }
    ],
    "sg:phone":"+1 541 472 8327",
    "sg:postcode":"97526",
    "sg:province":"OR",
    "sg:tags":[
        "operator",
        "local",
        "trucking"
    ],
    "wof:name":"Pacer",
    "wof:placetype":"venue"
},
  "geometry": {"coordinates":[-123.322503,42.453603],"type":"Point"}
}