{
  "type": "Feature",
  "properties": {
    "addr:full":"11800 SW Military Ln Portland OR 97219",
    "addr:housenumber":"11800",
    "addr:postcode":"97219",
    "addr:street":"Sw Military Ln",
    "iso:country":"US",
    "sg:address":"11800 SW Military Ln",
    "sg:city":"Portland",
    "sg:classifiers":[
        {
            "category":"Organizations",
            "subcategory":"Religious Organization",
            "type":"Services"
        }
    ],
    "sg:phone":"+1 503 636 5613",
    "sg:postcode":"97219",
    "sg:province":"OR",
    "sg:tags":[
        "episcopal",
        "church"
    ],
    "wof:name":"Episcpal Chrch Diocesan Hdqtrs",
    "wof:placetype":"venue"
},
  "geometry": {"coordinates":[-122.65365,45.441729],"type":"Point"}
}