{
  "type": "Feature",
  "properties": {
    "iso:country":"US",
    "sg:address":"879 SW Levens St",
    "sg:city":"Dallas",
    "sg:classifiers":[
        {
            "category":"Organizations",
            "subcategory":"Religious Organization",
            "type":"Services"
        }
    ],
    "sg:phone":"+1 503 623 3397",
    "sg:postcode":"97338",
    "sg:province":"OR",
    "sg:tags":[
        "church"
    ],
    "wof:name":"First Presbyterian Church",
    "wof:placetype":"venue"
},
  "geometry": {"coordinates":[-123.320196,44.92071],"type":"Point"}
}