{
  "type": "Feature",
  "properties": {
    "iso:country":"US",
    "sg:address":"17325 SE McLoughlin Blvd",
    "sg:city":"Portland",
    "sg:classifiers":[
        {
            "category":"Manufacturing",
            "subcategory":"Motor Vehicles & Parts",
            "type":"Manufacturing & Wholesale Goods"
        }
    ],
    "sg:phone":"+1 503 654 2175",
    "sg:postcode":"97267",
    "sg:province":"OR",
    "sg:tags":[
        "automobile",
        "supply"
    ],
    "sg:website":"www.quickor.com",
    "wof:name":"Quickor Suspension",
    "wof:placetype":"venue"
},
  "geometry": {"coordinates":[-122.617743,45.397629],"type":"Point"}
}