{
  "type": "Feature",
  "properties": {
    "addr:full":"8240 SW Macadam Ave Portland OR 97219",
    "addr:housenumber":"8240",
    "addr:postcode":"97219",
    "addr:street":"Sw Macadam Ave",
    "iso:country":"US",
    "sg:address":"8240 SW Macadam Ave",
    "sg:city":"Portland",
    "sg:classifiers":[
        {
            "category":"Autos & Motor Vehicles",
            "subcategory":"Boat Sales",
            "type":"Retail Goods"
        }
    ],
    "sg:phone":"+1 503 244 7505",
    "sg:postcode":"97219",
    "sg:province":"OR",
    "sg:tags":[
        "dealer",
        "sales"
    ],
    "sg:website":"www.staffjennings.com",
    "wof:name":"Staff Jennings Boating Ctr",
    "wof:placetype":"venue"
},
  "geometry": {"coordinates":[-122.668479,45.464588],"type":"Point"}
}