{
  "type": "Feature",
  "properties": {
    "iso:country":"US",
    "sg:address":"8219 SE 17th Ave",
    "sg:city":"Portland",
    "sg:classifiers":[
        {
            "category":"Real Estate",
            "subcategory":"Real Estate Agent",
            "type":"Services"
        },
        {
            "category":"Professional",
            "subcategory":"Business Services",
            "type":"Services"
        }
    ],
    "sg:phone":"+1 503 230 8018",
    "sg:postcode":"97202",
    "sg:province":"OR",
    "sg:tags":[
        "appraiser"
    ],
    "wof:name":"Appraisal Resource",
    "wof:placetype":"venue"
},
  "geometry": {"coordinates":[-122.647115,45.463024],"type":"Point"}
}