{
  "type": "Feature",
  "properties": {
    "iso:country":"US",
    "sg:address":"5327 N Interstate Avenue",
    "sg:city":"Portland",
    "sg:classifiers":[
        {
            "category":"Restaurant",
            "type":"Food & Drink"
        }
    ],
    "sg:phone":"+1 503 735 1191",
    "sg:postcode":"97217",
    "sg:province":"OR",
    "sg:website":"www.tacotime.com",
    "wof:name":"Taco Time",
    "wof:placetype":"venue"
},
  "geometry": {"coordinates":[-122.682501,45.561701],"type":"Point"}
}