{
  "type": "Feature",
  "properties": {
    "iso:country":"US",
    "sg:address":"25590 Chinook St",
    "sg:city":"Cloverdale",
    "sg:classifiers":[
        {
            "category":"Real Estate",
            "subcategory":"Real Estate Operator",
            "type":"Services"
        }
    ],
    "sg:phone":"+1 503 398 5191",
    "sg:postcode":"97112",
    "sg:province":"OR",
    "sg:tags":[
        "property",
        "lessor"
    ],
    "wof:name":"William Buck",
    "wof:placetype":"venue"
},
  "geometry": {"coordinates":[-123.83489299999999,45.268396],"type":"Point"}
}