{
  "type": "Feature",
  "properties": {
    "iso:country":"US",
    "sg:address":"1008 SE 212th Ave",
    "sg:city":"Gresham",
    "sg:classifiers":[
        {
            "category":"Building & Trades",
            "subcategory":"Construction",
            "type":"Services"
        }
    ],
    "sg:phone":"+1 503 661 8824",
    "sg:postcode":"97030",
    "sg:province":"OR",
    "sg:tags":[
        "house"
    ],
    "wof:name":"JDC Construction",
    "wof:placetype":"venue"
},
  "geometry": {"coordinates":[-122.444804,45.515465],"type":"Point"}
}