{
  "type": "Feature",
  "properties": {
    "addr:full":"1708 SW Hawthorne Ter Portland OR 97201",
    "addr:housenumber":"1708",
    "addr:postcode":"97201",
    "addr:street":"Sw;Ter",
    "iso:country":"US",
    "sg:address":"1708 SW Hawthorne Ter",
    "sg:city":"Portland",
    "sg:classifiers":[
        {
            "category":"Real Estate",
            "subcategory":"Real Estate Operator",
            "type":"Services"
        }
    ],
    "sg:phone":"+1 503 241 1304",
    "sg:postcode":"97201",
    "sg:province":"OR",
    "sg:tags":[
        "property",
        "lessor"
    ],
    "wof:name":"Your Own French Home LLC",
    "wof:placetype":"venue"
},
  "geometry": {"coordinates":[-122.70009,45.507596],"type":"Point"}
}