{
  "type": "Feature",
  "properties": {
    "iso:country":"US",
    "sg:address":"2255 33rd St",
    "sg:city":"Springfield",
    "sg:classifiers":[
        {
            "category":"Health Services",
            "subcategory":"Nursing And Care Facility",
            "type":"Services"
        }
    ],
    "sg:phone":"+1 541 726 6370",
    "sg:postcode":"97477",
    "sg:province":"OR",
    "sg:tags":[
        "skilled"
    ],
    "wof:name":"On Call Nursing Service LLC",
    "wof:placetype":"venue"
},
  "geometry": {"coordinates":[-122.978299,44.068952],"type":"Point"}
}