{
  "type": "Feature",
  "properties": {
    "iso:country":"US",
    "sg:address":"873 NW Grant Ave",
    "sg:city":"Corvallis",
    "sg:classifiers":[
        {
            "category":"Professional",
            "subcategory":"Employment Agencies",
            "type":"Services"
        }
    ],
    "sg:phone":"+1 541 753 8220",
    "sg:postcode":"97330",
    "sg:province":"OR",
    "wof:name":"Saint Vincent De Paul Staffing",
    "wof:placetype":"venue"
},
  "geometry": {"coordinates":[-123.261878,44.57971],"type":"Point"}
}