{
  "type": "Feature",
  "properties": {
    "iso:country":"US",
    "sg:address":"3981 Crater Lake Hwy",
    "sg:city":"Medford",
    "sg:classifiers":[
        {
            "category":"Manufacturing",
            "subcategory":"Signs",
            "type":"Manufacturing & Wholesale Goods"
        }
    ],
    "sg:phone":"+1 541 773 2765",
    "sg:postcode":"97504",
    "sg:province":"OR",
    "sg:tags":[
        "shop",
        "manufacture",
        "barricade",
        "rent"
    ],
    "wof:name":"Cantel Of Medford Inc",
    "wof:placetype":"venue"
},
  "geometry": {"coordinates":[-122.85601,42.376643],"type":"Point"}
}