{
  "type": "Feature",
  "properties": {
    "iso:country":"US",
    "sg:address":"29412 S Needy Rd",
    "sg:city":"Canby",
    "sg:classifiers":[
        {
            "category":"Building & Trades",
            "subcategory":"Construction",
            "type":"Services"
        }
    ],
    "sg:phone":"+1 503 266 1710",
    "sg:postcode":"97013",
    "sg:province":"OR",
    "sg:tags":[
        "contractor"
    ],
    "wof:name":"E M Hedrick Construction",
    "wof:placetype":"venue"
},
  "geometry": {"coordinates":[-122.702055,45.181219],"type":"Point"}
}