{
  "type": "Feature",
  "properties": {
    "iso:country":"US",
    "sg:address":"90294 Prairie Rd",
    "sg:city":"Eugene",
    "sg:classifiers":[
        {
            "category":"Freight",
            "type":"Transportation"
        }
    ],
    "sg:phone":"+1 541 689 7790",
    "sg:postcode":"97402",
    "sg:province":"OR",
    "sg:tags":[
        "operator",
        "local",
        "trucking"
    ],
    "wof:name":"Cad",
    "wof:placetype":"venue"
},
  "geometry": {"coordinates":[-123.16502,44.11081],"type":"Point"}
}