{
  "type": "Feature",
  "properties": {
    "iso:country":"US",
    "sg:address":"2363 SW 33rd St",
    "sg:city":"Redmond",
    "sg:classifiers":[
        {
            "category":"Building & Trades",
            "subcategory":"Construction",
            "type":"Services"
        }
    ],
    "sg:phone":"+1 541 504 5974",
    "sg:postcode":"97756",
    "sg:province":"OR",
    "sg:tags":[
        "residential"
    ],
    "wof:name":"Anthony Kuper",
    "wof:placetype":"venue"
},
  "geometry": {"coordinates":[-121.206785,44.255024],"type":"Point"}
}