{
  "type": "Feature",
  "properties": {
    "iso:country":"US",
    "sg:address":"17901 SE Tickle Creek Rd",
    "sg:city":"Boring",
    "sg:classifiers":[
        {
            "category":"Building & Trades",
            "subcategory":"Construction",
            "type":"Services"
        }
    ],
    "sg:phone":"+1 503 658 5782",
    "sg:postcode":"97009",
    "sg:province":"OR",
    "sg:tags":[
        "general",
        "contractor"
    ],
    "wof:name":"DHR Outdoor Construction",
    "wof:placetype":"venue"
},
  "geometry": {"coordinates":[-122.346608,45.39276],"type":"Point"}
}