{
  "type": "Feature",
  "properties": {
    "iso:country":"US",
    "sg:address":"4868 Tony Ct",
    "sg:city":"Klamath Falls",
    "sg:classifiers":[
        {
            "category":"Farming",
            "subcategory":"Farm",
            "type":"Manufacturing & Wholesale Goods"
        }
    ],
    "sg:phone":"+1 541 273 9769",
    "sg:postcode":"97603",
    "sg:province":"OR",
    "sg:tags":[
        "crop",
        "general"
    ],
    "wof:name":"Meeker Farms Inc",
    "wof:placetype":"venue"
},
  "geometry": {"coordinates":[-121.71705799999999,42.181669],"type":"Point"}
}