{
  "type": "Feature",
  "properties": {
    "iso:country":"US",
    "sg:address":"15110 SW Boones Ferry Rd Suite 250",
    "sg:city":"Lake Oswego",
    "sg:classifiers":[
        {
            "category":"Professional",
            "subcategory":"Management & Consulting",
            "type":"Services"
        }
    ],
    "sg:phone":"+1 503 675 6700",
    "sg:postcode":"97035",
    "sg:province":"OR",
    "sg:website":"http://www.intersoftinc.com/",
    "wof:name":"InterSoft",
    "wof:placetype":"venue"
},
  "geometry": {"coordinates":[-122.70080799999999,45.433814],"type":"Point"}
}