{
  "type": "Feature",
  "properties": {
    "iso:country":"US",
    "sg:address":"102 E Greenwood St",
    "sg:city":"Enterprise",
    "sg:classifiers":[
        {
            "category":"Travel",
            "subcategory":"Hotels & Motels",
            "type":"Entertainment"
        }
    ],
    "sg:phone":"+1 541 426 3186",
    "sg:postcode":"97828",
    "sg:province":"OR",
    "sg:tags":[
        "lodging"
    ],
    "wof:name":"Ponderosa Motel",
    "wof:placetype":"venue"
},
  "geometry": {"coordinates":[-117.277576,45.42461],"type":"Point"}
}