{
  "type": "Feature",
  "properties": {
    "iso:country":"US",
    "sg:address":"1405 Barnes Ave SE",
    "sg:city":"Salem",
    "sg:classifiers":[
        {
            "category":"Autos & Motor Vehicles",
            "subcategory":"Auto Supplies",
            "type":"Retail Goods"
        }
    ],
    "sg:phone":"+1 503 585 7545",
    "sg:postcode":"97306",
    "sg:province":"OR",
    "sg:tags":[
        "tire"
    ],
    "wof:name":"Les Schwab Tire Ctr",
    "wof:placetype":"venue"
},
  "geometry": {"coordinates":[-123.027253,44.881261],"type":"Point"}
}