{
  "type": "Feature",
  "properties": {
    "iso:country":"US",
    "sg:address":"1510 SW 205th Pl",
    "sg:city":"Beaverton",
    "sg:classifiers":[
        {
            "category":"Insurance",
            "subcategory":"Insurance Agent",
            "type":"Services"
        }
    ],
    "sg:phone":"+1 503 642 2573",
    "sg:postcode":"97006",
    "sg:province":"OR",
    "sg:tags":[
        "audit",
        "inspection",
        "commercial",
        "premium"
    ],
    "wof:name":"Tilton Inspection Service",
    "wof:placetype":"venue"
},
  "geometry": {"coordinates":[-122.888088,45.508817],"type":"Point"}
}