{
  "type": "Feature",
  "properties": {
    "iso:country":"US",
    "sg:address":"2626 Wyatt Dr",
    "sg:city":"Medford",
    "sg:classifiers":[
        {
            "category":"Professional",
            "subcategory":"Business Services",
            "type":"Services"
        }
    ],
    "sg:phone":"+1 541 857 1863",
    "sg:postcode":"97501",
    "sg:province":"OR",
    "sg:tags":[
        "personal",
        "assistant"
    ],
    "wof:name":"41 Enterprises Inc",
    "wof:placetype":"venue"
},
  "geometry": {"coordinates":[-122.895056,42.355796],"type":"Point"}
}