{
  "type": "Feature",
  "properties": {
    "iso:country":"US",
    "sg:address":"4625 Silverton Rd NE",
    "sg:city":"Salem",
    "sg:classifiers":[
        {
            "category":"Wholesale",
            "subcategory":"Stationery",
            "type":"Manufacturing & Wholesale Goods"
        }
    ],
    "sg:phone":"+1 503 585 7964",
    "sg:postcode":"97305",
    "sg:province":"OR",
    "sg:tags":[
        "paper"
    ],
    "wof:name":"Security Storage",
    "wof:placetype":"venue"
},
  "geometry": {"coordinates":[-122.96728,44.96975],"type":"Point"}
}