{
  "type": "Feature",
  "properties": {
    "addr:full":"5424 N Missouri Ave Portland OR 97217",
    "addr:housenumber":"5424",
    "addr:postcode":"97217",
    "addr:street":"N Missouri Ave",
    "iso:country":"US",
    "sg:address":"5424 N Missouri Ave",
    "sg:city":"Portland",
    "sg:classifiers":[
        {
            "category":"Wholesale",
            "subcategory":"Hardware",
            "type":"Manufacturing & Wholesale Goods"
        }
    ],
    "sg:phone":"+1 503 289 0538",
    "sg:postcode":"97217",
    "sg:province":"OR",
    "sg:tags":[
        "equipment",
        "energy",
        "solar"
    ],
    "wof:name":"W C Brown & Assoc",
    "wof:placetype":"venue"
},
  "geometry": {"coordinates":[-122.677925,45.561714],"type":"Point"}
}