{
  "type": "Feature",
  "properties": {
    "iso:country":"US",
    "sg:address":"5050 NE Hoyt St",
    "sg:city":"Portland",
    "sg:classifiers":[
        {
            "category":"Health Services",
            "subcategory":"Doctor",
            "type":"Services"
        }
    ],
    "sg:phone":"+1 503 231 1426",
    "sg:postcode":"97213",
    "sg:province":"OR",
    "sg:tags":[
        "physician",
        "surgeon"
    ],
    "sg:website":"www.brownkat.com",
    "wof:name":"Multnomah Orthopedic Clinic",
    "wof:placetype":"venue"
},
  "geometry": {"coordinates":[-122.611074,45.527144],"type":"Point"}
}