{
  "type": "Feature",
  "properties": {
    "addr:full":"5800 S Pacific Hwy Phoenix OR 97535",
    "addr:housenumber":"5800",
    "addr:postcode":"97535",
    "addr:street":"S Pacific Hwy",
    "iso:country":"US",
    "sg:address":"5800 S Pacific Hwy",
    "sg:city":"Phoenix",
    "sg:classifiers":[
        {
            "category":"Building & Trades",
            "subcategory":"Plumbing",
            "type":"Services"
        }
    ],
    "sg:phone":"+1 541 535 1619",
    "sg:postcode":"97535",
    "sg:province":"OR",
    "sg:tags":[
        "contractor"
    ],
    "wof:name":"Oregon Septic Systems",
    "wof:placetype":"venue"
},
  "geometry": {"coordinates":[-122.791499,42.250565],"type":"Point"}
}