{
  "type": "Feature",
  "properties": {
    "iso:country":"US",
    "sg:address":"8331 Cason Rd",
    "sg:city":"Gladstone",
    "sg:classifiers":[
        {
            "category":"Organizations",
            "subcategory":"Religious Organization",
            "type":"Services"
        }
    ],
    "sg:phone":"+1 503 722 2069",
    "sg:postcode":"97027",
    "sg:province":"OR",
    "sg:tags":[
        "church"
    ],
    "wof:name":"Church Of Jesus Christ Of Lds",
    "wof:placetype":"venue"
},
  "geometry": {"coordinates":[-122.57885899999999,45.39221],"type":"Point"}
}