{
  "type": "Feature",
  "properties": {
    "iso:country":"US",
    "sg:address":"2380 Main St",
    "sg:city":"Springfield",
    "sg:classifiers":[
        {
            "category":"Retail",
            "subcategory":"Auto Repair",
            "type":"Services"
        }
    ],
    "sg:phone":"+1 541 744 6292",
    "sg:postcode":"97477",
    "sg:province":"OR",
    "sg:tags":[
        "body",
        "automobile",
        "painting",
        "repairing"
    ],
    "sg:website":"http://www.olddominioncollision.com",
    "wof:name":"Old Dominion Carstar Collision",
    "wof:placetype":"venue"
},
  "geometry": {"coordinates":[-122.99118199999999,44.045868],"type":"Point"}
}