{
  "type": "Feature",
  "properties": {
    "iso:country":"US",
    "sg:address":"6114 SE King Rd",
    "sg:city":"Portland",
    "sg:classifiers":[
        {
            "category":"Cinema",
            "subcategory":"Movie Rental",
            "type":"Entertainment"
        }
    ],
    "sg:phone":"+1 503 653 2680",
    "sg:postcode":"97222",
    "sg:province":"OR",
    "sg:tags":[
        "game",
        "video"
    ],
    "wof:name":"Great American Video",
    "wof:placetype":"venue"
},
  "geometry": {"coordinates":[-122.599998,45.4478],"type":"Point"}
}