{
  "type": "Feature",
  "properties": {
    "iso:country":"US",
    "sg:address":"459 Snowberry Rd",
    "sg:city":"Roseburg",
    "sg:classifiers":[
        {
            "category":"Personal",
            "type":"Services"
        }
    ],
    "sg:phone":"+1 541 677 9658",
    "sg:postcode":"97470",
    "sg:province":"OR",
    "wof:name":"Hammer & Nails Home Repair",
    "wof:placetype":"venue"
},
  "geometry": {"coordinates":[-123.547188,43.24016],"type":"Point"}
}