{
  "type": "Feature",
  "properties": {
    "iso:country":"US",
    "sg:address":"22388 SE Ridgeview Dr",
    "sg:city":"Damascus",
    "sg:classifiers":[
        {
            "category":"Building & Trades",
            "subcategory":"Construction",
            "type":"Services"
        }
    ],
    "sg:phone":"+1 503 970 4238",
    "sg:postcode":"97089",
    "sg:province":"OR",
    "sg:tags":[
        "roofing",
        "industrial",
        "contractors-commercial",
        "contractor"
    ],
    "wof:name":"Logo's Roofing",
    "wof:placetype":"venue"
},
  "geometry": {"coordinates":[-122.43093,45.42995],"type":"Point"}
}