{
  "type": "Feature",
  "properties": {
    "iso:country":"US",
    "sg:address":"222 SW Columbia St",
    "sg:city":"Portland",
    "sg:classifiers":[
        {
            "category":"Social Services",
            "type":"Services"
        }
    ],
    "sg:phone":"+1 503 276 1555",
    "sg:postcode":"97201",
    "sg:province":"OR",
    "sg:tags":[
        "management",
        "individual",
        "family",
        "se"
    ],
    "wof:name":"Homestead Capital Inc",
    "wof:placetype":"venue"
},
  "geometry": {"coordinates":[-122.677935,45.513459],"type":"Point"}
}