{
  "type": "Feature",
  "properties": {
    "addr:full":"145 SE J St Grants Pass OR 97526",
    "addr:housenumber":"145",
    "addr:postcode":"97526",
    "addr:street":"Se J St",
    "iso:country":"US",
    "sg:address":"145 SE J St",
    "sg:city":"Grants Pass",
    "sg:classifiers":[
        {
            "category":"Recreation",
            "type":"Entertainment"
        }
    ],
    "sg:phone":"+1 541 955 5363",
    "sg:postcode":"97526",
    "sg:province":"OR",
    "sg:tags":[
        "lottery",
        "agent"
    ],
    "wof:name":"Purple Parrot",
    "wof:placetype":"venue"
},
  "geometry": {"coordinates":[-123.32762200000001,42.43651],"type":"Point"}
}