{
  "type": "Feature",
  "properties": {
    "addr:full":"2507 Polk St Eugene OR 97405",
    "addr:housenumber":"2507",
    "addr:postcode":"97405",
    "addr:street":"Polk St",
    "iso:country":"US",
    "sg:address":"2507 Polk St",
    "sg:city":"Eugene",
    "sg:classifiers":[
        {
            "category":"Building & Trades",
            "subcategory":"Construction",
            "type":"Services"
        }
    ],
    "sg:phone":"+1 541 683 5650",
    "sg:postcode":"97405",
    "sg:province":"OR",
    "sg:tags":[
        "contractor"
    ],
    "wof:name":"Gregory Drywall",
    "wof:placetype":"venue"
},
  "geometry": {"coordinates":[-123.112179,44.032444],"type":"Point"}
}