{
  "type": "Feature",
  "properties": {
    "iso:country":"US",
    "sg:address":"5200 NE Elam Young Pkwy",
    "sg:city":"Hillsboro",
    "sg:classifiers":[
        {
            "category":"Manufacturing",
            "subcategory":"Tools & Machinery",
            "type":"Manufacturing & Wholesale Goods"
        }
    ],
    "sg:phone":"+1 503 696 8080",
    "sg:postcode":"97124",
    "sg:province":"OR",
    "sg:tags":[
        "equipment",
        "peripheral",
        "computer",
        "mfg"
    ],
    "wof:name":"Intel",
    "wof:placetype":"venue"
},
  "geometry": {"coordinates":[-122.931388,45.529835],"type":"Point"}
}