{
  "type": "Feature",
  "properties": {
    "addr:full":"8306 SE 82nd Ave Portland OR 97266",
    "addr:housenumber":"8306",
    "addr:postcode":"97266",
    "addr:street":"Se 82Nd Ave",
    "iso:country":"US",
    "sg:address":"8306 SE 82nd Ave",
    "sg:city":"Portland",
    "sg:classifiers":[
        {
            "category":"Autos & Motor Vehicles",
            "subcategory":"Automobile Sales",
            "type":"Retail Goods"
        },
        {
            "category":"Wholesale",
            "subcategory":"Motor Vehicles",
            "type":"Manufacturing & Wholesale Goods"
        }
    ],
    "sg:phone":"+1 503 772 8988",
    "sg:postcode":"97266",
    "sg:province":"OR",
    "sg:tags":[
        "used",
        "truck",
        "broker"
    ],
    "wof:name":"Vital Auto Brokers",
    "wof:placetype":"venue"
},
  "geometry": {"coordinates":[-122.57896700000001,45.464069],"type":"Point"}
}