{
  "type": "Feature",
  "properties": {
    "addr:full":"1433 SE 1st Ave Ste 101 Canby OR 97013",
    "addr:housenumber":"1433",
    "addr:postcode":"97013",
    "addr:street":"Se 1St Ave Ste 101",
    "iso:country":"US",
    "sg:address":"1433 SE 1st Ave Ste 101",
    "sg:city":"Canby",
    "sg:classifiers":[
        {
            "category":"Banks & Credit Unions",
            "subcategory":"Investment Brokerage",
            "type":"Services"
        }
    ],
    "sg:phone":"+1 503 263 6552",
    "sg:postcode":"97013",
    "sg:province":"OR",
    "sg:tags":[
        "tape",
        "video",
        "sale",
        "dvds-rental"
    ],
    "wof:name":"Hollywood Video",
    "wof:placetype":"venue"
},
  "geometry": {"coordinates":[-122.677364,45.268187],"type":"Point"}
}