{
  "type": "Feature",
  "properties": {
    "iso:country":"US",
    "sg:address":"41841 Deerhorn Rd",
    "sg:city":"Springfield",
    "sg:classifiers":[
        {
            "category":"Real Estate",
            "subcategory":"Real Estate Services",
            "type":"Services"
        }
    ],
    "sg:phone":"+1 541 896 0919",
    "sg:postcode":"97478",
    "sg:province":"OR",
    "sg:tags":[
        "vacancy",
        "rental",
        "listing"
    ],
    "wof:name":"Bt Properties",
    "wof:placetype":"venue"
},
  "geometry": {"coordinates":[-122.71416600000001,44.087503],"type":"Point"}
}