{
  "type": "Feature",
  "properties": {
    "iso:country":"US",
    "sg:address":"1193 Royvonne Ave SE",
    "sg:city":"Salem",
    "sg:classifiers":[
        {
            "category":"Government",
            "subcategory":"Office",
            "type":"Public Place"
        }
    ],
    "sg:phone":"+1 503 566 2837",
    "sg:postcode":"97302",
    "sg:province":"OR",
    "sg:tags":[
        "quality",
        "ensures",
        "regulates",
        "geologist"
    ],
    "wof:name":"Osbge",
    "wof:placetype":"venue"
},
  "geometry": {"coordinates":[-123.030826,44.886042],"type":"Point"}
}