{
  "type": "Feature",
  "properties": {
    "iso:country":"US",
    "sg:address":"601 Mallard Ave",
    "sg:city":"Springfield",
    "sg:classifiers":[
        {
            "category":"Banks & Credit Unions",
            "subcategory":"Financial Services",
            "type":"Services"
        }
    ],
    "sg:phone":"+1 541 747 9740",
    "sg:postcode":"97477",
    "sg:province":"OR",
    "sg:tags":[
        "investor"
    ],
    "wof:name":"Dubs Investments",
    "wof:placetype":"venue"
},
  "geometry": {"coordinates":[-123.035454,44.077573],"type":"Point"}
}