{
  "type": "Feature",
  "properties": {
    "iso:country":"US",
    "sg:address":"1708 N Myrtle Rd",
    "sg:city":"Myrtle Creek",
    "sg:classifiers":[
        {
            "category":"Personal",
            "type":"Services"
        }
    ],
    "sg:phone":"+1 541 863 3140",
    "sg:postcode":"97457",
    "sg:province":"OR",
    "wof:name":"Rosalinas Designs",
    "wof:placetype":"venue"
},
  "geometry": {"coordinates":[-123.272459,43.034888],"type":"Point"}
}