{
  "type": "Feature",
  "properties": {
    "iso:country":"US",
    "sg:address":"9495 Southwest Cascade Ave",
    "sg:city":"Beaverton",
    "sg:classifiers":[
        {
            "category":"Personal",
            "type":"Services"
        }
    ],
    "sg:phone":"+1 503 504 3550",
    "sg:postcode":"97008",
    "sg:province":"OR",
    "sg:tags":[
        "mover"
    ],
    "sg:website":"www.pacificcoastmoving.com/",
    "wof:name":"Pacific Coast Moving",
    "wof:placetype":"venue"
},
  "geometry": {"coordinates":[-122.78540099999999,45.451267],"type":"Point"}
}