{
  "type": "Feature",
  "properties": {
    "iso:country":"US",
    "sg:address":"23585 NW Jacobson Rd",
    "sg:city":"Hillsboro",
    "sg:classifiers":[
        {
            "category":"Freight",
            "type":"Transportation"
        }
    ],
    "sg:phone":"+1 503 690 7425",
    "sg:postcode":"97124",
    "sg:province":"OR",
    "sg:tags":[
        "operator",
        "local",
        "trucking"
    ],
    "wof:name":"Ln D Trucking",
    "wof:placetype":"venue"
},
  "geometry": {"coordinates":[-122.91866400000001,45.565505],"type":"Point"}
}