{
  "type": "Feature",
  "properties": {
    "iso:country":"US",
    "sg:address":"280 Piller Pl",
    "sg:city":"Cave Junction",
    "sg:classifiers":[
        {
            "category":"Manufacturing",
            "subcategory":"Tools & Machinery",
            "type":"Manufacturing & Wholesale Goods"
        }
    ],
    "sg:phone":"+1 541 592 2777",
    "sg:postcode":"97523",
    "sg:province":"OR",
    "sg:tags":[
        "machine",
        "vending",
        "mfg"
    ],
    "wof:name":"Clear Water Vending Company",
    "wof:placetype":"venue"
},
  "geometry": {"coordinates":[-123.667035,42.137013],"type":"Point"}
}