{
  "type": "Feature",
  "properties": {
    "iso:country":"US",
    "sg:address":"930 N Keene Way Dr",
    "sg:city":"Medford",
    "sg:classifiers":[
        {
            "category":"Home & Garden",
            "subcategory":"Building Materials",
            "type":"Retail Goods"
        },
        {
            "category":"Building & Trades",
            "subcategory":"Construction",
            "type":"Services"
        }
    ],
    "sg:phone":"+1 541 773 2420",
    "sg:postcode":"97504",
    "sg:province":"OR",
    "sg:tags":[
        "concrete",
        "industrial",
        "demolition",
        "contractors-commercial",
        "contractor"
    ],
    "sg:website":"http://www.vikingconcretecutting.com",
    "wof:name":"Viking Concrete Cutting",
    "wof:placetype":"venue"
},
  "geometry": {"coordinates":[-122.852997,42.337592],"type":"Point"}
}