{
  "type": "Feature",
  "properties": {
    "addr:full":"1637 Goldcrest Ave NW Salem OR 97304",
    "addr:housenumber":"1637",
    "addr:postcode":"97304",
    "addr:street":"Goldcrest Ave Nw",
    "iso:country":"US",
    "sg:address":"1637 Goldcrest Ave NW",
    "sg:city":"Salem",
    "sg:classifiers":[
        {
            "category":"Professional",
            "type":"Services"
        }
    ],
    "sg:phone":"+1 503 371 4638",
    "sg:postcode":"97304",
    "sg:province":"OR",
    "wof:name":"Allied Funding Services",
    "wof:placetype":"venue"
},
  "geometry": {"coordinates":[-123.068843,44.962942],"type":"Point"}
}