{
  "type": "Feature",
  "properties": {
    "iso:country":"US",
    "sg:address":"740 SW 5th St",
    "sg:city":"Grants Pass",
    "sg:classifiers":[
        {
            "category":"Personal",
            "type":"Services"
        }
    ],
    "sg:phone":"+1 541 659 4654",
    "sg:postcode":"97526",
    "sg:province":"OR",
    "sg:tags":[
        "therapist",
        "massage"
    ],
    "wof:name":"Christine Gagnon",
    "wof:placetype":"venue"
},
  "geometry": {"coordinates":[-123.330749,42.435372],"type":"Point"}
}