{
  "type": "Feature",
  "properties": {
    "iso:country":"US",
    "sg:address":"2613 Tudor Way SE",
    "sg:city":"Albany",
    "sg:classifiers":[
        {
            "category":"Freight",
            "type":"Transportation"
        }
    ],
    "sg:phone":"+1 541 967 2829",
    "sg:postcode":"97322",
    "sg:province":"OR",
    "sg:tags":[
        "operator",
        "local",
        "trucking"
    ],
    "wof:name":"Larry Heins Trucking",
    "wof:placetype":"venue"
},
  "geometry": {"coordinates":[-123.08918199999999,44.616466],"type":"Point"}
}