{
  "type": "Feature",
  "properties": {
    "addr:full":"1515 NE Laurel Ave Woodburn OR 97071",
    "addr:housenumber":"1515",
    "addr:postcode":"97071",
    "addr:street":"Ne Laurel Ave",
    "iso:country":"US",
    "sg:address":"1515 NE Laurel Ave",
    "sg:city":"Woodburn",
    "sg:classifiers":[
        {
            "category":"Home & Garden",
            "subcategory":"Furniture",
            "type":"Retail Goods"
        }
    ],
    "sg:phone":"+1 503 982 9220",
    "sg:postcode":"97071",
    "sg:province":"OR",
    "wof:name":"Hayden Steve & Sons",
    "wof:placetype":"venue"
},
  "geometry": {"coordinates":[-122.839607,45.139219],"type":"Point"}
}