{
  "type": "Feature",
  "properties": {
    "iso:country":"US",
    "sg:address":"1207 E Powell Blvd",
    "sg:city":"Gresham",
    "sg:classifiers":[
        {
            "category":"Personal",
            "subcategory":"Beauty Salon",
            "type":"Services"
        }
    ],
    "sg:phone":"+1 503 618 1045",
    "sg:postcode":"97030",
    "sg:province":"OR",
    "wof:name":"Super Look Beauty Salon",
    "wof:placetype":"venue"
},
  "geometry": {"coordinates":[-122.41968799999999,45.498084],"type":"Point"}
}