{
  "type": "Feature",
  "properties": {
    "addr:full":"1705 NW 14th Ave Portland OR 97209",
    "addr:housenumber":"1705",
    "addr:postcode":"97209",
    "addr:street":"Nw 14Th Ave",
    "iso:country":"US",
    "sg:address":"1705 NW 14th Ave",
    "sg:city":"Portland",
    "sg:classifiers":[
        {
            "category":"Retail",
            "subcategory":"Repair Shop",
            "type":"Services"
        }
    ],
    "sg:phone":"+1 503 228 8313",
    "sg:postcode":"97209",
    "sg:province":"OR",
    "sg:tags":[
        "wholesale",
        "compressor",
        "hydraulic",
        "air"
    ],
    "wof:name":"Karn Repair Service Inc",
    "wof:placetype":"venue"
},
  "geometry": {"coordinates":[-122.685695,45.535413],"type":"Point"}
}