{
  "type": "Feature",
  "properties": {
    "addr:full":"19339 Willamette Dr West Linn OR 97068",
    "addr:housenumber":"19339",
    "addr:postcode":"97068",
    "addr:street":"Willamette Dr",
    "iso:country":"US",
    "sg:address":"19339 Willamette Dr",
    "sg:city":"West Linn",
    "sg:classifiers":[
        {
            "category":"Building & Trades",
            "subcategory":"Locksmith",
            "type":"Services"
        }
    ],
    "sg:phone":"+1 503 303 6811",
    "sg:postcode":"97068",
    "sg:province":"OR",
    "sg:tags":[
        "key"
    ],
    "wof:name":"1 Action 7 Day Lock Service",
    "wof:placetype":"venue"
},
  "geometry": {"coordinates":[-122.63945,45.38492],"type":"Point"}
}