{
  "type": "Feature",
  "properties": {
    "addr:full":"129 NW E St Grants Pass OR 97526",
    "addr:housenumber":"129",
    "addr:postcode":"97526",
    "addr:street":"Nw E St",
    "iso:country":"US",
    "sg:address":"129 NW E St",
    "sg:city":"Grants Pass",
    "sg:classifiers":[
        {
            "category":"Professional",
            "subcategory":"Computer Services",
            "type":"Services"
        }
    ],
    "sg:phone":"+1 541 476 3139",
    "sg:postcode":"97526",
    "sg:province":"OR",
    "sg:tags":[
        "processing",
        "datum"
    ],
    "sg:website":"www.pharmcomp.com",
    "wof:name":"Pharmacy Computer Svc Inc",
    "wof:placetype":"venue"
},
  "geometry": {"coordinates":[-123.326436,42.440799],"type":"Point"}
}