{
  "type": "Feature",
  "properties": {
    "iso:country":"US",
    "sg:address":"31915 Seven Mile Ln",
    "sg:city":"Tangent",
    "sg:classifiers":[
        {
            "category":"Freight",
            "type":"Transportation"
        }
    ],
    "sg:phone":"+1 541 928 7778",
    "sg:postcode":"97389",
    "sg:province":"OR",
    "sg:tags":[
        "storage"
    ],
    "wof:name":"Mid Valley Farm Seed Storage",
    "wof:placetype":"venue"
},
  "geometry": {"coordinates":[-123.049077,44.504892],"type":"Point"}
}