{
  "type": "Feature",
  "properties": {
    "addr:full":"1585 SE 19th St Lincoln City OR 97367",
    "addr:housenumber":"1585",
    "addr:postcode":"97367",
    "addr:street":"Se 19Th St",
    "iso:country":"US",
    "sg:address":"1585 SE 19th St",
    "sg:city":"Lincoln City",
    "sg:classifiers":[
        {
            "category":"Real Estate",
            "subcategory":"Real Estate Operator",
            "type":"Services"
        }
    ],
    "sg:phone":"+1 541 994 4499",
    "sg:postcode":"97367",
    "sg:province":"OR",
    "sg:tags":[
        "apartment",
        "complex"
    ],
    "wof:name":"Cedar Crest Apartments",
    "wof:placetype":"venue"
},
  "geometry": {"coordinates":[-124.010148,44.954695],"type":"Point"}
}