{
  "type": "Feature",
  "properties": {
    "iso:country":"US",
    "sg:address":"2402 11th Ave",
    "sg:city":"Forest Grove",
    "sg:classifiers":[
        {
            "category":"Manufacturing",
            "subcategory":"Lumber",
            "type":"Manufacturing & Wholesale Goods"
        }
    ],
    "sg:phone":"+1 503 357 8377",
    "sg:postcode":"97116",
    "sg:province":"OR",
    "sg:tags":[
        "cruiser",
        "timber"
    ],
    "wof:name":"Alo's Timber Co",
    "wof:placetype":"venue"
},
  "geometry": {"coordinates":[-123.103108,45.509627],"type":"Point"}
}