{
  "type": "Feature",
  "properties": {
    "addr:full":"5050 NE Hoyt St Ste 157 Portland OR 97213",
    "addr:housenumber":"5050",
    "addr:postcode":"97213",
    "addr:street":"Ne Hoyt St Ste 157",
    "iso:country":"US",
    "sg:address":"5050 NE Hoyt St Ste 157",
    "sg:city":"Portland",
    "sg:classifiers":[
        {
            "category":"Health Services",
            "subcategory":"Doctor",
            "type":"Services"
        }
    ],
    "sg:phone":"+1 503 230 6586",
    "sg:postcode":"97213",
    "sg:province":"OR",
    "sg:tags":[
        "physician",
        "surgeon"
    ],
    "sg:website":"http://www.providence.org",
    "wof:name":"Oregon Osteoporosis Center",
    "wof:placetype":"venue"
},
  "geometry": {"coordinates":[-122.61135,45.52721],"type":"Point"}
}