{
  "type": "Feature",
  "properties": {
    "iso:country":"US",
    "sg:address":"30470 SW Parkway Ave",
    "sg:city":"Wilsonville",
    "sg:classifiers":[
        {
            "category":"Manufacturing",
            "subcategory":"Printing",
            "type":"Manufacturing & Wholesale Goods"
        }
    ],
    "sg:phone":"+1 503 570 0807",
    "sg:postcode":"97070",
    "sg:province":"OR",
    "sg:tags":[
        "periodical"
    ],
    "wof:name":"Sforzando",
    "wof:placetype":"venue"
},
  "geometry": {"coordinates":[-122.768725,45.298911],"type":"Point"}
}