{
  "type": "Feature",
  "properties": {
    "iso:country":"US",
    "sg:address":"24377 Vaughn Rd",
    "sg:city":"Veneta",
    "sg:classifiers":[
        {
            "category":"Retail",
            "subcategory":"Animal Services",
            "type":"Services"
        }
    ],
    "sg:phone":"+1 541 935 0112",
    "sg:postcode":"97487",
    "sg:province":"OR",
    "sg:tags":[
        "training",
        "dog"
    ],
    "wof:name":"Trifecta Training Ctr",
    "wof:placetype":"venue"
},
  "geometry": {"coordinates":[-123.379379,44.000509],"type":"Point"}
}