{
  "type": "Feature",
  "properties": {
    "iso:country":"US",
    "sg:address":"8520 NE Alderwood Rd",
    "sg:city":"Portland",
    "sg:classifiers":[
        {
            "category":"Freight",
            "type":"Transportation"
        }
    ],
    "sg:phone":"+1 503 288 8158",
    "sg:postcode":"97220",
    "sg:province":"OR",
    "sg:tags":[
        "arrangement"
    ],
    "wof:name":"Oia",
    "wof:placetype":"venue"
},
  "geometry": {"coordinates":[-122.575098,45.575028],"type":"Point"}
}