{
  "type": "Feature",
  "properties": {
    "iso:country":"US",
    "sg:address":"4450 SW Saint Marys Dr",
    "sg:city":"Beaverton",
    "sg:classifiers":[
        {
            "category":"Social Services",
            "subcategory":"Child Care",
            "type":"Services"
        }
    ],
    "sg:phone":"+1 503 520 0214",
    "sg:postcode":"97007",
    "sg:province":"OR",
    "sg:tags":[
        "day"
    ],
    "wof:name":"Little Flower Development Ctr",
    "wof:placetype":"venue"
},
  "geometry": {"coordinates":[-122.83088100000001,45.487563],"type":"Point"}
}