{
  "type": "Feature",
  "properties": {
    "addr:full":"2340 NE Rene Ave Gresham OR 97030",
    "addr:housenumber":"2340",
    "addr:postcode":"97030",
    "addr:street":"Ne Rene Ave",
    "iso:country":"US",
    "sg:address":"2340 NE Rene Ave",
    "sg:city":"Gresham",
    "sg:classifiers":[
        {
            "category":"Professional",
            "type":"Services"
        }
    ],
    "sg:phone":"+1 503 665 1147",
    "sg:postcode":"97030",
    "sg:province":"OR",
    "wof:name":"Revolutionary Dynamics",
    "wof:placetype":"venue"
},
  "geometry": {"coordinates":[-122.409386,45.513334],"type":"Point"}
}