{
  "type": "Feature",
  "properties": {
    "iso:country":"US",
    "sg:address":"725 NE 4th St",
    "sg:city":"Mcminnville",
    "sg:classifiers":[
        {
            "category":"Food & Beverages",
            "subcategory":"Liquor & Beverages",
            "type":"Retail Goods"
        }
    ],
    "sg:phone":"+1 503 472 6454",
    "sg:postcode":"97128",
    "sg:province":"OR",
    "sg:tags":[
        "wine"
    ],
    "wof:name":"Oregon Wine Co",
    "wof:placetype":"venue"
},
  "geometry": {"coordinates":[-123.191868,45.210811],"type":"Point"}
}