{
  "type": "Feature",
  "properties": {
    "addr:full":"2340 SW 15th St Gresham OR 97080",
    "addr:housenumber":"2340",
    "addr:postcode":"97080",
    "addr:street":"Sw 15Th St",
    "iso:country":"US",
    "sg:address":"2340 SW 15th St",
    "sg:city":"Gresham",
    "sg:classifiers":[
        {
            "category":"Organizations",
            "subcategory":"Religious Organization",
            "type":"Services"
        }
    ],
    "sg:phone":"+1 503 665 0045",
    "sg:postcode":"97080",
    "sg:province":"OR",
    "wof:name":"Portland Korean 7th Day Advent",
    "wof:placetype":"venue"
},
  "geometry": {"coordinates":[-122.458117,45.486221],"type":"Point"}
}