{
  "type": "Feature",
  "properties": {
    "iso:country":"US",
    "sg:address":"6340 Failing St",
    "sg:city":"West Linn",
    "sg:classifiers":[
        {
            "category":"Home & Garden",
            "subcategory":"Building Materials",
            "type":"Retail Goods"
        }
    ],
    "sg:phone":"+1 503 655 1494",
    "sg:postcode":"97068",
    "sg:province":"OR",
    "wof:name":"Coralyn Glass Creation",
    "wof:placetype":"venue"
},
  "geometry": {"coordinates":[-122.621852,45.372331],"type":"Point"}
}