{
  "type": "Feature",
  "properties": {
    "iso:country":"US",
    "sg:address":"15958 NW Wismer Dr",
    "sg:city":"Portland",
    "sg:classifiers":[
        {
            "category":"Real Estate",
            "subcategory":"Real Estate Services",
            "type":"Services"
        },
        {
            "category":"Real Estate",
            "subcategory":"Real Estate Agent",
            "type":"Services"
        }
    ],
    "sg:phone":"+1 503 515 6784",
    "sg:postcode":"97229",
    "sg:province":"OR",
    "sg:tags":[
        "buyer",
        "broker"
    ],
    "wof:name":"Gem Realty Nw",
    "wof:placetype":"venue"
},
  "geometry": {"coordinates":[-122.841339,45.558819],"type":"Point"}
}