{
  "type": "Feature",
  "properties": {
    "addr:full":"7943 State Hwy 238 Jacksonville OR 97530",
    "addr:housenumber":"7943",
    "addr:postcode":"97530",
    "addr:street":"State Hwy 238",
    "iso:country":"US",
    "sg:address":"7943 State Hwy 238",
    "sg:city":"Jacksonville",
    "sg:classifiers":[
        {
            "category":"Building & Trades",
            "subcategory":"Construction",
            "type":"Services"
        }
    ],
    "sg:phone":"+1 541 899 9005",
    "sg:postcode":"97530",
    "sg:province":"OR",
    "sg:tags":[
        "house"
    ],
    "wof:name":"Don Durant Construction",
    "wof:placetype":"venue"
},
  "geometry": {"coordinates":[-123.04603400000001,42.236088],"type":"Point"}
}