{
  "type": "Feature",
  "properties": {
    "addr:full":"31955 SE Belfils Rd Estacada OR 97023",
    "addr:postcode":"31955;97023",
    "addr:street":"Se Belfils Rd",
    "iso:country":"US",
    "sg:address":"31955 SE Belfils Rd",
    "sg:city":"Estacada",
    "sg:classifiers":[
        {
            "category":"Manufacturing",
            "subcategory":"Metals",
            "type":"Manufacturing & Wholesale Goods"
        },
        {
            "category":"Building & Trades",
            "subcategory":"Construction",
            "type":"Services"
        }
    ],
    "sg:phone":"+1 503 630 5909",
    "sg:postcode":"97023",
    "sg:province":"OR",
    "sg:tags":[
        "shop",
        "fabricator",
        "fabricating"
    ],
    "wof:name":"Black Bear Metal Fab Inc",
    "wof:placetype":"venue"
},
  "geometry": {"coordinates":[-122.230276,45.294407],"type":"Point"}
}