{
  "type": "Feature",
  "properties": {
    "addr:full":"1211 SW 5th Ave Portland OR 97204",
    "addr:housenumber":"1211",
    "addr:postcode":"97204",
    "addr:street":"Sw 5Th Ave",
    "iso:country":"US",
    "sg:address":"1211 SW 5th Ave",
    "sg:city":"Portland",
    "sg:classifiers":[
        {
            "category":"Organizations",
            "subcategory":"Membership Organization",
            "type":"Services"
        },
        {
            "category":"Organizations",
            "subcategory":"Professional Association",
            "type":"Services"
        }
    ],
    "sg:phone":"+1 503 356 8385",
    "sg:postcode":"97204",
    "sg:province":"OR",
    "wof:name":"Oregon Land Title Association",
    "wof:placetype":"venue"
},
  "geometry": {"coordinates":[-122.679794,45.5149],"type":"Point"}
}