{
  "type": "Feature",
  "properties": {
    "addr:full":"7421 SW Barbur Blvd Portland OR 97219",
    "addr:housenumber":"7421",
    "addr:postcode":"97219",
    "addr:street":"Sw Barbur Blvd",
    "iso:country":"US",
    "sg:address":"7421 SW Barbur Blvd",
    "sg:city":"Portland",
    "sg:classifiers":[
        {
            "category":"Personal",
            "subcategory":"Beauty Salon",
            "type":"Services"
        }
    ],
    "sg:phone":"+1 503 768 3293",
    "sg:postcode":"97219",
    "sg:province":"OR",
    "sg:tags":[
        "hair",
        "shop"
    ],
    "wof:name":"Faye Judson Salon",
    "wof:placetype":"venue"
},
  "geometry": {"coordinates":[-122.686159,45.471136],"type":"Point"}
}