{
  "type": "Feature",
  "properties": {
    "addr:full":"36340 Oak Dr Lebanon OR 97355",
    "addr:housenumber":"36340",
    "addr:postcode":"97355",
    "addr:street":"Oak Dr",
    "iso:country":"US",
    "sg:address":"36340 Oak Dr",
    "sg:city":"Lebanon",
    "sg:classifiers":[
        {
            "category":"Building & Trades",
            "subcategory":"Construction",
            "type":"Services"
        }
    ],
    "sg:phone":"+1 541 258 6912",
    "sg:postcode":"97355",
    "sg:province":"OR",
    "sg:tags":[
        "house"
    ],
    "wof:name":"Ed Murphy Const",
    "wof:placetype":"venue"
},
  "geometry": {"coordinates":[-122.941143,44.536308],"type":"Point"}
}