{
  "type": "Feature",
  "properties": {
    "iso:country":"US",
    "sg:address":"36425 Alder Branch Rd",
    "sg:city":"Springfield",
    "sg:classifiers":[
        {
            "category":"Education",
            "subcategory":"Dance Studio",
            "type":"Public Place"
        }
    ],
    "sg:phone":"+1 541 746 6268",
    "sg:postcode":"97478",
    "sg:province":"OR",
    "wof:name":"Staver Dance Co",
    "wof:placetype":"venue"
},
  "geometry": {"coordinates":[-122.920281,44.110319],"type":"Point"}
}