{
  "type": "Feature",
  "properties": {
    "iso:country":"US",
    "sg:address":"2147 SW Kendall Ct",
    "sg:city":"Troutdale",
    "sg:classifiers":[
        {
            "category":"Professional",
            "subcategory":"Management & Consulting",
            "type":"Services"
        }
    ],
    "sg:phone":"+1 503 669 8572",
    "sg:postcode":"97060",
    "sg:province":"OR",
    "wof:name":"International Trade Management",
    "wof:placetype":"venue"
},
  "geometry": {"coordinates":[-122.39035,45.525555],"type":"Point"}
}