{
  "type": "Feature",
  "properties": {
    "iso:country":"US",
    "sg:address":"8645 SW Curry Dr",
    "sg:city":"Wilsonville",
    "sg:classifiers":[
        {
            "category":"Home & Garden",
            "subcategory":"Home Furnishings",
            "type":"Retail Goods"
        }
    ],
    "sg:phone":"+1 503 970 2849",
    "sg:postcode":"97070",
    "sg:province":"OR",
    "sg:tags":[
        "installation",
        "drapery"
    ],
    "wof:name":"Interior Enterprises",
    "wof:placetype":"venue"
},
  "geometry": {"coordinates":[-122.765755,45.28975],"type":"Point"}
}