{
  "type": "Feature",
  "properties": {
    "addr:full":"813 Hostetler Way W The Dalles OR 97058",
    "addr:housenumber":"813",
    "addr:postcode":"97058",
    "addr:street":"Hostetler Way W",
    "iso:country":"US",
    "sg:address":"813 Hostetler Way W",
    "sg:city":"The Dalles",
    "sg:classifiers":[
        {
            "category":"Building & Trades",
            "subcategory":"Construction",
            "type":"Services"
        }
    ],
    "sg:phone":"+1 541 296 1880",
    "sg:postcode":"97058",
    "sg:province":"OR",
    "sg:tags":[
        "residential",
        "installation",
        "remodel",
        "flooring"
    ],
    "wof:name":"Ervins Home Improvement",
    "wof:placetype":"venue"
},
  "geometry": {"coordinates":[-121.218367,45.623135],"type":"Point"}
}