{
  "type": "Feature",
  "properties": {
    "addr:full":"111 SW 5th Ave Ste 4000 Portland OR 97204",
    "addr:housenumber":"111",
    "addr:postcode":"97204",
    "addr:street":"Sw 5Th Ave Ste 4000",
    "iso:country":"US",
    "sg:address":"111 SW 5th Ave Ste 4000",
    "sg:city":"Portland",
    "sg:classifiers":[
        {
            "category":"Industrial Area",
            "type":"Public Place"
        }
    ],
    "sg:phone":"+1 503 299 4000",
    "sg:postcode":"97204",
    "sg:province":"OR",
    "sg:tags":[
        "development"
    ],
    "sg:website":"http://www.aetaxservice.com",
    "wof:name":"Southeast Company",
    "wof:placetype":"venue"
},
  "geometry": {"coordinates":[-122.675507,45.522598],"type":"Point"}
}