{
  "type": "Feature",
  "properties": {
    "iso:country":"US",
    "sg:address":"17871 SW 115th Ave",
    "sg:city":"Tualatin",
    "sg:classifiers":[
        {
            "category":"Place Of Worship",
            "subcategory":"Church",
            "type":"Public Place"
        },
        {
            "category":"Place Of Worship",
            "type":"Public Place"
        }
    ],
    "sg:phone":"+1 503 692 0900",
    "sg:postcode":"97062",
    "sg:province":"OR",
    "sg:tags":[
        "lutheran",
        "america",
        "churches-lutheran",
        "churches-lutheran-evangelical"
    ],
    "wof:name":"Apostolic Lutheran Church",
    "wof:placetype":"venue"
},
  "geometry": {"coordinates":[-122.79540299999999,45.390817],"type":"Point"}
}