{
  "type": "Feature",
  "properties": {
    "addr:full":"155 18th St Springfield OR 97477",
    "addr:housenumber":"155",
    "addr:postcode":"97477",
    "addr:street":"18Th St",
    "iso:country":"US",
    "sg:address":"155 18th St",
    "sg:city":"Springfield",
    "sg:classifiers":[
        {
            "category":"Real Estate",
            "subcategory":"Real Estate Agent",
            "type":"Services"
        }
    ],
    "sg:phone":"+1 541 434 1406",
    "sg:postcode":"97477",
    "sg:province":"OR",
    "wof:name":"Tactical Equity Asset Manageme",
    "wof:placetype":"venue"
},
  "geometry": {"coordinates":[-122.99853400000001,44.050043],"type":"Point"}
}