{
  "type": "Feature",
  "properties": {
    "addr:full":"15009 NE Airport Way Portland OR 97230",
    "addr:housenumber":"15009",
    "addr:postcode":"97230",
    "addr:street":"Ne Airport Way",
    "iso:country":"US",
    "sg:address":"15009 NE Airport Way",
    "sg:city":"Portland",
    "sg:classifiers":[
        {
            "category":"Wholesale",
            "subcategory":"Groceries",
            "type":"Manufacturing & Wholesale Goods"
        }
    ],
    "sg:phone":"+1 503 254 1500",
    "sg:postcode":"97230",
    "sg:province":"OR",
    "sg:tags":[
        "baker"
    ],
    "wof:name":"Oroweat Foods Co",
    "wof:placetype":"venue"
},
  "geometry": {"coordinates":[-122.50657099999999,45.559248],"type":"Point"}
}