{
  "type": "Feature",
  "properties": {
    "iso:country":"US",
    "sg:address":"609 E Main St",
    "sg:city":"Hermiston",
    "sg:classifiers":[
        {
            "category":"Professional",
            "subcategory":"Art Services",
            "type":"Services"
        }
    ],
    "sg:phone":"+1 541 567 0690",
    "sg:postcode":"97838",
    "sg:province":"OR",
    "sg:tags":[
        "commercial",
        "design"
    ],
    "wof:name":"Graphics Illustrated",
    "wof:placetype":"venue"
},
  "geometry": {"coordinates":[-119.281576,45.84052],"type":"Point"}
}