{
  "type": "Feature",
  "properties": {
    "iso:country":"US",
    "sg:address":"144 NE 28th Avenue",
    "sg:city":"Portland",
    "sg:classifiers":[
        {
            "category":"Shopping",
            "type":"Retail Goods"
        }
    ],
    "sg:phone":"+1 503 234 6877",
    "sg:postcode":"97232",
    "sg:province":"OR",
    "sg:website":"www.shopatbutterscotch.com/",
    "wof:name":"Butterscotch",
    "wof:placetype":"venue"
},
  "geometry": {"coordinates":[-122.637001,45.523899],"type":"Point"}
}