{
  "type": "Feature",
  "properties": {
    "iso:country":"US",
    "sg:address":"1220 NE Dogwood Ln",
    "sg:city":"Madras",
    "sg:classifiers":[
        {
            "category":"Building & Trades",
            "subcategory":"Construction",
            "type":"Services"
        }
    ],
    "sg:phone":"+1 541 475 3139",
    "sg:postcode":"97741",
    "sg:province":"OR",
    "sg:tags":[
        "excavation",
        "contractor"
    ],
    "wof:name":"Alan Clark D&Clark Teresa",
    "wof:placetype":"venue"
},
  "geometry": {"coordinates":[-121.11124599999999,44.679666],"type":"Point"}
}