{
  "type": "Feature",
  "properties": {
    "iso:country":"US",
    "sg:address":"3195 River Rd",
    "sg:city":"Eugene",
    "sg:classifiers":[
        {
            "category":"Building & Trades",
            "subcategory":"Construction",
            "type":"Services"
        }
    ],
    "sg:phone":"+1 541 689 1442",
    "sg:postcode":"97404",
    "sg:province":"OR",
    "sg:tags":[
        "excavation",
        "contractor"
    ],
    "wof:name":"Oregon Excavating Inc",
    "wof:placetype":"venue"
},
  "geometry": {"coordinates":[-123.13431799999999,44.110132],"type":"Point"}
}