{
  "type": "Feature",
  "properties": {
    "addr:full":"2469 Park Forest Dr Eugene OR 97405",
    "addr:housenumber":"2469",
    "addr:postcode":"97405",
    "addr:street":"Park Forest Dr",
    "iso:country":"US",
    "sg:address":"2469 Park Forest Dr",
    "sg:city":"Eugene",
    "sg:classifiers":[
        {
            "category":"Professional",
            "subcategory":"Business Services",
            "type":"Services"
        }
    ],
    "sg:phone":"+1 541 343 0327",
    "sg:postcode":"97405",
    "sg:province":"OR",
    "wof:name":"Von Ronne Enterprises",
    "wof:placetype":"venue"
},
  "geometry": {"coordinates":[-123.13689599999999,44.032429],"type":"Point"}
}