{
  "type": "Feature",
  "properties": {
    "iso:country":"US",
    "sg:address":"700 N Portland Blvd",
    "sg:city":"Portland",
    "sg:classifiers":[
        {
            "category":"Park",
            "type":"Public Place"
        }
    ],
    "sg:postcode":"97217",
    "sg:province":"OR",
    "wof:name":"Peninsula Park",
    "wof:placetype":"venue"
},
  "geometry": {"coordinates":[-122.651698,45.569797],"type":"Point"}
}