{
  "type": "Feature",
  "properties": {
    "addr:full":"26345 Gap Rd Brownsville OR 97327",
    "addr:postcode":"26345;97327",
    "addr:street":"Gap Rd",
    "iso:country":"US",
    "sg:address":"26345 Gap Rd",
    "sg:city":"Brownsville",
    "sg:classifiers":[
        {
            "category":"Farming",
            "subcategory":"Livestock Farm",
            "type":"Manufacturing & Wholesale Goods"
        }
    ],
    "sg:phone":"+1 541 466 5055",
    "sg:postcode":"97327",
    "sg:province":"OR",
    "sg:tags":[
        "beef",
        "feedlot",
        "cattle"
    ],
    "wof:name":"Carl Stubbs Farms",
    "wof:placetype":"venue"
},
  "geometry": {"coordinates":[-122.984619,44.3611],"type":"Point"}
}