{
  "type": "Feature",
  "properties": {
    "iso:country":"US",
    "sg:address":"1737 Washington St",
    "sg:city":"Oregon City",
    "sg:classifiers":[
        {
            "category":"Wholesale",
            "subcategory":"Durable Goods & Equipment",
            "type":"Manufacturing & Wholesale Goods"
        }
    ],
    "sg:phone":"+1 503 655 1968",
    "sg:postcode":"97045",
    "sg:province":"OR",
    "wof:name":"Western Cylinder Supply",
    "wof:placetype":"venue"
},
  "geometry": {"coordinates":[-122.58587,45.37093],"type":"Point"}
}