{
  "type": "Feature",
  "properties": {
    "addr:full":"1108 W 6th St The Dalles OR 97058",
    "addr:housenumber":"1108",
    "addr:postcode":"97058",
    "addr:street":"W 6Th St",
    "iso:country":"US",
    "sg:address":"1108 W 6th St",
    "sg:city":"The Dalles",
    "sg:classifiers":[
        {
            "category":"Restaurant",
            "type":"Food & Drink"
        }
    ],
    "sg:menulink":"http://www.allmenus.com/or/the-dalles/235414-taco-time/menu/",
    "sg:phone":"+1 541 298 5316",
    "sg:postcode":"97058",
    "sg:province":"OR",
    "sg:tags":[
        "american",
        "mexican",
        "tex-mex"
    ],
    "wof:name":"Taco Time",
    "wof:placetype":"venue"
},
  "geometry": {"coordinates":[-121.198851,45.605085],"type":"Point"}
}