{
  "type": "Feature",
  "properties": {
    "iso:country":"US",
    "sg:address":"3930 SE Division St",
    "sg:city":"Portland",
    "sg:classifiers":[
        {
            "category":"Health Services",
            "subcategory":"Doctor",
            "type":"Services"
        }
    ],
    "sg:phone":"+1 503 418 3900",
    "sg:postcode":"97202",
    "sg:province":"OR",
    "sg:tags":[
        "practice",
        "family"
    ],
    "wof:name":"Weprin Jennifer MD",
    "wof:placetype":"venue"
},
  "geometry": {"coordinates":[-122.62223899999999,45.504633],"type":"Point"}
}