{
  "type": "Feature",
  "properties": {
    "iso:country":"US",
    "sg:address":"2267 W 28th Ave",
    "sg:city":"Eugene",
    "sg:classifiers":[
        {
            "category":"Professional",
            "subcategory":"Art Services",
            "type":"Services"
        }
    ],
    "sg:phone":"+1 541 556 3060",
    "sg:postcode":"97405",
    "sg:province":"OR",
    "sg:tags":[
        "designer",
        "display",
        "producer"
    ],
    "wof:name":"Madra Design",
    "wof:placetype":"venue"
},
  "geometry": {"coordinates":[-123.128173,44.028692],"type":"Point"}
}