{
  "type": "Feature",
  "properties": {
    "addr:full":"11103 S Mount Hope Rd Molalla OR 97038",
    "addr:housenumber":"11103",
    "addr:postcode":"97038",
    "addr:street":"S Mount Hope Rd",
    "iso:country":"US",
    "sg:address":"11103 S Mount Hope Rd",
    "sg:city":"Molalla",
    "sg:classifiers":[
        {
            "category":"Shopping",
            "subcategory":"Computers & Home Electronics",
            "type":"Retail Goods"
        }
    ],
    "sg:phone":"+1 503 829 8929",
    "sg:postcode":"97038",
    "sg:province":"OR",
    "sg:tags":[
        "software"
    ],
    "wof:name":"Cadapult Software Solutions",
    "wof:placetype":"venue"
},
  "geometry": {"coordinates":[-122.646615,45.129019],"type":"Point"}
}