{
  "type": "Feature",
  "properties": {
    "iso:country":"US",
    "sg:address":"64835 Deer Island Hts Dr",
    "sg:city":"Deer Island",
    "sg:classifiers":[
        {
            "category":"Building & Trades",
            "subcategory":"Construction",
            "type":"Services"
        }
    ],
    "sg:phone":"+1 503 397 0987",
    "sg:postcode":"97054",
    "sg:province":"OR",
    "sg:tags":[
        "contractor"
    ],
    "wof:name":"Brumbles Drywall",
    "wof:placetype":"venue"
},
  "geometry": {"coordinates":[-122.848415,45.932607],"type":"Point"}
}