{
  "type": "Feature",
  "properties": {
    "addr:full":"740 E 3rd St Coquille OR 97423",
    "addr:housenumber":"740",
    "addr:postcode":"97423",
    "addr:street":"E 3Rd St",
    "iso:country":"US",
    "sg:address":"740 E 3rd St",
    "sg:city":"Coquille",
    "sg:classifiers":[
        {
            "category":"Building & Trades",
            "subcategory":"Construction",
            "type":"Services"
        }
    ],
    "sg:phone":"+1 541 396 4375",
    "sg:postcode":"97423",
    "sg:province":"OR",
    "sg:tags":[
        "carpentry",
        "contractor"
    ],
    "wof:name":"Patrick Grant",
    "wof:placetype":"venue"
},
  "geometry": {"coordinates":[-124.18128900000001,43.176958],"type":"Point"}
}