{
  "type": "Feature",
  "properties": {
    "iso:country":"US",
    "sg:address":"414 NE Galloway St",
    "sg:city":"Mcminnville",
    "sg:classifiers":[
        {
            "category":"Professional",
            "subcategory":"Lawyer & Legal Services",
            "type":"Services"
        }
    ],
    "sg:phone":"+1 503 472 3347",
    "sg:postcode":"97128",
    "sg:province":"OR",
    "sg:tags":[
        "attorney"
    ],
    "wof:name":"Beverly D Richardson",
    "wof:placetype":"venue"
},
  "geometry": {"coordinates":[-123.192072,45.211348],"type":"Point"}
}