{
  "type": "Feature",
  "properties": {
    "addr:full":"2929 NE Kane Dr Gresham OR 97030",
    "addr:housenumber":"2929",
    "addr:postcode":"97030",
    "addr:street":"Ne Kane Dr",
    "iso:country":"US",
    "sg:address":"2929 NE Kane Dr",
    "sg:city":"Gresham",
    "sg:classifiers":[
        {
            "category":"Cinema",
            "subcategory":"Movie Theater",
            "type":"Entertainment"
        }
    ],
    "sg:phone":"+1 503 618 0889",
    "sg:postcode":"97030",
    "sg:province":"OR",
    "sg:tags":[
        "motion",
        "picture"
    ],
    "wof:name":"Stark Street Cinema",
    "wof:placetype":"venue"
},
  "geometry": {"coordinates":[-122.399002,45.517899],"type":"Point"}
}