{
  "type": "Feature",
  "properties": {
    "addr:full":"1025 SW Myrtle Dr Portland OR 97201",
    "addr:housenumber":"1025",
    "addr:postcode":"97201",
    "addr:street":"Sw Myrtle Dr",
    "iso:country":"US",
    "sg:address":"1025 SW Myrtle Dr",
    "sg:city":"Portland",
    "sg:classifiers":[
        {
            "category":"Health Services",
            "subcategory":"Dentist",
            "type":"Services"
        }
    ],
    "sg:phone":"+1 503 450 0878",
    "sg:postcode":"97201",
    "sg:province":"OR",
    "wof:name":"Pike Allan R DDS",
    "wof:placetype":"venue"
},
  "geometry": {"coordinates":[-122.689376,45.507651],"type":"Point"}
}