{
  "type": "Feature",
  "properties": {
    "iso:country":"US",
    "sg:address":"3920 NW Terra Lynda Dr",
    "sg:city":"Albany",
    "sg:classifiers":[
        {
            "category":"Manufacturing",
            "subcategory":"Building Materials",
            "type":"Manufacturing & Wholesale Goods"
        }
    ],
    "sg:phone":"+1 541 928 1498",
    "sg:postcode":"97321",
    "sg:province":"OR",
    "sg:tags":[
        "mfg",
        "wood",
        "kitchen",
        "cabinet"
    ],
    "wof:name":"Bill Lane Cabinets",
    "wof:placetype":"venue"
},
  "geometry": {"coordinates":[-123.15337100000001,44.6788],"type":"Point"}
}