{
  "type": "Feature",
  "properties": {
    "addr:full":"1717 SE Alder Way Toledo OR 97391",
    "addr:housenumber":"1717",
    "addr:postcode":"97391",
    "addr:street":"Se Alder Way",
    "iso:country":"US",
    "sg:address":"1717 SE Alder Way",
    "sg:city":"Toledo",
    "sg:classifiers":[
        {
            "category":"Manufacturing",
            "subcategory":"Glass & Minerals",
            "type":"Manufacturing & Wholesale Goods"
        }
    ],
    "sg:phone":"+1 541 336 2622",
    "sg:postcode":"97391",
    "sg:province":"OR",
    "sg:tags":[
        "product",
        "mfg"
    ],
    "wof:name":"Draggin Glass",
    "wof:placetype":"venue"
},
  "geometry": {"coordinates":[-123.920238,44.611869],"type":"Point"}
}