{
  "type": "Feature",
  "properties": {
    "iso:country":"US",
    "sg:address":"15917 NW Logie Trl",
    "sg:city":"Hillsboro",
    "sg:classifiers":[
        {
            "category":"Building & Trades",
            "subcategory":"Electrical",
            "type":"Services"
        }
    ],
    "sg:phone":"+1 503 647 5823",
    "sg:postcode":"97124",
    "sg:province":"OR",
    "sg:tags":[
        "electrical",
        "contractor"
    ],
    "wof:name":"Athens Electric Inc",
    "wof:placetype":"venue"
},
  "geometry": {"coordinates":[-122.929179,45.632854],"type":"Point"}
}