{
  "type": "Feature",
  "properties": {
    "iso:country":"US",
    "sg:address":"11826 NE Glisan St",
    "sg:city":"Portland",
    "sg:classifiers":[
        {
            "category":"Shopping",
            "subcategory":"Department Store",
            "type":"Retail Goods"
        }
    ],
    "sg:phone":"+1 503 251 9997",
    "sg:postcode":"97220",
    "sg:province":"OR",
    "wof:name":"Target",
    "wof:placetype":"venue"
},
  "geometry": {"coordinates":[-122.54050599999999,45.525094],"type":"Point"}
}