{
  "type": "Feature",
  "properties": {
    "iso:country":"US",
    "sg:address":"83531 Rodgers Rd",
    "sg:city":"Creswell",
    "sg:classifiers":[
        {
            "category":"Freight",
            "type":"Transportation"
        }
    ],
    "sg:phone":"+1 541 895 4154",
    "sg:postcode":"97426",
    "sg:province":"OR",
    "sg:tags":[
        "operator",
        "trucking"
    ],
    "wof:name":"L C Good",
    "wof:placetype":"venue"
},
  "geometry": {"coordinates":[-122.963542,43.933071],"type":"Point"}
}