{
  "type": "Feature",
  "properties": {
    "iso:country":"US",
    "sg:address":"215 SW Adams Ave",
    "sg:city":"Hillsboro",
    "sg:classifiers":[
        {
            "category":"Government",
            "subcategory":"Police Station",
            "type":"Public Place"
        }
    ],
    "sg:phone":"+1 503 846 2700",
    "sg:postcode":"97123",
    "sg:province":"OR",
    "sg:tags":[
        "sheriff"
    ],
    "wof:name":"Washington County Sheriff",
    "wof:placetype":"venue"
},
  "geometry": {"coordinates":[-122.99140300000001,45.520305],"type":"Point"}
}