{
  "type": "Feature",
  "properties": {
    "iso:country":"US",
    "sg:address":"21300 NW Cornell Rd",
    "sg:city":"Hillsboro",
    "sg:classifiers":[
        {
            "category":"Freight",
            "type":"Transportation"
        }
    ],
    "sg:phone":"+1 503 690 1923",
    "sg:postcode":"97124",
    "sg:province":"OR",
    "sg:tags":[
        "warehouse",
        "mini",
        "recreational",
        "storage",
        "vehicle"
    ],
    "wof:name":"Tanasbourne Mini Storage & R V",
    "wof:placetype":"venue"
},
  "geometry": {"coordinates":[-122.898489,45.539638],"type":"Point"}
}