{
  "type": "Feature",
  "properties": {
    "iso:country":"US",
    "sg:address":"10121 SE Sunnyside Rd Ste 300",
    "sg:city":"Clackamas",
    "sg:classifiers":[
        {
            "category":"Banks & Credit Unions",
            "subcategory":"Atm",
            "type":"Services"
        }
    ],
    "sg:phone":"+1 503 654 9844",
    "sg:postcode":"97015",
    "sg:province":"OR",
    "sg:tags":[
        "bankruptcy"
    ],
    "wof:name":"Sunderland & Associates",
    "wof:placetype":"venue"
},
  "geometry": {"coordinates":[-122.55999799999999,45.433399],"type":"Point"}
}