{
  "type": "Feature",
  "properties": {
    "iso:country":"US",
    "sg:address":"328 Jonquil Ave",
    "sg:city":"Eugene",
    "sg:classifiers":[
        {
            "category":"Social Services",
            "subcategory":"Child Care",
            "type":"Services"
        }
    ],
    "sg:phone":"+1 541 689 6258",
    "sg:postcode":"97404",
    "sg:province":"OR",
    "sg:tags":[
        "day"
    ],
    "wof:name":"After School Club LLC",
    "wof:placetype":"venue"
},
  "geometry": {"coordinates":[-123.13736900000001,44.101764],"type":"Point"}
}