{
  "type": "Feature",
  "properties": {
    "addr:full":"20856 S Springwater Rd Estacada OR 97023",
    "addr:housenumber":"20856",
    "addr:postcode":"97023",
    "addr:street":"S Springwater Rd",
    "iso:country":"US",
    "sg:address":"20856 S Springwater Rd",
    "sg:city":"Estacada",
    "sg:classifiers":[
        {
            "category":"Building & Trades",
            "subcategory":"Construction",
            "type":"Services"
        }
    ],
    "sg:phone":"+1 503 631 2661",
    "sg:postcode":"97023",
    "sg:province":"OR",
    "sg:tags":[
        "carpentry",
        "contractor"
    ],
    "wof:name":"Nations Construction",
    "wof:placetype":"venue"
},
  "geometry": {"coordinates":[-122.38670999999999,45.304655],"type":"Point"}
}