{
  "type": "Feature",
  "properties": {
    "iso:country":"US",
    "sg:address":"20856 S Springwater Rd",
    "sg:city":"Estacada",
    "sg:classifiers":[
        {
            "category":"Building & Trades",
            "subcategory":"Construction",
            "type":"Services"
        }
    ],
    "sg:phone":"+1 503 631 2661",
    "sg:postcode":"97023",
    "sg:province":"OR",
    "sg:tags":[
        "carpentry",
        "contractor"
    ],
    "wof:name":"Nations Construction",
    "wof:placetype":"venue"
},
  "geometry": {"coordinates":[-122.38671,45.304655],"type":"Point"}
}