{
  "type": "Feature",
  "properties": {
    "addr:full":"41923 Holden Creek Ln Springfield OR 97478",
    "addr:housenumber":"41923",
    "addr:postcode":"97478",
    "addr:street":"Holden Creek Ln",
    "iso:country":"US",
    "sg:address":"41923 Holden Creek Ln",
    "sg:city":"Springfield",
    "sg:classifiers":[
        {
            "category":"Building & Trades",
            "subcategory":"Construction",
            "type":"Services"
        }
    ],
    "sg:phone":"+1 541 896 0264",
    "sg:postcode":"97478",
    "sg:province":"OR",
    "sg:tags":[
        "fabrication",
        "welding"
    ],
    "wof:name":"Jvs Mobile Wldg Millright Svc",
    "wof:placetype":"venue"
},
  "geometry": {"coordinates":[-122.708259,44.093626],"type":"Point"}
}