{
  "type": "Feature",
  "properties": {
    "addr:full":"5707 SE 128th Ave Portland OR 97236",
    "addr:housenumber":"5707",
    "addr:postcode":"97236",
    "addr:street":"Se 128Th Ave",
    "iso:country":"US",
    "sg:address":"5707 SE 128th Ave",
    "sg:city":"Portland",
    "sg:classifiers":[
        {
            "category":"Retail",
            "subcategory":"Laundry & Dry Cleaning",
            "type":"Services"
        }
    ],
    "sg:phone":"+1 503 692 1076",
    "sg:postcode":"97236",
    "sg:province":"OR",
    "sg:tags":[
        "cleaner",
        "rug",
        "carpet"
    ],
    "wof:name":"Mighty Clean",
    "wof:placetype":"venue"
},
  "geometry": {"coordinates":[-122.532329,45.48135],"type":"Point"}
}