{
  "type": "Feature",
  "properties": {
    "iso:country":"US",
    "sg:address":"10880 SW Barnes Rd",
    "sg:city":"Portland",
    "sg:classifiers":[
        {
            "category":"Education",
            "subcategory":"Dance Studio",
            "type":"Public Place"
        }
    ],
    "sg:phone":"+1 503 292 6205",
    "sg:postcode":"97225",
    "sg:province":"OR",
    "wof:name":"Canoy Studio LLC",
    "wof:placetype":"venue"
},
  "geometry": {"coordinates":[-122.788883,45.514593],"type":"Point"}
}