{
  "type": "Feature",
  "properties": {
    "iso:country":"US",
    "sg:address":"12008 NE Inverness Dr",
    "sg:city":"Portland",
    "sg:classifiers":[
        {
            "category":"Wholesale",
            "subcategory":"Motor Vehicles",
            "type":"Manufacturing & Wholesale Goods"
        },
        {
            "category":"Structure",
            "subcategory":"Warehouse",
            "type":"Public Place"
        },
        {
            "category":"Retail",
            "subcategory":"Auto Rental",
            "type":"Services"
        },
        {
            "category":"Travel",
            "subcategory":"Travel Agent",
            "type":"Entertainment"
        },
        {
            "category":"Retail",
            "subcategory":"Storage",
            "type":"Services"
        }
    ],
    "sg:phone":"+1 503 251 0500",
    "sg:postcode":"97220",
    "sg:province":"OR",
    "sg:tags":[
        "renting",
        "campers-wholesale",
        "leasing",
        "warehouses-public-commercial",
        "self",
        "recreational",
        "trailer",
        "manufacturer"
    ],
    "sg:website":"http://www.containerspace.com",
    "wof:name":"Mckinney Trailer",
    "wof:placetype":"venue"
},
  "geometry": {"coordinates":[-122.53664499999999,45.563025],"type":"Point"}
}