{
  "type": "Feature",
  "properties": {
    "iso:country":"US",
    "sg:address":"1494 NE Stephens St",
    "sg:city":"Roseburg",
    "sg:classifiers":[
        {
            "category":"Home & Garden",
            "subcategory":"Building Materials",
            "type":"Retail Goods"
        }
    ],
    "sg:phone":"+1 541 673 5127",
    "sg:postcode":"97470",
    "sg:province":"OR",
    "sg:tags":[
        "equipment",
        "electric",
        "supply"
    ],
    "wof:name":"Apex Ace Homectr",
    "wof:placetype":"venue"
},
  "geometry": {"coordinates":[-123.349169,43.226749],"type":"Point"}
}