{
  "type": "Feature",
  "properties": {
    "addr:full":"381 S Broadway St Estacada OR 97023",
    "addr:housenumber":"381",
    "addr:postcode":"97023",
    "addr:street":"S Broadway St",
    "iso:country":"US",
    "sg:address":"381 S Broadway St",
    "sg:city":"Estacada",
    "sg:classifiers":[
        {
            "category":"Cinema",
            "subcategory":"Movie Rental",
            "type":"Entertainment"
        }
    ],
    "sg:phone":"+1 503 630 4432",
    "sg:postcode":"97023",
    "sg:province":"OR",
    "sg:tags":[
        "leasing",
        "video",
        "disc",
        "tape"
    ],
    "wof:name":"Just In Video",
    "wof:placetype":"venue"
},
  "geometry": {"coordinates":[-122.335264,45.286912],"type":"Point"}
}