{
  "type": "Feature",
  "properties": {
    "iso:country":"US",
    "sg:address":"8002 N Lombard St",
    "sg:city":"Portland",
    "sg:classifiers":[
        {
            "category":"Bars & Pubs",
            "type":"Food & Drink"
        },
        {
            "category":"Restaurant",
            "type":"Food & Drink"
        }
    ],
    "sg:phone":"+1 503 289 7606",
    "sg:postcode":"97203",
    "sg:province":"OR",
    "sg:tags":[
        "traditional",
        "american"
    ],
    "sg:website":"www.leisurepublichouse.com/",
    "wof:name":"Leisure Public House",
    "wof:placetype":"venue"
},
  "geometry": {"coordinates":[-122.74827000000001,45.589073],"type":"Point"}
}