{
  "type": "Feature",
  "properties": {
    "iso:country":"US",
    "sg:address":"3920 Columbia View Dr",
    "sg:city":"The Dalles",
    "sg:classifiers":[
        {
            "category":"Government",
            "subcategory":"Office",
            "type":"Public Place"
        }
    ],
    "sg:phone":"+1 541 980 2541",
    "sg:postcode":"97058",
    "sg:province":"OR",
    "sg:tags":[
        "executive"
    ],
    "wof:name":"Celilo Converter Station",
    "wof:placetype":"venue"
},
  "geometry": {"coordinates":[-121.118706,45.60866],"type":"Point"}
}