{
  "type": "Feature",
  "properties": {
    "addr:full":"279 Kester Rd Roseburg OR 97470",
    "addr:housenumber":"279",
    "addr:postcode":"97470",
    "addr:street":"Kester Rd",
    "iso:country":"US",
    "sg:address":"279 Kester Rd",
    "sg:city":"Roseburg",
    "sg:classifiers":[
        {
            "category":"Building & Trades",
            "subcategory":"Construction",
            "type":"Services"
        }
    ],
    "sg:phone":"+1 541 672 9511",
    "sg:postcode":"97470",
    "sg:province":"OR",
    "sg:tags":[
        "general",
        "contractor"
    ],
    "wof:name":"J R Turner Construction Inc",
    "wof:placetype":"venue"
},
  "geometry": {"coordinates":[-123.28872200000001,43.2186],"type":"Point"}
}