{
  "type": "Feature",
  "properties": {
    "iso:country":"US",
    "sg:address":"390 18th St SE",
    "sg:city":"Salem",
    "sg:classifiers":[
        {
            "category":"Professional",
            "type":"Services"
        }
    ],
    "sg:phone":"+1 503 581 3645",
    "sg:postcode":"97301",
    "sg:province":"OR",
    "wof:name":"Bluegrass Boutique",
    "wof:placetype":"venue"
},
  "geometry": {"coordinates":[-123.02007500000001,44.93288],"type":"Point"}
}