{
  "type": "Feature",
  "properties": {
    "iso:country":"US",
    "sg:address":"9645 SW Beavertn Hllsdle Hwy",
    "sg:city":"Beaverton",
    "sg:classifiers":[
        {
            "category":"Personal",
            "subcategory":"Barber",
            "type":"Services"
        }
    ],
    "sg:phone":"+1 503 641 5272",
    "sg:postcode":"97005",
    "sg:province":"OR",
    "wof:name":"Watch Your Head",
    "wof:placetype":"venue"
},
  "geometry": {"coordinates":[-122.77600099999999,45.486401],"type":"Point"}
}