{
  "type": "Feature",
  "properties": {
    "iso:country":"US",
    "sg:address":"4205 NE Cully Boulevard",
    "sg:city":"Portland",
    "sg:classifiers":[
        {
            "category":"Retail",
            "subcategory":"Auto Repair",
            "type":"Services"
        }
    ],
    "sg:phone":"+1 503 460 9772",
    "sg:postcode":"97218",
    "sg:province":"OR",
    "wof:name":"Cully Boulevard Automotive",
    "wof:placetype":"venue"
},
  "geometry": {"coordinates":[-122.602706,45.553479],"type":"Point"}
}