{
  "type": "Feature",
  "properties": {
    "addr:full":"14455 SW Allen Blvd Beaverton OR 97005",
    "addr:housenumber":"14455",
    "addr:postcode":"97005",
    "addr:street":"Sw Allen Blvd",
    "iso:country":"US",
    "sg:address":"14455 SW Allen Blvd",
    "sg:city":"Beaverton",
    "sg:classifiers":[
        {
            "category":"Health Services",
            "subcategory":"Doctor",
            "type":"Services"
        }
    ],
    "sg:phone":"+1 503 671 9054",
    "sg:postcode":"97005",
    "sg:province":"OR",
    "wof:name":"Kathy Kim DDS",
    "wof:placetype":"venue"
},
  "geometry": {"coordinates":[-122.824583,45.476556],"type":"Point"}
}