{
  "type": "Feature",
  "properties": {
    "addr:full":"14700 SE Division St Portland OR 97236",
    "addr:postcode":"14700;97236",
    "addr:street":"Se Division St",
    "iso:country":"US",
    "sg:address":"14700 SE Division St",
    "sg:city":"Portland",
    "sg:classifiers":[
        {
            "category":"Shopping",
            "subcategory":"Optical Goods",
            "type":"Retail Goods"
        }
    ],
    "sg:phone":"+1 503 761 1975",
    "sg:postcode":"97236",
    "sg:province":"OR",
    "wof:name":"National Vision",
    "wof:placetype":"venue"
},
  "geometry": {"coordinates":[-122.511867,45.504127],"type":"Point"}
}