{
  "type": "Feature",
  "properties": {
    "iso:country":"US",
    "sg:address":"3703 Arock Rd",
    "sg:city":"Jordan Valley",
    "sg:classifiers":[
        {
            "category":"Travel",
            "subcategory":"Campground",
            "type":"Entertainment"
        }
    ],
    "sg:phone":"+1 541 586 2481",
    "sg:postcode":"97910",
    "sg:province":"OR",
    "sg:tags":[
        "camp"
    ],
    "wof:name":"Robert C Fretwell",
    "wof:placetype":"venue"
},
  "geometry": {"coordinates":[-117.523943,42.885352],"type":"Point"}
}