{
  "type": "Feature",
  "properties": {
    "iso:country":"US",
    "sg:address":"649 W Harrison St",
    "sg:city":"Roseburg",
    "sg:classifiers":[
        {
            "category":"Professional",
            "type":"Services"
        }
    ],
    "sg:phone":"+1 541 957 1800",
    "sg:postcode":"97470",
    "sg:province":"OR",
    "wof:name":"Dr Robert Clarke ND Lac",
    "wof:placetype":"venue"
},
  "geometry": {"coordinates":[-123.36082500000001,43.213075],"type":"Point"}
}