{
  "type": "Feature",
  "properties": {
    "iso:country":"US",
    "sg:address":"5781 Main St",
    "sg:city":"Springfield",
    "sg:classifiers":[
        {
            "category":"Health Services",
            "subcategory":"Doctor",
            "type":"Services"
        }
    ],
    "sg:phone":"+1 541 744 7305",
    "sg:postcode":"97478",
    "sg:province":"OR",
    "sg:tags":[
        "medical"
    ],
    "wof:name":"Thurston Medical Clinic",
    "wof:placetype":"venue"
},
  "geometry": {"coordinates":[-122.927441,44.045609],"type":"Point"}
}