{
  "type": "Feature",
  "properties": {
    "iso:country":"US",
    "sg:address":"9330 NE Schuyler St",
    "sg:city":"Portland",
    "sg:classifiers":[
        {
            "category":"Building & Trades",
            "subcategory":"Cleaning & Sanitation",
            "type":"Services"
        }
    ],
    "sg:phone":"+1 503 257 0347",
    "sg:postcode":"97220",
    "sg:province":"OR",
    "sg:tags":[
        "janitor"
    ],
    "wof:name":"Master Building Maintenance",
    "wof:placetype":"venue"
},
  "geometry": {"coordinates":[-122.56645899999999,45.535783],"type":"Point"}
}