{
  "type": "Feature",
  "properties": {
    "addr:full":"8025 SW 185th Ave Beaverton OR 97007",
    "addr:housenumber":"8025",
    "addr:postcode":"97007",
    "addr:street":"Sw 185Th Ave",
    "iso:country":"US",
    "sg:address":"8025 SW 185th Ave",
    "sg:city":"Beaverton",
    "sg:classifiers":[
        {
            "category":"Manufacturing",
            "subcategory":"Toys & Sporting Goods",
            "type":"Manufacturing & Wholesale Goods"
        }
    ],
    "sg:phone":"+1 503 649 7922",
    "sg:postcode":"97007",
    "sg:province":"OR",
    "sg:tags":[
        "stroller",
        "mfg"
    ],
    "wof:name":"Runabout/USA Inc",
    "wof:placetype":"venue"
},
  "geometry": {"coordinates":[-122.867582,45.460602],"type":"Point"}
}