{
  "type": "Feature",
  "properties": {
    "iso:country":"US",
    "sg:address":"2120 Pacific Blvd SW",
    "sg:city":"Albany",
    "sg:classifiers":[
        {
            "category":"Shopping",
            "subcategory":"Computers & Home Electronics",
            "type":"Retail Goods"
        }
    ],
    "sg:phone":"+1 541 928 1827",
    "sg:postcode":"97321",
    "sg:province":"OR",
    "sg:tags":[
        "parts",
        "supply"
    ],
    "wof:name":"Northwest Ribbon Recycling",
    "wof:placetype":"venue"
},
  "geometry": {"coordinates":[-123.111801,44.620944],"type":"Point"}
}