{
  "type": "Feature",
  "properties": {
    "iso:country":"US",
    "sg:address":"349 W D St",
    "sg:city":"Springfield",
    "sg:classifiers":[
        {
            "category":"Retail",
            "subcategory":"Repair Shop",
            "type":"Services"
        }
    ],
    "sg:phone":"+1 541 485 8930",
    "sg:postcode":"97477",
    "sg:province":"OR",
    "wof:name":"Ace Plumbing",
    "wof:placetype":"venue"
},
  "geometry": {"coordinates":[-123.029577,44.049655],"type":"Point"}
}