{
  "type": "Feature",
  "properties": {
    "iso:country":"US",
    "sg:address":"4877 Parkview Dr",
    "sg:city":"Lake Oswego",
    "sg:classifiers":[
        {
            "category":"Building & Trades",
            "subcategory":"Construction",
            "type":"Services"
        }
    ],
    "sg:phone":"+1 503 697 9805",
    "sg:postcode":"97035",
    "sg:province":"OR",
    "sg:tags":[
        "house"
    ],
    "wof:name":"Mock Construction Inc",
    "wof:placetype":"venue"
},
  "geometry": {"coordinates":[-122.73063999999999,45.420857],"type":"Point"}
}