{
  "type": "Feature",
  "properties": {
    "iso:country":"US",
    "sg:address":"1447 8th St",
    "sg:city":"Astoria",
    "sg:classifiers":[
        {
            "category":"Building & Trades",
            "subcategory":"Construction",
            "type":"Services"
        }
    ],
    "sg:phone":"+1 503 325 7406",
    "sg:postcode":"97103",
    "sg:province":"OR",
    "sg:tags":[
        "concrete",
        "contractor"
    ],
    "wof:name":"Jack Coffey Construction",
    "wof:placetype":"venue"
},
  "geometry": {"coordinates":[-123.835013,46.180484],"type":"Point"}
}