{
  "type": "Feature",
  "properties": {
    "iso:country":"US",
    "sg:address":"300 N Main St",
    "sg:city":"Lebanon",
    "sg:classifiers":[
        {
            "category":"Autos & Motor Vehicles",
            "subcategory":"Fuel & Gas Station",
            "type":"Retail Goods"
        }
    ],
    "sg:phone":"+1 541 451 1100",
    "sg:postcode":"97355",
    "sg:province":"OR",
    "sg:tags":[
        "oil"
    ],
    "wof:name":"Leathers Oil Co",
    "wof:placetype":"venue"
},
  "geometry": {"coordinates":[-122.907876,44.548749],"type":"Point"}
}