{
  "type": "Feature",
  "properties": {
    "iso:country":"US",
    "sg:address":"2029 25th St SE",
    "sg:city":"Salem",
    "sg:classifiers":[
        {
            "category":"Wholesale",
            "subcategory":"Machinery & Supplies",
            "type":"Manufacturing & Wholesale Goods"
        }
    ],
    "sg:phone":"+1 503 362 0811",
    "sg:postcode":"97301",
    "sg:province":"OR",
    "sg:tags":[
        "aircraft",
        "retail",
        "parts"
    ],
    "wof:name":"All Spares Inc",
    "wof:placetype":"venue"
},
  "geometry": {"coordinates":[-123.010375,44.916895],"type":"Point"}
}