{
  "type": "Feature",
  "properties": {
    "iso:country":"US",
    "sg:address":"2185 14th Ave SE",
    "sg:city":"Albany",
    "sg:classifiers":[
        {
            "category":"Personal",
            "subcategory":"Beauty Salon",
            "type":"Services"
        }
    ],
    "sg:phone":"+1 541 928 4141",
    "sg:postcode":"97322",
    "sg:province":"OR",
    "sg:tags":[
        "shop"
    ],
    "wof:name":"Excellent Nails",
    "wof:placetype":"venue"
},
  "geometry": {"coordinates":[-123.081102,44.628837],"type":"Point"}
}