{
  "type": "Feature",
  "properties": {
    "iso:country":"US",
    "sg:address":"1130 SE 225th Ave",
    "sg:city":"Gresham",
    "sg:classifiers":[
        {
            "category":"Real Estate",
            "subcategory":"Real Estate Agent",
            "type":"Services"
        }
    ],
    "sg:phone":"+1 503 661 3214",
    "sg:postcode":"97030",
    "sg:province":"OR",
    "wof:name":"David & Carol Duncan",
    "wof:placetype":"venue"
},
  "geometry": {"coordinates":[-122.431529,45.515804],"type":"Point"}
}