{
  "type": "Feature",
  "properties": {
    "iso:country":"US",
    "sg:address":"3426 Delta Waters Rd",
    "sg:city":"Medford",
    "sg:classifiers":[
        {
            "category":"Shopping",
            "type":"Retail Goods"
        }
    ],
    "sg:phone":"+1 541 772 7800",
    "sg:postcode":"97504",
    "sg:province":"OR",
    "sg:tags":[
        "plant",
        "flower",
        "tree",
        "artificial"
    ],
    "wof:name":"Silk Florist",
    "wof:placetype":"venue"
},
  "geometry": {"coordinates":[-122.827235,42.360109],"type":"Point"}
}