{
  "type": "Feature",
  "properties": {
    "iso:country":"US",
    "sg:address":"301 NE 6th St",
    "sg:city":"Grants Pass",
    "sg:classifiers":[
        {
            "category":"Professional",
            "subcategory":"Computer Services",
            "type":"Services"
        }
    ],
    "sg:phone":"+1 541 955 6930",
    "sg:postcode":"97526",
    "sg:province":"OR",
    "sg:tags":[
        "internet"
    ],
    "wof:name":"Rascal Internet Svc",
    "wof:placetype":"venue"
},
  "geometry": {"coordinates":[-123.326075,42.440757],"type":"Point"}
}