{
  "type": "Feature",
  "properties": {
    "iso:country":"US",
    "sg:address":"93520 Hwy 99 S",
    "sg:city":"Junction City",
    "sg:classifiers":[
        {
            "category":"Real Estate",
            "subcategory":"Developer",
            "type":"Services"
        }
    ],
    "sg:phone":"+1 541 998 6714",
    "sg:postcode":"97448",
    "sg:province":"OR",
    "sg:tags":[
        "mobile",
        "home"
    ],
    "wof:name":"Trailer Town",
    "wof:placetype":"venue"
},
  "geometry": {"coordinates":[-123.20331,44.20126],"type":"Point"}
}