{
  "type": "Feature",
  "properties": {
    "iso:country":"US",
    "sg:address":"601 NW Harmon Blvd",
    "sg:city":"Bend",
    "sg:classifiers":[
        {
            "category":"Organizations",
            "subcategory":"Non-profit Organization",
            "type":"Services"
        }
    ],
    "sg:phone":"+1 541 383 0844",
    "sg:postcode":"97701",
    "sg:province":"OR",
    "sg:tags":[
        "information",
        "alcoholism",
        "treatment"
    ],
    "wof:name":"Serenity Lane Treatment Ctr",
    "wof:placetype":"venue"
},
  "geometry": {"coordinates":[-121.326187,44.055699],"type":"Point"}
}