{
  "type": "Feature",
  "properties": {
    "addr:full":"937 11th Ave SW Albany OR 97321",
    "addr:housenumber":"937",
    "addr:postcode":"97321",
    "addr:street":"11Th Ave Sw",
    "iso:country":"US",
    "sg:address":"937 11th Ave SW",
    "sg:city":"Albany",
    "sg:classifiers":[
        {
            "category":"Professional",
            "type":"Services"
        }
    ],
    "sg:phone":"+1 541 967 6447",
    "sg:postcode":"97321",
    "sg:province":"OR",
    "wof:name":"Larry Peterson",
    "wof:placetype":"venue"
},
  "geometry": {"coordinates":[-123.113491,44.628523],"type":"Point"}
}