{
  "type": "Feature",
  "properties": {
    "addr:full":"3987 N Mississippi Ave Portland OR 97227",
    "addr:housenumber":"3987",
    "addr:postcode":"97227",
    "addr:street":"N Mississippi Ave",
    "iso:country":"US",
    "sg:address":"3987 N Mississippi Ave",
    "sg:city":"Portland",
    "sg:classifiers":[
        {
            "category":"Real Estate",
            "subcategory":"Real Estate Agent",
            "type":"Services"
        }
    ],
    "sg:phone":"+1 503 335 0947",
    "sg:postcode":"97227",
    "sg:province":"OR",
    "sg:tags":[
        "authorities",
        "housing"
    ],
    "wof:name":"Albina Community Dev Corp",
    "wof:placetype":"venue"
},
  "geometry": {"coordinates":[-122.675611,45.550998],"type":"Point"}
}