{
  "type": "Feature",
  "properties": {
    "iso:country":"US",
    "sg:address":"53877 Beach Loop Rd",
    "sg:city":"Bandon",
    "sg:classifiers":[
        {
            "category":"Travel",
            "subcategory":"Campground",
            "type":"Entertainment"
        }
    ],
    "sg:phone":"+1 541 347 2100",
    "sg:postcode":"97411",
    "sg:province":"OR",
    "sg:tags":[
        "recreational",
        "parks",
        "vehicle"
    ],
    "wof:name":"Beach Loop Rv Village",
    "wof:placetype":"venue"
},
  "geometry": {"coordinates":[-124.420607,43.068555],"type":"Point"}
}