{
  "type": "Feature",
  "properties": {
    "addr:full":"714 N Bertelsen Rd Eugene OR 97402",
    "addr:housenumber":"714",
    "addr:postcode":"97402",
    "addr:street":"N Bertelsen Rd",
    "iso:country":"US",
    "sg:address":"714 N Bertelsen Rd",
    "sg:city":"Eugene",
    "sg:classifiers":[
        {
            "category":"Wholesale",
            "subcategory":"Medical Equipment & Supplies",
            "type":"Manufacturing & Wholesale Goods"
        }
    ],
    "sg:phone":"+1 541 345 0529",
    "sg:postcode":"97402",
    "sg:province":"OR",
    "sg:tags":[
        "dental"
    ],
    "wof:name":"Patterson Dental Co",
    "wof:placetype":"venue"
},
  "geometry": {"coordinates":[-123.16314800000001,44.068342],"type":"Point"}
}