{
  "type": "Feature",
  "properties": {
    "addr:full":"13145 SE River Rd Portland OR 97222",
    "addr:postcode":"13145;97222",
    "addr:street":"Se River Rd",
    "iso:country":"US",
    "sg:address":"13145 SE River Rd",
    "sg:city":"Portland",
    "sg:classifiers":[
        {
            "category":"Social Services",
            "subcategory":"Job Training",
            "type":"Services"
        },
        {
            "category":"Social Services",
            "subcategory":"Retirement Home",
            "type":"Services"
        }
    ],
    "sg:phone":"+1 503 353 7000",
    "sg:postcode":"97222",
    "sg:province":"OR",
    "sg:tags":[
        "living",
        "assisted",
        "nursing",
        "homes-skilled",
        "facility"
    ],
    "wof:name":"Willamette View Retire Comm",
    "wof:placetype":"venue"
},
  "geometry": {"coordinates":[-122.64511299999999,45.427627],"type":"Point"}
}