{
  "type": "Feature",
  "properties": {
    "addr:full":"4822 SE Division St Portland OR 97206",
    "addr:housenumber":"4822",
    "addr:postcode":"97206",
    "addr:street":"Se Division St",
    "iso:country":"US",
    "sg:address":"4822 SE Division St",
    "sg:city":"Portland",
    "sg:classifiers":[
        {
            "category":"Bars & Pubs",
            "type":"Food & Drink"
        }
    ],
    "sg:phone":"+1 503 233 2971",
    "sg:postcode":"97206",
    "sg:province":"OR",
    "sg:tags":[
        "drinking"
    ],
    "wof:name":"Scoreboard Sports Bar",
    "wof:placetype":"venue"
},
  "geometry": {"coordinates":[-122.612171,45.505224],"type":"Point"}
}