{
  "type": "Feature",
  "properties": {
    "addr:full":"1702 SE Taylor St Portland OR 97214",
    "addr:housenumber":"1702",
    "addr:postcode":"97214",
    "addr:street":"Se Taylor St",
    "iso:country":"US",
    "sg:address":"1702 SE Taylor St",
    "sg:city":"Portland",
    "sg:classifiers":[
        {
            "category":"Professional",
            "subcategory":"Art Services",
            "type":"Services"
        }
    ],
    "sg:phone":"+1 503 851 5788",
    "sg:postcode":"97214",
    "sg:province":"OR",
    "sg:tags":[
        "photographer"
    ],
    "wof:name":"Matt D. Pictures",
    "wof:placetype":"venue"
},
  "geometry": {"coordinates":[-122.648257,45.515036],"type":"Point"}
}