{
  "type": "Feature",
  "properties": {
    "addr:full":"536 SW 10th St Redmond OR 97756",
    "addr:housenumber":"536",
    "addr:postcode":"97756",
    "addr:street":"Sw 10Th St",
    "iso:country":"US",
    "sg:address":"536 SW 10th St",
    "sg:city":"Redmond",
    "sg:classifiers":[
        {
            "category":"Organizations",
            "subcategory":"Religious Organization",
            "type":"Services"
        }
    ],
    "sg:phone":"+1 541 548 2974",
    "sg:postcode":"97756",
    "sg:province":"OR",
    "sg:tags":[
        "church"
    ],
    "sg:website":"www.redmondchristian.org",
    "wof:name":"Christian Church of Redmond or",
    "wof:placetype":"venue"
},
  "geometry": {"coordinates":[-121.178471,44.272192],"type":"Point"}
}