{
  "type": "Feature",
  "properties": {
    "iso:country":"US",
    "sg:address":"16253 SE 122nd Ave",
    "sg:city":"Clackamas",
    "sg:classifiers":[
        {
            "category":"Manufacturing",
            "subcategory":"Food",
            "type":"Manufacturing & Wholesale Goods"
        }
    ],
    "sg:phone":"+1 503 650 2000",
    "sg:postcode":"97015",
    "sg:province":"OR",
    "sg:tags":[
        "bakery",
        "prod",
        "cookie"
    ],
    "wof:name":"Clackamas Bakery",
    "wof:placetype":"venue"
},
  "geometry": {"coordinates":[-122.537941,45.406072],"type":"Point"}
}