{
  "type": "Feature",
  "properties": {
    "iso:country":"US",
    "sg:address":"18340 State Hwy 42",
    "sg:city":"Camas Valley",
    "sg:classifiers":[
        {
            "category":"Restaurant",
            "type":"Food & Drink"
        }
    ],
    "sg:phone":"+1 541 445 2000",
    "sg:postcode":"97416",
    "sg:province":"OR",
    "sg:tags":[
        "delicatessen"
    ],
    "wof:name":"Wolfe's Camas Valley General",
    "wof:placetype":"venue"
},
  "geometry": {"coordinates":[-123.672811,43.034763],"type":"Point"}
}