{
  "type": "Feature",
  "properties": {
    "iso:country":"US",
    "sg:address":"14400 N Rivergate Blvd",
    "sg:city":"Portland",
    "sg:classifiers":[
        {
            "category":"Manufacturing",
            "subcategory":"Metals",
            "type":"Manufacturing & Wholesale Goods"
        }
    ],
    "sg:phone":"+1 800 547 9451",
    "sg:postcode":"97203",
    "sg:province":"OR",
    "sg:tags":[
        "steel",
        "distributor",
        "mill",
        "warehouse"
    ],
    "wof:name":"Evraz Inc",
    "wof:placetype":"venue"
},
  "geometry": {"coordinates":[-122.780115,45.6254],"type":"Point"}
}