{
  "type": "Feature",
  "properties": {
    "addr:full":"3600 SE 17th Ave Portland OR 97202",
    "addr:housenumber":"3600",
    "addr:postcode":"97202",
    "addr:street":"Se 17Th Ave",
    "iso:country":"US",
    "sg:address":"3600 SE 17th Ave",
    "sg:city":"Portland",
    "sg:classifiers":[
        {
            "category":"Building & Trades",
            "subcategory":"Construction",
            "type":"Services"
        },
        {
            "category":"Home & Garden",
            "subcategory":"Furniture",
            "type":"Retail Goods"
        }
    ],
    "sg:phone":"+1 503 234 1291",
    "sg:postcode":"97202",
    "sg:province":"OR",
    "sg:tags":[
        "cabinet",
        "carpentry",
        "contractor"
    ],
    "wof:name":"Pai Custom Cabinet Inc",
    "wof:placetype":"venue"
},
  "geometry": {"coordinates":[-122.648304,45.49603],"type":"Point"}
}