{
  "type": "Feature",
  "properties": {
    "addr:full":"1424 W 2nd St The Dalles OR 97058",
    "addr:housenumber":"1424",
    "addr:postcode":"97058",
    "addr:street":"W 2Nd St",
    "iso:country":"US",
    "sg:address":"1424 W 2nd St",
    "sg:city":"The Dalles",
    "sg:classifiers":[
        {
            "category":"Restaurant",
            "type":"Food & Drink"
        }
    ],
    "sg:phone":"+1 541 298 7388",
    "sg:postcode":"97058",
    "sg:province":"OR",
    "wof:name":"Casa El Mirador",
    "wof:placetype":"venue"
},
  "geometry": {"coordinates":[-121.202061,45.610062],"type":"Point"}
}