{
  "type": "Feature",
  "properties": {
    "iso:country":"US",
    "sg:address":"20 NE 11th Ave",
    "sg:city":"Milton Freewater",
    "sg:classifiers":[
        {
            "category":"Real Estate",
            "subcategory":"Developer",
            "type":"Services"
        }
    ],
    "sg:phone":"+1 541 938 2800",
    "sg:postcode":"97862",
    "sg:province":"OR",
    "sg:tags":[
        "mobile",
        "home"
    ],
    "wof:name":"Meadowbrook Sales Office",
    "wof:placetype":"venue"
},
  "geometry": {"coordinates":[-118.39732600000001,45.94655],"type":"Point"}
}