{
  "type": "Feature",
  "properties": {
    "addr:full":"611 SE Grant Street Portland OR 97214",
    "addr:housenumber":"611",
    "addr:postcode":"97214",
    "addr:street":"Se Grant Street",
    "iso:country":"US",
    "sg:address":"611 SE Grant Street",
    "sg:city":"Portland",
    "sg:classifiers":[
        {
            "category":"Professional",
            "type":"Services"
        }
    ],
    "sg:phone":"+1 503 238 8889",
    "sg:postcode":"97214",
    "sg:province":"OR",
    "sg:tags":[
        "caterer"
    ],
    "sg:website":"www.caibpdx.com",
    "wof:name":"Catering At Its Best",
    "wof:placetype":"venue"
},
  "geometry": {"coordinates":[-122.659712,45.507355],"type":"Point"}
}