{
  "type": "Feature",
  "properties": {
    "iso:country":"US",
    "sg:address":"11411 SE Wood Ave",
    "sg:city":"Portland",
    "sg:classifiers":[
        {
            "category":"Building & Trades",
            "subcategory":"Construction",
            "type":"Services"
        }
    ],
    "sg:phone":"+1 503 654 3578",
    "sg:postcode":"97222",
    "sg:province":"OR",
    "sg:tags":[
        "house"
    ],
    "wof:name":"Jacks Remodeling & Wdwkg",
    "wof:placetype":"venue"
},
  "geometry": {"coordinates":[-122.608811,45.440055],"type":"Point"}
}