{
  "type": "Feature",
  "properties": {
    "addr:full":"19403 SW Boones Ferry Rd Tualatin OR 97062",
    "addr:housenumber":"19403",
    "addr:postcode":"97062",
    "addr:street":"Sw Boones Ferry Rd",
    "iso:country":"US",
    "sg:address":"19403 SW Boones Ferry Rd",
    "sg:city":"Tualatin",
    "sg:classifiers":[
        {
            "category":"Coffee & Tea",
            "type":"Food & Drink"
        },
        {
            "category":"Restaurant",
            "type":"Food & Drink"
        },
        {
            "category":"Donuts",
            "subcategory":"None",
            "type":"Food & Drink"
        }
    ],
    "sg:phone":"+1 503 692 8011",
    "sg:postcode":"97062",
    "sg:province":"OR",
    "sg:tags":[
        "shop",
        "espresso"
    ],
    "wof:name":"Donut King",
    "wof:placetype":"venue"
},
  "geometry": {"coordinates":[-122.764504,45.379175],"type":"Point"}
}