{
  "type": "Feature",
  "properties": {
    "iso:country":"US",
    "sg:address":"2219 NW Allie Ave",
    "sg:city":"Hillsboro",
    "sg:classifiers":[
        {
            "category":"Communications",
            "subcategory":"Radio Station",
            "type":"Services"
        }
    ],
    "sg:phone":"+1 503 690 9762",
    "sg:postcode":"97124",
    "sg:province":"OR",
    "wof:name":"Entercom Radio",
    "wof:placetype":"venue"
},
  "geometry": {"coordinates":[-122.87756899999999,45.537021],"type":"Point"}
}