{
  "type": "Feature",
  "properties": {
    "iso:country":"US",
    "sg:address":"337 Minnesota Blvd",
    "sg:city":"Roseburg",
    "sg:classifiers":[
        {
            "category":"Communications",
            "type":"Services"
        }
    ],
    "sg:phone":"+1 541 672 0914",
    "sg:postcode":"97470",
    "sg:province":"OR",
    "sg:tags":[
        "communication"
    ],
    "wof:name":"Personal Touch Communications",
    "wof:placetype":"venue"
},
  "geometry": {"coordinates":[-123.4882,43.261916],"type":"Point"}
}