{
  "type": "Feature",
  "properties": {
    "addr:full":"18430 Walton Rd Bend OR 97701",
    "addr:housenumber":"18430",
    "addr:postcode":"97701",
    "addr:street":"Walton Rd",
    "iso:country":"US",
    "sg:address":"18430 Walton Rd",
    "sg:city":"Bend",
    "sg:classifiers":[
        {
            "category":"Wholesale",
            "subcategory":"Plants",
            "type":"Manufacturing & Wholesale Goods"
        }
    ],
    "sg:phone":"+1 541 385 0880",
    "sg:postcode":"97701",
    "sg:province":"OR",
    "sg:tags":[
        "equipment",
        "nursery",
        "growers'",
        "landscape",
        "supply"
    ],
    "sg:website":"http://www.heartspringsdesign.com",
    "wof:name":"Heart Spring Designs",
    "wof:placetype":"venue"
},
  "geometry": {"coordinates":[-121.403074,44.152791],"type":"Point"}
}