{
  "type": "Feature",
  "properties": {
    "iso:country":"US",
    "sg:address":"9011 Loon Lake Rd",
    "sg:city":"Reedsport",
    "sg:classifiers":[
        {
            "category":"Travel",
            "subcategory":"Hotels & Motels",
            "type":"Entertainment"
        }
    ],
    "sg:phone":"+1 541 599 2244",
    "sg:postcode":"97467",
    "sg:province":"OR",
    "sg:tags":[
        "operation",
        "eating",
        "trailer"
    ],
    "sg:website":"www.loonlakerv.com",
    "wof:name":"Loon Lake Lodge",
    "wof:placetype":"venue"
},
  "geometry": {"coordinates":[-123.834355,43.584584],"type":"Point"}
}