{
  "type": "Feature",
  "properties": {
    "addr:full":"835 Chetco Ave Brookings OR 97415",
    "addr:housenumber":"835",
    "addr:postcode":"97415",
    "addr:street":"Chetco Ave",
    "iso:country":"US",
    "sg:address":"835 Chetco Ave",
    "sg:city":"Brookings",
    "sg:classifiers":[
        {
            "category":"Restaurant",
            "type":"Food & Drink"
        }
    ],
    "sg:phone":"+1 541 469 8818",
    "sg:postcode":"97415",
    "sg:province":"OR",
    "wof:name":"Letty's Buffet",
    "wof:placetype":"venue"
},
  "geometry": {"coordinates":[-124.286427,42.053462],"type":"Point"}
}