{
  "type": "Feature",
  "properties": {
    "addr:full":"327 SE 80th Avenue Portland OR 97215",
    "addr:housenumber":"327",
    "addr:postcode":"97215",
    "addr:street":"Se 80Th Avenue",
    "iso:country":"US",
    "sg:address":"327 SE 80th Avenue",
    "sg:city":"Portland",
    "sg:classifiers":[
        {
            "category":"Retail",
            "subcategory":"Repair Shop",
            "type":"Services"
        }
    ],
    "sg:phone":"+1 503 255 0044",
    "sg:postcode":"97215",
    "sg:province":"OR",
    "sg:tags":[
        "reupholstery",
        "furniture"
    ],
    "wof:name":"Dan's Auto Upholstery",
    "wof:placetype":"venue"
},
  "geometry": {"coordinates":[-122.581307,45.519792],"type":"Point"}
}