{
  "type": "Feature",
  "properties": {
    "iso:country":"US",
    "sg:address":"78613 Echols Rd",
    "sg:city":"Hermiston",
    "sg:classifiers":[
        {
            "category":"Shopping",
            "subcategory":"Hobbies, Toys, & Games",
            "type":"Retail Goods"
        }
    ],
    "sg:phone":"+1 541 567 7529",
    "sg:postcode":"97838",
    "sg:province":"OR",
    "wof:name":"Xanthron",
    "wof:placetype":"venue"
},
  "geometry": {"coordinates":[-119.33775799999999,45.81368],"type":"Point"}
}