{
  "type": "Feature",
  "properties": {
    "addr:full":"1215 SW 11th St Unit 18 Hermiston OR 97838",
    "addr:housenumber":"1215;18",
    "addr:postcode":"97838",
    "addr:street":"Sw 11Th St Unit",
    "iso:country":"US",
    "sg:address":"1215 SW 11th St Unit 18",
    "sg:city":"Hermiston",
    "sg:classifiers":[
        {
            "category":"Manufacturing",
            "subcategory":"Buildings",
            "type":"Manufacturing & Wholesale Goods"
        },
        {
            "category":"Building & Trades",
            "subcategory":"Construction",
            "type":"Services"
        }
    ],
    "sg:phone":"+1 541 561 4117",
    "sg:postcode":"97838",
    "sg:province":"OR",
    "sg:tags":[
        "home",
        "builder",
        "contractor"
    ],
    "wof:name":"Proud Colors Construction",
    "wof:placetype":"venue"
},
  "geometry": {"coordinates":[-119.31102,45.830262],"type":"Point"}
}