{
  "type": "Feature",
  "properties": {
    "iso:country":"US",
    "sg:address":"700 A Ave",
    "sg:city":"La Grande",
    "sg:classifiers":[
        {
            "category":"Health Services",
            "subcategory":"Doctor",
            "type":"Services"
        }
    ],
    "sg:phone":"+1 541 963 6985",
    "sg:postcode":"97850",
    "sg:province":"OR",
    "wof:name":"Patrick R McCarthy MD",
    "wof:placetype":"venue"
},
  "geometry": {"coordinates":[-118.10069300000001,45.312601],"type":"Point"}
}