{
  "type": "Feature",
  "properties": {
    "addr:full":"25575 S Windy Hill Rd Estacada OR 97023",
    "addr:housenumber":"25575",
    "addr:postcode":"97023",
    "addr:street":"S Windy Hill Rd",
    "iso:country":"US",
    "sg:address":"25575 S Windy Hill Rd",
    "sg:city":"Estacada",
    "sg:classifiers":[
        {
            "category":"Professional",
            "type":"Services"
        }
    ],
    "sg:phone":"+1 503 630 6062",
    "sg:postcode":"97023",
    "sg:province":"OR",
    "wof:name":"Kulwinder S Sangha",
    "wof:placetype":"venue"
},
  "geometry": {"coordinates":[-122.33991899999999,45.25529],"type":"Point"}
}