{
  "type": "Feature",
  "properties": {
    "iso:country":"US",
    "sg:address":"7292 Fieldview St NE",
    "sg:city":"Keizer",
    "sg:classifiers":[
        {
            "category":"Insurance",
            "subcategory":"Insurance Agent",
            "type":"Services"
        }
    ],
    "sg:phone":"+1 503 393 2442",
    "sg:postcode":"97303",
    "sg:province":"OR",
    "wof:name":"Farmer's Insurance",
    "wof:placetype":"venue"
},
  "geometry": {"coordinates":[-123.021666,45.024811],"type":"Point"}
}