{
  "type": "Feature",
  "properties": {
    "iso:country":"US",
    "sg:address":"8144 135th Ave SE",
    "sg:city":"Sublimity",
    "sg:classifiers":[
        {
            "category":"Farming",
            "subcategory":"Farm",
            "type":"Manufacturing & Wholesale Goods"
        }
    ],
    "sg:phone":"+1 503 769 2755",
    "sg:postcode":"97385",
    "sg:province":"OR",
    "sg:tags":[
        "field",
        "crop",
        "general"
    ],
    "wof:name":"Schumacher Farms",
    "wof:placetype":"venue"
},
  "geometry": {"coordinates":[-122.784421,44.838592],"type":"Point"}
}