{
  "type": "Feature",
  "properties": {
    "iso:country":"US",
    "sg:address":"161 NE 82nd Ave",
    "sg:city":"Portland",
    "sg:classifiers":[
        {
            "category":"Education",
            "subcategory":"School",
            "type":"Public Place"
        }
    ],
    "sg:phone":"+1 503 916 6437",
    "sg:postcode":"97220",
    "sg:province":"OR",
    "sg:website":"www.pps.k12.or.us",
    "wof:name":"Vestal Elementary School",
    "wof:placetype":"venue"
},
  "geometry": {"coordinates":[-122.579127,45.523961],"type":"Point"}
}