{
  "type": "Feature",
  "properties": {
    "iso:country":"US",
    "sg:address":"96629 de Moss Rd",
    "sg:city":"Brookings",
    "sg:classifiers":[
        {
            "category":"Building & Trades",
            "subcategory":"Plumbing",
            "type":"Services"
        }
    ],
    "sg:phone":"+1 541 469 8989",
    "sg:postcode":"97415",
    "sg:province":"OR",
    "sg:tags":[
        "plumbing",
        "contractor"
    ],
    "wof:name":"New Hope Plumbing Co",
    "wof:placetype":"venue"
},
  "geometry": {"coordinates":[-124.309388,42.083762],"type":"Point"}
}