{
  "type": "Feature",
  "properties": {
    "addr:full":"212 Benjamin St Eugene OR 97404",
    "addr:housenumber":"212",
    "addr:postcode":"97404",
    "addr:street":"Benjamin St",
    "iso:country":"US",
    "sg:address":"212 Benjamin St",
    "sg:city":"Eugene",
    "sg:classifiers":[
        {
            "category":"Home & Garden",
            "subcategory":"Building Materials",
            "type":"Retail Goods"
        }
    ],
    "sg:phone":"+1 541 686 6761",
    "sg:postcode":"97404",
    "sg:province":"OR",
    "wof:name":"Paintng Advntrs Realstcs Mrls",
    "wof:placetype":"venue"
},
  "geometry": {"coordinates":[-123.125838,44.082657],"type":"Point"}
}