{
  "type": "Feature",
  "properties": {
    "iso:country":"US",
    "sg:address":"17419 SE Mcloughlin Blvd",
    "sg:city":"Portland",
    "sg:classifiers":[
        {
            "category":"Bakery",
            "type":"Food & Drink"
        }
    ],
    "sg:phone":"+1 503 654 8339",
    "sg:postcode":"97267",
    "sg:province":"OR",
    "wof:name":"Panaderia Cinco De Mayo Inc",
    "wof:placetype":"venue"
},
  "geometry": {"coordinates":[-122.617009,45.396594],"type":"Point"}
}