{
  "type": "Feature",
  "properties": {
    "iso:country":"US",
    "sg:address":"67149 US Hwy 26",
    "sg:city":"Welches",
    "sg:classifiers":[
        {
            "category":"Restaurant",
            "type":"Food & Drink"
        }
    ],
    "sg:phone":"+1 503 622 6574",
    "sg:postcode":"97067",
    "sg:province":"OR",
    "sg:tags":[
        "shop",
        "coffee"
    ],
    "wof:name":"Mt Hood Roasters Coffee Sales",
    "wof:placetype":"venue"
},
  "geometry": {"coordinates":[-121.97402,45.351421],"type":"Point"}
}