{
  "type": "Feature",
  "properties": {
    "iso:country":"US",
    "sg:address":"7739 SW Capitol Hwy Suite # 240",
    "sg:city":"Portland",
    "sg:classifiers":[
        {
            "category":"Professional",
            "subcategory":"Art Services",
            "type":"Services"
        }
    ],
    "sg:phone":"+1 503 719 5095",
    "sg:postcode":"97219",
    "sg:province":"OR",
    "sg:tags":[
        "graphic",
        "commercial",
        "designer",
        "artist"
    ],
    "sg:website":"http://www.studiocue.com",
    "wof:name":"Studio Cue",
    "wof:placetype":"venue"
},
  "geometry": {"coordinates":[-122.711613,45.468415],"type":"Point"}
}