{
  "type": "Feature",
  "properties": {
    "iso:country":"US",
    "sg:address":"1023 NE 7th St",
    "sg:city":"Grants Pass",
    "sg:classifiers":[
        {
            "category":"Insurance",
            "subcategory":"Insurance Agent",
            "type":"Services"
        }
    ],
    "sg:phone":"+1 541 476 8851",
    "sg:postcode":"97526",
    "sg:province":"OR",
    "wof:name":"Landaker Sue",
    "wof:placetype":"venue"
},
  "geometry": {"coordinates":[-123.32056300000001,42.44785],"type":"Point"}
}