{
  "type": "Feature",
  "properties": {
    "iso:country":"US",
    "sg:address":"83616 Rock Hill Rd",
    "sg:city":"Creswell",
    "sg:classifiers":[
        {
            "category":"Manufacturing",
            "subcategory":"Lumber",
            "type":"Manufacturing & Wholesale Goods"
        }
    ],
    "sg:phone":"+1 541 895 3201",
    "sg:postcode":"97426",
    "sg:province":"OR",
    "sg:tags":[
        "forestry"
    ],
    "wof:name":"David A Walton",
    "wof:placetype":"venue"
},
  "geometry": {"coordinates":[-123.114437,43.931069],"type":"Point"}
}