{
  "type": "Feature",
  "properties": {
    "iso:country":"US",
    "sg:address":"899 SE Glenwood Dr",
    "sg:city":"Bend",
    "sg:classifiers":[
        {
            "category":"Manufacturing",
            "subcategory":"Printing",
            "type":"Manufacturing & Wholesale Goods"
        }
    ],
    "sg:phone":"+1 541 312 2038",
    "sg:postcode":"97702",
    "sg:province":"OR",
    "sg:tags":[
        "screen",
        "commercial"
    ],
    "wof:name":"Fink Ink Screen Printing",
    "wof:placetype":"venue"
},
  "geometry": {"coordinates":[-121.29495799999999,44.05101],"type":"Point"}
}