{
  "type": "Feature",
  "properties": {
    "iso:country":"US",
    "sg:address":"9585 SW Washington Square Rd",
    "sg:city":"Portland",
    "sg:classifiers":[
        {
            "category":"Shopping",
            "subcategory":"Shoes",
            "type":"Retail Goods"
        }
    ],
    "sg:phone":"+1 503 624 3949",
    "sg:postcode":"97223",
    "sg:province":"OR",
    "sg:tags":[
        "store"
    ],
    "sg:website":"www.crocs.com",
    "wof:name":"Crocs Inc",
    "wof:placetype":"venue"
},
  "geometry": {"coordinates":[-122.783432,45.449629],"type":"Point"}
}