{
  "type": "Feature",
  "properties": {
    "addr:full":"310 SE 2nd St Pendleton OR 97801",
    "addr:housenumber":"310",
    "addr:postcode":"97801",
    "addr:street":"Se 2Nd St",
    "iso:country":"US",
    "sg:address":"310 SE 2nd St",
    "sg:city":"Pendleton",
    "sg:classifiers":[
        {
            "category":"Health Services",
            "subcategory":"Chiropractor",
            "type":"Services"
        }
    ],
    "sg:phone":"+1 541 278 2225",
    "sg:postcode":"97801",
    "sg:province":"OR",
    "sg:tags":[
        "chiropractic"
    ],
    "wof:name":"Chiropractic Associates",
    "wof:placetype":"venue"
},
  "geometry": {"coordinates":[-118.78489399999999,45.672125],"type":"Point"}
}