{
  "type": "Feature",
  "properties": {
    "iso:country":"US",
    "sg:address":"17950 Van Fleet Ave",
    "sg:city":"Sandy",
    "sg:classifiers":[
        {
            "category":"Shopping",
            "subcategory":"Gifts & Souvenirs",
            "type":"Retail Goods"
        }
    ],
    "sg:phone":"+1 503 668 5370",
    "sg:postcode":"97055",
    "sg:province":"OR",
    "wof:name":"L&L Gift Gallery",
    "wof:placetype":"venue"
},
  "geometry": {"coordinates":[-122.253148,45.393326],"type":"Point"}
}