{
  "type": "Feature",
  "properties": {
    "addr:full":"3185 11th St Baker City OR 97814",
    "addr:housenumber":"3185",
    "addr:postcode":"97814",
    "addr:street":"11Th St",
    "iso:country":"US",
    "sg:address":"3185 11th St",
    "sg:city":"Baker City",
    "sg:classifiers":[
        {
            "category":"Retail",
            "subcategory":"Repair Shop",
            "type":"Services"
        }
    ],
    "sg:phone":"+1 541 523 5324",
    "sg:postcode":"97814",
    "sg:province":"OR",
    "sg:tags":[
        "welding"
    ],
    "wof:name":"Baker Welding Inc",
    "wof:placetype":"venue"
},
  "geometry": {"coordinates":[-117.842631,44.78724],"type":"Point"}
}