{
  "type": "Feature",
  "properties": {
    "iso:country":"US",
    "sg:address":"540 Helman St",
    "sg:city":"Ashland",
    "sg:classifiers":[
        {
            "category":"Manufacturing",
            "subcategory":"Tools & Machinery",
            "type":"Manufacturing & Wholesale Goods"
        }
    ],
    "sg:phone":"+1 541 488 0905",
    "sg:postcode":"97520",
    "sg:province":"OR",
    "sg:tags":[
        "instrument",
        "mfg"
    ],
    "wof:name":"Color Vision Serivces",
    "wof:placetype":"venue"
},
  "geometry": {"coordinates":[-122.711709,42.206214],"type":"Point"}
}