{
  "type": "Feature",
  "properties": {
    "addr:full":"610 SW 6th St Grants Pass OR 97526",
    "addr:housenumber":"610",
    "addr:postcode":"97526",
    "addr:street":"Sw 6Th St",
    "iso:country":"US",
    "sg:address":"610 SW 6th St",
    "sg:city":"Grants Pass",
    "sg:classifiers":[
        {
            "category":"Retail",
            "subcategory":"Auto Repair",
            "type":"Services"
        }
    ],
    "sg:phone":"+1 541 471 8973",
    "sg:postcode":"97526",
    "sg:province":"OR",
    "sg:tags":[
        "general"
    ],
    "wof:name":"Expert Tire",
    "wof:placetype":"venue"
},
  "geometry": {"coordinates":[-123.329222,42.435495],"type":"Point"}
}