{
  "type": "Feature",
  "properties": {
    "iso:country":"US",
    "sg:address":"3005 N Pacific Hwy W",
    "sg:city":"Rickreall",
    "sg:classifiers":[
        {
            "category":"Home & Garden",
            "subcategory":"Home Furnishings",
            "type":"Retail Goods"
        }
    ],
    "sg:phone":"+1 503 623 9987",
    "sg:postcode":"97371",
    "sg:province":"OR",
    "sg:tags":[
        "pottery"
    ],
    "wof:name":"Early Morning Pottery",
    "wof:placetype":"venue"
},
  "geometry": {"coordinates":[-123.21925299999999,44.977959],"type":"Point"}
}