{
  "type": "Feature",
  "properties": {
    "addr:full":"1545 NW Woodland Dr Corvallis OR 97330",
    "addr:housenumber":"1545",
    "addr:postcode":"97330",
    "addr:street":"Nw Woodland Dr",
    "iso:country":"US",
    "sg:address":"1545 NW Woodland Dr",
    "sg:city":"Corvallis",
    "sg:classifiers":[
        {
            "category":"Professional",
            "subcategory":"Management & Consulting",
            "type":"Services"
        }
    ],
    "sg:phone":"+1 541 752 5836",
    "sg:postcode":"97330",
    "sg:province":"OR",
    "wof:name":"Walker Consulting",
    "wof:placetype":"venue"
},
  "geometry": {"coordinates":[-123.295027,44.583415],"type":"Point"}
}