{
  "type": "Feature",
  "properties": {
    "iso:country":"US",
    "sg:address":"10117 SE Sunnyside Rd",
    "sg:city":"Clackamas",
    "sg:classifiers":[
        {
            "category":"Building & Trades",
            "subcategory":"Locksmith",
            "type":"Services"
        }
    ],
    "sg:phone":"+1 503 447 5676",
    "sg:postcode":"97015",
    "sg:province":"OR",
    "sg:tags":[
        "key"
    ],
    "wof:name":"A Fast Locksmith Service",
    "wof:placetype":"venue"
},
  "geometry": {"coordinates":[-122.560087,45.43367],"type":"Point"}
}