{
  "type": "Feature",
  "properties": {
    "addr:full":"470 Redwood Hwy Grants Pass OR 97527",
    "addr:housenumber":"470",
    "addr:postcode":"97527",
    "addr:street":"Redwood Hwy",
    "iso:country":"US",
    "sg:address":"470 Redwood Hwy",
    "sg:city":"Grants Pass",
    "sg:classifiers":[
        {
            "category":"Shopping",
            "subcategory":"Discount & Variety Stores",
            "type":"Retail Goods"
        },
        {
            "category":"Shopping",
            "subcategory":"Used Merchandise",
            "type":"Retail Goods"
        }
    ],
    "sg:phone":"+1 541 474 2992",
    "sg:postcode":"97527",
    "sg:province":"OR",
    "sg:tags":[
        "antique"
    ],
    "wof:name":"Dan'l Boone's Trading Post",
    "wof:placetype":"venue"
},
  "geometry": {"coordinates":[-123.335894,42.424428],"type":"Point"}
}