{
  "type": "Feature",
  "properties": {
    "iso:country":"US",
    "sg:address":"1000 Arrowhead Dr",
    "sg:city":"O Brien",
    "sg:classifiers":[
        {
            "category":"Wholesale",
            "subcategory":"Apparel",
            "type":"Manufacturing & Wholesale Goods"
        }
    ],
    "sg:phone":"+1 541 596 2331",
    "sg:postcode":"97534",
    "sg:province":"OR",
    "wof:name":"Eastwinds Trading Co",
    "wof:placetype":"venue"
},
  "geometry": {"coordinates":[-123.71978300000001,42.046181],"type":"Point"}
}