{
  "type": "Feature",
  "properties": {
    "addr:full":"513 NW 13th Ave Portland OR 97209",
    "addr:housenumber":"513",
    "addr:postcode":"97209",
    "addr:street":"Nw 13Th Ave",
    "iso:country":"US",
    "sg:address":"513 NW 13th Ave",
    "sg:city":"Portland",
    "sg:classifiers":[
        {
            "category":"Real Estate",
            "subcategory":"Real Estate Agent",
            "type":"Services"
        }
    ],
    "sg:phone":"+1 503 243 6670",
    "sg:postcode":"97209",
    "sg:province":"OR",
    "wof:name":"Lakha Properties Portlan LLC",
    "wof:placetype":"venue"
},
  "geometry": {"coordinates":[-122.684377,45.527109],"type":"Point"}
}