{
  "type": "Feature",
  "properties": {
    "iso:country":"US",
    "sg:address":"320 Oswego Pointe Dr",
    "sg:city":"Lake Oswego",
    "sg:classifiers":[
        {
            "category":"Building & Trades",
            "subcategory":"Locksmith",
            "type":"Services"
        }
    ],
    "sg:phone":"+1 503 303 6765",
    "sg:postcode":"97034",
    "sg:province":"OR",
    "sg:tags":[
        "key"
    ],
    "wof:name":"1 & 1 Anytime Locksmith",
    "wof:placetype":"venue"
},
  "geometry": {"coordinates":[-122.658852,45.417781],"type":"Point"}
}