{
  "type": "Feature",
  "properties": {
    "iso:country":"US",
    "sg:address":"6055 Ulali Dr NE",
    "sg:city":"Keizer",
    "sg:classifiers":[
        {
            "category":"Restaurant",
            "type":"Food & Drink"
        }
    ],
    "sg:phone":"+1 503 393 2150",
    "sg:postcode":"97303",
    "sg:province":"OR",
    "sg:tags":[
        "pizza"
    ],
    "sg:website":"http://www.roundtablepizza.com",
    "wof:name":"Round Table Pizza 964",
    "wof:placetype":"venue"
},
  "geometry": {"coordinates":[-122.998982,45.008722],"type":"Point"}
}