{
  "type": "Feature",
  "properties": {
    "iso:country":"US",
    "sg:address":"204 E Main St",
    "sg:city":"Eagle Point",
    "sg:classifiers":[
        {
            "category":"Retail",
            "subcategory":"Auto Repair",
            "type":"Services"
        }
    ],
    "sg:phone":"+1 541 826 2210",
    "sg:postcode":"97524",
    "sg:province":"OR",
    "sg:tags":[
        "machine",
        "automobile",
        "shop"
    ],
    "wof:name":"Eagle Automotive Machine",
    "wof:placetype":"venue"
},
  "geometry": {"coordinates":[-122.79964200000001,42.471231],"type":"Point"}
}