{
  "type": "Feature",
  "properties": {
    "iso:country":"US",
    "sg:address":"78242 Woodson Rd",
    "sg:city":"Clatskanie",
    "sg:classifiers":[
        {
            "category":"Freight",
            "type":"Transportation"
        }
    ],
    "sg:phone":"+1 503 728 0643",
    "sg:postcode":"97016",
    "sg:province":"OR",
    "sg:tags":[
        "operator",
        "local",
        "trucking"
    ],
    "wof:name":"Kdr Farm & Trucking",
    "wof:placetype":"venue"
},
  "geometry": {"coordinates":[-123.314894,46.134102],"type":"Point"}
}