{
  "type": "Feature",
  "properties": {
    "iso:country":"US",
    "sg:address":"11825 SW Pacific Hwy",
    "sg:city":"Portland",
    "sg:classifiers":[
        {
            "category":"Retail",
            "subcategory":"Funeral Services",
            "type":"Services"
        }
    ],
    "sg:phone":"+1 503 684 2527",
    "sg:postcode":"97223",
    "sg:province":"OR",
    "sg:tags":[
        "director"
    ],
    "wof:name":"American Burial Cremation Svcs",
    "wof:placetype":"venue"
},
  "geometry": {"coordinates":[-122.76307799999999,45.434774],"type":"Point"}
}