{
  "type": "Feature",
  "properties": {
    "iso:country":"US",
    "sg:address":"498 Parkhill Pl",
    "sg:city":"Grants Pass",
    "sg:classifiers":[
        {
            "category":"Shopping",
            "subcategory":"Beauty & Cosmetics",
            "type":"Retail Goods"
        }
    ],
    "sg:phone":"+1 541 474 3551",
    "sg:postcode":"97527",
    "sg:province":"OR",
    "sg:tags":[
        "merchandise"
    ],
    "wof:name":"Lane Lavender Inc",
    "wof:placetype":"venue"
},
  "geometry": {"coordinates":[-123.370847,42.430909],"type":"Point"}
}