{
  "type": "Feature",
  "properties": {
    "addr:full":"35929 Enterprise Rd Creswell OR 97426",
    "addr:housenumber":"35929",
    "addr:postcode":"97426",
    "addr:street":"Enterprise Rd",
    "iso:country":"US",
    "sg:address":"35929 Enterprise Rd",
    "sg:city":"Creswell",
    "sg:classifiers":[
        {
            "category":"Professional",
            "subcategory":"Management & Consulting",
            "type":"Services"
        }
    ],
    "sg:phone":"+1 541 895 2352",
    "sg:postcode":"97426",
    "sg:province":"OR",
    "sg:tags":[
        "business"
    ],
    "wof:name":"Robert Way",
    "wof:placetype":"venue"
},
  "geometry": {"coordinates":[-122.934014,43.930931],"type":"Point"}
}