{
  "type": "Feature",
  "properties": {
    "iso:country":"US",
    "sg:address":"805 Park St",
    "sg:city":"Lebanon",
    "sg:classifiers":[
        {
            "category":"Autos & Motor Vehicles",
            "subcategory":"Fuel & Gas Station",
            "type":"Retail Goods"
        }
    ],
    "sg:phone":"+1 541 258 6963",
    "sg:postcode":"97355",
    "sg:province":"OR",
    "sg:tags":[
        "oil"
    ],
    "wof:name":"M & M Chevron Mart",
    "wof:placetype":"venue"
},
  "geometry": {"coordinates":[-122.905478,44.538349],"type":"Point"}
}