{
  "type": "Feature",
  "properties": {
    "iso:country":"US",
    "sg:address":"195 E 49th Ave",
    "sg:city":"Eugene",
    "sg:classifiers":[
        {
            "category":"Professional",
            "subcategory":"Computer Services",
            "type":"Services"
        },
        {
            "category":"Manufacturing",
            "subcategory":"Printing",
            "type":"Manufacturing & Wholesale Goods"
        }
    ],
    "sg:phone":"+1 541 344 8395",
    "sg:postcode":"97405",
    "sg:province":"OR",
    "sg:tags":[
        "multimedia",
        "programing",
        "custom"
    ],
    "wof:name":"Magnetic Media LLC",
    "wof:placetype":"venue"
},
  "geometry": {"coordinates":[-123.091498,44.003417],"type":"Point"}
}