{
  "type": "Feature",
  "properties": {
    "addr:full":"25399 Brush Creek Rd Sweet Home OR 97386",
    "addr:housenumber":"25399",
    "addr:postcode":"97386",
    "addr:street":"Brush Creek Rd",
    "iso:country":"US",
    "sg:address":"25399 Brush Creek Rd",
    "sg:city":"Sweet Home",
    "sg:classifiers":[
        {
            "category":"Farming",
            "subcategory":"Farm",
            "type":"Manufacturing & Wholesale Goods"
        }
    ],
    "sg:phone":"+1 541 484 9054",
    "sg:postcode":"97386",
    "sg:province":"OR",
    "sg:tags":[
        "crop",
        "general"
    ],
    "wof:name":"Joan Patterson",
    "wof:placetype":"venue"
},
  "geometry": {"coordinates":[-122.839862,44.337677],"type":"Point"}
}