{
  "type": "Feature",
  "properties": {
    "iso:country":"US",
    "sg:address":"3685 Lachs Ct S",
    "sg:city":"Salem",
    "sg:classifiers":[
        {
            "category":"Professional",
            "subcategory":"Business Services",
            "type":"Services"
        }
    ],
    "sg:phone":"+1 503 588 0126",
    "sg:postcode":"97302",
    "sg:province":"OR",
    "sg:tags":[
        "interior",
        "designer"
    ],
    "wof:name":"Interior Design LLC",
    "wof:placetype":"venue"
},
  "geometry": {"coordinates":[-123.076492,44.90426],"type":"Point"}
}