{
  "type": "Feature",
  "properties": {
    "iso:country":"US",
    "sg:address":"907 W Main St",
    "sg:city":"Medford",
    "sg:classifiers":[
        {
            "category":"Professional",
            "subcategory":"Accounting & Tax Preparation",
            "type":"Services"
        }
    ],
    "sg:phone":"+1 541 734 4101",
    "sg:postcode":"97501",
    "sg:province":"OR",
    "wof:name":"General Accounting Services",
    "wof:placetype":"venue"
},
  "geometry": {"coordinates":[-122.882373,42.323643],"type":"Point"}
}