{
  "type": "Feature",
  "properties": {
    "iso:country":"US",
    "sg:address":"18122 SE McLoughlin Blvd",
    "sg:city":"Portland",
    "sg:classifiers":[
        {
            "category":"Building & Trades",
            "subcategory":"Locksmith",
            "type":"Services"
        }
    ],
    "sg:phone":"+1 971 925 3437",
    "sg:postcode":"97267",
    "sg:province":"OR",
    "sg:tags":[
        "key"
    ],
    "wof:name":"123 Portland Locksmith",
    "wof:placetype":"venue"
},
  "geometry": {"coordinates":[-122.61314,45.391844],"type":"Point"}
}