{
  "type": "Feature",
  "properties": {
    "addr:full":"1833 Nebraska Ave Grants Pass OR 97527",
    "addr:housenumber":"1833",
    "addr:postcode":"97527",
    "addr:street":"Nebraska Ave",
    "iso:country":"US",
    "sg:address":"1833 Nebraska Ave",
    "sg:city":"Grants Pass",
    "sg:classifiers":[
        {
            "category":"Health Services",
            "subcategory":"Medical Lab",
            "type":"Services"
        }
    ],
    "sg:phone":"+1 541 476 6331",
    "sg:postcode":"97527",
    "sg:province":"OR",
    "sg:tags":[
        "laboratory"
    ],
    "wof:name":"Laboratory Corp Of America",
    "wof:placetype":"venue"
},
  "geometry": {"coordinates":[-123.347326,42.416861],"type":"Point"}
}