{
  "type": "Feature",
  "properties": {
    "addr:full":"38500 Dexter Rd Dexter OR 97431",
    "addr:housenumber":"38500",
    "addr:postcode":"97431",
    "addr:street":"Dexter Rd",
    "iso:country":"US",
    "sg:address":"38500 Dexter Rd",
    "sg:city":"Dexter",
    "sg:classifiers":[
        {
            "category":"Government",
            "subcategory":"Office",
            "type":"Public Place"
        }
    ],
    "sg:phone":"+1 541 937 2121",
    "sg:postcode":"97431",
    "sg:province":"OR",
    "sg:tags":[
        "parish",
        "government-county"
    ],
    "sg:website":"http://www.laneeventscenter.org",
    "wof:name":"Lane County Of Public Works",
    "wof:placetype":"venue"
},
  "geometry": {"coordinates":[-122.835544,43.926104],"type":"Point"}
}