{
  "type": "Feature",
  "properties": {
    "addr:full":"310 Main Ave Tillamook OR 97141",
    "addr:housenumber":"310",
    "addr:postcode":"97141",
    "addr:street":"Main Ave",
    "iso:country":"US",
    "sg:address":"310 Main Ave",
    "sg:city":"Tillamook",
    "sg:classifiers":[
        {
            "category":"Cinema",
            "subcategory":"Movie Theater",
            "type":"Entertainment"
        }
    ],
    "sg:phone":"+1 503 842 6111",
    "sg:postcode":"97141",
    "sg:province":"OR",
    "sg:tags":[
        "motion",
        "picture"
    ],
    "wof:name":"Coliseum Theatre",
    "wof:placetype":"venue"
},
  "geometry": {"coordinates":[-123.84402900000001,45.456247],"type":"Point"}
}