{
  "type": "Feature",
  "properties": {
    "iso:country":"US",
    "sg:address":"6129 NE Fremont Street",
    "sg:city":"Portland",
    "sg:classifiers":[
        {
            "category":"Bars & Pubs",
            "subcategory":"Dive Bar",
            "type":"Food & Drink"
        }
    ],
    "sg:phone":"+1 503 288 2944",
    "sg:postcode":"97213",
    "sg:province":"OR",
    "wof:name":"Rovon Inn",
    "wof:placetype":"venue"
},
  "geometry": {"coordinates":[-122.599723,45.548332],"type":"Point"}
}