{
  "type": "Feature",
  "properties": {
    "addr:full":"16060 SW 85th Ave Tigard OR 97224",
    "addr:housenumber":"16060",
    "addr:postcode":"97224",
    "addr:street":"Sw 85Th Ave",
    "iso:country":"US",
    "sg:address":"16060 SW 85th Ave",
    "sg:city":"Tigard",
    "sg:classifiers":[
        {
            "category":"Government",
            "subcategory":"Office",
            "type":"Public Place"
        }
    ],
    "sg:phone":"+1 503 547 8175",
    "sg:postcode":"97224",
    "sg:province":"OR",
    "wof:name":"Treatment Plant Svc",
    "wof:placetype":"venue"
},
  "geometry": {"coordinates":[-122.764444,45.403429],"type":"Point"}
}