{
  "type": "Feature",
  "properties": {
    "iso:country":"US",
    "sg:address":"73569 McKay Ln",
    "sg:city":"Pendleton",
    "sg:classifiers":[
        {
            "category":"Building & Trades",
            "subcategory":"Construction",
            "type":"Services"
        }
    ],
    "sg:phone":"+1 541 276 7282",
    "sg:postcode":"97801",
    "sg:province":"OR",
    "sg:tags":[
        "product",
        "asphalt"
    ],
    "sg:website":"www.pioneerasphaltinc.com",
    "wof:name":"Pioneer Asphalt Inc",
    "wof:placetype":"venue"
},
  "geometry": {"coordinates":[-118.730757,45.671243],"type":"Point"}
}