{
  "type": "Feature",
  "properties": {
    "iso:country":"US",
    "sg:address":"8225 Kilchis River Rd",
    "sg:city":"Tillamook",
    "sg:classifiers":[
        {
            "category":"Retail",
            "subcategory":"Auto Repair",
            "type":"Services"
        }
    ],
    "sg:phone":"+1 503 842 6267",
    "sg:postcode":"97141",
    "sg:province":"OR",
    "sg:tags":[
        "repairing",
        "automobile"
    ],
    "wof:name":"Gary's Automotive",
    "wof:placetype":"venue"
},
  "geometry": {"coordinates":[-123.829229,45.516705],"type":"Point"}
}