{
  "type": "Feature",
  "properties": {
    "iso:country":"US",
    "sg:address":"734 State Hwy 99 N",
    "sg:city":"Eugene",
    "sg:classifiers":[
        {
            "category":"Restaurant",
            "type":"Food & Drink"
        }
    ],
    "sg:phone":"+1 541 688 8141",
    "sg:postcode":"97402",
    "sg:province":"OR",
    "wof:name":"Dairy Queen",
    "wof:placetype":"venue"
},
  "geometry": {"coordinates":[-123.142353,44.069375],"type":"Point"}
}