{
  "type": "Feature",
  "properties": {
    "addr:full":"14859 Doubletree Sisters OR 97759",
    "addr:housenumber":"14859",
    "addr:postcode":"97759",
    "addr:street":"Doubletree",
    "iso:country":"US",
    "sg:address":"14859 Doubletree",
    "sg:city":"Sisters",
    "sg:classifiers":[
        {
            "category":"Food & Beverages",
            "subcategory":"Specialty",
            "type":"Retail Goods"
        }
    ],
    "sg:phone":"+1 541 549 8015",
    "sg:postcode":"97759",
    "sg:province":"OR",
    "wof:name":"Better Health",
    "wof:placetype":"venue"
},
  "geometry": {"coordinates":[-121.591795,44.310244],"type":"Point"}
}