{
  "type": "Feature",
  "properties": {
    "addr:full":"1700 SE 6th Ave Portland OR 97214",
    "addr:housenumber":"1700",
    "addr:postcode":"97214",
    "addr:street":"Se 6Th Ave",
    "iso:country":"US",
    "sg:address":"1700 SE 6th Ave",
    "sg:city":"Portland",
    "sg:classifiers":[
        {
            "category":"Food & Beverages",
            "subcategory":"Specialty",
            "type":"Retail Goods"
        }
    ],
    "sg:phone":"+1 503 445 9900",
    "sg:postcode":"97214",
    "sg:province":"OR",
    "sg:tags":[
        "tea",
        "coffee"
    ],
    "wof:name":"Redwing Coffee & Bakery",
    "wof:placetype":"venue"
},
  "geometry": {"coordinates":[-122.65977599999999,45.510093],"type":"Point"}
}