{
  "type": "Feature",
  "properties": {
    "iso:country":"US",
    "sg:address":"3534 Lake Grove Ave",
    "sg:city":"Lake Oswego",
    "sg:classifiers":[
        {
            "category":"Recreation",
            "type":"Entertainment"
        }
    ],
    "sg:phone":"+1 503 636 7670",
    "sg:postcode":"97035",
    "sg:province":"OR",
    "wof:name":"Smiling Sunshine Art Education",
    "wof:placetype":"venue"
},
  "geometry": {"coordinates":[-122.71275900000001,45.410406],"type":"Point"}
}