{
  "type": "Feature",
  "properties": {
    "iso:country":"US",
    "sg:address":"7401 SW Washo Court, Suite 200",
    "sg:city":"Tualatin",
    "sg:classifiers":[
        {
            "category":"Professional",
            "subcategory":"Employment Agencies",
            "type":"Services"
        }
    ],
    "sg:phone":"+1 503 612 1400",
    "sg:postcode":"97062",
    "sg:province":"OR",
    "sg:tags":[
        "consultant",
        "opportunity",
        "screening",
        "resume"
    ],
    "sg:website":"https://tualatinor.expresspros.com/?utm_source=yellowpages&utm_content=1934&utm_campaign=localmaps",
    "wof:name":"Express Employment Professionals - Staffing",
    "wof:placetype":"venue"
},
  "geometry": {"coordinates":[-122.752824,45.37814],"type":"Point"}
}