{
  "type": "Feature",
  "properties": {
    "iso:country":"US",
    "sg:address":"18757 SW Martinazzi Ave Ste 100",
    "sg:city":"Tualatin",
    "sg:classifiers":[
        {
            "category":"Banks & Credit Unions",
            "subcategory":"Bank",
            "type":"Services"
        },
        {
            "category":"Banks & Credit Unions",
            "subcategory":"Financial Services",
            "type":"Services"
        }
    ],
    "sg:phone":"+1 503 885 7403",
    "sg:postcode":"97062",
    "sg:province":"OR",
    "sg:tags":[
        "commercial",
        "loan",
        "saving"
    ],
    "sg:website":"www.umpquabank.com",
    "wof:name":"Umpqua Bank",
    "wof:placetype":"venue"
},
  "geometry": {"coordinates":[-122.759038,45.384038],"type":"Point"}
}