{
  "type": "Feature",
  "properties": {
    "iso:country":"US",
    "sg:address":"15381 SE Bradford Rd",
    "sg:city":"Clackamas",
    "sg:classifiers":[
        {
            "category":"Building & Trades",
            "subcategory":"Construction",
            "type":"Services"
        }
    ],
    "sg:phone":"+1 503 558 9841",
    "sg:postcode":"97015",
    "sg:province":"OR",
    "sg:tags":[
        "sealing",
        "tile-cleaning",
        "refinishing",
        "contractor"
    ],
    "wof:name":"Georgian Tile, Marble & Granite Inc",
    "wof:placetype":"venue"
},
  "geometry": {"coordinates":[-122.50423600000001,45.415611],"type":"Point"}
}