{
  "type": "Feature",
  "properties": {
    "iso:country":"US",
    "sg:address":"18438 SE Pine St",
    "sg:city":"Portland",
    "sg:classifiers":[
        {
            "category":"Professional",
            "subcategory":"Accounting & Tax Preparation",
            "type":"Services"
        }
    ],
    "sg:phone":"+1 503 493 9211",
    "sg:postcode":"97233",
    "sg:province":"OR",
    "sg:tags":[
        "verification",
        "check",
        "recovery"
    ],
    "wof:name":"Recovery Association Project",
    "wof:placetype":"venue"
},
  "geometry": {"coordinates":[-122.473315,45.52054],"type":"Point"}
}