{
  "type": "Feature",
  "properties": {
    "iso:country":"US",
    "sg:address":"7100 SW Hampton St",
    "sg:city":"Tigard",
    "sg:classifiers":[
        {
            "category":"Wholesale",
            "subcategory":"Durable Goods & Equipment",
            "type":"Manufacturing & Wholesale Goods"
        }
    ],
    "sg:phone":"+1 503 620 0444",
    "sg:postcode":"97223",
    "sg:province":"OR",
    "sg:tags":[
        "representative",
        "manufacturer"
    ],
    "wof:name":"Muckle Sales Co",
    "wof:placetype":"venue"
},
  "geometry": {"coordinates":[-122.750445,45.42755],"type":"Point"}
}