{
  "type": "Feature",
  "properties": {
    "iso:country":"US",
    "sg:address":"1625 W Central Ave",
    "sg:city":"Sutherlin",
    "sg:classifiers":[
        {
            "category":"Restaurant",
            "type":"Food & Drink"
        }
    ],
    "sg:phone":"+1 541 459 8274",
    "sg:postcode":"97479",
    "sg:province":"OR",
    "wof:name":"Taco Bell",
    "wof:placetype":"venue"
},
  "geometry": {"coordinates":[-123.34070199999999,43.386439],"type":"Point"}
}