{
  "type": "Feature",
  "properties": {
    "iso:country":"US",
    "sg:address":"47 NW Oregon Ave",
    "sg:city":"Bend",
    "sg:classifiers":[
        {
            "category":"Professional",
            "subcategory":"Business Services",
            "type":"Services"
        }
    ],
    "sg:phone":"+1 541 385 7628",
    "sg:postcode":"97701",
    "sg:province":"OR",
    "wof:name":"Downtown Bend Station",
    "wof:placetype":"venue"
},
  "geometry": {"coordinates":[-121.310782,44.05816],"type":"Point"}
}