{
  "type": "Feature",
  "properties": {
    "iso:country":"US",
    "sg:address":"1942 N Portland Blvd",
    "sg:city":"Portland",
    "sg:classifiers":[
        {
            "category":"Restaurant",
            "type":"Food & Drink"
        }
    ],
    "sg:phone":"+1 503 735 9505",
    "sg:postcode":"97217",
    "sg:province":"OR",
    "sg:tags":[
        "eating"
    ],
    "wof:name":"El Burrito Loco",
    "wof:placetype":"venue"
},
  "geometry": {"coordinates":[-122.687033,45.56984],"type":"Point"}
}