{
  "type": "Feature",
  "properties": {
    "iso:country":"US",
    "sg:address":"854 A St",
    "sg:city":"Ashland",
    "sg:classifiers":[
        {
            "category":"Health Services",
            "subcategory":"Chiropractor",
            "type":"Services"
        }
    ],
    "sg:phone":"+1 541 488 0688",
    "sg:postcode":"97520",
    "sg:province":"OR",
    "wof:name":"Ilene Rubinstein",
    "wof:placetype":"venue"
},
  "geometry": {"coordinates":[-122.702729,42.197155],"type":"Point"}
}