{
  "type": "Feature",
  "properties": {
    "iso:country":"US",
    "sg:address":"1515 Bailey Hill Rd Apt 6",
    "sg:city":"Eugene",
    "sg:classifiers":[
        {
            "category":"Real Estate",
            "subcategory":"Real Estate Services",
            "type":"Services"
        },
        {
            "category":"Real Estate",
            "subcategory":"Real Estate Operator",
            "type":"Services"
        }
    ],
    "sg:phone":"+1 541 686 0379",
    "sg:postcode":"97402",
    "sg:province":"OR",
    "sg:tags":[
        "vacancy",
        "apartment",
        "rental",
        "finder",
        "listing"
    ],
    "sg:website":"http://www.jenningsgroup.com",
    "wof:name":"Bailey Hill Meadows Apartments",
    "wof:placetype":"venue"
},
  "geometry": {"coordinates":[-123.148033,44.043382],"type":"Point"}
}