{
  "type": "Feature",
  "properties": {
    "iso:country":"US",
    "sg:address":"16330 NW Lyndel Ln",
    "sg:city":"Beaverton",
    "sg:classifiers":[
        {
            "category":"Building & Trades",
            "subcategory":"Cleaning & Sanitation",
            "type":"Services"
        }
    ],
    "sg:phone":"+1 503 629 9155",
    "sg:postcode":"97006",
    "sg:province":"OR",
    "sg:tags":[
        "window"
    ],
    "wof:name":"Argus Windows Northwest",
    "wof:placetype":"venue"
},
  "geometry": {"coordinates":[-122.844695,45.538678],"type":"Point"}
}