{
  "type": "Feature",
  "properties": {
    "addr:full":"17375 SW Tualatin Valley Hwy Aloha OR 97006",
    "addr:housenumber":"17375",
    "addr:postcode":"97006",
    "addr:street":"Sw Tualatin Valley Hwy",
    "iso:country":"US",
    "sg:address":"17375 SW Tualatin Valley Hwy",
    "sg:city":"Aloha",
    "sg:classifiers":[
        {
            "category":"Restaurant",
            "type":"Food & Drink"
        }
    ],
    "sg:phone":"+1 503 356 1452",
    "sg:postcode":"97006",
    "sg:province":"OR",
    "sg:tags":[
        "eating"
    ],
    "wof:name":"Reo's Ribs",
    "wof:placetype":"venue"
},
  "geometry": {"coordinates":[-122.85305,45.492457],"type":"Point"}
}