{
  "type": "Feature",
  "properties": {
    "iso:country":"US",
    "sg:address":"3080 Ryan Dr SE",
    "sg:city":"Salem",
    "sg:classifiers":[
        {
            "category":"Autos & Motor Vehicles",
            "subcategory":"Recreational Vehicle Sales",
            "type":"Retail Goods"
        }
    ],
    "sg:phone":"+1 503 370 2555",
    "sg:postcode":"97301",
    "sg:province":"OR",
    "wof:name":"Roberson Rv Ctr",
    "wof:placetype":"venue"
},
  "geometry": {"coordinates":[-123.003197,44.92106],"type":"Point"}
}