{
  "type": "Feature",
  "properties": {
    "iso:country":"US",
    "sg:address":"1143 SE 213th Ave",
    "sg:city":"Gresham",
    "sg:classifiers":[
        {
            "category":"Professional",
            "subcategory":"Lawyer & Legal Services",
            "type":"Services"
        }
    ],
    "sg:phone":"+1 503 515 8117",
    "sg:postcode":"97030",
    "sg:province":"OR",
    "wof:name":"Bobby Arsanjani",
    "wof:placetype":"venue"
},
  "geometry": {"coordinates":[-122.443727,45.514949],"type":"Point"}
}