{
  "type": "Feature",
  "properties": {
    "addr:full":"650 SE 9th St Bend OR 97702",
    "addr:housenumber":"650",
    "addr:postcode":"97702",
    "addr:street":"Se 9Th St",
    "iso:country":"US",
    "sg:address":"650 SE 9th St",
    "sg:city":"Bend",
    "sg:classifiers":[
        {
            "category":"Manufacturing",
            "subcategory":"Wood Products",
            "type":"Manufacturing & Wholesale Goods"
        },
        {
            "category":"Home & Garden",
            "subcategory":"Furniture",
            "type":"Retail Goods"
        }
    ],
    "sg:phone":"+1 541 318 5200",
    "sg:postcode":"97702",
    "sg:province":"OR",
    "sg:tags":[
        "builder",
        "custom",
        "mfg"
    ],
    "wof:name":"Johan Woodworking LLC",
    "wof:placetype":"venue"
},
  "geometry": {"coordinates":[-121.292788,44.043853],"type":"Point"}
}