{
  "type": "Feature",
  "properties": {
    "iso:country":"US",
    "sg:address":"15252 S Union Mills Rd",
    "sg:city":"Mulino",
    "sg:classifiers":[
        {
            "category":"Building & Trades",
            "subcategory":"Construction",
            "type":"Services"
        }
    ],
    "sg:phone":"+1 503 829 2970",
    "sg:postcode":"97042",
    "sg:province":"OR",
    "sg:tags":[
        "roofing",
        "contractor"
    ],
    "wof:name":"R & M Roofing Inc",
    "wof:placetype":"venue"
},
  "geometry": {"coordinates":[-122.553163,45.196838],"type":"Point"}
}