{
  "type": "Feature",
  "properties": {
    "iso:country":"US",
    "sg:address":"255 Park Ave",
    "sg:city":"Coos Bay",
    "sg:classifiers":[
        {
            "category":"Shopping",
            "subcategory":"Clothing, Apparel, & Fashions",
            "type":"Retail Goods"
        }
    ],
    "sg:phone":"+1 541 269 9435",
    "sg:postcode":"97420",
    "sg:province":"OR",
    "sg:tags":[
        "dancing",
        "supply"
    ],
    "wof:name":"Jean's Dance & Exercise Wear",
    "wof:placetype":"venue"
},
  "geometry": {"coordinates":[-124.214364,43.370585],"type":"Point"}
}