{
  "type": "Feature",
  "properties": {
    "addr:full":"1090 Bailey Hill Rd Eugene OR 97402",
    "addr:housenumber":"1090",
    "addr:postcode":"97402",
    "addr:street":"Bailey Hill Rd",
    "iso:country":"US",
    "sg:address":"1090 Bailey Hill Rd",
    "sg:city":"Eugene",
    "sg:classifiers":[
        {
            "category":"Wholesale",
            "subcategory":"Stationery",
            "type":"Manufacturing & Wholesale Goods"
        }
    ],
    "sg:phone":"+1 541 345 3223",
    "sg:postcode":"97402",
    "sg:province":"OR",
    "sg:tags":[
        "personal",
        "product",
        "industrial",
        "paper"
    ],
    "wof:name":"Paper Plus",
    "wof:placetype":"venue"
},
  "geometry": {"coordinates":[-123.148027,44.048612],"type":"Point"}
}