{
  "type": "Feature",
  "properties": {
    "addr:full":"7100 NW Kaiser Rd Portland OR 97229",
    "addr:housenumber":"7100",
    "addr:postcode":"97229",
    "addr:street":"Nw Kaiser Rd",
    "iso:country":"US",
    "sg:address":"7100 NW Kaiser Rd",
    "sg:city":"Portland",
    "sg:classifiers":[
        {
            "category":"Building & Trades",
            "subcategory":"Construction",
            "type":"Services"
        }
    ],
    "sg:phone":"+1 503 645 3073",
    "sg:postcode":"97229",
    "sg:province":"OR",
    "sg:tags":[
        "house"
    ],
    "wof:name":"Touchstone Building Co",
    "wof:placetype":"venue"
},
  "geometry": {"coordinates":[-122.836877,45.569555],"type":"Point"}
}