{
  "type": "Feature",
  "properties": {
    "iso:country":"US",
    "sg:address":"885 SW Rimrock Way",
    "sg:city":"Redmond",
    "sg:phone":"+1 541 923 7388",
    "sg:postcode":"97756",
    "sg:province":"OR",
    "wof:name":"Cibellis New York Pizza",
    "wof:placetype":"venue"
},
  "geometry": {"coordinates":[-121.192403,44.267771],"type":"Point"}
}