{
  "type": "Feature",
  "properties": {
    "iso:country":"US",
    "sg:address":"1624 NW Glisan St",
    "sg:city":"Portland",
    "sg:classifiers":[
        {
            "category":"Restaurant",
            "type":"Food & Drink"
        }
    ],
    "sg:menulink":"http://www.allmenus.com/or/portland/25103-mcmenamins-mission-theater/menu/",
    "sg:phone":"+1 503 288 3286",
    "sg:postcode":"97209",
    "sg:province":"OR",
    "sg:tags":[
        "american"
    ],
    "wof:name":"McMenamins Mission Theater",
    "wof:placetype":"venue"
},
  "geometry": {"coordinates":[-122.687606,45.526434],"type":"Point"}
}