{
  "type": "Feature",
  "properties": {
    "iso:country":"US",
    "sg:address":"475 Bridge St",
    "sg:city":"Vernonia",
    "sg:classifiers":[
        {
            "category":"Education",
            "subcategory":"School",
            "type":"Public Place"
        }
    ],
    "sg:phone":"+1 503 429 5891",
    "sg:postcode":"97064",
    "sg:province":"OR",
    "wof:name":"Vernonia School District 47j",
    "wof:placetype":"venue"
},
  "geometry": {"coordinates":[-123.190263,45.858721],"type":"Point"}
}