{
  "type": "Feature",
  "properties": {
    "addr:full":"9561 SW Washington Square Rd Tigard OR 97223",
    "addr:housenumber":"9561",
    "addr:postcode":"97223",
    "addr:street":"Sw Washington Square Rd",
    "iso:country":"US",
    "sg:address":"9561 SW Washington Square Rd",
    "sg:city":"Tigard",
    "sg:classifiers":[
        {
            "category":"Shopping",
            "subcategory":"Shoes",
            "type":"Retail Goods"
        }
    ],
    "sg:phone":"+1 503 639 3399",
    "sg:postcode":"97223",
    "sg:province":"OR",
    "wof:name":"Stride Rite Bootery",
    "wof:placetype":"venue"
},
  "geometry": {"coordinates":[-122.78202899999999,45.447234],"type":"Point"}
}