{
  "type": "Feature",
  "properties": {
    "addr:full":"6750 SW Scholls Ferry Rd Beaverton OR 97008",
    "addr:housenumber":"6750",
    "addr:postcode":"97008",
    "addr:street":"Sw Scholls Ferry Rd",
    "iso:country":"US",
    "sg:address":"6750 SW Scholls Ferry Rd",
    "sg:city":"Beaverton",
    "sg:classifiers":[
        {
            "category":"Real Estate",
            "subcategory":"Real Estate Operator",
            "type":"Services"
        },
        {
            "category":"Real Estate",
            "subcategory":"Real Estate Agent",
            "type":"Services"
        }
    ],
    "sg:phone":"+1 503 246 6867",
    "sg:postcode":"97008",
    "sg:province":"OR",
    "sg:tags":[
        "apartment"
    ],
    "wof:name":"Brookside Estates",
    "wof:placetype":"venue"
},
  "geometry": {"coordinates":[-122.775002,45.471001],"type":"Point"}
}