{
  "type": "Feature",
  "properties": {
    "iso:country":"US",
    "sg:address":"1012 SW King Avenue",
    "sg:city":"Portland",
    "sg:classifiers":[
        {
            "category":"Professional",
            "subcategory":"Lawyer & Legal Services",
            "type":"Services"
        }
    ],
    "sg:phone":"+1 503 222 5433",
    "sg:postcode":"97205",
    "sg:province":"OR",
    "wof:name":"Murphey Bryan P PC",
    "wof:placetype":"venue"
},
  "geometry": {"coordinates":[-122.695408,45.520793],"type":"Point"}
}