{
  "type": "Feature",
  "properties": {
    "iso:country":"US",
    "sg:address":"15700 SE 82nd Dr",
    "sg:city":"Clackamas",
    "sg:classifiers":[
        {
            "category":"Food & Beverages",
            "subcategory":"Groceries & Convenience Stores",
            "type":"Retail Goods"
        }
    ],
    "sg:phone":"+1 503 655 6045",
    "sg:postcode":"97015",
    "sg:province":"OR",
    "wof:name":"United Grocers Inc",
    "wof:placetype":"venue"
},
  "geometry": {"coordinates":[-122.569,45.409199],"type":"Point"}
}