{
  "type": "Feature",
  "properties": {
    "iso:country":"US",
    "sg:address":"61525 Twin Lakes Loop",
    "sg:city":"Bend",
    "sg:classifiers":[
        {
            "category":"Wholesale",
            "subcategory":"Construction Materials",
            "type":"Manufacturing & Wholesale Goods"
        }
    ],
    "sg:phone":"+1 541 312 9299",
    "sg:postcode":"97702",
    "sg:province":"OR",
    "wof:name":"Antuco Forest Products LLC",
    "wof:placetype":"venue"
},
  "geometry": {"coordinates":[-121.279447,44.035685],"type":"Point"}
}