{
  "type": "Feature",
  "properties": {
    "iso:country":"US",
    "sg:address":"34974 Ede Rd",
    "sg:city":"Lebanon",
    "sg:classifiers":[
        {
            "category":"Professional",
            "type":"Services"
        }
    ],
    "sg:phone":"+1 541 451 1703",
    "sg:postcode":"97355",
    "sg:province":"OR",
    "wof:name":"Andrew J Mason",
    "wof:placetype":"venue"
},
  "geometry": {"coordinates":[-122.753702,44.603804],"type":"Point"}
}