{
  "type": "Feature",
  "properties": {
    "iso:country":"US",
    "sg:address":"13225 NW McNamee Rd",
    "sg:city":"Portland",
    "sg:classifiers":[
        {
            "category":"Freight",
            "type":"Transportation"
        }
    ],
    "sg:phone":"+1 503 286 4138",
    "sg:postcode":"97231",
    "sg:province":"OR",
    "sg:tags":[
        "operator",
        "local",
        "trucking"
    ],
    "wof:name":"Larry Luethe",
    "wof:placetype":"venue"
},
  "geometry": {"coordinates":[-122.834324,45.613213],"type":"Point"}
}