{
  "type": "Feature",
  "properties": {
    "addr:full":"10123 SE Market St Portland OR 97216",
    "addr:postcode":"10123;97216",
    "addr:street":"Se Market St",
    "iso:country":"US",
    "sg:address":"10123 SE Market St",
    "sg:city":"Portland",
    "sg:classifiers":[
        {
            "category":"Professional",
            "subcategory":"Accounting & Tax Preparation",
            "type":"Services"
        }
    ],
    "sg:phone":"+1 503 257 9590",
    "sg:postcode":"97216",
    "sg:province":"OR",
    "sg:tags":[
        "training",
        "employment",
        "billing"
    ],
    "wof:name":"Oic",
    "wof:placetype":"venue"
},
  "geometry": {"coordinates":[-122.559708,45.511292],"type":"Point"}
}