{
  "type": "Feature",
  "properties": {
    "iso:country":"US",
    "sg:address":"117 NE 12th Ave",
    "sg:city":"Canby",
    "sg:classifiers":[
        {
            "category":"Professional",
            "subcategory":"Business Services",
            "type":"Services"
        }
    ],
    "sg:phone":"+1 503 266 3225",
    "sg:postcode":"97013",
    "sg:province":"OR",
    "wof:name":"DK Design & Consulting Service",
    "wof:placetype":"venue"
},
  "geometry": {"coordinates":[-122.695228,45.271834],"type":"Point"}
}