{
  "type": "Feature",
  "properties": {
    "iso:country":"US",
    "sg:address":"728 NW Skyline Blvd",
    "sg:city":"Portland",
    "sg:classifiers":[
        {
            "category":"Professional",
            "subcategory":"Lawyer & Legal Services",
            "type":"Services"
        }
    ],
    "sg:phone":"+1 503 497 1010",
    "sg:postcode":"97229",
    "sg:province":"OR",
    "wof:name":"Dispute Resolution Service",
    "wof:placetype":"venue"
},
  "geometry": {"coordinates":[-122.750912,45.524784],"type":"Point"}
}