{
  "type": "Feature",
  "properties": {
    "addr:full":"34025 E Columbia Ave Scappoose OR 97056",
    "addr:housenumber":"34025",
    "addr:postcode":"97056",
    "addr:street":"E Columbia Ave",
    "iso:country":"US",
    "sg:address":"34025 E Columbia Ave",
    "sg:city":"Scappoose",
    "sg:classifiers":[
        {
            "category":"Transit Center",
            "subcategory":"Freight",
            "type":"Transportation"
        },
        {
            "category":"Building & Trades",
            "subcategory":"Construction",
            "type":"Services"
        }
    ],
    "sg:phone":"+1 503 780 8900",
    "sg:postcode":"97056",
    "sg:province":"OR",
    "sg:tags":[
        "fork",
        "trucks-industrial",
        "lift",
        "forklift",
        "truck"
    ],
    "wof:name":"Daves Mobile Repair",
    "wof:placetype":"venue"
},
  "geometry": {"coordinates":[-122.86742700000001,45.75606],"type":"Point"}
}