{
  "type": "Feature",
  "properties": {
    "addr:full":"113 SE 11th St Pendleton OR 97801",
    "addr:housenumber":"113",
    "addr:postcode":"97801",
    "addr:street":"Se 11Th St",
    "iso:country":"US",
    "sg:address":"113 SE 11th St",
    "sg:city":"Pendleton",
    "sg:classifiers":[
        {
            "category":"Professional",
            "type":"Services"
        }
    ],
    "sg:phone":"+1 541 278 8111",
    "sg:postcode":"97801",
    "sg:province":"OR",
    "wof:name":"Producciones Espiritu",
    "wof:placetype":"venue"
},
  "geometry": {"coordinates":[-118.77565800000001,45.675056],"type":"Point"}
}