{
  "type": "Feature",
  "properties": {
    "iso:country":"US",
    "sg:address":"10345 SW Homestead Ln",
    "sg:city":"Beaverton",
    "sg:classifiers":[
        {
            "category":"Professional",
            "subcategory":"Computer Services",
            "type":"Services"
        }
    ],
    "sg:phone":"+1 503 720 6579",
    "sg:postcode":"97008",
    "sg:province":"OR",
    "sg:tags":[
        "technology",
        "solution"
    ],
    "wof:name":"Red 5 Hosting",
    "wof:placetype":"venue"
},
  "geometry": {"coordinates":[-122.78279000000001,45.459308],"type":"Point"}
}