{
  "type": "Feature",
  "properties": {
    "addr:full":"2370 NE Highway 99W McMinnville OR 97128",
    "addr:housenumber":"2370",
    "addr:postcode":"97128",
    "addr:street":"Ne Highway 99W",
    "iso:country":"US",
    "sg:address":"2370 NE Highway 99W",
    "sg:city":"McMinnville",
    "sg:classifiers":[
        {
            "category":"Retail",
            "subcategory":"Pet Boarding",
            "type":"Services"
        }
    ],
    "sg:phone":"+1 503 474 4252",
    "sg:postcode":"97128",
    "sg:province":"OR",
    "sg:tags":[
        "boarding/pet",
        "sitting"
    ],
    "sg:website":"www.petco.com",
    "wof:name":"Petco",
    "wof:placetype":"venue"
},
  "geometry": {"coordinates":[-123.172997,45.2286],"type":"Point"}
}