{
  "type": "Feature",
  "properties": {
    "iso:country":"US",
    "sg:address":"1221 SE Salmon St",
    "sg:city":"Portland",
    "sg:classifiers":[
        {
            "category":"Wholesale",
            "subcategory":"Auto Parts",
            "type":"Manufacturing & Wholesale Goods"
        }
    ],
    "sg:phone":"+1 503 701 4050",
    "sg:postcode":"97214",
    "sg:province":"OR",
    "sg:tags":[
        "used"
    ],
    "wof:name":"McDowall Enterprises Inc",
    "wof:placetype":"venue"
},
  "geometry": {"coordinates":[-122.652794,45.514424],"type":"Point"}
}