{
  "type": "Feature",
  "properties": {
    "iso:country":"US",
    "sg:address":"6915 NE 42nd Avenue",
    "sg:city":"Portland",
    "sg:classifiers":[
        {
            "category":"Education",
            "subcategory":"School",
            "type":"Public Place"
        }
    ],
    "sg:phone":"+1 503 459 4056",
    "sg:postcode":"97218",
    "sg:province":"OR",
    "sg:website":"www.area1jatc.com",
    "wof:name":"Inside Electric Jatc",
    "wof:placetype":"venue"
},
  "geometry": {"coordinates":[-122.62038699999999,45.573409],"type":"Point"}
}