{
  "type": "Feature",
  "properties": {
    "addr:full":"12220 SW Walnut St Portland OR 97223",
    "addr:housenumber":"12220",
    "addr:postcode":"97223",
    "addr:street":"Sw Walnut St",
    "iso:country":"US",
    "sg:address":"12220 SW Walnut St",
    "sg:city":"Portland",
    "sg:classifiers":[
        {
            "category":"Building & Trades",
            "subcategory":"Cleaning & Sanitation",
            "type":"Services"
        }
    ],
    "sg:phone":"+1 503 590 2451",
    "sg:postcode":"97223",
    "sg:province":"OR",
    "sg:tags":[
        "maintenance"
    ],
    "wof:name":"Jlm Services Inc",
    "wof:placetype":"venue"
},
  "geometry": {"coordinates":[-122.800944,45.429391],"type":"Point"}
}