{
  "type": "Feature",
  "properties": {
    "iso:country":"US",
    "sg:address":"16285 SW 85th Ave",
    "sg:city":"Portland",
    "sg:classifiers":[
        {
            "category":"Retail",
            "subcategory":"Auto Repair",
            "type":"Services"
        }
    ],
    "sg:phone":"+1 503 684 2886",
    "sg:postcode":"97224",
    "sg:province":"OR",
    "sg:tags":[
        "repairing",
        "automobile",
        "general"
    ],
    "wof:name":"Import Auto Clinic Inc",
    "wof:placetype":"venue"
},
  "geometry": {"coordinates":[-122.764577,45.401135],"type":"Point"}
}