{
  "type": "Feature",
  "properties": {
    "iso:country":"US",
    "sg:address":"3895 SW 185th Ave Ste 140",
    "sg:city":"Beaverton",
    "sg:classifiers":[
        {
            "category":"Health Services",
            "subcategory":"Doctor",
            "type":"Services"
        },
        {
            "category":"Health Services",
            "subcategory":"Podiatrist",
            "type":"Services"
        }
    ],
    "sg:phone":"+1 503 591 7449",
    "sg:postcode":"97007",
    "sg:province":"OR",
    "sg:tags":[
        "physician",
        "surgeons"
    ],
    "wof:name":"Aloha Foot Care Specialist",
    "wof:placetype":"venue"
},
  "geometry": {"coordinates":[-122.866997,45.492401],"type":"Point"}
}