{
  "type": "Feature",
  "properties": {
    "iso:country":"US",
    "sg:address":"1480 W 6th Ave",
    "sg:city":"Eugene",
    "sg:classifiers":[
        {
            "category":"Manufacturing",
            "subcategory":"Signs",
            "type":"Manufacturing & Wholesale Goods"
        },
        {
            "category":"Professional",
            "subcategory":"Printing & Photocopies",
            "type":"Services"
        },
        {
            "category":"Manufacturing",
            "subcategory":"Glass & Minerals",
            "type":"Manufacturing & Wholesale Goods"
        }
    ],
    "sg:phone":"+1 541 343 0841",
    "sg:postcode":"97402",
    "sg:province":"OR",
    "sg:tags":[
        "engraving",
        "trophies",
        "products-metal",
        "medal",
        "plaque",
        "etched"
    ],
    "wof:name":"Bar-N-Dee Discount Trophies",
    "wof:placetype":"venue"
},
  "geometry": {"coordinates":[-123.115253,44.053267],"type":"Point"}
}