{
  "type": "Feature",
  "properties": {
    "addr:full":"4321 Waverly Dr NE Albany OR 97321",
    "addr:housenumber":"4321",
    "addr:postcode":"97321",
    "addr:street":"Waverly Dr Ne",
    "iso:country":"US",
    "sg:address":"4321 Waverly Dr NE",
    "sg:city":"Albany",
    "sg:classifiers":[
        {
            "category":"Professional",
            "type":"Services"
        }
    ],
    "sg:phone":"+1 541 928 1716",
    "sg:postcode":"97321",
    "sg:province":"OR",
    "wof:name":"Radiant Emanations",
    "wof:placetype":"venue"
},
  "geometry": {"coordinates":[-123.072954,44.682391],"type":"Point"}
}