{
  "type": "Feature",
  "properties": {
    "iso:country":"US",
    "sg:address":"19588 S Harper Rd",
    "sg:city":"Colton",
    "sg:classifiers":[
        {
            "category":"Manufacturing",
            "subcategory":"Lumber",
            "type":"Manufacturing & Wholesale Goods"
        }
    ],
    "sg:phone":"+1 503 824 2940",
    "sg:postcode":"97017",
    "sg:province":"OR",
    "sg:tags":[
        "logging"
    ],
    "wof:name":"Ben Parker Cutting Inc",
    "wof:placetype":"venue"
},
  "geometry": {"coordinates":[-122.46398600000001,45.164974],"type":"Point"}
}