{
  "type": "Feature",
  "properties": {
    "iso:country":"US",
    "sg:address":"53947 E Crockett Rd",
    "sg:city":"Milton Freewater",
    "sg:classifiers":[
        {
            "category":"Shopping",
            "subcategory":"Computers & Home Electronics",
            "type":"Retail Goods"
        }
    ],
    "sg:phone":"+1 541 938 6363",
    "sg:postcode":"97862",
    "sg:province":"OR",
    "sg:tags":[
        "software",
        "accounting",
        "engineering",
        "management",
        "research"
    ],
    "wof:name":"Specialized Systems Software",
    "wof:placetype":"venue"
},
  "geometry": {"coordinates":[-118.38301800000001,45.975008],"type":"Point"}
}