{
  "type": "Feature",
  "properties": {
    "addr:full":"1404 7th St Oregon City OR 97045",
    "addr:housenumber":"1404",
    "addr:postcode":"97045",
    "addr:street":"7Th St",
    "iso:country":"US",
    "sg:address":"1404 7th St",
    "sg:city":"Oregon City",
    "sg:classifiers":[
        {
            "category":"Education",
            "subcategory":"School",
            "type":"Public Place"
        }
    ],
    "sg:phone":"+1 503 657 2434",
    "sg:postcode":"97045",
    "sg:province":"OR",
    "wof:name":"Eastham Elementary School",
    "wof:placetype":"venue"
},
  "geometry": {"coordinates":[-122.597385,45.352443],"type":"Point"}
}