{
  "type": "Feature",
  "properties": {
    "addr:full":"1400 Queen Ave SE Albany OR 97322",
    "addr:housenumber":"1400",
    "addr:postcode":"97322",
    "addr:street":"Queen Ave Se",
    "iso:country":"US",
    "sg:address":"1400 Queen Ave SE",
    "sg:city":"Albany",
    "sg:classifiers":[
        {
            "category":"Communications",
            "type":"Services"
        }
    ],
    "sg:phone":"+1 541 812 1265",
    "sg:postcode":"97322",
    "sg:province":"OR",
    "sg:website":"www.dnc.net",
    "wof:name":"Direct Net Communications",
    "wof:placetype":"venue"
},
  "geometry": {"coordinates":[-123.084334,44.625212],"type":"Point"}
}