{
  "type": "Feature",
  "properties": {
    "addr:full":"13050 SW Tonquin Rd Sherwood OR 97140",
    "addr:housenumber":"13050",
    "addr:postcode":"97140",
    "addr:street":"Sw Tonquin Rd",
    "iso:country":"US",
    "sg:address":"13050 SW Tonquin Rd",
    "sg:city":"Sherwood",
    "sg:classifiers":[
        {
            "category":"Recreation",
            "type":"Entertainment"
        }
    ],
    "sg:phone":"+1 503 625 7318",
    "sg:postcode":"97140",
    "sg:province":"OR",
    "sg:tags":[
        "range",
        "trap",
        "skeet"
    ],
    "wof:name":"Tri-County Gun Club",
    "wof:placetype":"venue"
},
  "geometry": {"coordinates":[-122.81798999999999,45.354504],"type":"Point"}
}