{
  "type": "Feature",
  "properties": {
    "iso:country":"US",
    "sg:address":"998 Hawthorne Ave NE",
    "sg:city":"Salem",
    "sg:classifiers":[
        {
            "category":"Government",
            "subcategory":"Office",
            "type":"Public Place"
        }
    ],
    "sg:phone":"+1 503 399 3108",
    "sg:postcode":"97301",
    "sg:province":"OR",
    "sg:tags":[
        "educational",
        "program",
        "administration"
    ],
    "wof:name":"Salem-Keizer Public School Dst",
    "wof:placetype":"venue"
},
  "geometry": {"coordinates":[-122.99186,44.939789],"type":"Point"}
}