{
  "type": "Feature",
  "properties": {
    "iso:country":"US",
    "sg:address":"21228 State Hwy 62",
    "sg:city":"Shady Cove",
    "sg:classifiers":[
        {
            "category":"Retail",
            "subcategory":"Auto Repair",
            "type":"Services"
        }
    ],
    "sg:phone":"+1 541 878 3390",
    "sg:postcode":"97539",
    "sg:province":"OR",
    "sg:tags":[
        "body",
        "automobile",
        "painting"
    ],
    "wof:name":"Shady Cove Collision",
    "wof:placetype":"venue"
},
  "geometry": {"coordinates":[-122.814418,42.608753],"type":"Point"}
}