{
  "type": "Feature",
  "properties": {
    "iso:country":"US",
    "sg:address":"2749 Friendly St",
    "sg:city":"Eugene",
    "sg:classifiers":[
        {
            "category":"Health Services",
            "subcategory":"Health Practitioner",
            "type":"Services"
        }
    ],
    "sg:phone":"+1 541 349 9404",
    "sg:postcode":"97405",
    "sg:province":"OR",
    "sg:tags":[
        "physician"
    ],
    "wof:name":"Friendly St Natural Health Ctr",
    "wof:placetype":"venue"
},
  "geometry": {"coordinates":[-123.105468,44.028277],"type":"Point"}
}