{
  "type": "Feature",
  "properties": {
    "iso:country":"US",
    "sg:address":"3525 NE Broadway Street",
    "sg:city":"Portland",
    "sg:classifiers":[
        {
            "category":"Building & Trades",
            "subcategory":"Cleaning & Sanitation",
            "type":"Services"
        }
    ],
    "sg:phone":"+1 503 284 6869",
    "sg:postcode":"97232",
    "sg:province":"OR",
    "sg:tags":[
        "carpet"
    ],
    "wof:name":"Commercial Carpet Maintenance",
    "wof:placetype":"venue"
},
  "geometry": {"coordinates":[-122.627799,45.535272],"type":"Point"}
}