{
  "type": "Feature",
  "properties": {
    "iso:country":"US",
    "sg:address":"948 NE 102nd Avenue Suite 106",
    "sg:city":"Portland",
    "sg:classifiers":[
        {
            "category":"Health Services",
            "subcategory":"Chiropractor",
            "type":"Services"
        }
    ],
    "sg:phone":"+1 503 257 6036",
    "sg:postcode":"97220",
    "sg:province":"OR",
    "sg:tags":[
        "chiropractic"
    ],
    "wof:name":"Kirchem Greg DC",
    "wof:placetype":"venue"
},
  "geometry": {"coordinates":[-122.558109,45.529583],"type":"Point"}
}