{
  "type": "Feature",
  "properties": {
    "iso:country":"US",
    "sg:address":"90518 Link Rd",
    "sg:city":"Eugene",
    "sg:classifiers":[
        {
            "category":"Home & Garden",
            "subcategory":"Mobile Homes",
            "type":"Retail Goods"
        }
    ],
    "sg:phone":"+1 541 689 1129",
    "sg:postcode":"97402",
    "sg:province":"OR",
    "sg:tags":[
        "parts"
    ],
    "wof:name":"Ken's Mobile Tires & Axle",
    "wof:placetype":"venue"
},
  "geometry": {"coordinates":[-123.168083,44.119778],"type":"Point"}
}