{
  "type": "Feature",
  "properties": {
    "addr:full":"1600 Mount Hood Ave Woodburn OR 97071",
    "addr:housenumber":"1600",
    "addr:postcode":"97071",
    "addr:street":"Mount Hood Ave",
    "iso:country":"US",
    "sg:address":"1600 Mount Hood Ave",
    "sg:city":"Woodburn",
    "sg:classifiers":[
        {
            "category":"Shopping",
            "subcategory":"Department Store",
            "type":"Retail Goods"
        }
    ],
    "sg:phone":"+1 503 981 2101",
    "sg:postcode":"97071",
    "sg:province":"OR",
    "sg:website":"www.bimart.com",
    "wof:name":"Bi-Mart",
    "wof:placetype":"venue"
},
  "geometry": {"coordinates":[-122.836742,45.151338],"type":"Point"}
}