{
  "type": "Feature",
  "properties": {
    "iso:country":"US",
    "sg:address":"331 Boardman Ave NE",
    "sg:city":"Boardman",
    "sg:classifiers":[
        {
            "category":"Real Estate",
            "subcategory":"Real Estate Operator",
            "type":"Services"
        }
    ],
    "sg:phone":"+1 541 481 2212",
    "sg:postcode":"97818",
    "sg:province":"OR",
    "sg:tags":[
        "apartment"
    ],
    "wof:name":"Hab-Doc Apartments",
    "wof:placetype":"venue"
},
  "geometry": {"coordinates":[-119.693325,45.842114],"type":"Point"}
}