{
  "type": "Feature",
  "properties": {
    "iso:country":"US",
    "sg:address":"81 E 28th Ave",
    "sg:city":"Eugene",
    "sg:classifiers":[
        {
            "category":"Shopping",
            "subcategory":"Books",
            "type":"Retail Goods"
        }
    ],
    "sg:phone":"+1 541 683 8669",
    "sg:postcode":"97405",
    "sg:province":"OR",
    "sg:tags":[
        "bookstore",
        "christian"
    ],
    "wof:name":"Grace Amazing Bible Bookstore",
    "wof:placetype":"venue"
},
  "geometry": {"coordinates":[-123.08951500000001,44.028184],"type":"Point"}
}