{
  "type": "Feature",
  "properties": {
    "addr:full":"37112 NW Moss Rock Dr Corvallis OR 97330",
    "addr:housenumber":"37112",
    "addr:postcode":"97330",
    "addr:street":"Nw Moss Rock Dr",
    "iso:country":"US",
    "sg:address":"37112 NW Moss Rock Dr",
    "sg:city":"Corvallis",
    "sg:classifiers":[
        {
            "category":"Professional",
            "type":"Services"
        }
    ],
    "sg:phone":"+1 541 745 0240",
    "sg:postcode":"97330",
    "sg:province":"OR",
    "wof:name":"Joan Hadgar",
    "wof:placetype":"venue"
},
  "geometry": {"coordinates":[-123.29655099999999,44.649501],"type":"Point"}
}