{
  "type": "Feature",
  "properties": {
    "iso:country":"US",
    "sg:address":"35867 State Hwy 58",
    "sg:city":"Pleasant Hill",
    "sg:classifiers":[
        {
            "category":"Banks & Credit Unions",
            "subcategory":"Bank",
            "type":"Services"
        }
    ],
    "sg:phone":"+1 541 726 7211",
    "sg:postcode":"97455",
    "sg:province":"OR",
    "wof:name":"Siuslaw Valley Bank",
    "wof:placetype":"venue"
},
  "geometry": {"coordinates":[-122.938002,43.969232],"type":"Point"}
}