{
  "type": "Feature",
  "properties": {
    "addr:full":"241 SE 6th St Madras OR 97741",
    "addr:housenumber":"241",
    "addr:postcode":"97741",
    "addr:street":"Se 6Th St",
    "iso:country":"US",
    "sg:address":"241 SE 6th St",
    "sg:city":"Madras",
    "sg:classifiers":[
        {
            "category":"Manufacturing",
            "subcategory":"Printing",
            "type":"Manufacturing & Wholesale Goods"
        }
    ],
    "sg:phone":"+1 541 475 2275",
    "sg:postcode":"97741",
    "sg:province":"OR",
    "sg:tags":[
        "publishes",
        "print",
        "newspaper",
        "weekly"
    ],
    "sg:website":"www.madraspioneer.com",
    "wof:name":"Madras Pioneer The",
    "wof:placetype":"venue"
},
  "geometry": {"coordinates":[-121.128455,44.633037],"type":"Point"}
}