{
  "type": "Feature",
  "properties": {
    "iso:country":"US",
    "sg:address":"3004 SE 62nd Ave",
    "sg:city":"Portland",
    "sg:classifiers":[
        {
            "category":"Building & Trades",
            "subcategory":"Cleaning & Sanitation",
            "type":"Services"
        }
    ],
    "sg:phone":"+1 503 680 3511",
    "sg:postcode":"97206",
    "sg:province":"OR",
    "sg:tags":[
        "maintenance"
    ],
    "wof:name":"LBI Pacific",
    "wof:placetype":"venue"
},
  "geometry": {"coordinates":[-122.599384,45.500869],"type":"Point"}
}