{
  "type": "Feature",
  "properties": {
    "iso:country":"US",
    "sg:address":"14240 SE Rupert Dr",
    "sg:city":"Portland",
    "sg:classifiers":[
        {
            "category":"Building & Trades",
            "subcategory":"Construction",
            "type":"Services"
        }
    ],
    "sg:phone":"+1 503 654 3565",
    "sg:postcode":"97267",
    "sg:province":"OR",
    "sg:tags":[
        "house"
    ],
    "wof:name":"McCauley Construction",
    "wof:placetype":"venue"
},
  "geometry": {"coordinates":[-122.64021099999999,45.42219],"type":"Point"}
}