{
  "type": "Feature",
  "properties": {
    "iso:country":"US",
    "sg:address":"4832 Hwy 201",
    "sg:city":"Ontario",
    "sg:classifiers":[
        {
            "category":"Autos & Motor Vehicles",
            "subcategory":"Automobile Sales",
            "type":"Retail Goods"
        }
    ],
    "sg:phone":"+1 541 262 3107",
    "sg:postcode":"97914",
    "sg:province":"OR",
    "sg:tags":[
        "car",
        "dealer"
    ],
    "wof:name":"Performance Auto Builders",
    "wof:placetype":"venue"
},
  "geometry": {"coordinates":[-116.939496,44.130714],"type":"Point"}
}