{
  "type": "Feature",
  "properties": {
    "iso:country":"US",
    "sg:address":"25580 S Holman Rd",
    "sg:city":"Estacada",
    "sg:classifiers":[
        {
            "category":"Freight",
            "type":"Transportation"
        }
    ],
    "sg:phone":"+1 503 630 3353",
    "sg:postcode":"97023",
    "sg:province":"OR",
    "sg:tags":[
        "trucking"
    ],
    "wof:name":"Bob Soule Trucking",
    "wof:placetype":"venue"
},
  "geometry": {"coordinates":[-122.340169,45.242383],"type":"Point"}
}