{
  "type": "Feature",
  "properties": {
    "iso:country":"US",
    "sg:address":"12607 NW Forest Spring Ln",
    "sg:city":"Portland",
    "sg:classifiers":[
        {
            "category":"Professional",
            "subcategory":"Advertising",
            "type":"Services"
        }
    ],
    "sg:phone":"+1 503 352 4881",
    "sg:postcode":"97229",
    "sg:province":"OR",
    "sg:tags":[
        "marketing",
        "program"
    ],
    "wof:name":"Resonate Marketing",
    "wof:placetype":"venue"
},
  "geometry": {"coordinates":[-122.80711100000001,45.550758],"type":"Point"}
}