{
  "type": "Feature",
  "properties": {
    "iso:country":"US",
    "sg:address":"24386 Dawson Rd",
    "sg:city":"Monroe",
    "sg:classifiers":[
        {
            "category":"Retail",
            "subcategory":"Auto Repair",
            "type":"Services"
        }
    ],
    "sg:phone":"+1 541 424 3448",
    "sg:postcode":"97456",
    "sg:province":"OR",
    "sg:tags":[
        "windshield"
    ],
    "wof:name":"Dawson Road Auto Glass Repair",
    "wof:placetype":"venue"
},
  "geometry": {"coordinates":[-123.395842,44.357009],"type":"Point"}
}