{
  "type": "Feature",
  "properties": {
    "iso:country":"US",
    "sg:address":"3124 NW Broad St",
    "sg:city":"Roseburg",
    "sg:classifiers":[
        {
            "category":"Building & Trades",
            "subcategory":"Construction",
            "type":"Services"
        }
    ],
    "sg:phone":"+1 541 672 0957",
    "sg:postcode":"97470",
    "sg:province":"OR",
    "sg:tags":[
        "hanging",
        "contractor"
    ],
    "wof:name":"Family Painting",
    "wof:placetype":"venue"
},
  "geometry": {"coordinates":[-123.361974,43.246177],"type":"Point"}
}