{
  "type": "Feature",
  "properties": {
    "iso:country":"US",
    "sg:address":"19450 SW Cipole Rd",
    "sg:city":"Tualatin",
    "sg:classifiers":[
        {
            "category":"Retail",
            "subcategory":"Auto Repair",
            "type":"Services"
        }
    ],
    "sg:phone":"+1 503 612 9000",
    "sg:postcode":"97062",
    "sg:province":"OR",
    "sg:tags":[
        "glass",
        "coating",
        "tinting"
    ],
    "wof:name":"Pacific Window Tinting Inc",
    "wof:placetype":"venue"
},
  "geometry": {"coordinates":[-122.815428,45.378907],"type":"Point"}
}