{
  "type": "Feature",
  "properties": {
    "iso:country":"US",
    "sg:address":"37 W 13th Ave",
    "sg:city":"Eugene",
    "sg:classifiers":[
        {
            "category":"Professional",
            "type":"Services"
        }
    ],
    "sg:phone":"+1 541 687 7971",
    "sg:postcode":"97401",
    "sg:province":"OR",
    "wof:name":"H M C",
    "wof:placetype":"venue"
},
  "geometry": {"coordinates":[-123.09297,44.045594],"type":"Point"}
}