{
  "type": "Feature",
  "properties": {
    "addr:full":"16002 NW Ramona Dr Beaverton OR 97006",
    "addr:housenumber":"16002",
    "addr:postcode":"97006",
    "addr:street":"Nw Ramona Dr",
    "iso:country":"US",
    "sg:address":"16002 NW Ramona Dr",
    "sg:city":"Beaverton",
    "sg:classifiers":[
        {
            "category":"Wholesale",
            "subcategory":"Non-durable Goods",
            "type":"Manufacturing & Wholesale Goods"
        }
    ],
    "sg:phone":"+1 503 629 2129",
    "sg:postcode":"97006",
    "sg:province":"OR",
    "wof:name":"Gifts America",
    "wof:placetype":"venue"
},
  "geometry": {"coordinates":[-122.842023,45.539945],"type":"Point"}
}