{
  "type": "Feature",
  "properties": {
    "iso:country":"US",
    "sg:address":"2485 Riverview St",
    "sg:city":"Eugene",
    "sg:classifiers":[
        {
            "category":"Building & Trades",
            "subcategory":"Construction",
            "type":"Services"
        },
        {
            "category":"Restaurant",
            "type":"Food & Drink"
        }
    ],
    "sg:phone":"+1 541 485 0789",
    "sg:postcode":"97403",
    "sg:province":"OR",
    "sg:tags":[
        "eating",
        "woodworker"
    ],
    "wof:name":"Roman's Woodworks",
    "wof:placetype":"venue"
},
  "geometry": {"coordinates":[-123.051885,44.031805],"type":"Point"}
}