{
  "type": "Feature",
  "properties": {
    "iso:country":"US",
    "sg:address":"3240 SE Hawthorne Boulevard",
    "sg:city":"Portland",
    "sg:classifiers":[
        {
            "category":"Restaurant",
            "type":"Food & Drink"
        }
    ],
    "sg:phone":"+1 503 234 0073",
    "sg:postcode":"97214",
    "sg:province":"OR",
    "sg:tags":[
        "pizza"
    ],
    "wof:name":"Okie Dokie's Pizza & Deli",
    "wof:placetype":"venue"
},
  "geometry": {"coordinates":[-122.631744,45.512056],"type":"Point"}
}