{
  "type": "Feature",
  "properties": {
    "addr:full":"1176 State Hwy 99 N Eugene OR 97402",
    "addr:housenumber":"1176",
    "addr:postcode":"97402",
    "addr:street":"State Hwy 99 N",
    "iso:country":"US",
    "sg:address":"1176 State Hwy 99 N",
    "sg:city":"Eugene",
    "sg:classifiers":[
        {
            "category":"Personal",
            "subcategory":"Beauty Salon",
            "type":"Services"
        }
    ],
    "sg:phone":"+1 541 345 8110",
    "sg:postcode":"97402",
    "sg:province":"OR",
    "wof:name":"Tatiana's Hair Salon",
    "wof:placetype":"venue"
},
  "geometry": {"coordinates":[-123.150006,44.077822],"type":"Point"}
}