{
  "type": "Feature",
  "properties": {
    "iso:country":"US",
    "sg:address":"445 SW Pine Street",
    "sg:city":"Portland",
    "sg:classifiers":[
        {
            "category":"Retail",
            "subcategory":"Auto Rental",
            "type":"Services"
        }
    ],
    "sg:phone":"+1 503 275 5359",
    "sg:postcode":"97204",
    "sg:province":"OR",
    "sg:tags":[
        "car"
    ],
    "sg:website":"www.enterprise.com",
    "wof:name":"Enterprise Rent-A-Car",
    "wof:placetype":"venue"
},
  "geometry": {"coordinates":[-122.675212,45.521988],"type":"Point"}
}