{
  "type": "Feature",
  "properties": {
    "iso:country":"US",
    "sg:address":"2455 NW Marshall St",
    "sg:city":"Portland",
    "sg:classifiers":[
        {
            "category":"Real Estate",
            "subcategory":"Real Estate Agent",
            "type":"Services"
        }
    ],
    "sg:phone":"+1 503 245 3357",
    "sg:postcode":"97210",
    "sg:province":"OR",
    "sg:website":"www.modarealty.com",
    "wof:name":"Moda Realty",
    "wof:placetype":"venue"
},
  "geometry": {"coordinates":[-122.702106,45.530517],"type":"Point"}
}