{
  "type": "Feature",
  "properties": {
    "iso:country":"US",
    "sg:address":"8892 NE Quaale Rd",
    "sg:city":"Madras",
    "sg:classifiers":[
        {
            "category":"Retail",
            "subcategory":"Auto Rental",
            "type":"Services"
        }
    ],
    "sg:phone":"+1 541 475 3966",
    "sg:postcode":"97741",
    "sg:province":"OR",
    "sg:tags":[
        "water",
        "passenger",
        "transport",
        "car"
    ],
    "wof:name":"Deschutes Driftboat Rental",
    "wof:placetype":"venue"
},
  "geometry": {"coordinates":[-121.034329,44.760112],"type":"Point"}
}