{
  "type": "Feature",
  "properties": {
    "iso:country":"US",
    "sg:address":"4074 Winema Pl NE",
    "sg:city":"Salem",
    "sg:classifiers":[
        {
            "category":"Social Services",
            "type":"Services"
        }
    ],
    "sg:phone":"+1 503 378 2731",
    "sg:postcode":"97305",
    "sg:province":"OR",
    "sg:tags":[
        "government"
    ],
    "wof:name":"Adult & Family Svc Dept",
    "wof:placetype":"venue"
},
  "geometry": {"coordinates":[-122.979194,44.976013],"type":"Point"}
}