{
  "type": "Feature",
  "properties": {
    "addr:full":"20399 Sturgis Ln Alsea OR 97324",
    "addr:housenumber":"20399",
    "addr:postcode":"97324",
    "addr:street":"Sturgis Ln",
    "iso:country":"US",
    "sg:address":"20399 Sturgis Ln",
    "sg:city":"Alsea",
    "sg:classifiers":[
        {
            "category":"Manufacturing",
            "subcategory":"Building Materials",
            "type":"Manufacturing & Wholesale Goods"
        }
    ],
    "sg:phone":"+1 541 487 7303",
    "sg:postcode":"97324",
    "sg:province":"OR",
    "sg:tags":[
        "mfg"
    ],
    "wof:name":"Westlind Woodworking",
    "wof:placetype":"venue"
},
  "geometry": {"coordinates":[-123.54736,44.4187],"type":"Point"}
}