{
  "type": "Feature",
  "properties": {
    "iso:country":"US",
    "sg:address":"10 Crater Lake Ave",
    "sg:city":"Medford",
    "sg:classifiers":[
        {
            "category":"Wholesale",
            "subcategory":"Photographic Equipment",
            "type":"Manufacturing & Wholesale Goods"
        }
    ],
    "sg:phone":"+1 541 779 7962",
    "sg:postcode":"97504",
    "sg:province":"OR",
    "sg:tags":[
        "screen",
        "projection"
    ],
    "wof:name":"A V C Management Center",
    "wof:placetype":"venue"
},
  "geometry": {"coordinates":[-122.862227,42.329207],"type":"Point"}
}