{
  "type": "Feature",
  "properties": {
    "addr:full":"5626 NE M L King Blvd Portland OR 97211",
    "addr:housenumber":"5626",
    "addr:postcode":"97211",
    "addr:street":"Ne M L King Blvd",
    "iso:country":"US",
    "sg:address":"5626 NE M L King Blvd",
    "sg:city":"Portland",
    "sg:classifiers":[
        {
            "category":"Shopping",
            "subcategory":"Clothing, Apparel, & Fashions",
            "type":"Retail Goods"
        }
    ],
    "sg:phone":"+1 503 281 0599",
    "sg:postcode":"97211",
    "sg:province":"OR",
    "wof:name":"Friendly Fashion & Style",
    "wof:placetype":"venue"
},
  "geometry": {"coordinates":[-122.661349,45.563742],"type":"Point"}
}