{
  "type": "Feature",
  "properties": {
    "iso:country":"US",
    "sg:address":"245 N Willow St",
    "sg:city":"Merrill",
    "sg:classifiers":[
        {
            "category":"Professional",
            "type":"Services"
        }
    ],
    "sg:phone":"+1 541 798 0507",
    "sg:postcode":"97633",
    "sg:province":"OR",
    "wof:name":"Richard R Kerns",
    "wof:placetype":"venue"
},
  "geometry": {"coordinates":[-121.592235,42.02401],"type":"Point"}
}