{
  "type": "Feature",
  "properties": {
    "addr:full":"3341 SE Brooklyn St Portland OR 97202",
    "addr:housenumber":"3341",
    "addr:postcode":"97202",
    "addr:street":"Se Brooklyn St",
    "iso:country":"US",
    "sg:address":"3341 SE Brooklyn St",
    "sg:city":"Portland",
    "sg:classifiers":[
        {
            "category":"Professional",
            "subcategory":"Computer Services",
            "type":"Services"
        }
    ],
    "sg:phone":"+1 503 232 7997",
    "sg:postcode":"97202",
    "sg:province":"OR",
    "sg:tags":[
        "prepackaged",
        "software"
    ],
    "wof:name":"Pannet Software",
    "wof:placetype":"venue"
},
  "geometry": {"coordinates":[-122.62899299999999,45.501301],"type":"Point"}
}