{
  "type": "Feature",
  "properties": {
    "iso:country":"US",
    "sg:address":"448 W 3rd Ave",
    "sg:city":"Eugene",
    "sg:classifiers":[
        {
            "category":"Shopping",
            "subcategory":"Crafts & Fabrics",
            "type":"Retail Goods"
        }
    ],
    "sg:phone":"+1 541 484 1925",
    "sg:postcode":"97401",
    "sg:province":"OR",
    "sg:tags":[
        "sewing"
    ],
    "sg:website":"www.letterboxquilts.com",
    "wof:name":"Quilt Patch",
    "wof:placetype":"venue"
},
  "geometry": {"coordinates":[-123.098806,44.056539],"type":"Point"}
}