{
  "type": "Feature",
  "properties": {
    "addr:full":"9325 SW Ridder Rd Wilsonville OR 97070",
    "addr:housenumber":"9325",
    "addr:postcode":"97070",
    "addr:street":"Sw Ridder Rd",
    "iso:country":"US",
    "sg:address":"9325 SW Ridder Rd",
    "sg:city":"Wilsonville",
    "sg:classifiers":[
        {
            "category":"Manufacturing",
            "subcategory":"Rubber & Plastics",
            "type":"Manufacturing & Wholesale Goods"
        }
    ],
    "sg:phone":"+1 503 685 9092",
    "sg:postcode":"97070",
    "sg:province":"OR",
    "sg:tags":[
        "sealing",
        "mfg",
        "devices",
        "gasket"
    ],
    "wof:name":"Igi",
    "wof:placetype":"venue"
},
  "geometry": {"coordinates":[-122.774841,45.331824],"type":"Point"}
}