{
  "type": "Feature",
  "properties": {
    "iso:country":"US",
    "sg:address":"12570 NE Marx St",
    "sg:city":"Portland",
    "sg:classifiers":[
        {
            "category":"Wholesale",
            "subcategory":"Machinery & Supplies",
            "type":"Manufacturing & Wholesale Goods"
        },
        {
            "category":"Manufacturing",
            "subcategory":"Tools & Machinery",
            "type":"Manufacturing & Wholesale Goods"
        }
    ],
    "sg:phone":"+1 503 408 8771",
    "sg:postcode":"97230",
    "sg:province":"OR",
    "sg:tags":[
        "equipment",
        "industrial",
        "loading",
        "dock"
    ],
    "sg:website":"www.arbonequipment.com",
    "wof:name":"Arbon Equipment Corporation",
    "wof:placetype":"venue"
},
  "geometry": {"coordinates":[-122.53506,45.558931],"type":"Point"}
}