{
  "type": "Feature",
  "properties": {
    "addr:full":"800 Baker St Lebanon OR 97355",
    "addr:housenumber":"800",
    "addr:postcode":"97355",
    "addr:street":"Baker St",
    "iso:country":"US",
    "sg:address":"800 Baker St",
    "sg:city":"Lebanon",
    "sg:classifiers":[
        {
            "category":"Building & Trades",
            "subcategory":"Landscaping Services",
            "type":"Services"
        }
    ],
    "sg:phone":"+1 541 451 5571",
    "sg:postcode":"97355",
    "sg:province":"OR",
    "wof:name":"Cordoza Gardening",
    "wof:placetype":"venue"
},
  "geometry": {"coordinates":[-122.905422,44.504614],"type":"Point"}
}