{
  "type": "Feature",
  "properties": {
    "iso:country":"US",
    "sg:address":"83925 Cloud Nine Rd",
    "sg:city":"Florence",
    "sg:classifiers":[
        {
            "category":"Shopping",
            "subcategory":"Hobbies, Toys, & Games",
            "type":"Retail Goods"
        }
    ],
    "sg:phone":"+1 541 997 1759",
    "sg:postcode":"97439",
    "sg:province":"OR",
    "wof:name":"Check Mate",
    "wof:placetype":"venue"
},
  "geometry": {"coordinates":[-124.093598,43.914522],"type":"Point"}
}