{
  "type": "Feature",
  "properties": {
    "addr:full":"2665 Balfour St Eugene OR 97408",
    "addr:housenumber":"2665",
    "addr:postcode":"97408",
    "addr:street":"Balfour St",
    "iso:country":"US",
    "sg:address":"2665 Balfour St",
    "sg:city":"Eugene",
    "sg:classifiers":[
        {
            "category":"Professional",
            "subcategory":"Credit Reporting & Collection",
            "type":"Services"
        }
    ],
    "sg:phone":"+1 541 343 6607",
    "sg:postcode":"97408",
    "sg:province":"OR",
    "sg:tags":[
        "agency"
    ],
    "wof:name":"Custom Credit Collection",
    "wof:placetype":"venue"
},
  "geometry": {"coordinates":[-123.082588,44.090889],"type":"Point"}
}