{
  "type": "Feature",
  "properties": {
    "iso:country":"US",
    "sg:address":"1033 SW Myrtle Dr",
    "sg:city":"Portland",
    "sg:classifiers":[
        {
            "category":"Health Services",
            "subcategory":"Doctor",
            "type":"Services"
        },
        {
            "category":"Health Services",
            "subcategory":"Dentist",
            "type":"Services"
        }
    ],
    "sg:phone":"+1 503 274 9676",
    "sg:postcode":"97201",
    "sg:province":"OR",
    "sg:tags":[
        "dentists-oral",
        "physician",
        "maxillofacial",
        "surgeons",
        "surgery",
        "oral"
    ],
    "wof:name":"Service D Anthony Dmd",
    "wof:placetype":"venue"
},
  "geometry": {"coordinates":[-122.689982,45.507222],"type":"Point"}
}