{
  "type": "Feature",
  "properties": {
    "iso:country":"US",
    "sg:address":"760 Madrona Ave S",
    "sg:city":"Salem",
    "sg:classifiers":[
        {
            "category":"Building & Trades",
            "subcategory":"Construction",
            "type":"Services"
        }
    ],
    "sg:phone":"+1 503 362 4339",
    "sg:postcode":"97302",
    "sg:province":"OR",
    "sg:tags":[
        "contractor"
    ],
    "wof:name":"Borden",
    "wof:placetype":"venue"
},
  "geometry": {"coordinates":[-123.058308,44.904665],"type":"Point"}
}