{
  "type": "Feature",
  "properties": {
    "iso:country":"US",
    "sg:address":"203 E Main St",
    "sg:city":"Enterprise",
    "sg:classifiers":[
        {
            "category":"Place Of Worship",
            "subcategory":"Church",
            "type":"Public Place"
        },
        {
            "category":"Place Of Worship",
            "type":"Public Place"
        },
        {
            "category":"Organizations",
            "subcategory":"Religious Organization",
            "type":"Services"
        }
    ],
    "sg:phone":"+1 541 426 0301",
    "sg:postcode":"97828",
    "sg:province":"OR",
    "sg:tags":[
        "churches-evangelical",
        "churches-covenant",
        "covenant"
    ],
    "wof:name":"Christ Covenant Church",
    "wof:placetype":"venue"
},
  "geometry": {"coordinates":[-117.276265,45.42551],"type":"Point"}
}