{
  "type": "Feature",
  "properties": {
    "iso:country":"US",
    "sg:address":"15010 SE McLoughlin Blvd",
    "sg:city":"Milwaukie",
    "sg:classifiers":[
        {
            "category":"Manufacturing",
            "subcategory":"Printing",
            "type":"Manufacturing & Wholesale Goods"
        }
    ],
    "sg:phone":"+1 503 786 6140",
    "sg:postcode":"97267",
    "sg:province":"OR",
    "sg:tags":[
        "publisher",
        "book",
        "publishing"
    ],
    "wof:name":"Northwest Publishing",
    "wof:placetype":"venue"
},
  "geometry": {"coordinates":[-122.631643,45.415836],"type":"Point"}
}