{
  "type": "Feature",
  "properties": {
    "iso:country":"US",
    "sg:address":"2710 SE Long St",
    "sg:city":"Portland",
    "sg:classifiers":[
        {
            "category":"Wholesale",
            "subcategory":"Auto Parts",
            "type":"Manufacturing & Wholesale Goods"
        }
    ],
    "sg:phone":"+1 503 232 3151",
    "sg:postcode":"97202",
    "sg:province":"OR",
    "sg:tags":[
        "automobile",
        "supply"
    ],
    "wof:name":"R J Templeton Co",
    "wof:placetype":"venue"
},
  "geometry": {"coordinates":[-122.637636,45.48885],"type":"Point"}
}