{
  "type": "Feature",
  "properties": {
    "iso:country":"US",
    "sg:address":"3400 SW 172nd Ave",
    "sg:city":"Beaverton",
    "sg:classifiers":[
        {
            "category":"Shopping",
            "type":"Retail Goods"
        }
    ],
    "sg:phone":"+1 503 240 2773",
    "sg:postcode":"97006",
    "sg:province":"OR",
    "sg:tags":[
        "merchandise"
    ],
    "wof:name":"Personal Aquariums",
    "wof:placetype":"venue"
},
  "geometry": {"coordinates":[-122.854056,45.494402],"type":"Point"}
}