{
  "type": "Feature",
  "properties": {
    "iso:country":"US",
    "sg:address":"3691 Joshua Ave NE",
    "sg:city":"Salem",
    "sg:classifiers":[
        {
            "category":"Restaurant",
            "type":"Food & Drink"
        }
    ],
    "sg:phone":"+1 503 364 2986",
    "sg:postcode":"97305",
    "sg:province":"OR",
    "sg:tags":[
        "eating"
    ],
    "wof:name":"Classic Caterers & Co",
    "wof:placetype":"venue"
},
  "geometry": {"coordinates":[-122.96639500000001,44.96982],"type":"Point"}
}