{
  "type": "Feature",
  "properties": {
    "addr:full":"29990 SW Town Center Loop W Wilsonville OR 97070",
    "addr:housenumber":"29990",
    "addr:postcode":"97070",
    "addr:street":"Sw Town Center Loop W",
    "iso:country":"US",
    "sg:address":"29990 SW Town Center Loop W",
    "sg:city":"Wilsonville",
    "sg:classifiers":[
        {
            "category":"Health Services",
            "subcategory":"Doctor",
            "type":"Services"
        }
    ],
    "sg:phone":"+1 503 682 2110",
    "sg:postcode":"97070",
    "sg:province":"OR",
    "sg:tags":[
        "dentist"
    ],
    "wof:name":"Mack S Johnsen DDS",
    "wof:placetype":"venue"
},
  "geometry": {"coordinates":[-122.765711,45.303494],"type":"Point"}
}