{
  "type": "Feature",
  "properties": {
    "iso:country":"US",
    "sg:address":"403 S Water St",
    "sg:city":"Silverton",
    "sg:classifiers":[
        {
            "category":"Insurance",
            "subcategory":"Hazard Insurance",
            "type":"Services"
        },
        {
            "category":"Banks & Credit Unions",
            "subcategory":"Investment Brokerage",
            "type":"Services"
        },
        {
            "category":"Insurance",
            "subcategory":"Life Insurance",
            "type":"Services"
        },
        {
            "category":"Banks & Credit Unions",
            "subcategory":"Financial Services",
            "type":"Services"
        }
    ],
    "sg:phone":"+1 509 884 9505",
    "sg:postcode":"97381",
    "sg:province":"OR",
    "sg:website":"http://national.citysearch.com/profile/external/37038420/silverton_or/country_financial_david_phillips.html?publisher=yellowpages&reference_id=1&placement=ypwebsitemip",
    "wof:name":"COUNTRY Financial - David Phillips",
    "wof:placetype":"venue"
},
  "geometry": {"coordinates":[-122.78110599999999,45.002862],"type":"Point"}
}