{
  "type": "Feature",
  "properties": {
    "addr:full":"3170 NE Highway 99W McMinnville OR 97128",
    "addr:housenumber":"3170",
    "addr:postcode":"97128",
    "addr:street":"Ne Highway 99W",
    "iso:country":"US",
    "sg:address":"3170 NE Highway 99W",
    "sg:city":"McMinnville",
    "sg:classifiers":[
        {
            "category":"Home & Garden",
            "subcategory":"Garden Supply",
            "type":"Retail Goods"
        },
        {
            "category":"Shopping",
            "subcategory":"Pets & Pet Supplies",
            "type":"Retail Goods"
        }
    ],
    "sg:phone":"+1 503 472 7729",
    "sg:postcode":"97128",
    "sg:province":"OR",
    "sg:tags":[
        "nursery",
        "gardening",
        "store"
    ],
    "wof:name":"Kraemer's Garden & Pet Inc",
    "wof:placetype":"venue"
},
  "geometry": {"coordinates":[-123.166,45.230202],"type":"Point"}
}