{
  "type": "Feature",
  "properties": {
    "iso:country":"US",
    "sg:address":"4400 W 11th Ave",
    "sg:city":"Eugene",
    "sg:classifiers":[
        {
            "category":"Banks & Credit Unions",
            "subcategory":"Bank",
            "type":"Services"
        }
    ],
    "sg:phone":"+1 541 349 5001",
    "sg:postcode":"97402",
    "sg:province":"OR",
    "wof:name":"Oregon Metro Federal",
    "wof:placetype":"venue"
},
  "geometry": {"coordinates":[-123.16830400000001,44.048137],"type":"Point"}
}