{
  "type": "Feature",
  "properties": {
    "addr:full":"3375 K St Baker City OR 97814",
    "addr:housenumber":"3375",
    "addr:postcode":"97814",
    "addr:street":"K St",
    "iso:country":"US",
    "sg:address":"3375 K St",
    "sg:city":"Baker City",
    "sg:classifiers":[
        {
            "category":"Building & Trades",
            "subcategory":"Plumbing",
            "type":"Services"
        }
    ],
    "sg:phone":"+1 541 523 2488",
    "sg:postcode":"97814",
    "sg:province":"OR",
    "sg:tags":[
        "heating",
        "contractor"
    ],
    "wof:name":"Cook & Emele Heating Svc",
    "wof:placetype":"venue"
},
  "geometry": {"coordinates":[-117.847173,44.791592],"type":"Point"}
}