{
  "type": "Feature",
  "properties": {
    "addr:full":"2385 Van Buren St Eugene OR 97405",
    "addr:housenumber":"2385",
    "addr:postcode":"97405",
    "addr:street":"Van Buren St",
    "iso:country":"US",
    "sg:address":"2385 Van Buren St",
    "sg:city":"Eugene",
    "sg:classifiers":[
        {
            "category":"Building & Trades",
            "subcategory":"Construction",
            "type":"Services"
        }
    ],
    "sg:phone":"+1 541 338 8331",
    "sg:postcode":"97405",
    "sg:province":"OR",
    "sg:tags":[
        "carpentry",
        "contractor"
    ],
    "wof:name":"Donald Kearney",
    "wof:placetype":"venue"
},
  "geometry": {"coordinates":[-123.109639,44.035334],"type":"Point"}
}