{
  "type": "Feature",
  "properties": {
    "iso:country":"US",
    "sg:address":"777 NE 2nd St Ste A",
    "sg:city":"Corvallis",
    "sg:classifiers":[
        {
            "category":"Real Estate",
            "subcategory":"Real Estate Services",
            "type":"Services"
        },
        {
            "category":"Real Estate",
            "subcategory":"Real Estate Agent",
            "type":"Services"
        },
        {
            "category":"Real Estate",
            "subcategory":"Real Estate Operator",
            "type":"Services"
        }
    ],
    "sg:phone":"+1 541 758 4200",
    "sg:postcode":"97330",
    "sg:province":"OR",
    "sg:tags":[
        "management",
        "apartment",
        "rental"
    ],
    "sg:website":"http://www.mastercraftrestoration.com",
    "wof:name":"First General Services",
    "wof:placetype":"venue"
},
  "geometry": {"coordinates":[-123.256246,44.570876],"type":"Point"}
}