{
  "type": "Feature",
  "properties": {
    "addr:full":"1802 NE Evans St Mcminnville OR 97128",
    "addr:housenumber":"1802",
    "addr:postcode":"97128",
    "addr:street":"Ne Evans St",
    "iso:country":"US",
    "sg:address":"1802 NE Evans St",
    "sg:city":"Mcminnville",
    "sg:classifiers":[
        {
            "category":"Social Services",
            "type":"Services"
        }
    ],
    "sg:phone":"+1 503 434 5218",
    "sg:postcode":"97128",
    "sg:province":"OR",
    "wof:name":"Mid-Valley Rehabilitation Inc",
    "wof:placetype":"venue"
},
  "geometry": {"coordinates":[-123.19441500000001,45.22098],"type":"Point"}
}