{
  "type": "Feature",
  "properties": {
    "iso:country":"US",
    "sg:address":"25272 Alston Rd",
    "sg:city":"Rainier",
    "sg:classifiers":[
        {
            "category":"Organizations",
            "subcategory":"Religious Organization",
            "type":"Services"
        }
    ],
    "sg:phone":"+1 503 556 1961",
    "sg:postcode":"97048",
    "sg:province":"OR",
    "sg:tags":[
        "church"
    ],
    "wof:name":"Alston's Corner Assembly Chr",
    "wof:placetype":"venue"
},
  "geometry": {"coordinates":[-123.047715,46.099212],"type":"Point"}
}