{
  "type": "Feature",
  "properties": {
    "iso:country":"US",
    "sg:address":"8040 SE Stark St",
    "sg:city":"Portland",
    "sg:classifiers":[
        {
            "category":"Restaurant",
            "type":"Food & Drink"
        }
    ],
    "sg:phone":"+1 503 252 3242",
    "sg:postcode":"97215",
    "sg:province":"OR",
    "sg:website":"http://www.alaskaharvest.com",
    "wof:name":"Alaskan Harvest Seafood, Inc.",
    "wof:placetype":"venue"
},
  "geometry": {"coordinates":[-122.58105999999999,45.519138],"type":"Point"}
}