{
  "type": "Feature",
  "properties": {
    "iso:country":"US",
    "sg:address":"205 NE 3rd Ave",
    "sg:city":"Hillsboro",
    "sg:classifiers":[
        {
            "category":"Personal",
            "subcategory":"Beauty Salon",
            "type":"Services"
        }
    ],
    "sg:phone":"+1 503 693 8800",
    "sg:postcode":"97124",
    "sg:province":"OR",
    "sg:tags":[
        "shop"
    ],
    "wof:name":"3rd Ave Hair Studio",
    "wof:placetype":"venue"
},
  "geometry": {"coordinates":[-122.986185,45.525099],"type":"Point"}
}