{
  "type": "Feature",
  "properties": {
    "addr:full":"1316 SE Main St Roseburg OR 97470",
    "addr:housenumber":"1316",
    "addr:postcode":"97470",
    "addr:street":"Se Main St",
    "iso:country":"US",
    "sg:address":"1316 SE Main St",
    "sg:city":"Roseburg",
    "sg:classifiers":[
        {
            "category":"Professional",
            "subcategory":"Accounting & Tax Preparation",
            "type":"Services"
        }
    ],
    "sg:phone":"+1 541 672 7491",
    "sg:postcode":"97470",
    "sg:province":"OR",
    "sg:tags":[
        "return",
        "filing"
    ],
    "wof:name":"A A Personal Tax Svc",
    "wof:placetype":"venue"
},
  "geometry": {"coordinates":[-123.34697799999999,43.202004],"type":"Point"}
}