{
  "type": "Feature",
  "properties": {
    "iso:country":"US",
    "sg:address":"92688 Abbott Rd",
    "sg:city":"Astoria",
    "sg:classifiers":[
        {
            "category":"Wholesale",
            "subcategory":"Farm Supplies",
            "type":"Manufacturing & Wholesale Goods"
        }
    ],
    "sg:phone":"+1 503 458 6470",
    "sg:postcode":"97103",
    "sg:province":"OR",
    "sg:tags":[
        "feed"
    ],
    "wof:name":"Granny Patti",
    "wof:placetype":"venue"
},
  "geometry": {"coordinates":[-123.57635399999999,46.167902],"type":"Point"}
}