{
  "type": "Feature",
  "properties": {
    "iso:country":"US",
    "sg:address":"200 Pine Valley Rd",
    "sg:city":"Lake Oswego",
    "sg:classifiers":[
        {
            "category":"Manufacturing",
            "subcategory":"Toys & Sporting Goods",
            "type":"Manufacturing & Wholesale Goods"
        }
    ],
    "sg:phone":"+1 503 636 9703",
    "sg:postcode":"97034",
    "sg:province":"OR",
    "sg:tags":[
        "mfg"
    ],
    "wof:name":"Bears & Hares",
    "wof:placetype":"venue"
},
  "geometry": {"coordinates":[-122.679665,45.41785],"type":"Point"}
}