{
  "type": "Feature",
  "properties": {
    "iso:country":"US",
    "sg:address":"29772 SW Heater Rd",
    "sg:city":"Sherwood",
    "sg:classifiers":[
        {
            "category":"Building & Trades",
            "subcategory":"Construction",
            "type":"Services"
        }
    ],
    "sg:phone":"+1 503 625 2111",
    "sg:postcode":"97140",
    "sg:province":"OR",
    "sg:tags":[
        "road",
        "oiling"
    ],
    "wof:name":"Ashwood Construction",
    "wof:placetype":"venue"
},
  "geometry": {"coordinates":[-122.861441,45.304785],"type":"Point"}
}