{
  "type": "Feature",
  "properties": {
    "addr:full":"1129 SE Market Street Portland OR 97214",
    "addr:housenumber":"1129",
    "addr:postcode":"97214",
    "addr:street":"Se Market Street",
    "iso:country":"US",
    "sg:address":"1129 SE Market Street",
    "sg:city":"Portland",
    "sg:classifiers":[
        {
            "category":"Bakery",
            "type":"Food & Drink"
        }
    ],
    "sg:phone":"+1 503 233 6311",
    "sg:postcode":"97214",
    "sg:province":"OR",
    "wof:name":"Newhouse Cheesecakes",
    "wof:placetype":"venue"
},
  "geometry": {"coordinates":[-122.653971,45.510901],"type":"Point"}
}