{
  "type": "Feature",
  "properties": {
    "addr:full":"3339 Harrison Ave Astoria OR 97103",
    "addr:housenumber":"3339",
    "addr:postcode":"97103",
    "addr:street":"Harrison Ave",
    "iso:country":"US",
    "sg:address":"3339 Harrison Ave",
    "sg:city":"Astoria",
    "sg:classifiers":[
        {
            "category":"Utilities",
            "subcategory":"Water",
            "type":"Services"
        }
    ],
    "sg:phone":"+1 503 325 5782",
    "sg:postcode":"97103",
    "sg:province":"OR",
    "sg:tags":[
        "fishermen-commercial"
    ],
    "wof:name":"Camp 9 Fisheries Inc",
    "wof:placetype":"venue"
},
  "geometry": {"coordinates":[-123.806847,46.189369],"type":"Point"}
}