{
  "type": "Feature",
  "properties": {
    "addr:full":"1060 Chandler Rd Lake Oswego OR 97034",
    "addr:housenumber":"1060",
    "addr:postcode":"97034",
    "addr:street":"Chandler Rd",
    "iso:country":"US",
    "sg:address":"1060 Chandler Rd",
    "sg:city":"Lake Oswego",
    "sg:classifiers":[
        {
            "category":"Organizations",
            "subcategory":"Professional Association",
            "type":"Services"
        }
    ],
    "sg:phone":"+1 503 653 6625",
    "sg:postcode":"97034",
    "sg:province":"OR",
    "wof:name":"Friends Of Sabeel",
    "wof:placetype":"venue"
},
  "geometry": {"coordinates":[-122.67761299999999,45.420068],"type":"Point"}
}