{
  "type": "Feature",
  "properties": {
    "iso:country":"US",
    "sg:address":"19325 NW Emma Way",
    "sg:city":"Hillsboro",
    "sg:classifiers":[
        {
            "category":"Health Services",
            "subcategory":"Optometrist",
            "type":"Services"
        }
    ],
    "sg:phone":"+1 503 531 3540",
    "sg:postcode":"97124",
    "sg:province":"OR",
    "sg:website":"www.lenscrafters.com",
    "wof:name":"Lenscrafters",
    "wof:placetype":"venue"
},
  "geometry": {"coordinates":[-122.87772200000001,45.535572],"type":"Point"}
}