{
  "type": "Feature",
  "properties": {
    "addr:full":"1915 NE 33rd Ave Portland OR 97212",
    "addr:housenumber":"1915",
    "addr:postcode":"97212",
    "addr:street":"Ne 33Rd Ave",
    "iso:country":"US",
    "sg:address":"1915 NE 33rd Ave",
    "sg:city":"Portland",
    "sg:classifiers":[
        {
            "category":"Education",
            "subcategory":"School",
            "type":"Public Place"
        }
    ],
    "sg:phone":"+1 503 916 6480",
    "sg:postcode":"97212",
    "sg:province":"OR",
    "sg:tags":[
        "middle",
        "k-",
        "private"
    ],
    "sg:website":"http://www.pps.k12.or.us",
    "wof:name":"Fernwood Middle School",
    "wof:placetype":"venue"
},
  "geometry": {"coordinates":[-122.630662,45.536534],"type":"Point"}
}