{
  "type": "Feature",
  "properties": {
    "addr:full":"520 Wagon Trail Dr Jacksonville OR 97530",
    "addr:housenumber":"520",
    "addr:postcode":"97530",
    "addr:street":"Wagon Trail Dr",
    "iso:country":"US",
    "sg:address":"520 Wagon Trail Dr",
    "sg:city":"Jacksonville",
    "sg:classifiers":[
        {
            "category":"Building & Trades",
            "subcategory":"Electrical",
            "type":"Services"
        }
    ],
    "sg:phone":"+1 541 899 8897",
    "sg:postcode":"97530",
    "sg:province":"OR",
    "sg:tags":[
        "electrical",
        "contractor"
    ],
    "wof:name":"Landers Electric",
    "wof:placetype":"venue"
},
  "geometry": {"coordinates":[-122.992127,42.301649],"type":"Point"}
}