{
  "type": "Feature",
  "properties": {
    "iso:country":"US",
    "sg:address":"2330 Dellwood Dr",
    "sg:city":"Lake Oswego",
    "sg:classifiers":[
        {
            "category":"Banks & Credit Unions",
            "subcategory":"Investment Brokerage",
            "type":"Services"
        }
    ],
    "sg:phone":"+1 503 636 7215",
    "sg:postcode":"97034",
    "sg:province":"OR",
    "sg:tags":[
        "advisory",
        "financial"
    ],
    "wof:name":"Pqm Research",
    "wof:placetype":"venue"
},
  "geometry": {"coordinates":[-122.701964,45.400069],"type":"Point"}
}