{
  "type": "Feature",
  "properties": {
    "iso:country":"US",
    "sg:address":"19548 S Lyons Rd",
    "sg:city":"Oregon City",
    "sg:classifiers":[
        {
            "category":"Farming",
            "subcategory":"Livestock Farm",
            "type":"Manufacturing & Wholesale Goods"
        }
    ],
    "sg:phone":"+1 503 631 3421",
    "sg:postcode":"97045",
    "sg:province":"OR",
    "sg:tags":[
        "equine"
    ],
    "wof:name":"Jamestown Ranch",
    "wof:placetype":"venue"
},
  "geometry": {"coordinates":[-122.463268,45.305978],"type":"Point"}
}