{
  "type": "Feature",
  "properties": {
    "addr:full":"24690 Alsea Hwy Philomath OR 97370",
    "addr:postcode":"24690;97370",
    "addr:street":"Alsea Hwy",
    "iso:country":"US",
    "sg:address":"24690 Alsea Hwy",
    "sg:city":"Philomath",
    "sg:classifiers":[
        {
            "category":"Personal",
            "type":"Services"
        }
    ],
    "sg:phone":"+1 541 929 4444",
    "sg:postcode":"97370",
    "sg:province":"OR",
    "sg:tags":[
        "wedding",
        "chapel"
    ],
    "wof:name":"Greengable Gardens",
    "wof:placetype":"venue"
},
  "geometry": {"coordinates":[-123.390733,44.536369],"type":"Point"}
}