{
  "type": "Feature",
  "properties": {
    "iso:country":"US",
    "sg:address":"29757 Roberts Rd",
    "sg:city":"Shedd",
    "sg:classifiers":[
        {
            "category":"Building & Trades",
            "subcategory":"Landscaping Services",
            "type":"Services"
        }
    ],
    "sg:phone":"+1 541 491 3922",
    "sg:postcode":"97377",
    "sg:province":"OR",
    "sg:tags":[
        "landscape"
    ],
    "wof:name":"Cornerstone Contracting",
    "wof:placetype":"venue"
},
  "geometry": {"coordinates":[-123.083342,44.453042],"type":"Point"}
}