{
  "type": "Feature",
  "properties": {
    "addr:full":"1605 NE Broadway Street Portland OR 97232",
    "addr:housenumber":"1605",
    "addr:postcode":"97232",
    "addr:street":"Ne Broadway Street",
    "iso:country":"US",
    "sg:address":"1605 NE Broadway Street",
    "sg:city":"Portland",
    "sg:classifiers":[
        {
            "category":"Personal",
            "subcategory":"Hair Removal",
            "type":"Services"
        }
    ],
    "sg:phone":"+1 503 281 0311",
    "sg:postcode":"97232",
    "sg:province":"OR",
    "wof:name":"Broadway East Electrology",
    "wof:placetype":"venue"
},
  "geometry": {"coordinates":[-122.649372,45.535149],"type":"Point"}
}