{
  "type": "Feature",
  "properties": {
    "iso:country":"US",
    "sg:address":"431 Violet St",
    "sg:city":"Lebanon",
    "sg:classifiers":[
        {
            "category":"Social Services",
            "subcategory":"Child Care",
            "type":"Services"
        }
    ],
    "sg:phone":"+1 541 259 5977",
    "sg:postcode":"97355",
    "sg:province":"OR",
    "sg:tags":[
        "day"
    ],
    "wof:name":"Jungle Tots",
    "wof:placetype":"venue"
},
  "geometry": {"coordinates":[-122.914598,44.515897],"type":"Point"}
}