{
  "type": "Feature",
  "properties": {
    "iso:country":"US",
    "sg:address":"170 W Harbor St",
    "sg:city":"Warrenton",
    "sg:classifiers":[
        {
            "category":"Professional",
            "subcategory":"Management & Consulting",
            "type":"Services"
        }
    ],
    "sg:phone":"+1 503 861 0989",
    "sg:postcode":"97146",
    "sg:province":"OR",
    "sg:tags":[
        "retail",
        "direct",
        "sales"
    ],
    "wof:name":"Hooked On Java",
    "wof:placetype":"venue"
},
  "geometry": {"coordinates":[-123.927076,46.167],"type":"Point"}
}