{
  "type": "Feature",
  "properties": {
    "iso:country":"US",
    "sg:address":"9938 S Heinz Rd",
    "sg:city":"Canby",
    "sg:classifiers":[
        {
            "category":"Food & Beverages",
            "subcategory":"Fruits & Vegetables",
            "type":"Retail Goods"
        }
    ],
    "sg:phone":"+1 503 651 3307",
    "sg:postcode":"97013",
    "sg:province":"OR",
    "sg:tags":[
        "produce"
    ],
    "wof:name":"Schultz Farm",
    "wof:placetype":"venue"
},
  "geometry": {"coordinates":[-122.662977,45.192169],"type":"Point"}
}