{
  "type": "Feature",
  "properties": {
    "iso:country":"US",
    "sg:address":"8900 SW Burnham St",
    "sg:city":"Tigard",
    "sg:classifiers":[
        {
            "category":"Retail",
            "subcategory":"Laundry & Dry Cleaning",
            "type":"Services"
        }
    ],
    "sg:phone":"+1 503 598 9072",
    "sg:postcode":"97223",
    "sg:province":"OR",
    "sg:tags":[
        "cleaners",
        "rug",
        "carpet"
    ],
    "wof:name":"Cleaning Solution",
    "wof:placetype":"venue"
},
  "geometry": {"coordinates":[-122.767714,45.42666],"type":"Point"}
}