{
  "type": "Feature",
  "properties": {
    "iso:country":"US",
    "sg:address":"2211 NW York St",
    "sg:city":"Portland",
    "sg:classifiers":[
        {
            "category":"Retail",
            "subcategory":"Auto Repair",
            "type":"Services"
        }
    ],
    "sg:phone":"+1 503 228 3350",
    "sg:postcode":"97210",
    "sg:province":"OR",
    "sg:tags":[
        "general"
    ],
    "wof:name":"Autocraft Northwest",
    "wof:placetype":"venue"
},
  "geometry": {"coordinates":[-122.697025,45.539167],"type":"Point"}
}