{
  "type": "Feature",
  "properties": {
    "addr:full":"395 Howard Ave Eugene OR 97404",
    "addr:housenumber":"395",
    "addr:postcode":"97404",
    "addr:street":"Howard Ave",
    "iso:country":"US",
    "sg:address":"395 Howard Ave",
    "sg:city":"Eugene",
    "sg:classifiers":[
        {
            "category":"Professional",
            "subcategory":"Computer Services",
            "type":"Services"
        }
    ],
    "sg:phone":"+1 541 688 9553",
    "sg:postcode":"97404",
    "sg:province":"OR",
    "sg:tags":[
        "consulting",
        "related"
    ],
    "wof:name":"Simulated Reality Systems",
    "wof:placetype":"venue"
},
  "geometry": {"coordinates":[-123.130988,44.08804],"type":"Point"}
}