{
  "type": "Feature",
  "properties": {
    "iso:country":"US",
    "sg:address":"181 SW Birch St",
    "sg:city":"Pilot Rock",
    "sg:classifiers":[
        {
            "category":"Personal",
            "subcategory":"Beauty Salon",
            "type":"Services"
        }
    ],
    "sg:phone":"+1 541 443 2025",
    "sg:postcode":"97868",
    "sg:province":"OR",
    "wof:name":"Korner Kuts",
    "wof:placetype":"venue"
},
  "geometry": {"coordinates":[-118.835223,45.482273],"type":"Point"}
}