{
  "type": "Feature",
  "properties": {
    "addr:full":"1420 NW Lovejoy St Portland OR 97209",
    "addr:housenumber":"1420",
    "addr:postcode":"97209",
    "addr:street":"Nw Lovejoy St",
    "iso:country":"US",
    "sg:address":"1420 NW Lovejoy St",
    "sg:city":"Portland",
    "sg:classifiers":[
        {
            "category":"Communications",
            "type":"Services"
        },
        {
            "category":"Shopping",
            "subcategory":"Computers & Home Electronics",
            "type":"Retail Goods"
        }
    ],
    "sg:phone":"+1 503 241 7431",
    "sg:postcode":"97209",
    "sg:province":"OR",
    "sg:tags":[
        "sound",
        "television",
        "system",
        "equipment",
        "radio",
        "store"
    ],
    "wof:name":"National Instruments",
    "wof:placetype":"venue"
},
  "geometry": {"coordinates":[-122.685627,45.530057],"type":"Point"}
}