{
  "type": "Feature",
  "properties": {
    "iso:country":"US",
    "sg:address":"946 NE Hidden Valley Dr",
    "sg:city":"Bend",
    "sg:classifiers":[
        {
            "category":"Professional",
            "subcategory":"Accounting & Tax Preparation",
            "type":"Services"
        }
    ],
    "sg:phone":"+1 541 312 9400",
    "sg:postcode":"97701",
    "sg:province":"OR",
    "sg:tags":[
        "bookkeeping",
        "general"
    ],
    "wof:name":"Accounting By Computer",
    "wof:placetype":"venue"
},
  "geometry": {"coordinates":[-121.291313,44.078097],"type":"Point"}
}