{
  "type": "Feature",
  "properties": {
    "iso:country":"US",
    "sg:address":"510 E Pine St",
    "sg:city":"Central Point",
    "sg:classifiers":[
        {
            "category":"Banks & Credit Unions",
            "subcategory":"Bank",
            "type":"Services"
        }
    ],
    "sg:phone":"+1 541 664 5596",
    "sg:postcode":"97502",
    "sg:province":"OR",
    "sg:tags":[
        "national"
    ],
    "sg:website":"www.key.com",
    "wof:name":"Keybank",
    "wof:placetype":"venue"
},
  "geometry": {"coordinates":[-122.91300200000001,42.376099],"type":"Point"}
}