{
  "type": "Feature",
  "properties": {
    "addr:full":"5002 Commercial St SE Salem OR 97306",
    "addr:housenumber":"5002",
    "addr:postcode":"97306",
    "addr:street":"Commercial St Se",
    "iso:country":"US",
    "sg:address":"5002 Commercial St SE",
    "sg:city":"Salem",
    "sg:classifiers":[
        {
            "category":"Insurance",
            "subcategory":"Insurance Agent",
            "type":"Services"
        }
    ],
    "sg:phone":"+1 503 581 7835",
    "sg:postcode":"97306",
    "sg:province":"OR",
    "wof:name":"Farmers Insurance Group",
    "wof:placetype":"venue"
},
  "geometry": {"coordinates":[-123.03024499999999,44.882174],"type":"Point"}
}