{
  "type": "Feature",
  "properties": {
    "iso:country":"US",
    "sg:address":"1418 SW Ellis St",
    "sg:city":"Dallas",
    "sg:classifiers":[
        {
            "category":"Building & Trades",
            "subcategory":"Cleaning & Sanitation",
            "type":"Services"
        }
    ],
    "sg:phone":"+1 503 623 4201",
    "sg:postcode":"97338",
    "sg:province":"OR",
    "sg:tags":[
        "maintenance"
    ],
    "wof:name":"Zoom Broom Cleaning Service",
    "wof:placetype":"venue"
},
  "geometry": {"coordinates":[-123.32297,44.915252],"type":"Point"}
}