{
  "type": "Feature",
  "properties": {
    "addr:full":"18600 SE Stark St Portland OR 97233",
    "addr:postcode":"18600;97233",
    "addr:street":"Se Stark St",
    "iso:country":"US",
    "sg:address":"18600 SE Stark St",
    "sg:city":"Portland",
    "sg:classifiers":[
        {
            "category":"Building & Trades",
            "subcategory":"Cleaning & Sanitation",
            "type":"Services"
        }
    ],
    "sg:phone":"+1 503 492 0197",
    "sg:postcode":"97233",
    "sg:province":"OR",
    "sg:tags":[
        "house"
    ],
    "sg:website":"www.maidbrigade244.com",
    "wof:name":"Maid Brigade",
    "wof:placetype":"venue"
},
  "geometry": {"coordinates":[-122.47136500000001,45.519069],"type":"Point"}
}