{
  "type": "Feature",
  "properties": {
    "iso:country":"US",
    "sg:address":"15018 2nd St NE",
    "sg:city":"Aurora",
    "sg:classifiers":[
        {
            "category":"Landmark",
            "subcategory":"Historic",
            "type":"Public Place"
        }
    ],
    "sg:phone":"+1 503 678 5754",
    "sg:postcode":"97002",
    "sg:province":"OR",
    "sg:tags":[
        "historical"
    ],
    "wof:name":"Old Aurora Colony Museum The",
    "wof:placetype":"venue"
},
  "geometry": {"coordinates":[-122.754386,45.23173],"type":"Point"}
}