{
  "type": "Feature",
  "properties": {
    "iso:country":"US",
    "sg:address":"11940 SW Pacific Hwy",
    "sg:city":"Portland",
    "sg:classifiers":[
        {
            "category":"Shopping",
            "subcategory":"Jewelry",
            "type":"Retail Goods"
        },
        {
            "category":"Arts & Performance",
            "subcategory":"Music",
            "type":"Entertainment"
        },
        {
            "category":"Shopping",
            "subcategory":"Pawn Shop",
            "type":"Retail Goods"
        }
    ],
    "sg:phone":"+1 503 715 2925",
    "sg:postcode":"97223",
    "sg:province":"OR",
    "sg:tags":[
        "watch",
        "jeweler",
        "instrument",
        "pawnbroker",
        "musical"
    ],
    "sg:website":"http://www.tigardpawn4more.com",
    "wof:name":"Tigard Pawn 4 More",
    "wof:placetype":"venue"
},
  "geometry": {"coordinates":[-122.765533,45.433806],"type":"Point"}
}