{
  "type": "Feature",
  "properties": {
    "iso:country":"US",
    "sg:address":"4412 SW Cullen Blvd",
    "sg:city":"Portland",
    "sg:classifiers":[
        {
            "category":"Wholesale",
            "subcategory":"Drugs",
            "type":"Manufacturing & Wholesale Goods"
        }
    ],
    "sg:phone":"+1 503 244 1261",
    "sg:postcode":"97221",
    "sg:province":"OR",
    "sg:tags":[
        "decal"
    ],
    "wof:name":"Clark Decal Co",
    "wof:placetype":"venue"
},
  "geometry": {"coordinates":[-122.72232099999999,45.484089],"type":"Point"}
}