{
  "type": "Feature",
  "properties": {
    "iso:country":"US",
    "sg:address":"1120 E Main St",
    "sg:city":"Medford",
    "sg:classifiers":[
        {
            "category":"Wholesale",
            "subcategory":"Office Equipment",
            "type":"Manufacturing & Wholesale Goods"
        }
    ],
    "sg:phone":"+1 541 779 1251",
    "sg:postcode":"97504",
    "sg:province":"OR",
    "sg:tags":[
        "machine",
        "duplicating",
        "copying"
    ],
    "wof:name":"Superior Office Systems",
    "wof:placetype":"venue"
},
  "geometry": {"coordinates":[-122.859598,42.327803],"type":"Point"}
}