{
  "type": "Feature",
  "properties": {
    "addr:full":"205 SE M L King Blvd Ste 200 Portland OR 97214",
    "addr:housenumber":"205",
    "addr:postcode":"97214",
    "addr:street":"Se M L King Blvd Ste 200",
    "iso:country":"US",
    "sg:address":"205 SE M L King Blvd Ste 200",
    "sg:city":"Portland",
    "sg:classifiers":[
        {
            "category":"Manufacturing",
            "subcategory":"Building Materials",
            "type":"Manufacturing & Wholesale Goods"
        }
    ],
    "sg:phone":"+1 503 872 9242",
    "sg:postcode":"97214",
    "sg:province":"OR",
    "sg:tags":[
        "concrete",
        "products-wholesale",
        "manufacturer"
    ],
    "wof:name":"Zymark Inc",
    "wof:placetype":"venue"
},
  "geometry": {"coordinates":[-122.66177399999999,45.521486],"type":"Point"}
}