{
  "type": "Feature",
  "properties": {
    "iso:country":"US",
    "sg:address":"12435 NW Groveshire Ave",
    "sg:city":"Banks",
    "sg:classifiers":[
        {
            "category":"Professional",
            "subcategory":"Detective & Security Services",
            "type":"Services"
        }
    ],
    "sg:phone":"+1 503 324 0423",
    "sg:postcode":"97106",
    "sg:province":"OR",
    "sg:tags":[
        "information",
        "bureau"
    ],
    "wof:name":"Matt'n Mel's Sewer Scoping Services, Inc.",
    "wof:placetype":"venue"
},
  "geometry": {"coordinates":[-123.108019,45.609956],"type":"Point"}
}