{
  "type": "Feature",
  "properties": {
    "addr:full":"9410 SW 313th Ave Cornelius OR 97113",
    "addr:housenumber":"9410",
    "addr:postcode":"97113",
    "addr:street":"Sw 313Th Ave",
    "iso:country":"US",
    "sg:address":"9410 SW 313th Ave",
    "sg:city":"Cornelius",
    "sg:classifiers":[
        {
            "category":"Building & Trades",
            "subcategory":"Cleaning & Sanitation",
            "type":"Services"
        }
    ],
    "sg:phone":"+1 503 544 6270",
    "sg:postcode":"97113",
    "sg:province":"OR",
    "sg:tags":[
        "maintenance"
    ],
    "wof:name":"Rnc Janitorial Service",
    "wof:placetype":"venue"
},
  "geometry": {"coordinates":[-122.99961999999999,45.451811],"type":"Point"}
}