{
  "type": "Feature",
  "properties": {
    "iso:country":"US",
    "sg:address":"2412 SW Wickiup Ave",
    "sg:city":"Redmond",
    "sg:classifiers":[
        {
            "category":"Building & Trades",
            "subcategory":"Construction",
            "type":"Services"
        }
    ],
    "sg:phone":"+1 541 548 9337",
    "sg:postcode":"97756",
    "sg:province":"OR",
    "sg:tags":[
        "drywall",
        "contractor"
    ],
    "wof:name":"Rays Drywall",
    "wof:placetype":"venue"
},
  "geometry": {"coordinates":[-121.1965,44.247458],"type":"Point"}
}