{
  "type": "Feature",
  "properties": {
    "iso:country":"US",
    "sg:address":"111 SE Washington St",
    "sg:city":"Hillsboro",
    "sg:classifiers":[
        {
            "category":"Building & Trades",
            "subcategory":"Cleaning & Sanitation",
            "type":"Services"
        }
    ],
    "sg:phone":"+1 503 648 8715",
    "sg:postcode":"97123",
    "sg:province":"OR",
    "sg:tags":[
        "real",
        "esta",
        "maintenance"
    ],
    "wof:name":"Washington Cnty Property Maint",
    "wof:placetype":"venue"
},
  "geometry": {"coordinates":[-122.989341,45.521415],"type":"Point"}
}