{
  "type": "Feature",
  "properties": {
    "addr:full":"29640 NW Evergreen Rd Hillsboro OR 97124",
    "addr:housenumber":"29640",
    "addr:postcode":"97124",
    "addr:street":"Nw Evergreen Rd",
    "iso:country":"US",
    "sg:address":"29640 NW Evergreen Rd",
    "sg:city":"Hillsboro",
    "sg:classifiers":[
        {
            "category":"Freight",
            "type":"Transportation"
        }
    ],
    "sg:phone":"+1 503 693 6652",
    "sg:postcode":"97124",
    "sg:province":"OR",
    "sg:tags":[
        "operator",
        "local",
        "trucking"
    ],
    "wof:name":"MCR Transport Inc",
    "wof:placetype":"venue"
},
  "geometry": {"coordinates":[-122.983164,45.549887],"type":"Point"}
}