{
  "type": "Feature",
  "properties": {
    "addr:full":"8386 SW Durham Rd Tigard OR 97224",
    "addr:housenumber":"8386",
    "addr:postcode":"97224",
    "addr:street":"Sw Durham Rd",
    "iso:country":"US",
    "sg:address":"8386 SW Durham Rd",
    "sg:city":"Tigard",
    "sg:classifiers":[
        {
            "category":"Professional",
            "subcategory":"Computer Services",
            "type":"Services"
        }
    ],
    "sg:phone":"+1 503 347 8363",
    "sg:postcode":"97224",
    "sg:province":"OR",
    "sg:tags":[
        "website",
        "design"
    ],
    "wof:name":"Edge One Solutions",
    "wof:placetype":"venue"
},
  "geometry": {"coordinates":[-122.763221,45.40422],"type":"Point"}
}