{
  "type": "Feature",
  "properties": {
    "iso:country":"US",
    "sg:address":"17012 Stanhelma Dr",
    "sg:city":"Gladstone",
    "sg:classifiers":[
        {
            "category":"Home & Garden",
            "subcategory":"Home Furnishings",
            "type":"Retail Goods"
        }
    ],
    "sg:phone":"+1 503 723 6235",
    "sg:postcode":"97027",
    "sg:province":"OR",
    "sg:tags":[
        "mirror"
    ],
    "wof:name":"Mirrors Unlimited",
    "wof:placetype":"venue"
},
  "geometry": {"coordinates":[-122.58275500000001,45.399798],"type":"Point"}
}