{
  "type": "Feature",
  "properties": {
    "addr:full":"909 SE 69th Ave Portland OR 97215",
    "addr:housenumber":"909",
    "addr:postcode":"97215",
    "addr:street":"Se 69Th Ave",
    "iso:country":"US",
    "sg:address":"909 SE 69th Ave",
    "sg:city":"Portland",
    "sg:classifiers":[
        {
            "category":"Professional",
            "subcategory":"Business Services",
            "type":"Services"
        }
    ],
    "sg:phone":"+1 503 261 8731",
    "sg:postcode":"97215",
    "sg:province":"OR",
    "sg:tags":[
        "architectural"
    ],
    "wof:name":"Allen & None Designs",
    "wof:placetype":"venue"
},
  "geometry": {"coordinates":[-122.59228299999999,45.516228],"type":"Point"}
}