{
  "type": "Feature",
  "properties": {
    "iso:country":"US",
    "sg:address":"1111 NE 102nd Ave",
    "sg:city":"Portland",
    "sg:classifiers":[
        {
            "category":"Building & Trades",
            "subcategory":"Locksmith",
            "type":"Services"
        }
    ],
    "sg:phone":"+1 503 914 4404",
    "sg:postcode":"97220",
    "sg:province":"OR",
    "sg:tags":[
        "key"
    ],
    "wof:name":"Am Pm Locksmith",
    "wof:placetype":"venue"
},
  "geometry": {"coordinates":[-122.558256,45.531307],"type":"Point"}
}