{
  "type": "Feature",
  "properties": {
    "addr:full":"1679 Fircrest Dr Lake Oswego OR 97034",
    "addr:housenumber":"1679",
    "addr:postcode":"dr;97034",
    "addr:street":"Fircrest",
    "iso:country":"US",
    "sg:address":"1679 Fircrest Dr",
    "sg:city":"Lake Oswego",
    "sg:classifiers":[
        {
            "category":"Professional",
            "type":"Services"
        }
    ],
    "sg:phone":"+1 503 635 5391",
    "sg:postcode":"97034",
    "sg:province":"OR",
    "wof:name":"King Fisher Ltd",
    "wof:placetype":"venue"
},
  "geometry": {"coordinates":[-122.677655,45.403041],"type":"Point"}
}