{
  "type": "Feature",
  "properties": {
    "addr:full":"12365 SW Conestoga Dr Beaverton OR 97008",
    "addr:housenumber":"12365",
    "addr:postcode":"97008",
    "addr:street":"Sw Conestoga Dr",
    "iso:country":"US",
    "sg:address":"12365 SW Conestoga Dr",
    "sg:city":"Beaverton",
    "sg:classifiers":[
        {
            "category":"Health Services",
            "subcategory":"Clinic",
            "type":"Services"
        }
    ],
    "sg:phone":"+1 503 784 1397",
    "sg:postcode":"97008",
    "sg:province":"OR",
    "sg:tags":[
        "home",
        "care"
    ],
    "wof:name":"Gentle Professional Caregivers",
    "wof:placetype":"venue"
},
  "geometry": {"coordinates":[-122.802789,45.447707],"type":"Point"}
}