{
  "type": "Feature",
  "properties": {
    "iso:country":"US",
    "sg:address":"12505 NW Cornell Rd",
    "sg:city":"Portland",
    "sg:classifiers":[
        {
            "category":"Professional",
            "subcategory":"Accounting & Tax Preparation",
            "type":"Services"
        }
    ],
    "sg:phone":"+1 503 626 6638",
    "sg:postcode":"97229",
    "sg:province":"OR",
    "sg:tags":[
        "accountant"
    ],
    "sg:website":"www.levinecpa.com",
    "wof:name":"Levine & Co PC",
    "wof:placetype":"venue"
},
  "geometry": {"coordinates":[-122.80589000000001,45.525551],"type":"Point"}
}