{
  "type": "Feature",
  "properties": {
    "addr:full":"207 W Ellendale Ave Dallas OR 97338",
    "addr:housenumber":"207",
    "addr:postcode":"97338",
    "addr:street":"W Ellendale Ave",
    "iso:country":"US",
    "sg:address":"207 W Ellendale Ave",
    "sg:city":"Dallas",
    "sg:classifiers":[
        {
            "category":"Building & Trades",
            "subcategory":"Construction",
            "type":"Services"
        }
    ],
    "sg:phone":"+1 503 623 6959",
    "sg:postcode":"97338",
    "sg:province":"OR",
    "sg:tags":[
        "residential",
        "nonresidential"
    ],
    "wof:name":"Reed Beardsley",
    "wof:placetype":"venue"
},
  "geometry": {"coordinates":[-123.31566599999999,44.9289],"type":"Point"}
}