{
  "type": "Feature",
  "properties": {
    "addr:full":"19988 State Hwy 99E NE Aurora OR 97002",
    "addr:housenumber":"19988",
    "addr:postcode":"97002",
    "addr:street":"State Hwy 99E Ne",
    "iso:country":"US",
    "sg:address":"19988 State Hwy 99E NE",
    "sg:city":"Aurora",
    "sg:classifiers":[
        {
            "category":"Shopping",
            "subcategory":"Jewelry",
            "type":"Retail Goods"
        }
    ],
    "sg:phone":"+1 503 678 2513",
    "sg:postcode":"97002",
    "sg:province":"OR",
    "sg:tags":[
        "diamond"
    ],
    "wof:name":"Blue Diamond Receiving Station",
    "wof:placetype":"venue"
},
  "geometry": {"coordinates":[-122.775379,45.206344],"type":"Point"}
}