{
  "type": "Feature",
  "properties": {
    "iso:country":"US",
    "sg:address":"325 E Main St",
    "sg:city":"John Day",
    "sg:classifiers":[
        {
            "category":"Building & Trades",
            "subcategory":"Landscaping Services",
            "type":"Services"
        }
    ],
    "sg:phone":"+1 541 575 3990",
    "sg:postcode":"97845",
    "sg:province":"OR",
    "sg:tags":[
        "lawn",
        "care"
    ],
    "wof:name":"Bryans Lawn Care",
    "wof:placetype":"venue"
},
  "geometry": {"coordinates":[-118.948897,44.416192],"type":"Point"}
}