{
  "type": "Feature",
  "properties": {
    "addr:full":"854 SE 5th St Newport OR 97365",
    "addr:housenumber":"854",
    "addr:postcode":"97365",
    "addr:street":"Se 5Th St",
    "iso:country":"US",
    "sg:address":"854 SE 5th St",
    "sg:city":"Newport",
    "sg:classifiers":[
        {
            "category":"Professional",
            "subcategory":"Advertising",
            "type":"Services"
        }
    ],
    "sg:phone":"+1 541 265 8835",
    "sg:postcode":"97365",
    "sg:province":"OR",
    "wof:name":"B & W Advertising",
    "wof:placetype":"venue"
},
  "geometry": {"coordinates":[-124.04092900000001,44.63166],"type":"Point"}
}