{
  "type": "Feature",
  "properties": {
    "addr:full":"6708 SE Milwaukie Ave Portland OR 97202",
    "addr:housenumber":"6708",
    "addr:postcode":"97202",
    "addr:street":"Se Milwaukie Ave",
    "iso:country":"US",
    "sg:address":"6708 SE Milwaukie Ave",
    "sg:city":"Portland",
    "sg:classifiers":[
        {
            "category":"Restaurant",
            "type":"Food & Drink"
        }
    ],
    "sg:phone":"+1 503 235 5797",
    "sg:postcode":"97202",
    "sg:province":"OR",
    "sg:tags":[
        "lounge",
        "eating"
    ],
    "wof:name":"Limelight Restaurant & Lounge",
    "wof:placetype":"venue"
},
  "geometry": {"coordinates":[-122.648673,45.47425],"type":"Point"}
}