{
  "type": "Feature",
  "properties": {
    "iso:country":"US",
    "sg:address":"1 N Center Court St",
    "sg:city":"Portland",
    "sg:classifiers":[
        {
            "category":"Professional",
            "subcategory":"Business Services",
            "type":"Services"
        }
    ],
    "sg:phone":"+1 503 235 2585",
    "sg:postcode":"97227",
    "sg:province":"OR",
    "sg:tags":[
        "event"
    ],
    "wof:name":"Coast To Coast Event Svc",
    "wof:placetype":"venue"
},
  "geometry": {"coordinates":[-122.667773,45.533052],"type":"Point"}
}