{
  "type": "Feature",
  "properties": {
    "iso:country":"US",
    "sg:address":"6350 Zena Rd NW",
    "sg:city":"Salem",
    "sg:classifiers":[
        {
            "category":"Professional",
            "type":"Services"
        }
    ],
    "sg:phone":"+1 503 363 0892",
    "sg:postcode":"97304",
    "sg:province":"OR",
    "sg:tags":[
        "establishment"
    ],
    "wof:name":"KNOX/Douglas Inc",
    "wof:placetype":"venue"
},
  "geometry": {"coordinates":[-123.153852,45.030374],"type":"Point"}
}