{
  "type": "Feature",
  "properties": {
    "addr:full":"890 Promontory Pl SE Salem OR 97302",
    "addr:housenumber":"890",
    "addr:postcode":"97302",
    "addr:street":"Promontory Pl Se",
    "iso:country":"US",
    "sg:address":"890 Promontory Pl SE",
    "sg:city":"Salem",
    "sg:classifiers":[
        {
            "category":"Professional",
            "subcategory":"Art Services",
            "type":"Services"
        }
    ],
    "sg:phone":"+1 503 370 9377",
    "sg:postcode":"97302",
    "sg:province":"OR",
    "sg:tags":[
        "organization",
        "graphic",
        "religious",
        "designer"
    ],
    "sg:website":"www.churchartworks.com",
    "wof:name":"Church Art Works The",
    "wof:placetype":"venue"
},
  "geometry": {"coordinates":[-123.03686399999999,44.89587],"type":"Point"}
}