{
  "type": "Feature",
  "properties": {
    "iso:country":"US",
    "sg:address":"52484 Lost Ponderosa Rd",
    "sg:city":"La Pine",
    "sg:classifiers":[
        {
            "category":"Wholesale",
            "subcategory":"Machinery & Supplies",
            "type":"Manufacturing & Wholesale Goods"
        }
    ],
    "sg:phone":"+1 541 536 3236",
    "sg:postcode":"97739",
    "sg:province":"OR",
    "sg:tags":[
        "equipment",
        "establishment"
    ],
    "wof:name":"Buscher Engines",
    "wof:placetype":"venue"
},
  "geometry": {"coordinates":[-121.505523,43.708007],"type":"Point"}
}