{
  "type": "Feature",
  "properties": {
    "iso:country":"US",
    "sg:address":"767 Willamette St",
    "sg:city":"Eugene",
    "sg:classifiers":[
        {
            "category":"Banks & Credit Unions",
            "subcategory":"Investment Brokerage",
            "type":"Services"
        }
    ],
    "sg:phone":"+1 541 345 5669",
    "sg:postcode":"97401",
    "sg:province":"OR",
    "sg:tags":[
        "advisory",
        "security"
    ],
    "wof:name":"Progressive Investment Mgt",
    "wof:placetype":"venue"
},
  "geometry": {"coordinates":[-123.092661,44.051783],"type":"Point"}
}