{
  "type": "Feature",
  "properties": {
    "addr:full":"1545 SE Division St Portland OR 97202",
    "addr:housenumber":"1545",
    "addr:postcode":"97202",
    "addr:street":"Se Division St",
    "iso:country":"US",
    "sg:address":"1545 SE Division St",
    "sg:city":"Portland",
    "sg:classifiers":[
        {
            "category":"Professional",
            "type":"Services"
        }
    ],
    "sg:phone":"+1 503 235 2819",
    "sg:postcode":"97202",
    "sg:province":"OR",
    "wof:name":"Spin Back Audio",
    "wof:placetype":"venue"
},
  "geometry": {"coordinates":[-122.64944199999999,45.504911],"type":"Point"}
}