{
  "type": "Feature",
  "properties": {
    "iso:country":"US",
    "sg:address":"359 Glen Creek Rd NW",
    "sg:city":"Salem",
    "sg:classifiers":[
        {
            "category":"Education",
            "subcategory":"Special Training",
            "type":"Public Place"
        }
    ],
    "sg:phone":"+1 503 315 8700",
    "sg:postcode":"97304",
    "sg:province":"OR",
    "sg:tags":[
        "tutoring"
    ],
    "wof:name":"Reading Works",
    "wof:placetype":"venue"
},
  "geometry": {"coordinates":[-123.048546,44.950248],"type":"Point"}
}