{
  "type": "Feature",
  "properties": {
    "iso:country":"US",
    "sg:address":"5892 Main St",
    "sg:city":"Springfield",
    "sg:classifiers":[
        {
            "category":"Health Services",
            "subcategory":"Doctor",
            "type":"Services"
        }
    ],
    "sg:phone":"+1 541 741 7800",
    "sg:postcode":"97478",
    "sg:province":"OR",
    "sg:tags":[
        "dentist"
    ],
    "wof:name":"Thurston Family Dental",
    "wof:placetype":"venue"
},
  "geometry": {"coordinates":[-122.925923,44.045734],"type":"Point"}
}