{
  "type": "Feature",
  "properties": {
    "iso:country":"US",
    "sg:address":"24095 SW Scholls Ferry Rd",
    "sg:city":"Hillsboro",
    "sg:classifiers":[
        {
            "category":"Building & Trades",
            "subcategory":"Landscaping Services",
            "type":"Services"
        }
    ],
    "sg:phone":"+1 503 628 3112",
    "sg:postcode":"97123",
    "sg:province":"OR",
    "wof:name":"Roots & Shoots",
    "wof:placetype":"venue"
},
  "geometry": {"coordinates":[-122.92227699999999,45.408057],"type":"Point"}
}