{
  "type": "Feature",
  "properties": {
    "iso:country":"US",
    "sg:address":"18158 NW Stonehedge Ct",
    "sg:city":"Beaverton",
    "sg:classifiers":[
        {
            "category":"Professional",
            "type":"Services"
        }
    ],
    "sg:phone":"+1 503 307 5148",
    "sg:postcode":"97006",
    "sg:province":"OR",
    "wof:name":"Laqua Designs",
    "wof:placetype":"venue"
},
  "geometry": {"coordinates":[-122.863226,45.526546],"type":"Point"}
}