{
  "type": "Feature",
  "properties": {
    "iso:country":"US",
    "sg:address":"3990 Collins Way",
    "sg:city":"Lake Oswego",
    "sg:classifiers":[
        {
            "category":"Wholesale",
            "subcategory":"Computers",
            "type":"Manufacturing & Wholesale Goods"
        }
    ],
    "sg:phone":"+1 503 636 6019",
    "sg:postcode":"97035",
    "sg:province":"OR",
    "wof:name":"Westcom Computers",
    "wof:placetype":"venue"
},
  "geometry": {"coordinates":[-122.71700300000001,45.414001],"type":"Point"}
}