{
  "type": "Feature",
  "properties": {
    "iso:country":"US",
    "sg:address":"1500 NW Bethany Blvd Ste 155",
    "sg:city":"Beaverton",
    "sg:classifiers":[
        {
            "category":"Professional",
            "subcategory":"Employment Agencies",
            "type":"Services"
        }
    ],
    "sg:phone":"+1 503 614 8882",
    "sg:postcode":"97006",
    "sg:province":"OR",
    "sg:website":"www.appleone.com",
    "wof:name":"AppleOne Employment Services",
    "wof:placetype":"venue"
},
  "geometry": {"coordinates":[-122.843056,45.529632],"type":"Point"}
}