{
  "type": "Feature",
  "properties": {
    "iso:country":"US",
    "sg:address":"2575 NE Kathryn St",
    "sg:city":"Hillsboro",
    "sg:classifiers":[
        {
            "category":"Manufacturing",
            "subcategory":"Metals",
            "type":"Manufacturing & Wholesale Goods"
        }
    ],
    "sg:phone":"+1 503 648 3525",
    "sg:postcode":"97124",
    "sg:province":"OR",
    "sg:tags":[
        "screw",
        "product",
        "business",
        "services-household",
        "mfg",
        "machine",
        "organizing"
    ],
    "wof:name":"Agenda 1 Industries Inc.",
    "wof:placetype":"venue"
},
  "geometry": {"coordinates":[-122.95717500000001,45.538809],"type":"Point"}
}