{
  "type": "Feature",
  "properties": {
    "iso:country":"US",
    "sg:address":"2717 NE Dunckley St",
    "sg:city":"Portland",
    "sg:classifiers":[
        {
            "category":"Real Estate",
            "subcategory":"Developer",
            "type":"Services"
        }
    ],
    "sg:phone":"+1 503 970 5663",
    "sg:postcode":"97212",
    "sg:province":"OR",
    "wof:name":"JBW Development",
    "wof:placetype":"venue"
},
  "geometry": {"coordinates":[-122.63815200000001,45.552075],"type":"Point"}
}