{
  "type": "Feature",
  "properties": {
    "addr:full":"310 High St NE Salem OR 97301",
    "addr:housenumber":"310",
    "addr:postcode":"97301",
    "addr:street":"High St Ne",
    "iso:country":"US",
    "sg:address":"310 High St NE",
    "sg:city":"Salem",
    "sg:classifiers":[
        {
            "category":"Utilities",
            "subcategory":"Electric",
            "type":"Services"
        }
    ],
    "sg:phone":"+1 503 399 7717",
    "sg:postcode":"97301",
    "sg:province":"OR",
    "sg:tags":[
        "company"
    ],
    "wof:name":"Portland General Electric",
    "wof:placetype":"venue"
},
  "geometry": {"coordinates":[-123.03550199999999,44.942749],"type":"Point"}
}