{
  "type": "Feature",
  "properties": {
    "iso:country":"US",
    "sg:address":"322 Newtown St",
    "sg:city":"Medford",
    "sg:classifiers":[
        {
            "category":"Food & Beverages",
            "subcategory":"Groceries & Convenience Stores",
            "type":"Retail Goods"
        }
    ],
    "sg:phone":"+1 541 857 1121",
    "sg:postcode":"97501",
    "sg:province":"OR",
    "wof:name":"Low Carb Habit Grocery Medf",
    "wof:placetype":"venue"
},
  "geometry": {"coordinates":[-122.880037,42.319363],"type":"Point"}
}