{
  "type": "Feature",
  "properties": {
    "iso:country":"US",
    "sg:address":"3380 NE 15th Ave",
    "sg:city":"Hillsboro",
    "sg:classifiers":[
        {
            "category":"Autos & Motor Vehicles",
            "subcategory":"Automobile Sales",
            "type":"Retail Goods"
        },
        {
            "category":"Autos & Motor Vehicles",
            "subcategory":"Auto Supplies",
            "type":"Retail Goods"
        }
    ],
    "sg:phone":"+1 503 648 3186",
    "sg:postcode":"97124",
    "sg:province":"OR",
    "sg:tags":[
        "parts",
        "accessory",
        "equipment",
        "part",
        "electrical",
        "accessories-wholesale",
        "manufacturer"
    ],
    "sg:website":"http://www.napaonline.com",
    "wof:name":"Hillsboro Auto Parts",
    "wof:placetype":"venue"
},
  "geometry": {"coordinates":[-122.966393,45.548924],"type":"Point"}
}