{
  "type": "Feature",
  "properties": {
    "iso:country":"US",
    "sg:address":"29718 SE Shady Oak Dr",
    "sg:city":"Corvallis",
    "sg:classifiers":[
        {
            "category":"Shopping",
            "type":"Retail Goods"
        }
    ],
    "sg:phone":"+1 541 231 3135",
    "sg:postcode":"97333",
    "sg:province":"OR",
    "sg:tags":[
        "merchandise"
    ],
    "wof:name":"Owl Creek Golf Shop",
    "wof:placetype":"venue"
},
  "geometry": {"coordinates":[-123.19811,44.543294],"type":"Point"}
}