{
  "type": "Feature",
  "properties": {
    "addr:full":"4625 Cordon Rd NE Salem OR 97305",
    "addr:housenumber":"4625",
    "addr:postcode":"97305",
    "addr:street":"Cordon Rd Ne",
    "iso:country":"US",
    "sg:address":"4625 Cordon Rd NE",
    "sg:city":"Salem",
    "sg:classifiers":[
        {
            "category":"Organizations",
            "subcategory":"Religious Organization",
            "type":"Services"
        }
    ],
    "sg:phone":"+1 503 856 9700",
    "sg:postcode":"97305",
    "sg:province":"OR",
    "sg:tags":[
        "church"
    ],
    "wof:name":"Salem Spanish Seventh Day",
    "wof:placetype":"venue"
},
  "geometry": {"coordinates":[-122.954095,44.99057],"type":"Point"}
}