{
  "type": "Feature",
  "properties": {
    "addr:full":"20607 State Hwy 213 Oregon City OR 97045",
    "addr:housenumber":"20607",
    "addr:postcode":"97045",
    "addr:street":"State Hwy 213",
    "iso:country":"US",
    "sg:address":"20607 State Hwy 213",
    "sg:city":"Oregon City",
    "sg:classifiers":[
        {
            "category":"Organizations",
            "subcategory":"Religious Organization",
            "type":"Services"
        }
    ],
    "sg:phone":"+1 503 655 5030",
    "sg:postcode":"97045",
    "sg:province":"OR",
    "sg:tags":[
        "church"
    ],
    "wof:name":"Descent of The Holy Spirit Rom",
    "wof:placetype":"venue"
},
  "geometry": {"coordinates":[-122.56644900000001,45.30626],"type":"Point"}
}