{
  "type": "Feature",
  "properties": {
    "addr:full":"17757 Schalit Way Lake Oswego OR 97035",
    "addr:housenumber":"17757",
    "addr:postcode":"97035",
    "addr:street":"Schalit Way",
    "iso:country":"US",
    "sg:address":"17757 Schalit Way",
    "sg:city":"Lake Oswego",
    "sg:classifiers":[
        {
            "category":"Professional",
            "subcategory":"Engineering",
            "type":"Services"
        }
    ],
    "sg:phone":"+1 503 636 0320",
    "sg:postcode":"97035",
    "sg:province":"OR",
    "sg:tags":[
        "consulting",
        "computing",
        "research"
    ],
    "wof:name":"Bart-Masseycom LLC",
    "wof:placetype":"venue"
},
  "geometry": {"coordinates":[-122.727693,45.399286],"type":"Point"}
}