{
  "type": "Feature",
  "properties": {
    "iso:country":"US",
    "sg:address":"2650 NW Highland Dr",
    "sg:city":"Corvallis",
    "sg:classifiers":[
        {
            "category":"Organizations",
            "subcategory":"Religious Organization",
            "type":"Services"
        }
    ],
    "sg:phone":"+1 541 753 2816",
    "sg:postcode":"97330",
    "sg:province":"OR",
    "sg:tags":[
        "church"
    ],
    "wof:name":"Shepherd Of The Valley",
    "wof:placetype":"venue"
},
  "geometry": {"coordinates":[-123.262663,44.59394],"type":"Point"}
}