{
  "type": "Feature",
  "properties": {
    "iso:country":"US",
    "sg:address":"20300 SE Morrison Ter",
    "sg:city":"Gresham",
    "sg:classifiers":[
        {
            "category":"Communications",
            "subcategory":"Film & Video Production",
            "type":"Services"
        }
    ],
    "sg:phone":"+1 503 492 1504",
    "sg:postcode":"97030",
    "sg:province":"OR",
    "sg:tags":[
        "taping"
    ],
    "wof:name":"J Video Productions",
    "wof:placetype":"venue"
},
  "geometry": {"coordinates":[-122.4547,45.516343],"type":"Point"}
}