{
  "type": "Feature",
  "properties": {
    "iso:country":"US",
    "sg:address":"4335 River Rd N",
    "sg:city":"Keizer",
    "sg:classifiers":[
        {
            "category":"Organizations",
            "subcategory":"Non-profit Organization",
            "type":"Services"
        }
    ],
    "sg:phone":"+1 503 463 8563",
    "sg:postcode":"97303",
    "sg:province":"OR",
    "sg:tags":[
        "alternative",
        "abortion"
    ],
    "sg:website":"www.ortl.org",
    "wof:name":"Oregon Right-To-Life",
    "wof:placetype":"venue"
},
  "geometry": {"coordinates":[-123.026678,44.987069],"type":"Point"}
}