{
  "type": "Feature",
  "properties": {
    "addr:full":"3687 Table Rock Rd Medford OR 97504",
    "addr:housenumber":"3687",
    "addr:postcode":"97504",
    "addr:street":"Table Rock Rd",
    "iso:country":"US",
    "sg:address":"3687 Table Rock Rd",
    "sg:city":"Medford",
    "sg:classifiers":[
        {
            "category":"Building & Trades",
            "subcategory":"Cleaning & Sanitation",
            "type":"Services"
        }
    ],
    "sg:phone":"+1 541 665 5136",
    "sg:postcode":"97504",
    "sg:province":"OR",
    "wof:name":"Pro Cleaning Service",
    "wof:placetype":"venue"
},
  "geometry": {"coordinates":[-122.88539,42.368718],"type":"Point"}
}