{
  "type": "Feature",
  "properties": {
    "iso:country":"US",
    "sg:address":"1835 SE Oak St",
    "sg:city":"Portland",
    "sg:classifiers":[
        {
            "category":"Communications",
            "subcategory":"Film & Video Production",
            "type":"Services"
        }
    ],
    "sg:phone":"+1 503 246 9500",
    "sg:postcode":"97214",
    "sg:province":"OR",
    "sg:tags":[
        "taping"
    ],
    "wof:name":"Ed Belmudes Productions",
    "wof:placetype":"venue"
},
  "geometry": {"coordinates":[-122.64677,45.520108],"type":"Point"}
}