{
  "type": "Feature",
  "properties": {
    "iso:country":"US",
    "sg:address":"743 Lancaster Dr NE",
    "sg:city":"Salem",
    "sg:classifiers":[
        {
            "category":"Home & Garden",
            "subcategory":"Furniture",
            "type":"Retail Goods"
        }
    ],
    "sg:phone":"+1 503 585 5776",
    "sg:postcode":"97301",
    "sg:province":"OR",
    "sg:tags":[
        "mattress"
    ],
    "wof:name":"Sleep Country USA",
    "wof:placetype":"venue"
},
  "geometry": {"coordinates":[-122.983102,44.940158],"type":"Point"}
}