{
  "type": "Feature",
  "properties": {
    "addr:full":"730 SW 4th St Corvallis OR 97333",
    "addr:housenumber":"730",
    "addr:postcode":"97333",
    "addr:street":"Sw 4Th St",
    "iso:country":"US",
    "sg:address":"730 SW 4th St",
    "sg:city":"Corvallis",
    "sg:classifiers":[
        {
            "category":"Professional",
            "subcategory":"Lawyer & Legal Services",
            "type":"Services"
        }
    ],
    "sg:phone":"+1 541 757 1229",
    "sg:postcode":"97333",
    "sg:province":"OR",
    "sg:tags":[
        "attorney"
    ],
    "wof:name":"Gregory J Christensen",
    "wof:placetype":"venue"
},
  "geometry": {"coordinates":[-123.265185,44.558443],"type":"Point"}
}