{
  "type": "Feature",
  "properties": {
    "iso:country":"US",
    "sg:address":"461 SW 169th Pl",
    "sg:city":"Gresham",
    "sg:classifiers":[
        {
            "category":"Building & Trades",
            "subcategory":"Construction",
            "type":"Services"
        }
    ],
    "sg:phone":"+1 503 251 7511",
    "sg:postcode":"97006",
    "sg:province":"OR",
    "sg:tags":[
        "home",
        "builder"
    ],
    "wof:name":"Pacific Western Homes",
    "wof:placetype":"venue"
},
  "geometry": {"coordinates":[-122.851437,45.516909],"type":"Point"}
}