{
  "type": "Feature",
  "properties": {
    "iso:country":"US",
    "sg:address":"17017 Canal Cir",
    "sg:city":"Lake Oswego",
    "sg:classifiers":[
        {
            "category":"Building & Trades",
            "subcategory":"Construction",
            "type":"Services"
        }
    ],
    "sg:phone":"+1 503 319 0520",
    "sg:postcode":"97035",
    "sg:province":"OR",
    "sg:tags":[
        "residential"
    ],
    "wof:name":"Gfc Construction Inc",
    "wof:placetype":"venue"
},
  "geometry": {"coordinates":[-122.717418,45.403234],"type":"Point"}
}