{
  "type": "Feature",
  "properties": {
    "iso:country":"US",
    "sg:address":"321 2nd St",
    "sg:city":"Lake Oswego",
    "sg:classifiers":[
        {
            "category":"Personal",
            "subcategory":"Beauty Salon",
            "type":"Services"
        }
    ],
    "sg:phone":"+1 503 635 3959",
    "sg:postcode":"97034",
    "sg:province":"OR",
    "sg:tags":[
        "hair"
    ],
    "wof:name":"Lake Salon the",
    "wof:placetype":"venue"
},
  "geometry": {"coordinates":[-122.666,45.419201],"type":"Point"}
}