{
  "type": "Feature",
  "properties": {
    "iso:country":"US",
    "sg:address":"3364 Crater Lake Ave",
    "sg:city":"Medford",
    "sg:classifiers":[
        {
            "category":"Autos & Motor Vehicles",
            "subcategory":"Automobile Sales",
            "type":"Retail Goods"
        }
    ],
    "sg:phone":"+1 541 773 2490",
    "sg:postcode":"97504",
    "sg:province":"OR",
    "sg:tags":[
        "classic"
    ],
    "wof:name":"Chuck Holt & Sons Classic",
    "wof:placetype":"venue"
},
  "geometry": {"coordinates":[-122.85555600000001,42.364608],"type":"Point"}
}