{
  "type": "Feature",
  "properties": {
    "addr:full":"6640 SW Redwood Lane Portland OR 97224",
    "addr:housenumber":"6640",
    "addr:postcode":"97224",
    "addr:street":"Sw Redwood Lane",
    "iso:country":"US",
    "sg:address":"6640 SW Redwood Lane",
    "sg:city":"Portland",
    "sg:classifiers":[
        {
            "category":"Health Services",
            "subcategory":"Doctor",
            "type":"Services"
        }
    ],
    "sg:phone":"+1 503 620 7358",
    "sg:postcode":"97224",
    "sg:province":"OR",
    "sg:tags":[
        "medicine",
        "internal"
    ],
    "sg:website":"www.theportlandclinic.com",
    "wof:name":"Grewal Harminder MD",
    "wof:placetype":"venue"
},
  "geometry": {"coordinates":[-122.746262,45.409552],"type":"Point"}
}