{
  "type": "Feature",
  "properties": {
    "iso:country":"US",
    "sg:address":"90554 Highway 99 N",
    "sg:city":"Eugene",
    "sg:classifiers":[
        {
            "category":"Shopping",
            "subcategory":"Bicycles & Sporting Goods",
            "type":"Retail Goods"
        }
    ],
    "sg:phone":"+1 541 689 2920",
    "sg:postcode":"97402",
    "sg:province":"OR",
    "sg:tags":[
        "equipment",
        "supply",
        "archery"
    ],
    "sg:website":"http://www.diamondarchery.com",
    "wof:name":"Diamond Archery",
    "wof:placetype":"venue"
},
  "geometry": {"coordinates":[-123.20031,44.145378],"type":"Point"}
}