{
  "type": "Feature",
  "properties": {
    "addr:full":"3006 NE 156th Ave Portland OR 97230",
    "addr:housenumber":"3006",
    "addr:postcode":"97230",
    "addr:street":"Ne 156Th Ave",
    "iso:country":"US",
    "sg:address":"3006 NE 156th Ave",
    "sg:city":"Portland",
    "sg:classifiers":[
        {
            "category":"Home & Garden",
            "subcategory":"Carpets & Floor Coverings",
            "type":"Retail Goods"
        }
    ],
    "sg:phone":"+1 503 376 6587",
    "sg:postcode":"97230",
    "sg:province":"OR",
    "sg:tags":[
        "carpeting"
    ],
    "wof:name":"Easy Carpet and Upholstery Cleaning",
    "wof:placetype":"venue"
},
  "geometry": {"coordinates":[-122.501335,45.544684],"type":"Point"}
}