{
  "type": "Feature",
  "properties": {
    "addr:city":"Astoria",
    "addr:full":"446 W Marine Dr Astoria, Or 97103",
    "addr:house_number":"446",
    "addr:housenumber":"446",
    "addr:phone":"+1 503-325-5323",
    "addr:postcode":"97103",
    "addr:road":"W Marine Dr",
    "addr:state":"OR",
    "addr:street":"W Marine Dr",
    "iso:country":"US",
    "sg:address":"446 W Marine Dr",
    "sg:city":"Astoria",
    "sg:classifiers":[
        {
            "category":"Museum",
            "type":"Entertainment"
        }
    ],
    "sg:phone":"+1 503 325 5323",
    "sg:postcode":"97103",
    "sg:province":"OR",
    "wof:airports":[
        102532025
    ],
    "wof:name":"Astoria Railroad Preservation",
    "wof:placetype":"venue"
},
  "geometry": {"coordinates":[-123.83356999999999,46.18914],"type":"Point"}
}