{
  "type": "Feature",
  "properties": {
    "iso:country":"US",
    "sg:address":"446 W Marine Dr",
    "sg:city":"Astoria",
    "sg:classifiers":[
        {
            "category":"Museum",
            "type":"Entertainment"
        }
    ],
    "sg:phone":"+1 503 325 5323",
    "sg:postcode":"97103",
    "sg:province":"OR",
    "wof:name":"Astoria Railroad Preservation",
    "wof:placetype":"venue"
},
  "geometry": {"coordinates":[-123.856706,46.185681],"type":"Point"}
}