{
  "type": "Feature",
  "properties": {
    "iso:country":"US",
    "sg:address":"4875 Justice Way S",
    "sg:city":"Salem",
    "sg:classifiers":[
        {
            "category":"Social Services",
            "subcategory":"Child Care",
            "type":"Services"
        }
    ],
    "sg:phone":"+1 503 363 2127",
    "sg:postcode":"97302",
    "sg:province":"OR",
    "wof:name":"Salem Child Development Ctr",
    "wof:placetype":"venue"
},
  "geometry": {"coordinates":[-123.073314,44.885313],"type":"Point"}
}