{
  "type": "Feature",
  "properties": {
    "addr:full":"5400 SE 84th Ave Portland OR 97266",
    "addr:postcode":"5400;97266",
    "addr:street":"Se 84Th Ave",
    "iso:country":"US",
    "sg:address":"5400 SE 84th Ave",
    "sg:city":"Portland",
    "sg:classifiers":[
        {
            "category":"Organizations",
            "subcategory":"Community Association",
            "type":"Services"
        }
    ],
    "sg:phone":"+1 503 777 6606",
    "sg:postcode":"97266",
    "sg:province":"OR",
    "sg:tags":[
        "fraternal"
    ],
    "wof:name":"Knights Of Pythias",
    "wof:placetype":"venue"
},
  "geometry": {"coordinates":[-122.576893,45.482237],"type":"Point"}
}