{
  "type": "Feature",
  "properties": {
    "iso:country":"US",
    "sg:address":"518 S Fir St",
    "sg:city":"Medford",
    "sg:classifiers":[
        {
            "category":"Building & Trades",
            "subcategory":"Construction",
            "type":"Services"
        }
    ],
    "sg:phone":"+1 541 944 7464",
    "sg:postcode":"97501",
    "sg:province":"OR",
    "sg:tags":[
        "carpentry",
        "contractor"
    ],
    "wof:name":"As You Wish Woodworking",
    "wof:placetype":"venue"
},
  "geometry": {"coordinates":[-122.869575,42.320504],"type":"Point"}
}