{
  "type": "Feature",
  "properties": {
    "iso:country":"US",
    "sg:address":"4725 SW Caldew St",
    "sg:city":"Portland",
    "sg:classifiers":[
        {
            "category":"Professional",
            "subcategory":"Management & Consulting",
            "type":"Services"
        }
    ],
    "sg:phone":"+1 503 293 5632",
    "sg:postcode":"97219",
    "sg:province":"OR",
    "sg:tags":[
        "business"
    ],
    "wof:name":"Navigator Consulting",
    "wof:placetype":"venue"
},
  "geometry": {"coordinates":[-122.725531,45.471805],"type":"Point"}
}