{
  "type": "Feature",
  "properties": {
    "iso:country":"US",
    "sg:address":"8303 NE Sandy Blvd",
    "sg:city":"Portland",
    "sg:classifiers":[
        {
            "category":"Restaurant",
            "type":"Food & Drink"
        }
    ],
    "sg:menulink":"http://www.allmenus.com/or/portland/60838-steamers-restaurant/menu/",
    "sg:phone":"+1 503 256 5211",
    "sg:postcode":"97220",
    "sg:province":"OR",
    "sg:tags":[
        "seafood",
        "american"
    ],
    "wof:name":"Steamers Restaurant",
    "wof:placetype":"venue"
},
  "geometry": {"coordinates":[-122.575954,45.553544],"type":"Point"}
}