{
  "type": "Feature",
  "properties": {
    "addr:full":"300 Liberty St SE Salem OR 97301",
    "addr:housenumber":"300",
    "addr:postcode":"97301",
    "addr:street":"Liberty St Se",
    "iso:country":"US",
    "sg:address":"300 Liberty St SE",
    "sg:city":"Salem",
    "sg:classifiers":[
        {
            "category":"Restaurant",
            "type":"Food & Drink"
        }
    ],
    "sg:phone":"+1 503 365 9722",
    "sg:postcode":"97301",
    "sg:province":"OR",
    "sg:tags":[
        "eating"
    ],
    "wof:name":"A Change Of Seasons",
    "wof:placetype":"venue"
},
  "geometry": {"coordinates":[-123.040009,44.937608],"type":"Point"}
}