{
  "type": "Feature",
  "properties": {
    "iso:country":"US",
    "sg:address":"1001 Bridge St",
    "sg:city":"Vernonia",
    "sg:classifiers":[
        {
            "category":"Recreation",
            "type":"Entertainment"
        }
    ],
    "sg:phone":"+1 503 429 2531",
    "sg:postcode":"97064",
    "sg:province":"OR",
    "sg:tags":[
        "parks"
    ],
    "wof:name":"Anderson Park",
    "wof:placetype":"venue"
},
  "geometry": {"coordinates":[-123.1978,45.858681],"type":"Point"}
}