{
  "type": "Feature",
  "properties": {
    "iso:country":"US",
    "sg:address":"365 Warner Milne Rd",
    "sg:city":"Oregon City",
    "sg:classifiers":[
        {
            "category":"Health Services",
            "subcategory":"Chiropractor",
            "type":"Services"
        }
    ],
    "sg:phone":"+1 503 557 9266",
    "sg:postcode":"97045",
    "sg:province":"OR",
    "wof:name":"Complete Hlth Chiropractic Ctr",
    "wof:placetype":"venue"
},
  "geometry": {"coordinates":[-122.595144,45.336561],"type":"Point"}
}