{
  "type": "Feature",
  "properties": {
    "addr:full":"854 Grant Ave Vernonia OR 97064",
    "addr:housenumber":"854",
    "addr:postcode":"97064",
    "addr:street":"Grant Ave",
    "iso:country":"US",
    "sg:address":"854 Grant Ave",
    "sg:city":"Vernonia",
    "sg:classifiers":[
        {
            "category":"Manufacturing",
            "subcategory":"Lumber",
            "type":"Manufacturing & Wholesale Goods"
        }
    ],
    "sg:phone":"+1 503 429 6783",
    "sg:postcode":"97064",
    "sg:province":"OR",
    "sg:tags":[
        "logging"
    ],
    "wof:name":"Holce Logging Co Inc",
    "wof:placetype":"venue"
},
  "geometry": {"coordinates":[-123.191166,45.859187],"type":"Point"}
}