{
  "type": "Feature",
  "properties": {
    "addr:full":"12540 Beck Rd Dallas OR 97338",
    "addr:housenumber":"12540",
    "addr:postcode":"97338",
    "addr:street":"Beck Rd",
    "iso:country":"US",
    "sg:address":"12540 Beck Rd",
    "sg:city":"Dallas",
    "sg:classifiers":[
        {
            "category":"Manufacturing",
            "subcategory":"Rubber & Plastics",
            "type":"Manufacturing & Wholesale Goods"
        }
    ],
    "sg:phone":"+1 503 623 6665",
    "sg:postcode":"97338",
    "sg:province":"OR",
    "sg:tags":[
        "product"
    ],
    "wof:name":"Temperature Loss Control",
    "wof:placetype":"venue"
},
  "geometry": {"coordinates":[-123.28674700000001,45.028018],"type":"Point"}
}