{
  "type": "Feature",
  "properties": {
    "addr:full":"3809 SE Tualatin Valley Hwy Hillsboro OR 97123",
    "addr:housenumber":"3809",
    "addr:postcode":"97123",
    "addr:street":"Se Tualatin Valley Hwy",
    "iso:country":"US",
    "sg:address":"3809 SE Tualatin Valley Hwy",
    "sg:city":"Hillsboro",
    "sg:classifiers":[
        {
            "category":"Real Estate",
            "subcategory":"Developer",
            "type":"Services"
        }
    ],
    "sg:phone":"+1 503 648 5444",
    "sg:postcode":"97123",
    "sg:province":"OR",
    "sg:tags":[
        "cemetery"
    ],
    "wof:name":"Valley Memorial Park",
    "wof:placetype":"venue"
},
  "geometry": {"coordinates":[-122.944849,45.502045],"type":"Point"}
}