{
  "type": "Feature",
  "properties": {
    "iso:country":"US",
    "sg:address":"207 Fir St",
    "sg:city":"La Grande",
    "sg:classifiers":[
        {
            "category":"Recreation",
            "type":"Entertainment"
        }
    ],
    "sg:phone":"+1 541 962 9642",
    "sg:postcode":"97850",
    "sg:province":"OR",
    "sg:tags":[
        "instruction",
        "yoga"
    ],
    "wof:name":"Yoga Dawn Studio",
    "wof:placetype":"venue"
},
  "geometry": {"coordinates":[-118.09154,45.327883],"type":"Point"}
}