{
  "type": "Feature",
  "properties": {
    "iso:country":"US",
    "sg:address":"20925 SW Willapa Ct",
    "sg:city":"Tualatin",
    "sg:classifiers":[
        {
            "category":"Autos & Motor Vehicles",
            "subcategory":"Automobile Sales",
            "type":"Retail Goods"
        }
    ],
    "sg:phone":"+1 503 692 4807",
    "sg:postcode":"97062",
    "sg:province":"OR",
    "sg:tags":[
        "used"
    ],
    "wof:name":"Tom Hahn Motors",
    "wof:placetype":"venue"
},
  "geometry": {"coordinates":[-122.773788,45.368371],"type":"Point"}
}