{
  "type": "Feature",
  "properties": {
    "iso:country":"US",
    "sg:address":"2300 Colestine Rd",
    "sg:city":"Ashland",
    "sg:classifiers":[
        {
            "category":"Wholesale",
            "subcategory":"Furniture",
            "type":"Manufacturing & Wholesale Goods"
        }
    ],
    "sg:phone":"+1 541 488 3030",
    "sg:postcode":"97520",
    "sg:province":"OR",
    "wof:name":"Grace Furnishings and Services",
    "wof:placetype":"venue"
},
  "geometry": {"coordinates":[-122.64843999999999,42.01336],"type":"Point"}
}