{
  "type": "Feature",
  "properties": {
    "iso:country":"US",
    "sg:address":"233 Liberty St NE",
    "sg:city":"Salem",
    "sg:classifiers":[
        {
            "category":"Restaurant",
            "type":"Food & Drink"
        }
    ],
    "sg:phone":"+1 503 581 5863",
    "sg:postcode":"97301",
    "sg:province":"OR",
    "sg:tags":[
        "eating"
    ],
    "wof:name":"Straight From New York Pizza",
    "wof:placetype":"venue"
},
  "geometry": {"coordinates":[-123.037972,44.941843],"type":"Point"}
}