{
  "type": "Feature",
  "properties": {
    "addr:full":"685 High St NE Salem OR 97301",
    "addr:housenumber":"685",
    "addr:postcode":"97301",
    "addr:street":"High St Ne",
    "iso:country":"US",
    "sg:address":"685 High St NE",
    "sg:city":"Salem",
    "sg:classifiers":[
        {
            "category":"Retail",
            "subcategory":"Auto Repair",
            "type":"Services"
        }
    ],
    "sg:phone":"+1 503 581 4242",
    "sg:postcode":"97301",
    "sg:province":"OR",
    "sg:tags":[
        "body",
        "automobile",
        "painting"
    ],
    "wof:name":"Trachsel Body & Paint",
    "wof:placetype":"venue"
},
  "geometry": {"coordinates":[-123.034408,44.945296],"type":"Point"}
}