{
  "type": "Feature",
  "properties": {
    "addr:full":"129 Morton Rd Oregon City OR 97045",
    "addr:housenumber":"129",
    "addr:postcode":"97045",
    "addr:street":"Morton Rd",
    "iso:country":"US",
    "sg:address":"129 Morton Rd",
    "sg:city":"Oregon City",
    "sg:classifiers":[
        {
            "category":"Professional",
            "type":"Services"
        }
    ],
    "sg:phone":"+1 503 723 9435",
    "sg:postcode":"97045",
    "sg:province":"OR",
    "wof:name":"Caward Inc",
    "wof:placetype":"venue"
},
  "geometry": {"coordinates":[-122.586044,45.352861],"type":"Point"}
}