{
  "type": "Feature",
  "properties": {
    "iso:country":"US",
    "sg:address":"456 SW Washington Ave",
    "sg:city":"Corvallis",
    "sg:classifiers":[
        {
            "category":"Insurance",
            "subcategory":"Insurance Agent",
            "type":"Services"
        }
    ],
    "sg:phone":"+1 541 757 1990",
    "sg:postcode":"97333",
    "sg:province":"OR",
    "sg:website":"http://www.oregoninsurancestore.com/",
    "wof:name":"Corvallis Insurance Services Inc",
    "wof:placetype":"venue"
},
  "geometry": {"coordinates":[-123.26461,44.56084],"type":"Point"}
}