{
  "type": "Feature",
  "properties": {
    "iso:country":"US",
    "sg:address":"2217 Ohio St",
    "sg:city":"Eugene",
    "sg:classifiers":[
        {
            "category":"Professional",
            "subcategory":"Business Services",
            "type":"Services"
        }
    ],
    "sg:phone":"+1 541 461 6174",
    "sg:postcode":"97402",
    "sg:province":"OR",
    "wof:name":"Credit Investigation Assoc",
    "wof:placetype":"venue"
},
  "geometry": {"coordinates":[-123.19868,44.091727],"type":"Point"}
}