{
  "type": "Feature",
  "properties": {
    "addr:full":"7330 NE Fremont St Portland OR 97213",
    "addr:housenumber":"7330",
    "addr:postcode":"97213",
    "addr:street":"Ne Fremont St",
    "iso:country":"US",
    "sg:address":"7330 NE Fremont St",
    "sg:city":"Portland",
    "sg:classifiers":[
        {
            "category":"Restaurant",
            "type":"Food & Drink"
        }
    ],
    "sg:phone":"+1 503 284 8355",
    "sg:postcode":"97213",
    "sg:province":"OR",
    "sg:tags":[
        "vietnamese"
    ],
    "wof:name":"Pho Vinh",
    "wof:placetype":"venue"
},
  "geometry": {"coordinates":[-122.587566,45.548211],"type":"Point"}
}