{
  "type": "Feature",
  "properties": {
    "iso:country":"US",
    "sg:address":"210 NE Dunn Pl",
    "sg:city":"Mcminnville",
    "sg:classifiers":[
        {
            "category":"Farming",
            "subcategory":"Livestock Farm",
            "type":"Manufacturing & Wholesale Goods"
        }
    ],
    "sg:phone":"+1 503 434 6462",
    "sg:postcode":"97128",
    "sg:province":"OR",
    "wof:name":"Crystal Creek Farms",
    "wof:placetype":"venue"
},
  "geometry": {"coordinates":[-123.168467,45.203844],"type":"Point"}
}