{
  "type": "Feature",
  "properties": {
    "iso:country":"US",
    "sg:address":"416 NE Brazee St",
    "sg:city":"Portland",
    "sg:classifiers":[
        {
            "category":"Wholesale",
            "subcategory":"Machinery & Supplies",
            "type":"Manufacturing & Wholesale Goods"
        }
    ],
    "sg:phone":"+1 503 288 6771",
    "sg:postcode":"97212",
    "sg:province":"OR",
    "sg:tags":[
        "tool"
    ],
    "wof:name":"Claude Smith Inc",
    "wof:placetype":"venue"
},
  "geometry": {"coordinates":[-122.658716,45.540328],"type":"Point"}
}