{
  "type": "Feature",
  "properties": {
    "addr:full":"3315 NW 26th Ave Portland OR 97210",
    "addr:housenumber":"3315",
    "addr:postcode":"97210",
    "addr:street":"Nw 26Th Ave",
    "iso:country":"US",
    "sg:address":"3315 NW 26th Ave",
    "sg:city":"Portland",
    "sg:classifiers":[
        {
            "category":"Manufacturing",
            "subcategory":"Electronics",
            "type":"Manufacturing & Wholesale Goods"
        }
    ],
    "sg:phone":"+1 503 228 7624",
    "sg:postcode":"97210",
    "sg:province":"OR",
    "sg:tags":[
        "printers-equipment",
        "supply"
    ],
    "sg:website":"http://www.crsdatasolutions.com",
    "wof:name":"Crs Data Solutions",
    "wof:placetype":"venue"
},
  "geometry": {"coordinates":[-122.70496900000001,45.546295],"type":"Point"}
}