{
  "type": "Feature",
  "properties": {
    "iso:country":"US",
    "sg:address":"215 SW Hooker St",
    "sg:city":"Portland",
    "sg:classifiers":[
        {
            "category":"Professional",
            "subcategory":"Business Services",
            "type":"Services"
        }
    ],
    "sg:phone":"+1 503 223 9941",
    "sg:postcode":"97201",
    "sg:province":"OR",
    "sg:website":"www.adsrecording.com",
    "wof:name":"ADS Recording",
    "wof:placetype":"venue"
},
  "geometry": {"coordinates":[-122.681629,45.502359],"type":"Point"}
}