{
  "type": "Feature",
  "properties": {
    "addr:full":"3040 NE Sandy Blvd Portland OR 97232",
    "addr:housenumber":"3040",
    "addr:postcode":"97232",
    "addr:street":"Ne Sandy Blvd",
    "iso:country":"US",
    "sg:address":"3040 NE Sandy Blvd",
    "sg:city":"Portland",
    "sg:classifiers":[
        {
            "category":"Home & Garden",
            "subcategory":"Building Materials",
            "type":"Retail Goods"
        },
        {
            "category":"Building & Trades",
            "subcategory":"Construction",
            "type":"Services"
        },
        {
            "category":"Home & Garden",
            "subcategory":"Carpets & Floor Coverings",
            "type":"Retail Goods"
        }
    ],
    "sg:phone":"+1 503 235 8711",
    "sg:postcode":"97232",
    "sg:province":"OR",
    "sg:tags":[
        "flooring",
        "hardwood",
        "top",
        "counter",
        "rug",
        "contractor",
        "tile-contractors"
    ],
    "sg:website":"http://www.paulsonsfc.com",
    "wof:name":"Paulson's Floor Coverings",
    "wof:placetype":"venue"
},
  "geometry": {"coordinates":[-122.781937,45.448471],"type":"Point"}
}