{
  "type": "Feature",
  "properties": {
    "iso:country":"US",
    "sg:address":"3800 SW Cedar Hills Blvd",
    "sg:city":"Beaverton",
    "sg:classifiers":[
        {
            "category":"Communications",
            "type":"Services"
        }
    ],
    "sg:phone":"+1 503 644 6949",
    "sg:postcode":"97005",
    "sg:province":"OR",
    "sg:tags":[
        "web",
        "design"
    ],
    "sg:website":"www.blue-skywebdesign.com",
    "wof:name":"Blue Sky Web Design",
    "wof:placetype":"venue"
},
  "geometry": {"coordinates":[-122.808437,45.491893],"type":"Point"}
}