{
  "type": "Feature",
  "properties": {
    "iso:country":"US",
    "sg:address":"509 E Main St",
    "sg:city":"Rogue River",
    "sg:classifiers":[
        {
            "category":"Health Services",
            "subcategory":"Doctor",
            "type":"Services"
        }
    ],
    "sg:phone":"+1 541 582 0505",
    "sg:postcode":"97537",
    "sg:province":"OR",
    "sg:tags":[
        "medical"
    ],
    "wof:name":"Ed Glovinsky Do",
    "wof:placetype":"venue"
},
  "geometry": {"coordinates":[-123.16367,42.432762],"type":"Point"}
}