{
  "type": "Feature",
  "properties": {
    "iso:country":"US",
    "sg:address":"4030 SE Tenino St",
    "sg:city":"Portland",
    "sg:classifiers":[
        {
            "category":"Building & Trades",
            "subcategory":"Equipment Rental",
            "type":"Services"
        }
    ],
    "sg:phone":"+1 503 788 1864",
    "sg:postcode":"97202",
    "sg:province":"OR",
    "sg:tags":[
        "farm",
        "management"
    ],
    "wof:name":"Clayton Rental Homes",
    "wof:placetype":"venue"
},
  "geometry": {"coordinates":[-122.621859,45.464335],"type":"Point"}
}