{
  "type": "Feature",
  "properties": {
    "addr:full":"701 Western Ave Medford OR 97501",
    "addr:housenumber":"701",
    "addr:postcode":"97501",
    "addr:street":"Western Ave",
    "iso:country":"US",
    "sg:address":"701 Western Ave",
    "sg:city":"Medford",
    "sg:classifiers":[
        {
            "category":"Farming",
            "subcategory":"Livestock Farm",
            "type":"Manufacturing & Wholesale Goods"
        }
    ],
    "sg:phone":"+1 541 732 2452",
    "sg:postcode":"97501",
    "sg:province":"OR",
    "sg:tags":[
        "ranch"
    ],
    "wof:name":"ISH Ranch Estates",
    "wof:placetype":"venue"
},
  "geometry": {"coordinates":[-122.892478,42.331815],"type":"Point"}
}