{
  "type": "Feature",
  "properties": {
    "iso:country":"US",
    "sg:address":"585 Thornton Way",
    "sg:city":"Ashland",
    "sg:classifiers":[
        {
            "category":"Shopping",
            "subcategory":"Gifts & Souvenirs",
            "type":"Retail Goods"
        }
    ],
    "sg:phone":"+1 541 488 2405",
    "sg:postcode":"97520",
    "sg:province":"OR",
    "wof:name":"A Street Market",
    "wof:placetype":"venue"
},
  "geometry": {"coordinates":[-122.730799,42.203788],"type":"Point"}
}