{
  "type": "Feature",
  "properties": {
    "addr:full":"686 NW Eastman Pkwy Gresham OR 97030",
    "addr:housenumber":"686",
    "addr:postcode":"97030",
    "addr:street":"Nw Eastman Pkwy",
    "iso:country":"US",
    "sg:address":"686 NW Eastman Pkwy",
    "sg:city":"Gresham",
    "sg:classifiers":[
        {
            "category":"Real Estate",
            "subcategory":"Real Estate Services",
            "type":"Services"
        },
        {
            "category":"Insurance",
            "subcategory":"Title Insurance",
            "type":"Services"
        }
    ],
    "sg:phone":"+1 503 665 6151",
    "sg:postcode":"97030",
    "sg:province":"OR",
    "sg:tags":[
        "carrier"
    ],
    "sg:website":"http://www.ipx1031.com",
    "wof:name":"Fidelity National",
    "wof:placetype":"venue"
},
  "geometry": {"coordinates":[-122.436144,45.50247],"type":"Point"}
}