{
  "type": "Feature",
  "properties": {
    "iso:country":"US",
    "sg:address":"34161 Ophir Rd",
    "sg:city":"Ophir",
    "sg:classifiers":[
        {
            "category":"Travel",
            "subcategory":"Campground",
            "type":"Entertainment"
        }
    ],
    "sg:phone":"+1 541 247 2765",
    "sg:postcode":"97444",
    "sg:province":"OR",
    "wof:name":"Honey Bear Campground",
    "wof:placetype":"venue"
},
  "geometry": {"coordinates":[-124.39737599999999,42.537319],"type":"Point"}
}