{
  "type": "Feature",
  "properties": {
    "addr:full":"2175 NE 27th St Mcminnville OR 97128",
    "addr:housenumber":"2175",
    "addr:postcode":"97128",
    "addr:street":"Ne 27Th St",
    "iso:country":"US",
    "sg:address":"2175 NE 27th St",
    "sg:city":"Mcminnville",
    "sg:classifiers":[
        {
            "category":"Retail",
            "subcategory":"Auto Repair",
            "type":"Services"
        }
    ],
    "sg:phone":"+1 503 474 4455",
    "sg:postcode":"97128",
    "sg:province":"OR",
    "sg:tags":[
        "muffler",
        "exhaust",
        "system"
    ],
    "wof:name":"Affordable Muffler & Brake",
    "wof:placetype":"venue"
},
  "geometry": {"coordinates":[-123.17789999999999,45.22817],"type":"Point"}
}