{
  "type": "Feature",
  "properties": {
    "iso:country":"US",
    "sg:address":"198 Lexington Ave",
    "sg:city":"Astoria",
    "sg:classifiers":[
        {
            "category":"Professional",
            "subcategory":"Business Services",
            "type":"Services"
        }
    ],
    "sg:phone":"+1 503 325 3943",
    "sg:postcode":"97103",
    "sg:province":"OR",
    "wof:name":"Marincovich Marine Enterprises",
    "wof:placetype":"venue"
},
  "geometry": {"coordinates":[-123.840854,46.18284],"type":"Point"}
}