{
  "type": "Feature",
  "properties": {
    "iso:country":"US",
    "sg:address":"3289 Cheyenne Ct NW",
    "sg:city":"Salem",
    "sg:classifiers":[
        {
            "category":"Real Estate",
            "subcategory":"Real Estate Operator",
            "type":"Services"
        }
    ],
    "sg:phone":"+1 503 371 1031",
    "sg:postcode":"97304",
    "sg:province":"OR",
    "sg:tags":[
        "building",
        "nonresidential"
    ],
    "wof:name":"T&E Properties",
    "wof:placetype":"venue"
},
  "geometry": {"coordinates":[-123.09604,44.952599],"type":"Point"}
}