{
  "type": "Feature",
  "properties": {
    "iso:country":"US",
    "sg:address":"2760 SW 53rd St",
    "sg:city":"Corvallis",
    "sg:classifiers":[
        {
            "category":"Organizations",
            "subcategory":"Religious Organization",
            "type":"Services"
        }
    ],
    "sg:phone":"+1 541 753 2802",
    "sg:postcode":"97333",
    "sg:province":"OR",
    "sg:tags":[
        "churches-non-denominational",
        "church"
    ],
    "sg:website":"http://www.suburbanchurch.com",
    "wof:name":"Suburban Christian Church",
    "wof:placetype":"venue"
},
  "geometry": {"coordinates":[-123.311668,44.538705],"type":"Point"}
}