{
  "type": "Feature",
  "properties": {
    "addr:full":"2275 17th St Baker City OR 97814",
    "addr:housenumber":"2275",
    "addr:postcode":"97814",
    "addr:street":"17Th St",
    "iso:country":"US",
    "sg:address":"2275 17th St",
    "sg:city":"Baker City",
    "sg:classifiers":[
        {
            "category":"Insurance",
            "subcategory":"Insurance Agent",
            "type":"Services"
        }
    ],
    "sg:phone":"+1 541 523 5536",
    "sg:postcode":"97814",
    "sg:province":"OR",
    "wof:name":"Royal Neighbors of America",
    "wof:placetype":"venue"
},
  "geometry": {"coordinates":[-117.849931,44.779246],"type":"Point"}
}