{
  "type": "Feature",
  "properties": {
    "iso:country":"US",
    "sg:address":"1616 15th St",
    "sg:city":"Florence",
    "sg:classifiers":[
        {
            "category":"Organizations",
            "subcategory":"Religious Organization",
            "type":"Services"
        }
    ],
    "sg:phone":"+1 541 997 2523",
    "sg:postcode":"97439",
    "sg:province":"OR",
    "sg:tags":[
        "church"
    ],
    "wof:name":"Evangelical Church-N America",
    "wof:placetype":"venue"
},
  "geometry": {"coordinates":[-124.103005,43.979874],"type":"Point"}
}