{
  "type": "Feature",
  "properties": {
    "iso:country":"US",
    "sg:address":"3050 Dee Hwy",
    "sg:city":"Hood River",
    "sg:classifiers":[
        {
            "category":"Real Estate",
            "subcategory":"Real Estate Operator",
            "type":"Services"
        }
    ],
    "sg:phone":"+1 541 354 2555",
    "sg:postcode":"97031",
    "sg:province":"OR",
    "sg:tags":[
        "property",
        "lessor"
    ],
    "wof:name":"Ed Adams",
    "wof:placetype":"venue"
},
  "geometry": {"coordinates":[-121.585578,45.637748],"type":"Point"}
}