{
  "type": "Feature",
  "properties": {
    "iso:country":"US",
    "sg:address":"17696 NW Sue Ct",
    "sg:city":"Beaverton",
    "sg:classifiers":[
        {
            "category":"Building & Trades",
            "subcategory":"Landscaping Services",
            "type":"Services"
        }
    ],
    "sg:phone":"+1 503 645 6530",
    "sg:postcode":"97006",
    "sg:province":"OR",
    "wof:name":"Avery Landscaping Inc",
    "wof:placetype":"venue"
},
  "geometry": {"coordinates":[-122.858133,45.526166],"type":"Point"}
}