{
  "type": "Feature",
  "properties": {
    "addr:full":"1785 NE Sandy Blvd Portland OR 97232",
    "addr:housenumber":"1785",
    "addr:postcode":"97232",
    "addr:street":"Ne Sandy Blvd",
    "iso:country":"US",
    "sg:address":"1785 NE Sandy Blvd",
    "sg:city":"Portland",
    "sg:phone":"+1 503 283 9603",
    "sg:postcode":"97232",
    "sg:province":"OR",
    "wof:name":"School of Autism",
    "wof:placetype":"venue"
},
  "geometry": {"coordinates":[-122.647926,45.525028],"type":"Point"}
}