{
  "type": "Feature",
  "properties": {
    "addr:full":"624 Rossanley Dr Ste 103 Medford OR 97501",
    "addr:housenumber":"624",
    "addr:postcode":"97501",
    "addr:street":"Rossanley Dr Ste 103",
    "iso:country":"US",
    "sg:address":"624 Rossanley Dr Ste 103",
    "sg:city":"Medford",
    "sg:classifiers":[
        {
            "category":"Home & Garden",
            "subcategory":"Building Materials",
            "type":"Retail Goods"
        }
    ],
    "sg:phone":"+1 541 772 4496",
    "sg:postcode":"97501",
    "sg:province":"OR",
    "sg:tags":[
        "supply"
    ],
    "wof:name":"Heritage Stairs",
    "wof:placetype":"venue"
},
  "geometry": {"coordinates":[-122.89645,42.341144],"type":"Point"}
}