{
  "type": "Feature",
  "properties": {
    "addr:full":"319 SW G St Apt 18 Madras OR 97741",
    "addr:housenumber":"319;18",
    "addr:postcode":"97741",
    "addr:street":"Sw G St Apt",
    "iso:country":"US",
    "sg:address":"319 SW G St Apt 18",
    "sg:city":"Madras",
    "sg:classifiers":[
        {
            "category":"Real Estate",
            "subcategory":"Real Estate Operator",
            "type":"Services"
        }
    ],
    "sg:phone":"+1 541 475 7554",
    "sg:postcode":"97741",
    "sg:province":"OR",
    "sg:tags":[
        "apartment"
    ],
    "sg:website":"http://www.nmteam.com",
    "wof:name":"Jefferson Court Apartment",
    "wof:placetype":"venue"
},
  "geometry": {"coordinates":[-121.13492599999999,44.62899],"type":"Point"}
}