{
  "type": "Feature",
  "properties": {
    "addr:full":"215 N Calapooia St Sutherlin OR 97479",
    "addr:housenumber":"215",
    "addr:postcode":"97479",
    "addr:street":"N Calapooia St",
    "iso:country":"US",
    "sg:address":"215 N Calapooia St",
    "sg:city":"Sutherlin",
    "sg:classifiers":[
        {
            "category":"Organizations",
            "subcategory":"Religious Organization",
            "type":"Services"
        }
    ],
    "sg:phone":"+1 541 459 8855",
    "sg:postcode":"97479",
    "sg:province":"OR",
    "sg:tags":[
        "church"
    ],
    "wof:name":"Sutherlin New Life Ctr",
    "wof:placetype":"venue"
},
  "geometry": {"coordinates":[-123.315618,43.391194],"type":"Point"}
}