{
  "type": "Feature",
  "properties": {
    "addr:full":"3503 Old Hwy 99 S Roseburg OR 97470",
    "addr:housenumber":"3503",
    "addr:postcode":"97470",
    "addr:street":"Old Hwy 99 S",
    "iso:country":"US",
    "sg:address":"3503 Old Hwy 99 S",
    "sg:city":"Roseburg",
    "sg:classifiers":[
        {
            "category":"Government",
            "subcategory":"Office",
            "type":"Public Place"
        }
    ],
    "sg:phone":"+1 541 679 1231",
    "sg:postcode":"97470",
    "sg:province":"OR",
    "sg:tags":[
        "federal"
    ],
    "wof:name":"US Fish & Wildlife Svc",
    "wof:placetype":"venue"
},
  "geometry": {"coordinates":[-123.36691,43.165034],"type":"Point"}
}