{
  "type": "Feature",
  "properties": {
    "iso:country":"US",
    "sg:address":"481 Parkside Dr",
    "sg:city":"Ashland",
    "sg:classifiers":[
        {
            "category":"Professional",
            "subcategory":"Business Services",
            "type":"Services"
        }
    ],
    "sg:phone":"+1 541 482 6716",
    "sg:postcode":"97520",
    "sg:province":"OR",
    "wof:name":"Lane Enterprises",
    "wof:placetype":"venue"
},
  "geometry": {"coordinates":[-122.714007,42.20684],"type":"Point"}
}