{
  "type": "Feature",
  "properties": {
    "iso:country":"US",
    "sg:address":"3021 Ballyntyne Rd S",
    "sg:city":"Salem",
    "sg:classifiers":[
        {
            "category":"Professional",
            "subcategory":"Computer Services",
            "type":"Services"
        }
    ],
    "sg:phone":"+1 503 510 8252",
    "sg:postcode":"97302",
    "sg:province":"OR",
    "sg:tags":[
        "consultant",
        "designer"
    ],
    "wof:name":"Gla Consulting Svc",
    "wof:placetype":"venue"
},
  "geometry": {"coordinates":[-123.087756,44.879676],"type":"Point"}
}