{
  "type": "Feature",
  "properties": {
    "iso:country":"US",
    "sg:address":"126 S McLoughlin Blvd",
    "sg:city":"Oregon City",
    "sg:classifiers":[
        {
            "category":"Shopping",
            "subcategory":"Computers & Home Electronics",
            "type":"Retail Goods"
        }
    ],
    "sg:phone":"+1 503 650 6155",
    "sg:postcode":"97045",
    "sg:province":"OR",
    "sg:tags":[
        "software"
    ],
    "wof:name":"Computer Automated Towing Syst",
    "wof:placetype":"venue"
},
  "geometry": {"coordinates":[-122.61877699999999,45.34819],"type":"Point"}
}