{
  "type": "Feature",
  "properties": {
    "iso:country":"US",
    "sg:address":"54995 Rosa Rd",
    "sg:city":"Bandon",
    "sg:classifiers":[
        {
            "category":"Building & Trades",
            "subcategory":"Plumbing",
            "type":"Services"
        }
    ],
    "sg:phone":"+1 541 347 3733",
    "sg:postcode":"97411",
    "sg:province":"OR",
    "sg:tags":[
        "plumbing",
        "contractor"
    ],
    "wof:name":"Avery Plumbing",
    "wof:placetype":"venue"
},
  "geometry": {"coordinates":[-124.39698300000001,43.073468],"type":"Point"}
}