{
  "type": "Feature",
  "properties": {
    "iso:country":"US",
    "sg:address":"414 NE F St",
    "sg:city":"Grants Pass",
    "sg:classifiers":[
        {
            "category":"Retail",
            "subcategory":"Auto Repair",
            "type":"Services"
        }
    ],
    "sg:phone":"+1 541 476 9646",
    "sg:postcode":"97526",
    "sg:province":"OR",
    "sg:tags":[
        "repairing",
        "automobile"
    ],
    "wof:name":"Star Automotive",
    "wof:placetype":"venue"
},
  "geometry": {"coordinates":[-123.321634,42.438569],"type":"Point"}
}