{
  "type": "Feature",
  "properties": {
    "addr:full":"1320 NE Brazee St Portland OR 97212",
    "addr:housenumber":"1320",
    "addr:postcode":"97212",
    "addr:street":"Ne Brazee St",
    "iso:country":"US",
    "sg:address":"1320 NE Brazee St",
    "sg:city":"Portland",
    "sg:classifiers":[
        {
            "category":"Education",
            "subcategory":"School",
            "type":"Public Place"
        }
    ],
    "sg:phone":"+1 503 916 6185",
    "sg:postcode":"97212",
    "sg:province":"OR",
    "wof:name":"Schools Public",
    "wof:placetype":"venue"
},
  "geometry": {"coordinates":[-122.652472,45.540393],"type":"Point"}
}