{
  "type": "Feature",
  "properties": {
    "iso:country":"US",
    "sg:address":"93272 Hwy 99 S",
    "sg:city":"Junction City",
    "sg:classifiers":[
        {
            "category":"Autos & Motor Vehicles",
            "subcategory":"Recreational Vehicle Sales",
            "type":"Retail Goods"
        }
    ],
    "sg:phone":"+1 541 998 1177",
    "sg:postcode":"97448",
    "sg:province":"OR",
    "wof:name":"Nortech Designs",
    "wof:placetype":"venue"
},
  "geometry": {"coordinates":[-123.202824,44.195508],"type":"Point"}
}