{
  "type": "Feature",
  "properties": {
    "addr:full":"820 SW Church St Dallas OR 97338",
    "addr:housenumber":"820",
    "addr:postcode":"97338",
    "addr:street":"Sw Church St",
    "iso:country":"US",
    "sg:address":"820 SW Church St",
    "sg:city":"Dallas",
    "sg:classifiers":[
        {
            "category":"Freight",
            "type":"Transportation"
        }
    ],
    "sg:phone":"+1 503 623 4386",
    "sg:postcode":"97338",
    "sg:province":"OR",
    "sg:tags":[
        "warehouse",
        "self",
        "storage"
    ],
    "wof:name":"Insulectro",
    "wof:placetype":"venue"
},
  "geometry": {"coordinates":[-123.31854300000001,44.921324],"type":"Point"}
}