{
  "type": "Feature",
  "properties": {
    "addr:full":"1816 Tamarack Way Forest Grove OR 97116",
    "addr:housenumber":"1816",
    "addr:postcode":"97116",
    "addr:street":"Tamarack Way",
    "iso:country":"US",
    "sg:address":"1816 Tamarack Way",
    "sg:city":"Forest Grove",
    "sg:classifiers":[
        {
            "category":"Real Estate",
            "subcategory":"Real Estate Agent",
            "type":"Services"
        }
    ],
    "sg:phone":"+1 503 357 8384",
    "sg:postcode":"97116",
    "sg:province":"OR",
    "sg:tags":[
        "appraiser"
    ],
    "wof:name":"Steyaert & Steyaert",
    "wof:placetype":"venue"
},
  "geometry": {"coordinates":[-123.080164,45.517102],"type":"Point"}
}