{
  "type": "Feature",
  "properties": {
    "addr:full":"12648 SW Creekshire Dr Portland OR 97223",
    "addr:housenumber":"12648",
    "addr:postcode":"97223",
    "addr:street":"Sw Creekshire Dr",
    "iso:country":"US",
    "sg:address":"12648 SW Creekshire Dr",
    "sg:city":"Portland",
    "sg:classifiers":[
        {
            "category":"Building & Trades",
            "subcategory":"Locksmith",
            "type":"Services"
        }
    ],
    "sg:phone":"+1 503 715 3730",
    "sg:postcode":"97223",
    "sg:province":"OR",
    "sg:tags":[
        "key"
    ],
    "wof:name":"23 7 Locksmith",
    "wof:placetype":"venue"
},
  "geometry": {"coordinates":[-122.826725,45.428637],"type":"Point"}
}