{
  "type": "Feature",
  "properties": {
    "iso:country":"US",
    "sg:address":"422 Willow St",
    "sg:city":"Milton Freewater",
    "sg:classifiers":[
        {
            "category":"Freight",
            "type":"Transportation"
        }
    ],
    "sg:phone":"+1 541 938 6214",
    "sg:postcode":"97862",
    "sg:province":"OR",
    "sg:tags":[
        "general"
    ],
    "wof:name":"Jones Mini Storage",
    "wof:placetype":"venue"
},
  "geometry": {"coordinates":[-118.38384600000001,45.931996],"type":"Point"}
}