{
  "type": "Feature",
  "properties": {
    "iso:country":"US",
    "sg:address":"11 Nansen Summit",
    "sg:city":"Lake Oswego",
    "sg:classifiers":[
        {
            "category":"Insurance",
            "subcategory":"Insurance Agent",
            "type":"Services"
        }
    ],
    "sg:phone":"+1 503 248 6514",
    "sg:postcode":"97035",
    "sg:province":"OR",
    "wof:name":"J H Marsh McLennan",
    "wof:placetype":"venue"
},
  "geometry": {"coordinates":[-122.722949,45.437787],"type":"Point"}
}