{
  "type": "Feature",
  "properties": {
    "addr:full":"12800 Howell Prairie Rd NE Gervais OR 97026",
    "addr:housenumber":"12800",
    "addr:postcode":"97026",
    "addr:street":"Howell Prairie Rd Ne",
    "iso:country":"US",
    "sg:address":"12800 Howell Prairie Rd NE",
    "sg:city":"Gervais",
    "sg:classifiers":[
        {
            "category":"Building & Trades",
            "subcategory":"Construction",
            "type":"Services"
        }
    ],
    "sg:phone":"+1 503 792 3691",
    "sg:postcode":"97026",
    "sg:province":"OR",
    "sg:tags":[
        "industrial",
        "nonresidential"
    ],
    "wof:name":"CAM Construction Inc",
    "wof:placetype":"venue"
},
  "geometry": {"coordinates":[-122.86798,45.106106],"type":"Point"}
}