{
  "type": "Feature",
  "properties": {
    "iso:country":"US",
    "sg:address":"4790 Labish Garden Rd NE",
    "sg:city":"Salem",
    "sg:classifiers":[
        {
            "category":"Manufacturing",
            "subcategory":"Glass & Minerals",
            "type":"Manufacturing & Wholesale Goods"
        }
    ],
    "sg:phone":"+1 503 390 2411",
    "sg:postcode":"97305",
    "sg:province":"OR",
    "sg:tags":[
        "product",
        "mfg"
    ],
    "wof:name":"Wilsons Glass Art",
    "wof:placetype":"venue"
},
  "geometry": {"coordinates":[-122.96216099999999,45.010673],"type":"Point"}
}