{
  "type": "Feature",
  "properties": {
    "addr:full":"1911 Lancaster Dr NE Salem OR 97305",
    "addr:housenumber":"1911",
    "addr:postcode":"97305",
    "addr:street":"Lancaster Dr Ne",
    "iso:country":"US",
    "sg:address":"1911 Lancaster Dr NE",
    "sg:city":"Salem",
    "sg:classifiers":[
        {
            "category":"Shopping",
            "subcategory":"Clothing, Apparel, & Fashions",
            "type":"Retail Goods"
        }
    ],
    "sg:phone":"+1 503 362 2229",
    "sg:postcode":"97305",
    "sg:province":"OR",
    "sg:tags":[
        "infant",
        "wear",
        "child"
    ],
    "wof:name":"Once Upon A Child",
    "wof:placetype":"venue"
},
  "geometry": {"coordinates":[-122.98376500000001,44.952558],"type":"Point"}
}