{
  "type": "Feature",
  "properties": {
    "iso:country":"US",
    "sg:address":"2323 Avenue H",
    "sg:city":"White City",
    "sg:classifiers":[
        {
            "category":"Banks & Credit Unions",
            "subcategory":"Bank",
            "type":"Services"
        }
    ],
    "sg:phone":"+1 541 826 2541",
    "sg:postcode":"97503",
    "sg:province":"OR",
    "wof:name":"South Valley Bank & Trust",
    "wof:placetype":"venue"
},
  "geometry": {"coordinates":[-122.8509,42.438773],"type":"Point"}
}