{
  "type": "Feature",
  "properties": {
    "iso:country":"US",
    "sg:address":"32782 Kilgore Rd",
    "sg:city":"Ophir",
    "sg:classifiers":[
        {
            "category":"Professional",
            "subcategory":"Engineering",
            "type":"Services"
        }
    ],
    "sg:phone":"+1 541 247 7769",
    "sg:postcode":"97444",
    "sg:province":"OR",
    "sg:tags":[
        "engineer"
    ],
    "wof:name":"T Flatebo & Assoc Inc",
    "wof:placetype":"venue"
},
  "geometry": {"coordinates":[-124.41775800000001,42.498705],"type":"Point"}
}