{
  "type": "Feature",
  "properties": {
    "iso:country":"US",
    "sg:address":"11108 NE Sandy Blvd",
    "sg:city":"Portland",
    "sg:classifiers":[
        {
            "category":"Personal",
            "subcategory":"Beauty Salon",
            "type":"Services"
        }
    ],
    "sg:phone":"+1 503 256 2883",
    "sg:postcode":"97220",
    "sg:province":"OR",
    "sg:tags":[
        "shop"
    ],
    "wof:name":"Rose's Beauty Salon",
    "wof:placetype":"venue"
},
  "geometry": {"coordinates":[-122.547513,45.558129],"type":"Point"}
}