{
  "type": "Feature",
  "properties": {
    "iso:country":"US",
    "sg:address":"750 SW Meadow Dr",
    "sg:city":"Beaverton",
    "sg:classifiers":[
        {
            "category":"Banks & Credit Unions",
            "subcategory":"Financial Services",
            "type":"Services"
        }
    ],
    "sg:phone":"+1 503 644 5765",
    "sg:postcode":"97006",
    "sg:province":"OR",
    "sg:tags":[
        "company",
        "holding"
    ],
    "wof:name":"Sandlake Estates LLC",
    "wof:placetype":"venue"
},
  "geometry": {"coordinates":[-122.827461,45.515411],"type":"Point"}
}