{
  "type": "Feature",
  "properties": {
    "iso:country":"US",
    "sg:address":"1935 Roberts Rd",
    "sg:city":"Medford",
    "sg:classifiers":[
        {
            "category":"Professional",
            "subcategory":"Detective & Security Services",
            "type":"Services"
        }
    ],
    "sg:phone":"+1 541 734 3105",
    "sg:postcode":"97504",
    "sg:province":"OR",
    "sg:tags":[
        "investigator"
    ],
    "wof:name":"Ron Klingler & Assoc",
    "wof:placetype":"venue"
},
  "geometry": {"coordinates":[-122.856059,42.349349],"type":"Point"}
}