{
  "type": "Feature",
  "properties": {
    "addr:full":"916 SE 34th Ave Portland OR 97214",
    "addr:housenumber":"916",
    "addr:postcode":"97214",
    "addr:street":"Se 34Th Ave",
    "iso:country":"US",
    "sg:address":"916 SE 34th Ave",
    "sg:city":"Portland",
    "sg:classifiers":[
        {
            "category":"Manufacturing",
            "subcategory":"Tools & Machinery",
            "type":"Manufacturing & Wholesale Goods"
        }
    ],
    "sg:phone":"+1 503 731 8848",
    "sg:postcode":"97214",
    "sg:province":"OR",
    "sg:tags":[
        "product",
        "printed"
    ],
    "wof:name":"Print Products LLC",
    "wof:placetype":"venue"
},
  "geometry": {"coordinates":[-122.629486,45.515855],"type":"Point"}
}