{
  "type": "Feature",
  "properties": {
    "iso:country":"US",
    "sg:address":"1120 N Mist Dr",
    "sg:city":"Vernonia",
    "sg:classifiers":[
        {
            "category":"Retail",
            "subcategory":"Auto Repair",
            "type":"Services"
        }
    ],
    "sg:phone":"+1 503 429 0445",
    "sg:postcode":"97064",
    "sg:province":"OR",
    "sg:tags":[
        "exhaust"
    ],
    "wof:name":"Vernonia Exhaust Repair",
    "wof:placetype":"venue"
},
  "geometry": {"coordinates":[-123.173095,45.861097],"type":"Point"}
}