{
  "type": "Feature",
  "properties": {
    "iso:country":"US",
    "sg:address":"2697 12th Pl SE",
    "sg:city":"Salem",
    "sg:classifiers":[
        {
            "category":"Health Services",
            "subcategory":"Hospital",
            "type":"Services"
        }
    ],
    "sg:phone":"+1 503 763 1778",
    "sg:postcode":"97302",
    "sg:province":"OR",
    "sg:tags":[
        "mental"
    ],
    "wof:name":"Solarity Mental Health LLC",
    "wof:placetype":"venue"
},
  "geometry": {"coordinates":[-123.029895,44.914911],"type":"Point"}
}