{
  "type": "Feature",
  "properties": {
    "addr:full":"2697 12th Pl SE Salem OR 97302",
    "addr:housenumber":"2697",
    "addr:postcode":"97302",
    "addr:street":"12Th Pl Se",
    "iso:country":"US",
    "sg:address":"2697 12th Pl SE",
    "sg:city":"Salem",
    "sg:classifiers":[
        {
            "category":"Health Services",
            "subcategory":"Hospital",
            "type":"Services"
        }
    ],
    "sg:phone":"+1 503 763 1778",
    "sg:postcode":"97302",
    "sg:province":"OR",
    "sg:tags":[
        "mental"
    ],
    "wof:name":"Solarity Mental Health LLC",
    "wof:placetype":"venue"
},
  "geometry": {"coordinates":[-123.029895,44.914911],"type":"Point"}
}