{
  "type": "Feature",
  "properties": {
    "addr:full":"1103 SE Rogue Dr Grants Pass OR 97526",
    "addr:housenumber":"1103",
    "addr:postcode":"97526",
    "addr:street":"Se Rogue Dr",
    "iso:country":"US",
    "sg:address":"1103 SE Rogue Dr",
    "sg:city":"Grants Pass",
    "sg:classifiers":[
        {
            "category":"Building & Trades",
            "subcategory":"Construction",
            "type":"Services"
        }
    ],
    "sg:phone":"+1 541 479 7048",
    "sg:postcode":"97526",
    "sg:province":"OR",
    "sg:tags":[
        "general",
        "contractor"
    ],
    "wof:name":"Richard Starr Construction",
    "wof:placetype":"venue"
},
  "geometry": {"coordinates":[-123.307599,42.427657],"type":"Point"}
}