{
  "type": "Feature",
  "properties": {
    "addr:full":"4062 Pfeifer Ct Lake Oswego OR 97035",
    "addr:housenumber":"4062",
    "addr:postcode":"97035",
    "addr:street":"Pfeifer Ct",
    "iso:country":"US",
    "sg:address":"4062 Pfeifer Ct",
    "sg:city":"Lake Oswego",
    "sg:classifiers":[
        {
            "category":"Building & Trades",
            "subcategory":"Locksmith",
            "type":"Services"
        }
    ],
    "sg:phone":"+1 503 715 3829",
    "sg:postcode":"97035",
    "sg:province":"OR",
    "sg:tags":[
        "key"
    ],
    "wof:name":"A Emergency Locksmith",
    "wof:placetype":"venue"
},
  "geometry": {"coordinates":[-122.71821799999999,45.422023],"type":"Point"}
}