{
  "type": "Feature",
  "properties": {
    "iso:country":"US",
    "sg:address":"12613 SE Division",
    "sg:city":"Portland",
    "sg:classifiers":[
        {
            "category":"Coffee & Tea",
            "type":"Food & Drink"
        }
    ],
    "sg:phone":"+1 503 760 1493",
    "sg:postcode":"97236",
    "sg:province":"OR",
    "wof:name":"Starbucks",
    "wof:placetype":"venue"
},
  "geometry": {"coordinates":[-122.533632,45.504476],"type":"Point"}
}