{
  "type": "Feature",
  "properties": {
    "addr:full":"265 Union Ave Grants Pass OR 97527",
    "addr:housenumber":"265",
    "addr:postcode":"97527",
    "addr:street":"Union Ave",
    "iso:country":"US",
    "sg:address":"265 Union Ave",
    "sg:city":"Grants Pass",
    "sg:classifiers":[
        {
            "category":"Banks & Credit Unions",
            "subcategory":"Bank",
            "type":"Services"
        }
    ],
    "sg:phone":"+1 541 476 3128",
    "sg:postcode":"97527",
    "sg:province":"OR",
    "wof:name":"Bank Of The Cascades",
    "wof:placetype":"venue"
},
  "geometry": {"coordinates":[-123.3373,42.42233],"type":"Point"}
}