{
  "type": "Feature",
  "properties": {
    "iso:country":"US",
    "sg:address":"140 S Oregon St",
    "sg:city":"Ontario",
    "sg:classifiers":[
        {
            "category":"Personal",
            "subcategory":"Tanning Parlor",
            "type":"Services"
        },
        {
            "category":"Personal",
            "type":"Services"
        }
    ],
    "sg:phone":"+1 541 889 6494",
    "sg:postcode":"97914",
    "sg:province":"OR",
    "sg:tags":[
        "salon"
    ],
    "wof:name":"Electric Beach Tanning Salon",
    "wof:placetype":"venue"
},
  "geometry": {"coordinates":[-116.96329799999999,44.025362],"type":"Point"}
}