{
  "type": "Feature",
  "properties": {
    "addr:full":"34979 Oakville Rd SW Albany OR 97321",
    "addr:housenumber":"34979",
    "addr:postcode":"97321",
    "addr:street":"Oakville Rd Sw",
    "iso:country":"US",
    "sg:address":"34979 Oakville Rd SW",
    "sg:city":"Albany",
    "sg:classifiers":[
        {
            "category":"Retail",
            "subcategory":"Animal Services",
            "type":"Services"
        }
    ],
    "sg:phone":"+1 541 928 3161",
    "sg:postcode":"97321",
    "sg:province":"OR",
    "sg:tags":[
        "pet",
        "grooming",
        "washing"
    ],
    "wof:name":"Kathe's K-9 Grooming",
    "wof:placetype":"venue"
},
  "geometry": {"coordinates":[-123.14237300000001,44.59347],"type":"Point"}
}