{
  "type": "Feature",
  "properties": {
    "addr:full":"904 Garden Way Ashland OR 97520",
    "addr:housenumber":"904",
    "addr:postcode":"97520",
    "addr:street":"Garden Way",
    "iso:country":"US",
    "sg:address":"904 Garden Way",
    "sg:city":"Ashland",
    "sg:classifiers":[
        {
            "category":"Professional",
            "subcategory":"Business Services",
            "type":"Services"
        }
    ],
    "sg:phone":"+1 541 488 7494",
    "sg:postcode":"97520",
    "sg:province":"OR",
    "sg:tags":[
        "resolution",
        "conflict",
        "mediator"
    ],
    "wof:name":"Theresa Jensen & Associates",
    "wof:placetype":"venue"
},
  "geometry": {"coordinates":[-122.686295,42.179145],"type":"Point"}
}