{
  "type": "Feature",
  "properties": {
    "iso:country":"US",
    "sg:address":"14130 SE Division St",
    "sg:city":"Portland",
    "sg:classifiers":[
        {
            "category":"Restaurant",
            "type":"Food & Drink"
        }
    ],
    "sg:phone":"+1 503 760 4018",
    "sg:postcode":"97236",
    "sg:province":"OR",
    "sg:tags":[
        "mexican"
    ],
    "wof:name":"Don Camaron",
    "wof:placetype":"venue"
},
  "geometry": {"coordinates":[-122.517776,45.503797],"type":"Point"}
}