{
  "type": "Feature",
  "properties": {
    "iso:country":"US",
    "sg:address":"1211 SW 5th Ave",
    "sg:city":"Portland",
    "sg:classifiers":[
        {
            "category":"Professional",
            "subcategory":"Management & Consulting",
            "type":"Services"
        }
    ],
    "sg:phone":"+1 503 221 6500",
    "sg:postcode":"97204",
    "sg:province":"OR",
    "wof:name":"Bearingpoint Inc",
    "wof:placetype":"venue"
},
  "geometry": {"coordinates":[-122.679794,45.5149],"type":"Point"}
}