{
  "type": "Feature",
  "properties": {
    "iso:country":"US",
    "sg:address":"4057 N Mississippi Ave",
    "sg:city":"Portland",
    "sg:classifiers":[
        {
            "category":"Restaurant",
            "type":"Food & Drink"
        }
    ],
    "sg:menulink":"http://www.allmenus.com/or/portland/275409-lovely-hula-hands/menu/",
    "sg:phone":"+1 503 445 9910",
    "sg:postcode":"97227",
    "sg:province":"OR",
    "sg:tags":[
        "new",
        "american"
    ],
    "wof:name":"Lovely Hula Hands",
    "wof:placetype":"venue"
},
  "geometry": {"coordinates":[-122.675696,45.552801],"type":"Point"}
}