{
  "type": "Feature",
  "properties": {
    "addr:full":"7863 SW Capitol Hwy Portland OR 97219",
    "addr:housenumber":"7863",
    "addr:postcode":"97219",
    "addr:street":"Sw Capitol Hwy",
    "iso:country":"US",
    "sg:address":"7863 SW Capitol Hwy",
    "sg:city":"Portland",
    "sg:classifiers":[
        {
            "category":"Shopping",
            "subcategory":"Baby Store",
            "type":"Retail Goods"
        }
    ],
    "sg:phone":"+1 503 245 0700",
    "sg:postcode":"97219",
    "sg:province":"OR",
    "sg:tags":[
        "gear",
        "furniture"
    ],
    "wof:name":"Baby Oh Baby",
    "wof:placetype":"venue"
},
  "geometry": {"coordinates":[-122.71416600000001,45.467884],"type":"Point"}
}