{
  "type": "Feature",
  "properties": {
    "iso:country":"US",
    "sg:address":"1607 NE 41st Ave",
    "sg:city":"Portland",
    "sg:classifiers":[
        {
            "category":"Banks & Credit Unions",
            "subcategory":"Bank",
            "type":"Services"
        }
    ],
    "sg:phone":"+1 503 249 2781",
    "sg:postcode":"97232",
    "sg:province":"OR",
    "sg:tags":[
        "loan",
        "real estate"
    ],
    "wof:name":"Windermere Mortgage Svc",
    "wof:placetype":"venue"
},
  "geometry": {"coordinates":[-122.621364,45.534414],"type":"Point"}
}