{
  "type": "Feature",
  "properties": {
    "addr:full":"7987 SW Mohawk St Tualatin OR 97062",
    "addr:housenumber":"7987",
    "addr:postcode":"97062",
    "addr:street":"Sw Mohawk St",
    "iso:country":"US",
    "sg:address":"7987 SW Mohawk St",
    "sg:city":"Tualatin",
    "sg:classifiers":[
        {
            "category":"Real Estate",
            "subcategory":"Real Estate Agent",
            "type":"Services"
        }
    ],
    "sg:phone":"+1 503 885 1918",
    "sg:postcode":"97062",
    "sg:province":"OR",
    "sg:tags":[
        "investment"
    ],
    "wof:name":"INSIGNIA/Esg Inc",
    "wof:placetype":"venue"
},
  "geometry": {"coordinates":[-122.75859,45.376468],"type":"Point"}
}