{
  "type": "Feature",
  "properties": {
    "iso:country":"US",
    "sg:address":"15 NW 1st St",
    "sg:city":"Gresham",
    "sg:classifiers":[
        {
            "category":"Shopping",
            "subcategory":"Jewelry",
            "type":"Retail Goods"
        }
    ],
    "sg:phone":"+1 503 661 8221",
    "sg:postcode":"97030",
    "sg:province":"OR",
    "sg:tags":[
        "diamond",
        "jeweler"
    ],
    "sg:website":"http://www.aprilsdesignerjewelry.com",
    "wof:name":"April's Designer Jewelry",
    "wof:placetype":"venue"
},
  "geometry": {"coordinates":[-122.431175,45.498348],"type":"Point"}
}