{
  "type": "Feature",
  "properties": {
    "addr:full":"1501 E Jackson St Medford OR 97504",
    "addr:housenumber":"1501",
    "addr:postcode":"97504",
    "addr:street":"E Jackson St",
    "iso:country":"US",
    "sg:address":"1501 E Jackson St",
    "sg:city":"Medford",
    "sg:classifiers":[
        {
            "category":"Education",
            "subcategory":"School",
            "type":"Public Place"
        }
    ],
    "sg:phone":"+1 541 842 3702",
    "sg:postcode":"97504",
    "sg:province":"OR",
    "wof:name":"Schools Public",
    "wof:placetype":"venue"
},
  "geometry": {"coordinates":[-122.85344600000001,42.331267],"type":"Point"}
}