{
  "type": "Feature",
  "properties": {
    "iso:country":"US",
    "sg:address":"5670 SW Powhatan Ave",
    "sg:city":"Tualatin",
    "sg:classifiers":[
        {
            "category":"Building & Trades",
            "subcategory":"Construction",
            "type":"Services"
        }
    ],
    "sg:phone":"+1 503 692 9888",
    "sg:postcode":"97062",
    "sg:province":"OR",
    "sg:tags":[
        "painter"
    ],
    "wof:name":"Color-Wright Solutions Inc",
    "wof:placetype":"venue"
},
  "geometry": {"coordinates":[-122.735237,45.378203],"type":"Point"}
}