{
  "type": "Feature",
  "properties": {
    "iso:country":"US",
    "sg:address":"914 Molalla Ave",
    "sg:city":"Oregon City",
    "sg:classifiers":[
        {
            "category":"Insurance",
            "subcategory":"Insurance Agent",
            "type":"Services"
        }
    ],
    "sg:phone":"+1 503 657 3270",
    "sg:postcode":"97045",
    "sg:province":"OR",
    "wof:name":"Allstate Insurance",
    "wof:placetype":"venue"
},
  "geometry": {"coordinates":[-122.59435999999999,45.34141],"type":"Point"}
}