{
  "type": "Feature",
  "properties": {
    "iso:country":"US",
    "sg:address":"400 N Central Blvd",
    "sg:city":"Coquille",
    "sg:classifiers":[
        {
            "category":"Food & Beverages",
            "subcategory":"Specialty",
            "type":"Retail Goods"
        },
        {
            "category":"Food & Beverages",
            "subcategory":"Groceries & Convenience Stores",
            "type":"Retail Goods"
        }
    ],
    "sg:phone":"+1 541 396 4503",
    "sg:postcode":"97423",
    "sg:province":"OR",
    "sg:tags":[
        "grocers-specialty"
    ],
    "wof:name":"Mckays Market",
    "wof:placetype":"venue"
},
  "geometry": {"coordinates":[-124.189049,43.177952],"type":"Point"}
}