{
  "type": "Feature",
  "properties": {
    "iso:country":"US",
    "sg:address":"735 3rd St SE",
    "sg:city":"Bandon",
    "sg:classifiers":[
        {
            "category":"Deli",
            "type":"Food & Drink"
        },
        {
            "category":"Restaurant",
            "type":"Food & Drink"
        }
    ],
    "sg:phone":"+1 541 347 1336",
    "sg:postcode":"97411",
    "sg:province":"OR",
    "sg:tags":[
        "delicatessen"
    ],
    "wof:name":"Posh Nosh Deli",
    "wof:placetype":"venue"
},
  "geometry": {"coordinates":[-124.406243,43.118592],"type":"Point"}
}