{
  "type": "Feature",
  "properties": {
    "iso:country":"US",
    "sg:address":"2660 NW College Way",
    "sg:city":"Bend",
    "sg:classifiers":[
        {
            "category":"Building & Trades",
            "subcategory":"Construction",
            "type":"Services"
        }
    ],
    "sg:phone":"+1 541 382 2109",
    "sg:postcode":"97701",
    "sg:province":"OR",
    "sg:tags":[
        "builder",
        "operative"
    ],
    "wof:name":"Specialty Homes",
    "wof:placetype":"venue"
},
  "geometry": {"coordinates":[-121.348816,44.07587],"type":"Point"}
}