{
  "type": "Feature",
  "properties": {
    "iso:country":"US",
    "sg:address":"1500 NE Butler Market Rd",
    "sg:city":"Bend",
    "sg:classifiers":[
        {
            "category":"Communications",
            "subcategory":"Radio Station",
            "type":"Services"
        }
    ],
    "sg:phone":"+1 541 389 3333",
    "sg:postcode":"97701",
    "sg:province":"OR",
    "sg:tags":[
        "company",
        "broadcasting"
    ],
    "wof:name":"Gross Communications",
    "wof:placetype":"venue"
},
  "geometry": {"coordinates":[-121.282832,44.079163],"type":"Point"}
}