{
  "type": "Feature",
  "properties": {
    "iso:country":"US",
    "sg:address":"16505 NW Bethany Ct",
    "sg:city":"Beaverton",
    "sg:classifiers":[
        {
            "category":"Professional",
            "type":"Services"
        }
    ],
    "sg:phone":"+1 503 718 4100",
    "sg:postcode":"97006",
    "sg:province":"OR",
    "sg:tags":[
        "establishment"
    ],
    "wof:name":"Avnera",
    "wof:placetype":"venue"
},
  "geometry": {"coordinates":[-122.843692,45.529342],"type":"Point"}
}