{
  "type": "Feature",
  "properties": {
    "iso:country":"US",
    "sg:address":"4858 Ward Dr NE",
    "sg:city":"Salem",
    "sg:classifiers":[
        {
            "category":"Shopping",
            "subcategory":"Computers & Home Electronics",
            "type":"Retail Goods"
        }
    ],
    "sg:phone":"+1 503 393 0303",
    "sg:postcode":"97305",
    "sg:province":"OR",
    "sg:tags":[
        "related"
    ],
    "wof:name":"Belean Bewell",
    "wof:placetype":"venue"
},
  "geometry": {"coordinates":[-122.96256200000001,44.9827],"type":"Point"}
}