{
  "type": "Feature",
  "properties": {
    "addr:full":"2602 SE 162nd Ave Portland OR 97236",
    "addr:housenumber":"2602",
    "addr:postcode":"97236",
    "addr:street":"Se 162Nd Ave",
    "iso:country":"US",
    "sg:address":"2602 SE 162nd Ave",
    "sg:city":"Portland",
    "sg:classifiers":[
        {
            "category":"Shopping",
            "subcategory":"Hobbies, Toys, & Games",
            "type":"Retail Goods"
        }
    ],
    "sg:phone":"+1 503 760 1728",
    "sg:postcode":"97236",
    "sg:province":"OR",
    "wof:name":"Kd Did It Enterprises",
    "wof:placetype":"venue"
},
  "geometry": {"coordinates":[-122.496611,45.503677],"type":"Point"}
}