{
  "type": "Feature",
  "properties": {
    "addr:full":"520 Commercial St Eugene OR 97402",
    "addr:housenumber":"520",
    "addr:postcode":"97402",
    "addr:street":"Commercial St",
    "iso:country":"US",
    "sg:address":"520 Commercial St",
    "sg:city":"Eugene",
    "sg:classifiers":[
        {
            "category":"Building & Trades",
            "subcategory":"Construction",
            "type":"Services"
        }
    ],
    "sg:phone":"+1 541 302 3155",
    "sg:postcode":"97402",
    "sg:province":"OR",
    "sg:tags":[
        "concrete",
        "contractor"
    ],
    "wof:name":"Charles Foote Concrete",
    "wof:placetype":"venue"
},
  "geometry": {"coordinates":[-123.16726800000001,44.053359],"type":"Point"}
}