{
  "type": "Feature",
  "properties": {
    "iso:country":"US",
    "sg:address":"8315 SE 13th Ave",
    "sg:city":"Portland",
    "sg:classifiers":[
        {
            "category":"Shopping",
            "subcategory":"Used Merchandise",
            "type":"Retail Goods"
        }
    ],
    "sg:phone":"+1 503 658 8111",
    "sg:postcode":"97202",
    "sg:province":"OR",
    "sg:tags":[
        "antique"
    ],
    "wof:name":"Wood Pile Antiques",
    "wof:placetype":"venue"
},
  "geometry": {"coordinates":[-122.653001,45.462789],"type":"Point"}
}