{
  "type": "Feature",
  "properties": {
    "iso:country":"US",
    "sg:address":"18643 S Redland Rd",
    "sg:city":"Oregon City",
    "sg:classifiers":[
        {
            "category":"Professional",
            "subcategory":"Computer Services",
            "type":"Services"
        }
    ],
    "sg:phone":"+1 503 631 8980",
    "sg:postcode":"97045",
    "sg:province":"OR",
    "sg:tags":[
        "programing",
        "custom"
    ],
    "wof:name":"Microcomputer Consultants Inc",
    "wof:placetype":"venue"
},
  "geometry": {"coordinates":[-122.47478099999999,45.332866],"type":"Point"}
}