{
  "type": "Feature",
  "properties": {
    "iso:country":"US",
    "sg:address":"30 S 3rd St",
    "sg:city":"Central Point",
    "sg:classifiers":[
        {
            "category":"Restaurant",
            "type":"Food & Drink"
        }
    ],
    "sg:phone":"+1 541 779 9884",
    "sg:postcode":"97502",
    "sg:province":"OR",
    "sg:tags":[
        "wholesale",
        "coffee",
        "commercial",
        "equipment"
    ],
    "sg:website":"www.mellelo.com",
    "wof:name":"Mellelo Coffee Roasters",
    "wof:placetype":"venue"
},
  "geometry": {"coordinates":[-122.914721,42.374434],"type":"Point"}
}