{
  "type": "Feature",
  "properties": {
    "iso:country":"US",
    "sg:address":"9265 SW 74th Ave",
    "sg:city":"Portland",
    "sg:classifiers":[
        {
            "category":"Building & Trades",
            "subcategory":"Construction",
            "type":"Services"
        }
    ],
    "sg:phone":"+1 503 244 8694",
    "sg:postcode":"97223",
    "sg:province":"OR",
    "sg:tags":[
        "system",
        "contractor",
        "air conditioning"
    ],
    "wof:name":"Burke Mechanical",
    "wof:placetype":"venue"
},
  "geometry": {"coordinates":[-122.752672,45.452951],"type":"Point"}
}