{
  "type": "Feature",
  "properties": {
    "iso:country":"US",
    "sg:address":"3355 NE Cornell Rd",
    "sg:city":"Hillsboro",
    "sg:classifiers":[
        {
            "category":"Professional",
            "type":"Services"
        }
    ],
    "sg:phone":"+1 503 681 7668",
    "sg:postcode":"97124",
    "sg:province":"OR",
    "wof:name":"Premier Flying",
    "wof:placetype":"venue"
},
  "geometry": {"coordinates":[-122.946151,45.532199],"type":"Point"}
}