{
  "type": "Feature",
  "properties": {
    "iso:country":"US",
    "sg:address":"1315 Eckloff Rd",
    "sg:city":"Tillamook",
    "sg:classifiers":[
        {
            "category":"Wholesale",
            "subcategory":"Scrap",
            "type":"Manufacturing & Wholesale Goods"
        }
    ],
    "sg:phone":"+1 503 842 4588",
    "sg:postcode":"97141",
    "sg:province":"OR",
    "sg:tags":[
        "recycling",
        "center"
    ],
    "wof:name":"Don Averill Recycling Ctr",
    "wof:placetype":"venue"
},
  "geometry": {"coordinates":[-123.846328,45.416383],"type":"Point"}
}