{
  "type": "Feature",
  "properties": {
    "addr:full":"260 Minnesota Blvd Roseburg OR 97471",
    "addr:housenumber":"260",
    "addr:postcode":"97471",
    "addr:street":"Minnesota Blvd",
    "iso:country":"US",
    "sg:address":"260 Minnesota Blvd",
    "sg:city":"Roseburg",
    "sg:classifiers":[
        {
            "category":"Building & Trades",
            "subcategory":"Electrical",
            "type":"Services"
        }
    ],
    "sg:phone":"+1 541 440 3792",
    "sg:postcode":"97471",
    "sg:province":"OR",
    "sg:tags":[
        "industrial",
        "electrician",
        "contractors-commercial",
        "electric"
    ],
    "wof:name":"Sabin Electric Inc",
    "wof:placetype":"venue"
},
  "geometry": {"coordinates":[-123.49170700000001,43.261822],"type":"Point"}
}