{
  "type": "Feature",
  "properties": {
    "iso:country":"US",
    "sg:address":"9780 SW Shady Ln Ste 215",
    "sg:city":"Portland",
    "sg:classifiers":[
        {
            "category":"Professional",
            "subcategory":"Computer Services",
            "type":"Services"
        }
    ],
    "sg:phone":"+1 503 691 0304",
    "sg:postcode":"97223",
    "sg:province":"OR",
    "sg:tags":[
        "repair"
    ],
    "wof:name":"Computers Unlimited Inc",
    "wof:placetype":"venue"
},
  "geometry": {"coordinates":[-122.777,45.442001],"type":"Point"}
}