{
  "type": "Feature",
  "properties": {
    "iso:country":"US",
    "sg:address":"6805 SE Harold St",
    "sg:city":"Portland",
    "sg:classifiers":[
        {
            "category":"Retail",
            "subcategory":"Animal Services",
            "type":"Services"
        }
    ],
    "sg:phone":"+1 503 775 4104",
    "sg:postcode":"97206",
    "sg:province":"OR",
    "wof:name":"Cherokee Laws",
    "wof:placetype":"venue"
},
  "geometry": {"coordinates":[-122.592496,45.483128],"type":"Point"}
}