{
  "type": "Feature",
  "properties": {
    "iso:country":"US",
    "sg:address":"1695 NE Gillespie Ln",
    "sg:city":"Hermiston",
    "sg:classifiers":[
        {
            "category":"Building & Trades",
            "subcategory":"Construction",
            "type":"Services"
        }
    ],
    "sg:phone":"+1 541 564 9830",
    "sg:postcode":"97838",
    "sg:province":"OR",
    "sg:tags":[
        "excavation",
        "contractor"
    ],
    "wof:name":"Barton Laser Leveling Inc",
    "wof:placetype":"venue"
},
  "geometry": {"coordinates":[-119.25688,45.844799],"type":"Point"}
}