{
  "type": "Feature",
  "properties": {
    "iso:country":"US",
    "sg:address":"1545 Ashland Mine Rd",
    "sg:city":"Ashland",
    "sg:classifiers":[
        {
            "category":"Building & Trades",
            "subcategory":"Cleaning & Sanitation",
            "type":"Services"
        }
    ],
    "sg:phone":"+1 541 488 1271",
    "sg:postcode":"97520",
    "sg:province":"OR",
    "sg:tags":[
        "maintenance"
    ],
    "wof:name":"John Dorsh Construction",
    "wof:placetype":"venue"
},
  "geometry": {"coordinates":[-122.737661,42.211728],"type":"Point"}
}