{
  "type": "Feature",
  "properties": {
    "iso:country":"US",
    "sg:address":"13501 S Mueller Rd",
    "sg:city":"Oregon City",
    "sg:classifiers":[
        {
            "category":"Building & Trades",
            "subcategory":"Construction",
            "type":"Services"
        }
    ],
    "sg:phone":"+1 503 632 7082",
    "sg:postcode":"97045",
    "sg:province":"OR",
    "sg:tags":[
        "contractor"
    ],
    "wof:name":"Custom Gutter Inc",
    "wof:placetype":"venue"
},
  "geometry": {"coordinates":[-122.585508,45.278678],"type":"Point"}
}