{
  "type": "Feature",
  "properties": {
    "iso:country":"US",
    "sg:address":"557 W Washington St",
    "sg:city":"Burns",
    "sg:classifiers":[
        {
            "category":"Health Services",
            "subcategory":"Hospital",
            "type":"Services"
        }
    ],
    "sg:phone":"+1 541 573 7281",
    "sg:postcode":"97720",
    "sg:province":"OR",
    "sg:tags":[
        "medical",
        "clinic"
    ],
    "sg:website":"http://www.harneydh.com",
    "wof:name":"Harney District Hospital",
    "wof:placetype":"venue"
},
  "geometry": {"coordinates":[-119.06050500000001,43.58871],"type":"Point"}
}