{
  "type": "Feature",
  "properties": {
    "iso:country":"US",
    "sg:address":"6309 N Hudson St",
    "sg:city":"Portland",
    "sg:classifiers":[
        {
            "category":"Building & Trades",
            "subcategory":"Construction",
            "type":"Services"
        }
    ],
    "sg:phone":"+1 503 289 8153",
    "sg:postcode":"97203",
    "sg:province":"OR",
    "sg:tags":[
        "roofing",
        "contractor"
    ],
    "wof:name":"Teeter Roofing",
    "wof:placetype":"venue"
},
  "geometry": {"coordinates":[-122.731064,45.587968],"type":"Point"}
}