{
  "type": "Feature",
  "properties": {
    "iso:country":"US",
    "sg:address":"8655 SW White Ct",
    "sg:city":"Portland",
    "sg:classifiers":[
        {
            "category":"Professional",
            "subcategory":"Computer Services",
            "type":"Services"
        }
    ],
    "sg:phone":"+1 503 296 8602",
    "sg:postcode":"97225",
    "sg:province":"OR",
    "sg:tags":[
        "design",
        "system"
    ],
    "wof:name":"Setting Stnes Sgnature Designs",
    "wof:placetype":"venue"
},
  "geometry": {"coordinates":[-122.766676,45.51865],"type":"Point"}
}