{
  "type": "Feature",
  "properties": {
    "addr:full":"901 SW Highland Dr Gresham OR 97080",
    "addr:housenumber":"901",
    "addr:postcode":"97080",
    "addr:street":"Sw Highland Dr",
    "iso:country":"US",
    "sg:address":"901 SW Highland Dr",
    "sg:city":"Gresham",
    "sg:classifiers":[
        {
            "category":"Professional",
            "subcategory":"Accounting & Tax Preparation",
            "type":"Services"
        },
        {
            "category":"Banks & Credit Unions",
            "subcategory":"Financial Services",
            "type":"Services"
        }
    ],
    "sg:phone":"+1 503 492 6373",
    "sg:postcode":"97080",
    "sg:province":"OR",
    "sg:tags":[
        "return",
        "preparation-business",
        "taxes-consultants",
        "loan",
        "reporting",
        "representative",
        "alternative",
        "bookkeeping"
    ],
    "sg:website":"http://www.hrblock.com",
    "wof:name":"H&R Block",
    "wof:placetype":"venue"
},
  "geometry": {"coordinates":[-122.47554700000001,45.490035],"type":"Point"}
}