{
  "type": "Feature",
  "properties": {
    "iso:country":"US",
    "sg:address":"1701 Madras St SE",
    "sg:city":"Salem",
    "sg:classifiers":[
        {
            "category":"Real Estate",
            "subcategory":"Real Estate Operator",
            "type":"Services"
        }
    ],
    "sg:phone":"+1 503 362 8965",
    "sg:postcode":"97306",
    "sg:province":"OR",
    "sg:tags":[
        "building",
        "apartment"
    ],
    "wof:name":"Madras Apartments",
    "wof:placetype":"venue"
},
  "geometry": {"coordinates":[-123.022544,44.867082],"type":"Point"}
}