{
  "type": "Feature",
  "properties": {
    "iso:country":"US",
    "sg:address":"937 N 4th St",
    "sg:city":"Lakeview",
    "sg:classifiers":[
        {
            "category":"Manufacturing",
            "subcategory":"Printing",
            "type":"Manufacturing & Wholesale Goods"
        }
    ],
    "sg:phone":"+1 541 947 2303",
    "sg:postcode":"97630",
    "sg:province":"OR",
    "sg:tags":[
        "commercial",
        "printer",
        "lithographic"
    ],
    "wof:name":"Oregon Highlands Printing Co",
    "wof:placetype":"venue"
},
  "geometry": {"coordinates":[-120.35154199999999,42.193175],"type":"Point"}
}