{
  "type": "Feature",
  "properties": {
    "iso:country":"US",
    "sg:address":"109 McNary Estates Dr N",
    "sg:city":"Salem",
    "sg:classifiers":[
        {
            "category":"Health Services",
            "subcategory":"Health Practitioner",
            "type":"Services"
        }
    ],
    "sg:phone":"+1 503 463 5231",
    "sg:postcode":"97303",
    "sg:province":"OR",
    "wof:name":"McNary Physcl Therapy & Rehab",
    "wof:placetype":"venue"
},
  "geometry": {"coordinates":[-123.02353,45.011006],"type":"Point"}
}