{
  "type": "Feature",
  "properties": {
    "addr:full":"7410 SW Oleson Rd Portland OR 97223",
    "addr:housenumber":"7410",
    "addr:postcode":"97223",
    "addr:street":"Sw Oleson Rd",
    "iso:country":"US",
    "sg:address":"7410 SW Oleson Rd",
    "sg:city":"Portland",
    "sg:classifiers":[
        {
            "category":"Banks & Credit Unions",
            "subcategory":"Bank",
            "type":"Services"
        }
    ],
    "sg:phone":"+1 503 244 9029",
    "sg:postcode":"97223",
    "sg:province":"OR",
    "sg:tags":[
        "national",
        "commercial"
    ],
    "sg:website":"www.wellsfargo.com",
    "wof:name":"Wells Fargo",
    "wof:placetype":"venue"
},
  "geometry": {"coordinates":[-122.75254700000001,45.466514],"type":"Point"}
}