{
  "type": "Feature",
  "properties": {
    "iso:country":"US",
    "sg:address":"660 3rd St",
    "sg:city":"Lafayette",
    "sg:classifiers":[
        {
            "category":"Autos & Motor Vehicles",
            "subcategory":"Automobile Sales",
            "type":"Retail Goods"
        }
    ],
    "sg:phone":"+1 503 864 4530",
    "sg:postcode":"97127",
    "sg:province":"OR",
    "sg:tags":[
        "car",
        "dealer"
    ],
    "wof:name":"American Vehicle Resource",
    "wof:placetype":"venue"
},
  "geometry": {"coordinates":[-123.111765,45.243333],"type":"Point"}
}