{
  "type": "Feature",
  "properties": {
    "iso:country":"US",
    "sg:address":"4962 Regal Dr NE",
    "sg:city":"Salem",
    "sg:classifiers":[
        {
            "category":"Building & Trades",
            "subcategory":"Landscaping Services",
            "type":"Services"
        }
    ],
    "sg:phone":"+1 503 378 1715",
    "sg:postcode":"97301",
    "sg:province":"OR",
    "wof:name":"Landscape Brothers Lawn Care",
    "wof:placetype":"venue"
},
  "geometry": {"coordinates":[-122.964316,44.946944],"type":"Point"}
}