{
  "type": "Feature",
  "properties": {
    "iso:country":"US",
    "sg:address":"2335 SW Briggs Rd",
    "sg:city":"Beaverton",
    "sg:classifiers":[
        {
            "category":"Freight",
            "type":"Transportation"
        }
    ],
    "sg:phone":"+1 503 643 9086",
    "sg:postcode":"97005",
    "sg:province":"OR",
    "sg:tags":[
        "operator",
        "trucking"
    ],
    "wof:name":"Mac Transport",
    "wof:placetype":"venue"
},
  "geometry": {"coordinates":[-122.82022000000001,45.503166],"type":"Point"}
}