{
  "type": "Feature",
  "properties": {
    "iso:country":"US",
    "sg:address":"2121 NE Halsey St",
    "sg:city":"Portland",
    "sg:classifiers":[
        {
            "category":"Health Services",
            "subcategory":"Health Practitioner",
            "type":"Services"
        }
    ],
    "sg:phone":"+1 503 335 7056",
    "sg:postcode":"97232",
    "sg:province":"OR",
    "wof:name":"Shannon ND Braden",
    "wof:placetype":"venue"
},
  "geometry": {"coordinates":[-122.643259,45.533663],"type":"Point"}
}