{
  "type": "Feature",
  "properties": {
    "addr:full":"750 117th Ave NE Salem OR 97317",
    "addr:housenumber":"750",
    "addr:postcode":"97317",
    "addr:street":"117Th Ave Ne",
    "iso:country":"US",
    "sg:address":"750 117th Ave NE",
    "sg:city":"Salem",
    "sg:classifiers":[
        {
            "category":"Shopping",
            "subcategory":"Florist",
            "type":"Retail Goods"
        }
    ],
    "sg:phone":"+1 503 873 2452",
    "sg:postcode":"97317",
    "sg:province":"OR",
    "wof:name":"Bea's Floral Design & School",
    "wof:placetype":"venue"
},
  "geometry": {"coordinates":[-122.819575,44.936689],"type":"Point"}
}