{
  "type": "Feature",
  "properties": {
    "iso:country":"US",
    "sg:address":"9320 SW Barbur Blvd",
    "sg:city":"Portland",
    "sg:classifiers":[
        {
            "category":"Health Services",
            "subcategory":"Clinic",
            "type":"Services"
        }
    ],
    "sg:phone":"+1 503 977 2202",
    "sg:postcode":"97219",
    "sg:province":"OR",
    "sg:tags":[
        "specialty",
        "outpatient"
    ],
    "wof:name":"Genex",
    "wof:placetype":"venue"
},
  "geometry": {"coordinates":[-122.711431,45.457654],"type":"Point"}
}