{
  "type": "Feature",
  "properties": {
    "iso:country":"US",
    "sg:address":"1010 Waverly St",
    "sg:city":"Eugene",
    "sg:classifiers":[
        {
            "category":"Shopping",
            "subcategory":"Hobbies, Toys, & Games",
            "type":"Retail Goods"
        }
    ],
    "sg:phone":"+1 541 343 1347",
    "sg:postcode":"97401",
    "sg:province":"OR",
    "sg:tags":[
        "miniature",
        "collector",
        "for",
        "item"
    ],
    "wof:name":"Victorian Pearl",
    "wof:placetype":"venue"
},
  "geometry": {"coordinates":[-123.056892,44.0738],"type":"Point"}
}