{
  "type": "Feature",
  "properties": {
    "iso:country":"US",
    "sg:address":"1818 NW 156th Ave",
    "sg:city":"Beaverton",
    "sg:classifiers":[
        {
            "category":"Social Services",
            "type":"Services"
        }
    ],
    "sg:phone":"+1 503 617 0531",
    "sg:postcode":"97006",
    "sg:province":"OR",
    "wof:name":"Arise Counseling Center",
    "wof:placetype":"venue"
},
  "geometry": {"coordinates":[-122.836433,45.532939],"type":"Point"}
}