{
  "type": "Feature",
  "properties": {
    "addr:full":"7345 SW Brenne Ln Portland OR 97225",
    "addr:housenumber":"7345",
    "addr:postcode":"97225",
    "addr:street":"Sw Brenne Ln",
    "iso:country":"US",
    "sg:address":"7345 SW Brenne Ln",
    "sg:city":"Portland",
    "sg:classifiers":[
        {
            "category":"Retail",
            "subcategory":"Portrait Studio",
            "type":"Services"
        }
    ],
    "sg:phone":"+1 503 292 9405",
    "sg:postcode":"97225",
    "sg:province":"OR",
    "sg:tags":[
        "photo"
    ],
    "wof:name":"Inner Portrait",
    "wof:placetype":"venue"
},
  "geometry": {"coordinates":[-122.75298100000001,45.492402],"type":"Point"}
}