{
  "type": "Feature",
  "properties": {
    "iso:country":"US",
    "sg:address":"4 SW Sunrise Ct",
    "sg:city":"Hermiston",
    "sg:classifiers":[
        {
            "category":"Personal",
            "subcategory":"Beauty Salon",
            "type":"Services"
        },
        {
            "category":"Personal",
            "subcategory":"Barber",
            "type":"Services"
        }
    ],
    "sg:phone":"+1 541 567 0819",
    "sg:postcode":"97838",
    "sg:province":"OR",
    "wof:name":"The Wild Hare",
    "wof:placetype":"venue"
},
  "geometry": {"coordinates":[-119.312786,45.830994],"type":"Point"}
}