{
  "type": "Feature",
  "properties": {
    "addr:full":"131 Slide Creek Rd Myrtle Creek OR 97457",
    "addr:housenumber":"131",
    "addr:postcode":"97457",
    "addr:street":"Slide Creek Rd",
    "iso:country":"US",
    "sg:address":"131 Slide Creek Rd",
    "sg:city":"Myrtle Creek",
    "sg:classifiers":[
        {
            "category":"Manufacturing",
            "subcategory":"Watercraft",
            "type":"Manufacturing & Wholesale Goods"
        }
    ],
    "sg:phone":"+1 541 863 7820",
    "sg:postcode":"97457",
    "sg:province":"OR",
    "sg:tags":[
        "rebuilt",
        "part",
        "boat"
    ],
    "wof:name":"Little River Boats",
    "wof:placetype":"venue"
},
  "geometry": {"coordinates":[-123.167885,43.088045],"type":"Point"}
}