{
  "type": "Feature",
  "properties": {
    "iso:country":"US",
    "sg:address":"132 E Broadway",
    "sg:city":"Eugene",
    "sg:classifiers":[
        {
            "category":"Professional",
            "subcategory":"Research",
            "type":"Services"
        }
    ],
    "sg:phone":"+1 541 484 5971",
    "sg:postcode":"97401",
    "sg:province":"OR",
    "sg:tags":[
        "development",
        "laboratory",
        "chemical"
    ],
    "wof:name":"Organic Consultants",
    "wof:placetype":"venue"
},
  "geometry": {"coordinates":[-123.090941,44.049843],"type":"Point"}
}