{
  "type": "Feature",
  "properties": {
    "addr:full":"222 NW 5th Ave Portland OR 97209",
    "addr:housenumber":"222",
    "addr:postcode":"97209",
    "addr:street":"Nw 5Th Ave",
    "iso:country":"US",
    "sg:address":"222 NW 5th Ave",
    "sg:city":"Portland",
    "sg:classifiers":[
        {
            "category":"Professional",
            "type":"Services"
        }
    ],
    "sg:phone":"+1 503 222 0694",
    "sg:postcode":"97209",
    "sg:province":"OR",
    "wof:name":"Oregon Creative Services",
    "wof:placetype":"venue"
},
  "geometry": {"coordinates":[-122.675409,45.525062],"type":"Point"}
}