{
  "type": "Feature",
  "properties": {
    "addr:full":"117 NW E St Grants Pass OR 97526",
    "addr:housenumber":"117",
    "addr:postcode":"97526",
    "addr:street":"Nw E St",
    "iso:country":"US",
    "sg:address":"117 NW E St",
    "sg:city":"Grants Pass",
    "sg:classifiers":[
        {
            "category":"Banks & Credit Unions",
            "subcategory":"Investment Brokerage",
            "type":"Services"
        }
    ],
    "sg:phone":"+1 541 479 6432",
    "sg:postcode":"97526",
    "sg:province":"OR",
    "sg:tags":[
        "stock",
        "bond"
    ],
    "wof:name":"Edward Jones Co",
    "wof:placetype":"venue"
},
  "geometry": {"coordinates":[-123.326256,42.440751],"type":"Point"}
}