{
  "type": "Feature",
  "properties": {
    "iso:country":"US",
    "sg:address":"950 9th St",
    "sg:city":"Florence",
    "sg:classifiers":[
        {
            "category":"Health Services",
            "subcategory":"Doctor",
            "type":"Services"
        }
    ],
    "sg:phone":"+1 541 997 8858",
    "sg:postcode":"97439",
    "sg:province":"OR",
    "sg:tags":[
        "dentist"
    ],
    "wof:name":"Dr Ben White Orthodontics",
    "wof:placetype":"venue"
},
  "geometry": {"coordinates":[-124.111859,43.974537],"type":"Point"}
}