{
  "type": "Feature",
  "properties": {
    "iso:country":"US",
    "sg:address":"411 N 2nd Ave",
    "sg:city":"Stayton",
    "sg:classifiers":[
        {
            "category":"Travel",
            "subcategory":"Travel Agent",
            "type":"Entertainment"
        }
    ],
    "sg:phone":"+1 503 769 1499",
    "sg:postcode":"97383",
    "sg:province":"OR",
    "sg:tags":[
        "tours",
        "promoter"
    ],
    "wof:name":"Oregonwest Excursions",
    "wof:placetype":"venue"
},
  "geometry": {"coordinates":[-122.7933,44.79792],"type":"Point"}
}