{
  "type": "Feature",
  "properties": {
    "iso:country":"US",
    "sg:address":"2160 Davcor St SE",
    "sg:city":"Salem",
    "sg:classifiers":[
        {
            "category":"Building & Trades",
            "subcategory":"Construction",
            "type":"Services"
        }
    ],
    "sg:phone":"+1 503 763 0777",
    "sg:postcode":"97302",
    "sg:province":"OR",
    "wof:name":"Crown Castle International",
    "wof:placetype":"venue"
},
  "geometry": {"coordinates":[-123.02074399999999,44.914911],"type":"Point"}
}