{
  "type": "Feature",
  "properties": {
    "iso:country":"US",
    "sg:address":"3131 SW Talbot Rd",
    "sg:city":"Portland",
    "sg:classifiers":[
        {
            "category":"Professional",
            "subcategory":"Computer Services",
            "type":"Services"
        }
    ],
    "sg:phone":"+1 503 227 8258",
    "sg:postcode":"97201",
    "sg:province":"OR",
    "sg:tags":[
        "consultant",
        "designer"
    ],
    "wof:name":"Intel Corp",
    "wof:placetype":"venue"
},
  "geometry": {"coordinates":[-122.70889200000001,45.501216],"type":"Point"}
}