{
  "type": "Feature",
  "properties": {
    "iso:country":"US",
    "sg:address":"1505 SW 18th Ave",
    "sg:city":"Portland",
    "sg:classifiers":[
        {
            "category":"Health Services",
            "subcategory":"Hospital",
            "type":"Services"
        }
    ],
    "sg:phone":"+1 503 226 7935",
    "sg:postcode":"97201",
    "sg:province":"OR",
    "sg:tags":[
        "general"
    ],
    "wof:name":"Oregon/Idaho United Methodist",
    "wof:placetype":"venue"
},
  "geometry": {"coordinates":[-122.693395,45.516219],"type":"Point"}
}