{
  "type": "Feature",
  "properties": {
    "iso:country":"US",
    "sg:address":"3413 Quail Ridge Ln",
    "sg:city":"Eugene",
    "sg:classifiers":[
        {
            "category":"Restaurant",
            "type":"Food & Drink"
        }
    ],
    "sg:phone":"+1 541 688 0529",
    "sg:postcode":"97404",
    "sg:province":"OR",
    "sg:tags":[
        "eating"
    ],
    "wof:name":"Dribble Drive Basketball",
    "wof:placetype":"venue"
},
  "geometry": {"coordinates":[-123.158799,44.113739],"type":"Point"}
}