{
  "type": "Feature",
  "properties": {
    "addr:full":"62900 Mercury Pl Bend OR 97701",
    "addr:housenumber":"62900",
    "addr:postcode":"97701",
    "addr:street":"Mercury Pl",
    "iso:country":"US",
    "sg:address":"62900 Mercury Pl",
    "sg:city":"Bend",
    "sg:classifiers":[
        {
            "category":"Retail",
            "subcategory":"Repair Shop",
            "type":"Services"
        },
        {
            "category":"Real Estate",
            "subcategory":"Real Estate Services",
            "type":"Services"
        },
        {
            "category":"Retail",
            "subcategory":"Laundry & Dry Cleaning",
            "type":"Services"
        },
        {
            "category":"Professional",
            "subcategory":"Business Services",
            "type":"Services"
        },
        {
            "category":"Government",
            "subcategory":"Fire Station",
            "type":"Public Place"
        },
        {
            "category":"Building & Trades",
            "subcategory":"Cleaning & Sanitation",
            "type":"Services"
        }
    ],
    "sg:phone":"+1 541 749 2470",
    "sg:postcode":"97701",
    "sg:province":"OR",
    "sg:tags":[
        "cleaner",
        "disaster",
        "recovery",
        "damage",
        "rug",
        "water",
        "restoration",
        "relief",
        "maintenance",
        "cleaners-interior",
        "inspection",
        "carpet"
    ],
    "sg:website":"http://www.horizonrestoration.com",
    "wof:name":"Horizon Restoration",
    "wof:placetype":"venue"
},
  "geometry": {"coordinates":[-121.289906,44.083779],"type":"Point"}
}