{
  "type": "Feature",
  "properties": {
    "addr:full":"2215 NE 24th Ave Portland OR 97212",
    "addr:housenumber":"2215",
    "addr:postcode":"97212",
    "addr:street":"Ne 24Th Ave",
    "iso:country":"US",
    "sg:address":"2215 NE 24th Ave",
    "sg:city":"Portland",
    "sg:classifiers":[
        {
            "category":"Professional",
            "subcategory":"Business Services",
            "type":"Services"
        }
    ],
    "sg:phone":"+1 503 282 5027",
    "sg:postcode":"97212",
    "sg:province":"OR",
    "sg:tags":[
        "real estate"
    ],
    "wof:name":"Cox Auctions",
    "wof:placetype":"venue"
},
  "geometry": {"coordinates":[-122.641222,45.538071],"type":"Point"}
}