{
  "type": "Feature",
  "properties": {
    "iso:country":"US",
    "sg:address":"913 Lloyd Ctr",
    "sg:city":"Portland",
    "sg:classifiers":[
        {
            "category":"Bars & Pubs",
            "type":"Food & Drink"
        }
    ],
    "sg:menulink":"http://www.allmenus.com/or/portland/5205-stanfords-restaurant--bar/menu/",
    "sg:phone":"+1 503 335 0811",
    "sg:postcode":"97232",
    "sg:province":"OR",
    "sg:tags":[
        "american"
    ],
    "wof:name":"Stanford's Restaurant & Bar",
    "wof:placetype":"venue"
},
  "geometry": {"coordinates":[-122.656036,45.528549],"type":"Point"}
}