{
  "type": "Feature",
  "properties": {
    "addr:full":"295 Northridge Ct N Salem OR 97303",
    "addr:housenumber":"295",
    "addr:postcode":"97303",
    "addr:street":"Northridge Ct N",
    "iso:country":"US",
    "sg:address":"295 Northridge Ct N",
    "sg:city":"Salem",
    "sg:classifiers":[
        {
            "category":"Building & Trades",
            "subcategory":"Construction",
            "type":"Services"
        }
    ],
    "sg:phone":"+1 503 390 4671",
    "sg:postcode":"97303",
    "sg:province":"OR",
    "sg:tags":[
        "house"
    ],
    "wof:name":"Duane Hurley Construction",
    "wof:placetype":"venue"
},
  "geometry": {"coordinates":[-123.02715499999999,45.022285],"type":"Point"}
}