{
  "type": "Feature",
  "properties": {
    "addr:full":"9895 SE Sunnyside Rd Ste D Clackamas OR 97015",
    "addr:housenumber":"9895",
    "addr:postcode":"97015",
    "addr:street":"Se Sunnyside Rd Ste D",
    "iso:country":"US",
    "sg:address":"9895 SE Sunnyside Rd Ste D",
    "sg:city":"Clackamas",
    "sg:classifiers":[
        {
            "category":"Sports & Exercise",
            "subcategory":"Gym",
            "type":"Entertainment"
        }
    ],
    "sg:phone":"+1 503 654 1431",
    "sg:postcode":"97015",
    "sg:province":"OR",
    "sg:website":"www.curves.com",
    "wof:name":"Curves",
    "wof:placetype":"venue"
},
  "geometry": {"coordinates":[-122.56104999999999,45.433633],"type":"Point"}
}