{
  "type": "Feature",
  "properties": {
    "iso:country":"US",
    "sg:address":"63003 Plateau Dr",
    "sg:city":"Bend",
    "sg:classifiers":[
        {
            "category":"Manufacturing",
            "subcategory":"Tools & Machinery",
            "type":"Manufacturing & Wholesale Goods"
        }
    ],
    "sg:phone":"+1 541 330 8641",
    "sg:postcode":"97701",
    "sg:province":"OR",
    "sg:tags":[
        "machine",
        "shop",
        "specialty",
        "miniature"
    ],
    "wof:name":"Minimachine Inc",
    "wof:placetype":"venue"
},
  "geometry": {"coordinates":[-121.29322500000001,44.087984],"type":"Point"}
}