{
  "type": "Feature",
  "properties": {
    "addr:full":"14972 NE Rose Pkwy Portland OR 97230",
    "addr:housenumber":"14972",
    "addr:postcode":"97230",
    "addr:street":"Ne Rose Pkwy",
    "iso:country":"US",
    "sg:address":"14972 NE Rose Pkwy",
    "sg:city":"Portland",
    "sg:classifiers":[
        {
            "category":"Organizations",
            "subcategory":"Membership Organization",
            "type":"Services"
        }
    ],
    "sg:phone":"+1 503 253 5880",
    "sg:postcode":"97230",
    "sg:province":"OR",
    "wof:name":"Jasper Heights Condo Assn",
    "wof:placetype":"venue"
},
  "geometry": {"coordinates":[-122.50876599999999,45.544982],"type":"Point"}
}