{
  "type": "Feature",
  "properties": {
    "iso:country":"US",
    "sg:address":"14972 NE Rose Pkwy",
    "sg:city":"Portland",
    "sg:classifiers":[
        {
            "category":"Organizations",
            "subcategory":"Membership Organization",
            "type":"Services"
        }
    ],
    "sg:phone":"+1 503 253 5880",
    "sg:postcode":"97230",
    "sg:province":"OR",
    "wof:name":"Jasper Heights Condo Assn",
    "wof:placetype":"venue"
},
  "geometry": {"coordinates":[-122.508766,45.544982],"type":"Point"}
}