{
  "type": "Feature",
  "properties": {
    "addr:full":"336 N Main Ave Gresham OR 97030",
    "addr:housenumber":"336",
    "addr:postcode":"97030",
    "addr:street":"N Main Ave",
    "iso:country":"US",
    "sg:address":"336 N Main Ave",
    "sg:city":"Gresham",
    "sg:classifiers":[
        {
            "category":"Shopping",
            "subcategory":"Crafts & Fabrics",
            "type":"Retail Goods"
        }
    ],
    "sg:phone":"+1 503 491 9336",
    "sg:postcode":"97030",
    "sg:province":"OR",
    "sg:tags":[
        "sewing"
    ],
    "wof:name":"About A Dream Quilt Shop",
    "wof:placetype":"venue"
},
  "geometry": {"coordinates":[-122.43088400000001,45.500097],"type":"Point"}
}