{
  "type": "Feature",
  "properties": {
    "iso:country":"US",
    "sg:address":"1050 SE Baseline St",
    "sg:city":"Hillsboro",
    "sg:classifiers":[
        {
            "category":"Organizations",
            "subcategory":"Religious Organization",
            "type":"Services"
        }
    ],
    "sg:phone":"+1 503 693 1990",
    "sg:postcode":"97123",
    "sg:province":"OR",
    "wof:name":"Lighthouse Book & Bible",
    "wof:placetype":"venue"
},
  "geometry": {"coordinates":[-122.971034,45.519867],"type":"Point"}
}