{
  "type": "Feature",
  "properties": {
    "iso:country":"US",
    "sg:address":"2223 NE Oregon St",
    "sg:city":"Portland",
    "sg:classifiers":[
        {
            "category":"Communications",
            "subcategory":"Film & Video Production",
            "type":"Services"
        }
    ],
    "sg:phone":"+1 503 235 3456",
    "sg:postcode":"97232",
    "sg:province":"OR",
    "sg:tags":[
        "motion",
        "picture",
        "photography",
        "videography",
        "taping"
    ],
    "sg:website":"http://www.pixthis.com",
    "wof:name":"Picture This Production Services",
    "wof:placetype":"venue"
},
  "geometry": {"coordinates":[-122.643193,45.528568],"type":"Point"}
}