{
  "type": "Feature",
  "properties": {
    "addr:full":"1005 Granite Hill Rd Grants Pass OR 97526",
    "addr:housenumber":"1005",
    "addr:postcode":"97526",
    "addr:street":"Granite Hill Rd",
    "iso:country":"US",
    "sg:address":"1005 Granite Hill Rd",
    "sg:city":"Grants Pass",
    "sg:classifiers":[
        {
            "category":"Banks & Credit Unions",
            "subcategory":"Financial Services",
            "type":"Services"
        }
    ],
    "sg:phone":"+1 541 955 9250",
    "sg:postcode":"97526",
    "sg:province":"OR",
    "sg:tags":[
        "trust",
        "management"
    ],
    "wof:name":"Baldini Loving Trust",
    "wof:placetype":"venue"
},
  "geometry": {"coordinates":[-123.32405900000001,42.480953],"type":"Point"}
}