{
  "type": "Feature",
  "properties": {
    "addr:full":"780 Blair Blvd Eugene OR 97402",
    "addr:housenumber":"780",
    "addr:postcode":"97402",
    "addr:street":"Blair Blvd",
    "iso:country":"US",
    "sg:address":"780 Blair Blvd",
    "sg:city":"Eugene",
    "sg:classifiers":[
        {
            "category":"Shopping",
            "subcategory":"Books",
            "type":"Retail Goods"
        }
    ],
    "sg:phone":"+1 541 681 9212",
    "sg:postcode":"97402",
    "sg:province":"OR",
    "sg:tags":[
        "dealer"
    ],
    "wof:name":"Foolscap Books",
    "wof:placetype":"venue"
},
  "geometry": {"coordinates":[-123.10579799999999,44.051913],"type":"Point"}
}