{
  "type": "Feature",
  "properties": {
    "iso:country":"US",
    "sg:address":"2710 NW Vaughn St Ste 150",
    "sg:city":"Portland",
    "sg:classifiers":[
        {
            "category":"Health Services",
            "subcategory":"Hospital",
            "type":"Services"
        }
    ],
    "sg:phone":"+1 503 813 2000",
    "sg:postcode":"97210",
    "sg:province":"OR",
    "sg:tags":[
        "medical",
        "surgical",
        "hospitalization",
        "plan"
    ],
    "wof:name":"Kaiser Foundation Health Plan",
    "wof:placetype":"venue"
},
  "geometry": {"coordinates":[-122.70742300000001,45.536773],"type":"Point"}
}