{
  "type": "Feature",
  "properties": {
    "iso:country":"US",
    "sg:address":"1021 NW Highland Ave",
    "sg:city":"Grants Pass",
    "sg:classifiers":[
        {
            "category":"Social Services",
            "subcategory":"Child Care",
            "type":"Services"
        }
    ],
    "sg:phone":"+1 541 474 5495",
    "sg:postcode":"97526",
    "sg:province":"OR",
    "sg:tags":[
        "kindergarten",
        "academic",
        "school"
    ],
    "wof:name":"Josephine County Early Inter",
    "wof:placetype":"venue"
},
  "geometry": {"coordinates":[-123.332415,42.448018],"type":"Point"}
}