{
  "type": "Feature",
  "properties": {
    "iso:country":"US",
    "sg:address":"3110 Pierce Pkwy",
    "sg:city":"Springfield",
    "sg:classifiers":[
        {
            "category":"Military Area",
            "type":"Public Place"
        }
    ],
    "sg:phone":"+1 541 736 4600",
    "sg:postcode":"97477",
    "sg:province":"OR",
    "sg:tags":[
        "force",
        "armed",
        "recruiting"
    ],
    "wof:name":"Oregon Army National Guard",
    "wof:placetype":"venue"
},
  "geometry": {"coordinates":[-122.982114,44.065702],"type":"Point"}
}