{
  "type": "Feature",
  "properties": {
    "iso:country":"US",
    "sg:address":"1135 Court St",
    "sg:city":"Medford",
    "sg:classifiers":[
        {
            "category":"Autos & Motor Vehicles",
            "subcategory":"Automobile Sales",
            "type":"Retail Goods"
        }
    ],
    "sg:phone":"+1 541 779 0075",
    "sg:postcode":"97501",
    "sg:province":"OR",
    "sg:tags":[
        "car",
        "used",
        "dealer"
    ],
    "wof:name":"Dixon Auto Sales Inc",
    "wof:placetype":"venue"
},
  "geometry": {"coordinates":[-122.88054,42.339233],"type":"Point"}
}