{
  "type": "Feature",
  "properties": {
    "iso:country":"US",
    "sg:address":"408 SW Augustus Dr",
    "sg:city":"Dallas",
    "sg:classifiers":[
        {
            "category":"Autos & Motor Vehicles",
            "subcategory":"Auto Supplies",
            "type":"Retail Goods"
        }
    ],
    "sg:phone":"+1 503 623 7821",
    "sg:postcode":"97338",
    "sg:province":"OR",
    "wof:name":"NAPA Battery",
    "wof:placetype":"venue"
},
  "geometry": {"coordinates":[-123.33657700000001,44.925661],"type":"Point"}
}