{
  "type": "Feature",
  "properties": {
    "addr:full":"1535 N Pacific Hwy Woodburn OR 97071",
    "addr:housenumber":"1535",
    "addr:postcode":"97071",
    "addr:street":"N Pacific Hwy",
    "iso:country":"US",
    "sg:address":"1535 N Pacific Hwy",
    "sg:city":"Woodburn",
    "sg:classifiers":[
        {
            "category":"Insurance",
            "subcategory":"Insurance Agent",
            "type":"Services"
        }
    ],
    "sg:phone":"+1 503 981 3201",
    "sg:postcode":"97071",
    "sg:province":"OR",
    "wof:name":"Allstate",
    "wof:placetype":"venue"
},
  "geometry": {"coordinates":[-122.83172999999999,45.150898],"type":"Point"}
}