{
  "type": "Feature",
  "properties": {
    "iso:country":"US",
    "sg:address":"4727 NW Huserik Dr",
    "sg:city":"Portland",
    "sg:classifiers":[
        {
            "category":"Social Services",
            "subcategory":"Child Care",
            "type":"Services"
        }
    ],
    "sg:phone":"+1 503 466 4905",
    "sg:postcode":"97229",
    "sg:province":"OR",
    "sg:tags":[
        "day"
    ],
    "wof:name":"Talentree Advanced Lrng Ctr",
    "wof:placetype":"venue"
},
  "geometry": {"coordinates":[-122.830912,45.553214],"type":"Point"}
}