{
  "type": "Feature",
  "properties": {
    "addr:full":"9500 SW Red Alder Rd Mcminnville OR 97128",
    "addr:housenumber":"9500",
    "addr:postcode":"97128",
    "addr:street":"Sw Red Alder Rd",
    "iso:country":"US",
    "sg:address":"9500 SW Red Alder Rd",
    "sg:city":"Mcminnville",
    "sg:classifiers":[
        {
            "category":"Professional",
            "subcategory":"Research",
            "type":"Services"
        }
    ],
    "sg:phone":"+1 503 472 8186",
    "sg:postcode":"97128",
    "sg:province":"OR",
    "sg:tags":[
        "market",
        "analysis"
    ],
    "wof:name":"CMI Inc",
    "wof:placetype":"venue"
},
  "geometry": {"coordinates":[-123.339294,45.19217],"type":"Point"}
}