{
  "type": "Feature",
  "properties": {
    "addr:full":"20876 King David Ave Bend OR 97702",
    "addr:housenumber":"20876",
    "addr:postcode":"97702",
    "addr:street":"King David Ave",
    "iso:country":"US",
    "sg:address":"20876 King David Ave",
    "sg:city":"Bend",
    "sg:classifiers":[
        {
            "category":"Professional",
            "type":"Services"
        }
    ],
    "sg:phone":"+1 541 389 9609",
    "sg:postcode":"97702",
    "sg:province":"OR",
    "wof:name":"Infinite Dimensions",
    "wof:placetype":"venue"
},
  "geometry": {"coordinates":[-121.281238,44.027399],"type":"Point"}
}