{
  "type": "Feature",
  "properties": {
    "addr:full":"1548 NE Wagon Rd Toledo OR 97391",
    "addr:housenumber":"1548",
    "addr:postcode":"97391",
    "addr:street":"Ne Wagon Rd",
    "iso:country":"US",
    "sg:address":"1548 NE Wagon Rd",
    "sg:city":"Toledo",
    "sg:classifiers":[
        {
            "category":"Manufacturing",
            "subcategory":"Watercraft",
            "type":"Manufacturing & Wholesale Goods"
        }
    ],
    "sg:phone":"+1 541 336 5548",
    "sg:postcode":"97391",
    "sg:province":"OR",
    "wof:name":"Storm Force Fisheries Inc",
    "wof:placetype":"venue"
},
  "geometry": {"coordinates":[-123.932222,44.633255],"type":"Point"}
}