{
  "type": "Feature",
  "properties": {
    "iso:country":"US",
    "sg:address":"873 NE 34th Ave",
    "sg:city":"Hillsboro",
    "sg:classifiers":[
        {
            "category":"Professional",
            "subcategory":"Business Services",
            "type":"Services"
        }
    ],
    "sg:phone":"+1 503 648 1416",
    "sg:postcode":"97124",
    "sg:province":"OR",
    "sg:tags":[
        "convention",
        "meeting",
        "facility"
    ],
    "sg:website":"www.faircomplex.com",
    "wof:name":"Washington County Fair Grounds",
    "wof:placetype":"venue"
},
  "geometry": {"coordinates":[-122.94672199999999,45.531263],"type":"Point"}
}