{
  "type": "Feature",
  "properties": {
    "iso:country":"US",
    "sg:address":"46255 SE Wildcat Mountain Dr",
    "sg:city":"Sandy",
    "sg:classifiers":[
        {
            "category":"Manufacturing",
            "subcategory":"Tools & Machinery",
            "type":"Manufacturing & Wholesale Goods"
        }
    ],
    "sg:phone":"+1 503 668 8546",
    "sg:postcode":"97055",
    "sg:province":"OR",
    "sg:tags":[
        "machine",
        "shop"
    ],
    "wof:name":"Perfectech",
    "wof:placetype":"venue"
},
  "geometry": {"coordinates":[-122.18727,45.338429],"type":"Point"}
}