{
  "type": "Feature",
  "properties": {
    "addr:full":"8215 SW Tualatin Sherwood Rd Tualatin OR 97062",
    "addr:housenumber":"8215",
    "addr:postcode":"97062",
    "addr:street":"Sw Tualatin Sherwood Rd",
    "iso:country":"US",
    "sg:address":"8215 SW Tualatin Sherwood Rd",
    "sg:city":"Tualatin",
    "sg:classifiers":[
        {
            "category":"Insurance",
            "subcategory":"Insurance Agent",
            "type":"Services"
        }
    ],
    "sg:phone":"+1 503 691 8686",
    "sg:postcode":"97062",
    "sg:province":"OR",
    "wof:name":"Kevin B Moore CLU",
    "wof:placetype":"venue"
},
  "geometry": {"coordinates":[-122.759912,45.381336],"type":"Point"}
}