{
  "type": "Feature",
  "properties": {
    "addr:full":"1104 Turkey Crick Ln Roseburg OR 97470",
    "addr:housenumber":"1104",
    "addr:postcode":"97470",
    "addr:street":"Turkey Crick Ln",
    "iso:country":"US",
    "sg:address":"1104 Turkey Crick Ln",
    "sg:city":"Roseburg",
    "sg:classifiers":[
        {
            "category":"Farming",
            "subcategory":"Livestock Farm",
            "type":"Manufacturing & Wholesale Goods"
        }
    ],
    "sg:phone":"+1 541 459 7575",
    "sg:postcode":"97470",
    "sg:province":"OR",
    "sg:tags":[
        "animal",
        "general"
    ],
    "wof:name":"Wind Dancer Ranch",
    "wof:placetype":"venue"
},
  "geometry": {"coordinates":[-123.43767,43.316426],"type":"Point"}
}