{
  "type": "Feature",
  "properties": {
    "iso:country":"US",
    "sg:address":"4016 NE Fremont St",
    "sg:city":"Portland",
    "sg:classifiers":[
        {
            "category":"Personal",
            "subcategory":"Beauty Salon",
            "type":"Services"
        }
    ],
    "sg:phone":"+1 503 281 7831",
    "sg:postcode":"97212",
    "sg:province":"OR",
    "wof:name":"Gary Luckey Hair Design",
    "wof:placetype":"venue"
},
  "geometry": {"coordinates":[-122.62090499999999,45.548224],"type":"Point"}
}