{
  "type": "Feature",
  "properties": {
    "addr:full":"2637 NW Willamina Ave Forest Grove OR 97116",
    "addr:housenumber":"2637",
    "addr:postcode":"97116",
    "addr:street":"Nw Willamina Ave",
    "iso:country":"US",
    "sg:address":"2637 NW Willamina Ave",
    "sg:city":"Forest Grove",
    "sg:classifiers":[
        {
            "category":"Manufacturing",
            "subcategory":"Lumber",
            "type":"Manufacturing & Wholesale Goods"
        }
    ],
    "sg:phone":"+1 503 357 0516",
    "sg:postcode":"97116",
    "sg:province":"OR",
    "sg:tags":[
        "tree",
        "christmas",
        "contract"
    ],
    "wof:name":"Turnbull Christmas Trees",
    "wof:placetype":"venue"
},
  "geometry": {"coordinates":[-123.10103599999999,45.530504],"type":"Point"}
}