{
  "type": "Feature",
  "properties": {
    "iso:country":"US",
    "sg:address":"1151 SW Chamberlain St",
    "sg:city":"Bend",
    "sg:classifiers":[
        {
            "category":"Organizations",
            "subcategory":"Community Association",
            "type":"Services"
        }
    ],
    "sg:phone":"+1 541 383 3267",
    "sg:postcode":"97702",
    "sg:province":"OR",
    "wof:name":"Sct Consulting LLC",
    "wof:placetype":"venue"
},
  "geometry": {"coordinates":[-121.313604,44.039447],"type":"Point"}
}