{
  "type": "Feature",
  "properties": {
    "addr:full":"950 NE Elm St Prineville OR 97754",
    "addr:housenumber":"950",
    "addr:postcode":"97754",
    "addr:street":"Ne Elm St",
    "iso:country":"US",
    "sg:address":"950 NE Elm St",
    "sg:city":"Prineville",
    "sg:classifiers":[
        {
            "category":"Health Services",
            "subcategory":"Nursing And Care Facility",
            "type":"Services"
        }
    ],
    "sg:phone":"+1 541 447 7667",
    "sg:postcode":"97754",
    "sg:province":"OR",
    "sg:tags":[
        "home",
        "convalescent"
    ],
    "sg:website":"www.hilltophealthcare.com",
    "wof:name":"Ochoco Care Ctr",
    "wof:placetype":"venue"
},
  "geometry": {"coordinates":[-120.84241900000001,44.308307],"type":"Point"}
}