{
  "type": "Feature",
  "properties": {
    "iso:country":"US",
    "sg:address":"1250 82nd Dr",
    "sg:city":"Gladstone",
    "sg:classifiers":[
        {
            "category":"Retail",
            "subcategory":"Auto Repair",
            "type":"Services"
        }
    ],
    "sg:phone":"+1 503 655 0746",
    "sg:postcode":"97027",
    "sg:province":"OR",
    "sg:tags":[
        "repairing",
        "automobile",
        "general"
    ],
    "wof:name":"R & R Automotive Inc",
    "wof:placetype":"venue"
},
  "geometry": {"coordinates":[-122.57540299999999,45.391369],"type":"Point"}
}