{
  "type": "Feature",
  "properties": {
    "iso:country":"US",
    "sg:address":"335 NE Blodgett Rd",
    "sg:city":"Yachats",
    "sg:classifiers":[
        {
            "category":"Social Services",
            "subcategory":"Job Training",
            "type":"Services"
        }
    ],
    "sg:phone":"+1 541 547 4657",
    "sg:postcode":"97498",
    "sg:province":"OR",
    "sg:tags":[
        "rehab",
        "government"
    ],
    "wof:name":"Job Corps",
    "wof:placetype":"venue"
},
  "geometry": {"coordinates":[-124.086969,44.362598],"type":"Point"}
}