{
  "type": "Feature",
  "properties": {
    "iso:country":"US",
    "sg:address":"515 N Columbia River Hwy",
    "sg:city":"Saint Helens",
    "sg:classifiers":[
        {
            "category":"Health Services",
            "subcategory":"Doctor",
            "type":"Services"
        }
    ],
    "sg:phone":"+1 503 366 0556",
    "sg:postcode":"97051",
    "sg:province":"OR",
    "wof:name":"Murry Rex D DDS",
    "wof:placetype":"venue"
},
  "geometry": {"coordinates":[-122.819879,45.860678],"type":"Point"}
}