{
  "type": "Feature",
  "properties": {
    "iso:country":"US",
    "sg:address":"4724 SW Pomona St",
    "sg:city":"Portland",
    "sg:classifiers":[
        {
            "category":"Building & Trades",
            "subcategory":"Plumbing",
            "type":"Services"
        }
    ],
    "sg:phone":"+1 503 246 1201",
    "sg:postcode":"97219",
    "sg:province":"OR",
    "sg:tags":[
        "plumbing",
        "contractor"
    ],
    "wof:name":"Grand Prix Plumbing & Mech",
    "wof:placetype":"venue"
},
  "geometry": {"coordinates":[-122.72644,45.445298],"type":"Point"}
}