{
  "type": "Feature",
  "properties": {
    "addr:full":"829 SE 15th Avenue Portland OR 97214",
    "addr:housenumber":"829",
    "addr:postcode":"97214",
    "addr:street":"Se 15Th Avenue",
    "iso:country":"US",
    "sg:address":"829 SE 15th Avenue",
    "sg:city":"Portland",
    "sg:classifiers":[
        {
            "category":"Real Estate",
            "subcategory":"Real Estate Operator",
            "type":"Services"
        }
    ],
    "sg:phone":"+1 503 234 0667",
    "sg:postcode":"97214",
    "sg:province":"OR",
    "sg:tags":[
        "apartment"
    ],
    "wof:name":"Wellesley Court Apartments",
    "wof:placetype":"venue"
},
  "geometry": {"coordinates":[-122.65062399999999,45.516995],"type":"Point"}
}