{
  "type": "Feature",
  "properties": {
    "addr:full":"7750 Annen Ln NE Mount Angel OR 97362",
    "addr:housenumber":"7750",
    "addr:postcode":"97362",
    "addr:street":"Annen Ln Ne",
    "iso:country":"US",
    "sg:address":"7750 Annen Ln NE",
    "sg:city":"Mount Angel",
    "sg:phone":"+1 503 845 2494",
    "sg:postcode":"97362",
    "sg:province":"OR",
    "sg:tags":[
        "farm",
        "field",
        "crop"
    ],
    "wof:name":"Annen Bros Farm Shop",
    "wof:placetype":"venue"
},
  "geometry": {"coordinates":[-122.77681200000001,45.040119],"type":"Point"}
}