{
  "type": "Feature",
  "properties": {
    "iso:country":"US",
    "sg:address":"17805 SE 82nd Dr",
    "sg:city":"Gladstone",
    "sg:classifiers":[
        {
            "category":"Personal",
            "subcategory":"Day Spa",
            "type":"Services"
        },
        {
            "category":"Sports & Exercise",
            "subcategory":"Swimming Pool",
            "type":"Entertainment"
        }
    ],
    "sg:phone":"+1 503 650 7727",
    "sg:postcode":"97027",
    "sg:province":"OR",
    "sg:tags":[
        "repair",
        "hot",
        "tub"
    ],
    "sg:website":"http://www.calspasoforegon.com",
    "wof:name":"Cal Spas Of Oregon",
    "wof:placetype":"venue"
},
  "geometry": {"coordinates":[-122.574236,45.393956],"type":"Point"}
}