{
  "type": "Feature",
  "properties": {
    "addr:full":"235 SW Century Dr Bend OR 97702",
    "addr:housenumber":"235",
    "addr:postcode":"97702",
    "addr:street":"Sw Century Dr",
    "iso:country":"US",
    "sg:address":"235 SW Century Dr",
    "sg:city":"Bend",
    "sg:classifiers":[
        {
            "category":"Restaurant",
            "type":"Food & Drink"
        }
    ],
    "sg:phone":"+1 541 382 2848",
    "sg:postcode":"97702",
    "sg:province":"OR",
    "sg:tags":[
        "eating"
    ],
    "wof:name":"Howards Catering Etc",
    "wof:placetype":"venue"
},
  "geometry": {"coordinates":[-121.33184300000001,44.04816],"type":"Point"}
}