{
  "type": "Feature",
  "properties": {
    "addr:full":"434 Redwood St Brookings OR 97415",
    "addr:housenumber":"434",
    "addr:postcode":"97415",
    "addr:street":"Redwood St",
    "iso:country":"US",
    "sg:address":"434 Redwood St",
    "sg:city":"Brookings",
    "sg:classifiers":[
        {
            "category":"Professional",
            "subcategory":"Accounting & Tax Preparation",
            "type":"Services"
        }
    ],
    "sg:phone":"+1 541 469 3350",
    "sg:postcode":"97415",
    "sg:province":"OR",
    "sg:tags":[
        "return"
    ],
    "wof:name":"Debbies Tax Service",
    "wof:placetype":"venue"
},
  "geometry": {"coordinates":[-124.27735,42.05475],"type":"Point"}
}