{
  "type": "Feature",
  "properties": {
    "addr:full":"4450 SE McLoughlin Boulevard Portland OR 97202",
    "addr:housenumber":"4450",
    "addr:postcode":"97202",
    "addr:street":"Se Mcloughlin Boulevard",
    "iso:country":"US",
    "sg:address":"4450 SE McLoughlin Boulevard",
    "sg:city":"Portland",
    "sg:classifiers":[
        {
            "category":"Autos & Motor Vehicles",
            "subcategory":"Fuel & Gas Station",
            "type":"Retail Goods"
        }
    ],
    "sg:phone":"+1 503 231 5737",
    "sg:postcode":"97202",
    "sg:province":"OR",
    "wof:name":"Ram Gas & Food Mart",
    "wof:placetype":"venue"
},
  "geometry": {"coordinates":[-122.654358,45.490356],"type":"Point"}
}