{
  "type": "Feature",
  "properties": {
    "iso:country":"US",
    "sg:address":"694 Moorea Dr",
    "sg:city":"Roseburg",
    "sg:classifiers":[
        {
            "category":"Professional",
            "subcategory":"Business Services",
            "type":"Services"
        }
    ],
    "sg:phone":"+1 541 673 5730",
    "sg:postcode":"97470",
    "sg:province":"OR",
    "wof:name":"Ro Glo Enterprises Inc",
    "wof:placetype":"venue"
},
  "geometry": {"coordinates":[-123.38099099999999,43.243476],"type":"Point"}
}