{
  "type": "Feature",
  "properties": {
    "iso:country":"US",
    "sg:address":"4455 Marion St SE",
    "sg:city":"Albany",
    "sg:classifiers":[
        {
            "category":"Manufacturing",
            "subcategory":"Metals",
            "type":"Manufacturing & Wholesale Goods"
        }
    ],
    "sg:phone":"+1 541 928 1133",
    "sg:postcode":"97322",
    "sg:province":"OR",
    "sg:tags":[
        "steel"
    ],
    "wof:name":"Pacific Fabricators & Constrs",
    "wof:placetype":"venue"
},
  "geometry": {"coordinates":[-123.097883,44.602273],"type":"Point"}
}