{
  "type": "Feature",
  "properties": {
    "iso:country":"US",
    "sg:address":"265 SE Oak St",
    "sg:city":"Hillsboro",
    "sg:classifiers":[
        {
            "category":"Health Services",
            "subcategory":"Health Practitioner",
            "type":"Services"
        }
    ],
    "sg:phone":"+1 503 693 6390",
    "sg:postcode":"97123",
    "sg:province":"OR",
    "sg:tags":[
        "psychologist"
    ],
    "sg:website":"www.westernpsych.com",
    "wof:name":"Western Psychological Svc",
    "wof:placetype":"venue"
},
  "geometry": {"coordinates":[-122.98644400000001,45.518886],"type":"Point"}
}