{
  "type": "Feature",
  "properties": {
    "iso:country":"US",
    "sg:address":"38965 Pioneer Blvd",
    "sg:city":"Sandy",
    "sg:classifiers":[
        {
            "category":"Insurance",
            "subcategory":"Insurance Agent",
            "type":"Services"
        }
    ],
    "sg:phone":"+1 503 668 7977",
    "sg:postcode":"97055",
    "sg:province":"OR",
    "wof:name":"American Family Insurance",
    "wof:placetype":"venue"
},
  "geometry": {"coordinates":[-122.26254,45.396373],"type":"Point"}
}