{
  "type": "Feature",
  "properties": {
    "iso:country":"US",
    "sg:address":"15120 Hwy 36",
    "sg:city":"Deadwood",
    "sg:classifiers":[
        {
            "category":"Manufacturing",
            "subcategory":"Lumber",
            "type":"Manufacturing & Wholesale Goods"
        }
    ],
    "sg:phone":"+1 541 964 3345",
    "sg:postcode":"97430",
    "sg:province":"OR",
    "sg:tags":[
        "logging"
    ],
    "wof:name":"Wilbur Logging Co",
    "wof:placetype":"venue"
},
  "geometry": {"coordinates":[-123.732939,44.096077],"type":"Point"}
}