{
  "type": "Feature",
  "properties": {
    "iso:country":"US",
    "sg:address":"18153 Powers Creek Loop Rd NE",
    "sg:city":"Silverton",
    "sg:classifiers":[
        {
            "category":"Building & Trades",
            "subcategory":"Landscaping Services",
            "type":"Services"
        }
    ],
    "sg:phone":"+1 503 873 2043",
    "sg:postcode":"97381",
    "sg:province":"OR",
    "sg:tags":[
        "tree"
    ],
    "wof:name":"Alpine Tree Farms",
    "wof:placetype":"venue"
},
  "geometry": {"coordinates":[-122.661851,44.961813],"type":"Point"}
}