{
  "type": "Feature",
  "properties": {
    "iso:country":"US",
    "sg:address":"17824 Shank Rd NE",
    "sg:city":"Hubbard",
    "sg:classifiers":[
        {
            "category":"Manufacturing",
            "subcategory":"Signs",
            "type":"Manufacturing & Wholesale Goods"
        }
    ],
    "sg:phone":"+1 503 982 8140",
    "sg:postcode":"97032",
    "sg:province":"OR",
    "sg:tags":[
        "specialty",
        "mfg"
    ],
    "wof:name":"It's A Good Sign",
    "wof:placetype":"venue"
},
  "geometry": {"coordinates":[-122.79024200000001,45.178035],"type":"Point"}
}