{
  "type": "Feature",
  "properties": {
    "iso:country":"US",
    "sg:address":"5816 SW Hood Ave",
    "sg:city":"Portland",
    "sg:classifiers":[
        {
            "category":"Personal",
            "type":"Services"
        }
    ],
    "sg:phone":"+1 503 473 8119",
    "sg:postcode":"97239",
    "sg:province":"OR",
    "sg:tags":[
        "therapist",
        "massage"
    ],
    "wof:name":"Tranquil Connections",
    "wof:placetype":"venue"
},
  "geometry": {"coordinates":[-122.674797,45.48168],"type":"Point"}
}