{
  "type": "Feature",
  "properties": {
    "addr:full":"1060 12th St SE Salem OR 97302",
    "addr:housenumber":"1060",
    "addr:postcode":"97302",
    "addr:street":"12Th St Se",
    "iso:country":"US",
    "sg:address":"1060 12th St SE",
    "sg:city":"Salem",
    "sg:classifiers":[
        {
            "category":"Retail",
            "subcategory":"Auto Repair",
            "type":"Services"
        }
    ],
    "sg:phone":"+1 503 588 1688",
    "sg:postcode":"97302",
    "sg:province":"OR",
    "sg:tags":[
        "automotive",
        "fabrication"
    ],
    "wof:name":"Deanos Customs",
    "wof:placetype":"venue"
},
  "geometry": {"coordinates":[-123.03056599999999,44.926891],"type":"Point"}
}