{
  "type": "Feature",
  "properties": {
    "iso:country":"US",
    "sg:address":"2112 N Park Ave",
    "sg:city":"Eugene",
    "sg:classifiers":[
        {
            "category":"Wholesale",
            "subcategory":"Non-durable Goods",
            "type":"Manufacturing & Wholesale Goods"
        }
    ],
    "sg:phone":"+1 541 461 2337",
    "sg:postcode":"97404",
    "sg:province":"OR",
    "wof:name":"Studio M Creative",
    "wof:placetype":"venue"
},
  "geometry": {"coordinates":[-123.143947,44.097186],"type":"Point"}
}