{
  "type": "Feature",
  "properties": {
    "addr:full":"2502 SE Belmont St Portland OR 97214",
    "addr:housenumber":"2502",
    "addr:postcode":"97214",
    "addr:street":"Se Belmont St",
    "iso:country":"US",
    "sg:address":"2502 SE Belmont St",
    "sg:city":"Portland",
    "sg:classifiers":[
        {
            "category":"Real Estate",
            "subcategory":"Real Estate Agent",
            "type":"Services"
        }
    ],
    "sg:phone":"+1 503 234 3689",
    "sg:postcode":"97214",
    "sg:province":"OR",
    "wof:name":"Rivertown Realtors",
    "wof:placetype":"venue"
},
  "geometry": {"coordinates":[-122.639144,45.516366],"type":"Point"}
}