{
  "type": "Feature",
  "properties": {
    "iso:country":"US",
    "sg:address":"3637 SW 57th Ave",
    "sg:city":"Portland",
    "sg:classifiers":[
        {
            "category":"Professional",
            "subcategory":"Business Services",
            "type":"Services"
        }
    ],
    "sg:phone":"+1 503 297 3082",
    "sg:postcode":"97221",
    "sg:province":"OR",
    "wof:name":"Crumpacker & Smith Enterprises",
    "wof:placetype":"venue"
},
  "geometry": {"coordinates":[-122.735483,45.49681],"type":"Point"}
}