{
  "type": "Feature",
  "properties": {
    "iso:country":"US",
    "sg:address":"616 Industrial St",
    "sg:city":"Hood River",
    "sg:classifiers":[
        {
            "category":"Manufacturing",
            "subcategory":"Wood Products",
            "type":"Manufacturing & Wholesale Goods"
        }
    ],
    "sg:phone":"+1 541 387 2280",
    "sg:postcode":"97031",
    "sg:province":"OR",
    "sg:tags":[
        "mfg"
    ],
    "wof:name":"Pacific Molding",
    "wof:placetype":"venue"
},
  "geometry": {"coordinates":[-121.51810500000001,45.710933],"type":"Point"}
}