{
  "type": "Feature",
  "properties": {
    "addr:full":"8010 SW Mapleleaf St Portland OR 97223",
    "addr:housenumber":"8010",
    "addr:postcode":"97223",
    "addr:street":"Sw Mapleleaf St",
    "iso:country":"US",
    "sg:address":"8010 SW Mapleleaf St",
    "sg:city":"Portland",
    "sg:classifiers":[
        {
            "category":"Shopping",
            "subcategory":"Discount & Variety Stores",
            "type":"Retail Goods"
        }
    ],
    "sg:phone":"+1 503 245 3908",
    "sg:postcode":"97223",
    "sg:province":"OR",
    "sg:tags":[
        "merchandise",
        "general"
    ],
    "wof:name":"Roberts Products",
    "wof:placetype":"venue"
},
  "geometry": {"coordinates":[-122.761335,45.445395],"type":"Point"}
}