{
  "type": "Feature",
  "properties": {
    "addr:full":"541 SW 15th St Redmond OR 97756",
    "addr:housenumber":"541",
    "addr:postcode":"97756",
    "addr:street":"Sw 15Th St",
    "iso:country":"US",
    "sg:address":"541 SW 15th St",
    "sg:city":"Redmond",
    "sg:classifiers":[
        {
            "category":"Real Estate",
            "subcategory":"Real Estate Agent",
            "type":"Services"
        }
    ],
    "sg:phone":"+1 541 548 7633",
    "sg:postcode":"97756",
    "sg:province":"OR",
    "wof:name":"Northwest Commercial RE Svc",
    "wof:placetype":"venue"
},
  "geometry": {"coordinates":[-121.184167,44.272457],"type":"Point"}
}