{
  "type": "Feature",
  "properties": {
    "addr:full":"1330 SE 39th Avenue Portland OR 97214",
    "addr:housenumber":"1330",
    "addr:postcode":"97214",
    "addr:street":"Se 39Th Avenue",
    "iso:country":"US",
    "sg:address":"1330 SE 39th Avenue",
    "sg:city":"Portland",
    "sg:classifiers":[
        {
            "category":"Personal",
            "subcategory":"Day Spa",
            "type":"Services"
        }
    ],
    "sg:phone":"+1 503 232 1200",
    "sg:postcode":"97214",
    "sg:province":"OR",
    "wof:name":"Healthquest Spa",
    "wof:placetype":"venue"
},
  "geometry": {"coordinates":[-122.623051,45.513],"type":"Point"}
}