{
  "type": "Feature",
  "properties": {
    "iso:country":"US",
    "sg:address":"33864 E Loop Rd",
    "sg:city":"Stanfield",
    "sg:classifiers":[
        {
            "category":"Building & Trades",
            "subcategory":"Construction",
            "type":"Services"
        }
    ],
    "sg:phone":"+1 541 567 6222",
    "sg:postcode":"97875",
    "sg:province":"OR",
    "sg:tags":[
        "residential",
        "nonresidential"
    ],
    "wof:name":"Mike Norton Construction Inc",
    "wof:placetype":"venue"
},
  "geometry": {"coordinates":[-119.17152299999999,45.846026],"type":"Point"}
}