{
  "type": "Feature",
  "properties": {
    "iso:country":"US",
    "sg:address":"3111 Santiam Hwy SE",
    "sg:city":"Albany",
    "sg:classifiers":[
        {
            "category":"Health Services",
            "subcategory":"Health Practitioner",
            "type":"Services"
        }
    ],
    "sg:phone":"+1 541 791 4959",
    "sg:postcode":"97322",
    "sg:province":"OR",
    "sg:tags":[
        "pathologist",
        "speech"
    ],
    "wof:name":"Speech Language & Accent",
    "wof:placetype":"venue"
},
  "geometry": {"coordinates":[-123.066909,44.630679],"type":"Point"}
}