{
  "type": "Feature",
  "properties": {
    "addr:full":"8835 SW Canyon Lane Portland OR 97225",
    "addr:housenumber":"8835",
    "addr:postcode":"97225",
    "addr:street":"Sw Canyon Lane",
    "iso:country":"US",
    "sg:address":"8835 SW Canyon Lane",
    "sg:city":"Portland",
    "sg:classifiers":[
        {
            "category":"Building & Trades",
            "subcategory":"Construction",
            "type":"Services"
        }
    ],
    "sg:phone":"+1 503 384 9056",
    "sg:postcode":"97225",
    "sg:province":"OR",
    "sg:tags":[
        "contractor"
    ],
    "wof:name":"Crown Construction of Oregon",
    "wof:placetype":"venue"
},
  "geometry": {"coordinates":[-122.76732699999999,45.498413],"type":"Point"}
}