{
  "type": "Feature",
  "properties": {
    "addr:full":"3320 SE Holgate Blvd Portland OR 97202",
    "addr:housenumber":"3320",
    "addr:postcode":"97202",
    "addr:street":"Se Holgate Blvd",
    "iso:country":"US",
    "sg:address":"3320 SE Holgate Blvd",
    "sg:city":"Portland",
    "sg:classifiers":[
        {
            "category":"Building & Trades",
            "subcategory":"Locksmith",
            "type":"Services"
        }
    ],
    "sg:phone":"+1 503 715 3770",
    "sg:postcode":"97202",
    "sg:province":"OR",
    "sg:tags":[
        "key"
    ],
    "wof:name":"Available Locksmith",
    "wof:placetype":"venue"
},
  "geometry": {"coordinates":[-122.630668,45.490441],"type":"Point"}
}