{
  "type": "Feature",
  "properties": {
    "iso:country":"US",
    "sg:address":"600 NW 14th Ave",
    "sg:city":"Portland",
    "sg:classifiers":[
        {
            "category":"Personal",
            "type":"Services"
        }
    ],
    "sg:phone":"+1 503 595 5210",
    "sg:postcode":"97209",
    "sg:province":"OR",
    "sg:tags":[
        "consultant",
        "wedding"
    ],
    "wof:name":"Pearl Concierge",
    "wof:placetype":"venue"
},
  "geometry": {"coordinates":[-122.685345,45.527893],"type":"Point"}
}