{
  "type": "Feature",
  "properties": {
    "addr:full":"52507 Columbia River Hwy Scappoose OR 97056",
    "addr:housenumber":"52507",
    "addr:postcode":"97056",
    "addr:street":"Columbia River Hwy",
    "iso:country":"US",
    "sg:address":"52507 Columbia River Hwy",
    "sg:city":"Scappoose",
    "sg:classifiers":[
        {
            "category":"Shopping",
            "subcategory":"Tobacco",
            "type":"Retail Goods"
        }
    ],
    "sg:phone":"+1 503 543 7900",
    "sg:postcode":"97056",
    "sg:province":"OR",
    "sg:tags":[
        "cigarette",
        "cigar",
        "dealer"
    ],
    "wof:name":"Scappoose Smoke Shop",
    "wof:placetype":"venue"
},
  "geometry": {"coordinates":[-122.87813300000001,45.757384],"type":"Point"}
}