{
  "type": "Feature",
  "properties": {
    "iso:country":"US",
    "sg:address":"29738 Ellensburg Ave",
    "sg:city":"Gold Beach",
    "sg:classifiers":[
        {
            "category":"Personal",
            "subcategory":"Beauty Salon",
            "type":"Services"
        }
    ],
    "sg:phone":"+1 541 247 0760",
    "sg:postcode":"97444",
    "sg:province":"OR",
    "sg:tags":[
        "shop"
    ],
    "wof:name":"Country Cuttin'",
    "wof:placetype":"venue"
},
  "geometry": {"coordinates":[-124.420624,42.414758],"type":"Point"}
}