{
  "type": "Feature",
  "properties": {
    "iso:country":"US",
    "sg:address":"3130 Kathryn Ave NE",
    "sg:city":"Albany",
    "sg:classifiers":[
        {
            "category":"Building & Trades",
            "subcategory":"Electrical",
            "type":"Services"
        },
        {
            "category":"Wholesale",
            "subcategory":"Electrical",
            "type":"Manufacturing & Wholesale Goods"
        }
    ],
    "sg:phone":"+1 541 924 9120",
    "sg:postcode":"97321",
    "sg:province":"OR",
    "sg:tags":[
        "equipment",
        "contractor",
        "electric",
        "supply"
    ],
    "sg:website":"www.northcoastelectric.com",
    "wof:name":"North Coast Electric Company",
    "wof:placetype":"venue"
},
  "geometry": {"coordinates":[-123.06535100000001,44.645463],"type":"Point"}
}