{
  "type": "Feature",
  "properties": {
    "iso:country":"US",
    "sg:address":"1185 S Elm Street",
    "sg:city":"Portland",
    "sg:classifiers":[
        {
            "category":"Health Services",
            "subcategory":"Doctor",
            "type":"Services"
        }
    ],
    "sg:phone":"+1 503 723 4660",
    "sg:postcode":"97201",
    "sg:province":"OR",
    "sg:tags":[
        "practice",
        "family"
    ],
    "wof:name":"Pacific Medical Group",
    "wof:placetype":"venue"
},
  "geometry": {"coordinates":[-122.689333,45.511105],"type":"Point"}
}