{
  "type": "Feature",
  "properties": {
    "iso:country":"US",
    "sg:address":"12390 SW Winter Lake Dr",
    "sg:city":"Portland",
    "sg:classifiers":[
        {
            "category":"Professional",
            "subcategory":"Employment Agencies",
            "type":"Services"
        }
    ],
    "sg:phone":"+1 503 317 0218",
    "sg:postcode":"97223",
    "sg:province":"OR",
    "sg:tags":[
        "employee",
        "leasing"
    ],
    "wof:name":"Innovative Contract Staffing",
    "wof:placetype":"venue"
},
  "geometry": {"coordinates":[-122.804996,45.435363],"type":"Point"}
}