{
  "type": "Feature",
  "properties": {
    "iso:country":"US",
    "sg:address":"2540 Applegate St",
    "sg:city":"Philomath",
    "sg:classifiers":[
        {
            "category":"Organizations",
            "subcategory":"Religious Organization",
            "type":"Services"
        }
    ],
    "sg:phone":"+1 541 929 5504",
    "sg:postcode":"97370",
    "sg:province":"OR",
    "sg:tags":[
        "churches-lutheran"
    ],
    "sg:website":"www.home.comcast.net/peace_lutheran_chur",
    "wof:name":"Peace Lutheran Church",
    "wof:placetype":"venue"
},
  "geometry": {"coordinates":[-123.34762600000001,44.539288],"type":"Point"}
}