{
  "type": "Feature",
  "properties": {
    "addr:full":"4410 N Fessenden St Portland OR 97203",
    "addr:housenumber":"4410",
    "addr:postcode":"97203",
    "addr:street":"N Fessenden St",
    "iso:country":"US",
    "sg:address":"4410 N Fessenden St",
    "sg:city":"Portland",
    "sg:classifiers":[
        {
            "category":"Professional",
            "subcategory":"Computer Services",
            "type":"Services"
        }
    ],
    "sg:phone":"+1 971 506 5224",
    "sg:postcode":"97203",
    "sg:province":"OR",
    "sg:tags":[
        "publisher",
        "software",
        "developer"
    ],
    "wof:name":"Qinfasoft",
    "wof:placetype":"venue"
},
  "geometry": {"coordinates":[-122.714521,45.591479],"type":"Point"}
}