{
  "type": "Feature",
  "properties": {
    "iso:country":"US",
    "sg:address":"21210 Chilliwack Way",
    "sg:city":"Bend",
    "sg:classifiers":[
        {
            "category":"Building & Trades",
            "subcategory":"Construction",
            "type":"Services"
        }
    ],
    "sg:phone":"+1 541 388 0504",
    "sg:postcode":"97702",
    "sg:province":"OR",
    "sg:tags":[
        "carpentry",
        "contractor"
    ],
    "wof:name":"Robert Hurworth Enterprises",
    "wof:placetype":"venue"
},
  "geometry": {"coordinates":[-121.26089899999999,44.045758],"type":"Point"}
}