{
  "type": "Feature",
  "properties": {
    "iso:country":"US",
    "sg:address":"1135 SW Washington St",
    "sg:city":"Portland",
    "sg:classifiers":[
        {
            "category":"Restaurant",
            "type":"Food & Drink"
        }
    ],
    "sg:phone":"+1 503 243 2181",
    "sg:postcode":"97205",
    "sg:province":"OR",
    "sg:tags":[
        "eating"
    ],
    "wof:name":"S Estephano",
    "wof:placetype":"venue"
},
  "geometry": {"coordinates":[-122.683147,45.521863],"type":"Point"}
}