{
  "type": "Feature",
  "properties": {
    "iso:country":"US",
    "sg:address":"2010 NE Tilbury St",
    "sg:city":"Mcminnville",
    "sg:classifiers":[
        {
            "category":"Organizations",
            "subcategory":"Religious Organization",
            "type":"Services"
        }
    ],
    "sg:phone":"+1 503 864 2716",
    "sg:postcode":"97128",
    "sg:province":"OR",
    "sg:tags":[
        "church"
    ],
    "wof:name":"Jehovah's Witnesses",
    "wof:placetype":"venue"
},
  "geometry": {"coordinates":[-123.17881,45.203091],"type":"Point"}
}