{
  "type": "Feature",
  "properties": {
    "iso:country":"US",
    "sg:address":"250 NW Kings Blvd",
    "sg:city":"Corvallis",
    "sg:classifiers":[
        {
            "category":"Professional",
            "type":"Services"
        }
    ],
    "sg:phone":"+1 541 754 1048",
    "sg:postcode":"97330",
    "sg:province":"OR",
    "wof:name":"Elizabeth Barnum",
    "wof:placetype":"venue"
},
  "geometry": {"coordinates":[-123.27519,44.569652],"type":"Point"}
}