{
  "type": "Feature",
  "properties": {
    "iso:country":"US",
    "sg:address":"16209 W Hoffeldt Ln Ste C",
    "sg:city":"Brookings",
    "sg:classifiers":[
        {
            "category":"Personal",
            "subcategory":"Beauty Salon",
            "type":"Services"
        }
    ],
    "sg:phone":"+1 541 412 7666",
    "sg:postcode":"97415",
    "sg:province":"OR",
    "wof:name":"Tangles",
    "wof:placetype":"venue"
},
  "geometry": {"coordinates":[-124.258728,42.048359],"type":"Point"}
}