{
  "type": "Feature",
  "properties": {
    "iso:country":"US",
    "sg:address":"1488 Angel Crest Dr",
    "sg:city":"Medford",
    "sg:classifiers":[
        {
            "category":"Professional",
            "type":"Services"
        }
    ],
    "sg:phone":"+1 541 770 6263",
    "sg:postcode":"97504",
    "sg:province":"OR",
    "wof:name":"Extended Season",
    "wof:placetype":"venue"
},
  "geometry": {"coordinates":[-122.79186,42.337279],"type":"Point"}
}