{
  "type": "Feature",
  "properties": {
    "addr:full":"573 Kingwood Dr NW Salem OR 97304",
    "addr:housenumber":"573",
    "addr:postcode":"97304",
    "addr:street":"Kingwood Dr Nw",
    "iso:country":"US",
    "sg:address":"573 Kingwood Dr NW",
    "sg:city":"Salem",
    "sg:classifiers":[
        {
            "category":"Building & Trades",
            "subcategory":"Construction",
            "type":"Services"
        }
    ],
    "sg:phone":"+1 503 685 9868",
    "sg:postcode":"97304",
    "sg:province":"OR",
    "sg:tags":[
        "skylight"
    ],
    "wof:name":"Alternative Lighting Inc",
    "wof:placetype":"venue"
},
  "geometry": {"coordinates":[-123.071116,44.940326],"type":"Point"}
}