{
  "type": "Feature",
  "properties": {
    "iso:country":"US",
    "sg:address":"2700 Quail Run Rd",
    "sg:city":"Talent",
    "sg:classifiers":[
        {
            "category":"Food & Beverages",
            "subcategory":"Liquor & Beverages",
            "type":"Retail Goods"
        },
        {
            "category":"Wholesale",
            "subcategory":"Wine & Distilled Alcoholic Beverages",
            "type":"Manufacturing & Wholesale Goods"
        }
    ],
    "sg:phone":"+1 541 301 8793",
    "sg:postcode":"97540",
    "sg:province":"OR",
    "sg:tags":[
        "broker"
    ],
    "wof:name":"South Stage Winery",
    "wof:placetype":"venue"
},
  "geometry": {"coordinates":[-122.785156,42.225449],"type":"Point"}
}