{
  "type": "Feature",
  "properties": {
    "iso:country":"US",
    "sg:address":"19311 SW Mohave Ct",
    "sg:city":"Tualatin",
    "sg:classifiers":[
        {
            "category":"Health Services",
            "subcategory":"Chiropractor",
            "type":"Services"
        }
    ],
    "sg:phone":"+1 503 692 9095",
    "sg:postcode":"97062",
    "sg:province":"OR",
    "wof:name":"American Chiropractic Network",
    "wof:placetype":"venue"
},
  "geometry": {"coordinates":[-122.766998,45.3806],"type":"Point"}
}