{
  "type": "Feature",
  "properties": {
    "iso:country":"US",
    "sg:address":"2040 NW Newcastle St",
    "sg:city":"Roseburg",
    "sg:classifiers":[
        {
            "category":"Health Services",
            "subcategory":"Health Practitioner",
            "type":"Services"
        }
    ],
    "sg:phone":"+1 541 673 1808",
    "sg:postcode":"97470",
    "sg:province":"OR",
    "sg:tags":[
        "therapist",
        "physical"
    ],
    "sg:website":"www.taiweb.com",
    "wof:name":"Central Physical Therapy",
    "wof:placetype":"venue"
},
  "geometry": {"coordinates":[-123.382133,43.235757],"type":"Point"}
}