{
  "type": "Feature",
  "properties": {
    "addr:full":"15511 NW Pumpkin Ridge Rd North Plains OR 97133",
    "addr:housenumber":"15511",
    "addr:postcode":"97133",
    "addr:street":"Nw Pumpkin Ridge Rd",
    "iso:country":"US",
    "sg:address":"15511 NW Pumpkin Ridge Rd",
    "sg:city":"North Plains",
    "sg:classifiers":[
        {
            "category":"Building & Trades",
            "subcategory":"Construction",
            "type":"Services"
        }
    ],
    "sg:phone":"+1 503 647 5583",
    "sg:postcode":"97133",
    "sg:province":"OR",
    "sg:tags":[
        "house"
    ],
    "wof:name":"Beacham Builders",
    "wof:placetype":"venue"
},
  "geometry": {"coordinates":[-122.997553,45.632257],"type":"Point"}
}