{
  "type": "Feature",
  "properties": {
    "iso:country":"US",
    "sg:address":"1024 NW Glisan St",
    "sg:city":"Portland",
    "sg:classifiers":[
        {
            "category":"Home & Garden",
            "subcategory":"Carpets & Floor Coverings",
            "type":"Retail Goods"
        }
    ],
    "sg:phone":"+1 503 227 1197",
    "sg:postcode":"97209",
    "sg:province":"OR",
    "wof:name":"Khaden Fine Tibetan Carpets",
    "wof:placetype":"venue"
},
  "geometry": {"coordinates":[-122.682073,45.526452],"type":"Point"}
}