{
  "type": "Feature",
  "properties": {
    "addr:full":"1539 NE Stephens St Roseburg OR 97470",
    "addr:housenumber":"1539",
    "addr:postcode":"97470",
    "addr:street":"Ne Stephens St",
    "iso:country":"US",
    "sg:address":"1539 NE Stephens St",
    "sg:city":"Roseburg",
    "sg:classifiers":[
        {
            "category":"Coffee & Tea",
            "type":"Food & Drink"
        }
    ],
    "sg:menulink":"http://www.allmenus.com/or/roseburg/119315-starbucks-coffee/menu/",
    "sg:phone":"+1 541 957 2540",
    "sg:postcode":"97470",
    "sg:province":"OR",
    "sg:tags":[
        "american"
    ],
    "wof:name":"Starbucks Coffee",
    "wof:placetype":"venue"
},
  "geometry": {"coordinates":[-123.350238,43.228626],"type":"Point"}
}