{
  "type": "Feature",
  "properties": {
    "iso:country":"US",
    "sg:address":"791 Main St",
    "sg:city":"Dallas",
    "sg:classifiers":[
        {
            "category":"Banks & Credit Unions",
            "subcategory":"Bank",
            "type":"Services"
        }
    ],
    "sg:phone":"+1 503 623 8384",
    "sg:postcode":"97338",
    "sg:province":"OR",
    "wof:name":"Bank Of America",
    "wof:placetype":"venue"
},
  "geometry": {"coordinates":[-123.316807,44.921625],"type":"Point"}
}