{
  "type": "Feature",
  "properties": {
    "addr:full":"28641 S Sundowner Ct Canby OR 97013",
    "addr:housenumber":"28641",
    "addr:postcode":"97013",
    "addr:street":"S Sundowner Ct",
    "iso:country":"US",
    "sg:address":"28641 S Sundowner Ct",
    "sg:city":"Canby",
    "sg:classifiers":[
        {
            "category":"Professional",
            "subcategory":"Computer Services",
            "type":"Services"
        }
    ],
    "sg:phone":"+1 503 345 9143",
    "sg:postcode":"97013",
    "sg:province":"OR",
    "sg:tags":[
        "related"
    ],
    "wof:name":"Oregon Computer Connection",
    "wof:placetype":"venue"
},
  "geometry": {"coordinates":[-122.713652,45.19633],"type":"Point"}
}