{
  "type": "Feature",
  "properties": {
    "addr:full":"46940 NW Ganna Rd Forest Grove OR 97116",
    "addr:housenumber":"46940",
    "addr:postcode":"97116",
    "addr:street":"Nw Ganna Rd",
    "iso:country":"US",
    "sg:address":"46940 NW Ganna Rd",
    "sg:city":"Forest Grove",
    "sg:classifiers":[
        {
            "category":"Professional",
            "type":"Services"
        }
    ],
    "sg:phone":"+1 503 936 0859",
    "sg:postcode":"97116",
    "sg:province":"OR",
    "wof:name":"Out Back Art Studios",
    "wof:placetype":"venue"
},
  "geometry": {"coordinates":[-123.152365,45.567486],"type":"Point"}
}