{
  "type": "Feature",
  "properties": {
    "iso:country":"US",
    "sg:address":"3560 SW 11th Ave",
    "sg:city":"Portland",
    "sg:classifiers":[
        {
            "category":"Recreation",
            "type":"Entertainment"
        }
    ],
    "sg:phone":"+1 503 203 8025",
    "sg:postcode":"97201",
    "sg:province":"OR",
    "wof:name":"Fran Klabunde",
    "wof:placetype":"venue"
},
  "geometry": {"coordinates":[-122.691317,45.497667],"type":"Point"}
}