{
  "type": "Feature",
  "properties": {
    "iso:country":"US",
    "sg:address":"937 NW Beaver St",
    "sg:city":"Prineville",
    "sg:classifiers":[
        {
            "category":"Manufacturing",
            "subcategory":"Tools & Machinery",
            "type":"Manufacturing & Wholesale Goods"
        }
    ],
    "sg:phone":"+1 541 447 7660",
    "sg:postcode":"97754",
    "sg:province":"OR",
    "wof:name":"Duckett Welding & Mfg",
    "wof:placetype":"venue"
},
  "geometry": {"coordinates":[-120.848196,44.308578],"type":"Point"}
}