{
  "type": "Feature",
  "properties": {
    "addr:full":"2164 NE 7th Ave Portland OR 97212",
    "addr:housenumber":"2164",
    "addr:postcode":"97212",
    "addr:street":"Ne 7Th Ave",
    "iso:country":"US",
    "sg:address":"2164 NE 7th Ave",
    "sg:city":"Portland",
    "sg:classifiers":[
        {
            "category":"Banks & Credit Unions",
            "subcategory":"Investment Brokerage",
            "type":"Services"
        }
    ],
    "sg:phone":"+1 503 460 3661",
    "sg:postcode":"97212",
    "sg:province":"OR",
    "sg:tags":[
        "advisory"
    ],
    "wof:name":"Allied Financial Inc",
    "wof:placetype":"venue"
},
  "geometry": {"coordinates":[-122.658545,45.537606],"type":"Point"}
}