{
  "type": "Feature",
  "properties": {
    "iso:country":"US",
    "sg:address":"7701 SW Cedarcrest St",
    "sg:city":"Portland",
    "sg:classifiers":[
        {
            "category":"Building & Trades",
            "subcategory":"Locksmith",
            "type":"Services"
        }
    ],
    "sg:phone":"+1 503 205 1996",
    "sg:postcode":"97223",
    "sg:province":"OR",
    "sg:tags":[
        "key"
    ],
    "wof:name":"A Locksmith Srv 24 Hr",
    "wof:placetype":"venue"
},
  "geometry": {"coordinates":[-122.75653800000001,45.452807],"type":"Point"}
}