{
  "type": "Feature",
  "properties": {
    "iso:country":"US",
    "sg:address":"8885 SW Birchwood Rd",
    "sg:city":"Portland",
    "sg:classifiers":[
        {
            "category":"Travel",
            "subcategory":"Hotels & Motels",
            "type":"Entertainment"
        },
        {
            "category":"Travel",
            "subcategory":"Travel Agent",
            "type":"Entertainment"
        }
    ],
    "sg:phone":"+1 503 297 3503",
    "sg:postcode":"97225",
    "sg:province":"OR",
    "sg:tags":[
        "resort",
        "operation",
        "agency"
    ],
    "sg:website":"www.gtunlimited.com",
    "wof:name":"Great Trips Unlimited",
    "wof:placetype":"venue"
},
  "geometry": {"coordinates":[-122.767009,45.491948],"type":"Point"}
}