{
  "type": "Feature",
  "properties": {
    "iso:country":"US",
    "sg:address":"12365 SW Conestoga Dr Ofc",
    "sg:city":"Beaverton",
    "sg:classifiers":[
        {
            "category":"Real Estate",
            "subcategory":"Real Estate Operator",
            "type":"Services"
        }
    ],
    "sg:phone":"+1 503 524 5537",
    "sg:postcode":"97008",
    "sg:province":"OR",
    "sg:tags":[
        "apartment"
    ],
    "wof:name":"Sorrento View Apartments",
    "wof:placetype":"venue"
},
  "geometry": {"coordinates":[-122.804001,45.447701],"type":"Point"}
}