{
  "type": "Feature",
  "properties": {
    "iso:country":"US",
    "sg:address":"6650 N Basin Avenue",
    "sg:city":"Portland",
    "sg:classifiers":[
        {
            "category":"Personal",
            "type":"Services"
        }
    ],
    "sg:phone":"+1 503 289 2366",
    "sg:postcode":"97217",
    "sg:province":"OR",
    "sg:tags":[
        "mover"
    ],
    "wof:name":"Kent Moving Systems",
    "wof:placetype":"venue"
},
  "geometry": {"coordinates":[-122.716194,45.570686],"type":"Point"}
}