{
  "type": "Feature",
  "properties": {
    "iso:country":"US",
    "sg:address":"1750 Antelope Rd",
    "sg:city":"White City",
    "sg:classifiers":[
        {
            "category":"Building & Trades",
            "subcategory":"Equipment Rental",
            "type":"Services"
        }
    ],
    "sg:phone":"+1 541 826 1931",
    "sg:postcode":"97503",
    "sg:province":"OR",
    "sg:tags":[
        "crane"
    ],
    "wof:name":"Adept Crane Svc LLC",
    "wof:placetype":"venue"
},
  "geometry": {"coordinates":[-122.86305400000001,42.427265],"type":"Point"}
}