{
  "type": "Feature",
  "properties": {
    "iso:country":"US",
    "sg:address":"1017 N Riverside Ave",
    "sg:city":"Medford",
    "sg:classifiers":[
        {
            "category":"Utilities",
            "subcategory":"Telephone",
            "type":"Services"
        }
    ],
    "sg:phone":"+1 541 776 5380",
    "sg:postcode":"97501",
    "sg:province":"OR",
    "sg:tags":[
        "communications"
    ],
    "wof:name":"Unicom",
    "wof:placetype":"venue"
},
  "geometry": {"coordinates":[-122.875289,42.336671],"type":"Point"}
}