{
  "type": "Feature",
  "properties": {
    "iso:country":"US",
    "sg:address":"2127 Yolanda Ave",
    "sg:city":"Springfield",
    "sg:classifiers":[
        {
            "category":"Shopping",
            "subcategory":"Jewelry",
            "type":"Retail Goods"
        }
    ],
    "sg:phone":"+1 541 746 9606",
    "sg:postcode":"97477",
    "sg:province":"OR",
    "sg:tags":[
        "jeweler"
    ],
    "wof:name":"Firefly Jewelry & Beads",
    "wof:placetype":"venue"
},
  "geometry": {"coordinates":[-122.992527,44.072316],"type":"Point"}
}