{
  "type": "Feature",
  "properties": {
    "addr:full":"1840 NE Wichita Way Bend OR 97701",
    "addr:housenumber":"1840",
    "addr:postcode":"97701",
    "addr:street":"Ne Wichita Way",
    "iso:country":"US",
    "sg:address":"1840 NE Wichita Way",
    "sg:city":"Bend",
    "sg:classifiers":[
        {
            "category":"Building & Trades",
            "subcategory":"Construction",
            "type":"Services"
        }
    ],
    "sg:phone":"+1 541 318 7212",
    "sg:postcode":"97701",
    "sg:province":"OR",
    "sg:tags":[
        "rough",
        "framing",
        "contractor"
    ],
    "wof:name":"Randall K Bosch Construction",
    "wof:placetype":"venue"
},
  "geometry": {"coordinates":[-121.26303,44.068392],"type":"Point"}
}