{
  "type": "Feature",
  "properties": {
    "iso:country":"US",
    "sg:address":"155 W Grant St",
    "sg:city":"Lebanon",
    "sg:classifiers":[
        {
            "category":"Building & Trades",
            "subcategory":"Plumbing",
            "type":"Services"
        }
    ],
    "sg:phone":"+1 541 259 3431",
    "sg:postcode":"97355",
    "sg:province":"OR",
    "sg:tags":[
        "plumbing",
        "contractor"
    ],
    "wof:name":"South Santiam Plumbing Inc",
    "wof:placetype":"venue"
},
  "geometry": {"coordinates":[-122.90920699999999,44.538313],"type":"Point"}
}