{
  "type": "Feature",
  "properties": {
    "iso:country":"US",
    "sg:address":"2423 NE 61st Ave",
    "sg:city":"Portland",
    "sg:classifiers":[
        {
            "category":"Building & Trades",
            "subcategory":"Construction",
            "type":"Services"
        }
    ],
    "sg:phone":"+1 503 775 7948",
    "sg:postcode":"97213",
    "sg:province":"OR",
    "sg:tags":[
        "house"
    ],
    "wof:name":"Stix and Stones Construction",
    "wof:placetype":"venue"
},
  "geometry": {"coordinates":[-122.60056899999999,45.540724],"type":"Point"}
}