{
  "type": "Feature",
  "properties": {
    "addr:full":"6506 SE Reed College Pl Portland OR 97202",
    "addr:housenumber":"6506",
    "addr:postcode":"97202",
    "addr:street":"Se Reed College Pl",
    "iso:country":"US",
    "sg:address":"6506 SE Reed College Pl",
    "sg:city":"Portland",
    "sg:classifiers":[
        {
            "category":"Social Services",
            "type":"Services"
        }
    ],
    "sg:phone":"+1 503 775 7668",
    "sg:postcode":"97202",
    "sg:province":"OR",
    "wof:name":"Page Bailey Inst Internaitonal",
    "wof:placetype":"venue"
},
  "geometry": {"coordinates":[-122.62910599999999,45.475602],"type":"Point"}
}