{
  "type": "Feature",
  "properties": {
    "iso:country":"US",
    "sg:address":"6506 SE Reed College Pl",
    "sg:city":"Portland",
    "sg:classifiers":[
        {
            "category":"Social Services",
            "type":"Services"
        }
    ],
    "sg:phone":"+1 503 775 7668",
    "sg:postcode":"97202",
    "sg:province":"OR",
    "wof:name":"Page Bailey Inst Internaitonal",
    "wof:placetype":"venue"
},
  "geometry": {"coordinates":[-122.62910599999999,45.475602],"type":"Point"}
}