{
  "type": "Feature",
  "properties": {
    "addr:full":"10870 SW Muirwood Dr Portland OR 97225",
    "addr:housenumber":"10870",
    "addr:postcode":"97225",
    "addr:street":"Sw Muirwood Dr",
    "iso:country":"US",
    "sg:address":"10870 SW Muirwood Dr",
    "sg:city":"Portland",
    "sg:classifiers":[
        {
            "category":"Shopping",
            "subcategory":"Beauty & Cosmetics",
            "type":"Retail Goods"
        }
    ],
    "sg:phone":"+1 503 626 8447",
    "sg:postcode":"97225",
    "sg:province":"OR",
    "sg:tags":[
        "salons-equipment",
        "supply"
    ],
    "wof:name":"Sally Vingelen",
    "wof:placetype":"venue"
},
  "geometry": {"coordinates":[-122.78900899999999,45.510032],"type":"Point"}
}