{
  "type": "Feature",
  "properties": {
    "addr:full":"2360 5th St Columbia City OR 97018",
    "addr:housenumber":"2360",
    "addr:postcode":"97018",
    "addr:street":"5Th St",
    "iso:country":"US",
    "sg:address":"2360 5th St",
    "sg:city":"Columbia City",
    "sg:classifiers":[
        {
            "category":"Professional",
            "subcategory":"Computer Services",
            "type":"Services"
        }
    ],
    "sg:phone":"+1 503 397 6223",
    "sg:postcode":"97018",
    "sg:province":"OR",
    "sg:tags":[
        "programing",
        "custom"
    ],
    "wof:name":"Fyi of Columbia City Inc",
    "wof:placetype":"venue"
},
  "geometry": {"coordinates":[-122.813856,45.893033],"type":"Point"}
}