{
  "type": "Feature",
  "properties": {
    "addr:full":"267 SE Clay St Dallas OR 97338",
    "addr:housenumber":"267",
    "addr:postcode":"97338",
    "addr:street":"Se Clay St",
    "iso:country":"US",
    "sg:address":"267 SE Clay St",
    "sg:city":"Dallas",
    "sg:classifiers":[
        {
            "category":"Banks & Credit Unions",
            "subcategory":"Bank",
            "type":"Services"
        }
    ],
    "sg:phone":"+1 503 623 6581",
    "sg:postcode":"97338",
    "sg:province":"OR",
    "sg:tags":[
        "short",
        "institution",
        "business"
    ],
    "wof:name":"Cambridge Capitol Funding",
    "wof:placetype":"venue"
},
  "geometry": {"coordinates":[-123.314657,44.918334],"type":"Point"}
}