{
  "type": "Feature",
  "properties": {
    "iso:country":"US",
    "sg:address":"42876 Rodgers Mountain Loop",
    "sg:city":"Scio",
    "sg:classifiers":[
        {
            "category":"Wholesale",
            "subcategory":"Electrical",
            "type":"Manufacturing & Wholesale Goods"
        }
    ],
    "sg:phone":"+1 541 451 2111",
    "sg:postcode":"97374",
    "sg:province":"OR",
    "sg:tags":[
        "communication",
        "radio",
        "system"
    ],
    "wof:name":"R F Communications",
    "wof:placetype":"venue"
},
  "geometry": {"coordinates":[-122.772307,44.682327],"type":"Point"}
}