{
  "type": "Feature",
  "properties": {
    "iso:country":"US",
    "sg:address":"1970 W Harvard Ave",
    "sg:city":"Roseburg",
    "sg:classifiers":[
        {
            "category":"Insurance",
            "subcategory":"Insurance Agent",
            "type":"Services"
        }
    ],
    "sg:phone":"+1 541 677 1406",
    "sg:postcode":"97470",
    "sg:province":"OR",
    "wof:name":"Omega Management Group",
    "wof:placetype":"venue"
},
  "geometry": {"coordinates":[-123.373018,43.214001],"type":"Point"}
}