{
  "type": "Feature",
  "properties": {
    "iso:country":"US",
    "sg:address":"1141 Molalla Ave",
    "sg:city":"Oregon City",
    "sg:classifiers":[
        {
            "category":"Building & Trades",
            "subcategory":"Equipment Rental",
            "type":"Services"
        }
    ],
    "sg:phone":"+1 503 656 1401",
    "sg:postcode":"97045",
    "sg:province":"OR",
    "sg:tags":[
        "yard"
    ],
    "wof:name":"A A Rental Sales & Svc Inc",
    "wof:placetype":"venue"
},
  "geometry": {"coordinates":[-122.592437,45.338944],"type":"Point"}
}