{
  "type": "Feature",
  "properties": {
    "iso:country":"US",
    "sg:address":"690 SE 40th Ter",
    "sg:city":"Gresham",
    "sg:classifiers":[
        {
            "category":"Shopping",
            "subcategory":"Gifts & Souvenirs",
            "type":"Retail Goods"
        }
    ],
    "sg:phone":"+1 503 492 3336",
    "sg:postcode":"97080",
    "sg:province":"OR",
    "wof:name":"Gift of Giving Society",
    "wof:placetype":"venue"
},
  "geometry": {"coordinates":[-122.425401,45.469044],"type":"Point"}
}