{
  "type": "Feature",
  "properties": {
    "iso:country":"US",
    "sg:address":"3415 SW Cedar Hills Blvd",
    "sg:city":"Beaverton",
    "sg:classifiers":[
        {
            "category":"Shopping",
            "subcategory":"Books",
            "type":"Retail Goods"
        }
    ],
    "sg:phone":"+1 503 228 4651",
    "sg:postcode":"97005",
    "sg:province":"OR",
    "sg:tags":[
        "bookstore"
    ],
    "sg:website":"www.powells.com/info/places/beav...",
    "wof:name":"Powell's Books",
    "wof:placetype":"venue"
},
  "geometry": {"coordinates":[-122.81138799999999,45.495503],"type":"Point"}
}