{
  "type": "Feature",
  "properties": {
    "iso:country":"US",
    "sg:address":"1139 NW 11th Ave",
    "sg:city":"Portland",
    "sg:classifiers":[
        {
            "category":"Restaurant",
            "type":"Food & Drink"
        }
    ],
    "sg:phone":"+1 503 517 7778",
    "sg:postcode":"97209",
    "sg:province":"OR",
    "sg:tags":[
        "new",
        "american"
    ],
    "sg:website":"www.metrovinopdx.com",
    "wof:name":"Metrovino",
    "wof:placetype":"venue"
},
  "geometry": {"coordinates":[-122.682588,45.53138],"type":"Point"}
}