{
  "type": "Feature",
  "properties": {
    "addr:full":"1245 13th St SE Salem OR 97302",
    "addr:housenumber":"1245",
    "addr:postcode":"97302",
    "addr:street":"13Th St Se",
    "iso:country":"US",
    "sg:address":"1245 13th St SE",
    "sg:city":"Salem",
    "sg:classifiers":[
        {
            "category":"Home & Garden",
            "subcategory":"Household Appliances",
            "type":"Retail Goods"
        }
    ],
    "sg:phone":"+1 503 399 1600",
    "sg:postcode":"97302",
    "sg:province":"OR",
    "wof:name":"Brand Source Home Ctr",
    "wof:placetype":"venue"
},
  "geometry": {"coordinates":[-123.029335,44.925768],"type":"Point"}
}