{
  "type": "Feature",
  "properties": {
    "iso:country":"US",
    "sg:address":"1241 SW 4th Ave",
    "sg:city":"Ontario",
    "sg:classifiers":[
        {
            "category":"Restaurant",
            "type":"Food & Drink"
        }
    ],
    "sg:phone":"+1 541 889 3000",
    "sg:postcode":"97914",
    "sg:province":"OR",
    "sg:tags":[
        "eating"
    ],
    "wof:name":"Matsy's Restaurant & Lounge",
    "wof:placetype":"venue"
},
  "geometry": {"coordinates":[-116.982307,44.024872],"type":"Point"}
}