{
  "type": "Feature",
  "properties": {
    "iso:country":"US",
    "sg:address":"28979 Hurlburt Rd",
    "sg:city":"Corvallis",
    "sg:classifiers":[
        {
            "category":"Wholesale",
            "subcategory":"Farm Supplies",
            "type":"Manufacturing & Wholesale Goods"
        }
    ],
    "sg:phone":"+1 541 757 7933",
    "sg:postcode":"97333",
    "sg:province":"OR",
    "wof:name":"Work Unlimited",
    "wof:placetype":"venue"
},
  "geometry": {"coordinates":[-123.24179599999999,44.437702],"type":"Point"}
}