{
  "type": "Feature",
  "properties": {
    "iso:country":"US",
    "sg:address":"90370 Hill Rd",
    "sg:city":"Springfield",
    "sg:classifiers":[
        {
            "category":"Building & Trades",
            "subcategory":"Construction",
            "type":"Services"
        }
    ],
    "sg:phone":"+1 541 744 6685",
    "sg:postcode":"97478",
    "sg:province":"OR",
    "sg:tags":[
        "residential"
    ],
    "wof:name":"Timothy A Miller Construc",
    "wof:placetype":"venue"
},
  "geometry": {"coordinates":[-122.942442,44.117392],"type":"Point"}
}