{
  "type": "Feature",
  "properties": {
    "addr:full":"1171 SE Tualatin Valley Hwy Hillsboro OR 97123",
    "addr:housenumber":"1171",
    "addr:postcode":"97123",
    "addr:street":"Se Tualatin Valley Hwy",
    "iso:country":"US",
    "sg:address":"1171 SE Tualatin Valley Hwy",
    "sg:city":"Hillsboro",
    "sg:classifiers":[
        {
            "category":"Retail",
            "subcategory":"Auto Repair",
            "type":"Services"
        },
        {
            "category":"Manufacturing",
            "subcategory":"Tools & Machinery",
            "type":"Manufacturing & Wholesale Goods"
        }
    ],
    "sg:phone":"+1 503 648 1575",
    "sg:postcode":"97123",
    "sg:province":"OR",
    "sg:tags":[
        "repairing",
        "engine",
        "mfg",
        "automobile",
        "s",
        "automotive"
    ],
    "wof:name":"A E B Auto Electric & Battery",
    "wof:placetype":"venue"
},
  "geometry": {"coordinates":[-122.97176399999999,45.511213],"type":"Point"}
}