{
  "type": "Feature",
  "properties": {
    "iso:country":"US",
    "sg:address":"3366 Rosemont Way",
    "sg:city":"Eugene",
    "sg:classifiers":[
        {
            "category":"Professional",
            "subcategory":"Art Services",
            "type":"Services"
        }
    ],
    "sg:phone":"+1 541 484 4015",
    "sg:postcode":"97401",
    "sg:province":"OR",
    "sg:tags":[
        "commercial",
        "design"
    ],
    "wof:name":"Jennifer Designs",
    "wof:placetype":"venue"
},
  "geometry": {"coordinates":[-123.053224,44.078271],"type":"Point"}
}