{
  "type": "Feature",
  "properties": {
    "iso:country":"US",
    "sg:address":"1425 NE Irving St",
    "sg:city":"Portland",
    "sg:classifiers":[
        {
            "category":"Government",
            "subcategory":"Office",
            "type":"Public Place"
        }
    ],
    "sg:phone":"+1 503 731 3147",
    "sg:postcode":"97232",
    "sg:province":"OR",
    "sg:tags":[
        "government-state"
    ],
    "wof:name":"State of Oregon Child Welfare",
    "wof:placetype":"venue"
},
  "geometry": {"coordinates":[-122.65131599999999,45.527939],"type":"Point"}
}