{
  "type": "Feature",
  "properties": {
    "addr:full":"891 Ohare Pkwy Medford OR 97504",
    "addr:housenumber":"891",
    "addr:postcode":"97504",
    "addr:street":"Ohare Pkwy",
    "iso:country":"US",
    "sg:address":"891 Ohare Pkwy",
    "sg:city":"Medford",
    "sg:classifiers":[
        {
            "category":"Banks & Credit Unions",
            "subcategory":"Bank",
            "type":"Services"
        }
    ],
    "sg:phone":"+1 541 774 1400",
    "sg:postcode":"97504",
    "sg:province":"OR",
    "wof:name":"South Valley Bank & Trust",
    "wof:placetype":"venue"
},
  "geometry": {"coordinates":[-122.87691700000001,42.366783],"type":"Point"}
}