{
  "type": "Feature",
  "properties": {
    "iso:country":"US",
    "sg:address":"1326 SE Malden St",
    "sg:city":"Portland",
    "sg:classifiers":[
        {
            "category":"Personal",
            "subcategory":"Massage",
            "type":"Services"
        }
    ],
    "sg:phone":"+1 503 484 7622",
    "sg:postcode":"97202",
    "sg:province":"OR",
    "sg:website":"www.zenfulmonkey.com",
    "wof:name":"Zenful Monkey Holistic Massage Studio",
    "wof:placetype":"venue"
},
  "geometry": {"coordinates":[-122.652671,45.469375],"type":"Point"}
}