{
  "type": "Feature",
  "properties": {
    "iso:country":"US",
    "sg:address":"421 SW 6th Ave Ste 850",
    "sg:city":"Portland",
    "sg:classifiers":[
        {
            "category":"Professional",
            "subcategory":"Computer Services",
            "type":"Services"
        }
    ],
    "sg:phone":"+1 503 228 8708",
    "sg:postcode":"97204",
    "sg:province":"OR",
    "sg:tags":[
        "technical",
        "repair",
        "assistance",
        "support",
        "equipment-service"
    ],
    "wof:name":"Sanborn Map Co",
    "wof:placetype":"venue"
},
  "geometry": {"coordinates":[-122.67756199999999,45.520911],"type":"Point"}
}