{
  "type": "Feature",
  "properties": {
    "addr:full":"9955 SW Beaverton-Hillsdale Hwy Beaverton OR 97005",
    "addr:housenumber":"9955",
    "addr:postcode":"97005",
    "addr:street":"Sw Beaverton-Hillsdale Hwy",
    "iso:country":"US",
    "sg:address":"9955 SW Beaverton-Hillsdale Hwy",
    "sg:city":"Beaverton",
    "sg:classifiers":[
        {
            "category":"Shopping",
            "subcategory":"Hobbies, Toys, & Games",
            "type":"Retail Goods"
        }
    ],
    "sg:phone":"+1 503 626 9067",
    "sg:postcode":"97005",
    "sg:province":"OR",
    "sg:tags":[
        "shop",
        "hobby"
    ],
    "sg:website":"www.knightfallgames.com",
    "wof:name":"Knightfall Games",
    "wof:placetype":"venue"
},
  "geometry": {"coordinates":[-122.77999699999999,45.486922],"type":"Point"}
}