{
  "type": "Feature",
  "properties": {
    "iso:country":"US",
    "sg:address":"204 N 2nd St",
    "sg:city":"Jefferson",
    "sg:classifiers":[
        {
            "category":"Building & Trades",
            "subcategory":"Construction",
            "type":"Services"
        }
    ],
    "sg:phone":"+1 541 327 1521",
    "sg:postcode":"97352",
    "sg:province":"OR",
    "sg:tags":[
        "general",
        "contractor"
    ],
    "wof:name":"Baker Construction",
    "wof:placetype":"venue"
},
  "geometry": {"coordinates":[-123.010304,44.71972],"type":"Point"}
}