{
  "type": "Feature",
  "properties": {
    "iso:country":"US",
    "sg:address":"9225 SW Hall Blvd Ste E",
    "sg:city":"Portland",
    "sg:classifiers":[
        {
            "category":"Health Services",
            "subcategory":"Dentist",
            "type":"Services"
        }
    ],
    "sg:phone":"+1 503 620 7134",
    "sg:postcode":"97223",
    "sg:province":"OR",
    "wof:name":"Washington Sq Cosmetic Dentistry",
    "wof:placetype":"venue"
},
  "geometry": {"coordinates":[-122.775009,45.453164],"type":"Point"}
}