{
  "type": "Feature",
  "properties": {
    "iso:country":"US",
    "sg:address":"6916 Wheatland Rd N",
    "sg:city":"Salem",
    "sg:classifiers":[
        {
            "category":"Banks & Credit Unions",
            "subcategory":"Financial Services",
            "type":"Services"
        }
    ],
    "sg:phone":"+1 503 390 2886",
    "sg:postcode":"97303",
    "sg:province":"OR",
    "sg:tags":[
        "organization",
        "education"
    ],
    "wof:name":"Oregon Chapter of The Lewis &",
    "wof:placetype":"venue"
},
  "geometry": {"coordinates":[-123.024748,45.019228],"type":"Point"}
}