{
  "type": "Feature",
  "properties": {
    "iso:country":"US",
    "sg:address":"19675 SW 129th Ave",
    "sg:city":"Tualatin",
    "sg:classifiers":[
        {
            "category":"Wholesale",
            "subcategory":"Dairy",
            "type":"Manufacturing & Wholesale Goods"
        }
    ],
    "sg:phone":"+1 503 692 9700",
    "sg:postcode":"97062",
    "sg:province":"OR",
    "sg:tags":[
        "frozen",
        "dessert",
        "ice",
        "cream"
    ],
    "wof:name":"Nestle Ice Cream Co",
    "wof:placetype":"venue"
},
  "geometry": {"coordinates":[-122.810288,45.377662],"type":"Point"}
}