{
  "type": "Feature",
  "properties": {
    "iso:country":"US",
    "sg:address":"5319 SW Westgate Dr",
    "sg:city":"Portland",
    "sg:classifiers":[
        {
            "category":"Social Services",
            "type":"Services"
        }
    ],
    "sg:phone":"+1 503 789 3090",
    "sg:postcode":"97221",
    "sg:province":"OR",
    "sg:tags":[
        "counseling"
    ],
    "wof:name":"Westgate Counseling Services",
    "wof:placetype":"venue"
},
  "geometry": {"coordinates":[-122.73479,45.510698],"type":"Point"}
}