{
  "type": "Feature",
  "properties": {
    "addr:full":"2615 NE Alberta St Portland OR 97211",
    "addr:housenumber":"2615",
    "addr:postcode":"97211",
    "addr:street":"Ne Alberta St",
    "iso:country":"US",
    "sg:address":"2615 NE Alberta St",
    "sg:city":"Portland",
    "sg:classifiers":[
        {
            "category":"Utilities",
            "subcategory":"Refuse",
            "type":"Services"
        },
        {
            "category":"Utilities",
            "subcategory":"Recycling",
            "type":"Services"
        }
    ],
    "sg:phone":"+1 503 253 6616",
    "sg:postcode":"97211",
    "sg:province":"OR",
    "sg:tags":[
        "rubbish",
        "collection",
        "garbage",
        "removal"
    ],
    "wof:name":"Alberta Sanitary Service Inc",
    "wof:placetype":"venue"
},
  "geometry": {"coordinates":[-122.63875,45.559052],"type":"Point"}
}