{
  "type": "Feature",
  "properties": {
    "iso:country":"US",
    "sg:address":"123 E Powell Blvd",
    "sg:city":"Gresham",
    "sg:classifiers":[
        {
            "category":"Social Services",
            "type":"Services"
        }
    ],
    "sg:phone":"+1 503 784 8813",
    "sg:postcode":"97030",
    "sg:province":"OR",
    "sg:tags":[
        "counselor",
        "marriage",
        "family"
    ],
    "wof:name":"Richard Sansom",
    "wof:placetype":"venue"
},
  "geometry": {"coordinates":[-122.429299,45.498047],"type":"Point"}
}