{
  "type": "Feature",
  "properties": {
    "iso:country":"US",
    "sg:address":"9200 SW 91st Ave Ste 310",
    "sg:city":"Portland",
    "sg:classifiers":[
        {
            "category":"Professional",
            "subcategory":"Testing Lab",
            "type":"Services"
        }
    ],
    "sg:phone":"+1 877 685 6570",
    "sg:postcode":"97223",
    "sg:province":"OR",
    "sg:tags":[
        "blood",
        "typing"
    ],
    "wof:name":"Confidential STD Testing - Portland",
    "wof:placetype":"venue"
},
  "geometry": {"coordinates":[-122.77057600000001,45.453831],"type":"Point"}
}