{
  "type": "Feature",
  "properties": {
    "iso:country":"US",
    "sg:address":"202 SE 181st Ave",
    "sg:city":"Portland",
    "sg:classifiers":[
        {
            "category":"Insurance",
            "subcategory":"Insurance Agent",
            "type":"Services"
        }
    ],
    "sg:phone":"+1 503 667 7971",
    "sg:postcode":"97233",
    "sg:province":"OR",
    "wof:name":"Lori Stegmann Agency",
    "wof:placetype":"venue"
},
  "geometry": {"coordinates":[-122.477048,45.520571],"type":"Point"}
}