{
  "type": "Feature",
  "properties": {
    "iso:country":"US",
    "sg:address":"60210 Winnebago Ln",
    "sg:city":"Bend",
    "sg:classifiers":[
        {
            "category":"Autos & Motor Vehicles",
            "subcategory":"Auto Supplies",
            "type":"Retail Goods"
        }
    ],
    "sg:phone":"+1 541 480 7155",
    "sg:postcode":"97702",
    "sg:province":"OR",
    "sg:tags":[
        "tire"
    ],
    "wof:name":"Track And Tire",
    "wof:placetype":"venue"
},
  "geometry": {"coordinates":[-121.36088599999999,43.987455],"type":"Point"}
}