{
  "type": "Feature",
  "properties": {
    "addr:full":"520 NW Burnside Rd Gresham OR 97030",
    "addr:housenumber":"520",
    "addr:postcode":"97030",
    "addr:street":"Nw Burnside Rd",
    "iso:country":"US",
    "sg:address":"520 NW Burnside Rd",
    "sg:city":"Gresham",
    "sg:classifiers":[
        {
            "category":"Restaurant",
            "type":"Food & Drink"
        }
    ],
    "sg:menulink":"http://www.allmenus.com/or/portland/175472-arbys/menu/",
    "sg:phone":"+1 503 665 6517",
    "sg:postcode":"97030",
    "sg:province":"OR",
    "sg:tags":[
        "burger",
        "american"
    ],
    "wof:name":"Arby's",
    "wof:placetype":"venue"
},
  "geometry": {"coordinates":[-122.43932599999999,45.511155],"type":"Point"}
}