{
  "type": "Feature",
  "properties": {
    "iso:country":"US",
    "sg:address":"9790 SW Whitford Ln",
    "sg:city":"Beaverton",
    "sg:classifiers":[
        {
            "category":"Personal",
            "subcategory":"Beauty Salon",
            "type":"Services"
        }
    ],
    "sg:phone":"+1 503 641 3379",
    "sg:postcode":"97008",
    "sg:province":"OR",
    "sg:tags":[
        "shop"
    ],
    "wof:name":"All About Hair",
    "wof:placetype":"venue"
},
  "geometry": {"coordinates":[-122.775322,45.46411],"type":"Point"}
}