{
  "type": "Feature",
  "properties": {
    "addr:full":"720 NW Madras Hwy Prineville OR 97754",
    "addr:housenumber":"720",
    "addr:postcode":"97754",
    "addr:street":"Nw Madras Hwy",
    "iso:country":"US",
    "sg:address":"720 NW Madras Hwy",
    "sg:city":"Prineville",
    "sg:classifiers":[
        {
            "category":"Wholesale",
            "subcategory":"Machinery & Supplies",
            "type":"Manufacturing & Wholesale Goods"
        }
    ],
    "sg:phone":"+1 541 447 6890",
    "sg:postcode":"97754",
    "sg:province":"OR",
    "sg:tags":[
        "trailer"
    ],
    "wof:name":"W W Western Wear Saddlery",
    "wof:placetype":"venue"
},
  "geometry": {"coordinates":[-120.85658100000001,44.302983],"type":"Point"}
}