{
  "type": "Feature",
  "properties": {
    "addr:full":"10131 NE Sandy Blvd Portland OR 97220",
    "addr:housenumber":"10131",
    "addr:postcode":"97220",
    "addr:street":"Ne Sandy Blvd",
    "iso:country":"US",
    "sg:address":"10131 NE Sandy Blvd",
    "sg:city":"Portland",
    "sg:classifiers":[
        {
            "category":"Autos & Motor Vehicles",
            "subcategory":"Fuel & Gas Station",
            "type":"Retail Goods"
        }
    ],
    "sg:phone":"+1 503 253 5937",
    "sg:postcode":"97220",
    "sg:province":"OR",
    "sg:tags":[
        "oil"
    ],
    "wof:name":"Shell",
    "wof:placetype":"venue"
},
  "geometry": {"coordinates":[-122.55797,45.55922],"type":"Point"}
}