{
  "type": "Feature",
  "properties": {
    "iso:country":"US",
    "sg:address":"5220 SW Scholls Ferry Rd",
    "sg:city":"Portland",
    "sg:classifiers":[
        {
            "category":"Wholesale",
            "subcategory":"Non-durable Goods",
            "type":"Manufacturing & Wholesale Goods"
        }
    ],
    "sg:phone":"+1 503 292 1168",
    "sg:postcode":"97225",
    "sg:province":"OR",
    "wof:name":"Ria Distributing Inc",
    "wof:placetype":"venue"
},
  "geometry": {"coordinates":[-122.759767,45.481009],"type":"Point"}
}