{
  "type": "Feature",
  "properties": {
    "addr:full":"3412 NE 151st Ave Portland OR 97230",
    "addr:housenumber":"3412",
    "addr:postcode":"97230",
    "addr:street":"Ne 151St Ave",
    "iso:country":"US",
    "sg:address":"3412 NE 151st Ave",
    "sg:city":"Portland",
    "sg:classifiers":[
        {
            "category":"Wholesale",
            "subcategory":"Machinery & Supplies",
            "type":"Manufacturing & Wholesale Goods"
        }
    ],
    "sg:phone":"+1 971 570 9911",
    "sg:postcode":"97230",
    "sg:province":"OR",
    "sg:tags":[
        "director",
        "funeral"
    ],
    "wof:name":"Laser Masterpieces",
    "wof:placetype":"venue"
},
  "geometry": {"coordinates":[-122.506434,45.54786],"type":"Point"}
}