{
  "type": "Feature",
  "properties": {
    "iso:country":"US",
    "sg:address":"1203 E Jackson St",
    "sg:city":"Medford",
    "sg:classifiers":[
        {
            "category":"Food & Beverages",
            "subcategory":"Specialty",
            "type":"Retail Goods"
        }
    ],
    "sg:phone":"+1 541 858 0703",
    "sg:postcode":"97504",
    "sg:province":"OR",
    "sg:tags":[
        "tea",
        "coffee"
    ],
    "wof:name":"Crossroads Coffee Co",
    "wof:placetype":"venue"
},
  "geometry": {"coordinates":[-122.85711499999999,42.33117],"type":"Point"}
}