{
  "type": "Feature",
  "properties": {
    "iso:country":"US",
    "sg:address":"4280 SW Eureka Ln",
    "sg:city":"Madras",
    "sg:classifiers":[
        {
            "category":"Wholesale",
            "subcategory":"Construction Materials",
            "type":"Manufacturing & Wholesale Goods"
        }
    ],
    "sg:phone":"+1 541 475 7625",
    "sg:postcode":"97741",
    "sg:province":"OR",
    "sg:tags":[
        "sand",
        "gravel"
    ],
    "wof:name":"Rock & Road Quarry Products",
    "wof:placetype":"venue"
},
  "geometry": {"coordinates":[-121.21555499999999,44.578344],"type":"Point"}
}