{
  "type": "Feature",
  "properties": {
    "iso:country":"US",
    "sg:address":"31000 SE Kelso Rd",
    "sg:city":"Boring",
    "sg:classifiers":[
        {
            "category":"Organizations",
            "subcategory":"Religious Organization",
            "type":"Services"
        },
        {
            "category":"Social Services",
            "type":"Services"
        }
    ],
    "sg:phone":"+1 503 668 5571",
    "sg:postcode":"97009",
    "sg:province":"OR",
    "sg:tags":[
        "mission",
        "missionary"
    ],
    "sg:website":"www.interactministries.org",
    "wof:name":"Interact Ministries Inc",
    "wof:placetype":"venue"
},
  "geometry": {"coordinates":[-122.349717,45.417973],"type":"Point"}
}