{
  "type": "Feature",
  "properties": {
    "iso:country":"US",
    "sg:address":"41025 SE Loudon Rd",
    "sg:city":"Corbett",
    "sg:classifiers":[
        {
            "category":"Professional",
            "subcategory":"Lawyer & Legal Services",
            "type":"Services"
        }
    ],
    "sg:phone":"+1 503 695 5756",
    "sg:postcode":"97019",
    "sg:province":"OR",
    "wof:name":"John G Chamberlin Esquire",
    "wof:placetype":"venue"
},
  "geometry": {"coordinates":[-122.260277,45.508652],"type":"Point"}
}