{
  "type": "Feature",
  "properties": {
    "iso:country":"US",
    "sg:address":"2732 NE Broadway St",
    "sg:city":"Portland",
    "sg:classifiers":[
        {
            "category":"Social Services",
            "type":"Services"
        }
    ],
    "sg:phone":"+1 503 202 5424",
    "sg:postcode":"97232",
    "sg:province":"OR",
    "sg:tags":[
        "counselor",
        "marriage",
        "family"
    ],
    "wof:name":"Vivian Coles",
    "wof:placetype":"venue"
},
  "geometry": {"coordinates":[-122.636847,45.535085],"type":"Point"}
}