{
  "type": "Feature",
  "properties": {
    "addr:full":"5103 N Willis Blvd Portland OR 97203",
    "addr:housenumber":"5103",
    "addr:postcode":"97203",
    "addr:street":"N Willis Blvd",
    "iso:country":"US",
    "sg:address":"5103 N Willis Blvd",
    "sg:city":"Portland",
    "sg:classifiers":[
        {
            "category":"Government",
            "subcategory":"Office",
            "type":"Public Place"
        }
    ],
    "sg:phone":"+1 503 988 3815",
    "sg:postcode":"97203",
    "sg:province":"OR",
    "sg:tags":[
        "county",
        "program",
        "health"
    ],
    "wof:name":"Multnomah County Health Clinic",
    "wof:placetype":"venue"
},
  "geometry": {"coordinates":[-122.720428,45.584134],"type":"Point"}
}