{
  "type": "Feature",
  "properties": {
    "iso:country":"US",
    "sg:address":"1422 SE 34th Ave",
    "sg:city":"Portland",
    "sg:classifiers":[
        {
            "category":"Manufacturing",
            "subcategory":"Printing",
            "type":"Manufacturing & Wholesale Goods"
        }
    ],
    "sg:phone":"+1 503 238 9637",
    "sg:postcode":"97214",
    "sg:province":"OR",
    "sg:tags":[
        "graphic",
        "commercial",
        "designer"
    ],
    "wof:name":"Twain Photo Shoptics",
    "wof:placetype":"venue"
},
  "geometry": {"coordinates":[-122.62956200000001,45.512693],"type":"Point"}
}