{
  "type": "Feature",
  "properties": {
    "iso:country":"US",
    "sg:address":"3415 NW Newell Ave",
    "sg:city":"Terrebonne",
    "sg:classifiers":[
        {
            "category":"Professional",
            "subcategory":"Business Services",
            "type":"Services"
        }
    ],
    "sg:phone":"+1 541 548 5184",
    "sg:postcode":"97760",
    "sg:province":"OR",
    "wof:name":"M Becker Enterprises",
    "wof:placetype":"venue"
},
  "geometry": {"coordinates":[-121.208006,44.340065],"type":"Point"}
}