{
  "type": "Feature",
  "properties": {
    "iso:country":"US",
    "sg:address":"63135 Dickey Rd",
    "sg:city":"Bend",
    "sg:classifiers":[
        {
            "category":"Farming",
            "subcategory":"Livestock Farm",
            "type":"Manufacturing & Wholesale Goods"
        }
    ],
    "sg:phone":"+1 541 389 8204",
    "sg:postcode":"97701",
    "sg:province":"OR",
    "sg:tags":[
        "specialty",
        "animal"
    ],
    "wof:name":"Cascades View Llama Ranch",
    "wof:placetype":"venue"
},
  "geometry": {"coordinates":[-121.22356499999999,44.092843],"type":"Point"}
}