{
  "type": "Feature",
  "properties": {
    "iso:country":"US",
    "sg:address":"1822 17th Ave SE",
    "sg:city":"Albany",
    "sg:classifiers":[
        {
            "category":"Building & Trades",
            "subcategory":"Cleaning & Sanitation",
            "type":"Services"
        }
    ],
    "sg:phone":"+1 541 926 9277",
    "sg:postcode":"97322",
    "sg:province":"OR",
    "sg:tags":[
        "maid"
    ],
    "wof:name":"Maids The",
    "wof:placetype":"venue"
},
  "geometry": {"coordinates":[-123.082024,44.625871],"type":"Point"}
}