{
  "type": "Feature",
  "properties": {
    "iso:country":"US",
    "sg:address":"5766 S River Loop",
    "sg:city":"Lincoln City",
    "sg:classifiers":[
        {
            "category":"Professional",
            "subcategory":"Business Services",
            "type":"Services"
        }
    ],
    "sg:phone":"+1 503 550 8224",
    "sg:postcode":"97367",
    "sg:province":"OR",
    "wof:name":"Northwest Sacred Reiki Academy",
    "wof:placetype":"venue"
},
  "geometry": {"coordinates":[-123.939669,44.859925],"type":"Point"}
}