{
  "type": "Feature",
  "properties": {
    "addr:full":"165 N Main St Ashland OR 97520",
    "addr:housenumber":"165",
    "addr:postcode":"97520",
    "addr:street":"N Main St",
    "iso:country":"US",
    "sg:address":"165 N Main St",
    "sg:city":"Ashland",
    "sg:phone":"+1 541 210 3789",
    "sg:postcode":"97520",
    "sg:province":"OR",
    "wof:name":"Oregon Paint Company",
    "wof:placetype":"venue"
},
  "geometry": {"coordinates":[-122.71758800000001,42.200331],"type":"Point"}
}