{
  "type": "Feature",
  "properties": {
    "iso:country":"US",
    "sg:address":"18575 Couch Market Rd",
    "sg:city":"Bend",
    "sg:classifiers":[
        {
            "category":"Shopping",
            "type":"Retail Goods"
        }
    ],
    "sg:phone":"+1 541 388 6869",
    "sg:postcode":"97701",
    "sg:province":"OR",
    "sg:tags":[
        "merchandise"
    ],
    "wof:name":"Johnsons Creative Horizons",
    "wof:placetype":"venue"
},
  "geometry": {"coordinates":[-121.397589,44.167277],"type":"Point"}
}