{
  "type": "Feature",
  "properties": {
    "addr:full":"1519 SW Marlow Ave Portland OR 97225",
    "addr:housenumber":"1519",
    "addr:postcode":"97225",
    "addr:street":"Sw Marlow Ave",
    "iso:country":"US",
    "sg:address":"1519 SW Marlow Ave",
    "sg:city":"Portland",
    "sg:classifiers":[
        {
            "category":"Real Estate",
            "subcategory":"Real Estate Agent",
            "type":"Services"
        }
    ],
    "sg:phone":"+1 503 292 8125",
    "sg:postcode":"97225",
    "sg:province":"OR",
    "sg:website":"www.mcneeley.com",
    "wof:name":"Jim Mc Neeley Real Estate",
    "wof:placetype":"venue"
},
  "geometry": {"coordinates":[-122.78417,45.508232],"type":"Point"}
}