{
  "type": "Feature",
  "properties": {
    "iso:country":"US",
    "sg:address":"940 Upper Devon Ln",
    "sg:city":"Lake Oswego",
    "sg:classifiers":[
        {
            "category":"Health Services",
            "subcategory":"Health Practitioner",
            "type":"Services"
        }
    ],
    "sg:phone":"+1 503 341 1192",
    "sg:postcode":"97034",
    "sg:province":"OR",
    "sg:tags":[
        "speech",
        "technology"
    ],
    "wof:name":"Biospeech Inc",
    "wof:placetype":"venue"
},
  "geometry": {"coordinates":[-122.669688,45.402796],"type":"Point"}
}