{
  "type": "Feature",
  "properties": {
    "iso:country":"US",
    "sg:address":"3758 Mica View Ct SE",
    "sg:city":"Salem",
    "sg:classifiers":[
        {
            "category":"Real Estate",
            "subcategory":"Real Estate Operator",
            "type":"Services"
        }
    ],
    "sg:phone":"+1 503 399 8696",
    "sg:postcode":"97302",
    "sg:province":"OR",
    "wof:name":"Rippling Brook Terrace",
    "wof:placetype":"venue"
},
  "geometry": {"coordinates":[-123.05039499999999,44.901177],"type":"Point"}
}