{
  "type": "Feature",
  "properties": {
    "iso:country":"US",
    "sg:address":"437 S Bridge St",
    "sg:city":"Sheridan",
    "sg:classifiers":[
        {
            "category":"Education",
            "subcategory":"School",
            "type":"Public Place"
        }
    ],
    "sg:phone":"+1 503 843 2687",
    "sg:postcode":"97378",
    "sg:province":"OR",
    "sg:tags":[
        "elementary"
    ],
    "wof:name":"20030811",
    "wof:placetype":"venue"
},
  "geometry": {"coordinates":[-123.39536200000001,45.096029],"type":"Point"}
}