{
  "type": "Feature",
  "properties": {
    "iso:country":"US",
    "sg:address":"17180 NW Springville Rd",
    "sg:city":"Portland",
    "sg:classifiers":[
        {
            "category":"Retail",
            "subcategory":"Auto Repair",
            "type":"Services"
        }
    ],
    "sg:phone":"+1 503 629 0470",
    "sg:postcode":"97229",
    "sg:province":"OR",
    "wof:name":"NW Subaru Service",
    "wof:placetype":"venue"
},
  "geometry": {"coordinates":[-122.85370899999999,45.56296],"type":"Point"}
}