{
  "type": "Feature",
  "properties": {
    "addr:full":"544 W Umpqua St Roseburg OR 97470",
    "addr:housenumber":"544",
    "addr:postcode":"97470",
    "addr:street":"W Umpqua St",
    "iso:country":"US",
    "sg:address":"544 W Umpqua St",
    "sg:city":"Roseburg",
    "sg:classifiers":[
        {
            "category":"Health Services",
            "subcategory":"Doctor",
            "type":"Services"
        }
    ],
    "sg:phone":"+1 541 673 0496",
    "sg:postcode":"97470",
    "sg:province":"OR",
    "sg:tags":[
        "medical"
    ],
    "wof:name":"Edward J Ottenheimer",
    "wof:placetype":"venue"
},
  "geometry": {"coordinates":[-123.359172,43.215299],"type":"Point"}
}