{
  "type": "Feature",
  "properties": {
    "iso:country":"US",
    "sg:address":"8325 SW 42nd Ave.",
    "sg:city":"Portland",
    "sg:classifiers":[
        {
            "category":"Building & Trades",
            "subcategory":"Landscaping Services",
            "type":"Services"
        }
    ],
    "sg:phone":"+1 503 452 8160",
    "sg:postcode":"97219",
    "sg:province":"OR",
    "sg:tags":[
        "tree"
    ],
    "sg:website":"www.multnomahtree.com",
    "wof:name":"Multnomah Tree Experts Ltd",
    "wof:placetype":"venue"
},
  "geometry": {"coordinates":[-122.72094,45.464568],"type":"Point"}
}