{
  "type": "Feature",
  "properties": {
    "iso:country":"US",
    "sg:address":"1885 16th St SE",
    "sg:city":"Salem",
    "sg:classifiers":[
        {
            "category":"Professional",
            "subcategory":"Business Services",
            "type":"Services"
        }
    ],
    "sg:phone":"+1 503 363 8894",
    "sg:postcode":"97302",
    "sg:province":"OR",
    "sg:tags":[
        "organizing",
        "services-household"
    ],
    "wof:name":"Willamette Management Services",
    "wof:placetype":"venue"
},
  "geometry": {"coordinates":[-123.025248,44.91935],"type":"Point"}
}