{
  "type": "Feature",
  "properties": {
    "iso:country":"US",
    "sg:address":"13640 Johnson Ter",
    "sg:city":"Lake Oswego",
    "sg:classifiers":[
        {
            "category":"Restaurant",
            "type":"Food & Drink"
        }
    ],
    "sg:phone":"+1 503 636 3931",
    "sg:postcode":"97034",
    "sg:province":"OR",
    "sg:tags":[
        "eating"
    ],
    "wof:name":"Catering By Gail",
    "wof:placetype":"venue"
},
  "geometry": {"coordinates":[-122.69917599999999,45.426515],"type":"Point"}
}