{
  "type": "Feature",
  "properties": {
    "iso:country":"US",
    "sg:address":"16209 SE Webster Rd",
    "sg:city":"Portland",
    "sg:classifiers":[
        {
            "category":"Building & Trades",
            "subcategory":"Plumbing",
            "type":"Services"
        }
    ],
    "sg:phone":"+1 503 653 1636",
    "sg:postcode":"97267",
    "sg:province":"OR",
    "sg:tags":[
        "heating",
        "contractor"
    ],
    "wof:name":"Sure Flow HVAC",
    "wof:placetype":"venue"
},
  "geometry": {"coordinates":[-122.58732999999999,45.406139],"type":"Point"}
}