{
  "type": "Feature",
  "properties": {
    "iso:country":"US",
    "sg:address":"11556 SE Fuller Rd",
    "sg:city":"Portland",
    "sg:classifiers":[
        {
            "category":"Real Estate",
            "subcategory":"Real Estate Operator",
            "type":"Services"
        }
    ],
    "sg:phone":"+1 503 654 1434",
    "sg:postcode":"97222",
    "sg:province":"OR",
    "sg:tags":[
        "building",
        "apartment"
    ],
    "wof:name":"Pointe West Apartments",
    "wof:placetype":"venue"
},
  "geometry": {"coordinates":[-122.583285,45.439057],"type":"Point"}
}