{
  "type": "Feature",
  "properties": {
    "iso:country":"US",
    "sg:address":"30004 State Hwy 213",
    "sg:city":"Molalla",
    "sg:classifiers":[
        {
            "category":"Building & Trades",
            "subcategory":"Construction",
            "type":"Services"
        }
    ],
    "sg:phone":"+1 503 651 3614",
    "sg:postcode":"97038",
    "sg:province":"OR",
    "sg:tags":[
        "masonry",
        "contractor"
    ],
    "wof:name":"Molalla Masonry",
    "wof:placetype":"venue"
},
  "geometry": {"coordinates":[-122.595276,45.172449],"type":"Point"}
}