{
  "type": "Feature",
  "properties": {
    "iso:country":"US",
    "sg:address":"255 Capitol St NE",
    "sg:city":"Salem",
    "sg:classifiers":[
        {
            "category":"Government",
            "subcategory":"Office",
            "type":"Public Place"
        }
    ],
    "sg:phone":"+1 503 378 3121",
    "sg:postcode":"97301",
    "sg:province":"OR",
    "sg:tags":[
        "state"
    ],
    "wof:name":"Communications Division",
    "wof:placetype":"venue"
},
  "geometry": {"coordinates":[-123.028036,44.939677],"type":"Point"}
}