{
  "type": "Feature",
  "properties": {
    "iso:country":"US",
    "sg:address":"3825 SW Hall Blvd",
    "sg:city":"Beaverton",
    "sg:classifiers":[
        {
            "category":"Real Estate",
            "subcategory":"Developer",
            "type":"Services"
        }
    ],
    "sg:phone":"+1 503 646 2030",
    "sg:postcode":"97005",
    "sg:province":"OR",
    "sg:tags":[
        "bond",
        "broker",
        "stock"
    ],
    "wof:name":"Biggi Investment Co Inc",
    "wof:placetype":"venue"
},
  "geometry": {"coordinates":[-122.80665,45.49291],"type":"Point"}
}