{
  "type": "Feature",
  "properties": {
    "iso:country":"US",
    "sg:address":"9295 SW Electric St",
    "sg:city":"Portland",
    "sg:classifiers":[
        {
            "category":"Professional",
            "subcategory":"Management & Consulting",
            "type":"Services"
        }
    ],
    "sg:phone":"+1 503 639 6446",
    "sg:postcode":"97223",
    "sg:province":"OR",
    "sg:tags":[
        "marketing",
        "program"
    ],
    "wof:name":"Nw Core Collection",
    "wof:placetype":"venue"
},
  "geometry": {"coordinates":[-122.772021,45.430465],"type":"Point"}
}