{
  "type": "Feature",
  "properties": {
    "iso:country":"US",
    "sg:address":"1111 SW Broadway",
    "sg:city":"Portland",
    "sg:classifiers":[
        {
            "category":"Arts & Performance",
            "subcategory":"Theater",
            "type":"Entertainment"
        }
    ],
    "sg:phone":"+1 503 248 4335",
    "sg:postcode":"97205",
    "sg:province":"OR",
    "sg:tags":[
        "theatrical",
        "manager",
        "producer"
    ],
    "sg:website":"http://www.newmarktheatre.com",
    "wof:name":"Administrative Office",
    "wof:placetype":"venue"
},
  "geometry": {"coordinates":[-122.681068,45.516613],"type":"Point"}
}