{
  "type": "Feature",
  "properties": {
    "addr:full":"4590 SW 103rd Ave Beaverton OR 97005",
    "addr:housenumber":"4590",
    "addr:postcode":"97005",
    "addr:street":"Sw 103Rd Ave",
    "iso:country":"US",
    "sg:address":"4590 SW 103rd Ave",
    "sg:city":"Beaverton",
    "sg:classifiers":[
        {
            "category":"Personal",
            "subcategory":"Beauty Salon",
            "type":"Services"
        }
    ],
    "sg:phone":"+1 503 643 8526",
    "sg:postcode":"97005",
    "sg:province":"OR",
    "sg:tags":[
        "shop"
    ],
    "wof:name":"Classy Lady Hair Design",
    "wof:placetype":"venue"
},
  "geometry": {"coordinates":[-122.783069,45.486806],"type":"Point"}
}