{
  "type": "Feature",
  "properties": {
    "iso:country":"US",
    "sg:address":"604 W Central St",
    "sg:city":"Gates",
    "sg:classifiers":[
        {
            "category":"Professional",
            "type":"Services"
        }
    ],
    "sg:phone":"+1 503 897 2735",
    "sg:postcode":"97346",
    "sg:province":"OR",
    "wof:name":"University Lithos",
    "wof:placetype":"venue"
},
  "geometry": {"coordinates":[-122.4225,44.75553],"type":"Point"}
}