{
  "type": "Feature",
  "properties": {
    "iso:country":"US",
    "sg:address":"7211 SE Harmony Rd Apt# 165",
    "sg:city":"Portland",
    "sg:phone":"+1 503 449 8559",
    "sg:postcode":"97222",
    "sg:province":"OR",
    "wof:name":"Jimenez Construction",
    "wof:placetype":"venue"
},
  "geometry": {"coordinates":[-122.588852,45.432339],"type":"Point"}
}