{
  "type": "Feature",
  "properties": {
    "iso:country":"US",
    "sg:address":"6116 SE Milwaukie Ave",
    "sg:city":"Portland",
    "sg:classifiers":[
        {
            "category":"Health Services",
            "subcategory":"Dentist",
            "type":"Services"
        }
    ],
    "sg:phone":"+1 503 232 8088",
    "sg:postcode":"97202",
    "sg:province":"OR",
    "wof:name":"A Farid Bolouri DMD PC and Associates",
    "wof:placetype":"venue"
},
  "geometry": {"coordinates":[-122.649002,45.4781],"type":"Point"}
}