{
  "type": "Feature",
  "properties": {
    "iso:country":"US",
    "sg:address":"180 N Main St",
    "sg:city":"Banks",
    "sg:classifiers":[
        {
            "category":"Building & Trades",
            "subcategory":"Electrical",
            "type":"Services"
        }
    ],
    "sg:phone":"+1 503 324 0948",
    "sg:postcode":"97106",
    "sg:province":"OR",
    "sg:tags":[
        "electrical",
        "contractor"
    ],
    "wof:name":"Five Star Electric Inc",
    "wof:placetype":"venue"
},
  "geometry": {"coordinates":[-123.11423000000001,45.621477],"type":"Point"}
}