{
  "type": "Feature",
  "properties": {
    "iso:country":"US",
    "sg:address":"1741 W 34th Pl",
    "sg:city":"Eugene",
    "sg:classifiers":[
        {
            "category":"Social Services",
            "subcategory":"Job Training",
            "type":"Services"
        }
    ],
    "sg:phone":"+1 541 686 0993",
    "sg:postcode":"97405",
    "sg:province":"OR",
    "wof:name":"Sandler Sales Institute",
    "wof:placetype":"venue"
},
  "geometry": {"coordinates":[-123.119483,44.018896],"type":"Point"}
}