{
  "type": "Feature",
  "properties": {
    "addr:full":"11933 SE Stark St Portland OR 97216",
    "addr:postcode":"11933;97216",
    "addr:street":"Se Stark St",
    "iso:country":"US",
    "sg:address":"11933 SE Stark St",
    "sg:city":"Portland",
    "sg:classifiers":[
        {
            "category":"Personal",
            "subcategory":"Beauty Salon",
            "type":"Services"
        }
    ],
    "sg:phone":"+1 503 252 4695",
    "sg:postcode":"97216",
    "sg:province":"OR",
    "sg:tags":[
        "shop"
    ],
    "wof:name":"Jacquelines For Hair",
    "wof:placetype":"venue"
},
  "geometry": {"coordinates":[-122.537975,45.519097],"type":"Point"}
}