{
  "type": "Feature",
  "properties": {
    "iso:country":"US",
    "sg:address":"264 Norton Rd",
    "sg:city":"Williams",
    "sg:classifiers":[
        {
            "category":"Farming",
            "subcategory":"Livestock Farm",
            "type":"Manufacturing & Wholesale Goods"
        }
    ],
    "sg:phone":"+1 541 846 6090",
    "sg:postcode":"97544",
    "sg:province":"OR",
    "sg:tags":[
        "beef",
        "feedlot",
        "cattle"
    ],
    "wof:name":"Rainbird Ranch",
    "wof:placetype":"venue"
},
  "geometry": {"coordinates":[-123.273419,42.223027],"type":"Point"}
}