{
  "type": "Feature",
  "properties": {
    "addr:full":"1133 NE 37th Ave Portland OR 97232",
    "addr:housenumber":"1133",
    "addr:postcode":"97232",
    "addr:street":"Ne 37Th Ave",
    "iso:country":"US",
    "sg:address":"1133 NE 37th Ave",
    "sg:city":"Portland",
    "sg:classifiers":[
        {
            "category":"Real Estate",
            "subcategory":"Real Estate Agent",
            "type":"Services"
        }
    ],
    "sg:phone":"+1 503 239 8118",
    "sg:postcode":"97232",
    "sg:province":"OR",
    "wof:name":"Redtail Properties Llc",
    "wof:placetype":"venue"
},
  "geometry": {"coordinates":[-122.62495699999999,45.531249],"type":"Point"}
}