{
  "type": "Feature",
  "properties": {
    "addr:full":"903 SE Armour Rd Bend OR 97702",
    "addr:housenumber":"903",
    "addr:postcode":"97702",
    "addr:street":"Se Armour Rd",
    "iso:country":"US",
    "sg:address":"903 SE Armour Rd",
    "sg:city":"Bend",
    "sg:classifiers":[
        {
            "category":"Shopping",
            "subcategory":"Used Merchandise",
            "type":"Retail Goods"
        }
    ],
    "sg:phone":"+1 541 389 7047",
    "sg:postcode":"97702",
    "sg:province":"OR",
    "sg:tags":[
        "business",
        "general"
    ],
    "wof:name":"PAKIT Liquidators",
    "wof:placetype":"venue"
},
  "geometry": {"coordinates":[-121.289626,44.046314],"type":"Point"}
}