{
  "type": "Feature",
  "properties": {
    "addr:full":"2812 Goldfinch Loop Albany OR 97322",
    "addr:housenumber":"2812",
    "addr:postcode":"97322",
    "addr:street":"Goldfinch Loop",
    "iso:country":"US",
    "sg:address":"2812 Goldfinch Loop",
    "sg:city":"Albany",
    "sg:classifiers":[
        {
            "category":"Real Estate",
            "subcategory":"Real Estate Operator",
            "type":"Services"
        }
    ],
    "sg:phone":"+1 541 924 3877",
    "sg:postcode":"97322",
    "sg:province":"OR",
    "sg:tags":[
        "property",
        "lessor"
    ],
    "wof:name":"Van S Dyke",
    "wof:placetype":"venue"
},
  "geometry": {"coordinates":[-123.07280299999999,44.598765],"type":"Point"}
}