{
  "type": "Feature",
  "properties": {
    "iso:country":"US",
    "sg:address":"42279 Fish Hatchery Dr",
    "sg:city":"Scio",
    "sg:classifiers":[
        {
            "category":"Government",
            "subcategory":"Office",
            "type":"Public Place"
        }
    ],
    "sg:phone":"+1 503 394 2397",
    "sg:postcode":"97374",
    "sg:province":"OR",
    "sg:tags":[
        "state"
    ],
    "wof:name":"Fish & Wildlife Hatchery Host",
    "wof:placetype":"venue"
},
  "geometry": {"coordinates":[-122.71687300000001,44.624471],"type":"Point"}
}