{
  "type": "Feature",
  "properties": {
    "iso:country":"US",
    "sg:address":"3405 SE 82nd Ave",
    "sg:city":"Portland",
    "sg:classifiers":[
        {
            "category":"Autos & Motor Vehicles",
            "subcategory":"Automobile Sales",
            "type":"Retail Goods"
        }
    ],
    "sg:phone":"+1 503 772 2933",
    "sg:postcode":"97266",
    "sg:province":"OR",
    "sg:tags":[
        "used"
    ],
    "wof:name":"Direct Auto Wholesale",
    "wof:placetype":"venue"
},
  "geometry": {"coordinates":[-122.578743,45.497955],"type":"Point"}
}