{
  "type": "Feature",
  "properties": {
    "iso:country":"US",
    "sg:address":"42426 SE Wildcat Mountain Dr",
    "sg:city":"Sandy",
    "sg:classifiers":[
        {
            "category":"Professional",
            "type":"Services"
        }
    ],
    "sg:phone":"+1 503 668 9288",
    "sg:postcode":"97055",
    "sg:province":"OR",
    "wof:name":"In The Family Way",
    "wof:placetype":"venue"
},
  "geometry": {"coordinates":[-122.22736,45.338398],"type":"Point"}
}