{
  "type": "Feature",
  "properties": {
    "iso:country":"US",
    "sg:address":"19730 SW Cipole Rd",
    "sg:city":"Tualatin",
    "sg:classifiers":[
        {
            "category":"Professional",
            "subcategory":"Business Services",
            "type":"Services"
        }
    ],
    "sg:phone":"+1 503 692 6691",
    "sg:postcode":"97062",
    "sg:province":"OR",
    "sg:tags":[
        "industrial",
        "machinery",
        "mfg"
    ],
    "wof:name":"Rowans Machine Works",
    "wof:placetype":"venue"
},
  "geometry": {"coordinates":[-122.814305,45.376656],"type":"Point"}
}