{
  "type": "Feature",
  "properties": {
    "iso:country":"US",
    "sg:address":"175 NE 16th St",
    "sg:city":"Madras",
    "sg:classifiers":[
        {
            "category":"Health Services",
            "subcategory":"Nursing And Care Facility",
            "type":"Services"
        }
    ],
    "sg:phone":"+1 541 475 2273",
    "sg:postcode":"97741",
    "sg:province":"OR",
    "sg:tags":[
        "home",
        "retirement",
        "community"
    ],
    "wof:name":"East Cascade Assisted Living",
    "wof:placetype":"venue"
},
  "geometry": {"coordinates":[-121.117644,44.638533],"type":"Point"}
}