{
  "type": "Feature",
  "properties": {
    "iso:country":"US",
    "sg:address":"441 N Main St",
    "sg:city":"Heppner",
    "sg:classifiers":[
        {
            "category":"Organizations",
            "subcategory":"Non-profit Organization",
            "type":"Services"
        }
    ],
    "sg:phone":"+1 541 676 5024",
    "sg:postcode":"97836",
    "sg:province":"OR",
    "wof:name":"Neighborhood Center-S Morrow",
    "wof:placetype":"venue"
},
  "geometry": {"coordinates":[-119.553462,45.357085],"type":"Point"}
}