{
  "type": "Feature",
  "properties": {
    "addr:full":"2620 NE 5th St Redmond OR 97756",
    "addr:housenumber":"2620",
    "addr:postcode":"97756",
    "addr:street":"Ne 5Th St",
    "iso:country":"US",
    "sg:address":"2620 NE 5th St",
    "sg:city":"Redmond",
    "sg:classifiers":[
        {
            "category":"Professional",
            "subcategory":"Accounting & Tax Preparation",
            "type":"Services"
        }
    ],
    "sg:phone":"+1 541 550 0465",
    "sg:postcode":"97756",
    "sg:province":"OR",
    "sg:tags":[
        "bookkeeping",
        "billing"
    ],
    "wof:name":"Ferry's Bookkeeping, Etc.",
    "wof:placetype":"venue"
},
  "geometry": {"coordinates":[-121.16387899999999,44.300309],"type":"Point"}
}