{
  "type": "Feature",
  "properties": {
    "addr:full":"1001 SW Highland Dr Gresham OR 97080",
    "addr:housenumber":"1001",
    "addr:postcode":"97080",
    "addr:street":"Sw Highland Dr",
    "iso:country":"US",
    "sg:address":"1001 SW Highland Dr",
    "sg:city":"Gresham",
    "sg:classifiers":[
        {
            "category":"Utilities",
            "subcategory":"Mobile Phone",
            "type":"Services"
        },
        {
            "category":"Coffee & Tea",
            "type":"Food & Drink"
        }
    ],
    "sg:phone":"+1 503 674 7080",
    "sg:postcode":"97080",
    "sg:province":"OR",
    "sg:tags":[
        "shop",
        "wi-fi",
        "espresso",
        "hotspot",
        "restaurant"
    ],
    "sg:website":"http://www.starbuckscoffee.com",
    "wof:name":"Starbucks Coffee",
    "wof:placetype":"venue"
},
  "geometry": {"coordinates":[-122.47554,45.489482],"type":"Point"}
}