{
  "type": "Feature",
  "properties": {
    "iso:country":"US",
    "sg:address":"350 W Marine Dr",
    "sg:city":"Astoria",
    "sg:classifiers":[
        {
            "category":"Government",
            "subcategory":"Office",
            "type":"Public Place"
        }
    ],
    "sg:phone":"+1 503 861 0159",
    "sg:postcode":"97103",
    "sg:province":"OR",
    "sg:tags":[
        "government-state"
    ],
    "wof:name":"Oregon Department Of Transportation",
    "wof:placetype":"venue"
},
  "geometry": {"coordinates":[-123.85266900000001,46.187691],"type":"Point"}
}