{
  "type": "Feature",
  "properties": {
    "addr:full":"5128 SE Bybee Blvd Portland OR 97206",
    "addr:housenumber":"5128",
    "addr:postcode":"97206",
    "addr:street":"Se Bybee Blvd",
    "iso:country":"US",
    "sg:address":"5128 SE Bybee Blvd",
    "sg:city":"Portland",
    "sg:classifiers":[
        {
            "category":"Shopping",
            "subcategory":"Hobbies, Toys, & Games",
            "type":"Retail Goods"
        }
    ],
    "sg:phone":"+1 503 735 9659",
    "sg:postcode":"97206",
    "sg:province":"OR",
    "wof:name":"Creative Cottage",
    "wof:placetype":"venue"
},
  "geometry": {"coordinates":[-122.610204,45.472499],"type":"Point"}
}