{
  "type": "Feature",
  "properties": {
    "addr:full":"6033 NW Lilac Hill Rd Yamhill OR 97148",
    "addr:housenumber":"6033",
    "addr:postcode":"97148",
    "addr:street":"Nw Lilac Hill Rd",
    "iso:country":"US",
    "sg:address":"6033 NW Lilac Hill Rd",
    "sg:city":"Yamhill",
    "sg:classifiers":[
        {
            "category":"Professional",
            "subcategory":"Accounting & Tax Preparation",
            "type":"Services"
        }
    ],
    "sg:phone":"+1 503 662 4784",
    "sg:postcode":"97148",
    "sg:province":"OR",
    "sg:tags":[
        "return",
        "preparation-business"
    ],
    "wof:name":"Able Tax Service",
    "wof:placetype":"venue"
},
  "geometry": {"coordinates":[-123.174877,45.371481],"type":"Point"}
}