{
  "type": "Feature",
  "properties": {
    "addr:full":"2030 NE Lafayette Ave Mcminnville OR 97128",
    "addr:housenumber":"2030",
    "addr:postcode":"97128",
    "addr:street":"Ne Lafayette Ave",
    "iso:country":"US",
    "sg:address":"2030 NE Lafayette Ave",
    "sg:city":"Mcminnville",
    "sg:classifiers":[
        {
            "category":"Manufacturing",
            "subcategory":"Toys & Sporting Goods",
            "type":"Manufacturing & Wholesale Goods"
        }
    ],
    "sg:phone":"+1 503 474 9123",
    "sg:postcode":"97128",
    "sg:province":"OR",
    "wof:name":"Rainbow Village Toys",
    "wof:placetype":"venue"
},
  "geometry": {"coordinates":[-123.17542299999999,45.22377],"type":"Point"}
}