{
  "type": "Feature",
  "properties": {
    "addr:full":"2203 4th St Tillamook OR 97141",
    "addr:housenumber":"2203",
    "addr:postcode":"97141",
    "addr:street":"4Th St",
    "iso:country":"US",
    "sg:address":"2203 4th St",
    "sg:city":"Tillamook",
    "sg:classifiers":[
        {
            "category":"Organizations",
            "subcategory":"Religious Organization",
            "type":"Services"
        }
    ],
    "sg:phone":"+1 503 842 6213",
    "sg:postcode":"97141",
    "sg:province":"OR",
    "sg:tags":[
        "churches-interdenominational",
        "christ",
        "church"
    ],
    "wof:name":"First Christian Church",
    "wof:placetype":"venue"
},
  "geometry": {"coordinates":[-123.842066,45.455559],"type":"Point"}
}