{
  "type": "Feature",
  "properties": {
    "iso:country":"US",
    "sg:address":"48 S Birch Ave",
    "sg:city":"Burns",
    "sg:classifiers":[
        {
            "category":"Building & Trades",
            "subcategory":"Construction",
            "type":"Services"
        }
    ],
    "sg:phone":"+1 541 573 2596",
    "sg:postcode":"97720",
    "sg:province":"OR",
    "sg:tags":[
        "general",
        "contractor"
    ],
    "wof:name":"Northwest Solar & Construction",
    "wof:placetype":"venue"
},
  "geometry": {"coordinates":[-119.052398,43.585431],"type":"Point"}
}