{
  "type": "Feature",
  "properties": {
    "addr:full":"4731 Calumet Way Eugene OR 97404",
    "addr:housenumber":"4731",
    "addr:postcode":"97404",
    "addr:street":"Calumet Way",
    "iso:country":"US",
    "sg:address":"4731 Calumet Way",
    "sg:city":"Eugene",
    "sg:classifiers":[
        {
            "category":"Building & Trades",
            "subcategory":"Equipment Rental",
            "type":"Services"
        }
    ],
    "sg:phone":"+1 541 463 7871",
    "sg:postcode":"97404",
    "sg:province":"OR",
    "wof:name":"Jjs Tree Farm & Rentl Property",
    "wof:placetype":"venue"
},
  "geometry": {"coordinates":[-123.133393,44.128683],"type":"Point"}
}