{
  "type": "Feature",
  "properties": {
    "iso:country":"US",
    "sg:address":"16703 SE McLoughlin Blvd",
    "sg:city":"Oak Grove",
    "sg:classifiers":[
        {
            "category":"Banks & Credit Unions",
            "subcategory":"Bank",
            "type":"Services"
        }
    ],
    "sg:phone":"+1 503 659 7037",
    "sg:postcode":"97267",
    "sg:province":"OR",
    "sg:tags":[
        "financing"
    ],
    "wof:name":"Central Finance",
    "wof:placetype":"venue"
},
  "geometry": {"coordinates":[-122.621713,45.403024],"type":"Point"}
}