{
  "type": "Feature",
  "properties": {
    "addr:full":"256 NW 23rd Pl Ste 406 Portland OR 97210",
    "addr:housenumber":"256",
    "addr:postcode":"97210",
    "addr:street":"Nw 23Rd Pl Ste 406",
    "iso:country":"US",
    "sg:address":"256 NW 23rd Pl Ste 406",
    "sg:city":"Portland",
    "sg:classifiers":[
        {
            "category":"Manufacturing",
            "subcategory":"Printing",
            "type":"Manufacturing & Wholesale Goods"
        },
        {
            "category":"Wholesale",
            "subcategory":"Books, Periodicals, & Newspapers",
            "type":"Manufacturing & Wholesale Goods"
        }
    ],
    "sg:phone":"+1 503 223 9036",
    "sg:postcode":"97210",
    "sg:province":"OR",
    "sg:tags":[
        "magazines-distributors",
        "magazine"
    ],
    "wof:name":"Cascadia Times Inc",
    "wof:placetype":"venue"
},
  "geometry": {"coordinates":[-122.699444,45.524348],"type":"Point"}
}