{
  "type": "Feature",
  "properties": {
    "iso:country":"US",
    "sg:address":"6962 SW Beaverton-Hillsdale Hwy",
    "sg:city":"Portland",
    "sg:classifiers":[
        {
            "category":"Professional",
            "subcategory":"Secretarial Services",
            "type":"Services"
        }
    ],
    "sg:phone":"+1 503 977 0463",
    "sg:postcode":"97225",
    "sg:province":"OR",
    "sg:tags":[
        "convention",
        "court",
        "reporter"
    ],
    "wof:name":"Kairis Court Reporting",
    "wof:placetype":"venue"
},
  "geometry": {"coordinates":[-122.754625,45.486038],"type":"Point"}
}