{
  "type": "Feature",
  "properties": {
    "addr:full":"10202 SE 32nd Avenue Suite 502 Portland OR 97222",
    "addr:housenumber":"10202",
    "addr:postcode":"97222",
    "addr:street":"Se 32Nd Avenue Suite 502",
    "iso:country":"US",
    "sg:address":"10202 SE 32nd Avenue Suite 502",
    "sg:city":"Portland",
    "sg:classifiers":[
        {
            "category":"Health Services",
            "subcategory":"Doctor",
            "type":"Services"
        }
    ],
    "sg:phone":"+1 503 654 3108",
    "sg:postcode":"97222",
    "sg:province":"OR",
    "wof:name":"Budden Moir M MD",
    "wof:placetype":"venue"
},
  "geometry": {"coordinates":[-122.629763,45.449423],"type":"Point"}
}