{
  "type": "Feature",
  "properties": {
    "iso:country":"US",
    "sg:address":"1285 Wallis St",
    "sg:city":"Eugene",
    "sg:classifiers":[
        {
            "category":"Manufacturing",
            "subcategory":"Buildings",
            "type":"Manufacturing & Wholesale Goods"
        }
    ],
    "sg:phone":"+1 541 343 5330",
    "sg:postcode":"97402",
    "sg:province":"OR",
    "sg:tags":[
        "prefab"
    ],
    "sg:website":"www.yurtworks.com",
    "wof:name":"Oregon Yurt Works",
    "wof:placetype":"venue"
},
  "geometry": {"coordinates":[-123.155614,44.046583],"type":"Point"}
}