{
  "type": "Feature",
  "properties": {
    "iso:country":"US",
    "sg:address":"319 E Pine St",
    "sg:city":"Central Point",
    "sg:classifiers":[
        {
            "category":"Insurance",
            "subcategory":"Insurance Agent",
            "type":"Services"
        }
    ],
    "sg:phone":"+1 541 664 3352",
    "sg:postcode":"97502",
    "sg:province":"OR",
    "wof:name":"Chambers Insurance Services",
    "wof:placetype":"venue"
},
  "geometry": {"coordinates":[-122.914688,42.37559],"type":"Point"}
}