{
  "type": "Feature",
  "properties": {
    "addr:full":"64837 E Riverside Dr Brightwood OR 97067",
    "addr:housenumber":"64837",
    "addr:postcode":"97067",
    "addr:street":"E Riverside Dr",
    "iso:country":"US",
    "sg:address":"64837 E Riverside Dr",
    "sg:city":"Brightwood",
    "sg:classifiers":[
        {
            "category":"Arts & Performance",
            "subcategory":"Theater",
            "type":"Entertainment"
        }
    ],
    "sg:phone":"+1 503 622 4537",
    "sg:postcode":"97067",
    "sg:province":"OR",
    "sg:tags":[
        "group"
    ],
    "wof:name":"Back Up & Push",
    "wof:placetype":"venue"
},
  "geometry": {"coordinates":[-121.997675,45.364939],"type":"Point"}
}