{
  "type": "Feature",
  "properties": {
    "addr:full":"6153 SW Murray Blvd Beaverton OR 97008",
    "addr:housenumber":"6153",
    "addr:postcode":"97008",
    "addr:street":"Sw Murray Blvd",
    "iso:country":"US",
    "sg:address":"6153 SW Murray Blvd",
    "sg:city":"Beaverton",
    "sg:classifiers":[
        {
            "category":"Food & Beverages",
            "subcategory":"Specialty",
            "type":"Retail Goods"
        },
        {
            "category":"Food & Beverages",
            "subcategory":"Groceries & Convenience Stores",
            "type":"Retail Goods"
        }
    ],
    "sg:phone":"+1 503 646 7673",
    "sg:postcode":"97008",
    "sg:province":"OR",
    "sg:tags":[
        "gourmet",
        "shop"
    ],
    "wof:name":"Rose International Gourmet Food",
    "wof:placetype":"venue"
},
  "geometry": {"coordinates":[-122.825996,45.475399],"type":"Point"}
}