{
  "type": "Feature",
  "properties": {
    "addr:full":"1585 N 5th St Springfield OR 97477",
    "addr:housenumber":"1585",
    "addr:postcode":"97477",
    "addr:street":"N 5Th St",
    "iso:country":"US",
    "sg:address":"1585 N 5th St",
    "sg:city":"Springfield",
    "sg:classifiers":[
        {
            "category":"Organizations",
            "subcategory":"Religious Organization",
            "type":"Services"
        }
    ],
    "sg:phone":"+1 541 744 1079",
    "sg:postcode":"97477",
    "sg:province":"OR",
    "wof:name":"Family Christn Ctr Church God",
    "wof:placetype":"venue"
},
  "geometry": {"coordinates":[-123.01929699999999,44.060034],"type":"Point"}
}