{
  "type": "Feature",
  "properties": {
    "addr:full":"3282 W 1st Ave Eugene OR 97402",
    "addr:housenumber":"3282",
    "addr:postcode":"97402",
    "addr:street":"W 1St Ave",
    "iso:country":"US",
    "sg:address":"3282 W 1st Ave",
    "sg:city":"Eugene",
    "sg:classifiers":[
        {
            "category":"Wholesale",
            "subcategory":"Construction Materials",
            "type":"Manufacturing & Wholesale Goods"
        },
        {
            "category":"Wholesale",
            "subcategory":"Machinery & Supplies",
            "type":"Manufacturing & Wholesale Goods"
        },
        {
            "category":"Home & Garden",
            "subcategory":"Building Materials",
            "type":"Retail Goods"
        },
        {
            "category":"Manufacturing",
            "subcategory":"Tools & Machinery",
            "type":"Manufacturing & Wholesale Goods"
        },
        {
            "category":"Wholesale",
            "subcategory":"Home Furnishings",
            "type":"Manufacturing & Wholesale Goods"
        },
        {
            "category":"Professional",
            "subcategory":"Engineering",
            "type":"Services"
        }
    ],
    "sg:phone":"+1 541 484 0836",
    "sg:postcode":"97402",
    "sg:province":"OR",
    "sg:tags":[
        "heater",
        "valve",
        "fixture",
        "system",
        "water",
        "equipment",
        "part",
        "plumbing",
        "fixtures",
        "supplies-wholesale",
        "air conditioning",
        "manufacturer"
    ],
    "sg:website":"http://www-ferguson-com.netsolads.com/index.shtml?_nsag=39482",
    "wof:name":"Ferguson",
    "wof:placetype":"venue"
},
  "geometry": {"coordinates":[-123.14805,44.058876],"type":"Point"}
}