{
  "type": "Feature",
  "properties": {
    "iso:country":"US",
    "sg:address":"8765 SW Curry Ct",
    "sg:city":"Beaverton",
    "sg:classifiers":[
        {
            "category":"Professional",
            "type":"Services"
        }
    ],
    "sg:phone":"+1 503 626 8878",
    "sg:postcode":"97008",
    "sg:province":"OR",
    "sg:tags":[
        "consulting",
        "chemist"
    ],
    "wof:name":"Cascades Materials R & D Inc",
    "wof:placetype":"venue"
},
  "geometry": {"coordinates":[-122.809726,45.457053],"type":"Point"}
}