{
  "type": "Feature",
  "properties": {
    "iso:country":"US",
    "sg:address":"5511 Main St",
    "sg:city":"Springfield",
    "sg:classifiers":[
        {
            "category":"Food & Beverages",
            "subcategory":"Liquor & Beverages",
            "type":"Retail Goods"
        }
    ],
    "sg:phone":"+1 541 726 9278",
    "sg:postcode":"97478",
    "sg:province":"OR",
    "sg:tags":[
        "store"
    ],
    "wof:name":"Village Square Beverage",
    "wof:placetype":"venue"
},
  "geometry": {"coordinates":[-122.93296100000001,44.045699],"type":"Point"}
}