{
  "type": "Feature",
  "properties": {
    "iso:country":"US",
    "sg:address":"20970 Limestone Ave",
    "sg:city":"Bend",
    "sg:classifiers":[
        {
            "category":"Communications",
            "subcategory":"Film & Video Production",
            "type":"Services"
        }
    ],
    "sg:phone":"+1 541 382 0203",
    "sg:postcode":"97701",
    "sg:province":"OR",
    "sg:tags":[
        "motion"
    ],
    "wof:name":"Videoccasions",
    "wof:placetype":"venue"
},
  "geometry": {"coordinates":[-121.273164,44.172998],"type":"Point"}
}