{
  "type": "Feature",
  "properties": {
    "iso:country":"US",
    "sg:address":"35200 Learned Rd",
    "sg:city":"Cloverdale",
    "sg:classifiers":[
        {
            "category":"Farming",
            "subcategory":"Dairy Farm",
            "type":"Manufacturing & Wholesale Goods"
        }
    ],
    "sg:phone":"+1 503 392 4554",
    "sg:postcode":"97112",
    "sg:province":"OR",
    "wof:name":"J & C Edgerly Dairy",
    "wof:placetype":"venue"
},
  "geometry": {"coordinates":[-123.924955,45.200667],"type":"Point"}
}