{
  "type": "Feature",
  "properties": {
    "iso:country":"US",
    "sg:address":"1434 SW Park Ave",
    "sg:city":"Portland",
    "sg:classifiers":[
        {
            "category":"Restaurant",
            "type":"Food & Drink"
        }
    ],
    "sg:phone":"+1 503 295 3663",
    "sg:postcode":"97201",
    "sg:province":"OR",
    "sg:tags":[
        "italian",
        "pizza"
    ],
    "wof:name":"Pizzeria La Lombardia",
    "wof:placetype":"venue"
},
  "geometry": {"coordinates":[-122.68332700000001,45.514572],"type":"Point"}
}