{
  "type": "Feature",
  "properties": {
    "addr:full":"270 Montgomery St Woodburn OR 97071",
    "addr:housenumber":"270",
    "addr:postcode":"97071",
    "addr:street":"Montgomery St",
    "iso:country":"US",
    "sg:address":"270 Montgomery St",
    "sg:city":"Woodburn",
    "sg:classifiers":[
        {
            "category":"Government",
            "subcategory":"Office",
            "type":"Public Place"
        }
    ],
    "sg:phone":"+1 503 982 5228",
    "sg:postcode":"97071",
    "sg:province":"OR",
    "sg:tags":[
        "city"
    ],
    "wof:name":"City Hall",
    "wof:placetype":"venue"
},
  "geometry": {"coordinates":[-122.85893900000001,45.142005],"type":"Point"}
}