{
  "type": "Feature",
  "properties": {
    "iso:country":"US",
    "sg:address":"4415 NE 148th Ave",
    "sg:city":"Portland",
    "sg:classifiers":[
        {
            "category":"Retail",
            "subcategory":"Repair Shop",
            "type":"Services"
        }
    ],
    "sg:phone":"+1 503 727 3037",
    "sg:postcode":"97230",
    "sg:province":"OR",
    "wof:name":"Pauls Motorcycle Restoration",
    "wof:placetype":"venue"
},
  "geometry": {"coordinates":[-122.510374,45.55643],"type":"Point"}
}