{
  "type": "Feature",
  "properties": {
    "iso:country":"US",
    "sg:address":"7000 SW Hampton St # 517",
    "sg:city":"Portland",
    "sg:classifiers":[
        {
            "category":"Professional",
            "subcategory":"Employment Agencies",
            "type":"Services"
        }
    ],
    "sg:phone":"+1 503 670 7407",
    "sg:postcode":"97223",
    "sg:province":"OR",
    "sg:tags":[
        "opportunity",
        "contractor"
    ],
    "sg:website":"http://www.integratedhealthcarestaffing.com",
    "wof:name":"Integrated Medical Systems",
    "wof:placetype":"venue"
},
  "geometry": {"coordinates":[-122.74891700000001,45.427521],"type":"Point"}
}