{
  "type": "Feature",
  "properties": {
    "addr:full":"12035 NE Marx Street Portland OR 97220",
    "addr:housenumber":"12035",
    "addr:postcode":"97220",
    "addr:street":"Ne Marx Street",
    "iso:country":"US",
    "sg:address":"12035 NE Marx Street",
    "sg:city":"Portland",
    "sg:classifiers":[
        {
            "category":"Shopping",
            "subcategory":"Optician",
            "type":"Retail Goods"
        }
    ],
    "sg:phone":"+1 503 256 4727",
    "sg:postcode":"97220",
    "sg:province":"OR",
    "sg:tags":[
        "eyewear"
    ],
    "wof:name":"Gipson Safety Company",
    "wof:placetype":"venue"
},
  "geometry": {"coordinates":[-122.53935,45.559776],"type":"Point"}
}