{
  "type": "Feature",
  "properties": {
    "addr:full":"489 N Williams St Lebanon OR 97355",
    "addr:housenumber":"489",
    "addr:postcode":"97355",
    "addr:street":"N Williams St",
    "iso:country":"US",
    "sg:address":"489 N Williams St",
    "sg:city":"Lebanon",
    "sg:classifiers":[
        {
            "category":"Building & Trades",
            "subcategory":"Construction",
            "type":"Services"
        }
    ],
    "sg:phone":"+1 541 258 8773",
    "sg:postcode":"97355",
    "sg:province":"OR",
    "sg:tags":[
        "pipe",
        "line",
        "contractor"
    ],
    "sg:website":"www.tmpipeline.com",
    "wof:name":"T & M Pipe Line Constr",
    "wof:placetype":"venue"
},
  "geometry": {"coordinates":[-122.90200400000001,44.547201],"type":"Point"}
}