{
  "type": "Feature",
  "properties": {
    "iso:country":"US",
    "sg:address":"18786 SW Boones Ferry Rd",
    "sg:city":"Tualatin",
    "sg:classifiers":[
        {
            "category":"Travel",
            "subcategory":"Hotels & Motels",
            "type":"Entertainment"
        }
    ],
    "sg:phone":"+1 503 692 2765",
    "sg:postcode":"97062",
    "sg:province":"OR",
    "wof:name":"The Country Inn",
    "wof:placetype":"venue"
},
  "geometry": {"coordinates":[-122.763625,45.384074],"type":"Point"}
}