{
  "type": "Feature",
  "properties": {
    "iso:country":"US",
    "sg:address":"951 NE Linden Ave",
    "sg:city":"Gresham",
    "sg:classifiers":[
        {
            "category":"Real Estate",
            "subcategory":"Real Estate Operator",
            "type":"Services"
        }
    ],
    "sg:phone":"+1 503 665 5074",
    "sg:postcode":"97030",
    "sg:province":"OR",
    "sg:tags":[
        "building",
        "apartment"
    ],
    "wof:name":"Linden Apartments",
    "wof:placetype":"venue"
},
  "geometry": {"coordinates":[-122.423702,45.504064],"type":"Point"}
}