{
  "type": "Feature",
  "properties": {
    "iso:country":"US",
    "sg:address":"910 Ivy St",
    "sg:city":"Junction City",
    "sg:classifiers":[
        {
            "category":"Shopping",
            "subcategory":"Pharmacy",
            "type":"Retail Goods"
        }
    ],
    "sg:phone":"+1 541 465 1435",
    "sg:postcode":"97448",
    "sg:province":"OR",
    "wof:name":"Dunnington Inc",
    "wof:placetype":"venue"
},
  "geometry": {"coordinates":[-123.204774,44.222486],"type":"Point"}
}