{
  "type": "Feature",
  "properties": {
    "iso:country":"US",
    "sg:address":"3133 Winslow Way NW",
    "sg:city":"Salem",
    "sg:classifiers":[
        {
            "category":"Real Estate",
            "subcategory":"Real Estate Agent",
            "type":"Services"
        }
    ],
    "sg:phone":"+1 503 364 9496",
    "sg:postcode":"97304",
    "sg:province":"OR",
    "wof:name":"Courtside Manor LLC",
    "wof:placetype":"venue"
},
  "geometry": {"coordinates":[-123.068959,44.979663],"type":"Point"}
}