{
  "type": "Feature",
  "properties": {
    "addr:full":"3133 Winslow Way NW Salem OR 97304",
    "addr:housenumber":"3133",
    "addr:postcode":"97304",
    "addr:street":"Winslow Way Nw",
    "iso:country":"US",
    "sg:address":"3133 Winslow Way NW",
    "sg:city":"Salem",
    "sg:classifiers":[
        {
            "category":"Real Estate",
            "subcategory":"Real Estate Agent",
            "type":"Services"
        }
    ],
    "sg:phone":"+1 503 364 9496",
    "sg:postcode":"97304",
    "sg:province":"OR",
    "wof:name":"Courtside Manor LLC",
    "wof:placetype":"venue"
},
  "geometry": {"coordinates":[-123.06895900000001,44.979663],"type":"Point"}
}