{
  "type": "Feature",
  "properties": {
    "addr:full":"2475 Ferry St SW Albany OR 97322",
    "addr:housenumber":"2475",
    "addr:postcode":"97322",
    "addr:street":"Ferry St Sw",
    "iso:country":"US",
    "sg:address":"2475 Ferry St SW",
    "sg:city":"Albany",
    "sg:classifiers":[
        {
            "category":"Wholesale",
            "subcategory":"Machinery & Supplies",
            "type":"Manufacturing & Wholesale Goods"
        }
    ],
    "sg:phone":"+1 541 928 5885",
    "sg:postcode":"97322",
    "sg:province":"OR",
    "sg:tags":[
        "equipment",
        "industrial",
        "l"
    ],
    "wof:name":"Praxair",
    "wof:placetype":"venue"
},
  "geometry": {"coordinates":[-123.10354,44.61704],"type":"Point"}
}