{
  "type": "Feature",
  "properties": {
    "iso:country":"US",
    "sg:address":"2242 N Williams Ave",
    "sg:city":"Portland",
    "sg:classifiers":[
        {
            "category":"Retail",
            "subcategory":"Repair Shop",
            "type":"Services"
        },
        {
            "category":"Wholesale",
            "subcategory":"Machinery & Supplies",
            "type":"Manufacturing & Wholesale Goods"
        }
    ],
    "sg:phone":"+1 503 288 4154",
    "sg:postcode":"97227",
    "sg:province":"OR",
    "sg:tags":[
        "printing",
        "equipment",
        "printers-equipment",
        "industrial"
    ],
    "wof:name":"Printers Parts Store Nw",
    "wof:placetype":"venue"
},
  "geometry": {"coordinates":[-122.666707,45.539253],"type":"Point"}
}