{
  "type": "Feature",
  "properties": {
    "iso:country":"US",
    "sg:address":"13894 SW Aerie Dr",
    "sg:city":"Portland",
    "sg:classifiers":[
        {
            "category":"Building & Trades",
            "subcategory":"Locksmith",
            "type":"Services"
        }
    ],
    "sg:phone":"+1 503 715 3802",
    "sg:postcode":"97223",
    "sg:province":"OR",
    "sg:tags":[
        "key"
    ],
    "wof:name":"Downtown Locksmith",
    "wof:placetype":"venue"
},
  "geometry": {"coordinates":[-122.805487,45.419516],"type":"Point"}
}