{
  "type": "Feature",
  "properties": {
    "iso:country":"US",
    "sg:address":"6577 NW Mcgregor Ter",
    "sg:city":"Portland",
    "sg:classifiers":[
        {
            "category":"Banks & Credit Unions",
            "subcategory":"Financial Services",
            "type":"Services"
        }
    ],
    "sg:phone":"+1 503 867 2067",
    "sg:postcode":"97229",
    "sg:province":"OR",
    "sg:tags":[
        "escrow"
    ],
    "wof:name":"Market Escrow",
    "wof:placetype":"venue"
},
  "geometry": {"coordinates":[-122.826561,45.56754],"type":"Point"}
}