{
  "type": "Feature",
  "properties": {
    "iso:country":"US",
    "sg:address":"6900 SW 144th Pl",
    "sg:city":"Beaverton",
    "sg:classifiers":[
        {
            "category":"Real Estate",
            "subcategory":"Real Estate Agent",
            "type":"Services"
        }
    ],
    "sg:phone":"+1 503 642 3606",
    "sg:postcode":"97008",
    "sg:province":"OR",
    "sg:tags":[
        "apartment",
        "management"
    ],
    "wof:name":"Jacalyn Johnson Home",
    "wof:placetype":"venue"
},
  "geometry": {"coordinates":[-122.825319,45.46973],"type":"Point"}
}