{
  "type": "Feature",
  "properties": {
    "iso:country":"US",
    "sg:address":"4160 SE International Way",
    "sg:city":"Portland",
    "sg:classifiers":[
        {
            "category":"Professional",
            "subcategory":"Detective & Security Services",
            "type":"Services"
        }
    ],
    "sg:phone":"+1 503 652 1634",
    "sg:postcode":"97222",
    "sg:province":"OR",
    "sg:tags":[
        "investigator"
    ],
    "wof:name":"Five Stars Intl LTD",
    "wof:placetype":"venue"
},
  "geometry": {"coordinates":[-122.618953,45.439298],"type":"Point"}
}