{
  "type": "Feature",
  "properties": {
    "iso:country":"US",
    "sg:address":"64182 Marks Rd",
    "sg:city":"La Grande",
    "sg:classifiers":[
        {
            "category":"Manufacturing",
            "subcategory":"Lumber",
            "type":"Manufacturing & Wholesale Goods"
        }
    ],
    "sg:phone":"+1 541 963 0425",
    "sg:postcode":"97850",
    "sg:province":"OR",
    "sg:tags":[
        "logging"
    ],
    "wof:name":"James Baremore Logging",
    "wof:placetype":"venue"
},
  "geometry": {"coordinates":[-118.058229,45.402526],"type":"Point"}
}