{
  "type": "Feature",
  "properties": {
    "addr:full":"5050 NE Hoyt St Ste 515 Portland OR 97213",
    "addr:housenumber":"5050",
    "addr:postcode":"97213",
    "addr:street":"Ne Hoyt St Ste 515",
    "iso:country":"US",
    "sg:address":"5050 NE Hoyt St Ste 515",
    "sg:city":"Portland",
    "sg:classifiers":[
        {
            "category":"Health Services",
            "subcategory":"Doctor",
            "type":"Services"
        },
        {
            "category":"Health Services",
            "subcategory":"Hospital",
            "type":"Services"
        }
    ],
    "sg:phone":"+1 503 230 0747",
    "sg:postcode":"97213",
    "sg:province":"OR",
    "sg:tags":[
        "physician",
        "family",
        "practice",
        "surgeons",
        "sleep",
        "treatment",
        "medicine",
        "surgeon",
        "disorders-information"
    ],
    "wof:name":"James T Nolan Md",
    "wof:placetype":"venue"
},
  "geometry": {"coordinates":[-122.61135,45.52721],"type":"Point"}
}