{
  "type": "Feature",
  "properties": {
    "addr:full":"686 E Broadway Eugene OR 97401",
    "addr:housenumber":"686",
    "addr:postcode":"97401",
    "addr:street":"E Broadway",
    "iso:country":"US",
    "sg:address":"686 E Broadway",
    "sg:city":"Eugene",
    "sg:classifiers":[
        {
            "category":"Restaurant",
            "type":"Food & Drink"
        }
    ],
    "sg:menulink":"http://www.allmenus.com/or/eugene-springfield/160877-carls-jr/menu/",
    "sg:phone":"+1 541 343 6135",
    "sg:postcode":"97401",
    "sg:province":"OR",
    "sg:tags":[
        "burger",
        "american"
    ],
    "wof:name":"Carl's Jr.",
    "wof:placetype":"venue"
},
  "geometry": {"coordinates":[-123.08230399999999,44.049993],"type":"Point"}
}