{
  "type": "Feature",
  "properties": {
    "addr:full":"5919 NW Skyline Blvd Portland OR 97229",
    "addr:housenumber":"5919",
    "addr:postcode":"97229",
    "addr:street":"Nw Skyline Blvd",
    "iso:country":"US",
    "sg:address":"5919 NW Skyline Blvd",
    "sg:city":"Portland",
    "sg:classifiers":[
        {
            "category":"Mining & Drilling",
            "type":"Manufacturing & Wholesale Goods"
        }
    ],
    "sg:phone":"+1 503 292 3458",
    "sg:postcode":"97229",
    "sg:province":"OR",
    "sg:tags":[
        "exploration"
    ],
    "wof:name":"Oregon Land Exploration",
    "wof:placetype":"venue"
},
  "geometry": {"coordinates":[-122.79054499999999,45.566998],"type":"Point"}
}