{
  "type": "Feature",
  "properties": {
    "iso:country":"US",
    "sg:address":"1303 SE Oak St",
    "sg:city":"Oregon City",
    "sg:classifiers":[
        {
            "category":"Building & Trades",
            "subcategory":"Landscaping Services",
            "type":"Services"
        }
    ],
    "sg:phone":"+1 503 631 3676",
    "sg:postcode":"97045",
    "sg:province":"OR",
    "wof:name":"Michael A Warford Irrigation &",
    "wof:placetype":"venue"
},
  "geometry": {"coordinates":[-122.601491,45.349307],"type":"Point"}
}