{
  "type": "Feature",
  "properties": {
    "iso:country":"US",
    "sg:address":"601 SE Sherk Pl",
    "sg:city":"Sherwood",
    "sg:classifiers":[
        {
            "category":"Professional",
            "type":"Services"
        }
    ],
    "sg:phone":"+1 503 625 9621",
    "sg:postcode":"97140",
    "sg:province":"OR",
    "wof:name":"Alpine Controls",
    "wof:placetype":"venue"
},
  "geometry": {"coordinates":[-122.83099300000001,45.351963],"type":"Point"}
}