{
  "type": "Feature",
  "properties": {
    "iso:country":"US",
    "sg:address":"4790 Drift Creek Rd SE",
    "sg:city":"Sublimity",
    "sg:classifiers":[
        {
            "category":"Shopping",
            "type":"Retail Goods"
        },
        {
            "category":"Manufacturing",
            "subcategory":"Tools & Machinery",
            "type":"Manufacturing & Wholesale Goods"
        }
    ],
    "sg:phone":"+1 503 769 6834",
    "sg:postcode":"97385",
    "sg:province":"OR",
    "sg:tags":[
        "trophy",
        "optical",
        "medal",
        "award",
        "mfg"
    ],
    "sg:website":"www.firerescuenorthwest.com",
    "wof:name":"Cruise Master Engraving",
    "wof:placetype":"venue"
},
  "geometry": {"coordinates":[-122.71595,44.884669],"type":"Point"}
}