{
  "type": "Feature",
  "properties": {
    "iso:country":"US",
    "sg:address":"300 Broadway St",
    "sg:city":"Seaside",
    "sg:classifiers":[
        {
            "category":"Shopping",
            "subcategory":"Gifts & Souvenirs",
            "type":"Retail Goods"
        }
    ],
    "sg:phone":"+1 503 738 8196",
    "sg:postcode":"97138",
    "sg:province":"OR",
    "sg:tags":[
        "shop"
    ],
    "wof:name":"Country Bungalow",
    "wof:placetype":"venue"
},
  "geometry": {"coordinates":[-123.92684199999999,45.993165],"type":"Point"}
}