{
  "type": "Feature",
  "properties": {
    "iso:country":"US",
    "sg:address":"2365 Green Meadows Way",
    "sg:city":"Ashland",
    "sg:classifiers":[
        {
            "category":"Professional",
            "subcategory":"Art Services",
            "type":"Services"
        }
    ],
    "sg:phone":"+1 541 482 4403",
    "sg:postcode":"97520",
    "sg:province":"OR",
    "sg:tags":[
        "graphic",
        "artist"
    ],
    "wof:name":"Ashland Graphics",
    "wof:placetype":"venue"
},
  "geometry": {"coordinates":[-122.672372,42.167816],"type":"Point"}
}