{
  "type": "Feature",
  "properties": {
    "addr:full":"887 Alberta Ave Nyssa OR 97913",
    "addr:housenumber":"887",
    "addr:postcode":"97913",
    "addr:street":"Alberta Ave",
    "iso:country":"US",
    "sg:address":"887 Alberta Ave",
    "sg:city":"Nyssa",
    "sg:classifiers":[
        {
            "category":"Building & Trades",
            "subcategory":"Construction",
            "type":"Services"
        }
    ],
    "sg:phone":"+1 541 372 5452",
    "sg:postcode":"97913",
    "sg:province":"OR",
    "sg:tags":[
        "residential",
        "remodel",
        "contractor"
    ],
    "wof:name":"Randy O Froerer",
    "wof:placetype":"venue"
},
  "geometry": {"coordinates":[-117.07960799999999,43.880607],"type":"Point"}
}