{
  "type": "Feature",
  "properties": {
    "iso:country":"US",
    "sg:address":"13303 S Macksburg Rd",
    "sg:city":"Canby",
    "sg:classifiers":[
        {
            "category":"Shopping",
            "subcategory":"Florist",
            "type":"Retail Goods"
        }
    ],
    "sg:phone":"+1 503 266 2883",
    "sg:postcode":"97013",
    "sg:province":"OR",
    "wof:name":"Garden Path Nursery",
    "wof:placetype":"venue"
},
  "geometry": {"coordinates":[-122.593613,45.201501],"type":"Point"}
}