{
  "type": "Feature",
  "properties": {
    "iso:country":"US",
    "sg:address":"2737 E 16th St",
    "sg:city":"The Dalles",
    "sg:classifiers":[
        {
            "category":"Building & Trades",
            "subcategory":"Landscaping Services",
            "type":"Services"
        }
    ],
    "sg:phone":"+1 541 298 1949",
    "sg:postcode":"97058",
    "sg:province":"OR",
    "wof:name":"K & J Landscaping",
    "wof:placetype":"venue"
},
  "geometry": {"coordinates":[-121.14222100000001,45.590527],"type":"Point"}
}