{
  "type": "Feature",
  "properties": {
    "iso:country":"US",
    "sg:address":"1013 B St",
    "sg:city":"Springfield",
    "sg:classifiers":[
        {
            "category":"Professional",
            "subcategory":"Business Services",
            "type":"Services"
        }
    ],
    "sg:phone":"+1 541 726 7764",
    "sg:postcode":"97477",
    "sg:province":"OR",
    "sg:tags":[
        "registered",
        "nurse"
    ],
    "wof:name":"Newell Lorinda",
    "wof:placetype":"venue"
},
  "geometry": {"coordinates":[-123.009072,44.04783],"type":"Point"}
}