{
  "type": "Feature",
  "properties": {
    "iso:country":"US",
    "sg:address":"1916 Vine Ave",
    "sg:city":"Klamath Falls",
    "sg:classifiers":[
        {
            "category":"Building & Trades",
            "subcategory":"Construction",
            "type":"Services"
        }
    ],
    "sg:phone":"+1 541 273 3459",
    "sg:postcode":"97601",
    "sg:province":"OR",
    "sg:tags":[
        "contractor"
    ],
    "wof:name":"Linkville Tile & Tops",
    "wof:placetype":"venue"
},
  "geometry": {"coordinates":[-121.76694500000001,42.221917],"type":"Point"}
}