{
  "type": "Feature",
  "properties": {
    "iso:country":"US",
    "sg:address":"9730 SW Hillman Ct",
    "sg:city":"Wilsonville",
    "sg:classifiers":[
        {
            "category":"Wholesale",
            "subcategory":"Machinery & Supplies",
            "type":"Manufacturing & Wholesale Goods"
        }
    ],
    "sg:phone":"+1 503 682 4933",
    "sg:postcode":"97070",
    "sg:province":"OR",
    "sg:tags":[
        "chains"
    ],
    "wof:name":"HKK Chain Co",
    "wof:placetype":"venue"
},
  "geometry": {"coordinates":[-122.775085,45.321717],"type":"Point"}
}