{
  "type": "Feature",
  "properties": {
    "addr:full":"180 Moore St Harrisburg OR 97446",
    "addr:housenumber":"180",
    "addr:postcode":"97446",
    "addr:street":"Moore St",
    "iso:country":"US",
    "sg:address":"180 Moore St",
    "sg:city":"Harrisburg",
    "sg:classifiers":[
        {
            "category":"Wholesale",
            "subcategory":"Groceries",
            "type":"Manufacturing & Wholesale Goods"
        }
    ],
    "sg:phone":"+1 541 995 6570",
    "sg:postcode":"97446",
    "sg:province":"OR",
    "sg:tags":[
        "food",
        "product"
    ],
    "wof:name":"Real Cool Coolers",
    "wof:placetype":"venue"
},
  "geometry": {"coordinates":[-123.173489,44.271474],"type":"Point"}
}