{
  "type": "Feature",
  "properties": {
    "iso:country":"US",
    "sg:address":"1194 Barnes Ave SE",
    "sg:city":"Salem",
    "sg:classifiers":[
        {
            "category":"Real Estate",
            "subcategory":"Real Estate Operator",
            "type":"Services"
        }
    ],
    "sg:phone":"+1 503 364 1433",
    "sg:postcode":"97306",
    "sg:province":"OR",
    "sg:tags":[
        "building",
        "apartment"
    ],
    "wof:name":"Copper Field Apartments",
    "wof:placetype":"venue"
},
  "geometry": {"coordinates":[-123.031792,44.881161],"type":"Point"}
}