{
  "type": "Feature",
  "properties": {
    "addr:full":"300 NW 10th Ave Portland OR 97209",
    "addr:housenumber":"300",
    "addr:postcode":"97209",
    "addr:street":"Nw 10Th Ave",
    "iso:country":"US",
    "sg:address":"300 NW 10th Ave",
    "sg:city":"Portland",
    "sg:classifiers":[
        {
            "category":"Bars & Pubs",
            "type":"Food & Drink"
        },
        {
            "category":"Food & Beverages",
            "subcategory":"Bakery",
            "type":"Retail Goods"
        },
        {
            "category":"Fast Food",
            "type":"Food & Drink"
        }
    ],
    "sg:phone":"+1 503 224 1680",
    "sg:postcode":"97209",
    "sg:province":"OR",
    "sg:tags":[
        "burger",
        "sandwich"
    ],
    "wof:name":"Life of Riley Tavern",
    "wof:placetype":"venue"
},
  "geometry": {"coordinates":[-122.681183,45.525128],"type":"Point"}
}