{
  "type": "Feature",
  "properties": {
    "iso:country":"US",
    "sg:address":"615 N 2nd St",
    "sg:city":"Jefferson",
    "sg:classifiers":[
        {
            "category":"Social Services",
            "subcategory":"Child Care",
            "type":"Services"
        }
    ],
    "sg:phone":"+1 541 327 7924",
    "sg:postcode":"97352",
    "sg:province":"OR",
    "sg:tags":[
        "nursery",
        "day"
    ],
    "wof:name":"Jefferson Center",
    "wof:placetype":"venue"
},
  "geometry": {"coordinates":[-123.010246,44.723961],"type":"Point"}
}