{
  "type": "Feature",
  "properties": {
    "iso:country":"US",
    "sg:address":"710 Main St",
    "sg:city":"Springfield",
    "sg:classifiers":[
        {
            "category":"Professional",
            "type":"Services"
        },
        {
            "category":"Restaurant",
            "type":"Food & Drink"
        }
    ],
    "sg:phone":"+1 541 726 0622",
    "sg:postcode":"97477",
    "sg:province":"OR",
    "sg:tags":[
        "caterer"
    ],
    "sg:website":"http://www.pumpcafe.com",
    "wof:name":"Pump Cafe",
    "wof:placetype":"venue"
},
  "geometry": {"coordinates":[-123.016715,44.04618],"type":"Point"}
}