{
  "type": "Feature",
  "properties": {
    "addr:full":"547 Hoover Park Dr Medford OR 97504",
    "addr:housenumber":"547",
    "addr:postcode":"97504",
    "addr:street":"Hoover Park Dr",
    "iso:country":"US",
    "sg:address":"547 Hoover Park Dr",
    "sg:city":"Medford",
    "sg:classifiers":[
        {
            "category":"Building & Trades",
            "subcategory":"Construction",
            "type":"Services"
        }
    ],
    "sg:phone":"+1 541 857 9691",
    "sg:postcode":"97504",
    "sg:province":"OR",
    "sg:tags":[
        "house"
    ],
    "wof:name":"Paradise Builders Inc",
    "wof:placetype":"venue"
},
  "geometry": {"coordinates":[-122.839951,42.319419],"type":"Point"}
}