{
  "type": "Feature",
  "properties": {
    "addr:full":"62975 Boyd Acres Rd Bend OR 97701",
    "addr:housenumber":"62975",
    "addr:postcode":"97701",
    "addr:street":"Boyd Acres Rd",
    "iso:country":"US",
    "sg:address":"62975 Boyd Acres Rd",
    "sg:city":"Bend",
    "sg:classifiers":[
        {
            "category":"Restaurant",
            "type":"Food & Drink"
        }
    ],
    "sg:phone":"+1 541 388 3359",
    "sg:postcode":"97701",
    "sg:province":"OR",
    "sg:tags":[
        "eating"
    ],
    "wof:name":"Treasure Valley Coffee",
    "wof:placetype":"venue"
},
  "geometry": {"coordinates":[-121.29566,44.087985],"type":"Point"}
}