{
  "type": "Feature",
  "properties": {
    "iso:country":"US",
    "sg:address":"4251 SE Alder St",
    "sg:city":"Portland",
    "sg:classifiers":[
        {
            "category":"Health Services",
            "subcategory":"Doctor",
            "type":"Services"
        }
    ],
    "sg:phone":"+1 503 817 0595",
    "sg:postcode":"97215",
    "sg:province":"OR",
    "sg:tags":[
        "physician",
        "surgeon"
    ],
    "wof:name":"Donel R Courtney MD",
    "wof:placetype":"venue"
},
  "geometry": {"coordinates":[-122.61841,45.518014],"type":"Point"}
}