{
  "type": "Feature",
  "properties": {
    "addr:full":"260 NE Tomahawk Island Dr Portland OR 97217",
    "addr:housenumber":"260",
    "addr:postcode":"97217",
    "addr:street":"Ne Tomahawk Island Dr",
    "iso:country":"US",
    "sg:address":"260 NE Tomahawk Island Dr",
    "sg:city":"Portland",
    "sg:classifiers":[
        {
            "category":"Real Estate",
            "subcategory":"Real Estate Services",
            "type":"Services"
        }
    ],
    "sg:phone":"+1 503 735 0121",
    "sg:postcode":"97217",
    "sg:province":"OR",
    "sg:tags":[
        "company",
        "title"
    ],
    "wof:name":"Marine Title Northwest",
    "wof:placetype":"venue"
},
  "geometry": {"coordinates":[-122.654034,45.604583],"type":"Point"}
}