{
  "type": "Feature",
  "properties": {
    "addr:full":"696 Country Club Rd Eugene OR 97401",
    "addr:housenumber":"696",
    "addr:postcode":"97401",
    "addr:street":"Country Club Rd",
    "iso:country":"US",
    "sg:address":"696 Country Club Rd",
    "sg:city":"Eugene",
    "sg:classifiers":[
        {
            "category":"Professional",
            "subcategory":"Lawyer & Legal Services",
            "type":"Services"
        }
    ],
    "sg:phone":"+1 541 345 3330",
    "sg:postcode":"97401",
    "sg:province":"OR",
    "wof:name":"Barkovic Daniel J",
    "wof:placetype":"venue"
},
  "geometry": {"coordinates":[-123.094585,44.064381],"type":"Point"}
}