{
  "type": "Feature",
  "properties": {
    "iso:country":"US",
    "sg:address":"42515 Mill Pond Rd",
    "sg:city":"Port Orford",
    "sg:classifiers":[
        {
            "category":"Building & Trades",
            "subcategory":"Construction",
            "type":"Services"
        }
    ],
    "sg:phone":"+1 541 332 6023",
    "sg:postcode":"97465",
    "sg:province":"OR",
    "sg:tags":[
        "water",
        "well",
        "drilling"
    ],
    "wof:name":"South Coast Drilling",
    "wof:placetype":"venue"
},
  "geometry": {"coordinates":[-124.495463,42.765696],"type":"Point"}
}