{
  "type": "Feature",
  "properties": {
    "iso:country":"US",
    "sg:address":"9000 NE 5th St",
    "sg:city":"Terrebonne",
    "sg:classifiers":[
        {
            "category":"Professional",
            "subcategory":"Business Services",
            "type":"Services"
        }
    ],
    "sg:phone":"+1 541 548 7058",
    "sg:postcode":"97760",
    "sg:province":"OR",
    "wof:name":"Scott Enterprises",
    "wof:placetype":"venue"
},
  "geometry": {"coordinates":[-121.163624,44.361148],"type":"Point"}
}