{
  "type": "Feature",
  "properties": {
    "iso:country":"US",
    "sg:address":"4681 Isabelle St",
    "sg:city":"Eugene",
    "sg:classifiers":[
        {
            "category":"Manufacturing",
            "subcategory":"Aerospace",
            "type":"Manufacturing & Wholesale Goods"
        }
    ],
    "sg:phone":"+1 541 344 2304",
    "sg:postcode":"97402",
    "sg:province":"OR",
    "sg:tags":[
        "aircraft",
        "transportation",
        "mfg"
    ],
    "wof:name":"Heli Tech",
    "wof:placetype":"venue"
},
  "geometry": {"coordinates":[-123.177433,44.051495],"type":"Point"}
}