{
  "type": "Feature",
  "properties": {
    "iso:country":"US",
    "sg:address":"6799 Griffin Creek Rd",
    "sg:city":"Medford",
    "sg:classifiers":[
        {
            "category":"Building & Trades",
            "subcategory":"Construction",
            "type":"Services"
        }
    ],
    "sg:phone":"+1 541 779 5406",
    "sg:postcode":"97501",
    "sg:province":"OR",
    "sg:tags":[
        "concrete",
        "contractor"
    ],
    "wof:name":"Alliance Concrete Enclosures",
    "wof:placetype":"venue"
},
  "geometry": {"coordinates":[-122.887843,42.249252],"type":"Point"}
}