{
  "type": "Feature",
  "properties": {
    "addr:full":"25755 NW Hwy 47 Buxton OR 97109",
    "addr:housenumber":"25755",
    "addr:postcode":"97109",
    "addr:street":"Nw Hwy 47",
    "iso:country":"US",
    "sg:address":"25755 NW Hwy 47",
    "sg:city":"Buxton",
    "sg:classifiers":[
        {
            "category":"Professional",
            "type":"Services"
        }
    ],
    "sg:phone":"+1 503 324 9813",
    "sg:postcode":"97109",
    "sg:province":"OR",
    "wof:name":"Tom Rinck",
    "wof:placetype":"venue"
},
  "geometry": {"coordinates":[-123.201983,45.707585],"type":"Point"}
}