{
  "type": "Feature",
  "properties": {
    "addr:full":"980 S Front St Central Point OR 97502",
    "addr:housenumber":"980",
    "addr:postcode":"97502",
    "addr:street":"S Front St",
    "iso:country":"US",
    "sg:address":"980 S Front St",
    "sg:city":"Central Point",
    "sg:classifiers":[
        {
            "category":"Recreation",
            "subcategory":"Amusement Park",
            "type":"Entertainment"
        }
    ],
    "sg:phone":"+1 541 665 0011",
    "sg:postcode":"97502",
    "sg:province":"OR",
    "wof:name":"Crater Music Company",
    "wof:placetype":"venue"
},
  "geometry": {"coordinates":[-122.90799699999999,42.3629],"type":"Point"}
}