{
  "type": "Feature",
  "properties": {
    "iso:country":"US",
    "sg:address":"17858 SW Upper Boones Ferry Rd",
    "sg:city":"Portland",
    "sg:phone":"+1 503 684 1590",
    "sg:postcode":"97224",
    "sg:province":"OR",
    "wof:name":"Alpha Card Systems",
    "wof:placetype":"venue"
},
  "geometry": {"coordinates":[-122.756028,45.390934],"type":"Point"}
}