{
  "type": "Feature",
  "properties": {
    "addr:full":"2465 NW Monroe Ave Corvallis OR 97330",
    "addr:housenumber":"2465",
    "addr:postcode":"97330",
    "addr:street":"Nw Monroe Ave",
    "iso:country":"US",
    "sg:address":"2465 NW Monroe Ave",
    "sg:city":"Corvallis",
    "sg:classifiers":[
        {
            "category":"Shopping",
            "subcategory":"Photographic Equipment",
            "type":"Retail Goods"
        }
    ],
    "sg:phone":"+1 541 752 5089",
    "sg:postcode":"97330",
    "sg:province":"OR",
    "sg:tags":[
        "supply"
    ],
    "wof:name":"Shutterbug",
    "wof:placetype":"venue"
},
  "geometry": {"coordinates":[-123.27826399999999,44.568672],"type":"Point"}
}