{
  "type": "Feature",
  "properties": {
    "addr:full":"2336 NW Quimby St Portland OR 97210",
    "addr:housenumber":"2336",
    "addr:postcode":"97210",
    "addr:street":"Nw Quimby St",
    "iso:country":"US",
    "sg:address":"2336 NW Quimby St",
    "sg:city":"Portland",
    "sg:classifiers":[
        {
            "category":"Building & Trades",
            "subcategory":"Construction",
            "type":"Services"
        }
    ],
    "sg:phone":"+1 503 228 5081",
    "sg:postcode":"97210",
    "sg:province":"OR",
    "sg:tags":[
        "apartment",
        "contractor"
    ],
    "wof:name":"Leaven's Investments",
    "wof:placetype":"venue"
},
  "geometry": {"coordinates":[-122.69949,45.533341],"type":"Point"}
}