{
  "type": "Feature",
  "properties": {
    "iso:country":"US",
    "sg:address":"30216 Twin Creek Rd",
    "sg:city":"Scappoose",
    "sg:classifiers":[
        {
            "category":"Building & Trades",
            "subcategory":"Construction",
            "type":"Services"
        }
    ],
    "sg:phone":"+1 503 543 4669",
    "sg:postcode":"97056",
    "sg:province":"OR",
    "sg:tags":[
        "fabricator",
        "metal"
    ],
    "wof:name":"Knights Fabrication",
    "wof:placetype":"venue"
},
  "geometry": {"coordinates":[-122.946264,45.822215],"type":"Point"}
}