{
  "type": "Feature",
  "properties": {
    "iso:country":"US",
    "sg:address":"90451 Boeing Dr",
    "sg:city":"Eugene",
    "sg:classifiers":[
        {
            "category":"Building & Trades",
            "subcategory":"Equipment Rental",
            "type":"Services"
        }
    ],
    "sg:phone":"+1 541 688 4590",
    "sg:postcode":"97402",
    "sg:province":"OR",
    "sg:tags":[
        "transportation"
    ],
    "wof:name":"Heli Conversions",
    "wof:placetype":"venue"
},
  "geometry": {"coordinates":[-123.212096,44.114997],"type":"Point"}
}