{
  "type": "Feature",
  "properties": {
    "addr:full":"4388 NW Chanticleer Dr Portland OR 97229",
    "addr:housenumber":"4388",
    "addr:postcode":"97229",
    "addr:street":"Nw Chanticleer Dr",
    "iso:country":"US",
    "sg:address":"4388 NW Chanticleer Dr",
    "sg:city":"Portland",
    "sg:classifiers":[
        {
            "category":"Professional",
            "subcategory":"Computer Services",
            "type":"Services"
        }
    ],
    "sg:phone":"+1 503 439 0190",
    "sg:postcode":"97229",
    "sg:province":"OR",
    "sg:tags":[
        "related"
    ],
    "wof:name":"Solutions On Site",
    "wof:placetype":"venue"
},
  "geometry": {"coordinates":[-122.835695,45.552167],"type":"Point"}
}