{
  "type": "Feature",
  "properties": {
    "addr:full":"7939 SE Foster Rd Portland OR 97206",
    "addr:housenumber":"7939",
    "addr:postcode":"97206",
    "addr:street":"Se Foster Rd",
    "iso:country":"US",
    "sg:address":"7939 SE Foster Rd",
    "sg:city":"Portland",
    "sg:classifiers":[
        {
            "category":"Personal",
            "subcategory":"Beauty Salon",
            "type":"Services"
        }
    ],
    "sg:phone":"+1 503 771 8665",
    "sg:postcode":"97206",
    "sg:province":"OR",
    "wof:name":"Unlimited Hair & Nails",
    "wof:placetype":"venue"
},
  "geometry": {"coordinates":[-122.581823,45.48403],"type":"Point"}
}