{
  "type": "Feature",
  "properties": {
    "iso:country":"US",
    "sg:address":"7461 SW Bridgeport Rd",
    "sg:city":"Portland",
    "sg:classifiers":[
        {
            "category":"Shopping",
            "subcategory":"Clothing, Apparel, & Fashions",
            "type":"Retail Goods"
        }
    ],
    "sg:phone":"+1 503 620 6165",
    "sg:postcode":"97224",
    "sg:province":"OR",
    "wof:name":"Via Lago Bridgeport Village",
    "wof:placetype":"venue"
},
  "geometry": {"coordinates":[-122.75521,45.393502],"type":"Point"}
}