{
  "type": "Feature",
  "properties": {
    "iso:country":"US",
    "sg:address":"13800 SE Webster Rd # 102",
    "sg:city":"Portland",
    "sg:classifiers":[
        {
            "category":"Professional",
            "subcategory":"Business Services",
            "type":"Services"
        }
    ],
    "sg:phone":"+1 503 654 1450",
    "sg:postcode":"97267",
    "sg:province":"OR",
    "sg:tags":[
        "drafting"
    ],
    "wof:name":"Mechanical Concepts Inc",
    "wof:placetype":"venue"
},
  "geometry": {"coordinates":[-122.59314000000001,45.423409],"type":"Point"}
}