{
  "type": "Feature",
  "properties": {
    "addr:full":"1040 NW 22nd Ave Ste 420 Portland OR 97210",
    "addr:housenumber":"1040",
    "addr:postcode":"97210",
    "addr:street":"Nw 22Nd Ave Ste 420",
    "iso:country":"US",
    "sg:address":"1040 NW 22nd Ave Ste 420",
    "sg:city":"Portland",
    "sg:classifiers":[
        {
            "category":"Health Services",
            "subcategory":"Doctor",
            "type":"Services"
        }
    ],
    "sg:phone":"+1 503 488 2424",
    "sg:postcode":"97210",
    "sg:province":"OR",
    "sg:website":"www.oregonclinic.com",
    "wof:name":"McAllister Leslie D MD",
    "wof:placetype":"venue"
},
  "geometry": {"coordinates":[-122.696387,45.530126],"type":"Point"}
}