{
  "type": "Feature",
  "properties": {
    "iso:country":"US",
    "sg:address":"13389 SW Ascension Dr",
    "sg:city":"Portland",
    "sg:classifiers":[
        {
            "category":"Banks & Credit Unions",
            "subcategory":"Investment Brokerage",
            "type":"Services"
        }
    ],
    "sg:phone":"+1 503 524 1759",
    "sg:postcode":"97223",
    "sg:province":"OR",
    "sg:tags":[
        "brokerage",
        "bond",
        "stock"
    ],
    "wof:name":"Paulson Investment Company",
    "wof:placetype":"venue"
},
  "geometry": {"coordinates":[-122.821761,45.42474],"type":"Point"}
}