{
  "type": "Feature",
  "properties": {
    "iso:country":"US",
    "sg:address":"28081 SW Morgan St",
    "sg:city":"Wilsonville",
    "sg:classifiers":[
        {
            "category":"Building & Trades",
            "subcategory":"Landscaping Services",
            "type":"Services"
        }
    ],
    "sg:phone":"+1 503 589 4023",
    "sg:postcode":"97070",
    "sg:province":"OR",
    "sg:tags":[
        "landscape"
    ],
    "wof:name":"Mc Kenzies Landscape Maint",
    "wof:placetype":"venue"
},
  "geometry": {"coordinates":[-122.745338,45.316958],"type":"Point"}
}