{
  "type": "Feature",
  "properties": {
    "iso:country":"US",
    "sg:address":"15227 Stubb Rd NE",
    "sg:city":"Gervais",
    "sg:classifiers":[
        {
            "category":"Professional",
            "type":"Services"
        }
    ],
    "sg:phone":"+1 503 981 5696",
    "sg:postcode":"97026",
    "sg:province":"OR",
    "wof:name":"John M Hobson",
    "wof:placetype":"venue"
},
  "geometry": {"coordinates":[-122.879323,45.136857],"type":"Point"}
}