{
  "type": "Feature",
  "properties": {
    "iso:country":"US",
    "sg:address":"361 N Folsom St",
    "sg:city":"Coquille",
    "sg:classifiers":[
        {
            "category":"Social Services",
            "type":"Services"
        }
    ],
    "sg:phone":"+1 541 396 5249",
    "sg:postcode":"97423",
    "sg:province":"OR",
    "wof:name":"Pharaohs Pump Foundation",
    "wof:placetype":"venue"
},
  "geometry": {"coordinates":[-124.182706,43.177191],"type":"Point"}
}