{
  "type": "Feature",
  "properties": {
    "iso:country":"US",
    "sg:address":"621 SW Alder Street Suite 621",
    "sg:city":"Portland",
    "sg:classifiers":[
        {
            "category":"Professional",
            "subcategory":"Lawyer & Legal Services",
            "type":"Services"
        }
    ],
    "sg:phone":"+1 503 721 0140",
    "sg:postcode":"97205",
    "sg:province":"OR",
    "wof:name":"Karpinski Alan W Atty",
    "wof:placetype":"venue"
},
  "geometry": {"coordinates":[-122.678459,45.519821],"type":"Point"}
}