{
  "type": "Feature",
  "properties": {
    "addr:full":"4260 Galewood St Lake Oswego OR 97035",
    "addr:housenumber":"4260",
    "addr:postcode":"97035",
    "addr:street":"Galewood St",
    "iso:country":"US",
    "sg:address":"4260 Galewood St",
    "sg:city":"Lake Oswego",
    "sg:classifiers":[
        {
            "category":"Real Estate",
            "subcategory":"Real Estate Agent",
            "type":"Services"
        }
    ],
    "sg:phone":"+1 503 675 8380",
    "sg:postcode":"97035",
    "sg:province":"OR",
    "sg:tags":[
        "investment"
    ],
    "sg:website":"www.capitalpacific.com",
    "wof:name":"Capital Pacific",
    "wof:placetype":"venue"
},
  "geometry": {"coordinates":[-122.72367300000001,45.416461],"type":"Point"}
}