{
  "type": "Feature",
  "properties": {
    "addr:full":"62606 Booth Ln La Grande OR 97850",
    "addr:housenumber":"62606",
    "addr:postcode":"97850",
    "addr:street":"Booth Ln",
    "iso:country":"US",
    "sg:address":"62606 Booth Ln",
    "sg:city":"La Grande",
    "sg:classifiers":[
        {
            "category":"Building & Trades",
            "subcategory":"Construction",
            "type":"Services"
        }
    ],
    "sg:phone":"+1 541 963 8222",
    "sg:postcode":"97850",
    "sg:province":"OR",
    "sg:tags":[
        "painter"
    ],
    "wof:name":"Robert Brooks Contractor",
    "wof:placetype":"venue"
},
  "geometry": {"coordinates":[-118.065662,45.358742],"type":"Point"}
}