{
  "type": "Feature",
  "properties": {
    "iso:country":"US",
    "sg:address":"18226 SE Tibbetts Ct",
    "sg:city":"Gresham",
    "sg:classifiers":[
        {
            "category":"Professional",
            "type":"Services"
        }
    ],
    "sg:phone":"+1 503 667 1255",
    "sg:postcode":"97030",
    "sg:province":"OR",
    "wof:name":"B&L Amusement",
    "wof:placetype":"venue"
},
  "geometry": {"coordinates":[-122.474054,45.500207],"type":"Point"}
}