{
  "type": "Feature",
  "properties": {
    "addr:full":"7360 SW Bonita Rd Portland OR 97224",
    "addr:housenumber":"7360",
    "addr:postcode":"97224",
    "addr:street":"Sw Bonita Rd",
    "iso:country":"US",
    "sg:address":"7360 SW Bonita Rd",
    "sg:city":"Portland",
    "sg:classifiers":[
        {
            "category":"Professional",
            "subcategory":"Management & Consulting",
            "type":"Services"
        }
    ],
    "sg:phone":"+1 503 236 6421",
    "sg:postcode":"97224",
    "sg:province":"OR",
    "sg:tags":[
        "business"
    ],
    "wof:name":"Four Paws Problem Solving",
    "wof:placetype":"venue"
},
  "geometry": {"coordinates":[-122.75266999999999,45.415109],"type":"Point"}
}