{
  "type": "Feature",
  "properties": {
    "iso:country":"US",
    "sg:address":"14140 SW Teal Blvd",
    "sg:city":"Beaverton",
    "sg:classifiers":[
        {
            "category":"Professional",
            "subcategory":"Computer Services",
            "type":"Services"
        }
    ],
    "sg:phone":"+1 503 332 1134",
    "sg:postcode":"97008",
    "sg:province":"OR",
    "sg:tags":[
        "datum"
    ],
    "wof:name":"Dhdesigns",
    "wof:placetype":"venue"
},
  "geometry": {"coordinates":[-122.822064,45.441348],"type":"Point"}
}