{
  "type": "Feature",
  "properties": {
    "iso:country":"US",
    "sg:address":"2535 SE Pine St",
    "sg:city":"Portland",
    "sg:classifiers":[
        {
            "category":"Shopping",
            "subcategory":"Clothing, Apparel, & Fashions",
            "type":"Retail Goods"
        }
    ],
    "sg:phone":"+1 503 267 3933",
    "sg:postcode":"97214",
    "sg:province":"OR",
    "wof:name":"Passion Parties By Ralyn",
    "wof:placetype":"venue"
},
  "geometry": {"coordinates":[-122.640624,45.520807],"type":"Point"}
}