{
  "type": "Feature",
  "properties": {
    "iso:country":"US",
    "sg:address":"7830 NE Halsey St",
    "sg:city":"Portland",
    "sg:classifiers":[
        {
            "category":"Building & Trades",
            "subcategory":"Locksmith",
            "type":"Services"
        }
    ],
    "sg:phone":"+1 503 914 1162",
    "sg:postcode":"97213",
    "sg:province":"OR",
    "sg:tags":[
        "key"
    ],
    "wof:name":"24 Hour 7 Day Emergency Locksmith",
    "wof:placetype":"venue"
},
  "geometry": {"coordinates":[-122.58262499999999,45.533456],"type":"Point"}
}