{
  "type": "Feature",
  "properties": {
    "iso:country":"US",
    "sg:address":"10782 Cone St NE",
    "sg:city":"Donald",
    "sg:classifiers":[
        {
            "category":"Building & Trades",
            "subcategory":"Construction",
            "type":"Services"
        }
    ],
    "sg:phone":"+1 503 678 6019",
    "sg:postcode":"97002",
    "sg:province":"OR",
    "sg:tags":[
        "general",
        "contractor"
    ],
    "wof:name":"Silicon Forest Industries",
    "wof:placetype":"venue"
},
  "geometry": {"coordinates":[-122.841096,45.221407],"type":"Point"}
}