{
  "type": "Feature",
  "properties": {
    "iso:country":"US",
    "sg:address":"12755 SW Beaverdam Rd",
    "sg:city":"Beaverton",
    "sg:classifiers":[
        {
            "category":"Retail",
            "subcategory":"Repair Shop",
            "type":"Services"
        }
    ],
    "sg:phone":"+1 503 526 0845",
    "sg:postcode":"97005",
    "sg:province":"OR",
    "sg:tags":[
        "picture",
        "framing"
    ],
    "wof:name":"Don Hartwig Custom Framing",
    "wof:placetype":"venue"
},
  "geometry": {"coordinates":[-122.807429,45.488651],"type":"Point"}
}