{
  "type": "Feature",
  "properties": {
    "iso:country":"US",
    "sg:address":"2129 NE 12th Ave",
    "sg:city":"Portland",
    "sg:classifiers":[
        {
            "category":"Retail",
            "subcategory":"Portrait Studio",
            "type":"Services"
        }
    ],
    "sg:phone":"+1 503 249 5826",
    "sg:postcode":"97212",
    "sg:province":"OR",
    "sg:tags":[
        "photo"
    ],
    "wof:name":"As It Was Photography",
    "wof:placetype":"venue"
},
  "geometry": {"coordinates":[-122.653578,45.538778],"type":"Point"}
}