{
  "type": "Feature",
  "properties": {
    "iso:country":"US",
    "sg:address":"523 NE 69th Ave",
    "sg:city":"Portland",
    "sg:classifiers":[
        {
            "category":"Building & Trades",
            "subcategory":"Locksmith",
            "type":"Services"
        }
    ],
    "sg:phone":"+1 503 821 0951",
    "sg:postcode":"97213",
    "sg:province":"OR",
    "sg:tags":[
        "key"
    ],
    "wof:name":"Any Time 24 Locksmith",
    "wof:placetype":"venue"
},
  "geometry": {"coordinates":[-122.592597,45.526569],"type":"Point"}
}