{
  "type": "Feature",
  "properties": {
    "iso:country":"US",
    "sg:address":"35805 N Morning Star Rd",
    "sg:city":"Pleasant Hill",
    "sg:classifiers":[
        {
            "category":"Building & Trades",
            "subcategory":"Construction",
            "type":"Services"
        }
    ],
    "sg:phone":"+1 541 747 3117",
    "sg:postcode":"97455",
    "sg:province":"OR",
    "sg:tags":[
        "builder",
        "operative"
    ],
    "wof:name":"F3b Construction LLC",
    "wof:placetype":"venue"
},
  "geometry": {"coordinates":[-122.934899,43.951025],"type":"Point"}
}