{
  "type": "Feature",
  "properties": {
    "iso:country":"US",
    "sg:address":"37949 Upper Camp Creek Rd",
    "sg:city":"Springfield",
    "sg:classifiers":[
        {
            "category":"Farming",
            "subcategory":"Livestock Farm",
            "type":"Manufacturing & Wholesale Goods"
        }
    ],
    "sg:phone":"+1 541 746 1048",
    "sg:postcode":"97478",
    "sg:province":"OR",
    "sg:tags":[
        "beef",
        "feedlot",
        "cattle"
    ],
    "wof:name":"Fisher Land & Cattle Company",
    "wof:placetype":"venue"
},
  "geometry": {"coordinates":[-122.866686,44.08647],"type":"Point"}
}