{
  "type": "Feature",
  "properties": {
    "addr:full":"840 Explorer Ave Molalla OR 97038",
    "addr:housenumber":"840",
    "addr:postcode":"97038",
    "addr:street":"Explorer Ave",
    "iso:country":"US",
    "sg:address":"840 Explorer Ave",
    "sg:city":"Molalla",
    "sg:classifiers":[
        {
            "category":"Building & Trades",
            "subcategory":"Equipment Rental",
            "type":"Services"
        }
    ],
    "sg:phone":"+1 503 829 7448",
    "sg:postcode":"97038",
    "sg:province":"OR",
    "wof:name":"Clinkscales Portable Toilets",
    "wof:placetype":"venue"
},
  "geometry": {"coordinates":[-122.57946200000001,45.157863],"type":"Point"}
}