{
  "type": "Feature",
  "properties": {
    "iso:country":"US",
    "sg:address":"4320 SW Ben Hogan Dr",
    "sg:city":"Redmond",
    "sg:classifiers":[
        {
            "category":"Professional",
            "type":"Services"
        }
    ],
    "sg:phone":"+1 541 548 4138",
    "sg:postcode":"97756",
    "sg:province":"OR",
    "wof:name":"Pbb Family",
    "wof:placetype":"venue"
},
  "geometry": {"coordinates":[-121.199473,44.240528],"type":"Point"}
}