{
  "type": "Feature",
  "properties": {
    "iso:country":"US",
    "sg:address":"1120 SW 5th Ave",
    "sg:city":"Portland",
    "sg:classifiers":[
        {
            "category":"Government",
            "subcategory":"Office",
            "type":"Public Place"
        }
    ],
    "sg:phone":"+1 503 246 6699",
    "sg:postcode":"97204",
    "sg:province":"OR",
    "sg:tags":[
        "village"
    ],
    "wof:name":"Portland Water Bureau",
    "wof:placetype":"venue"
},
  "geometry": {"coordinates":[-122.679267,45.515576],"type":"Point"}
}