{
  "type": "Feature",
  "properties": {
    "iso:country":"US",
    "sg:address":"16601 S Stone Hill Dr",
    "sg:city":"Molalla",
    "sg:classifiers":[
        {
            "category":"Wholesale",
            "subcategory":"Machinery & Supplies",
            "type":"Manufacturing & Wholesale Goods"
        },
        {
            "category":"Building & Trades",
            "subcategory":"Construction",
            "type":"Services"
        }
    ],
    "sg:phone":"+1 503 829 9432",
    "sg:postcode":"97038",
    "sg:province":"OR",
    "sg:tags":[
        "system",
        "specialty",
        "heating",
        "pump",
        "contractor",
        "air conditioning"
    ],
    "wof:name":"D&M Pump & Heating Inc",
    "wof:placetype":"venue"
},
  "geometry": {"coordinates":[-122.51970900000001,45.159822],"type":"Point"}
}