{
  "type": "Feature",
  "properties": {
    "addr:full":"7080 SW Fir Loop Ste Lo0p Portland OR 97223",
    "addr:housenumber":"7080",
    "addr:postcode":"97223",
    "addr:street":"Sw Fir Loop Ste Lo0P",
    "iso:country":"US",
    "sg:address":"7080 SW Fir Loop Ste Lo0p",
    "sg:city":"Portland",
    "sg:classifiers":[
        {
            "category":"Professional",
            "subcategory":"Engineering",
            "type":"Services"
        },
        {
            "category":"Real Estate",
            "subcategory":"Architect",
            "type":"Services"
        }
    ],
    "sg:phone":"+1 503 684 9097",
    "sg:postcode":"97223",
    "sg:province":"OR",
    "sg:tags":[
        "architects'",
        "consulting",
        "specification",
        "builders'",
        "construction",
        "architectural",
        "engineer"
    ],
    "sg:website":"http://www.rizzo.com",
    "wof:name":"Tetra Tech",
    "wof:placetype":"venue"
},
  "geometry": {"coordinates":[-122.749894,45.423036],"type":"Point"}
}