{
  "type": "Feature",
  "properties": {
    "addr:full":"341 Tan Oak Dr Medford OR 97504",
    "addr:housenumber":"341",
    "addr:postcode":"97504",
    "addr:street":"Tan Oak Dr",
    "iso:country":"US",
    "sg:address":"341 Tan Oak Dr",
    "sg:city":"Medford",
    "sg:classifiers":[
        {
            "category":"Organizations",
            "subcategory":"Religious Organization",
            "type":"Services"
        }
    ],
    "sg:phone":"+1 541 776 2882",
    "sg:postcode":"97504",
    "sg:province":"OR",
    "wof:name":"A Wing & A Prayer",
    "wof:placetype":"venue"
},
  "geometry": {"coordinates":[-122.83560300000001,42.321929],"type":"Point"}
}