{
  "type": "Feature",
  "properties": {
    "addr:full":"520 SW Yamhill St Portland OR 97204",
    "addr:housenumber":"520",
    "addr:postcode":"97204",
    "addr:street":"Sw Yamhill St",
    "iso:country":"US",
    "sg:address":"520 SW Yamhill St",
    "sg:city":"Portland",
    "sg:classifiers":[
        {
            "category":"Manufacturing",
            "subcategory":"Buildings",
            "type":"Manufacturing & Wholesale Goods"
        },
        {
            "category":"Building & Trades",
            "subcategory":"Construction",
            "type":"Services"
        }
    ],
    "sg:phone":"+1 503 226 3643",
    "sg:postcode":"97204",
    "sg:province":"OR",
    "sg:tags":[
        "home",
        "builder",
        "contractor"
    ],
    "wof:name":"Horlyk Road Construction Inc",
    "wof:placetype":"venue"
},
  "geometry": {"coordinates":[-122.678173,45.51819],"type":"Point"}
}