{
  "type": "Feature",
  "properties": {
    "iso:country":"US",
    "sg:address":"56856 Enterprise Dr",
    "sg:city":"Bend",
    "sg:classifiers":[
        {
            "category":"Professional",
            "type":"Services"
        }
    ],
    "sg:phone":"+1 541 598 7267",
    "sg:postcode":"97707",
    "sg:province":"OR",
    "wof:name":"Sandra & David Brownlee",
    "wof:placetype":"venue"
},
  "geometry": {"coordinates":[-121.431608,43.866483],"type":"Point"}
}