{
  "type": "Feature",
  "properties": {
    "addr:full":"1668 Ashland St Ashland OR 97520",
    "addr:housenumber":"1668",
    "addr:postcode":"97520",
    "addr:street":"Ashland St",
    "iso:country":"US",
    "sg:address":"1668 Ashland St",
    "sg:city":"Ashland",
    "sg:classifiers":[
        {
            "category":"Shopping",
            "subcategory":"Department Store",
            "type":"Retail Goods"
        },
        {
            "category":"Shopping",
            "type":"Retail Goods"
        },
        {
            "category":"Shopping",
            "subcategory":"Discount & Variety Stores",
            "type":"Retail Goods"
        }
    ],
    "sg:phone":"+1 541 482 1477",
    "sg:postcode":"97520",
    "sg:province":"OR",
    "sg:tags":[
        "merchandise"
    ],
    "sg:website":"http://www.dollartree.com/",
    "wof:name":"Dollar Tree",
    "wof:placetype":"venue"
},
  "geometry": {"coordinates":[-122.686114,42.185425],"type":"Point"}
}