{
  "type": "Feature",
  "properties": {
    "addr:full":"93535 Prairie Rd Junction City OR 97448",
    "addr:housenumber":"93535",
    "addr:postcode":"97448",
    "addr:street":"Prairie Rd",
    "iso:country":"US",
    "sg:address":"93535 Prairie Rd",
    "sg:city":"Junction City",
    "sg:classifiers":[
        {
            "category":"Shopping",
            "subcategory":"Gifts & Souvenirs",
            "type":"Retail Goods"
        }
    ],
    "sg:phone":"+1 541 998 2494",
    "sg:postcode":"97448",
    "sg:province":"OR",
    "wof:name":"Kenneth R Evenson",
    "wof:placetype":"venue"
},
  "geometry": {"coordinates":[-123.20540200000001,44.201494],"type":"Point"}
}