{
  "type": "Feature",
  "properties": {
    "addr:full":"910 Glendale Ave Ashland OR 97520",
    "addr:housenumber":"910",
    "addr:postcode":"97520",
    "addr:street":"Glendale Ave",
    "iso:country":"US",
    "sg:address":"910 Glendale Ave",
    "sg:city":"Ashland",
    "sg:classifiers":[
        {
            "category":"Professional",
            "type":"Services"
        }
    ],
    "sg:phone":"+1 541 482 5413",
    "sg:postcode":"97520",
    "sg:province":"OR",
    "wof:name":"Alcyone Light Centre Inc",
    "wof:placetype":"venue"
},
  "geometry": {"coordinates":[-122.678078,42.179604],"type":"Point"}
}