{
  "type": "Feature",
  "properties": {
    "iso:country":"US",
    "sg:address":"10095 SW Hedges Ct",
    "sg:city":"Tualatin",
    "sg:classifiers":[
        {
            "category":"Wholesale",
            "subcategory":"Home Furnishings",
            "type":"Manufacturing & Wholesale Goods"
        }
    ],
    "sg:phone":"+1 503 692 4543",
    "sg:postcode":"97062",
    "sg:province":"OR",
    "wof:name":"Laurie Young Sales Inc",
    "wof:placetype":"venue"
},
  "geometry": {"coordinates":[-122.78151800000001,45.361335],"type":"Point"}
}