{
  "type": "Feature",
  "properties": {
    "iso:country":"US",
    "sg:address":"11515 SW Durham Rd",
    "sg:city":"Tigard",
    "sg:classifiers":[
        {
            "category":"Professional",
            "subcategory":"Engineering",
            "type":"Services"
        }
    ],
    "sg:phone":"+1 503 670 0499",
    "sg:postcode":"97224",
    "sg:province":"OR",
    "sg:tags":[
        "engineer"
    ],
    "wof:name":"HBH Consulting Engineers",
    "wof:placetype":"venue"
},
  "geometry": {"coordinates":[-122.796689,45.404507],"type":"Point"}
}