{
  "type": "Feature",
  "properties": {
    "iso:country":"US",
    "sg:address":"1880 SW Merlo Dr",
    "sg:city":"Beaverton",
    "sg:classifiers":[
        {
            "category":"Manufacturing",
            "subcategory":"Metals",
            "type":"Manufacturing & Wholesale Goods"
        }
    ],
    "sg:phone":"+1 503 649 9500",
    "sg:postcode":"97006",
    "sg:province":"OR",
    "sg:tags":[
        "fabricator",
        "sheet"
    ],
    "sg:website":"www.triaxmetal.com",
    "wof:name":"Triax Metal Products Inc",
    "wof:placetype":"venue"
},
  "geometry": {"coordinates":[-122.847218,45.505279],"type":"Point"}
}