{
  "type": "Feature",
  "properties": {
    "iso:country":"US",
    "sg:address":"10820 SE Division St",
    "sg:city":"Portland",
    "sg:classifiers":[
        {
            "category":"Autos & Motor Vehicles",
            "subcategory":"Automobile Sales",
            "type":"Retail Goods"
        }
    ],
    "sg:phone":"+1 503 256 6886",
    "sg:postcode":"97266",
    "sg:province":"OR",
    "sg:tags":[
        "car",
        "used"
    ],
    "wof:name":"My Auto",
    "wof:placetype":"venue"
},
  "geometry": {"coordinates":[-122.55213999999999,45.504224],"type":"Point"}
}