{
  "type": "Feature",
  "properties": {
    "iso:country":"US",
    "sg:address":"2004 4th St",
    "sg:city":"La Grande",
    "sg:classifiers":[
        {
            "category":"Food & Beverages",
            "subcategory":"Groceries & Convenience Stores",
            "type":"Retail Goods"
        }
    ],
    "sg:phone":"+1 541 963 4637",
    "sg:postcode":"97850",
    "sg:province":"OR",
    "sg:tags":[
        "grocer"
    ],
    "wof:name":"Safeway",
    "wof:placetype":"venue"
},
  "geometry": {"coordinates":[-118.09652,45.330799],"type":"Point"}
}