{
  "type": "Feature",
  "properties": {
    "addr:full":"713 SW 12th Ave Portland OR 97205",
    "addr:housenumber":"713",
    "addr:postcode":"97205",
    "addr:street":"Sw 12Th Ave",
    "iso:country":"US",
    "sg:address":"713 SW 12th Ave",
    "sg:city":"Portland",
    "sg:classifiers":[
        {
            "category":"Personal",
            "subcategory":"Beauty Salon",
            "type":"Services"
        }
    ],
    "sg:phone":"+1 503 224 7655",
    "sg:postcode":"97205",
    "sg:province":"OR",
    "sg:tags":[
        "shop"
    ],
    "wof:name":"Fada Salon",
    "wof:placetype":"venue"
},
  "geometry": {"coordinates":[-122.684196,45.520468],"type":"Point"}
}