{
  "type": "Feature",
  "properties": {
    "iso:country":"US",
    "sg:address":"1050 SE Belle Aire Dr",
    "sg:city":"Grants Pass",
    "sg:classifiers":[
        {
            "category":"Building & Trades",
            "subcategory":"Pest Control",
            "type":"Services"
        }
    ],
    "sg:phone":"+1 541 476 4735",
    "sg:postcode":"97526",
    "sg:province":"OR",
    "wof:name":"D & T Inspections",
    "wof:placetype":"venue"
},
  "geometry": {"coordinates":[-123.31277900000001,42.426817],"type":"Point"}
}