{
  "type": "Feature",
  "properties": {
    "iso:country":"US",
    "sg:address":"89950 Eaton Ln",
    "sg:city":"Eugene",
    "sg:classifiers":[
        {
            "category":"Building & Trades",
            "subcategory":"Construction",
            "type":"Services"
        }
    ],
    "sg:phone":"+1 541 744 1338",
    "sg:postcode":"97402",
    "sg:province":"OR",
    "sg:tags":[
        "masonry",
        "contractor"
    ],
    "wof:name":"Creative Design Masonry",
    "wof:placetype":"venue"
},
  "geometry": {"coordinates":[-123.25988,44.102102],"type":"Point"}
}