{
  "type": "Feature",
  "properties": {
    "iso:country":"US",
    "sg:address":"1011 Harlow Rd",
    "sg:city":"Springfield",
    "sg:classifiers":[
        {
            "category":"Banks & Credit Unions",
            "subcategory":"Investment Brokerage",
            "type":"Services"
        }
    ],
    "sg:phone":"+1 541 747 8766",
    "sg:postcode":"97477",
    "sg:province":"OR",
    "sg:tags":[
        "security"
    ],
    "wof:name":"Edward Jones 08375",
    "wof:placetype":"venue"
},
  "geometry": {"coordinates":[-123.042165,44.070596],"type":"Point"}
}