{
  "type": "Feature",
  "properties": {
    "iso:country":"US",
    "sg:address":"141 Michaels Ranch Ln",
    "sg:city":"Days Creek",
    "sg:classifiers":[
        {
            "category":"Organizations",
            "subcategory":"Religious Organization",
            "type":"Services"
        }
    ],
    "sg:phone":"+1 541 825 3330",
    "sg:postcode":"97429",
    "sg:province":"OR",
    "sg:tags":[
        "church"
    ],
    "wof:name":"Cross Roads Christian Fellowsh",
    "wof:placetype":"venue"
},
  "geometry": {"coordinates":[-123.168114,42.972688],"type":"Point"}
}