{
  "type": "Feature",
  "properties": {
    "addr:full":"349 S Wall St Coos Bay OR 97420",
    "addr:housenumber":"349",
    "addr:postcode":"97420",
    "addr:street":"S Wall St",
    "iso:country":"US",
    "sg:address":"349 S Wall St",
    "sg:city":"Coos Bay",
    "sg:classifiers":[
        {
            "category":"Farming",
            "subcategory":"Fish & Marine Products",
            "type":"Manufacturing & Wholesale Goods"
        }
    ],
    "sg:phone":"+1 541 290 6687",
    "sg:postcode":"97420",
    "sg:province":"OR",
    "sg:tags":[
        "vessel",
        "commercial"
    ],
    "wof:name":"Ms Julie LLC",
    "wof:placetype":"venue"
},
  "geometry": {"coordinates":[-124.276995,43.3891],"type":"Point"}
}