{
  "type": "Feature",
  "properties": {
    "iso:country":"US",
    "sg:address":"6125 N Omaha Ave",
    "sg:city":"Portland",
    "sg:classifiers":[
        {
            "category":"Personal",
            "type":"Services"
        }
    ],
    "sg:phone":"+1 503 289 4519",
    "sg:postcode":"97217",
    "sg:province":"OR",
    "sg:tags":[
        "therapist",
        "massage"
    ],
    "wof:name":"A B Massage Therapy",
    "wof:placetype":"venue"
},
  "geometry": {"coordinates":[-122.690471,45.567371],"type":"Point"}
}