{
  "type": "Feature",
  "properties": {
    "iso:country":"US",
    "sg:address":"2912 SE 76th Ave",
    "sg:city":"Portland",
    "sg:classifiers":[
        {
            "category":"Building & Trades",
            "subcategory":"Construction",
            "type":"Services"
        }
    ],
    "sg:phone":"+1 503 788 3509",
    "sg:postcode":"97206",
    "sg:province":"OR",
    "sg:tags":[
        "house"
    ],
    "wof:name":"Wah Yue Construction",
    "wof:placetype":"venue"
},
  "geometry": {"coordinates":[-122.58477,45.500134],"type":"Point"}
}