{
  "type": "Feature",
  "properties": {
    "iso:country":"US",
    "sg:address":"1595 N Henry St",
    "sg:city":"Coquille",
    "sg:classifiers":[
        {
            "category":"Organizations",
            "subcategory":"Community Association",
            "type":"Services"
        }
    ],
    "sg:phone":"+1 541 396 4693",
    "sg:postcode":"97423",
    "sg:province":"OR",
    "wof:name":"Kiwanis International Inc",
    "wof:placetype":"venue"
},
  "geometry": {"coordinates":[-124.181118,43.189166],"type":"Point"}
}