{
  "type": "Feature",
  "properties": {
    "iso:country":"US",
    "sg:address":"625 Shelokum Dr",
    "sg:city":"Silverton",
    "sg:classifiers":[
        {
            "category":"Insurance",
            "subcategory":"Insurance Agent",
            "type":"Services"
        }
    ],
    "sg:phone":"+1 503 874 9524",
    "sg:postcode":"97381",
    "sg:province":"OR",
    "wof:name":"Western Planning & Pensions",
    "wof:placetype":"venue"
},
  "geometry": {"coordinates":[-122.77332,45.002854],"type":"Point"}
}