{
  "type": "Feature",
  "properties": {
    "iso:country":"US",
    "sg:address":"47815 W 2nd St",
    "sg:city":"Oakridge",
    "sg:classifiers":[
        {
            "category":"Organizations",
            "subcategory":"Religious Organization",
            "type":"Services"
        }
    ],
    "sg:phone":"+1 541 782 3403",
    "sg:postcode":"97463",
    "sg:province":"OR",
    "wof:name":"Living Hope Bible Fellowship",
    "wof:placetype":"venue"
},
  "geometry": {"coordinates":[-122.476276,43.74927],"type":"Point"}
}