{
  "type": "Feature",
  "properties": {
    "iso:country":"US",
    "sg:address":"7950 SE Milwaukie Ave",
    "sg:city":"Portland",
    "sg:classifiers":[
        {
            "category":"Wholesale",
            "subcategory":"Jewelry",
            "type":"Manufacturing & Wholesale Goods"
        }
    ],
    "sg:phone":"+1 503 235 2284",
    "sg:postcode":"97202",
    "sg:province":"OR",
    "sg:tags":[
        "stone"
    ],
    "wof:name":"Tambrook Bead & Trade",
    "wof:placetype":"venue"
},
  "geometry": {"coordinates":[-122.647204,45.465742],"type":"Point"}
}