{
  "type": "Feature",
  "properties": {
    "iso:country":"US",
    "sg:address":"41467 Stayton Scio Rd SE",
    "sg:city":"Stayton",
    "sg:classifiers":[
        {
            "category":"Building & Trades",
            "subcategory":"Landscaping Services",
            "type":"Services"
        }
    ],
    "sg:phone":"+1 503 769 9459",
    "sg:postcode":"97383",
    "sg:province":"OR",
    "wof:name":"Family Afrair Timber Tree Svc",
    "wof:placetype":"venue"
},
  "geometry": {"coordinates":[-122.794348,44.781079],"type":"Point"}
}