{
  "type": "Feature",
  "properties": {
    "addr:full":"28600 Ridgeway Rd Sweet Home OR 97386",
    "addr:housenumber":"28600",
    "addr:postcode":"97386",
    "addr:street":"Ridgeway Rd",
    "iso:country":"US",
    "sg:address":"28600 Ridgeway Rd",
    "sg:city":"Sweet Home",
    "sg:classifiers":[
        {
            "category":"Shopping",
            "subcategory":"Bicycles & Sporting Goods",
            "type":"Retail Goods"
        }
    ],
    "sg:phone":"+1 541 746 8439",
    "sg:postcode":"97386",
    "sg:province":"OR",
    "wof:name":"L&R Trade Co",
    "wof:placetype":"venue"
},
  "geometry": {"coordinates":[-122.730468,44.430261],"type":"Point"}
}