{
  "type": "Feature",
  "properties": {
    "iso:country":"US",
    "sg:address":"10175 SW Barbur Boulevard",
    "sg:city":"Portland",
    "sg:classifiers":[
        {
            "category":"Banks & Credit Unions",
            "subcategory":"Financial Services",
            "type":"Services"
        }
    ],
    "sg:phone":"+1 503 892 9740",
    "sg:postcode":"97219",
    "sg:province":"OR",
    "sg:tags":[
        "broker",
        "mortgage"
    ],
    "wof:name":"Interstate Mutual Mortgage & Loan",
    "wof:placetype":"venue"
},
  "geometry": {"coordinates":[-122.725679,45.451832],"type":"Point"}
}