{
  "type": "Feature",
  "properties": {
    "addr:full":"5511 N Interstate Avenue Portland OR 97217",
    "addr:housenumber":"5511",
    "addr:postcode":"97217",
    "addr:street":"N Interstate Avenue",
    "iso:country":"US",
    "sg:address":"5511 N Interstate Avenue",
    "sg:city":"Portland",
    "sg:classifiers":[
        {
            "category":"Autos & Motor Vehicles",
            "subcategory":"Motorcycle Sales",
            "type":"Retail Goods"
        }
    ],
    "sg:phone":"+1 503 289 1251",
    "sg:postcode":"97217",
    "sg:province":"OR",
    "sg:website":"www.baisley.com",
    "wof:name":"Baisley Hi Performance",
    "wof:placetype":"venue"
},
  "geometry": {"coordinates":[-122.682486,45.563133],"type":"Point"}
}