{
  "type": "Feature",
  "properties": {
    "addr:full":"6720 SW MacAdam Avenue Portland OR 97219",
    "addr:housenumber":"6720",
    "addr:postcode":"97219",
    "addr:street":"Sw Macadam Avenue",
    "iso:country":"US",
    "sg:address":"6720 SW MacAdam Avenue",
    "sg:city":"Portland",
    "sg:classifiers":[
        {
            "category":"Building & Trades",
            "subcategory":"Construction",
            "type":"Services"
        },
        {
            "category":"Real Estate",
            "subcategory":"Architect",
            "type":"Services"
        }
    ],
    "sg:phone":"+1 503 245 7100",
    "sg:postcode":"97219",
    "sg:province":"OR",
    "sg:tags":[
        "interior",
        "design"
    ],
    "wof:name":"Ankrom Moisan Associated Architects PC",
    "wof:placetype":"venue"
},
  "geometry": {"coordinates":[-122.671656,45.475671],"type":"Point"}
}