{
  "type": "Feature",
  "properties": {
    "iso:country":"US",
    "sg:address":"7954 NE Wygant St",
    "sg:city":"Portland",
    "sg:classifiers":[
        {
            "category":"Autos & Motor Vehicles",
            "subcategory":"Auto Supplies",
            "type":"Retail Goods"
        }
    ],
    "sg:phone":"+1 503 545 6199",
    "sg:postcode":"97218",
    "sg:province":"OR",
    "sg:tags":[
        "wheel"
    ],
    "wof:name":"Pc On Wheels",
    "wof:placetype":"venue"
},
  "geometry": {"coordinates":[-122.580512,45.558125],"type":"Point"}
}