{
  "type": "Feature",
  "properties": {
    "iso:country":"US",
    "sg:address":"2780 Bunker Hill Rd S",
    "sg:city":"Salem",
    "sg:classifiers":[
        {
            "category":"Farming",
            "subcategory":"Farm & Veterinary Services",
            "type":"Manufacturing & Wholesale Goods"
        }
    ],
    "sg:phone":"+1 503 363 8813",
    "sg:postcode":"97306",
    "sg:province":"OR",
    "sg:tags":[
        "management"
    ],
    "wof:name":"Chene Coline Vineyard",
    "wof:placetype":"venue"
},
  "geometry": {"coordinates":[-123.086331,44.828059],"type":"Point"}
}