{
  "type": "Feature",
  "properties": {
    "iso:country":"US",
    "sg:address":"20 N Bridgeton Rd",
    "sg:city":"Portland",
    "sg:classifiers":[
        {
            "category":"Building & Trades",
            "subcategory":"Locksmith",
            "type":"Services"
        }
    ],
    "sg:phone":"+1 503 914 4376",
    "sg:postcode":"97217",
    "sg:province":"OR",
    "sg:tags":[
        "key"
    ],
    "wof:name":"Portland Locksmith",
    "wof:placetype":"venue"
},
  "geometry": {"coordinates":[-122.666344,45.602421],"type":"Point"}
}