{
  "type": "Feature",
  "properties": {
    "addr:full":"2940 SE Glacier Ave Gresham OR 97080",
    "addr:housenumber":"2940",
    "addr:postcode":"97080",
    "addr:street":"Se Glacier Ave",
    "iso:country":"US",
    "sg:address":"2940 SE Glacier Ave",
    "sg:city":"Gresham",
    "sg:classifiers":[
        {
            "category":"Shopping",
            "type":"Retail Goods"
        }
    ],
    "sg:phone":"+1 503 319 3442",
    "sg:postcode":"97080",
    "sg:province":"OR",
    "sg:tags":[
        "merchandise"
    ],
    "wof:name":"Cloninger Stores",
    "wof:placetype":"venue"
},
  "geometry": {"coordinates":[-122.38025,45.476604],"type":"Point"}
}