{
  "type": "Feature",
  "properties": {
    "addr:full":"9243 NE Glisan Street Portland OR 97220",
    "addr:housenumber":"9243",
    "addr:postcode":"97220",
    "addr:street":"Ne Glisan Street",
    "iso:country":"US",
    "sg:address":"9243 NE Glisan Street",
    "sg:city":"Portland",
    "sg:classifiers":[
        {
            "category":"Health Services",
            "subcategory":"Dentist",
            "type":"Services"
        }
    ],
    "sg:phone":"+1 503 255 1650",
    "sg:postcode":"97220",
    "sg:province":"OR",
    "wof:name":"Wu Catherine C DMD",
    "wof:placetype":"venue"
},
  "geometry": {"coordinates":[-122.56813,45.526458],"type":"Point"}
}