{
  "type": "Feature",
  "properties": {
    "addr:full":"612 N 1st St Silverton OR 97381",
    "addr:housenumber":"612",
    "addr:postcode":"97381",
    "addr:street":"N 1St St",
    "iso:country":"US",
    "sg:address":"612 N 1st St",
    "sg:city":"Silverton",
    "sg:classifiers":[
        {
            "category":"Shopping",
            "subcategory":"Pharmacy",
            "type":"Retail Goods"
        },
        {
            "category":"Health Services",
            "subcategory":"Health Practitioner",
            "type":"Services"
        }
    ],
    "sg:phone":"+1 503 873 6705",
    "sg:postcode":"97381",
    "sg:province":"OR",
    "sg:tags":[
        "acupuncture"
    ],
    "wof:name":"Eng Acupuncture Center",
    "wof:placetype":"venue"
},
  "geometry": {"coordinates":[-122.78432100000001,45.009593],"type":"Point"}
}