{
  "type": "Feature",
  "properties": {
    "addr:full":"6420 SW MacAdam Ave Ste 216 Portland OR 97239",
    "addr:housenumber":"6420",
    "addr:postcode":"97239",
    "addr:street":"Sw Macadam Ave Ste 216",
    "iso:country":"US",
    "sg:address":"6420 SW MacAdam Ave Ste 216",
    "sg:city":"Portland",
    "sg:classifiers":[
        {
            "category":"Health Services",
            "subcategory":"Optometrist",
            "type":"Services"
        },
        {
            "category":"Shopping",
            "subcategory":"Optician",
            "type":"Retail Goods"
        }
    ],
    "sg:phone":"+1 503 244 9418",
    "sg:postcode":"97239",
    "sg:province":"OR",
    "sg:tags":[
        "ophthalmologist",
        "eyewear"
    ],
    "sg:website":"www.oregoneyes.net",
    "wof:name":"Oregon Eye Specialists PC",
    "wof:placetype":"venue"
},
  "geometry": {"coordinates":[-122.671689,45.477605],"type":"Point"}
}