{
  "type": "Feature",
  "properties": {
    "iso:country":"US",
    "sg:address":"1086 Washburn Ln",
    "sg:city":"Medford",
    "sg:classifiers":[
        {
            "category":"Home & Garden",
            "subcategory":"Building Materials",
            "type":"Retail Goods"
        }
    ],
    "sg:phone":"+1 541 779 0272",
    "sg:postcode":"97501",
    "sg:province":"OR",
    "sg:tags":[
        "jewelry"
    ],
    "wof:name":"Lightgarden Stained Glass",
    "wof:placetype":"venue"
},
  "geometry": {"coordinates":[-122.921165,42.313148],"type":"Point"}
}