{
  "type": "Feature",
  "properties": {
    "iso:country":"US",
    "sg:address":"2326 NW Amberbrook Dr",
    "sg:city":"Beaverton",
    "sg:phone":"+1 503 466 2966",
    "sg:postcode":"97006",
    "sg:province":"OR",
    "wof:name":"Couple Of Eyes Vision Care",
    "wof:placetype":"venue"
},
  "geometry": {"coordinates":[-122.884472,45.536544],"type":"Point"}
}