{
  "type": "Feature",
  "properties": {
    "addr:full":"10338 Stayton Rd SE Aumsville OR 97325",
    "addr:housenumber":"10338",
    "addr:postcode":"97325",
    "addr:street":"Stayton Rd Se",
    "iso:country":"US",
    "sg:address":"10338 Stayton Rd SE",
    "sg:city":"Aumsville",
    "sg:classifiers":[
        {
            "category":"Farming",
            "subcategory":"Farm",
            "type":"Manufacturing & Wholesale Goods"
        }
    ],
    "sg:phone":"+1 503 769 2849",
    "sg:postcode":"97325",
    "sg:province":"OR",
    "sg:tags":[
        "food",
        "covered",
        "crop"
    ],
    "wof:name":"Frank Fery",
    "wof:placetype":"venue"
},
  "geometry": {"coordinates":[-122.85063599999999,44.787436],"type":"Point"}
}