{
  "type": "Feature",
  "properties": {
    "iso:country":"US",
    "sg:address":"11700 SW Corby Dr",
    "sg:city":"Portland",
    "sg:classifiers":[
        {
            "category":"Health Services",
            "subcategory":"Health Practitioner",
            "type":"Services"
        }
    ],
    "sg:phone":"+1 503 646 5007",
    "sg:postcode":"97225",
    "sg:province":"OR",
    "sg:tags":[
        "acupuncture"
    ],
    "wof:name":"Lowrie Shelley Ba Lac",
    "wof:placetype":"venue"
},
  "geometry": {"coordinates":[-122.797997,45.516399],"type":"Point"}
}