{
  "type": "Feature",
  "properties": {
    "iso:country":"US",
    "sg:address":"4330 Owl Ct",
    "sg:city":"West Linn",
    "sg:classifiers":[
        {
            "category":"Shopping",
            "subcategory":"Florist",
            "type":"Retail Goods"
        }
    ],
    "sg:phone":"+1 503 657 4185",
    "sg:postcode":"97068",
    "sg:province":"OR",
    "wof:name":"K Banta Interior Arrangement A",
    "wof:placetype":"venue"
},
  "geometry": {"coordinates":[-122.63211200000001,45.370792],"type":"Point"}
}