{
  "type": "Feature",
  "properties": {
    "iso:country":"US",
    "sg:address":"4002 N Michigan Ave",
    "sg:city":"Portland",
    "sg:classifiers":[
        {
            "category":"Professional",
            "subcategory":"Art Services",
            "type":"Services"
        }
    ],
    "sg:phone":"+1 503 284 2388",
    "sg:postcode":"97227",
    "sg:province":"OR",
    "sg:tags":[
        "commercial",
        "design"
    ],
    "wof:name":"Function Digitl Dsgn",
    "wof:placetype":"venue"
},
  "geometry": {"coordinates":[-122.676518,45.55334],"type":"Point"}
}