{
  "type": "Feature",
  "properties": {
    "addr:full":"3104 NE 26th Ave Portland OR 97212",
    "addr:housenumber":"3104",
    "addr:postcode":"97212",
    "addr:street":"Ne 26Th Ave",
    "iso:country":"US",
    "sg:address":"3104 NE 26th Ave",
    "sg:city":"Portland",
    "sg:classifiers":[
        {
            "category":"Communications",
            "type":"Services"
        }
    ],
    "sg:phone":"+1 503 284 7102",
    "sg:postcode":"97212",
    "sg:province":"OR",
    "wof:name":"Express For Success",
    "wof:placetype":"venue"
},
  "geometry": {"coordinates":[-122.63906799999999,45.545212],"type":"Point"}
}