{
  "type": "Feature",
  "properties": {
    "iso:country":"US",
    "sg:address":"3104 NE 26th Ave",
    "sg:city":"Portland",
    "sg:classifiers":[
        {
            "category":"Communications",
            "type":"Services"
        }
    ],
    "sg:phone":"+1 503 284 7102",
    "sg:postcode":"97212",
    "sg:province":"OR",
    "wof:name":"Express For Success",
    "wof:placetype":"venue"
},
  "geometry": {"coordinates":[-122.63906799999999,45.545212],"type":"Point"}
}