{
  "type": "Feature",
  "properties": {
    "iso:country":"US",
    "sg:address":"2046 W Main St",
    "sg:city":"Medford",
    "sg:classifiers":[
        {
            "category":"Shopping",
            "subcategory":"Used Merchandise",
            "type":"Retail Goods"
        }
    ],
    "sg:phone":"+1 541 773 2476",
    "sg:postcode":"97501",
    "sg:province":"OR",
    "sg:tags":[
        "shop",
        "thrift"
    ],
    "wof:name":"American Imports",
    "wof:placetype":"venue"
},
  "geometry": {"coordinates":[-122.89364399999999,42.323668],"type":"Point"}
}