{
  "type": "Feature",
  "properties": {
    "iso:country":"US",
    "sg:address":"8828 SE Division St",
    "sg:city":"Portland",
    "sg:classifiers":[
        {
            "category":"Home & Garden",
            "subcategory":"Garden Supply",
            "type":"Retail Goods"
        }
    ],
    "sg:phone":"+1 503 771 7202",
    "sg:postcode":"97266",
    "sg:province":"OR",
    "sg:tags":[
        "mowers-sharpening",
        "repairing",
        "lawn",
        "mower"
    ],
    "sg:website":"http://www.alslawnmower.com",
    "wof:name":"Al's Lawn Mower Sales & Svc",
    "wof:placetype":"venue"
},
  "geometry": {"coordinates":[-122.572281,45.50452],"type":"Point"}
}