{
  "type": "Feature",
  "properties": {
    "iso:country":"US",
    "sg:address":"3255 Gateway St",
    "sg:city":"Springfield",
    "sg:classifiers":[
        {
            "category":"Real Estate",
            "subcategory":"Real Estate Operator",
            "type":"Services"
        }
    ],
    "sg:phone":"+1 541 747 6124",
    "sg:postcode":"97477",
    "sg:province":"OR",
    "sg:tags":[
        "building",
        "apartment"
    ],
    "wof:name":"Gateway Village Apartments",
    "wof:placetype":"venue"
},
  "geometry": {"coordinates":[-123.042072,44.076909],"type":"Point"}
}