{
  "type": "Feature",
  "properties": {
    "addr:full":"2722 Jacksonville Hwy Medford OR 97501",
    "addr:housenumber":"2722",
    "addr:postcode":"97501",
    "addr:street":"Jacksonville Hwy",
    "iso:country":"US",
    "sg:address":"2722 Jacksonville Hwy",
    "sg:city":"Medford",
    "sg:classifiers":[
        {
            "category":"Shopping",
            "subcategory":"Bicycles & Sporting Goods",
            "type":"Retail Goods"
        }
    ],
    "sg:phone":"+1 541 772 1896",
    "sg:postcode":"97501",
    "sg:province":"OR",
    "wof:name":"Dewclaw Archery Supplies",
    "wof:placetype":"venue"
},
  "geometry": {"coordinates":[-122.90633200000001,42.323785],"type":"Point"}
}