{
  "type": "Feature",
  "properties": {
    "addr:full":"680 Cottage St NE Salem OR 97301",
    "addr:housenumber":"680",
    "addr:postcode":"97301",
    "addr:street":"Cottage St Ne",
    "iso:country":"US",
    "sg:address":"680 Cottage St NE",
    "sg:city":"Salem",
    "sg:classifiers":[
        {
            "category":"Professional",
            "type":"Services"
        }
    ],
    "sg:phone":"+1 503 581 1732",
    "sg:postcode":"97301",
    "sg:province":"OR",
    "wof:name":"Ern Program",
    "wof:placetype":"venue"
},
  "geometry": {"coordinates":[-123.030393,44.945501],"type":"Point"}
}