{
  "type": "Feature",
  "properties": {
    "addr:full":"38959 Pioneer Blvd Sandy OR 97055",
    "addr:housenumber":"38959",
    "addr:postcode":"97055",
    "addr:street":"Pioneer Blvd",
    "iso:country":"US",
    "sg:address":"38959 Pioneer Blvd",
    "sg:city":"Sandy",
    "sg:classifiers":[
        {
            "category":"Real Estate",
            "subcategory":"Real Estate Agent",
            "type":"Services"
        }
    ],
    "sg:phone":"+1 503 668 5881",
    "sg:postcode":"97055",
    "sg:province":"OR",
    "sg:tags":[
        "management"
    ],
    "wof:name":"3PM Pacific Pioneer Property",
    "wof:placetype":"venue"
},
  "geometry": {"coordinates":[-122.26258900000001,45.396375],"type":"Point"}
}