{
  "type": "Feature",
  "properties": {
    "addr:full":"57023 N Bank Rd Blue River OR 97413",
    "addr:housenumber":"57023",
    "addr:postcode":"97413",
    "addr:street":"N Bank Rd",
    "iso:country":"US",
    "sg:address":"57023 N Bank Rd",
    "sg:city":"Blue River",
    "sg:classifiers":[
        {
            "category":"Professional",
            "subcategory":"Computer Services",
            "type":"Services"
        }
    ],
    "sg:phone":"+1 541 822 3260",
    "sg:postcode":"97413",
    "sg:province":"OR",
    "sg:tags":[
        "prepackaged",
        "software"
    ],
    "wof:name":"Appletree Software",
    "wof:placetype":"venue"
},
  "geometry": {"coordinates":[-122.154661,44.178812],"type":"Point"}
}