{
  "type": "Feature",
  "properties": {
    "iso:country":"US",
    "sg:address":"3414 NE 82nd Ave",
    "sg:city":"Portland",
    "sg:classifiers":[
        {
            "category":"Education",
            "subcategory":"School",
            "type":"Public Place"
        },
        {
            "category":"Sports & Exercise",
            "subcategory":"Playing Field",
            "type":"Entertainment"
        }
    ],
    "sg:phone":"+1 503 327 8095",
    "sg:postcode":"97220",
    "sg:province":"OR",
    "sg:tags":[
        "personal",
        "development"
    ],
    "wof:name":"Pussycats Modeling Agent",
    "wof:placetype":"venue"
},
  "geometry": {"coordinates":[-122.578751,45.54745],"type":"Point"}
}