{
  "type": "Feature",
  "properties": {
    "iso:country":"US",
    "sg:address":"24275 NW Hansen Rd",
    "sg:city":"North Plains",
    "sg:classifiers":[
        {
            "category":"Building & Trades",
            "subcategory":"Plumbing",
            "type":"Services"
        }
    ],
    "sg:phone":"+1 503 314 2535",
    "sg:postcode":"97133",
    "sg:province":"OR",
    "sg:tags":[
        "conditioning",
        "air",
        "system",
        "contractor"
    ],
    "wof:name":"Shp Mechanical",
    "wof:placetype":"venue"
},
  "geometry": {"coordinates":[-122.93947900000001,45.695838],"type":"Point"}
}