{
  "type": "Feature",
  "properties": {
    "iso:country":"US",
    "sg:address":"1555 Dewey Ave",
    "sg:city":"Baker City",
    "sg:classifiers":[
        {
            "category":"Home & Garden",
            "subcategory":"Building Materials",
            "type":"Retail Goods"
        }
    ],
    "sg:phone":"+1 541 523 5373",
    "sg:postcode":"97814",
    "sg:province":"OR",
    "sg:tags":[
        "glass",
        "window",
        "plate"
    ],
    "wof:name":"Ragsdale Mobile Glass",
    "wof:placetype":"venue"
},
  "geometry": {"coordinates":[-117.83056,44.773035],"type":"Point"}
}