{
  "type": "Feature",
  "properties": {
    "addr:full":"2503 Lassen Way Grants Pass OR 97526",
    "addr:housenumber":"2503",
    "addr:postcode":"97526",
    "addr:street":"Lassen Way",
    "iso:country":"US",
    "sg:address":"2503 Lassen Way",
    "sg:city":"Grants Pass",
    "sg:classifiers":[
        {
            "category":"Manufacturing",
            "subcategory":"Building Materials",
            "type":"Manufacturing & Wholesale Goods"
        }
    ],
    "sg:phone":"+1 541 660 1641",
    "sg:postcode":"97526",
    "sg:province":"OR",
    "sg:tags":[
        "mfg",
        "wood",
        "kitchen",
        "cabinet"
    ],
    "wof:name":"Jones Don Cabinets Mill Works",
    "wof:placetype":"venue"
},
  "geometry": {"coordinates":[-123.341049,42.470003],"type":"Point"}
}