{
  "type": "Feature",
  "properties": {
    "iso:country":"US",
    "sg:address":"37307 Tennessee School Dr",
    "sg:city":"Lebanon",
    "sg:classifiers":[
        {
            "category":"Building & Trades",
            "subcategory":"Construction",
            "type":"Services"
        }
    ],
    "sg:phone":"+1 541 451 1781",
    "sg:postcode":"97355",
    "sg:province":"OR",
    "sg:tags":[
        "hanging",
        "contractor"
    ],
    "wof:name":"Joe Moseley Painting Co",
    "wof:placetype":"venue"
},
  "geometry": {"coordinates":[-122.921369,44.587099],"type":"Point"}
}