{
  "type": "Feature",
  "properties": {
    "iso:country":"US",
    "sg:address":"17500 SE Main St",
    "sg:city":"Portland",
    "sg:classifiers":[
        {
            "category":"Building & Trades",
            "subcategory":"Locksmith",
            "type":"Services"
        }
    ],
    "sg:phone":"+1 503 290 0501",
    "sg:postcode":"97233",
    "sg:province":"OR",
    "sg:tags":[
        "key"
    ],
    "wof:name":"One Twenty Four Seven A Locksmith",
    "wof:placetype":"venue"
},
  "geometry": {"coordinates":[-122.48302200000001,45.513523],"type":"Point"}
}