{
  "type": "Feature",
  "properties": {
    "addr:full":"33750 SW Ladd Hill Rd Wilsonville OR 97070",
    "addr:housenumber":"33750",
    "addr:postcode":"97070",
    "addr:street":"Sw Ladd Hill Rd",
    "iso:country":"US",
    "sg:address":"33750 SW Ladd Hill Rd",
    "sg:city":"Wilsonville",
    "sg:classifiers":[
        {
            "category":"Banks & Credit Unions",
            "subcategory":"Bank",
            "type":"Services"
        }
    ],
    "sg:phone":"+1 503 925 0712",
    "sg:postcode":"97070",
    "sg:province":"OR",
    "sg:tags":[
        "loan"
    ],
    "wof:name":"Dinger & Co",
    "wof:placetype":"venue"
},
  "geometry": {"coordinates":[-122.85668,45.280638],"type":"Point"}
}