{
  "type": "Feature",
  "properties": {
    "iso:country":"US",
    "sg:address":"3133 Broadway St",
    "sg:city":"North Bend",
    "sg:classifiers":[
        {
            "category":"Home & Garden",
            "subcategory":"Building Materials",
            "type":"Retail Goods"
        }
    ],
    "sg:phone":"+1 541 756 2051",
    "sg:postcode":"97459",
    "sg:province":"OR",
    "sg:tags":[
        "equipment",
        "electric",
        "supply"
    ],
    "wof:name":"Perry's Electric & Plumbing",
    "wof:placetype":"venue"
},
  "geometry": {"coordinates":[-124.239194,43.393679],"type":"Point"}
}