{
  "type": "Feature",
  "properties": {
    "iso:country":"US",
    "sg:address":"1125 SE Madison St 103A",
    "sg:city":"Portland",
    "sg:classifiers":[
        {
            "category":"Organizations",
            "subcategory":"Labor Organization",
            "type":"Services"
        }
    ],
    "sg:phone":"+1 503 232 5633",
    "sg:postcode":"97214",
    "sg:province":"OR",
    "wof:name":"Western States Regional Joint Board United Pacific North West District",
    "wof:placetype":"venue"
},
  "geometry": {"coordinates":[-122.65445099999999,45.512948],"type":"Point"}
}