{
  "type": "Feature",
  "properties": {
    "addr:full":"401 Ironwood Ter Woodburn OR 97071",
    "addr:housenumber":"401",
    "addr:postcode":"97071",
    "addr:street":"Ironwood Ter",
    "iso:country":"US",
    "sg:address":"401 Ironwood Ter",
    "sg:city":"Woodburn",
    "sg:classifiers":[
        {
            "category":"Professional",
            "subcategory":"Employment Agencies",
            "type":"Services"
        }
    ],
    "sg:phone":"+1 503 981 4969",
    "sg:postcode":"97071",
    "sg:province":"OR",
    "sg:tags":[
        "high",
        "tech",
        "recruiting"
    ],
    "wof:name":"Camacho Group Inc",
    "wof:placetype":"venue"
},
  "geometry": {"coordinates":[-122.849735,45.156359],"type":"Point"}
}