{
  "type": "Feature",
  "properties": {
    "iso:country":"US",
    "sg:address":"15880 Quarry Rd",
    "sg:city":"Lake Oswego",
    "sg:classifiers":[
        {
            "category":"Health Services",
            "subcategory":"Clinic",
            "type":"Services"
        }
    ],
    "sg:phone":"+1 503 697 1800",
    "sg:postcode":"97035",
    "sg:province":"OR",
    "sg:tags":[
        "counseling",
        "mental"
    ],
    "wof:name":"McClure Douglas G Psy D",
    "wof:placetype":"venue"
},
  "geometry": {"coordinates":[-122.72199999999999,45.410999],"type":"Point"}
}