{
  "type": "Feature",
  "properties": {
    "iso:country":"US",
    "sg:address":"530 1st St Ste B1",
    "sg:city":"Lake Oswego",
    "sg:classifiers":[
        {
            "category":"Health Services",
            "subcategory":"Doctor",
            "type":"Services"
        }
    ],
    "sg:phone":"+1 503 594 1114",
    "sg:postcode":"97034",
    "sg:province":"OR",
    "sg:tags":[
        "cardiologist"
    ],
    "wof:name":"Heartspace Center For Healing",
    "wof:placetype":"venue"
},
  "geometry": {"coordinates":[-122.664061,45.421088],"type":"Point"}
}