{
  "type": "Feature",
  "properties": {
    "addr:full":"80561 Ross Rd Tygh Valley OR 97063",
    "addr:housenumber":"80561",
    "addr:postcode":"97063",
    "addr:street":"Ross Rd",
    "iso:country":"US",
    "sg:address":"80561 Ross Rd",
    "sg:city":"Tygh Valley",
    "sg:classifiers":[
        {
            "category":"Professional",
            "subcategory":"Business Services",
            "type":"Services"
        }
    ],
    "sg:phone":"+1 541 544 2211",
    "sg:postcode":"97063",
    "sg:province":"OR",
    "wof:name":"Happy Valley Enterprises Inc",
    "wof:placetype":"venue"
},
  "geometry": {"coordinates":[-121.24999200000001,45.237329],"type":"Point"}
}