{
  "type": "Feature",
  "properties": {
    "iso:country":"US",
    "sg:address":"8305 SE Powell Blvd",
    "sg:city":"Portland",
    "sg:classifiers":[
        {
            "category":"Restaurant",
            "type":"Food & Drink"
        }
    ],
    "sg:phone":"+1 503 771 6868",
    "sg:postcode":"97266",
    "sg:province":"OR",
    "sg:tags":[
        "chinese"
    ],
    "wof:name":"Kenny's Noodle House",
    "wof:placetype":"venue"
},
  "geometry": {"coordinates":[-122.577495,45.49778],"type":"Point"}
}