{
  "type": "Feature",
  "properties": {
    "addr:full":"15302 SE Kensington Dr Clackamas OR 97015",
    "addr:housenumber":"15302",
    "addr:postcode":"97015",
    "addr:street":"Se Kensington Dr",
    "iso:country":"US",
    "sg:address":"15302 SE Kensington Dr",
    "sg:city":"Clackamas",
    "sg:classifiers":[
        {
            "category":"Retail",
            "subcategory":"Auto Repair",
            "type":"Services"
        }
    ],
    "sg:phone":"+1 503 654 4766",
    "sg:postcode":"97015",
    "sg:province":"OR",
    "sg:tags":[
        "general"
    ],
    "wof:name":"Johns Certified Auto LLC",
    "wof:placetype":"venue"
},
  "geometry": {"coordinates":[-122.504356,45.419547],"type":"Point"}
}