{
  "type": "Feature",
  "properties": {
    "iso:country":"US",
    "sg:address":"739 NE 10th St",
    "sg:city":"Bend",
    "sg:classifiers":[
        {
            "category":"Retail",
            "subcategory":"Portrait Studio",
            "type":"Services"
        }
    ],
    "sg:phone":"+1 541 385 3185",
    "sg:postcode":"97701",
    "sg:province":"OR",
    "sg:tags":[
        "photo"
    ],
    "sg:website":"www.chandlerphoto.com",
    "wof:name":"Chandler Photography",
    "wof:placetype":"venue"
},
  "geometry": {"coordinates":[-121.291642,44.056568],"type":"Point"}
}