{
  "type": "Feature",
  "properties": {
    "iso:country":"US",
    "sg:address":"1810 N Columbia Blvd",
    "sg:city":"Portland",
    "sg:classifiers":[
        {
            "category":"Banks & Credit Unions",
            "subcategory":"Bank",
            "type":"Services"
        }
    ],
    "sg:phone":"+1 503 286 5626",
    "sg:postcode":"97217",
    "sg:province":"OR",
    "sg:tags":[
        "loan",
        "real estate"
    ],
    "wof:name":"Raymond Love",
    "wof:placetype":"venue"
},
  "geometry": {"coordinates":[-122.685337,45.585206],"type":"Point"}
}