{
  "type": "Feature",
  "properties": {
    "iso:country":"US",
    "sg:address":"30771 Hwy 97 N",
    "sg:city":"Chiloquin",
    "sg:classifiers":[
        {
            "category":"Restaurant",
            "type":"Food & Drink"
        }
    ],
    "sg:phone":"+1 541 783 2400",
    "sg:postcode":"97624",
    "sg:province":"OR",
    "sg:tags":[
        "eating"
    ],
    "wof:name":"Vallarta Grill",
    "wof:placetype":"venue"
},
  "geometry": {"coordinates":[-121.880567,42.505472],"type":"Point"}
}