{
  "type": "Feature",
  "properties": {
    "addr:full":"507 N Main St Phoenix OR 97535",
    "addr:housenumber":"507",
    "addr:postcode":"97535",
    "addr:street":"N Main St",
    "iso:country":"US",
    "sg:address":"507 N Main St",
    "sg:city":"Phoenix",
    "sg:classifiers":[
        {
            "category":"Real Estate",
            "subcategory":"Real Estate Agent",
            "type":"Services"
        }
    ],
    "sg:phone":"+1 541 535 3020",
    "sg:postcode":"97535",
    "sg:province":"OR",
    "wof:name":"Oregon Advantage Properties",
    "wof:placetype":"venue"
},
  "geometry": {"coordinates":[-122.818918,42.277188],"type":"Point"}
}