{
  "type": "Feature",
  "properties": {
    "addr:full":"10014 SW 28th Ave Portland OR 97219",
    "addr:housenumber":"10014",
    "addr:postcode":"97219",
    "addr:street":"Sw 28Th Ave",
    "iso:country":"US",
    "sg:address":"10014 SW 28th Ave",
    "sg:city":"Portland",
    "sg:classifiers":[
        {
            "category":"Building & Trades",
            "subcategory":"Construction",
            "type":"Services"
        }
    ],
    "sg:phone":"+1 503 253 5086",
    "sg:postcode":"97219",
    "sg:province":"OR",
    "sg:tags":[
        "house"
    ],
    "wof:name":"Dan Hicks Construction",
    "wof:placetype":"venue"
},
  "geometry": {"coordinates":[-122.705895,45.451991],"type":"Point"}
}