{
  "type": "Feature",
  "properties": {
    "iso:country":"US",
    "sg:address":"61434 Linton Loop",
    "sg:city":"Bend",
    "sg:classifiers":[
        {
            "category":"Real Estate",
            "subcategory":"Real Estate Services",
            "type":"Services"
        },
        {
            "category":"Real Estate",
            "subcategory":"Real Estate Agent",
            "type":"Services"
        }
    ],
    "sg:phone":"+1 541 318 1999",
    "sg:postcode":"97702",
    "sg:province":"OR",
    "sg:tags":[
        "buyer",
        "broker"
    ],
    "wof:name":"Real Time Research",
    "wof:placetype":"venue"
},
  "geometry": {"coordinates":[-121.34034800000001,44.031809],"type":"Point"}
}