{
  "type": "Feature",
  "properties": {
    "iso:country":"US",
    "sg:address":"4848 Hastings Dr",
    "sg:city":"Lake Oswego",
    "sg:classifiers":[
        {
            "category":"Professional",
            "subcategory":"Management & Consulting",
            "type":"Services"
        }
    ],
    "sg:phone":"+1 503 534 9461",
    "sg:postcode":"97035",
    "sg:province":"OR",
    "sg:tags":[
        "consultant",
        "business"
    ],
    "wof:name":"Walker Co",
    "wof:placetype":"venue"
},
  "geometry": {"coordinates":[-122.727087,45.422916],"type":"Point"}
}