{
  "type": "Feature",
  "properties": {
    "iso:country":"US",
    "sg:address":"19866 NW Dorchester Way",
    "sg:city":"Hillsboro",
    "sg:classifiers":[
        {
            "category":"Communications",
            "subcategory":"Film & Video Production",
            "type":"Services"
        }
    ],
    "sg:phone":"+1 503 626 2676",
    "sg:postcode":"97124",
    "sg:province":"OR",
    "sg:tags":[
        "audio"
    ],
    "wof:name":"Bullwynkle Video Productions",
    "wof:placetype":"venue"
},
  "geometry": {"coordinates":[-122.880724,45.536941],"type":"Point"}
}