{
  "type": "Feature",
  "properties": {
    "iso:country":"US",
    "sg:address":"1000 Main Ave",
    "sg:city":"Tillamook",
    "sg:classifiers":[
        {
            "category":"Restaurant",
            "type":"Food & Drink"
        }
    ],
    "sg:phone":"+1 503 842 4133",
    "sg:postcode":"97141",
    "sg:province":"OR",
    "wof:name":"Fern Restaurant & Lounge",
    "wof:placetype":"venue"
},
  "geometry": {"coordinates":[-123.84396099999999,45.451152],"type":"Point"}
}