{
  "type": "Feature",
  "properties": {
    "addr:full":"209 Marson Ct Molalla OR 97038",
    "addr:housenumber":"209",
    "addr:postcode":"97038",
    "addr:street":"Marson Ct",
    "iso:country":"US",
    "sg:address":"209 Marson Ct",
    "sg:city":"Molalla",
    "sg:classifiers":[
        {
            "category":"Shopping",
            "subcategory":"Computers & Home Electronics",
            "type":"Retail Goods"
        }
    ],
    "sg:phone":"+1 503 829 6660",
    "sg:postcode":"97038",
    "sg:province":"OR",
    "sg:tags":[
        "software"
    ],
    "wof:name":"Western Datapro Inc",
    "wof:placetype":"venue"
},
  "geometry": {"coordinates":[-122.576269,45.148547],"type":"Point"}
}