{
  "type": "Feature",
  "properties": {
    "iso:country":"US",
    "sg:address":"1252 NW 6th St",
    "sg:city":"Grants Pass",
    "sg:classifiers":[
        {
            "category":"Building & Trades",
            "subcategory":"Plumbing",
            "type":"Services"
        }
    ],
    "sg:phone":"+1 541 476 1867",
    "sg:postcode":"97526",
    "sg:province":"OR",
    "sg:tags":[
        "plumbing",
        "contractor"
    ],
    "wof:name":"Ripam Plumbing & Mechanical",
    "wof:placetype":"venue"
},
  "geometry": {"coordinates":[-123.32262,42.450621],"type":"Point"}
}