{
  "type": "Feature",
  "properties": {
    "addr:full":"2802 W 2nd St The Dalles OR 97058",
    "addr:housenumber":"2802",
    "addr:postcode":"97058",
    "addr:street":"W 2Nd St",
    "iso:country":"US",
    "sg:address":"2802 W 2nd St",
    "sg:city":"The Dalles",
    "sg:classifiers":[
        {
            "category":"Building & Trades",
            "subcategory":"Construction",
            "type":"Services"
        }
    ],
    "sg:phone":"+1 541 993 1117",
    "sg:postcode":"97058",
    "sg:province":"OR",
    "sg:tags":[
        "re",
        "coating",
        "roof"
    ],
    "wof:name":"Infinity Coatings Inc",
    "wof:placetype":"venue"
},
  "geometry": {"coordinates":[-121.209732,45.619532],"type":"Point"}
}