{
  "type": "Feature",
  "properties": {
    "iso:country":"US",
    "sg:address":"526 NW Marlborough Ave",
    "sg:city":"Portland",
    "sg:classifiers":[
        {
            "category":"Organizations",
            "subcategory":"Professional Association",
            "type":"Services"
        }
    ],
    "sg:phone":"+1 503 241 4259",
    "sg:postcode":"97210",
    "sg:province":"OR",
    "sg:tags":[
        "business"
    ],
    "wof:name":"Pacific Rim Trade Association",
    "wof:placetype":"venue"
},
  "geometry": {"coordinates":[-122.704159,45.527],"type":"Point"}
}