{
  "type": "Feature",
  "properties": {
    "addr:full":"8738 SE Yamhill St Portland OR 97216",
    "addr:housenumber":"8738",
    "addr:postcode":"97216",
    "addr:street":"Se Yamhill St",
    "iso:country":"US",
    "sg:address":"8738 SE Yamhill St",
    "sg:city":"Portland",
    "sg:classifiers":[
        {
            "category":"Building & Trades",
            "subcategory":"Landscaping Services",
            "type":"Services"
        }
    ],
    "sg:phone":"+1 503 771 7522",
    "sg:postcode":"97216",
    "sg:province":"OR",
    "wof:name":"Gardenscapes Inc",
    "wof:placetype":"venue"
},
  "geometry": {"coordinates":[-122.57400699999999,45.516067],"type":"Point"}
}