{
  "type": "Feature",
  "properties": {
    "iso:country":"US",
    "sg:address":"3000 Gateway Loop",
    "sg:city":"Springfield",
    "sg:classifiers":[
        {
            "category":"Shopping",
            "subcategory":"Music",
            "type":"Retail Goods"
        }
    ],
    "sg:phone":"+1 541 746 6373",
    "sg:postcode":"97477",
    "sg:province":"OR",
    "wof:name":"Record Town Inc",
    "wof:placetype":"venue"
},
  "geometry": {"coordinates":[-123.045456,44.076986],"type":"Point"}
}