{
  "type": "Feature",
  "properties": {
    "addr:full":"820 NE Cleveland Ave Gresham OR 97030",
    "addr:housenumber":"820",
    "addr:postcode":"97030",
    "addr:street":"Ne Cleveland Ave",
    "iso:country":"US",
    "sg:address":"820 NE Cleveland Ave",
    "sg:city":"Gresham",
    "sg:classifiers":[
        {
            "category":"Retail",
            "subcategory":"Auto Repair",
            "type":"Services"
        }
    ],
    "sg:phone":"+1 503 666 6172",
    "sg:postcode":"97030",
    "sg:province":"OR",
    "sg:tags":[
        "repairing",
        "automobile",
        "general"
    ],
    "wof:name":"Cleveland Auto Repair Inc",
    "wof:placetype":"venue"
},
  "geometry": {"coordinates":[-122.421002,45.504321],"type":"Point"}
}