{
  "type": "Feature",
  "properties": {
    "iso:country":"US",
    "sg:address":"1431 Aerial Way SE",
    "sg:city":"Salem",
    "sg:classifiers":[
        {
            "category":"Shopping",
            "subcategory":"Bicycles & Sporting Goods",
            "type":"Retail Goods"
        }
    ],
    "sg:phone":"+1 503 588 0557",
    "sg:postcode":"97302",
    "sg:province":"OR",
    "wof:name":"Db Enterprises",
    "wof:placetype":"venue"
},
  "geometry": {"coordinates":[-123.02439,44.903244],"type":"Point"}
}