{
  "type": "Feature",
  "properties": {
    "addr:full":"9010 NW Kearney St Portland OR 97229",
    "addr:housenumber":"9010",
    "addr:postcode":"97229",
    "addr:street":"Nw Kearney St",
    "iso:country":"US",
    "sg:address":"9010 NW Kearney St",
    "sg:city":"Portland",
    "sg:classifiers":[
        {
            "category":"Professional",
            "subcategory":"Management & Consulting",
            "type":"Services"
        }
    ],
    "sg:phone":"+1 503 297 3889",
    "sg:postcode":"97229",
    "sg:province":"OR",
    "sg:tags":[
        "business"
    ],
    "wof:name":"Tyler Consulting Group",
    "wof:placetype":"venue"
},
  "geometry": {"coordinates":[-122.769119,45.5295],"type":"Point"}
}