{
  "type": "Feature",
  "properties": {
    "iso:country":"US",
    "sg:address":"1220 SW Morrison St",
    "sg:city":"Portland",
    "sg:classifiers":[
        {
            "category":"Professional",
            "subcategory":"Management & Consulting",
            "type":"Services"
        }
    ],
    "sg:phone":"+1 503 248 9058",
    "sg:postcode":"97205",
    "sg:province":"OR",
    "sg:website":"www.bnresearch.com",
    "wof:name":"Bardsley & Neidhart Inc",
    "wof:placetype":"venue"
},
  "geometry": {"coordinates":[-122.685076,45.520707],"type":"Point"}
}