{
  "type": "Feature",
  "properties": {
    "iso:country":"US",
    "sg:address":"3316 N Saratoga St",
    "sg:city":"Portland",
    "sg:classifiers":[
        {
            "category":"Personal",
            "subcategory":"Tattoo Parlor",
            "type":"Services"
        }
    ],
    "sg:phone":"+1 503 319 1963",
    "sg:postcode":"97217",
    "sg:province":"OR",
    "sg:tags":[
        "tattooing"
    ],
    "wof:name":"Adorn Henna",
    "wof:placetype":"venue"
},
  "geometry": {"coordinates":[-122.700875,45.572283],"type":"Point"}
}