{
  "type": "Feature",
  "properties": {
    "addr:full":"12311 NE Brazee St Portland OR 97230",
    "addr:housenumber":"12311",
    "addr:postcode":"97230",
    "addr:street":"Ne Brazee St",
    "iso:country":"US",
    "sg:address":"12311 NE Brazee St",
    "sg:city":"Portland",
    "sg:classifiers":[
        {
            "category":"Manufacturing",
            "subcategory":"Printing",
            "type":"Manufacturing & Wholesale Goods"
        }
    ],
    "sg:phone":"+1 503 253 9633",
    "sg:postcode":"97230",
    "sg:province":"OR",
    "sg:tags":[
        "technical",
        "publisher",
        "assistance",
        "computer",
        "support"
    ],
    "sg:website":"http://www.teachinghome.com",
    "wof:name":"The Teaching Home",
    "wof:placetype":"venue"
},
  "geometry": {"coordinates":[-122.536537,45.539897],"type":"Point"}
}