{
  "type": "Feature",
  "properties": {
    "iso:country":"US",
    "sg:address":"3760 Market St NE",
    "sg:city":"Salem",
    "sg:classifiers":[
        {
            "category":"Banks & Credit Unions",
            "subcategory":"Bank",
            "type":"Services"
        }
    ],
    "sg:phone":"+1 503 316 9000",
    "sg:postcode":"97301",
    "sg:province":"OR",
    "sg:tags":[
        "loan",
        "mortgage",
        "real estate"
    ],
    "wof:name":"D & L Capitol Funding",
    "wof:placetype":"venue"
},
  "geometry": {"coordinates":[-122.985634,44.950225],"type":"Point"}
}