{
  "type": "Feature",
  "properties": {
    "addr:full":"7535 SW Barnes Road Portland OR 97225",
    "addr:housenumber":"7535",
    "addr:postcode":"97225",
    "addr:street":"Sw Barnes Road",
    "iso:country":"US",
    "sg:address":"7535 SW Barnes Road",
    "sg:city":"Portland",
    "sg:classifiers":[
        {
            "category":"Cinema",
            "subcategory":"Movie Rental",
            "type":"Entertainment"
        }
    ],
    "sg:phone":"+1 503 296 9900",
    "sg:postcode":"97225",
    "sg:province":"OR",
    "sg:tags":[
        "game",
        "video"
    ],
    "sg:website":"www.blockbuster.com",
    "wof:name":"Blockbuster Video",
    "wof:placetype":"venue"
},
  "geometry": {"coordinates":[-122.774027,45.4997],"type":"Point"}
}