{
  "type": "Feature",
  "properties": {
    "addr:full":"710 8th St Hood River OR 97031",
    "addr:housenumber":"710",
    "addr:postcode":"97031",
    "addr:street":"8Th St",
    "iso:country":"US",
    "sg:address":"710 8th St",
    "sg:city":"Hood River",
    "sg:classifiers":[
        {
            "category":"Building & Trades",
            "subcategory":"Cleaning & Sanitation",
            "type":"Services"
        }
    ],
    "sg:phone":"+1 541 386 7470",
    "sg:postcode":"97031",
    "sg:province":"OR",
    "sg:tags":[
        "maintenance"
    ],
    "wof:name":"D&K Janitor Service",
    "wof:placetype":"venue"
},
  "geometry": {"coordinates":[-121.519002,45.704788],"type":"Point"}
}