{
  "type": "Feature",
  "properties": {
    "iso:country":"US",
    "sg:address":"7421 SW Barbur Boulevard",
    "sg:city":"Portland",
    "sg:classifiers":[
        {
            "category":"Restaurant",
            "type":"Food & Drink"
        }
    ],
    "sg:phone":"+1 503 595 0399",
    "sg:postcode":"97219",
    "sg:province":"OR",
    "wof:name":"Baja Fresh",
    "wof:placetype":"venue"
},
  "geometry": {"coordinates":[-122.68615699999999,45.471156],"type":"Point"}
}