{
  "type": "Feature",
  "properties": {
    "iso:country":"US",
    "sg:address":"480 W 7th Ave",
    "sg:city":"Junction City",
    "sg:classifiers":[
        {
            "category":"Retail",
            "subcategory":"Funeral Services",
            "type":"Services"
        }
    ],
    "sg:phone":"+1 541 998 1771",
    "sg:postcode":"97448",
    "sg:province":"OR",
    "sg:tags":[
        "director"
    ],
    "wof:name":"Alpha Cremation Service Co",
    "wof:placetype":"venue"
},
  "geometry": {"coordinates":[-123.20557599999999,44.220078],"type":"Point"}
}