{
  "type": "Feature",
  "properties": {
    "addr:full":"8635 SW Canyon Rd Portland OR 97225",
    "addr:housenumber":"8635",
    "addr:postcode":"97225",
    "addr:street":"Sw Canyon Rd",
    "iso:country":"US",
    "sg:address":"8635 SW Canyon Rd",
    "sg:city":"Portland",
    "sg:classifiers":[
        {
            "category":"Professional",
            "subcategory":"Business Services",
            "type":"Services"
        }
    ],
    "sg:phone":"+1 503 297 6248",
    "sg:postcode":"97225",
    "sg:province":"OR",
    "wof:name":"Dacascos Wum Hop Kuen Co Inc",
    "wof:placetype":"venue"
},
  "geometry": {"coordinates":[-122.766316,45.498251],"type":"Point"}
}