{
  "type": "Feature",
  "properties": {
    "iso:country":"US",
    "sg:address":"13810 NE Sandy Blvd",
    "sg:city":"Portland",
    "sg:classifiers":[
        {
            "category":"Restaurant",
            "type":"Food & Drink"
        }
    ],
    "sg:phone":"+1 503 254 2135",
    "sg:postcode":"97230",
    "sg:province":"OR",
    "sg:tags":[
        "thai"
    ],
    "wof:name":"Honey Jar Yogurt",
    "wof:placetype":"venue"
},
  "geometry": {"coordinates":[-122.521004,45.554199],"type":"Point"}
}