{
  "type": "Feature",
  "properties": {
    "iso:country":"US",
    "sg:address":"1350 Plaza Blvd Ste G",
    "sg:city":"Central Point",
    "sg:classifiers":[
        {
            "category":"Personal",
            "subcategory":"Nail Salon",
            "type":"Services"
        }
    ],
    "sg:phone":"+1 541 664 1822",
    "sg:postcode":"97502",
    "sg:province":"OR",
    "wof:name":"Happy Nails",
    "wof:placetype":"venue"
},
  "geometry": {"coordinates":[-122.904251,42.377028],"type":"Point"}
}