{
  "type": "Feature",
  "properties": {
    "iso:country":"US",
    "sg:address":"100 Green Ln",
    "sg:city":"Eugene",
    "sg:classifiers":[
        {
            "category":"Retail",
            "subcategory":"Portrait Studio",
            "type":"Services"
        }
    ],
    "sg:phone":"+1 541 461 3567",
    "sg:postcode":"97404",
    "sg:province":"OR",
    "sg:tags":[
        "photo"
    ],
    "wof:name":"Jack Liu Photographer",
    "wof:placetype":"venue"
},
  "geometry": {"coordinates":[-123.127649,44.101779],"type":"Point"}
}