{
  "type": "Feature",
  "properties": {
    "iso:country":"US",
    "sg:address":"7750 SW Mohawk St",
    "sg:city":"Tualatin",
    "sg:classifiers":[
        {
            "category":"Building & Trades",
            "subcategory":"Equipment Rental",
            "type":"Services"
        }
    ],
    "sg:phone":"+1 503 691 8334",
    "sg:postcode":"97062",
    "sg:province":"OR",
    "sg:tags":[
        "leasing"
    ],
    "sg:website":"www.kencolease.com",
    "wof:name":"Kenco Equipment Leasing Co",
    "wof:placetype":"venue"
},
  "geometry": {"coordinates":[-122.756815,45.377125],"type":"Point"}
}