{
  "type": "Feature",
  "properties": {
    "iso:country":"US",
    "sg:address":"8200 SW Hunziker Rd",
    "sg:city":"Tigard",
    "sg:classifiers":[
        {
            "category":"Building & Trades",
            "subcategory":"Construction",
            "type":"Services"
        }
    ],
    "sg:phone":"+1 503 638 6900",
    "sg:postcode":"97223",
    "sg:province":"OR",
    "sg:tags":[
        "demolition",
        "contractor"
    ],
    "sg:website":"www.nwdemolition.com",
    "wof:name":"Northwest Demolition-Dismantle",
    "wof:placetype":"venue"
},
  "geometry": {"coordinates":[-122.762917,45.429409],"type":"Point"}
}