{
  "type": "Feature",
  "properties": {
    "iso:country":"US",
    "sg:address":"27 B Ave",
    "sg:city":"Lake Oswego",
    "sg:classifiers":[
        {
            "category":"Retail",
            "subcategory":"Laundry & Dry Cleaning",
            "type":"Services"
        }
    ],
    "sg:phone":"+1 503 636 0220",
    "sg:postcode":"97034",
    "sg:province":"OR",
    "wof:name":"Lake Oswego Dry Cleaning & Laundry",
    "wof:placetype":"venue"
},
  "geometry": {"coordinates":[-122.66300200000001,45.420502],"type":"Point"}
}