{
  "type": "Feature",
  "properties": {
    "iso:country":"US",
    "sg:address":"16357 S Moore Rd",
    "sg:city":"Oregon City",
    "sg:classifiers":[
        {
            "category":"Home & Garden",
            "subcategory":"Building Materials",
            "type":"Retail Goods"
        }
    ],
    "sg:phone":"+1 503 632 7443",
    "sg:postcode":"97045",
    "sg:province":"OR",
    "sg:tags":[
        "door"
    ],
    "wof:name":"R B STEELE Co LLC",
    "wof:placetype":"venue"
},
  "geometry": {"coordinates":[-122.530216,45.315911],"type":"Point"}
}