{
  "type": "Feature",
  "properties": {
    "addr:full":"2491 E Santiam St Stayton OR 97383",
    "addr:housenumber":"2491",
    "addr:postcode":"97383",
    "addr:street":"E Santiam St",
    "iso:country":"US",
    "sg:address":"2491 E Santiam St",
    "sg:city":"Stayton",
    "sg:classifiers":[
        {
            "category":"Home & Garden",
            "subcategory":"Building Materials",
            "type":"Retail Goods"
        },
        {
            "category":"Manufacturing",
            "subcategory":"Building Materials",
            "type":"Manufacturing & Wholesale Goods"
        }
    ],
    "sg:phone":"+1 503 769 8887",
    "sg:postcode":"97383",
    "sg:province":"OR",
    "sg:tags":[
        "window",
        "doors-wholesale",
        "manufacturer"
    ],
    "wof:name":"Stayton Wood Windows",
    "wof:placetype":"venue"
},
  "geometry": {"coordinates":[-122.78860899999999,44.8022],"type":"Point"}
}