{
  "type": "Feature",
  "properties": {
    "addr:full":"1015 NE 176th Ave Portland OR 97230",
    "addr:housenumber":"1015",
    "addr:postcode":"97230",
    "addr:street":"Ne 176Th Ave",
    "iso:country":"US",
    "sg:address":"1015 NE 176th Ave",
    "sg:city":"Portland",
    "sg:classifiers":[
        {
            "category":"Banks & Credit Unions",
            "subcategory":"Bureau De Change",
            "type":"Services"
        }
    ],
    "sg:phone":"+1 503 255 7067",
    "sg:postcode":"97230",
    "sg:province":"OR",
    "sg:tags":[
        "currency",
        "exchange"
    ],
    "wof:name":"Toguchi's Ne 175th",
    "wof:placetype":"venue"
},
  "geometry": {"coordinates":[-122.48195,45.530941],"type":"Point"}
}