{
  "type": "Feature",
  "properties": {
    "iso:country":"US",
    "sg:address":"7909 Keller Rd",
    "sg:city":"Klamath Falls",
    "sg:classifiers":[
        {
            "category":"Retail",
            "subcategory":"Repair Shop",
            "type":"Services"
        }
    ],
    "sg:phone":"+1 541 882 0073",
    "sg:postcode":"97603",
    "sg:province":"OR",
    "wof:name":"Jeans Custom Upholstery",
    "wof:placetype":"venue"
},
  "geometry": {"coordinates":[-121.697484,42.184684],"type":"Point"}
}