{
  "type": "Feature",
  "properties": {
    "addr:full":"104 Adams Loop Roseburg OR 97470",
    "addr:housenumber":"104",
    "addr:postcode":"97470",
    "addr:street":"Adams Loop",
    "iso:country":"US",
    "sg:address":"104 Adams Loop",
    "sg:city":"Roseburg",
    "sg:classifiers":[
        {
            "category":"Personal",
            "subcategory":"Beauty Salon",
            "type":"Services"
        }
    ],
    "sg:phone":"+1 541 679 2926",
    "sg:postcode":"97470",
    "sg:province":"OR",
    "sg:tags":[
        "shop"
    ],
    "wof:name":"Tracy's 5th Generation Hair",
    "wof:placetype":"venue"
},
  "geometry": {"coordinates":[-123.382745,43.163732],"type":"Point"}
}