{
  "type": "Feature",
  "properties": {
    "iso:country":"US",
    "sg:address":"1045 NE 3rd St",
    "sg:city":"Bend",
    "sg:classifiers":[
        {
            "category":"Wholesale",
            "subcategory":"Medical Equipment & Supplies",
            "type":"Manufacturing & Wholesale Goods"
        }
    ],
    "sg:phone":"+1 541 382 6016",
    "sg:postcode":"97701",
    "sg:province":"OR",
    "sg:tags":[
        "handicapped"
    ],
    "wof:name":"Advanced Mobility Of Bend",
    "wof:placetype":"venue"
},
  "geometry": {"coordinates":[-121.30256900000001,44.0605],"type":"Point"}
}