{
  "type": "Feature",
  "properties": {
    "addr:full":"28399 State Hwy 213 Molalla OR 97038",
    "addr:housenumber":"28399",
    "addr:postcode":"97038",
    "addr:street":"State Hwy 213",
    "iso:country":"US",
    "sg:address":"28399 State Hwy 213",
    "sg:city":"Molalla",
    "sg:classifiers":[
        {
            "category":"Insurance",
            "subcategory":"Insurance Agent",
            "type":"Services"
        }
    ],
    "sg:phone":"+1 503 829 6612",
    "sg:postcode":"97038",
    "sg:province":"OR",
    "wof:name":"Mid Valley Insurance",
    "wof:placetype":"venue"
},
  "geometry": {"coordinates":[-122.582086,45.19625],"type":"Point"}
}