{
  "type": "Feature",
  "properties": {
    "addr:full":"4409 SW Obsidian Ave Redmond OR 97756",
    "addr:housenumber":"4409",
    "addr:postcode":"97756",
    "addr:street":"Sw Obsidian Ave",
    "iso:country":"US",
    "sg:address":"4409 SW Obsidian Ave",
    "sg:city":"Redmond",
    "sg:classifiers":[
        {
            "category":"Government",
            "subcategory":"Office",
            "type":"Public Place"
        }
    ],
    "sg:phone":"+1 541 548 2241",
    "sg:postcode":"97756",
    "sg:province":"OR",
    "sg:tags":[
        "state",
        "program"
    ],
    "wof:name":"Agriculture Dept",
    "wof:placetype":"venue"
},
  "geometry": {"coordinates":[-121.226833,44.262205],"type":"Point"}
}