{
  "type": "Feature",
  "properties": {
    "addr:full":"31744 S Meridian Rd Hubbard OR 97032",
    "addr:housenumber":"31744",
    "addr:postcode":"97032",
    "addr:street":"S Meridian Rd",
    "iso:country":"US",
    "sg:address":"31744 S Meridian Rd",
    "sg:city":"Hubbard",
    "sg:classifiers":[
        {
            "category":"Building & Trades",
            "subcategory":"Construction",
            "type":"Services"
        }
    ],
    "sg:phone":"+1 503 651 2956",
    "sg:postcode":"97032",
    "sg:province":"OR",
    "sg:tags":[
        "steel",
        "industrial",
        "contractor"
    ],
    "wof:name":"Pacific Western Bldg Erectors",
    "wof:placetype":"venue"
},
  "geometry": {"coordinates":[-122.75663299999999,45.148005],"type":"Point"}
}