{
  "type": "Feature",
  "properties": {
    "iso:country":"US",
    "sg:address":"444 SW 4th St",
    "sg:city":"Ontario",
    "sg:classifiers":[
        {
            "category":"Government",
            "subcategory":"Office",
            "type":"Public Place"
        }
    ],
    "sg:phone":"+1 541 881 3246",
    "sg:postcode":"97914",
    "sg:province":"OR",
    "sg:tags":[
        "govt",
        "city"
    ],
    "wof:name":"Utility Billing Dept",
    "wof:placetype":"venue"
},
  "geometry": {"coordinates":[-116.96914200000001,44.023496],"type":"Point"}
}