{
  "type": "Feature",
  "properties": {
    "iso:country":"US",
    "sg:address":"11525 Baker Creek Rd",
    "sg:city":"Mcminnville",
    "sg:classifiers":[
        {
            "category":"Building & Trades",
            "subcategory":"Landscaping Services",
            "type":"Services"
        }
    ],
    "sg:phone":"+1 503 472 5897",
    "sg:postcode":"97128",
    "sg:province":"OR",
    "sg:tags":[
        "landscape",
        "contractor"
    ],
    "wof:name":"Cascadia Landscaping",
    "wof:placetype":"venue"
},
  "geometry": {"coordinates":[-123.2317,45.229973],"type":"Point"}
}