{
  "type": "Feature",
  "properties": {
    "iso:country":"US",
    "sg:address":"16508 SW Waterleaf St",
    "sg:city":"Beaverton",
    "sg:classifiers":[
        {
            "category":"Professional",
            "subcategory":"Management & Consulting",
            "type":"Services"
        }
    ],
    "sg:phone":"+1 503 617 1848",
    "sg:postcode":"97006",
    "sg:province":"OR",
    "sg:tags":[
        "consultant",
        "educational"
    ],
    "wof:name":"Annie Woo",
    "wof:placetype":"venue"
},
  "geometry": {"coordinates":[-122.847327,45.513781],"type":"Point"}
}