{
  "type": "Feature",
  "properties": {
    "iso:country":"US",
    "sg:address":"4426 SE 122nd Ave",
    "sg:city":"Portland",
    "sg:classifiers":[
        {
            "category":"Personal",
            "type":"Services"
        }
    ],
    "sg:phone":"+1 503 668 8888",
    "sg:postcode":"97236",
    "sg:province":"OR",
    "sg:tags":[
        "mover"
    ],
    "sg:website":"www.westcoastmoving.com",
    "wof:name":"Master Movers Moving and Storage",
    "wof:placetype":"venue"
},
  "geometry": {"coordinates":[-122.537323,45.489838],"type":"Point"}
}