{
  "type": "Feature",
  "properties": {
    "iso:country":"US",
    "sg:address":"6800 NE M L King Blvd",
    "sg:city":"Portland",
    "sg:classifiers":[
        {
            "category":"Restaurant",
            "type":"Food & Drink"
        }
    ],
    "sg:phone":"+1 503 247 7211",
    "sg:postcode":"97211",
    "sg:province":"OR",
    "wof:name":"Steakadelphia",
    "wof:placetype":"venue"
},
  "geometry": {"coordinates":[-122.661362,45.573257],"type":"Point"}
}