{
  "type": "Feature",
  "properties": {
    "iso:country":"US",
    "sg:address":"3400 River Rd N",
    "sg:city":"Salem",
    "sg:classifiers":[
        {
            "category":"Restaurant",
            "type":"Food & Drink"
        }
    ],
    "sg:phone":"+1 503 390 5002",
    "sg:postcode":"97303",
    "sg:province":"OR",
    "sg:tags":[
        "eating"
    ],
    "wof:name":"Izzys Pizza",
    "wof:placetype":"venue"
},
  "geometry": {"coordinates":[-123.02731,44.97528],"type":"Point"}
}