{
  "type": "Feature",
  "properties": {
    "iso:country":"US",
    "sg:address":"20201 Hwy 97 S",
    "sg:city":"Klamath Falls",
    "sg:classifiers":[
        {
            "category":"Real Estate",
            "subcategory":"Real Estate Agent",
            "type":"Services"
        }
    ],
    "sg:phone":"+1 541 883 3466",
    "sg:postcode":"97603",
    "sg:province":"OR",
    "wof:name":"Henzel Properties Ltd",
    "wof:placetype":"venue"
},
  "geometry": {"coordinates":[-121.869716,42.042084],"type":"Point"}
}