{
  "type": "Feature",
  "properties": {
    "addr:full":"14865 SW 74th Avenue Suite 240 Tigard OR 97224",
    "addr:housenumber":"14865",
    "addr:postcode":"97224",
    "addr:street":"Sw 74Th Avenue Suite 240",
    "iso:country":"US",
    "sg:address":"14865 SW 74th Avenue Suite 240",
    "sg:city":"Tigard",
    "sg:classifiers":[
        {
            "category":"Building & Trades",
            "subcategory":"Pest Control",
            "type":"Services"
        }
    ],
    "sg:phone":"+1 503 639 2500",
    "sg:postcode":"97224",
    "sg:province":"OR",
    "sg:website":"www.pacificpestmgmt.com",
    "wof:name":"Pacific Pest and Wildlife Management",
    "wof:placetype":"venue"
},
  "geometry": {"coordinates":[-122.753293,45.412765],"type":"Point"}
}