{
  "type": "Feature",
  "properties": {
    "iso:country":"US",
    "sg:address":"811 Marie Ave",
    "sg:city":"Newberg",
    "sg:classifiers":[
        {
            "category":"Shopping",
            "type":"Retail Goods"
        }
    ],
    "sg:phone":"+1 503 538 9887",
    "sg:postcode":"97132",
    "sg:province":"OR",
    "sg:tags":[
        "merchandise"
    ],
    "wof:name":"Air Networks",
    "wof:placetype":"venue"
},
  "geometry": {"coordinates":[-122.956746,45.306407],"type":"Point"}
}