{
  "type": "Feature",
  "properties": {
    "iso:country":"US",
    "sg:address":"10525 SW 63rd Dr",
    "sg:city":"Portland",
    "sg:classifiers":[
        {
            "category":"Communications",
            "subcategory":"Film & Video Production",
            "type":"Services"
        }
    ],
    "sg:phone":"+1 503 246 1177",
    "sg:postcode":"97219",
    "sg:province":"OR",
    "sg:tags":[
        "motion"
    ],
    "wof:name":"Z Films Inc",
    "wof:placetype":"venue"
},
  "geometry": {"coordinates":[-122.740986,45.44974],"type":"Point"}
}