{
  "type": "Feature",
  "properties": {
    "iso:country":"US",
    "sg:address":"440 SW Emigrant Ave",
    "sg:city":"Pendleton",
    "sg:classifiers":[
        {
            "category":"Organizations",
            "subcategory":"Religious Organization",
            "type":"Services"
        }
    ],
    "sg:phone":"+1 541 276 2878",
    "sg:postcode":"97801",
    "sg:province":"OR",
    "sg:tags":[
        "church"
    ],
    "wof:name":"St Marys Outreach",
    "wof:placetype":"venue"
},
  "geometry": {"coordinates":[-118.790272,45.669266],"type":"Point"}
}