{
  "type": "Feature",
  "properties": {
    "iso:country":"US",
    "sg:address":"14385 NE Kinney Rd",
    "sg:city":"Newberg",
    "sg:classifiers":[
        {
            "category":"Retail",
            "subcategory":"Auto Repair",
            "type":"Services"
        }
    ],
    "sg:phone":"+1 503 537 0933",
    "sg:postcode":"97132",
    "sg:province":"OR",
    "sg:tags":[
        "glass",
        "replacement"
    ],
    "wof:name":"Mr Chips Windshield Repair",
    "wof:placetype":"venue"
},
  "geometry": {"coordinates":[-123.086281,45.312151],"type":"Point"}
}