{
  "type": "Feature",
  "properties": {
    "iso:country":"US",
    "sg:address":"971 Golden Aspen Pl",
    "sg:city":"Ashland",
    "sg:classifiers":[
        {
            "category":"Building & Trades",
            "subcategory":"Construction",
            "type":"Services"
        }
    ],
    "sg:phone":"+1 541 482 5404",
    "sg:postcode":"97520",
    "sg:province":"OR",
    "sg:tags":[
        "manufactured",
        "housing-communities"
    ],
    "wof:name":"Los Robles Mobile Home Estates",
    "wof:placetype":"venue"
},
  "geometry": {"coordinates":[-122.699589,42.208684],"type":"Point"}
}