{
  "type": "Feature",
  "properties": {
    "iso:country":"US",
    "sg:address":"555 NW 15th St",
    "sg:city":"Bend",
    "sg:classifiers":[
        {
            "category":"Government",
            "subcategory":"Police Station",
            "type":"Public Place"
        }
    ],
    "sg:phone":"+1 541 322 2960",
    "sg:postcode":"97701",
    "sg:province":"OR",
    "sg:tags":[
        "department"
    ],
    "sg:website":"www.ci.bend.or.us",
    "wof:name":"Bend Police Dept",
    "wof:placetype":"venue"
},
  "geometry": {"coordinates":[-121.333691,44.055399],"type":"Point"}
}