{
  "type": "Feature",
  "properties": {
    "addr:full":"150 N Pioneer St Ashland OR 97520",
    "addr:housenumber":"150",
    "addr:postcode":"97520",
    "addr:street":"N Pioneer St",
    "iso:country":"US",
    "sg:address":"150 N Pioneer St",
    "sg:city":"Ashland",
    "sg:classifiers":[
        {
            "category":"Social Services",
            "subcategory":"Job Training",
            "type":"Services"
        }
    ],
    "sg:phone":"+1 541 482 8888",
    "sg:postcode":"97520",
    "sg:province":"OR",
    "sg:tags":[
        "rehabilitation"
    ],
    "wof:name":"Vocational Resource Consultant",
    "wof:placetype":"venue"
},
  "geometry": {"coordinates":[-122.713156,42.197696],"type":"Point"}
}