{
  "type": "Feature",
  "properties": {
    "addr:full":"2718 SW Kelly Ave Portland OR 97201",
    "addr:housenumber":"2718",
    "addr:postcode":"97201",
    "addr:street":"Sw Kelly Ave",
    "iso:country":"US",
    "sg:address":"2718 SW Kelly Ave",
    "sg:city":"Portland",
    "sg:classifiers":[
        {
            "category":"Building & Trades",
            "subcategory":"Construction",
            "type":"Services"
        }
    ],
    "sg:phone":"+1 503 241 2443",
    "sg:postcode":"97201",
    "sg:province":"OR",
    "sg:tags":[
        "contractor"
    ],
    "wof:name":"Nick Kikes & Sons",
    "wof:placetype":"venue"
},
  "geometry": {"coordinates":[-122.67679699999999,45.503241],"type":"Point"}
}