{
  "type": "Feature",
  "properties": {
    "iso:country":"US",
    "sg:address":"380 SW 2nd St",
    "sg:city":"Newport",
    "sg:classifiers":[
        {
            "category":"Professional",
            "subcategory":"Lawyer & Legal Services",
            "type":"Services"
        }
    ],
    "sg:phone":"+1 541 265 5400",
    "sg:postcode":"97365",
    "sg:province":"OR",
    "sg:tags":[
        "attorney"
    ],
    "wof:name":"Clifford G Collard Atty",
    "wof:placetype":"venue"
},
  "geometry": {"coordinates":[-124.057073,44.63475],"type":"Point"}
}