{
  "type": "Feature",
  "properties": {
    "iso:country":"US",
    "sg:address":"9550 Springlake Rd",
    "sg:city":"Klamath Falls",
    "sg:classifiers":[
        {
            "category":"Farming",
            "subcategory":"Livestock Farm",
            "type":"Manufacturing & Wholesale Goods"
        }
    ],
    "sg:phone":"+1 541 882 6168",
    "sg:postcode":"97603",
    "sg:province":"OR",
    "sg:tags":[
        "equine"
    ],
    "wof:name":"Collins Corral",
    "wof:placetype":"venue"
},
  "geometry": {"coordinates":[-121.74256099999999,42.139075],"type":"Point"}
}