{
  "type": "Feature",
  "properties": {
    "iso:country":"US",
    "sg:address":"2055 W 12th Ave",
    "sg:city":"Eugene",
    "sg:classifiers":[
        {
            "category":"Health Services",
            "subcategory":"Clinic",
            "type":"Services"
        }
    ],
    "sg:phone":"+1 541 484 6558",
    "sg:postcode":"97402",
    "sg:province":"OR",
    "sg:tags":[
        "information",
        "medical"
    ],
    "wof:name":"Compassion Center",
    "wof:placetype":"venue"
},
  "geometry": {"coordinates":[-123.124652,44.046726],"type":"Point"}
}