{
  "type": "Feature",
  "properties": {
    "iso:country":"US",
    "sg:address":"94026 State Hwy 42",
    "sg:city":"Coos Bay",
    "sg:classifiers":[
        {
            "category":"Shopping",
            "subcategory":"Bicycles & Sporting Goods",
            "type":"Retail Goods"
        }
    ],
    "sg:phone":"+1 541 267 2543",
    "sg:postcode":"97420",
    "sg:province":"OR",
    "wof:name":"Blue Ribbon Tack",
    "wof:placetype":"venue"
},
  "geometry": {"coordinates":[-124.23190700000001,43.28174],"type":"Point"}
}