{
  "type": "Feature",
  "properties": {
    "iso:country":"US",
    "sg:address":"1130 Chetco Ave",
    "sg:city":"Brookings",
    "sg:classifiers":[
        {
            "category":"Retail",
            "subcategory":"Auto Repair",
            "type":"Services"
        }
    ],
    "sg:phone":"+1 541 469 0414",
    "sg:postcode":"97415",
    "sg:province":"OR",
    "sg:tags":[
        "machine",
        "automobile",
        "shop"
    ],
    "wof:name":"Arneson Motor & Machine",
    "wof:placetype":"venue"
},
  "geometry": {"coordinates":[-124.293904,42.056005],"type":"Point"}
}