{
  "type": "Feature",
  "properties": {
    "iso:country":"US",
    "sg:address":"5351 Landon St SE",
    "sg:city":"Salem",
    "sg:classifiers":[
        {
            "category":"Professional",
            "subcategory":"Business Services",
            "type":"Services"
        }
    ],
    "sg:phone":"+1 503 910 9112",
    "sg:postcode":"97306",
    "sg:province":"OR",
    "wof:name":"Michael Gilham Partnership",
    "wof:placetype":"venue"
},
  "geometry": {"coordinates":[-123.000715,44.877714],"type":"Point"}
}