{
  "type": "Feature",
  "properties": {
    "addr:full":"3715 Browns Creek Rd The Dalles OR 97058",
    "addr:housenumber":"3715",
    "addr:postcode":"97058",
    "addr:street":"Browns Creek Rd",
    "iso:country":"US",
    "sg:address":"3715 Browns Creek Rd",
    "sg:city":"The Dalles",
    "sg:classifiers":[
        {
            "category":"Manufacturing",
            "subcategory":"Lumber",
            "type":"Manufacturing & Wholesale Goods"
        }
    ],
    "sg:phone":"+1 541 296 9915",
    "sg:postcode":"97058",
    "sg:province":"OR",
    "sg:tags":[
        "operation",
        "timber",
        "tract"
    ],
    "wof:name":"Greenridge Treefarm",
    "wof:placetype":"venue"
},
  "geometry": {"coordinates":[-121.268123,45.59944],"type":"Point"}
}