{
  "type": "Feature",
  "properties": {
    "addr:full":"61430 Steens Mountain Loop Bend OR 97702",
    "addr:postcode":"61430;97702",
    "addr:street":"Steens Mountain Loop",
    "iso:country":"US",
    "sg:address":"61430 Steens Mountain Loop",
    "sg:city":"Bend",
    "sg:classifiers":[
        {
            "category":"Building & Trades",
            "subcategory":"Construction",
            "type":"Services"
        }
    ],
    "sg:phone":"+1 541 548 4617",
    "sg:postcode":"97702",
    "sg:province":"OR",
    "sg:tags":[
        "floor",
        "laying",
        "contractor"
    ],
    "wof:name":"Circa Woodworks",
    "wof:placetype":"venue"
},
  "geometry": {"coordinates":[-121.264864,44.027263],"type":"Point"}
}