{
  "type": "Feature",
  "properties": {
    "iso:country":"US",
    "sg:address":"12650 SW Grant Ave",
    "sg:city":"Portland",
    "sg:classifiers":[
        {
            "category":"Wholesale",
            "subcategory":"Plants",
            "type":"Manufacturing & Wholesale Goods"
        }
    ],
    "sg:phone":"+1 503 670 9101",
    "sg:postcode":"97223",
    "sg:province":"OR",
    "sg:tags":[
        "supply"
    ],
    "wof:name":"Brandy Wynne Flowers",
    "wof:placetype":"venue"
},
  "geometry": {"coordinates":[-122.780244,45.428091],"type":"Point"}
}