{
  "type": "Feature",
  "properties": {
    "addr:full":"19164 SW Briedwell Rd Amity OR 97101",
    "addr:housenumber":"19164",
    "addr:postcode":"97101",
    "addr:street":"Sw Briedwell Rd",
    "iso:country":"US",
    "sg:address":"19164 SW Briedwell Rd",
    "sg:city":"Amity",
    "sg:classifiers":[
        {
            "category":"Wholesale",
            "subcategory":"Farm Supplies",
            "type":"Manufacturing & Wholesale Goods"
        },
        {
            "category":"Autos & Motor Vehicles",
            "subcategory":"Automobile Sales",
            "type":"Retail Goods"
        },
        {
            "category":"Wholesale",
            "subcategory":"Machinery & Supplies",
            "type":"Manufacturing & Wholesale Goods"
        },
        {
            "category":"Farming",
            "subcategory":"Farm",
            "type":"Manufacturing & Wholesale Goods"
        }
    ],
    "sg:phone":"+1 503 835 3777",
    "sg:postcode":"97101",
    "sg:province":"OR",
    "sg:tags":[
        "equipment",
        "transport",
        "trailer",
        "tractor",
        "baling"
    ],
    "wof:name":"Lehman Bros Farm Equipment",
    "wof:placetype":"venue"
},
  "geometry": {"coordinates":[-123.24051,45.125146],"type":"Point"}
}