{
  "type": "Feature",
  "properties": {
    "addr:full":"13340 S Deer Meadows Rd Oregon City OR 97045",
    "addr:housenumber":"13340",
    "addr:postcode":"97045",
    "addr:street":"S Deer Meadows Rd",
    "iso:country":"US",
    "sg:address":"13340 S Deer Meadows Rd",
    "sg:city":"Oregon City",
    "sg:classifiers":[
        {
            "category":"Professional",
            "type":"Services"
        }
    ],
    "sg:phone":"+1 503 656 2346",
    "sg:postcode":"97045",
    "sg:province":"OR",
    "wof:name":"Netpeerscom",
    "wof:placetype":"venue"
},
  "geometry": {"coordinates":[-122.59250900000001,45.32324],"type":"Point"}
}