{
  "type": "Feature",
  "properties": {
    "iso:country":"US",
    "sg:address":"13340 S Deer Meadows Rd",
    "sg:city":"Oregon City",
    "sg:classifiers":[
        {
            "category":"Professional",
            "type":"Services"
        }
    ],
    "sg:phone":"+1 503 656 2346",
    "sg:postcode":"97045",
    "sg:province":"OR",
    "wof:name":"Netpeerscom",
    "wof:placetype":"venue"
},
  "geometry": {"coordinates":[-122.592509,45.32324],"type":"Point"}
}