{
  "type": "Feature",
  "properties": {
    "addr:full":"6128 SE King Rd Milwaukie OR 97222",
    "addr:housenumber":"6128",
    "addr:postcode":"97222",
    "addr:street":"Se King Rd",
    "iso:country":"US",
    "sg:address":"6128 SE King Rd",
    "sg:city":"Milwaukie",
    "sg:classifiers":[
        {
            "category":"Restaurant",
            "type":"Food & Drink"
        }
    ],
    "sg:phone":"+1 503 786 4567",
    "sg:postcode":"97222",
    "sg:province":"OR",
    "wof:name":"Hong Kong 97",
    "wof:placetype":"venue"
},
  "geometry": {"coordinates":[-122.59957,45.447943],"type":"Point"}
}