{
  "type": "Feature",
  "properties": {
    "iso:country":"US",
    "sg:address":"9120 SW Pioneer Ct",
    "sg:city":"Wilsonville",
    "sg:classifiers":[
        {
            "category":"Home & Garden",
            "subcategory":"Home Furnishings",
            "type":"Retail Goods"
        }
    ],
    "sg:phone":"+1 503 925 0660",
    "sg:postcode":"97070",
    "sg:province":"OR",
    "sg:tags":[
        "utensil",
        "cooking"
    ],
    "wof:name":"Northwest Elite Inc",
    "wof:placetype":"venue"
},
  "geometry": {"coordinates":[-122.77158900000001,45.338901],"type":"Point"}
}