{
  "type": "Feature",
  "properties": {
    "addr:full":"895 Salem Heights Ave S Salem OR 97302",
    "addr:housenumber":"895",
    "addr:postcode":"97302",
    "addr:street":"Salem Heights Ave S",
    "iso:country":"US",
    "sg:address":"895 Salem Heights Ave S",
    "sg:city":"Salem",
    "sg:classifiers":[
        {
            "category":"Professional",
            "subcategory":"Management & Consulting",
            "type":"Services"
        }
    ],
    "sg:phone":"+1 503 375 3533",
    "sg:postcode":"97302",
    "sg:province":"OR",
    "sg:tags":[
        "consultant",
        "business"
    ],
    "wof:name":"Northwest Forestry Resources",
    "wof:placetype":"venue"
},
  "geometry": {"coordinates":[-123.059523,44.908423],"type":"Point"}
}