{
  "type": "Feature",
  "properties": {
    "iso:country":"US",
    "sg:address":"101 SW Main St",
    "sg:city":"Portland",
    "sg:classifiers":[
        {
            "category":"Professional",
            "subcategory":"Business Services",
            "type":"Services"
        }
    ],
    "sg:phone":"+1 503 243 7108",
    "sg:postcode":"97204",
    "sg:province":"OR",
    "sg:tags":[
        "equipment"
    ],
    "wof:name":"Contract Office Group",
    "wof:placetype":"venue"
},
  "geometry": {"coordinates":[-122.67600299999999,45.515202],"type":"Point"}
}