{
  "type": "Feature",
  "properties": {
    "addr:full":"2350 SE Territorial Rd Canby OR 97013",
    "addr:housenumber":"2350",
    "addr:postcode":"97013",
    "addr:street":"Se Territorial Rd",
    "iso:country":"US",
    "sg:address":"2350 SE Territorial Rd",
    "sg:city":"Canby",
    "sg:classifiers":[
        {
            "category":"Organizations",
            "subcategory":"Religious Organization",
            "type":"Services"
        }
    ],
    "sg:phone":"+1 503 266 4444",
    "sg:postcode":"97013",
    "sg:province":"OR",
    "sg:tags":[
        "church"
    ],
    "sg:website":"www.canbyfoursquare.com",
    "wof:name":"New Life Foursquare Church",
    "wof:placetype":"venue"
},
  "geometry": {"coordinates":[-122.66542,45.279176],"type":"Point"}
}