{
  "type": "Feature",
  "properties": {
    "iso:country":"US",
    "sg:address":"13130 SE Sunnyside Rd",
    "sg:city":"Clackamas",
    "sg:classifiers":[
        {
            "category":"Organizations",
            "subcategory":"Religious Organization",
            "type":"Services"
        }
    ],
    "sg:phone":"+1 503 698 7004",
    "sg:postcode":"97015",
    "sg:province":"OR",
    "wof:name":"Church of Schkinah Glory",
    "wof:placetype":"venue"
},
  "geometry": {"coordinates":[-122.528812,45.42692],"type":"Point"}
}