{
  "type": "Feature",
  "properties": {
    "iso:country":"US",
    "sg:address":"7508 Steens Dr",
    "sg:city":"Klamath Falls",
    "sg:classifiers":[
        {
            "category":"Shopping",
            "type":"Retail Goods"
        }
    ],
    "sg:phone":"+1 541 882 7994",
    "sg:postcode":"97601",
    "sg:province":"OR",
    "sg:tags":[
        "installs",
        "telephone",
        "system"
    ],
    "wof:name":"Del-Tronics Co",
    "wof:placetype":"venue"
},
  "geometry": {"coordinates":[-121.84448999999999,42.176638],"type":"Point"}
}