{
  "type": "Feature",
  "properties": {
    "addr:full":"119 S 6th St Cottage Grove OR 97424",
    "addr:housenumber":"119",
    "addr:postcode":"97424",
    "addr:street":"S 6Th St",
    "iso:country":"US",
    "sg:address":"119 S 6th St",
    "sg:city":"Cottage Grove",
    "sg:classifiers":[
        {
            "category":"Shopping",
            "subcategory":"Florist",
            "type":"Retail Goods"
        }
    ],
    "sg:phone":"+1 541 942 0505",
    "sg:postcode":"97424",
    "sg:province":"OR",
    "sg:tags":[
        "potted",
        "flower",
        "plant"
    ],
    "wof:name":"Flower Basket The",
    "wof:placetype":"venue"
},
  "geometry": {"coordinates":[-123.061987,43.79617],"type":"Point"}
}