{
  "type": "Feature",
  "properties": {
    "addr:full":"7110 SW Fir Loop Portland OR 97223",
    "addr:housenumber":"7110",
    "addr:postcode":"97223",
    "addr:street":"Sw Fir Loop",
    "iso:country":"US",
    "sg:address":"7110 SW Fir Loop",
    "sg:city":"Portland",
    "sg:classifiers":[
        {
            "category":"Banks & Credit Unions",
            "subcategory":"Investment Brokerage",
            "type":"Services"
        }
    ],
    "sg:phone":"+1 503 670 9433",
    "sg:postcode":"97223",
    "sg:province":"OR",
    "sg:tags":[
        "advisory",
        "financial"
    ],
    "wof:name":"Robert Poe & Assoc",
    "wof:placetype":"venue"
},
  "geometry": {"coordinates":[-122.751295,45.42322],"type":"Point"}
}