{
  "type": "Feature",
  "properties": {
    "addr:full":"1011 7th Ave Seaside OR 97138",
    "addr:housenumber":"1011",
    "addr:postcode":"97138",
    "addr:street":"7Th Ave",
    "iso:country":"US",
    "sg:address":"1011 7th Ave",
    "sg:city":"Seaside",
    "sg:classifiers":[
        {
            "category":"Shopping",
            "subcategory":"Used Merchandise",
            "type":"Retail Goods"
        }
    ],
    "sg:phone":"+1 503 738 2182",
    "sg:postcode":"97138",
    "sg:province":"OR",
    "sg:tags":[
        "shop",
        "thrift"
    ],
    "wof:name":"Rag & Bone Thrift Store",
    "wof:placetype":"venue"
},
  "geometry": {"coordinates":[-123.91811199999999,45.998696],"type":"Point"}
}