{
  "type": "Feature",
  "properties": {
    "iso:country":"US",
    "sg:address":"240 W Oregon Ave",
    "sg:city":"Creswell",
    "sg:classifiers":[
        {
            "category":"Personal",
            "type":"Services"
        }
    ],
    "sg:phone":"+1 541 895 4755",
    "sg:postcode":"97426",
    "sg:province":"OR",
    "sg:tags":[
        "tanning",
        "salon",
        "health"
    ],
    "wof:name":"All Seasons Salon",
    "wof:placetype":"venue"
},
  "geometry": {"coordinates":[-123.02146500000001,43.917858],"type":"Point"}
}