{
  "type": "Feature",
  "properties": {
    "addr:full":"2546 SE 131st Ave Portland OR 97236",
    "addr:housenumber":"2546",
    "addr:postcode":"97236",
    "addr:street":"Se 131St Ave",
    "iso:country":"US",
    "sg:address":"2546 SE 131st Ave",
    "sg:city":"Portland",
    "sg:classifiers":[
        {
            "category":"Place Of Worship",
            "subcategory":"Church",
            "type":"Public Place"
        },
        {
            "category":"Place Of Worship",
            "type":"Public Place"
        },
        {
            "category":"Organizations",
            "subcategory":"Religious Organization",
            "type":"Services"
        }
    ],
    "sg:phone":"+1 503 761 2660",
    "sg:postcode":"97236",
    "sg:province":"OR",
    "sg:tags":[
        "christ",
        "churches-community",
        "denomination",
        "churches-interdenominational",
        "churches-various"
    ],
    "wof:name":"Midway Christian Church Inc",
    "wof:placetype":"venue"
},
  "geometry": {"coordinates":[-122.52845000000001,45.503746],"type":"Point"}
}