{
  "type": "Feature",
  "properties": {
    "addr:full":"707 S Main St Lebanon OR 97355",
    "addr:housenumber":"707",
    "addr:postcode":"97355",
    "addr:street":"S Main St",
    "iso:country":"US",
    "sg:address":"707 S Main St",
    "sg:city":"Lebanon",
    "sg:classifiers":[
        {
            "category":"Professional",
            "subcategory":"Business Services",
            "type":"Services"
        }
    ],
    "sg:phone":"+1 541 451 2221",
    "sg:postcode":"97355",
    "sg:province":"OR",
    "sg:tags":[
        "fund",
        "promotion",
        "raising"
    ],
    "sg:website":"www.loveyourpets.com",
    "wof:name":"Pacific Star Promotions",
    "wof:placetype":"venue"
},
  "geometry": {"coordinates":[-122.90698399999999,44.53909],"type":"Point"}
}