{
  "type": "Feature",
  "properties": {
    "iso:country":"US",
    "sg:address":"4035 SW Mercantile Dr Ste 206",
    "sg:city":"Lake Oswego",
    "sg:classifiers":[
        {
            "category":"Health Services",
            "subcategory":"Doctor",
            "type":"Services"
        }
    ],
    "sg:phone":"+1 503 635 8930",
    "sg:postcode":"97035",
    "sg:province":"OR",
    "sg:tags":[
        "surgeon",
        "cosmetic"
    ],
    "sg:website":"www.drleerobinson.com",
    "wof:name":"Lee D Robinson, MD",
    "wof:placetype":"venue"
},
  "geometry": {"coordinates":[-122.71883800000001,45.415097],"type":"Point"}
}