{
  "type": "Feature",
  "properties": {
    "iso:country":"US",
    "sg:address":"28549 SW Ash Meadows Blvd",
    "sg:city":"Wilsonville",
    "sg:classifiers":[
        {
            "category":"Professional",
            "subcategory":"Accounting & Tax Preparation",
            "type":"Services"
        }
    ],
    "sg:phone":"+1 503 570 0299",
    "sg:postcode":"97070",
    "sg:province":"OR",
    "wof:name":"Bookkeeping Services Ritas Lt",
    "wof:placetype":"venue"
},
  "geometry": {"coordinates":[-122.763538,45.312769],"type":"Point"}
}