{
  "type": "Feature",
  "properties": {
    "iso:country":"US",
    "sg:address":"2035 Allendale Way NE",
    "sg:city":"Salem",
    "sg:classifiers":[
        {
            "category":"Professional",
            "subcategory":"Business Services",
            "type":"Services"
        }
    ],
    "sg:phone":"+1 503 304 9094",
    "sg:postcode":"97303",
    "sg:province":"OR",
    "wof:name":"Dbd Enterprises",
    "wof:placetype":"venue"
},
  "geometry": {"coordinates":[-123.005595,44.998961],"type":"Point"}
}