{
  "type": "Feature",
  "properties": {
    "addr:full":"750 N Fremont St Portland OR 97227",
    "addr:housenumber":"750",
    "addr:postcode":"97227",
    "addr:street":"N Fremont St",
    "iso:country":"US",
    "sg:address":"750 N Fremont St",
    "sg:city":"Portland",
    "sg:classifiers":[
        {
            "category":"Arts & Performance",
            "subcategory":"Music",
            "type":"Entertainment"
        },
        {
            "category":"Bars & Pubs",
            "type":"Food & Drink"
        },
        {
            "category":"Restaurant",
            "type":"Food & Drink"
        }
    ],
    "sg:postcode":"97227",
    "sg:province":"OR",
    "sg:tags":[
        "venue"
    ],
    "sg:website":"www.thewaterheater.org/",
    "wof:name":"The WaterHeater",
    "wof:placetype":"venue"
},
  "geometry": {"coordinates":[-122.674317,45.547649],"type":"Point"}
}