{
  "type": "Feature",
  "properties": {
    "addr:full":"14354 SE Bluff Rd Sandy OR 97055",
    "addr:housenumber":"14354",
    "addr:postcode":"97055",
    "addr:street":"Se Bluff Rd",
    "iso:country":"US",
    "sg:address":"14354 SE Bluff Rd",
    "sg:city":"Sandy",
    "sg:classifiers":[
        {
            "category":"Manufacturing",
            "subcategory":"Printing",
            "type":"Manufacturing & Wholesale Goods"
        }
    ],
    "sg:phone":"+1 503 317 8683",
    "sg:postcode":"97055",
    "sg:province":"OR",
    "sg:tags":[
        "newspaper"
    ],
    "wof:name":"Oregon Home Resource",
    "wof:placetype":"venue"
},
  "geometry": {"coordinates":[-122.27272499999999,45.420076],"type":"Point"}
}