{
  "type": "Feature",
  "properties": {
    "addr:full":"4314 NE 148th Ave Portland OR 97230",
    "addr:housenumber":"4314",
    "addr:postcode":"97230",
    "addr:street":"Ne 148Th Ave",
    "iso:country":"US",
    "sg:address":"4314 NE 148th Ave",
    "sg:city":"Portland",
    "sg:classifiers":[
        {
            "category":"Building & Trades",
            "subcategory":"Construction",
            "type":"Services"
        }
    ],
    "sg:phone":"+1 503 255 8085",
    "sg:postcode":"97230",
    "sg:province":"OR",
    "sg:tags":[
        "welder"
    ],
    "wof:name":"B & G Quality Welding & Repair Inc",
    "wof:placetype":"venue"
},
  "geometry": {"coordinates":[-122.510295,45.554268],"type":"Point"}
}