{
  "type": "Feature",
  "properties": {
    "iso:country":"US",
    "sg:address":"114 US Hwy 101 N",
    "sg:city":"Yachats",
    "sg:classifiers":[
        {
            "category":"Health Services",
            "subcategory":"Doctor",
            "type":"Services"
        }
    ],
    "sg:phone":"+1 541 547 3301",
    "sg:postcode":"97498",
    "sg:province":"OR",
    "sg:tags":[
        "clinic"
    ],
    "wof:name":"Yachats Community Hlth Clinic",
    "wof:placetype":"venue"
},
  "geometry": {"coordinates":[-124.099368,44.308829],"type":"Point"}
}