{
  "type": "Feature",
  "properties": {
    "addr:full":"792 River St Ontario OR 97914",
    "addr:housenumber":"792",
    "addr:postcode":"97914",
    "addr:street":"River St",
    "iso:country":"US",
    "sg:address":"792 River St",
    "sg:city":"Ontario",
    "sg:classifiers":[
        {
            "category":"Retail",
            "subcategory":"Repair Shop",
            "type":"Services"
        }
    ],
    "sg:phone":"+1 541 889 7644",
    "sg:postcode":"97914",
    "sg:province":"OR",
    "sg:tags":[
        "welding"
    ],
    "wof:name":"Ontario Welding & Steel Supply",
    "wof:placetype":"venue"
},
  "geometry": {"coordinates":[-116.95998,44.033443],"type":"Point"}
}