{
  "type": "Feature",
  "properties": {
    "iso:country":"US",
    "sg:address":"5901 SW MacAdam Avenue",
    "sg:city":"Portland",
    "sg:classifiers":[
        {
            "category":"Professional",
            "subcategory":"Lawyer & Legal Services",
            "type":"Services"
        }
    ],
    "sg:phone":"+1 503 241 3491",
    "sg:postcode":"97239",
    "sg:province":"OR",
    "wof:name":"Moore Thomas S Atty",
    "wof:placetype":"venue"
},
  "geometry": {"coordinates":[-122.673486,45.481113],"type":"Point"}
}