{
  "type": "Feature",
  "properties": {
    "iso:country":"US",
    "sg:address":"10640 SW Summer Lake Dr",
    "sg:city":"Portland",
    "sg:classifiers":[
        {
            "category":"Building & Trades",
            "subcategory":"Cleaning & Sanitation",
            "type":"Services"
        }
    ],
    "sg:phone":"+1 503 579 0655",
    "sg:postcode":"97223",
    "sg:province":"OR",
    "sg:tags":[
        "repair",
        "maintenance",
        "house"
    ],
    "wof:name":"All Clean House Keeping",
    "wof:placetype":"venue"
},
  "geometry": {"coordinates":[-122.808138,45.44302],"type":"Point"}
}