{
  "type": "Feature",
  "properties": {
    "iso:country":"US",
    "sg:address":"921 SW Morrison Street Suite 220",
    "sg:city":"Portland",
    "sg:classifiers":[
        {
            "category":"Organizations",
            "subcategory":"Non-profit Organization",
            "type":"Services"
        }
    ],
    "sg:phone":"+1 503 226 2588",
    "sg:postcode":"97205",
    "sg:province":"OR",
    "sg:tags":[
        "service/non-profit",
        "community"
    ],
    "sg:website":"www.pdxgmc.org",
    "wof:name":"Portland Gay Men's Chorus",
    "wof:placetype":"venue"
},
  "geometry": {"coordinates":[-122.681318,45.519819],"type":"Point"}
}