{
  "type": "Feature",
  "properties": {
    "iso:country":"US",
    "sg:address":"10602 SE Highway 212",
    "sg:city":"Clackamas",
    "sg:classifiers":[
        {
            "category":"Building & Trades",
            "subcategory":"Locksmith",
            "type":"Services"
        }
    ],
    "sg:phone":"+1 503 764 4362",
    "sg:postcode":"97015",
    "sg:province":"OR",
    "sg:tags":[
        "key"
    ],
    "wof:name":"24Hr 1 Emergency Locksmith",
    "wof:placetype":"venue"
},
  "geometry": {"coordinates":[-122.553853,45.407653],"type":"Point"}
}