{
  "type": "Feature",
  "properties": {
    "addr:full":"37980 Reed Rd Manzanita OR 97131",
    "addr:housenumber":"37980",
    "addr:postcode":"97131",
    "addr:street":"Reed Rd",
    "iso:country":"US",
    "sg:address":"37980 Reed Rd",
    "sg:city":"Manzanita",
    "sg:classifiers":[
        {
            "category":"Education",
            "subcategory":"Library",
            "type":"Public Place"
        }
    ],
    "sg:phone":"+1 503 368 6990",
    "sg:postcode":"97131",
    "sg:province":"OR",
    "sg:tags":[
        "special",
        "interest"
    ],
    "wof:name":"Information Masters Library",
    "wof:placetype":"venue"
},
  "geometry": {"coordinates":[-123.943703,45.731969],"type":"Point"}
}