{
  "type": "Feature",
  "properties": {
    "iso:country":"US",
    "sg:address":"1106 Ivy Ave",
    "sg:city":"Tillamook",
    "sg:classifiers":[
        {
            "category":"Retail",
            "subcategory":"Repair Shop",
            "type":"Services"
        }
    ],
    "sg:phone":"+1 503 842 8678",
    "sg:postcode":"97141",
    "sg:province":"OR",
    "sg:tags":[
        "industrial",
        "machinery",
        "welding",
        "mfg"
    ],
    "wof:name":"M H Welding",
    "wof:placetype":"venue"
},
  "geometry": {"coordinates":[-123.84508700000001,45.450322],"type":"Point"}
}