{
  "type": "Feature",
  "properties": {
    "iso:country":"US",
    "sg:address":"25683 SE Stark St",
    "sg:city":"Troutdale",
    "sg:classifiers":[
        {
            "category":"Retail",
            "subcategory":"Laundry & Dry Cleaning",
            "type":"Services"
        }
    ],
    "sg:phone":"+1 503 674 5860",
    "sg:postcode":"97060",
    "sg:province":"OR",
    "sg:tags":[
        "cleaners"
    ],
    "wof:name":"All Seasons Cleaners",
    "wof:placetype":"venue"
},
  "geometry": {"coordinates":[-122.401138,45.519065],"type":"Point"}
}