{
  "type": "Feature",
  "properties": {
    "addr:full":"15282 SW Teal Blvd Beaverton OR 97007",
    "addr:housenumber":"15282",
    "addr:postcode":"97007",
    "addr:street":"Sw Teal Blvd",
    "iso:country":"US",
    "sg:address":"15282 SW Teal Blvd",
    "sg:city":"Beaverton",
    "sg:classifiers":[
        {
            "category":"Real Estate",
            "subcategory":"Real Estate Operator",
            "type":"Services"
        }
    ],
    "sg:phone":"+1 866 551 5779",
    "sg:postcode":"97007",
    "sg:province":"OR",
    "sg:tags":[
        "apartment"
    ],
    "sg:website":"www.andoverpark.com",
    "wof:name":"Andover Park Apartments",
    "wof:placetype":"venue"
},
  "geometry": {"coordinates":[-122.83207899999999,45.440511],"type":"Point"}
}