{
  "type": "Feature",
  "properties": {
    "addr:full":"23777 SE Howlett Rd Eagle Creek OR 97022",
    "addr:postcode":"23777;97022",
    "addr:street":"Se Howlett Rd",
    "iso:country":"US",
    "sg:address":"23777 SE Howlett Rd",
    "sg:city":"Eagle Creek",
    "sg:classifiers":[
        {
            "category":"Professional",
            "type":"Services"
        }
    ],
    "sg:phone":"+1 503 637 3677",
    "sg:postcode":"97022",
    "sg:province":"OR",
    "wof:name":"Philip N Shaw",
    "wof:placetype":"venue"
},
  "geometry": {"coordinates":[-122.31185499999999,45.352025],"type":"Point"}
}