{
  "type": "Feature",
  "properties": {
    "iso:country":"US",
    "sg:address":"925 NW Camellia Dr",
    "sg:city":"Corvallis",
    "sg:classifiers":[
        {
            "category":"Organizations",
            "subcategory":"Religious Organization",
            "type":"Services"
        }
    ],
    "sg:phone":"+1 541 738 0600",
    "sg:postcode":"97330",
    "sg:province":"OR",
    "sg:tags":[
        "church"
    ],
    "wof:name":"St Martin The Merciful Orthodx",
    "wof:placetype":"venue"
},
  "geometry": {"coordinates":[-123.260057,44.60466],"type":"Point"}
}