{
  "type": "Feature",
  "properties": {
    "iso:country":"US",
    "sg:address":"38757 Camp Creek Rd",
    "sg:city":"Springfield",
    "sg:classifiers":[
        {
            "category":"Building & Trades",
            "subcategory":"Landscaping Services",
            "type":"Services"
        }
    ],
    "sg:phone":"+1 541 736 9861",
    "sg:postcode":"97478",
    "sg:province":"OR",
    "wof:name":"Laughing Duck Landscape Maint",
    "wof:placetype":"venue"
},
  "geometry": {"coordinates":[-122.827174,44.066872],"type":"Point"}
}