{
  "type": "Feature",
  "properties": {
    "iso:country":"US",
    "sg:address":"2056 NW Aloclek Dr",
    "sg:city":"Hillsboro",
    "sg:classifiers":[
        {
            "category":"Building & Trades",
            "subcategory":"Electrical",
            "type":"Services"
        }
    ],
    "sg:phone":"+1 503 690 9107",
    "sg:postcode":"97124",
    "sg:province":"OR",
    "sg:tags":[
        "electrical",
        "contractor"
    ],
    "wof:name":"Diverse",
    "wof:placetype":"venue"
},
  "geometry": {"coordinates":[-122.895446,45.534766],"type":"Point"}
}