{
  "type": "Feature",
  "properties": {
    "iso:country":"US",
    "sg:address":"5672 NW 180th Pl",
    "sg:city":"Portland",
    "sg:classifiers":[
        {
            "category":"Travel",
            "subcategory":"Travel Agent",
            "type":"Entertainment"
        }
    ],
    "sg:phone":"+1 503 439 0426",
    "sg:postcode":"97229",
    "sg:province":"OR",
    "sg:tags":[
        "passenger",
        "transportation",
        "arrangement"
    ],
    "wof:name":"Airshopping Co LLC",
    "wof:placetype":"venue"
},
  "geometry": {"coordinates":[-122.862521,45.561049],"type":"Point"}
}