{
  "type": "Feature",
  "properties": {
    "iso:country":"US",
    "sg:address":"615 E Main St",
    "sg:city":"Cottage Grove",
    "sg:classifiers":[
        {
            "category":"Manufacturing",
            "subcategory":"Printing",
            "type":"Manufacturing & Wholesale Goods"
        }
    ],
    "sg:phone":"+1 541 942 0846",
    "sg:postcode":"97424",
    "sg:province":"OR",
    "sg:tags":[
        "publisher",
        "guide"
    ],
    "wof:name":"Mountain Meadow Enterprises",
    "wof:placetype":"venue"
},
  "geometry": {"coordinates":[-123.061819,43.797195],"type":"Point"}
}