{
  "type": "Feature",
  "properties": {
    "iso:country":"US",
    "sg:address":"25667 SE Stark St",
    "sg:city":"Troutdale",
    "sg:classifiers":[
        {
            "category":"Personal",
            "subcategory":"Beauty Salon",
            "type":"Services"
        }
    ],
    "sg:phone":"+1 503 667 5824",
    "sg:postcode":"97060",
    "sg:province":"OR",
    "sg:tags":[
        "shop"
    ],
    "wof:name":"Supercuts",
    "wof:placetype":"venue"
},
  "geometry": {"coordinates":[-122.401138,45.519065],"type":"Point"}
}