{
  "type": "Feature",
  "properties": {
    "iso:country":"US",
    "sg:address":"7194 SW Hazelfern Rd",
    "sg:city":"Portland",
    "sg:classifiers":[
        {
            "category":"Restaurant",
            "type":"Food & Drink"
        }
    ],
    "sg:phone":"+1 503 726 0308",
    "sg:postcode":"97224",
    "sg:province":"OR",
    "sg:tags":[
        "sushi",
        "bar"
    ],
    "sg:website":"www.sushilandusa.com",
    "wof:name":"Sushi Land",
    "wof:placetype":"venue"
},
  "geometry": {"coordinates":[-122.750513,45.394209],"type":"Point"}
}