{
  "type": "Feature",
  "properties": {
    "iso:country":"US",
    "sg:address":"1040 Tyinn St Ste 1",
    "sg:city":"Eugene",
    "sg:classifiers":[
        {
            "category":"Shopping",
            "subcategory":"Books",
            "type":"Retail Goods"
        },
        {
            "category":"Shopping",
            "type":"Retail Goods"
        }
    ],
    "sg:phone":"+1 541 338 8882",
    "sg:postcode":"97402",
    "sg:province":"OR",
    "sg:tags":[
        "bible",
        "religious"
    ],
    "wof:name":"Christian Outlet",
    "wof:placetype":"venue"
},
  "geometry": {"coordinates":[-123.136792,44.048769],"type":"Point"}
}