{
  "type": "Feature",
  "properties": {
    "iso:country":"US",
    "sg:address":"1088 S Main St",
    "sg:city":"Prineville",
    "sg:classifiers":[
        {
            "category":"Retail",
            "subcategory":"Repair Shop",
            "type":"Services"
        }
    ],
    "sg:phone":"+1 541 447 1515",
    "sg:postcode":"97754",
    "sg:province":"OR",
    "wof:name":"Rimrock Marine",
    "wof:placetype":"venue"
},
  "geometry": {"coordinates":[-120.84692699999999,44.294797],"type":"Point"}
}