{
  "type": "Feature",
  "properties": {
    "iso:country":"US",
    "sg:address":"5695 SE International Way Ste Ab",
    "sg:city":"Portland",
    "sg:classifiers":[
        {
            "category":"Manufacturing",
            "subcategory":"Metals",
            "type":"Manufacturing & Wholesale Goods"
        },
        {
            "category":"Building & Trades",
            "subcategory":"Construction",
            "type":"Services"
        }
    ],
    "sg:phone":"+1 503 652 5850",
    "sg:postcode":"97222",
    "sg:province":"OR",
    "sg:tags":[
        "finisher",
        "metals-pre-coated"
    ],
    "wof:name":"North American Carbide & Corrosion",
    "wof:placetype":"venue"
},
  "geometry": {"coordinates":[-122.60573100000001,45.431052],"type":"Point"}
}