{
  "type": "Feature",
  "properties": {
    "addr:full":"755 Water Ave NE Albany OR 97321",
    "addr:housenumber":"755",
    "addr:postcode":"97321",
    "addr:street":"Water Ave Ne",
    "iso:country":"US",
    "sg:address":"755 Water Ave NE",
    "sg:city":"Albany",
    "sg:classifiers":[
        {
            "category":"Retail",
            "subcategory":"Auto Repair",
            "type":"Services"
        }
    ],
    "sg:phone":"+1 541 926 6709",
    "sg:postcode":"97321",
    "sg:province":"OR",
    "sg:tags":[
        "alternator",
        "automotive",
        "rebuilds",
        "starter"
    ],
    "wof:name":"Titan Rebuilders Co Inc",
    "wof:placetype":"venue"
},
  "geometry": {"coordinates":[-123.09708000000001,44.63917],"type":"Point"}
}