{
  "type": "Feature",
  "properties": {
    "iso:country":"US",
    "sg:address":"35231 Kings Valley Hwy",
    "sg:city":"Philomath",
    "sg:classifiers":[
        {
            "category":"Manufacturing",
            "subcategory":"Buildings",
            "type":"Manufacturing & Wholesale Goods"
        },
        {
            "category":"Building & Trades",
            "subcategory":"Construction",
            "type":"Services"
        }
    ],
    "sg:phone":"+1 541 929 6216",
    "sg:postcode":"97370",
    "sg:province":"OR",
    "sg:tags":[
        "home",
        "builder",
        "contractor"
    ],
    "wof:name":"Steven Oien",
    "wof:placetype":"venue"
},
  "geometry": {"coordinates":[-123.427334,44.594902],"type":"Point"}
}