{
  "type": "Feature",
  "properties": {
    "iso:country":"US",
    "sg:address":"1130 Hazel St",
    "sg:city":"Central Point",
    "sg:classifiers":[
        {
            "category":"Organizations",
            "subcategory":"Community Association",
            "type":"Services"
        }
    ],
    "sg:phone":"+1 541 664 4240",
    "sg:postcode":"97502",
    "sg:province":"OR",
    "sg:tags":[
        "fraternal"
    ],
    "wof:name":"IOOF",
    "wof:placetype":"venue"
},
  "geometry": {"coordinates":[-122.913513,42.382542],"type":"Point"}
}