{
  "type": "Feature",
  "properties": {
    "iso:country":"US",
    "sg:address":"571 NE B St",
    "sg:city":"Bend",
    "sg:classifiers":[
        {
            "category":"Home & Garden",
            "subcategory":"Household Appliances",
            "type":"Retail Goods"
        }
    ],
    "sg:phone":"+1 541 382 6223",
    "sg:postcode":"97741",
    "sg:province":"OR",
    "wof:name":"Johnson Brothers TV & Appl",
    "wof:placetype":"venue"
},
  "geometry": {"coordinates":[-121.11843,44.635821],"type":"Point"}
}