{
  "type": "Feature",
  "properties": {
    "addr:full":"8205 SE Harney St Portland OR 97266",
    "addr:housenumber":"8205",
    "addr:postcode":"97266",
    "addr:street":"Se Harney St",
    "iso:country":"US",
    "sg:address":"8205 SE Harney St",
    "sg:city":"Portland",
    "sg:classifiers":[
        {
            "category":"Autos & Motor Vehicles",
            "subcategory":"Recreational Vehicle Sales",
            "type":"Retail Goods"
        }
    ],
    "sg:phone":"+1 503 771 6915",
    "sg:postcode":"97266",
    "sg:province":"OR",
    "wof:name":"OK Enterprises",
    "wof:placetype":"venue"
},
  "geometry": {"coordinates":[-122.577815,45.463362],"type":"Point"}
}