{
  "type": "Feature",
  "properties": {
    "addr:full":"1526 Broadway St NE Salem OR 97303",
    "addr:housenumber":"1526",
    "addr:postcode":"97303",
    "addr:street":"Broadway St Ne",
    "iso:country":"US",
    "sg:address":"1526 Broadway St NE",
    "sg:city":"Salem",
    "sg:classifiers":[
        {
            "category":"Retail",
            "subcategory":"Repair Shop",
            "type":"Services"
        }
    ],
    "sg:phone":"+1 503 393 4144",
    "sg:postcode":"97303",
    "sg:province":"OR",
    "sg:tags":[
        "lock",
        "locksmith"
    ],
    "wof:name":"Joe's Safe Lock & Security",
    "wof:placetype":"venue"
},
  "geometry": {"coordinates":[-123.02975499999999,44.954256],"type":"Point"}
}