{
  "type": "Feature",
  "properties": {
    "addr:full":"12800 Dead Indian Memorial Rd Ashland OR 97520",
    "addr:housenumber":"12800",
    "addr:postcode":"97520",
    "addr:street":"Dead Indian Memorial Rd",
    "iso:country":"US",
    "sg:address":"12800 Dead Indian Memorial Rd",
    "sg:city":"Ashland",
    "sg:classifiers":[
        {
            "category":"Professional",
            "type":"Services"
        }
    ],
    "sg:phone":"+1 541 488 0809",
    "sg:postcode":"97520",
    "sg:province":"OR",
    "sg:tags":[
        "establishment"
    ],
    "wof:name":"Foundation For Meditative Stds",
    "wof:placetype":"venue"
},
  "geometry": {"coordinates":[-122.50926,42.250068],"type":"Point"}
}