{
  "type": "Feature",
  "properties": {
    "iso:country":"US",
    "sg:address":"6161 SW Canal Blvd",
    "sg:city":"Redmond",
    "sg:classifiers":[
        {
            "category":"Building & Trades",
            "subcategory":"Construction",
            "type":"Services"
        }
    ],
    "sg:phone":"+1 541 504 8937",
    "sg:postcode":"97756",
    "sg:province":"OR",
    "sg:tags":[
        "house"
    ],
    "wof:name":"Ronald Barham",
    "wof:placetype":"venue"
},
  "geometry": {"coordinates":[-121.230046,44.219745],"type":"Point"}
}