{
  "type": "Feature",
  "properties": {
    "iso:country":"US",
    "sg:address":"1127 S Broadway",
    "sg:city":"Coos Bay",
    "sg:classifiers":[
        {
            "category":"Manufacturing",
            "subcategory":"Tools & Machinery",
            "type":"Manufacturing & Wholesale Goods"
        }
    ],
    "sg:phone":"+1 541 267 2325",
    "sg:postcode":"97420",
    "sg:province":"OR",
    "sg:tags":[
        "industrial",
        "truck"
    ],
    "wof:name":"All Coast Transportation",
    "wof:placetype":"venue"
},
  "geometry": {"coordinates":[-124.213392,43.355967],"type":"Point"}
}