{
  "type": "Feature",
  "properties": {
    "addr:full":"60 Division Ave Eugene OR 97404",
    "addr:housenumber":"60",
    "addr:postcode":"97404",
    "addr:street":"Division Ave",
    "iso:country":"US",
    "sg:address":"60 Division Ave",
    "sg:city":"Eugene",
    "sg:classifiers":[
        {
            "category":"Banks & Credit Unions",
            "subcategory":"Bank",
            "type":"Services"
        },
        {
            "category":"Banks & Credit Unions",
            "subcategory":"Financial Services",
            "type":"Services"
        }
    ],
    "sg:phone":"+1 541 465 3640",
    "sg:postcode":"97404",
    "sg:province":"OR",
    "sg:tags":[
        "commercial",
        "loan",
        "saving"
    ],
    "sg:website":"https://www.chase.com/",
    "wof:name":"CHASE Bank",
    "wof:placetype":"venue"
},
  "geometry": {"coordinates":[-123.126167,44.099015],"type":"Point"}
}