{
  "type": "Feature",
  "properties": {
    "addr:full":"2299 Butte Falls Rd Eagle Point OR 97524",
    "addr:housenumber":"2299",
    "addr:postcode":"97524",
    "addr:street":"Butte Falls Rd",
    "iso:country":"US",
    "sg:address":"2299 Butte Falls Rd",
    "sg:city":"Eagle Point",
    "sg:classifiers":[
        {
            "category":"Retail",
            "subcategory":"Animal Services",
            "type":"Services"
        }
    ],
    "sg:phone":"+1 541 826 9328",
    "sg:postcode":"97524",
    "sg:province":"OR",
    "wof:name":"Benson Ranches",
    "wof:placetype":"venue"
},
  "geometry": {"coordinates":[-122.797374,42.509763],"type":"Point"}
}