{
  "type": "Feature",
  "properties": {
    "iso:country":"US",
    "sg:address":"528 NE Franklin Ave",
    "sg:city":"Bend",
    "sg:classifiers":[
        {
            "category":"Building & Trades",
            "subcategory":"Construction",
            "type":"Services"
        }
    ],
    "sg:phone":"+1 541 923 5453",
    "sg:postcode":"97701",
    "sg:province":"OR",
    "sg:tags":[
        "roofing",
        "contractor"
    ],
    "wof:name":"S&K Metal Products",
    "wof:placetype":"venue"
},
  "geometry": {"coordinates":[-121.297668,44.056031],"type":"Point"}
}