{
  "type": "Feature",
  "properties": {
    "iso:country":"US",
    "sg:address":"19401 SW Boones Ferry Rd",
    "sg:city":"Tualatin",
    "sg:classifiers":[
        {
            "category":"Personal",
            "subcategory":"Shoe Repair & Shine",
            "type":"Services"
        }
    ],
    "sg:phone":"+1 503 691 9393",
    "sg:postcode":"97062",
    "sg:province":"OR",
    "sg:tags":[
        "parlor",
        "shoes"
    ],
    "wof:name":"Busy Shoes",
    "wof:placetype":"venue"
},
  "geometry": {"coordinates":[-122.76442400000001,45.380083],"type":"Point"}
}