{
  "type": "Feature",
  "properties": {
    "addr:full":"1786 SW Montmore Way Troutdale OR 97060",
    "addr:housenumber":"1786",
    "addr:postcode":"97060",
    "addr:street":"Sw Montmore Way",
    "iso:country":"US",
    "sg:address":"1786 SW Montmore Way",
    "sg:city":"Troutdale",
    "sg:classifiers":[
        {
            "category":"Professional",
            "subcategory":"Computer Services",
            "type":"Services"
        }
    ],
    "sg:phone":"+1 503 669 7316",
    "sg:postcode":"97060",
    "sg:province":"OR",
    "sg:tags":[
        "datum"
    ],
    "wof:name":"Advanced Data Services",
    "wof:placetype":"venue"
},
  "geometry": {"coordinates":[-122.404585,45.53397],"type":"Point"}
}