{
  "type": "Feature",
  "properties": {
    "addr:full":"7280 NW Butler St Hillsboro OR 97124",
    "addr:housenumber":"7280",
    "addr:postcode":"97124",
    "addr:street":"Nw Butler St",
    "iso:country":"US",
    "sg:address":"7280 NW Butler St",
    "sg:city":"Hillsboro",
    "sg:classifiers":[
        {
            "category":"Shopping",
            "subcategory":"Bicycles & Sporting Goods",
            "type":"Retail Goods"
        }
    ],
    "sg:phone":"+1 503 846 1814",
    "sg:postcode":"97124",
    "sg:province":"OR",
    "wof:name":"G I Joes Sports & Auto Stores",
    "wof:placetype":"venue"
},
  "geometry": {"coordinates":[-122.90202600000001,45.53725],"type":"Point"}
}