{
  "type": "Feature",
  "properties": {
    "addr:full":"88267 Territorial Rd Veneta OR 97487",
    "addr:postcode":"88267;97487",
    "addr:street":"Territorial Rd",
    "iso:country":"US",
    "sg:address":"88267 Territorial Rd",
    "sg:city":"Veneta",
    "sg:classifiers":[
        {
            "category":"Personal",
            "type":"Services"
        }
    ],
    "sg:phone":"+1 541 935 6000",
    "sg:postcode":"97487",
    "sg:province":"OR",
    "sg:tags":[
        "program",
        "physical",
        "exercise",
        "fitness"
    ],
    "wof:name":"Veneta Health Club",
    "wof:placetype":"venue"
},
  "geometry": {"coordinates":[-123.35166,44.053164],"type":"Point"}
}