{
  "type": "Feature",
  "properties": {
    "iso:country":"US",
    "sg:address":"304 NE 80th Ave",
    "sg:city":"Portland",
    "sg:classifiers":[
        {
            "category":"Organizations",
            "subcategory":"Religious Organization",
            "type":"Services"
        }
    ],
    "sg:phone":"+1 503 255 2791",
    "sg:postcode":"97213",
    "sg:province":"OR",
    "sg:tags":[
        "church"
    ],
    "wof:name":"Jehovah's Witnesses",
    "wof:placetype":"venue"
},
  "geometry": {"coordinates":[-122.581384,45.525228],"type":"Point"}
}