{
  "type": "Feature",
  "properties": {
    "addr:full":"543 SW Ash St Dallas OR 97338",
    "addr:housenumber":"543",
    "addr:postcode":"97338",
    "addr:street":"Sw Ash St",
    "iso:country":"US",
    "sg:address":"543 SW Ash St",
    "sg:city":"Dallas",
    "sg:classifiers":[
        {
            "category":"Retail",
            "subcategory":"Repair Shop",
            "type":"Services"
        }
    ],
    "sg:phone":"+1 503 623 3161",
    "sg:postcode":"97338",
    "sg:province":"OR",
    "sg:tags":[
        "house",
        "construction",
        "electrical"
    ],
    "wof:name":"Handyman Repair",
    "wof:placetype":"venue"
},
  "geometry": {"coordinates":[-123.32399599999999,44.91736],"type":"Point"}
}