{
  "type": "Feature",
  "properties": {
    "addr:full":"1333 SE 28th Ave Portland OR 97214",
    "addr:housenumber":"1333",
    "addr:postcode":"97214",
    "addr:street":"Se 28Th Ave",
    "iso:country":"US",
    "sg:address":"1333 SE 28th Ave",
    "sg:city":"Portland",
    "sg:classifiers":[
        {
            "category":"Organizations",
            "subcategory":"Religious Organization",
            "type":"Services"
        }
    ],
    "sg:phone":"+1 503 232 5253",
    "sg:postcode":"97214",
    "sg:province":"OR",
    "wof:name":"Epworth United Methdst Church",
    "wof:placetype":"venue"
},
  "geometry": {"coordinates":[-122.63720000000001,45.513106],"type":"Point"}
}