{
  "type": "Feature",
  "properties": {
    "addr:full":"22263 NW Imbrie Dr Hillsboro OR 97124",
    "addr:housenumber":"22263",
    "addr:postcode":"97124",
    "addr:street":"Nw Imbrie Dr",
    "iso:country":"US",
    "sg:address":"22263 NW Imbrie Dr",
    "sg:city":"Hillsboro",
    "sg:classifiers":[
        {
            "category":"Fast Food",
            "type":"Food & Drink"
        },
        {
            "category":"Restaurant",
            "type":"Food & Drink"
        }
    ],
    "sg:phone":"+1 503 640 5943",
    "sg:postcode":"97124",
    "sg:province":"OR",
    "sg:tags":[
        "seafood"
    ],
    "sg:website":"http://www.ljsilvers.com",
    "wof:name":"Long John Silver's",
    "wof:placetype":"venue"
},
  "geometry": {"coordinates":[-122.9064,45.549864],"type":"Point"}
}