{
  "type": "Feature",
  "properties": {
    "iso:country":"US",
    "sg:address":"3265 Blackthorn Dr",
    "sg:city":"Medford",
    "sg:classifiers":[
        {
            "category":"Building & Trades",
            "subcategory":"Landscaping Services",
            "type":"Services"
        }
    ],
    "sg:phone":"+1 541 779 6067",
    "sg:postcode":"97504",
    "sg:province":"OR",
    "wof:name":"Michael Bartlett",
    "wof:placetype":"venue"
},
  "geometry": {"coordinates":[-122.84906100000001,42.364207],"type":"Point"}
}