{
  "type": "Feature",
  "properties": {
    "iso:country":"US",
    "sg:address":"314 NW 4th St",
    "sg:city":"Grants Pass",
    "sg:classifiers":[
        {
            "category":"Professional",
            "type":"Services"
        }
    ],
    "sg:phone":"+1 541 471 7143",
    "sg:postcode":"97526",
    "sg:province":"OR",
    "sg:tags":[
        "establishment"
    ],
    "wof:name":"Indian Center So Oregon",
    "wof:placetype":"venue"
},
  "geometry": {"coordinates":[-123.328313,42.442172],"type":"Point"}
}