{
  "type": "Feature",
  "properties": {
    "addr:full":"22857 SW Norton St Sherwood OR 97140",
    "addr:housenumber":"22857",
    "addr:postcode":"97140",
    "addr:street":"Sw Norton St",
    "iso:country":"US",
    "sg:address":"22857 SW Norton St",
    "sg:city":"Sherwood",
    "sg:classifiers":[
        {
            "category":"Restaurant",
            "type":"Food & Drink"
        }
    ],
    "sg:phone":"+1 503 625 4408",
    "sg:postcode":"97140",
    "sg:province":"OR",
    "sg:tags":[
        "asian",
        "pan",
        "japanese"
    ],
    "wof:name":"Japanese Garden Specialty",
    "wof:placetype":"venue"
},
  "geometry": {"coordinates":[-122.833752,45.354367],"type":"Point"}
}