{
  "type": "Feature",
  "properties": {
    "iso:country":"US",
    "sg:address":"624 Main St",
    "sg:city":"Oregon City",
    "sg:classifiers":[
        {
            "category":"Wholesale",
            "subcategory":"Groceries",
            "type":"Manufacturing & Wholesale Goods"
        }
    ],
    "sg:phone":"+1 503 650 8342",
    "sg:postcode":"97045",
    "sg:province":"OR",
    "wof:name":"Bridgeview Beer & Wine Supply",
    "wof:placetype":"venue"
},
  "geometry": {"coordinates":[-122.609087,45.357409],"type":"Point"}
}