{
  "type": "Feature",
  "properties": {
    "iso:country":"US",
    "sg:address":"705 Ave Q",
    "sg:city":"Seaside",
    "sg:classifiers":[
        {
            "category":"Retail",
            "subcategory":"Car Wash",
            "type":"Services"
        }
    ],
    "sg:phone":"+1 503 738 5639",
    "sg:postcode":"97138",
    "sg:province":"OR",
    "sg:tags":[
        "polishing",
        "washing"
    ],
    "wof:name":"Herb's KWIK Kleen Car Wash",
    "wof:placetype":"venue"
},
  "geometry": {"coordinates":[-123.925273,45.983848],"type":"Point"}
}