{
  "type": "Feature",
  "properties": {
    "addr:full":"7130 Smullin Dr Mt Hood Parkdale OR 97041",
    "addr:postcode":"7130;97041",
    "addr:street":"Smullin Dr Mt",
    "iso:country":"US",
    "sg:address":"7130 Smullin Dr",
    "sg:city":"Mt Hood Parkdale",
    "sg:classifiers":[
        {
            "category":"Farming",
            "subcategory":"Orchard",
            "type":"Manufacturing & Wholesale Goods"
        }
    ],
    "sg:phone":"+1 541 352 7123",
    "sg:postcode":"97041",
    "sg:province":"OR",
    "sg:tags":[
        "grove",
        "management"
    ],
    "sg:website":"www.mthoodorganicfarms.com",
    "wof:name":"Mt Hood Organic Farms",
    "wof:placetype":"venue"
},
  "geometry": {"coordinates":[-121.561532,45.519696],"type":"Point"}
}