{
  "type": "Feature",
  "properties": {
    "addr:full":"4004 SW Kelly Ave Portland OR 97239",
    "addr:housenumber":"4004",
    "addr:postcode":"97239",
    "addr:street":"Sw Kelly Ave",
    "iso:country":"US",
    "sg:address":"4004 SW Kelly Ave",
    "sg:city":"Portland",
    "sg:classifiers":[
        {
            "category":"Personal",
            "subcategory":"Adult",
            "type":"Services"
        }
    ],
    "sg:phone":"+1 503 224 7744",
    "sg:postcode":"97239",
    "sg:province":"OR",
    "sg:tags":[
        "midwife"
    ],
    "wof:name":"Susan M Roberts, ND",
    "wof:placetype":"venue"
},
  "geometry": {"coordinates":[-122.674648,45.494242],"type":"Point"}
}