{
  "type": "Feature",
  "properties": {
    "iso:country":"US",
    "sg:address":"34480 SE Colorado Rd",
    "sg:city":"Sandy",
    "sg:classifiers":[
        {
            "category":"Wholesale",
            "subcategory":"Groceries",
            "type":"Manufacturing & Wholesale Goods"
        }
    ],
    "sg:phone":"+1 503 668 0057",
    "sg:postcode":"97055",
    "sg:province":"OR",
    "sg:tags":[
        "distributor"
    ],
    "wof:name":"Pacific Standard Distributors",
    "wof:placetype":"venue"
},
  "geometry": {"coordinates":[-122.308683,45.393075],"type":"Point"}
}