{
  "type": "Feature",
  "properties": {
    "addr:full":"2835 Tomahawk Ln Eugene OR 97401",
    "addr:housenumber":"2835",
    "addr:postcode":"97401",
    "addr:street":"Tomahawk Ln",
    "iso:country":"US",
    "sg:address":"2835 Tomahawk Ln",
    "sg:city":"Eugene",
    "sg:classifiers":[
        {
            "category":"Structure",
            "subcategory":"Office Building",
            "type":"Public Place"
        }
    ],
    "sg:phone":"+1 541 344 2896",
    "sg:postcode":"97401",
    "sg:province":"OR",
    "sg:tags":[
        "park"
    ],
    "wof:name":"Baker Properties Limited Partnership",
    "wof:placetype":"venue"
},
  "geometry": {"coordinates":[-123.06644799999999,44.071539],"type":"Point"}
}