{
  "type": "Feature",
  "properties": {
    "addr:full":"42500 E Larch Mountain Rd Corbett OR 97019",
    "addr:housenumber":"42500",
    "addr:postcode":"97019",
    "addr:street":"E Larch Mountain Rd",
    "iso:country":"US",
    "sg:address":"42500 E Larch Mountain Rd",
    "sg:city":"Corbett",
    "sg:classifiers":[
        {
            "category":"Social Services",
            "type":"Services"
        }
    ],
    "sg:phone":"+1 503 695 5813",
    "sg:postcode":"97019",
    "sg:province":"OR",
    "sg:tags":[
        "youth",
        "organization",
        "center"
    ],
    "wof:name":"Turning Point Program",
    "wof:placetype":"venue"
},
  "geometry": {"coordinates":[-122.22915399999999,45.521928],"type":"Point"}
}