{
  "type": "Feature",
  "properties": {
    "iso:country":"US",
    "sg:address":"1008 SW Morrison St",
    "sg:city":"Portland",
    "sg:classifiers":[
        {
            "category":"Personal",
            "subcategory":"Beauty Salon",
            "type":"Services"
        }
    ],
    "sg:phone":"+1 503 804 0147",
    "sg:postcode":"97205",
    "sg:province":"OR",
    "wof:name":"Kelly & Co",
    "wof:placetype":"venue"
},
  "geometry": {"coordinates":[-122.68309000000001,45.520191],"type":"Point"}
}