{
  "type": "Feature",
  "properties": {
    "iso:country":"US",
    "sg:address":"6710 SW 203rd Ct",
    "sg:city":"Beaverton",
    "sg:classifiers":[
        {
            "category":"Professional",
            "subcategory":"Management & Consulting",
            "type":"Services"
        }
    ],
    "sg:phone":"+1 503 201 4428",
    "sg:postcode":"97007",
    "sg:province":"OR",
    "sg:tags":[
        "consultant"
    ],
    "sg:website":"http://www.fecconsulting.com",
    "wof:name":"Fec Consulting",
    "wof:placetype":"venue"
},
  "geometry": {"coordinates":[-122.885696,45.471287],"type":"Point"}
}