{
  "type": "Feature",
  "properties": {
    "iso:country":"US",
    "sg:address":"4872 Grant Rd",
    "sg:city":"Central Point",
    "sg:classifiers":[
        {
            "category":"Building & Trades",
            "subcategory":"Plumbing",
            "type":"Services"
        }
    ],
    "sg:phone":"+1 541 664 3073",
    "sg:postcode":"97502",
    "sg:province":"OR",
    "sg:tags":[
        "contractor"
    ],
    "wof:name":"Robert J Brandes Plumbing",
    "wof:placetype":"venue"
},
  "geometry": {"coordinates":[-122.936432,42.384404],"type":"Point"}
}