{
  "type": "Feature",
  "properties": {
    "addr:full":"3338 SE 84th Ave Portland OR 97266",
    "addr:housenumber":"3338",
    "addr:postcode":"97266",
    "addr:street":"Se 84Th Ave",
    "iso:country":"US",
    "sg:address":"3338 SE 84th Ave",
    "sg:city":"Portland",
    "sg:classifiers":[
        {
            "category":"Professional",
            "type":"Services"
        }
    ],
    "sg:phone":"+1 503 294 1518",
    "sg:postcode":"97266",
    "sg:province":"OR",
    "wof:name":"C Michael Services",
    "wof:placetype":"venue"
},
  "geometry": {"coordinates":[-122.57622499999999,45.498472],"type":"Point"}
}