{
  "type": "Feature",
  "properties": {
    "iso:country":"US",
    "sg:address":"3770 Market St NE",
    "sg:city":"Salem",
    "sg:classifiers":[
        {
            "category":"Retail",
            "subcategory":"Repair Shop",
            "type":"Services"
        }
    ],
    "sg:phone":"+1 503 364 8888",
    "sg:postcode":"97301",
    "sg:province":"OR",
    "sg:tags":[
        "picture",
        "frame",
        "framing",
        "store"
    ],
    "wof:name":"Beards Frame Shoppes",
    "wof:placetype":"venue"
},
  "geometry": {"coordinates":[-122.98583000000001,44.950225],"type":"Point"}
}