{
  "type": "Feature",
  "properties": {
    "iso:country":"US",
    "sg:address":"1601 State Hwy 99 N",
    "sg:city":"Eugene",
    "sg:classifiers":[
        {
            "category":"Freight",
            "type":"Transportation"
        }
    ],
    "sg:phone":"+1 541 688 3835",
    "sg:postcode":"97402",
    "sg:province":"OR",
    "sg:tags":[
        "special",
        "general"
    ],
    "wof:name":"Central Self Storage",
    "wof:placetype":"venue"
},
  "geometry": {"coordinates":[-123.151218,44.079914],"type":"Point"}
}