{
  "type": "Feature",
  "properties": {
    "addr:full":"1011 Jerome Ave Astoria OR 97103",
    "addr:housenumber":"1011",
    "addr:postcode":"97103",
    "addr:street":"Jerome Ave",
    "iso:country":"US",
    "sg:address":"1011 Jerome Ave",
    "sg:city":"Astoria",
    "sg:classifiers":[
        {
            "category":"Professional",
            "subcategory":"Management & Consulting",
            "type":"Services"
        }
    ],
    "sg:phone":"+1 503 282 4718",
    "sg:postcode":"97103",
    "sg:province":"OR",
    "sg:tags":[
        "consultant",
        "training"
    ],
    "sg:website":"http://www.visionrealization.com",
    "wof:name":"Www Visionrealization Co",
    "wof:placetype":"venue"
},
  "geometry": {"coordinates":[-123.83281700000001,46.184119],"type":"Point"}
}