{
  "type": "Feature",
  "properties": {
    "addr:full":"23440 SE Stark St Gresham OR 97030",
    "addr:postcode":"23440;97030",
    "addr:street":"Se Stark St",
    "iso:country":"US",
    "sg:address":"23440 SE Stark St",
    "sg:city":"Gresham",
    "sg:classifiers":[
        {
            "category":"Health Services",
            "subcategory":"Chiropractor",
            "type":"Services"
        }
    ],
    "sg:phone":"+1 503 661 3930",
    "sg:postcode":"97030",
    "sg:province":"OR",
    "wof:name":"Olympic Chiropractic Center",
    "wof:placetype":"venue"
},
  "geometry": {"coordinates":[-122.421997,45.519001],"type":"Point"}
}