{
  "type": "Feature",
  "properties": {
    "addr:full":"11150 Kings Valley Hwy Monmouth OR 97361",
    "addr:housenumber":"11150",
    "addr:postcode":"97361",
    "addr:street":"Kings Valley Hwy",
    "iso:country":"US",
    "sg:address":"11150 Kings Valley Hwy",
    "sg:city":"Monmouth",
    "sg:classifiers":[
        {
            "category":"Shopping",
            "type":"Retail Goods"
        }
    ],
    "sg:phone":"+1 503 838 0576",
    "sg:postcode":"97361",
    "sg:province":"OR",
    "sg:tags":[
        "bird"
    ],
    "sg:website":"www.avianacres.com",
    "wof:name":"Avian Acres",
    "wof:placetype":"venue"
},
  "geometry": {"coordinates":[-123.418571,44.772854],"type":"Point"}
}