{
  "type": "Feature",
  "properties": {
    "iso:country":"US",
    "sg:address":"7901 Old Hwy 99 N",
    "sg:city":"Roseburg",
    "sg:classifiers":[
        {
            "category":"Freight",
            "type":"Transportation"
        }
    ],
    "sg:phone":"+1 541 672 2299",
    "sg:postcode":"97470",
    "sg:province":"OR",
    "sg:tags":[
        "marina",
        "operation",
        "ware",
        "special",
        "general"
    ],
    "wof:name":"Supreme Storage",
    "wof:placetype":"venue"
},
  "geometry": {"coordinates":[-123.346054,43.310055],"type":"Point"}
}