{
  "type": "Feature",
  "properties": {
    "addr:full":"301 E Main St Silverton OR 97381",
    "addr:housenumber":"301",
    "addr:postcode":"97381",
    "addr:street":"E Main St",
    "iso:country":"US",
    "sg:address":"301 E Main St",
    "sg:city":"Silverton",
    "sg:classifiers":[
        {
            "category":"Shopping",
            "subcategory":"Used Merchandise",
            "type":"Retail Goods"
        }
    ],
    "sg:phone":"+1 503 873 7362",
    "sg:postcode":"97381",
    "sg:province":"OR",
    "wof:name":"Clothes Garden",
    "wof:placetype":"venue"
},
  "geometry": {"coordinates":[-122.78098,45.005939],"type":"Point"}
}