{
  "type": "Feature",
  "properties": {
    "addr:full":"56666 Old Portland Rd Warren OR 97053",
    "addr:housenumber":"56666",
    "addr:postcode":"97053",
    "addr:street":"Old Portland Rd",
    "iso:country":"US",
    "sg:address":"56666 Old Portland Rd",
    "sg:city":"Warren",
    "sg:classifiers":[
        {
            "category":"Freight",
            "type":"Transportation"
        }
    ],
    "sg:phone":"+1 503 706 5385",
    "sg:postcode":"97053",
    "sg:province":"OR",
    "sg:tags":[
        "operator",
        "trucking"
    ],
    "wof:name":"Goodnight Transport Service",
    "wof:placetype":"venue"
},
  "geometry": {"coordinates":[-122.849575,45.81705],"type":"Point"}
}