{
  "type": "Feature",
  "properties": {
    "addr:full":"1242 SW Highland Ave Redmond OR 97756",
    "addr:housenumber":"1242",
    "addr:postcode":"97756",
    "addr:street":"Sw Highland Ave",
    "iso:country":"US",
    "sg:address":"1242 SW Highland Ave",
    "sg:city":"Redmond",
    "sg:classifiers":[
        {
            "category":"Food & Beverages",
            "subcategory":"Groceries & Convenience Stores",
            "type":"Retail Goods"
        }
    ],
    "sg:phone":"+1 541 548 3325",
    "sg:postcode":"97756",
    "sg:province":"OR",
    "wof:name":"Us Market 190",
    "wof:placetype":"venue"
},
  "geometry": {"coordinates":[-121.181264,44.269606],"type":"Point"}
}