{
  "type": "Feature",
  "properties": {
    "addr:full":"5331 SW MacAdam Avenue Portland OR 97239",
    "addr:housenumber":"5331",
    "addr:postcode":"97239",
    "addr:street":"Sw Macadam Avenue",
    "iso:country":"US",
    "sg:address":"5331 SW MacAdam Avenue",
    "sg:city":"Portland",
    "sg:classifiers":[
        {
            "category":"Home & Garden",
            "subcategory":"Furniture",
            "type":"Retail Goods"
        }
    ],
    "sg:phone":"+1 503 248 0359",
    "sg:postcode":"97239",
    "sg:province":"OR",
    "sg:tags":[
        "store"
    ],
    "wof:name":"Pier One Imports",
    "wof:placetype":"venue"
},
  "geometry": {"coordinates":[-122.67503000000001,45.484633],"type":"Point"}
}