{
  "type": "Feature",
  "properties": {
    "iso:country":"US",
    "sg:address":"18125 SE McLoughlin Boulevard",
    "sg:city":"Portland",
    "sg:classifiers":[
        {
            "category":"Home & Garden",
            "subcategory":"Furniture",
            "type":"Retail Goods"
        }
    ],
    "sg:phone":"+1 503 659 5989",
    "sg:postcode":"97267",
    "sg:province":"OR",
    "sg:tags":[
        "store"
    ],
    "wof:name":"Jer-Bear's Mattress Warehouse",
    "wof:placetype":"venue"
},
  "geometry": {"coordinates":[-122.613004,45.3916],"type":"Point"}
}