{
  "type": "Feature",
  "properties": {
    "iso:country":"US",
    "sg:address":"657 American Dr",
    "sg:city":"Halsey",
    "sg:classifiers":[
        {
            "category":"Place Of Worship",
            "subcategory":"Church",
            "type":"Public Place"
        },
        {
            "category":"Place Of Worship",
            "type":"Public Place"
        },
        {
            "category":"Organizations",
            "subcategory":"Religious Organization",
            "type":"Services"
        }
    ],
    "sg:phone":"+1 541 369 2639",
    "sg:postcode":"97348",
    "sg:province":"OR",
    "sg:tags":[
        "god",
        "god-independent",
        "churches-assemblies"
    ],
    "wof:name":"Central Valley Church",
    "wof:placetype":"venue"
},
  "geometry": {"coordinates":[-123.113747,44.389035],"type":"Point"}
}