{
  "type": "Feature",
  "properties": {
    "iso:country":"US",
    "sg:address":"1740 Salem Industrial Dr NE",
    "sg:city":"Salem",
    "sg:classifiers":[
        {
            "category":"Professional",
            "type":"Services"
        }
    ],
    "sg:phone":"+1 503 363 6213",
    "sg:postcode":"97301",
    "sg:province":"OR",
    "wof:name":"Rtr Services",
    "wof:placetype":"venue"
},
  "geometry": {"coordinates":[-123.00861,44.97453],"type":"Point"}
}