{
  "type": "Feature",
  "properties": {
    "addr:full":"36765 Highway 26 Sandy OR 97055",
    "addr:housenumber":"36765",
    "addr:postcode":"97055",
    "addr:street":"Highway 26",
    "iso:country":"US",
    "sg:address":"36765 Highway 26",
    "sg:city":"Sandy",
    "sg:phone":"+1 503 668 4390",
    "sg:postcode":"97055",
    "sg:province":"OR",
    "sg:website":"http://www.starbuckscoffee.com",
    "wof:name":"Starbucks Coffee",
    "wof:placetype":"venue"
},
  "geometry": {"coordinates":[-122.286942,45.403437],"type":"Point"}
}