{
  "type": "Feature",
  "properties": {
    "addr:full":"725 NE 102nd Ave Portland OR 97220",
    "addr:housenumber":"725",
    "addr:postcode":"97220",
    "addr:street":"Ne 102Nd Ave",
    "iso:country":"US",
    "sg:address":"725 NE 102nd Ave",
    "sg:city":"Portland",
    "sg:classifiers":[
        {
            "category":"Real Estate",
            "subcategory":"Real Estate Agent",
            "type":"Services"
        }
    ],
    "sg:phone":"+1 503 257 4009",
    "sg:postcode":"97220",
    "sg:province":"OR",
    "wof:name":"Ambassador Group Real Estate",
    "wof:placetype":"venue"
},
  "geometry": {"coordinates":[-122.558207,45.526756],"type":"Point"}
}