{
  "type": "Feature",
  "properties": {
    "iso:country":"US",
    "sg:address":"62999 Layton Ave Ste 4",
    "sg:city":"Bend",
    "sg:classifiers":[
        {
            "category":"Wholesale",
            "subcategory":"Furniture",
            "type":"Manufacturing & Wholesale Goods"
        },
        {
            "category":"Home & Garden",
            "subcategory":"Furniture",
            "type":"Retail Goods"
        }
    ],
    "sg:phone":"+1 541 330 8734",
    "sg:postcode":"97701",
    "sg:province":"OR",
    "sg:tags":[
        "store",
        "furniture-wholesale",
        "manufacturer"
    ],
    "wof:name":"Creative Furniture Designs Inc",
    "wof:placetype":"venue"
},
  "geometry": {"coordinates":[-121.29079299999999,44.086958],"type":"Point"}
}