{
  "type": "Feature",
  "properties": {
    "iso:country":"US",
    "sg:address":"29975 S Barlow Rd",
    "sg:city":"Canby",
    "sg:classifiers":[
        {
            "category":"Wholesale",
            "subcategory":"Farm Supplies",
            "type":"Manufacturing & Wholesale Goods"
        }
    ],
    "sg:phone":"+1 503 651 2130",
    "sg:postcode":"97013",
    "sg:province":"OR",
    "sg:tags":[
        "bulb",
        "seed"
    ],
    "sg:website":"www.turf-seed.com",
    "wof:name":"Turf Seed Inc",
    "wof:placetype":"venue"
},
  "geometry": {"coordinates":[-122.722601,45.173063],"type":"Point"}
}