{
  "type": "Feature",
  "properties": {
    "iso:country":"US",
    "sg:address":"19349 S Sylvan Ave",
    "sg:city":"Estacada",
    "sg:classifiers":[
        {
            "category":"Professional",
            "subcategory":"Business Services",
            "type":"Services"
        }
    ],
    "sg:phone":"+1 503 631 7833",
    "sg:postcode":"97023",
    "sg:province":"OR",
    "sg:tags":[
        "equipment",
        "furniture"
    ],
    "wof:name":"Smart Office Solutions",
    "wof:placetype":"venue"
},
  "geometry": {"coordinates":[-122.42652200000001,45.327123],"type":"Point"}
}