{
  "type": "Feature",
  "properties": {
    "iso:country":"US",
    "sg:address":"9498 SW Barbur Blvd",
    "sg:city":"Portland",
    "sg:classifiers":[
        {
            "category":"Insurance",
            "subcategory":"Insurance Agent",
            "type":"Services"
        }
    ],
    "sg:phone":"+1 503 293 6963",
    "sg:postcode":"97219",
    "sg:province":"OR",
    "wof:name":"Pioneer Mutual Life Insur Co",
    "wof:placetype":"venue"
},
  "geometry": {"coordinates":[-122.711688,45.457539],"type":"Point"}
}