{
  "type": "Feature",
  "properties": {
    "addr:full":"2999 S Santiam Hwy Lebanon OR 97355",
    "addr:housenumber":"2999",
    "addr:postcode":"97355",
    "addr:street":"S Santiam Hwy",
    "iso:country":"US",
    "sg:address":"2999 S Santiam Hwy",
    "sg:city":"Lebanon",
    "sg:classifiers":[
        {
            "category":"Autos & Motor Vehicles",
            "subcategory":"Automobile Sales",
            "type":"Retail Goods"
        }
    ],
    "sg:phone":"+1 541 259 2995",
    "sg:postcode":"97355",
    "sg:province":"OR",
    "sg:tags":[
        "used"
    ],
    "wof:name":"Hyers Auto Source",
    "wof:placetype":"venue"
},
  "geometry": {"coordinates":[-122.902936,44.520084],"type":"Point"}
}