{
  "type": "Feature",
  "properties": {
    "iso:country":"US",
    "sg:address":"15761 NW Graf St",
    "sg:city":"Portland",
    "sg:classifiers":[
        {
            "category":"Professional",
            "type":"Services"
        }
    ],
    "sg:phone":"+1 503 381 9595",
    "sg:postcode":"97229",
    "sg:province":"OR",
    "wof:name":"Acer Inspection Services",
    "wof:placetype":"venue"
},
  "geometry": {"coordinates":[-122.839513,45.563904],"type":"Point"}
}