{
  "type": "Feature",
  "properties": {
    "iso:country":"US",
    "sg:address":"5835 Wigrich Rd",
    "sg:city":"Independence",
    "sg:classifiers":[
        {
            "category":"Manufacturing",
            "subcategory":"Food",
            "type":"Manufacturing & Wholesale Goods"
        },
        {
            "category":"Farming",
            "subcategory":"Farm",
            "type":"Manufacturing & Wholesale Goods"
        }
    ],
    "sg:phone":"+1 503 838 1526",
    "sg:postcode":"97351",
    "sg:province":"OR",
    "sg:tags":[
        "corn",
        "product"
    ],
    "wof:name":"Wigrich Farm, Inc",
    "wof:placetype":"venue"
},
  "geometry": {"coordinates":[-123.150125,44.805998],"type":"Point"}
}