{
  "type": "Feature",
  "properties": {
    "iso:country":"US",
    "sg:address":"75722 Price Rd",
    "sg:city":"Rainier",
    "sg:classifiers":[
        {
            "category":"Manufacturing",
            "subcategory":"Lumber",
            "type":"Manufacturing & Wholesale Goods"
        }
    ],
    "sg:phone":"+1 503 556 3513",
    "sg:postcode":"97048",
    "sg:province":"OR",
    "sg:tags":[
        "logger"
    ],
    "wof:name":"Lange Logging",
    "wof:placetype":"venue"
},
  "geometry": {"coordinates":[-123.053405,46.092181],"type":"Point"}
}