{
  "type": "Feature",
  "properties": {
    "iso:country":"US",
    "sg:address":"1724 SE Clinton St",
    "sg:city":"Portland",
    "sg:classifiers":[
        {
            "category":"Food & Beverages",
            "subcategory":"Groceries & Convenience Stores",
            "type":"Retail Goods"
        }
    ],
    "sg:phone":"+1 503 235 5609",
    "sg:postcode":"97202",
    "sg:province":"OR",
    "sg:tags":[
        "grocer"
    ],
    "wof:name":"Ann's Market",
    "wof:placetype":"venue"
},
  "geometry": {"coordinates":[-122.647831,45.503405],"type":"Point"}
}