{
  "type": "Feature",
  "properties": {
    "iso:country":"US",
    "sg:address":"1706 NW 24th Ave",
    "sg:city":"Portland",
    "sg:classifiers":[
        {
            "category":"Government",
            "subcategory":"Post Office",
            "type":"Public Place"
        }
    ],
    "sg:phone":"+1 503 228 5412",
    "sg:postcode":"97210",
    "sg:province":"OR",
    "sg:website":"www.usps.com",
    "wof:name":"United States Post Office",
    "wof:placetype":"venue"
},
  "geometry": {"coordinates":[-122.70082600000001,45.534797],"type":"Point"}
}