{
  "type": "Feature",
  "properties": {
    "addr:full":"3120 SW Sherwood Pl Portland OR 97201",
    "addr:housenumber":"3120",
    "addr:postcode":"97201",
    "addr:street":"Sw Sherwood Pl",
    "iso:country":"US",
    "sg:address":"3120 SW Sherwood Pl",
    "sg:city":"Portland",
    "sg:classifiers":[
        {
            "category":"Personal",
            "subcategory":"Beauty Salon",
            "type":"Services"
        }
    ],
    "sg:phone":"+1 503 228 9660",
    "sg:postcode":"97201",
    "sg:province":"OR",
    "sg:tags":[
        "shop"
    ],
    "wof:name":"Noke Comprehensive Hair Design",
    "wof:placetype":"venue"
},
  "geometry": {"coordinates":[-122.698331,45.500894],"type":"Point"}
}