{
  "type": "Feature",
  "properties": {
    "addr:full":"5875 Peace Ln Central Point OR 97502",
    "addr:housenumber":"5875",
    "addr:postcode":"97502",
    "addr:street":"Peace Ln",
    "iso:country":"US",
    "sg:address":"5875 Peace Ln",
    "sg:city":"Central Point",
    "sg:classifiers":[
        {
            "category":"Shopping",
            "type":"Retail Goods"
        }
    ],
    "sg:phone":"+1 541 826 6627",
    "sg:postcode":"97502",
    "sg:province":"OR",
    "sg:tags":[
        "merchandise"
    ],
    "wof:name":"Table Rock Trophies Engra",
    "wof:placetype":"venue"
},
  "geometry": {"coordinates":[-122.870565,42.400266],"type":"Point"}
}