{
  "type": "Feature",
  "properties": {
    "iso:country":"US",
    "sg:address":"219 SW 6th Ave",
    "sg:city":"Portland",
    "sg:classifiers":[
        {
            "category":"Restaurant",
            "type":"Food & Drink"
        }
    ],
    "sg:phone":"+1 503 688 5952",
    "sg:postcode":"97205",
    "sg:province":"OR",
    "sg:tags":[
        "french"
    ],
    "sg:website":"littlebirdbistro.com/",
    "wof:name":"Little Bird",
    "wof:placetype":"venue"
},
  "geometry": {"coordinates":[-122.677019,45.522069],"type":"Point"}
}