{
  "type": "Feature",
  "properties": {
    "addr:full":"2866 Willamette St Eugene OR 97405",
    "addr:housenumber":"2866",
    "addr:postcode":"97405",
    "addr:street":"Willamette St",
    "iso:country":"US",
    "sg:address":"2866 Willamette St",
    "sg:city":"Eugene",
    "sg:classifiers":[
        {
            "category":"Food & Beverages",
            "subcategory":"Liquor & Beverages",
            "type":"Retail Goods"
        }
    ],
    "sg:phone":"+1 541 343 3611",
    "sg:postcode":"97405",
    "sg:province":"OR",
    "wof:name":"Williamette Plaza Liquor Store",
    "wof:placetype":"venue"
},
  "geometry": {"coordinates":[-123.09078700000001,44.027481],"type":"Point"}
}