{
  "type": "Feature",
  "properties": {
    "addr:full":"29292 SE Judd Rd Eagle Creek OR 97022",
    "addr:postcode":"29292;97022",
    "addr:street":"Se Judd Rd",
    "iso:country":"US",
    "sg:address":"29292 SE Judd Rd",
    "sg:city":"Eagle Creek",
    "sg:classifiers":[
        {
            "category":"Restaurant",
            "type":"Food & Drink"
        }
    ],
    "sg:phone":"+1 503 637 5333",
    "sg:postcode":"97022",
    "sg:province":"OR",
    "sg:tags":[
        "eating"
    ],
    "wof:name":"Bell Station",
    "wof:placetype":"venue"
},
  "geometry": {"coordinates":[-122.36185399999999,45.381525],"type":"Point"}
}