{
  "type": "Feature",
  "properties": {
    "iso:country":"US",
    "sg:address":"11831 SW Pacific Hwy",
    "sg:city":"Tigard",
    "sg:classifiers":[
        {
            "category":"Restaurant",
            "type":"Food & Drink"
        }
    ],
    "sg:postcode":"97223",
    "sg:province":"OR",
    "sg:tags":[
        "barbeque"
    ],
    "sg:website":"www.shanesbackyardbbq.com",
    "wof:name":"Shane's Backyard BBQ",
    "wof:placetype":"venue"
},
  "geometry": {"coordinates":[-122.763498,45.435005],"type":"Point"}
}