{
  "type": "Feature",
  "properties": {
    "iso:country":"US",
    "sg:address":"Nw 21st & Hoyt",
    "sg:city":"Portland",
    "sg:classifiers":[
        {
            "category":"Food Court",
            "type":"Food & Drink"
        },
        {
            "category":"Food & Beverages",
            "subcategory":"Meat & Fish",
            "type":"Retail Goods"
        }
    ],
    "sg:postcode":"97209",
    "sg:province":"OR",
    "sg:tags":[
        "hot",
        "stand",
        "dog"
    ],
    "wof:name":"Hoyt Dog",
    "wof:placetype":"venue"
},
  "geometry": {"coordinates":[-122.694441,45.527012],"type":"Point"}
}