{
  "type": "Feature",
  "properties": {
    "iso:country":"US",
    "sg:address":"301 US Hwy 97",
    "sg:city":"Moro",
    "sg:classifiers":[
        {
            "category":"Travel",
            "subcategory":"Hotels & Motels",
            "type":"Entertainment"
        }
    ],
    "sg:phone":"+1 541 565 3519",
    "sg:postcode":"97039",
    "sg:province":"OR",
    "wof:name":"Tall Winds Motel",
    "wof:placetype":"venue"
},
  "geometry": {"coordinates":[-120.73245300000001,45.482981],"type":"Point"}
}