{
  "type": "Feature",
  "properties": {
    "addr:full":"700 SE Emigrant Ave Pendleton OR 97801",
    "addr:housenumber":"700",
    "addr:postcode":"97801",
    "addr:street":"Se Emigrant Ave",
    "iso:country":"US",
    "sg:address":"700 SE Emigrant Ave",
    "sg:city":"Pendleton",
    "sg:classifiers":[
        {
            "category":"Government",
            "subcategory":"Office",
            "type":"Public Place"
        }
    ],
    "sg:phone":"+1 541 276 7880",
    "sg:postcode":"97801",
    "sg:province":"OR",
    "wof:name":"District Sanitarian",
    "wof:placetype":"venue"
},
  "geometry": {"coordinates":[-118.778728,45.672909],"type":"Point"}
}