{
  "type": "Feature",
  "properties": {
    "iso:country":"US",
    "sg:address":"561 NW Jackson Ave",
    "sg:city":"Corvallis",
    "sg:classifiers":[
        {
            "category":"Professional",
            "subcategory":"Research",
            "type":"Services"
        }
    ],
    "sg:phone":"+1 541 758 0947",
    "sg:postcode":"97330",
    "sg:province":"OR",
    "sg:tags":[
        "environmental",
        "ecological"
    ],
    "wof:name":"Biosystems",
    "wof:placetype":"venue"
},
  "geometry": {"coordinates":[-123.26298800000001,44.56606],"type":"Point"}
}