{
  "type": "Feature",
  "properties": {
    "iso:country":"US",
    "sg:address":"7600 SE Johnson Creek Blvd",
    "sg:city":"Portland",
    "sg:classifiers":[
        {
            "category":"Home & Garden",
            "subcategory":"Garden Supply",
            "type":"Retail Goods"
        }
    ],
    "sg:phone":"+1 503 788 8813",
    "sg:postcode":"97206",
    "sg:province":"OR",
    "sg:tags":[
        "sprinkler"
    ],
    "sg:website":"www.unitedpipe.com",
    "wof:name":"United Pipe & Supply Co",
    "wof:placetype":"venue"
},
  "geometry": {"coordinates":[-122.58474099999999,45.457032],"type":"Point"}
}