{
  "type": "Feature",
  "properties": {
    "iso:country":"US",
    "sg:address":"10202 SE 32nd Ave",
    "sg:city":"Portland",
    "sg:classifiers":[
        {
            "category":"Health Services",
            "subcategory":"Doctor",
            "type":"Services"
        }
    ],
    "sg:phone":"+1 503 513 5520",
    "sg:postcode":"97222",
    "sg:province":"OR",
    "sg:tags":[
        "medical"
    ],
    "wof:name":"Quita Lopez MD Facog",
    "wof:placetype":"venue"
},
  "geometry": {"coordinates":[-122.629652,45.447839],"type":"Point"}
}