{
  "type": "Feature",
  "properties": {
    "iso:country":"US",
    "sg:address":"4815 Commercial St SE",
    "sg:city":"Salem",
    "sg:classifiers":[
        {
            "category":"Shopping",
            "subcategory":"Crafts & Fabrics",
            "type":"Retail Goods"
        }
    ],
    "sg:phone":"+1 503 363 8102",
    "sg:postcode":"97302",
    "sg:province":"OR",
    "sg:tags":[
        "sewing",
        "supply"
    ],
    "sg:website":"www.joann.com",
    "wof:name":"Jo-Ann Fabrics & Crafts",
    "wof:placetype":"venue"
},
  "geometry": {"coordinates":[-123.032433,44.885652],"type":"Point"}
}