{
  "type": "Feature",
  "properties": {
    "addr:full":"30626 SE Division Dr Troutdale OR 97060",
    "addr:postcode":"30626;97060",
    "addr:street":"Se Division Dr",
    "iso:country":"US",
    "sg:address":"30626 SE Division Dr",
    "sg:city":"Troutdale",
    "sg:classifiers":[
        {
            "category":"Utilities",
            "subcategory":"Water",
            "type":"Services"
        }
    ],
    "sg:phone":"+1 503 663 3059",
    "sg:postcode":"97060",
    "sg:province":"OR",
    "sg:tags":[
        "company",
        "sewage"
    ],
    "wof:name":"Lusted Water District",
    "wof:placetype":"venue"
},
  "geometry": {"coordinates":[-122.350376,45.497419],"type":"Point"}
}