{
  "type": "Feature",
  "properties": {
    "iso:country":"US",
    "sg:address":"4858 SW Scholls Ferry Rd",
    "sg:city":"Portland",
    "sg:classifiers":[
        {
            "category":"Personal",
            "type":"Services"
        }
    ],
    "sg:phone":"+1 503 297 8805",
    "sg:postcode":"97225",
    "sg:province":"OR",
    "sg:tags":[
        "therapist",
        "massage"
    ],
    "sg:website":"www.creative-therapies.com",
    "wof:name":"Creative Therapies",
    "wof:placetype":"venue"
},
  "geometry": {"coordinates":[-122.754818,45.483371],"type":"Point"}
}