{
  "type": "Feature",
  "properties": {
    "iso:country":"US",
    "sg:address":"1905 Plum St",
    "sg:city":"Baker City",
    "sg:classifiers":[
        {
            "category":"Food & Beverages",
            "subcategory":"Specialty",
            "type":"Retail Goods"
        }
    ],
    "sg:phone":"+1 541 524 1180",
    "sg:postcode":"97814",
    "sg:province":"OR",
    "sg:tags":[
        "bars",
        "espresso"
    ],
    "wof:name":"Fregossinis Espresso Coffee",
    "wof:placetype":"venue"
},
  "geometry": {"coordinates":[-117.816086,44.776987],"type":"Point"}
}