{
  "type": "Feature",
  "properties": {
    "iso:country":"US",
    "sg:address":"4710 NE M L King Blvd",
    "sg:city":"Portland",
    "sg:classifiers":[
        {
            "category":"Shopping",
            "type":"Retail Goods"
        }
    ],
    "sg:phone":"+1 503 284 1885",
    "sg:postcode":"97211",
    "sg:province":"OR",
    "sg:tags":[
        "pet",
        "food",
        "merchandise",
        "supply"
    ],
    "wof:name":"Wagner's Pet Supplies",
    "wof:placetype":"venue"
},
  "geometry": {"coordinates":[-122.661467,45.55681],"type":"Point"}
}