{
  "type": "Feature",
  "properties": {
    "addr:full":"19295 NW Cornell Rd Hillsboro OR 97124",
    "addr:housenumber":"19295",
    "addr:postcode":"97124",
    "addr:street":"Nw Cornell Rd",
    "iso:country":"US",
    "sg:address":"19295 NW Cornell Rd",
    "sg:city":"Hillsboro",
    "sg:classifiers":[
        {
            "category":"Real Estate",
            "subcategory":"Real Estate Operator",
            "type":"Services"
        }
    ],
    "sg:phone":"+1 503 617 1900",
    "sg:postcode":"97124",
    "sg:province":"OR",
    "sg:tags":[
        "building",
        "apartment"
    ],
    "wof:name":"Rock Creek",
    "wof:placetype":"venue"
},
  "geometry": {"coordinates":[-122.87656800000001,45.534458],"type":"Point"}
}