{
  "type": "Feature",
  "properties": {
    "addr:full":"67898 US Hwy 26 Welches OR 97067",
    "addr:postcode":"67898;97067",
    "addr:street":"Us Hwy 26",
    "iso:country":"US",
    "sg:address":"67898 US Hwy 26",
    "sg:city":"Welches",
    "sg:classifiers":[
        {
            "category":"Restaurant",
            "type":"Food & Drink"
        }
    ],
    "sg:phone":"+1 503 622 6302",
    "sg:postcode":"97067",
    "sg:province":"OR",
    "wof:name":"Backyard Bistro",
    "wof:placetype":"venue"
},
  "geometry": {"coordinates":[-121.966561,45.349128],"type":"Point"}
}