{
  "type": "Feature",
  "properties": {
    "addr:full":"9635 SW Washington Square Rd Portland OR 97223",
    "addr:housenumber":"9635",
    "addr:postcode":"97223",
    "addr:street":"Sw Washington Square Rd",
    "iso:country":"US",
    "sg:address":"9635 SW Washington Square Rd",
    "sg:city":"Portland",
    "sg:classifiers":[
        {
            "category":"Building & Trades",
            "subcategory":"Locksmith",
            "type":"Services"
        }
    ],
    "sg:phone":"+1 503 403 0021",
    "sg:postcode":"97223",
    "sg:province":"OR",
    "sg:tags":[
        "key"
    ],
    "wof:name":"1 24 Hr 7 Days Locksmith of Portland",
    "wof:placetype":"venue"
},
  "geometry": {"coordinates":[-122.783241,45.44917],"type":"Point"}
}