{
  "type": "Feature",
  "properties": {
    "iso:country":"US",
    "sg:address":"2805 Maywood Dr",
    "sg:city":"Klamath Falls",
    "sg:classifiers":[
        {
            "category":"Wholesale",
            "subcategory":"Groceries",
            "type":"Manufacturing & Wholesale Goods"
        }
    ],
    "sg:phone":"+1 541 883 3000",
    "sg:postcode":"97603",
    "sg:province":"OR",
    "sg:tags":[
        "grocer"
    ],
    "wof:name":"Cash & Carry",
    "wof:placetype":"venue"
},
  "geometry": {"coordinates":[-121.759087,42.199624],"type":"Point"}
}