{
  "type": "Feature",
  "properties": {
    "iso:country":"US",
    "sg:address":"195 Country Ln",
    "sg:city":"Gold Hill",
    "sg:classifiers":[
        {
            "category":"Building & Trades",
            "subcategory":"Construction",
            "type":"Services"
        }
    ],
    "sg:phone":"+1 541 855 1328",
    "sg:postcode":"97525",
    "sg:province":"OR",
    "sg:tags":[
        "water",
        "well",
        "drilling",
        "contractor"
    ],
    "wof:name":"Gribble Well Drilling Inc",
    "wof:placetype":"venue"
},
  "geometry": {"coordinates":[-122.982193,42.49398],"type":"Point"}
}