{
  "type": "Feature",
  "properties": {
    "iso:country":"US",
    "sg:address":"15100 NW Blakely Ln",
    "sg:city":"Portland",
    "sg:classifiers":[
        {
            "category":"Personal",
            "subcategory":"Beauty Salon",
            "type":"Services"
        }
    ],
    "sg:phone":"+1 503 645 9608",
    "sg:postcode":"97229",
    "sg:province":"OR",
    "sg:tags":[
        "hair",
        "stylist"
    ],
    "wof:name":"W Slope Salon",
    "wof:placetype":"venue"
},
  "geometry": {"coordinates":[-122.83192200000001,45.556282],"type":"Point"}
}