{
  "type": "Feature",
  "properties": {
    "iso:country":"US",
    "sg:address":"505 NE 1st St",
    "sg:city":"Newport",
    "sg:classifiers":[
        {
            "category":"Social Services",
            "type":"Services"
        }
    ],
    "sg:phone":"+1 541 574 0320",
    "sg:postcode":"97365",
    "sg:province":"OR",
    "sg:tags":[
        "organization",
        "welfare"
    ],
    "wof:name":"Community Development Corp",
    "wof:placetype":"venue"
},
  "geometry": {"coordinates":[-124.046611,44.63707],"type":"Point"}
}