{
  "type": "Feature",
  "properties": {
    "iso:country":"US",
    "sg:address":"333 S 1st St",
    "sg:city":"St Helens",
    "sg:classifiers":[
        {
            "category":"Building & Trades",
            "subcategory":"Construction",
            "type":"Services"
        }
    ],
    "sg:phone":"+1 503 397 4453",
    "sg:postcode":"97051",
    "sg:province":"OR",
    "sg:tags":[
        "concrete",
        "contractor"
    ],
    "wof:name":"Franklin Concrete Construction",
    "wof:placetype":"venue"
},
  "geometry": {"coordinates":[-122.79749099999999,45.861631],"type":"Point"}
}