{
  "type": "Feature",
  "properties": {
    "addr:full":"719 NE Roberts Ave Gresham OR 97030",
    "addr:housenumber":"719",
    "addr:postcode":"97030",
    "addr:street":"Ne Roberts Ave",
    "iso:country":"US",
    "sg:address":"719 NE Roberts Ave",
    "sg:city":"Gresham",
    "sg:classifiers":[
        {
            "category":"Professional",
            "subcategory":"Management & Consulting",
            "type":"Services"
        }
    ],
    "sg:phone":"+1 503 720 0683",
    "sg:postcode":"97030",
    "sg:province":"OR",
    "wof:name":"Beranger Condominium Owners Association",
    "wof:placetype":"venue"
},
  "geometry": {"coordinates":[-122.429632,45.502445],"type":"Point"}
}