{
  "type": "Feature",
  "properties": {
    "iso:country":"US",
    "sg:address":"5370 Grange Rd",
    "sg:city":"Roseburg",
    "sg:classifiers":[
        {
            "category":"Food & Beverages",
            "subcategory":"Meat & Fish",
            "type":"Retail Goods"
        }
    ],
    "sg:phone":"+1 541 679 8511",
    "sg:postcode":"97470",
    "sg:province":"OR",
    "sg:tags":[
        "cutting"
    ],
    "wof:name":"Butcher's Block Meat Shop",
    "wof:placetype":"venue"
},
  "geometry": {"coordinates":[-123.392271,43.137309],"type":"Point"}
}