{
  "type": "Feature",
  "properties": {
    "addr:full":"15807 SE Bybee Dr Portland OR 97236",
    "addr:postcode":"15807;97236",
    "addr:street":"Se Bybee Dr",
    "iso:country":"US",
    "sg:address":"15807 SE Bybee Dr",
    "sg:city":"Portland",
    "sg:classifiers":[
        {
            "category":"Professional",
            "subcategory":"Management & Consulting",
            "type":"Services"
        }
    ],
    "sg:phone":"+1 503 781 6498",
    "sg:postcode":"97236",
    "sg:province":"OR",
    "sg:tags":[
        "consultant"
    ],
    "wof:name":"Tdg, Inc.",
    "wof:placetype":"venue"
},
  "geometry": {"coordinates":[-122.499459,45.47149],"type":"Point"}
}