{
  "type": "Feature",
  "properties": {
    "addr:full":"3090 Eagle Valley Rd Yoncalla OR 97499",
    "addr:housenumber":"3090",
    "addr:postcode":"97499",
    "addr:street":"Eagle Valley Rd",
    "iso:country":"US",
    "sg:address":"3090 Eagle Valley Rd",
    "sg:city":"Yoncalla",
    "sg:classifiers":[
        {
            "category":"Manufacturing",
            "subcategory":"Metals",
            "type":"Manufacturing & Wholesale Goods"
        }
    ],
    "sg:phone":"+1 541 849 2602",
    "sg:postcode":"97499",
    "sg:province":"OR",
    "wof:name":"Kopp Electric Inc",
    "wof:placetype":"venue"
},
  "geometry": {"coordinates":[-123.282916,43.604643],"type":"Point"}
}