{
  "type": "Feature",
  "properties": {
    "iso:country":"US",
    "sg:address":"19481 S Westling Dr",
    "sg:city":"Oregon City",
    "sg:classifiers":[
        {
            "category":"Shopping",
            "subcategory":"Gifts & Souvenirs",
            "type":"Retail Goods"
        }
    ],
    "sg:phone":"+1 503 557 1918",
    "sg:postcode":"97045",
    "sg:province":"OR",
    "sg:tags":[
        "basket",
        "parcel"
    ],
    "wof:name":"Creative Gift Baskets",
    "wof:placetype":"venue"
},
  "geometry": {"coordinates":[-122.622754,45.32417],"type":"Point"}
}