{
  "type": "Feature",
  "properties": {
    "iso:country":"US",
    "sg:address":"2505 Broadway St",
    "sg:city":"Baker City",
    "sg:classifiers":[
        {
            "category":"Social Services",
            "type":"Services"
        }
    ],
    "sg:phone":"+1 541 523 5853",
    "sg:postcode":"97814",
    "sg:province":"OR",
    "sg:tags":[
        "organization",
        "welfare"
    ],
    "wof:name":"Salvation Army",
    "wof:placetype":"venue"
},
  "geometry": {"coordinates":[-117.83784,44.778031],"type":"Point"}
}