{
  "type": "Feature",
  "properties": {
    "iso:country":"US",
    "sg:address":"1108 E Marina Dr",
    "sg:city":"Hood River",
    "sg:classifiers":[
        {
            "category":"Social Services",
            "subcategory":"Job Training",
            "type":"Services"
        }
    ],
    "sg:phone":"+1 541 386 6020",
    "sg:postcode":"97031",
    "sg:province":"OR",
    "sg:tags":[
        "rehab",
        "government"
    ],
    "wof:name":"Oregon State Employment Div",
    "wof:placetype":"venue"
},
  "geometry": {"coordinates":[-121.49997399999999,45.711393],"type":"Point"}
}