{
  "type": "Feature",
  "properties": {
    "iso:country":"US",
    "sg:address":"532 S Main St",
    "sg:city":"Lebanon",
    "sg:classifiers":[
        {
            "category":"Professional",
            "subcategory":"Business Services",
            "type":"Services"
        }
    ],
    "sg:phone":"+1 541 259 2969",
    "sg:postcode":"97355",
    "sg:province":"OR",
    "sg:tags":[
        "record",
        "medical"
    ],
    "wof:name":"Fisher Financial Svc",
    "wof:placetype":"venue"
},
  "geometry": {"coordinates":[-122.907144,44.540634],"type":"Point"}
}