{
  "type": "Feature",
  "properties": {
    "iso:country":"US",
    "sg:address":"344 Goodpasture Island Rd",
    "sg:city":"Eugene",
    "sg:classifiers":[
        {
            "category":"Autos & Motor Vehicles",
            "subcategory":"Automobile Sales",
            "type":"Retail Goods"
        }
    ],
    "sg:phone":"+1 541 342 2151",
    "sg:postcode":"97401",
    "sg:province":"OR",
    "sg:tags":[
        "car",
        "dealer"
    ],
    "sg:website":"www.kendallauto.com",
    "wof:name":"Kendall Ford",
    "wof:placetype":"venue"
},
  "geometry": {"coordinates":[-123.108062,44.069912],"type":"Point"}
}