{
  "type": "Feature",
  "properties": {
    "addr:full":"4575 SW Research Way Corvallis OR 97333",
    "addr:housenumber":"4575",
    "addr:postcode":"97333",
    "addr:street":"Sw Research Way",
    "iso:country":"US",
    "sg:address":"4575 SW Research Way",
    "sg:city":"Corvallis",
    "sg:classifiers":[
        {
            "category":"Professional",
            "subcategory":"Research",
            "type":"Services"
        }
    ],
    "sg:phone":"+1 541 753 2000",
    "sg:postcode":"97333",
    "sg:province":"OR",
    "sg:tags":[
        "laboratory",
        "pharmaceutical"
    ],
    "sg:website":"www.siga.com",
    "wof:name":"SIGA Technologies Inc",
    "wof:placetype":"venue"
},
  "geometry": {"coordinates":[-123.30123399999999,44.551786],"type":"Point"}
}