{
  "type": "Feature",
  "properties": {
    "addr:full":"419 SE 13th Ave Portland OR 97214",
    "addr:housenumber":"419",
    "addr:postcode":"97214",
    "addr:street":"Se 13Th Ave",
    "iso:country":"US",
    "sg:address":"419 SE 13th Ave",
    "sg:city":"Portland",
    "sg:classifiers":[
        {
            "category":"Manufacturing",
            "subcategory":"Retail Goods",
            "type":"Manufacturing & Wholesale Goods"
        }
    ],
    "sg:phone":"+1 503 236 2741",
    "sg:postcode":"97214",
    "sg:province":"OR",
    "sg:tags":[
        "giftware's-wholesale",
        "manufacturer"
    ],
    "wof:name":"Anne Garrison Design",
    "wof:placetype":"venue"
},
  "geometry": {"coordinates":[-122.65260600000001,45.51991],"type":"Point"}
}