{
  "type": "Feature",
  "properties": {
    "addr:full":"333 Broadalbin St SW Albany OR 97321",
    "addr:housenumber":"333",
    "addr:postcode":"97321",
    "addr:street":"Broadalbin St Sw",
    "iso:country":"US",
    "sg:address":"333 Broadalbin St SW",
    "sg:city":"Albany",
    "sg:classifiers":[
        {
            "category":"Government",
            "subcategory":"Office",
            "type":"Public Place"
        }
    ],
    "sg:phone":"+1 541 917 7524",
    "sg:postcode":"97321",
    "sg:province":"OR",
    "sg:tags":[
        "city"
    ],
    "wof:name":"Albany City Clerk",
    "wof:placetype":"venue"
},
  "geometry": {"coordinates":[-123.10698600000001,44.635314],"type":"Point"}
}