{
  "type": "Feature",
  "properties": {
    "iso:country":"US",
    "sg:address":"9935 SW Commerce Cir",
    "sg:city":"Wilsonville",
    "sg:classifiers":[
        {
            "category":"Home & Garden",
            "subcategory":"Household Appliances",
            "type":"Retail Goods"
        }
    ],
    "sg:phone":"+1 503 682 3625",
    "sg:postcode":"97070",
    "sg:province":"OR",
    "sg:tags":[
        "pump"
    ],
    "wof:name":"Mitchell Lewis & Staver Co",
    "wof:placetype":"venue"
},
  "geometry": {"coordinates":[-122.776157,45.335342],"type":"Point"}
}