{
  "type": "Feature",
  "properties": {
    "addr:full":"2320 Adams St Eugene OR 97405",
    "addr:housenumber":"2320",
    "addr:postcode":"97405",
    "addr:street":"Adams St",
    "iso:country":"US",
    "sg:address":"2320 Adams St",
    "sg:city":"Eugene",
    "sg:classifiers":[
        {
            "category":"Building & Trades",
            "subcategory":"Construction",
            "type":"Services"
        }
    ],
    "sg:phone":"+1 541 342 4540",
    "sg:postcode":"97405",
    "sg:province":"OR",
    "sg:tags":[
        "residential"
    ],
    "wof:name":"Cloudcap Construction",
    "wof:placetype":"venue"
},
  "geometry": {"coordinates":[-123.107097,44.033146],"type":"Point"}
}