{
  "type": "Feature",
  "properties": {
    "addr:full":"222 SW Harrison St Portland OR 97201",
    "addr:housenumber":"222",
    "addr:postcode":"97201",
    "addr:street":"Sw Harrison St",
    "iso:country":"US",
    "sg:address":"222 SW Harrison St",
    "sg:city":"Portland",
    "sg:classifiers":[
        {
            "category":"Real Estate",
            "subcategory":"Real Estate Operator",
            "type":"Services"
        }
    ],
    "sg:phone":"+1 503 295 5559",
    "sg:postcode":"97201",
    "sg:province":"OR",
    "sg:tags":[
        "apartment"
    ],
    "wof:name":"Jb Madison",
    "wof:placetype":"venue"
},
  "geometry": {"coordinates":[-122.67931799999999,45.509925],"type":"Point"}
}