{
  "type": "Feature",
  "properties": {
    "addr:full":"1172 SW 3rd Ave Ontario OR 97914",
    "addr:housenumber":"1172",
    "addr:postcode":"97914",
    "addr:street":"Sw 3Rd Ave",
    "iso:country":"US",
    "sg:address":"1172 SW 3rd Ave",
    "sg:city":"Ontario",
    "sg:classifiers":[
        {
            "category":"Building & Trades",
            "subcategory":"Construction",
            "type":"Services"
        }
    ],
    "sg:phone":"+1 541 881 1275",
    "sg:postcode":"97914",
    "sg:province":"OR",
    "sg:tags":[
        "painting",
        "contractor"
    ],
    "wof:name":"Jim's Painting",
    "wof:placetype":"venue"
},
  "geometry": {"coordinates":[-116.979974,44.02581],"type":"Point"}
}