{
  "type": "Feature",
  "properties": {
    "iso:country":"US",
    "sg:address":"10645 SE Malden St",
    "sg:city":"Portland",
    "sg:classifiers":[
        {
            "category":"Professional",
            "subcategory":"Engineering",
            "type":"Services"
        }
    ],
    "sg:phone":"+1 503 680 0026",
    "sg:postcode":"97266",
    "sg:province":"OR",
    "wof:name":"Metric Mind Engineering",
    "wof:placetype":"venue"
},
  "geometry": {"coordinates":[-122.554838,45.467008],"type":"Point"}
}