{
  "type": "Feature",
  "properties": {
    "addr:full":"3703 SE 65th Ave Portland OR 97206",
    "addr:housenumber":"3703",
    "addr:postcode":"97206",
    "addr:street":"Se 65Th Ave",
    "iso:country":"US",
    "sg:address":"3703 SE 65th Ave",
    "sg:city":"Portland",
    "sg:classifiers":[
        {
            "category":"Building & Trades",
            "subcategory":"Locksmith",
            "type":"Services"
        }
    ],
    "sg:phone":"+1 503 821 0931",
    "sg:postcode":"97206",
    "sg:province":"OR",
    "sg:tags":[
        "key"
    ],
    "wof:name":"Abbe Locks 24 Locksmith",
    "wof:placetype":"venue"
},
  "geometry": {"coordinates":[-122.596496,45.49569],"type":"Point"}
}