{
  "type": "Feature",
  "properties": {
    "iso:country":"US",
    "sg:address":"17237 Kelok Rd",
    "sg:city":"Lake Oswego",
    "sg:classifiers":[
        {
            "category":"Real Estate",
            "subcategory":"Real Estate Operator",
            "type":"Services"
        }
    ],
    "sg:phone":"+1 503 675 3087",
    "sg:postcode":"97034",
    "sg:province":"OR",
    "sg:tags":[
        "building",
        "nonresidential"
    ],
    "wof:name":"Fawn Court Properties LLC",
    "wof:placetype":"venue"
},
  "geometry": {"coordinates":[-122.713874,45.401473],"type":"Point"}
}