{
  "type": "Feature",
  "properties": {
    "iso:country":"US",
    "sg:address":"307 20th St",
    "sg:city":"La Grande",
    "sg:classifiers":[
        {
            "category":"Real Estate",
            "subcategory":"Real Estate Operator",
            "type":"Services"
        }
    ],
    "sg:phone":"+1 541 963 3785",
    "sg:postcode":"97850",
    "sg:province":"OR",
    "sg:tags":[
        "apartment"
    ],
    "wof:name":"Thunderbird-Cove Apartments",
    "wof:placetype":"venue"
},
  "geometry": {"coordinates":[-118.076149,45.314085],"type":"Point"}
}