{
  "type": "Feature",
  "properties": {
    "iso:country":"US",
    "sg:address":"85833 State Hwy 99 S",
    "sg:city":"Eugene",
    "sg:classifiers":[
        {
            "category":"Food & Beverages",
            "subcategory":"Specialty",
            "type":"Retail Goods"
        }
    ],
    "sg:phone":"+1 541 744 5651",
    "sg:postcode":"97405",
    "sg:province":"OR",
    "sg:tags":[
        "herb"
    ],
    "sg:website":"www.omchiherbs.com",
    "wof:name":"Om-Chi Herb Co",
    "wof:placetype":"venue"
},
  "geometry": {"coordinates":[-123.01170999999999,43.994004],"type":"Point"}
}