{
  "type": "Feature",
  "properties": {
    "iso:country":"US",
    "sg:address":"4380 SW Macadam Ave Ste 500",
    "sg:city":"Portland",
    "sg:classifiers":[
        {
            "category":"Food & Beverages",
            "subcategory":"Liquor & Beverages",
            "type":"Retail Goods"
        },
        {
            "category":"Wholesale",
            "subcategory":"Wine & Distilled Alcoholic Beverages",
            "type":"Manufacturing & Wholesale Goods"
        }
    ],
    "sg:phone":"+1 503 705 9398",
    "sg:postcode":"97239",
    "sg:province":"OR",
    "sg:tags":[
        "broker"
    ],
    "wof:name":"Zivo Wines",
    "wof:placetype":"venue"
},
  "geometry": {"coordinates":[-122.67308,45.491379],"type":"Point"}
}