{
  "type": "Feature",
  "properties": {
    "iso:country":"US",
    "sg:address":"800 S Roosevelt Dr",
    "sg:city":"Seaside",
    "sg:classifiers":[
        {
            "category":"Personal",
            "type":"Services"
        }
    ],
    "sg:phone":"+1 503 717 0413",
    "sg:postcode":"97138",
    "sg:province":"OR",
    "wof:name":"Fanny Tanners",
    "wof:placetype":"venue"
},
  "geometry": {"coordinates":[-123.922209,45.98814],"type":"Point"}
}