{
  "type": "Feature",
  "properties": {
    "iso:country":"US",
    "sg:address":"2325 Rural Ave SE",
    "sg:city":"Salem",
    "sg:classifiers":[
        {
            "category":"Building & Trades",
            "subcategory":"Construction",
            "type":"Services"
        }
    ],
    "sg:phone":"+1 503 581 2315",
    "sg:postcode":"97302",
    "sg:province":"OR",
    "sg:tags":[
        "masonry",
        "contractor"
    ],
    "wof:name":"CSU Masonry Inc",
    "wof:placetype":"venue"
},
  "geometry": {"coordinates":[-123.013505,44.921087],"type":"Point"}
}