{
  "type": "Feature",
  "properties": {
    "iso:country":"US",
    "sg:address":"503 N Main St",
    "sg:city":"Joseph",
    "sg:classifiers":[
        {
            "category":"Autos & Motor Vehicles",
            "subcategory":"Auto Supplies",
            "type":"Retail Goods"
        }
    ],
    "sg:phone":"+1 541 432 3221",
    "sg:postcode":"97846",
    "sg:province":"OR",
    "sg:tags":[
        "automobile",
        "parts"
    ],
    "wof:name":"Mike's Garage",
    "wof:placetype":"venue"
},
  "geometry": {"coordinates":[-117.229992,45.357138],"type":"Point"}
}