{
  "type": "Feature",
  "properties": {
    "iso:country":"US",
    "sg:address":"39084 Proctor Blvd",
    "sg:city":"Sandy",
    "sg:classifiers":[
        {
            "category":"Home & Garden",
            "subcategory":"Household Appliances",
            "type":"Retail Goods"
        }
    ],
    "sg:phone":"+1 503 668 8823",
    "sg:postcode":"97055",
    "sg:province":"OR",
    "sg:tags":[
        "cleaners",
        "vacuum"
    ],
    "wof:name":"Bailey Distributing",
    "wof:placetype":"venue"
},
  "geometry": {"coordinates":[-122.261256,45.397225],"type":"Point"}
}