{
  "type": "Feature",
  "properties": {
    "iso:country":"US",
    "sg:address":"766 E 13th Ave",
    "sg:city":"Eugene",
    "sg:classifiers":[
        {
            "category":"Health Services",
            "subcategory":"Optometrist",
            "type":"Services"
        }
    ],
    "sg:phone":"+1 541 343 3333",
    "sg:postcode":"97401",
    "sg:province":"OR",
    "sg:tags":[
        "optical",
        "good"
    ],
    "wof:name":"Rainbow Optics PC",
    "wof:placetype":"venue"
},
  "geometry": {"coordinates":[-123.08123000000001,44.045442],"type":"Point"}
}