{
  "type": "Feature",
  "properties": {
    "addr:full":"2935 W 15th Ave Eugene OR 97402",
    "addr:housenumber":"2935",
    "addr:postcode":"97402",
    "addr:street":"W 15Th Ave",
    "iso:country":"US",
    "sg:address":"2935 W 15th Ave",
    "sg:city":"Eugene",
    "sg:classifiers":[
        {
            "category":"Building & Trades",
            "subcategory":"Construction",
            "type":"Services"
        }
    ],
    "sg:phone":"+1 541 342 7750",
    "sg:postcode":"97402",
    "sg:province":"OR",
    "sg:tags":[
        "carpentry",
        "contractor"
    ],
    "wof:name":"Wild West Construction",
    "wof:placetype":"venue"
},
  "geometry": {"coordinates":[-123.13789300000001,44.043427],"type":"Point"}
}