{
  "type": "Feature",
  "properties": {
    "iso:country":"US",
    "sg:address":"1785 N Front St",
    "sg:city":"Woodburn",
    "sg:classifiers":[
        {
            "category":"Education",
            "subcategory":"School",
            "type":"Public Place"
        }
    ],
    "sg:phone":"+1 503 981 2600",
    "sg:postcode":"97071",
    "sg:province":"OR",
    "sg:website":"www.woodburn.k12.or.us",
    "wof:name":"Woodburn High School",
    "wof:placetype":"venue"
},
  "geometry": {"coordinates":[-122.84238000000001,45.153909],"type":"Point"}
}