{
  "type": "Feature",
  "properties": {
    "iso:country":"US",
    "sg:address":"3123 Broadway St NE",
    "sg:city":"Salem",
    "sg:classifiers":[
        {
            "category":"Utilities",
            "subcategory":"Natural Gas",
            "type":"Services"
        }
    ],
    "sg:phone":"+1 503 585 6611",
    "sg:postcode":"97303",
    "sg:province":"OR",
    "sg:tags":[
        "company"
    ],
    "wof:name":"Northwest Natural Gas Co",
    "wof:placetype":"venue"
},
  "geometry": {"coordinates":[-123.028565,44.9686],"type":"Point"}
}