{
  "type": "Feature",
  "properties": {
    "iso:country":"US",
    "sg:address":"3800 NE Webster St",
    "sg:city":"Portland",
    "sg:classifiers":[
        {
            "category":"Building & Trades",
            "subcategory":"Locksmith",
            "type":"Services"
        }
    ],
    "sg:phone":"+1 503 937 0077",
    "sg:postcode":"97211",
    "sg:province":"OR",
    "sg:tags":[
        "key"
    ],
    "wof:name":"A Locksmith Service",
    "wof:placetype":"venue"
},
  "geometry": {"coordinates":[-122.623914,45.559388],"type":"Point"}
}