{
  "type": "Feature",
  "properties": {
    "iso:country":"US",
    "sg:address":"1221 SW 4th Ave",
    "sg:city":"Portland",
    "sg:classifiers":[
        {
            "category":"Government",
            "subcategory":"Office",
            "type":"Public Place"
        }
    ],
    "sg:phone":"+1 503 823 4120",
    "sg:postcode":"97204",
    "sg:province":"OR",
    "sg:tags":[
        "city"
    ],
    "wof:name":"Portland Mayor's Office",
    "wof:placetype":"venue"
},
  "geometry": {"coordinates":[-122.67854,45.5151],"type":"Point"}
}