{
  "type": "Feature",
  "properties": {
    "addr:full":"548 NE E St Grants Pass OR 97526",
    "addr:housenumber":"548",
    "addr:postcode":"97526",
    "addr:street":"Ne E St",
    "iso:country":"US",
    "sg:address":"548 NE E St",
    "sg:city":"Grants Pass",
    "sg:classifiers":[
        {
            "category":"Banks & Credit Unions",
            "subcategory":"Bank",
            "type":"Services"
        }
    ],
    "sg:phone":"+1 541 472 0332",
    "sg:postcode":"97526",
    "sg:province":"OR",
    "sg:tags":[
        "loan"
    ],
    "wof:name":"Professional Mortgage Group",
    "wof:placetype":"venue"
},
  "geometry": {"coordinates":[-123.31848599999999,42.439429],"type":"Point"}
}