{
  "type": "Feature",
  "properties": {
    "addr:full":"24075 Klupenger Rd NE Aurora OR 97002",
    "addr:postcode":"24075;97002",
    "addr:street":"Klupenger Rd Ne",
    "iso:country":"US",
    "sg:address":"24075 Klupenger Rd NE",
    "sg:city":"Aurora",
    "sg:classifiers":[
        {
            "category":"Airline",
            "type":"Transportation"
        },
        {
            "category":"Travel",
            "subcategory":"Travel Agent",
            "type":"Entertainment"
        }
    ],
    "sg:phone":"+1 503 678 2664",
    "sg:postcode":"97002",
    "sg:province":"OR",
    "sg:tags":[
        "ticket",
        "agency"
    ],
    "sg:website":"http://www.trac100.com",
    "wof:name":"Trac",
    "wof:placetype":"venue"
},
  "geometry": {"coordinates":[-122.80538799999999,45.268605],"type":"Point"}
}