{
  "type": "Feature",
  "properties": {
    "iso:country":"US",
    "sg:address":"101 SW Main St",
    "sg:city":"Portland",
    "sg:classifiers":[
        {
            "category":"Banks & Credit Unions",
            "subcategory":"Bank",
            "type":"Services"
        }
    ],
    "sg:phone":"+1 503 224 3345",
    "sg:postcode":"97204",
    "sg:province":"OR",
    "wof:name":"Banner Bank Portland Br #76",
    "wof:placetype":"venue"
},
  "geometry": {"coordinates":[-122.67547500000001,45.515344],"type":"Point"}
}