{
  "type": "Feature",
  "properties": {
    "addr:full":"3830 SE 14th Avenue Portland OR 97202",
    "addr:housenumber":"3830",
    "addr:postcode":"97202",
    "addr:street":"Se 14Th Avenue",
    "iso:country":"US",
    "sg:address":"3830 SE 14th Avenue",
    "sg:city":"Portland",
    "sg:classifiers":[
        {
            "category":"Education",
            "subcategory":"School",
            "type":"Public Place"
        }
    ],
    "sg:phone":"+1 503 916 6200",
    "sg:postcode":"97202",
    "sg:province":"OR",
    "wof:name":"Schools Public",
    "wof:placetype":"venue"
},
  "geometry": {"coordinates":[-122.651518,45.495157],"type":"Point"}
}