{
  "type": "Feature",
  "properties": {
    "addr:full":"6797 D Ct Springfield OR 97478",
    "addr:housenumber":"6797",
    "addr:postcode":"97478",
    "addr:street":"D Ct",
    "iso:country":"US",
    "sg:address":"6797 D Ct",
    "sg:city":"Springfield",
    "sg:classifiers":[
        {
            "category":"Banks & Credit Unions",
            "subcategory":"Financial Services",
            "type":"Services"
        }
    ],
    "sg:phone":"+1 541 747 0376",
    "sg:postcode":"97478",
    "sg:province":"OR",
    "sg:tags":[
        "trust",
        "management"
    ],
    "wof:name":"Thomas M Rose Trust",
    "wof:placetype":"venue"
},
  "geometry": {"coordinates":[-122.90613999999999,44.049604],"type":"Point"}
}