{
  "type": "Feature",
  "properties": {
    "iso:country":"US",
    "sg:address":"13611 NE Rose Pkwy",
    "sg:city":"Portland",
    "sg:classifiers":[
        {
            "category":"Freight",
            "type":"Transportation"
        }
    ],
    "sg:phone":"+1 503 262 4885",
    "sg:postcode":"97230",
    "sg:province":"OR",
    "sg:tags":[
        "delivery"
    ],
    "wof:name":"Wright Express",
    "wof:placetype":"venue"
},
  "geometry": {"coordinates":[-122.51903799999999,45.544718],"type":"Point"}
}