{
  "type": "Feature",
  "properties": {
    "iso:country":"US",
    "sg:address":"400 7th St",
    "sg:city":"Umatilla",
    "sg:classifiers":[
        {
            "category":"Place Of Worship",
            "type":"Public Place"
        }
    ],
    "sg:phone":"+1 541 922 1287",
    "sg:postcode":"97882",
    "sg:province":"OR",
    "sg:tags":[
        "church"
    ],
    "wof:name":"Primeraiglesiabautista Church",
    "wof:placetype":"venue"
},
  "geometry": {"coordinates":[-119.347618,45.91581],"type":"Point"}
}