{
  "type": "Feature",
  "properties": {
    "iso:country":"US",
    "sg:address":"13665 SW Hathaway Terr",
    "sg:city":"Tigard",
    "sg:classifiers":[
        {
            "category":"Education",
            "subcategory":"Preschool",
            "type":"Public Place"
        }
    ],
    "sg:phone":"+1 503 521 8862",
    "sg:postcode":"97223",
    "sg:province":"OR",
    "wof:name":"Early Bird Preschool + Daycare",
    "wof:placetype":"venue"
},
  "geometry": {"coordinates":[-122.804378,45.421168],"type":"Point"}
}