{
  "type": "Feature",
  "properties": {
    "iso:country":"US",
    "sg:address":"12543 NE Honey Ln",
    "sg:city":"Newberg",
    "sg:classifiers":[
        {
            "category":"Professional",
            "subcategory":"Art Services",
            "type":"Services"
        }
    ],
    "sg:phone":"+1 503 538 9635",
    "sg:postcode":"97132",
    "sg:province":"OR",
    "sg:tags":[
        "photography",
        "commercial"
    ],
    "wof:name":"Five Gables Photography",
    "wof:placetype":"venue"
},
  "geometry": {"coordinates":[-122.989479,45.304094],"type":"Point"}
}