{
  "type": "Feature",
  "properties": {
    "iso:country":"US",
    "sg:address":"1770 Prairie Rd",
    "sg:city":"Eugene",
    "sg:classifiers":[
        {
            "category":"Freight",
            "type":"Transportation"
        }
    ],
    "sg:phone":"+1 541 463 1141",
    "sg:postcode":"97402",
    "sg:province":"OR",
    "sg:tags":[
        "delivery"
    ],
    "wof:name":"American Package Express",
    "wof:placetype":"venue"
},
  "geometry": {"coordinates":[-123.159214,44.093189],"type":"Point"}
}