{
  "type": "Feature",
  "properties": {
    "addr:full":"3223 W 18th Ave Eugene OR 97402",
    "addr:housenumber":"3223",
    "addr:postcode":"97402",
    "addr:street":"W 18Th Ave",
    "iso:country":"US",
    "sg:address":"3223 W 18th Ave",
    "sg:city":"Eugene",
    "sg:classifiers":[
        {
            "category":"Health Services",
            "subcategory":"Nursing And Care Facility",
            "type":"Services"
        }
    ],
    "sg:phone":"+1 541 465 9550",
    "sg:postcode":"97402",
    "sg:province":"OR",
    "sg:tags":[
        "intermediate"
    ],
    "wof:name":"Grandmas House",
    "wof:placetype":"venue"
},
  "geometry": {"coordinates":[-123.139724,44.040725],"type":"Point"}
}