{
  "type": "Feature",
  "properties": {
    "iso:country":"US",
    "sg:address":"85895 Lorane Hwy",
    "sg:city":"Eugene",
    "sg:classifiers":[
        {
            "category":"Professional",
            "type":"Services"
        }
    ],
    "sg:phone":"+1 541 484 7125",
    "sg:postcode":"97405",
    "sg:province":"OR",
    "wof:name":"Louis Macray Inc",
    "wof:placetype":"venue"
},
  "geometry": {"coordinates":[-123.155592,43.994357],"type":"Point"}
}