{
  "type": "Feature",
  "properties": {
    "iso:country":"US",
    "sg:address":"2127 N Albina Ave",
    "sg:city":"Portland",
    "sg:classifiers":[
        {
            "category":"Professional",
            "type":"Services"
        }
    ],
    "sg:phone":"+1 503 281 2175",
    "sg:postcode":"97227",
    "sg:province":"OR",
    "sg:tags":[
        "arts",
        "artist"
    ],
    "wof:name":"Vary Limited",
    "wof:placetype":"venue"
},
  "geometry": {"coordinates":[-122.675487,45.538343],"type":"Point"}
}