{
  "type": "Feature",
  "properties": {
    "addr:full":"524 Market St Klamath Falls OR 97601",
    "addr:housenumber":"524",
    "addr:postcode":"97601",
    "addr:street":"Market St",
    "iso:country":"US",
    "sg:address":"524 Market St",
    "sg:city":"Klamath Falls",
    "sg:classifiers":[
        {
            "category":"Wholesale",
            "subcategory":"Scrap",
            "type":"Manufacturing & Wholesale Goods"
        }
    ],
    "sg:phone":"+1 541 882 4895",
    "sg:postcode":"97601",
    "sg:province":"OR",
    "sg:tags":[
        "recycling",
        "center"
    ],
    "wof:name":"KFGM",
    "wof:placetype":"venue"
},
  "geometry": {"coordinates":[-121.77424999999999,42.22425],"type":"Point"}
}