{
  "type": "Feature",
  "properties": {
    "iso:country":"US",
    "sg:address":"2007 NW Ivy Pl",
    "sg:city":"Redmond",
    "sg:classifiers":[
        {
            "category":"Education",
            "subcategory":"Vocational School",
            "type":"Public Place"
        },
        {
            "category":"Shopping",
            "subcategory":"Computers & Home Electronics",
            "type":"Retail Goods"
        }
    ],
    "sg:phone":"+1 541 504 0817",
    "sg:postcode":"97756",
    "sg:province":"OR",
    "sg:tags":[
        "processing",
        "datum",
        "software"
    ],
    "sg:website":"www.ezofficetraining.com",
    "wof:name":"E Z Office Training",
    "wof:placetype":"venue"
},
  "geometry": {"coordinates":[-121.19082,44.284236],"type":"Point"}
}