{
  "type": "Feature",
  "properties": {
    "iso:country":"US",
    "sg:address":"315 E Main St",
    "sg:city":"Silverton",
    "sg:classifiers":[
        {
            "category":"Banks & Credit Unions",
            "subcategory":"Bank",
            "type":"Services"
        }
    ],
    "sg:phone":"+1 503 873 5376",
    "sg:postcode":"97381",
    "sg:province":"OR",
    "wof:name":"West Coast Bank",
    "wof:placetype":"venue"
},
  "geometry": {"coordinates":[-122.781119,45.005951],"type":"Point"}
}