{
  "type": "Feature",
  "properties": {
    "iso:country":"US",
    "sg:address":"1225 NW Murray Rd",
    "sg:city":"Portland",
    "sg:classifiers":[
        {
            "category":"Banks & Credit Unions",
            "subcategory":"Bank",
            "type":"Services"
        }
    ],
    "sg:phone":"+1 503 643 7369",
    "sg:postcode":"97229",
    "sg:province":"OR",
    "sg:tags":[
        "loan",
        "real estate"
    ],
    "wof:name":"Financial Group",
    "wof:placetype":"venue"
},
  "geometry": {"coordinates":[-122.813056,45.528148],"type":"Point"}
}