{
  "type": "Feature",
  "properties": {
    "iso:country":"US",
    "sg:address":"943 Automation Way",
    "sg:city":"Medford",
    "sg:classifiers":[
        {
            "category":"Retail",
            "subcategory":"Auto Repair",
            "type":"Services"
        }
    ],
    "sg:phone":"+1 541 779 6050",
    "sg:postcode":"97504",
    "sg:province":"OR",
    "sg:tags":[
        "glass",
        "coating",
        "tinting"
    ],
    "wof:name":"Eclipse Window Tinting",
    "wof:placetype":"venue"
},
  "geometry": {"coordinates":[-122.87797999999999,42.361652],"type":"Point"}
}