{
  "type": "Feature",
  "properties": {
    "iso:country":"US",
    "sg:address":"316 Osage Dr",
    "sg:city":"Roseburg",
    "sg:classifiers":[
        {
            "category":"Wholesale",
            "subcategory":"Construction Materials",
            "type":"Manufacturing & Wholesale Goods"
        }
    ],
    "sg:phone":"+1 541 673 7021",
    "sg:postcode":"97470",
    "sg:province":"OR",
    "wof:name":"Roseburg Sand and Gravel",
    "wof:placetype":"venue"
},
  "geometry": {"coordinates":[-123.404521,43.276571],"type":"Point"}
}