{
  "type": "Feature",
  "properties": {
    "iso:country":"US",
    "sg:address":"1395 Cole Rd S",
    "sg:city":"Salem",
    "sg:classifiers":[
        {
            "category":"Retail",
            "subcategory":"Repair Shop",
            "type":"Services"
        }
    ],
    "sg:phone":"+1 503 362 7835",
    "sg:postcode":"97306",
    "sg:province":"OR",
    "wof:name":"Seeco Equipment Repair",
    "wof:placetype":"venue"
},
  "geometry": {"coordinates":[-123.06682600000001,44.849071],"type":"Point"}
}