{
  "type": "Feature",
  "properties": {
    "iso:country":"US",
    "sg:address":"6030 NE 112th Avenue",
    "sg:city":"Portland",
    "sg:classifiers":[
        {
            "category":"Shopping",
            "subcategory":"Florist",
            "type":"Retail Goods"
        }
    ],
    "sg:phone":"+1 503 255 2002",
    "sg:postcode":"97220",
    "sg:province":"OR",
    "wof:name":"Howell's Craftland",
    "wof:placetype":"venue"
},
  "geometry": {"coordinates":[-122.547291,45.566223],"type":"Point"}
}