{
  "type": "Feature",
  "properties": {
    "addr:full":"1632 Williams Hwy Grants Pass OR 97527",
    "addr:housenumber":"1632",
    "addr:postcode":"97527",
    "addr:street":"Williams Hwy",
    "iso:country":"US",
    "sg:address":"1632 Williams Hwy",
    "sg:city":"Grants Pass",
    "sg:classifiers":[
        {
            "category":"Restaurant",
            "type":"Food & Drink"
        }
    ],
    "sg:menulink":"http://www.allmenus.com/or/grants-pass/116086-quiznos-sub/menu/",
    "sg:phone":"+1 541 476 1942",
    "sg:postcode":"97527",
    "sg:province":"OR",
    "sg:tags":[
        "wrap",
        "american",
        "sandwich"
    ],
    "wof:name":"Quiznos Sub",
    "wof:placetype":"venue"
},
  "geometry": {"coordinates":[-123.333108,42.42157],"type":"Point"}
}