{
  "type": "Feature",
  "properties": {
    "addr:full":"14050 de Armond Rd Monmouth OR 97361",
    "addr:postcode":"14050;97361",
    "addr:street":"Armond Rd",
    "iso:country":"US",
    "sg:address":"14050 de Armond Rd",
    "sg:city":"Monmouth",
    "sg:phone":"+1 503 838 1880",
    "sg:postcode":"97361",
    "sg:province":"OR",
    "sg:tags":[
        "farm",
        "field",
        "crop"
    ],
    "wof:name":"Mulkey Gylan",
    "wof:placetype":"venue"
},
  "geometry": {"coordinates":[-123.26790699999999,44.731125],"type":"Point"}
}