{
  "type": "Feature",
  "properties": {
    "addr:full":"310 NE 147th Ave Portland OR 97230",
    "addr:housenumber":"310",
    "addr:postcode":"97230",
    "addr:street":"Ne 147Th Ave",
    "iso:country":"US",
    "sg:address":"310 NE 147th Ave",
    "sg:city":"Portland",
    "sg:classifiers":[
        {
            "category":"Professional",
            "subcategory":"Business Services",
            "type":"Services"
        }
    ],
    "sg:phone":"+1 503 460 3992",
    "sg:postcode":"97230",
    "sg:province":"OR",
    "sg:tags":[
        "embroidery",
        "supply"
    ],
    "wof:name":"Kaleidoscope Design",
    "wof:placetype":"venue"
},
  "geometry": {"coordinates":[-122.511937,45.524841],"type":"Point"}
}