{
  "type": "Feature",
  "properties": {
    "addr:full":"619 Marr Pond Ln Enterprise OR 97828",
    "addr:housenumber":"619",
    "addr:postcode":"97828",
    "addr:street":"Marr Pond Ln",
    "iso:country":"US",
    "sg:address":"619 Marr Pond Ln",
    "sg:city":"Enterprise",
    "sg:classifiers":[
        {
            "category":"Government",
            "subcategory":"Office",
            "type":"Public Place"
        }
    ],
    "sg:phone":"+1 541 426 3332",
    "sg:postcode":"97828",
    "sg:province":"OR",
    "wof:name":"Wallowa County Road Supt",
    "wof:placetype":"venue"
},
  "geometry": {"coordinates":[-117.289655,45.420461],"type":"Point"}
}