{
  "type": "Feature",
  "properties": {
    "addr:full":"4050 Fairview Industrial Dr SE Salem OR 97302",
    "addr:housenumber":"4050",
    "addr:postcode":"97302",
    "addr:street":"Fairview Industrial Dr Se",
    "iso:country":"US",
    "sg:address":"4050 Fairview Industrial Dr SE",
    "sg:city":"Salem",
    "sg:classifiers":[
        {
            "category":"Home & Garden",
            "subcategory":"Garden Supply",
            "type":"Retail Goods"
        },
        {
            "category":"Food & Beverages",
            "subcategory":"Farmers Market",
            "type":"Retail Goods"
        },
        {
            "category":"Shopping",
            "subcategory":"Pets & Pet Supplies",
            "type":"Retail Goods"
        }
    ],
    "sg:phone":"+1 503 362 9700",
    "sg:postcode":"97302",
    "sg:province":"OR",
    "sg:tags":[
        "feed",
        "bulbs-wholesale",
        "concentrate",
        "supplement",
        "bulb",
        "seed",
        "grower"
    ],
    "wof:name":"Bailey Seed Co., Inc.",
    "wof:placetype":"venue"
},
  "geometry": {"coordinates":[-122.998706,44.894005],"type":"Point"}
}