{
  "type": "Feature",
  "properties": {
    "addr:full":"9810 NE Cascades Pkwy Portland OR 97220",
    "addr:housenumber":"9810",
    "addr:postcode":"97220",
    "addr:street":"Ne Cascades Pkwy",
    "iso:country":"US",
    "sg:address":"9810 NE Cascades Pkwy",
    "sg:city":"Portland",
    "sg:classifiers":[
        {
            "category":"Fast Food",
            "type":"Food & Drink"
        }
    ],
    "sg:phone":"+1 503 281 0351",
    "sg:postcode":"97220",
    "sg:province":"OR",
    "sg:tags":[
        "chicken",
        "wing"
    ],
    "sg:website":"www.buffalowildwings.com",
    "wof:name":"Buffalo Wild Wings",
    "wof:placetype":"venue"
},
  "geometry": {"coordinates":[-122.561913,45.573955],"type":"Point"}
}