{
  "type": "Feature",
  "properties": {
    "addr:full":"1513 SE 122nd Ave Portland OR 97233",
    "addr:housenumber":"1513",
    "addr:postcode":"97233",
    "addr:street":"Se 122Nd Ave",
    "iso:country":"US",
    "sg:address":"1513 SE 122nd Ave",
    "sg:city":"Portland",
    "sg:classifiers":[
        {
            "category":"Health Services",
            "subcategory":"Medical Lab",
            "type":"Services"
        }
    ],
    "sg:phone":"+1 503 274 1372",
    "sg:postcode":"97233",
    "sg:province":"OR",
    "wof:name":"Franklin Denture Ctr",
    "wof:placetype":"venue"
},
  "geometry": {"coordinates":[-122.537724,45.511623],"type":"Point"}
}