{
  "type": "Feature",
  "properties": {
    "iso:country":"US",
    "sg:address":"2998 Maranatha Ct SE",
    "sg:city":"Turner",
    "sg:classifiers":[
        {
            "category":"Shopping",
            "subcategory":"Hobbies, Toys, & Games",
            "type":"Retail Goods"
        },
        {
            "category":"Shopping",
            "subcategory":"Catalog Store",
            "type":"Retail Goods"
        }
    ],
    "sg:phone":"+1 503 371 3711",
    "sg:postcode":"97392",
    "sg:province":"OR",
    "sg:tags":[
        "mail",
        "online",
        "order",
        "supply"
    ],
    "wof:name":"Hide 'N' Seek Inc.",
    "wof:placetype":"venue"
},
  "geometry": {"coordinates":[-123.001137,44.84063],"type":"Point"}
}