{
  "type": "Feature",
  "properties": {
    "addr:full":"2100 SE Belmont St Portland OR 97214",
    "addr:housenumber":"2100",
    "addr:postcode":"97214",
    "addr:street":"Se Belmont St",
    "iso:country":"US",
    "sg:address":"2100 SE Belmont St",
    "sg:city":"Portland",
    "sg:classifiers":[
        {
            "category":"Building & Trades",
            "subcategory":"Landscaping Services",
            "type":"Services"
        },
        {
            "category":"Shopping",
            "subcategory":"Pets & Pet Supplies",
            "type":"Retail Goods"
        }
    ],
    "sg:phone":"+1 503 234 7733",
    "sg:postcode":"97214",
    "sg:province":"OR",
    "sg:tags":[
        "store",
        "gardener"
    ],
    "sg:website":"www.urbanfarmstore.com",
    "wof:name":"Urban Farm Store",
    "wof:placetype":"venue"
},
  "geometry": {"coordinates":[-122.64433099999999,45.516244],"type":"Point"}
}