{
  "type": "Feature",
  "properties": {
    "iso:country":"US",
    "sg:address":"1300 SW 6th Ave",
    "sg:city":"Portland",
    "sg:classifiers":[
        {
            "category":"Education",
            "subcategory":"Library",
            "type":"Public Place"
        }
    ],
    "sg:phone":"+1 503 419 4053",
    "sg:postcode":"97201",
    "sg:province":"OR",
    "wof:name":"Quick & Reilly Branch 1",
    "wof:placetype":"venue"
},
  "geometry": {"coordinates":[-122.68113,45.514409],"type":"Point"}
}