{
  "type": "Feature",
  "properties": {
    "iso:country":"US",
    "sg:address":"1430 Vermont St",
    "sg:city":"North Bend",
    "sg:classifiers":[
        {
            "category":"Restaurant",
            "type":"Food & Drink"
        }
    ],
    "sg:phone":"+1 541 756 0906",
    "sg:postcode":"97459",
    "sg:province":"OR",
    "sg:tags":[
        "eating"
    ],
    "wof:name":"LA Herradura",
    "wof:placetype":"venue"
},
  "geometry": {"coordinates":[-124.231818,43.403776],"type":"Point"}
}