{
  "type": "Feature",
  "properties": {
    "iso:country":"US",
    "sg:address":"62911 Peerless Ct",
    "sg:city":"Bend",
    "sg:classifiers":[
        {
            "category":"Utilities",
            "subcategory":"Water",
            "type":"Services"
        },
        {
            "category":"Wholesale",
            "subcategory":"Beer",
            "type":"Manufacturing & Wholesale Goods"
        },
        {
            "category":"Food & Beverages",
            "subcategory":"Liquor & Beverages",
            "type":"Retail Goods"
        },
        {
            "category":"Wholesale",
            "subcategory":"Vending Machines",
            "type":"Manufacturing & Wholesale Goods"
        }
    ],
    "sg:phone":"+1 541 382 3161",
    "sg:postcode":"97701",
    "sg:province":"OR",
    "sg:tags":[
        "bulk",
        "companies-bottled",
        "bottler",
        "beverages-distributors"
    ],
    "sg:website":"http://www.cokeconsolidated.com",
    "wof:name":"Coca Cola Bottling Co. Consolidated",
    "wof:placetype":"venue"
},
  "geometry": {"coordinates":[-121.291845,44.084444],"type":"Point"}
}