{
  "type": "Feature",
  "properties": {
    "iso:country":"US",
    "sg:address":"3565 SE 82nd Ave",
    "sg:city":"Portland",
    "sg:phone":"+1 503 771 2066",
    "sg:postcode":"97266",
    "sg:province":"OR",
    "wof:name":"B & J Auto Sales",
    "wof:placetype":"venue"
},
  "geometry": {"coordinates":[-122.578745,45.496662],"type":"Point"}
}