{
  "type": "Feature",
  "properties": {
    "iso:country":"US",
    "sg:address":"19221 SW Martinazzi Ave",
    "sg:city":"Tualatin",
    "sg:classifiers":[
        {
            "category":"Building & Trades",
            "subcategory":"Locksmith",
            "type":"Services"
        }
    ],
    "sg:phone":"+1 503 404 0446",
    "sg:postcode":"97062",
    "sg:province":"OR",
    "sg:tags":[
        "key"
    ],
    "wof:name":"1 After Dringking Locksmith Rescue",
    "wof:placetype":"venue"
},
  "geometry": {"coordinates":[-122.759235,45.380944],"type":"Point"}
}