{
  "type": "Feature",
  "properties": {
    "iso:country":"US",
    "sg:address":"1880 E Baseline St",
    "sg:city":"Cornelius",
    "sg:classifiers":[
        {
            "category":"Restaurant",
            "type":"Food & Drink"
        }
    ],
    "sg:phone":"+1 503 359 0447",
    "sg:postcode":"97113",
    "sg:province":"OR",
    "wof:name":"Bascos Burgers",
    "wof:placetype":"venue"
},
  "geometry": {"coordinates":[-123.049336,45.52014],"type":"Point"}
}