{
  "type": "Feature",
  "properties": {
    "addr:full":"7130 NE Mineral Springs Rd Carlton OR 97111",
    "addr:housenumber":"7130",
    "addr:postcode":"97111",
    "addr:street":"Ne Mineral Springs Rd",
    "iso:country":"US",
    "sg:address":"7130 NE Mineral Springs Rd",
    "sg:city":"Carlton",
    "sg:classifiers":[
        {
            "category":"Social Services",
            "subcategory":"Child Care",
            "type":"Services"
        }
    ],
    "sg:phone":"+1 503 852 7385",
    "sg:postcode":"97111",
    "sg:province":"OR",
    "wof:name":"Just 4 Kids Childcare",
    "wof:placetype":"venue"
},
  "geometry": {"coordinates":[-123.139471,45.266928],"type":"Point"}
}