{
  "type": "Feature",
  "properties": {
    "iso:country":"US",
    "sg:address":"1950 Echo Hollow Rd Ste A",
    "sg:city":"Eugene",
    "sg:classifiers":[
        {
            "category":"Donuts",
            "subcategory":"None",
            "type":"Food & Drink"
        }
    ],
    "sg:phone":"+1 541 607 9848",
    "sg:postcode":"97402",
    "sg:province":"OR",
    "sg:tags":[
        "shop"
    ],
    "wof:name":"Lee's Donuts",
    "wof:placetype":"venue"
},
  "geometry": {"coordinates":[-123.16811800000001,44.083683],"type":"Point"}
}