{
  "type": "Feature",
  "properties": {
    "addr:full":"909 S Holladay Dr Seaside OR 97138",
    "addr:housenumber":"909",
    "addr:postcode":"97138",
    "addr:street":"S Holladay Dr",
    "iso:country":"US",
    "sg:address":"909 S Holladay Dr",
    "sg:city":"Seaside",
    "sg:classifiers":[
        {
            "category":"Shopping",
            "subcategory":"Department Store",
            "type":"Retail Goods"
        }
    ],
    "sg:phone":"+1 503 738 0600",
    "sg:postcode":"97138",
    "sg:province":"OR",
    "wof:name":"Allways 99 Cents Super Store",
    "wof:placetype":"venue"
},
  "geometry": {"coordinates":[-123.923489,45.988074],"type":"Point"}
}