{
  "type": "Feature",
  "properties": {
    "addr:full":"5455 SW Brendon Ct Beaverton OR 97005",
    "addr:housenumber":"5455",
    "addr:postcode":"97005",
    "addr:street":"Sw Brendon Ct",
    "iso:country":"US",
    "sg:address":"5455 SW Brendon Ct",
    "sg:city":"Beaverton",
    "sg:classifiers":[
        {
            "category":"Building & Trades",
            "subcategory":"Cleaning & Sanitation",
            "type":"Services"
        }
    ],
    "sg:phone":"+1 503 641 2079",
    "sg:postcode":"97005",
    "sg:province":"OR",
    "sg:tags":[
        "maintenance"
    ],
    "wof:name":"Joanns Clean Sweep",
    "wof:placetype":"venue"
},
  "geometry": {"coordinates":[-122.820976,45.480164],"type":"Point"}
}