{
  "type": "Feature",
  "properties": {
    "iso:country":"US",
    "sg:address":"3551 2nd St",
    "sg:city":"Hubbard",
    "sg:classifiers":[
        {
            "category":"Building & Trades",
            "subcategory":"Construction",
            "type":"Services"
        }
    ],
    "sg:phone":"+1 503 981 5222",
    "sg:postcode":"97032",
    "sg:province":"OR",
    "sg:tags":[
        "system",
        "specialty",
        "heating",
        "mechanical",
        "contractor",
        "air conditioning"
    ],
    "wof:name":"Thermopower Industries Inc",
    "wof:placetype":"venue"
},
  "geometry": {"coordinates":[-122.806454,45.181795],"type":"Point"}
}