{
  "type": "Feature",
  "properties": {
    "addr:full":"180 Warren St S Monmouth OR 97361",
    "addr:housenumber":"180",
    "addr:postcode":"97361",
    "addr:street":"Warren St S",
    "iso:country":"US",
    "sg:address":"180 Warren St S",
    "sg:city":"Monmouth",
    "sg:classifiers":[
        {
            "category":"Social Services",
            "type":"Services"
        }
    ],
    "sg:phone":"+1 503 838 5678",
    "sg:postcode":"97361",
    "sg:province":"OR",
    "wof:name":"Senior Monmouth Center",
    "wof:placetype":"venue"
},
  "geometry": {"coordinates":[-123.235834,44.847648],"type":"Point"}
}