{
  "type": "Feature",
  "properties": {
    "addr:full":"1780 Columbia Blvd Saint Helens OR 97051",
    "addr:housenumber":"1780",
    "addr:postcode":"97051",
    "addr:street":"Columbia Blvd",
    "iso:country":"US",
    "sg:address":"1780 Columbia Blvd",
    "sg:city":"Saint Helens",
    "sg:classifiers":[
        {
            "category":"Autos & Motor Vehicles",
            "subcategory":"Auto Supplies",
            "type":"Retail Goods"
        }
    ],
    "sg:phone":"+1 503 397 3145",
    "sg:postcode":"97051",
    "sg:province":"OR",
    "sg:tags":[
        "automobile",
        "used"
    ],
    "wof:name":"Eatons Tire & Auto Repair",
    "wof:placetype":"venue"
},
  "geometry": {"coordinates":[-122.815657,45.859136],"type":"Point"}
}