{
  "type": "Feature",
  "properties": {
    "addr:full":"388 State St Salem OR 97301",
    "addr:housenumber":"388",
    "addr:postcode":"97301",
    "addr:street":"State St",
    "iso:country":"US",
    "sg:address":"388 State St",
    "sg:city":"Salem",
    "sg:classifiers":[
        {
            "category":"Government",
            "subcategory":"Office",
            "type":"Public Place"
        }
    ],
    "sg:phone":"+1 503 588 5169",
    "sg:postcode":"97301",
    "sg:province":"OR",
    "sg:tags":[
        "county",
        "program"
    ],
    "wof:name":"Marion County Solid Waste Mgmt",
    "wof:placetype":"venue"
},
  "geometry": {"coordinates":[-123.04031000000001,44.940258],"type":"Point"}
}