{
  "type": "Feature",
  "properties": {
    "iso:country":"US",
    "sg:address":"2761 Loop Rd",
    "sg:city":"Vale",
    "sg:classifiers":[
        {
            "category":"Farming",
            "subcategory":"Livestock Farm",
            "type":"Manufacturing & Wholesale Goods"
        }
    ],
    "sg:phone":"+1 541 473 3445",
    "sg:postcode":"97918",
    "sg:province":"OR",
    "sg:tags":[
        "feedlot",
        "grain",
        "cash",
        "beef",
        "cattle"
    ],
    "wof:name":"Randy Hyde",
    "wof:placetype":"venue"
},
  "geometry": {"coordinates":[-117.39690299999999,43.96871],"type":"Point"}
}