{
  "type": "Feature",
  "properties": {
    "addr:full":"12900 SE Powell Boulevard Portland OR 97236",
    "addr:housenumber":"12900",
    "addr:postcode":"97236",
    "addr:street":"Se Powell Boulevard",
    "iso:country":"US",
    "sg:address":"12900 SE Powell Boulevard",
    "sg:city":"Portland",
    "sg:classifiers":[
        {
            "category":"Social Services",
            "subcategory":"Child Care",
            "type":"Services"
        }
    ],
    "sg:phone":"+1 503 760 6783",
    "sg:postcode":"97236",
    "sg:province":"OR",
    "sg:tags":[
        "day"
    ],
    "wof:name":"Shannon's Child Care & Preschool",
    "wof:placetype":"venue"
},
  "geometry": {"coordinates":[-122.530903,45.497195],"type":"Point"}
}