{
  "type": "Feature",
  "properties": {
    "iso:country":"US",
    "sg:address":"3348 NW 17th Tee Pl",
    "sg:city":"Bend",
    "sg:classifiers":[
        {
            "category":"Professional",
            "subcategory":"Accounting & Tax Preparation",
            "type":"Services"
        }
    ],
    "sg:phone":"+1 541 385 4746",
    "sg:postcode":"97701",
    "sg:province":"OR",
    "sg:tags":[
        "bookkeeping",
        "billing"
    ],
    "wof:name":"Berner Bookkeeping",
    "wof:placetype":"venue"
},
  "geometry": {"coordinates":[-121.31610499999999,44.085277],"type":"Point"}
}