{
  "type": "Feature",
  "properties": {
    "iso:country":"US",
    "sg:address":"123 E Powell Blvd Ste 208",
    "sg:city":"Gresham",
    "sg:classifiers":[
        {
            "category":"Professional",
            "subcategory":"Lawyer & Legal Services",
            "type":"Services"
        }
    ],
    "sg:phone":"+1 503 666 3407",
    "sg:postcode":"97030",
    "sg:province":"OR",
    "sg:tags":[
        "attorney",
        "practice"
    ],
    "wof:name":"Rezvani Law Office",
    "wof:placetype":"venue"
},
  "geometry": {"coordinates":[-122.429541,45.498001],"type":"Point"}
}