{
  "type": "Feature",
  "properties": {
    "iso:country":"US",
    "sg:address":"16301 SE 82nd Dr",
    "sg:city":"Clackamas",
    "sg:classifiers":[
        {
            "category":"Shopping",
            "subcategory":"Optical Goods",
            "type":"Retail Goods"
        }
    ],
    "sg:phone":"+1 503 657 9504",
    "sg:postcode":"97015",
    "sg:province":"OR",
    "wof:name":"National Vision",
    "wof:placetype":"venue"
},
  "geometry": {"coordinates":[-122.568961,45.405788],"type":"Point"}
}