{
  "type": "Feature",
  "properties": {
    "iso:country":"US",
    "sg:address":"12900 State Hwy 212",
    "sg:city":"Clackamas",
    "sg:classifiers":[
        {
            "category":"Professional",
            "type":"Services"
        }
    ],
    "sg:phone":"+1 503 722 2127",
    "sg:postcode":"97015",
    "sg:province":"OR",
    "wof:name":"Wakeside LLC",
    "wof:placetype":"venue"
},
  "geometry": {"coordinates":[-122.53069600000001,45.408882],"type":"Point"}
}