{
  "type": "Feature",
  "properties": {
    "iso:country":"US",
    "sg:address":"15985 NW Schendel Ave Ste 100",
    "sg:city":"Beaverton",
    "sg:classifiers":[
        {
            "category":"Professional",
            "subcategory":"Employment Agencies",
            "type":"Services"
        }
    ],
    "sg:phone":"+1 503 617 2979",
    "sg:postcode":"97006",
    "sg:province":"OR",
    "wof:name":"Sfi Staff Finders Inc",
    "wof:placetype":"venue"
},
  "geometry": {"coordinates":[-122.841003,45.519798],"type":"Point"}
}