{
  "type": "Feature",
  "properties": {
    "iso:country":"US",
    "sg:address":"147 Barker Ave",
    "sg:city":"Oregon City",
    "sg:classifiers":[
        {
            "category":"Building & Trades",
            "subcategory":"Construction",
            "type":"Services"
        }
    ],
    "sg:phone":"+1 503 656 5502",
    "sg:postcode":"97045",
    "sg:province":"OR",
    "sg:tags":[
        "house"
    ],
    "wof:name":"Kevin L Sproul Construction",
    "wof:placetype":"venue"
},
  "geometry": {"coordinates":[-122.62156400000001,45.342718],"type":"Point"}
}