{
  "type": "Feature",
  "properties": {
    "iso:country":"US",
    "sg:address":"15635 SE 114th Ave",
    "sg:city":"Clackamas",
    "sg:classifiers":[
        {
            "category":"Wholesale",
            "subcategory":"Construction Materials",
            "type":"Manufacturing & Wholesale Goods"
        }
    ],
    "sg:phone":"+1 503 777 4009",
    "sg:postcode":"97015",
    "sg:province":"OR",
    "sg:tags":[
        "glass"
    ],
    "sg:website":"www.spiritofglass.com",
    "wof:name":"SOS Thin Films",
    "wof:placetype":"venue"
},
  "geometry": {"coordinates":[-122.552026,45.408417],"type":"Point"}
}