{
  "type": "Feature",
  "properties": {
    "iso:country":"US",
    "sg:address":"2007 W 2nd St",
    "sg:city":"The Dalles",
    "sg:classifiers":[
        {
            "category":"Wholesale",
            "subcategory":"Machinery & Supplies",
            "type":"Manufacturing & Wholesale Goods"
        }
    ],
    "sg:phone":"+1 541 296 5466",
    "sg:postcode":"97058",
    "sg:province":"OR",
    "sg:tags":[
        "machine",
        "equipment",
        "welding"
    ],
    "wof:name":"Mid Columbia Welders Supply Co",
    "wof:placetype":"venue"
},
  "geometry": {"coordinates":[-121.204664,45.612291],"type":"Point"}
}