{
  "type": "Feature",
  "properties": {
    "addr:full":"9840 SW 32nd Ave Portland OR 97219",
    "addr:housenumber":"9840",
    "addr:postcode":"97219",
    "addr:street":"Sw 32Nd Ave",
    "iso:country":"US",
    "sg:address":"9840 SW 32nd Ave",
    "sg:city":"Portland",
    "sg:classifiers":[
        {
            "category":"Real Estate",
            "subcategory":"Real Estate Agent",
            "type":"Services"
        }
    ],
    "sg:phone":"+1 503 228 8585",
    "sg:postcode":"97219",
    "sg:province":"OR",
    "sg:tags":[
        "appraiser"
    ],
    "wof:name":"Commercial Real Estate Apprsng",
    "wof:placetype":"venue"
},
  "geometry": {"coordinates":[-122.70962,45.453208],"type":"Point"}
}