{
  "type": "Feature",
  "properties": {
    "addr:full":"3214 SW Xero Ave Redmond OR 97756",
    "addr:housenumber":"3214",
    "addr:postcode":"97756",
    "addr:street":"Sw Xero Ave",
    "iso:country":"US",
    "sg:address":"3214 SW Xero Ave",
    "sg:city":"Redmond",
    "sg:classifiers":[
        {
            "category":"Professional",
            "subcategory":"Employment Agencies",
            "type":"Services"
        }
    ],
    "sg:phone":"+1 541 504 0038",
    "sg:postcode":"97756",
    "sg:province":"OR",
    "sg:tags":[
        "truck",
        "driver"
    ],
    "wof:name":"Thomas N Scourfield",
    "wof:placetype":"venue"
},
  "geometry": {"coordinates":[-121.208085,44.244335],"type":"Point"}
}