{
  "type": "Feature",
  "properties": {
    "addr:full":"60759 Currant Way Bend OR 97702",
    "addr:housenumber":"60759",
    "addr:postcode":"97702",
    "addr:street":"Currant Way",
    "iso:country":"US",
    "sg:address":"60759 Currant Way",
    "sg:city":"Bend",
    "sg:classifiers":[
        {
            "category":"Real Estate",
            "subcategory":"Developer",
            "type":"Services"
        }
    ],
    "sg:phone":"+1 541 385 9285",
    "sg:postcode":"97702",
    "sg:province":"OR",
    "wof:name":"Hulsey Development Co",
    "wof:placetype":"venue"
},
  "geometry": {"coordinates":[-121.385119,44.006809],"type":"Point"}
}