{
  "type": "Feature",
  "properties": {
    "iso:country":"US",
    "sg:address":"1969 SE Elkwood Ct",
    "sg:city":"Bend",
    "sg:classifiers":[
        {
            "category":"Professional",
            "subcategory":"Art Services",
            "type":"Services"
        }
    ],
    "sg:phone":"+1 541 382 1353",
    "sg:postcode":"97702",
    "sg:province":"OR",
    "sg:tags":[
        "commercial",
        "design"
    ],
    "wof:name":"Pjs Graphics",
    "wof:placetype":"venue"
},
  "geometry": {"coordinates":[-121.274762,44.039329],"type":"Point"}
}