{
  "type": "Feature",
  "properties": {
    "iso:country":"US",
    "sg:address":"6965 Wheatland Rd N",
    "sg:city":"Keizer",
    "sg:classifiers":[
        {
            "category":"Building & Trades",
            "subcategory":"Landscaping Services",
            "type":"Services"
        }
    ],
    "sg:phone":"+1 503 393 5923",
    "sg:postcode":"97303",
    "sg:province":"OR",
    "sg:tags":[
        "spraying"
    ],
    "wof:name":"Springer Spray Svc",
    "wof:placetype":"venue"
},
  "geometry": {"coordinates":[-123.024998,45.020039],"type":"Point"}
}