{
  "type": "Feature",
  "properties": {
    "iso:country":"US",
    "sg:address":"905 Main St",
    "sg:city":"Klamath Falls",
    "sg:classifiers":[
        {
            "category":"Health Services",
            "subcategory":"Doctor",
            "type":"Services"
        }
    ],
    "sg:phone":"+1 541 883 6370",
    "sg:postcode":"97601",
    "sg:province":"OR",
    "wof:name":"Arthur Belsky",
    "wof:placetype":"venue"
},
  "geometry": {"coordinates":[-121.779993,42.227043],"type":"Point"}
}