{
  "type": "Feature",
  "properties": {
    "addr:full":"1254 NW Civic Dr Gresham OR 97030",
    "addr:housenumber":"1254",
    "addr:postcode":"97030",
    "addr:street":"Nw Civic Dr",
    "iso:country":"US",
    "sg:address":"1254 NW Civic Dr",
    "sg:city":"Gresham",
    "sg:classifiers":[
        {
            "category":"Shopping",
            "subcategory":"Clothing, Apparel, & Fashions",
            "type":"Retail Goods"
        }
    ],
    "sg:phone":"+1 503 665 3126",
    "sg:postcode":"97030",
    "sg:province":"OR",
    "sg:tags":[
        "item",
        "boutique"
    ],
    "wof:name":"Claire's",
    "wof:placetype":"venue"
},
  "geometry": {"coordinates":[-122.441013,45.506216],"type":"Point"}
}