{
  "type": "Feature",
  "properties": {
    "addr:full":"4990 NE Logan Rd Lincoln City OR 97367",
    "addr:housenumber":"4990",
    "addr:postcode":"97367",
    "addr:street":"Ne Logan Rd",
    "iso:country":"US",
    "sg:address":"4990 NE Logan Rd",
    "sg:city":"Lincoln City",
    "sg:classifiers":[
        {
            "category":"Professional",
            "subcategory":"Business Services",
            "type":"Services"
        }
    ],
    "sg:phone":"+1 541 994 1777",
    "sg:postcode":"97367",
    "sg:province":"OR",
    "sg:tags":[
        "operation"
    ],
    "sg:website":"www.libertyinn.com",
    "wof:name":"Liberty Inn",
    "wof:placetype":"venue"
},
  "geometry": {"coordinates":[-124.004475,45.001506],"type":"Point"}
}