{
  "type": "Feature",
  "properties": {
    "addr:full":"2504 Glengary Loop Rd Roseburg OR 97470",
    "addr:housenumber":"2504",
    "addr:postcode":"97470",
    "addr:street":"Glengary Loop Rd",
    "iso:country":"US",
    "sg:address":"2504 Glengary Loop Rd",
    "sg:city":"Roseburg",
    "sg:classifiers":[
        {
            "category":"Retail",
            "subcategory":"Auto Repair",
            "type":"Services"
        }
    ],
    "sg:phone":"+1 541 679 0299",
    "sg:postcode":"97470",
    "sg:province":"OR",
    "sg:tags":[
        "exhaust"
    ],
    "wof:name":"Mufflers & More",
    "wof:placetype":"venue"
},
  "geometry": {"coordinates":[-123.330923,43.126142],"type":"Point"}
}