{
  "type": "Feature",
  "properties": {
    "iso:country":"US",
    "sg:address":"4930 Chauncy Ct SE",
    "sg:city":"Salem",
    "sg:classifiers":[
        {
            "category":"Shopping",
            "subcategory":"Computers & Home Electronics",
            "type":"Retail Goods"
        }
    ],
    "sg:phone":"+1 503 584 0847",
    "sg:postcode":"97302",
    "sg:province":"OR",
    "wof:name":"Sound Waves",
    "wof:placetype":"venue"
},
  "geometry": {"coordinates":[-123.01880300000001,44.883692],"type":"Point"}
}