{
  "type": "Feature",
  "properties": {
    "addr:full":"1112 Adams Ave La Grande OR 97850",
    "addr:housenumber":"1112",
    "addr:postcode":"97850",
    "addr:street":"Adams Ave",
    "iso:country":"US",
    "sg:address":"1112 Adams Ave",
    "sg:city":"La Grande",
    "sg:classifiers":[
        {
            "category":"Wholesale",
            "subcategory":"Chemicals & Plastics",
            "type":"Manufacturing & Wholesale Goods"
        }
    ],
    "sg:phone":"+1 541 963 3118",
    "sg:postcode":"97850",
    "sg:province":"OR",
    "sg:tags":[
        "oxygen"
    ],
    "wof:name":"Lincare",
    "wof:placetype":"venue"
},
  "geometry": {"coordinates":[-118.095517,45.329143],"type":"Point"}
}