{
  "type": "Feature",
  "properties": {
    "addr:full":"2101 W Main St Medford OR 97501",
    "addr:housenumber":"2101",
    "addr:postcode":"97501",
    "addr:street":"W Main St",
    "iso:country":"US",
    "sg:address":"2101 W Main St",
    "sg:city":"Medford",
    "sg:classifiers":[
        {
            "category":"Professional",
            "subcategory":"Business Services",
            "type":"Services"
        },
        {
            "category":"Wholesale",
            "subcategory":"Non-durable Goods",
            "type":"Manufacturing & Wholesale Goods"
        }
    ],
    "sg:phone":"+1 541 772 4457",
    "sg:postcode":"97501",
    "sg:province":"OR",
    "sg:tags":[
        "rubber",
        "product",
        "foam",
        "sewing",
        "custom",
        "sponge"
    ],
    "wof:name":"O'Keefe Foam Products Inc",
    "wof:placetype":"venue"
},
  "geometry": {"coordinates":[-122.895768,42.323732],"type":"Point"}
}