{
  "type": "Feature",
  "properties": {
    "iso:country":"US",
    "sg:address":"2188 SW Park Pl Ste 205",
    "sg:city":"Portland",
    "sg:classifiers":[
        {
            "category":"Health Services",
            "subcategory":"Doctor",
            "type":"Services"
        },
        {
            "category":"Health Services",
            "subcategory":"Clinic",
            "type":"Services"
        }
    ],
    "sg:phone":"+1 503 827 4800",
    "sg:postcode":"97205",
    "sg:province":"OR",
    "sg:tags":[
        "counseling",
        "mental",
        "psychiatrist"
    ],
    "wof:name":"Stuart Carol J Psyd",
    "wof:placetype":"venue"
},
  "geometry": {"coordinates":[-122.69654800000001,45.521081],"type":"Point"}
}