{
  "type": "Feature",
  "properties": {
    "addr:full":"1810 NW 192nd Ave Beaverton OR 97006",
    "addr:housenumber":"1810",
    "addr:postcode":"97006",
    "addr:street":"Nw 192Nd Ave",
    "iso:country":"US",
    "sg:address":"1810 NW 192nd Ave",
    "sg:city":"Beaverton",
    "sg:classifiers":[
        {
            "category":"Community Center",
            "type":"Public Place"
        }
    ],
    "sg:phone":"+1 503 533 1032",
    "sg:postcode":"97006",
    "sg:province":"OR",
    "sg:tags":[
        "recreation"
    ],
    "wof:name":"Magnolia Park",
    "wof:placetype":"venue"
},
  "geometry": {"coordinates":[-122.87499200000001,45.532512],"type":"Point"}
}