{
  "type": "Feature",
  "properties": {
    "addr:full":"3112 Schmidt Ln NE Hubbard OR 97032",
    "addr:housenumber":"3112",
    "addr:postcode":"97032",
    "addr:street":"Schmidt Ln Ne",
    "iso:country":"US",
    "sg:address":"3112 Schmidt Ln NE",
    "sg:city":"Hubbard",
    "sg:classifiers":[
        {
            "category":"Building & Trades",
            "subcategory":"Equipment Rental",
            "type":"Services"
        }
    ],
    "sg:phone":"+1 503 981 1880",
    "sg:postcode":"97032",
    "sg:province":"OR",
    "sg:tags":[
        "architectural",
        "supply"
    ],
    "wof:name":"R B W Inc",
    "wof:placetype":"venue"
},
  "geometry": {"coordinates":[-122.809951,45.1753],"type":"Point"}
}