{
  "type": "Feature",
  "properties": {
    "iso:country":"US",
    "sg:address":"806 SW Broadway Suite 400",
    "sg:city":"Portland",
    "sg:classifiers":[
        {
            "category":"Professional",
            "subcategory":"Lawyer & Legal Services",
            "type":"Services"
        }
    ],
    "sg:phone":"+1 503 243 6336",
    "sg:postcode":"97205",
    "sg:province":"OR",
    "wof:name":"David Slader Trial Lawyer",
    "wof:placetype":"venue"
},
  "geometry": {"coordinates":[-122.679986,45.518635],"type":"Point"}
}