{
  "type": "Feature",
  "properties": {
    "iso:country":"US",
    "sg:address":"875 SW Oak St Ste 5070",
    "sg:city":"Portland",
    "sg:classifiers":[
        {
            "category":"Health Services",
            "subcategory":"Doctor",
            "type":"Services"
        },
        {
            "category":"Health Services",
            "subcategory":"Clinic",
            "type":"Services"
        }
    ],
    "sg:phone":"+1 503 561 8565",
    "sg:postcode":"97205",
    "sg:province":"OR",
    "sg:tags":[
        "physician",
        "surgeon",
        "osteopathic"
    ],
    "wof:name":"Jennifer N Neahgring Md",
    "wof:placetype":"venue"
},
  "geometry": {"coordinates":[-122.67984300000001,45.522457],"type":"Point"}
}