{
  "type": "Feature",
  "properties": {
    "addr:full":"2057 Winchester Ave Reedsport OR 97467",
    "addr:housenumber":"2057",
    "addr:postcode":"97467",
    "addr:street":"Winchester Ave",
    "iso:country":"US",
    "sg:address":"2057 Winchester Ave",
    "sg:city":"Reedsport",
    "sg:classifiers":[
        {
            "category":"Retail",
            "subcategory":"Auto Repair",
            "type":"Services"
        }
    ],
    "sg:phone":"+1 541 271 0780",
    "sg:postcode":"97467",
    "sg:province":"OR",
    "sg:tags":[
        "recreational",
        "vehicle"
    ],
    "wof:name":"Bumble Bee Atv",
    "wof:placetype":"venue"
},
  "geometry": {"coordinates":[-124.120807,43.695673],"type":"Point"}
}