{
  "type": "Feature",
  "properties": {
    "iso:country":"US",
    "sg:address":"1596 Arlington Ave",
    "sg:city":"Woodburn",
    "sg:classifiers":[
        {
            "category":"Shopping",
            "subcategory":"Florist",
            "type":"Retail Goods"
        }
    ],
    "sg:phone":"+1 503 982 8658",
    "sg:postcode":"97071",
    "sg:province":"OR",
    "wof:name":"Parsons Exotic Plant Nursery",
    "wof:placetype":"venue"
},
  "geometry": {"coordinates":[-122.861768,45.155885],"type":"Point"}
}