{
  "type": "Feature",
  "properties": {
    "addr:full":"10185 SW Heartland Dr Gaston OR 97119",
    "addr:housenumber":"10185",
    "addr:postcode":"97119",
    "addr:street":"Sw Heartland Dr",
    "iso:country":"US",
    "sg:address":"10185 SW Heartland Dr",
    "sg:city":"Gaston",
    "sg:classifiers":[
        {
            "category":"Farming",
            "subcategory":"Livestock Farm",
            "type":"Manufacturing & Wholesale Goods"
        }
    ],
    "sg:phone":"+1 503 985 3557",
    "sg:postcode":"97119",
    "sg:province":"OR",
    "sg:tags":[
        "beef",
        "feedlot",
        "cattle"
    ],
    "wof:name":"Mesenbrink Farms",
    "wof:placetype":"venue"
},
  "geometry": {"coordinates":[-123.15866200000001,45.446415],"type":"Point"}
}