{
  "type": "Feature",
  "properties": {
    "iso:country":"US",
    "sg:address":"5175 Oakridge Rd",
    "sg:city":"Lake Oswego",
    "sg:classifiers":[
        {
            "category":"Building & Trades",
            "subcategory":"Locksmith",
            "type":"Services"
        }
    ],
    "sg:phone":"+1 503 715 3857",
    "sg:postcode":"97035",
    "sg:province":"OR",
    "sg:tags":[
        "key"
    ],
    "wof:name":"123 Express Locksmith",
    "wof:placetype":"venue"
},
  "geometry": {"coordinates":[-122.729726,45.409957],"type":"Point"}
}