{
  "type": "Feature",
  "properties": {
    "addr:full":"4 4th St Hood River OR 97031",
    "addr:housenumber":"4",
    "addr:postcode":"97031",
    "addr:street":"4Th St",
    "iso:country":"US",
    "sg:address":"4 4th St",
    "sg:city":"Hood River",
    "sg:classifiers":[
        {
            "category":"Manufacturing",
            "subcategory":"Toys & Sporting Goods",
            "type":"Manufacturing & Wholesale Goods"
        }
    ],
    "sg:phone":"+1 541 386 1980",
    "sg:postcode":"97031",
    "sg:province":"OR",
    "sg:tags":[
        "product",
        "for",
        "mfg",
        "industry",
        "foam",
        "custom"
    ],
    "sg:website":"www.nsipadz.com",
    "wof:name":"North Shore Inc",
    "wof:placetype":"venue"
},
  "geometry": {"coordinates":[-121.51437799999999,45.710263],"type":"Point"}
}