{
  "type": "Feature",
  "properties": {
    "addr:full":"17456 SE Colina Vista Ave Portland OR 97267",
    "addr:postcode":"17456;97267",
    "addr:street":"Se Colina Vista Ave",
    "iso:country":"US",
    "sg:address":"17456 SE Colina Vista Ave",
    "sg:city":"Portland",
    "sg:classifiers":[
        {
            "category":"Freight",
            "type":"Transportation"
        }
    ],
    "sg:phone":"+1 503 653 3543",
    "sg:postcode":"97267",
    "sg:province":"OR",
    "sg:tags":[
        "operator",
        "local",
        "trucking"
    ],
    "wof:name":"Bud Construction",
    "wof:placetype":"venue"
},
  "geometry": {"coordinates":[-122.603415,45.397042],"type":"Point"}
}