{
  "type": "Feature",
  "properties": {
    "addr:full":"9627 Sterling Creek Rd Jacksonville OR 97530",
    "addr:housenumber":"9627",
    "addr:postcode":"97530",
    "addr:street":"Sterling Creek Rd",
    "iso:country":"US",
    "sg:address":"9627 Sterling Creek Rd",
    "sg:city":"Jacksonville",
    "sg:classifiers":[
        {
            "category":"Professional",
            "subcategory":"Business Services",
            "type":"Services"
        }
    ],
    "sg:phone":"+1 541 899 5932",
    "sg:postcode":"97530",
    "sg:province":"OR",
    "wof:name":"Rennie Drummond",
    "wof:placetype":"venue"
},
  "geometry": {"coordinates":[-122.974946,42.182652],"type":"Point"}
}