{
  "type": "Feature",
  "properties": {
    "iso:country":"US",
    "sg:address":"701 Marshall Ave",
    "sg:city":"Medford",
    "sg:classifiers":[
        {
            "category":"Building & Trades",
            "subcategory":"Construction",
            "type":"Services"
        }
    ],
    "sg:phone":"+1 541 776 3413",
    "sg:postcode":"97501",
    "sg:province":"OR",
    "sg:tags":[
        "system",
        "specialty",
        "heating",
        "contractor",
        "air conditioning"
    ],
    "wof:name":"Pyramid Heating & Air Inc",
    "wof:placetype":"venue"
},
  "geometry": {"coordinates":[-122.877663,42.306839],"type":"Point"}
}