{
  "type": "Feature",
  "properties": {
    "iso:country":"US",
    "sg:address":"592 W Madison St",
    "sg:city":"Burns",
    "sg:classifiers":[
        {
            "category":"Organizations",
            "subcategory":"Religious Organization",
            "type":"Services"
        }
    ],
    "sg:phone":"+1 541 573 1154",
    "sg:postcode":"97720",
    "sg:province":"OR",
    "sg:tags":[
        "church"
    ],
    "sg:website":"http://www.watchtower.org",
    "wof:name":"Jehovah's Witnesses Kingdom Hall",
    "wof:placetype":"venue"
},
  "geometry": {"coordinates":[-119.060531,43.58644],"type":"Point"}
}