{
  "type": "Feature",
  "properties": {
    "iso:country":"US",
    "sg:address":"1507 SE 122nd Ave",
    "sg:city":"Portland",
    "sg:classifiers":[
        {
            "category":"Home & Garden",
            "subcategory":"Home Furnishings",
            "type":"Retail Goods"
        }
    ],
    "sg:phone":"+1 503 258 0194",
    "sg:postcode":"97233",
    "sg:province":"OR",
    "sg:tags":[
        "utensil",
        "cooking"
    ],
    "wof:name":"Magic Maid Intl",
    "wof:placetype":"venue"
},
  "geometry": {"coordinates":[-122.537724,45.511581],"type":"Point"}
}