{
  "type": "Feature",
  "properties": {
    "addr:full":"1939 NE Broadway St Portland OR 97232",
    "addr:housenumber":"1939",
    "addr:postcode":"97232",
    "addr:street":"Ne Broadway St",
    "iso:country":"US",
    "sg:address":"1939 NE Broadway St",
    "sg:city":"Portland",
    "sg:classifiers":[
        {
            "category":"Shopping",
            "subcategory":"Hobbies, Toys, & Games",
            "type":"Retail Goods"
        }
    ],
    "sg:phone":"+1 503 282 0332",
    "sg:postcode":"97232",
    "sg:province":"OR",
    "sg:tags":[
        "shop",
        "hobby",
        "model",
        "coin",
        "supply"
    ],
    "wof:name":"Bradley's Coins Inc",
    "wof:placetype":"venue"
},
  "geometry": {"coordinates":[-122.64630099999999,45.535011],"type":"Point"}
}