{
  "type": "Feature",
  "properties": {
    "iso:country":"US",
    "sg:address":"1605 S Main St",
    "sg:city":"Lebanon",
    "sg:classifiers":[
        {
            "category":"Autos & Motor Vehicles",
            "subcategory":"Fuel & Gas Station",
            "type":"Retail Goods"
        }
    ],
    "sg:phone":"+1 541 451 8234",
    "sg:postcode":"97355",
    "sg:province":"OR",
    "sg:tags":[
        "oil"
    ],
    "wof:name":"Lube Express",
    "wof:placetype":"venue"
},
  "geometry": {"coordinates":[-122.906977,44.530917],"type":"Point"}
}