{
  "type": "Feature",
  "properties": {
    "iso:country":"US",
    "sg:address":"12128 State Hwy 212",
    "sg:city":"Clackamas",
    "sg:classifiers":[
        {
            "category":"Retail",
            "subcategory":"Auto Repair",
            "type":"Services"
        }
    ],
    "sg:phone":"+1 503 656 1179",
    "sg:postcode":"97015",
    "sg:province":"OR",
    "sg:tags":[
        "general"
    ],
    "wof:name":"212 Auto Repair",
    "wof:placetype":"venue"
},
  "geometry": {"coordinates":[-122.538801,45.407754],"type":"Point"}
}