{
  "type": "Feature",
  "properties": {
    "iso:country":"US",
    "sg:address":"1615 SE Maple Ave",
    "sg:city":"Portland",
    "sg:classifiers":[
        {
            "category":"Communications",
            "subcategory":"Film & Video Production",
            "type":"Services"
        }
    ],
    "sg:phone":"+1 503 232 3454",
    "sg:postcode":"97214",
    "sg:province":"OR",
    "sg:tags":[
        "motion",
        "distribution"
    ],
    "wof:name":"P&G Investments",
    "wof:placetype":"venue"
},
  "geometry": {"coordinates":[-122.65044399999999,45.510826],"type":"Point"}
}