{
  "type": "Feature",
  "properties": {
    "addr:full":"505 Hemlock St Brookings OR 97415",
    "addr:housenumber":"505",
    "addr:postcode":"97415",
    "addr:street":"Hemlock St",
    "iso:country":"US",
    "sg:address":"505 Hemlock St",
    "sg:city":"Brookings",
    "sg:classifiers":[
        {
            "category":"Sports & Exercise",
            "subcategory":"Gym",
            "type":"Entertainment"
        }
    ],
    "sg:phone":"+1 541 469 6266",
    "sg:postcode":"97415",
    "sg:province":"OR",
    "sg:tags":[
        "personal",
        "fitness",
        "physical",
        "facility"
    ],
    "wof:name":"Shape Up Tone & Tan",
    "wof:placetype":"venue"
},
  "geometry": {"coordinates":[-124.27777399999999,42.052233],"type":"Point"}
}