{
  "type": "Feature",
  "properties": {
    "iso:country":"US",
    "sg:address":"419 SE Nursery St",
    "sg:city":"Amity",
    "sg:classifiers":[
        {
            "category":"Building & Trades",
            "subcategory":"Construction",
            "type":"Services"
        }
    ],
    "sg:phone":"+1 503 835 0157",
    "sg:postcode":"97101",
    "sg:province":"OR",
    "wof:name":"Jesse Allen Construction",
    "wof:placetype":"venue"
},
  "geometry": {"coordinates":[-123.202241,45.114447],"type":"Point"}
}