{
  "type": "Feature",
  "properties": {
    "iso:country":"US",
    "sg:address":"86020 Lorane Hwy",
    "sg:city":"Eugene",
    "sg:classifiers":[
        {
            "category":"Shopping",
            "subcategory":"Florist",
            "type":"Retail Goods"
        },
        {
            "category":"Home & Garden",
            "subcategory":"Garden Supply",
            "type":"Retail Goods"
        }
    ],
    "sg:phone":"+1 541 344 6481",
    "sg:postcode":"97405",
    "sg:province":"OR",
    "sg:tags":[
        "nurseryman"
    ],
    "wof:name":"Woodland Gardens Nursery",
    "wof:placetype":"venue"
},
  "geometry": {"coordinates":[-123.147459,44.001747],"type":"Point"}
}