{
  "type": "Feature",
  "properties": {
    "iso:country":"US",
    "sg:address":"45 NW 110th Ave",
    "sg:city":"Portland",
    "sg:classifiers":[
        {
            "category":"Professional",
            "subcategory":"Business Services",
            "type":"Services"
        }
    ],
    "sg:phone":"+1 503 469 0169",
    "sg:postcode":"97229",
    "sg:province":"OR",
    "sg:tags":[
        "interior",
        "design"
    ],
    "wof:name":"Sue Epps Interiors Inc",
    "wof:placetype":"venue"
},
  "geometry": {"coordinates":[-122.789624,45.519993],"type":"Point"}
}