{
  "type": "Feature",
  "properties": {
    "iso:country":"US",
    "sg:address":"3546 NE Tillamook St",
    "sg:city":"Portland",
    "sg:classifiers":[
        {
            "category":"Professional",
            "subcategory":"Management & Consulting",
            "type":"Services"
        }
    ],
    "sg:phone":"+1 503 282 4222",
    "sg:postcode":"97212",
    "sg:province":"OR",
    "sg:tags":[
        "farm"
    ],
    "wof:name":"Barnaby Chateau",
    "wof:placetype":"venue"
},
  "geometry": {"coordinates":[-122.627285,45.537079],"type":"Point"}
}