{
  "type": "Feature",
  "properties": {
    "addr:full":"14674 SE Sunnyside Rd Clackamas OR 97015",
    "addr:housenumber":"14674",
    "addr:postcode":"97015",
    "addr:street":"Se Sunnyside Rd",
    "iso:country":"US",
    "sg:address":"14674 SE Sunnyside Rd",
    "sg:city":"Clackamas",
    "sg:classifiers":[
        {
            "category":"Building & Trades",
            "subcategory":"Locksmith",
            "type":"Services"
        }
    ],
    "sg:phone":"+1 503 447 5869",
    "sg:postcode":"97015",
    "sg:province":"OR",
    "sg:tags":[
        "key"
    ],
    "wof:name":"A Locks & Locksmith 24X7",
    "wof:placetype":"venue"
},
  "geometry": {"coordinates":[-122.51248,45.424705],"type":"Point"}
}