{
  "type": "Feature",
  "properties": {
    "addr:full":"1870 NW Burnside Rd Gresham OR 97030",
    "addr:housenumber":"1870",
    "addr:postcode":"97030",
    "addr:street":"Nw Burnside Rd",
    "iso:country":"US",
    "sg:address":"1870 NW Burnside Rd",
    "sg:city":"Gresham",
    "sg:classifiers":[
        {
            "category":"Retail",
            "subcategory":"Auto Repair",
            "type":"Services"
        }
    ],
    "sg:phone":"+1 503 669 1835",
    "sg:postcode":"97030",
    "sg:province":"OR",
    "sg:tags":[
        "repairing",
        "automobile"
    ],
    "wof:name":"B C Motorsports",
    "wof:placetype":"venue"
},
  "geometry": {"coordinates":[-122.45375,45.514607],"type":"Point"}
}