{
  "type": "Feature",
  "properties": {
    "iso:country":"US",
    "sg:address":"11502 SE Flavel St",
    "sg:city":"Portland",
    "sg:classifiers":[
        {
            "category":"Restaurant",
            "type":"Food & Drink"
        }
    ],
    "sg:phone":"+1 503 287 9010",
    "sg:postcode":"97266",
    "sg:province":"OR",
    "sg:tags":[
        "eating"
    ],
    "wof:name":"King Little Sandwich Shop",
    "wof:placetype":"venue"
},
  "geometry": {"coordinates":[-122.542831,45.468345],"type":"Point"}
}