{
  "type": "Feature",
  "properties": {
    "iso:country":"US",
    "sg:address":"945 Kenyon St",
    "sg:city":"Medford",
    "sg:classifiers":[
        {
            "category":"Building & Trades",
            "subcategory":"Construction",
            "type":"Services"
        }
    ],
    "sg:phone":"+1 541 734 4669",
    "sg:postcode":"97501",
    "sg:province":"OR",
    "sg:tags":[
        "mobile",
        "home"
    ],
    "wof:name":"Above & Beyond Mobile Home Svc",
    "wof:placetype":"venue"
},
  "geometry": {"coordinates":[-122.86964500000001,42.314572],"type":"Point"}
}