{
  "type": "Feature",
  "properties": {
    "iso:country":"US",
    "sg:address":"16735 SW Pacific Hwy",
    "sg:city":"Portland",
    "sg:classifiers":[
        {
            "category":"Deli",
            "type":"Food & Drink"
        },
        {
            "category":"Food & Beverages",
            "subcategory":"Bakery",
            "type":"Retail Goods"
        }
    ],
    "sg:phone":"+1 503 639 0404",
    "sg:postcode":"97224",
    "sg:province":"OR",
    "sg:tags":[
        "sandwich"
    ],
    "wof:name":"Lil Brick Deli",
    "wof:placetype":"venue"
},
  "geometry": {"coordinates":[-122.798801,45.399182],"type":"Point"}
}