{
  "type": "Feature",
  "properties": {
    "iso:country":"US",
    "sg:address":"3084 Lancaster Dr NE",
    "sg:city":"Salem",
    "sg:classifiers":[
        {
            "category":"Retail",
            "subcategory":"Self-service Laundry",
            "type":"Services"
        }
    ],
    "sg:phone":"+1 503 566 7990",
    "sg:postcode":"97305",
    "sg:province":"OR",
    "wof:name":"Salem Laundromat",
    "wof:placetype":"venue"
},
  "geometry": {"coordinates":[-122.983395,44.969312],"type":"Point"}
}