{
  "type": "Feature",
  "properties": {
    "addr:full":"333 NE 3rd St Gresham OR 97030",
    "addr:housenumber":"333",
    "addr:postcode":"97030",
    "addr:street":"Ne 3Rd St",
    "iso:country":"US",
    "sg:address":"333 NE 3rd St",
    "sg:city":"Gresham",
    "sg:classifiers":[
        {
            "category":"Professional",
            "subcategory":"Accounting & Tax Preparation",
            "type":"Services"
        }
    ],
    "sg:phone":"+1 503 661 1900",
    "sg:postcode":"97030",
    "sg:province":"OR",
    "wof:name":"Jerome J McKay CPA",
    "wof:placetype":"venue"
},
  "geometry": {"coordinates":[-122.426087,45.499708],"type":"Point"}
}