{
  "type": "Feature",
  "properties": {
    "iso:country":"US",
    "sg:address":"206 N Coast Hwy",
    "sg:city":"Newport",
    "sg:classifiers":[
        {
            "category":"Travel",
            "subcategory":"Hotels & Motels",
            "type":"Entertainment"
        }
    ],
    "sg:phone":"+1 541 265 5321",
    "sg:postcode":"97365",
    "sg:province":"OR",
    "wof:name":"Sands Motor Lodge",
    "wof:placetype":"venue"
},
  "geometry": {"coordinates":[-124.053107,44.637758],"type":"Point"}
}