{
  "type": "Feature",
  "properties": {
    "addr:full":"1409 NE Columbia Blvd Portland OR 97211",
    "addr:housenumber":"1409",
    "addr:postcode":"97211",
    "addr:street":"Ne Columbia Blvd",
    "iso:country":"US",
    "sg:address":"1409 NE Columbia Blvd",
    "sg:city":"Portland",
    "sg:classifiers":[
        {
            "category":"Autos & Motor Vehicles",
            "subcategory":"Recreational Vehicle Sales",
            "type":"Retail Goods"
        }
    ],
    "sg:phone":"+1 503 289 6100",
    "sg:postcode":"97211",
    "sg:province":"OR",
    "sg:tags":[
        "home",
        "travel",
        "trailer"
    ],
    "wof:name":"La Mesa R V Center Inc",
    "wof:placetype":"venue"
},
  "geometry": {"coordinates":[-122.648245,45.577609],"type":"Point"}
}