{
  "type": "Feature",
  "properties": {
    "iso:country":"US",
    "sg:address":"23675 N Hwy 99W",
    "sg:city":"Newberg",
    "sg:classifiers":[
        {
            "category":"Building & Trades",
            "subcategory":"Construction",
            "type":"Services"
        }
    ],
    "sg:phone":"+1 503 538 4637",
    "sg:postcode":"97132",
    "sg:province":"OR",
    "sg:tags":[
        "masonry",
        "contractor"
    ],
    "sg:website":"www.ricemasonryinc.com",
    "wof:name":"Rice Masonry Inc",
    "wof:placetype":"venue"
},
  "geometry": {"coordinates":[-122.99635600000001,45.290955],"type":"Point"}
}