{
  "type": "Feature",
  "properties": {
    "iso:country":"US",
    "sg:address":"19004 NE San Rafael St",
    "sg:city":"Portland",
    "sg:classifiers":[
        {
            "category":"Autos & Motor Vehicles",
            "subcategory":"Auto Supplies",
            "type":"Retail Goods"
        }
    ],
    "sg:phone":"+1 503 665 6144",
    "sg:postcode":"97230",
    "sg:province":"OR",
    "sg:tags":[
        "tire"
    ],
    "wof:name":"Northwest Retreaders",
    "wof:placetype":"venue"
},
  "geometry": {"coordinates":[-122.46808900000001,45.536992],"type":"Point"}
}