{
  "type": "Feature",
  "properties": {
    "iso:country":"US",
    "sg:address":"166 E 13th Ave",
    "sg:city":"Eugene",
    "sg:classifiers":[
        {
            "category":"Organizations",
            "subcategory":"Religious Organization",
            "type":"Services"
        }
    ],
    "sg:phone":"+1 541 343 9253",
    "sg:postcode":"97401",
    "sg:province":"OR",
    "sg:tags":[
        "church"
    ],
    "sg:website":"www.saint-marys.org",
    "wof:name":"St Mary's Episcopal Church",
    "wof:placetype":"venue"
},
  "geometry": {"coordinates":[-123.089877,44.045443],"type":"Point"}
}