{
  "type": "Feature",
  "properties": {
    "addr:full":"786 Park St Ashland OR 97520",
    "addr:housenumber":"786",
    "addr:postcode":"97520",
    "addr:street":"Park St",
    "iso:country":"US",
    "sg:address":"786 Park St",
    "sg:city":"Ashland",
    "sg:classifiers":[
        {
            "category":"Building & Trades",
            "subcategory":"Construction",
            "type":"Services"
        }
    ],
    "sg:phone":"+1 541 488 8655",
    "sg:postcode":"97520",
    "sg:province":"OR",
    "sg:tags":[
        "house"
    ],
    "wof:name":"Craftsman Custom Homes",
    "wof:placetype":"venue"
},
  "geometry": {"coordinates":[-122.68094499999999,42.180255],"type":"Point"}
}