{
  "type": "Feature",
  "properties": {
    "iso:country":"US",
    "sg:address":"1111 NE 82nd Ave",
    "sg:city":"Portland",
    "sg:classifiers":[
        {
            "category":"Food & Beverages",
            "subcategory":"Groceries & Convenience Stores",
            "type":"Retail Goods"
        }
    ],
    "sg:phone":"+1 503 256 4206",
    "sg:postcode":"97220",
    "sg:province":"OR",
    "wof:name":"Saigon Market",
    "wof:placetype":"venue"
},
  "geometry": {"coordinates":[-122.579002,45.531101],"type":"Point"}
}