{
  "type": "Feature",
  "properties": {
    "iso:country":"US",
    "sg:address":"1302 13th St",
    "sg:city":"Hood River",
    "sg:classifiers":[
        {
            "category":"Restaurant",
            "type":"Food & Drink"
        }
    ],
    "sg:phone":"+1 541 386 1388",
    "sg:postcode":"97031",
    "sg:province":"OR",
    "sg:tags":[
        "pizza"
    ],
    "wof:name":"Stuffano's Pizzaria",
    "wof:placetype":"venue"
},
  "geometry": {"coordinates":[-121.524773,45.70091],"type":"Point"}
}