{
  "type": "Feature",
  "properties": {
    "addr:full":"10220 SW Greenburg Road Suite 245 Portland OR 97223",
    "addr:housenumber":"10220",
    "addr:postcode":"97223",
    "addr:street":"Sw Greenburg Road Suite 245",
    "iso:country":"US",
    "sg:address":"10220 SW Greenburg Road Suite 245",
    "sg:city":"Portland",
    "sg:classifiers":[
        {
            "category":"Banks & Credit Unions",
            "subcategory":"Financial Services",
            "type":"Services"
        }
    ],
    "sg:phone":"+1 503 246 4151",
    "sg:postcode":"97223",
    "sg:province":"OR",
    "sg:tags":[
        "broker",
        "mortgage"
    ],
    "wof:name":"American Home Mortgage",
    "wof:placetype":"venue"
},
  "geometry": {"coordinates":[-122.776253,45.446173],"type":"Point"}
}