{
  "type": "Feature",
  "properties": {
    "iso:country":"US",
    "sg:address":"50 SW Pine St Ste 200",
    "sg:city":"Portland",
    "sg:classifiers":[
        {
            "category":"Real Estate",
            "subcategory":"Real Estate Services",
            "type":"Services"
        }
    ],
    "sg:phone":"+1 503 224 6791",
    "sg:postcode":"97204",
    "sg:province":"OR",
    "sg:tags":[
        "management"
    ],
    "wof:name":"Elliott Associates Incorporated",
    "wof:placetype":"venue"
},
  "geometry": {"coordinates":[-122.67130299999999,45.520935],"type":"Point"}
}