{
  "type": "Feature",
  "properties": {
    "iso:country":"US",
    "sg:address":"400 Madrona Ave S",
    "sg:city":"Salem",
    "sg:classifiers":[
        {
            "category":"Shopping",
            "type":"Retail Goods"
        }
    ],
    "sg:phone":"+1 503 588 2922",
    "sg:postcode":"97302",
    "sg:province":"OR",
    "sg:tags":[
        "item",
        "boutique"
    ],
    "wof:name":"Annette's Lakeside Boutique",
    "wof:placetype":"venue"
},
  "geometry": {"coordinates":[-123.051609,44.904743],"type":"Point"}
}