{
  "type": "Feature",
  "properties": {
    "iso:country":"US",
    "sg:address":"937 California Ave",
    "sg:city":"Klamath Falls",
    "sg:classifiers":[
        {
            "category":"Building & Trades",
            "subcategory":"Cleaning & Sanitation",
            "type":"Services"
        }
    ],
    "sg:phone":"+1 541 892 8121",
    "sg:postcode":"97601",
    "sg:province":"OR",
    "sg:tags":[
        "janitor"
    ],
    "wof:name":"M & R Janitorial Svc",
    "wof:placetype":"venue"
},
  "geometry": {"coordinates":[-121.792177,42.227876],"type":"Point"}
}