{
  "type": "Feature",
  "properties": {
    "addr:full":"3784 Douglas Dr Springfield OR 97478",
    "addr:housenumber":"3784",
    "addr:postcode":"97478",
    "addr:street":"Douglas Dr",
    "iso:country":"US",
    "sg:address":"3784 Douglas Dr",
    "sg:city":"Springfield",
    "sg:classifiers":[
        {
            "category":"Building & Trades",
            "subcategory":"Construction",
            "type":"Services"
        }
    ],
    "sg:phone":"+1 541 747 4539",
    "sg:postcode":"97478",
    "sg:province":"OR",
    "sg:tags":[
        "resurfacing",
        "laying",
        "refinishing",
        "floor"
    ],
    "wof:name":"Gilbert Installation",
    "wof:placetype":"venue"
},
  "geometry": {"coordinates":[-122.9736,44.03856],"type":"Point"}
}