{
  "type": "Feature",
  "properties": {
    "iso:country":"US",
    "sg:address":"116 SW 4th St",
    "sg:city":"Corvallis",
    "sg:classifiers":[
        {
            "category":"Utilities",
            "subcategory":"Mobile Phone",
            "type":"Services"
        }
    ],
    "sg:phone":"+1 541 752 3154",
    "sg:postcode":"97333",
    "sg:province":"OR",
    "sg:tags":[
        "telephone",
        "cellular"
    ],
    "wof:name":"West Coast Communications",
    "wof:placetype":"venue"
},
  "geometry": {"coordinates":[-123.262114,44.564503],"type":"Point"}
}