{
  "type": "Feature",
  "properties": {
    "iso:country":"US",
    "sg:address":"1136 SW 3rd Ave",
    "sg:city":"Portland",
    "sg:classifiers":[
        {
            "category":"Restaurant",
            "type":"Food & Drink"
        }
    ],
    "sg:phone":"+1 503 227 1613",
    "sg:postcode":"97204",
    "sg:province":"OR",
    "sg:tags":[
        "eating"
    ],
    "wof:name":"Sandwich Paradise",
    "wof:placetype":"venue"
},
  "geometry": {"coordinates":[-122.676966,45.515561],"type":"Point"}
}