{
  "type": "Feature",
  "properties": {
    "iso:country":"US",
    "sg:address":"36081 Camp Creek Rd",
    "sg:city":"Springfield",
    "sg:classifiers":[
        {
            "category":"Building & Trades",
            "subcategory":"Landscaping Services",
            "type":"Services"
        }
    ],
    "sg:phone":"+1 541 746 9090",
    "sg:postcode":"97478",
    "sg:province":"OR",
    "sg:tags":[
        "lawn",
        "nursery",
        "garden",
        "landscape"
    ],
    "wof:name":"Green Leaf Nursery & Ldscpg",
    "wof:placetype":"venue"
},
  "geometry": {"coordinates":[-122.930215,44.073902],"type":"Point"}
}