{
  "type": "Feature",
  "properties": {
    "iso:country":"US",
    "sg:address":"541 Willamette St",
    "sg:city":"Eugene",
    "sg:classifiers":[
        {
            "category":"Personal",
            "type":"Services"
        },
        {
            "category":"Health Services",
            "subcategory":"Health Practitioner",
            "type":"Services"
        }
    ],
    "sg:phone":"+1 541 342 8106",
    "sg:postcode":"97401",
    "sg:province":"OR",
    "sg:tags":[
        "therapist",
        "massage"
    ],
    "wof:name":"Cranio Sacral Advanced Therapy",
    "wof:placetype":"venue"
},
  "geometry": {"coordinates":[-123.092656,44.053644],"type":"Point"}
}