{
  "type": "Feature",
  "properties": {
    "iso:country":"US",
    "sg:address":"838 NW 23rd Ave",
    "sg:city":"Portland",
    "sg:phone":"+1 503 241 9300",
    "sg:postcode":"97210",
    "sg:province":"OR",
    "wof:name":"Mio Gelato Caffe Italiano",
    "wof:placetype":"venue"
},
  "geometry": {"coordinates":[-122.69857399999999,45.528633],"type":"Point"}
}