{
  "type": "Feature",
  "properties": {
    "addr:full":"8305 SE Monterey Ave Ste 202 Portland OR 97266",
    "addr:housenumber":"8305",
    "addr:postcode":"97266",
    "addr:street":"Se Monterey Ave Ste 202",
    "iso:country":"US",
    "sg:address":"8305 SE Monterey Ave Ste 202",
    "sg:city":"Portland",
    "sg:classifiers":[
        {
            "category":"Professional",
            "subcategory":"Employment Agencies",
            "type":"Services"
        }
    ],
    "sg:phone":"+1 503 226 0060",
    "sg:postcode":"97266",
    "sg:province":"OR",
    "wof:name":"Bridgeport Staffing",
    "wof:placetype":"venue"
},
  "geometry": {"coordinates":[-122.578003,45.438301],"type":"Point"}
}