{
  "type": "Feature",
  "properties": {
    "addr:full":"302 Monmouth Ave S Monmouth OR 97361",
    "addr:housenumber":"302",
    "addr:postcode":"97361",
    "addr:street":"Monmouth Ave S",
    "iso:country":"US",
    "sg:address":"302 Monmouth Ave S",
    "sg:city":"Monmouth",
    "sg:classifiers":[
        {
            "category":"Professional",
            "type":"Services"
        }
    ],
    "sg:phone":"+1 503 838 7746",
    "sg:postcode":"97361",
    "sg:province":"OR",
    "wof:name":"Badboy Spin Doctors",
    "wof:placetype":"venue"
},
  "geometry": {"coordinates":[-123.23750099999999,44.846414],"type":"Point"}
}