{
  "type": "Feature",
  "properties": {
    "iso:country":"US",
    "sg:address":"22075 Bear Creek Rd",
    "sg:city":"Bend",
    "sg:classifiers":[
        {
            "category":"Retail",
            "subcategory":"Animal Services",
            "type":"Services"
        }
    ],
    "sg:phone":"+1 541 389 2108",
    "sg:postcode":"97701",
    "sg:province":"OR",
    "sg:tags":[
        "boarding",
        "sitting",
        "pet",
        "supply",
        "dog",
        "cat",
        "furnishing"
    ],
    "wof:name":"Park Your Pooch Kennel",
    "wof:placetype":"venue"
},
  "geometry": {"coordinates":[-121.22067800000001,44.05117],"type":"Point"}
}