{
  "type": "Feature",
  "properties": {
    "iso:country":"US",
    "sg:address":"2104 N Willis Boulevard",
    "sg:city":"Portland",
    "sg:classifiers":[
        {
            "category":"Retail",
            "subcategory":"Auto Repair",
            "type":"Services"
        }
    ],
    "sg:phone":"+1 503 283 2116",
    "sg:postcode":"97217",
    "sg:province":"OR",
    "wof:name":"Emeralds Auto & Rv",
    "wof:placetype":"venue"
},
  "geometry": {"coordinates":[-122.68832999999999,45.583824],"type":"Point"}
}