{
  "type": "Feature",
  "properties": {
    "iso:country":"US",
    "sg:address":"3615 NE Grand Ave",
    "sg:city":"Portland",
    "sg:phone":"+1 503 200 7579",
    "sg:postcode":"97212",
    "sg:province":"OR",
    "wof:name":"Tensegrity Health Acupuncture",
    "wof:placetype":"venue"
},
  "geometry": {"coordinates":[-122.660588,45.548988],"type":"Point"}
}