{
  "type": "Feature",
  "properties": {
    "addr:full":"9155 SW Barnes Rd Portland OR 97225",
    "addr:housenumber":"9155",
    "addr:postcode":"97225",
    "addr:street":"Sw Barnes Rd",
    "iso:country":"US",
    "sg:address":"9155 SW Barnes Rd",
    "sg:city":"Portland",
    "sg:classifiers":[
        {
            "category":"Shopping",
            "type":"Retail Goods"
        }
    ],
    "sg:phone":"+1 503 227 5109",
    "sg:postcode":"97225",
    "sg:province":"OR",
    "sg:tags":[
        "hearing",
        "equipment",
        "supply",
        "impaired"
    ],
    "wof:name":"Audiology Associates",
    "wof:placetype":"venue"
},
  "geometry": {"coordinates":[-122.772109,45.509065],"type":"Point"}
}