{
  "type": "Feature",
  "properties": {
    "iso:country":"US",
    "sg:address":"1020 SW Indian Ave Suite 103",
    "sg:city":"Redmond",
    "sg:classifiers":[
        {
            "category":"Banks & Credit Unions",
            "subcategory":"Investment Brokerage",
            "type":"Services"
        },
        {
            "category":"Banks & Credit Unions",
            "subcategory":"Bank",
            "type":"Services"
        },
        {
            "category":"Banks & Credit Unions",
            "subcategory":"Financial Services",
            "type":"Services"
        }
    ],
    "sg:phone":"+1 541 923 8848",
    "sg:postcode":"97756",
    "sg:province":"OR",
    "sg:tags":[
        "advisory",
        "mutual",
        "retirement",
        "annuity",
        "broker",
        "fund",
        "planning",
        "plan",
        "consultant",
        "security",
        "bond",
        "insurance",
        "stock"
    ],
    "sg:website":"http://bend.citysearch.com/profile/external/604328802/redmond_or/edward_jones_david_j_bishop.html?publisher=yellowpages&reference_id=1&placement=ypwebsitemip",
    "wof:name":"Edward Jones - DAVID J BISHOP",
    "wof:placetype":"venue"
},
  "geometry": {"coordinates":[-121.178889,44.268351],"type":"Point"}
}