{
  "type": "Feature",
  "properties": {
    "iso:country":"US",
    "sg:address":"223 N Grant St",
    "sg:city":"Canby",
    "sg:classifiers":[
        {
            "category":"Organizations",
            "subcategory":"Community Association",
            "type":"Services"
        }
    ],
    "sg:phone":"+1 503 266 3975",
    "sg:postcode":"97013",
    "sg:province":"OR",
    "sg:tags":[
        "fraternal"
    ],
    "wof:name":"Canby Odd Fellows Lodge Hall",
    "wof:placetype":"venue"
},
  "geometry": {"coordinates":[-122.696296,45.263273],"type":"Point"}
}