{
  "type": "Feature",
  "properties": {
    "iso:country":"US",
    "sg:address":"1035 2nd St NE",
    "sg:city":"Bandon",
    "sg:classifiers":[
        {
            "category":"Professional",
            "subcategory":"Accounting & Tax Preparation",
            "type":"Services"
        }
    ],
    "sg:phone":"+1 541 347 2917",
    "sg:postcode":"97411",
    "sg:province":"OR",
    "sg:tags":[
        "return",
        "filing"
    ],
    "wof:name":"Bandon Bookkeeping Svc",
    "wof:placetype":"venue"
},
  "geometry": {"coordinates":[-124.39959,43.122125],"type":"Point"}
}