{
  "type": "Feature",
  "properties": {
    "iso:country":"US",
    "sg:address":"14865 SW 74th Ave Ste 260",
    "sg:city":"Portland",
    "sg:classifiers":[
        {
            "category":"Wholesale",
            "subcategory":"Machinery & Supplies",
            "type":"Manufacturing & Wholesale Goods"
        }
    ],
    "sg:phone":"+1 503 968 2269",
    "sg:postcode":"97224",
    "sg:province":"OR",
    "sg:tags":[
        "generator"
    ],
    "wof:name":"Performance Power Concept",
    "wof:placetype":"venue"
},
  "geometry": {"coordinates":[-122.752543,45.414074],"type":"Point"}
}