{
  "type": "Feature",
  "properties": {
    "addr:full":"10122 SE Jesse Ln Portland OR 97266",
    "addr:postcode":"10122;97266",
    "addr:street":"Se Jesse Ln",
    "iso:country":"US",
    "sg:address":"10122 SE Jesse Ln",
    "sg:city":"Portland",
    "sg:classifiers":[
        {
            "category":"Restaurant",
            "type":"Food & Drink"
        }
    ],
    "sg:phone":"+1 503 761 1518",
    "sg:postcode":"97266",
    "sg:province":"OR",
    "sg:tags":[
        "asian",
        "chinese",
        "pan"
    ],
    "wof:name":"House Of Chan, The Inc.",
    "wof:placetype":"venue"
},
  "geometry": {"coordinates":[-122.55940200000001,45.501489],"type":"Point"}
}