{
  "type": "Feature",
  "properties": {
    "addr:full":"9469 SW Washington Square Rd Tigard OR 97223",
    "addr:housenumber":"9469",
    "addr:postcode":"97223",
    "addr:street":"Sw Washington Square Rd",
    "iso:country":"US",
    "sg:address":"9469 SW Washington Square Rd",
    "sg:city":"Tigard",
    "sg:classifiers":[
        {
            "category":"Food & Beverages",
            "subcategory":"Specialty",
            "type":"Retail Goods"
        }
    ],
    "sg:phone":"+1 503 684 0600",
    "sg:postcode":"97223",
    "sg:province":"OR",
    "sg:tags":[
        "health",
        "diet"
    ],
    "sg:website":"www.gnc.com",
    "wof:name":"General Nutrition Ctr",
    "wof:placetype":"venue"
},
  "geometry": {"coordinates":[-122.781003,45.446476],"type":"Point"}
}