{
  "type": "Feature",
  "properties": {
    "addr:full":"1708 SE 76th Ave Portland OR 97215",
    "addr:housenumber":"1708",
    "addr:postcode":"97215",
    "addr:street":"Se 76Th Ave",
    "iso:country":"US",
    "sg:address":"1708 SE 76th Ave",
    "sg:city":"Portland",
    "sg:classifiers":[
        {
            "category":"Shopping",
            "subcategory":"Music",
            "type":"Retail Goods"
        }
    ],
    "sg:phone":"+1 503 771 3403",
    "sg:postcode":"97215",
    "sg:province":"OR",
    "sg:tags":[
        "store"
    ],
    "wof:name":"Bob's Yesterday Records",
    "wof:placetype":"venue"
},
  "geometry": {"coordinates":[-122.58528,45.510664],"type":"Point"}
}