{
  "type": "Feature",
  "properties": {
    "iso:country":"US",
    "sg:address":"14314 SW Allen Blvd",
    "sg:city":"Beaverton",
    "sg:classifiers":[
        {
            "category":"Building & Trades",
            "subcategory":"Cleaning & Sanitation",
            "type":"Services"
        }
    ],
    "sg:phone":"+1 503 626 6327",
    "sg:postcode":"97005",
    "sg:province":"OR",
    "sg:tags":[
        "maintenance"
    ],
    "wof:name":"Celeste J Pinherio",
    "wof:placetype":"venue"
},
  "geometry": {"coordinates":[-122.825805,45.476379],"type":"Point"}
}