{
  "type": "Feature",
  "properties": {
    "addr:full":"2889 D St Baker City OR 97814",
    "addr:housenumber":"2889",
    "addr:postcode":"97814",
    "addr:street":"D St",
    "iso:country":"US",
    "sg:address":"2889 D St",
    "sg:city":"Baker City",
    "sg:classifiers":[
        {
            "category":"Health Services",
            "subcategory":"Doctor",
            "type":"Services"
        }
    ],
    "sg:phone":"+1 541 523 3870",
    "sg:postcode":"97814",
    "sg:province":"OR",
    "sg:tags":[
        "dentist"
    ],
    "wof:name":"Joel Bender DMD",
    "wof:placetype":"venue"
},
  "geometry": {"coordinates":[-117.839991,44.785259],"type":"Point"}
}