{
  "type": "Feature",
  "properties": {
    "iso:country":"US",
    "sg:address":"6626 Tarry Ln",
    "sg:city":"Talent",
    "sg:classifiers":[
        {
            "category":"Wholesale",
            "subcategory":"Fruits & Vegetables",
            "type":"Manufacturing & Wholesale Goods"
        }
    ],
    "sg:phone":"+1 541 535 2505",
    "sg:postcode":"97540",
    "sg:province":"OR",
    "sg:tags":[
        "shipper"
    ],
    "wof:name":"Meyer Orchards",
    "wof:placetype":"venue"
},
  "geometry": {"coordinates":[-122.801908,42.235713],"type":"Point"}
}