{
  "type": "Feature",
  "properties": {
    "iso:country":"US",
    "sg:address":"493 NE 3rd Ave",
    "sg:city":"Canby",
    "sg:classifiers":[
        {
            "category":"Retail",
            "subcategory":"Repair Shop",
            "type":"Services"
        }
    ],
    "sg:phone":"+1 503 314 7699",
    "sg:postcode":"97013",
    "sg:province":"OR",
    "wof:name":"Masons Custom Motorcycle & Ser",
    "wof:placetype":"venue"
},
  "geometry": {"coordinates":[-122.68815499999999,45.266185],"type":"Point"}
}