{
  "type": "Feature",
  "properties": {
    "addr:full":"314 Southeast Grand Avenue Portland OR 97214",
    "addr:housenumber":"314",
    "addr:postcode":"97214",
    "addr:street":"Southeast Grand Avenue",
    "iso:country":"US",
    "sg:address":"314 Southeast Grand Avenue",
    "sg:city":"Portland",
    "sg:classifiers":[
        {
            "category":"Retail",
            "subcategory":"Auto Repair",
            "type":"Services"
        }
    ],
    "sg:phone":"+1 503 236 0001",
    "sg:postcode":"97214",
    "sg:province":"OR",
    "sg:tags":[
        "body",
        "shop"
    ],
    "wof:name":"Straightline Body & Paint",
    "wof:placetype":"venue"
},
  "geometry": {"coordinates":[-122.660392,45.520509],"type":"Point"}
}