{
  "type": "Feature",
  "properties": {
    "iso:country":"US",
    "sg:address":"303 N Pacific Hwy",
    "sg:city":"Woodburn",
    "sg:classifiers":[
        {
            "category":"Food & Beverages",
            "subcategory":"Groceries & Convenience Stores",
            "type":"Retail Goods"
        }
    ],
    "sg:phone":"+1 503 981 4455",
    "sg:postcode":"97071",
    "sg:province":"OR",
    "sg:tags":[
        "eating"
    ],
    "wof:name":"Crossroads",
    "wof:placetype":"venue"
},
  "geometry": {"coordinates":[-122.84298800000001,45.138137],"type":"Point"}
}