{
  "type": "Feature",
  "properties": {
    "addr:full":"1600 NE Alberta St Portland OR 97211",
    "addr:housenumber":"1600",
    "addr:postcode":"97211",
    "addr:street":"Ne Alberta St",
    "iso:country":"US",
    "sg:address":"1600 NE Alberta St",
    "sg:city":"Portland",
    "sg:classifiers":[
        {
            "category":"Shopping",
            "subcategory":"Books",
            "type":"Retail Goods"
        }
    ],
    "sg:phone":"+1 503 954 2354",
    "sg:postcode":"97211",
    "sg:province":"OR",
    "sg:tags":[
        "bookstore"
    ],
    "wof:name":"Green Bean Books",
    "wof:placetype":"venue"
},
  "geometry": {"coordinates":[-122.648545,45.558941],"type":"Point"}
}