{
  "type": "Feature",
  "properties": {
    "iso:country":"US",
    "sg:address":"3125 E Burnside St",
    "sg:city":"Portland",
    "sg:classifiers":[
        {
            "category":"Organizations",
            "subcategory":"Non-profit Organization",
            "type":"Services"
        }
    ],
    "sg:phone":"+1 503 235 8946",
    "sg:postcode":"97214",
    "sg:province":"OR",
    "sg:tags":[
        "service/non-profit",
        "community"
    ],
    "wof:name":"City Repair Project",
    "wof:placetype":"venue"
},
  "geometry": {"coordinates":[-122.63249500000001,45.52312],"type":"Point"}
}