{
  "type": "Feature",
  "properties": {
    "iso:country":"US",
    "sg:address":"3763 Market St NE",
    "sg:city":"Salem",
    "sg:classifiers":[
        {
            "category":"Retail",
            "subcategory":"Auto Repair",
            "type":"Services"
        }
    ],
    "sg:phone":"+1 503 362 1603",
    "sg:postcode":"97301",
    "sg:province":"OR",
    "sg:tags":[
        "repairing",
        "automobile"
    ],
    "wof:name":"Superior Auto Svc",
    "wof:placetype":"venue"
},
  "geometry": {"coordinates":[-122.98566,44.950225],"type":"Point"}
}