{
  "type": "Feature",
  "properties": {
    "iso:country":"US",
    "sg:address":"112 SE M St",
    "sg:city":"Grants Pass",
    "sg:classifiers":[
        {
            "category":"Shopping",
            "subcategory":"Hobbies, Toys, & Games",
            "type":"Retail Goods"
        }
    ],
    "sg:phone":"+1 541 474 9896",
    "sg:postcode":"97526",
    "sg:province":"OR",
    "sg:tags":[
        "craft"
    ],
    "wof:name":"First Moms Club",
    "wof:placetype":"venue"
},
  "geometry": {"coordinates":[-123.328969,42.433522],"type":"Point"}
}