{
  "type": "Feature",
  "properties": {
    "iso:country":"US",
    "sg:address":"5709 Main St",
    "sg:city":"Springfield",
    "sg:classifiers":[
        {
            "category":"Health Services",
            "subcategory":"Health Practitioner",
            "type":"Services"
        }
    ],
    "sg:phone":"+1 541 988 3337",
    "sg:postcode":"97478",
    "sg:province":"OR",
    "wof:name":"Cheryl Gesik Pt",
    "wof:placetype":"venue"
},
  "geometry": {"coordinates":[-122.92685400000001,44.045613],"type":"Point"}
}