{
  "type": "Feature",
  "properties": {
    "iso:country":"US",
    "sg:address":"203 SE 1st Ave",
    "sg:city":"Canby",
    "sg:classifiers":[
        {
            "category":"Professional",
            "type":"Services"
        }
    ],
    "sg:phone":"+1 503 263 2114",
    "sg:postcode":"97013",
    "sg:province":"OR",
    "wof:name":"Canby Made By You",
    "wof:placetype":"venue"
},
  "geometry": {"coordinates":[-122.689606,45.26312],"type":"Point"}
}