{
  "type": "Feature",
  "properties": {
    "iso:country":"US",
    "sg:address":"9201 SE 91st Ave Ste 150",
    "sg:city":"Portland",
    "sg:classifiers":[
        {
            "category":"Retail",
            "subcategory":"Laundry & Dry Cleaning",
            "type":"Services"
        }
    ],
    "sg:phone":"+1 503 777 5638",
    "sg:postcode":"97086",
    "sg:province":"OR",
    "wof:name":"Mt Scott Dry Cleaners",
    "wof:placetype":"venue"
},
  "geometry": {"coordinates":[-122.57004499999999,45.45672],"type":"Point"}
}