{
  "type": "Feature",
  "properties": {
    "iso:country":"US",
    "sg:address":"2031 SE Belmont St",
    "sg:city":"Portland",
    "sg:classifiers":[
        {
            "category":"Organizations",
            "subcategory":"Non-profit Organization",
            "type":"Services"
        }
    ],
    "sg:phone":"+1 503 230 0421",
    "sg:postcode":"97214",
    "sg:province":"OR",
    "sg:website":"www.wildsalmon.org",
    "wof:name":"Save Our Wild Salmon",
    "wof:placetype":"venue"
},
  "geometry": {"coordinates":[-122.642711,45.516528],"type":"Point"}
}