{
  "type": "Feature",
  "properties": {
    "iso:country":"US",
    "sg:address":"660 NE 3rd St",
    "sg:city":"Bend",
    "sg:classifiers":[
        {
            "category":"Shopping",
            "subcategory":"Discount & Variety Stores",
            "type":"Retail Goods"
        },
        {
            "category":"Shopping",
            "subcategory":"Department Store",
            "type":"Retail Goods"
        }
    ],
    "sg:phone":"+1 541 388 8145",
    "sg:postcode":"97701",
    "sg:province":"OR",
    "wof:name":"Amazing Deals LLC",
    "wof:placetype":"venue"
},
  "geometry": {"coordinates":[-121.302425,44.056343],"type":"Point"}
}