{
  "type": "Feature",
  "properties": {
    "iso:country":"US",
    "sg:address":"41181 SW Laurelwood Rd",
    "sg:city":"Gaston",
    "sg:classifiers":[
        {
            "category":"Farming",
            "subcategory":"Farm",
            "type":"Manufacturing & Wholesale Goods"
        }
    ],
    "sg:phone":"+1 503 985 1060",
    "sg:postcode":"97119",
    "sg:province":"OR",
    "sg:tags":[
        "crop",
        "general"
    ],
    "wof:name":"Eugene Delplanche",
    "wof:placetype":"venue"
},
  "geometry": {"coordinates":[-123.099918,45.420233],"type":"Point"}
}