{
  "type": "Feature",
  "properties": {
    "iso:country":"US",
    "sg:address":"140 1st Ave E",
    "sg:city":"Albany",
    "sg:classifiers":[
        {
            "category":"Home & Garden",
            "subcategory":"Carpets & Floor Coverings",
            "type":"Retail Goods"
        }
    ],
    "sg:phone":"+1 541 928 0755",
    "sg:postcode":"97321",
    "sg:province":"OR",
    "sg:tags":[
        "dealer",
        "rug"
    ],
    "wof:name":"Ak Carpet & More Inc",
    "wof:placetype":"venue"
},
  "geometry": {"coordinates":[-123.10408200000001,44.637436],"type":"Point"}
}