{
  "type": "Feature",
  "properties": {
    "iso:country":"US",
    "sg:address":"9115 SW Oleson Rd",
    "sg:city":"Portland",
    "sg:classifiers":[
        {
            "category":"Insurance",
            "subcategory":"Insurance Agent",
            "type":"Services"
        }
    ],
    "sg:phone":"+1 503 244 5550",
    "sg:postcode":"97223",
    "sg:province":"OR",
    "wof:name":"Agents Financial Service",
    "wof:placetype":"venue"
},
  "geometry": {"coordinates":[-122.77221400000001,45.454367],"type":"Point"}
}