{
  "type": "Feature",
  "properties": {
    "iso:country":"US",
    "sg:address":"5335 Daisy St",
    "sg:city":"Springfield",
    "sg:classifiers":[
        {
            "category":"Wholesale",
            "subcategory":"Durable Goods & Equipment",
            "type":"Manufacturing & Wholesale Goods"
        }
    ],
    "sg:phone":"+1 541 726 5797",
    "sg:postcode":"97478",
    "sg:province":"OR",
    "wof:name":"Sunshine Unlimited",
    "wof:placetype":"venue"
},
  "geometry": {"coordinates":[-122.935782,44.041607],"type":"Point"}
}