{
  "type": "Feature",
  "properties": {
    "iso:country":"US",
    "sg:address":"112 SE Douglas St",
    "sg:city":"Newport",
    "sg:classifiers":[
        {
            "category":"Government",
            "subcategory":"Office",
            "type":"Public Place"
        }
    ],
    "sg:phone":"+1 541 574 2688",
    "sg:postcode":"97365",
    "sg:province":"OR",
    "sg:tags":[
        "county",
        "resource"
    ],
    "wof:name":"Lincoln County Council-Aging",
    "wof:placetype":"venue"
},
  "geometry": {"coordinates":[-124.048108,44.636103],"type":"Point"}
}