{
  "type": "Feature",
  "properties": {
    "addr:full":"33685 Highway 99E Tangent OR 97389",
    "addr:housenumber":"33685",
    "addr:postcode":"97389",
    "addr:street":"Highway 99E",
    "iso:country":"US",
    "sg:address":"33685 Highway 99E",
    "sg:city":"Tangent",
    "sg:classifiers":[
        {
            "category":"Deli",
            "type":"Food & Drink"
        },
        {
            "category":"Restaurant",
            "type":"Food & Drink"
        },
        {
            "category":"Food & Beverages",
            "subcategory":"Groceries & Convenience Stores",
            "type":"Retail Goods"
        }
    ],
    "sg:phone":"+1 541 926 6323",
    "sg:postcode":"97389",
    "sg:province":"OR",
    "sg:tags":[
        "delicatessen"
    ],
    "wof:name":"CrossRoads Deli & Company",
    "wof:placetype":"venue"
},
  "geometry": {"coordinates":[-123.11000799999999,44.55442],"type":"Point"}
}