{
  "type": "Feature",
  "properties": {
    "addr:full":"4427 Satter Pl NE Salem OR 97305",
    "addr:housenumber":"4427",
    "addr:postcode":"97305",
    "addr:street":"Satter Pl Ne",
    "iso:country":"US",
    "sg:address":"4427 Satter Pl NE",
    "sg:city":"Salem",
    "sg:classifiers":[
        {
            "category":"Real Estate",
            "subcategory":"Real Estate Operator",
            "type":"Services"
        }
    ],
    "sg:phone":"+1 503 393 1872",
    "sg:postcode":"97305",
    "sg:province":"OR",
    "sg:tags":[
        "building",
        "apartment"
    ],
    "wof:name":"Greenwood Park Apartments",
    "wof:placetype":"venue"
},
  "geometry": {"coordinates":[-122.975133,44.979884],"type":"Point"}
}