{
  "type": "Feature",
  "properties": {
    "addr:full":"300 S Redwood St Canby OR 97013",
    "addr:housenumber":"300",
    "addr:postcode":"97013",
    "addr:street":"S Redwood St",
    "iso:country":"US",
    "sg:address":"300 S Redwood St",
    "sg:city":"Canby",
    "sg:classifiers":[
        {
            "category":"Insurance",
            "subcategory":"Insurance Agent",
            "type":"Services"
        }
    ],
    "sg:phone":"+1 503 742 1695",
    "sg:postcode":"97013",
    "sg:province":"OR",
    "wof:name":"American Family Insurance",
    "wof:placetype":"venue"
},
  "geometry": {"coordinates":[-122.676627,45.262321],"type":"Point"}
}