{
  "type": "Feature",
  "properties": {
    "iso:country":"US",
    "sg:address":"2033 Vine St",
    "sg:city":"Grants Pass",
    "sg:classifiers":[
        {
            "category":"Personal",
            "subcategory":"Beauty Salon",
            "type":"Services"
        }
    ],
    "sg:phone":"+1 541 479 0749",
    "sg:postcode":"97526",
    "sg:province":"OR",
    "wof:name":"Positive Outlooks Hair Designs",
    "wof:placetype":"venue"
},
  "geometry": {"coordinates":[-123.32355099999999,42.46279],"type":"Point"}
}