{
  "type": "Feature",
  "properties": {
    "iso:country":"US",
    "sg:address":"2225 NE Alberta Ste A",
    "sg:city":"Portland",
    "sg:classifiers":[
        {
            "category":"Banks & Credit Unions",
            "subcategory":"Atm",
            "type":"Services"
        }
    ],
    "sg:phone":"+1 503 860 6868",
    "sg:postcode":"97211",
    "sg:province":"OR",
    "sg:tags":[
        "bankruptcy"
    ],
    "sg:website":"www.nwdrlf.com",
    "wof:name":"Northwest Debt Relief Law Firm",
    "wof:placetype":"venue"
},
  "geometry": {"coordinates":[-122.64225,45.559067],"type":"Point"}
}