{
  "type": "Feature",
  "properties": {
    "addr:full":"1456 Pine St Silverton OR 97381",
    "addr:housenumber":"1456",
    "addr:postcode":"97381",
    "addr:street":"Pine St",
    "iso:country":"US",
    "sg:address":"1456 Pine St",
    "sg:city":"Silverton",
    "sg:classifiers":[
        {
            "category":"Education",
            "subcategory":"School",
            "type":"Public Place"
        }
    ],
    "sg:phone":"+1 503 873 1970",
    "sg:postcode":"97381",
    "sg:province":"OR",
    "wof:name":"Silverton High School Pine",
    "wof:placetype":"venue"
},
  "geometry": {"coordinates":[-122.79855000000001,45.01151],"type":"Point"}
}