{
  "type": "Feature",
  "properties": {
    "addr:full":"29555 SW Boones Ferry Rd Wilsonville OR 97070",
    "addr:housenumber":"29555",
    "addr:postcode":"97070",
    "addr:street":"Sw Boones Ferry Rd",
    "iso:country":"US",
    "sg:address":"29555 SW Boones Ferry Rd",
    "sg:city":"Wilsonville",
    "sg:classifiers":[
        {
            "category":"Shopping",
            "subcategory":"Pharmacy",
            "type":"Retail Goods"
        }
    ],
    "sg:phone":"+1 503 682 2701",
    "sg:postcode":"97070",
    "sg:province":"OR",
    "sg:tags":[
        "photofinishing",
        "laboratory"
    ],
    "wof:name":"Rite Aid",
    "wof:placetype":"venue"
},
  "geometry": {"coordinates":[-122.769932,45.306591],"type":"Point"}
}