{
  "type": "Feature",
  "properties": {
    "iso:country":"US",
    "sg:address":"160 NE 6th St",
    "sg:city":"Newport",
    "sg:classifiers":[
        {
            "category":"Health Services",
            "subcategory":"Medical Lab",
            "type":"Services"
        }
    ],
    "sg:phone":"+1 541 265 8200",
    "sg:postcode":"97365",
    "sg:province":"OR",
    "sg:tags":[
        "laboratory",
        "dental"
    ],
    "wof:name":"Bremers Denture Center",
    "wof:placetype":"venue"
},
  "geometry": {"coordinates":[-124.052498,44.640315],"type":"Point"}
}