{
  "type": "Feature",
  "properties": {
    "addr:full":"1355 Boone Rd SE Salem OR 97306",
    "addr:housenumber":"1355",
    "addr:postcode":"97306",
    "addr:street":"Boone Rd Se",
    "iso:country":"US",
    "sg:address":"1355 Boone Rd SE",
    "sg:city":"Salem",
    "sg:classifiers":[
        {
            "category":"Health Services",
            "subcategory":"Nursing And Care Facility",
            "type":"Services"
        }
    ],
    "sg:phone":"+1 503 365 7500",
    "sg:postcode":"97306",
    "sg:province":"OR",
    "sg:tags":[
        "home",
        "skilled",
        "convalescent"
    ],
    "sg:website":"http://www.brookdaleliving.com/clare-bridge-of-salem.aspx",
    "wof:name":"Clare Bridge of Salem",
    "wof:placetype":"venue"
},
  "geometry": {"coordinates":[-123.028111,44.882992],"type":"Point"}
}