{
  "type": "Feature",
  "properties": {
    "iso:country":"US",
    "sg:address":"23600 SW Newland Rd",
    "sg:city":"Wilsonville",
    "sg:phone":"+1 503 638 4610",
    "sg:postcode":"97070",
    "sg:province":"OR",
    "wof:name":"Arrowhead Cooperative Co Inc",
    "wof:placetype":"venue"
},
  "geometry": {"coordinates":[-122.72258100000001,45.345726],"type":"Point"}
}