{
  "type": "Feature",
  "properties": {
    "iso:country":"US",
    "sg:address":"1124 Main St",
    "sg:city":"Springfield",
    "sg:classifiers":[
        {
            "category":"Professional",
            "subcategory":"Accounting & Tax Preparation",
            "type":"Services"
        }
    ],
    "sg:phone":"+1 541 741 8100",
    "sg:postcode":"97477",
    "sg:province":"OR",
    "wof:name":"S & H Manufacturing",
    "wof:placetype":"venue"
},
  "geometry": {"coordinates":[-123.009371,44.046012],"type":"Point"}
}