{
  "type": "Feature",
  "properties": {
    "iso:country":"US",
    "sg:address":"705 Ewald Ave SE",
    "sg:city":"Salem",
    "sg:classifiers":[
        {
            "category":"Health Services",
            "subcategory":"Chiropractor",
            "type":"Services"
        }
    ],
    "sg:phone":"+1 503 378 0068",
    "sg:postcode":"97302",
    "sg:province":"OR",
    "wof:name":"Chiropractic Psychians PC",
    "wof:placetype":"venue"
},
  "geometry": {"coordinates":[-123.038833,44.901302],"type":"Point"}
}