{
  "type": "Feature",
  "properties": {
    "iso:country":"US",
    "sg:address":"591 Myeena Loop",
    "sg:city":"Florence",
    "sg:classifiers":[
        {
            "category":"Professional",
            "type":"Services"
        }
    ],
    "sg:phone":"+1 541 902 1367",
    "sg:postcode":"97439",
    "sg:province":"OR",
    "wof:name":"3rs Metal Art",
    "wof:placetype":"venue"
},
  "geometry": {"coordinates":[-124.11600900000001,43.997833],"type":"Point"}
}