{
  "type": "Feature",
  "properties": {
    "iso:country":"US",
    "sg:address":"1875 5th Ave W",
    "sg:city":"Vale",
    "sg:phone":"+1 541 473 2648",
    "sg:postcode":"97918",
    "sg:province":"OR",
    "sg:tags":[
        "equine",
        "beef",
        "f",
        "farm",
        "crop",
        "field",
        "cattle"
    ],
    "wof:name":"W Bar Jay",
    "wof:placetype":"venue"
},
  "geometry": {"coordinates":[-117.281099,44.054335],"type":"Point"}
}