{
  "type": "Feature",
  "properties": {
    "iso:country":"US",
    "sg:address":"2350 Ferry St SW",
    "sg:city":"Albany",
    "sg:classifiers":[
        {
            "category":"Building & Trades",
            "subcategory":"Construction",
            "type":"Services"
        }
    ],
    "sg:phone":"+1 541 928 8842",
    "sg:postcode":"97322",
    "sg:province":"OR",
    "sg:tags":[
        "general",
        "contractor"
    ],
    "wof:name":"Allen & Laporte Contractors",
    "wof:placetype":"venue"
},
  "geometry": {"coordinates":[-123.104612,44.618571],"type":"Point"}
}