{
  "type": "Feature",
  "properties": {
    "iso:country":"US",
    "sg:address":"1537 Mount Hood Ave",
    "sg:city":"Woodburn",
    "sg:classifiers":[
        {
            "category":"Utilities",
            "subcategory":"Mobile Phone",
            "type":"Services"
        }
    ],
    "sg:phone":"+1 503 981 3237",
    "sg:postcode":"97071",
    "sg:province":"OR",
    "sg:tags":[
        "telephone",
        "cellular"
    ],
    "wof:name":"Direct Connect Cricket Wireless",
    "wof:placetype":"venue"
},
  "geometry": {"coordinates":[-122.834784,45.151366],"type":"Point"}
}