{
  "type": "Feature",
  "properties": {
    "iso:country":"US",
    "sg:address":"90697 Huntley Ct",
    "sg:city":"Coburg",
    "sg:classifiers":[
        {
            "category":"Wholesale",
            "subcategory":"Hardware",
            "type":"Manufacturing & Wholesale Goods"
        }
    ],
    "sg:phone":"+1 541 484 5291",
    "sg:postcode":"97408",
    "sg:province":"OR",
    "sg:tags":[
        "refrigerating"
    ],
    "wof:name":"Danco Refrigeration Inc",
    "wof:placetype":"venue"
},
  "geometry": {"coordinates":[-123.05462799999999,44.127238],"type":"Point"}
}