{
  "type": "Feature",
  "properties": {
    "iso:country":"US",
    "sg:address":"1670 Willamette St",
    "sg:city":"Eugene",
    "sg:classifiers":[
        {
            "category":"Organizations",
            "subcategory":"Non-profit Organization",
            "type":"Services"
        }
    ],
    "sg:phone":"+1 541 686 2771",
    "sg:postcode":"97401",
    "sg:province":"OR",
    "sg:website":"www.ffpir.org",
    "wof:name":"Fund For Public Interest Rsrch",
    "wof:placetype":"venue"
},
  "geometry": {"coordinates":[-123.09282899999999,44.04136],"type":"Point"}
}