{
  "type": "Feature",
  "properties": {
    "addr:full":"4125 SE 82nd Ave Portland OR 97266",
    "addr:housenumber":"4125",
    "addr:postcode":"97266",
    "addr:street":"Se 82Nd Ave",
    "iso:country":"US",
    "sg:address":"4125 SE 82nd Ave",
    "sg:city":"Portland",
    "sg:classifiers":[
        {
            "category":"Retail",
            "subcategory":"Auto Repair",
            "type":"Services"
        }
    ],
    "sg:phone":"+1 503 262 8326",
    "sg:postcode":"97266",
    "sg:province":"OR",
    "sg:website":"www.braketeam.pro/portland-autom...",
    "wof:name":"Brake Team",
    "wof:placetype":"venue"
},
  "geometry": {"coordinates":[-122.579312,45.49228],"type":"Point"}
}