{
  "type": "Feature",
  "properties": {
    "addr:full":"1812 NW 24th Ave Portland OR 97210",
    "addr:housenumber":"1812",
    "addr:postcode":"97210",
    "addr:street":"Nw 24Th Ave",
    "iso:country":"US",
    "sg:address":"1812 NW 24th Ave",
    "sg:city":"Portland",
    "sg:classifiers":[
        {
            "category":"Museum",
            "type":"Entertainment"
        }
    ],
    "sg:phone":"+1 503 224 6729",
    "sg:postcode":"97210",
    "sg:province":"OR",
    "sg:tags":[
        "gallery"
    ],
    "wof:name":"Carpenter Studio",
    "wof:placetype":"venue"
},
  "geometry": {"coordinates":[-122.700748,45.536791],"type":"Point"}
}