{
  "type": "Feature",
  "properties": {
    "addr:full":"4277 Orchard Heights Rd NW Salem OR 97304",
    "addr:housenumber":"4277",
    "addr:postcode":"97304",
    "addr:street":"Orchard Heights Rd Nw",
    "iso:country":"US",
    "sg:address":"4277 Orchard Heights Rd NW",
    "sg:city":"Salem",
    "sg:classifiers":[
        {
            "category":"Manufacturing",
            "subcategory":"Printing",
            "type":"Manufacturing & Wholesale Goods"
        }
    ],
    "sg:phone":"+1 503 540 8876",
    "sg:postcode":"97304",
    "sg:province":"OR",
    "sg:tags":[
        "commercial"
    ],
    "wof:name":"Screen Play Ink",
    "wof:placetype":"venue"
},
  "geometry": {"coordinates":[-123.11497300000001,44.96665],"type":"Point"}
}