{
  "type": "Feature",
  "properties": {
    "iso:country":"US",
    "sg:address":"7900 Sterling Creek Rd",
    "sg:city":"Jacksonville",
    "sg:classifiers":[
        {
            "category":"Building & Trades",
            "subcategory":"Construction",
            "type":"Services"
        }
    ],
    "sg:phone":"+1 541 890 0059",
    "sg:postcode":"97530",
    "sg:province":"OR",
    "sg:tags":[
        "carpentry",
        "contractor"
    ],
    "wof:name":"Robert Salisbury Construction",
    "wof:placetype":"venue"
},
  "geometry": {"coordinates":[-122.955488,42.194607],"type":"Point"}
}