{
  "type": "Feature",
  "properties": {
    "addr:full":"1254 E Madison Ave Cottage Grove OR 97424",
    "addr:housenumber":"1254",
    "addr:postcode":"97424",
    "addr:street":"E Madison Ave",
    "iso:country":"US",
    "sg:address":"1254 E Madison Ave",
    "sg:city":"Cottage Grove",
    "sg:classifiers":[
        {
            "category":"Shopping",
            "subcategory":"Computers & Home Electronics",
            "type":"Retail Goods"
        }
    ],
    "sg:phone":"+1 541 942 9481",
    "sg:postcode":"97424",
    "sg:province":"OR",
    "sg:tags":[
        "comp"
    ],
    "wof:name":"Trozco",
    "wof:placetype":"venue"
},
  "geometry": {"coordinates":[-123.05407,43.794138],"type":"Point"}
}