{
  "type": "Feature",
  "properties": {
    "addr:full":"1884 Murphy Creek Rd Grants Pass OR 97527",
    "addr:housenumber":"1884",
    "addr:postcode":"97527",
    "addr:street":"Murphy Creek Rd",
    "iso:country":"US",
    "sg:address":"1884 Murphy Creek Rd",
    "sg:city":"Grants Pass",
    "sg:classifiers":[
        {
            "category":"Shopping",
            "subcategory":"Hobbies, Toys, & Games",
            "type":"Retail Goods"
        }
    ],
    "sg:phone":"+1 541 862 0600",
    "sg:postcode":"97527",
    "sg:province":"OR",
    "wof:name":"Birdi Toy Chest",
    "wof:placetype":"venue"
},
  "geometry": {"coordinates":[-123.368859,42.302431],"type":"Point"}
}