{
  "type": "Feature",
  "properties": {
    "addr:full":"4599 Grant Rd Central Point OR 97502",
    "addr:housenumber":"4599",
    "addr:postcode":"97502",
    "addr:street":"Grant Rd",
    "iso:country":"US",
    "sg:address":"4599 Grant Rd",
    "sg:city":"Central Point",
    "sg:classifiers":[
        {
            "category":"Freight",
            "type":"Transportation"
        }
    ],
    "sg:phone":"+1 541 664 2734",
    "sg:postcode":"97502",
    "sg:province":"OR",
    "sg:tags":[
        "operator",
        "trucking"
    ],
    "wof:name":"Ralph R Kerr",
    "wof:placetype":"venue"
},
  "geometry": {"coordinates":[-122.93460899999999,42.381606],"type":"Point"}
}