{
  "type": "Feature",
  "properties": {
    "addr:full":"4698 Bluebelle Way Springfield OR 97478",
    "addr:housenumber":"4698",
    "addr:postcode":"97478",
    "addr:street":"Bluebelle Way",
    "iso:country":"US",
    "sg:address":"4698 Bluebelle Way",
    "sg:city":"Springfield",
    "sg:classifiers":[
        {
            "category":"Social Services",
            "subcategory":"Child Care",
            "type":"Services"
        }
    ],
    "sg:phone":"+1 541 744 9096",
    "sg:postcode":"97478",
    "sg:province":"OR",
    "sg:tags":[
        "day"
    ],
    "wof:name":"Braley Bunch",
    "wof:placetype":"venue"
},
  "geometry": {"coordinates":[-122.95349400000001,44.043165],"type":"Point"}
}