{
  "type": "Feature",
  "properties": {
    "iso:country":"US",
    "sg:address":"12355 NW Newell Pl",
    "sg:city":"Forest Grove",
    "sg:classifiers":[
        {
            "category":"Building & Trades",
            "subcategory":"Construction",
            "type":"Services"
        }
    ],
    "sg:phone":"+1 503 357 0236",
    "sg:postcode":"97116",
    "sg:province":"OR",
    "sg:tags":[
        "excavation",
        "contractor"
    ],
    "wof:name":"Dan J Fischer Excavating Inc",
    "wof:placetype":"venue"
},
  "geometry": {"coordinates":[-123.217268,45.613369],"type":"Point"}
}