{
  "type": "Feature",
  "properties": {
    "addr:full":"633 E Main St Molalla OR 97038",
    "addr:housenumber":"633",
    "addr:postcode":"97038",
    "addr:street":"E Main St",
    "iso:country":"US",
    "sg:address":"633 E Main St",
    "sg:city":"Molalla",
    "sg:classifiers":[
        {
            "category":"Manufacturing",
            "subcategory":"Lumber",
            "type":"Manufacturing & Wholesale Goods"
        }
    ],
    "sg:phone":"+1 503 829 9252",
    "sg:postcode":"97038",
    "sg:province":"OR",
    "sg:tags":[
        "operation",
        "timber",
        "tract"
    ],
    "wof:name":"Victor Ems",
    "wof:placetype":"venue"
},
  "geometry": {"coordinates":[-122.570829,45.146137],"type":"Point"}
}