{
  "type": "Feature",
  "properties": {
    "iso:country":"US",
    "sg:address":"6914 N Moore Ave",
    "sg:city":"Portland",
    "sg:classifiers":[
        {
            "category":"Shopping",
            "subcategory":"Clothing, Apparel, & Fashions",
            "type":"Retail Goods"
        }
    ],
    "sg:phone":"+1 503 283 2832",
    "sg:postcode":"97217",
    "sg:province":"OR",
    "wof:name":"Dekrey Enterprises",
    "wof:placetype":"venue"
},
  "geometry": {"coordinates":[-122.66769,45.573205],"type":"Point"}
}