{
  "type": "Feature",
  "properties": {
    "iso:country":"US",
    "sg:address":"9085 SW Beaverton Hillsdale",
    "sg:city":"Portland",
    "sg:classifiers":[
        {
            "category":"Autos & Motor Vehicles",
            "subcategory":"Fuel & Gas Station",
            "type":"Retail Goods"
        }
    ],
    "sg:phone":"+1 503 292 1747",
    "sg:postcode":"97225",
    "sg:province":"OR",
    "wof:name":"Beaverton Hillsdale Texaco",
    "wof:placetype":"venue"
},
  "geometry": {"coordinates":[-122.770551,45.486302],"type":"Point"}
}