{
  "type": "Feature",
  "properties": {
    "iso:country":"US",
    "sg:address":"9085 SW Beaverton Hillsdale Hwy",
    "sg:city":"Portland",
    "sg:classifiers":[
        {
            "category":"Building & Trades",
            "subcategory":"Locksmith",
            "type":"Services"
        }
    ],
    "sg:phone":"+1 971 228 5029",
    "sg:postcode":"97225",
    "sg:province":"OR",
    "sg:tags":[
        "key"
    ],
    "wof:name":"Always Portland Locksmith",
    "wof:placetype":"venue"
},
  "geometry": {"coordinates":[-122.77081099999999,45.48655],"type":"Point"}
}