{
  "type": "Feature",
  "properties": {
    "iso:country":"US",
    "sg:address":"1306 Adams Ave",
    "sg:city":"La Grande",
    "sg:classifiers":[
        {
            "category":"Professional",
            "subcategory":"Accounting & Tax Preparation",
            "type":"Services"
        }
    ],
    "sg:phone":"+1 541 663 0335",
    "sg:postcode":"97850",
    "sg:province":"OR",
    "sg:tags":[
        "accountant"
    ],
    "wof:name":"J Hume Inc",
    "wof:placetype":"venue"
},
  "geometry": {"coordinates":[-118.093416,45.327854],"type":"Point"}
}