{
  "type": "Feature",
  "properties": {
    "iso:country":"US",
    "sg:address":"3007 NE West Devils Lake Rd",
    "sg:city":"Lincoln City",
    "sg:classifiers":[
        {
            "category":"Health Services",
            "subcategory":"Doctor",
            "type":"Services"
        }
    ],
    "sg:phone":"+1 541 994 9070",
    "sg:postcode":"97367",
    "sg:province":"OR",
    "sg:tags":[
        "physician",
        "surgeon"
    ],
    "wof:name":"Bonnie Kim MD",
    "wof:placetype":"venue"
},
  "geometry": {"coordinates":[-123.996987,44.98835],"type":"Point"}
}