{
  "type": "Feature",
  "properties": {
    "iso:country":"US",
    "sg:address":"946 NE Purcell Blvd",
    "sg:city":"Bend",
    "sg:classifiers":[
        {
            "category":"Communications",
            "subcategory":"Film & Video Production",
            "type":"Services"
        }
    ],
    "sg:phone":"+1 541 617 0623",
    "sg:postcode":"97701",
    "sg:province":"OR",
    "sg:tags":[
        "motion"
    ],
    "wof:name":"Andy Val Productions",
    "wof:placetype":"venue"
},
  "geometry": {"coordinates":[-121.273824,44.060748],"type":"Point"}
}