{
  "type": "Feature",
  "properties": {
    "iso:country":"US",
    "sg:address":"8269 Wilsonville Rd",
    "sg:city":"Wilsonville",
    "sg:classifiers":[
        {
            "category":"Retail",
            "subcategory":"Repair Shop",
            "type":"Services"
        }
    ],
    "sg:phone":"+1 503 682 9757",
    "sg:postcode":"97070",
    "sg:province":"OR",
    "sg:tags":[
        "lock",
        "locksmith"
    ],
    "wof:name":"Wilsonville Lock Works",
    "wof:placetype":"venue"
},
  "geometry": {"coordinates":[-122.762022,45.30307],"type":"Point"}
}