{
  "type": "Feature",
  "properties": {
    "addr:full":"9360 N Columbia Blvd Portland OR 97203",
    "addr:housenumber":"9360",
    "addr:postcode":"97203",
    "addr:street":"N Columbia Blvd",
    "iso:country":"US",
    "sg:address":"9360 N Columbia Blvd",
    "sg:city":"Portland",
    "sg:classifiers":[
        {
            "category":"Government",
            "subcategory":"Office",
            "type":"Public Place"
        }
    ],
    "sg:phone":"+1 503 823 4631",
    "sg:postcode":"97203",
    "sg:province":"OR",
    "sg:tags":[
        "township",
        "government-city",
        "village"
    ],
    "wof:name":"Portland City Of For Information Relating To R",
    "wof:placetype":"venue"
},
  "geometry": {"coordinates":[-122.758315,45.60777],"type":"Point"}
}