{
  "type": "Feature",
  "properties": {
    "iso:country":"US",
    "sg:address":"17527 SE Stark Street",
    "sg:city":"Portland",
    "sg:classifiers":[
        {
            "category":"Restaurant",
            "type":"Food & Drink"
        }
    ],
    "sg:phone":"+1 503 253 7888",
    "sg:postcode":"97233",
    "sg:province":"OR",
    "wof:name":"Wok's Up",
    "wof:placetype":"venue"
},
  "geometry": {"coordinates":[-122.482752,45.519133],"type":"Point"}
}