{
  "type": "Feature",
  "properties": {
    "iso:country":"US",
    "sg:address":"110 NE 25th Ave",
    "sg:city":"Hillsboro",
    "sg:classifiers":[
        {
            "category":"Animal Shelter",
            "type":"Public Place"
        },
        {
            "category":"Retail",
            "subcategory":"Veterinary Services",
            "type":"Services"
        },
        {
            "category":"Retail",
            "subcategory":"Pet Boarding",
            "type":"Services"
        }
    ],
    "sg:phone":"+1 503 693 1063",
    "sg:postcode":"97124",
    "sg:province":"OR",
    "sg:tags":[
        "hospital",
        "specialty",
        "clinic",
        "veterinarian",
        "kennel"
    ],
    "sg:website":"http://www.companionpetclinics.com",
    "wof:name":"Companion Pet Clinics",
    "wof:placetype":"venue"
},
  "geometry": {"coordinates":[-122.95649400000001,45.52124],"type":"Point"}
}