{
  "type": "Feature",
  "properties": {
    "iso:country":"US",
    "sg:address":"38 NW Sleret Ave",
    "sg:city":"Gresham",
    "sg:classifiers":[
        {
            "category":"Wholesale",
            "subcategory":"Machinery & Supplies",
            "type":"Manufacturing & Wholesale Goods"
        }
    ],
    "sg:phone":"+1 503 667 3636",
    "sg:postcode":"97030",
    "sg:province":"OR",
    "sg:tags":[
        "transportation",
        "broker",
        "equipment",
        "aircraft",
        "part",
        "supplies-wholesale",
        "manufacturer"
    ],
    "sg:website":"http://www.transpacificair.com",
    "wof:name":"Trans-Pacific Air Inc",
    "wof:placetype":"venue"
},
  "geometry": {"coordinates":[-122.439612,45.497765],"type":"Point"}
}