{
  "type": "Feature",
  "properties": {
    "addr:full":"336 SW 3rd Ave Portland OR 97204",
    "addr:housenumber":"336",
    "addr:postcode":"97204",
    "addr:street":"Sw 3Rd Ave",
    "iso:country":"US",
    "sg:address":"336 SW 3rd Ave",
    "sg:city":"Portland",
    "sg:classifiers":[
        {
            "category":"Shopping",
            "subcategory":"Used Merchandise",
            "type":"Retail Goods"
        }
    ],
    "sg:phone":"+1 503 228 2391",
    "sg:postcode":"97204",
    "sg:province":"OR",
    "sg:tags":[
        "bookstore",
        "rare",
        "book"
    ],
    "sg:website":"www.cameronsbooks.com",
    "wof:name":"Cameron's Books & Magazines",
    "wof:placetype":"venue"
},
  "geometry": {"coordinates":[-122.674004,45.520802],"type":"Point"}
}