{
  "type": "Feature",
  "properties": {
    "addr:full":"2321 NW Kings Blvd Corvallis OR 97330",
    "addr:housenumber":"2321",
    "addr:postcode":"97330",
    "addr:street":"Nw Kings Blvd",
    "iso:country":"US",
    "sg:address":"2321 NW Kings Blvd",
    "sg:city":"Corvallis",
    "sg:phone":"+1 541 754 7556",
    "sg:postcode":"97330",
    "sg:province":"OR",
    "wof:name":"Corvalis Nails & Spa",
    "wof:placetype":"venue"
},
  "geometry": {"coordinates":[-123.27606,44.590336],"type":"Point"}
}