{
  "type": "Feature",
  "properties": {
    "iso:country":"US",
    "sg:address":"57392 S Morse Rd",
    "sg:city":"Warren",
    "sg:classifiers":[
        {
            "category":"Professional",
            "subcategory":"Business Services",
            "type":"Services"
        }
    ],
    "sg:phone":"+1 503 397 6696",
    "sg:postcode":"97053",
    "sg:province":"OR",
    "wof:name":"Hold Plus-Music & Message Svc",
    "wof:placetype":"venue"
},
  "geometry": {"coordinates":[-122.852231,45.826483],"type":"Point"}
}