{
  "type": "Feature",
  "properties": {
    "addr:full":"15382 NW Energia St Portland OR 97229",
    "addr:housenumber":"15382",
    "addr:postcode":"97229",
    "addr:street":"Nw Energia St",
    "iso:country":"US",
    "sg:address":"15382 NW Energia St",
    "sg:city":"Portland",
    "sg:classifiers":[
        {
            "category":"Professional",
            "subcategory":"Computer Services",
            "type":"Services"
        }
    ],
    "sg:phone":"+1 503 617 1662",
    "sg:postcode":"97229",
    "sg:province":"OR",
    "sg:tags":[
        "datum"
    ],
    "wof:name":"Spectrum Punch Studio",
    "wof:placetype":"venue"
},
  "geometry": {"coordinates":[-122.83626,45.56076],"type":"Point"}
}