{
  "type": "Feature",
  "properties": {
    "addr:full":"485 NW Albemarle Ter Portland OR 97210",
    "addr:housenumber":"485",
    "addr:postcode":"97210",
    "addr:street":"Nw Albemarle Ter",
    "iso:country":"US",
    "sg:address":"485 NW Albemarle Ter",
    "sg:city":"Portland",
    "sg:classifiers":[
        {
            "category":"Professional",
            "type":"Services"
        }
    ],
    "sg:phone":"+1 503 299 4746",
    "sg:postcode":"97210",
    "sg:province":"OR",
    "sg:tags":[
        "arts",
        "artist"
    ],
    "wof:name":"Arko N Studio",
    "wof:placetype":"venue"
},
  "geometry": {"coordinates":[-122.70562200000001,45.526877],"type":"Point"}
}