{
  "type": "Feature",
  "properties": {
    "addr:full":"7750 SW Nimbus Ave Beaverton OR 97008",
    "addr:housenumber":"7750",
    "addr:postcode":"97008",
    "addr:street":"Sw Nimbus Ave",
    "iso:country":"US",
    "sg:address":"7750 SW Nimbus Ave",
    "sg:city":"Beaverton",
    "sg:classifiers":[
        {
            "category":"Manufacturing",
            "subcategory":"Printing",
            "type":"Manufacturing & Wholesale Goods"
        }
    ],
    "sg:phone":"+1 503 641 7351",
    "sg:postcode":"97008",
    "sg:province":"OR",
    "sg:tags":[
        "lithographic",
        "commercial"
    ],
    "wof:name":"TV Screen Printing",
    "wof:placetype":"venue"
},
  "geometry": {"coordinates":[-122.788482,45.462154],"type":"Point"}
}