{
  "type": "Feature",
  "properties": {
    "iso:country":"US",
    "sg:address":"9011 SW Beaverton Hillsdale",
    "sg:city":"Portland",
    "sg:classifiers":[
        {
            "category":"Building & Trades",
            "subcategory":"Construction",
            "type":"Services"
        }
    ],
    "sg:phone":"+1 503 292 1640",
    "sg:postcode":"97225",
    "sg:province":"OR",
    "sg:tags":[
        "contractor"
    ],
    "wof:name":"Brewer Bros Construction",
    "wof:placetype":"venue"
},
  "geometry": {"coordinates":[-122.769747,45.486421],"type":"Point"}
}