{
  "type": "Feature",
  "properties": {
    "iso:country":"US",
    "sg:address":"2145 Manzanita St NE",
    "sg:city":"Keizer",
    "sg:classifiers":[
        {
            "category":"Building & Trades",
            "subcategory":"Construction",
            "type":"Services"
        }
    ],
    "sg:phone":"+1 503 390 8570",
    "sg:postcode":"97303",
    "sg:province":"OR",
    "sg:tags":[
        "general",
        "contractor"
    ],
    "wof:name":"Ed Ziebart Design",
    "wof:placetype":"venue"
},
  "geometry": {"coordinates":[-123.003214,45.011099],"type":"Point"}
}