{
  "type": "Feature",
  "properties": {
    "addr:full":"8469 Cooper Spur Rd Mount Hood Parkdale OR 97041",
    "addr:housenumber":"8469",
    "addr:postcode":"97041",
    "addr:street":"Cooper Spur Rd",
    "iso:country":"US",
    "sg:address":"8469 Cooper Spur Rd",
    "sg:city":"Mount Hood Parkdale",
    "sg:classifiers":[
        {
            "category":"Farming",
            "subcategory":"Orchard",
            "type":"Manufacturing & Wholesale Goods"
        }
    ],
    "sg:phone":"+1 541 352 7741",
    "sg:postcode":"97041",
    "sg:province":"OR",
    "sg:tags":[
        "fruit",
        "tree"
    ],
    "wof:name":"Valley Crest Orchard Inc",
    "wof:placetype":"venue"
},
  "geometry": {"coordinates":[-121.586476,45.485667],"type":"Point"}
}