{
  "type": "Feature",
  "properties": {
    "addr:full":"712 NW 13th St Corvallis OR 97330",
    "addr:housenumber":"712",
    "addr:postcode":"97330",
    "addr:street":"Nw 13Th St",
    "iso:country":"US",
    "sg:address":"712 NW 13th St",
    "sg:city":"Corvallis",
    "sg:classifiers":[
        {
            "category":"Professional",
            "subcategory":"Business Services",
            "type":"Services"
        }
    ],
    "sg:phone":"+1 541 753 9955",
    "sg:postcode":"97330",
    "sg:province":"OR",
    "wof:name":"Poetry Enterprises Inc",
    "wof:placetype":"venue"
},
  "geometry": {"coordinates":[-123.268126,44.573479],"type":"Point"}
}