{
  "type": "Feature",
  "properties": {
    "iso:country":"US",
    "sg:address":"801 N. Scott Rd",
    "sg:city":"Carlton",
    "sg:classifiers":[
        {
            "category":"Food & Beverages",
            "subcategory":"Liquor & Beverages",
            "type":"Retail Goods"
        }
    ],
    "sg:phone":"+1 503 284 6622",
    "sg:postcode":"97111",
    "sg:province":"OR",
    "sg:tags":[
        "beer",
        "spirit",
        "wine"
    ],
    "sg:website":"www.andrewrichwines.com",
    "wof:name":"Andrew Rich Wines",
    "wof:placetype":"venue"
},
  "geometry": {"coordinates":[-123.181999,45.298199],"type":"Point"}
}