{
  "type": "Feature",
  "properties": {
    "iso:country":"US",
    "sg:address":"28558 SW Wagner St",
    "sg:city":"Wilsonville",
    "sg:classifiers":[
        {
            "category":"Professional",
            "subcategory":"Management & Consulting",
            "type":"Services"
        }
    ],
    "sg:phone":"+1 503 682 9570",
    "sg:postcode":"97070",
    "sg:province":"OR",
    "wof:name":"Renaissancce Hospitality Corp",
    "wof:placetype":"venue"
},
  "geometry": {"coordinates":[-122.745261,45.314073],"type":"Point"}
}