{
  "type": "Feature",
  "properties": {
    "iso:country":"US",
    "sg:address":"540 Cross St SE",
    "sg:city":"Salem",
    "sg:classifiers":[
        {
            "category":"Professional",
            "type":"Services"
        }
    ],
    "sg:phone":"+1 503 371 2438",
    "sg:postcode":"97302",
    "sg:province":"OR",
    "wof:name":"Panards Constuction Inc",
    "wof:placetype":"venue"
},
  "geometry": {"coordinates":[-123.040432,44.925535],"type":"Point"}
}