{
  "type": "Feature",
  "properties": {
    "iso:country":"US",
    "sg:address":"2019 NE Josephine Dr",
    "sg:city":"Hillsboro",
    "sg:classifiers":[
        {
            "category":"Professional",
            "subcategory":"Business Services",
            "type":"Services"
        }
    ],
    "sg:phone":"+1 503 680 7939",
    "sg:postcode":"97124",
    "sg:province":"OR",
    "sg:tags":[
        "consultant",
        "coach"
    ],
    "wof:name":"Cafferata Consulting",
    "wof:placetype":"venue"
},
  "geometry": {"coordinates":[-122.98452399999999,45.540113],"type":"Point"}
}