{
  "type": "Feature",
  "properties": {
    "iso:country":"US",
    "sg:address":"90885 US Hwy 101",
    "sg:city":"Warrenton",
    "sg:classifiers":[
        {
            "category":"Building & Trades",
            "subcategory":"Construction",
            "type":"Services"
        }
    ],
    "sg:phone":"+1 503 861 4366",
    "sg:postcode":"97146",
    "sg:province":"OR",
    "sg:tags":[
        "general",
        "contractor"
    ],
    "wof:name":"Tomba Construction",
    "wof:placetype":"venue"
},
  "geometry": {"coordinates":[-123.920456,46.105014],"type":"Point"}
}