{
  "type": "Feature",
  "properties": {
    "iso:country":"US",
    "sg:address":"1520 Pacific Blvd SE",
    "sg:city":"Albany",
    "sg:classifiers":[
        {
            "category":"Bars & Pubs",
            "type":"Food & Drink"
        },
        {
            "category":"Restaurant",
            "type":"Food & Drink"
        },
        {
            "category":"Bars & Pubs",
            "subcategory":"Lounge",
            "type":"Food & Drink"
        }
    ],
    "sg:phone":"+1 541 926 7001",
    "sg:postcode":"97321",
    "sg:province":"OR",
    "sg:tags":[
        "tavern",
        "cocktail"
    ],
    "wof:name":"Wilhelm's Spirits & Eatery",
    "wof:placetype":"venue"
},
  "geometry": {"coordinates":[-123.08684599999999,44.633792],"type":"Point"}
}