{
  "type": "Feature",
  "properties": {
    "addr:full":"22317 Case Rd NE Aurora OR 97002",
    "addr:housenumber":"22317",
    "addr:postcode":"97002",
    "addr:street":"Case Rd Ne",
    "iso:country":"US",
    "sg:address":"22317 Case Rd NE",
    "sg:city":"Aurora",
    "sg:classifiers":[
        {
            "category":"Building & Trades",
            "subcategory":"Construction",
            "type":"Services"
        }
    ],
    "sg:phone":"+1 503 678 5278",
    "sg:postcode":"97002",
    "sg:province":"OR",
    "sg:tags":[
        "preparation",
        "site",
        "grading"
    ],
    "wof:name":"ITEL Construction",
    "wof:placetype":"venue"
},
  "geometry": {"coordinates":[-122.872169,45.24149],"type":"Point"}
}