{
  "type": "Feature",
  "properties": {
    "iso:country":"US",
    "sg:address":"7911 NE 33rd Dr Ste 370",
    "sg:city":"Portland",
    "sg:classifiers":[
        {
            "category":"Home & Garden",
            "subcategory":"Building Materials",
            "type":"Retail Goods"
        }
    ],
    "sg:phone":"+1 503 331 2321",
    "sg:postcode":"97211",
    "sg:province":"OR",
    "sg:tags":[
        "garage",
        "opener",
        "door"
    ],
    "wof:name":"Gates & Controls",
    "wof:placetype":"venue"
},
  "geometry": {"coordinates":[-122.63336200000001,45.580087],"type":"Point"}
}