{
  "type": "Feature",
  "properties": {
    "iso:country":"US",
    "sg:address":"1842 SE 1st St",
    "sg:city":"Redmond",
    "sg:classifiers":[
        {
            "category":"Home & Garden",
            "subcategory":"Furniture",
            "type":"Retail Goods"
        }
    ],
    "sg:phone":"+1 541 923 8563",
    "sg:postcode":"97756",
    "sg:province":"OR",
    "sg:tags":[
        "cabinet"
    ],
    "wof:name":"Glacier Cabinet Door Co",
    "wof:placetype":"venue"
},
  "geometry": {"coordinates":[-121.16877100000001,44.257087],"type":"Point"}
}