{
  "type": "Feature",
  "properties": {
    "addr:full":"1400 NW Irving St Apt 628 Portland OR 97209",
    "addr:housenumber":"1400;628",
    "addr:postcode":"97209",
    "addr:street":"Nw Irving St Apt",
    "iso:country":"US",
    "sg:address":"1400 NW Irving St Apt 628",
    "sg:city":"Portland",
    "sg:classifiers":[
        {
            "category":"Professional",
            "subcategory":"Business Services",
            "type":"Services"
        },
        {
            "category":"Professional",
            "subcategory":"Art Services",
            "type":"Services"
        }
    ],
    "sg:phone":"+1 503 228 9493",
    "sg:postcode":"97209",
    "sg:province":"OR",
    "sg:tags":[
        "development",
        "product",
        "graphic",
        "designers-industrial",
        "artist",
        "marketing",
        "commercial",
        "designer",
        "design"
    ],
    "sg:website":"http://www.redstudio.net",
    "wof:name":"Red Studio",
    "wof:placetype":"venue"
},
  "geometry": {"coordinates":[-122.68531,45.527908],"type":"Point"}
}