{
  "type": "Feature",
  "properties": {
    "iso:country":"US",
    "sg:address":"4858 SW Scholls Ferry Rd A",
    "sg:city":"Portland",
    "sg:classifiers":[
        {
            "category":"Social Services",
            "subcategory":"Job Training",
            "type":"Services"
        }
    ],
    "sg:phone":"+1 503 203 6956",
    "sg:postcode":"97225",
    "sg:province":"OR",
    "sg:tags":[
        "sale"
    ],
    "wof:name":"Foresight Consulting",
    "wof:placetype":"venue"
},
  "geometry": {"coordinates":[-122.75112,45.485133],"type":"Point"}
}