{
  "type": "Feature",
  "properties": {
    "iso:country":"US",
    "sg:address":"2639 Sparta Way",
    "sg:city":"Medford",
    "sg:classifiers":[
        {
            "category":"Restaurant",
            "type":"Food & Drink"
        }
    ],
    "sg:phone":"+1 541 282 7856",
    "sg:postcode":"97504",
    "sg:province":"OR",
    "sg:tags":[
        "eating"
    ],
    "wof:name":"Celenas Grill",
    "wof:placetype":"venue"
},
  "geometry": {"coordinates":[-122.844302,42.361981],"type":"Point"}
}