{
  "type": "Feature",
  "properties": {
    "iso:country":"US",
    "sg:address":"4233 SE 182nd Ave",
    "sg:city":"Gresham",
    "sg:classifiers":[
        {
            "category":"Building & Trades",
            "subcategory":"Locksmith",
            "type":"Services"
        }
    ],
    "sg:phone":"+1 503 447 5656",
    "sg:postcode":"97030",
    "sg:province":"OR",
    "sg:tags":[
        "key"
    ],
    "wof:name":"A Fast Locksmith Service",
    "wof:placetype":"venue"
},
  "geometry": {"coordinates":[-122.47574899999999,45.491397],"type":"Point"}
}