{
  "type": "Feature",
  "properties": {
    "iso:country":"US",
    "sg:address":"240 E Water St",
    "sg:city":"Stayton",
    "sg:classifiers":[
        {
            "category":"Retail",
            "subcategory":"Auto Repair",
            "type":"Services"
        }
    ],
    "sg:phone":"+1 503 769 2828",
    "sg:postcode":"97383",
    "sg:province":"OR",
    "sg:tags":[
        "body",
        "automobile",
        "painting"
    ],
    "wof:name":"Johnson's Body Shop Inc",
    "wof:placetype":"venue"
},
  "geometry": {"coordinates":[-122.792616,44.795719],"type":"Point"}
}