{
  "type": "Feature",
  "properties": {
    "iso:country":"US",
    "sg:address":"1930 State St",
    "sg:city":"Salem",
    "sg:classifiers":[
        {
            "category":"Shopping",
            "subcategory":"Discount & Variety Stores",
            "type":"Retail Goods"
        }
    ],
    "sg:phone":"+1 503 378 9055",
    "sg:postcode":"97301",
    "sg:province":"OR",
    "sg:tags":[
        "merchandise",
        "general"
    ],
    "wof:name":"Action Surplus Inc",
    "wof:placetype":"venue"
},
  "geometry": {"coordinates":[-123.017772,44.934524],"type":"Point"}
}