{
  "type": "Feature",
  "properties": {
    "iso:country":"US",
    "sg:address":"16036 NW Dairy Creek Rd",
    "sg:city":"North Plains",
    "sg:classifiers":[
        {
            "category":"Home & Garden",
            "subcategory":"Garden Supply",
            "type":"Retail Goods"
        }
    ],
    "sg:phone":"+1 503 647 5954",
    "sg:postcode":"97133",
    "sg:province":"OR",
    "wof:name":"Donald S South Trustee",
    "wof:placetype":"venue"
},
  "geometry": {"coordinates":[-123.044259,45.635474],"type":"Point"}
}