{
  "type": "Feature",
  "properties": {
    "iso:country":"US",
    "sg:address":"422 SW 6th St",
    "sg:city":"Pendleton",
    "sg:classifiers":[
        {
            "category":"Building & Trades",
            "subcategory":"Construction",
            "type":"Services"
        }
    ],
    "sg:phone":"+1 541 276 1353",
    "sg:postcode":"97801",
    "sg:province":"OR",
    "sg:tags":[
        "general",
        "contractor"
    ],
    "sg:website":"www.mccormackconstruction.com",
    "wof:name":"Mc Cormack Construction Co",
    "wof:placetype":"venue"
},
  "geometry": {"coordinates":[-118.791656,45.668687],"type":"Point"}
}