{
  "type": "Feature",
  "properties": {
    "iso:country":"US",
    "sg:address":"689 N Front St",
    "sg:city":"Woodburn",
    "sg:classifiers":[
        {
            "category":"Retail",
            "subcategory":"Auto Repair",
            "type":"Services"
        }
    ],
    "sg:phone":"+1 503 982 0282",
    "sg:postcode":"97071",
    "sg:province":"OR",
    "sg:tags":[
        "general"
    ],
    "wof:name":"Sandoval Auto Repair",
    "wof:placetype":"venue"
},
  "geometry": {"coordinates":[-122.854739,45.143974],"type":"Point"}
}