{
  "type": "Feature",
  "properties": {
    "addr:full":"2456 NW Northrup St Ste 1A Portland OR 97210",
    "addr:housenumber":"2456",
    "addr:postcode":"97210",
    "addr:street":"Nw Northrup St Ste 1A",
    "iso:country":"US",
    "sg:address":"2456 NW Northrup St Ste 1A",
    "sg:city":"Portland",
    "sg:classifiers":[
        {
            "category":"Health Services",
            "subcategory":"Doctor",
            "type":"Services"
        },
        {
            "category":"Health Services",
            "subcategory":"Chiropractor",
            "type":"Services"
        }
    ],
    "sg:phone":"+1 503 223 6414",
    "sg:postcode":"97210",
    "sg:province":"OR",
    "sg:website":"www.drsusanstrom.com",
    "wof:name":"Strom Susan Dcpc",
    "wof:placetype":"venue"
},
  "geometry": {"coordinates":[-122.701814,45.531026],"type":"Point"}
}