{
  "type": "Feature",
  "properties": {
    "addr:full":"872 NW Emerald Oaks Pl Albany OR 97321",
    "addr:housenumber":"872",
    "addr:postcode":"97321",
    "addr:street":"Nw Emerald Oaks Pl",
    "iso:country":"US",
    "sg:address":"872 NW Emerald Oaks Pl",
    "sg:city":"Albany",
    "sg:classifiers":[
        {
            "category":"Social Services",
            "subcategory":"Job Training",
            "type":"Services"
        }
    ],
    "sg:phone":"+1 541 928 2232",
    "sg:postcode":"97321",
    "sg:province":"OR",
    "wof:name":"Synergy In Motion",
    "wof:placetype":"venue"
},
  "geometry": {"coordinates":[-123.133838,44.647437],"type":"Point"}
}