{
  "type": "Feature",
  "properties": {
    "addr:full":"8625 SW Cascade Ave Beaverton OR 97008",
    "addr:housenumber":"8625",
    "addr:postcode":"97008",
    "addr:street":"Sw Cascade Ave",
    "iso:country":"US",
    "sg:address":"8625 SW Cascade Ave",
    "sg:city":"Beaverton",
    "sg:classifiers":[
        {
            "category":"Professional",
            "subcategory":"Employment Agencies",
            "type":"Services"
        }
    ],
    "sg:phone":"+1 503 644 1945",
    "sg:postcode":"97008",
    "sg:province":"OR",
    "sg:tags":[
        "opportunity"
    ],
    "wof:name":"Staffing Services Inc",
    "wof:placetype":"venue"
},
  "geometry": {"coordinates":[-122.786118,45.449657],"type":"Point"}
}