{
  "type": "Feature",
  "properties": {
    "iso:country":"US",
    "sg:address":"249 N Humbolt St",
    "sg:city":"Canyon City",
    "sg:classifiers":[
        {
            "category":"Social Services",
            "subcategory":"Child Care",
            "type":"Services"
        }
    ],
    "sg:phone":"+1 541 575 0166",
    "sg:postcode":"97820",
    "sg:province":"OR",
    "wof:name":"Grant County Child Ctr",
    "wof:placetype":"venue"
},
  "geometry": {"coordinates":[-118.94904699999999,44.397113],"type":"Point"}
}