{
  "type": "Feature",
  "properties": {
    "iso:country":"US",
    "sg:address":"2172 SW Park Pl",
    "sg:city":"Portland",
    "sg:classifiers":[
        {
            "category":"Professional",
            "subcategory":"Management & Consulting",
            "type":"Services"
        }
    ],
    "sg:phone":"+1 503 796 1800",
    "sg:postcode":"97205",
    "sg:province":"OR",
    "wof:name":"Incite Marketing Inc",
    "wof:placetype":"venue"
},
  "geometry": {"coordinates":[-122.696355,45.521219],"type":"Point"}
}