{
  "type": "Feature",
  "properties": {
    "iso:country":"US",
    "sg:address":"1046 6th Ave SW",
    "sg:city":"Albany",
    "sg:classifiers":[
        {
            "category":"Professional",
            "type":"Services"
        }
    ],
    "sg:phone":"+1 541 812 4703",
    "sg:postcode":"97321",
    "sg:province":"OR",
    "sg:tags":[
        "establishment"
    ],
    "wof:name":"Lifeline Emergency Response",
    "wof:placetype":"venue"
},
  "geometry": {"coordinates":[-123.116215,44.632044],"type":"Point"}
}