{
  "type": "Feature",
  "properties": {
    "iso:country":"US",
    "sg:address":"6935 SW 169th Pl",
    "sg:city":"Beaverton",
    "sg:classifiers":[
        {
            "category":"Professional",
            "subcategory":"Management & Consulting",
            "type":"Services"
        }
    ],
    "sg:phone":"+1 503 649 5195",
    "sg:postcode":"97007",
    "sg:province":"OR",
    "wof:name":"Hayden Nw Enterprises",
    "wof:placetype":"venue"
},
  "geometry": {"coordinates":[-122.851067,45.470852],"type":"Point"}
}