{
  "type": "Feature",
  "properties": {
    "addr:full":"2780 Ward Rd The Dalles OR 97058",
    "addr:housenumber":"2780",
    "addr:postcode":"97058",
    "addr:street":"Ward Rd",
    "iso:country":"US",
    "sg:address":"2780 Ward Rd",
    "sg:city":"The Dalles",
    "sg:phone":"+1 541 296 3492",
    "sg:postcode":"97058",
    "sg:province":"OR",
    "sg:tags":[
        "farm",
        "wheat",
        "beef",
        "feedlot",
        "cattle"
    ],
    "wof:name":"Kerege Josephine",
    "wof:placetype":"venue"
},
  "geometry": {"coordinates":[-121.06842399999999,45.510552],"type":"Point"}
}