{
  "type": "Feature",
  "properties": {
    "addr:full":"9820 SW Dapplegrey Loop Beaverton OR 97008",
    "addr:housenumber":"9820",
    "addr:postcode":"97008",
    "addr:street":"Sw Dapplegrey Loop",
    "iso:country":"US",
    "sg:address":"9820 SW Dapplegrey Loop",
    "sg:city":"Beaverton",
    "sg:classifiers":[
        {
            "category":"Building & Trades",
            "subcategory":"Construction",
            "type":"Services"
        }
    ],
    "sg:phone":"+1 503 620 5534",
    "sg:postcode":"97008",
    "sg:province":"OR",
    "sg:tags":[
        "repairing",
        "remodeling",
        "contractor"
    ],
    "wof:name":"Ameri Marks Group",
    "wof:placetype":"venue"
},
  "geometry": {"coordinates":[-122.825112,45.449099],"type":"Point"}
}