{
  "type": "Feature",
  "properties": {
    "iso:country":"US",
    "sg:address":"340 Oswego Pointe Dr",
    "sg:city":"Lake Oswego",
    "sg:classifiers":[
        {
            "category":"Professional",
            "subcategory":"Computer Services",
            "type":"Services"
        }
    ],
    "sg:phone":"+1 503 699 9745",
    "sg:postcode":"97034",
    "sg:province":"OR",
    "sg:tags":[
        "prepackaged",
        "software"
    ],
    "wof:name":"Clinical Information Systems",
    "wof:placetype":"venue"
},
  "geometry": {"coordinates":[-122.659874,45.417834],"type":"Point"}
}