{
  "type": "Feature",
  "properties": {
    "addr:full":"2027 Willamina Ave Forest Grove OR 97116",
    "addr:housenumber":"2027",
    "addr:postcode":"97116",
    "addr:street":"Willamina Ave",
    "iso:country":"US",
    "sg:address":"2027 Willamina Ave",
    "sg:city":"Forest Grove",
    "sg:classifiers":[
        {
            "category":"Building & Trades",
            "subcategory":"Landscaping Services",
            "type":"Services"
        }
    ],
    "sg:phone":"+1 503 992 8567",
    "sg:postcode":"97116",
    "sg:province":"OR",
    "sg:tags":[
        "landscape"
    ],
    "wof:name":"Nick Williams Designs",
    "wof:placetype":"venue"
},
  "geometry": {"coordinates":[-123.11095899999999,45.530693],"type":"Point"}
}