{
  "type": "Feature",
  "properties": {
    "iso:country":"US",
    "sg:address":"620 SW 5th Ave",
    "sg:city":"Portland",
    "sg:classifiers":[
        {
            "category":"Professional",
            "subcategory":"Business Services",
            "type":"Services"
        }
    ],
    "sg:phone":"+1 503 226 2730",
    "sg:postcode":"97204",
    "sg:province":"OR",
    "sg:tags":[
        "surveyor",
        "construction",
        "cost",
        "quantity",
        "consultant"
    ],
    "wof:name":"Rider Hunt Ackroyd",
    "wof:placetype":"venue"
},
  "geometry": {"coordinates":[-122.67745499999999,45.51891],"type":"Point"}
}