{
  "type": "Feature",
  "properties": {
    "iso:country":"US",
    "sg:address":"17502 Scott Canyon Ln",
    "sg:city":"Arlington",
    "sg:phone":"+1 541 384 6493",
    "sg:postcode":"97812",
    "sg:province":"OR",
    "sg:tags":[
        "farm",
        "wheat"
    ],
    "wof:name":"Barnett Farms",
    "wof:placetype":"venue"
},
  "geometry": {"coordinates":[-120.19928899999999,45.415816],"type":"Point"}
}