{
  "type": "Feature",
  "properties": {
    "iso:country":"US",
    "sg:address":"22985 NW Evergreen Pkwy",
    "sg:city":"Hillsboro",
    "sg:classifiers":[
        {
            "category":"Shopping",
            "subcategory":"Computers & Home Electronics",
            "type":"Retail Goods"
        }
    ],
    "sg:phone":"+1 503 844 4600",
    "sg:postcode":"97124",
    "sg:province":"OR",
    "sg:tags":[
        "equipment",
        "dealer"
    ],
    "sg:website":"www.lacie.com",
    "wof:name":"APS Technologies",
    "wof:placetype":"venue"
},
  "geometry": {"coordinates":[-122.914644,45.550935],"type":"Point"}
}