{
  "type": "Feature",
  "properties": {
    "addr:full":"8750 SW Citizens Dr Wilsonville OR 97070",
    "addr:housenumber":"8750",
    "addr:postcode":"97070",
    "addr:street":"Sw Citizens Dr",
    "iso:country":"US",
    "sg:address":"8750 SW Citizens Dr",
    "sg:city":"Wilsonville",
    "sg:classifiers":[
        {
            "category":"Restaurant",
            "type":"Food & Drink"
        }
    ],
    "sg:phone":"+1 503 682 2171",
    "sg:postcode":"97070",
    "sg:province":"OR",
    "sg:tags":[
        "eating"
    ],
    "wof:name":"Juan Colorado",
    "wof:placetype":"venue"
},
  "geometry": {"coordinates":[-122.767296,45.303893],"type":"Point"}
}