{
  "type": "Feature",
  "properties": {
    "addr:full":"2425 S Pacific Hwy Medford OR 97501",
    "addr:housenumber":"2425",
    "addr:postcode":"97501",
    "addr:street":"S Pacific Hwy",
    "iso:country":"US",
    "sg:address":"2425 S Pacific Hwy",
    "sg:city":"Medford",
    "sg:classifiers":[
        {
            "category":"Recreation",
            "subcategory":"Amusement Park",
            "type":"Entertainment"
        }
    ],
    "sg:phone":"+1 541 772 1400",
    "sg:postcode":"97501",
    "sg:province":"OR",
    "wof:name":"Medford Skate",
    "wof:placetype":"venue"
},
  "geometry": {"coordinates":[-122.849998,42.302399],"type":"Point"}
}