{
  "type": "Feature",
  "properties": {
    "iso:country":"US",
    "sg:address":"1300 SW 5th Ave",
    "sg:city":"Portland",
    "sg:classifiers":[
        {
            "category":"Deli",
            "type":"Food & Drink"
        }
    ],
    "sg:phone":"+1 503 827 3354",
    "sg:postcode":"97201",
    "sg:province":"OR",
    "wof:name":"Rose's Deli & Bakery",
    "wof:placetype":"venue"
},
  "geometry": {"coordinates":[-122.691002,45.5121],"type":"Point"}
}