{
  "type": "Feature",
  "properties": {
    "addr:full":"1020 SW Taylor St Ste 640 Portland OR 97205",
    "addr:housenumber":"1020",
    "addr:postcode":"97205",
    "addr:street":"Sw Taylor St Ste 640",
    "iso:country":"US",
    "sg:address":"1020 SW Taylor St Ste 640",
    "sg:city":"Portland",
    "sg:classifiers":[
        {
            "category":"Health Services",
            "subcategory":"Doctor",
            "type":"Services"
        }
    ],
    "sg:phone":"+1 503 295 5947",
    "sg:postcode":"97205",
    "sg:province":"OR",
    "sg:tags":[
        "physician",
        "surgeon"
    ],
    "wof:name":"Goranson, Eric E, Phy Md",
    "wof:placetype":"venue"
},
  "geometry": {"coordinates":[-122.683055,45.518742],"type":"Point"}
}