{
  "type": "Feature",
  "properties": {
    "addr:full":"105 Cypress Ave Garibaldi OR 97118",
    "addr:housenumber":"105",
    "addr:postcode":"97118",
    "addr:street":"Cypress Ave",
    "iso:country":"US",
    "sg:address":"105 Cypress Ave",
    "sg:city":"Garibaldi",
    "sg:classifiers":[
        {
            "category":"Building & Trades",
            "subcategory":"Construction",
            "type":"Services"
        }
    ],
    "sg:phone":"+1 503 322 2442",
    "sg:postcode":"97118",
    "sg:province":"OR",
    "sg:tags":[
        "general",
        "contractor"
    ],
    "wof:name":"Wine Country Construction",
    "wof:placetype":"venue"
},
  "geometry": {"coordinates":[-123.90889300000001,45.561413],"type":"Point"}
}