{
  "type": "Feature",
  "properties": {
    "iso:country":"US",
    "sg:address":"3215 Lincoln St",
    "sg:city":"Eugene",
    "sg:classifiers":[
        {
            "category":"Professional",
            "type":"Services"
        }
    ],
    "sg:phone":"+1 541 683 5065",
    "sg:postcode":"97405",
    "sg:province":"OR",
    "wof:name":"Lane Society of Periodont",
    "wof:placetype":"venue"
},
  "geometry": {"coordinates":[-123.09730399999999,44.021612],"type":"Point"}
}