{
  "type": "Feature",
  "properties": {
    "addr:full":"3003 Willamette St Eugene OR 97405",
    "addr:housenumber":"3003",
    "addr:postcode":"97405",
    "addr:street":"Willamette St",
    "iso:country":"US",
    "sg:address":"3003 Willamette St",
    "sg:city":"Eugene",
    "sg:classifiers":[
        {
            "category":"Social Services",
            "type":"Services"
        }
    ],
    "sg:phone":"+1 541 942 1108",
    "sg:postcode":"97405",
    "sg:province":"OR",
    "sg:tags":[
        "counselor",
        "marriage",
        "family"
    ],
    "wof:name":"Peggy Thompson",
    "wof:placetype":"venue"
},
  "geometry": {"coordinates":[-123.090636,44.023051],"type":"Point"}
}