{
  "type": "Feature",
  "properties": {
    "iso:country":"US",
    "sg:address":"1565 9th St",
    "sg:city":"Florence",
    "sg:classifiers":[
        {
            "category":"Restaurant",
            "type":"Food & Drink"
        }
    ],
    "sg:phone":"+1 541 997 9739",
    "sg:postcode":"97439",
    "sg:province":"OR",
    "wof:name":"Hickory 9th St Bbq Grill",
    "wof:placetype":"venue"
},
  "geometry": {"coordinates":[-124.104367,43.974753],"type":"Point"}
}