{
  "type": "Feature",
  "properties": {
    "addr:full":"2200 Riley Rd Eagle Point OR 97524",
    "addr:housenumber":"2200",
    "addr:postcode":"97524",
    "addr:street":"Riley Rd",
    "iso:country":"US",
    "sg:address":"2200 Riley Rd",
    "sg:city":"Eagle Point",
    "sg:classifiers":[
        {
            "category":"Building & Trades",
            "subcategory":"Construction",
            "type":"Services"
        }
    ],
    "sg:phone":"+1 541 826 4369",
    "sg:postcode":"97524",
    "sg:province":"OR",
    "wof:name":"George D Heppner Excavating",
    "wof:placetype":"venue"
},
  "geometry": {"coordinates":[-122.783981,42.456727],"type":"Point"}
}