{
  "type": "Feature",
  "properties": {
    "iso:country":"US",
    "sg:address":"33808 SE Kelso Rd",
    "sg:city":"Boring",
    "sg:classifiers":[
        {
            "category":"Professional",
            "subcategory":"Management & Consulting",
            "type":"Services"
        }
    ],
    "sg:phone":"+1 503 668 8400",
    "sg:postcode":"97009",
    "sg:province":"OR",
    "sg:tags":[
        "consultant",
        "telecommunication"
    ],
    "sg:website":"www.bry.com",
    "wof:name":"BRY.COM",
    "wof:placetype":"venue"
},
  "geometry": {"coordinates":[-122.314267,45.418291],"type":"Point"}
}