{
  "type": "Feature",
  "properties": {
    "addr:full":"1938 Sunset Dr Medford OR 97501",
    "addr:housenumber":"1938",
    "addr:postcode":"97501",
    "addr:street":"Sunset Dr",
    "iso:country":"US",
    "sg:address":"1938 Sunset Dr",
    "sg:city":"Medford",
    "sg:classifiers":[
        {
            "category":"Building & Trades",
            "subcategory":"Construction",
            "type":"Services"
        }
    ],
    "sg:phone":"+1 541 772 3988",
    "sg:postcode":"97501",
    "sg:province":"OR",
    "sg:tags":[
        "resurfacing",
        "laying",
        "refinishing",
        "floor"
    ],
    "wof:name":"Wood Floors Plus",
    "wof:placetype":"venue"
},
  "geometry": {"coordinates":[-122.898931,42.302625],"type":"Point"}
}