{
  "type": "Feature",
  "properties": {
    "addr:full":"4110 SE Hawthorne Blvd Portland OR 97214",
    "addr:housenumber":"4110",
    "addr:postcode":"97214",
    "addr:street":"Se Hawthorne Blvd",
    "iso:country":"US",
    "sg:address":"4110 SE Hawthorne Blvd",
    "sg:city":"Portland",
    "sg:classifiers":[
        {
            "category":"Manufacturing",
            "subcategory":"Printing",
            "type":"Manufacturing & Wholesale Goods"
        }
    ],
    "sg:phone":"+1 503 595 9359",
    "sg:postcode":"97214",
    "sg:province":"OR",
    "sg:tags":[
        "publisher"
    ],
    "wof:name":"Outdoors NW",
    "wof:placetype":"venue"
},
  "geometry": {"coordinates":[-122.61953800000001,45.511964],"type":"Point"}
}