{
  "type": "Feature",
  "properties": {
    "iso:country":"US",
    "sg:address":"19339 SW Chesapeake Dr",
    "sg:city":"Tualatin",
    "sg:classifiers":[
        {
            "category":"Insurance",
            "subcategory":"Insurance Agent",
            "type":"Services"
        }
    ],
    "sg:phone":"+1 503 691 1735",
    "sg:postcode":"97062",
    "sg:province":"OR",
    "wof:name":"David Arndorfer & Assoc",
    "wof:placetype":"venue"
},
  "geometry": {"coordinates":[-122.73283600000001,45.380561],"type":"Point"}
}