{
  "type": "Feature",
  "properties": {
    "iso:country":"US",
    "sg:address":"21990 State Hwy 62",
    "sg:city":"Shady Cove",
    "sg:classifiers":[
        {
            "category":"Health Services",
            "subcategory":"Doctor",
            "type":"Services"
        }
    ],
    "sg:phone":"+1 541 878 2022",
    "sg:postcode":"97539",
    "sg:province":"OR",
    "sg:tags":[
        "clinic"
    ],
    "wof:name":"Shady Cove Clinic",
    "wof:placetype":"venue"
},
  "geometry": {"coordinates":[-122.810746,42.617368],"type":"Point"}
}