{
  "type": "Feature",
  "properties": {
    "addr:full":"6603 SE Woodstock Blvd Portland OR 97206",
    "addr:housenumber":"6603",
    "addr:postcode":"97206",
    "addr:street":"Se Woodstock Blvd",
    "iso:country":"US",
    "sg:address":"6603 SE Woodstock Blvd",
    "sg:city":"Portland",
    "sg:classifiers":[
        {
            "category":"Building & Trades",
            "subcategory":"Landscaping Services",
            "type":"Services"
        }
    ],
    "sg:phone":"+1 503 422 1001",
    "sg:postcode":"97206",
    "sg:province":"OR",
    "sg:tags":[
        "landscape"
    ],
    "wof:name":"David Joiner",
    "wof:placetype":"venue"
},
  "geometry": {"coordinates":[-122.595389,45.479229],"type":"Point"}
}