{
  "type": "Feature",
  "properties": {
    "iso:country":"US",
    "sg:address":"6494 Windsor Island Rd N",
    "sg:city":"Keizer",
    "sg:classifiers":[
        {
            "category":"Wholesale",
            "subcategory":"Plants",
            "type":"Manufacturing & Wholesale Goods"
        },
        {
            "category":"Farming",
            "subcategory":"Nursery",
            "type":"Manufacturing & Wholesale Goods"
        }
    ],
    "sg:phone":"+1 503 393 8112",
    "sg:postcode":"97303",
    "sg:province":"OR",
    "sg:tags":[
        "farm",
        "ornamental",
        "tree",
        "berry",
        "crop"
    ],
    "sg:website":"www.weeksberry.com",
    "wof:name":"Weeks Berry Nursery",
    "wof:placetype":"venue"
},
  "geometry": {"coordinates":[-123.049318,45.009172],"type":"Point"}
}