{
  "type": "Feature",
  "properties": {
    "addr:full":"839 E Main St Medford OR 97504",
    "addr:housenumber":"839",
    "addr:postcode":"97504",
    "addr:street":"E Main St",
    "iso:country":"US",
    "sg:address":"839 E Main St",
    "sg:city":"Medford",
    "sg:classifiers":[
        {
            "category":"Shopping",
            "subcategory":"Pharmacy",
            "type":"Retail Goods"
        }
    ],
    "sg:phone":"+1 541 245 6658",
    "sg:postcode":"97504",
    "sg:province":"OR",
    "wof:name":"Cardinal Health",
    "wof:placetype":"venue"
},
  "geometry": {"coordinates":[-122.86319,42.327953],"type":"Point"}
}