{
  "type": "Feature",
  "properties": {
    "iso:country":"US",
    "sg:address":"3625 NW Deer Run St",
    "sg:city":"Corvallis",
    "sg:classifiers":[
        {
            "category":"Professional",
            "subcategory":"Business Services",
            "type":"Services"
        }
    ],
    "sg:phone":"+1 541 758 8167",
    "sg:postcode":"97330",
    "sg:province":"OR",
    "wof:name":"Bio Resource Technologies",
    "wof:placetype":"venue"
},
  "geometry": {"coordinates":[-123.311331,44.603047],"type":"Point"}
}