{
  "type": "Feature",
  "properties": {
    "addr:full":"15301 SE Sunnyside Rd Clackamas OR 97015",
    "addr:postcode":"15301;97015",
    "addr:street":"Se Sunnyside Rd",
    "iso:country":"US",
    "sg:address":"15301 SE Sunnyside Rd",
    "sg:city":"Clackamas",
    "sg:classifiers":[
        {
            "category":"Farming",
            "subcategory":"Livestock Farm",
            "type":"Manufacturing & Wholesale Goods"
        }
    ],
    "sg:phone":"+1 503 658 2429",
    "sg:postcode":"97015",
    "sg:province":"OR",
    "sg:tags":[
        "animal",
        "general"
    ],
    "wof:name":"Jw6 Ranch",
    "wof:placetype":"venue"
},
  "geometry": {"coordinates":[-122.504577,45.426327],"type":"Point"}
}