{
  "type": "Feature",
  "properties": {
    "addr:full":"18120 SE Stark St Portland OR 97233",
    "addr:postcode":"18120;97233",
    "addr:street":"Se Stark St",
    "iso:country":"US",
    "sg:address":"18120 SE Stark St",
    "sg:city":"Portland",
    "sg:classifiers":[
        {
            "category":"Autos & Motor Vehicles",
            "subcategory":"Auto Supplies",
            "type":"Retail Goods"
        },
        {
            "category":"Wholesale",
            "subcategory":"Auto Parts",
            "type":"Manufacturing & Wholesale Goods"
        }
    ],
    "sg:phone":"+1 503 667 1400",
    "sg:postcode":"97233",
    "sg:province":"OR",
    "sg:tags":[
        "body",
        "automobile",
        "truck",
        "equipment",
        "accessory"
    ],
    "sg:website":"http://www.oreillyauto.com?utm_source=yellowpages&utm_medium=iyp&utm_campaign=2514",
    "wof:name":"Schuck's O'Reilly Auto Parts",
    "wof:placetype":"venue"
},
  "geometry": {"coordinates":[-122.476888,45.519161],"type":"Point"}
}