{
  "type": "Feature",
  "properties": {
    "iso:country":"US",
    "sg:address":"11130 SW Barbur Blvd",
    "sg:city":"Portland",
    "sg:classifiers":[
        {
            "category":"Professional",
            "subcategory":"Accounting & Tax Preparation",
            "type":"Services"
        }
    ],
    "sg:phone":"+1 503 245 0194",
    "sg:postcode":"97219",
    "sg:province":"OR",
    "sg:tags":[
        "payroll"
    ],
    "sg:website":"www.primepay.com",
    "wof:name":"Primepay Northwest Inc",
    "wof:placetype":"venue"
},
  "geometry": {"coordinates":[-122.733069,45.445032],"type":"Point"}
}