{
  "type": "Feature",
  "properties": {
    "iso:country":"US",
    "sg:address":"16521 SE Powell Blvd",
    "sg:city":"Portland",
    "sg:classifiers":[
        {
            "category":"Insurance",
            "subcategory":"Insurance Agent",
            "type":"Services"
        }
    ],
    "sg:phone":"+1 503 669 6884",
    "sg:postcode":"97236",
    "sg:province":"OR",
    "wof:name":"State Farm Insurance",
    "wof:placetype":"venue"
},
  "geometry": {"coordinates":[-122.493853,45.49436],"type":"Point"}
}