{
  "type": "Feature",
  "properties": {
    "addr:full":"600 SW 10th Ave Suite 400 Portland OR 97205",
    "addr:housenumber":"600",
    "addr:postcode":"97205",
    "addr:street":"Sw 10Th Ave Suite 400",
    "iso:country":"US",
    "sg:address":"600 SW 10th Ave Suite 400",
    "sg:city":"Portland",
    "sg:classifiers":[
        {
            "category":"Education",
            "subcategory":"Vocational School",
            "type":"Public Place"
        }
    ],
    "sg:phone":"+1 888 891 6222",
    "sg:postcode":"97205",
    "sg:province":"OR",
    "sg:tags":[
        "cooking"
    ],
    "sg:website":"www.wci.edu",
    "wof:name":"Western Culinary Institute",
    "wof:placetype":"venue"
},
  "geometry": {"coordinates":[-122.68175599999999,45.520653],"type":"Point"}
}