{
  "type": "Feature",
  "properties": {
    "addr:full":"445 Buxton Ave Troutdale OR 97060",
    "addr:housenumber":"445",
    "addr:postcode":"97060",
    "addr:street":"Buxton Ave",
    "iso:country":"US",
    "sg:address":"445 Buxton Ave",
    "sg:city":"Troutdale",
    "sg:classifiers":[
        {
            "category":"Social Services",
            "subcategory":"Adult Care",
            "type":"Services"
        }
    ],
    "sg:phone":"+1 503 665 3334",
    "sg:postcode":"97060",
    "sg:province":"OR",
    "sg:tags":[
        "home",
        "residential"
    ],
    "wof:name":"Dungarvin Troutdale",
    "wof:placetype":"venue"
},
  "geometry": {"coordinates":[-122.388445,45.538213],"type":"Point"}
}