{
  "type": "Feature",
  "properties": {
    "addr:full":"1522 SE Tacoma St Portland OR 97202",
    "addr:housenumber":"1522",
    "addr:postcode":"97202",
    "addr:street":"Se Tacoma St",
    "iso:country":"US",
    "sg:address":"1522 SE Tacoma St",
    "sg:city":"Portland",
    "sg:classifiers":[
        {
            "category":"Building & Trades",
            "subcategory":"Construction",
            "type":"Services"
        },
        {
            "category":"Manufacturing",
            "subcategory":"Building Materials",
            "type":"Manufacturing & Wholesale Goods"
        }
    ],
    "sg:phone":"+1 503 351 0315",
    "sg:postcode":"97202",
    "sg:province":"OR",
    "sg:tags":[
        "cabinetmakers-commercial",
        "industrial",
        "maker",
        "cabinet"
    ],
    "wof:name":"Schneider Richard & Associates",
    "wof:placetype":"venue"
},
  "geometry": {"coordinates":[-122.650547,45.464329],"type":"Point"}
}