{
  "type": "Feature",
  "properties": {
    "iso:country":"US",
    "sg:address":"3163 SW 257th Ave",
    "sg:city":"Troutdale",
    "sg:classifiers":[
        {
            "category":"Cinema",
            "subcategory":"Movie Rental",
            "type":"Entertainment"
        }
    ],
    "sg:phone":"+1 503 674 0547",
    "sg:postcode":"97060",
    "sg:province":"OR",
    "sg:tags":[
        "game",
        "video"
    ],
    "sg:website":"www.blockbuster.com",
    "wof:name":"Blockbuster Video",
    "wof:placetype":"venue"
},
  "geometry": {"coordinates":[-122.398003,45.519299],"type":"Point"}
}