{
  "type": "Feature",
  "properties": {
    "addr:full":"833 SW Government St Newport OR 97365",
    "addr:housenumber":"833",
    "addr:postcode":"97365",
    "addr:street":"Sw Government St",
    "iso:country":"US",
    "sg:address":"833 SW Government St",
    "sg:city":"Newport",
    "sg:classifiers":[
        {
            "category":"Banks & Credit Unions",
            "subcategory":"Investment Brokerage",
            "type":"Services"
        }
    ],
    "sg:phone":"+1 541 574 6464",
    "sg:postcode":"97365",
    "sg:province":"OR",
    "sg:tags":[
        "advisory",
        "financial"
    ],
    "wof:name":"Carlson Financial",
    "wof:placetype":"venue"
},
  "geometry": {"coordinates":[-124.061894,44.625838],"type":"Point"}
}