{
  "type": "Feature",
  "properties": {
    "addr:full":"11630 Hwy 39 Klamath Falls OR 97603",
    "addr:housenumber":"11630",
    "addr:postcode":"97603",
    "addr:street":"Hwy 39",
    "iso:country":"US",
    "sg:address":"11630 Hwy 39",
    "sg:city":"Klamath Falls",
    "sg:classifiers":[
        {
            "category":"Retail",
            "subcategory":"Animal Services",
            "type":"Services"
        }
    ],
    "sg:phone":"+1 541 883 5227",
    "sg:postcode":"97603",
    "sg:province":"OR",
    "wof:name":"Stuller Creek Kennel",
    "wof:placetype":"venue"
},
  "geometry": {"coordinates":[-121.698534,42.117454],"type":"Point"}
}