{
  "type": "Feature",
  "properties": {
    "addr:full":"51214 Blue River Dr Vida OR 97488",
    "addr:housenumber":"51214",
    "addr:postcode":"97488",
    "addr:street":"Blue River Dr",
    "iso:country":"US",
    "sg:address":"51214 Blue River Dr",
    "sg:city":"Vida",
    "sg:classifiers":[
        {
            "category":"Place Of Worship",
            "subcategory":"Church",
            "type":"Public Place"
        },
        {
            "category":"Place Of Worship",
            "type":"Public Place"
        }
    ],
    "sg:phone":"+1 541 822 6262",
    "sg:postcode":"97488",
    "sg:province":"OR",
    "sg:tags":[
        "christ",
        "latter-day",
        "jesus",
        "churches-church",
        "saint"
    ],
    "sg:website":"http://www.lds.org",
    "wof:name":"The Church of Jesus Christ of Latter-Day Saints",
    "wof:placetype":"venue"
},
  "geometry": {"coordinates":[-122.345068,44.156132],"type":"Point"}
}