{
  "type": "Feature",
  "properties": {
    "addr:full":"617 S 71st St Springfield OR 97478",
    "addr:housenumber":"617",
    "addr:postcode":"97478",
    "addr:street":"S 71St St",
    "iso:country":"US",
    "sg:address":"617 S 71st St",
    "sg:city":"Springfield",
    "sg:classifiers":[
        {
            "category":"Shopping",
            "subcategory":"Hobbies, Toys, & Games",
            "type":"Retail Goods"
        }
    ],
    "sg:phone":"+1 541 747 0503",
    "sg:postcode":"97478",
    "sg:province":"OR",
    "wof:name":"Linda Kings Special Thing",
    "wof:placetype":"venue"
},
  "geometry": {"coordinates":[-122.899103,44.041443],"type":"Point"}
}