{
  "type": "Feature",
  "properties": {
    "iso:country":"US",
    "sg:address":"6034 Crater Lake Ave",
    "sg:city":"Central Point",
    "sg:classifiers":[
        {
            "category":"Retail",
            "subcategory":"Auto Repair",
            "type":"Services"
        }
    ],
    "sg:phone":"+1 541 830 4005",
    "sg:postcode":"97502",
    "sg:province":"OR",
    "wof:name":"Kelly's Automotive",
    "wof:placetype":"venue"
},
  "geometry": {"coordinates":[-122.855842,42.404407],"type":"Point"}
}