{
  "type": "Feature",
  "properties": {
    "iso:country":"US",
    "sg:address":"1590 NE Burnside Rd",
    "sg:city":"Gresham",
    "sg:classifiers":[
        {
            "category":"Restaurant",
            "type":"Food & Drink"
        }
    ],
    "sg:phone":"+1 503 665 5144",
    "sg:postcode":"97030",
    "sg:province":"OR",
    "sg:tags":[
        "eating"
    ],
    "wof:name":"Elmers Restaurants Inc",
    "wof:placetype":"venue"
},
  "geometry": {"coordinates":[-122.415668,45.503241],"type":"Point"}
}