{
  "type": "Feature",
  "properties": {
    "iso:country":"US",
    "sg:address":"2805 NW Westover Rd",
    "sg:city":"Portland",
    "sg:classifiers":[
        {
            "category":"Real Estate",
            "subcategory":"Architect",
            "type":"Services"
        }
    ],
    "sg:phone":"+1 503 735 9192",
    "sg:postcode":"97210",
    "sg:province":"OR",
    "sg:tags":[
        "architects'",
        "specification",
        "construction",
        "builders'",
        "architectural"
    ],
    "wof:name":"Acker Gregory Architect",
    "wof:placetype":"venue"
},
  "geometry": {"coordinates":[-122.707913,45.530978],"type":"Point"}
}