{
  "type": "Feature",
  "properties": {
    "iso:country":"US",
    "sg:address":"10510 SE Reedway St",
    "sg:city":"Portland",
    "sg:classifiers":[
        {
            "category":"Building & Trades",
            "subcategory":"Locksmith",
            "type":"Services"
        }
    ],
    "sg:phone":"+1 971 925 3429",
    "sg:postcode":"97266",
    "sg:province":"OR",
    "sg:tags":[
        "key"
    ],
    "wof:name":"Emergency 24Hr Portland Locksmith",
    "wof:placetype":"venue"
},
  "geometry": {"coordinates":[-122.55421699999999,45.480686],"type":"Point"}
}