{
  "type": "Feature",
  "properties": {
    "iso:country":"US",
    "sg:address":"165 Maple St",
    "sg:city":"Florence",
    "sg:classifiers":[
        {
            "category":"Restaurant",
            "type":"Food & Drink"
        }
    ],
    "sg:phone":"+1 541 997 5005",
    "sg:postcode":"97439",
    "sg:province":"OR",
    "sg:tags":[
        "cafe"
    ],
    "wof:name":"Pauline's Place",
    "wof:placetype":"venue"
},
  "geometry": {"coordinates":[-124.105793,43.967259],"type":"Point"}
}