{
  "type": "Feature",
  "properties": {
    "iso:country":"US",
    "sg:address":"3120 Centurion Cir",
    "sg:city":"Medford",
    "sg:classifiers":[
        {
            "category":"Manufacturing",
            "subcategory":"Metals",
            "type":"Manufacturing & Wholesale Goods"
        }
    ],
    "sg:phone":"+1 541 770 9189",
    "sg:postcode":"97504",
    "sg:province":"OR",
    "sg:tags":[
        "pipe",
        "fitting",
        "valve"
    ],
    "wof:name":"Ward Manufacturing Inc",
    "wof:placetype":"venue"
},
  "geometry": {"coordinates":[-122.820739,42.318944],"type":"Point"}
}