{
  "type": "Feature",
  "properties": {
    "iso:country":"US",
    "sg:address":"16760 SW Upper Boones Ferry Rd Upper Boones",
    "sg:city":"Portland",
    "sg:classifiers":[
        {
            "category":"Wholesale",
            "subcategory":"Electrical",
            "type":"Manufacturing & Wholesale Goods"
        }
    ],
    "sg:phone":"+1 503 601 4545",
    "sg:postcode":"97224",
    "sg:province":"OR",
    "sg:tags":[
        "semiconductor",
        "device"
    ],
    "sg:website":"http://www.pixelworks.com",
    "wof:name":"Pixelworks, Inc.",
    "wof:placetype":"venue"
},
  "geometry": {"coordinates":[-122.75466299999999,45.39889],"type":"Point"}
}