{
  "type": "Feature",
  "properties": {
    "iso:country":"US",
    "sg:address":"22680 SW 76th Ave",
    "sg:city":"Tualatin",
    "sg:classifiers":[
        {
            "category":"Professional",
            "type":"Services"
        }
    ],
    "sg:phone":"+1 503 638 9722",
    "sg:postcode":"97062",
    "sg:province":"OR",
    "wof:name":"Kuper Consulting",
    "wof:placetype":"venue"
},
  "geometry": {"coordinates":[-122.75427999999999,45.355821],"type":"Point"}
}