{
  "type": "Feature",
  "properties": {
    "addr:full":"11395 SW Riverwood Rd Portland OR 97219",
    "addr:housenumber":"11395",
    "addr:postcode":"97219",
    "addr:street":"Sw Riverwood Rd",
    "iso:country":"US",
    "sg:address":"11395 SW Riverwood Rd",
    "sg:city":"Portland",
    "sg:classifiers":[
        {
            "category":"Arts & Performance",
            "subcategory":"Art Gallery",
            "type":"Entertainment"
        }
    ],
    "sg:phone":"+1 503 539 5404",
    "sg:postcode":"97219",
    "sg:province":"OR",
    "sg:tags":[
        "consultant",
        "galleries"
    ],
    "wof:name":"Latin Painters Co",
    "wof:placetype":"venue"
},
  "geometry": {"coordinates":[-122.651158,45.442306],"type":"Point"}
}