{
  "type": "Feature",
  "properties": {
    "iso:country":"US",
    "sg:address":"1796 4th Ave E",
    "sg:city":"Vale",
    "sg:classifiers":[
        {
            "category":"Insurance",
            "subcategory":"Hazard Insurance",
            "type":"Services"
        }
    ],
    "sg:phone":"+1 541 473 2156",
    "sg:postcode":"97918",
    "sg:province":"OR",
    "wof:name":"Fly Farm Systems",
    "wof:placetype":"venue"
},
  "geometry": {"coordinates":[-117.269267,44.039849],"type":"Point"}
}