{
  "type": "Feature",
  "properties": {
    "addr:full":"4380 SW 175th Ave Beaverton OR 97007",
    "addr:housenumber":"4380",
    "addr:postcode":"97007",
    "addr:street":"Sw 175Th Ave",
    "iso:country":"US",
    "sg:address":"4380 SW 175th Ave",
    "sg:city":"Beaverton",
    "sg:classifiers":[
        {
            "category":"Building & Trades",
            "subcategory":"Cleaning & Sanitation",
            "type":"Services"
        }
    ],
    "sg:phone":"+1 503 245 3229",
    "sg:postcode":"97007",
    "sg:province":"OR",
    "sg:tags":[
        "janitorial"
    ],
    "wof:name":"M & M Cleaning Specialists",
    "wof:placetype":"venue"
},
  "geometry": {"coordinates":[-122.857496,45.490977],"type":"Point"}
}