{
  "type": "Feature",
  "properties": {
    "addr:full":"14675 SW Teal Blvd Beaverton OR 97007",
    "addr:housenumber":"14675",
    "addr:postcode":"97007",
    "addr:street":"Sw Teal Blvd",
    "iso:country":"US",
    "sg:address":"14675 SW Teal Blvd",
    "sg:city":"Beaverton",
    "sg:classifiers":[
        {
            "category":"Personal",
            "subcategory":"Beauty Salon",
            "type":"Services"
        }
    ],
    "sg:phone":"+1 503 524 2606",
    "sg:postcode":"97007",
    "sg:province":"OR",
    "sg:tags":[
        "hair"
    ],
    "sg:website":"bellasalonmurrayhill.com/",
    "wof:name":"Bella Salon",
    "wof:placetype":"venue"
},
  "geometry": {"coordinates":[-122.828003,45.4408],"type":"Point"}
}