{
  "type": "Feature",
  "properties": {
    "addr:full":"15160 NW Laidlaw Rd Ste 202 Portland OR 97229",
    "addr:housenumber":"15160",
    "addr:postcode":"97229",
    "addr:street":"Nw Laidlaw Rd Ste 202",
    "iso:country":"US",
    "sg:address":"15160 NW Laidlaw Rd Ste 202",
    "sg:city":"Portland",
    "sg:classifiers":[
        {
            "category":"Health Services",
            "subcategory":"Dentist",
            "type":"Services"
        }
    ],
    "sg:phone":"+1 503 533 2330",
    "sg:postcode":"97229",
    "sg:province":"OR",
    "sg:tags":[
        "dentists-cosmetic",
        "dentistry"
    ],
    "sg:website":"www.hillsidedentalatbethany.com",
    "wof:name":"Hillside Dental At Bethany",
    "wof:placetype":"venue"
},
  "geometry": {"coordinates":[-122.833134,45.555473],"type":"Point"}
}