{
  "type": "Feature",
  "properties": {
    "addr:full":"2890 SW Fairmont Dr Corvallis OR 97333",
    "addr:housenumber":"2890",
    "addr:postcode":"97333",
    "addr:street":"Sw Fairmont Dr",
    "iso:country":"US",
    "sg:address":"2890 SW Fairmont Dr",
    "sg:city":"Corvallis",
    "sg:classifiers":[
        {
            "category":"Professional",
            "subcategory":"Management & Consulting",
            "type":"Services"
        }
    ],
    "sg:phone":"+1 541 757 7375",
    "sg:postcode":"97333",
    "sg:province":"OR",
    "sg:tags":[
        "business"
    ],
    "wof:name":"Richard Adams",
    "wof:placetype":"venue"
},
  "geometry": {"coordinates":[-123.29341599999999,44.541377],"type":"Point"}
}