{
  "type": "Feature",
  "properties": {
    "iso:country":"US",
    "sg:address":"28997 Hirtzel Rd",
    "sg:city":"Rainier",
    "sg:classifiers":[
        {
            "category":"Manufacturing",
            "subcategory":"Printing",
            "type":"Manufacturing & Wholesale Goods"
        }
    ],
    "sg:phone":"+1 503 556 2500",
    "sg:postcode":"97048",
    "sg:province":"OR",
    "sg:tags":[
        "publishing"
    ],
    "wof:name":"Freedom Press Inc",
    "wof:placetype":"venue"
},
  "geometry": {"coordinates":[-122.966788,46.070689],"type":"Point"}
}