{
  "type": "Feature",
  "properties": {
    "addr:full":"3106 NE 64th Ave Portland OR 97213",
    "addr:housenumber":"3106",
    "addr:postcode":"97213",
    "addr:street":"Ne 64Th Ave",
    "iso:country":"US",
    "sg:address":"3106 NE 64th Ave",
    "sg:city":"Portland",
    "sg:classifiers":[
        {
            "category":"Shopping",
            "subcategory":"Gifts & Souvenirs",
            "type":"Retail Goods"
        }
    ],
    "sg:phone":"+1 503 241 8888",
    "sg:postcode":"97213",
    "sg:province":"OR",
    "wof:name":"Fantasy Creature Store",
    "wof:placetype":"venue"
},
  "geometry": {"coordinates":[-122.597295,45.545324],"type":"Point"}
}