{
  "type": "Feature",
  "properties": {
    "iso:country":"US",
    "sg:address":"911 Hall St",
    "sg:city":"Prairie City",
    "sg:classifiers":[
        {
            "category":"Building & Trades",
            "subcategory":"Construction",
            "type":"Services"
        }
    ],
    "sg:phone":"+1 541 820 3529",
    "sg:postcode":"97869",
    "sg:province":"OR",
    "sg:tags":[
        "excavation",
        "contractor"
    ],
    "wof:name":"Aspen Excavation",
    "wof:placetype":"venue"
},
  "geometry": {"coordinates":[-118.70983699999999,44.453504],"type":"Point"}
}