{
  "type": "Feature",
  "properties": {
    "iso:country":"US",
    "sg:address":"6001 Barger Dr",
    "sg:city":"Eugene",
    "sg:classifiers":[
        {
            "category":"Personal",
            "subcategory":"Beauty Salon",
            "type":"Services"
        }
    ],
    "sg:phone":"+1 541 688 2748",
    "sg:postcode":"97402",
    "sg:province":"OR",
    "wof:name":"Hair By Judy",
    "wof:placetype":"venue"
},
  "geometry": {"coordinates":[-123.208186,44.084751],"type":"Point"}
}