{
  "type": "Feature",
  "properties": {
    "iso:country":"US",
    "sg:address":"4028 SW Patton Rd",
    "sg:city":"Portland",
    "sg:classifiers":[
        {
            "category":"Professional",
            "type":"Services"
        }
    ],
    "sg:phone":"+1 503 292 6851",
    "sg:postcode":"97221",
    "sg:province":"OR",
    "wof:name":"Perseverance LLC",
    "wof:placetype":"venue"
},
  "geometry": {"coordinates":[-122.71728899999999,45.500011],"type":"Point"}
}