{
  "type": "Feature",
  "properties": {
    "addr:full":"10185 SW Beaverton-Hillsdale Hwy Beaverton OR 97005",
    "addr:housenumber":"10185",
    "addr:postcode":"97005",
    "addr:street":"Sw Beaverton-Hillsdale Hwy",
    "iso:country":"US",
    "sg:address":"10185 SW Beaverton-Hillsdale Hwy",
    "sg:city":"Beaverton",
    "sg:classifiers":[
        {
            "category":"Home & Garden",
            "subcategory":"Carpets & Floor Coverings",
            "type":"Retail Goods"
        }
    ],
    "sg:phone":"+1 503 520 2040",
    "sg:postcode":"97005",
    "sg:province":"OR",
    "sg:tags":[
        "flooring",
        "carpeting"
    ],
    "wof:name":"Urban Floors",
    "wof:placetype":"venue"
},
  "geometry": {"coordinates":[-122.781335,45.486991],"type":"Point"}
}