{
  "type": "Feature",
  "properties": {
    "iso:country":"US",
    "sg:address":"834 SW Lee St",
    "sg:city":"Newport",
    "sg:classifiers":[
        {
            "category":"Organizations",
            "subcategory":"Religious Organization",
            "type":"Services"
        }
    ],
    "sg:phone":"+1 541 574 6560",
    "sg:postcode":"97365",
    "sg:province":"OR",
    "sg:tags":[
        "church"
    ],
    "sg:website":"www.newportnet.com/unity",
    "wof:name":"Ocean Unity",
    "wof:placetype":"venue"
},
  "geometry": {"coordinates":[-124.055386,44.633582],"type":"Point"}
}