{
  "type": "Feature",
  "properties": {
    "iso:country":"US",
    "sg:address":"2133 NE Broadway St Ste 200 Suite 255",
    "sg:city":"Portland",
    "sg:classifiers":[
        {
            "category":"Banks & Credit Unions",
            "subcategory":"Financial Services",
            "type":"Services"
        }
    ],
    "sg:phone":"+1 503 228 2670",
    "sg:postcode":"97232",
    "sg:province":"OR",
    "sg:tags":[
        "broker",
        "mortgage"
    ],
    "wof:name":"Security Mortgage Lending",
    "wof:placetype":"venue"
},
  "geometry": {"coordinates":[-122.644008,45.535255],"type":"Point"}
}