{
  "type": "Feature",
  "properties": {
    "iso:country":"US",
    "sg:address":"3884 Commercial St SE",
    "sg:city":"Salem",
    "sg:classifiers":[
        {
            "category":"Social Services",
            "type":"Services"
        }
    ],
    "sg:phone":"+1 503 362 7024",
    "sg:postcode":"97302",
    "sg:province":"OR",
    "sg:tags":[
        "counselor",
        "marriage",
        "family"
    ],
    "wof:name":"Alpha Counseling & Therapy LTD",
    "wof:placetype":"venue"
},
  "geometry": {"coordinates":[-123.039392,44.900999],"type":"Point"}
}