{
  "type": "Feature",
  "properties": {
    "addr:full":"973 Ranch Rd Reedsport OR 97467",
    "addr:housenumber":"973",
    "addr:postcode":"97467",
    "addr:street":"Ranch Rd",
    "iso:country":"US",
    "sg:address":"973 Ranch Rd",
    "sg:city":"Reedsport",
    "sg:classifiers":[
        {
            "category":"Organizations",
            "subcategory":"Membership Organization",
            "type":"Services"
        }
    ],
    "sg:phone":"+1 541 271 5704",
    "sg:postcode":"97467",
    "sg:province":"OR",
    "wof:name":"Reedsport Activity Park Inc",
    "wof:placetype":"venue"
},
  "geometry": {"coordinates":[-124.13362499999999,43.701099],"type":"Point"}
}