{
  "type": "Feature",
  "properties": {
    "addr:full":"961 Peachwood Ct Medford OR 97501",
    "addr:housenumber":"961",
    "addr:postcode":"97501",
    "addr:street":"Peachwood Ct",
    "iso:country":"US",
    "sg:address":"961 Peachwood Ct",
    "sg:city":"Medford",
    "sg:classifiers":[
        {
            "category":"Personal",
            "type":"Services"
        }
    ],
    "sg:phone":"+1 541 773 5766",
    "sg:postcode":"97501",
    "sg:province":"OR",
    "sg:tags":[
        "towing"
    ],
    "wof:name":"Noble Towing & Recovery",
    "wof:placetype":"venue"
},
  "geometry": {"coordinates":[-122.88400300000001,42.308201],"type":"Point"}
}