{
  "type": "Feature",
  "properties": {
    "iso:country":"US",
    "sg:address":"4805 SW Oleson Rd",
    "sg:city":"Portland",
    "sg:classifiers":[
        {
            "category":"Personal",
            "subcategory":"Massage",
            "type":"Services"
        }
    ],
    "sg:phone":"+1 503 537 6577",
    "sg:postcode":"97225",
    "sg:province":"OR",
    "sg:website":"www.facebook.com/profile",
    "wof:name":"Amber Cook LMT",
    "wof:placetype":"venue"
},
  "geometry": {"coordinates":[-122.748141,45.485124],"type":"Point"}
}