{
  "type": "Feature",
  "properties": {
    "iso:country":"US",
    "sg:address":"4541 SW Scholls Ferry Rd",
    "sg:city":"Portland",
    "sg:classifiers":[
        {
            "category":"Education",
            "subcategory":"School",
            "type":"Public Place"
        }
    ],
    "sg:phone":"+1 503 292 3955",
    "sg:postcode":"97225",
    "sg:province":"OR",
    "wof:name":"Northwest School Of Energy",
    "wof:placetype":"venue"
},
  "geometry": {"coordinates":[-122.747457,45.486983],"type":"Point"}
}