{
  "type": "Feature",
  "properties": {
    "addr:full":"29252 SW Tami Loop Wilsonville OR 97070",
    "addr:housenumber":"29252",
    "addr:postcode":"97070",
    "addr:street":"Sw Tami Loop",
    "iso:country":"US",
    "sg:address":"29252 SW Tami Loop",
    "sg:city":"Wilsonville",
    "sg:classifiers":[
        {
            "category":"Real Estate",
            "subcategory":"Real Estate Operator",
            "type":"Services"
        }
    ],
    "sg:phone":"+1 503 682 8677",
    "sg:postcode":"97070",
    "sg:province":"OR",
    "sg:tags":[
        "building",
        "apartment"
    ],
    "wof:name":"Berkshire Court Apts",
    "wof:placetype":"venue"
},
  "geometry": {"coordinates":[-122.750744,45.308424],"type":"Point"}
}