{
  "type": "Feature",
  "properties": {
    "iso:country":"US",
    "sg:address":"511 SW 10th Ave Ste 610",
    "sg:city":"Portland",
    "sg:classifiers":[
        {
            "category":"Professional",
            "subcategory":"Testing Lab",
            "type":"Services"
        },
        {
            "category":"Health Services",
            "subcategory":"Medical Lab",
            "type":"Services"
        }
    ],
    "sg:phone":"+1 503 225 0899",
    "sg:postcode":"97205",
    "sg:province":"OR",
    "sg:tags":[
        "laboratory",
        "dental"
    ],
    "wof:name":"Owens Dental Lab",
    "wof:placetype":"venue"
},
  "geometry": {"coordinates":[-122.681425,45.521282],"type":"Point"}
}