{
  "type": "Feature",
  "properties": {
    "addr:full":"11818 NE Marx St Portland OR 97220",
    "addr:housenumber":"11818",
    "addr:postcode":"97220",
    "addr:street":"Ne Marx St",
    "iso:country":"US",
    "sg:address":"11818 NE Marx St",
    "sg:city":"Portland",
    "sg:classifiers":[
        {
            "category":"Freight",
            "type":"Transportation"
        }
    ],
    "sg:phone":"+1 503 254 9724",
    "sg:postcode":"97220",
    "sg:province":"OR",
    "sg:tags":[
        "operator",
        "local",
        "trucking"
    ],
    "sg:website":"http://www.motorcargo.com",
    "wof:name":"Motor Cargo",
    "wof:placetype":"venue"
},
  "geometry": {"coordinates":[-122.54165999999999,45.559707],"type":"Point"}
}