{
  "type": "Feature",
  "properties": {
    "iso:country":"US",
    "sg:address":"734 S Holly St",
    "sg:city":"Medford",
    "sg:classifiers":[
        {
            "category":"Building & Trades",
            "subcategory":"Construction",
            "type":"Services"
        }
    ],
    "sg:phone":"+1 541 776 4073",
    "sg:postcode":"97501",
    "sg:province":"OR",
    "sg:tags":[
        "system",
        "contractor",
        "air conditioning"
    ],
    "wof:name":"Rob's Air",
    "wof:placetype":"venue"
},
  "geometry": {"coordinates":[-122.868906,42.317198],"type":"Point"}
}