{
  "type": "Feature",
  "properties": {
    "addr:full":"3029 SE Division St Portland OR 97202",
    "addr:housenumber":"3029",
    "addr:postcode":"97202",
    "addr:street":"Se Division St",
    "iso:country":"US",
    "sg:address":"3029 SE Division St",
    "sg:city":"Portland",
    "sg:phone":"+1 503 234 7887",
    "sg:postcode":"97202",
    "sg:province":"OR",
    "wof:name":"Urban Flora Plant Oasis",
    "wof:placetype":"venue"
},
  "geometry": {"coordinates":[-122.634327,45.50481],"type":"Point"}
}