{
  "type": "Feature",
  "properties": {
    "addr:full":"2425 NE 50th Ave Portland OR 97213",
    "addr:housenumber":"2425",
    "addr:postcode":"97213",
    "addr:street":"Ne 50Th Ave",
    "iso:country":"US",
    "sg:address":"2425 NE 50th Ave",
    "sg:city":"Portland",
    "sg:classifiers":[
        {
            "category":"Government",
            "subcategory":"Post Office",
            "type":"Public Place"
        }
    ],
    "sg:phone":"+1 503 000 1111",
    "sg:postcode":"97213",
    "sg:province":"OR",
    "wof:name":"US Post Office",
    "wof:placetype":"venue"
},
  "geometry": {"coordinates":[-122.61200599999999,45.540012],"type":"Point"}
}