{
  "type": "Feature",
  "properties": {
    "iso:country":"US",
    "sg:address":"2425 NE 50th Ave",
    "sg:city":"Portland",
    "sg:classifiers":[
        {
            "category":"Government",
            "subcategory":"Post Office",
            "type":"Public Place"
        }
    ],
    "sg:phone":"+1 503 000 1111",
    "sg:postcode":"97213",
    "sg:province":"OR",
    "wof:name":"US Post Office",
    "wof:placetype":"venue"
},
  "geometry": {"coordinates":[-122.612006,45.540012],"type":"Point"}
}