{
  "type": "Feature",
  "properties": {
    "iso:country":"US",
    "sg:address":"1601 Willamette St",
    "sg:city":"Eugene",
    "sg:classifiers":[
        {
            "category":"Real Estate",
            "subcategory":"Real Estate Agent",
            "type":"Services"
        }
    ],
    "sg:phone":"+1 541 342 7625",
    "sg:postcode":"97401",
    "sg:province":"OR",
    "wof:name":"Prudential",
    "wof:placetype":"venue"
},
  "geometry": {"coordinates":[-123.092753,44.041684],"type":"Point"}
}