{
  "type": "Feature",
  "properties": {
    "iso:country":"US",
    "sg:address":"370 11th St SE",
    "sg:city":"Bandon",
    "sg:classifiers":[
        {
            "category":"Freight",
            "type":"Transportation"
        }
    ],
    "sg:phone":"+1 541 347 9629",
    "sg:postcode":"97411",
    "sg:province":"OR",
    "sg:tags":[
        "commercial",
        "storage"
    ],
    "wof:name":"Bandon EZ Storage",
    "wof:placetype":"venue"
},
  "geometry": {"coordinates":[-124.412371,43.113254],"type":"Point"}
}