{
  "type": "Feature",
  "properties": {
    "iso:country":"US",
    "sg:address":"1313 Highway 101 S",
    "sg:city":"Reedsport",
    "sg:classifiers":[
        {
            "category":"Health Services",
            "subcategory":"Doctor",
            "type":"Services"
        }
    ],
    "sg:phone":"+1 541 271 3946",
    "sg:postcode":"97467",
    "sg:province":"OR",
    "sg:tags":[
        "physician",
        "family",
        "practice",
        "surgeons",
        "medicine"
    ],
    "wof:name":"Clinton Faber Md",
    "wof:placetype":"venue"
},
  "geometry": {"coordinates":[-124.10965,43.699936],"type":"Point"}
}