{
  "type": "Feature",
  "properties": {
    "addr:full":"180 Ramsgate Sq S Salem OR 97302",
    "addr:housenumber":"180",
    "addr:postcode":"97302",
    "addr:street":"Ramsgate Sq",
    "iso:country":"US",
    "sg:address":"180 Ramsgate Sq S",
    "sg:city":"Salem",
    "sg:classifiers":[
        {
            "category":"Health Services",
            "subcategory":"Health Practitioner",
            "type":"Services"
        },
        {
            "category":"Social Services",
            "type":"Services"
        }
    ],
    "sg:phone":"+1 503 365 7510",
    "sg:postcode":"97302",
    "sg:province":"OR",
    "sg:tags":[
        "psychotherapist"
    ],
    "wof:name":"Austin & Swain LLP",
    "wof:placetype":"venue"
},
  "geometry": {"coordinates":[-123.050909,44.903425],"type":"Point"}
}