{
  "type": "Feature",
  "properties": {
    "iso:country":"US",
    "sg:address":"3439 NE Sandy Blvd",
    "sg:city":"Portland",
    "sg:classifiers":[
        {
            "category":"Professional",
            "type":"Services"
        }
    ],
    "sg:phone":"+1 503 275 1301",
    "sg:postcode":"97232",
    "sg:province":"OR",
    "wof:name":"With Thankscom",
    "wof:placetype":"venue"
},
  "geometry": {"coordinates":[-122.62840199999999,45.532665],"type":"Point"}
}