{
  "type": "Feature",
  "properties": {
    "addr:full":"1110 SE 4th St Hermiston OR 97838",
    "addr:housenumber":"1110",
    "addr:postcode":"97838",
    "addr:street":"Se 4Th St",
    "iso:country":"US",
    "sg:address":"1110 SE 4th St",
    "sg:city":"Hermiston",
    "sg:classifiers":[
        {
            "category":"Travel",
            "subcategory":"Hotels & Motels",
            "type":"Entertainment"
        }
    ],
    "sg:phone":"+1 541 567 2330",
    "sg:postcode":"97838",
    "sg:province":"OR",
    "sg:tags":[
        "operation"
    ],
    "wof:name":"Oak Tree Inn",
    "wof:placetype":"venue"
},
  "geometry": {"coordinates":[-119.285184,45.832281],"type":"Point"}
}