{
  "type": "Feature",
  "properties": {
    "iso:country":"US",
    "sg:address":"53694 Day Rd",
    "sg:city":"La Pine",
    "sg:classifiers":[
        {
            "category":"Professional",
            "subcategory":"Business Services",
            "type":"Services"
        }
    ],
    "sg:phone":"+1 541 536 0299",
    "sg:postcode":"97739",
    "sg:province":"OR",
    "wof:name":"Life For Children",
    "wof:placetype":"venue"
},
  "geometry": {"coordinates":[-121.525368,43.749045],"type":"Point"}
}