{
  "type": "Feature",
  "properties": {
    "iso:country":"US",
    "sg:address":"10207 SW Park Way",
    "sg:city":"Portland",
    "sg:classifiers":[
        {
            "category":"Travel",
            "subcategory":"Hotels & Motels",
            "type":"Entertainment"
        }
    ],
    "sg:phone":"+1 800 424 6423",
    "sg:postcode":"97225",
    "sg:province":"OR",
    "sg:website":"http://www.rodewayinn.com/hotel-portland-oregon-OR211?promo=yplocal",
    "wof:name":"Rodeway Inn & Suites Portland",
    "wof:placetype":"venue"
},
  "geometry": {"coordinates":[-122.78083100000001,45.507673],"type":"Point"}
}