{
  "type": "Feature",
  "properties": {
    "iso:country":"US",
    "sg:address":"2315 SE Grant St",
    "sg:city":"Portland",
    "sg:classifiers":[
        {
            "category":"Arts & Performance",
            "subcategory":"Theater",
            "type":"Entertainment"
        }
    ],
    "sg:phone":"+1 503 232 2346",
    "sg:postcode":"97214",
    "sg:province":"OR",
    "sg:tags":[
        "theatrical",
        "manager",
        "producer",
        "merchandise"
    ],
    "wof:name":"Ladybug Theatre Inc",
    "wof:placetype":"venue"
},
  "geometry": {"coordinates":[-122.642039,45.507034],"type":"Point"}
}