{
  "type": "Feature",
  "properties": {
    "iso:country":"US",
    "sg:address":"6700 SW Sandburg Street PO Box 4057",
    "sg:city":"Portland",
    "sg:classifiers":[
        {
            "category":"Food & Beverages",
            "subcategory":"Groceries & Convenience Stores",
            "type":"Retail Goods"
        }
    ],
    "sg:phone":"+1 503 639 6300",
    "sg:postcode":"97223",
    "sg:province":"OR",
    "sg:website":"www.westernfamily.com",
    "wof:name":"Western Family Foods",
    "wof:placetype":"venue"
},
  "geometry": {"coordinates":[-122.746883,45.420227],"type":"Point"}
}