{
  "type": "Feature",
  "properties": {
    "addr:full":"4225 SW West Shore Dr Gaston OR 97119",
    "addr:housenumber":"4225",
    "addr:postcode":"97119",
    "addr:street":"Sw West Shore Dr",
    "iso:country":"US",
    "sg:address":"4225 SW West Shore Dr",
    "sg:city":"Gaston",
    "sg:classifiers":[
        {
            "category":"Professional",
            "subcategory":"Computer Services",
            "type":"Services"
        }
    ],
    "sg:phone":"+1 503 357 1265",
    "sg:postcode":"97119",
    "sg:province":"OR",
    "sg:tags":[
        "prepackaged",
        "software"
    ],
    "wof:name":"Ebook Download Ebook Software",
    "wof:placetype":"venue"
},
  "geometry": {"coordinates":[-123.235834,45.485351],"type":"Point"}
}