{
  "type": "Feature",
  "properties": {
    "iso:country":"US",
    "sg:address":"221 W Central Ave",
    "sg:city":"Sutherlin",
    "sg:classifiers":[
        {
            "category":"Professional",
            "type":"Services"
        }
    ],
    "sg:phone":"+1 541 459 0116",
    "sg:postcode":"97479",
    "sg:province":"OR",
    "sg:tags":[
        "establishment"
    ],
    "wof:name":"Woody's",
    "wof:placetype":"venue"
},
  "geometry": {"coordinates":[-123.315402,43.389816],"type":"Point"}
}