{
  "type": "Feature",
  "properties": {
    "addr:full":"4747 N Channel Ave Portland OR 97217",
    "addr:housenumber":"4747",
    "addr:postcode":"97217",
    "addr:street":"N Channel Ave",
    "iso:country":"US",
    "sg:address":"4747 N Channel Ave",
    "sg:city":"Portland",
    "sg:classifiers":[
        {
            "category":"Professional",
            "subcategory":"Research",
            "type":"Services"
        }
    ],
    "sg:phone":"+1 503 745 2654",
    "sg:postcode":"97217",
    "sg:province":"OR",
    "sg:tags":[
        "engaged",
        "commercial"
    ],
    "wof:name":"Daimler-Chrysler Res & Tech",
    "wof:placetype":"venue"
},
  "geometry": {"coordinates":[-122.715205,45.561938],"type":"Point"}
}