{
  "type": "Feature",
  "properties": {
    "iso:country":"US",
    "sg:address":"5139 N Lombard St",
    "sg:city":"Portland",
    "sg:classifiers":[
        {
            "category":"Social Services",
            "type":"Services"
        }
    ],
    "sg:phone":"+1 503 721 6777",
    "sg:postcode":"97203",
    "sg:province":"OR",
    "sg:tags":[
        "senior",
        "citizen"
    ],
    "sg:website":"www.ywca-pdx.org",
    "wof:name":"Ywca Of Greater Portland",
    "wof:placetype":"venue"
},
  "geometry": {"coordinates":[-122.720994,45.581352],"type":"Point"}
}