{
  "type": "Feature",
  "properties": {
    "iso:country":"US",
    "sg:address":"1180 Oak St",
    "sg:city":"Ashland",
    "sg:classifiers":[
        {
            "category":"Shopping",
            "subcategory":"Gifts & Souvenirs",
            "type":"Retail Goods"
        }
    ],
    "sg:phone":"+1 541 482 7566",
    "sg:postcode":"97520",
    "sg:province":"OR",
    "wof:name":"Aloha Gifts",
    "wof:placetype":"venue"
},
  "geometry": {"coordinates":[-122.710424,42.215029],"type":"Point"}
}