{
  "type": "Feature",
  "properties": {
    "addr:full":"29424 N Umpqua Hwy Idleyld Park OR 97447",
    "addr:housenumber":"29424",
    "addr:postcode":"97447",
    "addr:street":"N Umpqua Hwy;Park",
    "iso:country":"US",
    "sg:address":"29424 N Umpqua Hwy",
    "sg:city":"Idleyld Park",
    "sg:classifiers":[
        {
            "category":"Manufacturing",
            "subcategory":"Lumber",
            "type":"Manufacturing & Wholesale Goods"
        }
    ],
    "sg:phone":"+1 541 496 0004",
    "sg:postcode":"97447",
    "sg:province":"OR",
    "sg:tags":[
        "equipment",
        "rental"
    ],
    "wof:name":"Gary B Kidd",
    "wof:placetype":"venue"
},
  "geometry": {"coordinates":[-122.927199,43.295476],"type":"Point"}
}