{
  "type": "Feature",
  "properties": {
    "iso:country":"US",
    "sg:address":"33250 S Wilhoit Rd",
    "sg:city":"Molalla",
    "sg:classifiers":[
        {
            "category":"Building & Trades",
            "subcategory":"Construction",
            "type":"Services"
        }
    ],
    "sg:phone":"+1 503 829 6319",
    "sg:postcode":"97038",
    "sg:province":"OR",
    "sg:tags":[
        "excavation",
        "contractor"
    ],
    "wof:name":"R&R Cattle Co",
    "wof:placetype":"venue"
},
  "geometry": {"coordinates":[-122.59053,45.126649],"type":"Point"}
}