{
  "type": "Feature",
  "properties": {
    "iso:country":"US",
    "sg:address":"70075 Nicolai Rd",
    "sg:city":"Rainier",
    "sg:classifiers":[
        {
            "category":"Mining & Drilling",
            "type":"Manufacturing & Wholesale Goods"
        }
    ],
    "sg:phone":"+1 503 556 4292",
    "sg:postcode":"97048",
    "sg:province":"OR",
    "sg:tags":[
        "limestone"
    ],
    "wof:name":"Westside Rock Goble Quarry",
    "wof:placetype":"venue"
},
  "geometry": {"coordinates":[-122.895677,46.006937],"type":"Point"}
}