{
  "type": "Feature",
  "properties": {
    "addr:full":"3265 Lingren Rd Odell OR 97031",
    "addr:housenumber":"3265",
    "addr:postcode":"97031",
    "addr:street":"Lingren Rd",
    "iso:country":"US",
    "sg:address":"3265 Lingren Rd",
    "sg:city":"Odell",
    "sg:classifiers":[
        {
            "category":"Professional",
            "subcategory":"Business Services",
            "type":"Services"
        }
    ],
    "sg:phone":"+1 541 354 3670",
    "sg:postcode":"97031",
    "sg:province":"OR",
    "sg:tags":[
        "embroidery"
    ],
    "wof:name":"A-1 Fancy Stitch",
    "wof:placetype":"venue"
},
  "geometry": {"coordinates":[-121.53430299999999,45.6305],"type":"Point"}
}