{
  "type": "Feature",
  "properties": {
    "iso:country":"US",
    "sg:address":"295 Idaho St",
    "sg:city":"Ashland",
    "sg:classifiers":[
        {
            "category":"Travel",
            "subcategory":"Hotels & Motels",
            "type":"Entertainment"
        }
    ],
    "sg:phone":"+1 541 488 1846",
    "sg:postcode":"97520",
    "sg:province":"OR",
    "sg:tags":[
        "operation"
    ],
    "wof:name":"Donald A Politis",
    "wof:placetype":"venue"
},
  "geometry": {"coordinates":[-122.708229,42.189106],"type":"Point"}
}