{
  "type": "Feature",
  "properties": {
    "iso:country":"US",
    "sg:address":"12251 SE Wildwood Dr",
    "sg:city":"Gresham",
    "sg:classifiers":[
        {
            "category":"Building & Trades",
            "subcategory":"Construction",
            "type":"Services"
        }
    ],
    "sg:phone":"+1 503 658 3046",
    "sg:postcode":"97089",
    "sg:province":"OR",
    "sg:tags":[
        "general"
    ],
    "wof:name":"Ralph E Anderson Construction",
    "wof:placetype":"venue"
},
  "geometry": {"coordinates":[-122.417761,45.439806],"type":"Point"}
}