{
  "type": "Feature",
  "properties": {
    "addr:full":"2636 Biehn St Klamath Falls OR 97601",
    "addr:postcode":"2636;97601",
    "addr:street":"Biehn St",
    "iso:country":"US",
    "sg:address":"2636 Biehn St",
    "sg:city":"Klamath Falls",
    "sg:classifiers":[
        {
            "category":"Shopping",
            "subcategory":"Used Merchandise",
            "type":"Retail Goods"
        }
    ],
    "sg:phone":"+1 541 273 6734",
    "sg:postcode":"97601",
    "sg:province":"OR",
    "sg:tags":[
        "clothing"
    ],
    "wof:name":"Transition Wear",
    "wof:placetype":"venue"
},
  "geometry": {"coordinates":[-121.791657,42.244776],"type":"Point"}
}