{
  "type": "Feature",
  "properties": {
    "addr:full":"400 Decker Ln Jacksonville OR 97530",
    "addr:housenumber":"400",
    "addr:postcode":"97530",
    "addr:street":"Decker Ln",
    "iso:country":"US",
    "sg:address":"400 Decker Ln",
    "sg:city":"Jacksonville",
    "sg:classifiers":[
        {
            "category":"Building & Trades",
            "subcategory":"Construction",
            "type":"Services"
        }
    ],
    "sg:phone":"+1 541 846 6630",
    "sg:postcode":"97530",
    "sg:province":"OR",
    "sg:tags":[
        "heavy"
    ],
    "wof:name":"Gene Decker Tuffy Excavation",
    "wof:placetype":"venue"
},
  "geometry": {"coordinates":[-123.19588299999999,42.210229],"type":"Point"}
}