{
  "type": "Feature",
  "properties": {
    "iso:country":"US",
    "sg:address":"722 Cardley Ave",
    "sg:city":"Medford",
    "sg:classifiers":[
        {
            "category":"Insurance",
            "subcategory":"Insurance Agent",
            "type":"Services"
        }
    ],
    "sg:phone":"+1 541 779 5364",
    "sg:postcode":"97504",
    "sg:province":"OR",
    "wof:name":"Thomas Stanaland Insur Agcy",
    "wof:placetype":"venue"
},
  "geometry": {"coordinates":[-122.868377,42.336573],"type":"Point"}
}