{
  "type": "Feature",
  "properties": {
    "addr:full":"1038 Tamera Dr Klamath Falls OR 97603",
    "addr:housenumber":"1038",
    "addr:postcode":"97603",
    "addr:street":"Tamera Dr",
    "iso:country":"US",
    "sg:address":"1038 Tamera Dr",
    "sg:city":"Klamath Falls",
    "sg:classifiers":[
        {
            "category":"Social Services",
            "type":"Services"
        }
    ],
    "sg:phone":"+1 541 884 2357",
    "sg:postcode":"97603",
    "sg:province":"OR",
    "sg:tags":[
        "counselor",
        "marriage",
        "family"
    ],
    "wof:name":"Stephen Shrifter",
    "wof:placetype":"venue"
},
  "geometry": {"coordinates":[-121.710331,42.220643],"type":"Point"}
}