{
  "type": "Feature",
  "properties": {
    "addr:full":"1607 SW 55th St Redmond OR 97756",
    "addr:housenumber":"1607",
    "addr:postcode":"97756",
    "addr:street":"Sw 55Th St",
    "iso:country":"US",
    "sg:address":"1607 SW 55th St",
    "sg:city":"Redmond",
    "sg:classifiers":[
        {
            "category":"Building & Trades",
            "subcategory":"Landscaping Services",
            "type":"Services"
        },
        {
            "category":"Wholesale",
            "subcategory":"Machinery & Supplies",
            "type":"Manufacturing & Wholesale Goods"
        },
        {
            "category":"Professional",
            "subcategory":"Business Services",
            "type":"Services"
        }
    ],
    "sg:phone":"+1 541 548 7325",
    "sg:postcode":"97756",
    "sg:province":"OR",
    "sg:tags":[
        "irrigation",
        "designer",
        "consultant",
        "system",
        "contractor",
        "equipment",
        "landscape"
    ],
    "wof:name":"Toevs Landscaping &Construction",
    "wof:placetype":"venue"
},
  "geometry": {"coordinates":[-121.23449599999999,44.261315],"type":"Point"}
}