{
  "type": "Feature",
  "properties": {
    "addr:full":"198 E Main St Hermiston OR 97838",
    "addr:housenumber":"198",
    "addr:postcode":"97838",
    "addr:street":"E Main St",
    "iso:country":"US",
    "sg:address":"198 E Main St",
    "sg:city":"Hermiston",
    "sg:classifiers":[
        {
            "category":"Bars & Pubs",
            "type":"Food & Drink"
        }
    ],
    "sg:phone":"+1 541 567 9229",
    "sg:postcode":"97838",
    "sg:province":"OR",
    "sg:tags":[
        "drinking"
    ],
    "wof:name":"Cozy Corner Tavern",
    "wof:placetype":"venue"
},
  "geometry": {"coordinates":[-119.288732,45.840505],"type":"Point"}
}