{
  "type": "Feature",
  "properties": {
    "iso:country":"US",
    "sg:address":"11100 SW Park Way",
    "sg:city":"Portland",
    "sg:classifiers":[
        {
            "category":"Education",
            "subcategory":"School",
            "type":"Public Place"
        }
    ],
    "sg:phone":"+1 503 672 3620",
    "sg:postcode":"97225",
    "sg:province":"OR",
    "wof:name":"Beaverton School District 48",
    "wof:placetype":"venue"
},
  "geometry": {"coordinates":[-122.790992,45.507216],"type":"Point"}
}