{
  "type": "Feature",
  "properties": {
    "addr:full":"Pac West Building 6th and Madison Portland OR 97212",
    "addr:postcode":"97212",
    "addr:street":"6Th And",
    "iso:country":"US",
    "sg:address":"Pac West Building 6th and Madison",
    "sg:city":"Portland",
    "sg:classifiers":[
        {
            "category":"Arts & Performance",
            "subcategory":"Music",
            "type":"Entertainment"
        }
    ],
    "sg:postcode":"97212",
    "sg:province":"OR",
    "sg:tags":[
        "venue"
    ],
    "wof:name":"Bing Lounge",
    "wof:placetype":"venue"
},
  "geometry": {"coordinates":[-122.65975899999999,45.512946],"type":"Point"}
}