{
  "type": "Feature",
  "properties": {
    "iso:country":"US",
    "sg:address":"36838 US Hwy 26",
    "sg:city":"Seaside",
    "sg:classifiers":[
        {
            "category":"Building & Trades",
            "subcategory":"Construction",
            "type":"Services"
        }
    ],
    "sg:phone":"+1 503 738 7891",
    "sg:postcode":"97138",
    "sg:province":"OR",
    "sg:tags":[
        "work",
        "carpentry"
    ],
    "wof:name":"Thomas J Butler",
    "wof:placetype":"venue"
},
  "geometry": {"coordinates":[-123.80691299999999,45.908131],"type":"Point"}
}