{
  "type": "Feature",
  "properties": {
    "addr:full":"17005 Sandlake Rd Cloverdale OR 97112",
    "addr:postcode":"17005;97112",
    "addr:street":"Sandlake Rd",
    "iso:country":"US",
    "sg:address":"17005 Sandlake Rd",
    "sg:city":"Cloverdale",
    "sg:classifiers":[
        {
            "category":"Freight",
            "type":"Transportation"
        }
    ],
    "sg:phone":"+1 503 398 5359",
    "sg:postcode":"97112",
    "sg:province":"OR",
    "sg:tags":[
        "operator",
        "local",
        "trucking"
    ],
    "wof:name":"Mel Remington",
    "wof:placetype":"venue"
},
  "geometry": {"coordinates":[-123.854388,45.327194],"type":"Point"}
}