{
  "type": "Feature",
  "properties": {
    "addr:full":"30500 SE Lawrence Rd Estacada OR 97023",
    "addr:postcode":"30500;97023",
    "addr:street":"Se Lawrence Rd",
    "iso:country":"US",
    "sg:address":"30500 SE Lawrence Rd",
    "sg:city":"Estacada",
    "sg:classifiers":[
        {
            "category":"Retail",
            "subcategory":"Animal Services",
            "type":"Services"
        }
    ],
    "sg:phone":"+1 503 630 7995",
    "sg:postcode":"97023",
    "sg:province":"OR",
    "sg:tags":[
        "pet",
        "grooming",
        "washing"
    ],
    "wof:name":"Purrfect Paw",
    "wof:placetype":"venue"
},
  "geometry": {"coordinates":[-122.31191800000001,45.302569],"type":"Point"}
}