{
  "type": "Feature",
  "properties": {
    "iso:country":"US",
    "sg:address":"921 SW Morrison St.",
    "sg:city":"Portland",
    "sg:phone":"+1 503 914 0901",
    "sg:postcode":"97205",
    "sg:province":"OR",
    "wof:name":"Allways Locksmith & Keys Portland",
    "wof:placetype":"venue"
},
  "geometry": {"coordinates":[-122.681326,45.519796],"type":"Point"}
}