{
  "type": "Feature",
  "properties": {
    "iso:country":"US",
    "sg:address":"824 E Jackson St Ste B",
    "sg:city":"Medford",
    "sg:classifiers":[
        {
            "category":"Personal",
            "subcategory":"Beauty Salon",
            "type":"Services"
        },
        {
            "category":"Personal",
            "subcategory":"Skin Care",
            "type":"Services"
        },
        {
            "category":"Personal",
            "subcategory":"Nail Salon",
            "type":"Services"
        }
    ],
    "sg:phone":"+1 541 282 2326",
    "sg:postcode":"97504",
    "sg:province":"OR",
    "sg:tags":[
        "hair"
    ],
    "sg:website":"www.ignitionsalon.com",
    "wof:name":"IGNITION",
    "wof:placetype":"venue"
},
  "geometry": {"coordinates":[-122.863281,42.330991],"type":"Point"}
}