{
  "type": "Feature",
  "properties": {
    "addr:full":"20163 SW Tualatin Valley Hwy Beaverton OR 97006",
    "addr:housenumber":"20163",
    "addr:postcode":"97006",
    "addr:street":"Sw Tualatin Valley Hwy",
    "iso:country":"US",
    "sg:address":"20163 SW Tualatin Valley Hwy",
    "sg:city":"Beaverton",
    "sg:classifiers":[
        {
            "category":"Cinema",
            "subcategory":"Movie Rental",
            "type":"Entertainment"
        }
    ],
    "sg:phone":"+1 503 649 2927",
    "sg:postcode":"97006",
    "sg:province":"OR",
    "sg:tags":[
        "leasing",
        "video",
        "disc",
        "tape"
    ],
    "sg:website":"www.hollywood.com",
    "wof:name":"Hollywood Video",
    "wof:placetype":"venue"
},
  "geometry": {"coordinates":[-122.88609,45.49587],"type":"Point"}
}