{
  "type": "Feature",
  "properties": {
    "iso:country":"US",
    "sg:address":"PO Box 39",
    "sg:city":"Portland",
    "sg:classifiers":[
        {
            "category":"Professional",
            "subcategory":"Lawyer & Legal Services",
            "type":"Services"
        }
    ],
    "sg:phone":"+1 503 492 3600",
    "sg:postcode":"97207",
    "sg:province":"OR",
    "wof:name":"Rounsefell Jack V PC",
    "wof:placetype":"venue"
},
  "geometry": {"coordinates":[-122.68000000000001,45.521],"type":"Point"}
}