{
  "type": "Feature",
  "properties": {
    "iso:country":"US",
    "sg:address":"8835 SW Canyon Ln",
    "sg:city":"Portland",
    "sg:classifiers":[
        {
            "category":"Health Services",
            "subcategory":"Chiropractor",
            "type":"Services"
        }
    ],
    "sg:phone":"+1 503 297 7959",
    "sg:postcode":"97225",
    "sg:province":"OR",
    "wof:name":"Bonofiglio Carl DC",
    "wof:placetype":"venue"
},
  "geometry": {"coordinates":[-122.767613,45.498129],"type":"Point"}
}