{
  "type": "Feature",
  "properties": {
    "iso:country":"US",
    "sg:address":"2330 10th St",
    "sg:city":"Baker City",
    "sg:classifiers":[
        {
            "category":"Wholesale",
            "subcategory":"Machinery & Supplies",
            "type":"Manufacturing & Wholesale Goods"
        },
        {
            "category":"Wholesale",
            "subcategory":"Hardware",
            "type":"Manufacturing & Wholesale Goods"
        }
    ],
    "sg:phone":"+1 541 523 7731",
    "sg:postcode":"97814",
    "sg:province":"OR",
    "sg:tags":[
        "plumbing",
        "equipment",
        "irrigation",
        "system"
    ],
    "wof:name":"Municipal Pipeline Supply Co",
    "wof:placetype":"venue"
},
  "geometry": {"coordinates":[-117.841094,44.780456],"type":"Point"}
}