{
  "type": "Feature",
  "properties": {
    "addr:full":"2293 Riviera Ct Hubbard OR 97032",
    "addr:housenumber":"2293",
    "addr:postcode":"97032",
    "addr:street":"Riviera Ct",
    "iso:country":"US",
    "sg:address":"2293 Riviera Ct",
    "sg:city":"Hubbard",
    "sg:classifiers":[
        {
            "category":"Professional",
            "subcategory":"Business Services",
            "type":"Services"
        }
    ],
    "sg:phone":"+1 503 981 4838",
    "sg:postcode":"97032",
    "sg:province":"OR",
    "wof:name":"Alltek Solutions",
    "wof:placetype":"venue"
},
  "geometry": {"coordinates":[-122.806512,45.188577],"type":"Point"}
}