{
  "type": "Feature",
  "properties": {
    "addr:full":"3975 SW 97th Ave Portland OR 97225",
    "addr:housenumber":"3975",
    "addr:postcode":"97225",
    "addr:street":"Sw 97Th Ave",
    "iso:country":"US",
    "sg:address":"3975 SW 97th Ave",
    "sg:city":"Portland",
    "sg:classifiers":[
        {
            "category":"Real Estate",
            "subcategory":"Real Estate Agent",
            "type":"Services"
        }
    ],
    "sg:phone":"+1 503 292 3555",
    "sg:postcode":"97225",
    "sg:province":"OR",
    "wof:name":"Lewis & Co Inc",
    "wof:placetype":"venue"
},
  "geometry": {"coordinates":[-122.776945,45.493628],"type":"Point"}
}