{
  "type": "Feature",
  "properties": {
    "iso:country":"US",
    "sg:address":"16140 SW Bobolink St",
    "sg:city":"Beaverton",
    "sg:classifiers":[
        {
            "category":"Professional",
            "subcategory":"Business Services",
            "type":"Services"
        }
    ],
    "sg:phone":"+1 503 590 3207",
    "sg:postcode":"97007",
    "sg:province":"OR",
    "wof:name":"Dimac Solutions Inc",
    "wof:placetype":"venue"
},
  "geometry": {"coordinates":[-122.841625,45.432463],"type":"Point"}
}