{
  "type": "Feature",
  "properties": {
    "addr:full":"953 Garfield St Medford OR 97501",
    "addr:housenumber":"953",
    "addr:postcode":"97501",
    "addr:street":"Garfield St",
    "iso:country":"US",
    "sg:address":"953 Garfield St",
    "sg:city":"Medford",
    "sg:classifiers":[
        {
            "category":"Organizations",
            "subcategory":"Religious Organization",
            "type":"Services"
        }
    ],
    "sg:phone":"+1 541 772 5938",
    "sg:postcode":"97501",
    "sg:province":"OR",
    "sg:tags":[
        "church"
    ],
    "wof:name":"Jehovah's Witnesses",
    "wof:placetype":"venue"
},
  "geometry": {"coordinates":[-122.884405,42.305528],"type":"Point"}
}