{
  "type": "Feature",
  "properties": {
    "iso:country":"US",
    "sg:address":"812 Newmark Ave",
    "sg:city":"Coos Bay",
    "sg:classifiers":[
        {
            "category":"Shopping",
            "subcategory":"Used Merchandise",
            "type":"Retail Goods"
        }
    ],
    "sg:phone":"+1 541 888 1808",
    "sg:postcode":"97420",
    "sg:province":"OR",
    "sg:tags":[
        "second",
        "store",
        "hand"
    ],
    "wof:name":"Empire Second Hand Store",
    "wof:placetype":"venue"
},
  "geometry": {"coordinates":[-124.272942,43.391832],"type":"Point"}
}