{
  "type": "Feature",
  "properties": {
    "iso:country":"US",
    "sg:address":"62929 N Highway 97 Ste B",
    "sg:city":"Bend",
    "sg:phone":"+1 541 389 0701",
    "sg:postcode":"97701",
    "sg:province":"OR",
    "wof:name":"Shoji's",
    "wof:placetype":"venue"
},
  "geometry": {"coordinates":[-121.304585,44.092687],"type":"Point"}
}