{
  "type": "Feature",
  "properties": {
    "iso:country":"US",
    "sg:address":"5110 Alexander Dr",
    "sg:city":"Mount Hood Parkdale",
    "sg:classifiers":[
        {
            "category":"Farming",
            "subcategory":"Dairy Farm",
            "type":"Manufacturing & Wholesale Goods"
        }
    ],
    "sg:phone":"+1 541 352 6265",
    "sg:postcode":"97041",
    "sg:province":"OR",
    "wof:name":"Cascade Dairy Inc",
    "wof:placetype":"venue"
},
  "geometry": {"coordinates":[-121.609391,45.552754],"type":"Point"}
}