{
  "type": "Feature",
  "properties": {
    "addr:full":"15325 NW Central Dr Portland OR 97229",
    "addr:housenumber":"15325",
    "addr:postcode":"97229",
    "addr:street":"Nw Central Dr",
    "iso:country":"US",
    "sg:address":"15325 NW Central Dr",
    "sg:city":"Portland",
    "sg:classifiers":[
        {
            "category":"Restaurant",
            "type":"Food & Drink"
        }
    ],
    "sg:phone":"+1 503 645 6113",
    "sg:postcode":"97229",
    "sg:province":"OR",
    "sg:tags":[
        "vegetarian",
        "indian",
        "asian",
        "pan"
    ],
    "sg:website":"http://www.curryleafpdx.com",
    "wof:name":"Curry Leaf",
    "wof:placetype":"venue"
},
  "geometry": {"coordinates":[-122.834935,45.554553],"type":"Point"}
}