{
  "type": "Feature",
  "properties": {
    "iso:country":"US",
    "sg:address":"32680 Bowers Dr",
    "sg:city":"Harrisburg",
    "sg:classifiers":[
        {
            "category":"Retail",
            "subcategory":"Animal Services",
            "type":"Services"
        }
    ],
    "sg:phone":"+1 541 995 3776",
    "sg:postcode":"97446",
    "sg:province":"OR",
    "wof:name":"Shady Grove Kennels",
    "wof:placetype":"venue"
},
  "geometry": {"coordinates":[-123.070153,44.228267],"type":"Point"}
}