{
  "type": "Feature",
  "properties": {
    "iso:country":"US",
    "sg:address":"16463 Boones Ferry Rd",
    "sg:city":"Lake Oswego",
    "sg:classifiers":[
        {
            "category":"Health Services",
            "subcategory":"Doctor",
            "type":"Services"
        }
    ],
    "sg:phone":"+1 503 635 3743",
    "sg:postcode":"97035",
    "sg:province":"OR",
    "sg:tags":[
        "physician",
        "surgeon",
        "medical"
    ],
    "wof:name":"Olsen Pediatric Clinic",
    "wof:placetype":"venue"
},
  "geometry": {"coordinates":[-122.724825,45.407747],"type":"Point"}
}