{
  "type": "Feature",
  "properties": {
    "addr:full":"890 Huron Ct SE Salem OR 97302",
    "addr:housenumber":"890",
    "addr:postcode":"97302",
    "addr:street":"Huron Ct Se",
    "iso:country":"US",
    "sg:address":"890 Huron Ct SE",
    "sg:city":"Salem",
    "sg:classifiers":[
        {
            "category":"Retail",
            "subcategory":"Laundry & Dry Cleaning",
            "type":"Services"
        }
    ],
    "sg:phone":"+1 503 362 3921",
    "sg:postcode":"97302",
    "sg:province":"OR",
    "wof:name":"Klean N Fresh Carpet Cleaning",
    "wof:placetype":"venue"
},
  "geometry": {"coordinates":[-123.03559199999999,44.898344],"type":"Point"}
}