{
  "type": "Feature",
  "properties": {
    "iso:country":"US",
    "sg:address":"620 E Whiteaker Ave",
    "sg:city":"Cottage Grove",
    "sg:classifiers":[
        {
            "category":"Manufacturing",
            "subcategory":"Printing",
            "type":"Manufacturing & Wholesale Goods"
        }
    ],
    "sg:phone":"+1 541 942 4438",
    "sg:postcode":"97424",
    "sg:province":"OR",
    "sg:tags":[
        "lithographic",
        "printer",
        "commercial"
    ],
    "wof:name":"Emerald Valley Craftsman",
    "wof:placetype":"venue"
},
  "geometry": {"coordinates":[-123.061705,43.798067],"type":"Point"}
}