{
  "type": "Feature",
  "properties": {
    "iso:country":"US",
    "sg:address":"767 Willamette St",
    "sg:city":"Eugene",
    "sg:classifiers":[
        {
            "category":"Professional",
            "subcategory":"Lawyer & Legal Services",
            "type":"Services"
        }
    ],
    "sg:phone":"+1 541 686 2904",
    "sg:postcode":"97401",
    "sg:province":"OR",
    "wof:name":"Marjorie R S Sobol",
    "wof:placetype":"venue"
},
  "geometry": {"coordinates":[-123.092661,44.051783],"type":"Point"}
}