{
  "type": "Feature",
  "properties": {
    "iso:country":"US",
    "sg:address":"396 N Central St",
    "sg:city":"Coquille",
    "sg:classifiers":[
        {
            "category":"Professional",
            "subcategory":"Employment Agencies",
            "type":"Services"
        }
    ],
    "sg:phone":"+1 541 396 1885",
    "sg:postcode":"97423",
    "sg:province":"OR",
    "sg:tags":[
        "help",
        "contractor"
    ],
    "wof:name":"Encore Technical Staffing",
    "wof:placetype":"venue"
},
  "geometry": {"coordinates":[-124.188929,43.176981],"type":"Point"}
}