{
  "type": "Feature",
  "properties": {
    "iso:country":"US",
    "sg:address":"4011 SE Belmont Street",
    "sg:city":"Portland",
    "sg:classifiers":[
        {
            "category":"Education",
            "subcategory":"Music School",
            "type":"Public Place"
        }
    ],
    "sg:phone":"+1 503 233 2234",
    "sg:postcode":"97214",
    "sg:province":"OR",
    "sg:tags":[
        "instrument",
        "teacher",
        "musical"
    ],
    "sg:website":"www.immortalpiano.com",
    "wof:name":"Immortal Piano Company",
    "wof:placetype":"venue"
},
  "geometry": {"coordinates":[-122.62145200000001,45.516689],"type":"Point"}
}