{
  "type": "Feature",
  "properties": {
    "iso:country":"US",
    "sg:address":"679 Brian Way",
    "sg:city":"Medford",
    "sg:classifiers":[
        {
            "category":"Manufacturing",
            "subcategory":"Printing",
            "type":"Manufacturing & Wholesale Goods"
        }
    ],
    "sg:phone":"+1 541 773 2939",
    "sg:postcode":"97501",
    "sg:province":"OR",
    "sg:tags":[
        "commercial",
        "printer",
        "lithographic"
    ],
    "wof:name":"Mustard Press Inc",
    "wof:placetype":"venue"
},
  "geometry": {"coordinates":[-122.898838,42.34222],"type":"Point"}
}