{
  "type": "Feature",
  "properties": {
    "iso:country":"US",
    "sg:address":"178 NE Atkinson Ct",
    "sg:city":"Roseburg",
    "sg:classifiers":[
        {
            "category":"Real Estate",
            "subcategory":"Real Estate Operator",
            "type":"Services"
        }
    ],
    "sg:phone":"+1 541 672 7474",
    "sg:postcode":"97470",
    "sg:province":"OR",
    "sg:tags":[
        "building",
        "apartment"
    ],
    "wof:name":"Atkinsonville Apartments",
    "wof:placetype":"venue"
},
  "geometry": {"coordinates":[-123.348609,43.239597],"type":"Point"}
}