{
  "type": "Feature",
  "properties": {
    "addr:full":"775 Court St NE Salem OR 97301",
    "addr:housenumber":"775",
    "addr:postcode":"97301",
    "addr:street":"Court St Ne",
    "iso:country":"US",
    "sg:address":"775 Court St NE",
    "sg:city":"Salem",
    "sg:classifiers":[
        {
            "category":"Government",
            "subcategory":"Office",
            "type":"Public Place"
        }
    ],
    "sg:phone":"+1 503 373 1102",
    "sg:postcode":"97301",
    "sg:province":"OR",
    "sg:tags":[
        "employee",
        "benefit",
        "board"
    ],
    "wof:name":"Public Employees Benefit Board",
    "wof:placetype":"venue"
},
  "geometry": {"coordinates":[-123.032715,44.939797],"type":"Point"}
}