{
  "type": "Feature",
  "properties": {
    "iso:country":"US",
    "sg:address":"10411 SW 41st Ave",
    "sg:city":"Portland",
    "sg:classifiers":[
        {
            "category":"Recreation",
            "type":"Entertainment"
        }
    ],
    "sg:phone":"+1 503 244 4357",
    "sg:postcode":"97219",
    "sg:province":"OR",
    "sg:tags":[
        "club",
        "membership"
    ],
    "wof:name":"1620 Club",
    "wof:placetype":"venue"
},
  "geometry": {"coordinates":[-122.719154,45.450389],"type":"Point"}
}