{
  "type": "Feature",
  "properties": {
    "iso:country":"US",
    "sg:address":"194 E Lincoln St",
    "sg:city":"Woodburn",
    "sg:classifiers":[
        {
            "category":"Professional",
            "subcategory":"Business Services",
            "type":"Services"
        }
    ],
    "sg:phone":"+1 503 869 4841",
    "sg:postcode":"97071",
    "sg:province":"OR",
    "sg:tags":[
        "consultant",
        "coach"
    ],
    "wof:name":"Rwc Consulting",
    "wof:placetype":"venue"
},
  "geometry": {"coordinates":[-122.852951,45.143261],"type":"Point"}
}