{
  "type": "Feature",
  "properties": {
    "addr:full":"1532 NW West Hills Ave Bend OR 97701",
    "addr:housenumber":"1532",
    "addr:postcode":"97701",
    "addr:street":"Nw West;Ave",
    "iso:country":"US",
    "sg:address":"1532 NW West Hills Ave",
    "sg:city":"Bend",
    "sg:classifiers":[
        {
            "category":"Real Estate",
            "subcategory":"Real Estate Agent",
            "type":"Services"
        }
    ],
    "sg:phone":"+1 541 388 8151",
    "sg:postcode":"97701",
    "sg:province":"OR",
    "wof:name":"Gardner & Gardner",
    "wof:placetype":"venue"
},
  "geometry": {"coordinates":[-121.33348100000001,44.069203],"type":"Point"}
}