{
  "type": "Feature",
  "properties": {
    "iso:country":"US",
    "sg:address":"18 SE D St",
    "sg:city":"Madras",
    "sg:classifiers":[
        {
            "category":"Home & Garden",
            "subcategory":"Home Furnishings",
            "type":"Retail Goods"
        }
    ],
    "sg:phone":"+1 541 475 2992",
    "sg:postcode":"97741",
    "sg:province":"OR",
    "wof:name":"Sunset Stoves",
    "wof:placetype":"venue"
},
  "geometry": {"coordinates":[-121.12924700000001,44.633588],"type":"Point"}
}