{
  "type": "Feature",
  "properties": {
    "addr:full":"3000 25th St SE Salem OR 97301",
    "addr:housenumber":"3000",
    "addr:postcode":"97301",
    "addr:street":"25Th St Se",
    "iso:country":"US",
    "sg:address":"3000 25th St SE",
    "sg:city":"Salem",
    "sg:classifiers":[
        {
            "category":"Government",
            "subcategory":"Office",
            "type":"Public Place"
        }
    ],
    "sg:phone":"+1 503 581 3323",
    "sg:postcode":"97301",
    "sg:province":"OR",
    "sg:tags":[
        "control",
        "traffic",
        "air"
    ],
    "wof:name":"Air Traffic Control Tower",
    "wof:placetype":"venue"
},
  "geometry": {"coordinates":[-123.0102,44.908539],"type":"Point"}
}