{
  "type": "Feature",
  "properties": {
    "iso:country":"US",
    "sg:address":"658 SE 10th Ave",
    "sg:city":"Hillsboro",
    "sg:classifiers":[
        {
            "category":"Ice Cream",
            "type":"Food & Drink"
        },
        {
            "category":"Food & Beverages",
            "subcategory":"Dairy",
            "type":"Retail Goods"
        }
    ],
    "sg:menulink":"http://www.allmenus.com/or/beaverton-hillsboro/243625-baskin-robbins/menu/",
    "sg:phone":"+1 503 648 4015",
    "sg:postcode":"97123",
    "sg:province":"OR",
    "sg:tags":[
        "american",
        "ice",
        "cream"
    ],
    "wof:name":"Baskin-Robbins",
    "wof:placetype":"venue"
},
  "geometry": {"coordinates":[-122.973575,45.515329],"type":"Point"}
}