{
  "type": "Feature",
  "properties": {
    "iso:country":"US",
    "sg:address":"11760 SW Ebberts Ct",
    "sg:city":"Beaverton",
    "sg:classifiers":[
        {
            "category":"Professional",
            "subcategory":"Computer Services",
            "type":"Services"
        }
    ],
    "sg:phone":"+1 503 309 1986",
    "sg:postcode":"97008",
    "sg:province":"OR",
    "sg:tags":[
        "datum"
    ],
    "wof:name":"Gilges Media",
    "wof:placetype":"venue"
},
  "geometry": {"coordinates":[-122.799182,45.448812],"type":"Point"}
}