{
  "type": "Feature",
  "properties": {
    "iso:country":"US",
    "sg:address":"2709 19th St SE",
    "sg:city":"Salem",
    "sg:classifiers":[
        {
            "category":"Wholesale",
            "subcategory":"Metals & Minerals",
            "type":"Manufacturing & Wholesale Goods"
        }
    ],
    "sg:phone":"+1 503 370 7022",
    "sg:postcode":"97302",
    "sg:province":"OR",
    "sg:tags":[
        "aluminum"
    ],
    "wof:name":"Statewide Components Inc",
    "wof:placetype":"venue"
},
  "geometry": {"coordinates":[-123.021135,44.913825],"type":"Point"}
}