{
  "type": "Feature",
  "properties": {
    "addr:full":"715 SW 4th St Madras OR 97741",
    "addr:housenumber":"715",
    "addr:postcode":"97741",
    "addr:street":"Sw 4Th St",
    "iso:country":"US",
    "sg:address":"715 SW 4th St",
    "sg:city":"Madras",
    "sg:classifiers":[
        {
            "category":"Professional",
            "type":"Services"
        }
    ],
    "sg:phone":"+1 541 475 1124",
    "sg:postcode":"97741",
    "sg:province":"OR",
    "sg:tags":[
        "establishment"
    ],
    "wof:name":"Redwood Toxicology",
    "wof:placetype":"venue"
},
  "geometry": {"coordinates":[-121.130527,44.625981],"type":"Point"}
}