{
  "type": "Feature",
  "properties": {
    "iso:country":"US",
    "sg:address":"16975 Falls City Rd",
    "sg:city":"Dallas",
    "sg:classifiers":[
        {
            "category":"Manufacturing",
            "subcategory":"Lumber",
            "type":"Manufacturing & Wholesale Goods"
        }
    ],
    "sg:phone":"+1 503 623 2028",
    "sg:postcode":"97338",
    "sg:province":"OR",
    "sg:tags":[
        "restoration",
        "forest"
    ],
    "wof:name":"Tree Best Reforesters Inc",
    "wof:placetype":"venue"
},
  "geometry": {"coordinates":[-123.377011,44.857223],"type":"Point"}
}