{
  "type": "Feature",
  "properties": {
    "iso:country":"US",
    "sg:address":"1175 E Main St",
    "sg:city":"Medford",
    "sg:classifiers":[
        {
            "category":"Building & Trades",
            "subcategory":"Construction",
            "type":"Services"
        }
    ],
    "sg:phone":"+1 541 245 4400",
    "sg:postcode":"97504",
    "sg:province":"OR",
    "sg:tags":[
        "excavating",
        "contractor"
    ],
    "wof:name":"Medford Concrete Pumping",
    "wof:placetype":"venue"
},
  "geometry": {"coordinates":[-122.859437,42.327955],"type":"Point"}
}