{
  "type": "Feature",
  "properties": {
    "iso:country":"US",
    "sg:address":"835 SE Oak Ave",
    "sg:city":"Roseburg",
    "sg:classifiers":[
        {
            "category":"Professional",
            "type":"Services"
        }
    ],
    "sg:phone":"+1 541 672 3821",
    "sg:postcode":"97470",
    "sg:province":"OR",
    "sg:tags":[
        "establishment"
    ],
    "wof:name":"Adapt",
    "wof:placetype":"venue"
},
  "geometry": {"coordinates":[-123.344766,43.209022],"type":"Point"}
}