{
  "type": "Feature",
  "properties": {
    "iso:country":"US",
    "sg:address":"535 Maple Ct",
    "sg:city":"Aumsville",
    "sg:classifiers":[
        {
            "category":"Home & Garden",
            "subcategory":"Carpets & Floor Coverings",
            "type":"Retail Goods"
        }
    ],
    "sg:phone":"+1 503 749 3940",
    "sg:postcode":"97325",
    "sg:province":"OR",
    "sg:tags":[
        "flooring",
        "contractor"
    ],
    "wof:name":"Dave's Installation",
    "wof:placetype":"venue"
},
  "geometry": {"coordinates":[-122.86985199999999,44.846488],"type":"Point"}
}