{
  "type": "Feature",
  "properties": {
    "iso:country":"US",
    "sg:address":"15485 Boones Ferry Rd",
    "sg:city":"Lake Oswego",
    "sg:classifiers":[
        {
            "category":"Building & Trades",
            "subcategory":"Locksmith",
            "type":"Services"
        }
    ],
    "sg:phone":"+1 503 914 0706",
    "sg:postcode":"97035",
    "sg:province":"OR",
    "sg:tags":[
        "key"
    ],
    "wof:name":"Available Locksmith",
    "wof:placetype":"venue"
},
  "geometry": {"coordinates":[-122.71693,45.41394],"type":"Point"}
}