{
  "type": "Feature",
  "properties": {
    "iso:country":"US",
    "sg:address":"4330 Snowberry St NE",
    "sg:city":"Salem",
    "sg:classifiers":[
        {
            "category":"Real Estate",
            "subcategory":"Real Estate Agent",
            "type":"Services"
        }
    ],
    "sg:phone":"+1 503 399 9300",
    "sg:postcode":"97305",
    "sg:province":"OR",
    "wof:name":"All Success Realty",
    "wof:placetype":"venue"
},
  "geometry": {"coordinates":[-122.97649199999999,44.957856],"type":"Point"}
}