{
  "type": "Feature",
  "properties": {
    "iso:country":"US",
    "sg:address":"9155 SW Barnes Rd Ste 940",
    "sg:city":"Portland",
    "sg:classifiers":[
        {
            "category":"Health Services",
            "subcategory":"Doctor",
            "type":"Services"
        }
    ],
    "sg:phone":"+1 503 297 1351",
    "sg:postcode":"97225",
    "sg:province":"OR",
    "wof:name":"Wolf Ronld F Phy & Sr Gnrl and Vsclr Srgry Clnc PC",
    "wof:placetype":"venue"
},
  "geometry": {"coordinates":[-122.769997,45.508801],"type":"Point"}
}