{
  "type": "Feature",
  "properties": {
    "iso:country":"US",
    "sg:address":"4690 SW Comus Pl",
    "sg:city":"Portland",
    "sg:classifiers":[
        {
            "category":"Real Estate",
            "subcategory":"Architect",
            "type":"Services"
        }
    ],
    "sg:phone":"+1 503 243 3603",
    "sg:postcode":"97219",
    "sg:province":"OR",
    "sg:tags":[
        "architectural"
    ],
    "wof:name":"Integrated Design Solutions",
    "wof:placetype":"venue"
},
  "geometry": {"coordinates":[-122.725098,45.446724],"type":"Point"}
}