{
  "type": "Feature",
  "properties": {
    "addr:full":"2926 N Williams Ave Portland OR 97227",
    "addr:housenumber":"2926",
    "addr:postcode":"97227",
    "addr:street":"N Williams Ave",
    "iso:country":"US",
    "sg:address":"2926 N Williams Ave",
    "sg:city":"Portland",
    "sg:classifiers":[
        {
            "category":"Organizations",
            "subcategory":"Religious Organization",
            "type":"Services"
        }
    ],
    "sg:phone":"+1 503 287 3724",
    "sg:postcode":"97227",
    "sg:province":"OR",
    "sg:tags":[
        "place",
        "worship",
        "church"
    ],
    "sg:website":"http://www.stannechurch.com",
    "wof:name":"Immaculate Heart Catholic Chr",
    "wof:placetype":"venue"
},
  "geometry": {"coordinates":[-122.66667200000001,45.544021],"type":"Point"}
}