{
  "type": "Feature",
  "properties": {
    "iso:country":"US",
    "sg:address":"17221 SW Baseline Rd",
    "sg:city":"Beaverton",
    "sg:classifiers":[
        {
            "category":"Personal",
            "subcategory":"Beauty Salon",
            "type":"Services"
        }
    ],
    "sg:phone":"+1 503 439 8053",
    "sg:postcode":"97006",
    "sg:province":"OR",
    "sg:tags":[
        "shop"
    ],
    "wof:name":"TS Nails",
    "wof:placetype":"venue"
},
  "geometry": {"coordinates":[-122.853175,45.512591],"type":"Point"}
}