{
  "type": "Feature",
  "properties": {
    "iso:country":"US",
    "sg:address":"853 Hillview Dr",
    "sg:city":"Ashland",
    "sg:classifiers":[
        {
            "category":"Professional",
            "subcategory":"Art Services",
            "type":"Services"
        }
    ],
    "sg:phone":"+1 541 488 2930",
    "sg:postcode":"97520",
    "sg:province":"OR",
    "sg:tags":[
        "commercial",
        "design"
    ],
    "wof:name":"Float Art Design",
    "wof:placetype":"venue"
},
  "geometry": {"coordinates":[-122.68376,42.180319],"type":"Point"}
}