{
  "type": "Feature",
  "properties": {
    "iso:country":"US",
    "sg:address":"2204 SE 82nd Ave",
    "sg:city":"Portland",
    "sg:classifiers":[
        {
            "category":"Restaurant",
            "type":"Food & Drink"
        }
    ],
    "sg:menulink":"http://www.allmenus.com/or/portland/152906-carrows/menu/",
    "sg:phone":"+1 503 775 3494",
    "sg:postcode":"97216",
    "sg:province":"OR",
    "sg:tags":[
        "sandwich",
        "salad",
        "burger",
        "dog",
        "soup",
        "hot",
        "wrap",
        "american"
    ],
    "wof:name":"Carrows",
    "wof:placetype":"venue"
},
  "geometry": {"coordinates":[-122.578081,45.506989],"type":"Point"}
}