{
  "type": "Feature",
  "properties": {
    "iso:country":"US",
    "sg:address":"818 SE 6th Ave",
    "sg:city":"Portland",
    "sg:classifiers":[
        {
            "category":"Arts & Performance",
            "subcategory":"Arts Center",
            "type":"Entertainment"
        }
    ],
    "sg:phone":"+1 503 222 5538",
    "sg:postcode":"97214",
    "sg:province":"OR",
    "sg:tags":[
        "performing"
    ],
    "sg:website":"www.obt.org",
    "wof:name":"Oregon Ballet Theatre",
    "wof:placetype":"venue"
},
  "geometry": {"coordinates":[-122.660004,45.517101],"type":"Point"}
}