{
  "type": "Feature",
  "properties": {
    "addr:full":"9212 SE Ramona St Portland OR 97266",
    "addr:housenumber":"9212",
    "addr:postcode":"97266",
    "addr:street":"Se Ramona St",
    "iso:country":"US",
    "sg:address":"9212 SE Ramona St",
    "sg:city":"Portland",
    "sg:classifiers":[
        {
            "category":"Sports & Exercise",
            "subcategory":"Gym",
            "type":"Entertainment"
        },
        {
            "category":"Arena",
            "subcategory":"Sports Club",
            "type":"Entertainment"
        }
    ],
    "sg:phone":"+1 503 771 5114",
    "sg:postcode":"97266",
    "sg:province":"OR",
    "sg:tags":[
        "trainer",
        "martial art"
    ],
    "wof:name":"Oregon Karate & Kung-Fu Association",
    "wof:placetype":"venue"
},
  "geometry": {"coordinates":[-122.568001,45.480598],"type":"Point"}
}