{
  "type": "Feature",
  "properties": {
    "iso:country":"US",
    "sg:address":"260 S Oregon St",
    "sg:city":"Jacksonville",
    "sg:classifiers":[
        {
            "category":"Banks & Credit Unions",
            "subcategory":"Investment Brokerage",
            "type":"Services"
        }
    ],
    "sg:phone":"+1 541 899 1905",
    "sg:postcode":"97530",
    "sg:province":"OR",
    "sg:tags":[
        "security"
    ],
    "wof:name":"Edward Jones Co",
    "wof:placetype":"venue"
},
  "geometry": {"coordinates":[-122.96914099999999,42.313818],"type":"Point"}
}