{
  "type": "Feature",
  "properties": {
    "iso:country":"US",
    "sg:address":"800 SE 26th St",
    "sg:city":"Portland",
    "sg:classifiers":[
        {
            "category":"Professional",
            "type":"Services"
        }
    ],
    "sg:phone":"+1 206 890 9906",
    "sg:postcode":"97214",
    "sg:province":"OR",
    "sg:website":"www.riotactmedia.com",
    "wof:name":"Riot Act Media",
    "wof:placetype":"venue"
},
  "geometry": {"coordinates":[-122.63881499999999,45.516871],"type":"Point"}
}