{
  "type": "Feature",
  "properties": {
    "addr:full":"411 4th St Gold Hill OR 97525",
    "addr:housenumber":"411",
    "addr:postcode":"97525",
    "addr:street":"4Th St",
    "iso:country":"US",
    "sg:address":"411 4th St",
    "sg:city":"Gold Hill",
    "sg:classifiers":[
        {
            "category":"Restaurant",
            "type":"Food & Drink"
        }
    ],
    "sg:phone":"+1 541 855 1593",
    "sg:postcode":"97525",
    "sg:province":"OR",
    "sg:tags":[
        "eating"
    ],
    "wof:name":"Miners Roost Rest & Lounge",
    "wof:placetype":"venue"
},
  "geometry": {"coordinates":[-123.048301,42.432869],"type":"Point"}
}