{
  "type": "Feature",
  "properties": {
    "iso:country":"US",
    "sg:address":"260 Fulton St",
    "sg:city":"Klamath Falls",
    "sg:classifiers":[
        {
            "category":"Home & Garden",
            "subcategory":"Home Furnishings",
            "type":"Retail Goods"
        }
    ],
    "sg:phone":"+1 541 850 1329",
    "sg:postcode":"97601",
    "sg:province":"OR",
    "sg:tags":[
        "curtain",
        "made",
        "drapery"
    ],
    "wof:name":"Rhonda's Custom Windows",
    "wof:placetype":"venue"
},
  "geometry": {"coordinates":[-121.794865,42.233001],"type":"Point"}
}