{
  "type": "Feature",
  "properties": {
    "iso:country":"US",
    "sg:address":"1300 SW 5th Ave",
    "sg:city":"Portland",
    "sg:classifiers":[
        {
            "category":"Professional",
            "subcategory":"Lawyer & Legal Services",
            "type":"Services"
        }
    ],
    "sg:phone":"+1 503 226 7677",
    "sg:postcode":"97201",
    "sg:province":"OR",
    "sg:tags":[
        "attorney",
        "business",
        "tax",
        "governmental",
        "law",
        "administrative",
        "bankruptcy"
    ],
    "wof:name":"Cosgrove , Paul S. - Lindsay Hart Neil &",
    "wof:placetype":"venue"
},
  "geometry": {"coordinates":[-122.67971799999999,45.514809],"type":"Point"}
}