{
  "type": "Feature",
  "properties": {
    "iso:country":"US",
    "sg:address":"3839 NE Tillamook St",
    "sg:city":"Portland",
    "sg:classifiers":[
        {
            "category":"Professional",
            "subcategory":"Lawyer & Legal Services",
            "type":"Services"
        }
    ],
    "sg:phone":"+1 503 249 8400",
    "sg:postcode":"97212",
    "sg:province":"OR",
    "sg:tags":[
        "divorce",
        "law",
        "family"
    ],
    "wof:name":"Andrea W. Snyder",
    "wof:placetype":"venue"
},
  "geometry": {"coordinates":[-122.623587,45.537782],"type":"Point"}
}