{
  "type": "Feature",
  "properties": {
    "iso:country":"US",
    "sg:address":"241 NE 125th Ave",
    "sg:city":"Portland",
    "sg:classifiers":[
        {
            "category":"Building & Trades",
            "subcategory":"Construction",
            "type":"Services"
        }
    ],
    "sg:phone":"+1 503 256 1983",
    "sg:postcode":"97230",
    "sg:province":"OR",
    "sg:tags":[
        "contractor"
    ],
    "wof:name":"Prodigy Construction",
    "wof:placetype":"venue"
},
  "geometry": {"coordinates":[-122.53473,45.524363],"type":"Point"}
}