{
  "type": "Feature",
  "properties": {
    "iso:country":"US",
    "sg:address":"1645 Mill St",
    "sg:city":"Eugene",
    "sg:classifiers":[
        {
            "category":"Building & Trades",
            "subcategory":"Construction",
            "type":"Services"
        }
    ],
    "sg:phone":"+1 541 343 4456",
    "sg:postcode":"97401",
    "sg:province":"OR",
    "sg:tags":[
        "painting",
        "contractor"
    ],
    "wof:name":"Columbia Painting & Repair Co",
    "wof:placetype":"venue"
},
  "geometry": {"coordinates":[-123.08663199999999,44.041622],"type":"Point"}
}