{
  "type": "Feature",
  "properties": {
    "iso:country":"US",
    "sg:address":"1291 NE Stephens St",
    "sg:city":"Roseburg",
    "sg:classifiers":[
        {
            "category":"Autos & Motor Vehicles",
            "subcategory":"Recreational Vehicle Sales",
            "type":"Retail Goods"
        }
    ],
    "sg:phone":"+1 541 672 8473",
    "sg:postcode":"97470",
    "sg:province":"OR",
    "sg:tags":[
        "repair",
        "parts",
        "se",
        "accessory"
    ],
    "wof:name":"Jims Trailer Supply",
    "wof:placetype":"venue"
},
  "geometry": {"coordinates":[-123.348133,43.225415],"type":"Point"}
}