{
  "type": "Feature",
  "properties": {
    "iso:country":"US",
    "sg:address":"1130 Old Hwy 99 S",
    "sg:city":"Ashland",
    "sg:classifiers":[
        {
            "category":"Professional",
            "subcategory":"Computer Services",
            "type":"Services"
        },
        {
            "category":"Shopping",
            "subcategory":"Computers & Home Electronics",
            "type":"Retail Goods"
        }
    ],
    "sg:phone":"+1 541 488 3237",
    "sg:postcode":"97520",
    "sg:province":"OR",
    "sg:tags":[
        "software",
        "programming",
        "custom"
    ],
    "wof:name":"Computer Consulting Group Inc",
    "wof:placetype":"venue"
},
  "geometry": {"coordinates":[-122.6123,42.129401],"type":"Point"}
}