{
  "type": "Feature",
  "properties": {
    "addr:full":"2145 14th Ave SE Albany OR 97322",
    "addr:housenumber":"2145",
    "addr:postcode":"97322",
    "addr:street":"14Th Ave Se",
    "iso:country":"US",
    "sg:address":"2145 14th Ave SE",
    "sg:city":"Albany",
    "sg:classifiers":[
        {
            "category":"Shopping",
            "subcategory":"Clothing, Apparel, & Fashions",
            "type":"Retail Goods"
        }
    ],
    "sg:phone":"+1 541 926 7345",
    "sg:postcode":"97322",
    "sg:province":"OR",
    "wof:name":"Maurice's",
    "wof:placetype":"venue"
},
  "geometry": {"coordinates":[-123.080766,44.628843],"type":"Point"}
}