{
  "type": "Feature",
  "properties": {
    "iso:country":"US",
    "sg:address":"14217 SE 312th Dr",
    "sg:city":"Boring",
    "sg:classifiers":[
        {
            "category":"Shopping",
            "subcategory":"Clothing, Apparel, & Fashions",
            "type":"Retail Goods"
        }
    ],
    "sg:phone":"+1 503 482 5833",
    "sg:postcode":"97009",
    "sg:province":"OR",
    "sg:tags":[
        "apparel",
        "women's"
    ],
    "wof:name":"Rhinestone Cowgirl Fashions",
    "wof:placetype":"venue"
},
  "geometry": {"coordinates":[-122.341999,45.420435],"type":"Point"}
}