{
  "type": "Feature",
  "properties": {
    "addr:full":"12062 SE Sunnyside Rd Clackamas OR 97015",
    "addr:postcode":"12062;97015",
    "addr:street":"Se Sunnyside Rd",
    "iso:country":"US",
    "sg:address":"12062 SE Sunnyside Rd",
    "sg:city":"Clackamas",
    "sg:classifiers":[
        {
            "category":"Restaurant",
            "type":"Food & Drink"
        }
    ],
    "sg:phone":"+1 503 698 8210",
    "sg:postcode":"97015",
    "sg:province":"OR",
    "wof:name":"Wan-Lung Restaurant",
    "wof:placetype":"venue"
},
  "geometry": {"coordinates":[-122.540001,45.429401],"type":"Point"}
}