{
  "type": "Feature",
  "properties": {
    "addr:full":"23000 S Unger Rd Colton OR 97017",
    "addr:housenumber":"23000",
    "addr:postcode":"97017",
    "addr:street":"S Unger Rd",
    "iso:country":"US",
    "sg:address":"23000 S Unger Rd",
    "sg:city":"Colton",
    "sg:classifiers":[
        {
            "category":"Wholesale",
            "subcategory":"Medical Equipment & Supplies",
            "type":"Manufacturing & Wholesale Goods"
        }
    ],
    "sg:phone":"+1 503 824 3563",
    "sg:postcode":"97017",
    "sg:province":"OR",
    "sg:tags":[
        "physician",
        "surgeon"
    ],
    "wof:name":"K & K Donegan & Assoc Inc",
    "wof:placetype":"venue"
},
  "geometry": {"coordinates":[-122.387692,45.206796],"type":"Point"}
}