{
  "type": "Feature",
  "properties": {
    "iso:country":"US",
    "sg:address":"6650 SW Redwood Ln",
    "sg:city":"Tigard",
    "sg:classifiers":[
        {
            "category":"Insurance",
            "subcategory":"Insurance Agent",
            "type":"Services"
        }
    ],
    "sg:phone":"+1 503 598 3029",
    "sg:postcode":"97224",
    "sg:province":"OR",
    "wof:name":"Horace Mann Insurance Co",
    "wof:placetype":"venue"
},
  "geometry": {"coordinates":[-122.746239,45.409665],"type":"Point"}
}