{
  "type": "Feature",
  "properties": {
    "addr:full":"1121 Helicopter Way Medford OR 97502",
    "addr:housenumber":"1121",
    "addr:postcode":"97502",
    "addr:street":"Helicopter Way",
    "iso:country":"US",
    "sg:address":"1121 Helicopter Way",
    "sg:city":"Medford",
    "sg:classifiers":[
        {
            "category":"Personal",
            "type":"Services"
        }
    ],
    "sg:phone":"+1 541 773 9999",
    "sg:postcode":"97502",
    "sg:province":"OR",
    "sg:tags":[
        "home"
    ],
    "sg:website":"superior4windows.com",
    "wof:name":"Superior Windows & Doors",
    "wof:placetype":"venue"
},
  "geometry": {"coordinates":[-122.862662,42.387345],"type":"Point"}
}