{
  "type": "Feature",
  "properties": {
    "iso:country":"US",
    "sg:address":"1189 SE Monmouth Cut Off Rd",
    "sg:city":"Dallas",
    "sg:classifiers":[
        {
            "category":"Building & Trades",
            "subcategory":"Construction",
            "type":"Services"
        }
    ],
    "sg:phone":"+1 503 831 0430",
    "sg:postcode":"97338",
    "sg:province":"OR",
    "sg:tags":[
        "system",
        "specialty",
        "heating",
        "contractor",
        "air conditioning"
    ],
    "wof:name":"C & S Heating and Cooling",
    "wof:placetype":"venue"
},
  "geometry": {"coordinates":[-123.300586,44.911117],"type":"Point"}
}