{
  "type": "Feature",
  "properties": {
    "iso:country":"US",
    "sg:address":"100 W Ellendale Ave",
    "sg:city":"Dallas",
    "sg:classifiers":[
        {
            "category":"Coffee & Tea",
            "type":"Food & Drink"
        },
        {
            "category":"Restaurant",
            "type":"Food & Drink"
        }
    ],
    "sg:phone":"+1 503 831 0811",
    "sg:postcode":"97338",
    "sg:province":"OR",
    "sg:tags":[
        "espresso"
    ],
    "wof:name":"Brooks & Terry's Esspresso",
    "wof:placetype":"venue"
},
  "geometry": {"coordinates":[-123.311691,44.929508],"type":"Point"}
}