{
  "type": "Feature",
  "properties": {
    "iso:country":"US",
    "sg:address":"41845 Kingston Jordan Rd SE",
    "sg:city":"Stayton",
    "sg:classifiers":[
        {
            "category":"Professional",
            "subcategory":"Computer Services",
            "type":"Services"
        }
    ],
    "sg:phone":"+1 503 769 4507",
    "sg:postcode":"97383",
    "sg:province":"OR",
    "sg:tags":[
        "repair"
    ],
    "wof:name":"Computer Repair & Recycling",
    "wof:placetype":"venue"
},
  "geometry": {"coordinates":[-122.79201399999999,44.788702],"type":"Point"}
}