{
  "type": "Feature",
  "properties": {
    "addr:full":"938 N 9th St Coos Bay OR 97420",
    "addr:housenumber":"938",
    "addr:postcode":"97420",
    "addr:street":"N 9Th St",
    "iso:country":"US",
    "sg:address":"938 N 9th St",
    "sg:city":"Coos Bay",
    "sg:classifiers":[
        {
            "category":"Building & Trades",
            "subcategory":"Plumbing",
            "type":"Services"
        }
    ],
    "sg:phone":"+1 541 269 2934",
    "sg:postcode":"97420",
    "sg:province":"OR",
    "sg:tags":[
        "contractor"
    ],
    "wof:name":"A&B Plumbing",
    "wof:placetype":"venue"
},
  "geometry": {"coordinates":[-124.221141,43.374112],"type":"Point"}
}