{
  "type": "Feature",
  "properties": {
    "iso:country":"US",
    "sg:address":"10873 SW Powell Butte Hwy",
    "sg:city":"Powell Butte",
    "sg:classifiers":[
        {
            "category":"Manufacturing",
            "subcategory":"Lumber",
            "type":"Manufacturing & Wholesale Goods"
        }
    ],
    "sg:phone":"+1 541 548 4313",
    "sg:postcode":"97753",
    "sg:province":"OR",
    "sg:tags":[
        "firefighter"
    ],
    "wof:name":"Norman A Borgaard",
    "wof:placetype":"venue"
},
  "geometry": {"coordinates":[-121.04813,44.225978],"type":"Point"}
}