{
  "type": "Feature",
  "properties": {
    "iso:country":"US",
    "sg:address":"680 SE 13th St",
    "sg:city":"Ontario",
    "sg:classifiers":[
        {
            "category":"Social Services",
            "type":"Services"
        }
    ],
    "sg:phone":"+1 541 889 9206",
    "sg:postcode":"97914",
    "sg:province":"OR",
    "sg:tags":[
        "organization",
        "welfare"
    ],
    "wof:name":"Foodbank Seo Regional",
    "wof:placetype":"venue"
},
  "geometry": {"coordinates":[-116.945323,44.019584],"type":"Point"}
}