{
  "type": "Feature",
  "properties": {
    "iso:country":"US",
    "sg:address":"4727 Homedale Rd",
    "sg:city":"Klamath Falls",
    "sg:classifiers":[
        {
            "category":"Education",
            "subcategory":"School",
            "type":"Public Place"
        }
    ],
    "sg:phone":"+1 541 883 5025",
    "sg:postcode":"97603",
    "sg:province":"OR",
    "wof:name":"Brixner Junior High School",
    "wof:placetype":"venue"
},
  "geometry": {"coordinates":[-121.722628,42.18322],"type":"Point"}
}