{
  "type": "Feature",
  "properties": {
    "addr:full":"51500 Hwy 97 La Pine OR 97739",
    "addr:housenumber":"51500",
    "addr:postcode":"97739",
    "addr:street":"Hwy 97",
    "iso:country":"US",
    "sg:address":"51500 Hwy 97",
    "sg:city":"La Pine",
    "sg:classifiers":[
        {
            "category":"Restaurant",
            "type":"Food & Drink"
        }
    ],
    "sg:phone":"+1 541 536 1670",
    "sg:postcode":"97739",
    "sg:province":"OR",
    "sg:tags":[
        "eating"
    ],
    "wof:name":"Angel's Thai Restaurant",
    "wof:placetype":"venue"
},
  "geometry": {"coordinates":[-121.50331799999999,43.670575],"type":"Point"}
}