{
  "type": "Feature",
  "properties": {
    "iso:country":"US",
    "sg:address":"10150 SW Herman Rd",
    "sg:city":"Tualatin",
    "sg:classifiers":[
        {
            "category":"Home & Garden",
            "subcategory":"Hardware",
            "type":"Retail Goods"
        },
        {
            "category":"Utilities",
            "subcategory":"Cable",
            "type":"Services"
        }
    ],
    "sg:phone":"+1 503 227 5555",
    "sg:postcode":"97062",
    "sg:province":"OR",
    "sg:tags":[
        "cable-non-electric",
        "wire",
        "cable-electric"
    ],
    "wof:name":"Pacific Western Agencies Inc",
    "wof:placetype":"venue"
},
  "geometry": {"coordinates":[-122.781431,45.385533],"type":"Point"}
}