{
  "type": "Feature",
  "properties": {
    "addr:full":"727 Medford Center Medford OR 97504",
    "addr:housenumber":"727",
    "addr:postcode":"97504",
    "addr:street":"Medford Center",
    "iso:country":"US",
    "sg:address":"727 Medford Center",
    "sg:city":"Medford",
    "sg:classifiers":[
        {
            "category":"Shopping",
            "subcategory":"Bicycles & Sporting Goods",
            "type":"Retail Goods"
        }
    ],
    "sg:phone":"+1 541 772 7099",
    "sg:postcode":"97504",
    "sg:province":"OR",
    "sg:tags":[
        "equipment",
        "parts",
        "exercise"
    ],
    "wof:name":"Sims Cycle & Fitness",
    "wof:placetype":"venue"
},
  "geometry": {"coordinates":[-122.867294,42.331131],"type":"Point"}
}