{
  "type": "Feature",
  "properties": {
    "addr:full":"2813 NE 59th Ave Portland OR 97213",
    "addr:housenumber":"2813",
    "addr:postcode":"97213",
    "addr:street":"Ne 59Th Ave",
    "iso:country":"US",
    "sg:address":"2813 NE 59th Ave",
    "sg:city":"Portland",
    "sg:classifiers":[
        {
            "category":"Real Estate",
            "subcategory":"Real Estate Agent",
            "type":"Services"
        }
    ],
    "sg:phone":"+1 503 249 1418",
    "sg:postcode":"97213",
    "sg:province":"OR",
    "wof:name":"North Fork Properties",
    "wof:placetype":"venue"
},
  "geometry": {"coordinates":[-122.602591,45.543611],"type":"Point"}
}