{
  "type": "Feature",
  "properties": {
    "addr:full":"3964 Center St NE Salem OR 97301",
    "addr:housenumber":"3964",
    "addr:postcode":"97301",
    "addr:street":"Center St Ne",
    "iso:country":"US",
    "sg:address":"3964 Center St NE",
    "sg:city":"Salem",
    "sg:classifiers":[
        {
            "category":"Restaurant",
            "type":"Food & Drink"
        }
    ],
    "sg:menulink":"http://www.allmenus.com/or/salem/6511-papa-johns-pizza/menu/",
    "sg:phone":"+1 503 585 7272",
    "sg:postcode":"97301",
    "sg:province":"OR",
    "sg:tags":[
        "american",
        "pizza"
    ],
    "wof:name":"Papa John's Pizza",
    "wof:placetype":"venue"
},
  "geometry": {"coordinates":[-122.98357,44.939682],"type":"Point"}
}