{
  "type": "Feature",
  "properties": {
    "iso:country":"US",
    "sg:address":"1016 NE Mast Ave",
    "sg:city":"Lincoln City",
    "sg:classifiers":[
        {
            "category":"Building & Trades",
            "subcategory":"Construction",
            "type":"Services"
        }
    ],
    "sg:phone":"+1 541 994 7077",
    "sg:postcode":"97367",
    "sg:province":"OR",
    "sg:tags":[
        "house"
    ],
    "wof:name":"Dl Remodeling",
    "wof:placetype":"venue"
},
  "geometry": {"coordinates":[-124.01047,44.973104],"type":"Point"}
}