{
  "type": "Feature",
  "properties": {
    "iso:country":"US",
    "sg:address":"201 NE 7th St",
    "sg:city":"Grants Pass",
    "sg:classifiers":[
        {
            "category":"Autos & Motor Vehicles",
            "subcategory":"Automobile Sales",
            "type":"Retail Goods"
        }
    ],
    "sg:phone":"+1 541 779 7153",
    "sg:postcode":"97526",
    "sg:province":"OR",
    "sg:tags":[
        "car",
        "dealer"
    ],
    "sg:website":"www.roemotors.com",
    "wof:name":"Roe Gm",
    "wof:placetype":"venue"
},
  "geometry": {"coordinates":[-123.32521800000001,42.439606],"type":"Point"}
}