{
  "type": "Feature",
  "properties": {
    "iso:country":"US",
    "sg:address":"3140 Cascade Ave",
    "sg:city":"Hood River",
    "sg:classifiers":[
        {
            "category":"Autos & Motor Vehicles",
            "subcategory":"Auto Supplies",
            "type":"Retail Goods"
        }
    ],
    "sg:phone":"+1 541 386 1123",
    "sg:postcode":"97031",
    "sg:province":"OR",
    "sg:tags":[
        "tire",
        "accessory"
    ],
    "wof:name":"Les Schwab Tire Center",
    "wof:placetype":"venue"
},
  "geometry": {"coordinates":[-121.544603,45.710792],"type":"Point"}
}