{
  "type": "Feature",
  "properties": {
    "iso:country":"US",
    "sg:address":"9580 SW 146th Ter",
    "sg:city":"Beaverton",
    "sg:classifiers":[
        {
            "category":"Organizations",
            "subcategory":"Religious Organization",
            "type":"Services"
        }
    ],
    "sg:phone":"+1 503 579 5009",
    "sg:postcode":"97007",
    "sg:province":"OR",
    "wof:name":"Willamtte Free Lutheran Church",
    "wof:placetype":"venue"
},
  "geometry": {"coordinates":[-122.826505,45.452829],"type":"Point"}
}