{
  "type": "Feature",
  "properties": {
    "iso:country":"US",
    "sg:address":"1724 23rd St SE",
    "sg:city":"Salem",
    "sg:classifiers":[
        {
            "category":"Manufacturing",
            "subcategory":"Electronics",
            "type":"Manufacturing & Wholesale Goods"
        }
    ],
    "sg:phone":"+1 503 399 7010",
    "sg:postcode":"97302",
    "sg:province":"OR",
    "wof:name":"Slater Communications Inc",
    "wof:placetype":"venue"
},
  "geometry": {"coordinates":[-123.014604,44.919858],"type":"Point"}
}