{
  "type": "Feature",
  "properties": {
    "addr:full":"1724 23rd St SE Salem OR 97302",
    "addr:housenumber":"1724",
    "addr:postcode":"97302",
    "addr:street":"23Rd St Se",
    "iso:country":"US",
    "sg:address":"1724 23rd St SE",
    "sg:city":"Salem",
    "sg:classifiers":[
        {
            "category":"Manufacturing",
            "subcategory":"Electronics",
            "type":"Manufacturing & Wholesale Goods"
        }
    ],
    "sg:phone":"+1 503 399 7010",
    "sg:postcode":"97302",
    "sg:province":"OR",
    "wof:name":"Slater Communications Inc",
    "wof:placetype":"venue"
},
  "geometry": {"coordinates":[-123.01460400000001,44.919858],"type":"Point"}
}