{
  "type": "Feature",
  "properties": {
    "iso:country":"US",
    "sg:address":"6330 D St",
    "sg:city":"Springfield",
    "sg:classifiers":[
        {
            "category":"Manufacturing",
            "subcategory":"Buildings",
            "type":"Manufacturing & Wholesale Goods"
        },
        {
            "category":"Building & Trades",
            "subcategory":"Construction",
            "type":"Services"
        }
    ],
    "sg:phone":"+1 541 510 0707",
    "sg:postcode":"97478",
    "sg:province":"OR",
    "sg:tags":[
        "home",
        "builder",
        "contractor"
    ],
    "wof:name":"Rees Brothers",
    "wof:placetype":"venue"
},
  "geometry": {"coordinates":[-122.917365,44.049573],"type":"Point"}
}