{
  "type": "Feature",
  "properties": {
    "addr:full":"3511 NE 82nd Ave Portland OR 97220",
    "addr:housenumber":"3511",
    "addr:postcode":"97220",
    "addr:street":"Ne 82Nd Ave",
    "iso:country":"US",
    "sg:address":"3511 NE 82nd Ave",
    "sg:city":"Portland",
    "sg:classifiers":[
        {
            "category":"Fast Food",
            "type":"Food & Drink"
        },
        {
            "category":"Restaurant",
            "type":"Food & Drink"
        }
    ],
    "sg:postcode":"97220",
    "sg:province":"OR",
    "sg:tags":[
        "southern"
    ],
    "sg:website":"www.popeyes.com",
    "wof:name":"Popeye's Chicken & Biscuits",
    "wof:placetype":"venue"
},
  "geometry": {"coordinates":[-122.578737,45.548226],"type":"Point"}
}