{
  "type": "Feature",
  "properties": {
    "iso:country":"US",
    "sg:address":"415 N State St",
    "sg:city":"Lake Oswego",
    "sg:classifiers":[
        {
            "category":"Professional",
            "subcategory":"Accounting & Tax Preparation",
            "type":"Services"
        }
    ],
    "sg:phone":"+1 503 699 5040",
    "sg:postcode":"97034",
    "sg:province":"OR",
    "wof:name":"Loren R Northup CPA",
    "wof:placetype":"venue"
},
  "geometry": {"coordinates":[-122.66260200000001,45.420321],"type":"Point"}
}