{
  "type": "Feature",
  "properties": {
    "addr:full":"1466 Commercial St SE Salem OR 97302",
    "addr:housenumber":"1466",
    "addr:postcode":"97302",
    "addr:street":"Commercial St Se",
    "iso:country":"US",
    "sg:address":"1466 Commercial St SE",
    "sg:city":"Salem",
    "sg:classifiers":[
        {
            "category":"Health Services",
            "subcategory":"Medical Lab",
            "type":"Services"
        }
    ],
    "sg:phone":"+1 503 485 2845",
    "sg:postcode":"97302",
    "sg:province":"OR",
    "sg:tags":[
        "laboratory",
        "dental"
    ],
    "wof:name":"Civilux Inc",
    "wof:placetype":"venue"
},
  "geometry": {"coordinates":[-123.044309,44.926558],"type":"Point"}
}