{
  "type": "Feature",
  "properties": {
    "iso:country":"US",
    "sg:address":"1100 Liberty St SE",
    "sg:city":"Salem",
    "sg:classifiers":[
        {
            "category":"Building & Trades",
            "subcategory":"Construction",
            "type":"Services"
        }
    ],
    "sg:phone":"+1 503 581 2485",
    "sg:postcode":"97302",
    "sg:province":"OR",
    "sg:tags":[
        "contractor"
    ],
    "wof:name":"George Suniga",
    "wof:placetype":"venue"
},
  "geometry": {"coordinates":[-123.04258,44.929159],"type":"Point"}
}