{
  "type": "Feature",
  "properties": {
    "iso:country":"US",
    "sg:address":"308 SW 1st Ave Ste 183",
    "sg:city":"Portland",
    "sg:classifiers":[
        {
            "category":"Professional",
            "type":"Services"
        }
    ],
    "sg:phone":"+1 503 232 7550",
    "sg:postcode":"97204",
    "sg:province":"OR",
    "sg:tags":[
        "planning",
        "event"
    ],
    "sg:website":"www.pgsca.com/",
    "wof:name":"Portland Guadalajara Sister City Association",
    "wof:placetype":"venue"
},
  "geometry": {"coordinates":[-122.672286,45.520179],"type":"Point"}
}