{
  "type": "Feature",
  "properties": {
    "iso:country":"US",
    "sg:address":"316 NE 19th Ave",
    "sg:city":"Portland",
    "sg:classifiers":[
        {
            "category":"Banks & Credit Unions",
            "subcategory":"Bank",
            "type":"Services"
        }
    ],
    "sg:phone":"+1 503 230 2552",
    "sg:postcode":"97232",
    "sg:province":"OR",
    "sg:tags":[
        "broker",
        "mortgage"
    ],
    "wof:name":"Advance Mortgage Group LLC",
    "wof:placetype":"venue"
},
  "geometry": {"coordinates":[-122.646415,45.525462],"type":"Point"}
}