{
  "type": "Feature",
  "properties": {
    "addr:full":"1729 NE Cornell Rd Hillsboro OR 97124",
    "addr:housenumber":"1729",
    "addr:postcode":"97124",
    "addr:street":"Ne Cornell Rd",
    "iso:country":"US",
    "sg:address":"1729 NE Cornell Rd",
    "sg:city":"Hillsboro",
    "sg:classifiers":[
        {
            "category":"Autos & Motor Vehicles",
            "subcategory":"Fuel & Gas Station",
            "type":"Retail Goods"
        }
    ],
    "sg:phone":"+1 503 648 5411",
    "sg:postcode":"97124",
    "sg:province":"OR",
    "sg:tags":[
        "oil"
    ],
    "wof:name":"Airport 76",
    "wof:placetype":"venue"
},
  "geometry": {"coordinates":[-122.962789,45.530762],"type":"Point"}
}