{
  "type": "Feature",
  "properties": {
    "iso:country":"US",
    "sg:address":"725 E 14th Ave",
    "sg:city":"Eugene",
    "sg:classifiers":[
        {
            "category":"Real Estate",
            "subcategory":"Real Estate Operator",
            "type":"Services"
        }
    ],
    "sg:phone":"+1 541 302 9088",
    "sg:postcode":"97401",
    "sg:province":"OR",
    "sg:tags":[
        "apartment"
    ],
    "wof:name":"Hilyard House Apartments",
    "wof:placetype":"venue"
},
  "geometry": {"coordinates":[-123.080635,44.044494],"type":"Point"}
}