{
  "type": "Feature",
  "properties": {
    "iso:country":"US",
    "sg:address":"214 Arnold St",
    "sg:city":"St Helens",
    "sg:classifiers":[
        {
            "category":"Social Services",
            "type":"Services"
        }
    ],
    "sg:phone":"+1 503 397 6161",
    "sg:postcode":"97051",
    "sg:province":"OR",
    "sg:tags":[
        "crisis",
        "intervention"
    ],
    "wof:name":"Women's Resource Ctr",
    "wof:placetype":"venue"
},
  "geometry": {"coordinates":[-122.82068,45.86053],"type":"Point"}
}