{
  "type": "Feature",
  "properties": {
    "iso:country":"US",
    "sg:address":"4045 Scenic Dr",
    "sg:city":"Eugene",
    "sg:classifiers":[
        {
            "category":"Shopping",
            "subcategory":"Catalog Store",
            "type":"Retail Goods"
        },
        {
            "category":"Professional",
            "subcategory":"Computer Services",
            "type":"Services"
        }
    ],
    "sg:phone":"+1 541 461 2742",
    "sg:postcode":"97404",
    "sg:province":"OR",
    "sg:tags":[
        "mail",
        "software",
        "order",
        "programing",
        "custom"
    ],
    "wof:name":"A-2 Technologies",
    "wof:placetype":"venue"
},
  "geometry": {"coordinates":[-123.130455,44.121726],"type":"Point"}
}