{
  "type": "Feature",
  "properties": {
    "iso:country":"US",
    "sg:address":"4219 SW Freeman St",
    "sg:city":"Portland",
    "sg:classifiers":[
        {
            "category":"Professional",
            "subcategory":"Engineering",
            "type":"Services"
        },
        {
            "category":"Professional",
            "subcategory":"Computer Services",
            "type":"Services"
        }
    ],
    "sg:phone":"+1 503 246 0698",
    "sg:postcode":"97219",
    "sg:province":"OR",
    "sg:tags":[
        "engineer",
        "consultant",
        "designer",
        "system",
        "integration"
    ],
    "wof:name":"Network Sciences Company, Inc",
    "wof:placetype":"venue"
},
  "geometry": {"coordinates":[-122.72150600000001,45.462881],"type":"Point"}
}