{
  "type": "Feature",
  "properties": {
    "iso:country":"US",
    "sg:address":"537 E 39th Pl",
    "sg:city":"Eugene",
    "sg:classifiers":[
        {
            "category":"Manufacturing",
            "subcategory":"Metals",
            "type":"Manufacturing & Wholesale Goods"
        }
    ],
    "sg:phone":"+1 541 683 3850",
    "sg:postcode":"97405",
    "sg:province":"OR",
    "sg:tags":[
        "metalwork",
        "architectural",
        "mfg"
    ],
    "wof:name":"Innovations In Iron",
    "wof:placetype":"venue"
},
  "geometry": {"coordinates":[-123.084066,44.012535],"type":"Point"}
}