{
  "type": "Feature",
  "properties": {
    "addr:full":"31404 S Twin Rocks Rd Molalla OR 97038",
    "addr:housenumber":"31404",
    "addr:postcode":"97038",
    "addr:street":"S Twin Rocks Rd",
    "iso:country":"US",
    "sg:address":"31404 S Twin Rocks Rd",
    "sg:city":"Molalla",
    "sg:classifiers":[
        {
            "category":"Professional",
            "type":"Services"
        }
    ],
    "sg:phone":"+1 503 829 4995",
    "sg:postcode":"97038",
    "sg:province":"OR",
    "wof:name":"Cumulus Resources LLC",
    "wof:placetype":"venue"
},
  "geometry": {"coordinates":[-122.53076900000001,45.156799],"type":"Point"}
}