{
  "type": "Feature",
  "properties": {
    "iso:country":"US",
    "sg:address":"31404 S Twin Rocks Rd",
    "sg:city":"Molalla",
    "sg:classifiers":[
        {
            "category":"Professional",
            "type":"Services"
        }
    ],
    "sg:phone":"+1 503 829 4995",
    "sg:postcode":"97038",
    "sg:province":"OR",
    "wof:name":"Cumulus Resources LLC",
    "wof:placetype":"venue"
},
  "geometry": {"coordinates":[-122.530769,45.156799],"type":"Point"}
}