{
  "type": "Feature",
  "properties": {
    "iso:country":"US",
    "sg:address":"5595 S Santiam Hwy",
    "sg:city":"Lebanon",
    "sg:classifiers":[
        {
            "category":"Manufacturing",
            "subcategory":"Building Materials",
            "type":"Manufacturing & Wholesale Goods"
        }
    ],
    "sg:phone":"+1 541 451 2441",
    "sg:postcode":"97355",
    "sg:province":"OR",
    "sg:tags":[
        "wood",
        "mfg"
    ],
    "wof:name":"Kenmar Molding Inc",
    "wof:placetype":"venue"
},
  "geometry": {"coordinates":[-122.8532,44.500533],"type":"Point"}
}