{
  "type": "Feature",
  "properties": {
    "addr:full":"2009 Main St Forest Grove OR 97116",
    "addr:housenumber":"2009",
    "addr:postcode":"97116",
    "addr:street":"Main St",
    "iso:country":"US",
    "sg:address":"2009 Main St",
    "sg:city":"Forest Grove",
    "sg:classifiers":[
        {
            "category":"Restaurant",
            "type":"Food & Drink"
        }
    ],
    "sg:phone":"+1 503 359 8471",
    "sg:postcode":"97116",
    "sg:province":"OR",
    "sg:tags":[
        "eating"
    ],
    "wof:name":"El Torero",
    "wof:placetype":"venue"
},
  "geometry": {"coordinates":[-123.111977,45.520837],"type":"Point"}
}