{
  "type": "Feature",
  "properties": {
    "iso:country":"US",
    "sg:address":"3200 SE Maple St",
    "sg:city":"Portland",
    "sg:classifiers":[
        {
            "category":"Restaurant",
            "type":"Food & Drink"
        }
    ],
    "sg:phone":"+1 503 654 1792",
    "sg:postcode":"97267",
    "sg:province":"OR",
    "sg:tags":[
        "used",
        "eating",
        "merchandise"
    ],
    "wof:name":"Yogibogi LLC",
    "wof:placetype":"venue"
},
  "geometry": {"coordinates":[-122.628722,45.418383],"type":"Point"}
}