{
  "type": "Feature",
  "properties": {
    "addr:full":"11015 SW Capitol Hwy Portland OR 97219",
    "addr:housenumber":"11015",
    "addr:postcode":"97219",
    "addr:street":"Sw Capitol Hwy",
    "iso:country":"US",
    "sg:address":"11015 SW Capitol Hwy",
    "sg:city":"Portland",
    "sg:classifiers":[
        {
            "category":"Professional",
            "type":"Services"
        }
    ],
    "sg:phone":"+1 503 977 6356",
    "sg:postcode":"97219",
    "sg:province":"OR",
    "wof:name":"Bailey Spike",
    "wof:placetype":"venue"
},
  "geometry": {"coordinates":[-122.726663,45.445507],"type":"Point"}
}