{
  "type": "Feature",
  "properties": {
    "addr:full":"635 NW Sonora Dr Bend OR 97701",
    "addr:housenumber":"635",
    "addr:postcode":"97701",
    "addr:street":"Nw Sonora Dr",
    "iso:country":"US",
    "sg:address":"635 NW Sonora Dr",
    "sg:city":"Bend",
    "sg:classifiers":[
        {
            "category":"Professional",
            "subcategory":"Advertising",
            "type":"Services"
        }
    ],
    "sg:phone":"+1 541 388 1969",
    "sg:postcode":"97701",
    "sg:province":"OR",
    "wof:name":"HEADTOHEAL.COM",
    "wof:placetype":"venue"
},
  "geometry": {"coordinates":[-121.32123,44.070295],"type":"Point"}
}