{
  "type": "Feature",
  "properties": {
    "iso:country":"US",
    "sg:address":"1303 Pinecrest Ter",
    "sg:city":"Grants Pass",
    "sg:classifiers":[
        {
            "category":"Building & Trades",
            "subcategory":"Construction",
            "type":"Services"
        }
    ],
    "sg:phone":"+1 541 479 1841",
    "sg:postcode":"97520",
    "sg:province":"OR",
    "sg:tags":[
        "house"
    ],
    "wof:name":"C 4 Construction",
    "wof:placetype":"venue"
},
  "geometry": {"coordinates":[-122.691176,42.176431],"type":"Point"}
}