{
  "type": "Feature",
  "properties": {
    "addr:full":"121 SW Morrison Street Suite 600 Portland OR 97204",
    "addr:housenumber":"121",
    "addr:postcode":"97204",
    "addr:street":"Sw Morrison Street Suite 600",
    "iso:country":"US",
    "sg:address":"121 SW Morrison Street Suite 600",
    "sg:city":"Portland",
    "sg:classifiers":[
        {
            "category":"Professional",
            "subcategory":"Lawyer & Legal Services",
            "type":"Services"
        }
    ],
    "sg:phone":"+1 503 228 6044",
    "sg:postcode":"97204",
    "sg:province":"OR",
    "wof:name":"Saul Karen E",
    "wof:placetype":"venue"
},
  "geometry": {"coordinates":[-122.673598,45.51776],"type":"Point"}
}