{
  "type": "Feature",
  "properties": {
    "addr:full":"101 SW Main Street Portland OR 97204",
    "addr:housenumber":"101",
    "addr:postcode":"97204",
    "addr:street":"Sw Main Street",
    "iso:country":"US",
    "sg:address":"101 SW Main Street",
    "sg:city":"Portland",
    "sg:classifiers":[
        {
            "category":"Professional",
            "subcategory":"Lawyer & Legal Services",
            "type":"Services"
        }
    ],
    "sg:phone":"+1 503 228 2525",
    "sg:postcode":"97204",
    "sg:province":"OR",
    "wof:name":"Parks Timothy M",
    "wof:placetype":"venue"
},
  "geometry": {"coordinates":[-122.67548600000001,45.515122],"type":"Point"}
}