{
  "type": "Feature",
  "properties": {
    "addr:full":"1017 NE 117th Ave Portland OR 97220",
    "addr:housenumber":"1017",
    "addr:postcode":"97220",
    "addr:street":"Ne 117Th Ave",
    "iso:country":"US",
    "sg:address":"1017 NE 117th Ave",
    "sg:city":"Portland",
    "sg:classifiers":[
        {
            "category":"Government",
            "subcategory":"Office",
            "type":"Public Place"
        }
    ],
    "sg:phone":"+1 503 823 4550",
    "sg:postcode":"97220",
    "sg:province":"OR",
    "sg:tags":[
        "township",
        "government-city",
        "village"
    ],
    "sg:website":"http://www.historicoverlookhouse.org",
    "wof:name":"City Of Portland",
    "wof:placetype":"venue"
},
  "geometry": {"coordinates":[-122.542744,45.530036],"type":"Point"}
}