{
  "type": "Feature",
  "properties": {
    "iso:country":"US",
    "sg:address":"1122 Spring St",
    "sg:city":"Medford",
    "sg:classifiers":[
        {
            "category":"Health Services",
            "subcategory":"Nursing And Care Facility",
            "type":"Services"
        },
        {
            "category":"Social Services",
            "subcategory":"Retirement Home",
            "type":"Services"
        },
        {
            "category":"Social Services",
            "subcategory":"Adult Care",
            "type":"Services"
        }
    ],
    "sg:phone":"+1 541 292 5488",
    "sg:postcode":"97504",
    "sg:province":"OR",
    "sg:tags":[
        "living",
        "people",
        "assisted",
        "community",
        "elder",
        "homes-elderly"
    ],
    "sg:website":"http://www.hortonplza.com/",
    "wof:name":"Horton Plaza",
    "wof:placetype":"venue"
},
  "geometry": {"coordinates":[-122.85881500000001,42.338243],"type":"Point"}
}