{
  "type": "Feature",
  "properties": {
    "addr:full":"1913 Portland Rd Newberg OR 97132",
    "addr:housenumber":"1913",
    "addr:postcode":"97132",
    "addr:street":"Portland Rd",
    "iso:country":"US",
    "sg:address":"1913 Portland Rd",
    "sg:city":"Newberg",
    "sg:phone":"+1 503 538 3800",
    "sg:postcode":"97132",
    "sg:province":"OR",
    "sg:website":"http://www.pizzainn.com",
    "wof:name":"Pizza Inn",
    "wof:placetype":"venue"
},
  "geometry": {"coordinates":[-122.96065299999999,45.302096],"type":"Point"}
}