{
  "type": "Feature",
  "properties": {
    "iso:country":"US",
    "sg:address":"8214 SW Nimbus Ave",
    "sg:city":"Beaverton",
    "sg:classifiers":[
        {
            "category":"Education",
            "subcategory":"Music School",
            "type":"Public Place"
        }
    ],
    "sg:phone":"+1 503 713 7660",
    "sg:postcode":"97008",
    "sg:province":"OR",
    "wof:name":"Allegro Music Academy Inc",
    "wof:placetype":"venue"
},
  "geometry": {"coordinates":[-122.78874399999999,45.460945],"type":"Point"}
}