{
  "type": "Feature",
  "properties": {
    "iso:country":"US",
    "sg:address":"16220 SW Westwind Dr",
    "sg:city":"Beaverton",
    "sg:classifiers":[
        {
            "category":"Manufacturing",
            "subcategory":"Jewelry",
            "type":"Manufacturing & Wholesale Goods"
        }
    ],
    "sg:phone":"+1 503 642 7344",
    "sg:postcode":"97007",
    "sg:province":"OR",
    "sg:tags":[
        "manufacturer",
        "costume",
        "jewelers-wholesale",
        "mfg"
    ],
    "wof:name":"Beaded Elephant",
    "wof:placetype":"venue"
},
  "geometry": {"coordinates":[-122.843778,45.487292],"type":"Point"}
}