{
  "type": "Feature",
  "properties": {
    "addr:full":"5041 SE Cascade Ct Hillsboro OR 97123",
    "addr:housenumber":"5041",
    "addr:postcode":"97123",
    "addr:street":"Se Cascade Ct",
    "iso:country":"US",
    "sg:address":"5041 SE Cascade Ct",
    "sg:city":"Hillsboro",
    "sg:classifiers":[
        {
            "category":"Building & Trades",
            "subcategory":"Construction",
            "type":"Services"
        }
    ],
    "sg:phone":"+1 503 846 9764",
    "sg:postcode":"97123",
    "sg:province":"OR",
    "sg:tags":[
        "roofing",
        "contractor"
    ],
    "wof:name":"Dan Stofford Roofing",
    "wof:placetype":"venue"
},
  "geometry": {"coordinates":[-122.930228,45.504912],"type":"Point"}
}