{
  "type": "Feature",
  "properties": {
    "addr:full":"200 Evergreen Rd Ontario OR 97914",
    "addr:housenumber":"200",
    "addr:postcode":"97914",
    "addr:street":"Evergreen Rd",
    "iso:country":"US",
    "sg:address":"200 Evergreen Rd",
    "sg:city":"Ontario",
    "sg:classifiers":[
        {
            "category":"Professional",
            "subcategory":"Accounting & Tax Preparation",
            "type":"Services"
        }
    ],
    "sg:phone":"+1 541 642 7760",
    "sg:postcode":"97914",
    "sg:province":"OR",
    "wof:name":"Dena Chamberlin",
    "wof:placetype":"venue"
},
  "geometry": {"coordinates":[-116.94001299999999,44.125877],"type":"Point"}
}