{
  "type": "Feature",
  "properties": {
    "iso:country":"US",
    "sg:address":"6514 SW Barnes Rd",
    "sg:city":"Portland",
    "sg:classifiers":[
        {
            "category":"Shopping",
            "type":"Retail Goods"
        }
    ],
    "sg:phone":"+1 503 972 6040",
    "sg:postcode":"97225",
    "sg:province":"OR",
    "sg:tags":[
        "art",
        "gallery",
        "dealer"
    ],
    "wof:name":"Bien Vestida",
    "wof:placetype":"venue"
},
  "geometry": {"coordinates":[-122.74519600000001,45.515665],"type":"Point"}
}