{
  "type": "Feature",
  "properties": {
    "iso:country":"US",
    "sg:address":"624 NW Riverfront St",
    "sg:city":"Bend",
    "sg:classifiers":[
        {
            "category":"Building & Trades",
            "subcategory":"Construction",
            "type":"Services"
        }
    ],
    "sg:phone":"+1 541 318 8491",
    "sg:postcode":"97701",
    "sg:province":"OR",
    "sg:tags":[
        "builder",
        "patio",
        "deck"
    ],
    "wof:name":"Alder Creek Fence & Deck",
    "wof:placetype":"venue"
},
  "geometry": {"coordinates":[-121.323919,44.056432],"type":"Point"}
}