{
  "type": "Feature",
  "properties": {
    "addr:full":"3502 Excel Dr Ste 103 Medford OR 97504",
    "addr:housenumber":"3502",
    "addr:postcode":"97504",
    "addr:street":"Excel Dr Ste 103",
    "iso:country":"US",
    "sg:address":"3502 Excel Dr Ste 103",
    "sg:city":"Medford",
    "sg:classifiers":[
        {
            "category":"Utilities",
            "type":"Services"
        }
    ],
    "sg:phone":"+1 541 776 5380",
    "sg:postcode":"97504",
    "sg:province":"OR",
    "sg:tags":[
        "provider",
        "internet"
    ],
    "sg:website":"www.integratelecom.com",
    "wof:name":"Integra Telecom",
    "wof:placetype":"venue"
},
  "geometry": {"coordinates":[-122.86154999999999,42.364823],"type":"Point"}
}