{
  "type": "Feature",
  "properties": {
    "addr:full":"11979 N Center Avenue Portland OR 97217",
    "addr:housenumber":"11979",
    "addr:postcode":"97217",
    "addr:street":"N Center Avenue",
    "iso:country":"US",
    "sg:address":"11979 N Center Avenue",
    "sg:city":"Portland",
    "sg:classifiers":[
        {
            "category":"Restaurant",
            "type":"Food & Drink"
        }
    ],
    "sg:phone":"+1 503 283 0890",
    "sg:postcode":"97217",
    "sg:province":"OR",
    "wof:name":"The Galley Sports Pub",
    "wof:placetype":"venue"
},
  "geometry": {"coordinates":[-122.68178,45.609977],"type":"Point"}
}