{
  "type": "Feature",
  "properties": {
    "addr:full":"520 2nd Ave Gold Hill OR 97525",
    "addr:housenumber":"520",
    "addr:postcode":"97525",
    "addr:street":"2Nd Ave",
    "iso:country":"US",
    "sg:address":"520 2nd Ave",
    "sg:city":"Gold Hill",
    "sg:classifiers":[
        {
            "category":"Professional",
            "subcategory":"Employment Agencies",
            "type":"Services"
        }
    ],
    "sg:phone":"+1 541 855 5340",
    "sg:postcode":"97525",
    "sg:province":"OR",
    "sg:tags":[
        "opportunity"
    ],
    "wof:name":"Handy Hands Pro Referrals LLC",
    "wof:placetype":"venue"
},
  "geometry": {"coordinates":[-123.05047999999999,42.431381],"type":"Point"}
}