{
  "type": "Feature",
  "properties": {
    "iso:country":"US",
    "sg:address":"7499 State Hwy 238",
    "sg:city":"Jacksonville",
    "sg:classifiers":[
        {
            "category":"Farming",
            "subcategory":"Vineyard",
            "type":"Manufacturing & Wholesale Goods"
        }
    ],
    "sg:phone":"+1 541 899 8529",
    "sg:postcode":"97530",
    "sg:province":"OR",
    "wof:name":"Stepping Stone Vineyard",
    "wof:placetype":"venue"
},
  "geometry": {"coordinates":[-123.03872,42.238288],"type":"Point"}
}