{
  "type": "Feature",
  "properties": {
    "iso:country":"US",
    "sg:address":"365 Short St",
    "sg:city":"Grants Pass",
    "sg:classifiers":[
        {
            "category":"Retail",
            "subcategory":"Auto Repair",
            "type":"Services"
        }
    ],
    "sg:phone":"+1 541 955 8346",
    "sg:postcode":"97527",
    "sg:province":"OR",
    "sg:tags":[
        "automotive"
    ],
    "wof:name":"Mg Services",
    "wof:placetype":"venue"
},
  "geometry": {"coordinates":[-123.33572,42.427222],"type":"Point"}
}