{
  "type": "Feature",
  "properties": {
    "iso:country":"US",
    "sg:address":"26231 Myers Creek Rd",
    "sg:city":"Gold Beach",
    "sg:classifiers":[
        {
            "category":"Building & Trades",
            "subcategory":"Construction",
            "type":"Services"
        }
    ],
    "sg:phone":"+1 541 247 6459",
    "sg:postcode":"97444",
    "sg:province":"OR",
    "sg:tags":[
        "house"
    ],
    "wof:name":"Frank Martinez",
    "wof:placetype":"venue"
},
  "geometry": {"coordinates":[-124.406502,42.312813],"type":"Point"}
}