{
  "type": "Feature",
  "properties": {
    "iso:country":"US",
    "sg:address":"305 NE Burnside Ave",
    "sg:city":"Bend",
    "sg:classifiers":[
        {
            "category":"Building & Trades",
            "subcategory":"Construction",
            "type":"Services"
        }
    ],
    "sg:phone":"+1 541 318 5475",
    "sg:postcode":"97701",
    "sg:province":"OR",
    "sg:tags":[
        "heavy",
        "consultant"
    ],
    "wof:name":"Heavy Railroad Excavations",
    "wof:placetype":"venue"
},
  "geometry": {"coordinates":[-121.30240999999999,44.052319],"type":"Point"}
}