{
  "type": "Feature",
  "properties": {
    "iso:country":"US",
    "sg:address":"334 NE B St",
    "sg:city":"Madras",
    "sg:classifiers":[
        {
            "category":"Building & Trades",
            "subcategory":"Electrical",
            "type":"Services"
        }
    ],
    "sg:phone":"+1 541 475 3524",
    "sg:postcode":"97741",
    "sg:province":"OR",
    "sg:tags":[
        "electrical",
        "electric",
        "contractor"
    ],
    "wof:name":"Madras Electric Inc",
    "wof:placetype":"venue"
},
  "geometry": {"coordinates":[-121.121622,44.63599],"type":"Point"}
}