{
  "type": "Feature",
  "properties": {
    "iso:country":"US",
    "sg:address":"13121 SE Mcloughlin Blvd",
    "sg:city":"Portland",
    "sg:classifiers":[
        {
            "category":"Social Services",
            "type":"Services"
        },
        {
            "category":"Organizations",
            "subcategory":"Community Association",
            "type":"Services"
        },
        {
            "category":"Organizations",
            "subcategory":"Membership Organization",
            "type":"Services"
        }
    ],
    "sg:phone":"+1 503 654 9580",
    "sg:postcode":"97222",
    "sg:province":"OR",
    "sg:tags":[
        "sorority",
        "fraternal",
        "fraternity"
    ],
    "sg:website":"http://www.elks.org/",
    "wof:name":"Elks Lodge",
    "wof:placetype":"venue"
},
  "geometry": {"coordinates":[-122.63435200000001,45.428296],"type":"Point"}
}