{
  "type": "Feature",
  "properties": {
    "iso:country":"US",
    "sg:address":"10929 NE Sandy Blvd",
    "sg:city":"Portland",
    "sg:classifiers":[
        {
            "category":"Banks & Credit Unions",
            "subcategory":"Bank",
            "type":"Services"
        }
    ],
    "sg:phone":"+1 503 255 4445",
    "sg:postcode":"97220",
    "sg:province":"OR",
    "sg:tags":[
        "loan"
    ],
    "wof:name":"Nationwide Budget Finance",
    "wof:placetype":"venue"
},
  "geometry": {"coordinates":[-122.551788,45.558659],"type":"Point"}
}