{
  "type": "Feature",
  "properties": {
    "addr:full":"3032 Cody St Medford OR 97504",
    "addr:housenumber":"3032",
    "addr:postcode":"97504",
    "addr:street":"Cody St",
    "iso:country":"US",
    "sg:address":"3032 Cody St",
    "sg:city":"Medford",
    "sg:classifiers":[
        {
            "category":"Building & Trades",
            "subcategory":"Construction",
            "type":"Services"
        }
    ],
    "sg:phone":"+1 541 779 0604",
    "sg:postcode":"97504",
    "sg:province":"OR",
    "sg:tags":[
        "hanging",
        "contractor"
    ],
    "wof:name":"Cascade Custom Painting Inc",
    "wof:placetype":"venue"
},
  "geometry": {"coordinates":[-122.831029,42.361987],"type":"Point"}
}