{
  "type": "Feature",
  "properties": {
    "iso:country":"US",
    "sg:address":"5615 NE 17th Ave",
    "sg:city":"Portland",
    "sg:classifiers":[
        {
            "category":"Building & Trades",
            "subcategory":"Construction",
            "type":"Services"
        }
    ],
    "sg:phone":"+1 503 281 6867",
    "sg:postcode":"97211",
    "sg:province":"OR",
    "sg:tags":[
        "hanging",
        "contractor"
    ],
    "wof:name":"Patrick McNassar & Sons",
    "wof:placetype":"venue"
},
  "geometry": {"coordinates":[-122.648107,45.563828],"type":"Point"}
}