{
  "type": "Feature",
  "properties": {
    "addr:full":"63345 NW Skyline Ranch Rd Bend OR 97701",
    "addr:housenumber":"63345",
    "addr:postcode":"97701",
    "addr:street":"Nw Skyline Ranch Rd",
    "iso:country":"US",
    "sg:address":"63345 NW Skyline Ranch Rd",
    "sg:city":"Bend",
    "sg:classifiers":[
        {
            "category":"Professional",
            "subcategory":"Business Services",
            "type":"Services"
        }
    ],
    "sg:phone":"+1 541 388 1416",
    "sg:postcode":"97701",
    "sg:province":"OR",
    "wof:name":"Efficiency Solutions",
    "wof:placetype":"venue"
},
  "geometry": {"coordinates":[-121.34983800000001,44.098695],"type":"Point"}
}