{
  "type": "Feature",
  "properties": {
    "iso:country":"US",
    "sg:address":"2312 NW 30th Avenue",
    "sg:city":"Portland",
    "sg:classifiers":[
        {
            "category":"Home & Garden",
            "subcategory":"Building Materials",
            "type":"Retail Goods"
        },
        {
            "category":"Building & Trades",
            "subcategory":"Construction",
            "type":"Services"
        }
    ],
    "sg:phone":"+1 503 720 6127",
    "sg:postcode":"97210",
    "sg:province":"OR",
    "sg:tags":[
        "contractor",
        "supply"
    ],
    "sg:website":"www.delatierra-stoneworks.com/",
    "wof:name":"de la tierra, inc.",
    "wof:placetype":"venue"
},
  "geometry": {"coordinates":[-122.71245500000001,45.538934],"type":"Point"}
}