{
  "type": "Feature",
  "properties": {
    "iso:country":"US",
    "sg:address":"4450 SW 184th Ave",
    "sg:city":"Aloha",
    "sg:classifiers":[
        {
            "category":"Organizations",
            "subcategory":"Non-profit Organization",
            "type":"Services"
        },
        {
            "category":"Social Services",
            "type":"Services"
        }
    ],
    "sg:phone":"+1 503 649 2066",
    "sg:postcode":"97007",
    "sg:province":"OR",
    "sg:tags":[
        "disability"
    ],
    "wof:name":"Autistic Childrens Activity P",
    "wof:placetype":"venue"
},
  "geometry": {"coordinates":[-122.86635,45.486529],"type":"Point"}
}