{
  "type": "Feature",
  "properties": {
    "addr:full":"6875 SW Philomath Blvd Corvallis OR 97333",
    "addr:housenumber":"6875",
    "addr:postcode":"97333",
    "addr:street":"Sw Philomath Blvd",
    "iso:country":"US",
    "sg:address":"6875 SW Philomath Blvd",
    "sg:city":"Corvallis",
    "sg:classifiers":[
        {
            "category":"Building & Trades",
            "subcategory":"Cleaning & Sanitation",
            "type":"Services"
        }
    ],
    "sg:phone":"+1 541 929 4302",
    "sg:postcode":"97333",
    "sg:province":"OR",
    "sg:tags":[
        "house"
    ],
    "wof:name":"Merry Maids Inc",
    "wof:placetype":"venue"
},
  "geometry": {"coordinates":[-123.327682,44.546056],"type":"Point"}
}