{
  "type": "Feature",
  "properties": {
    "addr:full":"The Big Yellow Truck SE 48th Ave & SE Division St Portland OR 97215",
    "addr:postcode":"97215",
    "addr:street":"Se 48Th Ave & Se Division St",
    "iso:country":"US",
    "sg:address":"The Big Yellow Truck SE 48th Ave & SE Division St",
    "sg:city":"Portland",
    "sg:classifiers":[
        {
            "category":"Food Court",
            "type":"Food & Drink"
        },
        {
            "category":"Restaurant",
            "type":"Food & Drink"
        },
        {
            "category":"Food & Beverages",
            "subcategory":"Bakery",
            "type":"Retail Goods"
        }
    ],
    "sg:phone":"+1 503 683 2822",
    "sg:postcode":"97215",
    "sg:province":"OR",
    "sg:tags":[
        "cuban",
        "sandwich",
        "stand"
    ],
    "sg:website":"www.havanacafepdx.com",
    "wof:name":"Havana Cafe",
    "wof:placetype":"venue"
},
  "geometry": {"coordinates":[-122.613241,45.505297],"type":"Point"}
}