{
  "type": "Feature",
  "properties": {
    "iso:country":"US",
    "sg:address":"275 N 3rd St",
    "sg:city":"Woodburn",
    "sg:classifiers":[
        {
            "category":"Professional",
            "subcategory":"Management & Consulting",
            "type":"Services"
        }
    ],
    "sg:phone":"+1 503 982 4220",
    "sg:postcode":"97071",
    "sg:province":"OR",
    "sg:tags":[
        "consultant",
        "educational"
    ],
    "sg:website":"www.youthchange.com",
    "wof:name":"Youth Change",
    "wof:placetype":"venue"
},
  "geometry": {"coordinates":[-122.859718,45.143575],"type":"Point"}
}