{
  "type": "Feature",
  "properties": {
    "iso:country":"US",
    "sg:address":"1 Juniper Cir",
    "sg:city":"Woodburn",
    "sg:classifiers":[
        {
            "category":"Real Estate",
            "subcategory":"Developer",
            "type":"Services"
        }
    ],
    "sg:phone":"+1 503 981 6600",
    "sg:postcode":"97071",
    "sg:province":"OR",
    "sg:tags":[
        "mobile",
        "home"
    ],
    "wof:name":"Woodburn West Mobile Estates",
    "wof:placetype":"venue"
},
  "geometry": {"coordinates":[-122.88537100000001,45.154251],"type":"Point"}
}