{
  "type": "Feature",
  "properties": {
    "iso:country":"US",
    "sg:address":"3551 NW Front Ave",
    "sg:city":"Portland",
    "sg:classifiers":[
        {
            "category":"Autos & Motor Vehicles",
            "subcategory":"Auto Supplies",
            "type":"Retail Goods"
        },
        {
            "category":"Retail",
            "subcategory":"Auto Repair",
            "type":"Services"
        },
        {
            "category":"Autos & Motor Vehicles",
            "subcategory":"Recreational Vehicle Sales",
            "type":"Retail Goods"
        }
    ],
    "sg:phone":"+1 503 227 5567",
    "sg:postcode":"97210",
    "sg:province":"OR",
    "sg:tags":[
        "automobile",
        "part",
        "camper",
        "accessory"
    ],
    "sg:website":"http://www.speedometerservice.net",
    "wof:name":"Speedometer Service & Instrmnt",
    "wof:placetype":"venue"
},
  "geometry": {"coordinates":[-122.705276,45.548146],"type":"Point"}
}