{
  "type": "Feature",
  "properties": {
    "iso:country":"US",
    "sg:address":"1710 Northview Blvd",
    "sg:city":"Eugene",
    "sg:classifiers":[
        {
            "category":"Real Estate",
            "subcategory":"Real Estate Operator",
            "type":"Services"
        }
    ],
    "sg:phone":"+1 541 484 6553",
    "sg:postcode":"97405",
    "sg:province":"OR",
    "sg:tags":[
        "building",
        "apartment"
    ],
    "wof:name":"Prospect Park Apartments",
    "wof:placetype":"venue"
},
  "geometry": {"coordinates":[-123.118129,44.030476],"type":"Point"}
}