{
  "type": "Feature",
  "properties": {
    "addr:full":"1749 Main St Springfield OR 97477",
    "addr:housenumber":"1749",
    "addr:postcode":"97477",
    "addr:street":"Main St",
    "iso:country":"US",
    "sg:address":"1749 Main St",
    "sg:city":"Springfield",
    "sg:classifiers":[
        {
            "category":"Retail",
            "subcategory":"Auto Rental",
            "type":"Services"
        }
    ],
    "sg:phone":"+1 541 741 4100",
    "sg:postcode":"97477",
    "sg:province":"OR",
    "sg:tags":[
        "renting",
        "automobile"
    ],
    "wof:name":"Enterprise Rent-A-Car",
    "wof:placetype":"venue"
},
  "geometry": {"coordinates":[-122.997249,44.045791],"type":"Point"}
}