{
  "type": "Feature",
  "properties": {
    "iso:country":"US",
    "sg:address":"304 W Main St",
    "sg:city":"Molalla",
    "sg:classifiers":[
        {
            "category":"Retail",
            "subcategory":"Auto Repair",
            "type":"Services"
        }
    ],
    "sg:phone":"+1 503 829 3555",
    "sg:postcode":"97038",
    "sg:province":"OR",
    "sg:tags":[
        "exhaust"
    ],
    "wof:name":"Molalla Radiator & Exhaust",
    "wof:placetype":"venue"
},
  "geometry": {"coordinates":[-122.580306,45.147825],"type":"Point"}
}