{
  "type": "Feature",
  "properties": {
    "addr:full":"304 W Main St Molalla OR 97038",
    "addr:housenumber":"304",
    "addr:postcode":"97038",
    "addr:street":"W Main St",
    "iso:country":"US",
    "sg:address":"304 W Main St",
    "sg:city":"Molalla",
    "sg:classifiers":[
        {
            "category":"Retail",
            "subcategory":"Auto Repair",
            "type":"Services"
        }
    ],
    "sg:phone":"+1 503 829 3555",
    "sg:postcode":"97038",
    "sg:province":"OR",
    "sg:tags":[
        "exhaust"
    ],
    "wof:name":"Molalla Radiator & Exhaust",
    "wof:placetype":"venue"
},
  "geometry": {"coordinates":[-122.58030599999999,45.147825],"type":"Point"}
}