{
  "type": "Feature",
  "properties": {
    "iso:country":"US",
    "sg:address":"245 SW Twin Oaks Cir",
    "sg:city":"Corvallis",
    "sg:classifiers":[
        {
            "category":"Home & Garden",
            "subcategory":"Building Materials",
            "type":"Retail Goods"
        },
        {
            "category":"Building & Trades",
            "subcategory":"Construction",
            "type":"Services"
        }
    ],
    "sg:phone":"+1 541 753 0592",
    "sg:postcode":"97333",
    "sg:province":"OR",
    "sg:tags":[
        "repair",
        "contractor",
        "maintenance",
        "improvement"
    ],
    "wof:name":"Coldiron Construction",
    "wof:placetype":"venue"
},
  "geometry": {"coordinates":[-123.266813,44.554124],"type":"Point"}
}