{
  "type": "Feature",
  "properties": {
    "iso:country":"US",
    "sg:address":"208 SE 1st Ave",
    "sg:city":"Ontario",
    "sg:classifiers":[
        {
            "category":"Place Of Worship",
            "subcategory":"Church",
            "type":"Public Place"
        },
        {
            "category":"Place Of Worship",
            "type":"Public Place"
        }
    ],
    "sg:phone":"+1 541 889 5458",
    "sg:postcode":"97914",
    "sg:province":"OR",
    "sg:tags":[
        "lutheran",
        "america",
        "churches-lutheran",
        "churches-lutheran-evangelical"
    ],
    "sg:website":"http://www.dexknows.com/INFO/541-889-5458",
    "wof:name":"Pilgrim Lutheran Church",
    "wof:placetype":"venue"
},
  "geometry": {"coordinates":[-116.958894,44.025003],"type":"Point"}
}