{
  "type": "Feature",
  "properties": {
    "iso:country":"US",
    "sg:address":"602 E 1st St",
    "sg:city":"Newberg",
    "sg:classifiers":[
        {
            "category":"Shopping",
            "subcategory":"Department Store",
            "type":"Retail Goods"
        }
    ],
    "sg:phone":"+1 503 538 3828",
    "sg:postcode":"97132",
    "sg:province":"OR",
    "sg:tags":[
        "shop"
    ],
    "wof:name":"Soapy Bear",
    "wof:placetype":"venue"
},
  "geometry": {"coordinates":[-122.97283299999999,45.30023],"type":"Point"}
}