{
  "type": "Feature",
  "properties": {
    "addr:full":"2108 NE 41st Ave Portland OR 97212",
    "addr:housenumber":"2108",
    "addr:postcode":"97212",
    "addr:street":"Ne 41St Ave",
    "iso:country":"US",
    "sg:address":"2108 NE 41st Ave",
    "sg:city":"Portland",
    "sg:classifiers":[
        {
            "category":"Building & Trades",
            "subcategory":"Construction",
            "type":"Services"
        }
    ],
    "sg:phone":"+1 503 528 9730",
    "sg:postcode":"97212",
    "sg:province":"OR",
    "sg:tags":[
        "system",
        "blower"
    ],
    "wof:name":"David P Wilson Co",
    "wof:placetype":"venue"
},
  "geometry": {"coordinates":[-122.620863,45.538986],"type":"Point"}
}