{
  "type": "Feature",
  "properties": {
    "iso:country":"US",
    "sg:address":"90868 Poodle Creek Rd",
    "sg:city":"Noti",
    "sg:classifiers":[
        {
            "category":"Organizations",
            "subcategory":"Community Association",
            "type":"Services"
        }
    ],
    "sg:phone":"+1 541 726 5163",
    "sg:postcode":"97461",
    "sg:province":"OR",
    "wof:name":"Club Rock",
    "wof:placetype":"venue"
},
  "geometry": {"coordinates":[-123.463785,44.12208],"type":"Point"}
}